{
  "type": "Feature",
  "properties": {
    "addr:full":"15871 Russell Ave White Rock BC V4B 2S5",
    "addr:housenumber":"15871",
    "addr:postcode":"v4b 2s5",
    "addr:street":"Russell Ave",
    "iso:country":"CA",
    "sg:address":"15871 Russell Ave",
    "sg:city":"White Rock",
    "sg:classifiers":[
        {
            "category":"Freight",
            "type":"Transportation"
        }
    ],
    "sg:phone":"+1 604 536 6620",
    "sg:postcode":"V4B 2S5",
    "sg:province":"BC",
    "sg:tags":[
        "delivery",
        "mover"
    ],
    "wof:name":"B & B Mobile Svc",
    "wof:placetype":"venue"
},
  "geometry": {"coordinates":[-122.782837,49.029396],"type":"Point"}
}