{
  "type": "Feature",
  "properties": {
    "iso:country":"CA",
    "sg:city":"London",
    "sg:classifiers":[
        {
            "category":"Restaurant",
            "type":"Food & Drink"
        }
    ],
    "sg:phone":"+1 519 679 7775",
    "sg:postcode":"N5X 1K4",
    "sg:province":"ON",
    "sg:tags":[
        "caterer"
    ],
    "wof:name":"Marshall's Pasta Mill",
    "wof:placetype":"venue"
},
  "geometry": {"coordinates":[-81.25243377690001,43.0306739807],"type":"Point"}
}