{
  "type": "Feature",
  "properties": {
    "addr:full":"8600 Keele St # 4 Concord ON L4K 4H8",
    "addr:housenumber":"8600",
    "addr:postcode":"l4k 4h8",
    "addr:street":"Keele St # 4",
    "iso:country":"CA",
    "sg:address":"8600 Keele St # 4",
    "sg:city":"Concord",
    "sg:classifiers":[
        {
            "category":"Travel",
            "subcategory":"Travel Agent",
            "type":"Entertainment"
        }
    ],
    "sg:phone":"+1 905 660 3322",
    "sg:postcode":"L4K 4H8",
    "sg:province":"ON",
    "sg:tags":[
        "agency",
        "bureau"
    ],
    "wof:name":"Clemar Travel",
    "wof:placetype":"venue"
},
  "geometry": {"coordinates":[-79.50495100000001,43.821964],"type":"Point"}
}