{
  "type": "Feature",
  "properties": {
    "iso:country":"CA",
    "sg:address":"93 Main St",
    "sg:city":"Birtle",
    "sg:classifiers":[
        {
            "category":"Wholesale",
            "subcategory":"Sporting Goods",
            "type":"Manufacturing & Wholesale Goods"
        }
    ],
    "sg:phone":"+1 204 842 3439",
    "sg:postcode":"R0M 0C0",
    "sg:province":"MB",
    "sg:tags":[
        "club",
        "equipment",
        "room"
    ],
    "wof:name":"Birtle Swim Club",
    "wof:placetype":"venue"
},
  "geometry": {"coordinates":[-101.055076599,50.4221382141],"type":"Point"}
}