{
  "type": "Feature",
  "properties": {
    "addr:full":"1078 Klondike Rd Kanata ON K2K 1X7",
    "addr:housenumber":"1078",
    "addr:postcode":"k2k 1x7",
    "addr:street":"Klondike Rd",
    "iso:country":"CA",
    "sg:address":"1078 Klondike Rd",
    "sg:city":"Kanata",
    "sg:classifiers":[
        {
            "category":"Organizations",
            "subcategory":"Religious Organization",
            "type":"Services"
        }
    ],
    "sg:phone":"+1 613 591 3246",
    "sg:postcode":"K2K 1X7",
    "sg:province":"ON",
    "sg:tags":[
        "church"
    ],
    "wof:name":"Fellowship Baptist Church",
    "wof:placetype":"venue"
},
  "geometry": {"coordinates":[-75.9306488037,45.3561553955],"type":"Point"}
}