{
  "type": "Feature",
  "properties": {
    "addr:full":"Edmonton AB T5S 1T7",
    "addr:postcode":"t5s 1t7",
    "iso:country":"CA",
    "sg:city":"Edmonton",
    "sg:classifiers":[
        {
            "category":"Restaurant",
            "type":"Food & Drink"
        }
    ],
    "sg:phone":"+1 780 447 3656",
    "sg:postcode":"T5S 1T7",
    "sg:province":"AB",
    "wof:name":"Winter's Restaurant & Bar Ltd",
    "wof:placetype":"venue"
},
  "geometry": {"coordinates":[-113.689232,53.550919],"type":"Point"}
}