{
  "type": "Feature",
  "properties": {
    "addr:full":"478 Albert St Ottawa ON K1R 5B5",
    "addr:housenumber":"478",
    "addr:postcode":"k1r 5b5",
    "addr:street":"Albert St",
    "iso:country":"CA",
    "sg:address":"478 Albert St",
    "sg:city":"Ottawa",
    "sg:classifiers":[
        {
            "category":"Travel",
            "subcategory":"Hotels & Motels",
            "type":"Entertainment"
        }
    ],
    "sg:phone":"+1 613 236 4479",
    "sg:postcode":"K1R 5B5",
    "sg:province":"ON",
    "sg:tags":[
        "breakfast",
        "accommodation",
        "bed"
    ],
    "wof:name":"Albert House Inn",
    "wof:placetype":"venue"
},
  "geometry": {"coordinates":[-75.707504,45.416698],"type":"Point"}
}