{
  "type": "Feature",
  "properties": {
    "addr:full":"Montreal QC H3B 4G5",
    "addr:postcode":"h3b 4g5",
    "iso:country":"CA",
    "sg:city":"Montreal",
    "sg:classifiers":[
        {
            "category":"Restaurant",
            "type":"Food & Drink"
        }
    ],
    "sg:phone":"+1 514 845 5502",
    "sg:postcode":"H3B 4G5",
    "sg:province":"QC",
    "wof:name":"Crepe DE Gerard Inc",
    "wof:placetype":"venue"
},
  "geometry": {"coordinates":[-73.5591964722,45.5153617859],"type":"Point"}
}