{
  "type": "Feature",
  "properties": {
    "addr:full":"1190 Weston Rd York ON M6M 4P4",
    "addr:housenumber":"1190",
    "addr:postcode":"m6m 4p4",
    "addr:street":"Weston Rd",
    "iso:country":"CA",
    "sg:address":"1190 Weston Rd",
    "sg:city":"York",
    "sg:classifiers":[
        {
            "category":"Food & Beverages",
            "subcategory":"Groceries & Convenience Stores",
            "type":"Retail Goods"
        }
    ],
    "sg:phone":"+1 416 614 2190",
    "sg:postcode":"M6M 4P4",
    "sg:province":"ON",
    "sg:tags":[
        "grocer"
    ],
    "wof:name":"P K & B Grocery Store",
    "wof:placetype":"venue"
},
  "geometry": {"coordinates":[-79.491348,43.687523],"type":"Point"}
}