{
  "type": "Feature",
  "properties": {
    "addr:full":"1050 Cote Du Beaver Hall Montreal QC H2Z 1S3",
    "addr:housenumber":"1050",
    "addr:postcode":"h2z 1s3",
    "addr:street":"Cote Du Beaver Hall",
    "iso:country":"CA",
    "sg:address":"1050 Cote Du Beaver Hall",
    "sg:city":"Montreal",
    "sg:classifiers":[
        {
            "category":"Banks & Credit Unions",
            "subcategory":"Bank",
            "type":"Services"
        }
    ],
    "sg:phone":"+1 514 393 9552",
    "sg:postcode":"H2Z 1S3",
    "sg:province":"QC",
    "wof:name":"Caisse D'Economie Kebectel",
    "wof:placetype":"venue"
},
  "geometry": {"coordinates":[-73.56461334230001,45.5021934509],"type":"Point"}
}