{
  "type": "Feature",
  "properties": {
    "addr:full":"302-852 Fort Street Victoria V8W1H8",
    "addr:housenumber":"302-852",
    "addr:postcode":"v8w1h8",
    "addr:street":"Fort Street",
    "iso:country":"CA",
    "sg:address":"302-852 Fort Street",
    "sg:city":"Victoria",
    "sg:classifiers":[
        {
            "category":"Professional",
            "subcategory":"Computer Services",
            "type":"Services"
        }
    ],
    "sg:postcode":"V8W1H8",
    "sg:website":"http://www.neverblue.com",
    "wof:name":"Neverblue",
    "wof:placetype":"venue"
},
  "geometry": {"coordinates":[-123.36390900000001,48.4244865],"type":"Point"}
}