{
  "type": "Feature",
  "properties": {
    "addr:full":"2112 Av Francis-Hughes Laval QC H7S 1N7",
    "addr:housenumber":"2112",
    "addr:postcode":"h7s 1n7",
    "addr:street":"Av Francis-Hughes",
    "iso:country":"CA",
    "sg:address":"2112 Av Francis-Hughes",
    "sg:city":"Laval",
    "sg:classifiers":[
        {
            "category":"Wholesale",
            "subcategory":"Machinery & Supplies",
            "type":"Manufacturing & Wholesale Goods"
        }
    ],
    "sg:phone":"+1 450 668 5010",
    "sg:postcode":"H7S 1N7",
    "sg:province":"QC",
    "sg:tags":[
        "tool",
        "grinding"
    ],
    "wof:name":"Merga",
    "wof:placetype":"venue"
},
  "geometry": {"coordinates":[-73.723099,45.580292],"type":"Point"}
}