{
  "type": "Feature",
  "properties": {
    "addr:full":"Mississauga ON L5T 1G7",
    "addr:postcode":"l5t 1g7",
    "iso:country":"CA",
    "sg:city":"Mississauga",
    "sg:classifiers":[
        {
            "category":"Wholesale",
            "subcategory":"Non-durable Goods",
            "type":"Manufacturing & Wholesale Goods"
        }
    ],
    "sg:phone":"+1 905 795 0930",
    "sg:postcode":"L5T 1G7",
    "sg:province":"ON",
    "sg:tags":[
        "mailing",
        "list"
    ],
    "wof:name":"Mediamix Marketing Group",
    "wof:placetype":"venue"
},
  "geometry": {"coordinates":[-79.64566802980001,43.6678619385],"type":"Point"}
}