{
  "type": "Feature",
  "properties": {
    "addr:full":"Maple Ridge BC V2X 6A4",
    "addr:postcode":"v2x 6a4",
    "iso:country":"CA",
    "sg:city":"Maple Ridge",
    "sg:classifiers":[
        {
            "category":"Health Services",
            "subcategory":"Medical Lab",
            "type":"Services"
        }
    ],
    "sg:phone":"+1 604 467 5141",
    "sg:postcode":"V2X 6A4",
    "sg:province":"BC",
    "sg:tags":[
        "laboratory"
    ],
    "wof:name":"B C Bio-Medical Laboratories",
    "wof:placetype":"venue"
},
  "geometry": {"coordinates":[-122.60161590600001,49.2158584595],"type":"Point"}
}