{
  "type": "Feature",
  "properties": {
    "addr:full":"808 Rue Sainte-Helene Longueuil QC J4K 3R6",
    "addr:housenumber":"808",
    "addr:postcode":"j4k 3r6",
    "addr:street":"Rue Sainte-Helene",
    "iso:country":"CA",
    "sg:address":"808 Rue Sainte-Helene",
    "sg:city":"Longueuil",
    "sg:classifiers":[
        {
            "category":"Retail",
            "subcategory":"Self-service Laundry",
            "type":"Services"
        }
    ],
    "sg:phone":"+1 450 677 4523",
    "sg:postcode":"J4K 3R6",
    "sg:province":"QC",
    "wof:name":"Buanderie Longueuil",
    "wof:placetype":"venue"
},
  "geometry": {"coordinates":[-73.508995,45.520931],"type":"Point"}
}