{
  "type": "Feature",
  "properties": {
    "addr:full":"Melfort SK S0E 1A0",
    "addr:postcode":"s0e 1a0",
    "addr:street":"Melfort",
    "iso:country":"CA",
    "sg:city":"Melfort",
    "sg:classifiers":[
        {
            "category":"Shopping",
            "subcategory":"Clothing, Apparel, & Fashions",
            "type":"Retail Goods"
        }
    ],
    "sg:phone":"+1 306 752 9100",
    "sg:postcode":"S0E 1A0",
    "sg:province":"SK",
    "wof:name":"Warehouse One the Jean Store",
    "wof:placetype":"venue"
},
  "geometry": {"coordinates":[-104.60894,52.863091],"type":"Point"}
}