{
  "type": "Feature",
  "properties": {
    "addr:full":"407 Rue Jarry E Montreal QC H2P 1V2",
    "addr:housenumber":"407",
    "addr:postcode":"h2p 1v2",
    "addr:street":"Rue Jarry E",
    "iso:country":"CA",
    "sg:address":"407 Rue Jarry E",
    "sg:city":"Montreal",
    "sg:classifiers":[
        {
            "category":"Personal",
            "subcategory":"Barber",
            "type":"Services"
        }
    ],
    "sg:phone":"+1 514 388 9184",
    "sg:postcode":"H2P 1V2",
    "sg:province":"QC",
    "wof:name":"Salon LA Retouche Inc",
    "wof:placetype":"venue"
},
  "geometry": {"coordinates":[-73.62924957280001,45.5427246094],"type":"Point"}
}