{
  "type": "Feature",
  "properties": {
    "iso:country":"CA",
    "sg:address":"419 West St",
    "sg:city":"Simcoe",
    "sg:classifiers":[
        {
            "category":"Autos & Motor Vehicles",
            "subcategory":"Fuel & Gas Station",
            "type":"Retail Goods"
        }
    ],
    "sg:phone":"+1 519 428 1534",
    "sg:postcode":"N3Y 1V1",
    "sg:province":"ON",
    "sg:tags":[
        "oil"
    ],
    "wof:name":"B B Family Convenience",
    "wof:placetype":"venue"
},
  "geometry": {"coordinates":[-80.3183288574,42.8342971802],"type":"Point"}
}