{
  "type": "Feature",
  "properties": {
    "addr:full":"Port Coquitlam BC V3C 1N1",
    "addr:postcode":"v3c 1n1",
    "iso:country":"CA",
    "sg:city":"Port Coquitlam",
    "sg:classifiers":[
        {
            "category":"Wholesale",
            "subcategory":"Auto Parts",
            "type":"Manufacturing & Wholesale Goods"
        }
    ],
    "sg:phone":"+1 604 250 6669",
    "sg:postcode":"V3C 1N1",
    "sg:province":"BC",
    "sg:tags":[
        "automobile",
        "wrecking"
    ],
    "wof:name":"Century Truck Sales & Parts",
    "wof:placetype":"venue"
},
  "geometry": {"coordinates":[-122.768494,49.253487],"type":"Point"}
}