{
  "type": "Feature",
  "properties": {
    "addr:full":"4578 Main St Vancouver BC V5V 3R5",
    "addr:housenumber":"4578",
    "addr:postcode":"v5v 3r5",
    "addr:street":"Main St",
    "iso:country":"CA",
    "sg:address":"4578 Main St",
    "sg:city":"Vancouver",
    "sg:classifiers":[
        {
            "category":"Home & Garden",
            "subcategory":"Hardware",
            "type":"Retail Goods"
        }
    ],
    "sg:phone":"+1 604 872 3118",
    "sg:postcode":"V5V 3R5",
    "sg:province":"BC",
    "wof:name":"Paul's True Value Hardware",
    "wof:placetype":"venue"
},
  "geometry": {"coordinates":[-123.101074,49.243649],"type":"Point"}
}