{
  "type": "Feature",
  "properties": {
    "addr:full":"Nakusp BC V0G 1R0",
    "addr:postcode":"v0g 1r0",
    "iso:country":"CA",
    "sg:city":"Nakusp",
    "sg:classifiers":[
        {
            "category":"Travel",
            "subcategory":"Hotels & Motels",
            "type":"Entertainment"
        }
    ],
    "sg:phone":"+1 250 265 3121",
    "sg:postcode":"V0G 1R0",
    "sg:province":"BC",
    "sg:tags":[
        "resort",
        "center",
        "skiing"
    ],
    "wof:name":"Kootenay Helicopter Skiing Ltd",
    "wof:placetype":"venue"
},
  "geometry": {"coordinates":[-117.804946899,50.2393379211],"type":"Point"}
}