{
  "type": "Feature",
  "properties": {
    "addr:full":"100 Edinburgh Rd S Guelph ON N1H 5P4",
    "addr:housenumber":"100",
    "addr:postcode":"n1h 5p4",
    "addr:street":"Edinburgh Rd",
    "iso:country":"CA",
    "sg:address":"100 Edinburgh Rd S",
    "sg:city":"Guelph",
    "sg:classifiers":[
        {
            "category":"Health Services",
            "subcategory":"Doctor",
            "type":"Services"
        }
    ],
    "sg:phone":"+1 519 824 4700",
    "sg:postcode":"N1H 5P4",
    "sg:province":"ON",
    "sg:tags":[
        "dentist"
    ],
    "wof:name":"Cohen, Donald S DDS",
    "wof:placetype":"venue"
},
  "geometry": {"coordinates":[-80.254791,43.535381],"type":"Point"}
}