{
  "type": "Feature",
  "properties": {
    "addr:full":"10164 107 St #A Westlock AB T7P 1X3",
    "addr:housenumber":"10164",
    "addr:postcode":"t7p 1x3",
    "addr:street":"107 St # A",
    "iso:country":"CA",
    "sg:address":"10164 107 St #A",
    "sg:city":"Westlock",
    "sg:classifiers":[
        {
            "category":"Organizations",
            "subcategory":"Professional Association",
            "type":"Services"
        }
    ],
    "sg:phone":"+1 780 349 5388",
    "sg:postcode":"T7P 1X3",
    "sg:province":"AB",
    "wof:name":"Westlock Independence Network",
    "wof:placetype":"venue"
},
  "geometry": {"coordinates":[-113.85823059099999,54.1574401855],"type":"Point"}
}