{
  "type": "Feature",
  "properties": {
    "addr:full":"Saint-Antoine-DE-Tilly QC G0S 2C0",
    "addr:postcode":"g0s 2c0",
    "iso:country":"CA",
    "sg:city":"Saint-Antoine-DE-Tilly",
    "sg:classifiers":[
        {
            "category":"Shopping",
            "subcategory":"Used Merchandise",
            "type":"Retail Goods"
        }
    ],
    "sg:phone":"+1 418 886 2230",
    "sg:postcode":"G0S 2C0",
    "sg:province":"QC",
    "sg:tags":[
        "antique"
    ],
    "wof:name":"Grange Des Phares",
    "wof:placetype":"venue"
},
  "geometry": {"coordinates":[-71.58200100000001,46.665241],"type":"Point"}
}