{
  "type": "Feature",
  "properties": {
    "addr:full":"1711 Pierard Rd North Vancouver BC V7J 1Y4",
    "addr:housenumber":"1711",
    "addr:postcode":"v7j 1y4",
    "addr:street":"Pierard Rd",
    "iso:country":"CA",
    "sg:address":"1711 Pierard Rd",
    "sg:city":"North Vancouver",
    "sg:classifiers":[
        {
            "category":"Building & Trades",
            "subcategory":"Construction",
            "type":"Services"
        }
    ],
    "sg:phone":"+1 604 986 4798",
    "sg:postcode":"V7J 1Y4",
    "sg:province":"BC",
    "sg:tags":[
        "general",
        "contractor"
    ],
    "wof:name":"Kcr Enterprises Ltd",
    "wof:placetype":"venue"
},
  "geometry": {"coordinates":[-123.02686300000001,49.340542],"type":"Point"}
}