{
  "type": "Feature",
  "properties": {
    "iso:country":"CA",
    "sg:address":"22 George St",
    "sg:city":"Pictou",
    "sg:classifiers":[
        {
            "category":"Personal",
            "subcategory":"Beauty Salon",
            "type":"Services"
        }
    ],
    "sg:phone":"+1 902 485 8892",
    "sg:postcode":"B0K 1H0",
    "sg:province":"NS",
    "wof:name":"Trenditions Hair Design",
    "wof:placetype":"venue"
},
  "geometry": {"coordinates":[-62.7070732117,45.6781806946],"type":"Point"}
}