{
  "type": "Feature",
  "properties": {
    "addr:full":"Collingwood ON L9Y 4T4",
    "addr:postcode":"l9y 4t4",
    "iso:country":"CA",
    "sg:city":"Collingwood",
    "sg:classifiers":[
        {
            "category":"Health Services",
            "subcategory":"Doctor",
            "type":"Services"
        }
    ],
    "sg:phone":"+1 705 444 5303",
    "sg:postcode":"L9Y 4T4",
    "sg:province":"ON",
    "sg:tags":[
        "physiotherapist",
        "surgeon",
        "physician"
    ],
    "wof:name":"Collingwood Sports Medicine",
    "wof:placetype":"venue"
},
  "geometry": {"coordinates":[-80.21668200000001,44.498184],"type":"Point"}
}