{
  "type": "Feature",
  "properties": {
    "addr:full":"New Lowell ON L0M 1N0",
    "addr:postcode":"l0m 1n0",
    "addr:street":"New",
    "iso:country":"CA",
    "sg:city":"New Lowell",
    "sg:classifiers":[
        {
            "category":"Building & Trades",
            "subcategory":"Construction",
            "type":"Services"
        }
    ],
    "sg:phone":"+1 705 424 1695",
    "sg:postcode":"L0M 1N0",
    "sg:province":"ON",
    "sg:tags":[
        "roofing",
        "contractor"
    ],
    "wof:name":"Always Roofing",
    "wof:placetype":"venue"
},
  "geometry": {"coordinates":[-79.965858,44.359894],"type":"Point"}
}