{
  "type": "Feature",
  "properties": {
    "addr:full":"212 Chain Lake Dr Halifax NS B3S 1C5",
    "addr:housenumber":"212",
    "addr:postcode":"b3s 1c5",
    "addr:street":"Chain Lake Dr",
    "iso:country":"CA",
    "sg:address":"212 Chain Lake Dr",
    "sg:city":"Halifax",
    "sg:classifiers":[
        {
            "category":"Shopping",
            "subcategory":"Clothing, Apparel, & Fashions",
            "type":"Retail Goods"
        }
    ],
    "sg:phone":"+1 902 450 0995",
    "sg:postcode":"B3S 1C5",
    "sg:province":"NS",
    "wof:name":"Cotton Ginny",
    "wof:placetype":"venue"
},
  "geometry": {"coordinates":[-63.6754226685,44.6504135132],"type":"Point"}
}