{
  "type": "Feature",
  "properties": {
    "iso:country":"CA",
    "sg:address":"17 1/2 Edward St",
    "sg:city":"London",
    "sg:classifiers":[
        {
            "category":"Sports & Exercise",
            "subcategory":"Bowling",
            "type":"Entertainment"
        }
    ],
    "sg:phone":"+1 519 438 5695",
    "sg:postcode":"N6C 3G9",
    "sg:province":"ON",
    "sg:tags":[
        "center"
    ],
    "wof:name":"Elmwood Lawn Bowling Club",
    "wof:placetype":"venue"
},
  "geometry": {"coordinates":[-81.258224,42.971333],"type":"Point"}
}