{
  "type": "Feature",
  "properties": {
    "addr:full":"Saskatoon SK S7K 2H6",
    "addr:postcode":"s7k 2h6",
    "iso:country":"CA",
    "sg:city":"Saskatoon",
    "sg:classifiers":[
        {
            "category":"Shopping",
            "type":"Retail Goods"
        }
    ],
    "sg:phone":"+1 306 655 4170",
    "sg:postcode":"S7K 2H6",
    "sg:province":"SK",
    "sg:tags":[
        "hearing",
        "equipment",
        "supply",
        "impaired"
    ],
    "wof:name":"Hearing Aid Plan",
    "wof:placetype":"venue"
},
  "geometry": {"coordinates":[-106.66168999999999,52.128876],"type":"Point"}
}