{
  "type": "Feature",
  "properties": {
    "addr:full":"5155 Empire Dr Burnaby BC V5B 1N1",
    "addr:housenumber":"5155",
    "addr:postcode":"v5b 1n1",
    "addr:street":"Empire Dr",
    "iso:country":"CA",
    "sg:address":"5155 Empire Dr",
    "sg:city":"Burnaby",
    "sg:classifiers":[
        {
            "category":"Personal",
            "type":"Services"
        }
    ],
    "sg:phone":"+1 604 298 7228",
    "sg:postcode":"V5B 1N1",
    "sg:province":"BC",
    "sg:tags":[
        "consultant",
        "image"
    ],
    "wof:name":"Personal Impact Image Mgmt",
    "wof:placetype":"venue"
},
  "geometry": {"coordinates":[-122.98835,49.281818],"type":"Point"}
}