{
  "type": "Feature",
  "properties": {
    "addr:full":"101 Placer Crt North York ON M2H 3H9",
    "addr:housenumber":"101",
    "addr:postcode":"m2h 3h9",
    "addr:street":"Placer Crt",
    "iso:country":"CA",
    "sg:address":"101 Placer Crt",
    "sg:city":"North York",
    "sg:classifiers":[
        {
            "category":"Education",
            "subcategory":"Special Training",
            "type":"Public Place"
        }
    ],
    "sg:phone":"+1 416 491 9915",
    "sg:postcode":"M2H 3H9",
    "sg:province":"ON",
    "sg:tags":[
        "instruction",
        "driving"
    ],
    "wof:name":"Al's Driving School",
    "wof:placetype":"venue"
},
  "geometry": {"coordinates":[-79.3416061401,43.8032455444],"type":"Point"}
}