{
  "type": "Feature",
  "properties": {
    "addr:full":"Surrey BC V3W 7X4",
    "addr:postcode":"v3w 7x4",
    "iso:country":"CA",
    "sg:city":"Surrey",
    "sg:classifiers":[
        {
            "category":"Manufacturing",
            "subcategory":"Furniture",
            "type":"Manufacturing & Wholesale Goods"
        }
    ],
    "sg:phone":"+1 604 591 5435",
    "sg:postcode":"V3W 7X4",
    "sg:province":"BC",
    "wof:name":"Purba Custom Furniture Mfr",
    "wof:placetype":"venue"
},
  "geometry": {"coordinates":[-122.86222100000001,49.14938],"type":"Point"}
}