{
  "type": "Feature",
  "properties": {
    "addr:full":"Quigleys Line Bell Island NL A0A 4H0",
    "addr:postcode":"a0a 4h0",
    "addr:street":"Line Bell",
    "iso:country":"CA",
    "sg:address":"Quigleys Line",
    "sg:city":"Bell Island",
    "sg:classifiers":[
        {
            "category":"Retail",
            "subcategory":"Funeral Services",
            "type":"Services"
        }
    ],
    "sg:phone":"+1 709 488 2056",
    "sg:postcode":"A0A 4H0",
    "sg:province":"NL",
    "sg:tags":[
        "director"
    ],
    "wof:name":"Pendergast Funeral Home Ltd",
    "wof:placetype":"venue"
},
  "geometry": {"coordinates":[-52.94907,47.622978],"type":"Point"}
}