{
  "type": "Feature",
  "properties": {
    "addr:full":"902 North Baptiste Lake Rd Maynooth ON K0L 2S0",
    "addr:housenumber":"902",
    "addr:postcode":"k0l 2s0",
    "addr:street":"North Baptiste Lake Rd",
    "iso:country":"CA",
    "sg:address":"902 North Baptiste Lake Rd",
    "sg:city":"Maynooth",
    "sg:classifiers":[
        {
            "category":"Professional",
            "subcategory":"Business Services",
            "type":"Services"
        }
    ],
    "sg:phone":"+1 613 338 3334",
    "sg:postcode":"K0L 2S0",
    "sg:province":"ON",
    "sg:tags":[
        "paralegal"
    ],
    "wof:name":"Graham Davis Advocate Paralega",
    "wof:placetype":"venue"
},
  "geometry": {"coordinates":[-77.936829,45.231323],"type":"Point"}
}