{
  "type": "Feature",
  "properties": {
    "iso:country":"CA",
    "sg:address":"10604 100 St",
    "sg:city":"Grande Prairie",
    "sg:classifiers":[
        {
            "category":"Manufacturing",
            "subcategory":"Printing",
            "type":"Manufacturing & Wholesale Goods"
        }
    ],
    "sg:phone":"+1 780 532 1110",
    "sg:postcode":"T8V 2M5",
    "sg:province":"AB",
    "sg:tags":[
        "newspaper"
    ],
    "wof:name":"Daily Herald-Tribune",
    "wof:placetype":"venue"
},
  "geometry": {"coordinates":[-118.79510498,55.1760368347],"type":"Point"}
}