{
  "type": "Feature",
  "properties": {
    "addr:full":"Port Williams NS B0P 1T0",
    "addr:postcode":"b0p 1t0",
    "iso:country":"CA",
    "sg:city":"Port Williams",
    "sg:classifiers":[
        {
            "category":"Farming",
            "subcategory":"Farm",
            "type":"Manufacturing & Wholesale Goods"
        }
    ],
    "sg:phone":"+1 902 582 7045",
    "sg:postcode":"B0P 1T0",
    "sg:province":"NS",
    "wof:name":"Scott Farms",
    "wof:placetype":"venue"
},
  "geometry": {"coordinates":[-64.4092178345,45.0968322754],"type":"Point"}
}