{
  "type": "Feature",
  "properties": {
    "addr:full":"208 Main St E Grimsby ON L3M 1P6",
    "addr:housenumber":"208",
    "addr:postcode":"l3m 1p6",
    "addr:street":"Main St E",
    "iso:country":"CA",
    "sg:address":"208 Main St E",
    "sg:city":"Grimsby",
    "sg:classifiers":[
        {
            "category":"Building & Trades",
            "subcategory":"Construction",
            "type":"Services"
        }
    ],
    "sg:phone":"+1 905 945 7748",
    "sg:postcode":"L3M 1P6",
    "sg:province":"ON",
    "sg:tags":[
        "painter"
    ],
    "wof:name":"Roy's Painting",
    "wof:placetype":"venue"
},
  "geometry": {"coordinates":[-79.536591,43.18605],"type":"Point"}
}