{
  "type": "Feature",
  "properties": {
    "addr:full":"7740 18 St SE Calgary AB T2C 2N5",
    "addr:housenumber":"7740",
    "addr:postcode":"t2c 2n5",
    "addr:street":"18 St Se",
    "iso:country":"CA",
    "sg:address":"7740 18 St SE",
    "sg:city":"Calgary",
    "sg:classifiers":[
        {
            "category":"Government",
            "subcategory":"Post Office",
            "type":"Public Place"
        }
    ],
    "sg:phone":"+1 403 236 0852",
    "sg:postcode":"T2C 2N5",
    "sg:province":"AB",
    "sg:tags":[
        "pharmacy"
    ],
    "wof:name":"Shoppers Drug Mart",
    "wof:placetype":"venue"
},
  "geometry": {"coordinates":[-114.015586853,50.9834861755],"type":"Point"}
}