{
  "type": "Feature",
  "properties": {
    "addr:full":"3028 Millar Ave Saskatoon SK S7K 5X9",
    "addr:housenumber":"3028",
    "addr:postcode":"s7k 5x9",
    "addr:street":"Millar Ave",
    "iso:country":"CA",
    "sg:address":"3028 Millar Ave",
    "sg:city":"Saskatoon",
    "sg:classifiers":[
        {
            "category":"Wholesale",
            "subcategory":"Machinery & Supplies",
            "type":"Manufacturing & Wholesale Goods"
        }
    ],
    "sg:phone":"+1 306 934 0700",
    "sg:postcode":"S7K 5X9",
    "sg:province":"SK",
    "sg:tags":[
        "bearing",
        "hydraulic",
        "equipment"
    ],
    "wof:name":"Kinecor Inc",
    "wof:placetype":"venue"
},
  "geometry": {"coordinates":[-106.64630099999999,52.178497],"type":"Point"}
}