{
  "type": "Feature",
  "properties": {
    "addr:full":"4A Ch D'Amour Low QC J0X 2C0",
    "addr:housenumber":"4a",
    "addr:postcode":"j0x 2c0",
    "addr:street":"Ch D'Amour",
    "iso:country":"CA",
    "sg:address":"4A Ch D'Amour",
    "sg:city":"Low",
    "sg:classifiers":[
        {
            "category":"Government",
            "subcategory":"Office",
            "type":"Public Place"
        }
    ],
    "sg:phone":"+1 819 422 3528",
    "sg:postcode":"J0X 2C0",
    "sg:province":"QC",
    "sg:tags":[
        "village"
    ],
    "wof:name":"Low Municipality Adm",
    "wof:placetype":"venue"
},
  "geometry": {"coordinates":[-75.9478225708,45.8074684143],"type":"Point"}
}