{
  "type": "Feature",
  "properties": {
    "addr:full":"Little Fort BC V0E 2C0",
    "addr:postcode":"v0e 2c0",
    "iso:country":"CA",
    "sg:city":"Little Fort",
    "sg:classifiers":[
        {
            "category":"Restaurant",
            "type":"Food & Drink"
        }
    ],
    "sg:phone":"+1 250 677 4242",
    "sg:postcode":"V0E 2C0",
    "sg:province":"BC",
    "sg:tags":[
        "pub"
    ],
    "wof:name":"Frontier Hotel",
    "wof:placetype":"venue"
},
  "geometry": {"coordinates":[-120.210067749,51.4259796143],"type":"Point"}
}