{
  "type": "Feature",
  "properties": {
    "addr:full":"10609 172 St NW Edmonton AB T5S 1P1",
    "addr:housenumber":"10609",
    "addr:postcode":"t5s 1p1",
    "addr:street":"172 St Nw",
    "iso:country":"CA",
    "sg:address":"10609 172 St NW",
    "sg:city":"Edmonton",
    "sg:phone":"+1 780 486 2325",
    "sg:postcode":"T5S 1P1",
    "sg:province":"AB",
    "sg:tags":[
        "equipment",
        "supply"
    ],
    "wof:name":"Hobart Food Equipmt Grp Canada",
    "wof:placetype":"venue"
},
  "geometry": {"coordinates":[-113.617660523,53.5508270264],"type":"Point"}
}