{
  "type": "Feature",
  "properties": {
    "addr:full":"5693 Ch DE LA Cote-Des-Neiges Montreal QC H3S 1Y7",
    "addr:postcode":"5693;h3s 1y7",
    "addr:street":"Ch De La Cote-Des-Neiges",
    "iso:country":"CA",
    "sg:address":"5693 Ch DE LA Cote-Des-Neiges",
    "sg:city":"Montreal",
    "sg:classifiers":[
        {
            "category":"Restaurant",
            "type":"Food & Drink"
        }
    ],
    "sg:phone":"+1 514 733 9633",
    "sg:postcode":"H3S 1Y7",
    "sg:province":"QC",
    "sg:tags":[
        "cafe"
    ],
    "wof:name":"Cafe Republique",
    "wof:placetype":"venue"
},
  "geometry": {"coordinates":[-73.627495,45.498764],"type":"Point"}
}