{
  "type": "Feature",
  "properties": {
    "iso:country":"CA",
    "sg:address":"309 5 St S",
    "sg:city":"Lethbridge",
    "sg:classifiers":[
        {
            "category":"Shopping",
            "subcategory":"Clothing, Apparel, & Fashions",
            "type":"Retail Goods"
        }
    ],
    "sg:phone":"+1 403 328 7554",
    "sg:postcode":"T1J 2B4",
    "sg:province":"AB",
    "sg:tags":[
        "western"
    ],
    "wof:name":"Leather Unlimited",
    "wof:placetype":"venue"
},
  "geometry": {"coordinates":[-112.840087891,49.6955604553],"type":"Point"}
}