{
  "type": "Feature",
  "properties": {
    "addr:full":"2630 Av Sainte-Anne Saint-Hyacinthe QC J2S 8R5",
    "addr:housenumber":"2630",
    "addr:postcode":"j2s 8r5",
    "addr:street":"Av Sainte-Anne",
    "iso:country":"CA",
    "sg:address":"2630 Av Sainte-Anne",
    "sg:city":"Saint-Hyacinthe",
    "sg:classifiers":[
        {
            "category":"Personal",
            "subcategory":"Beauty Salon",
            "type":"Services"
        }
    ],
    "sg:phone":"+1 450 773 7377",
    "sg:postcode":"J2S 8R5",
    "sg:province":"QC",
    "sg:tags":[
        "manicuring"
    ],
    "wof:name":"Dufour, Diane",
    "wof:placetype":"venue"
},
  "geometry": {"coordinates":[-72.9584579468,45.632774353],"type":"Point"}
}