{
  "type": "Feature",
  "properties": {
    "addr:full":"336 Herring Cove Rd Halifax NS B3R 1V7",
    "addr:housenumber":"336",
    "addr:postcode":"b3r 1v7",
    "addr:street":"Herring Cove Rd",
    "iso:country":"CA",
    "sg:address":"336 Herring Cove Rd",
    "sg:city":"Halifax",
    "sg:classifiers":[
        {
            "category":"Manufacturing",
            "subcategory":"Food",
            "type":"Manufacturing & Wholesale Goods"
        }
    ],
    "sg:phone":"+1 902 479 1293",
    "sg:postcode":"B3R 1V7",
    "sg:province":"NS",
    "sg:tags":[
        "shop",
        "bakery",
        "cookie",
        "gift"
    ],
    "wof:name":"Mrs P's Oatcakes",
    "wof:placetype":"venue"
},
  "geometry": {"coordinates":[-63.616875,44.613281],"type":"Point"}
}