{
  "type": "Feature",
  "properties": {
    "addr:full":"466 Granville St Vancouver BC V6C 1V4",
    "addr:housenumber":"466",
    "addr:postcode":"bc v6c 1v4",
    "addr:street":"Granville St",
    "iso:country":"CA",
    "sg:address":"466 Granville St",
    "sg:city":"Vancouver",
    "sg:classifiers":[
        {
            "category":"Restaurant",
            "type":"Food & Drink"
        }
    ],
    "sg:phone":"+1 604 681 0073",
    "sg:postcode":"V6C 1V4",
    "sg:province":"BC",
    "sg:tags":[
        "shop",
        "coffee"
    ],
    "wof:name":"Bagel & CO",
    "wof:placetype":"venue"
},
  "geometry": {"coordinates":[-123.114243,49.28479],"type":"Point"}
}