{
  "type": "Feature",
  "properties": {
    "addr:full":"10225 100 Ave NW Edmonton AB T5J 0A1",
    "addr:housenumber":"10225",
    "addr:postcode":"t5j 0a1",
    "addr:street":"100 Ave Nw",
    "iso:country":"CA",
    "sg:address":"10225 100 Ave NW",
    "sg:city":"Edmonton",
    "sg:classifiers":[
        {
            "category":"Government",
            "subcategory":"Office",
            "type":"Public Place"
        }
    ],
    "sg:phone":"+1 780 495 2476",
    "sg:postcode":"T5J 0A1",
    "sg:province":"AB",
    "wof:name":"Canada Corporate Affairs",
    "wof:placetype":"venue"
},
  "geometry": {"coordinates":[-113.496201,53.538696],"type":"Point"}
}