{
  "type": "Feature",
  "properties": {
    "iso:country":"CA",
    "sg:address":"137 Melville St",
    "sg:city":"Dundas",
    "sg:classifiers":[
        {
            "category":"Organizations",
            "subcategory":"Religious Organization",
            "type":"Services"
        }
    ],
    "sg:phone":"+1 905 627 1424",
    "sg:postcode":"L9H 2A6",
    "sg:province":"ON",
    "sg:tags":[
        "church"
    ],
    "wof:name":"St James Anglican Church",
    "wof:placetype":"venue"
},
  "geometry": {"coordinates":[-79.961472,43.269276],"type":"Point"}
}