{
  "type": "Feature",
  "properties": {
    "addr:full":"Lethbridge AB T1J 0K3",
    "addr:postcode":"t1j 0k3",
    "iso:country":"CA",
    "sg:city":"Lethbridge",
    "sg:classifiers":[
        {
            "category":"Insurance",
            "subcategory":"Insurance Agent",
            "type":"Services"
        }
    ],
    "sg:phone":"+1 403 328 2668",
    "sg:postcode":"T1J 0K3",
    "sg:province":"AB",
    "sg:tags":[
        "investment"
    ],
    "wof:name":"Primerica Financial Svc",
    "wof:placetype":"venue"
},
  "geometry": {"coordinates":[-112.82532501199999,49.6966323853],"type":"Point"}
}