{
  "type": "Feature",
  "properties": {
    "iso:country":"CA",
    "sg:address":"108 Av DE Touraine",
    "sg:city":"Saint-Lambert",
    "sg:classifiers":[
        {
            "category":"Professional",
            "subcategory":"Management & Consulting",
            "type":"Services"
        }
    ],
    "sg:phone":"+1 450 671 2436",
    "sg:postcode":"J4S 1H2",
    "sg:province":"QC",
    "sg:tags":[
        "communications",
        "publicity",
        "consultant"
    ],
    "wof:name":"Impact Communications",
    "wof:placetype":"venue"
},
  "geometry": {"coordinates":[-73.5037689209,45.4843025208],"type":"Point"}
}