{
  "type": "Feature",
  "properties": {
    "addr:full":"525 Kenaston Blvd Winnipeg MB R3J 3Y5",
    "addr:housenumber":"525",
    "addr:postcode":"r3j 3y5",
    "addr:street":"Kenaston Blvd",
    "iso:country":"CA",
    "sg:address":"525 Kenaston Blvd",
    "sg:city":"Winnipeg",
    "sg:classifiers":[
        {
            "category":"Recreation",
            "type":"Entertainment"
        }
    ],
    "sg:phone":"+1 204 888 4354",
    "sg:postcode":"R3J 3Y5",
    "sg:province":"MB",
    "sg:tags":[
        "club",
        "curling"
    ],
    "wof:name":"Cfb Winnipeg Curling Club",
    "wof:placetype":"venue"
},
  "geometry": {"coordinates":[-97.206802,49.858948],"type":"Point"}
}