{
  "type": "Feature",
  "properties": {
    "addr:full":"5331 Rue Bannantyne Verdun QC H4H 1E8",
    "addr:housenumber":"5331",
    "addr:postcode":"h4h 1e8",
    "addr:street":"Rue Bannantyne",
    "iso:country":"CA",
    "sg:address":"5331 Rue Bannantyne",
    "sg:city":"Verdun",
    "sg:classifiers":[
        {
            "category":"Professional",
            "subcategory":"Lawyer & Legal Services",
            "type":"Services"
        }
    ],
    "sg:phone":"+1 514 769 8527",
    "sg:postcode":"H4H 1E8",
    "sg:province":"QC",
    "sg:tags":[
        "attorney"
    ],
    "wof:name":"Etude Legale Robert Beaudet",
    "wof:placetype":"venue"
},
  "geometry": {"coordinates":[-73.576797,45.453739],"type":"Point"}
}