{
  "type": "Feature",
  "properties": {
    "addr:full":"Saint-Felicien QC G8K 1T1",
    "addr:postcode":"g8k 1t1",
    "iso:country":"CA",
    "sg:city":"Saint-Felicien",
    "sg:classifiers":[
        {
            "category":"Manufacturing",
            "subcategory":"Printing",
            "type":"Manufacturing & Wholesale Goods"
        }
    ],
    "sg:phone":"+1 418 679 5735",
    "sg:postcode":"G8K 1T1",
    "sg:province":"QC",
    "sg:tags":[
        "printer"
    ],
    "wof:name":"Imprimerie Norlac Ltee",
    "wof:placetype":"venue"
},
  "geometry": {"coordinates":[-72.41269699999999,48.641666],"type":"Point"}
}