{
  "type": "Feature",
  "properties": {
    "iso:country":"CA",
    "sg:address":"626 College St",
    "sg:city":"Toronto",
    "sg:classifiers":[
        {
            "category":"Food & Beverages",
            "subcategory":"Specialty",
            "type":"Retail Goods"
        }
    ],
    "sg:phone":"+1 416 531 7563",
    "sg:postcode":"M6G 1B4",
    "sg:province":"ON",
    "sg:tags":[
        "basket",
        "gourmet",
        "gift",
        "parcel",
        "shop"
    ],
    "wof:name":"Mercantile",
    "wof:placetype":"venue"
},
  "geometry": {"coordinates":[-79.4150085449,43.6551208496],"type":"Point"}
}