{
  "type": "Feature",
  "properties": {
    "addr:full":"424 Bloor St W Toronto ON M5S 1X5",
    "addr:housenumber":"424",
    "addr:postcode":"m5s 1x5",
    "addr:street":"Bloor St W",
    "iso:country":"CA",
    "sg:address":"424 Bloor St W",
    "sg:city":"Toronto",
    "sg:classifiers":[
        {
            "category":"Personal",
            "subcategory":"Barber",
            "type":"Services"
        }
    ],
    "sg:phone":"+1 416 323 0111",
    "sg:postcode":"M5S 1X5",
    "sg:province":"ON",
    "wof:name":"Alex Cuts",
    "wof:placetype":"venue"
},
  "geometry": {"coordinates":[-79.40818,43.66589],"type":"Point"}
}