{
  "type": "Feature",
  "properties": {
    "iso:country":"CA",
    "sg:address":"470 Harrop Dr",
    "sg:city":"Milton",
    "sg:classifiers":[
        {
            "category":"Manufacturing",
            "subcategory":"Metals",
            "type":"Manufacturing & Wholesale Goods"
        }
    ],
    "sg:phone":"+1 905 826 9270",
    "sg:postcode":"L9T 3H2",
    "sg:province":"ON",
    "sg:tags":[
        "screw"
    ],
    "wof:name":"Precision Fasteners Div",
    "wof:placetype":"venue"
},
  "geometry": {"coordinates":[-79.886452,43.531467],"type":"Point"}
}