{
  "type": "Feature",
  "properties": {
    "addr:full":"470 Harrop Dr Milton ON L9T 3H2",
    "addr:housenumber":"470",
    "addr:postcode":"l9t 3h2",
    "addr:street":"Harrop Dr",
    "iso:country":"CA",
    "sg:address":"470 Harrop Dr",
    "sg:city":"Milton",
    "sg:classifiers":[
        {
            "category":"Manufacturing",
            "subcategory":"Metals",
            "type":"Manufacturing & Wholesale Goods"
        }
    ],
    "sg:phone":"+1 905 826 9270",
    "sg:postcode":"L9T 3H2",
    "sg:province":"ON",
    "sg:tags":[
        "screw"
    ],
    "wof:name":"Precision Fasteners Div",
    "wof:placetype":"venue"
},
  "geometry": {"coordinates":[-79.88645200000001,43.531467],"type":"Point"}
}