{
  "type": "Feature",
  "properties": {
    "addr:full":"46 Blackfriars St London ON N6H 1K7",
    "addr:housenumber":"46",
    "addr:postcode":"n6h 1k7",
    "addr:street":"Blackfriars St",
    "iso:country":"CA",
    "sg:address":"46 Blackfriars St",
    "sg:city":"London",
    "sg:classifiers":[
        {
            "category":"Restaurant",
            "type":"Food & Drink"
        }
    ],
    "sg:phone":"+1 519 667 4930",
    "sg:postcode":"N6H 1K7",
    "sg:province":"ON",
    "sg:tags":[
        "caterer"
    ],
    "wof:name":"Blackfriars Bistro & Catering",
    "wof:placetype":"venue"
},
  "geometry": {"coordinates":[-81.260651,42.989136],"type":"Point"}
}