{
  "type": "Feature",
  "properties": {
    "addr:full":"3230 Fairview St Burlington ON L7N 3H5",
    "addr:housenumber":"3230",
    "addr:postcode":"l7n 3h5",
    "addr:street":"Fairview St",
    "iso:country":"CA",
    "sg:address":"3230 Fairview St",
    "sg:city":"Burlington",
    "sg:classifiers":[
        {
            "category":"Shopping",
            "subcategory":"Clothing, Apparel, & Fashions",
            "type":"Retail Goods"
        }
    ],
    "sg:phone":"+1 905 637 5637",
    "sg:postcode":"L7N 3H5",
    "sg:province":"ON",
    "sg:tags":[
        "furnishing"
    ],
    "wof:name":"Mark's Work Wearhouse Ltd",
    "wof:placetype":"venue"
},
  "geometry": {"coordinates":[-79.7897949219,43.3520736694],"type":"Point"}
}