{
  "type": "Feature",
  "properties": {
    "iso:country":"CA",
    "sg:city":"Chilliwack",
    "sg:classifiers":[
        {
            "category":"Health Services",
            "subcategory":"Doctor",
            "type":"Services"
        }
    ],
    "sg:phone":"+1 604 792 6512",
    "sg:postcode":"V2P 4H6",
    "sg:province":"BC",
    "sg:tags":[
        "physician",
        "surgeon"
    ],
    "wof:name":"S H Goodman Inc",
    "wof:placetype":"venue"
},
  "geometry": {"coordinates":[-121.959312439,49.1692733765],"type":"Point"}
}