{
  "type": "Feature",
  "properties": {
    "addr:full":"Lloydminster AB T9V 0A7",
    "addr:postcode":"t9v 0a7",
    "iso:country":"CA",
    "sg:city":"Lloydminster",
    "sg:classifiers":[
        {
            "category":"Shopping",
            "subcategory":"Department Store",
            "type":"Retail Goods"
        }
    ],
    "sg:phone":"+1 780 875 1111",
    "sg:postcode":"T9V 0A7",
    "sg:province":"AB",
    "wof:name":"Sears Canada Inc",
    "wof:placetype":"venue"
},
  "geometry": {"coordinates":[-110.011001587,53.2779350281],"type":"Point"}
}