{
  "type": "Feature",
  "properties": {
    "addr:full":"515 Clyde Rd Cambridge ON N1R 5S7",
    "addr:housenumber":"515",
    "addr:postcode":"n1r 5s7",
    "addr:street":"Clyde Rd",
    "iso:country":"CA",
    "sg:address":"515 Clyde Rd",
    "sg:city":"Cambridge",
    "sg:classifiers":[
        {
            "category":"Manufacturing",
            "subcategory":"Tools & Machinery",
            "type":"Manufacturing & Wholesale Goods"
        }
    ],
    "sg:phone":"+1 519 623 6800",
    "sg:postcode":"N1R 5S7",
    "sg:province":"ON",
    "sg:tags":[
        "machine",
        "shop"
    ],
    "wof:name":"Elite Bending Ltd",
    "wof:placetype":"venue"
},
  "geometry": {"coordinates":[-80.283401,43.373699],"type":"Point"}
}