{
  "type": "Feature",
  "properties": {
    "iso:country":"CA",
    "sg:address":"3614 Rue Ethel",
    "sg:city":"Verdun",
    "sg:classifiers":[
        {
            "category":"Social Services",
            "type":"Services"
        }
    ],
    "sg:phone":"+1 514 761 6668",
    "sg:postcode":"H4G 1S1",
    "sg:province":"QC",
    "sg:tags":[
        "youth",
        "organization",
        "center"
    ],
    "wof:name":"Groupe Jeunesse Action Active",
    "wof:placetype":"venue"
},
  "geometry": {"coordinates":[-73.567467,45.467724],"type":"Point"}
}