{
  "type": "Feature",
  "properties": {
    "addr:full":"38908 Bowen Ave Garibaldi Highlands BC V0N 1T0",
    "addr:housenumber":"38908",
    "addr:postcode":"v0n 1t0",
    "addr:street":"Bowen Ave Garibaldi",
    "iso:country":"CA",
    "sg:address":"38908 Bowen Ave",
    "sg:city":"Garibaldi Highlands",
    "sg:classifiers":[
        {
            "category":"Manufacturing",
            "subcategory":"Tools & Machinery",
            "type":"Manufacturing & Wholesale Goods"
        }
    ],
    "sg:phone":"+1 604 892 2226",
    "sg:postcode":"V0N 1T0",
    "sg:province":"BC",
    "sg:tags":[
        "machine",
        "shop",
        "welding"
    ],
    "wof:name":"Al's Mobile Welding Ltd",
    "wof:placetype":"venue"
},
  "geometry": {"coordinates":[-123.510520935,48.4851150513],"type":"Point"}
}