{
  "type": "Feature",
  "properties": {
    "iso:country":"CA",
    "sg:address":"174 Louth St",
    "sg:city":"St Catharines",
    "sg:classifiers":[
        {
            "category":"Building & Trades",
            "subcategory":"Electrical",
            "type":"Services"
        }
    ],
    "sg:phone":"+1 905 685 1078",
    "sg:postcode":"L2S 2R3",
    "sg:province":"ON",
    "sg:tags":[
        "electric",
        "contractor"
    ],
    "wof:name":"J Cyr Electric",
    "wof:placetype":"venue"
},
  "geometry": {"coordinates":[-79.25956,43.141911],"type":"Point"}
}