{
  "type": "Feature",
  "properties": {
    "addr:full":"174 Louth St St Catharines ON L2S 2R3",
    "addr:housenumber":"174",
    "addr:postcode":"l2s 2r3",
    "addr:street":"Louth St",
    "iso:country":"CA",
    "sg:address":"174 Louth St",
    "sg:city":"St Catharines",
    "sg:classifiers":[
        {
            "category":"Building & Trades",
            "subcategory":"Electrical",
            "type":"Services"
        }
    ],
    "sg:phone":"+1 905 685 1078",
    "sg:postcode":"L2S 2R3",
    "sg:province":"ON",
    "sg:tags":[
        "electric",
        "contractor"
    ],
    "wof:name":"J Cyr Electric",
    "wof:placetype":"venue"
},
  "geometry": {"coordinates":[-79.25955999999999,43.141911],"type":"Point"}
}