{
  "type": "Feature",
  "properties": {
    "addr:full":"Montreal QC H3C 2M1",
    "addr:postcode":"h3c 2m1",
    "iso:country":"CA",
    "sg:city":"Montreal",
    "sg:classifiers":[
        {
            "category":"Professional",
            "subcategory":"Management & Consulting",
            "type":"Services"
        }
    ],
    "sg:phone":"+1 514 871 4939",
    "sg:postcode":"H3C 2M1",
    "sg:province":"QC",
    "sg:tags":[
        "record",
        "consultant"
    ],
    "wof:name":"Interdoc",
    "wof:placetype":"venue"
},
  "geometry": {"coordinates":[-73.5562591553,45.4965667725],"type":"Point"}
}