{
  "type": "Feature",
  "properties": {
    "addr:full":"Toronto ON M5V 2L1",
    "addr:postcode":"m5v 2l1",
    "iso:country":"CA",
    "sg:city":"Toronto",
    "sg:classifiers":[
        {
            "category":"Professional",
            "subcategory":"Business Services",
            "type":"Services"
        }
    ],
    "sg:phone":"+1 416 408 4420",
    "sg:postcode":"M5V 2L1",
    "sg:province":"ON",
    "sg:tags":[
        "arbitration"
    ],
    "wof:name":"Community Legal Education Ont",
    "wof:placetype":"venue"
},
  "geometry": {"coordinates":[-79.39533996580001,43.6470527649],"type":"Point"}
}