{
  "type": "Feature",
  "properties": {
    "addr:full":"4555 Hwy 1 Windsor NS B0N 2T0",
    "addr:housenumber":"4555",
    "addr:postcode":"b0n 2t0",
    "addr:street":"Hwy 1",
    "iso:country":"CA",
    "sg:address":"4555 Hwy 1",
    "sg:city":"Windsor",
    "sg:classifiers":[
        {
            "category":"Education",
            "subcategory":"School",
            "type":"Public Place"
        }
    ],
    "sg:phone":"+1 902 792 6720",
    "sg:postcode":"B0N 2T0",
    "sg:province":"NS",
    "wof:name":"Three Mile Plains Elementary",
    "wof:placetype":"venue"
},
  "geometry": {"coordinates":[-64.12948608400001,44.9804954529],"type":"Point"}
}