{
  "type": "Feature",
  "properties": {
    "addr:full":"600 Front St Wolseley SK S0G 5H0",
    "addr:housenumber":"600",
    "addr:postcode":"s0g 5h0",
    "addr:street":"Front St",
    "iso:country":"CA",
    "sg:address":"600 Front St",
    "sg:city":"Wolseley",
    "sg:classifiers":[
        {
            "category":"Shopping",
            "subcategory":"Catalog Store",
            "type":"Retail Goods"
        }
    ],
    "sg:phone":"+1 306 698 2319",
    "sg:postcode":"S0G 5H0",
    "sg:province":"SK",
    "sg:tags":[
        "mail",
        "order",
        "internet"
    ],
    "wof:name":"Sears Canada Inc",
    "wof:placetype":"venue"
},
  "geometry": {"coordinates":[-103.27891540500001,50.4196395874],"type":"Point"}
}