{
  "type": "Feature",
  "properties": {
    "addr:full":"9768 Second St Sidney BC V8L 3Y8",
    "addr:housenumber":"9768",
    "addr:postcode":"v8l 3y8",
    "addr:street":"Second St",
    "iso:country":"CA",
    "sg:address":"9768 Second St",
    "sg:city":"Sidney",
    "sg:classifiers":[
        {
            "category":"Professional",
            "subcategory":"Research",
            "type":"Services"
        }
    ],
    "sg:phone":"+1 250 656 0127",
    "sg:postcode":"V8L 3Y8",
    "sg:province":"BC",
    "sg:tags":[
        "environmental",
        "ecological"
    ],
    "wof:name":"Lgl Ltd",
    "wof:placetype":"venue"
},
  "geometry": {"coordinates":[-123.39677399999999,48.648151],"type":"Point"}
}