{
  "type": "Feature",
  "properties": {
    "addr:full":"Atikokan ON P0T 1C0",
    "addr:postcode":"p0t 1c0",
    "iso:country":"CA",
    "sg:city":"Atikokan",
    "sg:classifiers":[
        {
            "category":"Autos & Motor Vehicles",
            "subcategory":"Boat Sales",
            "type":"Retail Goods"
        }
    ],
    "sg:phone":"+1 807 597 6801",
    "sg:postcode":"P0T 1C0",
    "sg:province":"ON",
    "sg:tags":[
        "dealer",
        "canoe"
    ],
    "wof:name":"Fletcher Canoes",
    "wof:placetype":"venue"
},
  "geometry": {"coordinates":[-91.5928726196,48.7592315674],"type":"Point"}
}