{
  "type": "Feature",
  "properties": {
    "addr:full":"745 Progress Ave Kingston ON K7M 6S4",
    "addr:housenumber":"745",
    "addr:postcode":"k7m 6s4",
    "addr:street":"Progress Ave",
    "iso:country":"CA",
    "sg:address":"745 Progress Ave",
    "sg:city":"Kingston",
    "sg:classifiers":[
        {
            "category":"Personal",
            "type":"Services"
        }
    ],
    "sg:phone":"+1 613 634 7008",
    "sg:postcode":"K7M 6S4",
    "sg:province":"ON",
    "sg:tags":[
        "program",
        "physical",
        "exercise",
        "fitness"
    ],
    "wof:name":"Progress Fitness & Aquatic Ctr",
    "wof:placetype":"venue"
},
  "geometry": {"coordinates":[-76.57461499999999,44.247009],"type":"Point"}
}