{
  "type": "Feature",
  "properties": {
    "addr:full":"88 Prince William St Saint John NB E2L 2B3",
    "addr:housenumber":"88",
    "addr:postcode":"nb e2l 2b3",
    "addr:street":"Prince William St",
    "iso:country":"CA",
    "sg:address":"88 Prince William St",
    "sg:city":"Saint John",
    "sg:classifiers":[
        {
            "category":"Restaurant",
            "type":"Food & Drink"
        }
    ],
    "sg:phone":"+1 506 652 5252",
    "sg:postcode":"E2L 2B3",
    "sg:province":"NB",
    "wof:name":"Mexicali Rosa's",
    "wof:placetype":"venue"
},
  "geometry": {"coordinates":[-66.061829,45.271893],"type":"Point"}
}