{
  "type": "Feature",
  "properties": {
    "iso:country":"CA",
    "sg:address":"242 Robin Cres",
    "sg:city":"Saskatoon",
    "sg:classifiers":[
        {
            "category":"Manufacturing",
            "subcategory":"Tools & Machinery",
            "type":"Manufacturing & Wholesale Goods"
        }
    ],
    "sg:phone":"+1 306 934 0640",
    "sg:postcode":"S7L 7C2",
    "sg:province":"SK",
    "sg:tags":[
        "farm",
        "equipment"
    ],
    "wof:name":"Agtron Enterprises Inc",
    "wof:placetype":"venue"
},
  "geometry": {"coordinates":[-106.684944153,52.1575393677],"type":"Point"}
}