{
  "type": "Feature",
  "properties": {
    "iso:country":"CA",
    "sg:address":"300 James St N",
    "sg:city":"Hamilton",
    "sg:classifiers":[
        {
            "category":"Restaurant",
            "type":"Food & Drink"
        }
    ],
    "sg:phone":"+1 905 522 2137",
    "sg:postcode":"L8R 2L3",
    "sg:province":"ON",
    "wof:name":"Atlantic Restaurant",
    "wof:placetype":"venue"
},
  "geometry": {"coordinates":[-79.8657608032,43.2638549805],"type":"Point"}
}