{
  "type": "Feature",
  "properties": {
    "addr:full":"10835 148 St Surrey BC V3R 3Y2",
    "addr:housenumber":"10835",
    "addr:postcode":"v3r 3y2",
    "addr:street":"148 St",
    "iso:country":"CA",
    "sg:address":"10835 148 St",
    "sg:city":"Surrey",
    "sg:classifiers":[
        {
            "category":"Retail",
            "subcategory":"Laundry & Dry Cleaning",
            "type":"Services"
        }
    ],
    "sg:phone":"+1 604 581 2911",
    "sg:postcode":"V3R 3Y2",
    "sg:province":"BC",
    "sg:tags":[
        "cleaners"
    ],
    "wof:name":"Betty Brite One Hour Cleaners",
    "wof:placetype":"venue"
},
  "geometry": {"coordinates":[-122.812729,49.199291],"type":"Point"}
}