{
  "type": "Feature",
  "properties": {
    "iso:country":"CA",
    "sg:address":"4484 Rue Sainte-Catherine E",
    "sg:city":"Montreal",
    "sg:classifiers":[
        {
            "category":"Shopping",
            "subcategory":"Pharmacy",
            "type":"Retail Goods"
        }
    ],
    "sg:phone":"+1 514 255 4914",
    "sg:postcode":"H1V 1Y5",
    "sg:province":"QC",
    "wof:name":"Jean Coutu Francois Bebirian",
    "wof:placetype":"venue"
},
  "geometry": {"coordinates":[-73.532684,45.552532],"type":"Point"}
}