{
  "type": "Feature",
  "properties": {
    "addr:full":"5173 Galway Dr Delta BC V4M 3R4",
    "addr:housenumber":"5173",
    "addr:postcode":"v4m 3r4",
    "addr:street":"Galway Dr",
    "iso:country":"CA",
    "sg:address":"5173 Galway Dr",
    "sg:city":"Delta",
    "sg:classifiers":[
        {
            "category":"Professional",
            "subcategory":"Accounting & Tax Preparation",
            "type":"Services"
        }
    ],
    "sg:phone":"+1 604 948 2676",
    "sg:postcode":"V4M 3R4",
    "sg:province":"BC",
    "sg:tags":[
        "accountant"
    ],
    "wof:name":"G V Sweezey Accounting Svc",
    "wof:placetype":"venue"
},
  "geometry": {"coordinates":[-123.081467,49.011459],"type":"Point"}
}