{
  "type": "Feature",
  "properties": {
    "addr:full":"4200 Rue Marcel-Lacasse Boisbriand QC J7H 1N3",
    "addr:housenumber":"4200",
    "addr:postcode":"j7h 1n3",
    "addr:street":"Rue Marcel-Lacasse",
    "iso:country":"CA",
    "sg:address":"4200 Rue Marcel-Lacasse",
    "sg:city":"Boisbriand",
    "sg:classifiers":[
        {
            "category":"Freight",
            "type":"Transportation"
        }
    ],
    "sg:phone":"+1 450 979 4441",
    "sg:postcode":"J7H 1N3",
    "sg:province":"QC",
    "sg:tags":[
        "storage"
    ],
    "wof:name":"Entrepots M Charette",
    "wof:placetype":"venue"
},
  "geometry": {"coordinates":[-73.872711,45.633663],"type":"Point"}
}