{
  "type": "Feature",
  "properties": {
    "addr:full":"137 Saunders Rd Mcadam NB E6J 1L9",
    "addr:housenumber":"137",
    "addr:postcode":"e6j 1l9",
    "addr:street":"Saunders Rd",
    "iso:country":"CA",
    "sg:address":"137 Saunders Rd",
    "sg:city":"Mcadam",
    "sg:classifiers":[
        {
            "category":"Wholesale",
            "subcategory":"Auto Parts",
            "type":"Manufacturing & Wholesale Goods"
        }
    ],
    "sg:phone":"+1 506 784 1911",
    "sg:postcode":"E6J 1L9",
    "sg:province":"NB",
    "sg:tags":[
        "automobile",
        "supply"
    ],
    "wof:name":"Ed's Auto Parts & Supplies",
    "wof:placetype":"venue"
},
  "geometry": {"coordinates":[-67.327461,45.593712],"type":"Point"}
}