{
  "type": "Feature",
  "properties": {
    "addr:full":"91 Champlain St North Bay ON P1B 7M3",
    "addr:housenumber":"91",
    "addr:postcode":"p1b 7m3",
    "addr:street":"Champlain St",
    "iso:country":"CA",
    "sg:address":"91 Champlain St",
    "sg:city":"North Bay",
    "sg:classifiers":[
        {
            "category":"Health Services",
            "subcategory":"Doctor",
            "type":"Services"
        }
    ],
    "sg:phone":"+1 705 494 8733",
    "sg:postcode":"P1B 7M3",
    "sg:province":"ON",
    "sg:tags":[
        "physician",
        "surgeon"
    ],
    "wof:name":"Preston, Paul R MD",
    "wof:placetype":"venue"
},
  "geometry": {"coordinates":[-79.471512,46.333324],"type":"Point"}
}