{
  "type": "Feature",
  "properties": {
    "addr:full":"346 Ryding Ave Toronto ON M6N 1H5",
    "addr:housenumber":"346",
    "addr:postcode":"m6n 1h5",
    "addr:street":"Ryding Ave",
    "iso:country":"CA",
    "sg:address":"346 Ryding Ave",
    "sg:city":"Toronto",
    "sg:classifiers":[
        {
            "category":"Home & Garden",
            "subcategory":"Furniture",
            "type":"Retail Goods"
        }
    ],
    "sg:phone":"+1 416 761 9527",
    "sg:postcode":"M6N 1H5",
    "sg:province":"ON",
    "sg:tags":[
        "equipment",
        "kitchen",
        "cabinet"
    ],
    "wof:name":"P North Kitchen Ltd",
    "wof:placetype":"venue"
},
  "geometry": {"coordinates":[-79.48170500000001,43.668365],"type":"Point"}
}