{
  "type": "Feature",
  "properties": {
    "addr:full":"675 Tecumseh Rd W Windsor ON N8X 1H4",
    "addr:housenumber":"675",
    "addr:postcode":"n8x 1h4",
    "addr:street":"Tecumseh Rd W",
    "iso:country":"CA",
    "sg:address":"675 Tecumseh Rd W",
    "sg:city":"Windsor",
    "sg:classifiers":[
        {
            "category":"Recreation",
            "subcategory":"Amusement Park",
            "type":"Entertainment"
        }
    ],
    "sg:phone":"+1 519 258 9321",
    "sg:postcode":"N8X 1H4",
    "sg:province":"ON",
    "sg:tags":[
        "center",
        "bowling"
    ],
    "wof:name":"Bowlero Bowl",
    "wof:placetype":"venue"
},
  "geometry": {"coordinates":[-83.033569,42.294716],"type":"Point"}
}