{
  "type": "Feature",
  "properties": {
    "addr:full":"540 Mountainview Sq Kitimat BC V8C 2N2",
    "addr:housenumber":"540",
    "addr:postcode":"bc v8c 2n2",
    "addr:street":"Mountainview Sq",
    "iso:country":"CA",
    "sg:address":"540 Mountainview Sq",
    "sg:city":"Kitimat",
    "sg:classifiers":[
        {
            "category":"Social Services",
            "type":"Services"
        }
    ],
    "sg:phone":"+1 250 632 6400",
    "sg:postcode":"V8C 2N2",
    "sg:province":"BC",
    "sg:tags":[
        "counselor"
    ],
    "wof:name":"Northwest Counselling Ctr",
    "wof:placetype":"venue"
},
  "geometry": {"coordinates":[-128.64944457999999,54.0521125793],"type":"Point"}
}