{
  "type": "Feature",
  "properties": {
    "addr:full":"9990 Trafalgar Rd Georgetown ON L7G 4S5",
    "addr:housenumber":"9990",
    "addr:postcode":"l7g 4s5",
    "addr:street":"Trafalgar Rd",
    "iso:country":"CA",
    "sg:address":"9990 Trafalgar Rd",
    "sg:city":"Georgetown",
    "sg:classifiers":[
        {
            "category":"Retail",
            "subcategory":"Auto Repair",
            "type":"Services"
        }
    ],
    "sg:phone":"+1 905 877 7443",
    "sg:postcode":"L7G 4S5",
    "sg:province":"ON",
    "sg:tags":[
        "repairing",
        "automobile"
    ],
    "wof:name":"T & T Auto Repair",
    "wof:placetype":"venue"
},
  "geometry": {"coordinates":[-79.891853,43.605827],"type":"Point"}
}