{
  "type": "Feature",
  "properties": {
    "addr:full":"4204 Fourth Ave Smithers BC V0J 2N3",
    "addr:housenumber":"4204",
    "addr:postcode":"v0j 2n3",
    "addr:street":"Fourth Ave",
    "iso:country":"CA",
    "sg:address":"4204 Fourth Ave",
    "sg:city":"Smithers",
    "sg:classifiers":[
        {
            "category":"Government",
            "subcategory":"Office",
            "type":"Public Place"
        }
    ],
    "sg:phone":"+1 250 847 5719",
    "sg:postcode":"V0J 2N3",
    "sg:province":"BC",
    "sg:tags":[
        "village"
    ],
    "wof:name":"Smithers Public Skating",
    "wof:placetype":"venue"
},
  "geometry": {"coordinates":[-127.177841187,54.7885093689],"type":"Point"}
}