{
  "type": "Feature",
  "properties": {
    "iso:country":"CA",
    "sg:address":"320 9E Av",
    "sg:city":"Deux-Montagnes",
    "sg:classifiers":[
        {
            "category":"Building & Trades",
            "subcategory":"Plumbing",
            "type":"Services"
        }
    ],
    "sg:phone":"+1 450 623 7620",
    "sg:postcode":"J7R 3M5",
    "sg:province":"QC",
    "sg:tags":[
        "contractor"
    ],
    "wof:name":"Plomberie Gil-Mar Inc",
    "wof:placetype":"venue"
},
  "geometry": {"coordinates":[-73.8985366821,45.5447616577],"type":"Point"}
}