{
  "type": "Feature",
  "properties": {
    "addr:full":"4251 Dundas St E RR 4 Belleville ON K8N 4Z4",
    "addr:housenumber":"4251",
    "addr:postcode":"k8n 4z4",
    "addr:street":"Dundas St;Rr 4",
    "iso:country":"CA",
    "sg:address":"4251 Dundas St E RR 4",
    "sg:city":"Belleville",
    "sg:classifiers":[
        {
            "category":"Building & Trades",
            "subcategory":"Electrical",
            "type":"Services"
        }
    ],
    "sg:phone":"+1 613 967 2275",
    "sg:postcode":"K8N 4Z4",
    "sg:province":"ON",
    "sg:tags":[
        "home",
        "contractor",
        "electric",
        "improvement"
    ],
    "wof:name":"Line's Electric",
    "wof:placetype":"venue"
},
  "geometry": {"coordinates":[-77.3128662109,44.1734962463],"type":"Point"}
}