{
  "type": "Feature",
  "properties": {
    "addr:full":"49 Huron Clinton ON N0M 1L0",
    "addr:housenumber":"49",
    "addr:postcode":"n0m 1l0",
    "addr:street":"Huron",
    "iso:country":"CA",
    "sg:address":"49 Huron",
    "sg:city":"Clinton",
    "sg:classifiers":[
        {
            "category":"Building & Trades",
            "subcategory":"Construction",
            "type":"Services"
        }
    ],
    "sg:phone":"+1 519 482 9276",
    "sg:postcode":"N0M 1L0",
    "sg:province":"ON",
    "sg:tags":[
        "insulation",
        "heat",
        "contractor"
    ],
    "wof:name":"Central Huron Insulation Inc",
    "wof:placetype":"venue"
},
  "geometry": {"coordinates":[-81.54113,43.617912],"type":"Point"}
}