{
  "type": "Feature",
  "properties": {
    "addr:full":"200 Lakeshore Rd New Liskeard ON P0J 1P0",
    "addr:housenumber":"200",
    "addr:postcode":"p0j 1p0",
    "addr:street":"Lakeshore Rd",
    "iso:country":"CA",
    "sg:address":"200 Lakeshore Rd",
    "sg:city":"New Liskeard",
    "sg:classifiers":[
        {
            "category":"Government",
            "subcategory":"Fire Station",
            "type":"Public Place"
        }
    ],
    "sg:phone":"+1 ",
    "sg:postcode":"P0J 1P0",
    "sg:province":"ON",
    "sg:tags":[
        "department"
    ],
    "wof:name":"New Liskeard Public Works",
    "wof:placetype":"venue"
},
  "geometry": {"coordinates":[-79.67990112299999,47.5040283203],"type":"Point"}
}