{
  "type": "Feature",
  "properties": {
    "addr:full":"29 Rte 275 N Frampton QC G0R 1M0",
    "addr:housenumber":"29",
    "addr:postcode":"g0r 1m0",
    "addr:street":"Rte 275 N",
    "iso:country":"CA",
    "sg:address":"29 Rte 275 N",
    "sg:city":"Frampton",
    "sg:classifiers":[
        {
            "category":"Sports & Exercise",
            "subcategory":"Golf",
            "type":"Entertainment"
        }
    ],
    "sg:phone":"+1 418 479 5589",
    "sg:postcode":"G0R 1M0",
    "sg:province":"QC",
    "sg:tags":[
        "range",
        "practice"
    ],
    "wof:name":"Club DE Golf Dorchester Inc",
    "wof:placetype":"venue"
},
  "geometry": {"coordinates":[-70.8417510986,46.4892692566],"type":"Point"}
}