{
  "type": "Feature",
  "properties": {
    "addr:full":"2236 Victoria St N Why 7 Breslau ON N0B 1M0",
    "addr:housenumber":"2236;7",
    "addr:postcode":"n0b 1m0",
    "addr:street":"Victoria St N Why",
    "iso:country":"CA",
    "sg:address":"2236 Victoria St N Why 7",
    "sg:city":"Breslau",
    "sg:classifiers":[
        {
            "category":"Manufacturing",
            "subcategory":"Metals",
            "type":"Manufacturing & Wholesale Goods"
        }
    ],
    "sg:phone":"+1 519 648 2944",
    "sg:postcode":"N0B 1M0",
    "sg:province":"ON",
    "sg:tags":[
        "stamping"
    ],
    "wof:name":"Kbk Mfg Ltd",
    "wof:placetype":"venue"
},
  "geometry": {"coordinates":[-80.414299,43.490158],"type":"Point"}
}