{
  "type": "Feature",
  "properties": {
    "iso:country":"CA",
    "sg:address":"805 Rue DE L'Innovation",
    "sg:city":"LA Baie",
    "sg:classifiers":[
        {
            "category":"Retail",
            "subcategory":"Repair Shop",
            "type":"Services"
        }
    ],
    "sg:phone":"+1 418 677 1518",
    "sg:postcode":"G7B 3N8",
    "sg:province":"QC",
    "sg:tags":[
        "machine",
        "welding"
    ],
    "wof:name":"Industrie Gmi Inc",
    "wof:placetype":"venue"
},
  "geometry": {"coordinates":[-70.9496231079,48.3275718689],"type":"Point"}
}