{
  "type": "Feature",
  "properties": {
    "addr:full":"PO Box 131 Middle Arm Gb NL A0K 3R0",
    "addr:housenumber":"po;131",
    "addr:postcode":"a0k 3r0",
    "addr:street":"Box;Middle Arm",
    "iso:country":"CA",
    "sg:address":"PO Box 131",
    "sg:city":"Middle Arm Gb",
    "sg:classifiers":[
        {
            "category":"Autos & Motor Vehicles",
            "subcategory":"Fuel & Gas Station",
            "type":"Retail Goods"
        }
    ],
    "sg:phone":"+1 709 252 2604",
    "sg:postcode":"A0K 3R0",
    "sg:province":"NL",
    "sg:tags":[
        "oil"
    ],
    "wof:name":"Noble's Gas Bar & Convenience",
    "wof:placetype":"venue"
},
  "geometry": {"coordinates":[-56.0895309448,49.7042312622],"type":"Point"}
}