{
  "type": "Feature",
  "properties": {
    "addr:full":"360 Mayfield Common NW Edmonton AB T5P 4B3",
    "addr:housenumber":"360",
    "addr:postcode":"t5p 4b3",
    "addr:street":"Mayfield Common Nw",
    "iso:country":"CA",
    "sg:address":"360 Mayfield Common NW",
    "sg:city":"Edmonton",
    "sg:classifiers":[
        {
            "category":"Food & Beverages",
            "subcategory":"Groceries & Convenience Stores",
            "type":"Retail Goods"
        }
    ],
    "sg:phone":"+1 780 484 1088",
    "sg:postcode":"T5P 4B3",
    "sg:province":"AB",
    "sg:tags":[
        "grocer"
    ],
    "wof:name":"Save-On-Foods & Drugs",
    "wof:placetype":"venue"
},
  "geometry": {"coordinates":[-113.615432739,53.5435295105],"type":"Point"}
}