{
  "type": "Feature",
  "properties": {
    "addr:full":"PO Box 26 Mclean SK S0G 3E0",
    "addr:housenumber":"po box 26",
    "addr:postcode":"s0g 3e0",
    "iso:country":"CA",
    "sg:address":"PO Box 26",
    "sg:city":"Mclean",
    "sg:classifiers":[
        {
            "category":"Building & Trades",
            "subcategory":"Construction",
            "type":"Services"
        }
    ],
    "sg:phone":"+1 306 699 7181",
    "sg:postcode":"S0G 3E0",
    "sg:province":"SK",
    "sg:tags":[
        "excavating",
        "contractor"
    ],
    "wof:name":"Grad's Construction",
    "wof:placetype":"venue"
},
  "geometry": {"coordinates":[-104.073357,50.514225],"type":"Point"}
}