{
  "type": "Feature",
  "properties": {
    "addr:full":"902 7 Ave S Lethbridge AB T1J 1J9",
    "addr:housenumber":"902",
    "addr:postcode":"t1j 1j9",
    "addr:street":"7 Ave S",
    "iso:country":"CA",
    "sg:address":"902 7 Ave S",
    "sg:city":"Lethbridge",
    "sg:classifiers":[
        {
            "category":"Personal",
            "subcategory":"Beauty Salon",
            "type":"Services"
        }
    ],
    "sg:phone":"+1 403 328 5463",
    "sg:postcode":"T1J 1J9",
    "sg:province":"AB",
    "wof:name":"Cheyanne's Cutting Corner",
    "wof:placetype":"venue"
},
  "geometry": {"coordinates":[-112.833023,49.689091],"type":"Point"}
}