{
  "type": "Feature",
  "properties": {
    "addr:full":"6 Pacific Ave Toronto ON M6P 2P3",
    "addr:housenumber":"6",
    "addr:postcode":"m6p 2p3",
    "addr:street":"Pacific Ave",
    "iso:country":"CA",
    "sg:address":"6 Pacific Ave",
    "sg:city":"Toronto",
    "sg:classifiers":[
        {
            "category":"Health Services",
            "subcategory":"Doctor",
            "type":"Services"
        }
    ],
    "sg:phone":"+1 416 762 9706",
    "sg:postcode":"M6P 2P3",
    "sg:province":"ON",
    "sg:tags":[
        "dentist"
    ],
    "wof:name":"Kominek, Ivan DDS",
    "wof:placetype":"venue"
},
  "geometry": {"coordinates":[-79.46405799999999,43.654312],"type":"Point"}
}