{
  "type": "Feature",
  "properties": {
    "addr:full":"40 Connell Close Red Deer AB T4P 2T8",
    "addr:housenumber":"40",
    "addr:postcode":"t4p 2t8",
    "addr:street":"Connell Close",
    "iso:country":"CA",
    "sg:address":"40 Connell Close",
    "sg:city":"Red Deer",
    "sg:classifiers":[
        {
            "category":"Building & Trades",
            "subcategory":"Construction",
            "type":"Services"
        }
    ],
    "sg:phone":"+1 403 346 5112",
    "sg:postcode":"T4P 2T8",
    "sg:province":"AB",
    "sg:tags":[
        "general",
        "contractor"
    ],
    "wof:name":"Help U Build Renovation",
    "wof:placetype":"venue"
},
  "geometry": {"coordinates":[-113.771805,52.270912],"type":"Point"}
}