{
  "type": "Feature",
  "properties": {
    "addr:full":"795 Northumberland Hts Rd Cobourg ON K9A 4J8",
    "addr:housenumber":"795",
    "addr:postcode":"k9a 4j8",
    "addr:street":"Northumberland Hts Rd",
    "iso:country":"CA",
    "sg:address":"795 Northumberland Hts Rd",
    "sg:city":"Cobourg",
    "sg:classifiers":[
        {
            "category":"Restaurant",
            "type":"Food & Drink"
        }
    ],
    "sg:phone":"+1 905 372 7500",
    "sg:postcode":"K9A 4J8",
    "sg:province":"ON",
    "wof:name":"Northumberland Heights Country",
    "wof:placetype":"venue"
},
  "geometry": {"coordinates":[-78.167778,43.959606],"type":"Point"}
}