{
  "type": "Feature",
  "properties": {
    "addr:full":"908 Dundas St Woodstock ON N4S 1H1",
    "addr:housenumber":"908",
    "addr:postcode":"n4s 1h1",
    "addr:street":"Dundas St",
    "iso:country":"CA",
    "sg:address":"908 Dundas St",
    "sg:city":"Woodstock",
    "sg:classifiers":[
        {
            "category":"Education",
            "subcategory":"School",
            "type":"Public Place"
        }
    ],
    "sg:phone":"+1 519 537 2012",
    "sg:postcode":"N4S 1H1",
    "sg:province":"ON",
    "wof:name":"St Rita's School",
    "wof:placetype":"venue"
},
  "geometry": {"coordinates":[-80.73747299999999,43.132732],"type":"Point"}
}