{
  "type": "Feature",
  "properties": {
    "addr:full":"Scarborough ON M1L 4S7",
    "addr:postcode":"m1l 4s7",
    "iso:country":"CA",
    "sg:city":"Scarborough",
    "sg:classifiers":[
        {
            "category":"Health Services",
            "subcategory":"Doctor",
            "type":"Services"
        }
    ],
    "sg:phone":"+1 416 285 8105",
    "sg:postcode":"M1L 4S7",
    "sg:province":"ON",
    "sg:tags":[
        "dentist"
    ],
    "wof:name":"Wong, Natalie E DDS",
    "wof:placetype":"venue"
},
  "geometry": {"coordinates":[-79.27973900000001,43.729733],"type":"Point"}
}