{
  "type": "Feature",
  "properties": {
    "iso:country":"CA",
    "sg:address":"551 10E Av",
    "sg:city":"Senneterre",
    "sg:classifiers":[
        {
            "category":"Government",
            "subcategory":"Office",
            "type":"Public Place"
        }
    ],
    "sg:phone":"+1 819 737 2446",
    "sg:postcode":"J0Y 2M0",
    "sg:province":"QC",
    "sg:tags":[
        "village"
    ],
    "wof:name":"Senneterre Office Municipal",
    "wof:placetype":"venue"
},
  "geometry": {"coordinates":[-77.24184417719999,48.3903274536],"type":"Point"}
}