{
  "type": "Feature",
  "properties": {
    "addr:full":"Laval QC H7V 3T7",
    "addr:postcode":"h7v 3t7",
    "iso:country":"CA",
    "sg:city":"Laval",
    "sg:classifiers":[
        {
            "category":"Personal",
            "type":"Services"
        }
    ],
    "sg:phone":"+1 450 681 7699",
    "sg:postcode":"H7V 3T7",
    "sg:province":"QC",
    "sg:tags":[
        "electrolysis"
    ],
    "wof:name":"Electrolyse Rebecca",
    "wof:placetype":"venue"
},
  "geometry": {"coordinates":[-73.7522354126,45.5442962646],"type":"Point"}
}