{
  "type": "Feature",
  "properties": {
    "addr:full":"Montreal QC H2N 2J3",
    "addr:postcode":"h2n 2j3",
    "iso:country":"CA",
    "sg:city":"Montreal",
    "sg:classifiers":[
        {
            "category":"Manufacturing",
            "subcategory":"Paper Products",
            "type":"Manufacturing & Wholesale Goods"
        }
    ],
    "sg:phone":"+1 514 381 2949",
    "sg:postcode":"H2N 2J3",
    "sg:province":"QC",
    "sg:tags":[
        "tag"
    ],
    "wof:name":"Ibc Svc Inc",
    "wof:placetype":"venue"
},
  "geometry": {"coordinates":[-73.648865,45.548431],"type":"Point"}
}