{
  "type": "Feature",
  "properties": {
    "addr:full":"8 Earle St Grand Falls-Windsor NL A2B 1H5",
    "addr:housenumber":"8",
    "addr:postcode":"a2b 1h5",
    "addr:street":"Earle St",
    "iso:country":"CA",
    "sg:address":"8 Earle St",
    "sg:city":"Grand Falls-Windsor",
    "sg:classifiers":[
        {
            "category":"Retail",
            "subcategory":"Auto Repair",
            "type":"Services"
        }
    ],
    "sg:phone":"+1 709 489 9186",
    "sg:postcode":"A2B 1H5",
    "sg:province":"NL",
    "sg:tags":[
        "repairing",
        "automobile"
    ],
    "wof:name":"Dyke's Auto Ctr",
    "wof:placetype":"venue"
},
  "geometry": {"coordinates":[-55.66222,48.952007],"type":"Point"}
}