{
  "type": "Feature",
  "properties": {
    "addr:full":"203 Catherine St Ottawa ON K2P 1C3",
    "addr:housenumber":"203",
    "addr:postcode":"k2p 1c3",
    "addr:street":"Catherine St",
    "iso:country":"CA",
    "sg:address":"203 Catherine St",
    "sg:city":"Ottawa",
    "sg:classifiers":[
        {
            "category":"Professional",
            "subcategory":"Management & Consulting",
            "type":"Services"
        }
    ],
    "sg:phone":"+1 613 233 8815",
    "sg:postcode":"K2P 1C3",
    "sg:province":"ON",
    "sg:tags":[
        "project"
    ],
    "wof:name":"R G Enterprise Inc",
    "wof:placetype":"venue"
},
  "geometry": {"coordinates":[-75.6916351318,45.4098014832],"type":"Point"}
}