{
  "type": "Feature",
  "properties": {
    "addr:full":"6300 Av Du Parc Montreal QC H2V 4H8",
    "addr:housenumber":"6300",
    "addr:postcode":"h2v 4h8",
    "addr:street":"Av Du Parc",
    "iso:country":"CA",
    "sg:address":"6300 Av Du Parc",
    "sg:city":"Montreal",
    "sg:classifiers":[
        {
            "category":"Arts & Performance",
            "subcategory":"Theater",
            "type":"Entertainment"
        }
    ],
    "sg:phone":"+1 514 270 0011",
    "sg:postcode":"H2V 4H8",
    "sg:province":"QC",
    "sg:tags":[
        "bureau"
    ],
    "wof:name":"Management Encore Inc",
    "wof:placetype":"venue"
},
  "geometry": {"coordinates":[-73.6124343872,45.5267066956],"type":"Point"}
}