{
  "type": "Feature",
  "properties": {
    "addr:full":"North Bay ON P1B 9S7",
    "addr:postcode":"p1b 9s7",
    "iso:country":"CA",
    "sg:city":"North Bay",
    "sg:classifiers":[
        {
            "category":"Manufacturing",
            "subcategory":"Glass & Minerals",
            "type":"Manufacturing & Wholesale Goods"
        }
    ],
    "sg:phone":"+1 705 495 4897",
    "sg:postcode":"P1B 9S7",
    "sg:province":"ON",
    "sg:tags":[
        "product",
        "marble"
    ],
    "wof:name":"Ageless Marble & Granite Ltd",
    "wof:placetype":"venue"
},
  "geometry": {"coordinates":[-79.4872665405,46.3277015686],"type":"Point"}
}