{
  "type": "Feature",
  "properties": {
    "addr:full":"Saint-Laurent QC H4M 2E2",
    "addr:postcode":"h4m 2e2",
    "iso:country":"CA",
    "sg:city":"Saint-Laurent",
    "sg:classifiers":[
        {
            "category":"Wholesale",
            "subcategory":"Apparel",
            "type":"Manufacturing & Wholesale Goods"
        }
    ],
    "sg:phone":"+1 514 748 9790",
    "sg:postcode":"H4M 2E2",
    "sg:province":"QC",
    "sg:tags":[
        "handbag"
    ],
    "wof:name":"Cheldy Sales Agency",
    "wof:placetype":"venue"
},
  "geometry": {"coordinates":[-73.6807937622,45.5018386841],"type":"Point"}
}