{
  "type": "Feature",
  "properties": {
    "addr:full":"233 Pembina Trail Ave Ste Agathe MB R0G 1Y0",
    "addr:housenumber":"233",
    "addr:postcode":"r0g 1y0",
    "addr:street":"Pembina Trail Ave Ste Agathe",
    "iso:country":"CA",
    "sg:address":"233 Pembina Trail Ave",
    "sg:city":"Ste Agathe",
    "sg:classifiers":[
        {
            "category":"Organizations",
            "subcategory":"Religious Organization",
            "type":"Services"
        }
    ],
    "sg:phone":"+1 204 882 2102",
    "sg:postcode":"R0G 1Y0",
    "sg:province":"MB",
    "sg:tags":[
        "church"
    ],
    "wof:name":"Ste Agathe Rc Rectory",
    "wof:placetype":"venue"
},
  "geometry": {"coordinates":[-97.1465911865,49.6004867554],"type":"Point"}
}