{
  "type": "Feature",
  "properties": {
    "addr:full":"1 Isleview Dr Stratford PE C1B 1M1",
    "addr:housenumber":"1",
    "addr:postcode":"c1b 1m1",
    "addr:street":"Isleview Dr",
    "iso:country":"CA",
    "sg:address":"1 Isleview Dr",
    "sg:city":"Stratford",
    "sg:classifiers":[
        {
            "category":"Wholesale",
            "subcategory":"Machinery & Supplies",
            "type":"Manufacturing & Wholesale Goods"
        }
    ],
    "sg:phone":"+1 902 569 4383",
    "sg:postcode":"C1B 1M1",
    "sg:province":"PE",
    "sg:tags":[
        "sprinkler"
    ],
    "wof:name":"Island Sprinkler Systems Ltd",
    "wof:placetype":"venue"
},
  "geometry": {"coordinates":[-63.0804634094,46.2009086609],"type":"Point"}
}