{
  "type": "Feature",
  "properties": {
    "addr:full":"Laval QC H7T 2L1",
    "addr:postcode":"h7t 2l1",
    "iso:country":"CA",
    "sg:city":"Laval",
    "sg:classifiers":[
        {
            "category":"Manufacturing",
            "subcategory":"Electronics",
            "type":"Manufacturing & Wholesale Goods"
        }
    ],
    "sg:phone":"+1 450 686 4723",
    "sg:postcode":"H7T 2L1",
    "sg:province":"QC",
    "sg:tags":[
        "semiconductor",
        "devices"
    ],
    "wof:name":"National Semiconductor Canada",
    "wof:placetype":"venue"
},
  "geometry": {"coordinates":[-73.7558135986,45.5671615601],"type":"Point"}
}