{
  "type": "Feature",
  "properties": {
    "addr:full":"1095 Mississaga St W Orillia ON L3V 6W7",
    "addr:housenumber":"1095",
    "addr:postcode":"l3v 6w7",
    "addr:street":"Mississaga St W",
    "iso:country":"CA",
    "sg:address":"1095 Mississaga St W",
    "sg:city":"Orillia",
    "sg:classifiers":[
        {
            "category":"Real Estate",
            "subcategory":"Real Estate Operator",
            "type":"Services"
        }
    ],
    "sg:phone":"+1 705 325 4533",
    "sg:postcode":"L3V 6W7",
    "sg:province":"ON",
    "sg:tags":[
        "apartment"
    ],
    "wof:name":"Village Green",
    "wof:placetype":"venue"
},
  "geometry": {"coordinates":[-79.4418716431,44.5926933289],"type":"Point"}
}