{
  "type": "Feature",
  "properties": {
    "addr:full":"Calgary AB T2E 8S7",
    "addr:postcode":"t2e 8s7",
    "iso:country":"CA",
    "sg:city":"Calgary",
    "sg:classifiers":[
        {
            "category":"Utilities",
            "subcategory":"Mobile Phone",
            "type":"Services"
        }
    ],
    "sg:phone":"+1 403 520 0388",
    "sg:postcode":"T2E 8S7",
    "sg:province":"AB",
    "sg:tags":[
        "telephone",
        "cellular"
    ],
    "wof:name":"Unipage Solutions Inc",
    "wof:placetype":"venue"
},
  "geometry": {"coordinates":[-114.062729,51.066242],"type":"Point"}
}