{
  "type": "Feature",
  "properties": {
    "addr:full":"3 Leamington Hts Point Leamington NL A0H 1Z0",
    "addr:housenumber":"3",
    "addr:postcode":"a0h 1z0",
    "addr:street":"Leamington Hts Point",
    "iso:country":"CA",
    "sg:address":"3 Leamington Hts",
    "sg:city":"Point Leamington",
    "sg:classifiers":[
        {
            "category":"Government",
            "subcategory":"Office",
            "type":"Public Place"
        }
    ],
    "sg:phone":"+1 709 484 3421",
    "sg:postcode":"A0H 1Z0",
    "sg:province":"NL",
    "sg:tags":[
        "village"
    ],
    "wof:name":"Point Leamington Town Council",
    "wof:placetype":"venue"
},
  "geometry": {"coordinates":[-55.406029,49.319309],"type":"Point"}
}