{
  "type": "Feature",
  "properties": {
    "addr:full":"37 Finkle St Woodstock ON N4S 3C7",
    "addr:housenumber":"37",
    "addr:postcode":"n4s 3c7",
    "addr:street":"Finkle St",
    "iso:country":"CA",
    "sg:address":"37 Finkle St",
    "sg:city":"Woodstock",
    "sg:classifiers":[
        {
            "category":"Manufacturing",
            "subcategory":"Tools & Machinery",
            "type":"Manufacturing & Wholesale Goods"
        }
    ],
    "sg:phone":"+1 519 539 3823",
    "sg:postcode":"N4S 3C7",
    "sg:province":"ON",
    "sg:tags":[
        "system",
        "electric",
        "heating",
        "air",
        "conditioning",
        "contractor"
    ],
    "wof:name":"Mike's Electric Ltd",
    "wof:placetype":"venue"
},
  "geometry": {"coordinates":[-80.757378,43.128769],"type":"Point"}
}