{
  "type": "Feature",
  "properties": {
    "addr:full":"PO Box 239 Baker Lake NU X0C 0A0",
    "addr:housenumber":"po",
    "addr:postcode":"x0c 0a0",
    "addr:street":"Box 239 Baker",
    "iso:country":"CA",
    "sg:address":"PO Box 239",
    "sg:city":"Baker Lake",
    "sg:classifiers":[
        {
            "category":"Professional",
            "subcategory":"Business Services",
            "type":"Services"
        }
    ],
    "sg:phone":"+1 867 793 2010",
    "sg:postcode":"X0C 0A0",
    "sg:province":"NU",
    "sg:tags":[
        "reservation",
        "motel",
        "hotel",
        "fraternal",
        "organization"
    ],
    "wof:name":"Baker Lake Lodge",
    "wof:placetype":"venue"
},
  "geometry": {"coordinates":[-96.020386,64.317345],"type":"Point"}
}