{
  "type": "Feature",
  "properties": {
    "addr:full":"10605 101 St NW Edmonton AB T5H 2S2",
    "addr:housenumber":"10605",
    "addr:postcode":"t5h 2s2",
    "addr:street":"101 St Nw",
    "iso:country":"CA",
    "sg:address":"10605 101 St NW",
    "sg:city":"Edmonton",
    "sg:classifiers":[
        {
            "category":"Food & Beverages",
            "subcategory":"Groceries & Convenience Stores",
            "type":"Retail Goods"
        }
    ],
    "sg:phone":"+1 780 426 6210",
    "sg:postcode":"T5H 2S2",
    "sg:province":"AB",
    "sg:tags":[
        "grocer"
    ],
    "wof:name":"Omonia Foods Import",
    "wof:placetype":"venue"
},
  "geometry": {"coordinates":[-113.49359893800001,53.5499687195],"type":"Point"}
}