{
  "type": "Feature",
  "properties": {
    "addr:full":"9251 50 St NW Edmonton AB T6B 3B6",
    "addr:housenumber":"9251",
    "addr:postcode":"t6b 3b6",
    "addr:street":"50 St Nw",
    "iso:country":"CA",
    "sg:address":"9251 50 St NW",
    "sg:city":"Edmonton",
    "sg:classifiers":[
        {
            "category":"Retail",
            "subcategory":"Auto Repair",
            "type":"Services"
        }
    ],
    "sg:phone":"+1 780 468 6464",
    "sg:postcode":"T6B 3B6",
    "sg:province":"AB",
    "sg:tags":[
        "muffler",
        "exhaust",
        "system"
    ],
    "wof:name":"Alta Custom Exhaust Ltd",
    "wof:placetype":"venue"
},
  "geometry": {"coordinates":[-113.417931,53.528576],"type":"Point"}
}