{
  "type": "Feature",
  "properties": {
    "iso:country":"CA",
    "sg:city":"Scarborough",
    "sg:classifiers":[
        {
            "category":"Retail",
            "subcategory":"Laundry & Dry Cleaning",
            "type":"Services"
        }
    ],
    "sg:phone":"+1 416 266 9896",
    "sg:postcode":"M1J 3M4",
    "sg:province":"ON",
    "sg:tags":[
        "cleaners"
    ],
    "wof:name":"Silvermile Dry Cleaners",
    "wof:placetype":"venue"
},
  "geometry": {"coordinates":[-79.207862854,43.7472915649],"type":"Point"}
}