{
  "type": "Feature",
  "properties": {
    "addr:full":"Warden QC J0E 2M0",
    "addr:postcode":"j0e 2m0",
    "iso:country":"CA",
    "sg:city":"Warden",
    "sg:classifiers":[
        {
            "category":"Building & Trades",
            "subcategory":"Electrical",
            "type":"Services"
        }
    ],
    "sg:phone":"+1 450 539 3233",
    "sg:postcode":"J0E 2M0",
    "sg:province":"QC",
    "sg:tags":[
        "electric",
        "contractor"
    ],
    "wof:name":"Beauregard Electrique G",
    "wof:placetype":"venue"
},
  "geometry": {"coordinates":[-72.502831,45.38105],"type":"Point"}
}