{
  "type": "Feature",
  "properties": {
    "addr:full":"2510 Rue Notre-Dame Lachine QC H8S 2G9",
    "addr:housenumber":"2510",
    "addr:postcode":"h8s 2g9",
    "addr:street":"Rue Notre-Dame",
    "iso:country":"CA",
    "sg:address":"2510 Rue Notre-Dame",
    "sg:city":"Lachine",
    "sg:classifiers":[
        {
            "category":"Insurance",
            "subcategory":"Insurance Agent",
            "type":"Services"
        }
    ],
    "sg:phone":"+1 514 634 7115",
    "sg:postcode":"H8S 2G9",
    "sg:province":"QC",
    "wof:name":"P Morin Courtier En Assurance",
    "wof:placetype":"venue"
},
  "geometry": {"coordinates":[-73.68656900000001,45.434856],"type":"Point"}
}