{
  "type": "Feature",
  "properties": {
    "addr:full":"70 Mattice Ave Etobicoke ON M9B 1T6",
    "addr:housenumber":"70",
    "addr:postcode":"m9b 1t6",
    "addr:street":"Mattice Ave",
    "iso:country":"CA",
    "sg:address":"70 Mattice Ave",
    "sg:city":"Etobicoke",
    "sg:classifiers":[
        {
            "category":"Education",
            "subcategory":"School",
            "type":"Public Place"
        }
    ],
    "sg:phone":"+1 416 393 5253",
    "sg:postcode":"M9B 1T6",
    "sg:province":"ON",
    "wof:name":"Our Lady of Peace",
    "wof:placetype":"venue"
},
  "geometry": {"coordinates":[-79.54033699999999,43.646355],"type":"Point"}
}