{
  "type": "Feature",
  "properties": {
    "addr:full":"69 Elgin St St Thomas ON N5R 3L9",
    "addr:housenumber":"69",
    "addr:postcode":"n5r 3l9",
    "addr:street":"Elgin St",
    "iso:country":"CA",
    "sg:address":"69 Elgin St",
    "sg:city":"St Thomas",
    "sg:classifiers":[
        {
            "category":"Shopping",
            "subcategory":"Discount & Variety Stores",
            "type":"Retail Goods"
        }
    ],
    "sg:phone":"+1 519 633 1364",
    "sg:postcode":"N5R 3L9",
    "sg:province":"ON",
    "wof:name":"Wellington Convenience & Video",
    "wof:placetype":"venue"
},
  "geometry": {"coordinates":[-81.198341,42.775562],"type":"Point"}
}