{
  "type": "Feature",
  "properties": {
    "addr:full":"331 Old Weston Rd York ON M6N 3A7",
    "addr:housenumber":"331",
    "addr:postcode":"m6n 3a7",
    "addr:street":"Old Weston Rd",
    "iso:country":"CA",
    "sg:address":"331 Old Weston Rd",
    "sg:city":"York",
    "sg:classifiers":[
        {
            "category":"Organizations",
            "subcategory":"Religious Organization",
            "type":"Services"
        }
    ],
    "sg:phone":"+1 416 656 5699",
    "sg:postcode":"M6N 3A7",
    "sg:province":"ON",
    "wof:name":"Sri Guru Singh Sabha Toronto",
    "wof:placetype":"venue"
},
  "geometry": {"coordinates":[-79.46614099999999,43.680321],"type":"Point"}
}