{
  "type": "Feature",
  "properties": {
    "iso:country":"CA",
    "sg:city":"Edmonton",
    "sg:classifiers":[
        {
            "category":"Health Services",
            "subcategory":"Doctor",
            "type":"Services"
        }
    ],
    "sg:phone":"+1 780 433 4225",
    "sg:postcode":"T6G 0T2",
    "sg:province":"AB",
    "sg:tags":[
        "physician",
        "surgeon"
    ],
    "wof:name":"Lobay, Gary W MD",
    "wof:placetype":"venue"
},
  "geometry": {"coordinates":[-113.516288757,53.5182876587],"type":"Point"}
}