{
  "type": "Feature",
  "properties": {
    "addr:full":"13 Champlain St Deep River ON K0J 1P0",
    "addr:housenumber":"13",
    "addr:postcode":"k0j 1p0",
    "addr:street":"Champlain St",
    "iso:country":"CA",
    "sg:address":"13 Champlain St",
    "sg:city":"Deep River",
    "sg:classifiers":[
        {
            "category":"Restaurant",
            "type":"Food & Drink"
        }
    ],
    "sg:phone":"+1 613 584 4443",
    "sg:postcode":"K0J 1P0",
    "sg:province":"ON",
    "sg:tags":[
        "pizza"
    ],
    "wof:name":"Godfather Pizza & Subs",
    "wof:placetype":"venue"
},
  "geometry": {"coordinates":[-77.4884109497,46.1016311646],"type":"Point"}
}