{
  "type": "Feature",
  "properties": {
    "iso:country":"CA",
    "sg:address":"3615 Pasqua St",
    "sg:city":"Regina",
    "sg:classifiers":[
        {
            "category":"Sports & Exercise",
            "subcategory":"Gym",
            "type":"Entertainment"
        }
    ],
    "sg:phone":"+1 306 584 1655",
    "sg:postcode":"S4S 6W8",
    "sg:province":"SK",
    "sg:tags":[
        "club",
        "health",
        "studio",
        "gymnasium"
    ],
    "wof:name":"Regina Court & Fitness Club",
    "wof:placetype":"venue"
},
  "geometry": {"coordinates":[-104.640686,50.42112],"type":"Point"}
}