{
  "type": "Feature",
  "properties": {
    "addr:full":"8270 Boul Pie-Ix Montreal QC H1Z 3T6",
    "addr:housenumber":"8270",
    "addr:postcode":"h1z 3t6",
    "addr:street":"Boul Pie-Ix",
    "iso:country":"CA",
    "sg:address":"8270 Boul Pie-Ix",
    "sg:city":"Montreal",
    "sg:classifiers":[
        {
            "category":"Wholesale",
            "subcategory":"Apparel",
            "type":"Manufacturing & Wholesale Goods"
        }
    ],
    "sg:phone":"+1 514 722 1122",
    "sg:postcode":"H1Z 3T6",
    "sg:province":"QC",
    "sg:tags":[
        "mitten",
        "glove"
    ],
    "wof:name":"Midway Industries Ltd",
    "wof:placetype":"venue"
},
  "geometry": {"coordinates":[-73.60655975340001,45.5730361938],"type":"Point"}
}