{
  "type": "Feature",
  "properties": {
    "addr:full":"1020 Dawson Rd Thunder Bay ON P7B 5V1",
    "addr:housenumber":"1020",
    "addr:postcode":"p7b 5v1",
    "addr:street":"Dawson Rd",
    "iso:country":"CA",
    "sg:address":"1020 Dawson Rd",
    "sg:city":"Thunder Bay",
    "sg:classifiers":[
        {
            "category":"Food & Beverages",
            "subcategory":"Groceries & Convenience Stores",
            "type":"Retail Goods"
        }
    ],
    "sg:phone":"+1 807 768 1984",
    "sg:postcode":"P7B 5V1",
    "sg:province":"ON",
    "sg:tags":[
        "grocer"
    ],
    "wof:name":"Quality Market County Fair Inc",
    "wof:placetype":"venue"
},
  "geometry": {"coordinates":[-89.2527389526,48.4513053894],"type":"Point"}
}