{
  "type": "Feature",
  "properties": {
    "addr:full":"9855 63 Ave NW Edmonton AB T6E 0G7",
    "addr:housenumber":"9855",
    "addr:postcode":"t6e 0g7",
    "addr:street":"63 Ave Nw",
    "iso:country":"CA",
    "sg:address":"9855 63 Ave NW",
    "sg:city":"Edmonton",
    "sg:classifiers":[
        {
            "category":"Food & Beverages",
            "subcategory":"Liquor & Beverages",
            "type":"Retail Goods"
        }
    ],
    "sg:phone":"+1 780 431 2685",
    "sg:postcode":"T6E 0G7",
    "sg:province":"AB",
    "sg:tags":[
        "store"
    ],
    "wof:name":"Edmonton Liquor Merchants",
    "wof:placetype":"venue"
},
  "geometry": {"coordinates":[-113.484931946,53.4997024536],"type":"Point"}
}