{
  "type": "Feature",
  "properties": {
    "addr:full":"690 Rue DE Terrebonne Canton-DE-Granby QC J2H 2A1",
    "addr:housenumber":"690",
    "addr:postcode":"j2h 2a1",
    "addr:street":"Rue De Terrebonne Canton-De-Granby",
    "iso:country":"CA",
    "sg:address":"690 Rue DE Terrebonne",
    "sg:city":"Canton-DE-Granby",
    "sg:classifiers":[
        {
            "category":"Personal",
            "subcategory":"Beauty Salon",
            "type":"Services"
        }
    ],
    "sg:phone":"+1 450 375 7608",
    "sg:postcode":"J2H 2A1",
    "sg:province":"QC",
    "wof:name":"Salon DE Coiffure Chez-Nous",
    "wof:placetype":"venue"
},
  "geometry": {"coordinates":[-72.742302,45.429005],"type":"Point"}
}