{
  "type": "Feature",
  "properties": {
    "addr:full":"609 Park St Regina SK S4N 5N1",
    "addr:housenumber":"609",
    "addr:postcode":"s4n 5n1",
    "addr:street":"Park St",
    "iso:country":"CA",
    "sg:address":"609 Park St",
    "sg:city":"Regina",
    "sg:classifiers":[
        {
            "category":"Professional",
            "subcategory":"Advertising",
            "type":"Services"
        }
    ],
    "sg:phone":"+1 306 721 7676",
    "sg:postcode":"S4N 5N1",
    "sg:province":"SK",
    "sg:tags":[
        "designer",
        "display",
        "producer"
    ],
    "wof:name":"Beauchesne & CO",
    "wof:placetype":"venue"
},
  "geometry": {"coordinates":[-104.57267,50.469849],"type":"Point"}
}