{
  "type": "Feature",
  "properties": {
    "iso:country":"CA",
    "sg:city":"Bolton",
    "sg:classifiers":[
        {
            "category":"Banks & Credit Unions",
            "subcategory":"Bank",
            "type":"Services"
        }
    ],
    "sg:phone":"+1 905 857 0502",
    "sg:postcode":"L7E 2B5",
    "sg:province":"ON",
    "wof:name":"Bank of Montreal",
    "wof:placetype":"venue"
},
  "geometry": {"coordinates":[-79.727211,43.872349],"type":"Point"}
}