{
  "type": "Feature",
  "properties": {
    "addr:full":"5094 48 Ave Delta BC V4K 1V8",
    "addr:housenumber":"5094",
    "addr:postcode":"v4k 1v8",
    "addr:street":"48 Ave",
    "iso:country":"CA",
    "sg:address":"5094 48 Ave",
    "sg:city":"Delta",
    "sg:classifiers":[
        {
            "category":"Insurance",
            "subcategory":"Insurance Agent",
            "type":"Services"
        }
    ],
    "sg:phone":"+1 604 946 4499",
    "sg:postcode":"V4K 1V8",
    "sg:province":"BC",
    "wof:name":"Delta Insurance Assoc Ltd",
    "wof:placetype":"venue"
},
  "geometry": {"coordinates":[-123.08277130099999,49.0899124146],"type":"Point"}
}