{
  "type": "Feature",
  "properties": {
    "addr:full":"195 Boul D'Anjou Chateauguay QC J6J 2R3",
    "addr:housenumber":"195",
    "addr:postcode":"j6j 2r3",
    "addr:street":"Boul D'Anjou",
    "iso:country":"CA",
    "sg:address":"195 Boul D'Anjou",
    "sg:city":"Chateauguay",
    "sg:classifiers":[
        {
            "category":"Restaurant",
            "type":"Food & Drink"
        }
    ],
    "sg:phone":"+1 450 691 8255",
    "sg:postcode":"J6J 2R3",
    "sg:province":"QC",
    "wof:name":"Restaurant Canada Drive-In",
    "wof:placetype":"venue"
},
  "geometry": {"coordinates":[-73.74011230470001,45.3614845276],"type":"Point"}
}