{
  "type": "Feature",
  "properties": {
    "iso:country":"CA",
    "sg:address":"2525 Howard Ave",
    "sg:city":"Windsor",
    "sg:classifiers":[
        {
            "category":"Home & Garden",
            "subcategory":"Furniture",
            "type":"Retail Goods"
        }
    ],
    "sg:phone":"+1 519 966 8898",
    "sg:postcode":"N8X 3W1",
    "sg:province":"ON",
    "sg:tags":[
        "bedding"
    ],
    "wof:name":"Bedroom Depot",
    "wof:placetype":"venue"
},
  "geometry": {"coordinates":[-83.01280975340001,42.2899932861],"type":"Point"}
}