{
  "type": "Feature",
  "properties": {
    "iso:country":"CA",
    "sg:address":"127 Christina St S",
    "sg:city":"Sarnia",
    "sg:classifiers":[
        {
            "category":"Museum",
            "type":"Entertainment"
        }
    ],
    "sg:phone":"+1 519 344 2787",
    "sg:postcode":"N7T 2M8",
    "sg:province":"ON",
    "sg:tags":[
        "organization",
        "arts",
        "information"
    ],
    "wof:name":"Sarnia Lambton Arts Council",
    "wof:placetype":"venue"
},
  "geometry": {"coordinates":[-82.408257,42.970055],"type":"Point"}
}