{
  "type": "Feature",
  "properties": {
    "iso:country":"CA",
    "sg:address":"26 7th Ave SE",
    "sg:city":"Dauphin",
    "sg:classifiers":[
        {
            "category":"Retail",
            "subcategory":"Repair Shop",
            "type":"Services"
        }
    ],
    "sg:phone":"+1 204 638 3343",
    "sg:postcode":"R7N 2E1",
    "sg:province":"MB",
    "sg:tags":[
        "upholsterer"
    ],
    "wof:name":"Beaulieu's Upholstering",
    "wof:placetype":"venue"
},
  "geometry": {"coordinates":[-100.05559539799999,51.1441307068],"type":"Point"}
}