{
  "type": "Feature",
  "properties": {
    "addr:full":"66 Rue Rene Sainte-Anne-Des-Plaines QC J0N 1H0",
    "addr:housenumber":"66",
    "addr:postcode":"j0n 1h0",
    "addr:street":"Rue Rene",
    "iso:country":"CA",
    "sg:address":"66 Rue Rene",
    "sg:city":"Sainte-Anne-Des-Plaines",
    "sg:classifiers":[
        {
            "category":"Organizations",
            "subcategory":"Religious Organization",
            "type":"Services"
        }
    ],
    "sg:phone":"+1 514 478 3162",
    "sg:postcode":"J0N 1H0",
    "sg:province":"QC",
    "sg:tags":[
        "church"
    ],
    "wof:name":"Eglise Evangelique",
    "wof:placetype":"venue"
},
  "geometry": {"coordinates":[-73.825417,45.76767],"type":"Point"}
}