{
  "type": "Feature",
  "properties": {
    "iso:country":"CA",
    "sg:address":"315 Rue DE LA Commune O",
    "sg:city":"Montreal",
    "sg:classifiers":[
        {
            "category":"Wholesale",
            "subcategory":"Machinery & Supplies",
            "type":"Manufacturing & Wholesale Goods"
        }
    ],
    "sg:phone":"+1 514 284 9193",
    "sg:postcode":"H2Y 2E1",
    "sg:province":"QC",
    "sg:tags":[
        "ship",
        "broker"
    ],
    "wof:name":"Flagship Trading & Shipping",
    "wof:placetype":"venue"
},
  "geometry": {"coordinates":[-73.551643,45.508469],"type":"Point"}
}