{
  "type": "Feature",
  "properties": {
    "addr:full":"111 Grant St Woodstock NB E7M 3Y5",
    "addr:housenumber":"111",
    "addr:postcode":"e7m 3y5",
    "addr:street":"Grant St",
    "iso:country":"CA",
    "sg:address":"111 Grant St",
    "sg:city":"Woodstock",
    "sg:classifiers":[
        {
            "category":"Professional",
            "subcategory":"Engineering",
            "type":"Services"
        }
    ],
    "sg:phone":"+1 506 328 3563",
    "sg:postcode":"E7M 3Y5",
    "sg:province":"NB",
    "sg:tags":[
        "surveyor"
    ],
    "wof:name":"Dale M Mac Farlane Land Srvyng",
    "wof:placetype":"venue"
},
  "geometry": {"coordinates":[-67.597725,46.151951],"type":"Point"}
}