{
  "type": "Feature",
  "properties": {
    "addr:full":"354 Rue Saint-Laurent Cap-DE-LA-Madeleine QC G8T 6H2",
    "addr:housenumber":"354",
    "addr:postcode":"g8t 6h2",
    "addr:street":"Rue Saint-Laurent",
    "iso:country":"CA",
    "sg:address":"354 Rue Saint-Laurent",
    "sg:city":"Cap-DE-LA-Madeleine",
    "sg:classifiers":[
        {
            "category":"Recreation",
            "type":"Entertainment"
        }
    ],
    "sg:phone":"+1 819 375 8424",
    "sg:postcode":"G8T 6H2",
    "sg:province":"QC",
    "sg:tags":[
        "gymnastic",
        "club",
        "instruction",
        "gymnasium",
        "health",
        "studio"
    ],
    "wof:name":"Des Chaines Gym Enr",
    "wof:placetype":"venue"
},
  "geometry": {"coordinates":[-72.52610799999999,46.372093],"type":"Point"}
}