{
  "type": "Feature",
  "properties": {
    "addr:full":"2372 Boul Saint-Martin E Laval QC H7E 5A4",
    "addr:housenumber":"2372",
    "addr:postcode":"h7e 5a4",
    "addr:street":"Boul Saint-Martin E",
    "iso:country":"CA",
    "sg:address":"2372 Boul Saint-Martin E",
    "sg:city":"Laval",
    "sg:classifiers":[
        {
            "category":"Real Estate",
            "subcategory":"Architect",
            "type":"Services"
        }
    ],
    "sg:phone":"+1 450 629 9992",
    "sg:postcode":"H7E 5A4",
    "sg:province":"QC",
    "wof:name":"Tremblay L'Ecuyer Architectes",
    "wof:placetype":"venue"
},
  "geometry": {"coordinates":[-73.685051,45.59811],"type":"Point"}
}