{
  "type": "Feature",
  "properties": {
    "addr:full":"Wikwemikong ON P0P 2J0",
    "addr:postcode":"p0p 2j0",
    "iso:country":"CA",
    "sg:city":"Wikwemikong",
    "sg:classifiers":[
        {
            "category":"Communications",
            "subcategory":"Film & Video Production",
            "type":"Services"
        }
    ],
    "sg:phone":"+1 705 859 3200",
    "sg:postcode":"P0P 2J0",
    "sg:province":"ON",
    "sg:tags":[
        "duplication",
        "tape"
    ],
    "wof:name":"Wiky Tv 5",
    "wof:placetype":"venue"
},
  "geometry": {"coordinates":[-81.72071800000001,45.803185],"type":"Point"}
}