{
  "type": "Feature",
  "properties": {
    "addr:full":"19985 68 Ave Langley BC V2Y 2W5",
    "addr:housenumber":"19985",
    "addr:postcode":"v2y 2w5",
    "addr:street":"68 Ave",
    "iso:country":"CA",
    "sg:address":"19985 68 Ave",
    "sg:city":"Langley",
    "sg:classifiers":[
        {
            "category":"Professional",
            "subcategory":"Credit Reporting & Collection",
            "type":"Services"
        }
    ],
    "sg:phone":"+1 604 530 0211",
    "sg:postcode":"V2Y 2W5",
    "sg:province":"BC",
    "sg:tags":[
        "agency"
    ],
    "wof:name":"Wiggins Adjustments Ltd",
    "wof:placetype":"venue"
},
  "geometry": {"coordinates":[-122.6692276,49.1263504028],"type":"Point"}
}