{
  "type": "Feature",
  "properties": {
    "addr:full":"551 4th St E Spiritwood SK S0J 2M0",
    "addr:housenumber":"551",
    "addr:postcode":"s0j 2m0",
    "addr:street":"4Th St E Spiritwood",
    "iso:country":"CA",
    "sg:address":"551 4th St E",
    "sg:city":"Spiritwood",
    "sg:classifiers":[
        {
            "category":"Manufacturing",
            "subcategory":"Tools & Machinery",
            "type":"Manufacturing & Wholesale Goods"
        }
    ],
    "sg:phone":"+1 306 883 2315",
    "sg:postcode":"S0J 2M0",
    "sg:province":"SK",
    "sg:tags":[
        "machine",
        "shop"
    ],
    "wof:name":"Lavoie's Machining & Welding",
    "wof:placetype":"venue"
},
  "geometry": {"coordinates":[-107.512619,53.365131],"type":"Point"}
}