{
  "type": "Feature",
  "properties": {
    "iso:country":"CA",
    "sg:city":"Forestville",
    "sg:classifiers":[
        {
            "category":"Shopping",
            "subcategory":"Florist",
            "type":"Retail Goods"
        }
    ],
    "sg:phone":"+1 418 587 2180",
    "sg:postcode":"G0T 1E0",
    "sg:province":"QC",
    "wof:name":"Maryse Fleuriste",
    "wof:placetype":"venue"
},
  "geometry": {"coordinates":[-69.086769,48.742172],"type":"Point"}
}