{
  "type": "Feature",
  "properties": {
    "addr:full":"Calgary AB T2H 0K8",
    "addr:postcode":"t2h 0k8",
    "iso:country":"CA",
    "sg:city":"Calgary",
    "sg:classifiers":[
        {
            "category":"Shopping",
            "subcategory":"Music",
            "type":"Retail Goods"
        }
    ],
    "sg:phone":"+1 403 319 0919",
    "sg:postcode":"T2H 0K8",
    "sg:province":"AB",
    "sg:tags":[
        "compact",
        "record",
        "disc",
        "tape"
    ],
    "wof:name":"Hmv Canada",
    "wof:placetype":"venue"
},
  "geometry": {"coordinates":[-114.071830749,50.9961624146],"type":"Point"}
}