{
  "type": "Feature",
  "properties": {
    "iso:country":"CA",
    "sg:address":"8960 Pemberton Meadows Rd",
    "sg:city":"Pemberton",
    "sg:classifiers":[
        {
            "category":"Real Estate",
            "subcategory":"Architect",
            "type":"Services"
        }
    ],
    "sg:phone":"+1 604 894 5887",
    "sg:postcode":"V0N 2L0",
    "sg:province":"BC",
    "wof:name":"Collins, Ernest",
    "wof:placetype":"venue"
},
  "geometry": {"coordinates":[-122.811180115,50.3264770508],"type":"Point"}
}