{
  "type": "Feature",
  "properties": {
    "addr:full":"1719 Bank St #304 Ottawa ON K1V 7Z4",
    "addr:housenumber":"1719",
    "addr:postcode":"k1v 7z4",
    "addr:street":"Bank St # 304",
    "iso:country":"CA",
    "sg:address":"1719 Bank St #304",
    "sg:city":"Ottawa",
    "sg:classifiers":[
        {
            "category":"Health Services",
            "subcategory":"Doctor",
            "type":"Services"
        }
    ],
    "sg:phone":"+1 613 731 4754",
    "sg:postcode":"K1V 7Z4",
    "sg:province":"ON",
    "sg:tags":[
        "dentist"
    ],
    "wof:name":"Ted Henike & Assoc",
    "wof:placetype":"venue"
},
  "geometry": {"coordinates":[-75.66525268549999,45.3745880127],"type":"Point"}
}