{
  "type": "Feature",
  "properties": {
    "iso:country":"CA",
    "sg:address":"695 Cranbrook Rd",
    "sg:city":"London",
    "sg:classifiers":[
        {
            "category":"Health Services",
            "subcategory":"Doctor",
            "type":"Services"
        }
    ],
    "sg:phone":"+1 519 472 2060",
    "sg:postcode":"N6K 1W8",
    "sg:province":"ON",
    "sg:tags":[
        "physician",
        "surgeon"
    ],
    "wof:name":"Butchey, Maurice MD",
    "wof:placetype":"venue"
},
  "geometry": {"coordinates":[-81.303108,42.943764],"type":"Point"}
}