{
  "type": "Feature",
  "properties": {
    "addr:full":"Leduc AB T9E 6Z5",
    "addr:postcode":"t9e 6z5",
    "iso:country":"CA",
    "sg:city":"Leduc",
    "sg:classifiers":[
        {
            "category":"Health Services",
            "subcategory":"Optometrist",
            "type":"Services"
        }
    ],
    "sg:phone":"+1 780 986 8441",
    "sg:postcode":"T9E 6Z5",
    "sg:province":"AB",
    "wof:name":"Vision Care Plus",
    "wof:placetype":"venue"
},
  "geometry": {"coordinates":[-113.55233800000001,53.26659],"type":"Point"}
}