{
  "type": "Feature",
  "properties": {
    "addr:full":"1511 Bedford Hwy Bedford NS B4A 1E3",
    "addr:housenumber":"1511",
    "addr:postcode":"b4a 1e3",
    "addr:street":"Bedford Hwy",
    "iso:country":"CA",
    "sg:address":"1511 Bedford Hwy",
    "sg:city":"Bedford",
    "sg:classifiers":[
        {
            "category":"Restaurant",
            "type":"Food & Drink"
        }
    ],
    "sg:phone":"+1 902 832 1050",
    "sg:postcode":"B4A 1E3",
    "sg:province":"NS",
    "wof:name":"Wendy's",
    "wof:placetype":"venue"
},
  "geometry": {"coordinates":[-63.6605,44.730949],"type":"Point"}
}