{
  "type": "Feature",
  "properties": {
    "iso:country":"CA",
    "sg:address":"4888 Rue Jarry E # 101",
    "sg:city":"Saint-Leonard",
    "sg:classifiers":[
        {
            "category":"Real Estate",
            "subcategory":"Real Estate Agent",
            "type":"Services"
        }
    ],
    "sg:phone":"+1 514 327 0021",
    "sg:postcode":"H1R 1X9",
    "sg:province":"QC",
    "wof:name":"Services Immobiliers LA Natl",
    "wof:placetype":"venue"
},
  "geometry": {"coordinates":[-73.595604,45.579227],"type":"Point"}
}