{
  "type": "Feature",
  "properties": {
    "addr:full":"4888 Rue Jarry E # 101 Saint-Leonard QC H1R 1X9",
    "addr:housenumber":"4888",
    "addr:postcode":"h1r 1x9",
    "addr:street":"Rue Jarry E # 101",
    "iso:country":"CA",
    "sg:address":"4888 Rue Jarry E # 101",
    "sg:city":"Saint-Leonard",
    "sg:classifiers":[
        {
            "category":"Real Estate",
            "subcategory":"Real Estate Agent",
            "type":"Services"
        }
    ],
    "sg:phone":"+1 514 327 0021",
    "sg:postcode":"H1R 1X9",
    "sg:province":"QC",
    "wof:name":"Services Immobiliers LA Natl",
    "wof:placetype":"venue"
},
  "geometry": {"coordinates":[-73.59560399999999,45.579227],"type":"Point"}
}