{
  "type": "Feature",
  "properties": {
    "addr:full":"3613 117 Ave NW Edmonton AB T5W 0X9",
    "addr:housenumber":"3613",
    "addr:postcode":"t5w 0x9",
    "addr:street":"117 Ave Nw",
    "iso:country":"CA",
    "sg:address":"3613 117 Ave NW",
    "sg:city":"Edmonton",
    "sg:classifiers":[
        {
            "category":"Building & Trades",
            "subcategory":"Construction",
            "type":"Services"
        }
    ],
    "sg:phone":"+1 780 471 3107",
    "sg:postcode":"T5W 0X9",
    "sg:province":"AB",
    "sg:tags":[
        "excavating",
        "contractor"
    ],
    "wof:name":"Tony's Bobcat Svc",
    "wof:placetype":"venue"
},
  "geometry": {"coordinates":[-113.397087,53.569344],"type":"Point"}
}