{
  "type": "Feature",
  "properties": {
    "addr:full":"8032 34 Ave NW Calgary AB T3B 1P7",
    "addr:housenumber":"8032",
    "addr:postcode":"t3b 1p7",
    "addr:street":"34 Ave Nw",
    "iso:country":"CA",
    "sg:address":"8032 34 Ave NW",
    "sg:city":"Calgary",
    "sg:classifiers":[
        {
            "category":"Utilities",
            "type":"Services"
        }
    ],
    "sg:phone":"+1 403 288 1196",
    "sg:postcode":"T3B 1P7",
    "sg:province":"AB",
    "sg:tags":[
        "locating"
    ],
    "wof:name":"Tracker Pipeline & Utility",
    "wof:placetype":"venue"
},
  "geometry": {"coordinates":[-114.20317799999999,51.086796],"type":"Point"}
}