{
  "type": "Feature",
  "properties": {
    "iso:country":"CA",
    "sg:address":"129 Campbell St",
    "sg:city":"Sarnia",
    "sg:classifiers":[
        {
            "category":"Restaurant",
            "type":"Food & Drink"
        }
    ],
    "sg:phone":"+1 519 344 2777",
    "sg:postcode":"N7T 2G6",
    "sg:province":"ON",
    "wof:name":"Lee's Snack House",
    "wof:placetype":"venue"
},
  "geometry": {"coordinates":[-82.4032821655,42.9590606689],"type":"Point"}
}