{
  "type": "Feature",
  "properties": {
    "addr:full":"1400 United Blvd Coquitlam BC V3K 6Y2",
    "addr:housenumber":"1400",
    "addr:postcode":"v3k 6y2",
    "addr:street":"United Blvd",
    "iso:country":"CA",
    "sg:address":"1400 United Blvd",
    "sg:city":"Coquitlam",
    "sg:classifiers":[
        {
            "category":"Home & Garden",
            "subcategory":"Furniture",
            "type":"Retail Goods"
        }
    ],
    "sg:phone":"+1 604 524 3444",
    "sg:postcode":"V3K 6Y2",
    "sg:province":"BC",
    "wof:name":"Scan Designs Ltd",
    "wof:placetype":"venue"
},
  "geometry": {"coordinates":[-122.849884,49.228893],"type":"Point"}
}