{
  "type": "Feature",
  "properties": {
    "iso:country":"CA",
    "sg:address":"167 Centre St E",
    "sg:city":"Richmond Hill",
    "sg:classifiers":[
        {
            "category":"Retail",
            "subcategory":"Auto Repair",
            "type":"Services"
        }
    ],
    "sg:phone":"+1 905 883 0223",
    "sg:postcode":"L4C 1A5",
    "sg:province":"ON",
    "sg:tags":[
        "automobile",
        "rustproofing",
        "undercoating"
    ],
    "wof:name":"Krown Rust Control Ctr",
    "wof:placetype":"venue"
},
  "geometry": {"coordinates":[-79.42980194090001,43.8779067993],"type":"Point"}
}