{
  "type": "Feature",
  "properties": {
    "iso:country":"CA",
    "sg:address":"8 Rue Grove",
    "sg:city":"Granby",
    "sg:classifiers":[
        {
            "category":"Personal",
            "type":"Services"
        }
    ],
    "sg:phone":"+1 450 378 2044",
    "sg:postcode":"J2G 4M4",
    "sg:province":"QC",
    "sg:tags":[
        "electrolysis"
    ],
    "wof:name":"Esthetique Studio S Godbout",
    "wof:placetype":"venue"
},
  "geometry": {"coordinates":[-72.71342468260001,45.3989181519],"type":"Point"}
}