{
  "type": "Feature",
  "properties": {
    "addr:full":"201 Washington St Davidson SK S0G 1A0",
    "addr:housenumber":"201",
    "addr:postcode":"s0g 1a0",
    "addr:street":"Washington St",
    "iso:country":"CA",
    "sg:address":"201 Washington St",
    "sg:city":"Davidson",
    "sg:classifiers":[
        {
            "category":"Education",
            "subcategory":"School",
            "type":"Public Place"
        }
    ],
    "sg:phone":"+1 306 567 2885",
    "sg:postcode":"S0G 1A0",
    "sg:province":"SK",
    "wof:name":"Carlton Trail Regional College",
    "wof:placetype":"venue"
},
  "geometry": {"coordinates":[-105.995987,51.267365],"type":"Point"}
}