{
  "type": "Feature",
  "properties": {
    "addr:full":"1488 Cliveden Ave Delta BC V3M 6L9",
    "addr:housenumber":"1488",
    "addr:postcode":"v3m 6l9",
    "addr:street":"Cliveden Ave",
    "iso:country":"CA",
    "sg:address":"1488 Cliveden Ave",
    "sg:city":"Delta",
    "sg:classifiers":[
        {
            "category":"Wholesale",
            "subcategory":"Computers",
            "type":"Manufacturing & Wholesale Goods"
        }
    ],
    "sg:phone":"+1 604 523 6321",
    "sg:postcode":"V3M 6L9",
    "sg:province":"BC",
    "wof:name":"Daytek Electronics Corp",
    "wof:placetype":"venue"
},
  "geometry": {"coordinates":[-122.963783264,49.1665802002],"type":"Point"}
}