{
  "type": "Feature",
  "properties": {
    "addr:full":"15 Hillside Ave Lower Sackville NS B4C 1W6",
    "addr:housenumber":"15",
    "addr:postcode":"b4c 1w6",
    "addr:street":"Hillside Ave",
    "iso:country":"CA",
    "sg:address":"15 Hillside Ave",
    "sg:city":"Lower Sackville",
    "sg:classifiers":[
        {
            "category":"Education",
            "subcategory":"School",
            "type":"Public Place"
        }
    ],
    "sg:phone":"+1 902 864 6873",
    "sg:postcode":"B4C 1W6",
    "sg:province":"NS",
    "wof:name":"Hillside Park Elementary Schl",
    "wof:placetype":"venue"
},
  "geometry": {"coordinates":[-63.6631698608,44.7573318481],"type":"Point"}
}