{
  "type": "Feature",
  "properties": {
    "addr:full":"4325 Steeles Ave W North York ON M3N 1V7",
    "addr:housenumber":"4325",
    "addr:postcode":"m3n 1v7",
    "addr:street":"Steeles Ave W",
    "iso:country":"CA",
    "sg:address":"4325 Steeles Ave W",
    "sg:city":"North York",
    "sg:classifiers":[
        {
            "category":"Building & Trades",
            "subcategory":"Cleaning & Sanitation",
            "type":"Services"
        }
    ],
    "sg:phone":"+1 416 708 9220",
    "sg:postcode":"M3N 1V7",
    "sg:province":"ON",
    "wof:name":"Castor Enterprise",
    "wof:placetype":"venue"
},
  "geometry": {"coordinates":[-79.53047943120001,43.7734565735],"type":"Point"}
}