{
  "type": "Feature",
  "properties": {
    "addr:full":"526 5 Ave Wainwright AB T9W 1B1",
    "addr:housenumber":"526",
    "addr:postcode":"t9w 1b1",
    "addr:street":"5 Ave",
    "iso:country":"CA",
    "sg:address":"526 5 Ave",
    "sg:city":"Wainwright",
    "sg:classifiers":[
        {
            "category":"Organizations",
            "subcategory":"Religious Organization",
            "type":"Services"
        }
    ],
    "sg:phone":"+1 780 842 4070",
    "sg:postcode":"T9W 1B1",
    "sg:province":"AB",
    "sg:tags":[
        "church"
    ],
    "wof:name":"Lutheran Church",
    "wof:placetype":"venue"
},
  "geometry": {"coordinates":[-110.867699,52.840015],"type":"Point"}
}