{
  "type": "Feature",
  "properties": {
    "addr:full":"1360 Kelly St Bridesville BC V0H 1B0",
    "addr:housenumber":"1360",
    "addr:postcode":"v0h 1b0",
    "addr:street":"Kelly St",
    "iso:country":"CA",
    "sg:address":"1360 Kelly St",
    "sg:city":"Bridesville",
    "sg:classifiers":[
        {
            "category":"Shopping",
            "type":"Retail Goods"
        }
    ],
    "sg:phone":"+1 604 451 7415",
    "sg:postcode":"V0H 1B0",
    "sg:province":"BC",
    "sg:tags":[
        "cosmetic",
        "perfume"
    ],
    "wof:name":"Aloette Cosmetics Vancouver",
    "wof:placetype":"venue"
},
  "geometry": {"coordinates":[-119.149353,49.037136],"type":"Point"}
}