{
  "type": "Feature",
  "properties": {
    "addr:full":"13 Wentworth Cres St Albert AB T8N 3G7",
    "addr:housenumber":"13",
    "addr:postcode":"t8n 3g7",
    "addr:street":"Wentworth Cres",
    "iso:country":"CA",
    "sg:address":"13 Wentworth Cres",
    "sg:city":"St Albert",
    "sg:classifiers":[
        {
            "category":"Building & Trades",
            "subcategory":"Construction",
            "type":"Services"
        }
    ],
    "sg:phone":"+1 780 459 5754",
    "sg:postcode":"T8N 3G7",
    "sg:province":"AB",
    "sg:tags":[
        "telecommunication",
        "supply",
        "cabling",
        "wiring",
        "telephone",
        "equipment"
    ],
    "wof:name":"Telephone Installation Svc",
    "wof:placetype":"venue"
},
  "geometry": {"coordinates":[-113.598991,53.64555],"type":"Point"}
}