{
  "type": "Feature",
  "properties": {
    "addr:full":"Hwy 59 Scanterbury MB R0E 1W0",
    "addr:postcode":"r0e 1w0",
    "addr:street":"Hwy 59 Scanterbury",
    "iso:country":"CA",
    "sg:address":"Hwy 59",
    "sg:city":"Scanterbury",
    "sg:classifiers":[
        {
            "category":"Organizations",
            "subcategory":"Community Association",
            "type":"Services"
        }
    ],
    "sg:phone":"+1 204 766 2494",
    "sg:postcode":"R0E 1W0",
    "sg:province":"MB",
    "sg:tags":[
        "native"
    ],
    "wof:name":"Brokenhead Ojibway Nation",
    "wof:placetype":"venue"
},
  "geometry": {"coordinates":[-96.629845,50.376045],"type":"Point"}
}