{
  "type": "Feature",
  "properties": {
    "addr:full":"11220 153 St NW Edmonton AB T5M 1X6",
    "addr:housenumber":"11220",
    "addr:postcode":"t5m 1x6",
    "addr:street":"153 St Nw",
    "iso:country":"CA",
    "sg:address":"11220 153 St NW",
    "sg:city":"Edmonton",
    "sg:classifiers":[
        {
            "category":"Building & Trades",
            "subcategory":"Construction",
            "type":"Services"
        }
    ],
    "sg:phone":"+1 780 452 7611",
    "sg:postcode":"T5M 1X6",
    "sg:province":"AB",
    "sg:tags":[
        "paving",
        "contractor"
    ],
    "wof:name":"Sandstar Corp",
    "wof:placetype":"venue"
},
  "geometry": {"coordinates":[-113.584411621,53.5612106323],"type":"Point"}
}