{
  "type": "Feature",
  "properties": {
    "addr:full":"45999 Harriston Rd 87 Gorrie ON N0G 1X0",
    "addr:housenumber":"87",
    "addr:postcode":"45999;n0g 1x0",
    "addr:street":"Harriston Rd",
    "iso:country":"CA",
    "sg:address":"45999 Harriston Rd 87",
    "sg:city":"Gorrie",
    "sg:classifiers":[
        {
            "category":"Building & Trades",
            "subcategory":"Construction",
            "type":"Services"
        }
    ],
    "sg:phone":"+1 519 335 3189",
    "sg:postcode":"N0G 1X0",
    "sg:province":"ON",
    "sg:tags":[
        "contractor"
    ],
    "wof:name":"Queen's Bush Construction",
    "wof:placetype":"venue"
},
  "geometry": {"coordinates":[-81.1036224365,43.8766403198],"type":"Point"}
}