{
  "type": "Feature",
  "properties": {
    "addr:full":"14 Southwick St St Thomas ON N5R 3R6",
    "addr:housenumber":"14",
    "addr:postcode":"n5r 3r6",
    "addr:street":"Southwick St",
    "iso:country":"CA",
    "sg:address":"14 Southwick St",
    "sg:city":"St Thomas",
    "sg:classifiers":[
        {
            "category":"Professional",
            "subcategory":"Lawyer & Legal Services",
            "type":"Services"
        }
    ],
    "sg:phone":"+1 519 633 0800",
    "sg:postcode":"N5R 3R6",
    "sg:province":"ON",
    "sg:tags":[
        "attorney"
    ],
    "wof:name":"Cline, Robert F",
    "wof:placetype":"venue"
},
  "geometry": {"coordinates":[-81.195435,42.777893],"type":"Point"}
}