{
  "type": "Feature",
  "properties": {
    "addr:full":"1939 Queen St E Toronto ON M4L 1H7",
    "addr:housenumber":"1939",
    "addr:postcode":"m4l 1h7",
    "addr:street":"Queen St E",
    "iso:country":"CA",
    "sg:address":"1939 Queen St E",
    "sg:city":"Toronto",
    "sg:classifiers":[
        {
            "category":"Home & Garden",
            "subcategory":"Home Furnishings",
            "type":"Retail Goods"
        }
    ],
    "sg:phone":"+1 416 690 2808",
    "sg:postcode":"M4L 1H7",
    "sg:province":"ON",
    "sg:tags":[
        "linen"
    ],
    "wof:name":"Beddington's Bed & Bath",
    "wof:placetype":"venue"
},
  "geometry": {"coordinates":[-79.303268,43.669201],"type":"Point"}
}