{
  "type": "Feature",
  "properties": {
    "addr:full":"235 Ardelt Ave Kitchener ON N2C 2M3",
    "addr:housenumber":"235",
    "addr:postcode":"n2c 2m3",
    "addr:street":"Ardelt Ave",
    "iso:country":"CA",
    "sg:address":"235 Ardelt Ave",
    "sg:city":"Kitchener",
    "sg:classifiers":[
        {
            "category":"Professional",
            "type":"Services"
        }
    ],
    "sg:phone":"+1 519 745 6888",
    "sg:postcode":"N2C 2M3",
    "sg:province":"ON",
    "sg:tags":[
        "food",
        "establishment",
        "broker"
    ],
    "wof:name":"Bruce Edmeades Sales Ltd",
    "wof:placetype":"venue"
},
  "geometry": {"coordinates":[-80.47421264650001,43.4240570068],"type":"Point"}
}