{
  "type": "Feature",
  "properties": {
    "addr:full":"Church Point NS B0W 1M0",
    "addr:postcode":"b0w 1m0",
    "iso:country":"CA",
    "sg:city":"Church Point",
    "sg:classifiers":[
        {
            "category":"Personal",
            "subcategory":"Beauty Salon",
            "type":"Services"
        }
    ],
    "sg:phone":"+1 902 837 7733",
    "sg:postcode":"B0W 1M0",
    "sg:province":"NS",
    "wof:name":"Styles in Motion",
    "wof:placetype":"venue"
},
  "geometry": {"coordinates":[-66.11591300000001,44.336178],"type":"Point"}
}