{
  "type": "Feature",
  "properties": {
    "addr:full":"Marquette Lake Shining Tree ON P0M 2X0",
    "addr:postcode":"p0m 2x0",
    "addr:street":"Marquette",
    "iso:country":"CA",
    "sg:address":"Marquette Lake",
    "sg:city":"Shining Tree",
    "sg:classifiers":[
        {
            "category":"Professional",
            "type":"Services"
        }
    ],
    "sg:phone":"+1 705 263 2002",
    "sg:postcode":"P0M 2X0",
    "sg:province":"ON",
    "sg:tags":[
        "aircraft",
        "management",
        "establishment"
    ],
    "wof:name":"Lauzon Aviation",
    "wof:placetype":"venue"
},
  "geometry": {"coordinates":[-81.301559,47.52549],"type":"Point"}
}