{
  "type": "Feature",
  "properties": {
    "iso:country":"CA",
    "sg:address":"42 Drinkwater Rd",
    "sg:city":"Brampton",
    "sg:classifiers":[
        {
            "category":"Building & Trades",
            "subcategory":"Plumbing",
            "type":"Services"
        }
    ],
    "sg:phone":"+1 416 782 3775",
    "sg:postcode":"L6Y 4T9",
    "sg:province":"ON",
    "sg:tags":[
        "heating",
        "contractor"
    ],
    "wof:name":"Heatizon Heating & Air Cond",
    "wof:placetype":"venue"
},
  "geometry": {"coordinates":[-79.76555633540001,43.6597328186],"type":"Point"}
}