{
  "type": "Feature",
  "properties": {
    "addr:full":"325 Killam Dr Moncton NB E1C 3T1",
    "addr:housenumber":"325",
    "addr:postcode":"e1c 3t1",
    "addr:street":"Killam Dr",
    "iso:country":"CA",
    "sg:address":"325 Killam Dr",
    "sg:city":"Moncton",
    "sg:classifiers":[
        {
            "category":"Food & Beverages",
            "subcategory":"Groceries & Convenience Stores",
            "type":"Retail Goods"
        }
    ],
    "sg:phone":"+1 506 383 4402",
    "sg:postcode":"E1C 3T1",
    "sg:province":"NB",
    "wof:name":"Ayer Convenience Ltd",
    "wof:placetype":"venue"
},
  "geometry": {"coordinates":[-64.8286514282,46.0945167542],"type":"Point"}
}