{
  "type": "Feature",
  "properties": {
    "addr:full":"St Albert AB T8N 5C3",
    "addr:postcode":"t8n 5c3",
    "iso:country":"CA",
    "sg:city":"St Albert",
    "sg:classifiers":[
        {
            "category":"Wholesale",
            "subcategory":"Machinery & Supplies",
            "type":"Manufacturing & Wholesale Goods"
        }
    ],
    "sg:phone":"+1 780 459 5599",
    "sg:postcode":"T8N 5C3",
    "sg:province":"AB",
    "sg:tags":[
        "glass",
        "tank",
        "septic",
        "plastic"
    ],
    "wof:name":"Focus Industries",
    "wof:placetype":"venue"
},
  "geometry": {"coordinates":[-113.64340199999999,53.622738],"type":"Point"}
}