{
  "type": "Feature",
  "properties": {
    "addr:full":"2489 Beacon Ave Sidney BC V8L 1X9",
    "addr:housenumber":"2489",
    "addr:postcode":"v8l 1x9",
    "addr:street":"Beacon Ave",
    "iso:country":"CA",
    "sg:address":"2489 Beacon Ave",
    "sg:city":"Sidney",
    "sg:classifiers":[
        {
            "category":"Insurance",
            "subcategory":"Insurance Agent",
            "type":"Services"
        }
    ],
    "sg:phone":"+1 250 656 5511",
    "sg:postcode":"V8L 1X9",
    "sg:province":"BC",
    "wof:name":"Sparling Real Estate Ltd",
    "wof:placetype":"venue"
},
  "geometry": {"coordinates":[-123.39702606199999,48.6487846375],"type":"Point"}
}