{
  "type": "Feature",
  "properties": {
    "addr:full":"137 Ontario St Stratford ON N5A 3H1",
    "addr:housenumber":"137",
    "addr:postcode":"n5a 3h1",
    "addr:street":"Ontario St",
    "iso:country":"CA",
    "sg:address":"137 Ontario St",
    "sg:city":"Stratford",
    "sg:classifiers":[
        {
            "category":"Shopping",
            "subcategory":"Clothing, Apparel, & Fashions",
            "type":"Retail Goods"
        }
    ],
    "sg:phone":"+1 519 273 4030",
    "sg:postcode":"N5A 3H1",
    "sg:province":"ON",
    "wof:name":"Touchmark Shop",
    "wof:placetype":"venue"
},
  "geometry": {"coordinates":[-80.9805603027,43.371257782],"type":"Point"}
}