{
  "type": "Feature",
  "properties": {
    "addr:full":"Saint-Augustin-DE-Desmaures QC G3A 2L4",
    "addr:postcode":"g3a 2l4",
    "iso:country":"CA",
    "sg:city":"Saint-Augustin-DE-Desmaures",
    "sg:classifiers":[
        {
            "category":"Retail",
            "subcategory":"Auto Repair",
            "type":"Services"
        }
    ],
    "sg:phone":"+1 418 877 8400",
    "sg:postcode":"G3A 2L4",
    "sg:province":"QC",
    "sg:tags":[
        "repairing",
        "automobile"
    ],
    "wof:name":"Centre DE L'Auto R Bety Inc",
    "wof:placetype":"venue"
},
  "geometry": {"coordinates":[-71.38472,46.749168],"type":"Point"}
}