{
  "type": "Feature",
  "properties": {
    "addr:full":"109 King St E Gananoque ON K7G 1G3",
    "addr:housenumber":"109",
    "addr:postcode":"k7g 1g3",
    "addr:street":"King St E",
    "iso:country":"CA",
    "sg:address":"109 King St E",
    "sg:city":"Gananoque",
    "sg:classifiers":[
        {
            "category":"Shopping",
            "subcategory":"Jewelry",
            "type":"Retail Goods"
        }
    ],
    "sg:phone":"+1 613 382 3202",
    "sg:postcode":"K7G 1G3",
    "sg:province":"ON",
    "sg:tags":[
        "jeweler"
    ],
    "wof:name":"Woodley's Jewellers",
    "wof:placetype":"venue"
},
  "geometry": {"coordinates":[-76.16207900000001,44.329697],"type":"Point"}
}