{
  "type": "Feature",
  "properties": {
    "addr:full":"202 Rue Carlyle E Chateauguay QC J6J 6A9",
    "addr:housenumber":"202",
    "addr:postcode":"j6j 6a9",
    "addr:street":"Rue Carlyle E Chateauguay",
    "iso:country":"CA",
    "sg:address":"202 Rue Carlyle E",
    "sg:city":"Chateauguay",
    "sg:classifiers":[
        {
            "category":"Home & Garden",
            "subcategory":"Building Materials",
            "type":"Retail Goods"
        }
    ],
    "sg:phone":"+1 450 692 8417",
    "sg:postcode":"J6J 6A9",
    "sg:province":"QC",
    "sg:tags":[
        "screen",
        "window"
    ],
    "wof:name":"Moustiquaires Major Inc",
    "wof:placetype":"venue"
},
  "geometry": {"coordinates":[-73.7284698486,45.3766403198],"type":"Point"}
}