{
  "type": "Feature",
  "properties": {
    "addr:full":"4811 Benson Rd NW Calgary AB T2L 1R9",
    "addr:housenumber":"4811",
    "addr:postcode":"t2l 1r9",
    "addr:street":"Benson Rd Nw",
    "iso:country":"CA",
    "sg:address":"4811 Benson Rd NW",
    "sg:city":"Calgary",
    "sg:classifiers":[
        {
            "category":"Wholesale",
            "subcategory":"Electrical",
            "type":"Manufacturing & Wholesale Goods"
        }
    ],
    "sg:phone":"+1 403 262 1980",
    "sg:postcode":"T2L 1R9",
    "sg:province":"AB",
    "sg:tags":[
        "control",
        "security",
        "system"
    ],
    "wof:name":"Dynovac Plus Security",
    "wof:placetype":"venue"
},
  "geometry": {"coordinates":[-114.129524231,51.095539093],"type":"Point"}
}