{
  "type": "Feature",
  "properties": {
    "iso:country":"CA",
    "sg:address":"542 138 Rte",
    "sg:city":"Longue-Rive",
    "sg:classifiers":[
        {
            "category":"Building & Trades",
            "subcategory":"Construction",
            "type":"Services"
        }
    ],
    "sg:phone":"+1 418 231 2437",
    "sg:postcode":"G0T 1Z0",
    "sg:province":"QC",
    "sg:tags":[
        "boring",
        "breaking",
        "contractor",
        "concrete",
        "cutting",
        "drilling",
        "sawing"
    ],
    "wof:name":"Forage Dynamitage Girard Inc",
    "wof:placetype":"venue"
},
  "geometry": {"coordinates":[-69.23528289790001,48.5701446533],"type":"Point"}
}