{
  "type": "Feature",
  "properties": {
    "addr:full":"3911 Mooseland Rd Mooseland NS B0J 2J0",
    "addr:housenumber":"3911",
    "addr:postcode":"b0j 2j0",
    "addr:street":"Mooseland Rd",
    "iso:country":"CA",
    "sg:address":"3911 Mooseland Rd",
    "sg:city":"Mooseland",
    "sg:classifiers":[
        {
            "category":"Manufacturing",
            "subcategory":"Lumber",
            "type":"Manufacturing & Wholesale Goods"
        }
    ],
    "sg:phone":"+1 902 772 2352",
    "sg:postcode":"B0J 2J0",
    "sg:province":"NS",
    "sg:tags":[
        "forester"
    ],
    "wof:name":"Forestex Limited",
    "wof:placetype":"venue"
},
  "geometry": {"coordinates":[-62.798847,44.947769],"type":"Point"}
}