{
  "type": "Feature",
  "properties": {
    "addr:full":"NE 17-3-5W Morden MB R6M 1C3",
    "addr:postcode":"r6m 1c3",
    "addr:street":"Ne 17-3-5W",
    "iso:country":"CA",
    "sg:address":"NE 17-3-5W",
    "sg:city":"Morden",
    "sg:classifiers":[
        {
            "category":"Building & Trades",
            "subcategory":"Construction",
            "type":"Services"
        }
    ],
    "sg:phone":"+1 204 822 6561",
    "sg:postcode":"R6M 1C3",
    "sg:province":"MB",
    "sg:tags":[
        "maker",
        "cabinet"
    ],
    "wof:name":"Tops & Tile",
    "wof:placetype":"venue"
},
  "geometry": {"coordinates":[-98.113022,49.192284],"type":"Point"}
}