{
  "type": "Feature",
  "properties": {
    "addr:full":"3484 Av Des Eglises Charny QC G6X 1W7",
    "addr:housenumber":"3484",
    "addr:postcode":"g6x 1w7",
    "addr:street":"Av Des Eglises",
    "iso:country":"CA",
    "sg:address":"3484 Av Des Eglises",
    "sg:city":"Charny",
    "sg:classifiers":[
        {
            "category":"Health Services",
            "subcategory":"Chiropractor",
            "type":"Services"
        }
    ],
    "sg:phone":"+1 418 832 4629",
    "sg:postcode":"G6X 1W7",
    "sg:province":"QC",
    "wof:name":"Clinique C Allyson DC",
    "wof:placetype":"venue"
},
  "geometry": {"coordinates":[-71.2705612183,46.7153816223],"type":"Point"}
}