{
  "type": "Feature",
  "properties": {
    "addr:full":"15232 Stony Plain Rd NW Edmonton AB T5P 3Y5",
    "addr:housenumber":"15232",
    "addr:postcode":"t5p 3y5",
    "addr:street":"Stony Plain Rd Nw",
    "iso:country":"CA",
    "sg:address":"15232 Stony Plain Rd NW",
    "sg:city":"Edmonton",
    "sg:classifiers":[
        {
            "category":"Home & Garden",
            "subcategory":"Household Appliances",
            "type":"Retail Goods"
        }
    ],
    "sg:phone":"+1 780 484 5052",
    "sg:postcode":"T5P 3Y5",
    "sg:province":"AB",
    "sg:tags":[
        "cleaners",
        "vacuum"
    ],
    "wof:name":"All-Make Vacuum Svc",
    "wof:placetype":"venue"
},
  "geometry": {"coordinates":[-113.58390799999999,53.541401],"type":"Point"}
}