{
  "type": "Feature",
  "properties": {
    "iso:country":"CA",
    "sg:address":"171 Centennial Rd",
    "sg:city":"Lumsden",
    "sg:classifiers":[
        {
            "category":"Bars & Pubs",
            "type":"Food & Drink"
        }
    ],
    "sg:phone":"+1 709 530 2323",
    "sg:postcode":"A0G 3E0",
    "sg:province":"NL",
    "sg:tags":[
        "lounge",
        "cocktail"
    ],
    "wof:name":"Morrison's Lounge",
    "wof:placetype":"venue"
},
  "geometry": {"coordinates":[-53.6036376953,49.2962493896],"type":"Point"}
}