{
  "type": "Feature",
  "properties": {
    "addr:full":"24 Church Ranches Blvd Calgary AB T3R 1C1",
    "addr:housenumber":"24",
    "addr:postcode":"t3r 1c1",
    "addr:street":"Church Ranches Blvd",
    "iso:country":"CA",
    "sg:address":"24 Church Ranches Blvd",
    "sg:city":"Calgary",
    "sg:classifiers":[
        {
            "category":"Home & Garden",
            "subcategory":"Home Furnishings",
            "type":"Retail Goods"
        }
    ],
    "sg:phone":"+1 403 547 4787",
    "sg:postcode":"T3R 1C1",
    "sg:province":"AB",
    "sg:tags":[
        "venetian",
        "blind"
    ],
    "wof:name":"Calgary Wholesale Blinds",
    "wof:placetype":"venue"
},
  "geometry": {"coordinates":[-114.063194275,51.0450744629],"type":"Point"}
}