{
  "type": "Feature",
  "properties": {
    "addr:full":"Toronto ON M5T 2V8",
    "addr:postcode":"m5t 2v8",
    "iso:country":"CA",
    "sg:city":"Toronto",
    "sg:classifiers":[
        {
            "category":"Health Services",
            "subcategory":"Optometrist",
            "type":"Services"
        }
    ],
    "sg:phone":"+1 416 926 3744",
    "sg:postcode":"M5T 2V8",
    "sg:province":"ON",
    "wof:name":"Le, Duc N OD",
    "wof:placetype":"venue"
},
  "geometry": {"coordinates":[-79.40334320069999,43.6572265625],"type":"Point"}
}