{
  "type": "Feature",
  "properties": {
    "addr:full":"39 Cambridge St S Lindsay ON K9V 3B9",
    "addr:housenumber":"39",
    "addr:postcode":"k9v 3b9",
    "addr:street":"Cambridge St S",
    "iso:country":"CA",
    "sg:address":"39 Cambridge St S",
    "sg:city":"Lindsay",
    "sg:classifiers":[
        {
            "category":"Home & Garden",
            "subcategory":"Building Materials",
            "type":"Retail Goods"
        }
    ],
    "sg:phone":"+1 705 324 3305",
    "sg:postcode":"K9V 3B9",
    "sg:province":"ON",
    "sg:tags":[
        "glass",
        "window",
        "plate"
    ],
    "wof:name":"Lindsay Glass Ltd",
    "wof:placetype":"venue"
},
  "geometry": {"coordinates":[-78.738724,44.35273],"type":"Point"}
}