{
  "type": "Feature",
  "properties": {
    "addr:full":"8515 Boul Henri-Bourassa O Saint-Laurent QC H4S 1P7",
    "addr:housenumber":"8515",
    "addr:postcode":"h4s 1p7",
    "addr:street":"Boul Henri-Bourassa O",
    "iso:country":"CA",
    "sg:address":"8515 Boul Henri-Bourassa O",
    "sg:city":"Saint-Laurent",
    "sg:classifiers":[
        {
            "category":"Wholesale",
            "subcategory":"Machinery & Supplies",
            "type":"Manufacturing & Wholesale Goods"
        }
    ],
    "sg:phone":"+1 514 332 0322",
    "sg:postcode":"H4S 1P7",
    "sg:province":"QC",
    "sg:tags":[
        "equipment",
        "material",
        "handling"
    ],
    "wof:name":"Materiaux D'Expedition Lion",
    "wof:placetype":"venue"
},
  "geometry": {"coordinates":[-73.744758606,45.5026359558],"type":"Point"}
}