{
  "type": "Feature",
  "properties": {
    "addr:full":"908 Dufferin Ave Wallaceburg ON N8A 2V6",
    "addr:housenumber":"908",
    "addr:postcode":"n8a 2v6",
    "addr:street":"Dufferin Ave",
    "iso:country":"CA",
    "sg:address":"908 Dufferin Ave",
    "sg:city":"Wallaceburg",
    "sg:classifiers":[
        {
            "category":"Autos & Motor Vehicles",
            "subcategory":"Fuel & Gas Station",
            "type":"Retail Goods"
        }
    ],
    "sg:phone":"+1 519 627 1128",
    "sg:postcode":"N8A 2V6",
    "sg:province":"ON",
    "sg:tags":[
        "oil"
    ],
    "wof:name":"Dufferin Avenue Sunoco",
    "wof:placetype":"venue"
},
  "geometry": {"coordinates":[-82.391182,42.592945],"type":"Point"}
}