{
  "type": "Feature",
  "properties": {
    "addr:full":"6589 Boul Monk Montreal QC H4E 3J2",
    "addr:housenumber":"6589",
    "addr:postcode":"h4e 3j2",
    "addr:street":"Boul Monk",
    "iso:country":"CA",
    "sg:address":"6589 Boul Monk",
    "sg:city":"Montreal",
    "sg:classifiers":[
        {
            "category":"Shopping",
            "subcategory":"Used Merchandise",
            "type":"Retail Goods"
        }
    ],
    "sg:phone":"+1 514 769 8886",
    "sg:postcode":"H4E 3J2",
    "sg:province":"QC",
    "sg:tags":[
        "pawnbroker"
    ],
    "wof:name":"Comptant Monk",
    "wof:placetype":"venue"
},
  "geometry": {"coordinates":[-73.594162,45.453033],"type":"Point"}
}