{
  "type": "Feature",
  "properties": {
    "addr:full":"20 Ashbourne Dr Etobicoke ON M9B 4G9",
    "addr:housenumber":"20",
    "addr:postcode":"m9b 4g9",
    "addr:street":"Ashbourne Dr",
    "iso:country":"CA",
    "sg:address":"20 Ashbourne Dr",
    "sg:city":"Etobicoke",
    "sg:classifiers":[
        {
            "category":"Professional",
            "subcategory":"Engineering",
            "type":"Services"
        }
    ],
    "sg:phone":"+1 416 233 8834",
    "sg:postcode":"M9B 4G9",
    "sg:province":"ON",
    "sg:tags":[
        "engineer"
    ],
    "wof:name":"Pragma Engineering Inc",
    "wof:placetype":"venue"
},
  "geometry": {"coordinates":[-79.542625,43.641617],"type":"Point"}
}