{
  "type": "Feature",
  "properties": {
    "addr:full":"1195 Courtneypark Dr E Mississauga ON L5T 1R1",
    "addr:housenumber":"1195",
    "addr:postcode":"l5t 1r1",
    "addr:street":"Courtneypark Dr E",
    "iso:country":"CA",
    "sg:address":"1195 Courtneypark Dr E",
    "sg:city":"Mississauga",
    "sg:classifiers":[
        {
            "category":"Freight",
            "type":"Transportation"
        }
    ],
    "sg:phone":"+1 905 670 0009",
    "sg:postcode":"L5T 1R1",
    "sg:province":"ON",
    "sg:tags":[
        "warehouse",
        "self",
        "storage"
    ],
    "wof:name":"Global Distribution & Warehsng",
    "wof:placetype":"venue"
},
  "geometry": {"coordinates":[-79.6634521484,43.6589775085],"type":"Point"}
}