{
  "type": "Feature",
  "properties": {
    "iso:country":"CA",
    "sg:city":"Aurora",
    "sg:classifiers":[
        {
            "category":"Food & Beverages",
            "subcategory":"Groceries & Convenience Stores",
            "type":"Retail Goods"
        }
    ],
    "sg:phone":"+1 905 713 2802",
    "sg:postcode":"L4G 6H8",
    "sg:province":"ON",
    "wof:name":"Youn Convenience",
    "wof:placetype":"venue"
},
  "geometry": {"coordinates":[-79.46505,43.989922],"type":"Point"}
}