{
  "type": "Feature",
  "properties": {
    "addr:full":"10 Mary Ave Naughton ON P0M 2M0",
    "addr:housenumber":"10",
    "addr:postcode":"p0m 2m0",
    "addr:street":"Mary Ave Naughton",
    "iso:country":"CA",
    "sg:address":"10 Mary Ave",
    "sg:city":"Naughton",
    "sg:classifiers":[
        {
            "category":"Organizations",
            "subcategory":"Religious Organization",
            "type":"Services"
        }
    ],
    "sg:phone":"+1 705 692 0513",
    "sg:postcode":"P0M 2M0",
    "sg:province":"ON",
    "sg:tags":[
        "church"
    ],
    "wof:name":"Naughton Congregational Church",
    "wof:placetype":"venue"
},
  "geometry": {"coordinates":[-81.194397,46.401691],"type":"Point"}
}