{
  "type": "Feature",
  "properties": {
    "addr:full":"PO Box 460 Hamiota MB R0M 0T0",
    "addr:housenumber":"po",
    "addr:postcode":"r0m 0t0",
    "addr:street":"Box 460",
    "iso:country":"CA",
    "sg:address":"PO Box 460",
    "sg:city":"Hamiota",
    "sg:classifiers":[
        {
            "category":"Farming",
            "subcategory":"Farm & Veterinary Services",
            "type":"Manufacturing & Wholesale Goods"
        }
    ],
    "sg:phone":"+1 204 764 2111",
    "sg:postcode":"R0M 0T0",
    "sg:province":"MB",
    "sg:tags":[
        "product",
        "protection",
        "crop"
    ],
    "wof:name":"Agricore United",
    "wof:placetype":"venue"
},
  "geometry": {"coordinates":[-100.599845886,50.182510376],"type":"Point"}
}