{
  "type": "Feature",
  "properties": {
    "addr:full":"300 Sidney St Belleville ON K8P 3Z3",
    "addr:housenumber":"300",
    "addr:postcode":"k8p 3z3",
    "addr:street":"Sidney St",
    "iso:country":"CA",
    "sg:address":"300 Sidney St",
    "sg:city":"Belleville",
    "sg:classifiers":[
        {
            "category":"Education",
            "subcategory":"School",
            "type":"Public Place"
        }
    ],
    "sg:phone":"+1 613 962 2162",
    "sg:postcode":"K8P 3Z3",
    "sg:province":"ON",
    "wof:name":"Our Lady of Fatima School",
    "wof:placetype":"venue"
},
  "geometry": {"coordinates":[-77.4006729126,44.1647987366],"type":"Point"}
}