{
  "type": "Feature",
  "properties": {
    "addr:full":"Saskatoon SK S7K 0B2",
    "addr:postcode":"s7k 0b2",
    "iso:country":"CA",
    "sg:city":"Saskatoon",
    "sg:classifiers":[
        {
            "category":"Organizations",
            "subcategory":"Professional Association",
            "type":"Services"
        }
    ],
    "sg:phone":"+1 306 652 0769",
    "sg:postcode":"S7K 0B2",
    "sg:province":"SK",
    "wof:name":"Saskatchewan Ophthalmic Dspnsr",
    "wof:placetype":"venue"
},
  "geometry": {"coordinates":[-106.66580200200001,52.1272697449],"type":"Point"}
}