{
  "type": "Feature",
  "properties": {
    "addr:full":"16646 104 Ave Surrey BC V4N 1Z1",
    "addr:housenumber":"16646",
    "addr:postcode":"v4n 1z1",
    "addr:street":"104 Ave",
    "iso:country":"CA",
    "sg:address":"16646 104 Ave",
    "sg:city":"Surrey",
    "sg:classifiers":[
        {
            "category":"Retail",
            "subcategory":"Auto Repair",
            "type":"Services"
        }
    ],
    "sg:phone":"+1 604 951 3244",
    "sg:postcode":"V4N 1Z1",
    "sg:province":"BC",
    "sg:tags":[
        "automobile",
        "customizing"
    ],
    "wof:name":"Pro Cal Distributors Inc",
    "wof:placetype":"venue"
},
  "geometry": {"coordinates":[-122.76026899999999,49.191456],"type":"Point"}
}