{
  "type": "Feature",
  "properties": {
    "addr:full":"105 Hwy 40 & 12 Blaine Lake SK S0J 0J0",
    "addr:housenumber":"105",
    "addr:postcode":"s0j 0j0",
    "addr:street":"Hwy 40 & 12 Blaine Lake",
    "iso:country":"CA",
    "sg:address":"105 Hwy 40 & 12",
    "sg:city":"Blaine Lake",
    "sg:classifiers":[
        {
            "category":"Food & Beverages",
            "subcategory":"Groceries & Convenience Stores",
            "type":"Retail Goods"
        }
    ],
    "sg:phone":"+1 306 497 3300",
    "sg:postcode":"S0J 0J0",
    "sg:province":"SK",
    "wof:name":"Blaine Lake Esso",
    "wof:placetype":"venue"
},
  "geometry": {"coordinates":[-106.87867,52.827629],"type":"Point"}
}