{
  "type": "Feature",
  "properties": {
    "iso:country":"CA",
    "sg:address":"4000 Boul Des Forges",
    "sg:city":"Trois-Rivieres",
    "sg:classifiers":[
        {
            "category":"Shopping",
            "subcategory":"Books",
            "type":"Retail Goods"
        }
    ],
    "sg:phone":"+1 819 379 4153",
    "sg:postcode":"G8Y 1V7",
    "sg:province":"QC",
    "sg:tags":[
        "dealer"
    ],
    "wof:name":"Morin, Clement",
    "wof:placetype":"venue"
},
  "geometry": {"coordinates":[-72.5847320557,46.3556518555],"type":"Point"}
}