{
  "type": "Feature",
  "properties": {
    "addr:full":"5205 Boul Hebert Saint-Timothee QC J6S 6B8",
    "addr:housenumber":"5205",
    "addr:postcode":"j6s 6b8",
    "addr:street":"Boul Hebert Saint-Timothee",
    "iso:country":"CA",
    "sg:address":"5205 Boul Hebert",
    "sg:city":"Saint-Timothee",
    "sg:classifiers":[
        {
            "category":"Bars & Pubs",
            "type":"Food & Drink"
        }
    ],
    "sg:phone":"+1 450 377 9911",
    "sg:postcode":"J6S 6B8",
    "sg:province":"QC",
    "sg:tags":[
        "lounge",
        "cocktail"
    ],
    "wof:name":"Bar Salon L'Oasis Enrg",
    "wof:placetype":"venue"
},
  "geometry": {"coordinates":[-74.04741668699999,45.2884025574],"type":"Point"}
}