{
  "type": "Feature",
  "properties": {
    "addr:full":"446 Lyndoch St Corunna ON N0N 1G0",
    "addr:housenumber":"446",
    "addr:postcode":"n0n 1g0",
    "addr:street":"Lyndoch St",
    "iso:country":"CA",
    "sg:address":"446 Lyndoch St",
    "sg:city":"Corunna",
    "sg:classifiers":[
        {
            "category":"Autos & Motor Vehicles",
            "subcategory":"Auto Supplies",
            "type":"Retail Goods"
        }
    ],
    "sg:phone":"+1 519 862 2860",
    "sg:postcode":"N0N 1G0",
    "sg:province":"ON",
    "sg:tags":[
        "automobile",
        "parts"
    ],
    "wof:name":"Downriver Auto Ltd",
    "wof:placetype":"venue"
},
  "geometry": {"coordinates":[-82.453217,42.885853],"type":"Point"}
}