{
  "type": "Feature",
  "properties": {
    "addr:full":"1631 Dundas St E Whitby ON L1N 2K9",
    "addr:housenumber":"1631",
    "addr:postcode":"l1n 2k9",
    "addr:street":"Dundas St E",
    "iso:country":"CA",
    "sg:address":"1631 Dundas St E",
    "sg:city":"Whitby",
    "sg:classifiers":[
        {
            "category":"Health Services",
            "subcategory":"Chiropractor",
            "type":"Services"
        }
    ],
    "sg:phone":"+1 905 728 3608",
    "sg:postcode":"L1N 2K9",
    "sg:province":"ON",
    "wof:name":"Family Wellness Clinic",
    "wof:placetype":"venue"
},
  "geometry": {"coordinates":[-78.91158299999999,43.886669],"type":"Point"}
}