{
  "type": "Feature",
  "properties": {
    "addr:full":"37 Ch DE Blue Sea Gracefield QC J0X 1W0",
    "addr:housenumber":"37",
    "addr:postcode":"j0x 1w0",
    "addr:street":"Ch De Blue Sea",
    "iso:country":"CA",
    "sg:address":"37 Ch DE Blue Sea",
    "sg:city":"Gracefield",
    "sg:classifiers":[
        {
            "category":"Taxi",
            "type":"Transportation"
        }
    ],
    "sg:phone":"+1 819 463 2062",
    "sg:postcode":"J0X 1W0",
    "sg:province":"QC",
    "sg:tags":[
        "taxicab"
    ],
    "wof:name":"Jacques Lauriault Taxi",
    "wof:placetype":"venue"
},
  "geometry": {"coordinates":[-76.062477,46.10186],"type":"Point"}
}