{
  "type": "Feature",
  "properties": {
    "addr:full":"2323 Fosgate Rd Campbell River BC V9H 1B8",
    "addr:housenumber":"2323",
    "addr:postcode":"v9h 1b8",
    "addr:street":"Fosgate Rd",
    "iso:country":"CA",
    "sg:address":"2323 Fosgate Rd",
    "sg:city":"Campbell River",
    "sg:classifiers":[
        {
            "category":"Building & Trades",
            "subcategory":"Construction",
            "type":"Services"
        }
    ],
    "sg:phone":"+1 250 923 7553",
    "sg:postcode":"V9H 1B8",
    "sg:province":"BC",
    "sg:tags":[
        "sand",
        "gravel",
        "excavating",
        "contractor"
    ],
    "wof:name":"Five Star Aggregate & Excavtg",
    "wof:placetype":"venue"
},
  "geometry": {"coordinates":[-125.248168945,50.0246086121],"type":"Point"}
}