{
  "type": "Feature",
  "properties": {
    "addr:full":"LA Crete AB T0H 2H0",
    "addr:postcode":"t0h 2h0",
    "iso:country":"CA",
    "sg:city":"LA Crete",
    "sg:classifiers":[
        {
            "category":"Autos & Motor Vehicles",
            "subcategory":"Auto Supplies",
            "type":"Retail Goods"
        }
    ],
    "sg:phone":"+1 780 928 3912",
    "sg:postcode":"T0H 2H0",
    "sg:province":"AB",
    "sg:tags":[
        "automobile",
        "parts"
    ],
    "wof:name":"Norpine Auto Supply Ltd",
    "wof:placetype":"venue"
},
  "geometry": {"coordinates":[-116.40451,58.180882],"type":"Point"}
}