{
  "type": "Feature",
  "properties": {
    "addr:full":"5686 Spring Garden Rd Halifax NS B3J 1H5",
    "addr:housenumber":"5686",
    "addr:postcode":"ns b3j 1h5",
    "addr:street":"Spring Garden Rd",
    "iso:country":"CA",
    "sg:address":"5686 Spring Garden Rd",
    "sg:city":"Halifax",
    "sg:classifiers":[
        {
            "category":"Shopping",
            "subcategory":"News",
            "type":"Retail Goods"
        }
    ],
    "sg:phone":"+1 902 429 6397",
    "sg:postcode":"B3J 1H5",
    "sg:province":"NS",
    "sg:tags":[
        "dealer"
    ],
    "wof:name":"Daily Grind Newstand & Cafe",
    "wof:placetype":"venue"
},
  "geometry": {"coordinates":[-63.579422,44.642227],"type":"Point"}
}