{
  "type": "Feature",
  "properties": {
    "iso:country":"CA",
    "sg:address":"605 Main St N",
    "sg:city":"Moose Jaw",
    "sg:classifiers":[
        {
            "category":"Food & Beverages",
            "subcategory":"Specialty",
            "type":"Retail Goods"
        }
    ],
    "sg:phone":"+1 306 694 0111",
    "sg:postcode":"S6H 0W6",
    "sg:province":"SK",
    "sg:tags":[
        "product",
        "health",
        "diet"
    ],
    "wof:name":"Nutter's Bulk & Natural Foods",
    "wof:placetype":"venue"
},
  "geometry": {"coordinates":[-105.53441619900001,50.3954734802],"type":"Point"}
}