{
  "type": "Feature",
  "properties": {
    "addr:full":"1188 Ottawa St S Kitchener ON N2E 1L8",
    "addr:housenumber":"1188",
    "addr:postcode":"n2e 1l8",
    "addr:street":"Ottawa St S",
    "iso:country":"CA",
    "sg:address":"1188 Ottawa St S",
    "sg:city":"Kitchener",
    "sg:classifiers":[
        {
            "category":"Health Services",
            "subcategory":"Optometrist",
            "type":"Services"
        }
    ],
    "sg:phone":"+1 519 745 0310",
    "sg:postcode":"N2E 1L8",
    "sg:province":"ON",
    "wof:name":"Code & Nickel",
    "wof:placetype":"venue"
},
  "geometry": {"coordinates":[-80.5064697266,43.4197540283],"type":"Point"}
}