{
  "type": "Feature",
  "properties": {
    "addr:full":"Toronto ON M6S 3P2",
    "addr:postcode":"m6s 3p2",
    "iso:country":"CA",
    "sg:city":"Toronto",
    "sg:classifiers":[
        {
            "category":"Education",
            "subcategory":"Special Training",
            "type":"Public Place"
        }
    ],
    "sg:phone":"+1 416 769 0846",
    "sg:postcode":"M6S 3P2",
    "sg:province":"ON",
    "sg:tags":[
        "consultant",
        "management",
        "business"
    ],
    "wof:name":"Communicare",
    "wof:placetype":"venue"
},
  "geometry": {"coordinates":[-79.474647522,43.6376533508],"type":"Point"}
}