{
  "type": "Feature",
  "properties": {
    "iso:country":"CA",
    "sg:address":"3318 Millar Ave",
    "sg:city":"Saskatoon",
    "sg:classifiers":[
        {
            "category":"Wholesale",
            "subcategory":"Durable Goods & Equipment",
            "type":"Manufacturing & Wholesale Goods"
        }
    ],
    "sg:phone":"+1 306 933 0039",
    "sg:postcode":"S7K 7G9",
    "sg:province":"SK",
    "sg:tags":[
        "magnet",
        "magnetic",
        "devices"
    ],
    "wof:name":"Lynum Engineering Sales",
    "wof:placetype":"venue"
},
  "geometry": {"coordinates":[-106.646255493,52.1844406128],"type":"Point"}
}