{
  "type": "Feature",
  "properties": {
    "addr:full":"6516 Chebucto Rd Halifax NS B3L 1L7",
    "addr:housenumber":"6516",
    "addr:postcode":"b3l 1l7",
    "addr:street":"Chebucto Rd",
    "iso:country":"CA",
    "sg:address":"6516 Chebucto Rd",
    "sg:city":"Halifax",
    "sg:classifiers":[
        {
            "category":"Food & Beverages",
            "subcategory":"Groceries & Convenience Stores",
            "type":"Retail Goods"
        }
    ],
    "sg:phone":"+1 902 422 5679",
    "sg:postcode":"B3L 1L7",
    "sg:province":"NS",
    "sg:tags":[
        "grocer"
    ],
    "wof:name":"European Pantry",
    "wof:placetype":"venue"
},
  "geometry": {"coordinates":[-63.6056518555,44.6477622986],"type":"Point"}
}