{
  "type": "Feature",
  "properties": {
    "addr:full":"Courtenay BC V9N 2L9",
    "addr:postcode":"v9n 2l9",
    "iso:country":"CA",
    "sg:city":"Courtenay",
    "sg:classifiers":[
        {
            "category":"Shopping",
            "subcategory":"Clothing, Apparel, & Fashions",
            "type":"Retail Goods"
        }
    ],
    "sg:phone":"+1 250 334 2533",
    "sg:postcode":"V9N 2L9",
    "sg:province":"BC",
    "wof:name":"Suzanne's",
    "wof:placetype":"venue"
},
  "geometry": {"coordinates":[-124.977875,49.668613],"type":"Point"}
}