{
  "type": "Feature",
  "properties": {
    "iso:country":"CA",
    "sg:city":"Richelieu",
    "sg:classifiers":[
        {
            "category":"Health Services",
            "subcategory":"Clinic",
            "type":"Services"
        }
    ],
    "sg:phone":"+1 450 658 9862",
    "sg:postcode":"J3L 6P9",
    "sg:province":"QC",
    "sg:tags":[
        "holistic",
        "practitioner"
    ],
    "wof:name":"O Centre",
    "wof:placetype":"venue"
},
  "geometry": {"coordinates":[-73.2395248413,45.4108200073],"type":"Point"}
}