{
  "type": "Feature",
  "properties": {
    "iso:country":"CA",
    "sg:address":"9902 101 St",
    "sg:city":"Grande Prairie",
    "sg:classifiers":[
        {
            "category":"Education",
            "subcategory":"School",
            "type":"Public Place"
        }
    ],
    "sg:phone":"+1 780 532 3013",
    "sg:postcode":"T8V 2P4",
    "sg:province":"AB",
    "wof:name":"Grande Prairie Catholic School",
    "wof:placetype":"venue"
},
  "geometry": {"coordinates":[-118.797866821,55.1699066162],"type":"Point"}
}