{
  "type": "Feature",
  "properties": {
    "addr:full":"120 Carlton St # 214 Toronto ON M5A 4K2",
    "addr:housenumber":"120",
    "addr:postcode":"m5a 4k2",
    "addr:street":"Carlton St # 214",
    "iso:country":"CA",
    "sg:address":"120 Carlton St # 214",
    "sg:city":"Toronto",
    "sg:classifiers":[
        {
            "category":"Professional",
            "subcategory":"Lawyer & Legal Services",
            "type":"Services"
        }
    ],
    "sg:phone":"+1 416 944 1222",
    "sg:postcode":"M5A 4K2",
    "sg:province":"ON",
    "sg:tags":[
        "attorney"
    ],
    "wof:name":"Ernest Guiste & Assoc",
    "wof:placetype":"venue"
},
  "geometry": {"coordinates":[-79.37661,43.662506],"type":"Point"}
}