{
  "type": "Feature",
  "properties": {
    "addr:full":"3555 Don Mills Rd North York ON M2H 3N3",
    "addr:housenumber":"3555",
    "addr:postcode":"m2h 3n3",
    "addr:street":"Don Mills Rd",
    "iso:country":"CA",
    "sg:address":"3555 Don Mills Rd",
    "sg:city":"North York",
    "sg:classifiers":[
        {
            "category":"Government",
            "subcategory":"Office",
            "type":"Public Place"
        }
    ],
    "sg:phone":"+1 416 497 9497",
    "sg:postcode":"M2H 3N3",
    "sg:province":"ON",
    "wof:name":"Ontario Drivers & Vehicles",
    "wof:placetype":"venue"
},
  "geometry": {"coordinates":[-79.35498800000001,43.79454],"type":"Point"}
}