{
  "type": "Feature",
  "properties": {
    "addr:full":"613 9th St E Saskatoon SK S7H 0M4",
    "addr:housenumber":"613",
    "addr:postcode":"s7h 0m4",
    "addr:street":"9Th St E",
    "iso:country":"CA",
    "sg:address":"613 9th St E",
    "sg:city":"Saskatoon",
    "sg:classifiers":[
        {
            "category":"Professional",
            "subcategory":"Accounting & Tax Preparation",
            "type":"Services"
        }
    ],
    "sg:phone":"+1 306 665 7728",
    "sg:postcode":"S7H 0M4",
    "sg:province":"SK",
    "sg:tags":[
        "accountant"
    ],
    "wof:name":"Smith, Barry J CA",
    "wof:placetype":"venue"
},
  "geometry": {"coordinates":[-106.656143,52.115829],"type":"Point"}
}