{
  "type": "Feature",
  "properties": {
    "addr:full":"133 Centre St Spalding SK S0K 4C0",
    "addr:housenumber":"133",
    "addr:postcode":"s0k 4c0",
    "addr:street":"Centre St",
    "iso:country":"CA",
    "sg:address":"133 Centre St",
    "sg:city":"Spalding",
    "sg:classifiers":[
        {
            "category":"Health Services",
            "subcategory":"Doctor",
            "type":"Services"
        }
    ],
    "sg:phone":"+1 306 872 2011",
    "sg:postcode":"S0K 4C0",
    "sg:province":"SK",
    "sg:tags":[
        "clinic"
    ],
    "wof:name":"Spalding Community Health Ctr",
    "wof:placetype":"venue"
},
  "geometry": {"coordinates":[-104.496582031,52.3327331543],"type":"Point"}
}