{
  "type": "Feature",
  "properties": {
    "addr:full":"460 Rue Saint-Gabriel Montreal QC H2Y 2Z9",
    "addr:housenumber":"460",
    "addr:postcode":"h2y 2z9",
    "addr:street":"Rue Saint-Gabriel",
    "iso:country":"CA",
    "sg:address":"460 Rue Saint-Gabriel",
    "sg:city":"Montreal",
    "sg:classifiers":[
        {
            "category":"Professional",
            "subcategory":"Lawyer & Legal Services",
            "type":"Services"
        }
    ],
    "sg:phone":"+1 514 861 6794",
    "sg:postcode":"H2Y 2Z9",
    "sg:province":"QC",
    "sg:tags":[
        "attorney"
    ],
    "wof:name":"Girard, Mario",
    "wof:placetype":"venue"
},
  "geometry": {"coordinates":[-73.554665,45.506622],"type":"Point"}
}