{
  "type": "Feature",
  "properties": {
    "addr:full":"21 Mullen Dr Thornhill ON L4J 2T6",
    "addr:housenumber":"21",
    "addr:postcode":"l4j 2t6",
    "addr:street":"Mullen Dr",
    "iso:country":"CA",
    "sg:address":"21 Mullen Dr",
    "sg:city":"Thornhill",
    "sg:classifiers":[
        {
            "category":"Education",
            "subcategory":"School",
            "type":"Public Place"
        }
    ],
    "sg:phone":"+1 905 882 4844",
    "sg:postcode":"L4J 2T6",
    "sg:province":"ON",
    "wof:name":"Holy Family Catholic School",
    "wof:placetype":"venue"
},
  "geometry": {"coordinates":[-79.4581451416,43.7961349487],"type":"Point"}
}