{
  "type": "Feature",
  "properties": {
    "addr:full":"Westerose AB T0C 2V0",
    "addr:postcode":"t0c 2v0",
    "iso:country":"CA",
    "sg:city":"Westerose",
    "sg:classifiers":[
        {
            "category":"Food & Beverages",
            "subcategory":"Groceries & Convenience Stores",
            "type":"Retail Goods"
        }
    ],
    "sg:phone":"+1 780 586 3860",
    "sg:postcode":"T0C 2V0",
    "sg:province":"AB",
    "sg:tags":[
        "grocer"
    ],
    "wof:name":"Village Market",
    "wof:placetype":"venue"
},
  "geometry": {"coordinates":[-114.018669,52.959751],"type":"Point"}
}