{
  "type": "Feature",
  "properties": {
    "addr:full":"56 Susan St Meaford ON N4L 1J2",
    "addr:housenumber":"56",
    "addr:postcode":"n4l 1j2",
    "addr:street":"Susan St",
    "iso:country":"CA",
    "sg:address":"56 Susan St",
    "sg:city":"Meaford",
    "sg:classifiers":[
        {
            "category":"Building & Trades",
            "subcategory":"Landscaping Services",
            "type":"Services"
        }
    ],
    "sg:phone":"+1 519 538 4147",
    "sg:postcode":"N4L 1J2",
    "sg:province":"ON",
    "sg:tags":[
        "landscape",
        "contractor"
    ],
    "wof:name":"Aardvark Landscaping & Constr",
    "wof:placetype":"venue"
},
  "geometry": {"coordinates":[-80.601074,44.614021],"type":"Point"}
}