{
  "type": "Feature",
  "properties": {
    "addr:full":"100 Rue Emile-Des Pins Charlemagne QC J5Z 3L6",
    "addr:housenumber":"100",
    "addr:postcode":"j5z 3l6",
    "addr:street":"Rue Emile-Des Pins",
    "iso:country":"CA",
    "sg:address":"100 Rue Emile-Des Pins",
    "sg:city":"Charlemagne",
    "sg:classifiers":[
        {
            "category":"Autos & Motor Vehicles",
            "subcategory":"Automobile Sales",
            "type":"Retail Goods"
        }
    ],
    "sg:phone":"+1 514 237 7000",
    "sg:postcode":"J5Z 3L6",
    "sg:province":"QC",
    "sg:tags":[
        "car",
        "dealer"
    ],
    "wof:name":"Qualite Prix Autoplus Inc",
    "wof:placetype":"venue"
},
  "geometry": {"coordinates":[-73.49118,45.721691],"type":"Point"}
}