{
  "type": "Feature",
  "properties": {
    "addr:full":"1300 Hewetson Ave Pincher Creek AB T0K 1W0",
    "addr:housenumber":"1300",
    "addr:postcode":"t0k 1w0",
    "addr:street":"Hewetson Ave",
    "iso:country":"CA",
    "sg:address":"1300 Hewetson Ave",
    "sg:city":"Pincher Creek",
    "sg:classifiers":[
        {
            "category":"Education",
            "subcategory":"Special Training",
            "type":"Public Place"
        }
    ],
    "sg:phone":"+1 403 627 3311",
    "sg:postcode":"T0K 1W0",
    "sg:province":"AB",
    "sg:tags":[
        "reading",
        "instruction",
        "improvement"
    ],
    "wof:name":"Read/Write Program",
    "wof:placetype":"venue"
},
  "geometry": {"coordinates":[-113.94787599999999,49.493149],"type":"Point"}
}