{
  "type": "Feature",
  "properties": {
    "addr:full":"Westmount QC H3Z 1P9",
    "addr:postcode":"h3z 1p9",
    "iso:country":"CA",
    "sg:city":"Westmount",
    "sg:classifiers":[
        {
            "category":"Professional",
            "subcategory":"Management & Consulting",
            "type":"Services"
        }
    ],
    "sg:phone":"+1 514 932 2188",
    "sg:postcode":"H3Z 1P9",
    "sg:province":"QC",
    "sg:tags":[
        "construction"
    ],
    "wof:name":"Revay & Assoc Ltd",
    "wof:placetype":"venue"
},
  "geometry": {"coordinates":[-73.590065,45.484089],"type":"Point"}
}