{
  "type": "Feature",
  "properties": {
    "addr:full":"61 Doxsee St Campbellford ON K0L 1L0",
    "addr:housenumber":"61",
    "addr:postcode":"k0l 1l0",
    "addr:street":"Doxsee St",
    "iso:country":"CA",
    "sg:address":"61 Doxsee St",
    "sg:city":"Campbellford",
    "sg:classifiers":[
        {
            "category":"Health Services",
            "subcategory":"Optometrist",
            "type":"Services"
        }
    ],
    "sg:phone":"+1 705 653 1290",
    "sg:postcode":"K0L 1L0",
    "sg:province":"ON",
    "wof:name":"Pallen, Richard L OD",
    "wof:placetype":"venue"
},
  "geometry": {"coordinates":[-77.79541,44.310116],"type":"Point"}
}