{
  "type": "Feature",
  "properties": {
    "addr:full":"611 Main St N Gravelbourg SK S0H 1X0",
    "addr:housenumber":"611",
    "addr:postcode":"s0h 1x0",
    "addr:street":"Main St N Gravelbourg",
    "iso:country":"CA",
    "sg:address":"611 Main St N",
    "sg:city":"Gravelbourg",
    "sg:classifiers":[
        {
            "category":"Manufacturing",
            "subcategory":"Printing",
            "type":"Manufacturing & Wholesale Goods"
        }
    ],
    "sg:phone":"+1 306 648 3479",
    "sg:postcode":"S0H 1X0",
    "sg:province":"SK",
    "sg:tags":[
        "newspaper"
    ],
    "wof:name":"Gravelbourg Tribune Weekly",
    "wof:placetype":"venue"
},
  "geometry": {"coordinates":[-106.557342529,49.8774604797],"type":"Point"}
}