{
  "type": "Feature",
  "properties": {
    "iso:country":"CA",
    "sg:city":"High Level",
    "sg:classifiers":[
        {
            "category":"Building & Trades",
            "subcategory":"Construction",
            "type":"Services"
        }
    ],
    "sg:phone":"+1 780 926 3225",
    "sg:postcode":"T0H 1Z0",
    "sg:province":"AB",
    "sg:tags":[
        "contractor"
    ],
    "wof:name":"Derksen Construction",
    "wof:placetype":"venue"
},
  "geometry": {"coordinates":[-117.126091003,58.5167198181],"type":"Point"}
}