{
  "type": "Feature",
  "properties": {
    "addr:full":"Hull QC J8Z 2M4",
    "addr:postcode":"j8z 2m4",
    "iso:country":"CA",
    "sg:city":"Hull",
    "sg:classifiers":[
        {
            "category":"Organizations",
            "subcategory":"Labor Organization",
            "type":"Services"
        }
    ],
    "sg:phone":"+1 819 776 1774",
    "sg:postcode":"J8Z 2M4",
    "sg:province":"QC",
    "wof:name":"Syndicat Du Soutien Scolaire",
    "wof:placetype":"venue"
},
  "geometry": {"coordinates":[-75.734459,45.468609],"type":"Point"}
}