{
  "type": "Feature",
  "properties": {
    "addr:full":"663 Kingsway Garden Mall NW Edmonton AB T5G 3E6",
    "addr:housenumber":"663",
    "addr:postcode":"t5g 3e6",
    "addr:street":"Kingsway Garden Mall Nw",
    "iso:country":"CA",
    "sg:address":"663 Kingsway Garden Mall NW",
    "sg:city":"Edmonton",
    "sg:classifiers":[
        {
            "category":"Shopping",
            "subcategory":"Gifts & Souvenirs",
            "type":"Retail Goods"
        }
    ],
    "sg:phone":"+1 780 477 5255",
    "sg:postcode":"T5G 3E6",
    "sg:province":"AB",
    "sg:tags":[
        "shop"
    ],
    "wof:name":"Disney Store Inc",
    "wof:placetype":"venue"
},
  "geometry": {"coordinates":[-113.490371704,53.5462188721],"type":"Point"}
}