{
  "type": "Feature",
  "properties": {
    "addr:full":"992 St. Peter Ave Bathurst NB E2A 2Z4",
    "addr:housenumber":"992",
    "addr:postcode":"e2a 2z4",
    "addr:street":"St. Peter Ave",
    "iso:country":"CA",
    "sg:address":"992 St. Peter Ave",
    "sg:city":"Bathurst",
    "sg:classifiers":[
        {
            "category":"Shopping",
            "subcategory":"Optical Goods",
            "type":"Retail Goods"
        }
    ],
    "sg:phone":"+1 506 546 2628",
    "sg:postcode":"E2A 2Z4",
    "sg:province":"NB",
    "sg:tags":[
        "optician"
    ],
    "wof:name":"Vogue Optical",
    "wof:placetype":"venue"
},
  "geometry": {"coordinates":[-65.673264,47.634998],"type":"Point"}
}