{
  "type": "Feature",
  "properties": {
    "addr:full":"1024 6th St Rosthern SK S0K 3R0",
    "addr:housenumber":"1024",
    "addr:postcode":"s0k 3r0",
    "addr:street":"6Th St",
    "iso:country":"CA",
    "sg:address":"1024 6th St",
    "sg:city":"Rosthern",
    "sg:classifiers":[
        {
            "category":"Shopping",
            "subcategory":"Gifts & Souvenirs",
            "type":"Retail Goods"
        }
    ],
    "sg:phone":"+1 306 232 4303",
    "sg:postcode":"S0K 3R0",
    "sg:province":"SK",
    "sg:tags":[
        "shop"
    ],
    "wof:name":"Rosthern Flower & Gift House",
    "wof:placetype":"venue"
},
  "geometry": {"coordinates":[-106.33169599999999,52.657753],"type":"Point"}
}