{
  "type": "Feature",
  "properties": {
    "iso:country":"CA",
    "sg:address":"372 Bay St., Suite 1600",
    "sg:city":"Toronto",
    "sg:classifiers":[
        {
            "category":"Professional",
            "subcategory":"Computer Services",
            "type":"Services"
        }
    ],
    "sg:postcode":"M5H 2W9",
    "sg:tags":[
        "requirements"
    ],
    "sg:website":"http://www.blueprintsys.com/",
    "wof:name":"Blueprint Software Systems",
    "wof:placetype":"venue"
},
  "geometry": {"coordinates":[-79.381254,43.65101],"type":"Point"}
}