{
  "type": "Feature",
  "properties": {
    "iso:country":"CA",
    "sg:city":"Toronto",
    "sg:classifiers":[
        {
            "category":"Health Services",
            "subcategory":"Doctor",
            "type":"Services"
        }
    ],
    "sg:phone":"+1 416 461 0156",
    "sg:postcode":"M4J 1N4",
    "sg:province":"ON",
    "sg:tags":[
        "dentist"
    ],
    "wof:name":"Cumberland Periodontics",
    "wof:placetype":"venue"
},
  "geometry": {"coordinates":[-79.3257675171,43.6829986572],"type":"Point"}
}