{
  "type": "Feature",
  "properties": {
    "addr:full":"272 S Copper St Greenwood BC V0H 1J0",
    "addr:housenumber":"272",
    "addr:postcode":"v0h 1j0",
    "addr:street":"S Copper St",
    "iso:country":"CA",
    "sg:address":"272 S Copper St",
    "sg:city":"Greenwood",
    "sg:classifiers":[
        {
            "category":"Food & Beverages",
            "subcategory":"Liquor & Beverages",
            "type":"Retail Goods"
        }
    ],
    "sg:phone":"+1 250 445 6336",
    "sg:postcode":"V0H 1J0",
    "sg:province":"BC",
    "sg:tags":[
        "store"
    ],
    "wof:name":"Liquor Stores-Government",
    "wof:placetype":"venue"
},
  "geometry": {"coordinates":[-118.677368164,49.0955581665],"type":"Point"}
}