{
  "type": "Feature",
  "properties": {
    "addr:full":"15 Elm St Truro NS B2N 3H5",
    "addr:housenumber":"15",
    "addr:postcode":"b2n 3h5",
    "addr:street":"Elm St",
    "iso:country":"CA",
    "sg:address":"15 Elm St",
    "sg:city":"Truro",
    "sg:classifiers":[
        {
            "category":"Organizations",
            "subcategory":"Religious Organization",
            "type":"Services"
        }
    ],
    "sg:phone":"+1 902 893 9312",
    "sg:postcode":"B2N 3H5",
    "sg:province":"NS",
    "sg:tags":[
        "church"
    ],
    "wof:name":"Peoples Church",
    "wof:placetype":"venue"
},
  "geometry": {"coordinates":[-63.28648,45.368767],"type":"Point"}
}