{
  "type": "Feature",
  "properties": {
    "addr:full":"Mississauga ON L5V 1Z3",
    "addr:postcode":"l5v 1z3",
    "iso:country":"CA",
    "sg:city":"Mississauga",
    "sg:classifiers":[
        {
            "category":"Social Services",
            "type":"Services"
        }
    ],
    "sg:phone":"+1 905 567 7171",
    "sg:postcode":"L5V 1Z3",
    "sg:province":"ON",
    "sg:tags":[
        "organization",
        "welfare"
    ],
    "wof:name":"Supportive Housing in Peel",
    "wof:placetype":"venue"
},
  "geometry": {"coordinates":[-79.683212,43.592712],"type":"Point"}
}