{
  "type": "Feature",
  "properties": {
    "addr:full":"2607 Yonge St Toronto ON M4P 2J1",
    "addr:housenumber":"2607",
    "addr:postcode":"m4p 2j1",
    "addr:street":"Yonge St",
    "iso:country":"CA",
    "sg:address":"2607 Yonge St",
    "sg:city":"Toronto",
    "sg:classifiers":[
        {
            "category":"Shopping",
            "subcategory":"Clothing, Apparel, & Fashions",
            "type":"Retail Goods"
        }
    ],
    "sg:phone":"+1 416 544 0701",
    "sg:postcode":"M4P 2J1",
    "sg:province":"ON",
    "wof:name":"Divas Clothing Inc",
    "wof:placetype":"venue"
},
  "geometry": {"coordinates":[-79.399872,43.714714],"type":"Point"}
}