{
  "type": "Feature",
  "properties": {
    "iso:country":"CA",
    "sg:address":"420 Rue Saint-Martin",
    "sg:city":"Montreal",
    "sg:classifiers":[
        {
            "category":"Communications",
            "subcategory":"Film & Video Production",
            "type":"Services"
        }
    ],
    "sg:phone":"+1 514 931 0066",
    "sg:postcode":"H3J 1W2",
    "sg:province":"QC",
    "sg:tags":[
        "motion",
        "picture",
        "studio",
        "producer"
    ],
    "wof:name":"Cinelande Inc",
    "wof:placetype":"venue"
},
  "geometry": {"coordinates":[-73.567604,45.487793],"type":"Point"}
}