{
  "type": "Feature",
  "properties": {
    "addr:full":"115 Forestview Rd Orillia ON L3V 6H1",
    "addr:housenumber":"115",
    "addr:postcode":"l3v 6h1",
    "addr:street":"Forestview Rd",
    "iso:country":"CA",
    "sg:address":"115 Forestview Rd",
    "sg:city":"Orillia",
    "sg:classifiers":[
        {
            "category":"Manufacturing",
            "subcategory":"Textiles",
            "type":"Manufacturing & Wholesale Goods"
        }
    ],
    "sg:phone":"+1 705 325 5665",
    "sg:postcode":"L3V 6H1",
    "sg:province":"ON",
    "sg:tags":[
        "rope"
    ],
    "wof:name":"Redpoint Ropes Inc",
    "wof:placetype":"venue"
},
  "geometry": {"coordinates":[-79.42237091059999,44.5823860168],"type":"Point"}
}