{
  "type": "Feature",
  "properties": {
    "addr:full":"3852 Boul Notre-Dame Laval QC H7V 1R9",
    "addr:housenumber":"3852",
    "addr:postcode":"h7v 1r9",
    "addr:street":"Boul Notre-Dame",
    "iso:country":"CA",
    "sg:address":"3852 Boul Notre-Dame",
    "sg:city":"Laval",
    "sg:classifiers":[
        {
            "category":"Social Services",
            "subcategory":"Child Care",
            "type":"Services"
        }
    ],
    "sg:phone":"+1 450 687 7710",
    "sg:postcode":"H7V 1R9",
    "sg:province":"QC",
    "wof:name":"Garderie LA Belle Aventure",
    "wof:placetype":"venue"
},
  "geometry": {"coordinates":[-73.7472076416,45.5412712097],"type":"Point"}
}