{
  "type": "Feature",
  "properties": {
    "addr:full":"1125 Rue Sainte-Catherine O Montreal QC H3B 1H8",
    "addr:housenumber":"1125",
    "addr:postcode":"h3b 1h8",
    "addr:street":"Rue Sainte-Catherine O",
    "iso:country":"CA",
    "sg:address":"1125 Rue Sainte-Catherine O",
    "sg:city":"Montreal",
    "sg:classifiers":[
        {
            "category":"Shopping",
            "subcategory":"Clothing, Apparel, & Fashions",
            "type":"Retail Goods"
        }
    ],
    "sg:phone":"+1 514 288 6399",
    "sg:postcode":"H3B 1H8",
    "sg:province":"QC",
    "sg:tags":[
        "item",
        "boutique"
    ],
    "wof:name":"Mexx Canada Inc",
    "wof:placetype":"venue"
},
  "geometry": {"coordinates":[-73.55699157710001,45.517780304],"type":"Point"}
}