{
  "type": "Feature",
  "properties": {
    "iso:country":"CA",
    "sg:address":"Folly Lake",
    "sg:city":"Debert",
    "sg:classifiers":[
        {
            "category":"Organizations",
            "subcategory":"Professional Association",
            "type":"Services"
        }
    ],
    "sg:phone":"+1 902 662 3290",
    "sg:postcode":"B0M 1G0",
    "sg:province":"NS",
    "sg:tags":[
        "club"
    ],
    "wof:name":"Fundy Trail Snowmobile Club",
    "wof:placetype":"venue"
},
  "geometry": {"coordinates":[-63.4477386475,45.430480957],"type":"Point"}
}