{
  "type": "Feature",
  "properties": {
    "addr:full":"168 Charing Cross St Brantford ON N3R 2J4",
    "addr:housenumber":"168",
    "addr:postcode":"n3r 2j4",
    "addr:street":"Charing Cross St",
    "iso:country":"CA",
    "sg:address":"168 Charing Cross St",
    "sg:city":"Brantford",
    "sg:classifiers":[
        {
            "category":"Restaurant",
            "type":"Food & Drink"
        }
    ],
    "sg:phone":"+1 519 759 1130",
    "sg:postcode":"N3R 2J4",
    "sg:province":"ON",
    "sg:tags":[
        "pizza"
    ],
    "wof:name":"Domino's Pizza",
    "wof:placetype":"venue"
},
  "geometry": {"coordinates":[-80.261253,43.157845],"type":"Point"}
}