{
  "type": "Feature",
  "properties": {
    "addr:full":"15 Greenland Rd North York ON M3C 1N1",
    "addr:housenumber":"15",
    "addr:postcode":"m3c 1n1",
    "addr:street":"Greenland Rd",
    "iso:country":"CA",
    "sg:address":"15 Greenland Rd",
    "sg:city":"North York",
    "sg:classifiers":[
        {
            "category":"Social Services",
            "subcategory":"Child Care",
            "type":"Services"
        }
    ],
    "sg:phone":"+1 416 441 3170",
    "sg:postcode":"M3C 1N1",
    "sg:province":"ON",
    "wof:name":"Playhouse Childcare Ctr Inc",
    "wof:placetype":"venue"
},
  "geometry": {"coordinates":[-79.33795928959999,43.7341041565],"type":"Point"}
}