{
  "type": "Feature",
  "properties": {
    "addr:full":"28 Mill St E Hillsdale ON L0L 1V0",
    "addr:housenumber":"28",
    "addr:postcode":"l0l 1v0",
    "addr:street":"Mill St E",
    "iso:country":"CA",
    "sg:address":"28 Mill St E",
    "sg:city":"Hillsdale",
    "sg:classifiers":[
        {
            "category":"Building & Trades",
            "subcategory":"Construction",
            "type":"Services"
        }
    ],
    "sg:phone":"+1 705 835 2102",
    "sg:postcode":"L0L 1V0",
    "sg:province":"ON",
    "sg:tags":[
        "pavement",
        "sealing"
    ],
    "wof:name":"Paul's Sealing Svc",
    "wof:placetype":"venue"
},
  "geometry": {"coordinates":[-79.757668,44.581879],"type":"Point"}
}