{
  "type": "Feature",
  "properties": {
    "addr:full":"4859 50 St Alix AB T0C 0B0",
    "addr:housenumber":"4859",
    "addr:postcode":"t0c 0b0",
    "addr:street":"50 St",
    "iso:country":"CA",
    "sg:address":"4859 50 St",
    "sg:city":"Alix",
    "sg:classifiers":[
        {
            "category":"Banks & Credit Unions",
            "subcategory":"Bank",
            "type":"Services"
        }
    ],
    "sg:phone":"+1 403 747 2751",
    "sg:postcode":"T0C 0B0",
    "sg:province":"AB",
    "wof:name":"Community Savings",
    "wof:placetype":"venue"
},
  "geometry": {"coordinates":[-113.192978,52.398624],"type":"Point"}
}