{
  "type": "Feature",
  "properties": {
    "addr:full":"74 Rue Principale Parent QC G0X 3P0",
    "addr:housenumber":"74",
    "addr:postcode":"g0x 3p0",
    "addr:street":"Rue Principale",
    "iso:country":"CA",
    "sg:address":"74 Rue Principale",
    "sg:city":"Parent",
    "sg:classifiers":[
        {
            "category":"Autos & Motor Vehicles",
            "subcategory":"Fuel & Gas Station",
            "type":"Retail Goods"
        }
    ],
    "sg:phone":"+1 819 667 2271",
    "sg:postcode":"G0X 3P0",
    "sg:province":"QC",
    "sg:tags":[
        "oil"
    ],
    "wof:name":"Gaz Bar Parent",
    "wof:placetype":"venue"
},
  "geometry": {"coordinates":[-74.624130249,47.92004776],"type":"Point"}
}