{
  "type": "Feature",
  "properties": {
    "addr:full":"102 Station Rd Labrador City NL A2V 2X9",
    "addr:housenumber":"102",
    "addr:postcode":"a2v 2x9",
    "addr:street":"Station Rd",
    "iso:country":"CA",
    "sg:address":"102 Station Rd",
    "sg:city":"Labrador City",
    "sg:classifiers":[
        {
            "category":"Wholesale",
            "subcategory":"Machinery & Supplies",
            "type":"Manufacturing & Wholesale Goods"
        }
    ],
    "sg:phone":"+1 709 944 7641",
    "sg:postcode":"A2V 2X9",
    "sg:province":"NL",
    "sg:tags":[
        "contractor"
    ],
    "wof:name":"Strongco Equipment",
    "wof:placetype":"venue"
},
  "geometry": {"coordinates":[-66.8968658447,52.9459838867],"type":"Point"}
}