{
  "type": "Feature",
  "properties": {
    "addr:full":"85 Crois Roxton Montreal-Ouest QC H4X 1C7",
    "addr:housenumber":"85",
    "addr:postcode":"h4x 1c7",
    "addr:street":"Crois;Montreal-Ouest",
    "iso:country":"CA",
    "sg:address":"85 Crois Roxton",
    "sg:city":"Montreal-Ouest",
    "sg:classifiers":[
        {
            "category":"Health Services",
            "subcategory":"Health Practitioner",
            "type":"Services"
        }
    ],
    "sg:phone":"+1 514 483 4621",
    "sg:postcode":"H4X 1C7",
    "sg:province":"QC",
    "sg:tags":[
        "psychologist"
    ],
    "wof:name":"Distress Center",
    "wof:placetype":"venue"
},
  "geometry": {"coordinates":[-73.657585,45.45467],"type":"Point"}
}