{
  "type": "Feature",
  "properties": {
    "addr:full":"1880 Rue Sainte-Marie Pohenegamook QC G0L 1J0",
    "addr:housenumber":"1880",
    "addr:postcode":"g0l 1j0",
    "addr:street":"Rue Sainte-Marie",
    "iso:country":"CA",
    "sg:address":"1880 Rue Sainte-Marie",
    "sg:city":"Pohenegamook",
    "sg:classifiers":[
        {
            "category":"Home & Garden",
            "subcategory":"Hardware",
            "type":"Retail Goods"
        }
    ],
    "sg:phone":"+1 418 859 2568",
    "sg:postcode":"G0L 1J0",
    "sg:province":"QC",
    "wof:name":"Quincaillerie Mario Lapointe",
    "wof:placetype":"venue"
},
  "geometry": {"coordinates":[-69.278542,47.487152],"type":"Point"}
}