{
  "type": "Feature",
  "properties": {
    "addr:full":"Saint-Pie QC J0H 1W0",
    "addr:postcode":"j0h 1w0",
    "iso:country":"CA",
    "sg:city":"Saint-Pie",
    "sg:classifiers":[
        {
            "category":"Manufacturing",
            "subcategory":"Furniture",
            "type":"Manufacturing & Wholesale Goods"
        }
    ],
    "sg:phone":"+1 450 772 6208",
    "sg:postcode":"J0H 1W0",
    "sg:province":"QC",
    "wof:name":"Meubles Lt Enr",
    "wof:placetype":"venue"
},
  "geometry": {"coordinates":[-72.9052581787,45.5027389526],"type":"Point"}
}