{
  "type": "Feature",
  "properties": {
    "addr:full":"222 Victoria St Niagara on the Lake ON L0S 1J0",
    "addr:housenumber":"222",
    "addr:postcode":"l0s 1j0",
    "addr:street":"Victoria St;On",
    "iso:country":"CA",
    "sg:address":"222 Victoria St",
    "sg:city":"Niagara on the Lake",
    "sg:classifiers":[
        {
            "category":"Organizations",
            "subcategory":"Religious Organization",
            "type":"Services"
        }
    ],
    "sg:phone":"+1 905 468 4044",
    "sg:postcode":"L0S 1J0",
    "sg:province":"ON",
    "sg:tags":[
        "church"
    ],
    "wof:name":"Grace United Church",
    "wof:placetype":"venue"
},
  "geometry": {"coordinates":[-79.0742645264,43.2556877136],"type":"Point"}
}