{
  "type": "Feature",
  "properties": {
    "addr:full":"Edmonton AB T5G 3A6",
    "addr:postcode":"t5g 3a6",
    "iso:country":"CA",
    "sg:city":"Edmonton",
    "sg:classifiers":[
        {
            "category":"Shopping",
            "subcategory":"Computers & Home Electronics",
            "type":"Retail Goods"
        }
    ],
    "sg:phone":"+1 780 477 1055",
    "sg:postcode":"T5G 3A6",
    "sg:province":"AB",
    "sg:tags":[
        "television",
        "radio"
    ],
    "wof:name":"Sony Store",
    "wof:placetype":"venue"
},
  "geometry": {"coordinates":[-113.490371704,53.5462188721],"type":"Point"}
}