{
  "type": "Feature",
  "properties": {
    "addr:full":"381 Rte Principale Wentworth-Nord QC J0T 1Y0",
    "addr:housenumber":"381",
    "addr:postcode":"j0t 1y0",
    "addr:street":"Rte Principale",
    "iso:country":"CA",
    "sg:address":"381 Rte Principale",
    "sg:city":"Wentworth-Nord",
    "sg:classifiers":[
        {
            "category":"Wholesale",
            "subcategory":"Meat",
            "type":"Manufacturing & Wholesale Goods"
        }
    ],
    "sg:phone":"+1 450 226 1411",
    "sg:postcode":"J0T 1Y0",
    "sg:province":"QC",
    "sg:tags":[
        "grocer",
        "butchering"
    ],
    "wof:name":"Boucherie Laurentienne Ltee",
    "wof:placetype":"venue"
},
  "geometry": {"coordinates":[-74.34539794920001,45.8889198303],"type":"Point"}
}