{
  "type": "Feature",
  "properties": {
    "addr:full":"501 1st Ave E Assiniboia SK S0H 0B0",
    "addr:housenumber":"501",
    "addr:postcode":"s0h 0b0",
    "addr:street":"1St Ave E Assiniboia",
    "iso:country":"CA",
    "sg:address":"501 1st Ave E",
    "sg:city":"Assiniboia",
    "sg:classifiers":[
        {
            "category":"Retail",
            "subcategory":"Repair Shop",
            "type":"Services"
        }
    ],
    "sg:phone":"+1 306 642 4786",
    "sg:postcode":"S0H 0B0",
    "sg:province":"SK",
    "sg:tags":[
        "welding"
    ],
    "wof:name":"M & S Welding Ltd",
    "wof:placetype":"venue"
},
  "geometry": {"coordinates":[-105.99627700000001,49.633991],"type":"Point"}
}