{
  "type": "Feature",
  "properties": {
    "addr:full":"Burin Bay Arm NL A0E 1G0",
    "addr:postcode":"a0e 1g0",
    "addr:street":"Burin Bay",
    "iso:country":"CA",
    "sg:city":"Burin Bay Arm",
    "sg:classifiers":[
        {
            "category":"Restaurant",
            "type":"Food & Drink"
        }
    ],
    "sg:phone":"+1 709 891 2880",
    "sg:postcode":"A0E 1G0",
    "sg:province":"NL",
    "wof:name":"Lucky House Restaurant",
    "wof:placetype":"venue"
},
  "geometry": {"coordinates":[-55.1766052246,47.0617828369],"type":"Point"}
}