{
  "type": "Feature",
  "properties": {
    "addr:full":"8780 Boul Saint-Laurent Montreal QC H2N 1M4",
    "addr:housenumber":"8780",
    "addr:postcode":"h2n 1m4",
    "addr:street":"Boul Saint-Laurent",
    "iso:country":"CA",
    "sg:address":"8780 Boul Saint-Laurent",
    "sg:city":"Montreal",
    "sg:classifiers":[
        {
            "category":"Wholesale",
            "subcategory":"Electrical",
            "type":"Manufacturing & Wholesale Goods"
        }
    ],
    "sg:phone":"+1 514 722 4694",
    "sg:postcode":"H2N 1M4",
    "sg:province":"QC",
    "sg:tags":[
        "equipment",
        "electronic",
        "supply"
    ],
    "wof:name":"Via Distributions Inc",
    "wof:placetype":"venue"
},
  "geometry": {"coordinates":[-73.64325714109999,45.5420150757],"type":"Point"}
}