{
  "type": "Feature",
  "properties": {
    "addr:full":"Sioux Narrows ON P0X 1N0",
    "addr:postcode":"p0x 1n0",
    "iso:country":"CA",
    "sg:city":"Sioux Narrows",
    "sg:classifiers":[
        {
            "category":"Travel",
            "subcategory":"Hotels & Motels",
            "type":"Entertainment"
        }
    ],
    "sg:phone":"+1 807 226 5622",
    "sg:postcode":"P0X 1N0",
    "sg:province":"ON",
    "sg:tags":[
        "resort"
    ],
    "wof:name":"Tomahawk Resort",
    "wof:placetype":"venue"
},
  "geometry": {"coordinates":[-94.075684,49.400116],"type":"Point"}
}