{
  "type": "Feature",
  "properties": {
    "iso:country":"CA",
    "sg:address":"950 Walkers Line",
    "sg:city":"Burlington",
    "sg:classifiers":[
        {
            "category":"Travel",
            "subcategory":"Hotels & Motels",
            "type":"Entertainment"
        }
    ],
    "sg:phone":"+1 905 639 9290",
    "sg:postcode":"L7N 2G2",
    "sg:province":"ON",
    "wof:name":"Travelodge Burlington",
    "wof:placetype":"venue"
},
  "geometry": {"coordinates":[-79.819786,43.393822],"type":"Point"}
}