{
  "type": "Feature",
  "properties": {
    "addr:full":"7800 7E Av Laval QC H7R 2Z9",
    "addr:housenumber":"7800",
    "addr:postcode":"h7r 2z9",
    "addr:street":"7E Av",
    "iso:country":"CA",
    "sg:address":"7800 7E Av",
    "sg:city":"Laval",
    "sg:classifiers":[
        {
            "category":"Wholesale",
            "subcategory":"Hardware",
            "type":"Manufacturing & Wholesale Goods"
        }
    ],
    "sg:phone":"+1 450 962 7868",
    "sg:postcode":"H7R 2Z9",
    "sg:province":"QC",
    "sg:tags":[
        "refrigerating"
    ],
    "wof:name":"Services Benoit Lapierre Inc",
    "wof:placetype":"venue"
},
  "geometry": {"coordinates":[-73.8746643066,45.5358543396],"type":"Point"}
}