{
  "type": "Feature",
  "properties": {
    "addr:full":"745 Av Newton Quebec QC G1P 4C4",
    "addr:postcode":"g1p 4c4",
    "addr:street":"745 Av Newton",
    "iso:country":"CA",
    "sg:address":"745 Av Newton",
    "sg:city":"Quebec",
    "sg:classifiers":[
        {
            "category":"Home & Garden",
            "subcategory":"Furniture",
            "type":"Retail Goods"
        }
    ],
    "sg:phone":"+1 418 872 9981",
    "sg:postcode":"G1P 4C4",
    "sg:province":"QC",
    "sg:tags":[
        "hardware",
        "kitchen",
        "cabinet"
    ],
    "wof:name":"Quinko Tek Quebec",
    "wof:placetype":"venue"
},
  "geometry": {"coordinates":[-71.30192599999999,46.802593],"type":"Point"}
}