{
  "type": "Feature",
  "properties": {
    "addr:full":"312 Main St Kinistino SK S0J 1H0",
    "addr:housenumber":"312",
    "addr:postcode":"s0j 1h0",
    "addr:street":"Main St",
    "iso:country":"CA",
    "sg:address":"312 Main St",
    "sg:city":"Kinistino",
    "sg:classifiers":[
        {
            "category":"Wholesale",
            "subcategory":"Electrical",
            "type":"Manufacturing & Wholesale Goods"
        }
    ],
    "sg:phone":"+1 306 864 3366",
    "sg:postcode":"S0J 1H0",
    "sg:province":"SK",
    "sg:tags":[
        "alarm",
        "burglar",
        "system"
    ],
    "wof:name":"Aps Security Systems",
    "wof:placetype":"venue"
},
  "geometry": {"coordinates":[-105.034218,52.951115],"type":"Point"}
}