{
  "type": "Feature",
  "properties": {
    "addr:full":"155 Rue Notre-Dame Repentigny QC J6A 5L3",
    "addr:housenumber":"155",
    "addr:postcode":"j6a 5l3",
    "addr:street":"Rue Notre-Dame",
    "iso:country":"CA",
    "sg:address":"155 Rue Notre-Dame",
    "sg:city":"Repentigny",
    "sg:classifiers":[
        {
            "category":"Banks & Credit Unions",
            "subcategory":"Bank",
            "type":"Services"
        }
    ],
    "sg:phone":"+1 450 585 5900",
    "sg:postcode":"J6A 5L3",
    "sg:province":"QC",
    "wof:name":"Banque Nationale Du Canada",
    "wof:placetype":"venue"
},
  "geometry": {"coordinates":[-73.470169,45.717484],"type":"Point"}
}