{
  "type": "Feature",
  "properties": {
    "addr:full":"368 Drew St Woodstock ON N4S 4V2",
    "addr:housenumber":"368",
    "addr:postcode":"n4s 4v2",
    "addr:street":"Drew St",
    "iso:country":"CA",
    "sg:address":"368 Drew St",
    "sg:city":"Woodstock",
    "sg:classifiers":[
        {
            "category":"Wholesale",
            "subcategory":"Office Equipment",
            "type":"Manufacturing & Wholesale Goods"
        }
    ],
    "sg:phone":"+1 519 539 9394",
    "sg:postcode":"N4S 4V2",
    "sg:province":"ON",
    "sg:tags":[
        "accounting",
        "bookkeeping",
        "system"
    ],
    "wof:name":"Alert Tax Svc & Bookkeeping",
    "wof:placetype":"venue"
},
  "geometry": {"coordinates":[-80.76316799999999,43.134342],"type":"Point"}
}