{
  "type": "Feature",
  "properties": {
    "addr:full":"106 Ashbury Crt London ON N6E 3T5",
    "addr:housenumber":"106",
    "addr:postcode":"n6e 3t5",
    "addr:street":"Ashbury Crt",
    "iso:country":"CA",
    "sg:address":"106 Ashbury Crt",
    "sg:city":"London",
    "sg:classifiers":[
        {
            "category":"Manufacturing",
            "subcategory":"Signs",
            "type":"Manufacturing & Wholesale Goods"
        }
    ],
    "sg:phone":"+1 519 681 1087",
    "sg:postcode":"N6E 3T5",
    "sg:province":"ON",
    "sg:tags":[
        "automobile",
        "detail",
        "clean"
    ],
    "wof:name":"Auto Trim Design of Lambton",
    "wof:placetype":"venue"
},
  "geometry": {"coordinates":[-81.20327,42.937103],"type":"Point"}
}