{
  "type": "Feature",
  "properties": {
    "addr:full":"4714 Hwy 2 E Belleville ON K8N 4Z4",
    "addr:housenumber":"4714",
    "addr:postcode":"k8n 4z4",
    "addr:street":"Hwy 2 E",
    "iso:country":"CA",
    "sg:address":"4714 Hwy 2 E",
    "sg:city":"Belleville",
    "sg:classifiers":[
        {
            "category":"Mining & Drilling",
            "type":"Manufacturing & Wholesale Goods"
        }
    ],
    "sg:phone":"+1 613 967 4210",
    "sg:postcode":"K8N 4Z4",
    "sg:province":"ON",
    "sg:tags":[
        "quarry"
    ],
    "wof:name":"Lafarge Canada Inc",
    "wof:placetype":"venue"
},
  "geometry": {"coordinates":[-77.2840042114,44.1778411865],"type":"Point"}
}