{
  "type": "Feature",
  "properties": {
    "addr:full":"9919 Fairmount Dr SE Calgary AB T2J 0S3",
    "addr:housenumber":"9919",
    "addr:postcode":"t2j 0s3",
    "addr:street":"Fairmount Dr Se",
    "iso:country":"CA",
    "sg:address":"9919 Fairmount Dr SE",
    "sg:city":"Calgary",
    "sg:classifiers":[
        {
            "category":"Shopping",
            "subcategory":"Used Merchandise",
            "type":"Retail Goods"
        }
    ],
    "sg:phone":"+1 403 225 0087",
    "sg:postcode":"T2J 0S3",
    "sg:province":"AB",
    "sg:tags":[
        "clothing"
    ],
    "wof:name":"Salvation Army Thrift Stores",
    "wof:placetype":"venue"
},
  "geometry": {"coordinates":[-114.058846,50.963337],"type":"Point"}
}