{
  "type": "Feature",
  "properties": {
    "addr:full":"274 66 St Delta BC V4L 1M8",
    "addr:housenumber":"66",
    "addr:postcode":"v4l 1m8",
    "addr:street":"274",
    "iso:country":"CA",
    "sg:address":"274 66 St",
    "sg:city":"Delta",
    "sg:classifiers":[
        {
            "category":"Professional",
            "subcategory":"Computer Services",
            "type":"Services"
        }
    ],
    "sg:phone":"+1 604 948 1553",
    "sg:postcode":"V4L 1M8",
    "sg:province":"BC",
    "sg:tags":[
        "consultant",
        "designer",
        "software"
    ],
    "wof:name":"Angus Software Engineering",
    "wof:placetype":"venue"
},
  "geometry": {"coordinates":[-123.040939331,49.0075378418],"type":"Point"}
}