{
  "type": "Feature",
  "properties": {
    "iso:country":"CA",
    "sg:address":"5142 Boul Bourque",
    "sg:city":"Rock Forest",
    "sg:classifiers":[
        {
            "category":"Wholesale",
            "subcategory":"Electrical",
            "type":"Manufacturing & Wholesale Goods"
        }
    ],
    "sg:phone":"+1 819 820 8080",
    "sg:postcode":"J1N 2K7",
    "sg:province":"QC",
    "sg:tags":[
        "control"
    ],
    "wof:name":"Nsw Controle Inc",
    "wof:placetype":"venue"
},
  "geometry": {"coordinates":[-71.993294,45.368103],"type":"Point"}
}