{
  "type": "Feature",
  "properties": {
    "addr:full":"136 Rue Gaspard S Joliette QC J6E 5V3",
    "addr:housenumber":"136",
    "addr:postcode":"j6e 5v3",
    "addr:street":"Rue Gaspard S",
    "iso:country":"CA",
    "sg:address":"136 Rue Gaspard S",
    "sg:city":"Joliette",
    "sg:classifiers":[
        {
            "category":"Home & Garden",
            "subcategory":"Carpets & Floor Coverings",
            "type":"Retail Goods"
        }
    ],
    "sg:phone":"+1 450 755 3177",
    "sg:postcode":"J6E 5V3",
    "sg:province":"QC",
    "sg:tags":[
        "dealer",
        "rug"
    ],
    "wof:name":"Centre DE Liquidation DE Tapis",
    "wof:placetype":"venue"
},
  "geometry": {"coordinates":[-73.4429016113,46.0204277039],"type":"Point"}
}