{
  "type": "Feature",
  "properties": {
    "addr:full":"Front St Archerwill SK S0E 0B0",
    "addr:postcode":"s0e 0b0",
    "addr:street":"Front St",
    "iso:country":"CA",
    "sg:address":"Front St",
    "sg:city":"Archerwill",
    "sg:classifiers":[
        {
            "category":"Shopping",
            "type":"Retail Goods"
        }
    ],
    "sg:phone":"+1 306 323 2004",
    "sg:postcode":"S0E 0B0",
    "sg:province":"SK",
    "sg:tags":[
        "monument"
    ],
    "wof:name":"Bouchard Monuments",
    "wof:placetype":"venue"
},
  "geometry": {"coordinates":[-103.861022949,52.4420585632],"type":"Point"}
}