{
  "type": "Feature",
  "properties": {
    "addr:full":"York ON M9N 3V1",
    "addr:postcode":"m9n 3v1",
    "iso:country":"CA",
    "sg:city":"York",
    "sg:classifiers":[
        {
            "category":"Autos & Motor Vehicles",
            "subcategory":"Auto Supplies",
            "type":"Retail Goods"
        }
    ],
    "sg:phone":"+1 416 242 9898",
    "sg:postcode":"M9N 3V1",
    "sg:province":"ON",
    "sg:tags":[
        "grill",
        "guard",
        "bumper",
        "automobile"
    ],
    "wof:name":"Delta Automotive Supply",
    "wof:placetype":"venue"
},
  "geometry": {"coordinates":[-79.5113601685,43.7011184692],"type":"Point"}
}