{
  "type": "Feature",
  "properties": {
    "iso:country":"CA",
    "sg:city":"Mississauga",
    "sg:classifiers":[
        {
            "category":"Building & Trades",
            "subcategory":"Pest Control",
            "type":"Services"
        }
    ],
    "sg:phone":"+1 905 849 8918",
    "sg:postcode":"L5L 5M6",
    "sg:province":"ON",
    "wof:name":"Abell Pest Control Inc",
    "wof:placetype":"venue"
},
  "geometry": {"coordinates":[-79.68938446040001,43.5186347961],"type":"Point"}
}