{
  "type": "Feature",
  "properties": {
    "addr:full":"115 Fleming Rd Guelph ON N1E 6X5",
    "addr:housenumber":"115",
    "addr:postcode":"n1e 6x5",
    "addr:street":"Fleming Rd",
    "iso:country":"CA",
    "sg:address":"115 Fleming Rd",
    "sg:city":"Guelph",
    "sg:classifiers":[
        {
            "category":"Organizations",
            "subcategory":"Community Association",
            "type":"Services"
        }
    ],
    "sg:phone":"+1 519 836 1366",
    "sg:postcode":"N1E 6X5",
    "sg:province":"ON",
    "sg:tags":[
        "club"
    ],
    "wof:name":"German Canadian Club Guelph",
    "wof:placetype":"venue"
},
  "geometry": {"coordinates":[-80.215446,43.568981],"type":"Point"}
}