{
  "type": "Feature",
  "properties": {
    "addr:full":"844 Don Mills Rd North York ON M3C 1V7",
    "addr:housenumber":"844",
    "addr:postcode":"m3c 1v7",
    "addr:street":"Don Mills Rd",
    "iso:country":"CA",
    "sg:address":"844 Don Mills Rd",
    "sg:city":"North York",
    "sg:classifiers":[
        {
            "category":"Manufacturing",
            "subcategory":"Electronics",
            "type":"Manufacturing & Wholesale Goods"
        }
    ],
    "sg:phone":"+1 416 448 5800",
    "sg:postcode":"M3C 1V7",
    "sg:province":"ON",
    "sg:tags":[
        "equipment",
        "electronic",
        "supply"
    ],
    "wof:name":"Celestica Inc",
    "wof:placetype":"venue"
},
  "geometry": {"coordinates":[-79.3397521973,43.722618103],"type":"Point"}
}