{
  "type": "Feature",
  "properties": {
    "addr:full":"Brockville ON K6V 3P7",
    "addr:postcode":"k6v 3p7",
    "iso:country":"CA",
    "sg:city":"Brockville",
    "sg:classifiers":[
        {
            "category":"Real Estate",
            "subcategory":"Developer",
            "type":"Services"
        }
    ],
    "sg:phone":"+1 613 345 3266",
    "sg:postcode":"K6V 3P7",
    "sg:province":"ON",
    "wof:name":"Brockmoor Development Corp Ltd",
    "wof:placetype":"venue"
},
  "geometry": {"coordinates":[-75.68393707280001,44.5896492004],"type":"Point"}
}