{
  "type": "Feature",
  "properties": {
    "addr:full":"377 Olivewood Rd Etobicoke ON M8Z 2Z8",
    "addr:housenumber":"377",
    "addr:postcode":"m8z 2z8",
    "addr:street":"Olivewood Rd",
    "iso:country":"CA",
    "sg:address":"377 Olivewood Rd",
    "sg:city":"Etobicoke",
    "sg:classifiers":[
        {
            "category":"Wholesale",
            "subcategory":"Meat",
            "type":"Manufacturing & Wholesale Goods"
        }
    ],
    "sg:phone":"+1 416 239 4187",
    "sg:postcode":"M8Z 2Z8",
    "sg:province":"ON",
    "sg:tags":[
        "packer"
    ],
    "wof:name":"West End Meat Packers Ltd",
    "wof:placetype":"venue"
},
  "geometry": {"coordinates":[-79.5312042236,43.6357154846],"type":"Point"}
}