{
  "type": "Feature",
  "properties": {
    "addr:full":"210 Ambassador Dr Mississauga ON L5T 2J2",
    "addr:housenumber":"210",
    "addr:postcode":"l5t 2j2",
    "addr:street":"Ambassador Dr",
    "iso:country":"CA",
    "sg:address":"210 Ambassador Dr",
    "sg:city":"Mississauga",
    "sg:classifiers":[
        {
            "category":"Restaurant",
            "type":"Food & Drink"
        }
    ],
    "sg:phone":"+1 905 670 2290",
    "sg:postcode":"L5T 2J2",
    "sg:province":"ON",
    "sg:tags":[
        "caterer"
    ],
    "wof:name":"Royal Town Foods Inc",
    "wof:placetype":"venue"
},
  "geometry": {"coordinates":[-79.692635,43.642181],"type":"Point"}
}