{
  "type": "Feature",
  "properties": {
    "addr:full":"Toronto ON M5R 1C1",
    "addr:postcode":"m5r 1c1",
    "iso:country":"CA",
    "sg:city":"Toronto",
    "sg:classifiers":[
        {
            "category":"Health Services",
            "subcategory":"Optometrist",
            "type":"Services"
        }
    ],
    "sg:phone":"+1 416 968 2300",
    "sg:postcode":"M5R 1C1",
    "sg:province":"ON",
    "wof:name":"Skrapits, Linda OD",
    "wof:placetype":"venue"
},
  "geometry": {"coordinates":[-79.3922119141,43.6707801819],"type":"Point"}
}