{
  "type": "Feature",
  "properties": {
    "addr:full":"Shedden ON N0L 2E0",
    "addr:postcode":"n0l 2e0",
    "iso:country":"CA",
    "sg:city":"Shedden",
    "sg:classifiers":[
        {
            "category":"Personal",
            "subcategory":"Beauty Salon",
            "type":"Services"
        }
    ],
    "sg:phone":"+1 519 764 2287",
    "sg:postcode":"N0L 2E0",
    "sg:province":"ON",
    "wof:name":"Village Square Salon",
    "wof:placetype":"venue"
},
  "geometry": {"coordinates":[-81.3154220581,42.7702293396],"type":"Point"}
}