{
  "type": "Feature",
  "properties": {
    "iso:country":"CA",
    "sg:city":"Victoria",
    "sg:classifiers":[
        {
            "category":"Personal",
            "subcategory":"Beauty Salon",
            "type":"Services"
        }
    ],
    "sg:phone":"+1 250 472 7521",
    "sg:postcode":"V8W 3P3",
    "sg:province":"BC",
    "wof:name":"On the Fringe Hair Design",
    "wof:placetype":"venue"
},
  "geometry": {"coordinates":[-123.364532471,48.4283103943],"type":"Point"}
}