{
  "type": "Feature",
  "properties": {
    "addr:full":"6197 136 St Surrey BC V3X 1H4",
    "addr:housenumber":"6197",
    "addr:postcode":"v3x 1h4",
    "addr:street":"136 St",
    "iso:country":"CA",
    "sg:address":"6197 136 St",
    "sg:city":"Surrey",
    "sg:classifiers":[
        {
            "category":"Shopping",
            "subcategory":"Used Merchandise",
            "type":"Retail Goods"
        }
    ],
    "sg:phone":"+1 604 590 8290",
    "sg:postcode":"V3X 1H4",
    "sg:province":"BC",
    "sg:tags":[
        "shop",
        "consignment"
    ],
    "wof:name":"Classic Closet",
    "wof:placetype":"venue"
},
  "geometry": {"coordinates":[-122.845497131,49.1152801514],"type":"Point"}
}