{
  "type": "Feature",
  "properties": {
    "addr:full":"44 Donald St Barrie ON L4N 1E3",
    "addr:housenumber":"44",
    "addr:postcode":"l4n 1e3",
    "addr:street":"Donald St",
    "iso:country":"CA",
    "sg:address":"44 Donald St",
    "sg:city":"Barrie",
    "sg:classifiers":[
        {
            "category":"Health Services",
            "subcategory":"Nursing And Care Facility",
            "type":"Services"
        }
    ],
    "sg:phone":"+1 705 722 5750",
    "sg:postcode":"L4N 1E3",
    "sg:province":"ON",
    "sg:tags":[
        "home",
        "retirement",
        "community"
    ],
    "wof:name":"Simcoe Terrace",
    "wof:placetype":"venue"
},
  "geometry": {"coordinates":[-79.70169799999999,44.386978],"type":"Point"}
}