{
  "type": "Feature",
  "properties": {
    "addr:full":"Canmore AB T1W 1P1",
    "addr:postcode":"t1w 1p1",
    "iso:country":"CA",
    "sg:city":"Canmore",
    "sg:classifiers":[
        {
            "category":"Government",
            "subcategory":"Jail",
            "type":"Public Place"
        }
    ],
    "sg:phone":"+1 403 678 4843",
    "sg:postcode":"T1W 1P1",
    "sg:province":"AB",
    "sg:tags":[
        "provincial",
        "institution"
    ],
    "wof:name":"Alberta Community Corrections",
    "wof:placetype":"venue"
},
  "geometry": {"coordinates":[-115.351562,51.088741],"type":"Point"}
}