{
  "type": "Feature",
  "properties": {
    "addr:full":"103 Albion St S Amherst NS B4H 2X2",
    "addr:housenumber":"103",
    "addr:postcode":"b4h 2x2",
    "addr:street":"Albion St S",
    "iso:country":"CA",
    "sg:address":"103 Albion St S",
    "sg:city":"Amherst",
    "sg:classifiers":[
        {
            "category":"Shopping",
            "subcategory":"Computers & Home Electronics",
            "type":"Retail Goods"
        }
    ],
    "sg:phone":"+1 902 661 0941",
    "sg:postcode":"B4H 2X2",
    "sg:province":"NS",
    "sg:tags":[
        "equipment",
        "dealer"
    ],
    "wof:name":"Fcs Technology",
    "wof:placetype":"venue"
},
  "geometry": {"coordinates":[-64.20556640620001,45.8183670044],"type":"Point"}
}