{
  "type": "Feature",
  "properties": {
    "addr:full":"10 Oyler Dr Port Perry ON L9L 1B3",
    "addr:housenumber":"10",
    "addr:postcode":"l9l 1b3",
    "addr:street":"Oyler Dr",
    "iso:country":"CA",
    "sg:address":"10 Oyler Dr",
    "sg:city":"Port Perry",
    "sg:classifiers":[
        {
            "category":"Recreation",
            "subcategory":"Marina",
            "type":"Entertainment"
        }
    ],
    "sg:phone":"+1 905 985 3192",
    "sg:postcode":"L9L 1B3",
    "sg:province":"ON",
    "wof:name":"Maximum Marine Svc Ltd",
    "wof:placetype":"venue"
},
  "geometry": {"coordinates":[-78.93885,44.086926],"type":"Point"}
}