{
  "type": "Feature",
  "properties": {
    "addr:full":"Aylmer QC J9H 6N7",
    "addr:postcode":"j9h 6n7",
    "iso:country":"CA",
    "sg:city":"Aylmer",
    "sg:classifiers":[
        {
            "category":"Retail",
            "subcategory":"Auto Repair",
            "type":"Services"
        }
    ],
    "sg:phone":"+1 819 684 3841",
    "sg:postcode":"J9H 6N7",
    "sg:province":"QC",
    "sg:tags":[
        "repairing",
        "automobile"
    ],
    "wof:name":"Euro J & P",
    "wof:placetype":"venue"
},
  "geometry": {"coordinates":[-75.855194,45.398659],"type":"Point"}
}