{
  "type": "Feature",
  "properties": {
    "addr:full":"Burnaby BC V3N 1B8",
    "addr:postcode":"v3n 1b8",
    "iso:country":"CA",
    "sg:city":"Burnaby",
    "sg:classifiers":[
        {
            "category":"Building & Trades",
            "subcategory":"Construction",
            "type":"Services"
        }
    ],
    "sg:phone":"+1 604 524 9701",
    "sg:postcode":"V3N 1B8",
    "sg:province":"BC",
    "sg:tags":[
        "steel"
    ],
    "wof:name":"Paramount Detailing Svc Ltd",
    "wof:placetype":"venue"
},
  "geometry": {"coordinates":[-122.937843,49.225605],"type":"Point"}
}