{
  "type": "Feature",
  "properties": {
    "addr:full":"794 Easy St Pembroke ON K8A 7C8",
    "addr:housenumber":"794",
    "addr:postcode":"k8a 7c8",
    "addr:street":"Easy St",
    "iso:country":"CA",
    "sg:address":"794 Easy St",
    "sg:city":"Pembroke",
    "sg:classifiers":[
        {
            "category":"Food & Beverages",
            "subcategory":"Groceries & Convenience Stores",
            "type":"Retail Goods"
        }
    ],
    "sg:phone":"+1 613 735 5079",
    "sg:postcode":"K8A 7C8",
    "sg:province":"ON",
    "sg:tags":[
        "grocer"
    ],
    "wof:name":"Bayview Grocery",
    "wof:placetype":"venue"
},
  "geometry": {"coordinates":[-77.112213,45.826481],"type":"Point"}
}