{
  "type": "Feature",
  "properties": {
    "addr:full":"Laval QC H7V 1B1",
    "addr:postcode":"h7v 1b1",
    "iso:country":"CA",
    "sg:city":"Laval",
    "sg:classifiers":[
        {
            "category":"Shopping",
            "subcategory":"Pharmacy",
            "type":"Retail Goods"
        }
    ],
    "sg:phone":"+1 450 688 0016",
    "sg:postcode":"H7V 1B1",
    "sg:province":"QC",
    "wof:name":"Pharmacie Hoang NM",
    "wof:placetype":"venue"
},
  "geometry": {"coordinates":[-73.725998,45.537773],"type":"Point"}
}