{
  "type": "Feature",
  "properties": {
    "addr:full":"8757 Armstrong Ave Burnaby BC V3N 2H8",
    "addr:housenumber":"8757",
    "addr:postcode":"v3n 2h8",
    "addr:street":"Armstrong Ave",
    "iso:country":"CA",
    "sg:address":"8757 Armstrong Ave",
    "sg:city":"Burnaby",
    "sg:classifiers":[
        {
            "category":"Education",
            "subcategory":"School",
            "type":"Public Place"
        }
    ],
    "sg:phone":"+1 604 664 8587",
    "sg:postcode":"V3N 2H8",
    "sg:province":"BC",
    "wof:name":"Armstrong Elementary",
    "wof:placetype":"venue"
},
  "geometry": {"coordinates":[-122.907447815,49.2339706421],"type":"Point"}
}