{
  "type": "Feature",
  "properties": {
    "addr:full":"333 Boul Cure Labelle Sainte-Therese QC J7E 2Y2",
    "addr:housenumber":"333",
    "addr:postcode":"j7e 2y2",
    "addr:street":"Boul Cure",
    "iso:country":"CA",
    "sg:address":"333 Boul Cure Labelle",
    "sg:city":"Sainte-Therese",
    "sg:classifiers":[
        {
            "category":"Retail",
            "subcategory":"Auto Repair",
            "type":"Services"
        }
    ],
    "sg:phone":"+1 450 433 7174",
    "sg:postcode":"J7E 2Y2",
    "sg:province":"QC",
    "sg:tags":[
        "muffler",
        "exhaust",
        "system"
    ],
    "wof:name":"Silencieux Gms Inc",
    "wof:placetype":"venue"
},
  "geometry": {"coordinates":[-73.84423099999999,45.640247],"type":"Point"}
}