{
  "type": "Feature",
  "properties": {
    "addr:full":"3610 Nashua Dr Mississauga ON L4V 1L2",
    "addr:housenumber":"3610",
    "addr:postcode":"l4v 1l2",
    "addr:street":"Nashua Dr",
    "iso:country":"CA",
    "sg:address":"3610 Nashua Dr",
    "sg:city":"Mississauga",
    "sg:classifiers":[
        {
            "category":"Freight",
            "type":"Transportation"
        }
    ],
    "sg:phone":"+1 905 671 4022",
    "sg:postcode":"L4V 1L2",
    "sg:province":"ON",
    "sg:tags":[
        "trucking"
    ],
    "wof:name":"1474188 Ont Inc",
    "wof:placetype":"venue"
},
  "geometry": {"coordinates":[-79.626762,43.714542],"type":"Point"}
}