{
  "type": "Feature",
  "properties": {
    "addr:full":"1631 St Mary's Rd Winnipeg MB R2N 1Z4",
    "addr:housenumber":"1631",
    "addr:postcode":"r2n 1z4",
    "addr:street":"St Mary'S Rd",
    "iso:country":"CA",
    "sg:address":"1631 St Mary's Rd",
    "sg:city":"Winnipeg",
    "sg:classifiers":[
        {
            "category":"Organizations",
            "subcategory":"Professional Association",
            "type":"Services"
        }
    ],
    "sg:phone":"+1 204 254 1891",
    "sg:postcode":"R2N 1Z4",
    "sg:province":"MB",
    "wof:name":"Manitoba Used Car Dealers Assn",
    "wof:placetype":"venue"
},
  "geometry": {"coordinates":[-97.11302947999999,49.8200492859],"type":"Point"}
}