{
  "type": "Feature",
  "properties": {
    "addr:full":"Toronto ON M4G 1R8",
    "addr:postcode":"m4g 1r8",
    "iso:country":"CA",
    "sg:city":"Toronto",
    "sg:classifiers":[
        {
            "category":"Food & Beverages",
            "subcategory":"Bakery",
            "type":"Retail Goods"
        }
    ],
    "sg:phone":"+1 416 424 3855",
    "sg:postcode":"M4G 1R8",
    "sg:province":"ON",
    "sg:tags":[
        "tea",
        "coffee",
        "doughnut"
    ],
    "wof:name":"Tim Hortons",
    "wof:placetype":"venue"
},
  "geometry": {"coordinates":[-79.371796,43.717827],"type":"Point"}
}