{
  "type": "Feature",
  "properties": {
    "addr:full":"49 Burwell St Brantford ON N3T 4T5",
    "addr:housenumber":"49",
    "addr:postcode":"n3t 4t5",
    "addr:street":"Burwell St",
    "iso:country":"CA",
    "sg:address":"49 Burwell St",
    "sg:city":"Brantford",
    "sg:classifiers":[
        {
            "category":"Retail",
            "subcategory":"Auto Repair",
            "type":"Services"
        }
    ],
    "sg:phone":"+1 519 756 3815",
    "sg:postcode":"N3T 4T5",
    "sg:province":"ON",
    "sg:tags":[
        "body",
        "automobile",
        "painting"
    ],
    "wof:name":"Auto Quest Auto Painting",
    "wof:placetype":"venue"
},
  "geometry": {"coordinates":[-80.285301,43.145233],"type":"Point"}
}