{
  "type": "Feature",
  "properties": {
    "iso:country":"CA",
    "sg:address":"84 Oakdale Rd",
    "sg:city":"North York",
    "sg:classifiers":[
        {
            "category":"Manufacturing",
            "subcategory":"Food",
            "type":"Manufacturing & Wholesale Goods"
        }
    ],
    "sg:phone":"+1 416 742 6741",
    "sg:postcode":"M3N 1V9",
    "sg:province":"ON",
    "sg:tags":[
        "baker",
        "product",
        "manufacturer"
    ],
    "wof:name":"Capri Bagels & Buns Inc",
    "wof:placetype":"venue"
},
  "geometry": {"coordinates":[-79.5258407593,43.7410774231],"type":"Point"}
}