{
  "type": "Feature",
  "properties": {
    "addr:full":"1027 Gordon St Guelph ON N1G 4X1",
    "addr:housenumber":"1027",
    "addr:postcode":"n1g 4x1",
    "addr:street":"Gordon St",
    "iso:country":"CA",
    "sg:address":"1027 Gordon St",
    "sg:city":"Guelph",
    "sg:classifiers":[
        {
            "category":"Real Estate",
            "subcategory":"Real Estate Agent",
            "type":"Services"
        }
    ],
    "sg:phone":"+1 519 836 1072",
    "sg:postcode":"N1G 4X1",
    "sg:province":"ON",
    "wof:name":"Homelife Realty Ltd",
    "wof:placetype":"venue"
},
  "geometry": {"coordinates":[-80.2101593018,43.5206947327],"type":"Point"}
}