{
  "type": "Feature",
  "properties": {
    "addr:full":"11408 156 St NW Edmonton AB T5M 3N2",
    "addr:housenumber":"11408",
    "addr:postcode":"t5m 3n2",
    "addr:street":"156 St Nw",
    "iso:country":"CA",
    "sg:address":"11408 156 St NW",
    "sg:city":"Edmonton",
    "sg:classifiers":[
        {
            "category":"Building & Trades",
            "subcategory":"Plumbing",
            "type":"Services"
        }
    ],
    "sg:phone":"+1 780 453 3741",
    "sg:postcode":"T5M 3N2",
    "sg:province":"AB",
    "sg:tags":[
        "heating",
        "contractor"
    ],
    "wof:name":"Economy Heating Ltd",
    "wof:placetype":"venue"
},
  "geometry": {"coordinates":[-113.59065200000001,53.563499],"type":"Point"}
}