{
  "type": "Feature",
  "properties": {
    "iso:country":"CA",
    "sg:address":"146 Pownal St",
    "sg:city":"Charlottetown",
    "sg:classifiers":[
        {
            "category":"Travel",
            "subcategory":"Hotels & Motels",
            "type":"Entertainment"
        }
    ],
    "sg:phone":"+1 902 892 1217",
    "sg:postcode":"C1A 3W6",
    "sg:province":"PE",
    "wof:name":"Islander Motor Lodge",
    "wof:placetype":"venue"
},
  "geometry": {"coordinates":[-63.129863739,46.2338523865],"type":"Point"}
}