{
  "type": "Feature",
  "properties": {
    "addr:full":"PO Box 1060 STN Main Penticton BC V2A 6J9",
    "addr:housenumber":"po",
    "addr:postcode":"v2a 6j9",
    "addr:street":"Box 1060 Stn Main",
    "iso:country":"CA",
    "sg:address":"PO Box 1060 STN Main",
    "sg:city":"Penticton",
    "sg:classifiers":[
        {
            "category":"Travel",
            "subcategory":"Hotels & Motels",
            "type":"Entertainment"
        }
    ],
    "sg:phone":"+1 250 487 4848",
    "sg:postcode":"V2A 6J9",
    "sg:province":"BC",
    "sg:tags":[
        "resort",
        "center",
        "skiing"
    ],
    "wof:name":"Apex Mountain Resort Ltd",
    "wof:placetype":"venue"
},
  "geometry": {"coordinates":[-119.593857,49.500229],"type":"Point"}
}