{
  "type": "Feature",
  "properties": {
    "addr:full":"141 Spencer St E Cobourg ON K9A 1C3",
    "addr:housenumber":"141",
    "addr:postcode":"k9a 1c3",
    "addr:street":"Spencer St E",
    "iso:country":"CA",
    "sg:address":"141 Spencer St E",
    "sg:city":"Cobourg",
    "sg:classifiers":[
        {
            "category":"Building & Trades",
            "subcategory":"Cleaning & Sanitation",
            "type":"Services"
        }
    ],
    "sg:phone":"+1 905 372 3295",
    "sg:postcode":"K9A 1C3",
    "sg:province":"ON",
    "sg:tags":[
        "janitor"
    ],
    "wof:name":"Elliott Brothers Window Clng",
    "wof:placetype":"venue"
},
  "geometry": {"coordinates":[-78.162109,43.966549],"type":"Point"}
}