{
  "type": "Feature",
  "properties": {
    "addr:full":"749 Fullerton Ave Victoria BC V9A 3Z9",
    "addr:housenumber":"749",
    "addr:postcode":"v9a 3z9",
    "addr:street":"Fullerton Ave",
    "iso:country":"CA",
    "sg:address":"749 Fullerton Ave",
    "sg:city":"Victoria",
    "sg:classifiers":[
        {
            "category":"Organizations",
            "subcategory":"Religious Organization",
            "type":"Services"
        }
    ],
    "sg:phone":"+1 250 383 6290",
    "sg:postcode":"V9A 3Z9",
    "sg:province":"BC",
    "sg:tags":[
        "church"
    ],
    "wof:name":"Salvation Army",
    "wof:placetype":"venue"
},
  "geometry": {"coordinates":[-123.389488,48.434559],"type":"Point"}
}