{
  "type": "Feature",
  "properties": {
    "addr:full":"Toronto ON M4V 1L5",
    "addr:postcode":"m4v 1l5",
    "iso:country":"CA",
    "sg:city":"Toronto",
    "sg:classifiers":[
        {
            "category":"Shopping",
            "subcategory":"Optical Goods",
            "type":"Retail Goods"
        }
    ],
    "sg:phone":"+1 416 923 9203",
    "sg:postcode":"M4V 1L5",
    "sg:province":"ON",
    "sg:tags":[
        "contact",
        "lense"
    ],
    "wof:name":"Visual Contact",
    "wof:placetype":"venue"
},
  "geometry": {"coordinates":[-79.394592,43.688118],"type":"Point"}
}