{
  "type": "Feature",
  "properties": {
    "addr:full":"11 Russell St Leamington ON N8H 1T7",
    "addr:housenumber":"11",
    "addr:postcode":"n8h 1t7",
    "addr:street":"Russell St",
    "iso:country":"CA",
    "sg:address":"11 Russell St",
    "sg:city":"Leamington",
    "sg:classifiers":[
        {
            "category":"Professional",
            "subcategory":"Accounting & Tax Preparation",
            "type":"Services"
        }
    ],
    "sg:phone":"+1 519 322 2560",
    "sg:postcode":"N8H 1T7",
    "sg:province":"ON",
    "sg:tags":[
        "return",
        "filing"
    ],
    "wof:name":"Financial Centre of Leamington",
    "wof:placetype":"venue"
},
  "geometry": {"coordinates":[-82.600899,42.051445],"type":"Point"}
}