{
  "type": "Feature",
  "properties": {
    "addr:full":"12765 Keele St King City ON L7B 1H5",
    "addr:housenumber":"12765",
    "addr:postcode":"l7b 1h5",
    "addr:street":"Keele St",
    "iso:country":"CA",
    "sg:address":"12765 Keele St",
    "sg:city":"King City",
    "sg:classifiers":[
        {
            "category":"Retail",
            "subcategory":"Auto Repair",
            "type":"Services"
        }
    ],
    "sg:phone":"+1 905 833 6642",
    "sg:postcode":"L7B 1H5",
    "sg:province":"ON",
    "sg:tags":[
        "repairing",
        "automobile"
    ],
    "wof:name":"Clearview Motors",
    "wof:placetype":"venue"
},
  "geometry": {"coordinates":[-79.526321,43.922436],"type":"Point"}
}