{
  "type": "Feature",
  "properties": {
    "addr:full":"2540 Sturdies Bay Rd Galiano BC V0N 1P0",
    "addr:housenumber":"2540",
    "addr:postcode":"v0n 1p0",
    "addr:street":"Sturdies Bay Rd",
    "iso:country":"CA",
    "sg:address":"2540 Sturdies Bay Rd",
    "sg:city":"Galiano",
    "sg:classifiers":[
        {
            "category":"Shopping",
            "subcategory":"Gifts & Souvenirs",
            "type":"Retail Goods"
        }
    ],
    "sg:phone":"+1 250 539 2944",
    "sg:postcode":"V0N 1P0",
    "sg:province":"BC",
    "sg:tags":[
        "shop"
    ],
    "wof:name":"Art & Soul Craft Gallery",
    "wof:placetype":"venue"
},
  "geometry": {"coordinates":[-123.31867981000001,48.8789710999],"type":"Point"}
}