{
  "type": "Feature",
  "properties": {
    "addr:full":"Hangar 9 Bonnyville AB T9N 2H9",
    "addr:postcode":"t9n 2h9",
    "iso:country":"CA",
    "sg:address":"Hangar 9",
    "sg:city":"Bonnyville",
    "sg:classifiers":[
        {
            "category":"Farming",
            "subcategory":"Farm & Veterinary Services",
            "type":"Manufacturing & Wholesale Goods"
        }
    ],
    "sg:phone":"+1 780 826 6885",
    "sg:postcode":"T9N 2H9",
    "sg:province":"AB",
    "sg:tags":[
        "aerial",
        "applicator"
    ],
    "wof:name":"Bonnyville Air Svc Ltd",
    "wof:placetype":"venue"
},
  "geometry": {"coordinates":[-110.75366200000001,54.267956],"type":"Point"}
}