{
  "type": "Feature",
  "properties": {
    "addr:full":"1267 Queen St W Toronto ON M6K 1L5",
    "addr:housenumber":"1267",
    "addr:postcode":"m6k 1l5",
    "addr:street":"Queen St W",
    "iso:country":"CA",
    "sg:address":"1267 Queen St W",
    "sg:city":"Toronto",
    "sg:classifiers":[
        {
            "category":"Shopping",
            "subcategory":"Clothing, Apparel, & Fashions",
            "type":"Retail Goods"
        }
    ],
    "sg:phone":"+1 416 534 0181",
    "sg:postcode":"M6K 1L5",
    "sg:province":"ON",
    "sg:tags":[
        "food",
        "health",
        "diet"
    ],
    "wof:name":"Shop",
    "wof:placetype":"venue"
},
  "geometry": {"coordinates":[-79.43130499999999,43.641537],"type":"Point"}
}