{
  "type": "Feature",
  "properties": {
    "addr:full":"99 Thornton Rd S Oshawa ON L1J 5Y1",
    "addr:housenumber":"99",
    "addr:postcode":"l1j 5y1",
    "addr:street":"Thornton Rd",
    "iso:country":"CA",
    "sg:address":"99 Thornton Rd S",
    "sg:city":"Oshawa",
    "sg:classifiers":[
        {
            "category":"Organizations",
            "subcategory":"Professional Association",
            "type":"Services"
        }
    ],
    "sg:phone":"+1 905 433 0900",
    "sg:postcode":"L1J 5Y1",
    "sg:province":"ON",
    "sg:tags":[
        "club"
    ],
    "wof:name":"Oshawa Generals Junior Hockey",
    "wof:placetype":"venue"
},
  "geometry": {"coordinates":[-78.891846,43.888168],"type":"Point"}
}