{
  "type": "Feature",
  "properties": {
    "addr:full":"11 Huron Dr Leduc AB T9E 4N3",
    "addr:housenumber":"11",
    "addr:postcode":"t9e 4n3",
    "addr:street":"Huron Dr",
    "iso:country":"CA",
    "sg:address":"11 Huron Dr",
    "sg:city":"Leduc",
    "sg:classifiers":[
        {
            "category":"Retail",
            "subcategory":"Repair Shop",
            "type":"Services"
        }
    ],
    "sg:phone":"+1 780 986 4990",
    "sg:postcode":"T9E 4N3",
    "sg:province":"AB",
    "sg:tags":[
        "welding"
    ],
    "wof:name":"Greg's Welding",
    "wof:placetype":"venue"
},
  "geometry": {"coordinates":[-113.551445,53.252296],"type":"Point"}
}