{
  "type": "Feature",
  "properties": {
    "addr:full":"127 Rue Victoria Edmundston NB E3V 2H5",
    "addr:housenumber":"127",
    "addr:postcode":"e3v 2h5",
    "addr:street":"Rue Victoria",
    "iso:country":"CA",
    "sg:address":"127 Rue Victoria",
    "sg:city":"Edmundston",
    "sg:classifiers":[
        {
            "category":"Travel",
            "subcategory":"Hotels & Motels",
            "type":"Entertainment"
        }
    ],
    "sg:phone":"+1 506 735 5567",
    "sg:postcode":"E3V 2H5",
    "sg:province":"NB",
    "wof:name":"Praga Hotel",
    "wof:placetype":"venue"
},
  "geometry": {"coordinates":[-68.321945,47.367393],"type":"Point"}
}