{
  "type": "Feature",
  "properties": {
    "addr:full":"300 Main St Debden SK S0J 0S0",
    "addr:housenumber":"300",
    "addr:postcode":"s0j 0s0",
    "addr:street":"Main St",
    "iso:country":"CA",
    "sg:address":"300 Main St",
    "sg:city":"Debden",
    "sg:classifiers":[
        {
            "category":"Travel",
            "subcategory":"Hotels & Motels",
            "type":"Entertainment"
        }
    ],
    "sg:phone":"+1 306 724 2140",
    "sg:postcode":"S0J 0S0",
    "sg:province":"SK",
    "wof:name":"Debden Hotel",
    "wof:placetype":"venue"
},
  "geometry": {"coordinates":[-106.87822723399999,53.5272254944],"type":"Point"}
}