{
  "type": "Feature",
  "properties": {
    "addr:full":"830 Mcmillan Ave Winnipeg MB R3M 0V4",
    "addr:housenumber":"830",
    "addr:postcode":"r3m 0v4",
    "addr:street":"Mcmillan Ave",
    "iso:country":"CA",
    "sg:address":"830 Mcmillan Ave",
    "sg:city":"Winnipeg",
    "sg:classifiers":[
        {
            "category":"Professional",
            "subcategory":"Computer Services",
            "type":"Services"
        }
    ],
    "sg:phone":"+1 204 478 1603",
    "sg:postcode":"R3M 0V4",
    "sg:province":"MB",
    "sg:tags":[
        "internet"
    ],
    "wof:name":"Internet Media Publications",
    "wof:placetype":"venue"
},
  "geometry": {"coordinates":[-97.158783,49.869862],"type":"Point"}
}