{
  "type": "Feature",
  "properties": {
    "iso:country":"CA",
    "sg:address":"Hwy 93",
    "sg:city":"Jasper",
    "sg:classifiers":[
        {
            "category":"Travel",
            "subcategory":"Hotels & Motels",
            "type":"Entertainment"
        }
    ],
    "sg:phone":"+1 780 852 4852",
    "sg:postcode":"T0E 1E0",
    "sg:province":"AB",
    "wof:name":"Sunwapta Falls Resort Ltd",
    "wof:placetype":"venue"
},
  "geometry": {"coordinates":[-118.072090149,52.8482017517],"type":"Point"}
}