{
  "type": "Feature",
  "properties": {
    "iso:country":"CA",
    "sg:address":"170 Boul Marcel-Laurin",
    "sg:city":"Saint-Laurent",
    "sg:classifiers":[
        {
            "category":"Wholesale",
            "subcategory":"Apparel",
            "type":"Manufacturing & Wholesale Goods"
        }
    ],
    "sg:phone":"+1 514 737 7271",
    "sg:postcode":"H4P 2J5",
    "sg:province":"QC",
    "sg:tags":[
        "shoes"
    ],
    "wof:name":"Black & White Merchandising CO",
    "wof:placetype":"venue"
},
  "geometry": {"coordinates":[-73.671394,45.502918],"type":"Point"}
}