{
  "type": "Feature",
  "properties": {
    "addr:full":"Bruce Mines ON P0R 1C0",
    "addr:postcode":"p0r 1c0",
    "iso:country":"CA",
    "sg:city":"Bruce Mines",
    "sg:classifiers":[
        {
            "category":"Government",
            "subcategory":"Office",
            "type":"Public Place"
        }
    ],
    "sg:phone":"+1 705 785 3493",
    "sg:postcode":"P0R 1C0",
    "sg:province":"ON",
    "sg:tags":[
        "municipality"
    ],
    "wof:name":"Bruce Mines Municipal Office",
    "wof:placetype":"venue"
},
  "geometry": {"coordinates":[-83.78620147709999,46.3000564575],"type":"Point"}
}