{
  "type": "Feature",
  "properties": {
    "addr:full":"7120 76 Ave NW Edmonton AB T6B 0B2",
    "addr:housenumber":"7120",
    "addr:postcode":"t6b 0b2",
    "addr:street":"76 Ave Nw",
    "iso:country":"CA",
    "sg:address":"7120 76 Ave NW",
    "sg:city":"Edmonton",
    "sg:classifiers":[
        {
            "category":"Manufacturing",
            "subcategory":"Tools & Machinery",
            "type":"Manufacturing & Wholesale Goods"
        }
    ],
    "sg:phone":"+1 780 466 2340",
    "sg:postcode":"T6B 0B2",
    "sg:province":"AB",
    "sg:tags":[
        "machine",
        "shop"
    ],
    "wof:name":"Etd Machine Ltd",
    "wof:placetype":"venue"
},
  "geometry": {"coordinates":[-113.437347,53.512527],"type":"Point"}
}