{
  "type": "Feature",
  "properties": {
    "addr:full":"131 Beacon Hill Rd Beaconsfield QC H9W 1S8",
    "addr:housenumber":"131",
    "addr:postcode":"h9w 1s8",
    "addr:street":"Beacon Hill Rd",
    "iso:country":"CA",
    "sg:address":"131 Beacon Hill Rd",
    "sg:city":"Beaconsfield",
    "sg:classifiers":[
        {
            "category":"Real Estate",
            "subcategory":"Real Estate Agent",
            "type":"Services"
        }
    ],
    "sg:phone":"+1 514 693 0255",
    "sg:postcode":"H9W 1S8",
    "sg:province":"QC",
    "sg:tags":[
        "economic",
        "relocation",
        "analysis",
        "research"
    ],
    "wof:name":"Concierges K & P",
    "wof:placetype":"venue"
},
  "geometry": {"coordinates":[-73.8396987915,45.4415054321],"type":"Point"}
}