{
  "type": "Feature",
  "properties": {
    "addr:full":"160 Rue DE LA Station Laval QC H7M 3H7",
    "addr:housenumber":"160",
    "addr:postcode":"h7m 3h7",
    "addr:street":"Rue De La Station",
    "iso:country":"CA",
    "sg:address":"160 Rue DE LA Station",
    "sg:city":"Laval",
    "sg:classifiers":[
        {
            "category":"Wholesale",
            "subcategory":"Auto Parts",
            "type":"Manufacturing & Wholesale Goods"
        }
    ],
    "sg:phone":"+1 450 669 0005",
    "sg:postcode":"H7M 3H7",
    "sg:province":"QC",
    "sg:tags":[
        "automobile",
        "rebuilt"
    ],
    "wof:name":"Auto Vany",
    "wof:placetype":"venue"
},
  "geometry": {"coordinates":[-73.72096252439999,45.588306427],"type":"Point"}
}