{
  "type": "Feature",
  "properties": {
    "addr:full":"433 Rue Saint-Dizier Montreal QC H2Y 2Y2",
    "addr:housenumber":"433",
    "addr:postcode":"h2y 2y2",
    "addr:street":"Rue Saint-Dizier",
    "iso:country":"CA",
    "sg:address":"433 Rue Saint-Dizier",
    "sg:city":"Montreal",
    "sg:classifiers":[
        {
            "category":"Professional",
            "subcategory":"Management & Consulting",
            "type":"Services"
        }
    ],
    "sg:phone":"+1 514 284 2037",
    "sg:postcode":"H2Y 2Y2",
    "sg:province":"QC",
    "sg:tags":[
        "consultant",
        "business"
    ],
    "wof:name":"Secoma Limitee",
    "wof:placetype":"venue"
},
  "geometry": {"coordinates":[-73.554749,45.505451],"type":"Point"}
}