{
  "type": "Feature",
  "properties": {
    "addr:full":"530 Williams Ave Killarney MB R0K 1G0",
    "addr:housenumber":"530",
    "addr:postcode":"r0k 1g0",
    "addr:street":"Williams Ave",
    "iso:country":"CA",
    "sg:address":"530 Williams Ave",
    "sg:city":"Killarney",
    "sg:classifiers":[
        {
            "category":"Shopping",
            "subcategory":"Department Store",
            "type":"Retail Goods"
        }
    ],
    "sg:phone":"+1 204 523 7027",
    "sg:postcode":"R0K 1G0",
    "sg:province":"MB",
    "sg:tags":[
        "shop"
    ],
    "wof:name":"Your Dollar Store With More",
    "wof:placetype":"venue"
},
  "geometry": {"coordinates":[-99.664932251,49.1841430664],"type":"Point"}
}