{
  "type": "Feature",
  "properties": {
    "addr:full":"323 Rue Saint-Marcel Drummondville QC J2B 2E8",
    "addr:housenumber":"323",
    "addr:postcode":"j2b 2e8",
    "addr:street":"Rue Saint-Marcel",
    "iso:country":"CA",
    "sg:address":"323 Rue Saint-Marcel",
    "sg:city":"Drummondville",
    "sg:classifiers":[
        {
            "category":"Shopping",
            "subcategory":"Bicycles & Sporting Goods",
            "type":"Retail Goods"
        }
    ],
    "sg:phone":"+1 819 477 3141",
    "sg:postcode":"J2B 2E8",
    "sg:province":"QC",
    "wof:name":"Pierre Roux Sport Enr",
    "wof:placetype":"venue"
},
  "geometry": {"coordinates":[-72.485107,45.873314],"type":"Point"}
}