{
  "type": "Feature",
  "properties": {
    "addr:full":"1600 Ch Des Patriotes Sainte-Victoire-DE-Sorel QC J0G 1T0",
    "addr:housenumber":"1600",
    "addr:postcode":"j0g 1t0",
    "addr:street":"Ch Des Patriotes",
    "iso:country":"CA",
    "sg:address":"1600 Ch Des Patriotes",
    "sg:city":"Sainte-Victoire-DE-Sorel",
    "sg:classifiers":[
        {
            "category":"Building & Trades",
            "subcategory":"Electrical",
            "type":"Services"
        }
    ],
    "sg:phone":"+1 450 782 2886",
    "sg:postcode":"J0G 1T0",
    "sg:province":"QC",
    "sg:tags":[
        "electric",
        "contractor"
    ],
    "wof:name":"Entreprises Michel Morin",
    "wof:placetype":"venue"
},
  "geometry": {"coordinates":[-73.13827499999999,45.979973],"type":"Point"}
}