{
  "type": "Feature",
  "properties": {
    "addr:full":"845 15th St W North Vancouver BC V7P 1M5",
    "addr:housenumber":"845",
    "addr:postcode":"v7p 1m5",
    "addr:street":"15Th St W",
    "iso:country":"CA",
    "sg:address":"845 15th St W",
    "sg:city":"North Vancouver",
    "sg:classifiers":[
        {
            "category":"Wholesale",
            "subcategory":"Durable Goods & Equipment",
            "type":"Manufacturing & Wholesale Goods"
        }
    ],
    "sg:phone":"+1 604 986 2391",
    "sg:postcode":"V7P 1M5",
    "sg:province":"BC",
    "sg:tags":[
        "engineering",
        "blueprinting",
        "supply"
    ],
    "wof:name":"Western Technical Supply CO",
    "wof:placetype":"venue"
},
  "geometry": {"coordinates":[-123.095809937,49.3221511841],"type":"Point"}
}