{
  "type": "Feature",
  "properties": {
    "iso:country":"CA",
    "sg:address":"164 Main St E",
    "sg:city":"Milton",
    "sg:classifiers":[
        {
            "category":"Shopping",
            "subcategory":"Books",
            "type":"Retail Goods"
        }
    ],
    "sg:phone":"+1 905 875 1683",
    "sg:postcode":"L9T 1N6",
    "sg:province":"ON",
    "sg:tags":[
        "dealer"
    ],
    "wof:name":"Gospel Lighthouse",
    "wof:placetype":"venue"
},
  "geometry": {"coordinates":[-79.8840789795,43.5120697021],"type":"Point"}
}