{
  "type": "Feature",
  "properties": {
    "addr:full":"241 Applewood Cres Concord ON L4K 4E6",
    "addr:housenumber":"241",
    "addr:postcode":"l4k 4e6",
    "addr:street":"Applewood Cres",
    "iso:country":"CA",
    "sg:address":"241 Applewood Cres",
    "sg:city":"Concord",
    "sg:classifiers":[
        {
            "category":"Building & Trades",
            "subcategory":"Construction",
            "type":"Services"
        }
    ],
    "sg:phone":"+1 905 660 7415",
    "sg:postcode":"L4K 4E6",
    "sg:province":"ON",
    "sg:tags":[
        "contractor"
    ],
    "wof:name":"Fifthshire Homes Ltd",
    "wof:placetype":"venue"
},
  "geometry": {"coordinates":[-79.53784899999999,43.807529],"type":"Point"}
}