{
  "type": "Feature",
  "properties": {
    "addr:full":"Winnipeg MB R3C 0P9",
    "addr:postcode":"r3c 0p9",
    "iso:country":"CA",
    "sg:city":"Winnipeg",
    "sg:classifiers":[
        {
            "category":"Government",
            "subcategory":"Office",
            "type":"Public Place"
        }
    ],
    "sg:phone":"+1 204 945 5740",
    "sg:postcode":"R3C 0P9",
    "sg:province":"MB",
    "wof:name":"Manitoba Jury Coordinator",
    "wof:placetype":"venue"
},
  "geometry": {"coordinates":[-97.1475524902,49.8877716064],"type":"Point"}
}