{
  "type": "Feature",
  "properties": {
    "addr:full":"2280 Rue Belvedere S Ascot QC J1H 5R7",
    "addr:housenumber":"2280",
    "addr:postcode":"j1h 5r7",
    "addr:street":"Rue Belvedere S",
    "iso:country":"CA",
    "sg:address":"2280 Rue Belvedere S",
    "sg:city":"Ascot",
    "sg:classifiers":[
        {
            "category":"Manufacturing",
            "subcategory":"Metals",
            "type":"Manufacturing & Wholesale Goods"
        }
    ],
    "sg:phone":"+1 819 569 3486",
    "sg:postcode":"J1H 5R7",
    "sg:province":"QC",
    "sg:tags":[
        "solder"
    ],
    "wof:name":"Claude Soudure",
    "wof:placetype":"venue"
},
  "geometry": {"coordinates":[-71.8939666748,45.3688545227],"type":"Point"}
}