{
  "type": "Feature",
  "properties": {
    "iso:country":"CA",
    "sg:address":"71 King St W",
    "sg:city":"Brockville",
    "sg:classifiers":[
        {
            "category":"Shopping",
            "subcategory":"Books",
            "type":"Retail Goods"
        }
    ],
    "sg:phone":"+1 613 342 5728",
    "sg:postcode":"K6V 3P8",
    "sg:province":"ON",
    "sg:tags":[
        "dealer"
    ],
    "wof:name":"Leeds County Books",
    "wof:placetype":"venue"
},
  "geometry": {"coordinates":[-75.68486799999999,44.589138],"type":"Point"}
}