{
  "type": "Feature",
  "properties": {
    "addr:full":"180 Kenilworth Ave N Hamilton ON L8H 4S1",
    "addr:housenumber":"180",
    "addr:postcode":"l8h 4s1",
    "addr:street":"Kenilworth Ave N",
    "iso:country":"CA",
    "sg:address":"180 Kenilworth Ave N",
    "sg:city":"Hamilton",
    "sg:classifiers":[
        {
            "category":"Food & Beverages",
            "subcategory":"Groceries & Convenience Stores",
            "type":"Retail Goods"
        }
    ],
    "sg:phone":"+1 905 544 0289",
    "sg:postcode":"L8H 4S1",
    "sg:province":"ON",
    "sg:tags":[
        "grocer"
    ],
    "wof:name":"Big Bee Foodmart",
    "wof:placetype":"venue"
},
  "geometry": {"coordinates":[-79.807526,43.24567],"type":"Point"}
}