{
  "type": "Feature",
  "properties": {
    "addr:full":"Richmond Hill ON L4C 1T6",
    "addr:postcode":"l4c 1t6",
    "iso:country":"CA",
    "sg:city":"Richmond Hill",
    "sg:classifiers":[
        {
            "category":"Health Services",
            "subcategory":"Doctor",
            "type":"Services"
        }
    ],
    "sg:phone":"+1 905 737 4224",
    "sg:postcode":"L4C 1T6",
    "sg:province":"ON",
    "sg:tags":[
        "physician",
        "surgeon"
    ],
    "wof:name":"York Region Urology Ctr",
    "wof:placetype":"venue"
},
  "geometry": {"coordinates":[-79.4383010864,43.8752822876],"type":"Point"}
}