{
  "type": "Feature",
  "properties": {
    "addr:full":"13 Pelton Dr Kentville NS B4N 3V7",
    "addr:housenumber":"13",
    "addr:postcode":"b4n 3v7",
    "addr:street":"Pelton Dr",
    "iso:country":"CA",
    "sg:address":"13 Pelton Dr",
    "sg:city":"Kentville",
    "sg:classifiers":[
        {
            "category":"Freight",
            "type":"Transportation"
        }
    ],
    "sg:phone":"+1 902 678 4114",
    "sg:postcode":"B4N 3V7",
    "sg:province":"NS",
    "sg:tags":[
        "courier"
    ],
    "wof:name":"Purolator Courier Ltd",
    "wof:placetype":"venue"
},
  "geometry": {"coordinates":[-64.546921,45.069473],"type":"Point"}
}