{
  "type": "Feature",
  "properties": {
    "addr:full":"145 Riviera Dr Markham ON L3R 5J6",
    "addr:housenumber":"145",
    "addr:postcode":"l3r 5j6",
    "addr:street":"Riviera Dr",
    "iso:country":"CA",
    "sg:address":"145 Riviera Dr",
    "sg:city":"Markham",
    "sg:classifiers":[
        {
            "category":"Building & Trades",
            "subcategory":"Equipment Rental",
            "type":"Services"
        }
    ],
    "sg:phone":"+1 905 479 3737",
    "sg:postcode":"L3R 5J6",
    "sg:province":"ON",
    "sg:tags":[
        "contractor"
    ],
    "wof:name":"Performance Platforms Ltd",
    "wof:placetype":"venue"
},
  "geometry": {"coordinates":[-79.3410644531,43.8324317932],"type":"Point"}
}