{
  "type": "Feature",
  "properties": {
    "addr:full":"16 Division St S Kingsville ON N9Y 1P2",
    "addr:housenumber":"16",
    "addr:postcode":"n9y 1p2",
    "addr:street":"Division St S",
    "iso:country":"CA",
    "sg:address":"16 Division St S",
    "sg:city":"Kingsville",
    "sg:classifiers":[
        {
            "category":"Personal",
            "subcategory":"Beauty Salon",
            "type":"Services"
        }
    ],
    "sg:phone":"+1 519 733 2121",
    "sg:postcode":"N9Y 1P2",
    "sg:province":"ON",
    "wof:name":"Shades Unlimited Hair Studio",
    "wof:placetype":"venue"
},
  "geometry": {"coordinates":[-82.7398223877,42.0373687744],"type":"Point"}
}