{
  "type": "Feature",
  "properties": {
    "addr:full":"16 Kirtling Pl North York ON M2L 1W4",
    "addr:housenumber":"16",
    "addr:postcode":"m2l 1w4",
    "addr:street":"Kirtling Pl",
    "iso:country":"CA",
    "sg:address":"16 Kirtling Pl",
    "sg:city":"North York",
    "sg:classifiers":[
        {
            "category":"Health Services",
            "subcategory":"Health Practitioner",
            "type":"Services"
        }
    ],
    "sg:phone":"+1 416 444 6540",
    "sg:postcode":"M2L 1W4",
    "sg:province":"ON",
    "sg:tags":[
        "physician"
    ],
    "wof:name":"Gay, Donald A",
    "wof:placetype":"venue"
},
  "geometry": {"coordinates":[-79.376526,43.750462],"type":"Point"}
}