{
  "type": "Feature",
  "properties": {
    "addr:full":"25 Forks Market Rd Winnipeg MB R3C 4S8",
    "addr:housenumber":"25",
    "addr:postcode":"r3c 4s8",
    "addr:street":"Forks Market Rd",
    "iso:country":"CA",
    "sg:address":"25 Forks Market Rd",
    "sg:city":"Winnipeg",
    "sg:classifiers":[
        {
            "category":"Shopping",
            "subcategory":"Used Merchandise",
            "type":"Retail Goods"
        }
    ],
    "sg:phone":"+1 204 947 3952",
    "sg:postcode":"R3C 4S8",
    "sg:province":"MB",
    "sg:tags":[
        "antique"
    ],
    "wof:name":"Johnston Terminal Antique Mall",
    "wof:placetype":"venue"
},
  "geometry": {"coordinates":[-97.1295166016,49.8874816895],"type":"Point"}
}