{
  "type": "Feature",
  "properties": {
    "addr:full":"3964 Albert St Regina SK S4S 3R1",
    "addr:housenumber":"3964",
    "addr:postcode":"s4s 3r1",
    "addr:street":"Albert St",
    "iso:country":"CA",
    "sg:address":"3964 Albert St",
    "sg:city":"Regina",
    "sg:classifiers":[
        {
            "category":"Restaurant",
            "type":"Food & Drink"
        }
    ],
    "sg:phone":"+1 306 585 1455",
    "sg:postcode":"S4S 3R1",
    "sg:province":"SK",
    "wof:name":"Mr Sub",
    "wof:placetype":"venue"
},
  "geometry": {"coordinates":[-104.618286133,50.4159622192],"type":"Point"}
}