{
  "type": "Feature",
  "properties": {
    "iso:country":"CA",
    "sg:city":"Courtenay",
    "sg:classifiers":[
        {
            "category":"Shopping",
            "type":"Retail Goods"
        }
    ],
    "sg:phone":"+1 250 334 4044",
    "sg:postcode":"V9N 1K2",
    "sg:province":"BC",
    "sg:tags":[
        "hearing",
        "equipment",
        "supply",
        "impaired"
    ],
    "wof:name":"Beltone Better Hearing Ctr",
    "wof:placetype":"venue"
},
  "geometry": {"coordinates":[-124.965492248,49.7088012695],"type":"Point"}
}