{
  "type": "Feature",
  "properties": {
    "addr:full":"431 Rue Boivin Granby QC J2G 2L2",
    "addr:housenumber":"431",
    "addr:postcode":"j2g 2l2",
    "addr:street":"Rue Boivin",
    "iso:country":"CA",
    "sg:address":"431 Rue Boivin",
    "sg:city":"Granby",
    "sg:classifiers":[
        {
            "category":"Retail",
            "subcategory":"Auto Repair",
            "type":"Services"
        }
    ],
    "sg:phone":"+1 450 375 1944",
    "sg:postcode":"J2G 2L2",
    "sg:province":"QC",
    "sg:tags":[
        "repairing",
        "automobile"
    ],
    "wof:name":"Desparts Transmission",
    "wof:placetype":"venue"
},
  "geometry": {"coordinates":[-72.7337188721,45.4059181213],"type":"Point"}
}