{
  "type": "Feature",
  "properties": {
    "addr:full":"321 Main St Selkirk MB R1A 1T2",
    "addr:housenumber":"321",
    "addr:postcode":"r1a 1t2",
    "addr:street":"Main St",
    "iso:country":"CA",
    "sg:address":"321 Main St",
    "sg:city":"Selkirk",
    "sg:classifiers":[
        {
            "category":"Food & Beverages",
            "subcategory":"Specialty",
            "type":"Retail Goods"
        }
    ],
    "sg:phone":"+1 204 785 1810",
    "sg:postcode":"R1A 1T2",
    "sg:province":"MB",
    "sg:tags":[
        "water",
        "bulk",
        "company"
    ],
    "wof:name":"World of Water",
    "wof:placetype":"venue"
},
  "geometry": {"coordinates":[-96.87687683110001,50.1417388916],"type":"Point"}
}