{
  "type": "Feature",
  "properties": {
    "addr:full":"28 Old Cart Rd South River NL A0A 3W0",
    "addr:housenumber":"28",
    "addr:postcode":"a0a 3w0",
    "addr:street":"Old Cart Rd",
    "iso:country":"CA",
    "sg:address":"28 Old Cart Rd",
    "sg:city":"South River",
    "sg:classifiers":[
        {
            "category":"Building & Trades",
            "subcategory":"Plumbing",
            "type":"Services"
        }
    ],
    "sg:phone":"+1 709 786 7001",
    "sg:postcode":"A0A 3W0",
    "sg:province":"NL",
    "sg:tags":[
        "refrigeration",
        "contractor"
    ],
    "wof:name":"Chafe Refrigeration Ltd",
    "wof:placetype":"venue"
},
  "geometry": {"coordinates":[-53.269871,47.536968],"type":"Point"}
}