{
  "type": "Feature",
  "properties": {
    "addr:full":"460 Ward St Nelson BC V1L 1S8",
    "addr:housenumber":"460",
    "addr:postcode":"bc v1l 1s8",
    "addr:street":"Ward St",
    "iso:country":"CA",
    "sg:address":"460 Ward St",
    "sg:city":"Nelson",
    "sg:classifiers":[
        {
            "category":"Shopping",
            "subcategory":"Used Merchandise",
            "type":"Retail Goods"
        }
    ],
    "sg:phone":"+1 250 352 7822",
    "sg:postcode":"V1L 1S8",
    "sg:province":"BC",
    "sg:tags":[
        "antique"
    ],
    "wof:name":"Little House Collectibles",
    "wof:placetype":"venue"
},
  "geometry": {"coordinates":[-117.29444100000001,49.492241],"type":"Point"}
}