{
  "type": "Feature",
  "properties": {
    "addr:full":"3441 Ch Royal Sainte-Famille QC G0A 3P0",
    "addr:postcode":"3441;g0a 3p0",
    "addr:street":"Ch Royal",
    "iso:country":"CA",
    "sg:address":"3441 Ch Royal",
    "sg:city":"Sainte-Famille",
    "sg:classifiers":[
        {
            "category":"Building & Trades",
            "subcategory":"Plumbing",
            "type":"Services"
        }
    ],
    "sg:phone":"+1 418 829 2720",
    "sg:postcode":"G0A 3P0",
    "sg:province":"QC",
    "sg:tags":[
        "contractor"
    ],
    "wof:name":"Gaetan Letourneau Inc",
    "wof:placetype":"venue"
},
  "geometry": {"coordinates":[-70.990166,46.947086],"type":"Point"}
}