{
  "type": "Feature",
  "properties": {
    "addr:full":"116 Hartzell Rd St Catharines ON L2P 1N5",
    "addr:housenumber":"116",
    "addr:postcode":"l2p 1n5",
    "addr:street":"Hartzell Rd",
    "iso:country":"CA",
    "sg:address":"116 Hartzell Rd",
    "sg:city":"St Catharines",
    "sg:classifiers":[
        {
            "category":"Personal",
            "subcategory":"Beauty Salon",
            "type":"Services"
        }
    ],
    "sg:phone":"+1 905 684 7992",
    "sg:postcode":"L2P 1N5",
    "sg:province":"ON",
    "wof:name":"Sheri's Creative Edge",
    "wof:placetype":"venue"
},
  "geometry": {"coordinates":[-79.2140884399,43.1506385803],"type":"Point"}
}