{
  "type": "Feature",
  "properties": {
    "addr:full":"5365 Munro Crt Burlington ON L7L 5M7",
    "addr:housenumber":"5365",
    "addr:postcode":"l7l 5m7",
    "addr:street":"Munro Crt",
    "iso:country":"CA",
    "sg:address":"5365 Munro Crt",
    "sg:city":"Burlington",
    "sg:classifiers":[
        {
            "category":"Shopping",
            "subcategory":"Hobbies, Toys, & Games",
            "type":"Retail Goods"
        }
    ],
    "sg:phone":"+1 905 637 8137",
    "sg:postcode":"L7L 5M7",
    "sg:province":"ON",
    "sg:tags":[
        "equipment",
        "ceramic",
        "supply"
    ],
    "wof:name":"Vitrex Ceramics Ltd",
    "wof:placetype":"venue"
},
  "geometry": {"coordinates":[-79.75818599999999,43.390034],"type":"Point"}
}