{
  "type": "Feature",
  "properties": {
    "iso:country":"CA",
    "sg:address":"Eldon St",
    "sg:city":"Fortune",
    "sg:classifiers":[
        {
            "category":"Social Services",
            "type":"Services"
        }
    ],
    "sg:phone":"+1 709 832 1107",
    "sg:postcode":"A0E 1P0",
    "sg:province":"NL",
    "sg:tags":[
        "senior",
        "citizen"
    ],
    "wof:name":"Fortune Senior Citizens Club",
    "wof:placetype":"venue"
},
  "geometry": {"coordinates":[-55.8259544373,47.0741348267],"type":"Point"}
}