{
  "type": "Feature",
  "properties": {
    "addr:full":"3885 Stouffville Rd Stouffville ON L4A 7X5",
    "addr:housenumber":"3885",
    "addr:postcode":"l4a 7x5",
    "addr:street":"Stouffville Rd",
    "iso:country":"CA",
    "sg:address":"3885 Stouffville Rd",
    "sg:city":"Stouffville",
    "sg:classifiers":[
        {
            "category":"Organizations",
            "subcategory":"Religious Organization",
            "type":"Services"
        }
    ],
    "sg:phone":"+1 905 887 5651",
    "sg:postcode":"L4A 7X5",
    "sg:province":"ON",
    "sg:tags":[
        "church"
    ],
    "wof:name":"Springvale Baptist Church",
    "wof:placetype":"venue"
},
  "geometry": {"coordinates":[-79.3246765137,43.9541358948],"type":"Point"}
}