{
  "type": "Feature",
  "properties": {
    "addr:full":"505 Ellesmere Rd #3 Scarborough ON M1R 4E5",
    "addr:housenumber":"505",
    "addr:postcode":"m1r 4e5",
    "addr:street":"Ellesmere Rd # 3",
    "iso:country":"CA",
    "sg:address":"505 Ellesmere Rd #3",
    "sg:city":"Scarborough",
    "sg:classifiers":[
        {
            "category":"Professional",
            "subcategory":"Lawyer & Legal Services",
            "type":"Services"
        }
    ],
    "sg:phone":"+1 416 752 0720",
    "sg:postcode":"M1R 4E5",
    "sg:province":"ON",
    "sg:tags":[
        "attorney"
    ],
    "wof:name":"Pilon, Maurice W",
    "wof:placetype":"venue"
},
  "geometry": {"coordinates":[-79.2951049805,43.7623825073],"type":"Point"}
}