{
  "type": "Feature",
  "properties": {
    "addr:full":"2536 Boul Sainte-Sophie Sainte-Sophie QC J5J 2V3",
    "addr:housenumber":"2536",
    "addr:postcode":"j5j 2v3",
    "addr:street":"Boul Sainte-Sophie",
    "iso:country":"CA",
    "sg:address":"2536 Boul Sainte-Sophie",
    "sg:city":"Sainte-Sophie",
    "sg:classifiers":[
        {
            "category":"Manufacturing",
            "subcategory":"Tools & Machinery",
            "type":"Manufacturing & Wholesale Goods"
        }
    ],
    "sg:phone":"+1 450 431 1233",
    "sg:postcode":"J5J 2V3",
    "sg:province":"QC",
    "sg:tags":[
        "equipment",
        "hydraulic",
        "supply"
    ],
    "wof:name":"Atelier Hydrauluc",
    "wof:placetype":"venue"
},
  "geometry": {"coordinates":[-73.89660600000001,45.819359],"type":"Point"}
}