{
  "type": "Feature",
  "properties": {
    "iso:country":"CA",
    "sg:address":"60 15E Rue",
    "sg:city":"Laval",
    "sg:classifiers":[
        {
            "category":"Professional",
            "subcategory":"Testing Lab",
            "type":"Services"
        }
    ],
    "sg:phone":"+1 450 629 8101",
    "sg:postcode":"H7N 1L1",
    "sg:province":"QC",
    "sg:tags":[
        "laboratory"
    ],
    "wof:name":"Radon Detection",
    "wof:placetype":"venue"
},
  "geometry": {"coordinates":[-73.697372,45.565838],"type":"Point"}
}