{
  "type": "Feature",
  "properties": {
    "addr:full":"Wekweti NT X0E 1W0",
    "addr:postcode":"x0e 1w0",
    "iso:country":"CA",
    "sg:city":"Wekweti",
    "sg:classifiers":[
        {
            "category":"Utilities",
            "subcategory":"Electric",
            "type":"Services"
        }
    ],
    "sg:phone":"+1 867 713 2704",
    "sg:postcode":"X0E 1W0",
    "sg:province":"NT",
    "sg:tags":[
        "company"
    ],
    "wof:name":"Northland Utilities Ltd",
    "wof:placetype":"venue"
},
  "geometry": {"coordinates":[-114.18284606900001,64.1904296875],"type":"Point"}
}