{
  "type": "Feature",
  "properties": {
    "addr:full":"St Jean Baptiste MB R0G 2B0",
    "addr:postcode":"r0g 2b0",
    "addr:street":"St Jean Baptiste",
    "iso:country":"CA",
    "sg:city":"St Jean Baptiste",
    "sg:classifiers":[
        {
            "category":"Arena",
            "subcategory":"Sports Club",
            "type":"Entertainment"
        }
    ],
    "sg:phone":"+1 204 758 3840",
    "sg:postcode":"R0G 2B0",
    "sg:province":"MB",
    "sg:tags":[
        "athletic",
        "fields",
        "stadium"
    ],
    "wof:name":"St Jean Arena",
    "wof:placetype":"venue"
},
  "geometry": {"coordinates":[-98.69615899999999,49.630447],"type":"Point"}
}