{
  "type": "Feature",
  "properties": {
    "addr:full":"1901 23 St SE Medicine Hat AB T1A 2E1",
    "addr:housenumber":"1901",
    "addr:postcode":"t1a 2e1",
    "addr:street":"23 St Se",
    "iso:country":"CA",
    "sg:address":"1901 23 St SE",
    "sg:city":"Medicine Hat",
    "sg:classifiers":[
        {
            "category":"Building & Trades",
            "subcategory":"Electrical",
            "type":"Services"
        }
    ],
    "sg:phone":"+1 403 529 2993",
    "sg:postcode":"T1A 2E1",
    "sg:province":"AB",
    "sg:tags":[
        "electric",
        "contractor"
    ],
    "wof:name":"Dnb Electric",
    "wof:placetype":"venue"
},
  "geometry": {"coordinates":[-110.65568500000001,50.01791],"type":"Point"}
}