{
  "type": "Feature",
  "properties": {
    "addr:full":"Toronto ON M4W 3E2",
    "addr:postcode":"m4w 3e2",
    "iso:country":"CA",
    "sg:city":"Toronto",
    "sg:classifiers":[
        {
            "category":"Education",
            "subcategory":"Special Training",
            "type":"Public Place"
        }
    ],
    "sg:phone":"+1 416 922 2223",
    "sg:postcode":"M4W 3E2",
    "sg:province":"ON",
    "sg:tags":[
        "school",
        "language"
    ],
    "wof:name":"Centre Linguista",
    "wof:placetype":"venue"
},
  "geometry": {"coordinates":[-79.387428,43.670231],"type":"Point"}
}