{
  "type": "Feature",
  "properties": {
    "iso:country":"CA",
    "sg:address":"150 Water St",
    "sg:city":"Oakville",
    "sg:classifiers":[
        {
            "category":"Organizations",
            "subcategory":"Professional Association",
            "type":"Services"
        }
    ],
    "sg:phone":"+1 905 844 3607",
    "sg:postcode":"L6J 7R4",
    "sg:province":"ON",
    "sg:tags":[
        "club"
    ],
    "wof:name":"Oakville Power Boat Club",
    "wof:placetype":"venue"
},
  "geometry": {"coordinates":[-79.672554,43.444057],"type":"Point"}
}