{
  "type": "Feature",
  "properties": {
    "addr:full":"1 C. L. Dobbin Dr Gander NL A1V 2V3",
    "addr:housenumber":"1",
    "addr:postcode":"a1v 2v3",
    "addr:street":"C. L. Dobbin Dr",
    "iso:country":"CA",
    "sg:address":"1 C. L. Dobbin Dr",
    "sg:city":"Gander",
    "sg:classifiers":[
        {
            "category":"Airport",
            "type":"Transportation"
        }
    ],
    "sg:phone":"+1 709 256 6111",
    "sg:postcode":"A1V 2V3",
    "sg:province":"NL",
    "sg:tags":[
        "aircraft",
        "maintenance"
    ],
    "wof:name":"Chc Composites Ltd",
    "wof:placetype":"venue"
},
  "geometry": {"coordinates":[-54.60918,48.956829],"type":"Point"}
}