{
  "type": "Feature",
  "properties": {
    "addr:full":"676 Jane St York ON M6N 4A7",
    "addr:housenumber":"676",
    "addr:postcode":"m6n 4a7",
    "addr:street":"Jane St",
    "iso:country":"CA",
    "sg:address":"676 Jane St",
    "sg:city":"York",
    "sg:classifiers":[
        {
            "category":"Social Services",
            "subcategory":"Child Care",
            "type":"Services"
        }
    ],
    "sg:phone":"+1 416 769 1289",
    "sg:postcode":"M6N 4A7",
    "sg:province":"ON",
    "wof:name":"Happy Day Child Care Ctr",
    "wof:placetype":"venue"
},
  "geometry": {"coordinates":[-79.4924621582,43.6683082581],"type":"Point"}
}