{
  "type": "Feature",
  "properties": {
    "addr:full":"5587 Rue DE Verdun Verdun QC H4H 1L2",
    "addr:housenumber":"5587",
    "addr:postcode":"h4h 1l2",
    "addr:street":"Rue De Verdun",
    "iso:country":"CA",
    "sg:address":"5587 Rue DE Verdun",
    "sg:city":"Verdun",
    "sg:classifiers":[
        {
            "category":"Wholesale",
            "subcategory":"Meat",
            "type":"Manufacturing & Wholesale Goods"
        }
    ],
    "sg:phone":"+1 514 761 0976",
    "sg:postcode":"H4H 1L2",
    "sg:province":"QC",
    "sg:tags":[
        "butchering"
    ],
    "wof:name":"Boucherie Codiv Enr",
    "wof:placetype":"venue"
},
  "geometry": {"coordinates":[-73.572571,45.451637],"type":"Point"}
}