{
  "type": "Feature",
  "properties": {
    "addr:full":"1093 Stouffville Rd Gormley ON L0H 1G0",
    "addr:housenumber":"1093",
    "addr:postcode":"l0h 1g0",
    "addr:street":"Stouffville Rd",
    "iso:country":"CA",
    "sg:address":"1093 Stouffville Rd",
    "sg:city":"Gormley",
    "sg:classifiers":[
        {
            "category":"Autos & Motor Vehicles",
            "subcategory":"Automobile Sales",
            "type":"Retail Goods"
        }
    ],
    "sg:phone":"+1 905 773 5675",
    "sg:postcode":"L0H 1G0",
    "sg:province":"ON",
    "sg:tags":[
        "classic"
    ],
    "wof:name":"Al Webster Classic Cars",
    "wof:placetype":"venue"
},
  "geometry": {"coordinates":[-79.387756,43.9403],"type":"Point"}
}