{
  "type": "Feature",
  "properties": {
    "iso:country":"CA",
    "sg:address":"6636 Lethbridge Cres SW",
    "sg:city":"Calgary",
    "sg:classifiers":[
        {
            "category":"Retail",
            "subcategory":"Repair Shop",
            "type":"Services"
        }
    ],
    "sg:phone":"+1 403 246 1252",
    "sg:postcode":"T3E 6A4",
    "sg:province":"AB",
    "sg:tags":[
        "repairing",
        "piano",
        "refinishing"
    ],
    "wof:name":"Hopland's Piano Svc",
    "wof:placetype":"venue"
},
  "geometry": {"coordinates":[-114.13943500000001,50.995277],"type":"Point"}
}