{
  "type": "Feature",
  "properties": {
    "addr:full":"210 Deadmans Harbour Rd Blacks Harbour NB E5H 1J3",
    "addr:housenumber":"210",
    "addr:postcode":"e5h 1j3",
    "addr:street":"Deadmans Harbour Rd",
    "iso:country":"CA",
    "sg:address":"210 Deadmans Harbour Rd",
    "sg:city":"Blacks Harbour",
    "sg:classifiers":[
        {
            "category":"Retail",
            "subcategory":"Repair Shop",
            "type":"Services"
        }
    ],
    "sg:phone":"+1 506 456 2244",
    "sg:postcode":"E5H 1J3",
    "sg:province":"NB",
    "sg:tags":[
        "upholsterer"
    ],
    "wof:name":"Le-Chau's Upholstery",
    "wof:placetype":"venue"
},
  "geometry": {"coordinates":[-66.77844238279999,45.0553207397],"type":"Point"}
}