{
  "type": "Feature",
  "properties": {
    "addr:full":"Saint John NB E2L 3P4",
    "addr:postcode":"e2l 3p4",
    "iso:country":"CA",
    "sg:city":"Saint John",
    "sg:classifiers":[
        {
            "category":"Local Transit",
            "type":"Transportation"
        }
    ],
    "sg:phone":"+1 506 648 0609",
    "sg:postcode":"E2L 3P4",
    "sg:province":"NB",
    "sg:tags":[
        "handicapped"
    ],
    "wof:name":"Handi-Bus",
    "wof:placetype":"venue"
},
  "geometry": {"coordinates":[-66.05620574949999,45.2773742676],"type":"Point"}
}