{
  "type": "Feature",
  "properties": {
    "addr:full":"226 Turnberry St N Brussels ON N0G 1H0",
    "addr:housenumber":"226",
    "addr:postcode":"n0g 1h0",
    "addr:street":"Turnberry St N",
    "iso:country":"CA",
    "sg:address":"226 Turnberry St N",
    "sg:city":"Brussels",
    "sg:classifiers":[
        {
            "category":"Home & Garden",
            "subcategory":"Hardware",
            "type":"Retail Goods"
        }
    ],
    "sg:phone":"+1 519 887 6277",
    "sg:postcode":"N0G 1H0",
    "sg:province":"ON",
    "sg:tags":[
        "lumber"
    ],
    "wof:name":"Mc Donald Home Hardware & Lmbr",
    "wof:placetype":"venue"
},
  "geometry": {"coordinates":[-81.246307,43.748993],"type":"Point"}
}