{
  "type": "Feature",
  "properties": {
    "addr:full":"3440 Marentette Ave Windsor ON N8X 5C2",
    "addr:housenumber":"3440",
    "addr:postcode":"n8x 5c2",
    "addr:street":"Marentette Ave",
    "iso:country":"CA",
    "sg:address":"3440 Marentette Ave",
    "sg:city":"Windsor",
    "sg:classifiers":[
        {
            "category":"Building & Trades",
            "subcategory":"Construction",
            "type":"Services"
        }
    ],
    "sg:phone":"+1 519 682 1666",
    "sg:postcode":"N8X 5C2",
    "sg:province":"ON",
    "sg:tags":[
        "concrete",
        "contractor"
    ],
    "wof:name":"Tilbury Concrete",
    "wof:placetype":"venue"
},
  "geometry": {"coordinates":[-82.99401899999999,42.268501],"type":"Point"}
}