{
  "type": "Feature",
  "properties": {
    "iso:country":"CA",
    "sg:address":"136 Seventh St",
    "sg:city":"Etobicoke",
    "sg:classifiers":[
        {
            "category":"Health Services",
            "subcategory":"Doctor",
            "type":"Services"
        }
    ],
    "sg:phone":"+1 416 251 2061",
    "sg:postcode":"M8V 3B4",
    "sg:province":"ON",
    "sg:tags":[
        "dentist"
    ],
    "wof:name":"Joe, Jack DDS",
    "wof:placetype":"venue"
},
  "geometry": {"coordinates":[-79.5049209595,43.5994987488],"type":"Point"}
}