{
  "type": "Feature",
  "properties": {
    "addr:full":"Chase BC V0E 1M3",
    "addr:postcode":"v0e 1m3",
    "iso:country":"CA",
    "sg:city":"Chase",
    "sg:classifiers":[
        {
            "category":"Autos & Motor Vehicles",
            "subcategory":"Fuel & Gas Station",
            "type":"Retail Goods"
        }
    ],
    "sg:phone":"+1 250 679 3698",
    "sg:postcode":"V0E 1M3",
    "sg:province":"BC",
    "sg:tags":[
        "oil"
    ],
    "wof:name":"Ska-Hiish Esso",
    "wof:placetype":"venue"
},
  "geometry": {"coordinates":[-119.672065735,50.8250389099],"type":"Point"}
}