{
  "type": "Feature",
  "properties": {
    "addr:full":"1528 172 St Surrey BC V3S 9M6",
    "addr:housenumber":"1528",
    "addr:postcode":"v3s 9m6",
    "addr:street":"172 St",
    "iso:country":"CA",
    "sg:address":"1528 172 St",
    "sg:city":"Surrey",
    "sg:classifiers":[
        {
            "category":"Recreation",
            "type":"Entertainment"
        }
    ],
    "sg:phone":"+1 604 536 9440",
    "sg:postcode":"V3S 9M6",
    "sg:province":"BC",
    "sg:tags":[
        "stable"
    ],
    "wof:name":"Semiahmoo Stables",
    "wof:placetype":"venue"
},
  "geometry": {"coordinates":[-122.746109,49.03117],"type":"Point"}
}