{
  "type": "Feature",
  "properties": {
    "addr:full":"1580 Bernard Ave Kelowna BC V1Y 6R9",
    "addr:housenumber":"1580",
    "addr:postcode":"v1y 6r9",
    "addr:street":"Bernard Ave",
    "iso:country":"CA",
    "sg:address":"1580 Bernard Ave",
    "sg:city":"Kelowna",
    "sg:classifiers":[
        {
            "category":"Social Services",
            "subcategory":"Child Care",
            "type":"Services"
        }
    ],
    "sg:phone":"+1 250 868 4845",
    "sg:postcode":"V1Y 6R9",
    "sg:province":"BC",
    "wof:name":"L'Escale Day Care Ctr",
    "wof:placetype":"venue"
},
  "geometry": {"coordinates":[-119.46363830599999,49.8864059448],"type":"Point"}
}