{
  "type": "Feature",
  "properties": {
    "iso:country":"CA",
    "sg:address":"253 11th Ave E",
    "sg:city":"Vancouver",
    "sg:classifiers":[
        {
            "category":"Wholesale",
            "subcategory":"Non-durable Goods",
            "type":"Manufacturing & Wholesale Goods"
        }
    ],
    "sg:phone":"+1 604 873 3117",
    "sg:postcode":"V5T 2C4",
    "sg:province":"BC",
    "sg:tags":[
        "advertising"
    ],
    "wof:name":"Buttons Factory of Vancouver",
    "wof:placetype":"venue"
},
  "geometry": {"coordinates":[-123.099174499,49.2612686157],"type":"Point"}
}