{
  "type": "Feature",
  "properties": {
    "iso:country":"CA",
    "sg:address":"423 Booth Dr",
    "sg:city":"Winnipeg",
    "sg:classifiers":[
        {
            "category":"Manufacturing",
            "subcategory":"Food",
            "type":"Manufacturing & Wholesale Goods"
        }
    ],
    "sg:phone":"+1 204 831 6074",
    "sg:postcode":"R3J 3M9",
    "sg:province":"MB",
    "sg:tags":[
        "product",
        "health"
    ],
    "wof:name":"Cran-Dale Inc",
    "wof:placetype":"venue"
},
  "geometry": {"coordinates":[-97.276787,49.883762],"type":"Point"}
}