{
  "type": "Feature",
  "properties": {
    "addr:full":"440 Richmond Ave E Brandon MB R7A 7G7",
    "addr:housenumber":"440",
    "addr:postcode":"r7a 7g7",
    "addr:street":"Richmond Ave E",
    "iso:country":"CA",
    "sg:address":"440 Richmond Ave E",
    "sg:city":"Brandon",
    "sg:classifiers":[
        {
            "category":"Wholesale",
            "subcategory":"Machinery & Supplies",
            "type":"Manufacturing & Wholesale Goods"
        }
    ],
    "sg:phone":"+1 204 728 1215",
    "sg:postcode":"R7A 7G7",
    "sg:province":"MB",
    "sg:tags":[
        "janitor"
    ],
    "wof:name":"Zep Mfg",
    "wof:placetype":"venue"
},
  "geometry": {"coordinates":[-99.933403,49.827347],"type":"Point"}
}