{
  "type": "Feature",
  "properties": {
    "addr:full":"4631 31 Ave NE Calgary AB T1Y 1G8",
    "addr:housenumber":"4631",
    "addr:postcode":"t1y 1g8",
    "addr:street":"31 Ave Ne",
    "iso:country":"CA",
    "sg:address":"4631 31 Ave NE",
    "sg:city":"Calgary",
    "sg:classifiers":[
        {
            "category":"Wholesale",
            "subcategory":"Electrical",
            "type":"Manufacturing & Wholesale Goods"
        }
    ],
    "sg:phone":"+1 403 272 9886",
    "sg:postcode":"T1Y 1G8",
    "sg:province":"AB",
    "sg:tags":[
        "communications",
        "equipment"
    ],
    "wof:name":"Aca Electric Ltd",
    "wof:placetype":"venue"
},
  "geometry": {"coordinates":[-113.96817799999999,51.080276],"type":"Point"}
}