{
  "type": "Feature",
  "properties": {
    "addr:full":"2700 Ouellette Ave Windsor ON N8X 1L7",
    "addr:housenumber":"2700",
    "addr:postcode":"n8x 1l7",
    "addr:street":"Ouellette Ave",
    "iso:country":"CA",
    "sg:address":"2700 Ouellette Ave",
    "sg:city":"Windsor",
    "sg:classifiers":[
        {
            "category":"Manufacturing",
            "subcategory":"Furniture",
            "type":"Manufacturing & Wholesale Goods"
        }
    ],
    "sg:phone":"+1 519 969 7332",
    "sg:postcode":"N8X 1L7",
    "sg:province":"ON",
    "wof:name":"Peter Anthony Design Ltd",
    "wof:placetype":"venue"
},
  "geometry": {"coordinates":[-83.01681518549999,42.2832527161],"type":"Point"}
}