{
  "type": "Feature",
  "properties": {
    "addr:full":"Waterloo QC J0E 2N0",
    "addr:postcode":"j0e 2n0",
    "iso:country":"CA",
    "sg:city":"Waterloo",
    "sg:classifiers":[
        {
            "category":"Wholesale",
            "subcategory":"Chemicals & Plastics",
            "type":"Manufacturing & Wholesale Goods"
        }
    ],
    "sg:phone":"+1 450 539 4759",
    "sg:postcode":"J0E 2N0",
    "sg:province":"QC",
    "wof:name":"Laboratoires E & G Inc",
    "wof:placetype":"venue"
},
  "geometry": {"coordinates":[-72.5161743164,45.3528175354],"type":"Point"}
}