{
  "type": "Feature",
  "properties": {
    "addr:full":"2375 Rue Canadien Drummondville QC J2C 7W1",
    "addr:housenumber":"2375",
    "addr:postcode":"j2c 7w1",
    "addr:street":"Rue Canadien",
    "iso:country":"CA",
    "sg:address":"2375 Rue Canadien",
    "sg:city":"Drummondville",
    "sg:classifiers":[
        {
            "category":"Building & Trades",
            "subcategory":"Construction",
            "type":"Services"
        }
    ],
    "sg:phone":"+1 819 474 2323",
    "sg:postcode":"J2C 7W1",
    "sg:province":"QC",
    "sg:tags":[
        "contractor",
        "general"
    ],
    "wof:name":"Excell Plus Construction",
    "wof:placetype":"venue"
},
  "geometry": {"coordinates":[-72.5443572998,45.8820571899],"type":"Point"}
}