{
  "type": "Feature",
  "properties": {
    "addr:full":"RR 1 Clive AB T0C 0Y0",
    "addr:postcode":"t0c 0y0",
    "addr:street":"Rr 1",
    "iso:country":"CA",
    "sg:address":"RR 1",
    "sg:city":"Clive",
    "sg:classifiers":[
        {
            "category":"Manufacturing",
            "subcategory":"Tools & Machinery",
            "type":"Manufacturing & Wholesale Goods"
        }
    ],
    "sg:phone":"+1 403 784 3864",
    "sg:postcode":"T0C 0Y0",
    "sg:province":"AB",
    "sg:tags":[
        "farm",
        "equipment"
    ],
    "wof:name":"Rodono Industries Ltd",
    "wof:placetype":"venue"
},
  "geometry": {"coordinates":[-113.44967699999999,52.47773],"type":"Point"}
}