{
  "type": "Feature",
  "properties": {
    "addr:full":"Calgary AB T2H 2B8",
    "addr:postcode":"t2h 2b8",
    "iso:country":"CA",
    "sg:city":"Calgary",
    "sg:classifiers":[
        {
            "category":"Shopping",
            "subcategory":"Bicycles & Sporting Goods",
            "type":"Retail Goods"
        }
    ],
    "sg:phone":"+1 403 258 0545",
    "sg:postcode":"T2H 2B8",
    "sg:province":"AB",
    "wof:name":"Russell Sporting Goods",
    "wof:placetype":"venue"
},
  "geometry": {"coordinates":[-114.071250916,50.9823570251],"type":"Point"}
}