{
  "type": "Feature",
  "properties": {
    "addr:full":"29 Victoria Rd Bridgewater NS B4V 2N1",
    "addr:housenumber":"29",
    "addr:postcode":"b4v 2n1",
    "addr:street":"Victoria Rd",
    "iso:country":"CA",
    "sg:address":"29 Victoria Rd",
    "sg:city":"Bridgewater",
    "sg:classifiers":[
        {
            "category":"Social Services",
            "type":"Services"
        }
    ],
    "sg:phone":"+1 902 543 7444",
    "sg:postcode":"B4V 2N1",
    "sg:province":"NS",
    "sg:tags":[
        "counselor",
        "marriage",
        "family"
    ],
    "wof:name":"Alternatives",
    "wof:placetype":"venue"
},
  "geometry": {"coordinates":[-64.5233383179,44.3802986145],"type":"Point"}
}