{
  "type": "Feature",
  "properties": {
    "iso:country":"CA",
    "sg:city":"Calgary",
    "sg:classifiers":[
        {
            "category":"Professional",
            "subcategory":"Computer Services",
            "type":"Services"
        }
    ],
    "sg:phone":"+1 403 230 9225",
    "sg:postcode":"T2E 2P6",
    "sg:province":"AB",
    "sg:tags":[
        "website",
        "design"
    ],
    "wof:name":"Internet Centre Inc",
    "wof:placetype":"venue"
},
  "geometry": {"coordinates":[-114.062644959,51.0598754883],"type":"Point"}
}