{
  "type": "Feature",
  "properties": {
    "addr:full":"1 Linthurst Ave North York ON M3M 1P1",
    "addr:housenumber":"1",
    "addr:postcode":"m3m 1p1",
    "addr:street":"Linthurst Ave",
    "iso:country":"CA",
    "sg:address":"1 Linthurst Ave",
    "sg:city":"North York",
    "sg:classifiers":[
        {
            "category":"Social Services",
            "type":"Services"
        }
    ],
    "sg:phone":"+1 416 781 9140",
    "sg:postcode":"M3M 1P1",
    "sg:province":"ON",
    "sg:tags":[
        "organization",
        "welfare"
    ],
    "wof:name":"Celiac Toronto Chapter Help",
    "wof:placetype":"venue"
},
  "geometry": {"coordinates":[-79.506027,43.731728],"type":"Point"}
}