{
  "type": "Feature",
  "properties": {
    "iso:country":"CA",
    "sg:city":"Surrey",
    "sg:classifiers":[
        {
            "category":"Manufacturing",
            "subcategory":"Food",
            "type":"Manufacturing & Wholesale Goods"
        }
    ],
    "sg:phone":"+1 604 580 6811",
    "sg:postcode":"V3R 0R8",
    "sg:province":"BC",
    "sg:tags":[
        "beverage"
    ],
    "wof:name":"Adams Beverages Ltd",
    "wof:placetype":"venue"
},
  "geometry": {"coordinates":[-122.853683,49.213188],"type":"Point"}
}