{
  "type": "Feature",
  "properties": {
    "iso:country":"CA",
    "sg:address":"1895 Rue DE LA Sidbec S",
    "sg:city":"Trois-Rivieres-Ouest",
    "sg:classifiers":[
        {
            "category":"Manufacturing",
            "subcategory":"Tools & Machinery",
            "type":"Manufacturing & Wholesale Goods"
        }
    ],
    "sg:phone":"+1 819 374 7093",
    "sg:postcode":"G8Z 4M6",
    "sg:province":"QC",
    "sg:tags":[
        "machine",
        "shop"
    ],
    "wof:name":"Plastiques Usines Clement Inc",
    "wof:placetype":"venue"
},
  "geometry": {"coordinates":[-72.5843048096,46.3319091797],"type":"Point"}
}