{
  "type": "Feature",
  "properties": {
    "addr:full":"Farm Kindersley SK S0L 1S0",
    "addr:postcode":"s0l 1s0",
    "addr:street":"Kindersley",
    "iso:country":"CA",
    "sg:address":"Farm",
    "sg:city":"Kindersley",
    "sg:classifiers":[
        {
            "category":"Professional",
            "subcategory":"Management & Consulting",
            "type":"Services"
        }
    ],
    "sg:phone":"+1 306 463 3468",
    "sg:postcode":"S0L 1S0",
    "sg:province":"SK",
    "sg:tags":[
        "fire",
        "consultant",
        "protection"
    ],
    "wof:name":"Pincem N Fire & Safety",
    "wof:placetype":"venue"
},
  "geometry": {"coordinates":[-109.16464233400001,51.4749336243],"type":"Point"}
}