{
  "type": "Feature",
  "properties": {
    "addr:full":"Alexandria ON K0C 1A0",
    "addr:postcode":"k0c 1a0",
    "iso:country":"CA",
    "sg:city":"Alexandria",
    "sg:classifiers":[
        {
            "category":"Retail",
            "subcategory":"Repair Shop",
            "type":"Services"
        }
    ],
    "sg:phone":"+1 613 525 1032",
    "sg:postcode":"K0C 1A0",
    "sg:province":"ON",
    "sg:tags":[
        "steel",
        "welding"
    ],
    "wof:name":"Sabourin Hubert Sanilit Ltd",
    "wof:placetype":"venue"
},
  "geometry": {"coordinates":[-74.629143,45.309299],"type":"Point"}
}