{
  "type": "Feature",
  "properties": {
    "addr:full":"Montreal QC H1L 1A5",
    "addr:postcode":"h1l 1a5",
    "iso:country":"CA",
    "sg:city":"Montreal",
    "sg:classifiers":[
        {
            "category":"Social Services",
            "type":"Services"
        }
    ],
    "sg:phone":"+1 514 351 6473",
    "sg:postcode":"H1L 1A5",
    "sg:province":"QC",
    "sg:tags":[
        "organization",
        "welfare"
    ],
    "wof:name":"Etincelle DE L'Amitie Inc",
    "wof:placetype":"venue"
},
  "geometry": {"coordinates":[-73.535858,45.594612],"type":"Point"}
}