{
  "type": "Feature",
  "properties": {
    "iso:country":"CA",
    "sg:address":"1550 Birchmount Rd",
    "sg:city":"Scarborough",
    "sg:classifiers":[
        {
            "category":"Manufacturing",
            "subcategory":"Furniture",
            "type":"Manufacturing & Wholesale Goods"
        }
    ],
    "sg:phone":"+1 416 285 8282",
    "sg:postcode":"M1P 2H1",
    "sg:province":"ON",
    "sg:tags":[
        "equipment",
        "refrigerating"
    ],
    "wof:name":"Rapid Refrigeration Mfg CO",
    "wof:placetype":"venue"
},
  "geometry": {"coordinates":[-79.2900695801,43.7598419189],"type":"Point"}
}