{
  "type": "Feature",
  "properties": {
    "iso:country":"CA",
    "sg:address":"5669 199 St",
    "sg:city":"Langley",
    "sg:classifiers":[
        {
            "category":"Home & Garden",
            "subcategory":"Building Materials",
            "type":"Retail Goods"
        }
    ],
    "sg:phone":"+1 604 532 7892",
    "sg:postcode":"V3A 1H9",
    "sg:province":"BC",
    "sg:tags":[
        "wood",
        "preserving",
        "preservative"
    ],
    "wof:name":"Mako Building Products Ltd",
    "wof:placetype":"venue"
},
  "geometry": {"coordinates":[-122.67111206,49.1054077148],"type":"Point"}
}