{
  "type": "Feature",
  "properties": {
    "addr:full":"171 Main St E North Bay ON P1B 1A9",
    "addr:housenumber":"171",
    "addr:postcode":"p1b 1a9",
    "addr:street":"Main St E",
    "iso:country":"CA",
    "sg:address":"171 Main St E",
    "sg:city":"North Bay",
    "sg:classifiers":[
        {
            "category":"Personal",
            "subcategory":"Beauty Salon",
            "type":"Services"
        }
    ],
    "sg:phone":"+1 705 497 0700",
    "sg:postcode":"P1B 1A9",
    "sg:province":"ON",
    "wof:name":"Hair Bizzare Head Quarters",
    "wof:placetype":"venue"
},
  "geometry": {"coordinates":[-79.4634170532,46.3094100952],"type":"Point"}
}