{
  "type": "Feature",
  "properties": {
    "addr:full":"550 Cochrane Dr Markham ON L3R 8E2",
    "addr:housenumber":"550",
    "addr:postcode":"l3r 8e2",
    "addr:street":"Cochrane Dr",
    "iso:country":"CA",
    "sg:address":"550 Cochrane Dr",
    "sg:city":"Markham",
    "sg:classifiers":[
        {
            "category":"Wholesale",
            "subcategory":"Stationery",
            "type":"Manufacturing & Wholesale Goods"
        }
    ],
    "sg:phone":"+1 416 495 0298",
    "sg:postcode":"L3R 8E2",
    "sg:province":"ON",
    "sg:tags":[
        "product",
        "paper"
    ],
    "wof:name":"Precision Fine Papers Inc",
    "wof:placetype":"venue"
},
  "geometry": {"coordinates":[-79.36549377439999,43.8439598083],"type":"Point"}
}