{
  "type": "Feature",
  "properties": {
    "iso:country":"CA",
    "sg:address":"88 Boul Saint-Jean-Baptiste",
    "sg:city":"Chateauguay",
    "sg:classifiers":[
        {
            "category":"Restaurant",
            "type":"Food & Drink"
        }
    ],
    "sg:phone":"+1 450 692 8112",
    "sg:postcode":"J6K 3A6",
    "sg:province":"QC",
    "wof:name":"Restaurant Tahiti Inc",
    "wof:placetype":"venue"
},
  "geometry": {"coordinates":[-73.714264,45.361076],"type":"Point"}
}