{
  "type": "Feature",
  "properties": {
    "addr:full":"930 Rue DE LA Berge Havre-Saint-Pierre QC G0G 1P0",
    "addr:housenumber":"930",
    "addr:postcode":"g0g 1p0",
    "addr:street":"Rue De La Berge",
    "iso:country":"CA",
    "sg:address":"930 Rue DE LA Berge",
    "sg:city":"Havre-Saint-Pierre",
    "sg:classifiers":[
        {
            "category":"Shopping",
            "subcategory":"Bicycles & Sporting Goods",
            "type":"Retail Goods"
        }
    ],
    "sg:phone":"+1 418 538 3456",
    "sg:postcode":"G0G 1P0",
    "sg:province":"QC",
    "wof:name":"Michel Elias Sport Ltee",
    "wof:placetype":"venue"
},
  "geometry": {"coordinates":[-63.607277,50.237377],"type":"Point"}
}