{
  "type": "Feature",
  "properties": {
    "iso:country":"CA",
    "sg:address":"591 Rue Roussin",
    "sg:city":"Lac-Saint-Charles",
    "sg:classifiers":[
        {
            "category":"Retail",
            "subcategory":"Auto Repair",
            "type":"Services"
        }
    ],
    "sg:phone":"+1 418 849 2886",
    "sg:postcode":"G3G 2C8",
    "sg:province":"QC",
    "sg:tags":[
        "repairing",
        "automobile"
    ],
    "wof:name":"Auto Action Plus",
    "wof:placetype":"venue"
},
  "geometry": {"coordinates":[-71.365562439,46.8911056519],"type":"Point"}
}