{
  "type": "Feature",
  "properties": {
    "addr:full":"271 Rang Lepage Sainte-Anne-Des-Plaines QC J0N 1H0",
    "addr:housenumber":"271",
    "addr:postcode":"j0n 1h0",
    "addr:street":"Rang Lepage",
    "iso:country":"CA",
    "sg:address":"271 Rang Lepage",
    "sg:city":"Sainte-Anne-Des-Plaines",
    "sg:classifiers":[
        {
            "category":"Wholesale",
            "subcategory":"Machinery & Supplies",
            "type":"Manufacturing & Wholesale Goods"
        }
    ],
    "sg:phone":"+1 450 478 2588",
    "sg:postcode":"J0N 1H0",
    "sg:province":"QC",
    "sg:tags":[
        "farm",
        "equipment"
    ],
    "wof:name":"Equipements Yvon Rivard Inc",
    "wof:placetype":"venue"
},
  "geometry": {"coordinates":[-73.80862399999999,45.731255],"type":"Point"}
}