{
  "type": "Feature",
  "properties": {
    "addr:full":"800 Boul DE Maisonneuve E Montreal QC H2L 4L8",
    "addr:housenumber":"800",
    "addr:postcode":"h2l 4l8",
    "addr:street":"Boul De Maisonneuve E",
    "iso:country":"CA",
    "sg:address":"800 Boul DE Maisonneuve E",
    "sg:city":"Montreal",
    "sg:classifiers":[
        {
            "category":"Retail",
            "subcategory":"Repair Shop",
            "type":"Services"
        }
    ],
    "sg:phone":"+1 514 908 9159",
    "sg:postcode":"H2L 4L8",
    "sg:province":"QC",
    "sg:tags":[
        "equipment",
        "conditioning",
        "air"
    ],
    "wof:name":"Empire Maintenance Ind",
    "wof:placetype":"venue"
},
  "geometry": {"coordinates":[-73.5602340698,45.5161552429],"type":"Point"}
}