{
  "type": "Feature",
  "properties": {
    "addr:full":"3604 40 Ave NW Edmonton AB T6L 6M8",
    "addr:housenumber":"3604",
    "addr:postcode":"t6l 6m8",
    "addr:street":"40 Ave Nw",
    "iso:country":"CA",
    "sg:address":"3604 40 Ave NW",
    "sg:city":"Edmonton",
    "sg:classifiers":[
        {
            "category":"Building & Trades",
            "subcategory":"Construction",
            "type":"Services"
        }
    ],
    "sg:phone":"+1 780 440 0748",
    "sg:postcode":"T6L 6M8",
    "sg:province":"AB",
    "sg:tags":[
        "plastering",
        "stucco",
        "contractor"
    ],
    "wof:name":"A & S Construction",
    "wof:placetype":"venue"
},
  "geometry": {"coordinates":[-113.39608,53.475471],"type":"Point"}
}