{
  "type": "Feature",
  "properties": {
    "addr:full":"16 Parkdale Ave N Hamilton ON L8H 5W8",
    "addr:housenumber":"16",
    "addr:postcode":"l8h 5w8",
    "addr:street":"Parkdale Ave N",
    "iso:country":"CA",
    "sg:address":"16 Parkdale Ave N",
    "sg:city":"Hamilton",
    "sg:classifiers":[
        {
            "category":"Food & Beverages",
            "subcategory":"Groceries & Convenience Stores",
            "type":"Retail Goods"
        }
    ],
    "sg:phone":"+1 905 312 8989",
    "sg:postcode":"L8H 5W8",
    "sg:province":"ON",
    "sg:tags":[
        "grocer"
    ],
    "wof:name":"Korean Food Market",
    "wof:placetype":"venue"
},
  "geometry": {"coordinates":[-79.7917098999,43.236782074],"type":"Point"}
}