{
  "type": "Feature",
  "properties": {
    "addr:full":"915 Meyerside Dr Mississauga ON L5T 1R8",
    "addr:housenumber":"915",
    "addr:postcode":"l5t 1r8",
    "addr:street":"Meyerside Dr",
    "iso:country":"CA",
    "sg:address":"915 Meyerside Dr",
    "sg:city":"Mississauga",
    "sg:classifiers":[
        {
            "category":"Wholesale",
            "subcategory":"Durable Goods & Equipment",
            "type":"Manufacturing & Wholesale Goods"
        }
    ],
    "sg:phone":"+1 905 564 1030",
    "sg:postcode":"L5T 1R8",
    "sg:province":"ON",
    "sg:tags":[
        "laboratory",
        "supply"
    ],
    "wof:name":"Prepared Media Laboratory",
    "wof:placetype":"venue"
},
  "geometry": {"coordinates":[-79.6669540405,43.6494636536],"type":"Point"}
}