{
  "type": "Feature",
  "properties": {
    "addr:full":"7685 Rue Edouard Lasalle QC H8P 1T7",
    "addr:housenumber":"7685",
    "addr:postcode":"h8p 1t7",
    "addr:street":"Rue Edouard",
    "iso:country":"CA",
    "sg:address":"7685 Rue Edouard",
    "sg:city":"Lasalle",
    "sg:classifiers":[
        {
            "category":"Education",
            "subcategory":"Special Training",
            "type":"Public Place"
        }
    ],
    "sg:phone":"+1 514 363 6771",
    "sg:postcode":"H8P 1T7",
    "sg:province":"QC",
    "sg:tags":[
        "instruction",
        "music"
    ],
    "wof:name":"Academie DE Musique DE Lasalle",
    "wof:placetype":"venue"
},
  "geometry": {"coordinates":[-73.5950622559,45.4296798706],"type":"Point"}
}