{
  "type": "Feature",
  "properties": {
    "addr:full":"349 Kenneth Ave North York ON M2N 4V9",
    "addr:housenumber":"349",
    "addr:postcode":"m2n 4v9",
    "addr:street":"Kenneth Ave",
    "iso:country":"CA",
    "sg:address":"349 Kenneth Ave",
    "sg:city":"North York",
    "sg:classifiers":[
        {
            "category":"Organizations",
            "subcategory":"Religious Organization",
            "type":"Services"
        }
    ],
    "sg:phone":"+1 416 225 2309",
    "sg:postcode":"M2N 4V9",
    "sg:province":"ON",
    "sg:tags":[
        "church"
    ],
    "wof:name":"Willowdale United Church",
    "wof:placetype":"venue"
},
  "geometry": {"coordinates":[-79.410202,43.775871],"type":"Point"}
}