{
  "type": "Feature",
  "properties": {
    "addr:full":"8100 Radium Golf Course Rd Radium Hot Springs BC V0A 1M0",
    "addr:housenumber":"8100",
    "addr:postcode":"v0a 1m0",
    "addr:street":"Radium Golf Course Rd",
    "iso:country":"CA",
    "sg:address":"8100 Radium Golf Course Rd",
    "sg:city":"Radium Hot Springs",
    "sg:classifiers":[
        {
            "category":"Sports & Exercise",
            "subcategory":"Golf",
            "type":"Entertainment"
        }
    ],
    "sg:phone":"+1 250 347 6266",
    "sg:postcode":"V0A 1M0",
    "sg:province":"BC",
    "sg:tags":[
        "resort",
        "course"
    ],
    "wof:name":"Radium Resort",
    "wof:placetype":"venue"
},
  "geometry": {"coordinates":[-116.07126599999999,50.621365],"type":"Point"}
}