{
  "type": "Feature",
  "properties": {
    "addr:full":"720 the West Mall Etobicoke ON M9C 4Y4",
    "addr:housenumber":"720",
    "addr:postcode":"m9c 4y4",
    "addr:street":"The West Mall",
    "iso:country":"CA",
    "sg:address":"720 the West Mall",
    "sg:city":"Etobicoke",
    "sg:classifiers":[
        {
            "category":"Recreation",
            "type":"Entertainment"
        }
    ],
    "sg:phone":"+1 416 621 8699",
    "sg:postcode":"M9C 4Y4",
    "sg:province":"ON",
    "sg:tags":[
        "center"
    ],
    "wof:name":"Buckingham Recreation Club",
    "wof:placetype":"venue"
},
  "geometry": {"coordinates":[-79.572205,43.655384],"type":"Point"}
}