{
  "type": "Feature",
  "properties": {
    "addr:full":"478 Rue Des Pignons Pohenegamook QC G0L 1J0",
    "addr:housenumber":"478",
    "addr:postcode":"g0l 1j0",
    "addr:street":"Rue Des Pignons Pohenegamook",
    "iso:country":"CA",
    "sg:address":"478 Rue Des Pignons",
    "sg:city":"Pohenegamook",
    "sg:classifiers":[
        {
            "category":"Building & Trades",
            "subcategory":"Landscaping Services",
            "type":"Services"
        }
    ],
    "sg:phone":"+1 418 859 3221",
    "sg:postcode":"G0L 1J0",
    "sg:province":"QC",
    "sg:tags":[
        "landscape",
        "contractor"
    ],
    "wof:name":"Pre-Vert Plus Inc",
    "wof:placetype":"venue"
},
  "geometry": {"coordinates":[-69.288353,47.493423],"type":"Point"}
}