{
  "type": "Feature",
  "properties": {
    "addr:full":"3323 Bloor St W Etobicoke ON M8X 1E7",
    "addr:housenumber":"3323",
    "addr:postcode":"m8x 1e7",
    "addr:street":"Bloor St W",
    "iso:country":"CA",
    "sg:address":"3323 Bloor St W",
    "sg:city":"Etobicoke",
    "sg:classifiers":[
        {
            "category":"Personal",
            "subcategory":"Beauty Salon",
            "type":"Services"
        }
    ],
    "sg:phone":"+1 416 231 0009",
    "sg:postcode":"M8X 1E7",
    "sg:province":"ON",
    "wof:name":"Lily's Hair Salon",
    "wof:placetype":"venue"
},
  "geometry": {"coordinates":[-79.520645,43.645168],"type":"Point"}
}