{
  "type": "Feature",
  "properties": {
    "addr:full":"3123 Carp Rd Carp ON K0A 1L0",
    "addr:housenumber":"3123",
    "addr:postcode":"k0a 1l0",
    "addr:street":"Carp Rd",
    "iso:country":"CA",
    "sg:address":"3123 Carp Rd",
    "sg:city":"Carp",
    "sg:classifiers":[
        {
            "category":"Organizations",
            "subcategory":"Religious Organization",
            "type":"Services"
        }
    ],
    "sg:phone":"+1 613 839 7528",
    "sg:postcode":"K0A 1L0",
    "sg:province":"ON",
    "sg:tags":[
        "church"
    ],
    "wof:name":"West Ottawa Christian Cmnty",
    "wof:placetype":"venue"
},
  "geometry": {"coordinates":[-76.00391399999999,45.318729],"type":"Point"}
}