{
  "type": "Feature",
  "properties": {
    "addr:full":"4967 Boul Des Laurentides Laval QC H7K 2J6",
    "addr:housenumber":"4967",
    "addr:postcode":"qc h7k 2j6",
    "addr:street":"Boul Des Laurentides",
    "iso:country":"CA",
    "sg:address":"4967 Boul Des Laurentides",
    "sg:city":"Laval",
    "sg:classifiers":[
        {
            "category":"Shopping",
            "type":"Retail Goods"
        }
    ],
    "sg:phone":"+1 450 625 2703",
    "sg:postcode":"H7K 2J6",
    "sg:province":"QC",
    "sg:tags":[
        "miscellaneous",
        "store"
    ],
    "wof:name":"Plaisir & Seduction",
    "wof:placetype":"venue"
},
  "geometry": {"coordinates":[-73.743988,45.619381],"type":"Point"}
}