{
  "type": "Feature",
  "properties": {
    "addr:full":"10 the Bridle Walk Gormley ON L0H 1G0",
    "addr:housenumber":"10",
    "addr:postcode":"l0h 1g0",
    "addr:street":"The Bridle Walk",
    "iso:country":"CA",
    "sg:address":"10 the Bridle Walk",
    "sg:city":"Gormley",
    "sg:classifiers":[
        {
            "category":"Building & Trades",
            "subcategory":"Construction",
            "type":"Services"
        }
    ],
    "sg:phone":"+1 905 887 3738",
    "sg:postcode":"L0H 1G0",
    "sg:province":"ON",
    "sg:tags":[
        "general",
        "contractor"
    ],
    "wof:name":"Mattamy Homes Ltd",
    "wof:placetype":"venue"
},
  "geometry": {"coordinates":[-79.37900500000001,43.94339],"type":"Point"}
}