{
  "type": "Feature",
  "properties": {
    "addr:full":"587 Mountain Rd Moncton NB E1C 2N9",
    "addr:housenumber":"587",
    "addr:postcode":"e1c 2n9",
    "addr:street":"Mountain Rd",
    "iso:country":"CA",
    "sg:address":"587 Mountain Rd",
    "sg:city":"Moncton",
    "sg:classifiers":[
        {
            "category":"Retail",
            "subcategory":"Portrait Studio",
            "type":"Services"
        }
    ],
    "sg:phone":"+1 506 854 3318",
    "sg:postcode":"E1C 2N9",
    "sg:province":"NB",
    "sg:tags":[
        "photographer"
    ],
    "wof:name":"Tom Barnes Photography",
    "wof:placetype":"venue"
},
  "geometry": {"coordinates":[-64.799026,46.098396],"type":"Point"}
}