{
  "type": "Feature",
  "properties": {
    "addr:full":"303 2nd Ave Beaverlodge AB T0H 0C0",
    "addr:housenumber":"303",
    "addr:postcode":"t0h 0c0",
    "addr:street":"2Nd Ave",
    "iso:country":"CA",
    "sg:address":"303 2nd Ave",
    "sg:city":"Beaverlodge",
    "sg:classifiers":[
        {
            "category":"Retail",
            "subcategory":"Auto Repair",
            "type":"Services"
        }
    ],
    "sg:phone":"+1 780 354 8982",
    "sg:postcode":"T0H 0C0",
    "sg:province":"AB",
    "sg:tags":[
        "repairing",
        "automobile"
    ],
    "wof:name":"J R Sales & Rentals",
    "wof:placetype":"venue"
},
  "geometry": {"coordinates":[-119.424919,55.20702],"type":"Point"}
}