{
  "type": "Feature",
  "properties": {
    "addr:full":"288 Welton St Sydney NS B1P 5S4",
    "addr:housenumber":"288",
    "addr:postcode":"b1p 5s4",
    "addr:street":"Welton St",
    "iso:country":"CA",
    "sg:address":"288 Welton St",
    "sg:city":"Sydney",
    "sg:classifiers":[
        {
            "category":"Wholesale",
            "subcategory":"Machinery & Supplies",
            "type":"Manufacturing & Wholesale Goods"
        }
    ],
    "sg:phone":"+1 902 562 8557",
    "sg:postcode":"B1P 5S4",
    "sg:province":"NS",
    "sg:tags":[
        "salon",
        "beauty"
    ],
    "wof:name":"Maritime Beauty Supply CO Ltd",
    "wof:placetype":"venue"
},
  "geometry": {"coordinates":[-60.164604,46.143578],"type":"Point"}
}