{
  "type": "Feature",
  "properties": {
    "addr:full":"Calgary AB T2E 6T5",
    "addr:postcode":"t2e 6t5",
    "iso:country":"CA",
    "sg:city":"Calgary",
    "sg:classifiers":[
        {
            "category":"Manufacturing",
            "subcategory":"Chemicals & Compounds",
            "type":"Manufacturing & Wholesale Goods"
        }
    ],
    "sg:phone":"+1 403 250 9493",
    "sg:postcode":"T2E 6T5",
    "sg:province":"AB",
    "sg:tags":[
        "product",
        "polyurethane",
        "plastic"
    ],
    "wof:name":"Duraprene Industries Ltd",
    "wof:placetype":"venue"
},
  "geometry": {"coordinates":[-114.00885,51.084717],"type":"Point"}
}