{
  "type": "Feature",
  "properties": {
    "addr:full":"54 Rexdale Blvd Etobicoke ON M9W 1N7",
    "addr:housenumber":"54",
    "addr:postcode":"m9w 1n7",
    "addr:street":"Rexdale Blvd",
    "iso:country":"CA",
    "sg:address":"54 Rexdale Blvd",
    "sg:city":"Etobicoke",
    "sg:classifiers":[
        {
            "category":"Food & Beverages",
            "subcategory":"Groceries & Convenience Stores",
            "type":"Retail Goods"
        }
    ],
    "sg:phone":"+1 416 749 1037",
    "sg:postcode":"M9W 1N7",
    "sg:province":"ON",
    "sg:tags":[
        "grocer"
    ],
    "wof:name":"Sara Convenience",
    "wof:placetype":"venue"
},
  "geometry": {"coordinates":[-79.5603179932,43.7134284973],"type":"Point"}
}