{
  "type": "Feature",
  "properties": {
    "addr:full":"622 Front St Nelson BC V1L 4B7",
    "addr:housenumber":"622",
    "addr:postcode":"bc v1l 4b7",
    "addr:street":"Front St",
    "iso:country":"CA",
    "sg:address":"622 Front St",
    "sg:city":"Nelson",
    "sg:classifiers":[
        {
            "category":"Shopping",
            "subcategory":"Hobbies, Toys, & Games",
            "type":"Retail Goods"
        }
    ],
    "sg:phone":"+1 250 354 4919",
    "sg:postcode":"V1L 4B7",
    "sg:province":"BC",
    "sg:tags":[
        "craft"
    ],
    "wof:name":"Creative Scrapbooking",
    "wof:placetype":"venue"
},
  "geometry": {"coordinates":[-117.29405199999999,49.494602],"type":"Point"}
}