{
  "type": "Feature",
  "properties": {
    "iso:country":"CA",
    "sg:address":"275 Export Blvd",
    "sg:city":"Mississauga",
    "sg:classifiers":[
        {
            "category":"Freight",
            "type":"Transportation"
        }
    ],
    "sg:phone":"+1 905 564 8855",
    "sg:postcode":"L5S 1Y4",
    "sg:province":"ON",
    "sg:tags":[
        "mover"
    ],
    "wof:name":"Brytor International Moving",
    "wof:placetype":"venue"
},
  "geometry": {"coordinates":[-79.703049,43.651897],"type":"Point"}
}