{
  "type": "Feature",
  "properties": {
    "addr:full":"48 Rue Saint-Andre Metabetchouan-Lac-A-LA-Croix QC G8G 1T9",
    "addr:housenumber":"48",
    "addr:postcode":"g8g 1t9",
    "addr:street":"Rue Saint-Andre",
    "iso:country":"CA",
    "sg:address":"48 Rue Saint-Andre",
    "sg:city":"Metabetchouan-Lac-A-LA-Croix",
    "sg:classifiers":[
        {
            "category":"Health Services",
            "subcategory":"Nursing And Care Facility",
            "type":"Services"
        }
    ],
    "sg:phone":"+1 418 349 2502",
    "sg:postcode":"G8G 1T9",
    "sg:province":"QC",
    "sg:tags":[
        "home",
        "retirement",
        "community"
    ],
    "wof:name":"Residence Le Majeur",
    "wof:placetype":"venue"
},
  "geometry": {"coordinates":[-71.870735,48.429821],"type":"Point"}
}