{
  "type": "Feature",
  "properties": {
    "addr:full":"649 Chalmers Ave Winnipeg MB R2L 0G7",
    "addr:housenumber":"649",
    "addr:postcode":"r2l 0g7",
    "addr:street":"Chalmers Ave",
    "iso:country":"CA",
    "sg:address":"649 Chalmers Ave",
    "sg:city":"Winnipeg",
    "sg:classifiers":[
        {
            "category":"Shopping",
            "type":"Retail Goods"
        }
    ],
    "sg:phone":"+1 204 661 5455",
    "sg:postcode":"R2L 0G7",
    "sg:province":"MB",
    "sg:tags":[
        "ice"
    ],
    "wof:name":"Krystal Dreams Ice Sculptures",
    "wof:placetype":"venue"
},
  "geometry": {"coordinates":[-97.093231,49.908337],"type":"Point"}
}