{
  "type": "Feature",
  "properties": {
    "addr:full":"1624 Ch Parc Industriel Roberval QC G8H 2M9",
    "addr:housenumber":"1624",
    "addr:postcode":"g8h 2m9",
    "addr:street":"Ch Parc Industriel",
    "iso:country":"CA",
    "sg:address":"1624 Ch Parc Industriel",
    "sg:city":"Roberval",
    "sg:classifiers":[
        {
            "category":"Retail",
            "subcategory":"Auto Repair",
            "type":"Services"
        }
    ],
    "sg:phone":"+1 418 275 5611",
    "sg:postcode":"G8H 2M9",
    "sg:province":"QC",
    "sg:tags":[
        "truck"
    ],
    "wof:name":"Garage Gmr Inc",
    "wof:placetype":"venue"
},
  "geometry": {"coordinates":[-72.2562332153,48.5319671631],"type":"Point"}
}