{
  "type": "Feature",
  "properties": {
    "addr:full":"Winnipeg MB R2X 2R8",
    "addr:postcode":"r2x 2r8",
    "iso:country":"CA",
    "sg:city":"Winnipeg",
    "sg:classifiers":[
        {
            "category":"Real Estate",
            "subcategory":"Real Estate Agent",
            "type":"Services"
        }
    ],
    "sg:phone":"+1 204 632 0746",
    "sg:postcode":"R2X 2R8",
    "sg:province":"MB",
    "sg:tags":[
        "housing"
    ],
    "wof:name":"Willow Park Housing CO-OP Ltd",
    "wof:placetype":"venue"
},
  "geometry": {"coordinates":[-97.19263458250001,49.9361076355],"type":"Point"}
}