{
  "type": "Feature",
  "properties": {
    "addr:full":"Vancouver BC V6C 3L2",
    "addr:postcode":"v6c 3l2",
    "iso:country":"CA",
    "sg:city":"Vancouver",
    "sg:classifiers":[
        {
            "category":"Professional",
            "subcategory":"Business Services",
            "type":"Services"
        }
    ],
    "sg:phone":"+1 604 682 8663",
    "sg:postcode":"V6C 3L2",
    "sg:province":"BC",
    "sg:tags":[
        "translator",
        "interpreter"
    ],
    "wof:name":"Zone Communications",
    "wof:placetype":"venue"
},
  "geometry": {"coordinates":[-123.120132,49.284039],"type":"Point"}
}