{
  "type": "Feature",
  "properties": {
    "addr:full":"199 Langstaff Dr Carp ON K0A 1L0",
    "addr:housenumber":"199",
    "addr:postcode":"k0a 1l0",
    "addr:street":"Langstaff Dr",
    "iso:country":"CA",
    "sg:address":"199 Langstaff Dr",
    "sg:city":"Carp",
    "sg:classifiers":[
        {
            "category":"Recreation",
            "type":"Entertainment"
        }
    ],
    "sg:phone":"+1 613 839 3177",
    "sg:postcode":"K0A 1L0",
    "sg:province":"ON",
    "sg:tags":[
        "club",
        "curling"
    ],
    "wof:name":"Huntley Curling Club",
    "wof:placetype":"venue"
},
  "geometry": {"coordinates":[-76.0349349976,45.3485298157],"type":"Point"}
}