{
  "type": "Feature",
  "properties": {
    "addr:full":"37 Woodlawn Rd Dartmouth NS B2W 2R7",
    "addr:housenumber":"37",
    "addr:postcode":"b2w 2r7",
    "addr:street":"Woodlawn Rd",
    "iso:country":"CA",
    "sg:address":"37 Woodlawn Rd",
    "sg:city":"Dartmouth",
    "sg:classifiers":[
        {
            "category":"Education",
            "subcategory":"School",
            "type":"Public Place"
        }
    ],
    "sg:phone":"+1 902 435 8452",
    "sg:postcode":"B2W 2R7",
    "sg:province":"NS",
    "wof:name":"Prince Andrew High School",
    "wof:placetype":"venue"
},
  "geometry": {"coordinates":[-63.5270729065,44.6811408997],"type":"Point"}
}