{
  "type": "Feature",
  "properties": {
    "iso:country":"CA",
    "sg:address":"9333 Manzer St",
    "sg:city":"Mission",
    "sg:classifiers":[
        {
            "category":"Building & Trades",
            "subcategory":"Construction",
            "type":"Services"
        }
    ],
    "sg:phone":"+1 604 826 5936",
    "sg:postcode":"V4S 1K2",
    "sg:province":"BC",
    "sg:tags":[
        "excavating",
        "contractor"
    ],
    "wof:name":"Mission Contractors Ltd",
    "wof:placetype":"venue"
},
  "geometry": {"coordinates":[-122.38246154799999,49.1722297668],"type":"Point"}
}