{
  "type": "Feature",
  "properties": {
    "iso:country":"CA",
    "sg:address":"6426 Birch Bay Rd",
    "sg:city":"Horsefly",
    "sg:classifiers":[
        {
            "category":"Marine",
            "type":"Transportation"
        }
    ],
    "sg:phone":"+1 250 620 3504",
    "sg:postcode":"V0L 1L0",
    "sg:province":"BC",
    "sg:tags":[
        "towing"
    ],
    "wof:name":"Clearwater Tug Ltd",
    "wof:placetype":"venue"
},
  "geometry": {"coordinates":[-121.407501,52.331345],"type":"Point"}
}