{
  "type": "Feature",
  "properties": {
    "iso:country":"CA",
    "sg:address":"20286 Michaud Cres",
    "sg:city":"Langley",
    "sg:classifiers":[
        {
            "category":"Food & Beverages",
            "subcategory":"Fruits & Vegetables",
            "type":"Retail Goods"
        }
    ],
    "sg:phone":"+1 604 534 4963",
    "sg:postcode":"V3A 4B2",
    "sg:province":"BC",
    "sg:tags":[
        "produce"
    ],
    "wof:name":"Langley Produce Market",
    "wof:placetype":"venue"
},
  "geometry": {"coordinates":[-122.660301209,49.1030464172],"type":"Point"}
}