{
  "type": "Feature",
  "properties": {
    "addr:full":"690 Queen St E Sault Ste Marie ON P6A 2A4",
    "addr:housenumber":"690",
    "addr:postcode":"p6a 2a4",
    "addr:street":"Queen St E",
    "iso:country":"CA",
    "sg:address":"690 Queen St E",
    "sg:city":"Sault Ste Marie",
    "sg:classifiers":[
        {
            "category":"Health Services",
            "subcategory":"Health Practitioner",
            "type":"Services"
        }
    ],
    "sg:phone":"+1 705 942 9662",
    "sg:postcode":"P6A 2A4",
    "sg:province":"ON",
    "sg:tags":[
        "psychologist"
    ],
    "wof:name":"Isbitsky, J R",
    "wof:placetype":"venue"
},
  "geometry": {"coordinates":[-84.32804870610001,46.5080871582],"type":"Point"}
}