{
  "type": "Feature",
  "properties": {
    "iso:country":"CA",
    "sg:address":"390 Springbank Dr",
    "sg:city":"London",
    "sg:classifiers":[
        {
            "category":"Restaurant",
            "type":"Food & Drink"
        }
    ],
    "sg:phone":"+1 519 473 5521",
    "sg:postcode":"N6J 1G9",
    "sg:province":"ON",
    "wof:name":"Fatty Patty's Restaurants Inc",
    "wof:placetype":"venue"
},
  "geometry": {"coordinates":[-81.2824554443,42.9686050415],"type":"Point"}
}