{
  "type": "Feature",
  "properties": {
    "addr:full":"120 Thornhill Dr Dartmouth NS B3B 1S3",
    "addr:housenumber":"120",
    "addr:postcode":"b3b 1s3",
    "addr:street":"Thornhill Dr",
    "iso:country":"CA",
    "sg:address":"120 Thornhill Dr",
    "sg:city":"Dartmouth",
    "sg:classifiers":[
        {
            "category":"Manufacturing",
            "subcategory":"Metals",
            "type":"Manufacturing & Wholesale Goods"
        }
    ],
    "sg:phone":"+1 902 468 6776",
    "sg:postcode":"B3B 1S3",
    "sg:province":"NS",
    "sg:tags":[
        "foundry"
    ],
    "wof:name":"Imp Group Foundry",
    "wof:placetype":"venue"
},
  "geometry": {"coordinates":[-63.5940246582,44.6927833557],"type":"Point"}
}