{
  "type": "Feature",
  "properties": {
    "addr:full":"640 West St Brantford ON N3R 6M3",
    "addr:housenumber":"640",
    "addr:postcode":"n3r 6m3",
    "addr:street":"West St",
    "iso:country":"CA",
    "sg:address":"640 West St",
    "sg:city":"Brantford",
    "sg:classifiers":[
        {
            "category":"Real Estate",
            "subcategory":"Real Estate Operator",
            "type":"Services"
        }
    ],
    "sg:phone":"+1 519 752 8301",
    "sg:postcode":"N3R 6M3",
    "sg:province":"ON",
    "sg:tags":[
        "condominium"
    ],
    "wof:name":"Village Tower Brant Condo",
    "wof:placetype":"venue"
},
  "geometry": {"coordinates":[-80.2481842041,43.1723823547],"type":"Point"}
}