{
  "type": "Feature",
  "properties": {
    "addr:full":"223 Rue Provost Sorel-Tracy QC J3P 1R8",
    "addr:housenumber":"223",
    "addr:postcode":"j3p 1r8",
    "addr:street":"Rue Provost",
    "iso:country":"CA",
    "sg:address":"223 Rue Provost",
    "sg:city":"Sorel-Tracy",
    "sg:classifiers":[
        {
            "category":"Building & Trades",
            "subcategory":"Construction",
            "type":"Services"
        }
    ],
    "sg:phone":"+1 450 742 1460",
    "sg:postcode":"J3P 1R8",
    "sg:province":"QC",
    "sg:tags":[
        "concrete",
        "contractor"
    ],
    "wof:name":"Sorel Tracy Ciment Inc",
    "wof:placetype":"venue"
},
  "geometry": {"coordinates":[-73.103027,46.043575],"type":"Point"}
}