{
  "type": "Feature",
  "properties": {
    "iso:country":"CA",
    "sg:address":"270 Main St",
    "sg:city":"Cardston",
    "sg:classifiers":[
        {
            "category":"Retail",
            "subcategory":"Auto Repair",
            "type":"Services"
        }
    ],
    "sg:phone":"+1 403 653 3385",
    "sg:postcode":"T0K 0K0",
    "sg:province":"AB",
    "sg:tags":[
        "body",
        "automobile",
        "painting"
    ],
    "wof:name":"D & T Autobody",
    "wof:placetype":"venue"
},
  "geometry": {"coordinates":[-113.30155944800001,49.1997871399],"type":"Point"}
}