{
  "type": "Feature",
  "properties": {
    "iso:country":"CA",
    "sg:address":"20 Baif Blvd # 107",
    "sg:city":"Richmond Hill",
    "sg:classifiers":[
        {
            "category":"Real Estate",
            "subcategory":"Real Estate Operator",
            "type":"Services"
        }
    ],
    "sg:phone":"+1 905 737 6116",
    "sg:postcode":"L4C 8T1",
    "sg:province":"ON",
    "sg:tags":[
        "condominium"
    ],
    "wof:name":"Yrcc 601",
    "wof:placetype":"venue"
},
  "geometry": {"coordinates":[-79.435493,43.858353],"type":"Point"}
}