{
  "type": "Feature",
  "properties": {
    "addr:full":"3031 Mackenzie Ave N Williams Lake BC V2G 1P5",
    "addr:housenumber":"3031",
    "addr:postcode":"v2g 1p5",
    "addr:street":"Mackenzie Ave N",
    "iso:country":"CA",
    "sg:address":"3031 Mackenzie Ave N",
    "sg:city":"Williams Lake",
    "sg:classifiers":[
        {
            "category":"Manufacturing",
            "subcategory":"Tools & Machinery",
            "type":"Manufacturing & Wholesale Goods"
        }
    ],
    "sg:phone":"+1 250 392 7117",
    "sg:postcode":"V2G 1P5",
    "sg:province":"BC",
    "sg:tags":[
        "steel",
        "machine",
        "shop"
    ],
    "wof:name":"Scorpion Design & Fabricating",
    "wof:placetype":"venue"
},
  "geometry": {"coordinates":[-122.170196533,52.1473731995],"type":"Point"}
}