{
  "type": "Feature",
  "properties": {
    "addr:full":"420 Prospect Ave Cabri SK S0N 0J0",
    "addr:housenumber":"420",
    "addr:postcode":"s0n 0j0",
    "addr:street":"Prospect Ave",
    "iso:country":"CA",
    "sg:address":"420 Prospect Ave",
    "sg:city":"Cabri",
    "sg:classifiers":[
        {
            "category":"Education",
            "subcategory":"School",
            "type":"Public Place"
        }
    ],
    "sg:phone":"+1 306 587 2229",
    "sg:postcode":"S0N 0J0",
    "sg:province":"SK",
    "wof:name":"Cabri School",
    "wof:placetype":"venue"
},
  "geometry": {"coordinates":[-108.456886,50.620476],"type":"Point"}
}