{
  "type": "Feature",
  "properties": {
    "addr:full":"288 Caswell Dr Sudbury ON P3E 2N8",
    "addr:housenumber":"288",
    "addr:postcode":"p3e 2n8",
    "addr:street":"Caswell Dr",
    "iso:country":"CA",
    "sg:address":"288 Caswell Dr",
    "sg:city":"Sudbury",
    "sg:classifiers":[
        {
            "category":"Sports & Exercise",
            "subcategory":"Gym",
            "type":"Entertainment"
        }
    ],
    "sg:phone":"+1 705 524 2787",
    "sg:postcode":"P3E 2N8",
    "sg:province":"ON",
    "sg:tags":[
        "club",
        "gymnasium",
        "program",
        "health",
        "fitness",
        "studio",
        "physical"
    ],
    "wof:name":"Curves For Women",
    "wof:placetype":"venue"
},
  "geometry": {"coordinates":[-81.0063858032,46.4566001892],"type":"Point"}
}