{
  "type": "Feature",
  "properties": {
    "addr:full":"5526 South River Dr Manotick ON K4M 1J3",
    "addr:housenumber":"5526",
    "addr:postcode":"k4m 1j3",
    "addr:street":"South River Dr",
    "iso:country":"CA",
    "sg:address":"5526 South River Dr",
    "sg:city":"Manotick",
    "sg:classifiers":[
        {
            "category":"Building & Trades",
            "subcategory":"Construction",
            "type":"Services"
        }
    ],
    "sg:phone":"+1 613 692 3850",
    "sg:postcode":"K4M 1J3",
    "sg:province":"ON",
    "sg:tags":[
        "general",
        "contractor"
    ],
    "wof:name":"Chuchryk Construction",
    "wof:placetype":"venue"
},
  "geometry": {"coordinates":[-75.68026,45.228252],"type":"Point"}
}