{
  "type": "Feature",
  "properties": {
    "iso:country":"CA",
    "sg:city":"Edmonton",
    "sg:classifiers":[
        {
            "category":"Real Estate",
            "subcategory":"Real Estate Agent",
            "type":"Services"
        }
    ],
    "sg:phone":"+1 780 428 9607",
    "sg:postcode":"T5J 1J4",
    "sg:province":"AB",
    "sg:tags":[
        "management"
    ],
    "wof:name":"Obam Properties",
    "wof:placetype":"venue"
},
  "geometry": {"coordinates":[-113.504989624,53.5413284302],"type":"Point"}
}