{
  "type": "Feature",
  "properties": {
    "addr:full":"Arnprior ON K7S 3T9",
    "addr:postcode":"k7s 3t9",
    "iso:country":"CA",
    "sg:city":"Arnprior",
    "sg:classifiers":[
        {
            "category":"Professional",
            "subcategory":"Lawyer & Legal Services",
            "type":"Services"
        }
    ],
    "sg:phone":"+1 613 623 6593",
    "sg:postcode":"K7S 3T9",
    "sg:province":"ON",
    "sg:tags":[
        "attorney"
    ],
    "wof:name":"Merla, Christopher",
    "wof:placetype":"venue"
},
  "geometry": {"coordinates":[-76.355164,45.433998],"type":"Point"}
}