{
  "type": "Feature",
  "properties": {
    "addr:full":"1001 3rd Ave N Saskatoon SK S7K 2K5",
    "addr:housenumber":"1001",
    "addr:postcode":"s7k 2k5",
    "addr:street":"3Rd Ave N",
    "iso:country":"CA",
    "sg:address":"1001 3rd Ave N",
    "sg:city":"Saskatoon",
    "sg:classifiers":[
        {
            "category":"Banks & Credit Unions",
            "subcategory":"Investment Brokerage",
            "type":"Services"
        }
    ],
    "sg:phone":"+1 306 244 3030",
    "sg:postcode":"S7K 2K5",
    "sg:province":"SK",
    "wof:name":"Ifs Securities Inc",
    "wof:placetype":"venue"
},
  "geometry": {"coordinates":[-106.65836299999999,52.142712],"type":"Point"}
}