{
  "type": "Feature",
  "properties": {
    "addr:full":"Alexandria ON K0C 1A0",
    "addr:postcode":"k0c 1a0",
    "iso:country":"CA",
    "sg:city":"Alexandria",
    "sg:classifiers":[
        {
            "category":"Education",
            "subcategory":"School",
            "type":"Public Place"
        }
    ],
    "sg:phone":"+1 613 525 4194",
    "sg:postcode":"K0C 1A0",
    "sg:province":"ON",
    "sg:tags":[
        "academic",
        "special"
    ],
    "wof:name":"A LA Page",
    "wof:placetype":"venue"
},
  "geometry": {"coordinates":[-74.637039,45.31411],"type":"Point"}
}