{
  "type": "Feature",
  "properties": {
    "addr:full":"Cfb Borden ON L0M 1C0",
    "addr:postcode":"l0m 1c0",
    "iso:country":"CA",
    "sg:address":"Cfb",
    "sg:city":"Borden",
    "sg:classifiers":[
        {
            "category":"Government",
            "subcategory":"Office",
            "type":"Public Place"
        }
    ],
    "sg:phone":"+1 705 474 5789",
    "sg:postcode":"L0M 1C0",
    "sg:province":"ON",
    "wof:name":"Canada Defense Construction",
    "wof:placetype":"venue"
},
  "geometry": {"coordinates":[-79.894722,44.284149],"type":"Point"}
}