{
  "type": "Feature",
  "properties": {
    "addr:full":"237 1st St Shaughnessy AB T0K 2A0",
    "addr:housenumber":"237",
    "addr:postcode":"t0k 2a0",
    "addr:street":"1St St",
    "iso:country":"CA",
    "sg:address":"237 1st St",
    "sg:city":"Shaughnessy",
    "sg:classifiers":[
        {
            "category":"Food & Beverages",
            "subcategory":"Groceries & Convenience Stores",
            "type":"Retail Goods"
        }
    ],
    "sg:phone":"+1 403 381 3611",
    "sg:postcode":"T0K 2A0",
    "sg:province":"AB",
    "sg:tags":[
        "grocer"
    ],
    "wof:name":"Heritage Grocery",
    "wof:placetype":"venue"
},
  "geometry": {"coordinates":[-112.843155,49.850941],"type":"Point"}
}