{
  "type": "Feature",
  "properties": {
    "addr:full":"White Lakes Rd Corner Brook NL A2H 6J3",
    "addr:postcode":"a2h 6j3",
    "addr:street":"White Lakes Rd",
    "iso:country":"CA",
    "sg:address":"White Lakes Rd",
    "sg:city":"Corner Brook",
    "sg:classifiers":[
        {
            "category":"Freight",
            "type":"Transportation"
        }
    ],
    "sg:phone":"+1 709 634 4763",
    "sg:postcode":"A2H 6J3",
    "sg:province":"NL",
    "sg:tags":[
        "trucking"
    ],
    "wof:name":"Way's Transport Ltd",
    "wof:placetype":"venue"
},
  "geometry": {"coordinates":[-57.949471,48.950199],"type":"Point"}
}