{
  "type": "Feature",
  "properties": {
    "addr:full":"22 King St Miramichi NB E1N 2N1",
    "addr:housenumber":"22",
    "addr:postcode":"e1n 2n1",
    "addr:street":"King St",
    "iso:country":"CA",
    "sg:address":"22 King St",
    "sg:city":"Miramichi",
    "sg:classifiers":[
        {
            "category":"Restaurant",
            "type":"Food & Drink"
        }
    ],
    "sg:phone":"+1 506 773 6909",
    "sg:postcode":"E1N 2N1",
    "sg:province":"NB",
    "wof:name":"Dixie Lee Family Restaurant",
    "wof:placetype":"venue"
},
  "geometry": {"coordinates":[-65.4669952393,47.0316543579],"type":"Point"}
}