{
  "type": "Feature",
  "properties": {
    "addr:full":"Fort Nelson BC V0C 1R0",
    "addr:postcode":"bc v0c 1r0",
    "iso:country":"CA",
    "sg:city":"Fort Nelson",
    "sg:classifiers":[
        {
            "category":"Professional",
            "subcategory":"Research",
            "type":"Services"
        }
    ],
    "sg:phone":"+1 250 774 6727",
    "sg:postcode":"V0C 1R0",
    "sg:province":"BC",
    "sg:tags":[
        "environmental",
        "ecological",
        "general",
        "contractor"
    ],
    "wof:name":"Cf Wright Transport Ltd",
    "wof:placetype":"venue"
},
  "geometry": {"coordinates":[-122.67758178699999,58.7973213196],"type":"Point"}
}