{
  "type": "Feature",
  "properties": {
    "addr:full":"2224 Orient Park Dr Gloucester ON K1B 4W2",
    "addr:housenumber":"2224",
    "addr:postcode":"k1b 4w2",
    "addr:street":"Orient Park Dr",
    "iso:country":"CA",
    "sg:address":"2224 Orient Park Dr",
    "sg:city":"Gloucester",
    "sg:classifiers":[
        {
            "category":"Professional",
            "subcategory":"Accounting & Tax Preparation",
            "type":"Services"
        }
    ],
    "sg:phone":"+1 613 830 5191",
    "sg:postcode":"K1B 4W2",
    "sg:province":"ON",
    "sg:tags":[
        "return",
        "filing"
    ],
    "wof:name":"Padgett Business Svc",
    "wof:placetype":"venue"
},
  "geometry": {"coordinates":[-75.5599060059,45.4328918457],"type":"Point"}
}