{
  "type": "Feature",
  "properties": {
    "addr:full":"1458 Rue DE LA Colline Cap-Rouge QC G1Y 2Z8",
    "addr:housenumber":"1458",
    "addr:postcode":"g1y 2z8",
    "addr:street":"Rue De La Colline",
    "iso:country":"CA",
    "sg:address":"1458 Rue DE LA Colline",
    "sg:city":"Cap-Rouge",
    "sg:classifiers":[
        {
            "category":"Professional",
            "subcategory":"Business Services",
            "type":"Services"
        }
    ],
    "sg:phone":"+1 418 657 4030",
    "sg:postcode":"G1Y 2Z8",
    "sg:province":"QC",
    "sg:tags":[
        "translator",
        "interpreter",
        "engineer"
    ],
    "wof:name":"Belle-Isle Traduction Tech",
    "wof:placetype":"venue"
},
  "geometry": {"coordinates":[-71.349304,46.751575],"type":"Point"}
}