{
  "type": "Feature",
  "properties": {
    "addr:full":"515 Boul Everard H Daigle Grand-Sault/Grand Falls NB E3Z 2R5",
    "addr:housenumber":"515",
    "addr:postcode":"e3z 2r5",
    "addr:street":"Boul Everard H Daigle",
    "iso:country":"CA",
    "sg:address":"515 Boul Everard H Daigle",
    "sg:city":"Grand-Sault/Grand Falls",
    "sg:classifiers":[
        {
            "category":"Retail",
            "subcategory":"Funeral Services",
            "type":"Services"
        }
    ],
    "sg:phone":"+1 506 473 3063",
    "sg:postcode":"E3Z 2R5",
    "sg:province":"NB",
    "sg:tags":[
        "director"
    ],
    "wof:name":"Maison Funeraire Guy L'o Regan",
    "wof:placetype":"venue"
},
  "geometry": {"coordinates":[-67.749352,47.046989],"type":"Point"}
}