{
  "type": "Feature",
  "properties": {
    "addr:full":"16 Memel Rd Hopewell Hill NB E4H 3L2",
    "addr:housenumber":"16",
    "addr:postcode":"e4h 3l2",
    "addr:street":"Memel Rd",
    "iso:country":"CA",
    "sg:address":"16 Memel Rd",
    "sg:city":"Hopewell Hill",
    "sg:classifiers":[
        {
            "category":"Retail",
            "subcategory":"Auto Repair",
            "type":"Services"
        }
    ],
    "sg:phone":"+1 506 882 2872",
    "sg:postcode":"E4H 3L2",
    "sg:province":"NB",
    "sg:tags":[
        "repairing",
        "automobile"
    ],
    "wof:name":"Dixon's Repair Shop Ltd",
    "wof:placetype":"venue"
},
  "geometry": {"coordinates":[-64.68358600000001,45.766911],"type":"Point"}
}