{
  "type": "Feature",
  "properties": {
    "addr:full":"650 Georgia St W # 2110 Vancouver BC V6B 6L7",
    "addr:housenumber":"650",
    "addr:postcode":"v6b 6l7",
    "addr:street":"Georgia St W # 2110",
    "iso:country":"CA",
    "sg:address":"650 Georgia St W # 2110",
    "sg:city":"Vancouver",
    "sg:classifiers":[
        {
            "category":"Banks & Credit Unions",
            "subcategory":"Investment Brokerage",
            "type":"Services"
        }
    ],
    "sg:phone":"+1 604 718 7100",
    "sg:postcode":"V6B 6L7",
    "sg:province":"BC",
    "sg:tags":[
        "advisory",
        "financial"
    ],
    "wof:name":"Scotia Private Client Group",
    "wof:placetype":"venue"
},
  "geometry": {"coordinates":[-123.11769866900001,49.282081604],"type":"Point"}
}