{
  "type": "Feature",
  "properties": {
    "addr:full":"4 Queen St W Elmvale ON L0L 1P0",
    "addr:housenumber":"4",
    "addr:postcode":"l0l 1p0",
    "addr:street":"Queen St W",
    "iso:country":"CA",
    "sg:address":"4 Queen St W",
    "sg:city":"Elmvale",
    "sg:classifiers":[
        {
            "category":"Home & Garden",
            "subcategory":"Hardware",
            "type":"Retail Goods"
        }
    ],
    "sg:phone":"+1 705 322 1123",
    "sg:postcode":"L0L 1P0",
    "sg:province":"ON",
    "wof:name":"Campbell's Hardware",
    "wof:placetype":"venue"
},
  "geometry": {"coordinates":[-79.866325,44.583599],"type":"Point"}
}