{
  "type": "Feature",
  "properties": {
    "addr:full":"Farm RR 1 North Battleford SK S9A 2X3",
    "addr:postcode":"s9a 2x3",
    "addr:street":"Rr 1",
    "iso:country":"CA",
    "sg:address":"Farm RR 1",
    "sg:city":"North Battleford",
    "sg:classifiers":[
        {
            "category":"Farming",
            "subcategory":"Nursery",
            "type":"Manufacturing & Wholesale Goods"
        }
    ],
    "sg:phone":"+1 306 445 5630",
    "sg:postcode":"S9A 2X3",
    "sg:province":"SK",
    "sg:tags":[
        "seed"
    ],
    "wof:name":"Doug Illingworth Seeds Ltd",
    "wof:placetype":"venue"
},
  "geometry": {"coordinates":[-108.31314086899999,52.7362365723],"type":"Point"}
}