{
  "type": "Feature",
  "properties": {
    "iso:country":"CA",
    "sg:address":"111 Carry Dr SE",
    "sg:city":"Medicine Hat",
    "sg:classifiers":[
        {
            "category":"Health Services",
            "subcategory":"Doctor",
            "type":"Services"
        }
    ],
    "sg:phone":"+1 403 527 7900",
    "sg:postcode":"T1B 3M6",
    "sg:province":"AB",
    "sg:tags":[
        "clinic"
    ],
    "wof:name":"Denture Care Ltd",
    "wof:placetype":"venue"
},
  "geometry": {"coordinates":[-110.644279,50.007626],"type":"Point"}
}