{
  "type": "Feature",
  "properties": {
    "addr:full":"15 Mcmurrich St Toronto ON M5R 3M6",
    "addr:housenumber":"15",
    "addr:postcode":"m5r 3m6",
    "addr:street":"Mcmurrich St",
    "iso:country":"CA",
    "sg:address":"15 Mcmurrich St",
    "sg:city":"Toronto",
    "sg:classifiers":[
        {
            "category":"Manufacturing",
            "subcategory":"Printing",
            "type":"Manufacturing & Wholesale Goods"
        }
    ],
    "sg:phone":"+1 416 961 6687",
    "sg:postcode":"M5R 3M6",
    "sg:province":"ON",
    "sg:tags":[
        "publisher",
        "music"
    ],
    "wof:name":"Chung Gee Music Administration",
    "wof:placetype":"venue"
},
  "geometry": {"coordinates":[-79.38943500000001,43.673351],"type":"Point"}
}