{
  "type": "Feature",
  "properties": {
    "addr:full":"109 Boul Perron O New Richmond QC G0C 2B0",
    "addr:housenumber":"109",
    "addr:postcode":"g0c 2b0",
    "addr:street":"Boul Perron",
    "iso:country":"CA",
    "sg:address":"109 Boul Perron O",
    "sg:city":"New Richmond",
    "sg:classifiers":[
        {
            "category":"Real Estate",
            "subcategory":"Real Estate Agent",
            "type":"Services"
        }
    ],
    "sg:phone":"+1 418 392 6120",
    "sg:postcode":"G0C 2B0",
    "sg:province":"QC",
    "wof:name":"Espace 2000 Courtier Immobilie",
    "wof:placetype":"venue"
},
  "geometry": {"coordinates":[-65.853737,48.159859],"type":"Point"}
}