{
  "type": "Feature",
  "properties": {
    "addr:full":"Surrey BC V4N 4C1",
    "addr:postcode":"v4n 4c1",
    "iso:country":"CA",
    "sg:city":"Surrey",
    "sg:classifiers":[
        {
            "category":"Shopping",
            "subcategory":"Computers & Home Electronics",
            "type":"Retail Goods"
        }
    ],
    "sg:phone":"+1 604 882 3882",
    "sg:postcode":"V4N 4C1",
    "sg:province":"BC",
    "sg:tags":[
        "software"
    ],
    "wof:name":"Positec Solutions Inc",
    "wof:placetype":"venue"
},
  "geometry": {"coordinates":[-122.686272,49.176872],"type":"Point"}
}