{
  "type": "Feature",
  "properties": {
    "addr:full":"3860 Notre Dame Suite 304 Laval H7V 1S1",
    "addr:housenumber":"3860",
    "addr:postcode":"h7v 1s1",
    "addr:street":"Notre Dame Suite 304",
    "iso:country":"CA",
    "sg:address":"3860 Notre Dame Suite 304",
    "sg:city":"Laval",
    "sg:classifiers":[
        {
            "category":"Professional",
            "subcategory":"Computer Services",
            "type":"Services"
        }
    ],
    "sg:postcode":"H7V 1S1",
    "sg:tags":[
        "instant-web-video-web-videos-online-video-editing-online-special-effects"
    ],
    "sg:website":"http://www.InstantWebVideos.Com",
    "wof:name":"InnovSoft Consulting Limited",
    "wof:placetype":"venue"
},
  "geometry": {"coordinates":[-73.7481222,45.5411602],"type":"Point"}
}