{
  "type": "Feature",
  "properties": {
    "iso:country":"CA",
    "sg:address":"1141 Highbury Ave N",
    "sg:city":"London",
    "sg:classifiers":[
        {
            "category":"Professional",
            "subcategory":"Accounting & Tax Preparation",
            "type":"Services"
        }
    ],
    "sg:phone":"+1 519 451 4218",
    "sg:postcode":"N5Y 1A5",
    "sg:province":"ON",
    "sg:tags":[
        "bookkeeping",
        "general"
    ],
    "wof:name":"1263021 Ont Ltd",
    "wof:placetype":"venue"
},
  "geometry": {"coordinates":[-81.212379,43.013737],"type":"Point"}
}