{
  "type": "Feature",
  "properties": {
    "addr:full":"55 Rue DE L'Eglise Verdun QC H4G 3E7",
    "addr:housenumber":"55",
    "addr:postcode":"h4g 3e7",
    "addr:street":"Rue De L'Eglise",
    "iso:country":"CA",
    "sg:address":"55 Rue DE L'Eglise",
    "sg:city":"Verdun",
    "sg:classifiers":[
        {
            "category":"Health Services",
            "subcategory":"Doctor",
            "type":"Services"
        }
    ],
    "sg:phone":"+1 514 761 2911",
    "sg:postcode":"H4G 3E7",
    "sg:province":"QC",
    "sg:tags":[
        "physician",
        "surgeon"
    ],
    "wof:name":"Bureau Des Docteurs Brais",
    "wof:placetype":"venue"
},
  "geometry": {"coordinates":[-73.5642776489,45.4628410339],"type":"Point"}
}