{
  "type": "Feature",
  "properties": {
    "addr:full":"1791 Rte Saint-Yves Saint-Leon QC J0K 2W0",
    "addr:housenumber":"1791",
    "addr:postcode":"j0k 2w0",
    "addr:street":"Rte Saint-Yves Saint-Leon",
    "iso:country":"CA",
    "sg:address":"1791 Rte Saint-Yves",
    "sg:city":"Saint-Leon",
    "sg:classifiers":[
        {
            "category":"Wholesale",
            "subcategory":"Construction Materials",
            "type":"Manufacturing & Wholesale Goods"
        }
    ],
    "sg:phone":"+1 819 228 5005",
    "sg:postcode":"J0K 2W0",
    "sg:province":"QC",
    "sg:tags":[
        "sand",
        "gravel"
    ],
    "wof:name":"St-Yves Viateur Transport",
    "wof:placetype":"venue"
},
  "geometry": {"coordinates":[-72.9430923462,46.3110160828],"type":"Point"}
}