{
  "type": "Feature",
  "properties": {
    "addr:full":"140 Rice Lake Dr Bewdley ON K0L 1E0",
    "addr:housenumber":"140",
    "addr:postcode":"k0l 1e0",
    "addr:street":"Rice Lake Dr",
    "iso:country":"CA",
    "sg:address":"140 Rice Lake Dr",
    "sg:city":"Bewdley",
    "sg:classifiers":[
        {
            "category":"Recreation",
            "subcategory":"Marina",
            "type":"Entertainment"
        }
    ],
    "sg:phone":"+1 905 797 2790",
    "sg:postcode":"K0L 1E0",
    "sg:province":"ON",
    "wof:name":"Heartland Marine Products Ltd",
    "wof:placetype":"venue"
},
  "geometry": {"coordinates":[-78.31632995610001,44.0784187317],"type":"Point"}
}