{
  "type": "Feature",
  "properties": {
    "iso:country":"CA",
    "sg:city":"Concord",
    "sg:classifiers":[
        {
            "category":"Insurance",
            "subcategory":"Insurance Agent",
            "type":"Services"
        }
    ],
    "sg:phone":"+1 905 738 4164",
    "sg:postcode":"L4K 1Y2",
    "sg:province":"ON",
    "wof:name":"Masters Insurance Ltd",
    "wof:placetype":"venue"
},
  "geometry": {"coordinates":[-79.49816131590001,43.7958106995],"type":"Point"}
}