{
  "type": "Feature",
  "properties": {
    "iso:country":"CA",
    "sg:address":"1826 Berkel Rd",
    "sg:city":"Mississauga",
    "sg:classifiers":[
        {
            "category":"Retail",
            "subcategory":"Auto Repair",
            "type":"Services"
        }
    ],
    "sg:phone":"+1 905 206 0535",
    "sg:postcode":"L4X 1M7",
    "sg:province":"ON",
    "sg:tags":[
        "repairing",
        "automobile"
    ],
    "wof:name":"Pozpol Car Care",
    "wof:placetype":"venue"
},
  "geometry": {"coordinates":[-79.5768356323,43.6205825806],"type":"Point"}
}