{
  "type": "Feature",
  "properties": {
    "addr:full":"Grandes-Piles QC G0X 1H0",
    "addr:postcode":"g0x 1h0",
    "iso:country":"CA",
    "sg:city":"Grandes-Piles",
    "sg:classifiers":[
        {
            "category":"Government",
            "subcategory":"Office",
            "type":"Public Place"
        }
    ],
    "sg:phone":"+1 819 538 9708",
    "sg:postcode":"G0X 1H0",
    "sg:province":"QC",
    "sg:tags":[
        "village"
    ],
    "wof:name":"Grandes-Piles Hotel DE Ville",
    "wof:placetype":"venue"
},
  "geometry": {"coordinates":[-72.724754,46.687077],"type":"Point"}
}