{
  "type": "Feature",
  "properties": {
    "addr:full":"120 Harry Walker Pky N Newmarket ON L3Y 7B2",
    "addr:housenumber":"120",
    "addr:postcode":"l3y 7b2",
    "addr:street":"Harry Walker Pky N",
    "iso:country":"CA",
    "sg:address":"120 Harry Walker Pky N",
    "sg:city":"Newmarket",
    "sg:classifiers":[
        {
            "category":"Wholesale",
            "subcategory":"Electrical",
            "type":"Manufacturing & Wholesale Goods"
        }
    ],
    "sg:phone":"+1 905 836 0900",
    "sg:postcode":"L3Y 7B2",
    "sg:province":"ON",
    "sg:tags":[
        "equipment",
        "electric",
        "supply"
    ],
    "wof:name":"Nedco",
    "wof:placetype":"venue"
},
  "geometry": {"coordinates":[-79.42514801030001,44.0714111328],"type":"Point"}
}