{
  "type": "Feature",
  "properties": {
    "addr:full":"26 Cadogan Rd NW Calgary AB T2K 1W2",
    "addr:housenumber":"26",
    "addr:postcode":"t2k 1w2",
    "addr:street":"Cadogan Rd Nw",
    "iso:country":"CA",
    "sg:address":"26 Cadogan Rd NW",
    "sg:city":"Calgary",
    "sg:classifiers":[
        {
            "category":"Building & Trades",
            "subcategory":"Construction",
            "type":"Services"
        }
    ],
    "sg:phone":"+1 403 289 3880",
    "sg:postcode":"T2K 1W2",
    "sg:province":"AB",
    "sg:tags":[
        "handyman"
    ],
    "wof:name":"Handyman Can",
    "wof:placetype":"venue"
},
  "geometry": {"coordinates":[-114.091209412,51.0852508545],"type":"Point"}
}