{
  "type": "Feature",
  "properties": {
    "addr:full":"Montreal QC H2T 1X3",
    "addr:postcode":"h2t 1x3",
    "iso:country":"CA",
    "sg:city":"Montreal",
    "sg:classifiers":[
        {
            "category":"Shopping",
            "subcategory":"Clothing, Apparel, & Fashions",
            "type":"Retail Goods"
        }
    ],
    "sg:phone":"+1 514 271 5274",
    "sg:postcode":"H2T 1X3",
    "sg:province":"QC",
    "sg:tags":[
        "item",
        "boutique"
    ],
    "wof:name":"Carmen G",
    "wof:placetype":"venue"
},
  "geometry": {"coordinates":[-73.595268,45.526089],"type":"Point"}
}