{
  "type": "Feature",
  "properties": {
    "addr:full":"7181 Rue Saint-Hubert Montreal QC H2R 2N2",
    "addr:housenumber":"7181",
    "addr:postcode":"h2r 2n2",
    "addr:street":"Rue Saint-Hubert",
    "iso:country":"CA",
    "sg:address":"7181 Rue Saint-Hubert",
    "sg:city":"Montreal",
    "sg:classifiers":[
        {
            "category":"Personal",
            "subcategory":"Beauty Salon",
            "type":"Services"
        }
    ],
    "sg:phone":"+1 514 271 2617",
    "sg:postcode":"H2R 2N2",
    "sg:province":"QC",
    "wof:name":"Regine Studio DE Beaute",
    "wof:placetype":"venue"
},
  "geometry": {"coordinates":[-73.613556,45.541073],"type":"Point"}
}