{
  "type": "Feature",
  "properties": {
    "addr:full":"1081 Burrard St Vancouver BC V6Z 1Y6",
    "addr:housenumber":"1081",
    "addr:postcode":"v6z 1y6",
    "addr:street":"Burrard St",
    "iso:country":"CA",
    "sg:address":"1081 Burrard St",
    "sg:city":"Vancouver",
    "sg:classifiers":[
        {
            "category":"Health Services",
            "subcategory":"Doctor",
            "type":"Services"
        }
    ],
    "sg:phone":"+1 604 806 8698",
    "sg:postcode":"V6Z 1Y6",
    "sg:province":"BC",
    "sg:tags":[
        "physician",
        "surgeon"
    ],
    "wof:name":"Reid, John D S MD",
    "wof:placetype":"venue"
},
  "geometry": {"coordinates":[-123.12719,49.280449],"type":"Point"}
}