{
  "type": "Feature",
  "properties": {
    "addr:full":"143 Wedge Rd Saskatoon SK S7L 6P9",
    "addr:housenumber":"143",
    "addr:postcode":"s7l 6p9",
    "addr:street":"Wedge Rd",
    "iso:country":"CA",
    "sg:address":"143 Wedge Rd",
    "sg:city":"Saskatoon",
    "sg:classifiers":[
        {
            "category":"Organizations",
            "subcategory":"Religious Organization",
            "type":"Services"
        }
    ],
    "sg:phone":"+1 306 384 4100",
    "sg:postcode":"S7L 6P9",
    "sg:province":"SK",
    "sg:tags":[
        "church"
    ],
    "wof:name":"Circle West Presbyterian Chr",
    "wof:placetype":"venue"
},
  "geometry": {"coordinates":[-106.72736399999999,52.145821],"type":"Point"}
}