{
  "type": "Feature",
  "properties": {
    "addr:full":"8 Valleyview Dr Bancroft ON K0L 1C0",
    "addr:housenumber":"8",
    "addr:postcode":"k0l 1c0",
    "addr:street":"Valleyview Dr",
    "iso:country":"CA",
    "sg:address":"8 Valleyview Dr",
    "sg:city":"Bancroft",
    "sg:classifiers":[
        {
            "category":"Autos & Motor Vehicles",
            "subcategory":"Automobile Sales",
            "type":"Retail Goods"
        }
    ],
    "sg:phone":"+1 613 332 2438",
    "sg:postcode":"K0L 1C0",
    "sg:province":"ON",
    "sg:tags":[
        "car",
        "painting",
        "dealer"
    ],
    "wof:name":"Bancroft Motors Ltd",
    "wof:placetype":"venue"
},
  "geometry": {"coordinates":[-77.874672,45.053082],"type":"Point"}
}