{
  "type": "Feature",
  "properties": {
    "addr:full":"PO Box 5325 STN Main Lacombe AB T4L 1X1",
    "addr:housenumber":"po",
    "addr:postcode":"t4l 1x1",
    "addr:street":"Box 5325 Stn Main",
    "iso:country":"CA",
    "sg:address":"PO Box 5325 STN Main",
    "sg:city":"Lacombe",
    "sg:classifiers":[
        {
            "category":"Building & Trades",
            "subcategory":"Construction",
            "type":"Services"
        }
    ],
    "sg:phone":"+1 403 782 3766",
    "sg:postcode":"T4L 1X1",
    "sg:province":"AB",
    "sg:tags":[
        "maker",
        "cabinet"
    ],
    "wof:name":"L A County Cabinets",
    "wof:placetype":"venue"
},
  "geometry": {"coordinates":[-113.73670196499999,52.4631118774],"type":"Point"}
}