{
  "type": "Feature",
  "properties": {
    "addr:full":"5899 Av Du Parc Montreal QC H2V 4H4",
    "addr:housenumber":"5899",
    "addr:postcode":"h2v 4h4",
    "addr:street":"Av Du Parc",
    "iso:country":"CA",
    "sg:address":"5899 Av Du Parc",
    "sg:city":"Montreal",
    "sg:classifiers":[
        {
            "category":"Communications",
            "subcategory":"Radio Station",
            "type":"Services"
        }
    ],
    "sg:phone":"+1 514 273 2481",
    "sg:postcode":"H2V 4H4",
    "sg:province":"QC",
    "sg:tags":[
        "company",
        "broadcasting"
    ],
    "wof:name":"Chcr Mf LA Voix Hellenique",
    "wof:placetype":"venue"
},
  "geometry": {"coordinates":[-73.6068191528,45.5244026184],"type":"Point"}
}