{
  "type": "Feature",
  "properties": {
    "addr:full":"Dryden ON P8N 3K8",
    "addr:postcode":"p8n 3k8",
    "iso:country":"CA",
    "sg:city":"Dryden",
    "sg:classifiers":[
        {
            "category":"Professional",
            "subcategory":"Management & Consulting",
            "type":"Services"
        }
    ],
    "sg:phone":"+1 807 221 3293",
    "sg:postcode":"P8N 3K8",
    "sg:province":"ON",
    "sg:tags":[
        "consultant",
        "business"
    ],
    "wof:name":"Patricia Area Community Endvrs",
    "wof:placetype":"venue"
},
  "geometry": {"coordinates":[-92.81955000000001,49.785233],"type":"Point"}
}