{
  "type": "Feature",
  "properties": {
    "addr:full":"25 101 Ave Hay River NT X0E 0R9",
    "addr:housenumber":"101",
    "addr:postcode":"x0e 0r9",
    "addr:street":"25;Ave",
    "iso:country":"CA",
    "sg:address":"25 101 Ave",
    "sg:city":"Hay River",
    "sg:classifiers":[
        {
            "category":"Utilities",
            "subcategory":"Fuel Oil & Lpg",
            "type":"Services"
        }
    ],
    "sg:phone":"+1 867 874 2525",
    "sg:postcode":"X0E 0R9",
    "sg:province":"NT",
    "sg:tags":[
        "propane",
        "gas"
    ],
    "wof:name":"Superior Propane Inc",
    "wof:placetype":"venue"
},
  "geometry": {"coordinates":[-115.74807699999999,60.848259],"type":"Point"}
}