{
  "type": "Feature",
  "properties": {
    "addr:full":"2250 Torquay Ave Ottawa ON K2C 1J3",
    "addr:housenumber":"2250",
    "addr:postcode":"k2c 1j3",
    "addr:street":"Torquay Ave",
    "iso:country":"CA",
    "sg:address":"2250 Torquay Ave",
    "sg:city":"Ottawa",
    "sg:classifiers":[
        {
            "category":"Recreation",
            "type":"Entertainment"
        }
    ],
    "sg:phone":"+1 613 828 3118",
    "sg:postcode":"K2C 1J3",
    "sg:province":"ON",
    "sg:tags":[
        "government",
        "swimming"
    ],
    "wof:name":"Ottawa Pinecrest Community Ctr",
    "wof:placetype":"venue"
},
  "geometry": {"coordinates":[-75.774963,45.347336],"type":"Point"}
}