{
  "type": "Feature",
  "properties": {
    "addr:full":"1607 the Queensway Etobicoke ON M8Z 1T8",
    "addr:housenumber":"1607",
    "addr:postcode":"m8z 1t8",
    "addr:street":"The Queensway",
    "iso:country":"CA",
    "sg:address":"1607 the Queensway",
    "sg:city":"Etobicoke",
    "sg:classifiers":[
        {
            "category":"Wholesale",
            "subcategory":"Durable Goods & Equipment",
            "type":"Manufacturing & Wholesale Goods"
        }
    ],
    "sg:phone":"+1 416 251 1234",
    "sg:postcode":"M8Z 1T8",
    "sg:province":"ON",
    "sg:tags":[
        "importer"
    ],
    "wof:name":"Lucky Chan Trading CO",
    "wof:placetype":"venue"
},
  "geometry": {"coordinates":[-79.54349499999999,43.616966],"type":"Point"}
}