{
  "type": "Feature",
  "properties": {
    "addr:full":"Burnaby BC V5H 4M4",
    "addr:postcode":"v5h 4m4",
    "iso:country":"CA",
    "sg:city":"Burnaby",
    "sg:classifiers":[
        {
            "category":"Education",
            "subcategory":"Vocational School",
            "type":"Public Place"
        }
    ],
    "sg:phone":"+1 604 437 8585",
    "sg:postcode":"V5H 4M4",
    "sg:province":"BC",
    "sg:tags":[
        "training",
        "computer"
    ],
    "wof:name":"Cdi Career Development Inst",
    "wof:placetype":"venue"
},
  "geometry": {"coordinates":[-123.001922607,49.2294311523],"type":"Point"}
}