{
  "type": "Feature",
  "properties": {
    "iso:country":"CA",
    "sg:address":"2421 1st Ave E",
    "sg:city":"Vancouver",
    "sg:classifiers":[
        {
            "category":"Retail",
            "subcategory":"Laundry & Dry Cleaning",
            "type":"Services"
        }
    ],
    "sg:phone":"+1 604 255 5235",
    "sg:postcode":"V5M 1A2",
    "sg:province":"BC",
    "sg:tags":[
        "cleaners"
    ],
    "wof:name":"Busy Bee Cleaners",
    "wof:placetype":"venue"
},
  "geometry": {"coordinates":[-123.056091309,49.2697296143],"type":"Point"}
}