{
  "type": "Feature",
  "properties": {
    "addr:full":"421 Main St Esterhazy SK S0A 0X0",
    "addr:housenumber":"421",
    "addr:postcode":"s0a 0x0",
    "addr:street":"Main St",
    "iso:country":"CA",
    "sg:address":"421 Main St",
    "sg:city":"Esterhazy",
    "sg:classifiers":[
        {
            "category":"Home & Garden",
            "subcategory":"Carpets & Floor Coverings",
            "type":"Retail Goods"
        }
    ],
    "sg:phone":"+1 306 745 6144",
    "sg:postcode":"S0A 0X0",
    "sg:province":"SK",
    "sg:tags":[
        "paint",
        "rug"
    ],
    "wof:name":"Town-N-Country Decorating Ltd",
    "wof:placetype":"venue"
},
  "geometry": {"coordinates":[-102.07875061,50.6536865234],"type":"Point"}
}