{
  "type": "Feature",
  "properties": {
    "addr:full":"PO Box 699 Nanton AB T0L 1R0",
    "addr:housenumber":"po",
    "addr:postcode":"t0l 1r0",
    "addr:street":"Box 699",
    "iso:country":"CA",
    "sg:address":"PO Box 699",
    "sg:city":"Nanton",
    "sg:classifiers":[
        {
            "category":"Wholesale",
            "subcategory":"Construction Materials",
            "type":"Manufacturing & Wholesale Goods"
        }
    ],
    "sg:phone":"+1 403 646 3166",
    "sg:postcode":"T0L 1R0",
    "sg:province":"AB",
    "sg:tags":[
        "sand",
        "gravel"
    ],
    "wof:name":"Hydra-West Enterprises Ltd",
    "wof:placetype":"venue"
},
  "geometry": {"coordinates":[-113.773849,50.349819],"type":"Point"}
}