{
  "type": "Feature",
  "properties": {
    "addr:full":"12849 96 Ave Surrey BC V3V 6V9",
    "addr:housenumber":"12849",
    "addr:postcode":"v3v 6v9",
    "addr:street":"96 Ave",
    "iso:country":"CA",
    "sg:address":"12849 96 Ave",
    "sg:city":"Surrey",
    "sg:classifiers":[
        {
            "category":"Restaurant",
            "type":"Food & Drink"
        }
    ],
    "sg:phone":"+1 604 589 9559",
    "sg:postcode":"V3V 6V9",
    "sg:province":"BC",
    "sg:tags":[
        "pizza"
    ],
    "wof:name":"Camy's Pizza",
    "wof:placetype":"venue"
},
  "geometry": {"coordinates":[-122.86650848399999,49.177318573],"type":"Point"}
}