{
  "type": "Feature",
  "properties": {
    "addr:full":"RR 1 STN Main Perth ON K7H 3C3",
    "addr:postcode":"k7h 3c3",
    "addr:street":"Rr 1 Stn",
    "iso:country":"CA",
    "sg:address":"RR 1 STN Main",
    "sg:city":"Perth",
    "sg:classifiers":[
        {
            "category":"Professional",
            "subcategory":"Business Services",
            "type":"Services"
        }
    ],
    "sg:phone":"+1 613 267 6027",
    "sg:postcode":"K7H 3C3",
    "sg:province":"ON",
    "sg:tags":[
        "auctioneer"
    ],
    "wof:name":"Hands Auction",
    "wof:placetype":"venue"
},
  "geometry": {"coordinates":[-76.248329,44.898945],"type":"Point"}
}