{
  "type": "Feature",
  "properties": {
    "addr:full":"Toronto ON M5H 1J8",
    "addr:postcode":"m5h 1j8",
    "iso:country":"CA",
    "sg:city":"Toronto",
    "sg:classifiers":[
        {
            "category":"Personal",
            "subcategory":"Beauty Salon",
            "type":"Services"
        }
    ],
    "sg:phone":"+1 416 368 3774",
    "sg:postcode":"M5H 1J8",
    "sg:province":"ON",
    "wof:name":"Melanger Full Svc Salon",
    "wof:placetype":"venue"
},
  "geometry": {"coordinates":[-79.384262085,43.6476211548],"type":"Point"}
}