{
  "type": "Feature",
  "properties": {
    "addr:full":"35 Rue Des Villas LA Malbaie QC G5A 3B9",
    "addr:housenumber":"35",
    "addr:postcode":"g5a 3b9",
    "addr:street":"Rue Des Villas",
    "iso:country":"CA",
    "sg:address":"35 Rue Des Villas",
    "sg:city":"LA Malbaie",
    "sg:classifiers":[
        {
            "category":"Travel",
            "subcategory":"Hotels & Motels",
            "type":"Entertainment"
        }
    ],
    "sg:phone":"+1 418 665 9696",
    "sg:postcode":"G5A 3B9",
    "sg:province":"QC",
    "wof:name":"Villas Richelieu",
    "wof:placetype":"venue"
},
  "geometry": {"coordinates":[-70.152092,47.622196],"type":"Point"}
}