{
  "type": "Feature",
  "properties": {
    "addr:full":"5527 4 Ave Edson AB T7E 1L6",
    "addr:housenumber":"5527",
    "addr:postcode":"t7e 1l6",
    "addr:street":"4 Ave",
    "iso:country":"CA",
    "sg:address":"5527 4 Ave",
    "sg:city":"Edson",
    "sg:classifiers":[
        {
            "category":"Retail",
            "subcategory":"Repair Shop",
            "type":"Services"
        }
    ],
    "sg:phone":"+1 780 723 3706",
    "sg:postcode":"T7E 1L6",
    "sg:province":"AB",
    "sg:tags":[
        "welding"
    ],
    "wof:name":"Matts Iron Work & Welding",
    "wof:placetype":"venue"
},
  "geometry": {"coordinates":[-116.444480896,53.579536438],"type":"Point"}
}