{
  "type": "Feature",
  "properties": {
    "addr:full":"3949 Montee Saint-Hubert Saint-Hubert QC J3Y 4K2",
    "addr:housenumber":"3949",
    "addr:postcode":"j3y 4k2",
    "addr:street":"Montee Saint-Hubert",
    "iso:country":"CA",
    "sg:address":"3949 Montee Saint-Hubert",
    "sg:city":"Saint-Hubert",
    "sg:classifiers":[
        {
            "category":"Professional",
            "subcategory":"Business Services",
            "type":"Services"
        }
    ],
    "sg:phone":"+1 450 678 3206",
    "sg:postcode":"J3Y 4K2",
    "sg:province":"QC",
    "sg:tags":[
        "embroidery"
    ],
    "wof:name":"Sport Lem Ltee",
    "wof:placetype":"venue"
},
  "geometry": {"coordinates":[-73.43130499999999,45.49028],"type":"Point"}
}