{
  "type": "Feature",
  "properties": {
    "addr:full":"760 Huron Rd New Dundee ON N0B 2E0",
    "addr:housenumber":"760",
    "addr:postcode":"n0b 2e0",
    "addr:street":"Huron Rd",
    "iso:country":"CA",
    "sg:address":"760 Huron Rd",
    "sg:city":"New Dundee",
    "sg:classifiers":[
        {
            "category":"Building & Trades",
            "subcategory":"Landscaping Services",
            "type":"Services"
        }
    ],
    "sg:phone":"+1 519 696 2981",
    "sg:postcode":"N0B 2E0",
    "sg:province":"ON",
    "sg:tags":[
        "landscape",
        "contractor"
    ],
    "wof:name":"Van Oordt Landscaping",
    "wof:placetype":"venue"
},
  "geometry": {"coordinates":[-80.5154876709,43.3776397705],"type":"Point"}
}