{
  "type": "Feature",
  "properties": {
    "addr:full":"2080 Lawrence Ave W York ON M9N 1J1",
    "addr:housenumber":"2080",
    "addr:postcode":"m9n 1j1",
    "addr:street":"Lawrence Ave W",
    "iso:country":"CA",
    "sg:address":"2080 Lawrence Ave W",
    "sg:city":"York",
    "sg:classifiers":[
        {
            "category":"Travel",
            "subcategory":"Travel Agent",
            "type":"Entertainment"
        }
    ],
    "sg:phone":"+1 416 243 8822",
    "sg:postcode":"M9N 1J1",
    "sg:province":"ON",
    "sg:tags":[
        "agency",
        "bureau"
    ],
    "wof:name":"International Travel & Tours",
    "wof:placetype":"venue"
},
  "geometry": {"coordinates":[-79.517365,43.700012],"type":"Point"}
}