{
  "type": "Feature",
  "properties": {
    "addr:full":"10 Overlea Blvd East York ON M4H 1A4",
    "addr:housenumber":"10",
    "addr:postcode":"m4h 1a4",
    "addr:street":"Overlea Blvd",
    "iso:country":"CA",
    "sg:address":"10 Overlea Blvd",
    "sg:city":"East York",
    "sg:classifiers":[
        {
            "category":"Professional",
            "subcategory":"Employment Agencies",
            "type":"Services"
        }
    ],
    "sg:phone":"+1 416 425 3463",
    "sg:postcode":"M4H 1A4",
    "sg:province":"ON",
    "sg:tags":[
        "opportunity",
        "rehabilitation"
    ],
    "wof:name":"Ontario March of Dimes",
    "wof:placetype":"venue"
},
  "geometry": {"coordinates":[-79.35217299999999,43.703175],"type":"Point"}
}