{
  "type": "Feature",
  "properties": {
    "addr:full":"475 Rte 132 O Port-Daniel QC G0C 2N0",
    "addr:housenumber":"475",
    "addr:postcode":"g0c 2n0",
    "addr:street":"Rte 132 O",
    "iso:country":"CA",
    "sg:address":"475 Rte 132 O",
    "sg:city":"Port-Daniel",
    "sg:classifiers":[
        {
            "category":"Retail",
            "subcategory":"Auto Repair",
            "type":"Services"
        }
    ],
    "sg:phone":"+1 418 396 2721",
    "sg:postcode":"G0C 2N0",
    "sg:province":"QC",
    "sg:tags":[
        "repairing",
        "automobile"
    ],
    "wof:name":"Garage Gaetan Mc Innis",
    "wof:placetype":"venue"
},
  "geometry": {"coordinates":[-64.97380099999999,48.174812],"type":"Point"}
}