{
  "type": "Feature",
  "properties": {
    "iso:country":"CA",
    "sg:address":"10015 101 Ave",
    "sg:city":"Morinville",
    "sg:classifiers":[
        {
            "category":"Social Services",
            "subcategory":"Adult Care",
            "type":"Services"
        }
    ],
    "sg:phone":"+1 780 939 3212",
    "sg:postcode":"T8R 1M2",
    "sg:province":"AB",
    "sg:tags":[
        "senior",
        "housing",
        "citizen"
    ],
    "wof:name":"Heritage Place Senior Citizens",
    "wof:placetype":"venue"
},
  "geometry": {"coordinates":[-113.645332336,53.8033714294],"type":"Point"}
}