{
  "type": "Feature",
  "properties": {
    "addr:full":"545 Rue Dufferin Stanstead QC J0B 3E0",
    "addr:housenumber":"545",
    "addr:postcode":"j0b 3e0",
    "addr:street":"Rue Dufferin",
    "iso:country":"CA",
    "sg:address":"545 Rue Dufferin",
    "sg:city":"Stanstead",
    "sg:classifiers":[
        {
            "category":"Retail",
            "subcategory":"Funeral Services",
            "type":"Services"
        }
    ],
    "sg:phone":"+1 819 876 5213",
    "sg:postcode":"J0B 3E0",
    "sg:province":"QC",
    "sg:tags":[
        "director"
    ],
    "wof:name":"Residence Funeraire Cass Inc",
    "wof:placetype":"venue"
},
  "geometry": {"coordinates":[-72.09345999999999,45.016472],"type":"Point"}
}