{
  "type": "Feature",
  "properties": {
    "addr:full":"148 Bank St Ottawa ON K1P 5N8",
    "addr:housenumber":"148",
    "addr:postcode":"k1p 5n8",
    "addr:street":"Bank St",
    "iso:country":"CA",
    "sg:address":"148 Bank St",
    "sg:city":"Ottawa",
    "sg:classifiers":[
        {
            "category":"Restaurant",
            "type":"Food & Drink"
        }
    ],
    "sg:phone":"+1 613 569 9444",
    "sg:postcode":"K1P 5N8",
    "sg:province":"ON",
    "wof:name":"Ugly Iguana Cajun Cantina",
    "wof:placetype":"venue"
},
  "geometry": {"coordinates":[-75.699623,45.418865],"type":"Point"}
}