{
  "type": "Feature",
  "properties": {
    "iso:country":"CA",
    "sg:address":"169 Dundas St E",
    "sg:city":"Mississauga",
    "sg:classifiers":[
        {
            "category":"Bars & Pubs",
            "type":"Food & Drink"
        }
    ],
    "sg:phone":"+1 905 273 7928",
    "sg:postcode":"L5A 1W8",
    "sg:province":"ON",
    "wof:name":"Total Sports Bar Restaurant",
    "wof:placetype":"venue"
},
  "geometry": {"coordinates":[-79.612411,43.583961],"type":"Point"}
}