{
  "type": "Feature",
  "properties": {
    "addr:full":"Calgary AB T2P 2Y3",
    "addr:postcode":"t2p 2y3",
    "iso:country":"CA",
    "sg:city":"Calgary",
    "sg:classifiers":[
        {
            "category":"Professional",
            "subcategory":"Lawyer & Legal Services",
            "type":"Services"
        }
    ],
    "sg:phone":"+1 403 262 3775",
    "sg:postcode":"T2P 2Y3",
    "sg:province":"AB",
    "sg:tags":[
        "attorney"
    ],
    "wof:name":"Carscallen Lockwood Llp",
    "wof:placetype":"venue"
},
  "geometry": {"coordinates":[-114.067802,51.049271],"type":"Point"}
}