{
  "type": "Feature",
  "properties": {
    "addr:full":"Lasalle QC H8N 1S2",
    "addr:postcode":"h8n 1s2",
    "iso:country":"CA",
    "sg:city":"Lasalle",
    "sg:classifiers":[
        {
            "category":"Banks & Credit Unions",
            "subcategory":"Bank",
            "type":"Services"
        }
    ],
    "sg:phone":"+1 514 368 5610",
    "sg:postcode":"H8N 1S2",
    "sg:province":"QC",
    "wof:name":"Banque Royale",
    "wof:placetype":"venue"
},
  "geometry": {"coordinates":[-73.635063,45.431004],"type":"Point"}
}