{
  "type": "Feature",
  "properties": {
    "addr:full":"4000 Boul DE Maisonneuve O Westmount QC H3Z 1J9",
    "addr:housenumber":"4000",
    "addr:postcode":"h3z 1j9",
    "addr:street":"Boul De Maisonneuve O",
    "iso:country":"CA",
    "sg:address":"4000 Boul DE Maisonneuve O",
    "sg:city":"Westmount",
    "sg:classifiers":[
        {
            "category":"Real Estate",
            "subcategory":"Real Estate Operator",
            "type":"Services"
        }
    ],
    "sg:phone":"+1 514 935 4657",
    "sg:postcode":"H3Z 1J9",
    "sg:province":"QC",
    "sg:tags":[
        "apartment"
    ],
    "wof:name":"Appartements Plaza Tower",
    "wof:placetype":"venue"
},
  "geometry": {"coordinates":[-73.587509,45.488403],"type":"Point"}
}