{
  "type": "Feature",
  "properties": {
    "addr:full":"2504 37 St Vernon BC V1T 6G4",
    "addr:housenumber":"2504",
    "addr:postcode":"v1t 6g4",
    "addr:street":"37 St",
    "iso:country":"CA",
    "sg:address":"2504 37 St",
    "sg:city":"Vernon",
    "sg:classifiers":[
        {
            "category":"Wholesale",
            "subcategory":"Machinery & Supplies",
            "type":"Manufacturing & Wholesale Goods"
        }
    ],
    "sg:phone":"+1 250 503 0232",
    "sg:postcode":"V1T 6G4",
    "sg:province":"BC",
    "sg:tags":[
        "equipment",
        "irrigation",
        "system",
        "sprinkler"
    ],
    "wof:name":"Eljay Irrigation Ltd",
    "wof:placetype":"venue"
},
  "geometry": {"coordinates":[-119.28434,50.260365],"type":"Point"}
}