{
  "type": "Feature",
  "properties": {
    "addr:full":"1509 Sherbrooke St RR 3 Peterborough ON K9J 6X4",
    "addr:housenumber":"1509",
    "addr:postcode":"k9j 6x4",
    "addr:street":"Sherbrooke St Rr 3",
    "iso:country":"CA",
    "sg:address":"1509 Sherbrooke St RR 3",
    "sg:city":"Peterborough",
    "sg:classifiers":[
        {
            "category":"Organizations",
            "subcategory":"Religious Organization",
            "type":"Services"
        }
    ],
    "sg:phone":"+1 705 743 9911",
    "sg:postcode":"K9J 6X4",
    "sg:province":"ON",
    "sg:tags":[
        "church"
    ],
    "wof:name":"Westdale United Church",
    "wof:placetype":"venue"
},
  "geometry": {"coordinates":[-78.366524,44.290611],"type":"Point"}
}