{
  "type": "Feature",
  "properties": {
    "addr:full":"49 Beaverhall Dr North York ON M2L 2C8",
    "addr:housenumber":"49",
    "addr:postcode":"m2l 2c8",
    "addr:street":"Beaverhall Dr",
    "iso:country":"CA",
    "sg:address":"49 Beaverhall Dr",
    "sg:city":"North York",
    "sg:classifiers":[
        {
            "category":"Banks & Credit Unions",
            "subcategory":"Bank",
            "type":"Services"
        }
    ],
    "sg:phone":"+1 416 969 9860",
    "sg:postcode":"M2L 2C8",
    "sg:province":"ON",
    "sg:tags":[
        "loan",
        "real estate"
    ],
    "wof:name":"Excel Financial",
    "wof:placetype":"venue"
},
  "geometry": {"coordinates":[-79.36779,43.758266],"type":"Point"}
}