{
  "type": "Feature",
  "properties": {
    "addr:full":"500 Main St Montague PE C0A 1R0",
    "addr:housenumber":"500",
    "addr:postcode":"c0a 1r0",
    "addr:street":"Main St",
    "iso:country":"CA",
    "sg:address":"500 Main St",
    "sg:city":"Montague",
    "sg:classifiers":[
        {
            "category":"Recreation",
            "type":"Entertainment"
        }
    ],
    "sg:phone":"+1 902 838 7665",
    "sg:postcode":"C0A 1R0",
    "sg:province":"PE",
    "sg:tags":[
        "lounge",
        "parlor",
        "billiard",
        "cocktail"
    ],
    "wof:name":"Doolys",
    "wof:placetype":"venue"
},
  "geometry": {"coordinates":[-62.642429,46.162933],"type":"Point"}
}