{
  "type": "Feature",
  "properties": {
    "addr:full":"1027 Yonge St #200 Toronto ON M4W 2K9",
    "addr:housenumber":"1027",
    "addr:postcode":"m4w 2k9",
    "addr:street":"Yonge St # 200",
    "iso:country":"CA",
    "sg:address":"1027 Yonge St #200",
    "sg:city":"Toronto",
    "sg:classifiers":[
        {
            "category":"Travel",
            "subcategory":"Travel Agent",
            "type":"Entertainment"
        }
    ],
    "sg:phone":"+1 416 922 8835",
    "sg:postcode":"M4W 2K9",
    "sg:province":"ON",
    "sg:tags":[
        "agency",
        "bureau"
    ],
    "wof:name":"Payless Travel",
    "wof:placetype":"venue"
},
  "geometry": {"coordinates":[-79.38962600000001,43.677708],"type":"Point"}
}