{
  "type": "Feature",
  "properties": {
    "iso:country":"CA",
    "sg:address":"201 Boul Tache O",
    "sg:city":"Montmagny",
    "sg:classifiers":[
        {
            "category":"Autos & Motor Vehicles",
            "subcategory":"Automobile Sales",
            "type":"Retail Goods"
        }
    ],
    "sg:phone":"+1 418 248 0014",
    "sg:postcode":"G5V 4P5",
    "sg:province":"QC",
    "sg:tags":[
        "car",
        "dealer"
    ],
    "wof:name":"Montmagny Mazda",
    "wof:placetype":"venue"
},
  "geometry": {"coordinates":[-70.5554733276,46.9846305847],"type":"Point"}
}