{
  "type": "Feature",
  "properties": {
    "addr:full":"2148 Dundas St W Toronto ON M6R 1X2",
    "addr:housenumber":"2148",
    "addr:postcode":"m6r 1x2",
    "addr:street":"Dundas St W",
    "iso:country":"CA",
    "sg:address":"2148 Dundas St W",
    "sg:city":"Toronto",
    "sg:classifiers":[
        {
            "category":"Wholesale",
            "subcategory":"Auto Parts",
            "type":"Manufacturing & Wholesale Goods"
        }
    ],
    "sg:phone":"+1 416 531 3566",
    "sg:postcode":"M6R 1X2",
    "sg:province":"ON",
    "sg:tags":[
        "automobile",
        "supply"
    ],
    "wof:name":"West End Auto Supplies",
    "wof:placetype":"venue"
},
  "geometry": {"coordinates":[-79.4497680664,43.6530685425],"type":"Point"}
}