{
  "type": "Feature",
  "properties": {
    "addr:full":"Vaudreuil-Dorion QC J7V 2N5",
    "addr:postcode":"j7v 2n5",
    "iso:country":"CA",
    "sg:city":"Vaudreuil-Dorion",
    "sg:classifiers":[
        {
            "category":"Retail",
            "subcategory":"Repair Shop",
            "type":"Services"
        }
    ],
    "sg:phone":"+1 450 455 9706",
    "sg:postcode":"J7V 2N5",
    "sg:province":"QC",
    "sg:tags":[
        "lock",
        "locksmith"
    ],
    "wof:name":"Serrurier Plus",
    "wof:placetype":"venue"
},
  "geometry": {"coordinates":[-74.028954,45.401325],"type":"Point"}
}