{
  "type": "Feature",
  "properties": {
    "addr:full":"Newmarket ON L3Y 7T9",
    "addr:postcode":"l3y 7t9",
    "iso:country":"CA",
    "sg:city":"Newmarket",
    "sg:classifiers":[
        {
            "category":"Education",
            "subcategory":"Special Training",
            "type":"Public Place"
        }
    ],
    "sg:phone":"+1 905 836 4311",
    "sg:postcode":"L3Y 7T9",
    "sg:province":"ON",
    "sg:tags":[
        "instruction",
        "driving"
    ],
    "wof:name":"A 1 Seneca Driving School",
    "wof:placetype":"venue"
},
  "geometry": {"coordinates":[-79.45945,44.059628],"type":"Point"}
}