{
  "type": "Feature",
  "properties": {
    "addr:full":"1209 Rue Saint-Marc Montreal QC H3H 2E4",
    "addr:housenumber":"1209",
    "addr:postcode":"h3h 2e4",
    "addr:street":"Rue Saint-Marc",
    "iso:country":"CA",
    "sg:address":"1209 Rue Saint-Marc",
    "sg:city":"Montreal",
    "sg:classifiers":[
        {
            "category":"Education",
            "subcategory":"Special Training",
            "type":"Public Place"
        }
    ],
    "sg:phone":"+1 514 939 6362",
    "sg:postcode":"H3H 2E4",
    "sg:province":"QC",
    "sg:tags":[
        "school",
        "language"
    ],
    "wof:name":"Fleur DE Lys Svc Lngstqs",
    "wof:placetype":"venue"
},
  "geometry": {"coordinates":[-73.57862091059999,45.4919395447],"type":"Point"}
}