{
  "type": "Feature",
  "properties": {
    "addr:full":"Vancouver BC V7X 1M3",
    "addr:postcode":"v7x 1m3",
    "iso:country":"CA",
    "sg:city":"Vancouver",
    "sg:classifiers":[
        {
            "category":"Government",
            "subcategory":"Office",
            "type":"Public Place"
        }
    ],
    "sg:phone":"+1 604 662 8880",
    "sg:postcode":"V7X 1M3",
    "sg:province":"BC",
    "sg:tags":[
        "federal",
        "affairs"
    ],
    "wof:name":"Consulate General of Peru",
    "wof:placetype":"venue"
},
  "geometry": {"coordinates":[-123.11797332800001,49.2866172791],"type":"Point"}
}