{
  "type": "Feature",
  "properties": {
    "addr:full":"230 Boul Henri-Bourassa E # 203 Montreal QC H3L 1B8",
    "addr:housenumber":"230",
    "addr:postcode":"h3l 1b8",
    "addr:street":"Boul Henri-Bourassa E # 203",
    "iso:country":"CA",
    "sg:address":"230 Boul Henri-Bourassa E # 203",
    "sg:city":"Montreal",
    "sg:classifiers":[
        {
            "category":"Health Services",
            "subcategory":"Doctor",
            "type":"Services"
        }
    ],
    "sg:phone":"+1 514 382 0699",
    "sg:postcode":"H3L 1B8",
    "sg:province":"QC",
    "sg:tags":[
        "dentist"
    ],
    "wof:name":"Sylvie Forrest & Assoc",
    "wof:placetype":"venue"
},
  "geometry": {"coordinates":[-73.6694946289,45.5522575378],"type":"Point"}
}