{
  "type": "Feature",
  "properties": {
    "addr:full":"9838 Park Lane Coldstream BC V1B 3E4",
    "addr:housenumber":"9838",
    "addr:postcode":"bc v1b 3e4",
    "addr:street":"Park Lane",
    "iso:country":"CA",
    "sg:address":"9838 Park Lane",
    "sg:city":"Coldstream",
    "sg:classifiers":[
        {
            "category":"Building & Trades",
            "subcategory":"Construction",
            "type":"Services"
        }
    ],
    "sg:phone":"+1 250 542 3551",
    "sg:postcode":"V1B 3E4",
    "sg:province":"BC",
    "sg:tags":[
        "demolition",
        "contractor"
    ],
    "wof:name":"Jock's Blasting & Son Ltd",
    "wof:placetype":"venue"
},
  "geometry": {"coordinates":[-119.08648700000001,50.236259],"type":"Point"}
}