{
  "type": "Feature",
  "properties": {
    "addr:full":"New Richmond QC G0C 2B0",
    "addr:postcode":"g0c 2b0",
    "iso:country":"CA",
    "sg:city":"New Richmond",
    "sg:classifiers":[
        {
            "category":"Retail",
            "subcategory":"Auto Repair",
            "type":"Services"
        }
    ],
    "sg:phone":"+1 418 392 5021",
    "sg:postcode":"G0C 2B0",
    "sg:province":"QC",
    "sg:tags":[
        "truck"
    ],
    "wof:name":"Gaspesie Diesel Inc",
    "wof:placetype":"venue"
},
  "geometry": {"coordinates":[-65.83409899999999,48.161236],"type":"Point"}
}