{
  "type": "Feature",
  "properties": {
    "addr:full":"6796 Main St Millbank ON N0K 1L0",
    "addr:housenumber":"6796",
    "addr:postcode":"n0k 1l0",
    "addr:street":"Main St",
    "iso:country":"CA",
    "sg:address":"6796 Main St",
    "sg:city":"Millbank",
    "sg:classifiers":[
        {
            "category":"Home & Garden",
            "subcategory":"Furniture",
            "type":"Retail Goods"
        }
    ],
    "sg:phone":"+1 519 595 8694",
    "sg:postcode":"N0K 1L0",
    "sg:province":"ON",
    "wof:name":"Heritage Wood Mills",
    "wof:placetype":"venue"
},
  "geometry": {"coordinates":[-80.83764600000001,43.56778],"type":"Point"}
}