{
  "type": "Feature",
  "properties": {
    "iso:country":"CA",
    "sg:address":"1722 Montreal Rd",
    "sg:city":"Gloucester",
    "sg:classifiers":[
        {
            "category":"Retail",
            "subcategory":"Repair Shop",
            "type":"Services"
        }
    ],
    "sg:phone":"+1 613 737 7043",
    "sg:postcode":"K1J 6N5",
    "sg:province":"ON",
    "sg:tags":[
        "upholsterer"
    ],
    "wof:name":"Classico Decor",
    "wof:placetype":"venue"
},
  "geometry": {"coordinates":[-75.610825,45.445911],"type":"Point"}
}