{
  "type": "Feature",
  "properties": {
    "iso:country":"CA",
    "sg:address":"413 Port Royal Trail",
    "sg:city":"Scarborough",
    "sg:classifiers":[
        {
            "category":"Wholesale",
            "subcategory":"Groceries",
            "type":"Manufacturing & Wholesale Goods"
        }
    ],
    "sg:phone":"+1 416 298 4034",
    "sg:postcode":"M1V 4R2",
    "sg:province":"ON",
    "sg:tags":[
        "food",
        "product"
    ],
    "wof:name":"Garnet Food CO",
    "wof:placetype":"venue"
},
  "geometry": {"coordinates":[-79.28954315190001,43.8253364563],"type":"Point"}
}