{
  "type": "Feature",
  "properties": {
    "addr:full":"225 Main St E Listowel ON N4W 2B8",
    "addr:housenumber":"225",
    "addr:postcode":"n4w 2b8",
    "addr:street":"Main St E",
    "iso:country":"CA",
    "sg:address":"225 Main St E",
    "sg:city":"Listowel",
    "sg:classifiers":[
        {
            "category":"Personal",
            "subcategory":"Tanning Parlor",
            "type":"Services"
        }
    ],
    "sg:phone":"+1 519 291 2122",
    "sg:postcode":"N4W 2B8",
    "sg:province":"ON",
    "sg:tags":[
        "salon",
        "program",
        "physical",
        "exercise",
        "fitness"
    ],
    "wof:name":"Dynafit Exercise Ctr",
    "wof:placetype":"venue"
},
  "geometry": {"coordinates":[-80.951187,43.730919],"type":"Point"}
}