{
  "type": "Feature",
  "properties": {
    "addr:full":"25 Central St Bay Roberts NL A0A 1G0",
    "addr:housenumber":"25",
    "addr:postcode":"a0a 1g0",
    "addr:street":"Central St",
    "iso:country":"CA",
    "sg:address":"25 Central St",
    "sg:city":"Bay Roberts",
    "sg:classifiers":[
        {
            "category":"Home & Garden",
            "subcategory":"Building Materials",
            "type":"Retail Goods"
        }
    ],
    "sg:phone":"+1 709 786 6681",
    "sg:postcode":"A0A 1G0",
    "sg:province":"NL",
    "sg:tags":[
        "lumber"
    ],
    "wof:name":"R Churchill Building Supls Ltd",
    "wof:placetype":"venue"
},
  "geometry": {"coordinates":[-53.2652931213,47.5948257446],"type":"Point"}
}