{
  "type": "Feature",
  "properties": {
    "addr:full":"Fredericton NB E3B 5X8",
    "addr:postcode":"e3b 5x8",
    "iso:country":"CA",
    "sg:city":"Fredericton",
    "sg:classifiers":[
        {
            "category":"Professional",
            "subcategory":"Engineering",
            "type":"Services"
        }
    ],
    "sg:phone":"+1 506 459 3070",
    "sg:postcode":"E3B 5X8",
    "sg:province":"NB",
    "sg:tags":[
        "fire",
        "consultant",
        "protection"
    ],
    "wof:name":"R J Bartlett Engineering Ltd",
    "wof:placetype":"venue"
},
  "geometry": {"coordinates":[-66.65735599999999,45.94162],"type":"Point"}
}