{
  "type": "Feature",
  "properties": {
    "addr:full":"193 Rue Lafontaine Riviere-Du-Loup QC G5R 3A6",
    "addr:housenumber":"193",
    "addr:postcode":"g5r 3a6",
    "addr:street":"Rue Lafontaine",
    "iso:country":"CA",
    "sg:address":"193 Rue Lafontaine",
    "sg:city":"Riviere-Du-Loup",
    "sg:classifiers":[
        {
            "category":"Travel",
            "subcategory":"Travel Agent",
            "type":"Entertainment"
        }
    ],
    "sg:phone":"+1 418 867 8001",
    "sg:postcode":"G5R 3A6",
    "sg:province":"QC",
    "sg:tags":[
        "agency",
        "bureau"
    ],
    "wof:name":"Voyages Ciel D'Azur",
    "wof:placetype":"venue"
},
  "geometry": {"coordinates":[-69.536812,47.8354],"type":"Point"}
}