{
  "type": "Feature",
  "properties": {
    "addr:full":"1 Cormack Cres Bracebridge ON P1L 1R3",
    "addr:housenumber":"1",
    "addr:postcode":"p1l 1r3",
    "addr:street":"Cormack Cres",
    "iso:country":"CA",
    "sg:address":"1 Cormack Cres",
    "sg:city":"Bracebridge",
    "sg:classifiers":[
        {
            "category":"Building & Trades",
            "subcategory":"Construction",
            "type":"Services"
        }
    ],
    "sg:phone":"+1 705 645 8605",
    "sg:postcode":"P1L 1R3",
    "sg:province":"ON",
    "sg:tags":[
        "roofing",
        "contractor"
    ],
    "wof:name":"Muskoka Steel Roofing Systems",
    "wof:placetype":"venue"
},
  "geometry": {"coordinates":[-79.33316000000001,45.070824],"type":"Point"}
}