{
  "type": "Feature",
  "properties": {
    "addr:full":"124 Whitetail Dr Carp ON K0A 1L0",
    "addr:housenumber":"124",
    "addr:postcode":"k0a 1l0",
    "addr:street":"Whitetail Dr",
    "iso:country":"CA",
    "sg:address":"124 Whitetail Dr",
    "sg:city":"Carp",
    "sg:classifiers":[
        {
            "category":"Building & Trades",
            "subcategory":"Electrical",
            "type":"Services"
        }
    ],
    "sg:phone":"+1 613 836 7898",
    "sg:postcode":"K0A 1L0",
    "sg:province":"ON",
    "sg:tags":[
        "electric",
        "contractor"
    ],
    "wof:name":"Ddc Electrical",
    "wof:placetype":"venue"
},
  "geometry": {"coordinates":[-76.0425872803,45.3500442505],"type":"Point"}
}