{
  "type": "Feature",
  "properties": {
    "addr:full":"1172 Rue Pierre-Mallet Dorval QC H9S 5V9",
    "addr:housenumber":"1172",
    "addr:postcode":"h9s 5v9",
    "addr:street":"Rue Pierre-Mallet",
    "iso:country":"CA",
    "sg:address":"1172 Rue Pierre-Mallet",
    "sg:city":"Dorval",
    "sg:classifiers":[
        {
            "category":"Wholesale",
            "subcategory":"Machinery & Supplies",
            "type":"Manufacturing & Wholesale Goods"
        }
    ],
    "sg:phone":"+1 514 633 9307",
    "sg:postcode":"H9S 5V9",
    "sg:province":"QC",
    "sg:tags":[
        "equipment",
        "marine"
    ],
    "wof:name":"Lgb Controls & Equipment Ltd",
    "wof:placetype":"venue"
},
  "geometry": {"coordinates":[-73.751121521,45.4462203979],"type":"Point"}
}