{
  "type": "Feature",
  "properties": {
    "addr:full":"Mountain ON K0E 1S0",
    "addr:postcode":"k0e 1s0",
    "iso:country":"CA",
    "sg:city":"Mountain",
    "sg:classifiers":[
        {
            "category":"Personal",
            "subcategory":"Beauty Salon",
            "type":"Services"
        }
    ],
    "sg:phone":"+1 613 989 2697",
    "sg:postcode":"K0E 1S0",
    "sg:province":"ON",
    "wof:name":"Country Stylist",
    "wof:placetype":"venue"
},
  "geometry": {"coordinates":[-75.4944152832,45.034034729],"type":"Point"}
}