{
  "type": "Feature",
  "properties": {
    "iso:country":"CA",
    "sg:address":"3205 Boul DE LA Cote-Vertu",
    "sg:city":"Saint-Laurent",
    "sg:classifiers":[
        {
            "category":"Shopping",
            "subcategory":"Shoes",
            "type":"Retail Goods"
        }
    ],
    "sg:phone":"+1 514 332 7772",
    "sg:postcode":"H4R 1Y5",
    "sg:province":"QC",
    "wof:name":"Chaussures Arizona",
    "wof:placetype":"venue"
},
  "geometry": {"coordinates":[-73.70462,45.497139],"type":"Point"}
}