{
  "type": "Feature",
  "properties": {
    "addr:full":"4322 Hwy 31 Williamsburg ON K0C 2H0",
    "addr:housenumber":"4322",
    "addr:postcode":"k0c 2h0",
    "addr:street":"Hwy 31",
    "iso:country":"CA",
    "sg:address":"4322 Hwy 31",
    "sg:city":"Williamsburg",
    "sg:classifiers":[
        {
            "category":"Wholesale",
            "subcategory":"Meat",
            "type":"Manufacturing & Wholesale Goods"
        }
    ],
    "sg:phone":"+1 613 535 2310",
    "sg:postcode":"K0C 2H0",
    "sg:province":"ON",
    "sg:tags":[
        "butchering"
    ],
    "wof:name":"Whitteker Meat Market",
    "wof:placetype":"venue"
},
  "geometry": {"coordinates":[-75.2433929443,44.9741973877],"type":"Point"}
}