{
  "type": "Feature",
  "properties": {
    "addr:full":"5625 Rte Sainte-Genevieve Quebec QC G3K 1A5",
    "addr:housenumber":"5625",
    "addr:postcode":"g3k 1a5",
    "addr:street":"Rte Sainte-Genevieve",
    "iso:country":"CA",
    "sg:address":"5625 Rte Sainte-Genevieve",
    "sg:city":"Quebec",
    "sg:classifiers":[
        {
            "category":"Home & Garden",
            "subcategory":"Garden Supply",
            "type":"Retail Goods"
        }
    ],
    "sg:phone":"+1 418 845 2224",
    "sg:postcode":"G3K 1A5",
    "sg:province":"QC",
    "sg:tags":[
        "nurseryman",
        "center"
    ],
    "wof:name":"Arboreal Quebec Ltee",
    "wof:placetype":"venue"
},
  "geometry": {"coordinates":[-71.40311431879999,46.8337974548],"type":"Point"}
}