{
  "type": "Feature",
  "properties": {
    "addr:full":"7868 Oakwood Dr Niagara Falls ON L2E 6S5",
    "addr:housenumber":"7868",
    "addr:postcode":"l2e 6s5",
    "addr:street":"Oakwood Dr",
    "iso:country":"CA",
    "sg:address":"7868 Oakwood Dr",
    "sg:city":"Niagara Falls",
    "sg:classifiers":[
        {
            "category":"Wholesale",
            "subcategory":"Groceries",
            "type":"Manufacturing & Wholesale Goods"
        }
    ],
    "sg:phone":"+1 905 354 0929",
    "sg:postcode":"L2E 6S5",
    "sg:province":"ON",
    "sg:tags":[
        "pasta"
    ],
    "wof:name":"DE Best Pasta Suace",
    "wof:placetype":"venue"
},
  "geometry": {"coordinates":[-79.1215667725,43.062084198],"type":"Point"}
}