{
  "type": "Feature",
  "properties": {
    "iso:country":"CA",
    "sg:city":"Hartland",
    "sg:classifiers":[
        {
            "category":"Personal",
            "subcategory":"Beauty Salon",
            "type":"Services"
        }
    ],
    "sg:phone":"+1 506 375 4888",
    "sg:postcode":"E7P 2N2",
    "sg:province":"NB",
    "wof:name":"Tlc Hair & Tanning Salon",
    "wof:placetype":"venue"
},
  "geometry": {"coordinates":[-67.52745819090001,46.2977561951],"type":"Point"}
}