{
  "type": "Feature",
  "properties": {
    "addr:full":"7466 Welton St Mission BC V2V 6L4",
    "addr:housenumber":"7466",
    "addr:postcode":"v2v 6l4",
    "addr:street":"Welton St",
    "iso:country":"CA",
    "sg:address":"7466 Welton St",
    "sg:city":"Mission",
    "sg:classifiers":[
        {
            "category":"Education",
            "subcategory":"School",
            "type":"Public Place"
        }
    ],
    "sg:phone":"+1 604 826 1414",
    "sg:postcode":"V2V 6L4",
    "sg:province":"BC",
    "wof:name":"Mission Central Elementary",
    "wof:placetype":"venue"
},
  "geometry": {"coordinates":[-122.304604,49.13728],"type":"Point"}
}