{
  "type": "Feature",
  "properties": {
    "addr:full":"1471 Bourcier Dr Orleans ON K1E 3K1",
    "addr:housenumber":"1471",
    "addr:postcode":"k1e 3k1",
    "addr:street":"Bourcier Dr",
    "iso:country":"CA",
    "sg:address":"1471 Bourcier Dr",
    "sg:city":"Orleans",
    "sg:classifiers":[
        {
            "category":"Building & Trades",
            "subcategory":"Construction",
            "type":"Services"
        }
    ],
    "sg:phone":"+1 613 830 9589",
    "sg:postcode":"K1E 3K1",
    "sg:province":"ON",
    "sg:tags":[
        "painter"
    ],
    "wof:name":"Cumberland Painters",
    "wof:placetype":"venue"
},
  "geometry": {"coordinates":[-75.50598100000001,45.473194],"type":"Point"}
}