{
  "type": "Feature",
  "properties": {
    "addr:full":"1744 Kenworth St Thornhill BC V8G 4P9",
    "addr:housenumber":"1744",
    "addr:postcode":"v8g 4p9",
    "addr:street":"Kenworth St",
    "iso:country":"CA",
    "sg:address":"1744 Kenworth St",
    "sg:city":"Thornhill",
    "sg:classifiers":[
        {
            "category":"Organizations",
            "subcategory":"Religious Organization",
            "type":"Services"
        }
    ],
    "sg:phone":"+1 250 635 9263",
    "sg:postcode":"V8G 4P9",
    "sg:province":"BC",
    "sg:tags":[
        "church"
    ],
    "wof:name":"Church of Jesus Christ-Lds",
    "wof:placetype":"venue"
},
  "geometry": {"coordinates":[-128.57962000000001,54.494549],"type":"Point"}
}