{
  "type": "Feature",
  "properties": {
    "addr:full":"1030 Georgia St W #122 Vancouver BC V6E 2Y3",
    "addr:housenumber":"1030",
    "addr:postcode":"v6e 2y3",
    "addr:street":"Georgia St W # 122",
    "iso:country":"CA",
    "sg:address":"1030 Georgia St W #122",
    "sg:city":"Vancouver",
    "sg:classifiers":[
        {
            "category":"Freight",
            "type":"Transportation"
        }
    ],
    "sg:phone":"+1 604 688 8511",
    "sg:postcode":"V6E 2Y3",
    "sg:province":"BC",
    "sg:tags":[
        "broker",
        "customs"
    ],
    "wof:name":"Schenker of Canada Ltd",
    "wof:placetype":"venue"
},
  "geometry": {"coordinates":[-123.121849,49.284756],"type":"Point"}
}