{
  "type": "Feature",
  "properties": {
    "addr:full":"4548 Hwy 14 Windsor NS B0N 2T0",
    "addr:housenumber":"4548",
    "addr:postcode":"b0n 2t0",
    "addr:street":"Hwy 14",
    "iso:country":"CA",
    "sg:address":"4548 Hwy 14",
    "sg:city":"Windsor",
    "sg:classifiers":[
        {
            "category":"Organizations",
            "subcategory":"Professional Association",
            "type":"Services"
        }
    ],
    "sg:phone":"+1 902 798 0187",
    "sg:postcode":"B0N 2T0",
    "sg:province":"NS",
    "wof:name":"Chamber of Mineral Resources",
    "wof:placetype":"venue"
},
  "geometry": {"coordinates":[-64.143967,44.967953],"type":"Point"}
}