{
  "type": "Feature",
  "properties": {
    "addr:full":"19 Rue St-Andre Sainte-Agathe-Des-Monts QC J8C 2K5",
    "addr:housenumber":"19",
    "addr:postcode":"j8c 2k5",
    "addr:street":"Rue St-Andre",
    "iso:country":"CA",
    "sg:address":"19 Rue St-Andre",
    "sg:city":"Sainte-Agathe-Des-Monts",
    "sg:classifiers":[
        {
            "category":"Social Services",
            "type":"Services"
        }
    ],
    "sg:phone":"+1 819 326 0804",
    "sg:postcode":"J8C 2K5",
    "sg:province":"QC",
    "sg:tags":[
        "youth",
        "organization",
        "center"
    ],
    "wof:name":"Maison Des Jeunes",
    "wof:placetype":"venue"
},
  "geometry": {"coordinates":[-74.28383636469999,46.0481796265],"type":"Point"}
}