{
  "type": "Feature",
  "properties": {
    "iso:country":"CA",
    "sg:address":"SE 27 9 19W",
    "sg:city":"Brandon",
    "sg:classifiers":[
        {
            "category":"Building & Trades",
            "subcategory":"Construction",
            "type":"Services"
        }
    ],
    "sg:phone":"+1 204 728 2702",
    "sg:postcode":"R7A 5Y1",
    "sg:province":"MB",
    "sg:tags":[
        "water",
        "well",
        "drilling"
    ],
    "wof:name":"Fred Zavislak Well Drilling",
    "wof:placetype":"venue"
},
  "geometry": {"coordinates":[-99.9619522095,49.8476982117],"type":"Point"}
}