{
  "type": "Feature",
  "properties": {
    "addr:full":"2644 Rue Dandurand Montreal QC H1Y 1S5",
    "addr:housenumber":"2644",
    "addr:postcode":"h1y 1s5",
    "addr:street":"Rue Dandurand",
    "iso:country":"CA",
    "sg:address":"2644 Rue Dandurand",
    "sg:city":"Montreal",
    "sg:classifiers":[
        {
            "category":"Personal",
            "subcategory":"Beauty Salon",
            "type":"Services"
        }
    ],
    "sg:phone":"+1 514 728 3726",
    "sg:postcode":"H1Y 1S5",
    "sg:province":"QC",
    "wof:name":"Coiffure Jacques Menard",
    "wof:placetype":"venue"
},
  "geometry": {"coordinates":[-73.5792770386,45.546710968],"type":"Point"}
}