{
  "type": "Feature",
  "properties": {
    "addr:full":"341 Highview Dr Huntsville ON P1H 1C1",
    "addr:housenumber":"341",
    "addr:postcode":"p1h 1c1",
    "addr:street":"Highview Dr",
    "iso:country":"CA",
    "sg:address":"341 Highview Dr",
    "sg:city":"Huntsville",
    "sg:classifiers":[
        {
            "category":"Wholesale",
            "subcategory":"Hardware",
            "type":"Manufacturing & Wholesale Goods"
        }
    ],
    "sg:phone":"+1 705 789 6134",
    "sg:postcode":"P1H 1C1",
    "sg:province":"ON",
    "sg:tags":[
        "equipment",
        "energy",
        "solar"
    ],
    "wof:name":"Muskoka Renewable Energy",
    "wof:placetype":"venue"
},
  "geometry": {"coordinates":[-79.195511,45.340282],"type":"Point"}
}