{
  "type": "Feature",
  "properties": {
    "addr:full":"5305 Av Rosedale Montreal QC H4V 2H7",
    "addr:housenumber":"5305",
    "addr:postcode":"h4v 2h7",
    "addr:street":"Av Rosedale",
    "iso:country":"CA",
    "sg:address":"5305 Av Rosedale",
    "sg:city":"Montreal",
    "sg:classifiers":[
        {
            "category":"Organizations",
            "subcategory":"Religious Organization",
            "type":"Services"
        }
    ],
    "sg:phone":"+1 514 484 1122",
    "sg:postcode":"H4V 2H7",
    "sg:province":"QC",
    "sg:tags":[
        "synagogue"
    ],
    "wof:name":"Shaare Zedek Congregation",
    "wof:placetype":"venue"
},
  "geometry": {"coordinates":[-73.64885700000001,45.467033],"type":"Point"}
}