{
  "type": "Feature",
  "properties": {
    "addr:full":"3401 Rue Prieur E Montreal-Nord QC H1H 2L1",
    "addr:housenumber":"3401",
    "addr:postcode":"h1h 2l1",
    "addr:street":"Rue Prieur E",
    "iso:country":"CA",
    "sg:address":"3401 Rue Prieur E",
    "sg:city":"Montreal-Nord",
    "sg:classifiers":[
        {
            "category":"Personal",
            "subcategory":"Beauty Salon",
            "type":"Services"
        }
    ],
    "sg:phone":"+1 514 328 0266",
    "sg:postcode":"H1H 2L1",
    "sg:province":"QC",
    "wof:name":"Salon Marie Nadine",
    "wof:placetype":"venue"
},
  "geometry": {"coordinates":[-73.64409637449999,45.5830879211],"type":"Point"}
}