{
  "type": "Feature",
  "properties": {
    "addr:full":"4913 52 St Thorsby AB T0C 2P0",
    "addr:housenumber":"4913",
    "addr:postcode":"t0c 2p0",
    "addr:street":"52 St",
    "iso:country":"CA",
    "sg:address":"4913 52 St",
    "sg:city":"Thorsby",
    "sg:classifiers":[
        {
            "category":"Retail",
            "subcategory":"Veterinary Services",
            "type":"Services"
        }
    ],
    "sg:phone":"+1 780 789 3911",
    "sg:postcode":"T0C 2P0",
    "sg:province":"AB",
    "sg:tags":[
        "veterinarian"
    ],
    "wof:name":"Thorsby Veterinary Svc",
    "wof:placetype":"venue"
},
  "geometry": {"coordinates":[-114.046905518,53.2296104431],"type":"Point"}
}