{
  "type": "Feature",
  "properties": {
    "addr:full":"396 Williams Ave Milton ON L9T 2G4",
    "addr:housenumber":"396",
    "addr:postcode":"l9t 2g4",
    "addr:street":"Williams Ave",
    "iso:country":"CA",
    "sg:address":"396 Williams Ave",
    "sg:city":"Milton",
    "sg:classifiers":[
        {
            "category":"Education",
            "subcategory":"School",
            "type":"Public Place"
        }
    ],
    "sg:phone":"+1 905 878 2839",
    "sg:postcode":"L9T 2G4",
    "sg:province":"ON",
    "wof:name":"Milton District High School",
    "wof:placetype":"venue"
},
  "geometry": {"coordinates":[-79.87009429930001,43.5073661804],"type":"Point"}
}