{
  "type": "Feature",
  "properties": {
    "addr:full":"850 St. Anne St Bathurst NB E2A 6X2",
    "addr:housenumber":"850",
    "addr:postcode":"e2a 6x2",
    "addr:street":"St. Anne St",
    "iso:country":"CA",
    "sg:address":"850 St. Anne St",
    "sg:city":"Bathurst",
    "sg:classifiers":[
        {
            "category":"Arena",
            "subcategory":"Sports Club",
            "type":"Entertainment"
        }
    ],
    "sg:phone":"+1 506 549 3333",
    "sg:postcode":"E2A 6X2",
    "sg:province":"NB",
    "sg:tags":[
        "athletic",
        "fields",
        "stadium"
    ],
    "wof:name":"K C Irving Regional Ctr",
    "wof:placetype":"venue"
},
  "geometry": {"coordinates":[-65.689133,47.626446],"type":"Point"}
}