{
  "type": "Feature",
  "properties": {
    "addr:full":"1307 Rue Sainte-Catherine O Montreal QC H3G 1P7",
    "addr:housenumber":"1307",
    "addr:postcode":"h3g 1p7",
    "addr:street":"Rue Sainte-Catherine O",
    "iso:country":"CA",
    "sg:address":"1307 Rue Sainte-Catherine O",
    "sg:city":"Montreal",
    "sg:classifiers":[
        {
            "category":"Shopping",
            "subcategory":"Luggage & Leather Goods",
            "type":"Retail Goods"
        }
    ],
    "sg:phone":"+1 514 288 6219",
    "sg:postcode":"H3G 1P7",
    "sg:province":"QC",
    "wof:name":"Taschen-Bree",
    "wof:placetype":"venue"
},
  "geometry": {"coordinates":[-73.5553970337,45.5195121765],"type":"Point"}
}