{
  "type": "Feature",
  "properties": {
    "addr:full":"1459 Ogilvie Rd Gloucester ON K1J 8K6",
    "addr:housenumber":"1459",
    "addr:postcode":"k1j 8k6",
    "addr:street":"Ogilvie Rd",
    "iso:country":"CA",
    "sg:address":"1459 Ogilvie Rd",
    "sg:city":"Gloucester",
    "sg:classifiers":[
        {
            "category":"Retail",
            "subcategory":"Auto Repair",
            "type":"Services"
        }
    ],
    "sg:phone":"+1 613 745 4447",
    "sg:postcode":"K1J 8K6",
    "sg:province":"ON",
    "sg:tags":[
        "repairing",
        "automobile"
    ],
    "wof:name":"Ogilvie Service Ctr",
    "wof:placetype":"venue"
},
  "geometry": {"coordinates":[-75.61724100000001,45.432148],"type":"Point"}
}