{
  "type": "Feature",
  "properties": {
    "addr:full":"Alliston ON L9R 1V2",
    "addr:postcode":"l9r 1v2",
    "addr:street":"Alliston",
    "iso:country":"CA",
    "sg:city":"Alliston",
    "sg:classifiers":[
        {
            "category":"Building & Trades",
            "subcategory":"Electrical",
            "type":"Services"
        }
    ],
    "sg:phone":"+1 705 435 3624",
    "sg:postcode":"L9R 1V2",
    "sg:province":"ON",
    "sg:tags":[
        "electric",
        "contractor"
    ],
    "wof:name":"Simcoe York Electric",
    "wof:placetype":"venue"
},
  "geometry": {"coordinates":[-79.8681259155,44.1542167664],"type":"Point"}
}