{
  "type": "Feature",
  "properties": {
    "iso:country":"CA",
    "sg:address":"12307 63 Ave NW",
    "sg:city":"Edmonton",
    "sg:classifiers":[
        {
            "category":"Health Services",
            "subcategory":"Health Practitioner",
            "type":"Services"
        }
    ],
    "sg:phone":"+1 780 437 8000",
    "sg:postcode":"T6H 1R4",
    "sg:province":"AB",
    "sg:tags":[
        "therapist",
        "physical"
    ],
    "wof:name":"Grandview Heights Physical Tpy",
    "wof:placetype":"venue"
},
  "geometry": {"coordinates":[-113.54238891599999,53.5002746582],"type":"Point"}
}