{
  "type": "Feature",
  "properties": {
    "addr:full":"1481 106th St North Battleford SK S9A 1X5",
    "addr:housenumber":"1481",
    "addr:postcode":"s9a 1x5",
    "addr:street":"106Th St",
    "iso:country":"CA",
    "sg:address":"1481 106th St",
    "sg:city":"North Battleford",
    "sg:classifiers":[
        {
            "category":"Professional",
            "subcategory":"Business Services",
            "type":"Services"
        }
    ],
    "sg:phone":"+1 306 445 5946",
    "sg:postcode":"S9A 1X5",
    "sg:province":"SK",
    "sg:tags":[
        "auctioneer"
    ],
    "wof:name":"Ledinski's Auction Svc",
    "wof:placetype":"venue"
},
  "geometry": {"coordinates":[-108.290367,52.779194],"type":"Point"}
}