{
  "type": "Feature",
  "properties": {
    "iso:country":"CA",
    "sg:address":"100 City Centre Dr",
    "sg:city":"Mississauga",
    "sg:classifiers":[
        {
            "category":"Shopping",
            "subcategory":"Clothing, Apparel, & Fashions",
            "type":"Retail Goods"
        }
    ],
    "sg:phone":"+1 905 281 0155",
    "sg:postcode":"L5B 2C9",
    "sg:province":"ON",
    "sg:tags":[
        "infant",
        "wear"
    ],
    "wof:name":"Childrens Place",
    "wof:placetype":"venue"
},
  "geometry": {"coordinates":[-79.6395111084,43.5920944214],"type":"Point"}
}