{
  "type": "Feature",
  "properties": {
    "iso:country":"CA",
    "sg:address":"17 Alexander Rd",
    "sg:city":"Newmarket",
    "sg:classifiers":[
        {
            "category":"Retail",
            "subcategory":"Car Wash",
            "type":"Services"
        }
    ],
    "sg:phone":"+1 905 898 7382",
    "sg:postcode":"L3Y 3J2",
    "sg:province":"ON",
    "sg:tags":[
        "automobile",
        "detail",
        "clean"
    ],
    "wof:name":"Noble's Detailing",
    "wof:placetype":"venue"
},
  "geometry": {"coordinates":[-79.444527,44.062267],"type":"Point"}
}