{
  "type": "Feature",
  "properties": {
    "addr:full":"939 Elisabella St Sudbury ON P3A 5K1",
    "addr:housenumber":"939",
    "addr:postcode":"p3a 5k1",
    "addr:street":"Elisabella St",
    "iso:country":"CA",
    "sg:address":"939 Elisabella St",
    "sg:city":"Sudbury",
    "sg:classifiers":[
        {
            "category":"Manufacturing",
            "subcategory":"Metals",
            "type":"Manufacturing & Wholesale Goods"
        }
    ],
    "sg:phone":"+1 705 566 3033",
    "sg:postcode":"P3A 5K1",
    "sg:province":"ON",
    "sg:tags":[
        "steel"
    ],
    "wof:name":"City Welding Ltd",
    "wof:placetype":"venue"
},
  "geometry": {"coordinates":[-80.909752,46.518707],"type":"Point"}
}