{
  "type": "Feature",
  "properties": {
    "addr:full":"2967 Lake Shore Blvd W Etobicoke ON M8V 1J5",
    "addr:housenumber":"2967",
    "addr:postcode":"m8v 1j5",
    "addr:street":"Lake Shore Blvd W",
    "iso:country":"CA",
    "sg:address":"2967 Lake Shore Blvd W",
    "sg:city":"Etobicoke",
    "sg:classifiers":[
        {
            "category":"Personal",
            "subcategory":"Beauty Salon",
            "type":"Services"
        }
    ],
    "sg:phone":"+1 416 201 9087",
    "sg:postcode":"M8V 1J5",
    "sg:province":"ON",
    "wof:name":"Sava Hair Salon Ltd",
    "wof:placetype":"venue"
},
  "geometry": {"coordinates":[-79.506111,43.600479],"type":"Point"}
}