{
  "type": "Feature",
  "properties": {
    "addr:full":"Vancouver BC V6J 1Z2",
    "addr:postcode":"v6j 1z2",
    "iso:country":"CA",
    "sg:city":"Vancouver",
    "sg:classifiers":[
        {
            "category":"Shopping",
            "subcategory":"Computers & Home Electronics",
            "type":"Retail Goods"
        }
    ],
    "sg:phone":"+1 604 739 0438",
    "sg:postcode":"V6J 1Z2",
    "sg:province":"BC",
    "sg:tags":[
        "equipment",
        "dealer"
    ],
    "wof:name":"Strong Computer Inc",
    "wof:placetype":"venue"
},
  "geometry": {"coordinates":[-123.148796081,49.2636413574],"type":"Point"}
}