{
  "type": "Feature",
  "properties": {
    "addr:full":"344 Victoria St Watford ON N0M 2S0",
    "addr:housenumber":"344",
    "addr:postcode":"n0m 2s0",
    "addr:street":"Victoria St",
    "iso:country":"CA",
    "sg:address":"344 Victoria St",
    "sg:city":"Watford",
    "sg:classifiers":[
        {
            "category":"Health Services",
            "subcategory":"Nursing And Care Facility",
            "type":"Services"
        }
    ],
    "sg:phone":"+1 519 876 2520",
    "sg:postcode":"N0M 2S0",
    "sg:province":"ON",
    "sg:tags":[
        "home",
        "convalescent"
    ],
    "wof:name":"Watford Quality Care Ctr",
    "wof:placetype":"venue"
},
  "geometry": {"coordinates":[-81.8857574463,42.9524536133],"type":"Point"}
}