{
  "type": "Feature",
  "properties": {
    "addr:full":"5 Mill St E Tottenham ON L0G 1W0",
    "addr:housenumber":"5",
    "addr:postcode":"l0g 1w0",
    "addr:street":"Mill St",
    "iso:country":"CA",
    "sg:address":"5 Mill St E",
    "sg:city":"Tottenham",
    "sg:classifiers":[
        {
            "category":"Professional",
            "subcategory":"Lawyer & Legal Services",
            "type":"Services"
        }
    ],
    "sg:phone":"+1 905 936 4262",
    "sg:postcode":"L0G 1W0",
    "sg:province":"ON",
    "sg:tags":[
        "attorney"
    ],
    "wof:name":"Switzer, Jerry W",
    "wof:placetype":"venue"
},
  "geometry": {"coordinates":[-79.8051986694,44.0223770142],"type":"Point"}
}