{
  "type": "Feature",
  "properties": {
    "iso:country":"CA",
    "sg:city":"Montreal",
    "sg:classifiers":[
        {
            "category":"Professional",
            "subcategory":"Management & Consulting",
            "type":"Services"
        }
    ],
    "sg:phone":"+1 514 484 8788",
    "sg:postcode":"H3A 1H3",
    "sg:province":"QC",
    "sg:tags":[
        "project"
    ],
    "wof:name":"Groupe Montaigne",
    "wof:placetype":"venue"
},
  "geometry": {"coordinates":[-73.56575,45.521587],"type":"Point"}
}