{
  "type": "Feature",
  "properties": {
    "addr:full":"6 Wellesley St W Toronto ON M4Y 1E7",
    "addr:housenumber":"6",
    "addr:postcode":"m4y 1e7",
    "addr:street":"Wellesley St W",
    "iso:country":"CA",
    "sg:address":"6 Wellesley St W",
    "sg:city":"Toronto",
    "sg:classifiers":[
        {
            "category":"Restaurant",
            "type":"Food & Drink"
        }
    ],
    "sg:phone":"+1 416 967 7199",
    "sg:postcode":"M4Y 1E7",
    "sg:province":"ON",
    "wof:name":"Mammina's Ristorante",
    "wof:placetype":"venue"
},
  "geometry": {"coordinates":[-79.38492599999999,43.664986],"type":"Point"}
}