{
  "type": "Feature",
  "properties": {
    "addr:full":"1050 Rue Des Cascades O Saint-Hyacinthe QC J2S 3G6",
    "addr:housenumber":"1050",
    "addr:postcode":"j2s 3g6",
    "addr:street":"Rue Des Cascades O",
    "iso:country":"CA",
    "sg:address":"1050 Rue Des Cascades O",
    "sg:city":"Saint-Hyacinthe",
    "sg:classifiers":[
        {
            "category":"Shopping",
            "subcategory":"Used Merchandise",
            "type":"Retail Goods"
        }
    ],
    "sg:phone":"+1 450 778 2689",
    "sg:postcode":"J2S 3G6",
    "sg:province":"QC",
    "sg:tags":[
        "antique"
    ],
    "wof:name":"Boutique Tel Quel",
    "wof:placetype":"venue"
},
  "geometry": {"coordinates":[-72.94322200000001,45.626507],"type":"Point"}
}