{
  "type": "Feature",
  "properties": {
    "addr:full":"435 North Rd Coquitlam BC V3K 3V9",
    "addr:housenumber":"435",
    "addr:postcode":"v3k 3v9",
    "addr:street":"North Rd",
    "iso:country":"CA",
    "sg:address":"435 North Rd",
    "sg:city":"Coquitlam",
    "sg:classifiers":[
        {
            "category":"Personal",
            "subcategory":"Beauty Salon",
            "type":"Services"
        }
    ],
    "sg:phone":"+1 604 931 4042",
    "sg:postcode":"V3K 3V9",
    "sg:province":"BC",
    "wof:name":"Great Clips For Hair",
    "wof:placetype":"venue"
},
  "geometry": {"coordinates":[-122.89256286600001,49.2475280762],"type":"Point"}
}