{
  "type": "Feature",
  "properties": {
    "addr:full":"329 12th Ave Estevan SK S4A 1E3",
    "addr:housenumber":"329",
    "addr:postcode":"s4a 1e3",
    "addr:street":"12Th Ave",
    "iso:country":"CA",
    "sg:address":"329 12th Ave",
    "sg:city":"Estevan",
    "sg:classifiers":[
        {
            "category":"Professional",
            "subcategory":"Lawyer & Legal Services",
            "type":"Services"
        }
    ],
    "sg:phone":"+1 306 634 7494",
    "sg:postcode":"S4A 1E3",
    "sg:province":"SK",
    "sg:tags":[
        "attorney"
    ],
    "wof:name":"Goby Law Office",
    "wof:placetype":"venue"
},
  "geometry": {"coordinates":[-102.99488830599999,49.1402282715],"type":"Point"}
}