{
  "type": "Feature",
  "properties": {
    "iso:country":"CA",
    "sg:address":"922 Fort Fraser Rise",
    "sg:city":"Port Coquitlam",
    "sg:classifiers":[
        {
            "category":"Professional",
            "subcategory":"Computer Services",
            "type":"Services"
        }
    ],
    "sg:phone":"+1 604 945 0459",
    "sg:postcode":"V3C 6K4",
    "sg:province":"BC",
    "sg:tags":[
        "website",
        "design"
    ],
    "wof:name":"Computer & Business Integrator",
    "wof:placetype":"venue"
},
  "geometry": {"coordinates":[-122.792579651,49.2304115295],"type":"Point"}
}