{
  "type": "Feature",
  "properties": {
    "addr:full":"209 Royal Rd Wingham ON N0G 2W0",
    "addr:housenumber":"209",
    "addr:postcode":"n0g 2w0",
    "addr:street":"Royal Rd",
    "iso:country":"CA",
    "sg:address":"209 Royal Rd",
    "sg:city":"Wingham",
    "sg:classifiers":[
        {
            "category":"Organizations",
            "subcategory":"Professional Association",
            "type":"Services"
        }
    ],
    "sg:phone":"+1 519 357 4230",
    "sg:postcode":"N0G 2W0",
    "sg:province":"ON",
    "wof:name":"Wingham Sportsman Assn",
    "wof:placetype":"venue"
},
  "geometry": {"coordinates":[-81.3105773926,43.8892440796],"type":"Point"}
}