{
  "type": "Feature",
  "properties": {
    "addr:full":"63A Main St Selkirk MB R1A 1R2",
    "addr:housenumber":"63a",
    "addr:postcode":"r1a 1r2",
    "addr:street":"Main St",
    "iso:country":"CA",
    "sg:address":"63A Main St",
    "sg:city":"Selkirk",
    "sg:classifiers":[
        {
            "category":"Food & Beverages",
            "subcategory":"Specialty",
            "type":"Retail Goods"
        }
    ],
    "sg:phone":"+1 204 482 8590",
    "sg:postcode":"R1A 1R2",
    "sg:province":"MB",
    "sg:tags":[
        "health",
        "diet"
    ],
    "wof:name":"Sangster's Health Ctr",
    "wof:placetype":"venue"
},
  "geometry": {"coordinates":[-96.8896102905,50.1315116882],"type":"Point"}
}