{
  "type": "Feature",
  "properties": {
    "addr:full":"2140 Rue Garneau Plessisville QC G6L 2Y6",
    "addr:housenumber":"2140",
    "addr:postcode":"g6l 2y6",
    "addr:street":"Rue Garneau",
    "iso:country":"CA",
    "sg:address":"2140 Rue Garneau",
    "sg:city":"Plessisville",
    "sg:classifiers":[
        {
            "category":"Manufacturing",
            "subcategory":"Tools & Machinery",
            "type":"Manufacturing & Wholesale Goods"
        }
    ],
    "sg:phone":"+1 819 362 3267",
    "sg:postcode":"G6L 2Y6",
    "sg:province":"QC",
    "sg:tags":[
        "pattern",
        "mold",
        "maker"
    ],
    "wof:name":"Modelerie Glt Inc",
    "wof:placetype":"venue"
},
  "geometry": {"coordinates":[-71.77990699999999,46.229691],"type":"Point"}
}