{
  "type": "Feature",
  "properties": {
    "addr:full":"281 Rue DE Liege E Montreal QC H2P 1J3",
    "addr:housenumber":"281",
    "addr:postcode":"h2p 1j3",
    "addr:street":"Rue De Liege E",
    "iso:country":"CA",
    "sg:address":"281 Rue DE Liege E",
    "sg:city":"Montreal",
    "sg:classifiers":[
        {
            "category":"Food & Beverages",
            "subcategory":"Groceries & Convenience Stores",
            "type":"Retail Goods"
        }
    ],
    "sg:phone":"+1 514 387 6133",
    "sg:postcode":"H2P 1J3",
    "sg:province":"QC",
    "wof:name":"Depanneur & Plus",
    "wof:placetype":"venue"
},
  "geometry": {"coordinates":[-73.6363525391,45.543006897],"type":"Point"}
}