{
  "type": "Feature",
  "properties": {
    "addr:full":"5852 3E Av Montreal QC H1Y 2X1",
    "addr:housenumber":"5852",
    "addr:postcode":"h1y 2x1",
    "addr:street":"3E Av",
    "iso:country":"CA",
    "sg:address":"5852 3E Av",
    "sg:city":"Montreal",
    "sg:classifiers":[
        {
            "category":"Professional",
            "subcategory":"Business Services",
            "type":"Services"
        }
    ],
    "sg:phone":"+1 514 725 2215",
    "sg:postcode":"H1Y 2X1",
    "sg:province":"QC",
    "sg:tags":[
        "designer",
        "dealer",
        "pool",
        "swimming"
    ],
    "wof:name":"Hors-Terre Expert",
    "wof:placetype":"venue"
},
  "geometry": {"coordinates":[-73.58330535890001,45.5485229492],"type":"Point"}
}