{
  "type": "Feature",
  "properties": {
    "addr:full":"Halifax NS B3L 4H9",
    "addr:postcode":"b3l 4h9",
    "iso:country":"CA",
    "sg:city":"Halifax",
    "sg:classifiers":[
        {
            "category":"Real Estate",
            "subcategory":"Real Estate Agent",
            "type":"Services"
        }
    ],
    "sg:phone":"+1 902 453 5552",
    "sg:postcode":"B3L 4H9",
    "sg:province":"NS",
    "wof:name":"Sutton Group Professional Rlty",
    "wof:placetype":"venue"
},
  "geometry": {"coordinates":[-63.6276626587,44.6607971191],"type":"Point"}
}