{
  "type": "Feature",
  "properties": {
    "iso:country":"CA",
    "sg:address":"10231 121 St NW",
    "sg:city":"Edmonton",
    "sg:classifiers":[
        {
            "category":"Banks & Credit Unions",
            "subcategory":"Investment Brokerage",
            "type":"Services"
        }
    ],
    "sg:phone":"+1 780 451 3152",
    "sg:postcode":"T5N 1K6",
    "sg:province":"AB",
    "sg:tags":[
        "consultant",
        "planning",
        "financial"
    ],
    "wof:name":"Taylor Financial Group",
    "wof:placetype":"venue"
},
  "geometry": {"coordinates":[-113.530517578,53.5435714722],"type":"Point"}
}