{
  "type": "Feature",
  "properties": {
    "addr:full":"6774 Rue Jarry E Saint-Leonard QC H1P 1W3",
    "addr:housenumber":"6774",
    "addr:postcode":"h1p 1w3",
    "addr:street":"Rue Jarry E",
    "iso:country":"CA",
    "sg:address":"6774 Rue Jarry E",
    "sg:city":"Saint-Leonard",
    "sg:classifiers":[
        {
            "category":"Manufacturing",
            "subcategory":"Tools & Machinery",
            "type":"Manufacturing & Wholesale Goods"
        }
    ],
    "sg:phone":"+1 514 327 7556",
    "sg:postcode":"H1P 1W3",
    "sg:province":"QC",
    "sg:tags":[
        "machine",
        "shop",
        "supply",
        "automobile"
    ],
    "wof:name":"Lafco Outillage Inc",
    "wof:placetype":"venue"
},
  "geometry": {"coordinates":[-73.579018,45.597446],"type":"Point"}
}