{
  "type": "Feature",
  "properties": {
    "iso:country":"CA",
    "sg:address":"550 Robertson St",
    "sg:city":"Winnipeg",
    "sg:classifiers":[
        {
            "category":"Education",
            "subcategory":"School",
            "type":"Public Place"
        }
    ],
    "sg:phone":"+1 204 589 4745",
    "sg:postcode":"R2X 2C4",
    "sg:province":"MB",
    "wof:name":"Robertson School",
    "wof:placetype":"venue"
},
  "geometry": {"coordinates":[-97.1572265625,49.9340553284],"type":"Point"}
}