{
  "type": "Feature",
  "properties": {
    "addr:full":"285 Huron St Stratford ON N5A 5T3",
    "addr:housenumber":"285",
    "addr:postcode":"n5a 5t3",
    "addr:street":"Huron St",
    "iso:country":"CA",
    "sg:address":"285 Huron St",
    "sg:city":"Stratford",
    "sg:classifiers":[
        {
            "category":"Health Services",
            "subcategory":"Doctor",
            "type":"Services"
        }
    ],
    "sg:phone":"+1 519 275 2604",
    "sg:postcode":"N5A 5T3",
    "sg:province":"ON",
    "sg:tags":[
        "physician",
        "surgeon"
    ],
    "wof:name":"Wilkinson, Mark MD",
    "wof:placetype":"venue"
},
  "geometry": {"coordinates":[-80.99379730219999,43.3763885498],"type":"Point"}
}