{
  "type": "Feature",
  "properties": {
    "addr:full":"Laval QC H7L 5R2",
    "addr:postcode":"h7l 5r2",
    "iso:country":"CA",
    "sg:city":"Laval",
    "sg:classifiers":[
        {
            "category":"Professional",
            "subcategory":"Art Services",
            "type":"Services"
        }
    ],
    "sg:phone":"+1 450 622 1938",
    "sg:postcode":"H7L 5R2",
    "sg:province":"QC",
    "sg:tags":[
        "graphic",
        "publicity",
        "designer"
    ],
    "wof:name":"G X Communication Design Inc",
    "wof:placetype":"venue"
},
  "geometry": {"coordinates":[-73.76114699999999,45.593296],"type":"Point"}
}