{
  "type": "Feature",
  "properties": {
    "addr:full":"Calgary AB T2P 3R5",
    "addr:postcode":"t2p 3r5",
    "iso:country":"CA",
    "sg:city":"Calgary",
    "sg:classifiers":[
        {
            "category":"Banks & Credit Unions",
            "subcategory":"Investment Brokerage",
            "type":"Services"
        }
    ],
    "sg:phone":"+1 403 531 6800",
    "sg:postcode":"T2P 3R5",
    "sg:province":"AB",
    "sg:tags":[
        "stock",
        "broker",
        "bond"
    ],
    "wof:name":"Leeds Financial Markets Inc",
    "wof:placetype":"venue"
},
  "geometry": {"coordinates":[-114.07810974100001,51.0458450317],"type":"Point"}
}