{
  "type": "Feature",
  "properties": {
    "iso:country":"CA",
    "sg:address":"1447 Erie St E",
    "sg:city":"Windsor",
    "sg:classifiers":[
        {
            "category":"Food & Beverages",
            "subcategory":"Bakery",
            "type":"Retail Goods"
        }
    ],
    "sg:phone":"+1 519 977 5331",
    "sg:postcode":"N9A 4A1",
    "sg:province":"ON",
    "sg:tags":[
        "baker"
    ],
    "wof:name":"Milena's Bakery",
    "wof:placetype":"venue"
},
  "geometry": {"coordinates":[-83.0140838623,42.3157310486],"type":"Point"}
}