{
  "type": "Feature",
  "properties": {
    "addr:full":"520 Rue Fleury E Montreal QC H3L 1G5",
    "addr:housenumber":"520",
    "addr:postcode":"h3l 1g5",
    "addr:street":"Rue Fleury E",
    "iso:country":"CA",
    "sg:address":"520 Rue Fleury E",
    "sg:city":"Montreal",
    "sg:classifiers":[
        {
            "category":"Personal",
            "subcategory":"Beauty Salon",
            "type":"Services"
        }
    ],
    "sg:phone":"+1 514 382 9502",
    "sg:postcode":"H3L 1G5",
    "sg:province":"QC",
    "wof:name":"Salon DE Coiffure C Futur",
    "wof:placetype":"venue"
},
  "geometry": {"coordinates":[-73.6619567871,45.5529403687],"type":"Point"}
}