{
  "type": "Feature",
  "properties": {
    "addr:full":"330 Central Ave Grand Forks BC V0H 1H0",
    "addr:housenumber":"330",
    "addr:postcode":"v0h 1h0",
    "addr:street":"Central Ave",
    "iso:country":"CA",
    "sg:address":"330 Central Ave",
    "sg:city":"Grand Forks",
    "sg:classifiers":[
        {
            "category":"Shopping",
            "subcategory":"Pharmacy",
            "type":"Retail Goods"
        }
    ],
    "sg:phone":"+1 250 442 3515",
    "sg:postcode":"V0H 1H0",
    "sg:province":"BC",
    "wof:name":"Pharmasave",
    "wof:placetype":"venue"
},
  "geometry": {"coordinates":[-118.439224243,49.0332984924],"type":"Point"}
}