{
  "type": "Feature",
  "properties": {
    "iso:country":"CA",
    "sg:city":"Westmount",
    "sg:classifiers":[
        {
            "category":"Health Services",
            "subcategory":"Doctor",
            "type":"Services"
        }
    ],
    "sg:phone":"+1 514 932 7438",
    "sg:postcode":"H3Z 2Z3",
    "sg:province":"QC",
    "sg:tags":[
        "clinic"
    ],
    "wof:name":"Rheumatic Disease Ctr Montreal",
    "wof:placetype":"venue"
},
  "geometry": {"coordinates":[-73.585647583,45.4881515503],"type":"Point"}
}