{
  "type": "Feature",
  "properties": {
    "addr:full":"121 Lower Ganges Rd Salt Spring Island BC V8K 2T1",
    "addr:housenumber":"121",
    "addr:postcode":"v8k 2t1",
    "addr:street":"Lower Ganges Rd",
    "iso:country":"CA",
    "sg:address":"121 Lower Ganges Rd",
    "sg:city":"Salt Spring Island",
    "sg:classifiers":[
        {
            "category":"Travel",
            "subcategory":"Travel Agent",
            "type":"Entertainment"
        }
    ],
    "sg:phone":"+1 250 537 5252",
    "sg:postcode":"V8K 2T1",
    "sg:province":"BC",
    "sg:tags":[
        "information",
        "tourist"
    ],
    "wof:name":"Salt Spring Tourist Info Ctr",
    "wof:placetype":"venue"
},
  "geometry": {"coordinates":[-123.499657,48.853207],"type":"Point"}
}