{
  "type": "Feature",
  "properties": {
    "addr:full":"1990 Av Francis-Hughes Laval QC H7S 1N4",
    "addr:housenumber":"1990",
    "addr:postcode":"h7s 1n4",
    "addr:street":"Av Francis-Hughes",
    "iso:country":"CA",
    "sg:address":"1990 Av Francis-Hughes",
    "sg:city":"Laval",
    "sg:classifiers":[
        {
            "category":"Professional",
            "subcategory":"Management & Consulting",
            "type":"Services"
        }
    ],
    "sg:phone":"+1 450 967 7357",
    "sg:postcode":"H7S 1N4",
    "sg:province":"QC",
    "sg:tags":[
        "food"
    ],
    "wof:name":"Services Alimentaires Miraval",
    "wof:placetype":"venue"
},
  "geometry": {"coordinates":[-73.7214508057,45.5786743164],"type":"Point"}
}