{
  "type": "Feature",
  "properties": {
    "iso:country":"CA",
    "sg:address":"333 Reid St",
    "sg:city":"Quesnel",
    "sg:classifiers":[
        {
            "category":"Insurance",
            "subcategory":"Insurance Agent",
            "type":"Services"
        }
    ],
    "sg:phone":"+1 250 992 6611",
    "sg:postcode":"V2J 2M5",
    "sg:province":"BC",
    "wof:name":"Aim Insurance",
    "wof:placetype":"venue"
},
  "geometry": {"coordinates":[-122.496986389,52.9779663086],"type":"Point"}
}