{
  "type": "Feature",
  "properties": {
    "addr:full":"68 Broadway St Kensington PE C0B 1M0",
    "addr:housenumber":"68",
    "addr:postcode":"c0b 1m0",
    "addr:street":"Broadway St",
    "iso:country":"CA",
    "sg:address":"68 Broadway St",
    "sg:city":"Kensington",
    "sg:classifiers":[
        {
            "category":"Organizations",
            "subcategory":"Religious Organization",
            "type":"Services"
        }
    ],
    "sg:phone":"+1 902 836 3609",
    "sg:postcode":"C0B 1M0",
    "sg:province":"PE",
    "sg:tags":[
        "church"
    ],
    "wof:name":"Holy Family Parish House",
    "wof:placetype":"venue"
},
  "geometry": {"coordinates":[-63.638897,46.438786],"type":"Point"}
}