{
  "type": "Feature",
  "properties": {
    "addr:full":"315 Lakeshore Rd E Oakville ON L6J 1J3",
    "addr:housenumber":"315",
    "addr:postcode":"l6j 1j3",
    "addr:street":"Lakeshore Rd E",
    "iso:country":"CA",
    "sg:address":"315 Lakeshore Rd E",
    "sg:city":"Oakville",
    "sg:classifiers":[
        {
            "category":"Shopping",
            "subcategory":"Florist",
            "type":"Retail Goods"
        }
    ],
    "sg:phone":"+1 905 844 1750",
    "sg:postcode":"L6J 1J3",
    "sg:province":"ON",
    "wof:name":"Bloom Flower Shop Inc",
    "wof:placetype":"venue"
},
  "geometry": {"coordinates":[-79.66594696040001,43.4480895996],"type":"Point"}
}