{
  "type": "Feature",
  "properties": {
    "iso:country":"CA",
    "sg:address":"9407 51 Ave NW",
    "sg:city":"Edmonton",
    "sg:classifiers":[
        {
            "category":"Wholesale",
            "subcategory":"Machinery & Supplies",
            "type":"Manufacturing & Wholesale Goods"
        }
    ],
    "sg:phone":"+1 780 435 3928",
    "sg:postcode":"T6E 4W8",
    "sg:province":"AB",
    "sg:tags":[
        "machine",
        "tool"
    ],
    "wof:name":"Thomas Skinner & Son Ltd",
    "wof:placetype":"venue"
},
  "geometry": {"coordinates":[-113.473426819,53.487865448],"type":"Point"}
}