{
  "type": "Feature",
  "properties": {
    "addr:full":"1418 Craigflower Rd Victoria BC V9A 2Y8",
    "addr:housenumber":"1418",
    "addr:postcode":"v9a 2y8",
    "addr:street":"Craigflower Rd",
    "iso:country":"CA",
    "sg:address":"1418 Craigflower Rd",
    "sg:city":"Victoria",
    "sg:classifiers":[
        {
            "category":"Building & Trades",
            "subcategory":"Construction",
            "type":"Services"
        }
    ],
    "sg:phone":"+1 250 384 2185",
    "sg:postcode":"V9A 2Y8",
    "sg:province":"BC",
    "sg:tags":[
        "resurfacing",
        "laying",
        "refinishing",
        "floor"
    ],
    "wof:name":"Five Star Hardwood Floors",
    "wof:placetype":"venue"
},
  "geometry": {"coordinates":[-123.393051,48.439442],"type":"Point"}
}