{
  "type": "Feature",
  "properties": {
    "addr:full":"480 Egerton St London ON N5W 3Z6",
    "addr:housenumber":"480",
    "addr:postcode":"n5w 3z6",
    "addr:street":"Egerton St",
    "iso:country":"CA",
    "sg:address":"480 Egerton St",
    "sg:city":"London",
    "sg:classifiers":[
        {
            "category":"Organizations",
            "subcategory":"Professional Association",
            "type":"Services"
        }
    ],
    "sg:phone":"+1 519 453 9086",
    "sg:postcode":"N5W 3Z6",
    "sg:province":"ON",
    "wof:name":"Lung Association",
    "wof:placetype":"venue"
},
  "geometry": {"coordinates":[-81.21612500000001,42.989857],"type":"Point"}
}