{
  "type": "Feature",
  "properties": {
    "iso:country":"CA",
    "sg:address":"480 Egerton St",
    "sg:city":"London",
    "sg:classifiers":[
        {
            "category":"Organizations",
            "subcategory":"Professional Association",
            "type":"Services"
        }
    ],
    "sg:phone":"+1 519 453 9086",
    "sg:postcode":"N5W 3Z6",
    "sg:province":"ON",
    "wof:name":"Lung Association",
    "wof:placetype":"venue"
},
  "geometry": {"coordinates":[-81.216125,42.989857],"type":"Point"}
}