{
  "type": "Feature",
  "properties": {
    "addr:full":"9734 170 St NW Edmonton AB T5T 5L5",
    "addr:housenumber":"9734",
    "addr:postcode":"t5t 5l5",
    "addr:street":"170 St Nw",
    "iso:country":"CA",
    "sg:address":"9734 170 St NW",
    "sg:city":"Edmonton",
    "sg:classifiers":[
        {
            "category":"Personal",
            "subcategory":"Beauty Salon",
            "type":"Services"
        }
    ],
    "sg:phone":"+1 780 484 5742",
    "sg:postcode":"T5T 5L5",
    "sg:province":"AB",
    "wof:name":"Terra Losa Hair Studio",
    "wof:placetype":"venue"
},
  "geometry": {"coordinates":[-113.615494,53.534241],"type":"Point"}
}