{
  "type": "Feature",
  "properties": {
    "iso:country":"CA",
    "sg:address":"390 Victoria Ave",
    "sg:city":"Windsor",
    "sg:classifiers":[
        {
            "category":"Education",
            "subcategory":"Special Training",
            "type":"Public Place"
        }
    ],
    "sg:phone":"+1 519 258 8800",
    "sg:postcode":"N9A 4M6",
    "sg:province":"ON",
    "sg:tags":[
        "loan",
        "tutoring",
        "real estate"
    ],
    "wof:name":"Academy For Mathematics & Svc",
    "wof:placetype":"venue"
},
  "geometry": {"coordinates":[-83.040321,42.316143],"type":"Point"}
}