{
  "type": "Feature",
  "properties": {
    "addr:full":"121 Main St N Mount Forest ON N0G 2L0",
    "addr:housenumber":"121",
    "addr:postcode":"n0g 2l0",
    "addr:street":"Main St N",
    "iso:country":"CA",
    "sg:address":"121 Main St N",
    "sg:city":"Mount Forest",
    "sg:classifiers":[
        {
            "category":"Personal",
            "subcategory":"Beauty Salon",
            "type":"Services"
        }
    ],
    "sg:phone":"+1 519 323 2181",
    "sg:postcode":"N0G 2L0",
    "sg:province":"ON",
    "wof:name":"Diane Beauty Salon",
    "wof:placetype":"venue"
},
  "geometry": {"coordinates":[-80.7352142334,43.981338501],"type":"Point"}
}