{
  "type": "Feature",
  "properties": {
    "addr:full":"Longueuil QC J4J 2Z3",
    "addr:postcode":"j4j 2z3",
    "iso:country":"CA",
    "sg:city":"Longueuil",
    "sg:phone":"+1 450 670 5530",
    "sg:postcode":"J4J 2Z3",
    "sg:province":"QC",
    "sg:tags":[
        "oil"
    ],
    "wof:name":"Produits Chimiques Cromac Ltee",
    "wof:placetype":"venue"
},
  "geometry": {"coordinates":[-73.47458648680001,45.5225906372],"type":"Point"}
}