{
  "type": "Feature",
  "properties": {
    "addr:full":"10673 97 St NW Edmonton AB T5H 2L7",
    "addr:housenumber":"10673",
    "addr:postcode":"t5h 2l7",
    "addr:street":"97 St Nw",
    "iso:country":"CA",
    "sg:address":"10673 97 St NW",
    "sg:city":"Edmonton",
    "sg:classifiers":[
        {
            "category":"Shopping",
            "subcategory":"Jewelry",
            "type":"Retail Goods"
        }
    ],
    "sg:phone":"+1 780 426 2423",
    "sg:postcode":"T5H 2L7",
    "sg:province":"AB",
    "sg:tags":[
        "jeweler"
    ],
    "wof:name":"Gold Crown Jewelers",
    "wof:placetype":"venue"
},
  "geometry": {"coordinates":[-113.489074707,53.5514640808],"type":"Point"}
}