{
  "type": "Feature",
  "properties": {
    "addr:full":"156 Townline Rd Sheguiandah ON P0P 1W0",
    "addr:housenumber":"156",
    "addr:postcode":"p0p 1w0",
    "addr:street":"Townline Rd",
    "iso:country":"CA",
    "sg:address":"156 Townline Rd",
    "sg:city":"Sheguiandah",
    "sg:classifiers":[
        {
            "category":"Retail",
            "subcategory":"Auto Repair",
            "type":"Services"
        }
    ],
    "sg:phone":"+1 705 368 1976",
    "sg:postcode":"P0P 1W0",
    "sg:province":"ON",
    "sg:tags":[
        "body",
        "automobile",
        "painting"
    ],
    "wof:name":"Batman's Restoration & Supply",
    "wof:placetype":"venue"
},
  "geometry": {"coordinates":[-81.916527,45.883816],"type":"Point"}
}