{
  "type": "Feature",
  "properties": {
    "addr:full":"692 Rue Principale St Leonard NB E7E 2H6",
    "addr:housenumber":"692",
    "addr:postcode":"e7e 2h6",
    "addr:street":"Rue Principale St",
    "iso:country":"CA",
    "sg:address":"692 Rue Principale",
    "sg:city":"St Leonard",
    "sg:classifiers":[
        {
            "category":"Banks & Credit Unions",
            "subcategory":"Bank",
            "type":"Services"
        }
    ],
    "sg:phone":"+1 506 423 6389",
    "sg:postcode":"E7E 2H6",
    "sg:province":"NB",
    "wof:name":"National Bank of Canada",
    "wof:placetype":"venue"
},
  "geometry": {"coordinates":[-67.92557525629999,47.1647834778],"type":"Point"}
}