{
  "type": "Feature",
  "properties": {
    "addr:full":"Toronto ON M4K 1N2",
    "addr:postcode":"m4k 1n2",
    "iso:country":"CA",
    "sg:city":"Toronto",
    "sg:classifiers":[
        {
            "category":"Health Services",
            "subcategory":"Health Practitioner",
            "type":"Services"
        }
    ],
    "sg:phone":"+1 416 469 5909",
    "sg:postcode":"M4K 1N2",
    "sg:province":"ON",
    "sg:tags":[
        "psychologist"
    ],
    "wof:name":"Centre For Reading Education",
    "wof:placetype":"venue"
},
  "geometry": {"coordinates":[-79.35485799999999,43.676849],"type":"Point"}
}