{
  "type": "Feature",
  "properties": {
    "iso:country":"CA",
    "sg:address":"73 Pembrook Lake Rd",
    "sg:city":"Grand Etang",
    "sg:classifiers":[
        {
            "category":"Building & Trades",
            "subcategory":"Construction",
            "type":"Services"
        }
    ],
    "sg:phone":"+1 902 224 3201",
    "sg:postcode":"B0E 1L0",
    "sg:province":"NS",
    "sg:tags":[
        "general",
        "contractor"
    ],
    "wof:name":"Larade's Construction CO Ltd",
    "wof:placetype":"venue"
},
  "geometry": {"coordinates":[-61.0423431396,46.5471382141],"type":"Point"}
}