{
  "type": "Feature",
  "properties": {
    "addr:full":"28 Barnes Rd West Brome QC J0E 2P0",
    "addr:housenumber":"28",
    "addr:postcode":"j0e 2p0",
    "addr:street":"Barnes Rd",
    "iso:country":"CA",
    "sg:address":"28 Barnes Rd",
    "sg:city":"West Brome",
    "sg:classifiers":[
        {
            "category":"Retail",
            "subcategory":"Animal Services",
            "type":"Services"
        }
    ],
    "sg:phone":"+1 450 243 5587",
    "sg:postcode":"J0E 2P0",
    "sg:province":"QC",
    "sg:tags":[
        "washing",
        "pet",
        "dog",
        "cat",
        "grooming",
        "kennel"
    ],
    "wof:name":"Chenil Lac Brome",
    "wof:placetype":"venue"
},
  "geometry": {"coordinates":[-72.616905,45.203968],"type":"Point"}
}