{
  "type": "Feature",
  "properties": {
    "addr:full":"28 Rue Nicolet Hull QC J8Y 2J4",
    "addr:housenumber":"28",
    "addr:postcode":"j8y 2j4",
    "addr:street":"Rue Nicolet",
    "iso:country":"CA",
    "sg:address":"28 Rue Nicolet",
    "sg:city":"Hull",
    "sg:classifiers":[
        {
            "category":"Professional",
            "subcategory":"Business Services",
            "type":"Services"
        }
    ],
    "sg:phone":"+1 819 777 7788",
    "sg:postcode":"J8Y 2J4",
    "sg:province":"QC",
    "sg:tags":[
        "notary"
    ],
    "wof:name":"Lafortune, Pierre",
    "wof:placetype":"venue"
},
  "geometry": {"coordinates":[-75.73420715330001,45.4389610291],"type":"Point"}
}