{
  "type": "Feature",
  "properties": {
    "addr:full":"659 Rue Shefford Bromont QC J2L 1C2",
    "addr:housenumber":"659",
    "addr:postcode":"j2l 1c2",
    "addr:street":"Rue Shefford",
    "iso:country":"CA",
    "sg:address":"659 Rue Shefford",
    "sg:city":"Bromont",
    "sg:classifiers":[
        {
            "category":"Food & Beverages",
            "subcategory":"Bakery",
            "type":"Retail Goods"
        }
    ],
    "sg:phone":"+1 450 534 4785",
    "sg:postcode":"J2L 1C2",
    "sg:province":"QC",
    "sg:tags":[
        "baker"
    ],
    "wof:name":"Desirables",
    "wof:placetype":"venue"
},
  "geometry": {"coordinates":[-72.653542,45.318676],"type":"Point"}
}