{
  "type": "Feature",
  "properties": {
    "addr:full":"5360 Rue Saint-Roch S Drummondville QC J2B 6V4",
    "addr:housenumber":"5360",
    "addr:postcode":"j2b 6v4",
    "addr:street":"Rue Saint-Roch S",
    "iso:country":"CA",
    "sg:address":"5360 Rue Saint-Roch S",
    "sg:city":"Drummondville",
    "sg:classifiers":[
        {
            "category":"Autos & Motor Vehicles",
            "subcategory":"Automobile Sales",
            "type":"Retail Goods"
        }
    ],
    "sg:phone":"+1 819 478 8186",
    "sg:postcode":"J2B 6V4",
    "sg:province":"QC",
    "sg:tags":[
        "truck"
    ],
    "wof:name":"Centre Du Camion Beaudoin Inc",
    "wof:placetype":"venue"
},
  "geometry": {"coordinates":[-72.533844,45.896156],"type":"Point"}
}