{
  "type": "Feature",
  "properties": {
    "addr:full":"130 Cliff St Nanaimo BC V9R 5E7",
    "addr:housenumber":"130",
    "addr:postcode":"v9r 5e7",
    "addr:street":"Cliff St",
    "iso:country":"CA",
    "sg:address":"130 Cliff St",
    "sg:city":"Nanaimo",
    "sg:classifiers":[
        {
            "category":"Retail",
            "subcategory":"Auto Repair",
            "type":"Services"
        }
    ],
    "sg:phone":"+1 250 753 3268",
    "sg:postcode":"V9R 5E7",
    "sg:province":"BC",
    "sg:tags":[
        "transmission"
    ],
    "wof:name":"Alberni Auto Transmission Ltd",
    "wof:placetype":"venue"
},
  "geometry": {"coordinates":[-123.93913999999999,49.1684],"type":"Point"}
}