{
  "type": "Feature",
  "properties": {
    "iso:country":"CA",
    "sg:address":"130 Cliff St",
    "sg:city":"Nanaimo",
    "sg:classifiers":[
        {
            "category":"Retail",
            "subcategory":"Auto Repair",
            "type":"Services"
        }
    ],
    "sg:phone":"+1 250 753 3268",
    "sg:postcode":"V9R 5E7",
    "sg:province":"BC",
    "sg:tags":[
        "transmission"
    ],
    "wof:name":"Alberni Auto Transmission Ltd",
    "wof:placetype":"venue"
},
  "geometry": {"coordinates":[-123.93914,49.1684],"type":"Point"}
}