{
  "type": "Feature",
  "properties": {
    "addr:full":"1791 Commercial Dr Vancouver BC V5N 4A4",
    "addr:housenumber":"1791",
    "addr:postcode":"v5n 4a4",
    "addr:street":"Commercial Dr",
    "iso:country":"CA",
    "sg:address":"1791 Commercial Dr",
    "sg:city":"Vancouver",
    "sg:classifiers":[
        {
            "category":"Restaurant",
            "type":"Food & Drink"
        }
    ],
    "sg:phone":"+1 604 255 3911",
    "sg:postcode":"V5N 4A4",
    "sg:province":"BC",
    "sg:tags":[
        "delicatessen"
    ],
    "wof:name":"LA Grotta Del Formaggio Inc",
    "wof:placetype":"venue"
},
  "geometry": {"coordinates":[-123.069878,49.26886],"type":"Point"}
}