{
  "type": "Feature",
  "properties": {
    "iso:country":"CA",
    "sg:address":"545 7E Rue",
    "sg:city":"Grand-Mere",
    "sg:classifiers":[
        {
            "category":"Health Services",
            "subcategory":"Doctor",
            "type":"Services"
        }
    ],
    "sg:phone":"+1 819 538 0768",
    "sg:postcode":"G9T 4N1",
    "sg:province":"QC",
    "sg:tags":[
        "dentist"
    ],
    "wof:name":"Gagnon, Yves DDS",
    "wof:placetype":"venue"
},
  "geometry": {"coordinates":[-72.6927108765,46.6135673523],"type":"Point"}
}