{
  "type": "Feature",
  "properties": {
    "addr:full":"840 Pape Ave East York ON M4K 3T6",
    "addr:housenumber":"840",
    "addr:postcode":"m4k 3t6",
    "addr:street":"Pape Ave",
    "iso:country":"CA",
    "sg:address":"840 Pape Ave",
    "sg:city":"East York",
    "sg:classifiers":[
        {
            "category":"Organizations",
            "subcategory":"Professional Association",
            "type":"Services"
        }
    ],
    "sg:phone":"+1 416 466 3042",
    "sg:postcode":"M4K 3T6",
    "sg:province":"ON",
    "wof:name":"Amfiktionia Hellinon Hermes",
    "wof:placetype":"venue"
},
  "geometry": {"coordinates":[-79.346687,43.683632],"type":"Point"}
}