{
  "type": "Feature",
  "properties": {
    "iso:country":"CA",
    "sg:city":"Sainte-Rose-Du-Nord",
    "sg:classifiers":[
        {
            "category":"Travel",
            "subcategory":"Hotels & Motels",
            "type":"Entertainment"
        }
    ],
    "sg:phone":"+1 418 675 1326",
    "sg:postcode":"G0V 1T0",
    "sg:province":"QC",
    "sg:tags":[
        "breakfast",
        "accommodation",
        "bed"
    ],
    "wof:name":"Gite-Resto Au Presbytere",
    "wof:placetype":"venue"
},
  "geometry": {"coordinates":[-70.6208267212,48.4157791138],"type":"Point"}
}