{
  "type": "Feature",
  "properties": {
    "addr:full":"Burnaby BC V5C 3Y6",
    "addr:postcode":"v5c 3y6",
    "iso:country":"CA",
    "sg:city":"Burnaby",
    "sg:classifiers":[
        {
            "category":"Manufacturing",
            "subcategory":"Printing",
            "type":"Manufacturing & Wholesale Goods"
        }
    ],
    "sg:phone":"+1 604 294 5452",
    "sg:postcode":"V5C 3Y6",
    "sg:province":"BC",
    "sg:tags":[
        "screen"
    ],
    "wof:name":"Design Sportswear Ltd",
    "wof:placetype":"venue"
},
  "geometry": {"coordinates":[-123.011657715,49.2665023804],"type":"Point"}
}