{
  "type": "Feature",
  "properties": {
    "addr:full":"3110 Pine Point Rd Port Perry ON L9L 1B4",
    "addr:housenumber":"3110",
    "addr:postcode":"l9l 1b4",
    "addr:street":"Pine Point Rd",
    "iso:country":"CA",
    "sg:address":"3110 Pine Point Rd",
    "sg:city":"Port Perry",
    "sg:classifiers":[
        {
            "category":"Taxi",
            "type":"Transportation"
        }
    ],
    "sg:phone":"+1 905 985 8294",
    "sg:postcode":"L9L 1B4",
    "sg:province":"ON",
    "sg:tags":[
        "taxicab"
    ],
    "wof:name":"Island Taxi",
    "wof:placetype":"venue"
},
  "geometry": {"coordinates":[-78.8661117554,44.1495094299],"type":"Point"}
}