{
  "type": "Feature",
  "properties": {
    "addr:full":"418 Boul Labelle Rosemere QC J7A 3R8",
    "addr:housenumber":"418",
    "addr:postcode":"j7a 3r8",
    "addr:street":"Boul Labelle",
    "iso:country":"CA",
    "sg:address":"418 Boul Labelle",
    "sg:city":"Rosemere",
    "sg:classifiers":[
        {
            "category":"Retail",
            "subcategory":"Funeral Services",
            "type":"Services"
        }
    ],
    "sg:phone":"+1 514 871 2020",
    "sg:postcode":"J7A 3R8",
    "sg:province":"QC",
    "sg:tags":[
        "director"
    ],
    "wof:name":"Salon Funeraire Guay Inc",
    "wof:placetype":"venue"
},
  "geometry": {"coordinates":[-73.8181381226,45.6337203979],"type":"Point"}
}