{
  "type": "Feature",
  "properties": {
    "iso:country":"CA",
    "sg:address":"1341 Johnston Dr",
    "sg:city":"Peterborough",
    "sg:classifiers":[
        {
            "category":"Building & Trades",
            "subcategory":"Construction",
            "type":"Services"
        }
    ],
    "sg:phone":"+1 705 745 0212",
    "sg:postcode":"K9J 6X6",
    "sg:province":"ON",
    "sg:tags":[
        "excavating",
        "contractor"
    ],
    "wof:name":"Brockwell Excavating",
    "wof:placetype":"venue"
},
  "geometry": {"coordinates":[-78.339935,44.26244],"type":"Point"}
}