{
  "type": "Feature",
  "properties": {
    "addr:full":"5155 Grand Blvd Windsor ON N8T 1M2",
    "addr:housenumber":"5155",
    "addr:postcode":"n8t 1m2",
    "addr:street":"Grand Blvd",
    "iso:country":"CA",
    "sg:address":"5155 Grand Blvd",
    "sg:city":"Windsor",
    "sg:classifiers":[
        {
            "category":"Building & Trades",
            "subcategory":"Pest Control",
            "type":"Services"
        }
    ],
    "sg:phone":"+1 519 945 1843",
    "sg:postcode":"N8T 1M2",
    "sg:province":"ON",
    "wof:name":"Bug Doctor Inc",
    "wof:placetype":"venue"
},
  "geometry": {"coordinates":[-82.9554367065,42.2972412109],"type":"Point"}
}