{
  "type": "Feature",
  "properties": {
    "addr:full":"737 Av Meloche Dorval QC H9P 2S4",
    "addr:housenumber":"737",
    "addr:postcode":"h9p 2s4",
    "addr:street":"Av Meloche",
    "iso:country":"CA",
    "sg:address":"737 Av Meloche",
    "sg:city":"Dorval",
    "sg:classifiers":[
        {
            "category":"Wholesale",
            "subcategory":"Machinery & Supplies",
            "type":"Manufacturing & Wholesale Goods"
        }
    ],
    "sg:phone":"+1 514 636 1605",
    "sg:postcode":"H9P 2S4",
    "sg:province":"QC",
    "sg:tags":[
        "abrasive"
    ],
    "wof:name":"Abrasicorp & Equipment Ltd",
    "wof:placetype":"venue"
},
  "geometry": {"coordinates":[-73.7278060913,45.4567222595],"type":"Point"}
}