{
  "type": "Feature",
  "properties": {
    "addr:full":"4101 32 St Vernon BC V1T 5P3",
    "addr:housenumber":"4101",
    "addr:postcode":"v1t 5p3",
    "addr:street":"32 St",
    "iso:country":"CA",
    "sg:address":"4101 32 St",
    "sg:city":"Vernon",
    "sg:classifiers":[
        {
            "category":"Restaurant",
            "type":"Food & Drink"
        }
    ],
    "sg:phone":"+1 250 542 7161",
    "sg:postcode":"V1T 5P3",
    "sg:province":"BC",
    "wof:name":"Waddy's Family Restaurant",
    "wof:placetype":"venue"
},
  "geometry": {"coordinates":[-119.27372699999999,50.272469],"type":"Point"}
}