{
  "type": "Feature",
  "properties": {
    "addr:full":"700 Kerr St Oakville ON L6K 3W5",
    "addr:housenumber":"700",
    "addr:postcode":"l6k 3w5",
    "addr:street":"Kerr St",
    "iso:country":"CA",
    "sg:address":"700 Kerr St",
    "sg:city":"Oakville",
    "sg:classifiers":[
        {
            "category":"Professional",
            "subcategory":"Lawyer & Legal Services",
            "type":"Services"
        }
    ],
    "sg:phone":"+1 905 842 8030",
    "sg:postcode":"L6K 3W5",
    "sg:province":"ON",
    "sg:tags":[
        "attorney"
    ],
    "wof:name":"Gangbar, Larry S",
    "wof:placetype":"venue"
},
  "geometry": {"coordinates":[-79.69230651860001,43.4492874146],"type":"Point"}
}