{
  "type": "Feature",
  "properties": {
    "addr:full":"804 16 Ave Cold Lake AB T9M 1L2",
    "addr:postcode":"t9m 1l2",
    "addr:street":"804 16 Ave",
    "iso:country":"CA",
    "sg:address":"804 16 Ave",
    "sg:city":"Cold Lake",
    "sg:classifiers":[
        {
            "category":"Food & Beverages",
            "subcategory":"Groceries & Convenience Stores",
            "type":"Retail Goods"
        }
    ],
    "sg:phone":"+1 780 639 3289",
    "sg:postcode":"T9M 1L2",
    "sg:province":"AB",
    "sg:tags":[
        "grocer"
    ],
    "wof:name":"D & B Convenience Store Ltd",
    "wof:placetype":"venue"
},
  "geometry": {"coordinates":[-110.169929504,54.4571037292],"type":"Point"}
}