{
  "type": "Feature",
  "properties": {
    "addr:full":"125 King Side Rd Richmond Hill ON L4E 1A5",
    "addr:housenumber":"125",
    "addr:postcode":"l4e 1a5",
    "addr:street":"King Side Rd",
    "iso:country":"CA",
    "sg:address":"125 King Side Rd",
    "sg:city":"Richmond Hill",
    "sg:classifiers":[
        {
            "category":"Home & Garden",
            "subcategory":"Hardware",
            "type":"Retail Goods"
        }
    ],
    "sg:phone":"+1 905 773 5428",
    "sg:postcode":"L4E 1A5",
    "sg:province":"ON",
    "wof:name":"Home Hardware Stores",
    "wof:placetype":"venue"
},
  "geometry": {"coordinates":[-79.378471,43.846554],"type":"Point"}
}