{
  "type": "Feature",
  "properties": {
    "addr:full":"1800 Garcia St Merritt BC V1K 1B8",
    "addr:housenumber":"1800",
    "addr:postcode":"v1k 1b8",
    "addr:street":"Garcia St",
    "iso:country":"CA",
    "sg:address":"1800 Garcia St",
    "sg:city":"Merritt",
    "sg:classifiers":[
        {
            "category":"Shopping",
            "subcategory":"Pharmacy",
            "type":"Retail Goods"
        }
    ],
    "sg:phone":"+1 250 378 9238",
    "sg:postcode":"V1K 1B8",
    "sg:province":"BC",
    "wof:name":"Pharmasave Drugs",
    "wof:placetype":"venue"
},
  "geometry": {"coordinates":[-120.78769699999999,50.108955],"type":"Point"}
}