{
  "type": "Feature",
  "properties": {
    "addr:full":"42 Grand River St N Paris ON N3L 2M2",
    "addr:housenumber":"42",
    "addr:postcode":"n3l 2m2",
    "addr:street":"Grand;St N",
    "iso:country":"CA",
    "sg:address":"42 Grand River St N",
    "sg:city":"Paris",
    "sg:classifiers":[
        {
            "category":"Home & Garden",
            "subcategory":"Building Materials",
            "type":"Retail Goods"
        }
    ],
    "sg:phone":"+1 519 442 3152",
    "sg:postcode":"N3L 2M2",
    "sg:province":"ON",
    "sg:tags":[
        "wallpaper"
    ],
    "wof:name":"Sales Decorating Ctr",
    "wof:placetype":"venue"
},
  "geometry": {"coordinates":[-80.38413199999999,43.193214],"type":"Point"}
}