{
  "type": "Feature",
  "properties": {
    "addr:full":"817 1E Rang Saint-Antonin QC G0L 2J0",
    "addr:housenumber":"817",
    "addr:postcode":"g0l 2j0",
    "addr:street":"1E Rang",
    "iso:country":"CA",
    "sg:address":"817 1E Rang",
    "sg:city":"Saint-Antonin",
    "sg:classifiers":[
        {
            "category":"Freight",
            "type":"Transportation"
        }
    ],
    "sg:phone":"+1 418 867 4141",
    "sg:postcode":"G0L 2J0",
    "sg:province":"QC",
    "sg:tags":[
        "renting",
        "truck",
        "leasing",
        "trucking"
    ],
    "wof:name":"An-Je-Re Inc",
    "wof:placetype":"venue"
},
  "geometry": {"coordinates":[-69.4792022705,47.7612266541],"type":"Point"}
}