{
  "type": "Feature",
  "properties": {
    "addr:full":"6317 Donway Dr Mississauga ON L5V 1J1",
    "addr:housenumber":"6317",
    "addr:postcode":"l5v 1j1",
    "addr:street":"Donway Dr",
    "iso:country":"CA",
    "sg:address":"6317 Donway Dr",
    "sg:city":"Mississauga",
    "sg:classifiers":[
        {
            "category":"Manufacturing",
            "subcategory":"Electronics",
            "type":"Manufacturing & Wholesale Goods"
        }
    ],
    "sg:phone":"+1 905 814 1725",
    "sg:postcode":"L5V 1J1",
    "sg:province":"ON",
    "sg:tags":[
        "equipment",
        "electronic",
        "supply"
    ],
    "wof:name":"Trans Electronics",
    "wof:placetype":"venue"
},
  "geometry": {"coordinates":[-79.710167,43.61298],"type":"Point"}
}