{
  "type": "Feature",
  "properties": {
    "iso:country":"CA",
    "sg:address":"2562 Av Des Diamants",
    "sg:city":"Alma",
    "sg:classifiers":[
        {
            "category":"Manufacturing",
            "subcategory":"Metals",
            "type":"Manufacturing & Wholesale Goods"
        }
    ],
    "sg:phone":"+1 418 662 4836",
    "sg:postcode":"G8E 2C4",
    "sg:province":"QC",
    "sg:tags":[
        "enameling",
        "japanning",
        "lacquering"
    ],
    "wof:name":"Baignoire Email Du Lac",
    "wof:placetype":"venue"
},
  "geometry": {"coordinates":[-71.6327133179,48.5970306396],"type":"Point"}
}