{
  "type": "Feature",
  "properties": {
    "addr:full":"27271 Fraser Hwy Aldergrove BC V4W 3P9",
    "addr:housenumber":"27271",
    "addr:postcode":"v4w 3p9",
    "addr:street":"Fraser Hwy",
    "iso:country":"CA",
    "sg:address":"27271 Fraser Hwy",
    "sg:city":"Aldergrove",
    "sg:classifiers":[
        {
            "category":"Travel",
            "subcategory":"Travel Agent",
            "type":"Entertainment"
        }
    ],
    "sg:phone":"+1 604 856 7741",
    "sg:postcode":"V4W 3P9",
    "sg:province":"BC",
    "sg:tags":[
        "agency",
        "bureau"
    ],
    "wof:name":"Marlin Travel",
    "wof:placetype":"venue"
},
  "geometry": {"coordinates":[-122.46863555900001,49.0580711365],"type":"Point"}
}