{
  "type": "Feature",
  "properties": {
    "addr:full":"2365 Industrial Park Rd Innisfil ON L9S 3W1",
    "addr:housenumber":"2365",
    "addr:postcode":"l9s 3w1",
    "addr:street":"Industrial Park Rd",
    "iso:country":"CA",
    "sg:address":"2365 Industrial Park Rd",
    "sg:city":"Innisfil",
    "sg:classifiers":[
        {
            "category":"Wholesale",
            "subcategory":"Apparel",
            "type":"Manufacturing & Wholesale Goods"
        }
    ],
    "sg:phone":"+1 705 436 6137",
    "sg:postcode":"L9S 3W1",
    "sg:province":"ON",
    "sg:tags":[
        "advertising"
    ],
    "wof:name":"Graphic Apparel Inc",
    "wof:placetype":"venue"
},
  "geometry": {"coordinates":[-79.681725,44.295971],"type":"Point"}
}