{
  "type": "Feature",
  "properties": {
    "addr:full":"566 Laurier Dr Prince Albert SK S6V 5M3",
    "addr:housenumber":"566",
    "addr:postcode":"s6v 5m3",
    "addr:street":"Laurier Dr",
    "iso:country":"CA",
    "sg:address":"566 Laurier Dr",
    "sg:city":"Prince Albert",
    "sg:classifiers":[
        {
            "category":"Home & Garden",
            "subcategory":"Garden Supply",
            "type":"Retail Goods"
        }
    ],
    "sg:phone":"+1 306 764 4319",
    "sg:postcode":"S6V 5M3",
    "sg:province":"SK",
    "sg:tags":[
        "sprinkler"
    ],
    "wof:name":"Midland Undergrnd Lawn Sprnklr",
    "wof:placetype":"venue"
},
  "geometry": {"coordinates":[-105.76620483400001,53.1862754822],"type":"Point"}
}