{
  "type": "Feature",
  "properties": {
    "addr:full":"26 Park St Gore Bay ON P0P 1H0",
    "addr:housenumber":"26",
    "addr:postcode":"p0p 1h0",
    "addr:street":"Park St",
    "iso:country":"CA",
    "sg:address":"26 Park St",
    "sg:city":"Gore Bay",
    "sg:classifiers":[
        {
            "category":"Building & Trades",
            "subcategory":"Plumbing",
            "type":"Services"
        }
    ],
    "sg:phone":"+1 705 282 2843",
    "sg:postcode":"P0P 1H0",
    "sg:province":"ON",
    "sg:tags":[
        "heating",
        "contractor"
    ],
    "wof:name":"W & C Mc Quarrie Heating",
    "wof:placetype":"venue"
},
  "geometry": {"coordinates":[-82.46511099999999,45.908722],"type":"Point"}
}