{
  "type": "Feature",
  "properties": {
    "addr:full":"Gander NL A1V 1W8",
    "addr:postcode":"a1v 1w8",
    "iso:country":"CA",
    "sg:city":"Gander",
    "sg:classifiers":[
        {
            "category":"Airport",
            "type":"Transportation"
        }
    ],
    "sg:phone":"+1 709 651 5000",
    "sg:postcode":"A1V 1W8",
    "sg:province":"NL",
    "sg:tags":[
        "aircraft",
        "maintenance"
    ],
    "wof:name":"Irving Aviation Svc Ltd",
    "wof:placetype":"venue"
},
  "geometry": {"coordinates":[-54.580238,48.94648],"type":"Point"}
}