{
  "type": "Feature",
  "properties": {
    "addr:full":"7550 Duncan St Powell River BC V8A 1W7",
    "addr:housenumber":"7550",
    "addr:postcode":"v8a 1w7",
    "addr:street":"Duncan St",
    "iso:country":"CA",
    "sg:address":"7550 Duncan St",
    "sg:city":"Powell River",
    "sg:classifiers":[
        {
            "category":"Restaurant",
            "type":"Food & Drink"
        }
    ],
    "sg:phone":"+1 604 485 5975",
    "sg:postcode":"V8A 1W7",
    "sg:province":"BC",
    "sg:tags":[
        "delicatessen"
    ],
    "wof:name":"Airport Market",
    "wof:placetype":"venue"
},
  "geometry": {"coordinates":[-124.494469,49.836769],"type":"Point"}
}