{
  "type": "Feature",
  "properties": {
    "iso:country":"CA",
    "sg:address":"7335 Edmonds St",
    "sg:city":"Burnaby",
    "sg:classifiers":[
        {
            "category":"Professional",
            "subcategory":"Accounting & Tax Preparation",
            "type":"Services"
        }
    ],
    "sg:phone":"+1 604 522 2152",
    "sg:postcode":"V3N 1A7",
    "sg:province":"BC",
    "sg:tags":[
        "accountant",
        "bookkeeping",
        "general"
    ],
    "wof:name":"Pmh Accounting Svc",
    "wof:placetype":"venue"
},
  "geometry": {"coordinates":[-122.95059204099999,49.2191238403],"type":"Point"}
}