{
  "type": "Feature",
  "properties": {
    "iso:country":"CA",
    "sg:address":"415 Rue Ellice",
    "sg:city":"Beauharnois",
    "sg:classifiers":[
        {
            "category":"Health Services",
            "subcategory":"Optometrist",
            "type":"Services"
        }
    ],
    "sg:phone":"+1 450 429 2254",
    "sg:postcode":"J6N 1X6",
    "sg:province":"QC",
    "wof:name":"Iris Optometristes-Opticiens",
    "wof:placetype":"venue"
},
  "geometry": {"coordinates":[-73.87465667719999,45.3145179749],"type":"Point"}
}