{
  "type": "Feature",
  "properties": {
    "addr:full":"510 Duncan Ave Burnaby BC V5B 4L9",
    "addr:housenumber":"510",
    "addr:postcode":"v5b 4l9",
    "addr:street":"Duncan Ave",
    "iso:country":"CA",
    "sg:address":"510 Duncan Ave",
    "sg:city":"Burnaby",
    "sg:classifiers":[
        {
            "category":"Education",
            "subcategory":"School",
            "type":"Public Place"
        }
    ],
    "sg:phone":"+1 604 664 8878",
    "sg:postcode":"V5B 4L9",
    "sg:province":"BC",
    "wof:name":"Westridge Elementary School",
    "wof:placetype":"venue"
},
  "geometry": {"coordinates":[-122.962143,49.279465],"type":"Point"}
}