{
  "type": "Feature",
  "properties": {
    "addr:full":"Gravenhurst ON P1P 1H5",
    "addr:postcode":"p1p 1h5",
    "iso:country":"CA",
    "sg:city":"Gravenhurst",
    "sg:classifiers":[
        {
            "category":"Manufacturing",
            "subcategory":"Printing",
            "type":"Manufacturing & Wholesale Goods"
        }
    ],
    "sg:phone":"+1 705 687 1510",
    "sg:postcode":"P1P 1H5",
    "sg:province":"ON",
    "sg:tags":[
        "printer",
        "duplicating",
        "copying"
    ],
    "wof:name":"Artstract CO",
    "wof:placetype":"venue"
},
  "geometry": {"coordinates":[-79.37331399999999,44.91861],"type":"Point"}
}