{
  "type": "Feature",
  "properties": {
    "addr:full":"621 Rue Jarry O Montreal QC H3N 1G3",
    "addr:housenumber":"621",
    "addr:postcode":"h3n 1g3",
    "addr:street":"Rue Jarry O",
    "iso:country":"CA",
    "sg:address":"621 Rue Jarry O",
    "sg:city":"Montreal",
    "sg:classifiers":[
        {
            "category":"Food & Beverages",
            "subcategory":"Groceries & Convenience Stores",
            "type":"Retail Goods"
        }
    ],
    "sg:phone":"+1 514 495 8907",
    "sg:postcode":"H3N 1G3",
    "sg:province":"QC",
    "wof:name":"Marche Africana Enr",
    "wof:placetype":"venue"
},
  "geometry": {"coordinates":[-73.62809753419999,45.5446395874],"type":"Point"}
}