{
  "type": "Feature",
  "properties": {
    "iso:country":"CA",
    "sg:address":"11925 Haney Pl",
    "sg:city":"Maple Ridge",
    "sg:classifiers":[
        {
            "category":"Social Services",
            "subcategory":"Child Care",
            "type":"Services"
        }
    ],
    "sg:phone":"+1 604 463 4652",
    "sg:postcode":"V2X 6G2",
    "sg:province":"BC",
    "wof:name":"Golden Ears Preschool",
    "wof:placetype":"venue"
},
  "geometry": {"coordinates":[-122.60114288299999,49.2191696167],"type":"Point"}
}