{
  "type": "Feature",
  "properties": {
    "addr:full":"930 Rue Jean-Talon O Montreal QC H3N 1S8",
    "addr:housenumber":"930",
    "addr:postcode":"h3n 1s8",
    "addr:street":"Rue Jean-Talon O",
    "iso:country":"CA",
    "sg:address":"930 Rue Jean-Talon O",
    "sg:city":"Montreal",
    "sg:classifiers":[
        {
            "category":"Shopping",
            "subcategory":"Pharmacy",
            "type":"Retail Goods"
        }
    ],
    "sg:phone":"+1 514 276 3155",
    "sg:postcode":"H3N 1S8",
    "sg:province":"QC",
    "wof:name":"Jean Coutu",
    "wof:placetype":"venue"
},
  "geometry": {"coordinates":[-73.61267100000001,45.54126],"type":"Point"}
}