{
  "type": "Feature",
  "properties": {
    "iso:country":"CA",
    "sg:address":"1550 Lansdowne St W",
    "sg:city":"Peterborough",
    "sg:classifiers":[
        {
            "category":"Shopping",
            "type":"Retail Goods"
        }
    ],
    "sg:phone":"+1 705 742 1311",
    "sg:postcode":"K9J 2A2",
    "sg:province":"ON",
    "sg:tags":[
        "pet",
        "food",
        "supply"
    ],
    "wof:name":"Paulmac's Pet Food Plus Pets",
    "wof:placetype":"venue"
},
  "geometry": {"coordinates":[-78.3646316528,44.2774505615],"type":"Point"}
}