{
  "type": "Feature",
  "properties": {
    "addr:full":"5956 Rue Saint-Laurent Levis QC G6V 3P4",
    "addr:housenumber":"5956",
    "addr:postcode":"g6v 3p4",
    "addr:street":"Rue Saint-Laurent",
    "iso:country":"CA",
    "sg:address":"5956 Rue Saint-Laurent",
    "sg:city":"Levis",
    "sg:classifiers":[
        {
            "category":"Sports & Exercise",
            "subcategory":"Bowling",
            "type":"Entertainment"
        }
    ],
    "sg:phone":"+1 418 833 2655",
    "sg:postcode":"G6V 3P4",
    "sg:province":"QC",
    "sg:tags":[
        "center"
    ],
    "wof:name":"Salle-Quilles Grondin & Nadeau",
    "wof:placetype":"venue"
},
  "geometry": {"coordinates":[-71.1865234375,46.8093109131],"type":"Point"}
}