{
  "type": "Feature",
  "properties": {
    "addr:full":"479 King St W Hamilton ON L8P 1B9",
    "addr:housenumber":"479",
    "addr:postcode":"l8p 1b9",
    "addr:street":"King St W",
    "iso:country":"CA",
    "sg:address":"479 King St W",
    "sg:city":"Hamilton",
    "sg:classifiers":[
        {
            "category":"Personal",
            "subcategory":"Beauty Salon",
            "type":"Services"
        }
    ],
    "sg:phone":"+1 905 527 5235",
    "sg:postcode":"L8P 1B9",
    "sg:province":"ON",
    "wof:name":"Moda Hair Dressing",
    "wof:placetype":"venue"
},
  "geometry": {"coordinates":[-79.883430481,43.260799408],"type":"Point"}
}