{
  "type": "Feature",
  "properties": {
    "addr:full":"8888 128 St Surrey BC V3V 5M7",
    "addr:housenumber":"8888",
    "addr:postcode":"v3v 5m7",
    "addr:street":"128 St",
    "iso:country":"CA",
    "sg:address":"8888 128 St",
    "sg:city":"Surrey",
    "sg:classifiers":[
        {
            "category":"Social Services",
            "subcategory":"Child Care",
            "type":"Services"
        }
    ],
    "sg:phone":"+1 604 590 3348",
    "sg:postcode":"V3V 5M7",
    "sg:province":"BC",
    "wof:name":"Premier Pas Preschool",
    "wof:placetype":"venue"
},
  "geometry": {"coordinates":[-122.867858887,49.1644744873],"type":"Point"}
}