{
  "type": "Feature",
  "properties": {
    "addr:full":"Windsor ON N8W 5K8",
    "addr:postcode":"n8w 5k8",
    "iso:country":"CA",
    "sg:city":"Windsor",
    "sg:classifiers":[
        {
            "category":"Banks & Credit Unions",
            "subcategory":"Bank",
            "type":"Services"
        }
    ],
    "sg:phone":"+1 519 945 6847",
    "sg:postcode":"N8W 5K8",
    "sg:province":"ON",
    "sg:tags":[
        "loan",
        "real estate"
    ],
    "wof:name":"Mortgage Intelligence",
    "wof:placetype":"venue"
},
  "geometry": {"coordinates":[-82.9699020386,42.2820167542],"type":"Point"}
}