{
  "type": "Feature",
  "properties": {
    "addr:full":"PO Box 5360 STN Main Fort Mcmurray AB T9H 3G4",
    "addr:housenumber":"po",
    "addr:postcode":"5360;t9h 3g4",
    "addr:street":"Box;Stn Main",
    "iso:country":"CA",
    "sg:address":"PO Box 5360 STN Main",
    "sg:city":"Fort Mcmurray",
    "sg:classifiers":[
        {
            "category":"Organizations",
            "subcategory":"Professional Association",
            "type":"Services"
        }
    ],
    "sg:phone":"+1 780 828 4220",
    "sg:postcode":"T9H 3G4",
    "sg:province":"AB",
    "wof:name":"Fort Mc Kay First Nation",
    "wof:placetype":"venue"
},
  "geometry": {"coordinates":[-111.380302429,56.7271881104],"type":"Point"}
}