{
  "type": "Feature",
  "properties": {
    "addr:full":"Scarborough ON M1T 3K4",
    "addr:postcode":"m1t 3k4",
    "iso:country":"CA",
    "sg:city":"Scarborough",
    "sg:classifiers":[
        {
            "category":"Professional",
            "subcategory":"Employment Agencies",
            "type":"Services"
        }
    ],
    "sg:phone":"+1 416 291 2219",
    "sg:postcode":"M1T 3K4",
    "sg:province":"ON",
    "sg:tags":[
        "opportunity"
    ],
    "wof:name":"Affordable Personnel Svc Inc",
    "wof:placetype":"venue"
},
  "geometry": {"coordinates":[-79.306946,43.779095],"type":"Point"}
}