{
  "type": "Feature",
  "properties": {
    "addr:full":"3919 Nelthorpe St Victoria BC V8X 3Z2",
    "addr:housenumber":"3919",
    "addr:postcode":"v8x 3z2",
    "addr:street":"Nelthorpe St",
    "iso:country":"CA",
    "sg:address":"3919 Nelthorpe St",
    "sg:city":"Victoria",
    "sg:classifiers":[
        {
            "category":"Personal",
            "subcategory":"Beauty Salon",
            "type":"Services"
        }
    ],
    "sg:phone":"+1 250 592 5655",
    "sg:postcode":"V8X 3Z2",
    "sg:province":"BC",
    "sg:tags":[
        "consultant",
        "health",
        "treatment",
        "skin"
    ],
    "wof:name":"Michelle's Esthetic Studio",
    "wof:placetype":"venue"
},
  "geometry": {"coordinates":[-123.364517212,48.428314209],"type":"Point"}
}