{
  "type": "Feature",
  "properties": {
    "iso:country":"CA",
    "sg:address":"465 Lyndhurst Rd",
    "sg:city":"Lyndhurst",
    "sg:classifiers":[
        {
            "category":"Travel",
            "subcategory":"Campground",
            "type":"Entertainment"
        }
    ],
    "sg:phone":"+1 613 928 2557",
    "sg:postcode":"K0E 1N0",
    "sg:province":"ON",
    "wof:name":"Wilson's Tent & Trailer Park",
    "wof:placetype":"venue"
},
  "geometry": {"coordinates":[-76.11962127690001,44.5537261963],"type":"Point"}
}