{
  "type": "Feature",
  "properties": {
    "addr:full":"Prince George BC V2L 2L5",
    "addr:postcode":"v2l 2l5",
    "iso:country":"CA",
    "sg:city":"Prince George",
    "sg:classifiers":[
        {
            "category":"Personal",
            "type":"Services"
        }
    ],
    "sg:phone":"+1 250 561 1958",
    "sg:postcode":"V2L 2L5",
    "sg:province":"BC",
    "sg:tags":[
        "therapist",
        "massage"
    ],
    "wof:name":"Therapeutic Massage Ctr",
    "wof:placetype":"venue"
},
  "geometry": {"coordinates":[-122.755424,53.908833],"type":"Point"}
}