{
  "type": "Feature",
  "properties": {
    "addr:full":"176 18th Ave E Vancouver BC V5V 1E3",
    "addr:housenumber":"176",
    "addr:postcode":"v5v 1e3",
    "addr:street":"18Th Ave E",
    "iso:country":"CA",
    "sg:address":"176 18th Ave E",
    "sg:city":"Vancouver",
    "sg:classifiers":[
        {
            "category":"Retail",
            "subcategory":"Auto Repair",
            "type":"Services"
        }
    ],
    "sg:phone":"+1 604 876 0929",
    "sg:postcode":"V5V 1E3",
    "sg:province":"BC",
    "sg:tags":[
        "repairing",
        "automobile"
    ],
    "wof:name":"Sam & Sons Automotive Ltd",
    "wof:placetype":"venue"
},
  "geometry": {"coordinates":[-123.101707459,49.254524231],"type":"Point"}
}