{
  "type": "Feature",
  "properties": {
    "addr:full":"1810 Rogers Pl Kamloops BC V1S 1T7",
    "addr:housenumber":"1810",
    "addr:postcode":"bc v1s 1t7",
    "addr:street":"Rogers Pl",
    "iso:country":"CA",
    "sg:address":"1810 Rogers Pl",
    "sg:city":"Kamloops",
    "sg:classifiers":[
        {
            "category":"Travel",
            "subcategory":"Hotels & Motels",
            "type":"Entertainment"
        }
    ],
    "sg:phone":"+1 250 372 0987",
    "sg:postcode":"V1S 1T7",
    "sg:province":"BC",
    "wof:name":"Comfort Inn",
    "wof:placetype":"venue"
},
  "geometry": {"coordinates":[-120.369446,50.652241],"type":"Point"}
}