{
  "type": "Feature",
  "properties": {
    "iso:country":"CA",
    "sg:address":"600 Rue Du Parc",
    "sg:city":"Black Lake",
    "sg:classifiers":[
        {
            "category":"Government",
            "subcategory":"Office",
            "type":"Public Place"
        }
    ],
    "sg:phone":"+1 418 423 7571",
    "sg:postcode":"G6H 1A2",
    "sg:province":"QC",
    "wof:name":"Quebec Transports",
    "wof:placetype":"venue"
},
  "geometry": {"coordinates":[-71.3571395874,46.0661315918],"type":"Point"}
}