{
  "type": "Feature",
  "properties": {
    "iso:country":"CA",
    "sg:address":"88 James St",
    "sg:city":"Parry Sound",
    "sg:classifiers":[
        {
            "category":"Professional",
            "subcategory":"Lawyer & Legal Services",
            "type":"Services"
        }
    ],
    "sg:phone":"+1 705 746 4207",
    "sg:postcode":"P2A 1T9",
    "sg:province":"ON",
    "sg:tags":[
        "attorney"
    ],
    "wof:name":"Powell Cunningham & Grandy",
    "wof:placetype":"venue"
},
  "geometry": {"coordinates":[-80.03388200000001,45.347095],"type":"Point"}
}