{
  "type": "Feature",
  "properties": {
    "addr:full":"2934 County Road 19 St Marys ON N4X 1C9",
    "addr:housenumber":"2934",
    "addr:postcode":"n4x 1c9",
    "addr:street":"County Road 19",
    "iso:country":"CA",
    "sg:address":"2934 County Road 19",
    "sg:city":"St Marys",
    "sg:classifiers":[
        {
            "category":"Building & Trades",
            "subcategory":"Construction",
            "type":"Services"
        }
    ],
    "sg:phone":"+1 519 284 8090",
    "sg:postcode":"N4X 1C9",
    "sg:province":"ON",
    "sg:tags":[
        "masonry",
        "contractor"
    ],
    "wof:name":"Tony's Masonry & Concrete",
    "wof:placetype":"venue"
},
  "geometry": {"coordinates":[-81.141426,43.259495],"type":"Point"}
}