{
  "type": "Feature",
  "properties": {
    "addr:full":"88 Tacoma Dr Dartmouth NS B2W 3E5",
    "addr:housenumber":"88",
    "addr:postcode":"b2w 3e5",
    "addr:street":"Tacoma Dr",
    "iso:country":"CA",
    "sg:address":"88 Tacoma Dr",
    "sg:city":"Dartmouth",
    "sg:classifiers":[
        {
            "category":"Restaurant",
            "type":"Food & Drink"
        }
    ],
    "sg:phone":"+1 902 435 1136",
    "sg:postcode":"B2W 3E5",
    "sg:province":"NS",
    "wof:name":"Burger King",
    "wof:placetype":"venue"
},
  "geometry": {"coordinates":[-63.5365447998,44.6803894043],"type":"Point"}
}