{
  "type": "Feature",
  "properties": {
    "iso:country":"CA",
    "sg:address":"1608 Princess Ave",
    "sg:city":"Brandon",
    "sg:classifiers":[
        {
            "category":"Food & Beverages",
            "subcategory":"Groceries & Convenience Stores",
            "type":"Retail Goods"
        }
    ],
    "sg:phone":"+1 204 727 7135",
    "sg:postcode":"R7A 0R9",
    "sg:province":"MB",
    "sg:tags":[
        "confectionery",
        "candy"
    ],
    "wof:name":"Hurl's Food Marts",
    "wof:placetype":"venue"
},
  "geometry": {"coordinates":[-99.9598770142,49.8467407227],"type":"Point"}
}