{
  "type": "Feature",
  "properties": {
    "addr:full":"Vernon BC V1T 7E3",
    "addr:postcode":"v1t 7e3",
    "iso:country":"CA",
    "sg:city":"Vernon",
    "sg:classifiers":[
        {
            "category":"Shopping",
            "subcategory":"Catalog Store",
            "type":"Retail Goods"
        }
    ],
    "sg:phone":"+1 250 545 0551",
    "sg:postcode":"V1T 7E3",
    "sg:province":"BC",
    "sg:tags":[
        "mail",
        "order",
        "internet"
    ],
    "wof:name":"Sears Canada Inc",
    "wof:placetype":"venue"
},
  "geometry": {"coordinates":[-119.26281,50.256313],"type":"Point"}
}