{
  "type": "Feature",
  "properties": {
    "addr:full":"750 Upper James St Hamilton ON L9C 3A2",
    "addr:housenumber":"750",
    "addr:postcode":"l9c 3a2",
    "addr:street":"Upper James St",
    "iso:country":"CA",
    "sg:address":"750 Upper James St",
    "sg:city":"Hamilton",
    "sg:classifiers":[
        {
            "category":"Home & Garden",
            "subcategory":"Furniture",
            "type":"Retail Goods"
        }
    ],
    "sg:phone":"+1 905 387 5957",
    "sg:postcode":"L9C 3A2",
    "sg:province":"ON",
    "wof:name":"Designer Furniture & Mattress",
    "wof:placetype":"venue"
},
  "geometry": {"coordinates":[-79.881187,43.230415],"type":"Point"}
}