{
  "type": "Feature",
  "properties": {
    "addr:full":"6135 28 Ave NW Edmonton AB T6L 6N5",
    "addr:housenumber":"6135",
    "addr:postcode":"t6l 6n5",
    "addr:street":"28 Ave Nw",
    "iso:country":"CA",
    "sg:address":"6135 28 Ave NW",
    "sg:city":"Edmonton",
    "sg:classifiers":[
        {
            "category":"Health Services",
            "subcategory":"Optometrist",
            "type":"Services"
        }
    ],
    "sg:phone":"+1 780 462 8209",
    "sg:postcode":"T6L 6N5",
    "sg:province":"AB",
    "wof:name":"Milton & Assoc",
    "wof:placetype":"venue"
},
  "geometry": {"coordinates":[-113.42823,53.458618],"type":"Point"}
}