{
  "type": "Feature",
  "properties": {
    "addr:full":"Toronto ON M5G 1Z5",
    "addr:postcode":"m5g 1z5",
    "iso:country":"CA",
    "sg:city":"Toronto",
    "sg:classifiers":[
        {
            "category":"Health Services",
            "subcategory":"Optometrist",
            "type":"Services"
        }
    ],
    "sg:phone":"+1 416 977 8194",
    "sg:postcode":"M5G 1Z5",
    "sg:province":"ON",
    "wof:name":"Spilkin, Jonathan OD",
    "wof:placetype":"venue"
},
  "geometry": {"coordinates":[-79.39036560060001,43.6587524414],"type":"Point"}
}