{
  "type": "Feature",
  "properties": {
    "addr:full":"2025 Morgans Rd Newcastle ON L1B 1L9",
    "addr:housenumber":"2025",
    "addr:postcode":"l1b 1l9",
    "addr:street":"Morgans Rd",
    "iso:country":"CA",
    "sg:address":"2025 Morgans Rd",
    "sg:city":"Newcastle",
    "sg:classifiers":[
        {
            "category":"Building & Trades",
            "subcategory":"Plumbing",
            "type":"Services"
        }
    ],
    "sg:phone":"+1 905 987 0573",
    "sg:postcode":"L1B 1L9",
    "sg:province":"ON",
    "sg:tags":[
        "refrigeration",
        "contractor"
    ],
    "wof:name":"Enviroaire Heating & Cooling",
    "wof:placetype":"venue"
},
  "geometry": {"coordinates":[-78.53340900000001,43.932438],"type":"Point"}
}