{
  "type": "Feature",
  "properties": {
    "addr:full":"30 Birch St Seaforth ON N0K 1W0",
    "addr:housenumber":"30",
    "addr:postcode":"n0k 1w0",
    "addr:street":"Birch St",
    "iso:country":"CA",
    "sg:address":"30 Birch St",
    "sg:city":"Seaforth",
    "sg:classifiers":[
        {
            "category":"Retail",
            "subcategory":"Auto Repair",
            "type":"Services"
        }
    ],
    "sg:phone":"+1 519 527 2208",
    "sg:postcode":"N0K 1W0",
    "sg:province":"ON",
    "sg:tags":[
        "repairing",
        "automobile"
    ],
    "wof:name":"Silver Creek Automotive",
    "wof:placetype":"venue"
},
  "geometry": {"coordinates":[-81.3983917236,43.54637146],"type":"Point"}
}