{
  "type": "Feature",
  "properties": {
    "addr:full":"4825 118 Ave NW Edmonton AB T5W 1B5",
    "addr:housenumber":"4825",
    "addr:postcode":"t5w 1b5",
    "addr:street":"118 Ave Nw",
    "iso:country":"CA",
    "sg:address":"4825 118 Ave NW",
    "sg:city":"Edmonton",
    "sg:classifiers":[
        {
            "category":"Wholesale",
            "subcategory":"Scrap",
            "type":"Manufacturing & Wholesale Goods"
        }
    ],
    "sg:phone":"+1 780 479 3991",
    "sg:postcode":"T5W 1B5",
    "sg:province":"AB",
    "sg:tags":[
        "recycling",
        "can",
        "bottle",
        "depot"
    ],
    "wof:name":"Beverly Bottle Depot",
    "wof:placetype":"venue"
},
  "geometry": {"coordinates":[-113.416999817,53.5702819824],"type":"Point"}
}