{
  "type": "Feature",
  "properties": {
    "addr:full":"739 Windmill Rd Dartmouth NS B3B 1C1",
    "addr:housenumber":"739",
    "addr:postcode":"b3b 1c1",
    "addr:street":"Windmill Rd",
    "iso:country":"CA",
    "sg:address":"739 Windmill Rd",
    "sg:city":"Dartmouth",
    "sg:classifiers":[
        {
            "category":"Travel",
            "subcategory":"Hotels & Motels",
            "type":"Entertainment"
        }
    ],
    "sg:phone":"+1 902 468 7117",
    "sg:postcode":"B3B 1C1",
    "sg:province":"NS",
    "wof:name":"Burnside Hotel",
    "wof:placetype":"venue"
},
  "geometry": {"coordinates":[-63.6106987,44.7029457092],"type":"Point"}
}