{
  "type": "Feature",
  "properties": {
    "addr:full":"230 Main St W Merrickville ON K0G 1N0",
    "addr:housenumber":"230",
    "addr:postcode":"k0g 1n0",
    "addr:street":"Main St W Merrickville",
    "iso:country":"CA",
    "sg:address":"230 Main St W",
    "sg:city":"Merrickville",
    "sg:classifiers":[
        {
            "category":"Organizations",
            "subcategory":"Religious Organization",
            "type":"Services"
        }
    ],
    "sg:phone":"+1 613 269 4220",
    "sg:postcode":"K0G 1N0",
    "sg:province":"ON",
    "sg:tags":[
        "church"
    ],
    "wof:name":"Saint Ann Catholic Church",
    "wof:placetype":"venue"
},
  "geometry": {"coordinates":[-75.839195,44.915703],"type":"Point"}
}