{
  "type": "Feature",
  "properties": {
    "addr:full":"29 Gladiola Crt Whitby ON L1R 1N8",
    "addr:housenumber":"29",
    "addr:postcode":"l1r 1n8",
    "addr:street":"Gladiola Crt",
    "iso:country":"CA",
    "sg:address":"29 Gladiola Crt",
    "sg:city":"Whitby",
    "sg:classifiers":[
        {
            "category":"Arts & Performance",
            "subcategory":"Theater",
            "type":"Entertainment"
        }
    ],
    "sg:phone":"+1 905 723 3175",
    "sg:postcode":"L1R 1N8",
    "sg:province":"ON",
    "sg:tags":[
        "music"
    ],
    "wof:name":"Entertainment Galore",
    "wof:placetype":"venue"
},
  "geometry": {"coordinates":[-78.91288,43.906452],"type":"Point"}
}