{
  "type": "Feature",
  "properties": {
    "addr:full":"Havre-Saint-Pierre QC G0G 1P0",
    "addr:postcode":"g0g 1p0",
    "iso:country":"CA",
    "sg:city":"Havre-Saint-Pierre",
    "sg:classifiers":[
        {
            "category":"Professional",
            "subcategory":"Engineering",
            "type":"Services"
        }
    ],
    "sg:phone":"+1 418 538 1312",
    "sg:postcode":"G0G 1P0",
    "sg:province":"QC",
    "sg:tags":[
        "engineer"
    ],
    "wof:name":"Entreprises Doyle Ltee",
    "wof:placetype":"venue"
},
  "geometry": {"coordinates":[-63.5957221985,50.2411270142],"type":"Point"}
}