{
  "type": "Feature",
  "properties": {
    "addr:full":"Wawa ON P0S 1K0",
    "addr:postcode":"p0s 1k0",
    "iso:country":"CA",
    "sg:city":"Wawa",
    "sg:classifiers":[
        {
            "category":"Autos & Motor Vehicles",
            "subcategory":"Fuel & Gas Station",
            "type":"Retail Goods"
        }
    ],
    "sg:phone":"+1 705 856 2560",
    "sg:postcode":"P0S 1K0",
    "sg:province":"ON",
    "sg:tags":[
        "oil"
    ],
    "wof:name":"Pete's Auto Svc",
    "wof:placetype":"venue"
},
  "geometry": {"coordinates":[-84.77827499999999,47.987297],"type":"Point"}
}