{
  "type": "Feature",
  "properties": {
    "iso:country":"CA",
    "sg:city":"Scarborough",
    "sg:classifiers":[
        {
            "category":"Health Services",
            "subcategory":"Health Practitioner",
            "type":"Services"
        }
    ],
    "sg:phone":"+1 416 335 9880",
    "sg:postcode":"M1V 3S1",
    "sg:province":"ON",
    "sg:tags":[
        "acupuncture"
    ],
    "wof:name":"Oriental Pain Relief Clinic",
    "wof:placetype":"venue"
},
  "geometry": {"coordinates":[-79.305214,43.819962],"type":"Point"}
}