{
  "type": "Feature",
  "properties": {
    "iso:country":"CA",
    "sg:city":"Montreal",
    "sg:classifiers":[
        {
            "category":"Manufacturing",
            "subcategory":"Apparel",
            "type":"Manufacturing & Wholesale Goods"
        }
    ],
    "sg:phone":"+1 514 276 0311",
    "sg:postcode":"H2T 3B3",
    "sg:province":"QC",
    "sg:tags":[
        "clothes",
        "accessory"
    ],
    "wof:name":"Pepita LA Bambola",
    "wof:placetype":"venue"
},
  "geometry": {"coordinates":[-73.59632873539999,45.52734375],"type":"Point"}
}