{
  "type": "Feature",
  "properties": {
    "addr:full":"Sainte-Foy QC G2G 1C1",
    "addr:postcode":"g2g 1c1",
    "iso:country":"CA",
    "sg:city":"Sainte-Foy",
    "sg:classifiers":[
        {
            "category":"Real Estate",
            "subcategory":"Real Estate Agent",
            "type":"Services"
        }
    ],
    "sg:phone":"+1 418 877 7732",
    "sg:postcode":"G2G 1C1",
    "sg:province":"QC",
    "sg:tags":[
        "consultant",
        "management"
    ],
    "wof:name":"Douville Moffet & Assoc Inc",
    "wof:placetype":"venue"
},
  "geometry": {"coordinates":[-71.377312,46.773689],"type":"Point"}
}