{
  "type": "Feature",
  "properties": {
    "iso:country":"CA",
    "sg:city":"Laval",
    "sg:classifiers":[
        {
            "category":"Professional",
            "subcategory":"Printing & Photocopies",
            "type":"Services"
        }
    ],
    "sg:phone":"+1 450 967 7678",
    "sg:postcode":"H7M 4M2",
    "sg:province":"QC",
    "sg:tags":[
        "courier",
        "copying",
        "duplicating"
    ],
    "wof:name":"Copie Courrier & Plus",
    "wof:placetype":"venue"
},
  "geometry": {"coordinates":[-73.734726,45.609207],"type":"Point"}
}