{
  "type": "Feature",
  "properties": {
    "addr:full":"1060 Rue Girouard Marieville QC J3M 1G7",
    "addr:housenumber":"1060",
    "addr:postcode":"j3m 1g7",
    "addr:street":"Rue Girouard",
    "iso:country":"CA",
    "sg:address":"1060 Rue Girouard",
    "sg:city":"Marieville",
    "sg:classifiers":[
        {
            "category":"Home & Garden",
            "subcategory":"Hardware",
            "type":"Retail Goods"
        }
    ],
    "sg:phone":"+1 450 469 4048",
    "sg:postcode":"J3M 1G7",
    "sg:province":"QC",
    "wof:name":"Coopexcel Cooperative Agricole",
    "wof:placetype":"venue"
},
  "geometry": {"coordinates":[-73.16427612299999,45.429145813],"type":"Point"}
}