{
  "type": "Feature",
  "properties": {
    "addr:full":"2567 Eglinton Ave E Scarborough ON M1K 2R7",
    "addr:housenumber":"2567",
    "addr:postcode":"m1k 2r7",
    "addr:street":"Eglinton Ave E",
    "iso:country":"CA",
    "sg:address":"2567 Eglinton Ave E",
    "sg:city":"Scarborough",
    "sg:classifiers":[
        {
            "category":"Restaurant",
            "type":"Food & Drink"
        }
    ],
    "sg:phone":"+1 416 267 1173",
    "sg:postcode":"M1K 2R7",
    "sg:province":"ON",
    "wof:name":"Kfc",
    "wof:placetype":"venue"
},
  "geometry": {"coordinates":[-79.255745,43.734947],"type":"Point"}
}