{
  "type": "Feature",
  "properties": {
    "iso:country":"CA",
    "sg:address":"372 Boul Maloney O",
    "sg:city":"Gatineau",
    "sg:classifiers":[
        {
            "category":"Retail",
            "subcategory":"Auto Repair",
            "type":"Services"
        }
    ],
    "sg:phone":"+1 819 643 1936",
    "sg:postcode":"J8P 6W2",
    "sg:province":"QC",
    "sg:tags":[
        "repairing",
        "automobile"
    ],
    "wof:name":"Experts Sur Roues Inc",
    "wof:placetype":"venue"
},
  "geometry": {"coordinates":[-75.641853,45.484455],"type":"Point"}
}