{
  "type": "Feature",
  "properties": {
    "addr:full":"921 Mississauga Valley Blvd Mississauga ON L5A 2A1",
    "addr:housenumber":"921",
    "addr:postcode":"l5a 2a1",
    "addr:street":"Mississauga Valley Blvd",
    "iso:country":"CA",
    "sg:address":"921 Mississauga Valley Blvd",
    "sg:city":"Mississauga",
    "sg:classifiers":[
        {
            "category":"Home & Garden",
            "subcategory":"Building Materials",
            "type":"Retail Goods"
        }
    ],
    "sg:phone":"+1 905 949 5505",
    "sg:postcode":"L5A 2A1",
    "sg:province":"ON",
    "sg:tags":[
        "windows"
    ],
    "wof:name":"Eurotherm Windows Industry",
    "wof:placetype":"venue"
},
  "geometry": {"coordinates":[-79.61629499999999,43.601376],"type":"Point"}
}