{
  "type": "Feature",
  "properties": {
    "iso:country":"CA",
    "sg:address":"5225 Rue Berri",
    "sg:city":"Montreal",
    "sg:classifiers":[
        {
            "category":"Organizations",
            "subcategory":"Professional Association",
            "type":"Services"
        }
    ],
    "sg:phone":"+1 514 948 2044",
    "sg:postcode":"H2J 2S4",
    "sg:province":"QC",
    "wof:name":"Institut Canadien D'Education",
    "wof:placetype":"venue"
},
  "geometry": {"coordinates":[-73.5903930664,45.5292205811],"type":"Point"}
}