{
  "type": "Feature",
  "properties": {
    "addr:full":"Kemptville ON K0G 1J0",
    "addr:postcode":"k0g 1j0",
    "iso:country":"CA",
    "sg:city":"Kemptville",
    "sg:classifiers":[
        {
            "category":"Building & Trades",
            "subcategory":"Plumbing",
            "type":"Services"
        }
    ],
    "sg:phone":"+1 613 258 1262",
    "sg:postcode":"K0G 1J0",
    "sg:province":"ON",
    "sg:tags":[
        "furnace",
        "heating",
        "contractor"
    ],
    "wof:name":"R B Heating & Air Cond",
    "wof:placetype":"venue"
},
  "geometry": {"coordinates":[-75.62293200000001,45.08427],"type":"Point"}
}