{
  "type": "Feature",
  "properties": {
    "addr:full":"Saskatoon SK S7M 1X1",
    "addr:postcode":"s7m 1x1",
    "iso:country":"CA",
    "sg:city":"Saskatoon",
    "sg:classifiers":[
        {
            "category":"Food & Beverages",
            "subcategory":"Groceries & Convenience Stores",
            "type":"Retail Goods"
        }
    ],
    "sg:phone":"+1 306 653 4177",
    "sg:postcode":"S7M 1X1",
    "sg:province":"SK",
    "sg:tags":[
        "grocer"
    ],
    "wof:name":"Riversdale Grocery Store",
    "wof:placetype":"venue"
},
  "geometry": {"coordinates":[-106.681678772,52.1211929321],"type":"Point"}
}