{
  "type": "Feature",
  "properties": {
    "addr:full":"45 O'Connor St Ottawa ON K1P 1A4",
    "addr:housenumber":"45",
    "addr:postcode":"k1p 1a4",
    "addr:street":"O'Connor St",
    "iso:country":"CA",
    "sg:address":"45 O'Connor St",
    "sg:city":"Ottawa",
    "sg:classifiers":[
        {
            "category":"Government",
            "subcategory":"Office",
            "type":"Public Place"
        }
    ],
    "sg:phone":"+1 613 238 6464",
    "sg:postcode":"K1P 1A4",
    "sg:province":"ON",
    "sg:tags":[
        "federal",
        "affairs"
    ],
    "wof:name":"Delegation of European Comms",
    "wof:placetype":"venue"
},
  "geometry": {"coordinates":[-75.698898,45.421761],"type":"Point"}
}