{
  "type": "Feature",
  "properties": {
    "iso:country":"CA",
    "sg:address":"87 Main St",
    "sg:city":"Latchford",
    "sg:classifiers":[
        {
            "category":"Wholesale",
            "subcategory":"Construction Materials",
            "type":"Manufacturing & Wholesale Goods"
        }
    ],
    "sg:phone":"+1 705 676 2422",
    "sg:postcode":"P0J 1N0",
    "sg:province":"ON",
    "sg:tags":[
        "sand",
        "gravel"
    ],
    "wof:name":"Ron Paige Trucking Ltd",
    "wof:placetype":"venue"
},
  "geometry": {"coordinates":[-79.8109283447,47.3320007324],"type":"Point"}
}