{
  "type": "Feature",
  "properties": {
    "addr:full":"60 Rue Saint-Georges Windsor QC J1S 1J6",
    "addr:housenumber":"60",
    "addr:postcode":"j1s 1j6",
    "addr:street":"Rue Saint-Georges",
    "iso:country":"CA",
    "sg:address":"60 Rue Saint-Georges",
    "sg:city":"Windsor",
    "sg:classifiers":[
        {
            "category":"Home & Garden",
            "subcategory":"Carpets & Floor Coverings",
            "type":"Retail Goods"
        }
    ],
    "sg:phone":"+1 819 845 7475",
    "sg:postcode":"J1S 1J6",
    "sg:province":"QC",
    "sg:tags":[
        "paint",
        "rug"
    ],
    "wof:name":"Centre Du Tapis Windsor Enr",
    "wof:placetype":"venue"
},
  "geometry": {"coordinates":[-72.0024108887,45.5703735352],"type":"Point"}
}