{
  "type": "Feature",
  "properties": {
    "addr:full":"691 1st Ave Fernie BC V0B 1M0",
    "addr:housenumber":"691",
    "addr:postcode":"bc v0b 1m0",
    "addr:street":"1St Ave",
    "iso:country":"CA",
    "sg:address":"691 1st Ave",
    "sg:city":"Fernie",
    "sg:classifiers":[
        {
            "category":"Travel",
            "subcategory":"Hotels & Motels",
            "type":"Entertainment"
        }
    ],
    "sg:phone":"+1 250 423 6444",
    "sg:postcode":"V0B 1M0",
    "sg:province":"BC",
    "wof:name":"Fernie Hotel",
    "wof:placetype":"venue"
},
  "geometry": {"coordinates":[-115.05937957800001,49.5042495728],"type":"Point"}
}