{
  "type": "Feature",
  "properties": {
    "addr:full":"Calgary AB T2E 7B2",
    "addr:postcode":"t2e 7b2",
    "iso:country":"CA",
    "sg:city":"Calgary",
    "sg:classifiers":[
        {
            "category":"Wholesale",
            "subcategory":"Motor Vehicles",
            "type":"Manufacturing & Wholesale Goods"
        }
    ],
    "sg:phone":"+1 403 250 7825",
    "sg:postcode":"T2E 7B2",
    "sg:province":"AB",
    "sg:tags":[
        "automobile",
        "truck",
        "broker"
    ],
    "wof:name":"Fourth Dimension Vehicles Inc",
    "wof:placetype":"venue"
},
  "geometry": {"coordinates":[-114.013885,51.079811],"type":"Point"}
}