{
  "type": "Feature",
  "properties": {
    "addr:full":"30 Farnham Gate Rd # 125 Halifax NS B3M 3W8",
    "addr:housenumber":"30",
    "addr:postcode":"b3m 3w8",
    "addr:street":"Farnham Gate Rd # 125",
    "iso:country":"CA",
    "sg:address":"30 Farnham Gate Rd # 125",
    "sg:city":"Halifax",
    "sg:classifiers":[
        {
            "category":"Autos & Motor Vehicles",
            "subcategory":"Fuel & Gas Station",
            "type":"Retail Goods"
        }
    ],
    "sg:phone":"+1 902 443 6919",
    "sg:postcode":"B3M 3W8",
    "sg:province":"NS",
    "sg:tags":[
        "oil"
    ],
    "wof:name":"Wilson's Gas Stop",
    "wof:placetype":"venue"
},
  "geometry": {"coordinates":[-63.664959,44.673153],"type":"Point"}
}