{
  "type": "Feature",
  "properties": {
    "addr:full":"107 Cameron St Foam Lake SK S0A 1A0",
    "addr:housenumber":"107",
    "addr:postcode":"s0a 1a0",
    "addr:street":"Cameron St",
    "iso:country":"CA",
    "sg:address":"107 Cameron St",
    "sg:city":"Foam Lake",
    "sg:classifiers":[
        {
            "category":"Autos & Motor Vehicles",
            "subcategory":"Automobile Sales",
            "type":"Retail Goods"
        }
    ],
    "sg:phone":"+1 306 272 3214",
    "sg:postcode":"S0A 1A0",
    "sg:province":"SK",
    "sg:tags":[
        "car",
        "dealer"
    ],
    "wof:name":"Foam Lake Motors Ltd",
    "wof:placetype":"venue"
},
  "geometry": {"coordinates":[-103.535064697,51.6377868652],"type":"Point"}
}