{
  "type": "Feature",
  "properties": {
    "addr:full":"Halifax NS B3M 4N7",
    "addr:postcode":"b3m 4n7",
    "iso:country":"CA",
    "sg:city":"Halifax",
    "sg:classifiers":[
        {
            "category":"Retail",
            "subcategory":"Veterinary Services",
            "type":"Services"
        }
    ],
    "sg:phone":"+1 902 457 1575",
    "sg:postcode":"B3M 4N7",
    "sg:province":"NS",
    "sg:tags":[
        "veterinarian"
    ],
    "wof:name":"Carnegy Animal Hospital Ltd",
    "wof:placetype":"venue"
},
  "geometry": {"coordinates":[-63.6631240845,44.6700973511],"type":"Point"}
}