{
  "type": "Feature",
  "properties": {
    "addr:full":"3634 Main St Vancouver BC V5V 3N5",
    "addr:housenumber":"3634",
    "addr:postcode":"v5v 3n5",
    "addr:street":"Main St",
    "iso:country":"CA",
    "sg:address":"3634 Main St",
    "sg:city":"Vancouver",
    "sg:classifiers":[
        {
            "category":"Shopping",
            "subcategory":"Clothing, Apparel, & Fashions",
            "type":"Retail Goods"
        }
    ],
    "sg:phone":"+1 604 873 5459",
    "sg:postcode":"V5V 3N5",
    "sg:province":"BC",
    "sg:tags":[
        "item",
        "boutique"
    ],
    "wof:name":"Smoking Lily",
    "wof:placetype":"venue"
},
  "geometry": {"coordinates":[-123.100662,49.252525],"type":"Point"}
}