{
  "type": "Feature",
  "properties": {
    "iso:country":"CA",
    "sg:address":"301 Oxford St W # 56",
    "sg:city":"London",
    "sg:classifiers":[
        {
            "category":"Shopping",
            "subcategory":"Optical Goods",
            "type":"Retail Goods"
        }
    ],
    "sg:phone":"+1 519 433 3355",
    "sg:postcode":"N6H 1S6",
    "sg:province":"ON",
    "sg:tags":[
        "optician"
    ],
    "wof:name":"Cherry Hill Optical",
    "wof:placetype":"venue"
},
  "geometry": {"coordinates":[-81.275581,42.988998],"type":"Point"}
}