{
  "type": "Feature",
  "properties": {
    "addr:full":"3 Blakley Ave York ON M6N 3Y4",
    "addr:housenumber":"3",
    "addr:postcode":"m6n 3y4",
    "addr:street":"Blakley Ave",
    "iso:country":"CA",
    "sg:address":"3 Blakley Ave",
    "sg:city":"York",
    "sg:classifiers":[
        {
            "category":"Building & Trades",
            "subcategory":"Cleaning & Sanitation",
            "type":"Services"
        }
    ],
    "sg:phone":"+1 416 769 8492",
    "sg:postcode":"M6N 3Y4",
    "sg:province":"ON",
    "sg:tags":[
        "cleaners",
        "janitor",
        "rug",
        "carpet"
    ],
    "wof:name":"Inter City Carpet Cleaning",
    "wof:placetype":"venue"
},
  "geometry": {"coordinates":[-79.4807510376,43.6717262268],"type":"Point"}
}