{
  "type": "Feature",
  "properties": {
    "addr:full":"Garson ON P3L 1B4",
    "addr:postcode":"p3l 1b4",
    "iso:country":"CA",
    "sg:city":"Garson",
    "sg:classifiers":[
        {
            "category":"Food & Beverages",
            "subcategory":"Groceries & Convenience Stores",
            "type":"Retail Goods"
        }
    ],
    "sg:phone":"+1 705 693 2813",
    "sg:postcode":"P3L 1B4",
    "sg:province":"ON",
    "wof:name":"Garson Foodmarket",
    "wof:placetype":"venue"
},
  "geometry": {"coordinates":[-80.86307499999999,46.558556],"type":"Point"}
}