{
  "type": "Feature",
  "properties": {
    "addr:full":"924 Edmonton Trail NE Calgary AB T2E 3K1",
    "addr:housenumber":"924",
    "addr:postcode":"t2e 3k1",
    "addr:street":"Edmonton Trail Ne",
    "iso:country":"CA",
    "sg:address":"924 Edmonton Trail NE",
    "sg:city":"Calgary",
    "sg:classifiers":[
        {
            "category":"Food & Beverages",
            "subcategory":"Groceries & Convenience Stores",
            "type":"Retail Goods"
        }
    ],
    "sg:phone":"+1 403 230 0031",
    "sg:postcode":"T2E 3K1",
    "sg:province":"AB",
    "wof:name":"Number One Convenience Store",
    "wof:placetype":"venue"
},
  "geometry": {"coordinates":[-114.054359436,51.0600471497],"type":"Point"}
}