{
  "type": "Feature",
  "properties": {
    "addr:full":"38 Peel St Barrie ON L4M 3L2",
    "addr:housenumber":"38",
    "addr:postcode":"l4m 3l2",
    "addr:street":"Peel St",
    "iso:country":"CA",
    "sg:address":"38 Peel St",
    "sg:city":"Barrie",
    "sg:classifiers":[
        {
            "category":"Building & Trades",
            "subcategory":"Construction",
            "type":"Services"
        }
    ],
    "sg:phone":"+1 705 728 4762",
    "sg:postcode":"L4M 3L2",
    "sg:province":"ON",
    "sg:tags":[
        "contractor"
    ],
    "wof:name":"Classic Country Homes",
    "wof:placetype":"venue"
},
  "geometry": {"coordinates":[-79.68817138670001,44.3948287964],"type":"Point"}
}