{
  "type": "Feature",
  "properties": {
    "addr:full":"Abbotsford BC V2T 4X1",
    "addr:postcode":"v2t 4x1",
    "iso:country":"CA",
    "sg:city":"Abbotsford",
    "sg:classifiers":[
        {
            "category":"Government",
            "subcategory":"Office",
            "type":"Public Place"
        }
    ],
    "sg:phone":"+1 604 504 4121",
    "sg:postcode":"V2T 4X1",
    "sg:province":"BC",
    "wof:name":"B C Attorney General",
    "wof:placetype":"venue"
},
  "geometry": {"coordinates":[-122.32173899999999,49.054436],"type":"Point"}
}