{
  "type": "Feature",
  "properties": {
    "addr:full":"5665 Rue Pare Mont-Royal QC H4P 1S1",
    "addr:housenumber":"5665",
    "addr:postcode":"h4p 1s1",
    "addr:street":"Rue Pare",
    "iso:country":"CA",
    "sg:address":"5665 Rue Pare",
    "sg:city":"Mont-Royal",
    "sg:classifiers":[
        {
            "category":"Wholesale",
            "subcategory":"Auto Parts",
            "type":"Manufacturing & Wholesale Goods"
        }
    ],
    "sg:phone":"+1 514 342 1044",
    "sg:postcode":"H4P 1S1",
    "sg:province":"QC",
    "sg:tags":[
        "automobile",
        "supply"
    ],
    "wof:name":"Autolectra Inc",
    "wof:placetype":"venue"
},
  "geometry": {"coordinates":[-73.664345,45.489349],"type":"Point"}
}