{
  "type": "Feature",
  "properties": {
    "addr:full":"PO Box 16 Teslin YT Y0A 1B0",
    "addr:housenumber":"po box 16",
    "addr:postcode":"y0a 1b0",
    "iso:country":"CA",
    "sg:address":"PO Box 16",
    "sg:city":"Teslin",
    "sg:classifiers":[
        {
            "category":"Education",
            "subcategory":"School",
            "type":"Public Place"
        }
    ],
    "sg:phone":"+1 867 390 2570",
    "sg:postcode":"Y0A 1B0",
    "sg:province":"YT",
    "wof:name":"Teslin School",
    "wof:placetype":"venue"
},
  "geometry": {"coordinates":[-132.711959839,60.1686248779],"type":"Point"}
}