{
  "type": "Feature",
  "properties": {
    "addr:full":"2 Arnott St Wawa ON P0S 1K0",
    "addr:housenumber":"2",
    "addr:postcode":"p0s 1k0",
    "addr:street":"Arnott St",
    "iso:country":"CA",
    "sg:address":"2 Arnott St",
    "sg:city":"Wawa",
    "sg:classifiers":[
        {
            "category":"Education",
            "subcategory":"School",
            "type":"Public Place"
        }
    ],
    "sg:phone":"+1 705 856 4521",
    "sg:postcode":"P0S 1K0",
    "sg:province":"ON",
    "wof:name":"St Joseph's School",
    "wof:placetype":"venue"
},
  "geometry": {"coordinates":[-84.772667,47.990986],"type":"Point"}
}