{
  "type": "Feature",
  "properties": {
    "addr:full":"730 1E Rue O Barraute QC J0Y 1A0",
    "addr:housenumber":"730",
    "addr:postcode":"j0y 1a0",
    "addr:street":"1E Rue O",
    "iso:country":"CA",
    "sg:address":"730 1E Rue O",
    "sg:city":"Barraute",
    "sg:classifiers":[
        {
            "category":"Shopping",
            "subcategory":"Clothing, Apparel, & Fashions",
            "type":"Retail Goods"
        }
    ],
    "sg:phone":"+1 819 734 6781",
    "sg:postcode":"J0Y 1A0",
    "sg:province":"QC",
    "sg:tags":[
        "boutique",
        "fur",
        "business"
    ],
    "wof:name":"Fourrures Grenier Inc",
    "wof:placetype":"venue"
},
  "geometry": {"coordinates":[-77.637207,48.441628],"type":"Point"}
}