{
  "type": "Feature",
  "properties": {
    "addr:full":"7700 Pine Valley Dr # 10 Woodbridge ON L4L 2X4",
    "addr:housenumber":"7700",
    "addr:postcode":"l4l 2x4",
    "addr:street":"Pine Valley Dr # 10",
    "iso:country":"CA",
    "sg:address":"7700 Pine Valley Dr # 10",
    "sg:city":"Woodbridge",
    "sg:classifiers":[
        {
            "category":"Restaurant",
            "type":"Food & Drink"
        }
    ],
    "sg:phone":"+1 905 851 3299",
    "sg:postcode":"L4L 2X4",
    "sg:province":"ON",
    "sg:tags":[
        "sandwich"
    ],
    "wof:name":"Mr Submarine",
    "wof:placetype":"venue"
},
  "geometry": {"coordinates":[-79.5728759766,43.7824325562],"type":"Point"}
}