{
  "type": "Feature",
  "properties": {
    "addr:full":"601 Truro Heights Rd Truro NS B2N 5A9",
    "addr:housenumber":"601",
    "addr:postcode":"b2n 5a9",
    "addr:street":"Truro Heights Rd",
    "iso:country":"CA",
    "sg:address":"601 Truro Heights Rd",
    "sg:city":"Truro",
    "sg:classifiers":[
        {
            "category":"Freight",
            "type":"Transportation"
        }
    ],
    "sg:phone":"+1 902 893 7111",
    "sg:postcode":"B2N 5A9",
    "sg:province":"NS",
    "sg:tags":[
        "building",
        "house",
        "mover"
    ],
    "wof:name":"Phil Leil Enterprises Ltd",
    "wof:placetype":"venue"
},
  "geometry": {"coordinates":[-63.3048095703,45.3391990662],"type":"Point"}
}