{
  "type": "Feature",
  "properties": {
    "iso:country":"CA",
    "sg:address":"103 2nd Ave E",
    "sg:city":"Nokomis",
    "sg:classifiers":[
        {
            "category":"Health Services",
            "subcategory":"Hospital",
            "type":"Services"
        }
    ],
    "sg:phone":"+1 ",
    "sg:postcode":"S0G 3R0",
    "sg:province":"SK",
    "wof:name":"Ambulance Emergency",
    "wof:placetype":"venue"
},
  "geometry": {"coordinates":[-105.00812530499999,51.5074501038],"type":"Point"}
}