{
  "type": "Feature",
  "properties": {
    "addr:full":"17 D'Arcy St Perth ON K7H 2T9",
    "addr:housenumber":"17",
    "addr:postcode":"k7h 2t9",
    "addr:street":"D'Arcy St",
    "iso:country":"CA",
    "sg:address":"17 D'Arcy St",
    "sg:city":"Perth",
    "sg:classifiers":[
        {
            "category":"Organizations",
            "subcategory":"Religious Organization",
            "type":"Services"
        }
    ],
    "sg:phone":"+1 613 267 2023",
    "sg:postcode":"K7H 2T9",
    "sg:province":"ON",
    "sg:tags":[
        "church"
    ],
    "wof:name":"First Baptist Church",
    "wof:placetype":"venue"
},
  "geometry": {"coordinates":[-76.24678,44.897652],"type":"Point"}
}