{
  "type": "Feature",
  "properties": {
    "addr:full":"60 Clarkson Ave York ON M6E 2T6",
    "addr:housenumber":"60",
    "addr:postcode":"m6e 2t6",
    "addr:street":"Clarkson Ave",
    "iso:country":"CA",
    "sg:address":"60 Clarkson Ave",
    "sg:city":"York",
    "sg:classifiers":[
        {
            "category":"Banks & Credit Unions",
            "subcategory":"Financial Services",
            "type":"Services"
        }
    ],
    "sg:phone":"+1 416 256 9100",
    "sg:postcode":"M6E 2T6",
    "sg:province":"ON",
    "sg:tags":[
        "company",
        "holding"
    ],
    "wof:name":"Castlewall Developments Ltd",
    "wof:placetype":"venue"
},
  "geometry": {"coordinates":[-79.462189,43.69751],"type":"Point"}
}