{
  "type": "Feature",
  "properties": {
    "addr:full":"156 Edward St Clarksburg ON N0H 1J0",
    "addr:housenumber":"156",
    "addr:postcode":"n0h 1j0",
    "addr:street":"Edward St",
    "iso:country":"CA",
    "sg:address":"156 Edward St",
    "sg:city":"Clarksburg",
    "sg:classifiers":[
        {
            "category":"Health Services",
            "subcategory":"Doctor",
            "type":"Services"
        }
    ],
    "sg:phone":"+1 519 599 2120",
    "sg:postcode":"N0H 1J0",
    "sg:province":"ON",
    "sg:tags":[
        "physician",
        "surgeon"
    ],
    "wof:name":"Irvine, I F MD",
    "wof:placetype":"venue"
},
  "geometry": {"coordinates":[-80.464523,44.549206],"type":"Point"}
}