{
  "type": "Feature",
  "properties": {
    "addr:full":"2435 Rue DE LA Sidbec S Trois-Rivieres-Ouest QC G8Z 4M6",
    "addr:housenumber":"2435",
    "addr:postcode":"g8z 4m6",
    "addr:street":"Rue De La Sidbec S Trois-Rivieres-Ouest",
    "iso:country":"CA",
    "sg:address":"2435 Rue DE LA Sidbec S",
    "sg:city":"Trois-Rivieres-Ouest",
    "sg:classifiers":[
        {
            "category":"Wholesale",
            "subcategory":"Electrical",
            "type":"Manufacturing & Wholesale Goods"
        }
    ],
    "sg:phone":"+1 819 691 4212",
    "sg:postcode":"G8Z 4M6",
    "sg:province":"QC",
    "sg:tags":[
        "equipment",
        "electric",
        "supply"
    ],
    "wof:name":"Wesco Distribution Canada Inc",
    "wof:placetype":"venue"
},
  "geometry": {"coordinates":[-72.58265686039999,46.3341751099],"type":"Point"}
}