{
  "type": "Feature",
  "properties": {
    "addr:full":"1798 Rte Kennedy Scott QC G0S 3G0",
    "addr:housenumber":"1798",
    "addr:postcode":"g0s 3g0",
    "addr:street":"Rte Kennedy",
    "iso:country":"CA",
    "sg:address":"1798 Rte Kennedy",
    "sg:city":"Scott",
    "sg:classifiers":[
        {
            "category":"Building & Trades",
            "subcategory":"Construction",
            "type":"Services"
        }
    ],
    "sg:phone":"+1 418 387 2323",
    "sg:postcode":"G0S 3G0",
    "sg:province":"QC",
    "sg:tags":[
        "hatchery",
        "roofing",
        "fish",
        "contractor"
    ],
    "wof:name":"Scott Couvoir Ltee",
    "wof:placetype":"venue"
},
  "geometry": {"coordinates":[-71.0789642334,46.5340995789],"type":"Point"}
}