{
  "type": "Feature",
  "properties": {
    "addr:full":"108 7th Ave N Swan River MB R0L 1Z0",
    "addr:housenumber":"108",
    "addr:postcode":"r0l 1z0",
    "addr:street":"7Th Ave N",
    "iso:country":"CA",
    "sg:address":"108 7th Ave N",
    "sg:city":"Swan River",
    "sg:classifiers":[
        {
            "category":"Retail",
            "subcategory":"Self-service Laundry",
            "type":"Services"
        }
    ],
    "sg:phone":"+1 204 734 2010",
    "sg:postcode":"R0L 1Z0",
    "sg:province":"MB",
    "wof:name":"King Koin Laundromat",
    "wof:placetype":"venue"
},
  "geometry": {"coordinates":[-101.265152,52.103561],"type":"Point"}
}