{
  "type": "Feature",
  "properties": {
    "iso:country":"CA",
    "sg:address":"420 Proctor St",
    "sg:city":"Williams Lake",
    "sg:classifiers":[
        {
            "category":"Health Services",
            "subcategory":"Chiropractor",
            "type":"Services"
        }
    ],
    "sg:phone":"+1 250 392 1077",
    "sg:postcode":"V2G 1S2",
    "sg:province":"BC",
    "wof:name":"Carson Chiropractic",
    "wof:placetype":"venue"
},
  "geometry": {"coordinates":[-122.141251,52.132114],"type":"Point"}
}