{
  "type": "Feature",
  "properties": {
    "iso:country":"CA",
    "sg:city":"Brampton",
    "sg:classifiers":[
        {
            "category":"Shopping",
            "subcategory":"Musical Instruments",
            "type":"Retail Goods"
        }
    ],
    "sg:phone":"+1 905 455 9884",
    "sg:postcode":"L6T 5E2",
    "sg:province":"ON",
    "wof:name":"Drummer's Choice",
    "wof:placetype":"venue"
},
  "geometry": {"coordinates":[-79.726372,43.703922],"type":"Point"}
}