{
  "type": "Feature",
  "properties": {
    "addr:full":"4283 Victoria Ave Vineland Station ON L0R 2E0",
    "addr:housenumber":"4283",
    "addr:postcode":"l0r 2e0",
    "addr:street":"Victoria Ave",
    "iso:country":"CA",
    "sg:address":"4283 Victoria Ave",
    "sg:city":"Vineland Station",
    "sg:classifiers":[
        {
            "category":"Retail",
            "subcategory":"Auto Repair",
            "type":"Services"
        }
    ],
    "sg:phone":"+1 905 562 6000",
    "sg:postcode":"L0R 2E0",
    "sg:province":"ON",
    "sg:tags":[
        "wrecker"
    ],
    "wof:name":"Jne",
    "wof:placetype":"venue"
},
  "geometry": {"coordinates":[-79.393784,43.169456],"type":"Point"}
}