{
  "type": "Feature",
  "properties": {
    "addr:full":"2661 Kingston Rd Scarborough ON M1M 1M3",
    "addr:housenumber":"2661",
    "addr:postcode":"m1m 1m3",
    "addr:street":"Kingston Rd",
    "iso:country":"CA",
    "sg:address":"2661 Kingston Rd",
    "sg:city":"Scarborough",
    "sg:classifiers":[
        {
            "category":"Education",
            "subcategory":"College",
            "type":"Public Place"
        }
    ],
    "sg:phone":"+1 416 264 9477",
    "sg:postcode":"M1M 1M3",
    "sg:province":"ON",
    "sg:tags":[
        "academic",
        "school"
    ],
    "wof:name":"Redeptoris Mater Seminar",
    "wof:placetype":"venue"
},
  "geometry": {"coordinates":[-79.242813,43.715839],"type":"Point"}
}