{
  "type": "Feature",
  "properties": {
    "addr:full":"4 Ch Des Journalistes Ferme-Neuve QC J0W 1C0",
    "addr:housenumber":"4",
    "addr:postcode":"j0w 1c0",
    "addr:street":"Ch Des Journalistes",
    "iso:country":"CA",
    "sg:address":"4 Ch Des Journalistes",
    "sg:city":"Ferme-Neuve",
    "sg:classifiers":[
        {
            "category":"Travel",
            "subcategory":"Hotels & Motels",
            "type":"Entertainment"
        }
    ],
    "sg:phone":"+1 819 587 3513",
    "sg:postcode":"J0W 1C0",
    "sg:province":"QC",
    "wof:name":"Motel Des Journalistes",
    "wof:placetype":"venue"
},
  "geometry": {"coordinates":[-75.45637499999999,46.711605],"type":"Point"}
}