{
  "type": "Feature",
  "properties": {
    "addr:full":"1065 Notre Dame Ave Winnipeg MB R3E 0N4",
    "addr:housenumber":"1065",
    "addr:postcode":"r3e 0n4",
    "addr:street":"Notre Dame Ave",
    "iso:country":"CA",
    "sg:address":"1065 Notre Dame Ave",
    "sg:city":"Winnipeg",
    "sg:classifiers":[
        {
            "category":"Home & Garden",
            "subcategory":"Furniture",
            "type":"Retail Goods"
        }
    ],
    "sg:phone":"+1 204 783 8065",
    "sg:postcode":"R3E 0N4",
    "sg:province":"MB",
    "wof:name":"Furniture Depot Ltd",
    "wof:placetype":"venue"
},
  "geometry": {"coordinates":[-97.17433200000001,49.906387],"type":"Point"}
}