{
  "type": "Feature",
  "properties": {
    "addr:full":"14 Woodward Ave Blind River ON P0R 1B0",
    "addr:housenumber":"14",
    "addr:postcode":"p0r 1b0",
    "addr:street":"Woodward Ave",
    "iso:country":"CA",
    "sg:address":"14 Woodward Ave",
    "sg:city":"Blind River",
    "sg:classifiers":[
        {
            "category":"Shopping",
            "subcategory":"Clothing, Apparel, & Fashions",
            "type":"Retail Goods"
        }
    ],
    "sg:phone":"+1 705 356 9891",
    "sg:postcode":"P0R 1B0",
    "sg:province":"ON",
    "sg:tags":[
        "furnishing"
    ],
    "wof:name":"Hagger's Men's Wear",
    "wof:placetype":"venue"
},
  "geometry": {"coordinates":[-82.954208374,46.1860275269],"type":"Point"}
}