{
  "type": "Feature",
  "properties": {
    "addr:full":"5803 11A Ave NW Edmonton AB T6L 6A8",
    "addr:housenumber":"5803",
    "addr:postcode":"t6l 6a8",
    "addr:street":"11A Ave Nw",
    "iso:country":"CA",
    "sg:address":"5803 11A Ave NW",
    "sg:city":"Edmonton",
    "sg:classifiers":[
        {
            "category":"Organizations",
            "subcategory":"Religious Organization",
            "type":"Services"
        }
    ],
    "sg:phone":"+1 780 450 1986",
    "sg:postcode":"T6L 6A8",
    "sg:province":"AB",
    "sg:tags":[
        "church"
    ],
    "wof:name":"St Mary & St Mark Coptic Ortho",
    "wof:placetype":"venue"
},
  "geometry": {"coordinates":[-113.428726,53.440315],"type":"Point"}
}