{
  "type": "Feature",
  "properties": {
    "iso:country":"CA",
    "sg:city":"Warwick",
    "sg:classifiers":[
        {
            "category":"Wholesale",
            "subcategory":"Farm Supplies",
            "type":"Manufacturing & Wholesale Goods"
        }
    ],
    "sg:phone":"+1 819 358 2288",
    "sg:postcode":"J0A 1M0",
    "sg:province":"QC",
    "sg:tags":[
        "broker",
        "animal",
        "dealer"
    ],
    "wof:name":"Beauchesne, Pierre",
    "wof:placetype":"venue"
},
  "geometry": {"coordinates":[-71.9845733643,45.9567070007],"type":"Point"}
}