{
  "type": "Feature",
  "properties": {
    "addr:full":"825 Boul Maloney E Gatineau QC J8P 1G5",
    "addr:housenumber":"825",
    "addr:postcode":"j8p 1g5",
    "addr:street":"Boul Maloney E",
    "iso:country":"CA",
    "sg:address":"825 Boul Maloney E",
    "sg:city":"Gatineau",
    "sg:classifiers":[
        {
            "category":"Shopping",
            "subcategory":"Florist",
            "type":"Retail Goods"
        }
    ],
    "sg:phone":"+1 819 663 0033",
    "sg:postcode":"J8P 1G5",
    "sg:province":"QC",
    "wof:name":"Fleuriste Au Jardin DE Mariell",
    "wof:placetype":"venue"
},
  "geometry": {"coordinates":[-75.6098861694,45.4843482971],"type":"Point"}
}