{
  "type": "Feature",
  "properties": {
    "addr:full":"Mistissini QC G0W 1C0",
    "addr:postcode":"g0w 1c0",
    "iso:country":"CA",
    "sg:city":"Mistissini",
    "sg:classifiers":[
        {
            "category":"Organizations",
            "subcategory":"Professional Association",
            "type":"Services"
        }
    ],
    "sg:phone":"+1 418 923 3334",
    "sg:postcode":"G0W 1C0",
    "sg:province":"QC",
    "wof:name":"Office DE LA Securite Revenu",
    "wof:placetype":"venue"
},
  "geometry": {"coordinates":[-73.873688,50.417915],"type":"Point"}
}