{
  "type": "Feature",
  "properties": {
    "addr:full":"1048 Marine Dr North Vancouver BC V7P 1S5",
    "addr:housenumber":"1048",
    "addr:postcode":"v7p 1s5",
    "addr:street":"Marine Dr",
    "iso:country":"CA",
    "sg:address":"1048 Marine Dr",
    "sg:city":"North Vancouver",
    "sg:classifiers":[
        {
            "category":"Professional",
            "subcategory":"Computer Services",
            "type":"Services"
        }
    ],
    "sg:phone":"+1 604 988 4440",
    "sg:postcode":"V7P 1S5",
    "sg:province":"BC",
    "sg:tags":[
        "repair"
    ],
    "wof:name":"Sortek Electronics",
    "wof:placetype":"venue"
},
  "geometry": {"coordinates":[-123.10208900000001,49.32375],"type":"Point"}
}