{
  "type": "Feature",
  "properties": {
    "addr:full":"365 Sandwich St S Amherstburg ON N9V 2B2",
    "addr:housenumber":"365",
    "addr:postcode":"n9v 2b2",
    "addr:street":"Sandwich St S",
    "iso:country":"CA",
    "sg:address":"365 Sandwich St S",
    "sg:city":"Amherstburg",
    "sg:classifiers":[
        {
            "category":"Organizations",
            "subcategory":"Religious Organization",
            "type":"Services"
        }
    ],
    "sg:phone":"+1 519 736 4362",
    "sg:postcode":"N9V 2B2",
    "sg:province":"ON",
    "sg:tags":[
        "church"
    ],
    "wof:name":"Wesley United Church",
    "wof:placetype":"venue"
},
  "geometry": {"coordinates":[-83.108002,42.098499],"type":"Point"}
}