{
  "type": "Feature",
  "properties": {
    "addr:full":"534 Rue Collard O Alma QC G8B 1N2",
    "addr:housenumber":"534",
    "addr:postcode":"g8b 1n2",
    "addr:street":"Rue Collard O",
    "iso:country":"CA",
    "sg:address":"534 Rue Collard O",
    "sg:city":"Alma",
    "sg:classifiers":[
        {
            "category":"Restaurant",
            "type":"Food & Drink"
        }
    ],
    "sg:phone":"+1 418 668 7231",
    "sg:postcode":"G8B 1N2",
    "sg:province":"QC",
    "wof:name":"Brasserie Mario Tremblay Inc",
    "wof:placetype":"venue"
},
  "geometry": {"coordinates":[-71.650680542,48.5488586426],"type":"Point"}
}