{
  "type": "Feature",
  "properties": {
    "addr:full":"PO Box 2635 STN M Calgary AB T2P 3C1",
    "addr:housenumber":"po",
    "addr:postcode":"2635;t2p 3c1",
    "addr:street":"Box;M",
    "iso:country":"CA",
    "sg:address":"PO Box 2635 STN M",
    "sg:city":"Calgary",
    "sg:classifiers":[
        {
            "category":"Professional",
            "subcategory":"Business Services",
            "type":"Services"
        }
    ],
    "sg:phone":"+1 403 243 3477",
    "sg:postcode":"T2P 3C1",
    "sg:province":"AB",
    "sg:tags":[
        "translator",
        "interpreter"
    ],
    "wof:name":"Association of Translators",
    "wof:placetype":"venue"
},
  "geometry": {"coordinates":[-114.063194275,51.0450744629],"type":"Point"}
}