{
  "type": "Feature",
  "properties": {
    "addr:full":"1180 Lansdowne St Hawkesbury ON K6A 1J1",
    "addr:housenumber":"1180",
    "addr:postcode":"k6a 1j1",
    "addr:street":"Lansdowne St",
    "iso:country":"CA",
    "sg:address":"1180 Lansdowne St",
    "sg:city":"Hawkesbury",
    "sg:classifiers":[
        {
            "category":"Social Services",
            "type":"Services"
        }
    ],
    "sg:phone":"+1 613 632 1131",
    "sg:postcode":"K6A 1J1",
    "sg:province":"ON",
    "sg:tags":[
        "organization",
        "welfare"
    ],
    "wof:name":"Maison Interlude House",
    "wof:placetype":"venue"
},
  "geometry": {"coordinates":[-74.59135437010001,45.6063575745],"type":"Point"}
}