{
  "type": "Feature",
  "properties": {
    "addr:full":"564 Yates St Victoria BC V8W 1K8",
    "addr:housenumber":"564",
    "addr:postcode":"v8w 1k8",
    "addr:street":"Yates St",
    "iso:country":"CA",
    "sg:address":"564 Yates St",
    "sg:city":"Victoria",
    "sg:classifiers":[
        {
            "category":"Shopping",
            "subcategory":"Clothing, Apparel, & Fashions",
            "type":"Retail Goods"
        }
    ],
    "sg:phone":"+1 250 381 4405",
    "sg:postcode":"V8W 1K8",
    "sg:province":"BC",
    "wof:name":"Hughes Limited",
    "wof:placetype":"venue"
},
  "geometry": {"coordinates":[-123.3685,48.42672],"type":"Point"}
}