{
  "type": "Feature",
  "properties": {
    "iso:country":"CA",
    "sg:address":"9 Vine Pl",
    "sg:city":"Corner Brook",
    "sg:classifiers":[
        {
            "category":"Organizations",
            "subcategory":"Professional Association",
            "type":"Services"
        }
    ],
    "sg:phone":"+1 709 634 4691",
    "sg:postcode":"A2H 6E6",
    "sg:province":"NL",
    "wof:name":"Dunfield Park Community Ctr",
    "wof:placetype":"venue"
},
  "geometry": {"coordinates":[-57.94947052,48.9501991272],"type":"Point"}
}