{
  "type": "Feature",
  "properties": {
    "addr:full":"410 Hochelaga St E Moose Jaw SK S6H 0P3",
    "addr:housenumber":"410",
    "addr:postcode":"s6h 0p3",
    "addr:street":"Hochelaga St E",
    "iso:country":"CA",
    "sg:address":"410 Hochelaga St E",
    "sg:city":"Moose Jaw",
    "sg:classifiers":[
        {
            "category":"Organizations",
            "subcategory":"Professional Association",
            "type":"Services"
        }
    ],
    "sg:phone":"+1 306 693 6066",
    "sg:postcode":"S6H 0P3",
    "sg:province":"SK",
    "wof:name":"Citizens All Assn",
    "wof:placetype":"venue"
},
  "geometry": {"coordinates":[-105.524254,50.396095],"type":"Point"}
}