{
  "type": "Feature",
  "properties": {
    "addr:full":"120 Owen Sound St Shelburne ON L0N 1S0",
    "addr:housenumber":"120",
    "addr:postcode":"l0n 1s0",
    "addr:street":"Owen;St",
    "iso:country":"CA",
    "sg:address":"120 Owen Sound St",
    "sg:city":"Shelburne",
    "sg:classifiers":[
        {
            "category":"Restaurant",
            "type":"Food & Drink"
        }
    ],
    "sg:phone":"+1 519 925 1755",
    "sg:postcode":"L0N 1S0",
    "sg:province":"ON",
    "wof:name":"Four Seasons Chinese Rstrnt",
    "wof:placetype":"venue"
},
  "geometry": {"coordinates":[-80.204956,44.078457],"type":"Point"}
}