{
  "type": "Feature",
  "properties": {
    "addr:full":"Vancouver BC V5Z 1G4",
    "addr:postcode":"v5z 1g4",
    "iso:country":"CA",
    "sg:city":"Vancouver",
    "sg:classifiers":[
        {
            "category":"Health Services",
            "subcategory":"Health Practitioner",
            "type":"Services"
        }
    ],
    "sg:phone":"+1 604 215 2150",
    "sg:postcode":"V5Z 1G4",
    "sg:province":"BC",
    "sg:tags":[
        "psychologist"
    ],
    "wof:name":"Ward Hanely, Jordan PhD",
    "wof:placetype":"venue"
},
  "geometry": {"coordinates":[-123.118736267,49.2631454468],"type":"Point"}
}