{
  "type": "Feature",
  "properties": {
    "addr:full":"1235 Shawson Dr Mississauga ON L4W 1C4",
    "addr:housenumber":"1235",
    "addr:postcode":"l4w 1c4",
    "addr:street":"Shawson Dr",
    "iso:country":"CA",
    "sg:address":"1235 Shawson Dr",
    "sg:city":"Mississauga",
    "sg:classifiers":[
        {
            "category":"Manufacturing",
            "subcategory":"Apparel",
            "type":"Manufacturing & Wholesale Goods"
        }
    ],
    "sg:phone":"+1 905 795 8390",
    "sg:postcode":"L4W 1C4",
    "sg:province":"ON",
    "sg:tags":[
        "textile",
        "manufacturer"
    ],
    "wof:name":"Quality Rags Ltd",
    "wof:placetype":"venue"
},
  "geometry": {"coordinates":[-79.64916229249999,43.6479415894],"type":"Point"}
}