{
  "type": "Feature",
  "properties": {
    "addr:full":"1769 Evergreen Dr Agassiz BC V0M 1A2",
    "addr:housenumber":"1769",
    "addr:postcode":"v0m 1a2",
    "addr:street":"Evergreen Dr",
    "iso:country":"CA",
    "sg:address":"1769 Evergreen Dr",
    "sg:city":"Agassiz",
    "sg:classifiers":[
        {
            "category":"Personal",
            "type":"Services"
        }
    ],
    "sg:phone":"+1 604 796 5597",
    "sg:postcode":"V0M 1A2",
    "sg:province":"BC",
    "sg:tags":[
        "therapist",
        "massage"
    ],
    "wof:name":"Agassiz Therapeutic Massage",
    "wof:placetype":"venue"
},
  "geometry": {"coordinates":[-121.76694500000001,49.235432],"type":"Point"}
}