{
  "type": "Feature",
  "properties": {
    "addr:full":"3122 Edgemont Blvd North Vancouver BC V7R 2N6",
    "addr:housenumber":"3122",
    "addr:postcode":"v7r 2n6",
    "addr:street":"Edgemont Blvd",
    "iso:country":"CA",
    "sg:address":"3122 Edgemont Blvd",
    "sg:city":"North Vancouver",
    "sg:classifiers":[
        {
            "category":"Shopping",
            "subcategory":"Used Merchandise",
            "type":"Retail Goods"
        }
    ],
    "sg:phone":"+1 604 984 2551",
    "sg:postcode":"V7R 2N6",
    "sg:province":"BC",
    "sg:tags":[
        "shop",
        "consignment"
    ],
    "wof:name":"Comeback",
    "wof:placetype":"venue"
},
  "geometry": {"coordinates":[-123.102081,49.337849],"type":"Point"}
}