{
  "type": "Feature",
  "properties": {
    "iso:country":"CA",
    "sg:address":"41 Clarence St",
    "sg:city":"Brampton",
    "sg:classifiers":[
        {
            "category":"Retail",
            "subcategory":"Repair Shop",
            "type":"Services"
        }
    ],
    "sg:phone":"+1 905 454 3203",
    "sg:postcode":"L6W 1S2",
    "sg:province":"ON",
    "sg:tags":[
        "repairing",
        "piano",
        "refinishing"
    ],
    "wof:name":"Robert O'Brien Piano Svc",
    "wof:placetype":"venue"
},
  "geometry": {"coordinates":[-79.75043487550001,43.6818885803],"type":"Point"}
}