{
  "type": "Feature",
  "properties": {
    "addr:full":"Allanburg ON L0S 1A0",
    "addr:postcode":"l0s 1a0",
    "iso:country":"CA",
    "sg:city":"Allanburg",
    "sg:classifiers":[
        {
            "category":"Professional",
            "subcategory":"Detective & Security Services",
            "type":"Services"
        }
    ],
    "sg:phone":"+1 905 227 8333",
    "sg:postcode":"L0S 1A0",
    "sg:province":"ON",
    "sg:tags":[
        "control",
        "traffic"
    ],
    "wof:name":"Roadside Rentals Inc",
    "wof:placetype":"venue"
},
  "geometry": {"coordinates":[-79.1986083984,43.0725784302],"type":"Point"}
}