{
  "type": "Feature",
  "properties": {
    "addr:full":"910 Boul Du Seminaire N Saint-Jean-Sur-Richelieu QC J3A 1B5",
    "addr:housenumber":"910",
    "addr:postcode":"j3a 1b5",
    "addr:street":"Boul Du Seminaire N",
    "iso:country":"CA",
    "sg:address":"910 Boul Du Seminaire N",
    "sg:city":"Saint-Jean-Sur-Richelieu",
    "sg:classifiers":[
        {
            "category":"Shopping",
            "subcategory":"Florist",
            "type":"Retail Goods"
        }
    ],
    "sg:phone":"+1 450 348 7389",
    "sg:postcode":"J3A 1B5",
    "sg:province":"QC",
    "wof:name":"Fleuriste Decorateur",
    "wof:placetype":"venue"
},
  "geometry": {"coordinates":[-73.26792907710001,45.3313484192],"type":"Point"}
}