{
  "type": "Feature",
  "properties": {
    "addr:full":"Victoria BC V8R 1J5",
    "addr:postcode":"v8r 1j5",
    "iso:country":"CA",
    "sg:city":"Victoria",
    "sg:classifiers":[
        {
            "category":"Health Services",
            "subcategory":"Doctor",
            "type":"Services"
        }
    ],
    "sg:phone":"+1 250 595 1331",
    "sg:postcode":"V8R 1J5",
    "sg:province":"BC",
    "sg:tags":[
        "dentist"
    ],
    "wof:name":"Fort Street Dental Ctr",
    "wof:placetype":"venue"
},
  "geometry": {"coordinates":[-123.330703735,48.4294128418],"type":"Point"}
}