{
  "type": "Feature",
  "properties": {
    "addr:full":"4588 Roblin Blvd Winnipeg MB R3R 0G4",
    "addr:postcode":"4588;r3r 0g4",
    "addr:street":"Roblin Blvd",
    "iso:country":"CA",
    "sg:address":"4588 Roblin Blvd",
    "sg:city":"Winnipeg",
    "sg:classifiers":[
        {
            "category":"Organizations",
            "subcategory":"Religious Organization",
            "type":"Services"
        }
    ],
    "sg:phone":"+1 204 832 1993",
    "sg:postcode":"R3R 0G4",
    "sg:province":"MB",
    "sg:tags":[
        "church"
    ],
    "wof:name":"Our Lady of Perpetual Help Chr",
    "wof:placetype":"venue"
},
  "geometry": {"coordinates":[-97.2770233154,49.8593864441],"type":"Point"}
}