{
  "type": "Feature",
  "properties": {
    "addr:full":"3400 Boul Des Trinitaires Montreal QC H4E 4J3",
    "addr:housenumber":"3400",
    "addr:postcode":"h4e 4j3",
    "addr:street":"Boul Des Trinitaires",
    "iso:country":"CA",
    "sg:address":"3400 Boul Des Trinitaires",
    "sg:city":"Montreal",
    "sg:classifiers":[
        {
            "category":"Government",
            "subcategory":"Office",
            "type":"Public Place"
        }
    ],
    "sg:phone":"+1 514 872 2816",
    "sg:postcode":"H4E 4J3",
    "sg:province":"QC",
    "sg:tags":[
        "village"
    ],
    "wof:name":"Montreal Ferme Angrignon",
    "wof:placetype":"venue"
},
  "geometry": {"coordinates":[-73.6025466919,45.446685791],"type":"Point"}
}