{
  "type": "Feature",
  "properties": {
    "addr:full":"2287 Rue Guenette Saint-Laurent QC H4R 2E9",
    "addr:housenumber":"2287",
    "addr:postcode":"h4r 2e9",
    "addr:street":"Rue Guenette",
    "iso:country":"CA",
    "sg:address":"2287 Rue Guenette",
    "sg:city":"Saint-Laurent",
    "sg:classifiers":[
        {
            "category":"Freight",
            "type":"Transportation"
        }
    ],
    "sg:phone":"+1 514 333 7727",
    "sg:postcode":"H4R 2E9",
    "sg:province":"QC",
    "sg:tags":[
        "shipping",
        "agent"
    ],
    "wof:name":"Alphatrans Int'l Inc",
    "wof:placetype":"venue"
},
  "geometry": {"coordinates":[-73.7260055542,45.4987564087],"type":"Point"}
}