{
  "type": "Feature",
  "properties": {
    "iso:country":"CA",
    "sg:address":"3585 Rue Lefort",
    "sg:city":"Trois-Rivieres-Ouest",
    "sg:classifiers":[
        {
            "category":"Professional",
            "subcategory":"Management & Consulting",
            "type":"Services"
        }
    ],
    "sg:phone":"+1 819 691 9927",
    "sg:postcode":"G8Y 5P9",
    "sg:province":"QC",
    "sg:tags":[
        "control",
        "consultant",
        "quality"
    ],
    "wof:name":"Qualicum Inc",
    "wof:placetype":"venue"
},
  "geometry": {"coordinates":[-72.593269,46.332253],"type":"Point"}
}