{
  "type": "Feature",
  "properties": {
    "addr:full":"PO Box 7633 STN Main Drayton Valley AB T7A 1S7",
    "addr:housenumber":"po",
    "addr:postcode":"t7a 1s7",
    "addr:street":"Box 7633 Stn Main",
    "iso:country":"CA",
    "sg:address":"PO Box 7633 STN Main",
    "sg:city":"Drayton Valley",
    "sg:classifiers":[
        {
            "category":"Building & Trades",
            "subcategory":"Construction",
            "type":"Services"
        }
    ],
    "sg:phone":"+1 780 542 7633",
    "sg:postcode":"T7A 1S7",
    "sg:province":"AB",
    "sg:tags":[
        "contractor"
    ],
    "wof:name":"Ayotte Construction",
    "wof:placetype":"venue"
},
  "geometry": {"coordinates":[-114.98689299999999,53.227997],"type":"Point"}
}