{
  "type": "Feature",
  "properties": {
    "addr:full":"566 Alexandra St Sydney NS B1S 2G8",
    "addr:housenumber":"566",
    "addr:postcode":"b1s 2g8",
    "addr:street":"Alexandra St",
    "iso:country":"CA",
    "sg:address":"566 Alexandra St",
    "sg:city":"Sydney",
    "sg:classifiers":[
        {
            "category":"Health Services",
            "subcategory":"Nursing And Care Facility",
            "type":"Services"
        }
    ],
    "sg:phone":"+1 902 562 3610",
    "sg:postcode":"B1S 2G8",
    "sg:province":"NS",
    "sg:tags":[
        "home",
        "rest"
    ],
    "wof:name":"R & P House",
    "wof:placetype":"venue"
},
  "geometry": {"coordinates":[-60.200703,46.11467],"type":"Point"}
}