{
  "type": "Feature",
  "properties": {
    "iso:country":"CA",
    "sg:address":"155 Falconridge Cres NE",
    "sg:city":"Calgary",
    "sg:classifiers":[
        {
            "category":"Organizations",
            "subcategory":"Religious Organization",
            "type":"Services"
        }
    ],
    "sg:phone":"+1 403 285 3300",
    "sg:postcode":"T3J 1Z9",
    "sg:province":"AB",
    "sg:tags":[
        "church"
    ],
    "wof:name":"Full Gospel Tabernacle",
    "wof:placetype":"venue"
},
  "geometry": {"coordinates":[-113.952636719,51.0967483521],"type":"Point"}
}