{
  "type": "Feature",
  "properties": {
    "iso:country":"CA",
    "sg:address":"379 Orenda Rd",
    "sg:city":"Brampton",
    "sg:classifiers":[
        {
            "category":"Wholesale",
            "subcategory":"Machinery & Supplies",
            "type":"Manufacturing & Wholesale Goods"
        }
    ],
    "sg:phone":"+1 905 791 9793",
    "sg:postcode":"L6T 1G4",
    "sg:province":"ON",
    "sg:tags":[
        "baker"
    ],
    "wof:name":"Catalogue Sales Div",
    "wof:placetype":"venue"
},
  "geometry": {"coordinates":[-79.6975097656,43.7021522522],"type":"Point"}
}