{
  "type": "Feature",
  "properties": {
    "addr:full":"406 Roncesvalles Ave Toronto ON M6R 2M9",
    "addr:housenumber":"406",
    "addr:postcode":"m6r 2m9",
    "addr:street":"Roncesvalles Ave",
    "iso:country":"CA",
    "sg:address":"406 Roncesvalles Ave",
    "sg:city":"Toronto",
    "sg:classifiers":[
        {
            "category":"Retail",
            "subcategory":"Laundry & Dry Cleaning",
            "type":"Services"
        }
    ],
    "sg:phone":"+1 416 536 5936",
    "sg:postcode":"M6R 2M9",
    "sg:province":"ON",
    "sg:tags":[
        "fur",
        "business"
    ],
    "wof:name":"Stephan's Furs",
    "wof:placetype":"venue"
},
  "geometry": {"coordinates":[-79.4511566162,43.6512718201],"type":"Point"}
}