{
  "type": "Feature",
  "properties": {
    "addr:full":"4385 Ch Saint-Charles Lachenaie QC J6V 1B5",
    "addr:housenumber":"4385",
    "addr:postcode":"j6v 1b5",
    "addr:street":"Ch Saint-Charles",
    "iso:country":"CA",
    "sg:address":"4385 Ch Saint-Charles",
    "sg:city":"Lachenaie",
    "sg:classifiers":[
        {
            "category":"Manufacturing",
            "subcategory":"Apparel",
            "type":"Manufacturing & Wholesale Goods"
        }
    ],
    "sg:phone":"+1 450 657 0190",
    "sg:postcode":"J6V 1B5",
    "sg:province":"QC",
    "sg:tags":[
        "emblem",
        "embroidery"
    ],
    "wof:name":"Creation Transbro Inc",
    "wof:placetype":"venue"
},
  "geometry": {"coordinates":[-73.51720400000001,45.706829],"type":"Point"}
}