{
  "type": "Feature",
  "properties": {
    "iso:country":"CA",
    "sg:address":"1300 Boul Du MI-Vallon",
    "sg:city":"Rock Forest",
    "sg:classifiers":[
        {
            "category":"Cinema",
            "subcategory":"Movie Rental",
            "type":"Entertainment"
        }
    ],
    "sg:phone":"+1 819 562 1400",
    "sg:postcode":"J1N 3B9",
    "sg:province":"QC",
    "sg:tags":[
        "leasing",
        "video",
        "disc",
        "tape"
    ],
    "wof:name":"Club International Video Film",
    "wof:placetype":"venue"
},
  "geometry": {"coordinates":[-71.977722168,45.3754959106],"type":"Point"}
}