{
  "type": "Feature",
  "properties": {
    "iso:country":"CA",
    "sg:address":"3025 Boul Pitfield",
    "sg:city":"Saint-Laurent",
    "sg:classifiers":[
        {
            "category":"Manufacturing",
            "subcategory":"Food",
            "type":"Manufacturing & Wholesale Goods"
        }
    ],
    "sg:phone":"+1 514 333 0196",
    "sg:postcode":"H4S 1N3",
    "sg:province":"QC",
    "sg:tags":[
        "product",
        "pickle",
        "manufacturer"
    ],
    "wof:name":"Aliments Cibona Foods Inc",
    "wof:placetype":"venue"
},
  "geometry": {"coordinates":[-73.74778,45.497971],"type":"Point"}
}