{
  "type": "Feature",
  "properties": {
    "addr:full":"3025 Boul Pitfield Saint-Laurent QC H4S 1N3",
    "addr:housenumber":"3025",
    "addr:postcode":"h4s 1n3",
    "addr:street":"Boul Pitfield",
    "iso:country":"CA",
    "sg:address":"3025 Boul Pitfield",
    "sg:city":"Saint-Laurent",
    "sg:classifiers":[
        {
            "category":"Manufacturing",
            "subcategory":"Food",
            "type":"Manufacturing & Wholesale Goods"
        }
    ],
    "sg:phone":"+1 514 333 0196",
    "sg:postcode":"H4S 1N3",
    "sg:province":"QC",
    "sg:tags":[
        "product",
        "pickle",
        "manufacturer"
    ],
    "wof:name":"Aliments Cibona Foods Inc",
    "wof:placetype":"venue"
},
  "geometry": {"coordinates":[-73.74778000000001,45.497971],"type":"Point"}
}