{
  "type": "Feature",
  "properties": {
    "addr:full":"London ON N6E 3M7",
    "addr:postcode":"n6e 3m7",
    "iso:country":"CA",
    "sg:city":"London",
    "sg:classifiers":[
        {
            "category":"Home & Garden",
            "subcategory":"Building Materials",
            "type":"Retail Goods"
        }
    ],
    "sg:phone":"+1 519 681 2007",
    "sg:postcode":"N6E 3M7",
    "sg:province":"ON",
    "sg:tags":[
        "paint"
    ],
    "wof:name":"Glidden Paints",
    "wof:placetype":"venue"
},
  "geometry": {"coordinates":[-81.2340087891,42.9426193237],"type":"Point"}
}