{
  "type": "Feature",
  "properties": {
    "addr:full":"762 Rue Claude-DE Ramezay Marieville QC J3M 1G1",
    "addr:housenumber":"762",
    "addr:postcode":"j3m 1g1",
    "addr:street":"Rue Claude-De Ramezay",
    "iso:country":"CA",
    "sg:address":"762 Rue Claude-DE Ramezay",
    "sg:city":"Marieville",
    "sg:classifiers":[
        {
            "category":"Organizations",
            "subcategory":"Religious Organization",
            "type":"Services"
        }
    ],
    "sg:phone":"+1 450 460 3163",
    "sg:postcode":"J3M 1G1",
    "sg:province":"QC",
    "sg:tags":[
        "church"
    ],
    "wof:name":"Eglise Evangelique Baptiste",
    "wof:placetype":"venue"
},
  "geometry": {"coordinates":[-73.15878295900001,45.4300956726],"type":"Point"}
}