{
  "type": "Feature",
  "properties": {
    "addr:full":"Osoyoos BC V0H 1V0",
    "addr:postcode":"v0h 1v0",
    "iso:country":"CA",
    "sg:city":"Osoyoos",
    "sg:classifiers":[
        {
            "category":"Professional",
            "subcategory":"Lawyer & Legal Services",
            "type":"Services"
        }
    ],
    "sg:phone":"+1 250 495 6508",
    "sg:postcode":"V0H 1V0",
    "sg:province":"BC",
    "sg:tags":[
        "attorney"
    ],
    "wof:name":"Gordon & CO",
    "wof:placetype":"venue"
},
  "geometry": {"coordinates":[-119.464241,49.032841],"type":"Point"}
}