{
  "type": "Feature",
  "properties": {
    "iso:country":"CA",
    "sg:address":"202 Blake St",
    "sg:city":"Barrie",
    "sg:classifiers":[
        {
            "category":"Retail",
            "subcategory":"Auto Repair",
            "type":"Services"
        }
    ],
    "sg:phone":"+1 705 725 9005",
    "sg:postcode":"L4M 1K3",
    "sg:province":"ON",
    "sg:tags":[
        "repairing",
        "automobile"
    ],
    "wof:name":"B & K Blake Auto Svc",
    "wof:placetype":"venue"
},
  "geometry": {"coordinates":[-79.6645126343,44.3953514099],"type":"Point"}
}