{
  "type": "Feature",
  "properties": {
    "addr:full":"233 the Queensway S Keswick ON L4P 2A8",
    "addr:housenumber":"233",
    "addr:postcode":"l4p 2a8",
    "addr:street":"The Queensway S",
    "iso:country":"CA",
    "sg:address":"233 the Queensway S",
    "sg:city":"Keswick",
    "sg:classifiers":[
        {
            "category":"Recreation",
            "subcategory":"Marina",
            "type":"Entertainment"
        }
    ],
    "sg:phone":"+1 905 476 0441",
    "sg:postcode":"L4P 2A8",
    "sg:province":"ON",
    "wof:name":"Harry's Riverside Sprts & Bait",
    "wof:placetype":"venue"
},
  "geometry": {"coordinates":[-79.4646987915,44.2281455994],"type":"Point"}
}