{
  "type": "Feature",
  "properties": {
    "iso:country":"CA",
    "sg:address":"194 King St",
    "sg:city":"Cathcart",
    "sg:classifiers":[
        {
            "category":"Retail",
            "subcategory":"Repair Shop",
            "type":"Services"
        }
    ],
    "sg:phone":"+1 519 458 8018",
    "sg:postcode":"N0E 1B0",
    "sg:province":"ON",
    "sg:tags":[
        "welding"
    ],
    "wof:name":"Vision Fabricating & Welding",
    "wof:placetype":"venue"
},
  "geometry": {"coordinates":[-80.5293045044,43.1015663147],"type":"Point"}
}