{
  "type": "Feature",
  "properties": {
    "addr:full":"25 Ilsley Ave Dartmouth NS B3B 1L5",
    "addr:housenumber":"25",
    "addr:postcode":"b3b 1l5",
    "addr:street":"Ilsley Ave",
    "iso:country":"CA",
    "sg:address":"25 Ilsley Ave",
    "sg:city":"Dartmouth",
    "sg:classifiers":[
        {
            "category":"Autos & Motor Vehicles",
            "subcategory":"Auto Supplies",
            "type":"Retail Goods"
        }
    ],
    "sg:phone":"+1 902 468 7223",
    "sg:postcode":"B3B 1L5",
    "sg:province":"NS",
    "sg:tags":[
        "equipment",
        "racing",
        "car",
        "automobile"
    ],
    "wof:name":"Racers Only",
    "wof:placetype":"venue"
},
  "geometry": {"coordinates":[-63.593269,44.703671],"type":"Point"}
}