{
  "type": "Feature",
  "properties": {
    "addr:full":"157 Rue Principale Ile-Aux-Noix QC J0J 1G0",
    "addr:housenumber":"157",
    "addr:postcode":"j0j 1g0",
    "addr:street":"Rue Principale",
    "iso:country":"CA",
    "sg:address":"157 Rue Principale",
    "sg:city":"Ile-Aux-Noix",
    "sg:classifiers":[
        {
            "category":"Building & Trades",
            "subcategory":"Construction",
            "type":"Services"
        }
    ],
    "sg:phone":"+1 450 246 2559",
    "sg:postcode":"J0J 1G0",
    "sg:province":"QC",
    "sg:tags":[
        "painter"
    ],
    "wof:name":"Peintures Cosmos Enr",
    "wof:placetype":"venue"
},
  "geometry": {"coordinates":[-73.33210754389999,45.0772514343],"type":"Point"}
}