{
  "type": "Feature",
  "properties": {
    "addr:full":"85 Av Ashgrove Pointe-Claire QC H9R 3N5",
    "addr:postcode":"h9r 3n5",
    "addr:street":"85 Av Ashgrove",
    "iso:country":"CA",
    "sg:address":"85 Av Ashgrove",
    "sg:city":"Pointe-Claire",
    "sg:classifiers":[
        {
            "category":"Retail",
            "subcategory":"Laundry & Dry Cleaning",
            "type":"Services"
        }
    ],
    "sg:phone":"+1 514 426 2326",
    "sg:postcode":"H9R 3N5",
    "sg:province":"QC",
    "sg:tags":[
        "cleaners"
    ],
    "wof:name":"Nettoyeur Donegani",
    "wof:placetype":"venue"
},
  "geometry": {"coordinates":[-73.8030929565,45.4482650757],"type":"Point"}
}