{
  "type": "Feature",
  "properties": {
    "iso:country":"CA",
    "sg:address":"3860 Rue DE Rouen",
    "sg:city":"Montreal",
    "sg:classifiers":[
        {
            "category":"Retail",
            "subcategory":"Auto Repair",
            "type":"Services"
        }
    ],
    "sg:phone":"+1 514 525 8637",
    "sg:postcode":"H1W 1N1",
    "sg:province":"QC",
    "sg:tags":[
        "body",
        "automobile",
        "painting"
    ],
    "wof:name":"Carrosseries Michel Enr",
    "wof:placetype":"venue"
},
  "geometry": {"coordinates":[-73.546494,45.548824],"type":"Point"}
}