{
  "type": "Feature",
  "properties": {
    "iso:country":"CA",
    "sg:city":"Montreal",
    "sg:classifiers":[
        {
            "category":"Real Estate",
            "subcategory":"Real Estate Agent",
            "type":"Services"
        }
    ],
    "sg:phone":"+1 514 844 6951",
    "sg:postcode":"H2L 3Z5",
    "sg:province":"QC",
    "sg:tags":[
        "hotel"
    ],
    "wof:name":"Teddy & Teddy Inc",
    "wof:placetype":"venue"
},
  "geometry": {"coordinates":[-73.565254,45.518242],"type":"Point"}
}