{
  "type": "Feature",
  "properties": {
    "addr:full":"Nepean ON K2E 7M6",
    "addr:postcode":"k2e 7m6",
    "iso:country":"CA",
    "sg:city":"Nepean",
    "sg:classifiers":[
        {
            "category":"Building & Trades",
            "subcategory":"Construction",
            "type":"Services"
        }
    ],
    "sg:phone":"+1 613 225 6646",
    "sg:postcode":"K2E 7M6",
    "sg:province":"ON",
    "sg:tags":[
        "management",
        "contractor"
    ],
    "wof:name":"Sitecast Construction Crop",
    "wof:placetype":"venue"
},
  "geometry": {"coordinates":[-75.723007,45.341431],"type":"Point"}
}