{
  "type": "Feature",
  "properties": {
    "addr:full":"St Paul AB T0A 3A2",
    "addr:postcode":"t0a 3a2",
    "iso:country":"CA",
    "sg:city":"St Paul",
    "sg:classifiers":[
        {
            "category":"Retail",
            "subcategory":"Laundry & Dry Cleaning",
            "type":"Services"
        }
    ],
    "sg:phone":"+1 780 645 3871",
    "sg:postcode":"T0A 3A2",
    "sg:province":"AB",
    "sg:tags":[
        "cleaners"
    ],
    "wof:name":"Classic Cleaners",
    "wof:placetype":"venue"
},
  "geometry": {"coordinates":[-111.27318572999999,53.9923248291],"type":"Point"}
}