{
  "type": "Feature",
  "properties": {
    "iso:country":"CA",
    "sg:address":"365 Stewart Blvd",
    "sg:city":"Brockville",
    "sg:classifiers":[
        {
            "category":"Restaurant",
            "type":"Food & Drink"
        }
    ],
    "sg:phone":"+1 613 342 8333",
    "sg:postcode":"K6V 4W9",
    "sg:province":"ON",
    "wof:name":"Luna Pizzeria Restaurant",
    "wof:placetype":"venue"
},
  "geometry": {"coordinates":[-75.70622253419999,44.60131073],"type":"Point"}
}