{
  "type": "Feature",
  "properties": {
    "addr:full":"3600 Townline Rd Abbotsford BC V2T 5W8",
    "addr:housenumber":"3600",
    "addr:postcode":"v2t 5w8",
    "addr:street":"Townline Rd",
    "iso:country":"CA",
    "sg:address":"3600 Townline Rd",
    "sg:city":"Abbotsford",
    "sg:classifiers":[
        {
            "category":"Restaurant",
            "type":"Food & Drink"
        }
    ],
    "sg:phone":"+1 604 504 3949",
    "sg:postcode":"V2T 5W8",
    "sg:province":"BC",
    "wof:name":"Blue Ridge Bar & Grille",
    "wof:placetype":"venue"
},
  "geometry": {"coordinates":[-122.359512329,49.0681114197],"type":"Point"}
}