{
  "type": "Feature",
  "properties": {
    "addr:full":"2095 Dorchester Rd Dorchester ON N0L 1G2",
    "addr:housenumber":"2095",
    "addr:postcode":"n0l 1g2",
    "addr:street":"Dorchester Rd",
    "iso:country":"CA",
    "sg:address":"2095 Dorchester Rd",
    "sg:city":"Dorchester",
    "sg:classifiers":[
        {
            "category":"Shopping",
            "subcategory":"Pharmacy",
            "type":"Retail Goods"
        }
    ],
    "sg:phone":"+1 519 268 7341",
    "sg:postcode":"N0L 1G2",
    "sg:province":"ON",
    "wof:name":"Shoppers Drug Mart",
    "wof:placetype":"venue"
},
  "geometry": {"coordinates":[-81.057884,42.985565],"type":"Point"}
}