{
  "type": "Feature",
  "properties": {
    "addr:full":"201 144E Rue Beauceville QC G5X 3J9",
    "addr:housenumber":"201",
    "addr:postcode":"g5x 3j9",
    "addr:street":"144E Rue",
    "iso:country":"CA",
    "sg:address":"201 144E Rue",
    "sg:city":"Beauceville",
    "sg:classifiers":[
        {
            "category":"Personal",
            "subcategory":"Beauty Salon",
            "type":"Services"
        }
    ],
    "sg:phone":"+1 418 774 6056",
    "sg:postcode":"G5X 3J9",
    "sg:province":"QC",
    "wof:name":"Caroline Belanger Coiffure Enr",
    "wof:placetype":"venue"
},
  "geometry": {"coordinates":[-70.78632399999999,46.215389],"type":"Point"}
}