{
  "type": "Feature",
  "properties": {
    "iso:country":"CA",
    "sg:address":"4993 Boul Des Sources",
    "sg:city":"Pierrefonds",
    "sg:classifiers":[
        {
            "category":"Government",
            "subcategory":"Police Station",
            "type":"Public Place"
        }
    ],
    "sg:phone":"+1 514 280 0103",
    "sg:postcode":"H8Y 3E3",
    "sg:province":"QC",
    "sg:tags":[
        "department"
    ],
    "wof:name":"Montreal Police Dept",
    "wof:placetype":"venue"
},
  "geometry": {"coordinates":[-73.820488,45.507767],"type":"Point"}
}