{
  "type": "Feature",
  "properties": {
    "addr:full":"Mississauga ON L5M 3C9",
    "addr:postcode":"l5m 3c9",
    "iso:country":"CA",
    "sg:city":"Mississauga",
    "sg:classifiers":[
        {
            "category":"Manufacturing",
            "subcategory":"Tools & Machinery",
            "type":"Manufacturing & Wholesale Goods"
        }
    ],
    "sg:phone":"+1 905 820 5434",
    "sg:postcode":"L5M 3C9",
    "sg:province":"ON",
    "sg:tags":[
        "surgical",
        "pharmacy"
    ],
    "wof:name":"Neilson Pharmacy Ltd",
    "wof:placetype":"venue"
},
  "geometry": {"coordinates":[-79.70089,43.557461],"type":"Point"}
}