{
  "type": "Feature",
  "properties": {
    "addr:full":"Alliston ON L9R 1P8",
    "addr:postcode":"l9r 1p8",
    "addr:street":"Alliston",
    "iso:country":"CA",
    "sg:city":"Alliston",
    "sg:classifiers":[
        {
            "category":"Shopping",
            "type":"Retail Goods"
        }
    ],
    "sg:phone":"+1 705 435 0744",
    "sg:postcode":"L9R 1P8",
    "sg:province":"ON",
    "sg:tags":[
        "pet",
        "food",
        "supply"
    ],
    "wof:name":"Pet Valu",
    "wof:placetype":"venue"
},
  "geometry": {"coordinates":[-79.88009643549999,44.1489448547],"type":"Point"}
}