{
  "type": "Feature",
  "properties": {
    "addr:full":"126 Main St Thedford ON N0M 2N0",
    "addr:housenumber":"126",
    "addr:postcode":"n0m 2n0",
    "addr:street":"Main St",
    "iso:country":"CA",
    "sg:address":"126 Main St",
    "sg:city":"Thedford",
    "sg:classifiers":[
        {
            "category":"Building & Trades",
            "subcategory":"Equipment Rental",
            "type":"Services"
        }
    ],
    "sg:phone":"+1 519 296 5676",
    "sg:postcode":"N0M 2N0",
    "sg:province":"ON",
    "sg:tags":[
        "leasing"
    ],
    "wof:name":"Arm Leasing",
    "wof:placetype":"venue"
},
  "geometry": {"coordinates":[-81.854034,43.164654],"type":"Point"}
}