{
  "type": "Feature",
  "properties": {
    "addr:full":"RR 3 Tara ON N0H 2N0",
    "addr:postcode":"n0h 2n0",
    "addr:street":"Rr 3",
    "iso:country":"CA",
    "sg:address":"RR 3",
    "sg:city":"Tara",
    "sg:classifiers":[
        {
            "category":"Building & Trades",
            "subcategory":"Construction",
            "type":"Services"
        }
    ],
    "sg:phone":"+1 519 934 2608",
    "sg:postcode":"N0H 2N0",
    "sg:province":"ON",
    "sg:tags":[
        "roofing",
        "painter",
        "contractor"
    ],
    "wof:name":"Rjk Roofing",
    "wof:placetype":"venue"
},
  "geometry": {"coordinates":[-81.14524841310001,44.476524353],"type":"Point"}
}