{
  "type": "Feature",
  "properties": {
    "iso:country":"CA",
    "sg:city":"London",
    "sg:classifiers":[
        {
            "category":"Professional",
            "subcategory":"Lawyer & Legal Services",
            "type":"Services"
        }
    ],
    "sg:phone":"+1 519 672 7410",
    "sg:postcode":"N6A 1E2",
    "sg:province":"ON",
    "sg:tags":[
        "attorney"
    ],
    "wof:name":"Braiden, Richard",
    "wof:placetype":"venue"
},
  "geometry": {"coordinates":[-81.251205,42.982548],"type":"Point"}
}