{
  "type": "Feature",
  "properties": {
    "addr:full":"Brossard QC J4W 2S8",
    "addr:postcode":"j4w 2s8",
    "iso:country":"CA",
    "sg:city":"Brossard",
    "sg:classifiers":[
        {
            "category":"Retail",
            "subcategory":"Auto Repair",
            "type":"Services"
        }
    ],
    "sg:phone":"+1 450 923 5598",
    "sg:postcode":"J4W 2S8",
    "sg:province":"QC",
    "sg:tags":[
        "repairing",
        "automobile"
    ],
    "wof:name":"B J Auto",
    "wof:placetype":"venue"
},
  "geometry": {"coordinates":[-73.46979522709999,45.4669418335],"type":"Point"}
}