{
  "type": "Feature",
  "properties": {
    "addr:full":"4251 Rue Sainte-Catherine E Montreal QC H1V 1X5",
    "addr:housenumber":"4251",
    "addr:postcode":"h1v 1x5",
    "addr:street":"Rue Sainte-Catherine E",
    "iso:country":"CA",
    "sg:address":"4251 Rue Sainte-Catherine E",
    "sg:city":"Montreal",
    "sg:classifiers":[
        {
            "category":"Shopping",
            "subcategory":"Pharmacy",
            "type":"Retail Goods"
        }
    ],
    "sg:phone":"+1 514 255 4400",
    "sg:postcode":"H1V 1X5",
    "sg:province":"QC",
    "wof:name":"Uniprix Corbeil & Morin",
    "wof:placetype":"venue"
},
  "geometry": {"coordinates":[-73.534569,45.550098],"type":"Point"}
}