{
  "type": "Feature",
  "properties": {
    "iso:country":"CA",
    "sg:address":"2599 Tecumseh Rd W",
    "sg:city":"Windsor",
    "sg:classifiers":[
        {
            "category":"Autos & Motor Vehicles",
            "subcategory":"Auto Supplies",
            "type":"Retail Goods"
        }
    ],
    "sg:phone":"+1 519 252 7291",
    "sg:postcode":"N9B 1W4",
    "sg:province":"ON",
    "sg:tags":[
        "repairing",
        "automobile"
    ],
    "wof:name":"Phoenix Automotives",
    "wof:placetype":"venue"
},
  "geometry": {"coordinates":[-83.05676269529999,42.2910499573],"type":"Point"}
}