{
  "type": "Feature",
  "properties": {
    "addr:full":"1101 97 Ave Dawson Creek BC V1G 1N5",
    "addr:housenumber":"1101",
    "addr:postcode":"v1g 1n5",
    "addr:street":"97 Ave",
    "iso:country":"CA",
    "sg:address":"1101 97 Ave",
    "sg:city":"Dawson Creek",
    "sg:classifiers":[
        {
            "category":"Wholesale",
            "subcategory":"Electrical",
            "type":"Manufacturing & Wholesale Goods"
        }
    ],
    "sg:phone":"+1 250 782 4896",
    "sg:postcode":"V1G 1N5",
    "sg:province":"BC",
    "sg:tags":[
        "equipment",
        "electric",
        "supply"
    ],
    "wof:name":"E B Horsman & Son",
    "wof:placetype":"venue"
},
  "geometry": {"coordinates":[-120.232788,55.764973],"type":"Point"}
}