{
  "type": "Feature",
  "properties": {
    "addr:full":"5202 51 Ave Cold Lake AB T9M 1P2",
    "addr:housenumber":"5202",
    "addr:postcode":"t9m 1p2",
    "addr:street":"51 Ave",
    "iso:country":"CA",
    "sg:address":"5202 51 Ave",
    "sg:city":"Cold Lake",
    "sg:classifiers":[
        {
            "category":"Building & Trades",
            "subcategory":"Construction",
            "type":"Services"
        }
    ],
    "sg:phone":"+1 780 594 1994",
    "sg:postcode":"T9M 1P2",
    "sg:province":"AB",
    "sg:tags":[
        "contractor"
    ],
    "wof:name":"Knight Construction Ltd",
    "wof:placetype":"venue"
},
  "geometry": {"coordinates":[-110.209686,54.414528],"type":"Point"}
}