{
  "type": "Feature",
  "properties": {
    "addr:full":"1244 Pembroke St E Pembroke ON K8A 7R9",
    "addr:housenumber":"1244",
    "addr:postcode":"k8a 7r9",
    "addr:street":"Pembroke St E",
    "iso:country":"CA",
    "sg:address":"1244 Pembroke St E",
    "sg:city":"Pembroke",
    "sg:classifiers":[
        {
            "category":"Banks & Credit Unions",
            "subcategory":"Investment Brokerage",
            "type":"Services"
        }
    ],
    "sg:phone":"+1 613 638 2154",
    "sg:postcode":"K8A 7R9",
    "sg:province":"ON",
    "sg:tags":[
        "consultant",
        "planning",
        "financial"
    ],
    "wof:name":"Ryan, Gerard",
    "wof:placetype":"venue"
},
  "geometry": {"coordinates":[-77.085526,45.824032],"type":"Point"}
}