{
  "type": "Feature",
  "properties": {
    "iso:country":"CA",
    "sg:city":"Burnaby",
    "sg:classifiers":[
        {
            "category":"Shopping",
            "subcategory":"Computers & Home Electronics",
            "type":"Retail Goods"
        }
    ],
    "sg:phone":"+1 604 292 9000",
    "sg:postcode":"V5C 6G9",
    "sg:province":"BC",
    "sg:tags":[
        "equipment",
        "satellite",
        "system"
    ],
    "wof:name":"Norsat International Inc",
    "wof:placetype":"venue"
},
  "geometry": {"coordinates":[-123.007118225,49.2601013184],"type":"Point"}
}