{
  "type": "Feature",
  "properties": {
    "addr:full":"380 Wellington St #200 London ON N6A 5B5",
    "addr:housenumber":"380",
    "addr:postcode":"n6a 5b5",
    "addr:street":"Wellington St # 200",
    "iso:country":"CA",
    "sg:address":"380 Wellington St #200",
    "sg:city":"London",
    "sg:classifiers":[
        {
            "category":"Real Estate",
            "subcategory":"Real Estate Agent",
            "type":"Services"
        }
    ],
    "sg:phone":"+1 519 672 5940",
    "sg:postcode":"N6A 5B5",
    "sg:province":"ON",
    "sg:tags":[
        "mall",
        "management",
        "shopping",
        "center"
    ],
    "wof:name":"Redcliff Realty Management Inc",
    "wof:placetype":"venue"
},
  "geometry": {"coordinates":[-81.24462127690001,42.9841003418],"type":"Point"}
}