{
  "type": "Feature",
  "properties": {
    "addr:full":"1095 Boul Graham Mont-Royal QC H3P 2G1",
    "addr:housenumber":"1095",
    "addr:postcode":"h3p 2g1",
    "addr:street":"Boul Graham",
    "iso:country":"CA",
    "sg:address":"1095 Boul Graham",
    "sg:city":"Mont-Royal",
    "sg:classifiers":[
        {
            "category":"Real Estate",
            "subcategory":"Real Estate Agent",
            "type":"Services"
        }
    ],
    "sg:phone":"+1 514 737 5220",
    "sg:postcode":"H3P 2G1",
    "sg:province":"QC",
    "wof:name":"Acropole Realties",
    "wof:placetype":"venue"
},
  "geometry": {"coordinates":[-73.638229,45.517879],"type":"Point"}
}