{
  "type": "Feature",
  "properties": {
    "addr:full":"603 1st Ave Maple Creek SK S0N 1N0",
    "addr:housenumber":"603",
    "addr:postcode":"s0n 1n0",
    "addr:street":"1St Ave",
    "iso:country":"CA",
    "sg:address":"603 1st Ave",
    "sg:city":"Maple Creek",
    "sg:classifiers":[
        {
            "category":"Restaurant",
            "type":"Food & Drink"
        }
    ],
    "sg:phone":"+1 306 662 3525",
    "sg:postcode":"S0N 1N0",
    "sg:province":"SK",
    "wof:name":"Cypress Pizza & Chicken",
    "wof:placetype":"venue"
},
  "geometry": {"coordinates":[-109.480407715,49.9065856934],"type":"Point"}
}