{
  "type": "Feature",
  "properties": {
    "addr:full":"Calgary AB T2J 5N8",
    "addr:postcode":"t2j 5n8",
    "iso:country":"CA",
    "sg:city":"Calgary",
    "sg:classifiers":[
        {
            "category":"Food & Beverages",
            "subcategory":"Meat & Fish",
            "type":"Retail Goods"
        }
    ],
    "sg:phone":"+1 403 278 7842",
    "sg:postcode":"T2J 5N8",
    "sg:province":"AB",
    "sg:tags":[
        "frozen"
    ],
    "wof:name":"M & M Meat Shops Ltd",
    "wof:placetype":"venue"
},
  "geometry": {"coordinates":[-114.071281,50.956909],"type":"Point"}
}