{
  "type": "Feature",
  "properties": {
    "addr:full":"136 222 Rte Racine QC J0E 1Y0",
    "addr:housenumber":"222",
    "addr:postcode":"j0e 1y0",
    "addr:street":"Rte Racine",
    "iso:country":"CA",
    "sg:address":"136 222 Rte",
    "sg:city":"Racine",
    "sg:classifiers":[
        {
            "category":"Recreation",
            "type":"Entertainment"
        }
    ],
    "sg:phone":"+1 450 532 3441",
    "sg:postcode":"J0E 1Y0",
    "sg:province":"QC",
    "sg:tags":[
        "center"
    ],
    "wof:name":"Centre Communautaire DE Racine",
    "wof:placetype":"venue"
},
  "geometry": {"coordinates":[-72.2494277954,45.5034370422],"type":"Point"}
}