{
  "type": "Feature",
  "properties": {
    "addr:full":"1865 Pilgrims Way Oakville ON L6M 1X1",
    "addr:housenumber":"1865",
    "addr:postcode":"l6m 1x1",
    "addr:street":"Pilgrims Way",
    "iso:country":"CA",
    "sg:address":"1865 Pilgrims Way",
    "sg:city":"Oakville",
    "sg:classifiers":[
        {
            "category":"Professional",
            "subcategory":"Management & Consulting",
            "type":"Services"
        }
    ],
    "sg:phone":"+1 905 469 8887",
    "sg:postcode":"L6M 1X1",
    "sg:province":"ON",
    "sg:tags":[
        "consultant",
        "business"
    ],
    "wof:name":"Leadership Fundamentals Inc",
    "wof:placetype":"venue"
},
  "geometry": {"coordinates":[-79.73097229,43.4425201416],"type":"Point"}
}