{
  "type": "Feature",
  "properties": {
    "addr:full":"4574 Rue Saint-Denis Montreal QC H2J 2L3",
    "addr:housenumber":"4574",
    "addr:postcode":"h2j 2l3",
    "addr:street":"Rue Saint-Denis",
    "iso:country":"CA",
    "sg:address":"4574 Rue Saint-Denis",
    "sg:city":"Montreal",
    "sg:classifiers":[
        {
            "category":"Professional",
            "subcategory":"Advertising",
            "type":"Services"
        }
    ],
    "sg:phone":"+1 514 842 3480",
    "sg:postcode":"H2J 2L3",
    "sg:province":"QC",
    "sg:tags":[
        "publisher"
    ],
    "wof:name":"Guerin Printing Ltee",
    "wof:placetype":"venue"
},
  "geometry": {"coordinates":[-73.58409899999999,45.524349],"type":"Point"}
}