{
  "type": "Feature",
  "properties": {
    "addr:full":"798 Dundas St W Toronto ON M6J 1V1",
    "addr:housenumber":"798",
    "addr:postcode":"m6j 1v1",
    "addr:street":"Dundas St W",
    "iso:country":"CA",
    "sg:address":"798 Dundas St W",
    "sg:city":"Toronto",
    "sg:classifiers":[
        {
            "category":"Personal",
            "subcategory":"Beauty Salon",
            "type":"Services"
        }
    ],
    "sg:phone":"+1 416 603 9699",
    "sg:postcode":"M6J 1V1",
    "sg:province":"ON",
    "wof:name":"Dorrie Hairstylist",
    "wof:placetype":"venue"
},
  "geometry": {"coordinates":[-79.4082870483,43.651966095],"type":"Point"}
}