{
  "type": "Feature",
  "properties": {
    "addr:full":"1825 14 Ave N Lethbridge AB T1H 5J7",
    "addr:housenumber":"1825",
    "addr:postcode":"t1h 5j7",
    "addr:street":"14 Ave N",
    "iso:country":"CA",
    "sg:address":"1825 14 Ave N",
    "sg:city":"Lethbridge",
    "sg:classifiers":[
        {
            "category":"Building & Trades",
            "subcategory":"Plumbing",
            "type":"Services"
        }
    ],
    "sg:phone":"+1 403 327 0139",
    "sg:postcode":"T1H 5J7",
    "sg:province":"AB",
    "sg:tags":[
        "air",
        "conditioning",
        "contractor",
        "system",
        "heating"
    ],
    "wof:name":"Derksen Refrigeration Ltd",
    "wof:placetype":"venue"
},
  "geometry": {"coordinates":[-112.81649,49.717426],"type":"Point"}
}