{
  "type": "Feature",
  "properties": {
    "iso:country":"CA",
    "sg:address":"2095 Weston Rd",
    "sg:city":"York",
    "sg:classifiers":[
        {
            "category":"Personal",
            "type":"Services"
        }
    ],
    "sg:phone":"+1 416 243 9362",
    "sg:postcode":"M9N 1X7",
    "sg:province":"ON",
    "sg:tags":[
        "physician",
        "therapist",
        "massage"
    ],
    "wof:name":"Moonlight Spas",
    "wof:placetype":"venue"
},
  "geometry": {"coordinates":[-79.5226593018,43.7021217346],"type":"Point"}
}