{
  "type": "Feature",
  "properties": {
    "addr:full":"568 Rosehill Rd Fort Erie ON L2A 5M4",
    "addr:housenumber":"568",
    "addr:postcode":"l2a 5m4",
    "addr:street":"Rosehill Rd",
    "iso:country":"CA",
    "sg:address":"568 Rosehill Rd",
    "sg:city":"Fort Erie",
    "sg:classifiers":[
        {
            "category":"Building & Trades",
            "subcategory":"Plumbing",
            "type":"Services"
        }
    ],
    "sg:phone":"+1 905 871 6925",
    "sg:postcode":"L2A 5M4",
    "sg:province":"ON",
    "sg:tags":[
        "heating",
        "contractor"
    ],
    "wof:name":"Glenn Held Plumbing & Heating",
    "wof:placetype":"venue"
},
  "geometry": {"coordinates":[-78.979874,42.890934],"type":"Point"}
}