{
  "type": "Feature",
  "properties": {
    "addr:full":"33 Yonge St Toronto ON M5E 1G4",
    "addr:housenumber":"33",
    "addr:postcode":"m5e 1g4",
    "addr:street":"Yonge St",
    "iso:country":"CA",
    "sg:address":"33 Yonge St",
    "sg:city":"Toronto",
    "sg:classifiers":[
        {
            "category":"Retail",
            "subcategory":"Photofinishing",
            "type":"Services"
        }
    ],
    "sg:phone":"+1 416 366 3686",
    "sg:postcode":"M5E 1G4",
    "sg:province":"ON",
    "sg:tags":[
        "photo",
        "finishing"
    ],
    "wof:name":"Just One Hour Film Processing",
    "wof:placetype":"venue"
},
  "geometry": {"coordinates":[-79.3768615723,43.6471099854],"type":"Point"}
}