{
  "type": "Feature",
  "properties": {
    "iso:country":"CA",
    "sg:address":"10654 82 Ave NW",
    "sg:city":"Edmonton",
    "sg:classifiers":[
        {
            "category":"Professional",
            "subcategory":"Advertising",
            "type":"Services"
        }
    ],
    "sg:phone":"+1 780 414 5800",
    "sg:postcode":"T6E 2A7",
    "sg:province":"AB",
    "sg:tags":[
        "packaging",
        "mailing",
        "shipping"
    ],
    "wof:name":"Mail Boxes Etc",
    "wof:placetype":"venue"
},
  "geometry": {"coordinates":[-113.504997253,53.5182189941],"type":"Point"}
}