{
  "type": "Feature",
  "properties": {
    "iso:country":"CA",
    "sg:city":"Toronto",
    "sg:classifiers":[
        {
            "category":"Shopping",
            "type":"Retail Goods"
        }
    ],
    "sg:phone":"+1 416 504 9515",
    "sg:postcode":"M5V 2J4",
    "sg:province":"ON",
    "sg:tags":[
        "art",
        "gallery",
        "dealer"
    ],
    "wof:name":"Leo Kamen Gallery",
    "wof:placetype":"venue"
},
  "geometry": {"coordinates":[-79.395447,43.645809],"type":"Point"}
}