{
  "type": "Feature",
  "properties": {
    "addr:full":"Richmond Hill ON L4C 5K9",
    "addr:postcode":"l4c 5k9",
    "iso:country":"CA",
    "sg:city":"Richmond Hill",
    "sg:classifiers":[
        {
            "category":"Health Services",
            "subcategory":"Optometrist",
            "type":"Services"
        }
    ],
    "sg:phone":"+1 905 884 0061",
    "sg:postcode":"L4C 5K9",
    "sg:province":"ON",
    "wof:name":"Capitelli, Susan OD",
    "wof:placetype":"venue"
},
  "geometry": {"coordinates":[-79.439369,43.879616],"type":"Point"}
}