{
  "type": "Feature",
  "properties": {
    "addr:full":"Saint-Raymond QC G3L 4A7",
    "addr:postcode":"g3l 4a7",
    "iso:country":"CA",
    "sg:city":"Saint-Raymond",
    "sg:classifiers":[
        {
            "category":"Building & Trades",
            "subcategory":"Plumbing",
            "type":"Services"
        }
    ],
    "sg:phone":"+1 418 337 7095",
    "sg:postcode":"G3L 4A7",
    "sg:province":"QC",
    "sg:tags":[
        "conditioning",
        "air",
        "refrigeration",
        "system",
        "contractor"
    ],
    "wof:name":"Refrigeration Fabien Trudel",
    "wof:placetype":"venue"
},
  "geometry": {"coordinates":[-71.8283081055,46.8934288025],"type":"Point"}
}