{
  "type": "Feature",
  "properties": {
    "addr:full":"Regina SK S4P 0S4",
    "addr:postcode":"s4p 0s4",
    "iso:country":"CA",
    "sg:city":"Regina",
    "sg:classifiers":[
        {
            "category":"Health Services",
            "subcategory":"Optometrist",
            "type":"Services"
        }
    ],
    "sg:phone":"+1 306 791 6899",
    "sg:postcode":"S4P 0S4",
    "sg:province":"SK",
    "wof:name":"Neumann, Robert M OD",
    "wof:placetype":"venue"
},
  "geometry": {"coordinates":[-104.61264038100001,50.4469718933],"type":"Point"}
}