{
  "type": "Feature",
  "properties": {
    "addr:full":"10043 63 Ave NW Edmonton AB T6E 4Z2",
    "addr:housenumber":"10043",
    "addr:postcode":"t6e 4z2",
    "addr:street":"63 Ave Nw",
    "iso:country":"CA",
    "sg:address":"10043 63 Ave NW",
    "sg:city":"Edmonton",
    "sg:classifiers":[
        {
            "category":"Retail",
            "subcategory":"Repair Shop",
            "type":"Services"
        }
    ],
    "sg:phone":"+1 780 434 9988",
    "sg:postcode":"T6E 4Z2",
    "sg:province":"AB",
    "sg:tags":[
        "refinishing",
        "furniture"
    ],
    "wof:name":"Jack the Stripper Ltd",
    "wof:placetype":"venue"
},
  "geometry": {"coordinates":[-113.489952,53.499565],"type":"Point"}
}