{
  "type": "Feature",
  "properties": {
    "iso:country":"CA",
    "sg:address":"404 Enterprise Ave",
    "sg:city":"Kitimat",
    "sg:classifiers":[
        {
            "category":"Restaurant",
            "type":"Food & Drink"
        }
    ],
    "sg:phone":"+1 250 639 9839",
    "sg:postcode":"V8C 2E2",
    "sg:province":"BC",
    "wof:name":"Cor's",
    "wof:placetype":"venue"
},
  "geometry": {"coordinates":[-128.687881,54.058826],"type":"Point"}
}