{
  "type": "Feature",
  "properties": {
    "addr:full":"5119 50A Ave Sylvan Lake AB T4S 1E1",
    "addr:housenumber":"5119",
    "addr:postcode":"t4s 1e1",
    "addr:street":"50A Ave",
    "iso:country":"CA",
    "sg:address":"5119 50A Ave",
    "sg:city":"Sylvan Lake",
    "sg:classifiers":[
        {
            "category":"Organizations",
            "subcategory":"Community Association",
            "type":"Services"
        }
    ],
    "sg:phone":"+1 403 887 3390",
    "sg:postcode":"T4S 1E1",
    "sg:province":"AB",
    "sg:tags":[
        "club"
    ],
    "wof:name":"Sylvan Lake & District Lions",
    "wof:placetype":"venue"
},
  "geometry": {"coordinates":[-114.10083,52.308102],"type":"Point"}
}