{
  "type": "Feature",
  "properties": {
    "addr:full":"Woodstock NB E7M 2C5",
    "addr:postcode":"e7m 2c5",
    "iso:country":"CA",
    "sg:city":"Woodstock",
    "sg:classifiers":[
        {
            "category":"Shopping",
            "subcategory":"Gifts & Souvenirs",
            "type":"Retail Goods"
        }
    ],
    "sg:phone":"+1 506 325 1138",
    "sg:postcode":"E7M 2C5",
    "sg:province":"NB",
    "sg:tags":[
        "shop"
    ],
    "wof:name":"Fabulous Finds",
    "wof:placetype":"venue"
},
  "geometry": {"coordinates":[-67.5733337402,46.1500167847],"type":"Point"}
}