{
  "type": "Feature",
  "properties": {
    "addr:full":"Edwardsville NS B2A 4T7",
    "addr:postcode":"b2a 4t7",
    "iso:country":"CA",
    "sg:city":"Edwardsville",
    "sg:classifiers":[
        {
            "category":"Manufacturing",
            "subcategory":"Tools & Machinery",
            "type":"Manufacturing & Wholesale Goods"
        }
    ],
    "sg:phone":"+1 902 564 5592",
    "sg:postcode":"B2A 4T7",
    "sg:province":"NS",
    "sg:tags":[
        "equipment",
        "mining",
        "trencher",
        "supply"
    ],
    "wof:name":"Baldwin & Francis Elec Ltd",
    "wof:placetype":"venue"
},
  "geometry": {"coordinates":[-60.229553,46.155071],"type":"Point"}
}