{
  "type": "Feature",
  "properties": {
    "addr:full":"345 Ravenhill Ave Ottawa ON K2A 0J5",
    "addr:housenumber":"345",
    "addr:postcode":"k2a 0j5",
    "addr:street":"Ravenhill Ave",
    "iso:country":"CA",
    "sg:address":"345 Ravenhill Ave",
    "sg:city":"Ottawa",
    "sg:classifiers":[
        {
            "category":"Education",
            "subcategory":"School",
            "type":"Public Place"
        }
    ],
    "sg:phone":"+1 613 722 4474",
    "sg:postcode":"K2A 0J5",
    "sg:province":"ON",
    "wof:name":"Churchill Alternative School",
    "wof:placetype":"venue"
},
  "geometry": {"coordinates":[-75.75347137449999,45.3902931213],"type":"Point"}
}