{
  "type": "Feature",
  "properties": {
    "addr:full":"5502 Rue Notre-Dame E Montreal QC H1N 2C4",
    "addr:housenumber":"5502",
    "addr:postcode":"h1n 2c4",
    "addr:street":"Rue Notre-Dame E",
    "iso:country":"CA",
    "sg:address":"5502 Rue Notre-Dame E",
    "sg:city":"Montreal",
    "sg:classifiers":[
        {
            "category":"Wholesale",
            "subcategory":"Electrical",
            "type":"Manufacturing & Wholesale Goods"
        }
    ],
    "sg:phone":"+1 514 254 4420",
    "sg:postcode":"H1N 2C4",
    "sg:province":"QC",
    "sg:tags":[
        "television"
    ],
    "wof:name":"Cvs Central Video Systeme",
    "wof:placetype":"venue"
},
  "geometry": {"coordinates":[-73.523972,45.563297],"type":"Point"}
}