{
  "type": "Feature",
  "properties": {
    "addr:full":"1086 Northmount Dr NW Calgary AB T2L 0C2",
    "addr:housenumber":"1086",
    "addr:postcode":"t2l 0c2",
    "addr:street":"Northmount Dr Nw",
    "iso:country":"CA",
    "sg:address":"1086 Northmount Dr NW",
    "sg:city":"Calgary",
    "sg:classifiers":[
        {
            "category":"Professional",
            "subcategory":"Accounting & Tax Preparation",
            "type":"Services"
        }
    ],
    "sg:phone":"+1 403 284 1495",
    "sg:postcode":"T2L 0C2",
    "sg:province":"AB",
    "sg:tags":[
        "accountant"
    ],
    "wof:name":"P & D Accounting Svc Ltd",
    "wof:placetype":"venue"
},
  "geometry": {"coordinates":[-114.11380800000001,51.088631],"type":"Point"}
}