{
  "type": "Feature",
  "properties": {
    "iso:country":"CA",
    "sg:address":"34294 Farmer Rd",
    "sg:city":"Abbotsford",
    "sg:classifiers":[
        {
            "category":"Building & Trades",
            "subcategory":"Construction",
            "type":"Services"
        }
    ],
    "sg:phone":"+1 604 850 5522",
    "sg:postcode":"V2S 7M4",
    "sg:province":"BC",
    "sg:tags":[
        "excavating",
        "contractor"
    ],
    "wof:name":"Larry's Excavating",
    "wof:placetype":"venue"
},
  "geometry": {"coordinates":[-122.275146,49.009338],"type":"Point"}
}