{
  "type": "Feature",
  "properties": {
    "addr:full":"347 Montee Sainte-Victoire Sainte-Victoire-DE-Sorel QC J0G 1T0",
    "addr:housenumber":"347",
    "addr:postcode":"j0g 1t0",
    "addr:street":"Montee Sainte-Victoire",
    "iso:country":"CA",
    "sg:address":"347 Montee Sainte-Victoire",
    "sg:city":"Sainte-Victoire-DE-Sorel",
    "sg:classifiers":[
        {
            "category":"Recreation",
            "type":"Entertainment"
        }
    ],
    "sg:phone":"+1 450 782 2406",
    "sg:postcode":"J0G 1T0",
    "sg:province":"QC",
    "sg:tags":[
        "center"
    ],
    "wof:name":"Loisir & Centre Recreatif",
    "wof:placetype":"venue"
},
  "geometry": {"coordinates":[-73.087547,45.948643],"type":"Point"}
}