{
  "type": "Feature",
  "properties": {
    "addr:full":"529 Upper Sherman Ave Hamilton ON L8V 3L9",
    "addr:housenumber":"529",
    "addr:postcode":"l8v 3l9",
    "addr:street":"Upper Sherman Ave",
    "iso:country":"CA",
    "sg:address":"529 Upper Sherman Ave",
    "sg:city":"Hamilton",
    "sg:classifiers":[
        {
            "category":"Real Estate",
            "subcategory":"Real Estate Agent",
            "type":"Services"
        }
    ],
    "sg:phone":"+1 905 387 5992",
    "sg:postcode":"L8V 3L9",
    "sg:province":"ON",
    "wof:name":"M Panton Real Estate",
    "wof:placetype":"venue"
},
  "geometry": {"coordinates":[-79.847328186,43.2316436768],"type":"Point"}
}