{
  "type": "Feature",
  "properties": {
    "addr:full":"1129 Kingsway Vancouver BC V5V 3C9",
    "addr:housenumber":"1129",
    "addr:postcode":"v5v 3c9",
    "addr:street":"Kingsway",
    "iso:country":"CA",
    "sg:address":"1129 Kingsway",
    "sg:city":"Vancouver",
    "sg:classifiers":[
        {
            "category":"Retail",
            "subcategory":"Auto Repair",
            "type":"Services"
        }
    ],
    "sg:phone":"+1 604 708 9783",
    "sg:postcode":"V5V 3C9",
    "sg:province":"BC",
    "sg:tags":[
        "body",
        "automobile",
        "painting"
    ],
    "wof:name":"Tao's Autobody Collision",
    "wof:placetype":"venue"
},
  "geometry": {"coordinates":[-123.080940247,49.2527122498],"type":"Point"}
}