{
  "type": "Feature",
  "properties": {
    "addr:full":"3695 Lougheed Hwy Vancouver BC V5M 2A6",
    "addr:housenumber":"3695",
    "addr:postcode":"v5m 2a6",
    "addr:street":"Lougheed Hwy",
    "iso:country":"CA",
    "sg:address":"3695 Lougheed Hwy",
    "sg:city":"Vancouver",
    "sg:classifiers":[
        {
            "category":"Restaurant",
            "type":"Food & Drink"
        }
    ],
    "sg:phone":"+1 604 718 1050",
    "sg:postcode":"V5M 2A6",
    "sg:province":"BC",
    "wof:name":"Mc Donald's",
    "wof:placetype":"venue"
},
  "geometry": {"coordinates":[-123.02444457999999,49.2655601501],"type":"Point"}
}