{
  "type": "Feature",
  "properties": {
    "addr:full":"80 Catherine St Trenton ON K8V 6N8",
    "addr:housenumber":"80",
    "addr:postcode":"k8v 6n8",
    "addr:street":"Catherine St",
    "iso:country":"CA",
    "sg:address":"80 Catherine St",
    "sg:city":"Trenton",
    "sg:classifiers":[
        {
            "category":"Real Estate",
            "subcategory":"Real Estate Operator",
            "type":"Services"
        }
    ],
    "sg:phone":"+1 613 394 2688",
    "sg:postcode":"K8V 6N8",
    "sg:province":"ON",
    "sg:tags":[
        "apartment"
    ],
    "wof:name":"Trenton Memorial Lodge",
    "wof:placetype":"venue"
},
  "geometry": {"coordinates":[-77.587761,44.099957],"type":"Point"}
}