{
  "type": "Feature",
  "properties": {
    "addr:full":"Grand Valley ON L0N 1G0",
    "addr:postcode":"l0n 1g0",
    "iso:country":"CA",
    "sg:city":"Grand Valley",
    "sg:classifiers":[
        {
            "category":"Building & Trades",
            "subcategory":"Construction",
            "type":"Services"
        }
    ],
    "sg:phone":"+1 519 928 5394",
    "sg:postcode":"L0N 1G0",
    "sg:province":"ON",
    "sg:tags":[
        "roofing",
        "contractor"
    ],
    "wof:name":"Grand Valley Roofing",
    "wof:placetype":"venue"
},
  "geometry": {"coordinates":[-80.315612793,43.9004096985],"type":"Point"}
}