{
  "type": "Feature",
  "properties": {
    "addr:full":"617 Kennedy Rd Scarborough ON M1K 2B2",
    "addr:housenumber":"617",
    "addr:postcode":"m1k 2b2",
    "addr:street":"Kennedy Rd",
    "iso:country":"CA",
    "sg:address":"617 Kennedy Rd",
    "sg:city":"Scarborough",
    "sg:classifiers":[
        {
            "category":"Manufacturing",
            "subcategory":"Furniture",
            "type":"Manufacturing & Wholesale Goods"
        }
    ],
    "sg:phone":"+1 416 261 3939",
    "sg:postcode":"M1K 2B2",
    "sg:province":"ON",
    "sg:tags":[
        "equipment",
        "supply"
    ],
    "wof:name":"Dream Team Upholstery",
    "wof:placetype":"venue"
},
  "geometry": {"coordinates":[-79.26448822019999,43.7245750427],"type":"Point"}
}