{
  "type": "Feature",
  "properties": {
    "addr:full":"1175 Gordon Dr Kelowna BC V1Y 3E5",
    "addr:housenumber":"1175",
    "addr:postcode":"v1y 3e5",
    "addr:street":"Gordon Dr",
    "iso:country":"CA",
    "sg:address":"1175 Gordon Dr",
    "sg:city":"Kelowna",
    "sg:classifiers":[
        {
            "category":"Shopping",
            "type":"Retail Goods"
        }
    ],
    "sg:phone":"+1 250 862 2414",
    "sg:postcode":"V1Y 3E5",
    "sg:province":"BC",
    "sg:tags":[
        "pet",
        "food",
        "supply"
    ],
    "wof:name":"Pets First Products & Svc",
    "wof:placetype":"venue"
},
  "geometry": {"coordinates":[-119.476829529,49.8933486938],"type":"Point"}
}