{
  "type": "Feature",
  "properties": {
    "iso:country":"CA",
    "sg:address":"133 Inshes Ave",
    "sg:city":"Chatham",
    "sg:classifiers":[
        {
            "category":"Arts & Performance",
            "subcategory":"Theater",
            "type":"Entertainment"
        }
    ],
    "sg:phone":"+1 519 351 0951",
    "sg:postcode":"N7M 2Z1",
    "sg:province":"ON",
    "sg:tags":[
        "live",
        "music"
    ],
    "wof:name":"Sound Effx Audio",
    "wof:placetype":"venue"
},
  "geometry": {"coordinates":[-82.19068145750001,42.3972511292],"type":"Point"}
}