{
  "type": "Feature",
  "properties": {
    "addr:full":"2515 Boul Casavant O Saint-Hyacinthe QC J2S 8B8",
    "addr:housenumber":"2515",
    "addr:postcode":"j2s 8b8",
    "addr:street":"Boul Casavant O",
    "iso:country":"CA",
    "sg:address":"2515 Boul Casavant O",
    "sg:city":"Saint-Hyacinthe",
    "sg:classifiers":[
        {
            "category":"Home & Garden",
            "subcategory":"Building Materials",
            "type":"Retail Goods"
        }
    ],
    "sg:phone":"+1 450 773 0423",
    "sg:postcode":"J2S 8B8",
    "sg:province":"QC",
    "sg:tags":[
        "paint"
    ],
    "wof:name":"Peinture Prefontaine Inc",
    "wof:placetype":"venue"
},
  "geometry": {"coordinates":[-72.968941,45.632668],"type":"Point"}
}