{
  "type": "Feature",
  "properties": {
    "addr:full":"Waterloo ON N2J 4R1",
    "addr:postcode":"n2j 4r1",
    "iso:country":"CA",
    "sg:city":"Waterloo",
    "sg:classifiers":[
        {
            "category":"Building & Trades",
            "subcategory":"Construction",
            "type":"Services"
        }
    ],
    "sg:phone":"+1 519 725 3903",
    "sg:postcode":"N2J 4R1",
    "sg:province":"ON",
    "sg:tags":[
        "designer",
        "dealer",
        "pool",
        "swimming"
    ],
    "wof:name":"Ponds For People Pools",
    "wof:placetype":"venue"
},
  "geometry": {"coordinates":[-80.5166854858,43.4883460999],"type":"Point"}
}