{
  "type": "Feature",
  "properties": {
    "addr:full":"1328 Main St Cap-D'Espoir QC G0C 1G0",
    "addr:housenumber":"1328",
    "addr:postcode":"g0c 1g0",
    "addr:street":"Main St",
    "iso:country":"CA",
    "sg:address":"1328 Main St",
    "sg:city":"Cap-D'Espoir",
    "sg:classifiers":[
        {
            "category":"Shopping",
            "subcategory":"Discount & Variety Stores",
            "type":"Retail Goods"
        }
    ],
    "sg:phone":"+1 418 782 2424",
    "sg:postcode":"G0C 1G0",
    "sg:province":"QC",
    "sg:tags":[
        "merchandise",
        "general"
    ],
    "wof:name":"J W Bourget Ltd",
    "wof:placetype":"venue"
},
  "geometry": {"coordinates":[-65.919815,48.202938],"type":"Point"}
}