{
  "type": "Feature",
  "properties": {
    "addr:full":"55 Colossus Dr Woodbridge ON L4L 9J8",
    "addr:housenumber":"55",
    "addr:postcode":"l4l 9j8",
    "addr:street":"Colossus Dr",
    "iso:country":"CA",
    "sg:address":"55 Colossus Dr",
    "sg:city":"Woodbridge",
    "sg:classifiers":[
        {
            "category":"Shopping",
            "subcategory":"Bicycles & Sporting Goods",
            "type":"Retail Goods"
        }
    ],
    "sg:phone":"+1 905 264 8809",
    "sg:postcode":"L4L 9J8",
    "sg:province":"ON",
    "sg:tags":[
        "equipment",
        "golf",
        "supply"
    ],
    "wof:name":"Golf Town",
    "wof:placetype":"venue"
},
  "geometry": {"coordinates":[-79.54242706300001,43.7869186401],"type":"Point"}
}