{
  "type": "Feature",
  "properties": {
    "iso:country":"CA",
    "sg:city":"Brampton",
    "sg:classifiers":[
        {
            "category":"Manufacturing",
            "subcategory":"Metals",
            "type":"Manufacturing & Wholesale Goods"
        }
    ],
    "sg:phone":"+1 905 451 7774",
    "sg:postcode":"L6W 3K1",
    "sg:province":"ON",
    "sg:tags":[
        "fastener"
    ],
    "wof:name":"Brafasco",
    "wof:placetype":"venue"
},
  "geometry": {"coordinates":[-79.73165130620001,43.6995620728],"type":"Point"}
}