{
  "type": "Feature",
  "properties": {
    "addr:full":"1500 Rue Notre-Dame E Montreal QC H2L 2R4",
    "addr:housenumber":"1500",
    "addr:postcode":"h2l 2r4",
    "addr:street":"Rue Notre-Dame E",
    "iso:country":"CA",
    "sg:address":"1500 Rue Notre-Dame E",
    "sg:city":"Montreal",
    "sg:classifiers":[
        {
            "category":"Manufacturing",
            "subcategory":"Food",
            "type":"Manufacturing & Wholesale Goods"
        }
    ],
    "sg:phone":"+1 514 597 1786",
    "sg:postcode":"H2L 2R4",
    "sg:province":"QC",
    "sg:tags":[
        "brewer"
    ],
    "wof:name":"Molson CO Ltd",
    "wof:placetype":"venue"
},
  "geometry": {"coordinates":[-73.54819500000001,45.517822],"type":"Point"}
}