{
  "type": "Feature",
  "properties": {
    "addr:full":"44 Ed Belfour Dr Carman MB R0G 0J0",
    "addr:housenumber":"44",
    "addr:postcode":"r0g 0j0",
    "addr:street":"Ed Belfour Dr",
    "iso:country":"CA",
    "sg:address":"44 Ed Belfour Dr",
    "sg:city":"Carman",
    "sg:classifiers":[
        {
            "category":"Organizations",
            "subcategory":"Community Association",
            "type":"Services"
        }
    ],
    "sg:phone":"+1 204 745 1990",
    "sg:postcode":"R0G 0J0",
    "sg:province":"MB",
    "sg:tags":[
        "club"
    ],
    "wof:name":"Carman & Dufferin Recreation",
    "wof:placetype":"venue"
},
  "geometry": {"coordinates":[-98.002319,49.508606],"type":"Point"}
}