{
  "type": "Feature",
  "properties": {
    "iso:country":"CA",
    "sg:city":"Markham",
    "sg:classifiers":[
        {
            "category":"Wholesale",
            "subcategory":"Machinery & Supplies",
            "type":"Manufacturing & Wholesale Goods"
        }
    ],
    "sg:phone":"+1 905 474 9340",
    "sg:postcode":"L3R 5L9",
    "sg:province":"ON",
    "sg:tags":[
        "equipment",
        "safety",
        "clothing"
    ],
    "wof:name":"Winsafe Corp",
    "wof:placetype":"venue"
},
  "geometry": {"coordinates":[-79.360069,43.85667],"type":"Point"}
}