{
  "type": "Feature",
  "properties": {
    "addr:full":"630 Rue Laurent Granby QC J2G 8V1",
    "addr:housenumber":"630",
    "addr:postcode":"j2g 8v1",
    "addr:street":"Rue Laurent",
    "iso:country":"CA",
    "sg:address":"630 Rue Laurent",
    "sg:city":"Granby",
    "sg:classifiers":[
        {
            "category":"Professional",
            "subcategory":"Business Services",
            "type":"Services"
        }
    ],
    "sg:phone":"+1 450 372 8844",
    "sg:postcode":"J2G 8V1",
    "sg:province":"QC",
    "sg:tags":[
        "water",
        "treatment"
    ],
    "wof:name":"Aldex Chemical CO Ltd",
    "wof:placetype":"venue"
},
  "geometry": {"coordinates":[-72.75466900000001,45.391815],"type":"Point"}
}