{
  "type": "Feature",
  "properties": {
    "addr:full":"2324 2nd St S Cranbrook BC V1C 1E1",
    "addr:housenumber":"2324",
    "addr:postcode":"v1c 1e1",
    "addr:street":"2Nd St S",
    "iso:country":"CA",
    "sg:address":"2324 2nd St S",
    "sg:city":"Cranbrook",
    "sg:classifiers":[
        {
            "category":"Organizations",
            "subcategory":"Religious Organization",
            "type":"Services"
        }
    ],
    "sg:phone":"+1 250 489 5411",
    "sg:postcode":"V1C 1E1",
    "sg:province":"BC",
    "sg:tags":[
        "church"
    ],
    "wof:name":"Cranbrook Christian Ctr",
    "wof:placetype":"venue"
},
  "geometry": {"coordinates":[-115.74968699999999,49.508636],"type":"Point"}
}