{
  "type": "Feature",
  "properties": {
    "addr:full":"Toronto ON M4N 2M1",
    "addr:postcode":"m4n 2m1",
    "iso:country":"CA",
    "sg:city":"Toronto",
    "sg:classifiers":[
        {
            "category":"Health Services",
            "subcategory":"Health Practitioner",
            "type":"Services"
        }
    ],
    "sg:phone":"+1 416 440 0408",
    "sg:postcode":"M4N 2M1",
    "sg:province":"ON",
    "sg:tags":[
        "psychologist"
    ],
    "wof:name":"Amin, S",
    "wof:placetype":"venue"
},
  "geometry": {"coordinates":[-79.40362548829999,43.7310256958],"type":"Point"}
}