{
  "type": "Feature",
  "properties": {
    "addr:full":"505 St Anne's Rd Winnipeg MB R2M 3E5",
    "addr:housenumber":"505",
    "addr:postcode":"r2m 3e5",
    "addr:street":"St Anne'S Rd",
    "iso:country":"CA",
    "sg:address":"505 St Anne's Rd",
    "sg:city":"Winnipeg",
    "sg:classifiers":[
        {
            "category":"Social Services",
            "subcategory":"Child Care",
            "type":"Services"
        }
    ],
    "sg:phone":"+1 204 982 6690",
    "sg:postcode":"R2M 3E5",
    "sg:province":"MB",
    "wof:name":"Morrow Avenue Day Care Inc",
    "wof:placetype":"venue"
},
  "geometry": {"coordinates":[-97.09465,49.842354],"type":"Point"}
}