{
  "type": "Feature",
  "properties": {
    "iso:country":"CA",
    "sg:address":"505 St Anne's Rd",
    "sg:city":"Winnipeg",
    "sg:classifiers":[
        {
            "category":"Social Services",
            "subcategory":"Child Care",
            "type":"Services"
        }
    ],
    "sg:phone":"+1 204 982 6690",
    "sg:postcode":"R2M 3E5",
    "sg:province":"MB",
    "wof:name":"Morrow Avenue Day Care Inc",
    "wof:placetype":"venue"
},
  "geometry": {"coordinates":[-97.09465,49.842354],"type":"Point"}
}