{
  "type": "Feature",
  "properties": {
    "iso:country":"CA",
    "sg:address":"6925 Enterprise Way",
    "sg:city":"Windsor",
    "sg:classifiers":[
        {
            "category":"Health Services",
            "subcategory":"Doctor",
            "type":"Services"
        }
    ],
    "sg:phone":"+1 519 948 4119",
    "sg:postcode":"N8T 3N6",
    "sg:province":"ON",
    "sg:tags":[
        "dentist"
    ],
    "wof:name":"Serra, Paul DDS",
    "wof:placetype":"venue"
},
  "geometry": {"coordinates":[-82.93924713129999,42.3080291748],"type":"Point"}
}