{
  "type": "Feature",
  "properties": {
    "addr:full":"293 Reid St Quesnel BC V2J 2M1",
    "addr:housenumber":"293",
    "addr:postcode":"v2j 2m1",
    "addr:street":"Reid St",
    "iso:country":"CA",
    "sg:address":"293 Reid St",
    "sg:city":"Quesnel",
    "sg:classifiers":[
        {
            "category":"Banks & Credit Unions",
            "subcategory":"Bank",
            "type":"Services"
        }
    ],
    "sg:phone":"+1 250 992 7021",
    "sg:postcode":"V2J 2M1",
    "sg:province":"BC",
    "wof:name":"Scotiabank",
    "wof:placetype":"venue"
},
  "geometry": {"coordinates":[-122.496864,52.977123],"type":"Point"}
}