{
  "type": "Feature",
  "properties": {
    "addr:full":"311 Dundas St S Cambridge ON N1T 1P8",
    "addr:housenumber":"311",
    "addr:postcode":"n1t 1p8",
    "addr:street":"Dundas St S",
    "iso:country":"CA",
    "sg:address":"311 Dundas St S",
    "sg:city":"Cambridge",
    "sg:classifiers":[
        {
            "category":"Banks & Credit Unions",
            "subcategory":"Bank",
            "type":"Services"
        }
    ],
    "sg:phone":"+1 519 740 4460",
    "sg:postcode":"N1T 1P8",
    "sg:province":"ON",
    "wof:name":"Royal Bank Financial Group",
    "wof:placetype":"venue"
},
  "geometry": {"coordinates":[-80.28703308110001,43.3545799255],"type":"Point"}
}