{
  "type": "Feature",
  "properties": {
    "iso:country":"CA",
    "sg:address":"276 Ch DE LA Grande-Cote",
    "sg:city":"Saint-Eustache",
    "sg:classifiers":[
        {
            "category":"Autos & Motor Vehicles",
            "subcategory":"Auto Supplies",
            "type":"Retail Goods"
        }
    ],
    "sg:phone":"+1 450 491 1302",
    "sg:postcode":"J7P 5H8",
    "sg:province":"QC",
    "sg:tags":[
        "tire"
    ],
    "wof:name":"Pneus Rcl",
    "wof:placetype":"venue"
},
  "geometry": {"coordinates":[-73.8676452637,45.5717277527],"type":"Point"}
}