{
  "type": "Feature",
  "properties": {
    "addr:full":"Richmond BC V6X 3J3",
    "addr:postcode":"v6x 3j3",
    "iso:country":"CA",
    "sg:city":"Richmond",
    "sg:classifiers":[
        {
            "category":"Restaurant",
            "type":"Food & Drink"
        }
    ],
    "sg:phone":"+1 604 303 7977",
    "sg:postcode":"V6X 3J3",
    "sg:province":"BC",
    "wof:name":"Mui Garden Restaurant",
    "wof:placetype":"venue"
},
  "geometry": {"coordinates":[-123.140022,49.171082],"type":"Point"}
}