{
  "type": "Feature",
  "properties": {
    "addr:full":"Sexsmith AB T0H 3C0",
    "addr:postcode":"t0h 3c0",
    "iso:country":"CA",
    "sg:city":"Sexsmith",
    "sg:classifiers":[
        {
            "category":"Manufacturing",
            "subcategory":"Signs",
            "type":"Manufacturing & Wholesale Goods"
        }
    ],
    "sg:phone":"+1 780 568 2157",
    "sg:postcode":"T0H 3C0",
    "sg:province":"AB",
    "wof:name":"Saddle Hills Signs",
    "wof:placetype":"venue"
},
  "geometry": {"coordinates":[-118.780762,55.345112],"type":"Point"}
}