{
  "type": "Feature",
  "properties": {
    "addr:full":"Saint-Zacharie QC G0M 2C0",
    "addr:postcode":"g0m 2c0",
    "iso:country":"CA",
    "sg:city":"Saint-Zacharie",
    "sg:classifiers":[
        {
            "category":"Building & Trades",
            "subcategory":"Construction",
            "type":"Services"
        }
    ],
    "sg:phone":"+1 418 593 5025",
    "sg:postcode":"G0M 2C0",
    "sg:province":"QC",
    "sg:tags":[
        "general",
        "contractor"
    ],
    "wof:name":"Lariviere & Fils DE Beauce Inc",
    "wof:placetype":"venue"
},
  "geometry": {"coordinates":[-70.363029,46.126438],"type":"Point"}
}