{
  "type": "Feature",
  "properties": {
    "addr:full":"9906 101 Ave Lac LA Biche AB T0A 2C0",
    "addr:housenumber":"9906",
    "addr:postcode":"t0a 2c0",
    "addr:street":"101 Ave",
    "iso:country":"CA",
    "sg:address":"9906 101 Ave",
    "sg:city":"Lac LA Biche",
    "sg:classifiers":[
        {
            "category":"Arena",
            "subcategory":"Sports Club",
            "type":"Entertainment"
        }
    ],
    "sg:phone":"+1 780 623 4707",
    "sg:postcode":"T0A 2C0",
    "sg:province":"AB",
    "sg:tags":[
        "athletic",
        "fields",
        "stadium",
        "government"
    ],
    "wof:name":"Centennial Arena",
    "wof:placetype":"venue"
},
  "geometry": {"coordinates":[-111.969009,54.773266],"type":"Point"}
}