{
  "type": "Feature",
  "properties": {
    "addr:full":"Gloucester ON K1J 1A3",
    "addr:postcode":"k1j 1a3",
    "iso:country":"CA",
    "sg:city":"Gloucester",
    "sg:classifiers":[
        {
            "category":"Professional",
            "subcategory":"Engineering",
            "type":"Services"
        }
    ],
    "sg:phone":"+1 613 749 9685",
    "sg:postcode":"K1J 1A3",
    "sg:province":"ON",
    "sg:tags":[
        "engineer"
    ],
    "wof:name":"Thompson Rosemount Group Inc",
    "wof:placetype":"venue"
},
  "geometry": {"coordinates":[-75.61431884770001,45.428943634],"type":"Point"}
}