{
  "type": "Feature",
  "properties": {
    "iso:country":"CA",
    "sg:city":"Haileybury",
    "sg:classifiers":[
        {
            "category":"Government",
            "subcategory":"Office",
            "type":"Public Place"
        }
    ],
    "sg:phone":"+1 705 672 2664",
    "sg:postcode":"P0J 1K0",
    "sg:province":"ON",
    "wof:name":"Canada Deputes Federaux",
    "wof:placetype":"venue"
},
  "geometry": {"coordinates":[-79.6376647949,47.4494094849],"type":"Point"}
}