{
  "type": "Feature",
  "properties": {
    "addr:full":"Amqui QC G5J 2B7",
    "addr:postcode":"g5j 2b7",
    "iso:country":"CA",
    "sg:city":"Amqui",
    "sg:classifiers":[
        {
            "category":"Banks & Credit Unions",
            "subcategory":"Bank",
            "type":"Services"
        }
    ],
    "sg:phone":"+1 418 629 4416",
    "sg:postcode":"G5J 2B7",
    "sg:province":"QC",
    "wof:name":"Banque Nationale Du Canada",
    "wof:placetype":"venue"
},
  "geometry": {"coordinates":[-67.423615,48.464115],"type":"Point"}
}