{
  "type": "Feature",
  "properties": {
    "addr:full":"3842 Muskoka Rd 118 W Port Carling ON P0B 1J0",
    "addr:housenumber":"3842",
    "addr:postcode":"p0b 1j0",
    "addr:street":"Muskoka Rd 118 W",
    "iso:country":"CA",
    "sg:address":"3842 Muskoka Rd 118 W",
    "sg:city":"Port Carling",
    "sg:classifiers":[
        {
            "category":"Restaurant",
            "type":"Food & Drink"
        }
    ],
    "sg:phone":"+1 705 765 0244",
    "sg:postcode":"P0B 1J0",
    "sg:province":"ON",
    "wof:name":"Rebecca's Casual Fine Dining",
    "wof:placetype":"venue"
},
  "geometry": {"coordinates":[-79.60576629640001,45.0984268188],"type":"Point"}
}