{
  "type": "Feature",
  "properties": {
    "addr:full":"Capreol ON P0M 1H0",
    "addr:postcode":"p0m 1h0",
    "iso:country":"CA",
    "sg:city":"Capreol",
    "sg:classifiers":[
        {
            "category":"Building & Trades",
            "subcategory":"Construction",
            "type":"Services"
        }
    ],
    "sg:phone":"+1 705 858 2152",
    "sg:postcode":"P0M 1H0",
    "sg:province":"ON",
    "sg:tags":[
        "general",
        "contractor"
    ],
    "wof:name":"Renger Resources",
    "wof:placetype":"venue"
},
  "geometry": {"coordinates":[-80.925781,46.713772],"type":"Point"}
}