{
  "type": "Feature",
  "properties": {
    "addr:full":"1 Charles Walk Elliot Lake ON P5A 2A2",
    "addr:housenumber":"1",
    "addr:postcode":"p5a 2a2",
    "addr:street":"Charles Walk",
    "iso:country":"CA",
    "sg:address":"1 Charles Walk",
    "sg:city":"Elliot Lake",
    "sg:classifiers":[
        {
            "category":"Autos & Motor Vehicles",
            "subcategory":"Auto Supplies",
            "type":"Retail Goods"
        }
    ],
    "sg:phone":"+1 705 848 5666",
    "sg:postcode":"P5A 2A2",
    "sg:province":"ON",
    "sg:tags":[
        "automobile",
        "parts"
    ],
    "wof:name":"Farquhar Automotive",
    "wof:placetype":"venue"
},
  "geometry": {"coordinates":[-82.64823199999999,46.386257],"type":"Point"}
}