{
  "type": "Feature",
  "properties": {
    "addr:full":"71 Delta Park Blvd # 1 Brampton ON L6T 5E7",
    "addr:housenumber":"71",
    "addr:postcode":"l6t 5e7",
    "addr:street":"Delta Park Blvd # 1",
    "iso:country":"CA",
    "sg:address":"71 Delta Park Blvd # 1",
    "sg:city":"Brampton",
    "sg:classifiers":[
        {
            "category":"Manufacturing",
            "subcategory":"Rubber & Plastics",
            "type":"Manufacturing & Wholesale Goods"
        }
    ],
    "sg:phone":"+1 905 792 5057",
    "sg:postcode":"L6T 5E7",
    "sg:province":"ON",
    "wof:name":"Deltaflex Plastics Inc",
    "wof:placetype":"venue"
},
  "geometry": {"coordinates":[-79.68737792970001,43.7396697998],"type":"Point"}
}