{
  "type": "Feature",
  "properties": {
    "addr:full":"11202 149 St NW Edmonton AB T5M 1W5",
    "addr:housenumber":"11202",
    "addr:postcode":"t5m 1w5",
    "addr:street":"149 St Nw",
    "iso:country":"CA",
    "sg:address":"11202 149 St NW",
    "sg:city":"Edmonton",
    "sg:classifiers":[
        {
            "category":"Manufacturing",
            "subcategory":"Tools & Machinery",
            "type":"Manufacturing & Wholesale Goods"
        }
    ],
    "sg:phone":"+1 780 447 4800",
    "sg:postcode":"T5M 1W5",
    "sg:province":"AB",
    "sg:tags":[
        "water",
        "equipment",
        "works",
        "valve"
    ],
    "wof:name":"Emco Waterworks",
    "wof:placetype":"venue"
},
  "geometry": {"coordinates":[-113.578262329,53.5608787537],"type":"Point"}
}