{
  "type": "Feature",
  "properties": {
    "iso:country":"CA",
    "sg:city":"Chesley",
    "sg:classifiers":[
        {
            "category":"Building & Trades",
            "subcategory":"Construction",
            "type":"Services"
        }
    ],
    "sg:phone":"+1 519 363 3811",
    "sg:postcode":"N0G 1L0",
    "sg:province":"ON",
    "sg:tags":[
        "paving",
        "contractor"
    ],
    "wof:name":"Multiple Enterprises Inc",
    "wof:placetype":"venue"
},
  "geometry": {"coordinates":[-81.096496582,44.3022766113],"type":"Point"}
}