{
  "type": "Feature",
  "properties": {
    "addr:full":"1377 Ch Mille Isles Mille-Isles QC J0R 1A0",
    "addr:housenumber":"1377",
    "addr:postcode":"j0r 1a0",
    "addr:street":"Ch Mille",
    "iso:country":"CA",
    "sg:address":"1377 Ch Mille Isles",
    "sg:city":"Mille-Isles",
    "sg:classifiers":[
        {
            "category":"Building & Trades",
            "subcategory":"Construction",
            "type":"Services"
        }
    ],
    "sg:phone":"+1 450 438 8087",
    "sg:postcode":"J0R 1A0",
    "sg:province":"QC",
    "sg:tags":[
        "builder",
        "gazebo"
    ],
    "wof:name":"Pavillon Jaro",
    "wof:placetype":"venue"
},
  "geometry": {"coordinates":[-74.231911,45.818958],"type":"Point"}
}