{
  "type": "Feature",
  "properties": {
    "addr:full":"Thornhill ON L4J 7X1",
    "addr:postcode":"l4j 7x1",
    "iso:country":"CA",
    "sg:city":"Thornhill",
    "sg:classifiers":[
        {
            "category":"Real Estate",
            "subcategory":"Real Estate Agent",
            "type":"Services"
        }
    ],
    "sg:phone":"+1 905 762 0505",
    "sg:postcode":"L4J 7X1",
    "sg:province":"ON",
    "sg:tags":[
        "management"
    ],
    "wof:name":"International Apartment Ltd",
    "wof:placetype":"venue"
},
  "geometry": {"coordinates":[-79.4218292236,43.804107666],"type":"Point"}
}