{
  "type": "Feature",
  "properties": {
    "addr:full":"277 Hutchings St Winnipeg MB R2X 2R4",
    "addr:housenumber":"277",
    "addr:postcode":"r2x 2r4",
    "addr:street":"Hutchings St",
    "iso:country":"CA",
    "sg:address":"277 Hutchings St",
    "sg:city":"Winnipeg",
    "sg:classifiers":[
        {
            "category":"Wholesale",
            "subcategory":"Groceries",
            "type":"Manufacturing & Wholesale Goods"
        }
    ],
    "sg:phone":"+1 204 477 0022",
    "sg:postcode":"R2X 2R4",
    "sg:province":"MB",
    "sg:tags":[
        "food",
        "grocer",
        "product"
    ],
    "wof:name":"Watkins Inc",
    "wof:placetype":"venue"
},
  "geometry": {"coordinates":[-97.179703,49.944271],"type":"Point"}
}