{
  "type": "Feature",
  "properties": {
    "addr:full":"220 Mcallister Dr Saint John NB E2J 2S7",
    "addr:housenumber":"220",
    "addr:postcode":"e2j 2s7",
    "addr:street":"Mcallister Dr",
    "iso:country":"CA",
    "sg:address":"220 Mcallister Dr",
    "sg:city":"Saint John",
    "sg:classifiers":[
        {
            "category":"Bars & Pubs",
            "type":"Food & Drink"
        }
    ],
    "sg:phone":"+1 506 696 3320",
    "sg:postcode":"E2J 2S7",
    "sg:province":"NB",
    "sg:tags":[
        "lounge",
        "cocktail"
    ],
    "wof:name":"Chuckles Lounge Inc",
    "wof:placetype":"venue"
},
  "geometry": {"coordinates":[-66.0217285156,45.3120956421],"type":"Point"}
}