{
  "type": "Feature",
  "properties": {
    "addr:full":"297 Knowlton Rd # C Knowlton QC J0E 1V0",
    "addr:housenumber":"297",
    "addr:postcode":"j0e 1v0",
    "addr:street":"Knowlton Rd # C Knowlton",
    "iso:country":"CA",
    "sg:address":"297 Knowlton Rd # C",
    "sg:city":"Knowlton",
    "sg:classifiers":[
        {
            "category":"Wholesale",
            "subcategory":"Apparel",
            "type":"Manufacturing & Wholesale Goods"
        }
    ],
    "sg:phone":"+1 450 242 2050",
    "sg:postcode":"J0E 1V0",
    "sg:province":"QC",
    "sg:tags":[
        "textile"
    ],
    "wof:name":"Sevantex Inc",
    "wof:placetype":"venue"
},
  "geometry": {"coordinates":[-72.51178741459999,45.2163848877],"type":"Point"}
}