{
  "type": "Feature",
  "properties": {
    "addr:full":"22270 North Ave Maple Ridge BC V2X 2L5",
    "addr:housenumber":"22270",
    "addr:postcode":"v2x 2l5",
    "addr:street":"North Ave",
    "iso:country":"CA",
    "sg:address":"22270 North Ave",
    "sg:city":"Maple Ridge",
    "sg:classifiers":[
        {
            "category":"Social Services",
            "type":"Services"
        }
    ],
    "sg:phone":"+1 604 463 6617",
    "sg:postcode":"V2X 2L5",
    "sg:province":"BC",
    "sg:tags":[
        "information",
        "organization",
        "treatment",
        "alcoholism",
        "welfare"
    ],
    "wof:name":"Alcohol Information & Rfrl",
    "wof:placetype":"venue"
},
  "geometry": {"coordinates":[-122.605293274,49.215839386],"type":"Point"}
}