{
  "type": "Feature",
  "properties": {
    "addr:full":"3050 Pharmacy Ave Scarborough ON M1W 2N7",
    "addr:housenumber":"3050",
    "addr:postcode":"m1w 2n7",
    "addr:street":"Pharmacy Ave",
    "iso:country":"CA",
    "sg:address":"3050 Pharmacy Ave",
    "sg:city":"Scarborough",
    "sg:classifiers":[
        {
            "category":"Real Estate",
            "subcategory":"Real Estate Operator",
            "type":"Services"
        }
    ],
    "sg:phone":"+1 416 497 3335",
    "sg:postcode":"M1W 2N7",
    "sg:province":"ON",
    "sg:tags":[
        "apartment"
    ],
    "wof:name":"Park Property Management Inc",
    "wof:placetype":"venue"
},
  "geometry": {"coordinates":[-79.32682800000001,43.795277],"type":"Point"}
}