{
  "type": "Feature",
  "properties": {
    "iso:country":"CA",
    "sg:address":"4625 Albert St # 4",
    "sg:city":"Regina",
    "sg:classifiers":[
        {
            "category":"Shopping",
            "subcategory":"Clothing, Apparel, & Fashions",
            "type":"Retail Goods"
        }
    ],
    "sg:phone":"+1 306 586 3140",
    "sg:postcode":"S4S 6B6",
    "sg:province":"SK",
    "sg:tags":[
        "tailor"
    ],
    "wof:name":"Venice Tailors",
    "wof:placetype":"venue"
},
  "geometry": {"coordinates":[-104.61734,50.405781],"type":"Point"}
}