{
  "type": "Feature",
  "properties": {
    "addr:full":"3 Watson Rd S # 2 Guelph ON N1L 1E3",
    "addr:housenumber":"3",
    "addr:postcode":"n1l 1e3",
    "addr:street":"Watson Rd S # 2",
    "iso:country":"CA",
    "sg:address":"3 Watson Rd S # 2",
    "sg:city":"Guelph",
    "sg:classifiers":[
        {
            "category":"Wholesale",
            "subcategory":"Electrical",
            "type":"Manufacturing & Wholesale Goods"
        }
    ],
    "sg:phone":"+1 519 763 4406",
    "sg:postcode":"N1L 1E3",
    "sg:province":"ON",
    "sg:tags":[
        "equipment",
        "electronic",
        "supply"
    ],
    "wof:name":"Norgay Enterprises Ltd",
    "wof:placetype":"venue"
},
  "geometry": {"coordinates":[-80.2057723999,43.5645980835],"type":"Point"}
}