{
  "type": "Feature",
  "properties": {
    "addr:full":"6075 Kingston Rd Scarborough ON M1C 1K5",
    "addr:housenumber":"6075",
    "addr:postcode":"m1c 1k5",
    "addr:street":"Kingston Rd",
    "iso:country":"CA",
    "sg:address":"6075 Kingston Rd",
    "sg:city":"Scarborough",
    "sg:classifiers":[
        {
            "category":"Recreation",
            "type":"Entertainment"
        }
    ],
    "sg:phone":"+1 416 284 0746",
    "sg:postcode":"M1C 1K5",
    "sg:province":"ON",
    "sg:tags":[
        "paint",
        "game",
        "ball",
        "sport"
    ],
    "wof:name":"Premium Paintball Products",
    "wof:placetype":"venue"
},
  "geometry": {"coordinates":[-79.1691741943,43.7834663391],"type":"Point"}
}