{
  "type": "Feature",
  "properties": {
    "addr:full":"307 Highway 140 Welland ON L3B 5N7",
    "addr:housenumber":"307",
    "addr:postcode":"l3b 5n7",
    "addr:street":"Highway 140",
    "iso:country":"CA",
    "sg:address":"307 Highway 140",
    "sg:city":"Welland",
    "sg:classifiers":[
        {
            "category":"Freight",
            "type":"Transportation"
        }
    ],
    "sg:phone":"+1 905 732 4757",
    "sg:postcode":"L3B 5N7",
    "sg:province":"ON",
    "sg:tags":[
        "commercial",
        "storage"
    ],
    "wof:name":"Bronco Mini Storage Ltd",
    "wof:placetype":"venue"
},
  "geometry": {"coordinates":[-79.239243,42.99345],"type":"Point"}
}