{
  "type": "Feature",
  "properties": {
    "iso:country":"CA",
    "sg:address":"95 First St",
    "sg:city":"Orangeville",
    "sg:classifiers":[
        {
            "category":"Personal",
            "subcategory":"Tanning Parlor",
            "type":"Services"
        }
    ],
    "sg:phone":"+1 519 940 9377",
    "sg:postcode":"L9W 2E8",
    "sg:province":"ON",
    "sg:tags":[
        "salon"
    ],
    "wof:name":"Fabutan",
    "wof:placetype":"venue"
},
  "geometry": {"coordinates":[-80.09982299799999,43.9294433594],"type":"Point"}
}