{
  "type": "Feature",
  "properties": {
    "addr:full":"110 King St Nobleford AB T0L 1S0",
    "addr:housenumber":"110",
    "addr:postcode":"t0l 1s0",
    "addr:street":"King St",
    "iso:country":"CA",
    "sg:address":"110 King St",
    "sg:city":"Nobleford",
    "sg:classifiers":[
        {
            "category":"Food & Beverages",
            "subcategory":"Groceries & Convenience Stores",
            "type":"Retail Goods"
        }
    ],
    "sg:phone":"+1 403 824 3372",
    "sg:postcode":"T0L 1S0",
    "sg:province":"AB",
    "sg:tags":[
        "grocer"
    ],
    "wof:name":"Nobleford Food Market",
    "wof:placetype":"venue"
},
  "geometry": {"coordinates":[-113.056938,49.881592],"type":"Point"}
}