{
  "type": "Feature",
  "properties": {
    "addr:full":"1511 Cheadle St W Swift Current SK S9H 5G4",
    "addr:housenumber":"1511",
    "addr:postcode":"s9h 5g4",
    "addr:street":"Cheadle St W",
    "iso:country":"CA",
    "sg:address":"1511 Cheadle St W",
    "sg:city":"Swift Current",
    "sg:classifiers":[
        {
            "category":"Retail",
            "subcategory":"Auto Repair",
            "type":"Services"
        }
    ],
    "sg:phone":"+1 306 773 7293",
    "sg:postcode":"S9H 5G4",
    "sg:province":"SK",
    "sg:tags":[
        "lining",
        "brake"
    ],
    "wof:name":"Brake & Drive Systems SC",
    "wof:placetype":"venue"
},
  "geometry": {"coordinates":[-107.820915,50.283619],"type":"Point"}
}