{
  "type": "Feature",
  "properties": {
    "addr:full":"2859 Lake Shore Blvd W Etobicoke ON M8V 1H8",
    "addr:housenumber":"2859",
    "addr:postcode":"m8v 1h8",
    "addr:street":"Lake Shore Blvd W",
    "iso:country":"CA",
    "sg:address":"2859 Lake Shore Blvd W",
    "sg:city":"Etobicoke",
    "sg:classifiers":[
        {
            "category":"Personal",
            "subcategory":"Beauty Salon",
            "type":"Services"
        }
    ],
    "sg:phone":"+1 416 503 4275",
    "sg:postcode":"M8V 1H8",
    "sg:province":"ON",
    "wof:name":"Ingrid's Hair Salon",
    "wof:placetype":"venue"
},
  "geometry": {"coordinates":[-79.50238800050001,43.601272583],"type":"Point"}
}