{
  "type": "Feature",
  "properties": {
    "addr:full":"700 Ch Bord Du Lac Dorval QC H9S 2B8",
    "addr:housenumber":"700",
    "addr:postcode":"h9s 2b8",
    "addr:street":"Ch Bord Du Lac",
    "iso:country":"CA",
    "sg:address":"700 Ch Bord Du Lac",
    "sg:city":"Dorval",
    "sg:classifiers":[
        {
            "category":"Wholesale",
            "subcategory":"Groceries",
            "type":"Manufacturing & Wholesale Goods"
        }
    ],
    "sg:phone":"+1 514 631 2795",
    "sg:postcode":"H9S 2B8",
    "sg:province":"QC",
    "sg:tags":[
        "food",
        "broker"
    ],
    "wof:name":"Madison Avenue Retail Brands",
    "wof:placetype":"venue"
},
  "geometry": {"coordinates":[-73.7368011475,45.4391365051],"type":"Point"}
}