{
  "type": "Feature",
  "properties": {
    "addr:full":"Edmonton AB T5R 1W2",
    "addr:postcode":"t5r 1w2",
    "iso:country":"CA",
    "sg:city":"Edmonton",
    "sg:classifiers":[
        {
            "category":"Health Services",
            "subcategory":"Health Practitioner",
            "type":"Services"
        }
    ],
    "sg:phone":"+1 780 448 0880",
    "sg:postcode":"T5R 1W2",
    "sg:province":"AB",
    "sg:tags":[
        "therapist",
        "physical"
    ],
    "wof:name":"Shular, Mara",
    "wof:placetype":"venue"
},
  "geometry": {"coordinates":[-113.58880600000001,53.51981],"type":"Point"}
}