{
  "type": "Feature",
  "properties": {
    "addr:full":"10 Scarlett Rd York ON M6N 4J6",
    "addr:housenumber":"10",
    "addr:postcode":"m6n 4j6",
    "addr:street":"Scarlett Rd",
    "iso:country":"CA",
    "sg:address":"10 Scarlett Rd",
    "sg:city":"York",
    "sg:classifiers":[
        {
            "category":"Manufacturing",
            "subcategory":"Signs",
            "type":"Manufacturing & Wholesale Goods"
        }
    ],
    "sg:phone":"+1 416 767 4841",
    "sg:postcode":"M6N 4J6",
    "sg:province":"ON",
    "wof:name":"James Signs",
    "wof:placetype":"venue"
},
  "geometry": {"coordinates":[-79.4995422363,43.6664657593],"type":"Point"}
}