{
  "type": "Feature",
  "properties": {
    "addr:full":"312 Broadview Ave Toronto ON M4M 2G9",
    "addr:housenumber":"312",
    "addr:postcode":"m4m 2g9",
    "addr:street":"Broadview Ave",
    "iso:country":"CA",
    "sg:address":"312 Broadview Ave",
    "sg:city":"Toronto",
    "sg:classifiers":[
        {
            "category":"Social Services",
            "type":"Services"
        }
    ],
    "sg:phone":"+1 416 465 6970",
    "sg:postcode":"M4M 2G9",
    "sg:province":"ON",
    "sg:tags":[
        "organization",
        "welfare"
    ],
    "wof:name":"Salvation Army",
    "wof:placetype":"venue"
},
  "geometry": {"coordinates":[-79.3523178101,43.6642799377],"type":"Point"}
}