{
  "type": "Feature",
  "properties": {
    "addr:full":"1880 Eglinton Ave E Scarborough ON M1L 2L1",
    "addr:housenumber":"1880",
    "addr:postcode":"m1l 2l1",
    "addr:street":"Eglinton Ave E",
    "iso:country":"CA",
    "sg:address":"1880 Eglinton Ave E",
    "sg:city":"Scarborough",
    "sg:classifiers":[
        {
            "category":"Professional",
            "subcategory":"Accounting & Tax Preparation",
            "type":"Services"
        }
    ],
    "sg:phone":"+1 416 773 1999",
    "sg:postcode":"M1L 2L1",
    "sg:province":"ON",
    "sg:tags":[
        "accountant"
    ],
    "wof:name":"Softron Tax",
    "wof:placetype":"venue"
},
  "geometry": {"coordinates":[-79.30052185060001,43.7252197266],"type":"Point"}
}