{
  "type": "Feature",
  "properties": {
    "addr:full":"213 Herring Cove Rd Halifax NS B3P 1L1",
    "addr:housenumber":"213",
    "addr:postcode":"b3p 1l1",
    "addr:street":"Herring Cove Rd",
    "iso:country":"CA",
    "sg:address":"213 Herring Cove Rd",
    "sg:city":"Halifax",
    "sg:classifiers":[
        {
            "category":"Food & Beverages",
            "subcategory":"Groceries & Convenience Stores",
            "type":"Retail Goods"
        }
    ],
    "sg:phone":"+1 902 477 9966",
    "sg:postcode":"B3P 1L1",
    "sg:province":"NS",
    "sg:tags":[
        "grocer"
    ],
    "wof:name":"Spryfield Discount Meat Market",
    "wof:placetype":"venue"
},
  "geometry": {"coordinates":[-63.617954,44.623127],"type":"Point"}
}