{
  "type": "Feature",
  "properties": {
    "iso:country":"CA",
    "sg:address":"19 Rue Gareapy",
    "sg:city":"LA Patrie",
    "sg:classifiers":[
        {
            "category":"Retail",
            "subcategory":"Auto Repair",
            "type":"Services"
        }
    ],
    "sg:phone":"+1 819 888 2208",
    "sg:postcode":"J0B 1Y0",
    "sg:province":"QC",
    "sg:tags":[
        "repairing",
        "automobile"
    ],
    "wof:name":"Garage Charles Verret Enrg",
    "wof:placetype":"venue"
},
  "geometry": {"coordinates":[-71.25141143800001,45.4025993347],"type":"Point"}
}