{
  "type": "Feature",
  "properties": {
    "addr:full":"580 Rue Principale #225 Lachute QC J8H 1Y7",
    "addr:housenumber":"580",
    "addr:postcode":"j8h 1y7",
    "addr:street":"Rue Principale # 225",
    "iso:country":"CA",
    "sg:address":"580 Rue Principale #225",
    "sg:city":"Lachute",
    "sg:classifiers":[
        {
            "category":"Organizations",
            "subcategory":"Professional Association",
            "type":"Services"
        }
    ],
    "sg:phone":"+1 450 562 1947",
    "sg:postcode":"J8H 1Y7",
    "sg:province":"QC",
    "wof:name":"Chambre Commerce DE Lachute",
    "wof:placetype":"venue"
},
  "geometry": {"coordinates":[-74.332787,45.657078],"type":"Point"}
}