{
  "type": "Feature",
  "properties": {
    "addr:full":"400 Boul Industriel Asbestos QC J1T 4T7",
    "addr:housenumber":"400",
    "addr:postcode":"j1t 4t7",
    "addr:street":"Boul Industriel",
    "iso:country":"CA",
    "sg:address":"400 Boul Industriel",
    "sg:city":"Asbestos",
    "sg:classifiers":[
        {
            "category":"Building & Trades",
            "subcategory":"Construction",
            "type":"Services"
        }
    ],
    "sg:phone":"+1 819 758 6431",
    "sg:postcode":"J1T 4T7",
    "sg:province":"QC",
    "sg:tags":[
        "excavating",
        "contractor"
    ],
    "wof:name":"Excavations Marchand & Fils",
    "wof:placetype":"venue"
},
  "geometry": {"coordinates":[-71.943871,45.767319],"type":"Point"}
}