{
  "type": "Feature",
  "properties": {
    "iso:country":"CA",
    "sg:address":"1595 16th St E",
    "sg:city":"Owen Sound",
    "sg:classifiers":[
        {
            "category":"Personal",
            "subcategory":"Beauty Salon",
            "type":"Services"
        }
    ],
    "sg:phone":"+1 519 371 0918",
    "sg:postcode":"N4K 5N3",
    "sg:province":"ON",
    "wof:name":"First Choice Haircutters",
    "wof:placetype":"venue"
},
  "geometry": {"coordinates":[-80.9184951782,44.5744094849],"type":"Point"}
}