{
  "type": "Feature",
  "properties": {
    "addr:full":"6910 71 St NW Edmonton AB T6B 2M4",
    "addr:housenumber":"6910",
    "addr:postcode":"t6b 2m4",
    "addr:street":"71 St Nw",
    "iso:country":"CA",
    "sg:address":"6910 71 St NW",
    "sg:city":"Edmonton",
    "sg:classifiers":[
        {
            "category":"Manufacturing",
            "subcategory":"Metals",
            "type":"Manufacturing & Wholesale Goods"
        }
    ],
    "sg:phone":"+1 780 465 9730",
    "sg:postcode":"T6B 2M4",
    "sg:province":"AB",
    "sg:tags":[
        "steel"
    ],
    "wof:name":"Rampart Steel Ltd",
    "wof:placetype":"venue"
},
  "geometry": {"coordinates":[-113.43674469,53.50573349],"type":"Point"}
}