{
  "type": "Feature",
  "properties": {
    "addr:full":"344 Ridge Rd N Ridgeway ON L0S 1N0",
    "addr:housenumber":"344",
    "addr:postcode":"l0s 1n0",
    "addr:street":"Ridge Rd N",
    "iso:country":"CA",
    "sg:address":"344 Ridge Rd N",
    "sg:city":"Ridgeway",
    "sg:classifiers":[
        {
            "category":"Communications",
            "subcategory":"Film & Video Production",
            "type":"Services"
        }
    ],
    "sg:phone":"+1 905 894 6212",
    "sg:postcode":"L0S 1N0",
    "sg:province":"ON",
    "sg:tags":[
        "taping"
    ],
    "wof:name":"Pacific Productions Intl",
    "wof:placetype":"venue"
},
  "geometry": {"coordinates":[-79.0518035889,42.8842353821],"type":"Point"}
}