{
  "type": "Feature",
  "properties": {
    "iso:country":"CA",
    "sg:address":"1217 Rue Bishop",
    "sg:city":"Montreal",
    "sg:classifiers":[
        {
            "category":"Parking",
            "type":"Transportation"
        }
    ],
    "sg:phone":"+1 514 393 0808",
    "sg:postcode":"H3G 2E2",
    "sg:province":"QC",
    "sg:tags":[
        "garage",
        "marking",
        "maintenance"
    ],
    "wof:name":"B Crescent Parking",
    "wof:placetype":"venue"
},
  "geometry": {"coordinates":[-73.575035,45.496113],"type":"Point"}
}