{
  "type": "Feature",
  "properties": {
    "addr:full":"140 Albany Ave Toronto ON M5R 3C4",
    "addr:housenumber":"140",
    "addr:postcode":"m5r 3c4",
    "addr:street":"Albany Ave",
    "iso:country":"CA",
    "sg:address":"140 Albany Ave",
    "sg:city":"Toronto",
    "sg:classifiers":[
        {
            "category":"Health Services",
            "subcategory":"Health Practitioner",
            "type":"Services"
        }
    ],
    "sg:phone":"+1 416 535 9432",
    "sg:postcode":"M5R 3C4",
    "sg:province":"ON",
    "sg:tags":[
        "psychologist"
    ],
    "wof:name":"White, Heather A PhD",
    "wof:placetype":"venue"
},
  "geometry": {"coordinates":[-79.411919,43.669811],"type":"Point"}
}