{
  "type": "Feature",
  "properties": {
    "addr:full":"2100 Richmond St Windsor ON N8Y 1L4",
    "addr:housenumber":"2100",
    "addr:postcode":"n8y 1l4",
    "addr:street":"Richmond St",
    "iso:country":"CA",
    "sg:address":"2100 Richmond St",
    "sg:city":"Windsor",
    "sg:classifiers":[
        {
            "category":"Education",
            "subcategory":"School",
            "type":"Public Place"
        }
    ],
    "sg:phone":"+1 519 252 6514",
    "sg:postcode":"N8Y 1L4",
    "sg:province":"ON",
    "wof:name":"Walkerville Public Secondary",
    "wof:placetype":"venue"
},
  "geometry": {"coordinates":[-83.006683,42.316902],"type":"Point"}
}