{
  "type": "Feature",
  "properties": {
    "addr:full":"305 Boul Marc-Aurele-Fortin Laval QC H7L 2A3",
    "addr:housenumber":"305",
    "addr:postcode":"h7l 2a3",
    "addr:street":"Boul Marc-Aurele-Fortin",
    "iso:country":"CA",
    "sg:address":"305 Boul Marc-Aurele-Fortin",
    "sg:city":"Laval",
    "sg:classifiers":[
        {
            "category":"Banks & Credit Unions",
            "subcategory":"Financial Services",
            "type":"Services"
        }
    ],
    "sg:phone":"+1 450 622 4833",
    "sg:postcode":"H7L 2A3",
    "sg:province":"QC",
    "sg:tags":[
        "franchising"
    ],
    "wof:name":"Franchises Panda Ltee",
    "wof:placetype":"venue"
},
  "geometry": {"coordinates":[-73.79177900000001,45.60553],"type":"Point"}
}