{
  "type": "Feature",
  "properties": {
    "iso:country":"CA",
    "sg:address":"4862 Ch DE LA Cote-Des-Neiges #11",
    "sg:city":"Montreal",
    "sg:classifiers":[
        {
            "category":"Food & Beverages",
            "subcategory":"Groceries & Convenience Stores",
            "type":"Retail Goods"
        }
    ],
    "sg:phone":"+1 514 735 6377",
    "sg:postcode":"H3V 1G9",
    "sg:province":"QC",
    "sg:tags":[
        "grocer"
    ],
    "wof:name":"Nouveau Marche Rockhill",
    "wof:placetype":"venue"
},
  "geometry": {"coordinates":[-73.6142883301,45.4951896667],"type":"Point"}
}