{
  "type": "Feature",
  "properties": {
    "addr:full":"810 Mcquay Blvd Whitby ON L1P 1J1",
    "addr:housenumber":"810",
    "addr:postcode":"l1p 1j1",
    "addr:street":"Mcquay Blvd",
    "iso:country":"CA",
    "sg:address":"810 Mcquay Blvd",
    "sg:city":"Whitby",
    "sg:classifiers":[
        {
            "category":"Education",
            "subcategory":"School",
            "type":"Public Place"
        }
    ],
    "sg:phone":"+1 905 666 3901",
    "sg:postcode":"L1P 1J1",
    "sg:province":"ON",
    "wof:name":"Colonel Je Farewell Pub Schl",
    "wof:placetype":"venue"
},
  "geometry": {"coordinates":[-78.96946,43.886898],"type":"Point"}
}