{
  "type": "Feature",
  "properties": {
    "iso:country":"CA",
    "sg:address":"321 Rue Sainte-Marguerite",
    "sg:city":"Montreal",
    "sg:classifiers":[
        {
            "category":"Food & Beverages",
            "subcategory":"Groceries & Convenience Stores",
            "type":"Retail Goods"
        }
    ],
    "sg:phone":"+1 514 933 6540",
    "sg:postcode":"H4C 2W9",
    "sg:province":"QC",
    "sg:tags":[
        "grocer"
    ],
    "wof:name":"Depanneur Laurion",
    "wof:placetype":"venue"
},
  "geometry": {"coordinates":[-73.58545684809999,45.4749832153],"type":"Point"}
}