{
  "type": "Feature",
  "properties": {
    "addr:full":"20 Cranston Park Ave # 8 Maple ON L6A 2W2",
    "addr:housenumber":"20",
    "addr:postcode":"l6a 2w2",
    "addr:street":"Cranston Park Ave # 8",
    "iso:country":"CA",
    "sg:address":"20 Cranston Park Ave # 8",
    "sg:city":"Maple",
    "sg:classifiers":[
        {
            "category":"Retail",
            "subcategory":"Laundry & Dry Cleaning",
            "type":"Services"
        }
    ],
    "sg:phone":"+1 905 303 9949",
    "sg:postcode":"L6A 2W2",
    "sg:province":"ON",
    "sg:tags":[
        "cleaners"
    ],
    "wof:name":"Panetta Express Cleaners",
    "wof:placetype":"venue"
},
  "geometry": {"coordinates":[-79.524101,43.858852],"type":"Point"}
}