{
  "type": "Feature",
  "properties": {
    "iso:country":"CA",
    "sg:address":"4571 Marine Ave",
    "sg:city":"Powell River",
    "sg:classifiers":[
        {
            "category":"Professional",
            "subcategory":"Lawyer & Legal Services",
            "type":"Services"
        }
    ],
    "sg:phone":"+1 604 485 2771",
    "sg:postcode":"V8A 2K5",
    "sg:province":"BC",
    "sg:tags":[
        "attorney"
    ],
    "wof:name":"Giroday, Shirley E",
    "wof:placetype":"venue"
},
  "geometry": {"coordinates":[-124.52819061300001,49.839389801],"type":"Point"}
}