{
  "type": "Feature",
  "properties": {
    "addr:full":"Mississauga ON L4W 1V7",
    "addr:postcode":"l4w 1v7",
    "iso:country":"CA",
    "sg:city":"Mississauga",
    "sg:classifiers":[
        {
            "category":"Manufacturing",
            "subcategory":"Tools & Machinery",
            "type":"Manufacturing & Wholesale Goods"
        }
    ],
    "sg:phone":"+1 416 414 9088",
    "sg:postcode":"L4W 1V7",
    "sg:province":"ON",
    "sg:tags":[
        "machine",
        "duplicating",
        "copying"
    ],
    "wof:name":"Copytek",
    "wof:placetype":"venue"
},
  "geometry": {"coordinates":[-79.6159210205,43.6319351196],"type":"Point"}
}