{
  "type": "Feature",
  "properties": {
    "addr:full":"12823 20th Ave Blairmore AB T0K 0E0",
    "addr:housenumber":"12823",
    "addr:postcode":"t0k 0e0",
    "addr:street":"20Th Ave",
    "iso:country":"CA",
    "sg:address":"12823 20th Ave",
    "sg:city":"Blairmore",
    "sg:classifiers":[
        {
            "category":"Home & Garden",
            "subcategory":"Hardware",
            "type":"Retail Goods"
        }
    ],
    "sg:phone":"+1 403 562 8844",
    "sg:postcode":"T0K 0E0",
    "sg:province":"AB",
    "wof:name":"Allied True Value Hardware",
    "wof:placetype":"venue"
},
  "geometry": {"coordinates":[-114.43942300000001,49.608089],"type":"Point"}
}