{
  "type": "Feature",
  "properties": {
    "addr:full":"Rougemont QC J0L 1M0",
    "addr:postcode":"j0l 1m0",
    "iso:country":"CA",
    "sg:city":"Rougemont",
    "sg:classifiers":[
        {
            "category":"Manufacturing",
            "subcategory":"Food",
            "type":"Manufacturing & Wholesale Goods"
        }
    ],
    "sg:phone":"+1 450 469 3104",
    "sg:postcode":"J0L 1M0",
    "sg:province":"QC",
    "sg:tags":[
        "winery"
    ],
    "wof:name":"Cellier A Vin",
    "wof:placetype":"venue"
},
  "geometry": {"coordinates":[-73.0813903809,45.4413833618],"type":"Point"}
}