{
  "type": "Feature",
  "properties": {
    "addr:full":"41 Union St Grand Falls-Windsor NL A2A 2C9",
    "addr:housenumber":"41",
    "addr:postcode":"a2a 2c9",
    "addr:street":"Union St",
    "iso:country":"CA",
    "sg:address":"41 Union St",
    "sg:city":"Grand Falls-Windsor",
    "sg:classifiers":[
        {
            "category":"Autos & Motor Vehicles",
            "subcategory":"Fuel & Gas Station",
            "type":"Retail Goods"
        }
    ],
    "sg:phone":"+1 709 489 8812",
    "sg:postcode":"A2A 2C9",
    "sg:province":"NL",
    "sg:tags":[
        "oil"
    ],
    "wof:name":"Ultramar Central Pipeline",
    "wof:placetype":"venue"
},
  "geometry": {"coordinates":[-55.6481895447,48.9327583313],"type":"Point"}
}