{
  "type": "Feature",
  "properties": {
    "addr:full":"Dollard-Des-Ormeaux QC H9B 1Z8",
    "addr:postcode":"h9b 1z8",
    "iso:country":"CA",
    "sg:city":"Dollard-Des-Ormeaux",
    "sg:classifiers":[
        {
            "category":"Restaurant",
            "type":"Food & Drink"
        }
    ],
    "sg:phone":"+1 514 421 0783",
    "sg:postcode":"H9B 1Z8",
    "sg:province":"QC",
    "wof:name":"Chez Cora Dejeuners",
    "wof:placetype":"venue"
},
  "geometry": {"coordinates":[-73.7961196899,45.4837226868],"type":"Point"}
}