{
  "type": "Feature",
  "properties": {
    "addr:full":"38 Hirons St Toronto ON M6N 1E3",
    "addr:housenumber":"38",
    "addr:postcode":"m6n 1e3",
    "addr:street":"Hirons St",
    "iso:country":"CA",
    "sg:address":"38 Hirons St",
    "sg:city":"Toronto",
    "sg:classifiers":[
        {
            "category":"Retail",
            "subcategory":"Auto Repair",
            "type":"Services"
        }
    ],
    "sg:phone":"+1 416 762 7579",
    "sg:postcode":"M6N 1E3",
    "sg:province":"ON",
    "sg:tags":[
        "repairing",
        "automobile",
        "radiator"
    ],
    "wof:name":"Dominion Auto Radiator Svc",
    "wof:placetype":"venue"
},
  "geometry": {"coordinates":[-79.465431,43.669861],"type":"Point"}
}