{
  "type": "Feature",
  "properties": {
    "iso:country":"CA",
    "sg:address":"8350 Boul Saint-Laurent",
    "sg:city":"Montreal",
    "sg:classifiers":[
        {
            "category":"Professional",
            "subcategory":"Management & Consulting",
            "type":"Services"
        }
    ],
    "sg:phone":"+1 514 382 9670",
    "sg:postcode":"H2P 2M3",
    "sg:province":"QC",
    "sg:tags":[
        "consultant",
        "business"
    ],
    "wof:name":"Gestion Trivium Inc",
    "wof:placetype":"venue"
},
  "geometry": {"coordinates":[-73.6355209351,45.539932251],"type":"Point"}
}