{
  "type": "Feature",
  "properties": {
    "addr:full":"8492 Henderson Hwy Selkirk MB R1A 2A8",
    "addr:housenumber":"8492",
    "addr:postcode":"r1a 2a8",
    "addr:street":"Henderson Hwy",
    "iso:country":"CA",
    "sg:address":"8492 Henderson Hwy",
    "sg:city":"Selkirk",
    "sg:classifiers":[
        {
            "category":"Wholesale",
            "subcategory":"Fruits & Vegetables",
            "type":"Manufacturing & Wholesale Goods"
        }
    ],
    "sg:phone":"+1 204 757 2020",
    "sg:postcode":"R1A 2A8",
    "sg:province":"MB",
    "sg:tags":[
        "shipper"
    ],
    "wof:name":"Strawberry Patch",
    "wof:placetype":"venue"
},
  "geometry": {"coordinates":[-96.8705062866,50.142288208],"type":"Point"}
}