{
  "type": "Feature",
  "properties": {
    "iso:country":"CA",
    "sg:address":"134 Main St S",
    "sg:city":"Exeter",
    "sg:classifiers":[
        {
            "category":"Restaurant",
            "type":"Food & Drink"
        }
    ],
    "sg:phone":"+1 519 235 4623",
    "sg:postcode":"N0M 1S1",
    "sg:province":"ON",
    "wof:name":"Huron Family Restaurant",
    "wof:placetype":"venue"
},
  "geometry": {"coordinates":[-81.48155975340001,43.3529930115],"type":"Point"}
}