{
  "type": "Feature",
  "properties": {
    "addr:full":"Windham Centre ON N0E 2A0",
    "addr:postcode":"n0e 2a0",
    "addr:street":"Windham",
    "iso:country":"CA",
    "sg:city":"Windham Centre",
    "sg:classifiers":[
        {
            "category":"Education",
            "subcategory":"School",
            "type":"Public Place"
        }
    ],
    "sg:phone":"+1 519 443 8474",
    "sg:postcode":"N0E 2A0",
    "sg:province":"ON",
    "wof:name":"Windham Central School",
    "wof:placetype":"venue"
},
  "geometry": {"coordinates":[-80.421066,42.915272],"type":"Point"}
}