{
  "type": "Feature",
  "properties": {
    "addr:full":"450 Dundas St W Toronto ON M5T 1G7",
    "addr:housenumber":"450",
    "addr:postcode":"m5t 1g7",
    "addr:street":"Dundas St W",
    "iso:country":"CA",
    "sg:address":"450 Dundas St W",
    "sg:city":"Toronto",
    "sg:classifiers":[
        {
            "category":"Organizations",
            "subcategory":"Religious Organization",
            "type":"Services"
        }
    ],
    "sg:phone":"+1 416 977 2530",
    "sg:postcode":"M5T 1G7",
    "sg:province":"ON",
    "sg:tags":[
        "church"
    ],
    "wof:name":"Chinese Gospel Church",
    "wof:placetype":"venue"
},
  "geometry": {"coordinates":[-79.39598846440001,43.6534805298],"type":"Point"}
}