{
  "type": "Feature",
  "properties": {
    "iso:country":"CA",
    "sg:address":"143 Main St N",
    "sg:city":"Bobcaygeon",
    "sg:classifiers":[
        {
            "category":"Building & Trades",
            "subcategory":"Construction",
            "type":"Services"
        }
    ],
    "sg:phone":"+1 705 738 3515",
    "sg:postcode":"K0M 1A0",
    "sg:province":"ON",
    "sg:tags":[
        "general",
        "contractor"
    ],
    "wof:name":"Frank B Partridge Construction",
    "wof:placetype":"venue"
},
  "geometry": {"coordinates":[-78.5440444946,44.5439453125],"type":"Point"}
}