{
  "type": "Feature",
  "properties": {
    "addr:full":"20 Cleopatra Dr Nepean ON K2G 0B3",
    "addr:housenumber":"20",
    "addr:postcode":"k2g 0b3",
    "addr:street":"Cleopatra Dr",
    "iso:country":"CA",
    "sg:address":"20 Cleopatra Dr",
    "sg:city":"Nepean",
    "sg:classifiers":[
        {
            "category":"Professional",
            "subcategory":"Detective & Security Services",
            "type":"Services"
        }
    ],
    "sg:phone":"+1 613 228 2813",
    "sg:postcode":"K2G 0B3",
    "sg:province":"ON",
    "sg:tags":[
        "guard",
        "patrol"
    ],
    "wof:name":"Iron Horse Investigations",
    "wof:placetype":"venue"
},
  "geometry": {"coordinates":[-75.7225265503,45.3262290955],"type":"Point"}
}