{
  "type": "Feature",
  "properties": {
    "addr:full":"460 St Laurent Blvd Ottawa ON K1K 2Z6",
    "addr:housenumber":"460",
    "addr:postcode":"k1k 2z6",
    "addr:street":"St Laurent Blvd",
    "iso:country":"CA",
    "sg:address":"460 St Laurent Blvd",
    "sg:city":"Ottawa",
    "sg:classifiers":[
        {
            "category":"Retail",
            "subcategory":"Auto Repair",
            "type":"Services"
        }
    ],
    "sg:phone":"+1 613 745 9668",
    "sg:postcode":"K1K 2Z6",
    "sg:province":"ON",
    "sg:tags":[
        "repairing",
        "automobile"
    ],
    "wof:name":"John's Sunoco",
    "wof:placetype":"venue"
},
  "geometry": {"coordinates":[-75.649307251,45.4449539185],"type":"Point"}
}