{
  "type": "Feature",
  "properties": {
    "addr:full":"5120 51 Ave Ponoka AB T4J 1R7",
    "addr:housenumber":"5120",
    "addr:postcode":"t4j 1r7",
    "addr:street":"51 Ave",
    "iso:country":"CA",
    "sg:address":"5120 51 Ave",
    "sg:city":"Ponoka",
    "sg:classifiers":[
        {
            "category":"Health Services",
            "subcategory":"Optometrist",
            "type":"Services"
        }
    ],
    "sg:phone":"+1 403 783 5575",
    "sg:postcode":"T4J 1R7",
    "sg:province":"AB",
    "wof:name":"Wilson, Perry G OD",
    "wof:placetype":"venue"
},
  "geometry": {"coordinates":[-113.578484,52.677746],"type":"Point"}
}