{
  "type": "Feature",
  "properties": {
    "addr:full":"3976 West Graham Pl London ON N6P 1G4",
    "addr:housenumber":"3976",
    "addr:postcode":"n6p 1g4",
    "addr:street":"West Graham Pl",
    "iso:country":"CA",
    "sg:address":"3976 West Graham Pl",
    "sg:city":"London",
    "sg:classifiers":[
        {
            "category":"Building & Trades",
            "subcategory":"Cleaning & Sanitation",
            "type":"Services"
        }
    ],
    "sg:phone":"+1 519 652 1223",
    "sg:postcode":"N6P 1G4",
    "sg:province":"ON",
    "sg:tags":[
        "maintenance"
    ],
    "wof:name":"Aqua Clean Restoration Svc",
    "wof:placetype":"venue"
},
  "geometry": {"coordinates":[-81.3210144043,42.9175643921],"type":"Point"}
}