{
  "type": "Feature",
  "properties": {
    "iso:country":"CA",
    "sg:address":"1333 Rose St",
    "sg:city":"Regina",
    "sg:classifiers":[
        {
            "category":"Building & Trades",
            "subcategory":"Construction",
            "type":"Services"
        }
    ],
    "sg:phone":"+1 306 525 3701",
    "sg:postcode":"S4R 1Z7",
    "sg:province":"SK",
    "sg:tags":[
        "maker",
        "cabinet"
    ],
    "wof:name":"Supreme Kitchens & Millwork",
    "wof:placetype":"venue"
},
  "geometry": {"coordinates":[-104.607711792,50.4577331543],"type":"Point"}
}