{
  "type": "Feature",
  "properties": {
    "addr:full":"343 Main St Cardston AB T0K 0K0",
    "addr:housenumber":"343",
    "addr:postcode":"t0k 0k0",
    "addr:street":"Main St",
    "iso:country":"CA",
    "sg:address":"343 Main St",
    "sg:city":"Cardston",
    "sg:classifiers":[
        {
            "category":"Shopping",
            "subcategory":"Bicycles & Sporting Goods",
            "type":"Retail Goods"
        }
    ],
    "sg:phone":"+1 403 653 2600",
    "sg:postcode":"T0K 0K0",
    "sg:province":"AB",
    "wof:name":"Pro Shop",
    "wof:placetype":"venue"
},
  "geometry": {"coordinates":[-113.301903,49.197979],"type":"Point"}
}