{
  "type": "Feature",
  "properties": {
    "addr:full":"Edmonton AB T6G 2N2",
    "addr:postcode":"t6g 2n2",
    "iso:country":"CA",
    "sg:city":"Edmonton",
    "sg:classifiers":[
        {
            "category":"Bars & Pubs",
            "type":"Food & Drink"
        }
    ],
    "sg:phone":"+1 780 492 3101",
    "sg:postcode":"T6G 2N2",
    "sg:province":"AB",
    "sg:tags":[
        "club",
        "night"
    ],
    "wof:name":"Power Plant Bar & Restaurant",
    "wof:placetype":"venue"
},
  "geometry": {"coordinates":[-113.49443100000001,53.511131],"type":"Point"}
}