{
  "type": "Feature",
  "properties": {
    "addr:full":"591 Brennan Rd Sudbury ON P3C 5L6",
    "addr:housenumber":"591",
    "addr:postcode":"p3c 5l6",
    "addr:street":"Brennan Rd",
    "iso:country":"CA",
    "sg:address":"591 Brennan Rd",
    "sg:city":"Sudbury",
    "sg:classifiers":[
        {
            "category":"Organizations",
            "subcategory":"Religious Organization",
            "type":"Services"
        }
    ],
    "sg:phone":"+1 705 673 1774",
    "sg:postcode":"P3C 5L6",
    "sg:province":"ON",
    "sg:tags":[
        "church"
    ],
    "wof:name":"Our Lady of Hope",
    "wof:placetype":"venue"
},
  "geometry": {"coordinates":[-81.016212,46.480358],"type":"Point"}
}