{
  "type": "Feature",
  "properties": {
    "addr:full":"150 Lockwood Ave Red Deer AB T4R 2M4",
    "addr:housenumber":"150",
    "addr:postcode":"t4r 2m4",
    "addr:street":"Lockwood Ave",
    "iso:country":"CA",
    "sg:address":"150 Lockwood Ave",
    "sg:city":"Red Deer",
    "sg:classifiers":[
        {
            "category":"Education",
            "subcategory":"School",
            "type":"Public Place"
        }
    ],
    "sg:phone":"+1 403 342 7799",
    "sg:postcode":"T4R 2M4",
    "sg:province":"AB",
    "wof:name":"Hunting Hills High School",
    "wof:placetype":"venue"
},
  "geometry": {"coordinates":[-113.76010100000001,52.250748],"type":"Point"}
}