{
  "type": "Feature",
  "properties": {
    "addr:full":"23853 Fraser Hwy Langley BC V2Z 2K5",
    "addr:housenumber":"23853",
    "addr:postcode":"v2z 2k5",
    "addr:street":"Fraser Hwy",
    "iso:country":"CA",
    "sg:address":"23853 Fraser Hwy",
    "sg:city":"Langley",
    "sg:classifiers":[
        {
            "category":"Freight",
            "type":"Transportation"
        }
    ],
    "sg:phone":"+1 604 533 9434",
    "sg:postcode":"V2Z 2K5",
    "sg:province":"BC",
    "sg:tags":[
        "trucking"
    ],
    "wof:name":"Pvc Transportation Systs Inc",
    "wof:placetype":"venue"
},
  "geometry": {"coordinates":[-122.56471999999999,49.076454],"type":"Point"}
}