{
  "type": "Feature",
  "properties": {
    "addr:full":"310 Notre Dame Ave Winnipeg MB R3B 1P4",
    "addr:housenumber":"310",
    "addr:postcode":"r3b 1p4",
    "addr:street":"Notre Dame Ave",
    "iso:country":"CA",
    "sg:address":"310 Notre Dame Ave",
    "sg:city":"Winnipeg",
    "sg:classifiers":[
        {
            "category":"Personal",
            "type":"Services"
        }
    ],
    "sg:phone":"+1 204 947 3917",
    "sg:postcode":"R3B 1P4",
    "sg:province":"MB",
    "sg:tags":[
        "wear",
        "formal"
    ],
    "wof:name":"Aldo Formal Wear & Tailors",
    "wof:placetype":"venue"
},
  "geometry": {"coordinates":[-97.14455413819999,49.8966751099],"type":"Point"}
}