{
  "type": "Feature",
  "properties": {
    "addr:full":"Edmonton AB T5J 2B1",
    "addr:postcode":"t5j 2b1",
    "iso:country":"CA",
    "sg:city":"Edmonton",
    "sg:classifiers":[
        {
            "category":"Bars & Pubs",
            "type":"Food & Drink"
        }
    ],
    "sg:phone":"+1 780 420 0779",
    "sg:postcode":"T5J 2B1",
    "sg:province":"AB",
    "sg:tags":[
        "lounge",
        "cocktail"
    ],
    "wof:name":"Boun Thai Restaurant",
    "wof:placetype":"venue"
},
  "geometry": {"coordinates":[-113.45488739,53.5577087402],"type":"Point"}
}