{
  "type": "Feature",
  "properties": {
    "addr:full":"12534 128 St NW Edmonton AB T5L 1C8",
    "addr:housenumber":"12534",
    "addr:postcode":"t5l 1c8",
    "addr:street":"128 St Nw",
    "iso:country":"CA",
    "sg:address":"12534 128 St NW",
    "sg:city":"Edmonton",
    "sg:classifiers":[
        {
            "category":"Building & Trades",
            "subcategory":"Construction",
            "type":"Services"
        }
    ],
    "sg:phone":"+1 780 454 7799",
    "sg:postcode":"T5L 1C8",
    "sg:province":"AB",
    "sg:tags":[
        "home",
        "builder"
    ],
    "wof:name":"Iron Stone Home Builders Inc",
    "wof:placetype":"venue"
},
  "geometry": {"coordinates":[-113.543091,53.581779],"type":"Point"}
}