{
  "type": "Feature",
  "properties": {
    "addr:full":"90 Place Bourget S Joliette QC J6E 5E7",
    "addr:housenumber":"90",
    "addr:postcode":"j6e 5e7",
    "addr:street":"Place Bourget S",
    "iso:country":"CA",
    "sg:address":"90 Place Bourget S",
    "sg:city":"Joliette",
    "sg:classifiers":[
        {
            "category":"Shopping",
            "subcategory":"Shoes",
            "type":"Retail Goods"
        }
    ],
    "sg:phone":"+1 450 759 4652",
    "sg:postcode":"J6E 5E7",
    "sg:province":"QC",
    "wof:name":"Chaussures Des Rochers",
    "wof:placetype":"venue"
},
  "geometry": {"coordinates":[-73.439163208,46.024066925],"type":"Point"}
}