{
  "type": "Feature",
  "properties": {
    "addr:full":"1002 37 St SW Calgary AB T3C 1S1",
    "addr:housenumber":"1002",
    "addr:postcode":"t3c 1s1",
    "addr:street":"37 St Sw",
    "iso:country":"CA",
    "sg:address":"1002 37 St SW",
    "sg:city":"Calgary",
    "sg:classifiers":[
        {
            "category":"Restaurant",
            "type":"Food & Drink"
        }
    ],
    "sg:phone":"+1 403 249 7933",
    "sg:postcode":"T3C 1S1",
    "sg:province":"AB",
    "wof:name":"Aussie Rules Food House & Bar",
    "wof:placetype":"venue"
},
  "geometry": {"coordinates":[-114.140869141,51.0440940857],"type":"Point"}
}