{
  "type": "Feature",
  "properties": {
    "iso:country":"CA",
    "sg:address":"2020 Boul Rene-Gaultier",
    "sg:city":"Varennes",
    "sg:classifiers":[
        {
            "category":"Personal",
            "subcategory":"Beauty Salon",
            "type":"Services"
        }
    ],
    "sg:phone":"+1 450 652 9745",
    "sg:postcode":"J3X 1N9",
    "sg:province":"QC",
    "wof:name":"Coiffelle Enrg",
    "wof:placetype":"venue"
},
  "geometry": {"coordinates":[-73.434509,45.677944],"type":"Point"}
}