{
  "type": "Feature",
  "properties": {
    "addr:full":"101 Lake St St Catharines ON L2R 5X7",
    "addr:housenumber":"101",
    "addr:postcode":"l2r 5x7",
    "addr:street":"Lake St",
    "iso:country":"CA",
    "sg:address":"101 Lake St",
    "sg:city":"St Catharines",
    "sg:classifiers":[
        {
            "category":"Restaurant",
            "type":"Food & Drink"
        }
    ],
    "sg:phone":"+1 905 682 5195",
    "sg:postcode":"L2R 5X7",
    "sg:province":"ON",
    "sg:tags":[
        "sandwich"
    ],
    "wof:name":"Ed's Subs N' Scoops",
    "wof:placetype":"venue"
},
  "geometry": {"coordinates":[-79.25078600000001,43.164455],"type":"Point"}
}