{
  "type": "Feature",
  "properties": {
    "addr:full":"14390 Woodbine Gormley ON L0H 1G0",
    "addr:housenumber":"14390",
    "addr:postcode":"l0h 1g0",
    "addr:street":"Woodbine",
    "iso:country":"CA",
    "sg:address":"14390 Woodbine",
    "sg:city":"Gormley",
    "sg:classifiers":[
        {
            "category":"Wholesale",
            "subcategory":"Machinery & Supplies",
            "type":"Manufacturing & Wholesale Goods"
        }
    ],
    "sg:phone":"+1 905 726 2283",
    "sg:postcode":"L0H 1G0",
    "sg:province":"ON",
    "sg:tags":[
        "farm",
        "equipment"
    ],
    "wof:name":"Tractorland Inc",
    "wof:placetype":"venue"
},
  "geometry": {"coordinates":[-79.390625,43.994766],"type":"Point"}
}