{
  "type": "Feature",
  "properties": {
    "addr:full":"Cap-Chat QC G0J 1E0",
    "addr:postcode":"g0j 1e0",
    "iso:country":"CA",
    "sg:city":"Cap-Chat",
    "sg:classifiers":[
        {
            "category":"Restaurant",
            "type":"Food & Drink"
        }
    ],
    "sg:phone":"+1 418 786 5779",
    "sg:postcode":"G0J 1E0",
    "sg:province":"QC",
    "wof:name":"Resto Chez Richard Inc",
    "wof:placetype":"venue"
},
  "geometry": {"coordinates":[-66.6872253418,49.0973052979],"type":"Point"}
}