{
  "type": "Feature",
  "properties": {
    "addr:full":"35 Mary St Picton ON K0K 2T0",
    "addr:housenumber":"35",
    "addr:postcode":"k0k 2t0",
    "addr:street":"Mary St",
    "iso:country":"CA",
    "sg:address":"35 Mary St",
    "sg:city":"Picton",
    "sg:classifiers":[
        {
            "category":"Autos & Motor Vehicles",
            "subcategory":"Auto Supplies",
            "type":"Retail Goods"
        }
    ],
    "sg:phone":"+1 613 476 3680",
    "sg:postcode":"K0K 2T0",
    "sg:province":"ON",
    "sg:tags":[
        "tire"
    ],
    "wof:name":"Van Zuylen's Tire Svc Ltd",
    "wof:placetype":"venue"
},
  "geometry": {"coordinates":[-77.14112854,44.0062408447],"type":"Point"}
}