{
  "type": "Feature",
  "properties": {
    "addr:full":"5692 Rue Drake Montreal QC H4E 4G3",
    "addr:housenumber":"5692",
    "addr:postcode":"h4e 4g3",
    "addr:street":"Rue Drake",
    "iso:country":"CA",
    "sg:address":"5692 Rue Drake",
    "sg:city":"Montreal",
    "sg:classifiers":[
        {
            "category":"Retail",
            "subcategory":"Photofinishing",
            "type":"Services"
        }
    ],
    "sg:phone":"+1 514 362 9780",
    "sg:postcode":"H4E 4G3",
    "sg:province":"QC",
    "sg:tags":[
        "photograph"
    ],
    "wof:name":"Photographie Eric Clusiau",
    "wof:placetype":"venue"
},
  "geometry": {"coordinates":[-73.5817871094,45.4608535767],"type":"Point"}
}