{
  "type": "Feature",
  "properties": {
    "iso:country":"CA",
    "sg:address":"10235 Yonge St # 201",
    "sg:city":"Richmond Hill",
    "sg:classifiers":[
        {
            "category":"Retail",
            "subcategory":"Repair Shop",
            "type":"Services"
        }
    ],
    "sg:phone":"+1 905 883 0810",
    "sg:postcode":"L4C 3B4",
    "sg:province":"ON",
    "sg:tags":[
        "equipment",
        "electronic",
        "supply"
    ],
    "wof:name":"Geralyn Electronics",
    "wof:placetype":"venue"
},
  "geometry": {"coordinates":[-79.4384,43.877136],"type":"Point"}
}