{
  "type": "Feature",
  "properties": {
    "iso:country":"CA",
    "sg:city":"St Albert",
    "sg:classifiers":[
        {
            "category":"Health Services",
            "subcategory":"Doctor",
            "type":"Services"
        }
    ],
    "sg:phone":"+1 780 458 5330",
    "sg:postcode":"T8N 6B9",
    "sg:province":"AB",
    "sg:tags":[
        "physician",
        "surgeon"
    ],
    "wof:name":"Prakash, A MD",
    "wof:placetype":"venue"
},
  "geometry": {"coordinates":[-113.626938,53.653862],"type":"Point"}
}