{
  "type": "Feature",
  "properties": {
    "addr:full":"105 Newton Dr Penhold AB T0M 1R0",
    "addr:housenumber":"105",
    "addr:postcode":"t0m 1r0",
    "addr:street":"Newton Dr",
    "iso:country":"CA",
    "sg:address":"105 Newton Dr",
    "sg:city":"Penhold",
    "sg:classifiers":[
        {
            "category":"Education",
            "subcategory":"School",
            "type":"Public Place"
        }
    ],
    "sg:phone":"+1 403 886 2233",
    "sg:postcode":"T0M 1R0",
    "sg:province":"AB",
    "wof:name":"Jessie Duncan Elementary Schl",
    "wof:placetype":"venue"
},
  "geometry": {"coordinates":[-113.868011,52.132072],"type":"Point"}
}