{
  "type": "Feature",
  "properties": {
    "iso:country":"CA",
    "sg:address":"370 Front St",
    "sg:city":"Belleville",
    "sg:classifiers":[
        {
            "category":"Health Services",
            "subcategory":"Nursing And Care Facility",
            "type":"Services"
        }
    ],
    "sg:phone":"+1 613 962 8888",
    "sg:postcode":"K8N 5L9",
    "sg:province":"ON",
    "sg:tags":[
        "home",
        "retirement",
        "community"
    ],
    "wof:name":"Quinte Living Ctr Inc",
    "wof:placetype":"venue"
},
  "geometry": {"coordinates":[-77.385956,44.167358],"type":"Point"}
}