{
  "type": "Feature",
  "properties": {
    "addr:full":"500 Kings Rd Sydney NS B1S 1A8",
    "addr:housenumber":"500",
    "addr:postcode":"b1s 1a8",
    "addr:street":"Kings Rd",
    "iso:country":"CA",
    "sg:address":"500 Kings Rd",
    "sg:city":"Sydney",
    "sg:classifiers":[
        {
            "category":"Education",
            "subcategory":"Vocational School",
            "type":"Public Place"
        }
    ],
    "sg:phone":"+1 902 539 0153",
    "sg:postcode":"B1S 1A8",
    "sg:province":"NS",
    "sg:tags":[
        "training",
        "computer"
    ],
    "wof:name":"Centre For Distance Education",
    "wof:placetype":"venue"
},
  "geometry": {"coordinates":[-60.2032775879,46.1219711304],"type":"Point"}
}