{
  "type": "Feature",
  "properties": {
    "addr:full":"Myrnam AB T0B 3K0",
    "addr:postcode":"t0b 3k0",
    "iso:country":"CA",
    "sg:city":"Myrnam",
    "sg:classifiers":[
        {
            "category":"Recreation",
            "type":"Entertainment"
        }
    ],
    "sg:phone":"+1 780 366 3819",
    "sg:postcode":"T0B 3K0",
    "sg:province":"AB",
    "sg:tags":[
        "hall",
        "auditorium"
    ],
    "wof:name":"Ukrainian Catholic Parish Hall",
    "wof:placetype":"venue"
},
  "geometry": {"coordinates":[-111.230835,53.661903],"type":"Point"}
}