{
  "type": "Feature",
  "properties": {
    "addr:full":"Edmonton AB T5G 0X5",
    "addr:postcode":"t5g 0x5",
    "iso:country":"CA",
    "sg:city":"Edmonton",
    "sg:classifiers":[
        {
            "category":"Professional",
            "subcategory":"Business Services",
            "type":"Services"
        }
    ],
    "sg:phone":"+1 780 453 3030",
    "sg:postcode":"T5G 0X5",
    "sg:province":"AB",
    "sg:tags":[
        "reservation",
        "motel",
        "hotel"
    ],
    "wof:name":"Eu-Anna Hospitality",
    "wof:placetype":"venue"
},
  "geometry": {"coordinates":[-113.524169922,53.5677528381],"type":"Point"}
}