{
  "type": "Feature",
  "properties": {
    "iso:country":"CA",
    "sg:address":"1298 Florence St",
    "sg:city":"London",
    "sg:classifiers":[
        {
            "category":"Autos & Motor Vehicles",
            "subcategory":"Automobile Sales",
            "type":"Retail Goods"
        }
    ],
    "sg:phone":"+1 519 455 5985",
    "sg:postcode":"N5W 2N7",
    "sg:province":"ON",
    "sg:tags":[
        "car",
        "dealer"
    ],
    "wof:name":"Subaru of London",
    "wof:placetype":"venue"
},
  "geometry": {"coordinates":[-81.203918,42.993446],"type":"Point"}
}