{
  "type": "Feature",
  "properties": {
    "addr:full":"5860 Boul Saint-Laurent Montreal QC H2T 1T3",
    "addr:housenumber":"5860",
    "addr:postcode":"h2t 1t3",
    "addr:street":"Boul Saint-Laurent",
    "iso:country":"CA",
    "sg:address":"5860 Boul Saint-Laurent",
    "sg:city":"Montreal",
    "sg:classifiers":[
        {
            "category":"Home & Garden",
            "subcategory":"Household Appliances",
            "type":"Retail Goods"
        }
    ],
    "sg:phone":"+1 514 273 2821",
    "sg:postcode":"H2T 1T3",
    "sg:province":"QC",
    "sg:tags":[
        "cleaners",
        "vacuum"
    ],
    "wof:name":"A LA Maison DE L'Aspirateur",
    "wof:placetype":"venue"
},
  "geometry": {"coordinates":[-73.603134,45.527634],"type":"Point"}
}