{
  "type": "Feature",
  "properties": {
    "addr:full":"793 Boul Maloney E Gatineau QC J8P 1G5",
    "addr:housenumber":"793",
    "addr:postcode":"j8p 1g5",
    "addr:street":"Boul Maloney E",
    "iso:country":"CA",
    "sg:address":"793 Boul Maloney E",
    "sg:city":"Gatineau",
    "sg:classifiers":[
        {
            "category":"Travel",
            "subcategory":"Hotels & Motels",
            "type":"Entertainment"
        }
    ],
    "sg:phone":"+1 819 663 4208",
    "sg:postcode":"J8P 1G5",
    "sg:province":"QC",
    "wof:name":"Motel Gatineau",
    "wof:placetype":"venue"
},
  "geometry": {"coordinates":[-75.61441802980001,45.4829330444],"type":"Point"}
}