{
  "type": "Feature",
  "properties": {
    "addr:full":"Vancouver BC V6E 1V6",
    "addr:postcode":"v6e 1v6",
    "iso:country":"CA",
    "sg:city":"Vancouver",
    "sg:classifiers":[
        {
            "category":"Manufacturing",
            "subcategory":"Apparel",
            "type":"Manufacturing & Wholesale Goods"
        }
    ],
    "sg:phone":"+1 604 685 1234",
    "sg:postcode":"V6E 1V6",
    "sg:province":"BC",
    "wof:name":"Lee Sailmakers Ltd",
    "wof:placetype":"venue"
},
  "geometry": {"coordinates":[-123.138458,49.28083],"type":"Point"}
}