{
  "type": "Feature",
  "properties": {
    "iso:country":"CA",
    "sg:address":"1032 Dufferin Ave",
    "sg:city":"Wallaceburg",
    "sg:classifiers":[
        {
            "category":"Health Services",
            "subcategory":"Doctor",
            "type":"Services"
        }
    ],
    "sg:phone":"+1 519 627 2231",
    "sg:postcode":"N8A 2V8",
    "sg:province":"ON",
    "sg:tags":[
        "dentist"
    ],
    "wof:name":"Dickerson, Mark DDS",
    "wof:placetype":"venue"
},
  "geometry": {"coordinates":[-82.393059,42.593044],"type":"Point"}
}