{
  "type": "Feature",
  "properties": {
    "addr:full":"1195 Rue Ricard Acton Vale QC J0H 1A0",
    "addr:housenumber":"1195",
    "addr:postcode":"j0h 1a0",
    "addr:street":"Rue Ricard",
    "iso:country":"CA",
    "sg:address":"1195 Rue Ricard",
    "sg:city":"Acton Vale",
    "sg:classifiers":[
        {
            "category":"Social Services",
            "subcategory":"Child Care",
            "type":"Services"
        }
    ],
    "sg:phone":"+1 450 546 3314",
    "sg:postcode":"J0H 1A0",
    "sg:province":"QC",
    "wof:name":"Garderie Les P'Tites Frimousse",
    "wof:placetype":"venue"
},
  "geometry": {"coordinates":[-72.567154,45.652561],"type":"Point"}
}