{
  "type": "Feature",
  "properties": {
    "iso:country":"CA",
    "sg:city":"Pickering",
    "sg:classifiers":[
        {
            "category":"Shopping",
            "subcategory":"Clothing, Apparel, & Fashions",
            "type":"Retail Goods"
        }
    ],
    "sg:phone":"+1 905 427 4348",
    "sg:postcode":"L1X 2R2",
    "sg:province":"ON",
    "sg:tags":[
        "uniform"
    ],
    "wof:name":"Uniforms Plus",
    "wof:placetype":"venue"
},
  "geometry": {"coordinates":[-79.079124,43.858231],"type":"Point"}
}