{
  "type": "Feature",
  "properties": {
    "iso:country":"CA",
    "sg:address":"1050 Rue DE L'Echo",
    "sg:city":"Val-D'Or",
    "sg:classifiers":[
        {
            "category":"Manufacturing",
            "subcategory":"Tools & Machinery",
            "type":"Manufacturing & Wholesale Goods"
        }
    ],
    "sg:phone":"+1 819 825 8501",
    "sg:postcode":"J9P 6X8",
    "sg:province":"QC",
    "sg:tags":[
        "machine",
        "shop",
        "equipment",
        "hydraulic",
        "supply"
    ],
    "wof:name":"Hydraulique Val D'Or Enr",
    "wof:placetype":"venue"
},
  "geometry": {"coordinates":[-71.0033187866,45.3835067749],"type":"Point"}
}