{
  "type": "Feature",
  "properties": {
    "iso:country":"CA",
    "sg:address":"223 Rte Grand-Capsa",
    "sg:city":"Pont-Rouge",
    "sg:classifiers":[
        {
            "category":"Recreation",
            "type":"Entertainment"
        }
    ],
    "sg:phone":"+1 418 873 2164",
    "sg:postcode":"G3H 1K7",
    "sg:province":"QC",
    "sg:tags":[
        "sugar",
        "syrup",
        "hall",
        "maple",
        "auditorium"
    ],
    "wof:name":"Erabliere Mart-L Enr",
    "wof:placetype":"venue"
},
  "geometry": {"coordinates":[-71.56439208979999,46.7844238281],"type":"Point"}
}