{
  "type": "Feature",
  "properties": {
    "iso:country":"CA",
    "sg:address":"535 Yates St",
    "sg:city":"Victoria",
    "sg:classifiers":[
        {
            "category":"Government",
            "subcategory":"Office",
            "type":"Public Place"
        }
    ],
    "sg:phone":"+1 250 363 6910",
    "sg:postcode":"V8W 2Z6",
    "sg:province":"BC",
    "wof:name":"Canada Federal Treaty Ngtns",
    "wof:placetype":"venue"
},
  "geometry": {"coordinates":[-123.369537,48.426662],"type":"Point"}
}