{
  "type": "Feature",
  "properties": {
    "addr:full":"555 Rue Notre-Dame Lachine QC H8S 2A9",
    "addr:housenumber":"555",
    "addr:postcode":"h8s 2a9",
    "addr:street":"Rue Notre-Dame",
    "iso:country":"CA",
    "sg:address":"555 Rue Notre-Dame",
    "sg:city":"Lachine",
    "sg:classifiers":[
        {
            "category":"Manufacturing",
            "subcategory":"Metals",
            "type":"Manufacturing & Wholesale Goods"
        }
    ],
    "sg:phone":"+1 514 634 3311",
    "sg:postcode":"H8S 2A9",
    "sg:province":"QC",
    "sg:tags":[
        "tube",
        "fabricating"
    ],
    "wof:name":"Cintubes Ltee",
    "wof:placetype":"venue"
},
  "geometry": {"coordinates":[-73.6690368652,45.4347076416],"type":"Point"}
}