{
  "type": "Feature",
  "properties": {
    "addr:full":"355 Boul Des Laurentides # A Laval QC H7G 2T9",
    "addr:housenumber":"355;# a",
    "addr:postcode":"qc h7g 2t9",
    "addr:street":"Boul Des Laurentides",
    "iso:country":"CA",
    "sg:address":"355 Boul Des Laurentides # A",
    "sg:city":"Laval",
    "sg:classifiers":[
        {
            "category":"Shopping",
            "subcategory":"Clothing, Apparel, & Fashions",
            "type":"Retail Goods"
        }
    ],
    "sg:phone":"+1 450 669 2023",
    "sg:postcode":"H7G 2T9",
    "sg:province":"QC",
    "sg:tags":[
        "item",
        "boutique"
    ],
    "wof:name":"Sheffrens Magasins Ltee",
    "wof:placetype":"venue"
},
  "geometry": {"coordinates":[-73.688934,45.56778],"type":"Point"}
}