{
  "type": "Feature",
  "properties": {
    "iso:country":"CA",
    "sg:address":"2391 Proton Ave",
    "sg:city":"Gull Lake",
    "sg:classifiers":[
        {
            "category":"Insurance",
            "subcategory":"Insurance Agent",
            "type":"Services"
        }
    ],
    "sg:phone":"+1 306 672 3522",
    "sg:postcode":"S0N 1A0",
    "sg:province":"SK",
    "wof:name":"Gull Agencies Ltd",
    "wof:placetype":"venue"
},
  "geometry": {"coordinates":[-108.483924866,50.0979690552],"type":"Point"}
}