{
  "type": "Feature",
  "properties": {
    "addr:full":"230 Eddystone Ave North York ON M3N 1H7",
    "addr:housenumber":"230",
    "addr:postcode":"m3n 1h7",
    "addr:street":"Eddystone Ave",
    "iso:country":"CA",
    "sg:address":"230 Eddystone Ave",
    "sg:city":"North York",
    "sg:classifiers":[
        {
            "category":"Home & Garden",
            "subcategory":"Home Furnishings",
            "type":"Retail Goods"
        }
    ],
    "sg:phone":"+1 416 741 8025",
    "sg:postcode":"M3N 1H7",
    "sg:province":"ON",
    "sg:tags":[
        "curtain",
        "made",
        "drapery"
    ],
    "wof:name":"Designers Finish",
    "wof:placetype":"venue"
},
  "geometry": {"coordinates":[-79.520714,43.748119],"type":"Point"}
}