{
  "type": "Feature",
  "properties": {
    "addr:full":"309 York Mills Rd North York ON M2L 1L3",
    "addr:housenumber":"309",
    "addr:postcode":"m2l 1l3",
    "addr:street":"York Mills Rd",
    "iso:country":"CA",
    "sg:address":"309 York Mills Rd",
    "sg:city":"North York",
    "sg:classifiers":[
        {
            "category":"Restaurant",
            "type":"Food & Drink"
        }
    ],
    "sg:phone":"+1 416 444 4477",
    "sg:postcode":"M2L 1L3",
    "sg:province":"ON",
    "sg:tags":[
        "caterer"
    ],
    "wof:name":"Champman's Essential Foods",
    "wof:placetype":"venue"
},
  "geometry": {"coordinates":[-79.3843078613,43.7478637695],"type":"Point"}
}