{
  "type": "Feature",
  "properties": {
    "addr:full":"3402 Rue Du Muguet Jonquiere QC G7S 5W4",
    "addr:housenumber":"3402",
    "addr:postcode":"g7s 5w4",
    "addr:street":"Rue Du Muguet",
    "iso:country":"CA",
    "sg:address":"3402 Rue Du Muguet",
    "sg:city":"Jonquiere",
    "sg:classifiers":[
        {
            "category":"Professional",
            "subcategory":"Accounting & Tax Preparation",
            "type":"Services"
        }
    ],
    "sg:phone":"+1 418 542 0446",
    "sg:postcode":"G7S 5W4",
    "sg:province":"QC",
    "sg:tags":[
        "bookkeeping",
        "general"
    ],
    "wof:name":"Info-Gestion Enr",
    "wof:placetype":"venue"
},
  "geometry": {"coordinates":[-71.21978759770001,48.4251022339],"type":"Point"}
}