{
  "type": "Feature",
  "properties": {
    "iso:country":"CA",
    "sg:city":"Carlyle",
    "sg:classifiers":[
        {
            "category":"Wholesale",
            "subcategory":"Farm Supplies",
            "type":"Manufacturing & Wholesale Goods"
        }
    ],
    "sg:phone":"+1 306 453 2255",
    "sg:postcode":"S0C 0R0",
    "sg:province":"SK",
    "sg:tags":[
        "fertilizer"
    ],
    "wof:name":"Precision Agricultural Svc Inc",
    "wof:placetype":"venue"
},
  "geometry": {"coordinates":[-102.265388489,49.6365852356],"type":"Point"}
}