{
  "type": "Feature",
  "properties": {
    "addr:full":"22790 Amiens Rd Komoka ON N0L 1R0",
    "addr:housenumber":"22790",
    "addr:postcode":"n0l 1r0",
    "addr:street":"Amiens Rd",
    "iso:country":"CA",
    "sg:address":"22790 Amiens Rd",
    "sg:city":"Komoka",
    "sg:classifiers":[
        {
            "category":"Travel",
            "subcategory":"Campground",
            "type":"Entertainment"
        }
    ],
    "sg:phone":"+1 519 471 2720",
    "sg:postcode":"N0L 1R0",
    "sg:province":"ON",
    "wof:name":"Oriole Park Resort",
    "wof:placetype":"venue"
},
  "geometry": {"coordinates":[-81.46208190919999,42.9367980957],"type":"Point"}
}