{
  "type": "Feature",
  "properties": {
    "addr:full":"2010 Rue Saint-Pierre Drummondville QC J2C 3Y5",
    "addr:housenumber":"2010",
    "addr:postcode":"j2c 3y5",
    "addr:street":"Rue Saint-Pierre",
    "iso:country":"CA",
    "sg:address":"2010 Rue Saint-Pierre",
    "sg:city":"Drummondville",
    "sg:classifiers":[
        {
            "category":"Restaurant",
            "type":"Food & Drink"
        }
    ],
    "sg:phone":"+1 819 474 3881",
    "sg:postcode":"J2C 3Y5",
    "sg:province":"QC",
    "wof:name":"Restaurant Valentine",
    "wof:placetype":"venue"
},
  "geometry": {"coordinates":[-72.51568603520001,45.8727111816],"type":"Point"}
}