{
  "type": "Feature",
  "properties": {
    "addr:full":"1019 Sheppard Ave E North York ON M2K 1C2",
    "addr:housenumber":"1019",
    "addr:postcode":"m2k 1c2",
    "addr:street":"Sheppard Ave E",
    "iso:country":"CA",
    "sg:address":"1019 Sheppard Ave E",
    "sg:city":"North York",
    "sg:classifiers":[
        {
            "category":"Autos & Motor Vehicles",
            "subcategory":"Auto Supplies",
            "type":"Retail Goods"
        }
    ],
    "sg:phone":"+1 416 226 4411",
    "sg:postcode":"M2K 1C2",
    "sg:province":"ON",
    "sg:tags":[
        "repairing",
        "automobile",
        "parts"
    ],
    "wof:name":"Canadian Tire",
    "wof:placetype":"venue"
},
  "geometry": {"coordinates":[-79.37618255620001,43.7691764832],"type":"Point"}
}