{
  "type": "Feature",
  "properties": {
    "addr:full":"1268 Ch Denison O Granby QC J2G 8C6",
    "addr:housenumber":"1268",
    "addr:postcode":"j2g 8c6",
    "addr:street":"Ch Denison O",
    "iso:country":"CA",
    "sg:address":"1268 Ch Denison O",
    "sg:city":"Granby",
    "sg:classifiers":[
        {
            "category":"Manufacturing",
            "subcategory":"Lumber",
            "type":"Manufacturing & Wholesale Goods"
        }
    ],
    "sg:phone":"+1 450 375 5238",
    "sg:postcode":"J2G 8C6",
    "sg:province":"QC",
    "sg:tags":[
        "syrup",
        "maple",
        "sugar"
    ],
    "wof:name":"Erabliere Bernard",
    "wof:placetype":"venue"
},
  "geometry": {"coordinates":[-72.7734527588,45.3570480347],"type":"Point"}
}