{
  "type": "Feature",
  "properties": {
    "addr:full":"Melfort SK S0E 1A0",
    "addr:postcode":"s0e 1a0",
    "addr:street":"Melfort",
    "iso:country":"CA",
    "sg:city":"Melfort",
    "sg:classifiers":[
        {
            "category":"Government",
            "subcategory":"Office",
            "type":"Public Place"
        }
    ],
    "sg:phone":"+1 306 752 4442",
    "sg:postcode":"S0E 1A0",
    "sg:province":"SK",
    "wof:name":"Canada Agriculture & Agri-Food",
    "wof:placetype":"venue"
},
  "geometry": {"coordinates":[-104.604713,52.867081],"type":"Point"}
}