{
  "type": "Feature",
  "properties": {
    "addr:full":"Toronto ON M5B 2H1",
    "addr:postcode":"m5b 2h1",
    "iso:country":"CA",
    "sg:city":"Toronto",
    "sg:classifiers":[
        {
            "category":"Shopping",
            "subcategory":"Clothing, Apparel, & Fashions",
            "type":"Retail Goods"
        }
    ],
    "sg:phone":"+1 416 260 2082",
    "sg:postcode":"M5B 2H1",
    "sg:province":"ON",
    "sg:tags":[
        "infant",
        "wear"
    ],
    "wof:name":"Gymboree",
    "wof:placetype":"venue"
},
  "geometry": {"coordinates":[-79.37975299999999,43.653236],"type":"Point"}
}