{
  "type": "Feature",
  "properties": {
    "addr:full":"11721 90 St Grande Prairie AB T8X 1K1",
    "addr:housenumber":"11721",
    "addr:postcode":"t8x 1k1",
    "addr:street":"90 St",
    "iso:country":"CA",
    "sg:address":"11721 90 St",
    "sg:city":"Grande Prairie",
    "sg:classifiers":[
        {
            "category":"Building & Trades",
            "subcategory":"Construction",
            "type":"Services"
        }
    ],
    "sg:phone":"+1 780 538 9399",
    "sg:postcode":"T8X 1K1",
    "sg:province":"AB",
    "sg:tags":[
        "line",
        "telephone",
        "power"
    ],
    "wof:name":"Bram Consulting Ltd",
    "wof:placetype":"venue"
},
  "geometry": {"coordinates":[-118.76254299999999,55.186829],"type":"Point"}
}