{
  "type": "Feature",
  "properties": {
    "addr:full":"699 Charlotte St Windsor ON N8X 3A6",
    "addr:housenumber":"699",
    "addr:postcode":"n8x 3a6",
    "addr:street":"Charlotte St",
    "iso:country":"CA",
    "sg:address":"699 Charlotte St",
    "sg:city":"Windsor",
    "sg:classifiers":[
        {
            "category":"Shopping",
            "subcategory":"Discount & Variety Stores",
            "type":"Retail Goods"
        }
    ],
    "sg:phone":"+1 519 966 2788",
    "sg:postcode":"N8X 3A6",
    "sg:province":"ON",
    "wof:name":"J & K Variety Store",
    "wof:placetype":"venue"
},
  "geometry": {"coordinates":[-83.008247,42.287014],"type":"Point"}
}