{
  "type": "Feature",
  "properties": {
    "addr:full":"2442 Av Champlain Shawinigan QC G9N 2L9",
    "addr:housenumber":"2442",
    "addr:postcode":"g9n 2l9",
    "addr:street":"Av Champlain",
    "iso:country":"CA",
    "sg:address":"2442 Av Champlain",
    "sg:city":"Shawinigan",
    "sg:classifiers":[
        {
            "category":"Personal",
            "subcategory":"Beauty Salon",
            "type":"Services"
        }
    ],
    "sg:phone":"+1 819 539 6820",
    "sg:postcode":"G9N 2L9",
    "sg:province":"QC",
    "wof:name":"Studio Champlain",
    "wof:placetype":"venue"
},
  "geometry": {"coordinates":[-72.739555,46.556232],"type":"Point"}
}