{
  "type": "Feature",
  "properties": {
    "iso:country":"CA",
    "sg:address":"1040 5 Ave SW",
    "sg:city":"Calgary",
    "sg:classifiers":[
        {
            "category":"Manufacturing",
            "subcategory":"Jewelry",
            "type":"Manufacturing & Wholesale Goods"
        }
    ],
    "sg:phone":"+1 403 228 0633",
    "sg:postcode":"T2P 0P1",
    "sg:province":"AB",
    "wof:name":"Meiko Jewelry Ltd",
    "wof:placetype":"venue"
},
  "geometry": {"coordinates":[-114.08456420900001,51.0491447449],"type":"Point"}
}