{
  "type": "Feature",
  "properties": {
    "addr:full":"3048 Main St Vancouver BC V5T 3G5",
    "addr:housenumber":"3048",
    "addr:postcode":"v5t 3g5",
    "addr:street":"Main St",
    "iso:country":"CA",
    "sg:address":"3048 Main St",
    "sg:city":"Vancouver",
    "sg:classifiers":[
        {
            "category":"Wholesale",
            "subcategory":"Groceries",
            "type":"Manufacturing & Wholesale Goods"
        }
    ],
    "sg:phone":"+1 604 879 0188",
    "sg:postcode":"V5T 3G5",
    "sg:province":"BC",
    "sg:tags":[
        "grocer"
    ],
    "wof:name":"Veggie Flavour",
    "wof:placetype":"venue"
},
  "geometry": {"coordinates":[-123.100906372,49.2580108643],"type":"Point"}
}