{
  "type": "Feature",
  "properties": {
    "addr:full":"Pincher Creek AB T0K 1W0",
    "addr:postcode":"t0k 1w0",
    "iso:country":"CA",
    "sg:city":"Pincher Creek",
    "sg:classifiers":[
        {
            "category":"Health Services",
            "subcategory":"Hospital",
            "type":"Services"
        }
    ],
    "sg:phone":"+1 403 627 1234",
    "sg:postcode":"T0K 1W0",
    "sg:province":"AB",
    "wof:name":"Pincher Creek Hospital",
    "wof:placetype":"venue"
},
  "geometry": {"coordinates":[-113.94632,49.492645],"type":"Point"}
}