{
  "type": "Feature",
  "properties": {
    "iso:country":"CA",
    "sg:city":"Winnipeg",
    "sg:classifiers":[
        {
            "category":"Travel",
            "subcategory":"Travel Agent",
            "type":"Entertainment"
        }
    ],
    "sg:phone":"+1 204 775 8839",
    "sg:postcode":"R3E 0B2",
    "sg:province":"MB",
    "sg:tags":[
        "agency",
        "bureau"
    ],
    "wof:name":"Galaxy Travel Ltd",
    "wof:placetype":"venue"
},
  "geometry": {"coordinates":[-97.1640625,49.8966255188],"type":"Point"}
}