{
  "type": "Feature",
  "properties": {
    "addr:full":"Pembroke ON K8A 6W8",
    "addr:postcode":"k8a 6w8",
    "iso:country":"CA",
    "sg:city":"Pembroke",
    "sg:classifiers":[
        {
            "category":"Building & Trades",
            "subcategory":"Plumbing",
            "type":"Services"
        }
    ],
    "sg:phone":"+1 613 732 4926",
    "sg:postcode":"K8A 6W8",
    "sg:province":"ON",
    "sg:tags":[
        "septic"
    ],
    "wof:name":"K B Septic Tank Pumping",
    "wof:placetype":"venue"
},
  "geometry": {"coordinates":[-77.112213,45.826481],"type":"Point"}
}