{
  "type": "Feature",
  "properties": {
    "addr:full":"Highway 533 Nanton AB T0L 1R0",
    "addr:postcode":"t0l 1r0",
    "addr:street":"Highway 533 Nanton",
    "iso:country":"CA",
    "sg:address":"Highway 533",
    "sg:city":"Nanton",
    "sg:classifiers":[
        {
            "category":"Sports & Exercise",
            "subcategory":"Golf",
            "type":"Entertainment"
        }
    ],
    "sg:phone":"+1 403 646 2050",
    "sg:postcode":"T0L 1R0",
    "sg:province":"AB",
    "sg:tags":[
        "course"
    ],
    "wof:name":"Nanton Golf Club",
    "wof:placetype":"venue"
},
  "geometry": {"coordinates":[-113.77384948700001,50.3498191833],"type":"Point"}
}