{
  "type": "Feature",
  "properties": {
    "addr:full":"Surrey BC V3T 2Z3",
    "addr:postcode":"v3t 2z3",
    "iso:country":"CA",
    "sg:city":"Surrey",
    "sg:classifiers":[
        {
            "category":"Health Services",
            "subcategory":"Doctor",
            "type":"Services"
        }
    ],
    "sg:phone":"+1 604 585 4466",
    "sg:postcode":"V3T 2Z3",
    "sg:province":"BC",
    "sg:tags":[
        "dentist"
    ],
    "wof:name":"Irene A Ku Inc",
    "wof:placetype":"venue"
},
  "geometry": {"coordinates":[-122.867515564,49.1884536743],"type":"Point"}
}