{
  "type": "Feature",
  "properties": {
    "addr:full":"7 Equestrian Crt North York ON M2H 3M9",
    "addr:housenumber":"7",
    "addr:postcode":"m2h 3m9",
    "addr:street":"Equestrian Crt",
    "iso:country":"CA",
    "sg:address":"7 Equestrian Crt",
    "sg:city":"North York",
    "sg:classifiers":[
        {
            "category":"Wholesale",
            "subcategory":"Durable Goods & Equipment",
            "type":"Manufacturing & Wholesale Goods"
        }
    ],
    "sg:phone":"+1 416 269 2950",
    "sg:postcode":"M2H 3M9",
    "sg:province":"ON",
    "sg:tags":[
        "representative",
        "manufacturer"
    ],
    "wof:name":"Reho International",
    "wof:placetype":"venue"
},
  "geometry": {"coordinates":[-79.3723373413,43.8069381714],"type":"Point"}
}