{
  "type": "Feature",
  "properties": {
    "addr:full":"539 Ash St Winnipeg MB R3N 0R3",
    "addr:housenumber":"539",
    "addr:postcode":"r3n 0r3",
    "addr:street":"Ash St",
    "iso:country":"CA",
    "sg:address":"539 Ash St",
    "sg:city":"Winnipeg",
    "sg:classifiers":[
        {
            "category":"Personal",
            "subcategory":"Beauty Salon",
            "type":"Services"
        }
    ],
    "sg:phone":"+1 204 487 2683",
    "sg:postcode":"R3N 0R3",
    "sg:province":"MB",
    "sg:tags":[
        "treatment",
        "skin"
    ],
    "wof:name":"Ana Carrasco Aesthetics",
    "wof:placetype":"venue"
},
  "geometry": {"coordinates":[-97.1835021973,49.862739563],"type":"Point"}
}