{
  "type": "Feature",
  "properties": {
    "addr:full":"4020 Rue Saint-Ambroise Montreal QC H4C 2C7",
    "addr:housenumber":"4020",
    "addr:postcode":"h4c 2c7",
    "addr:street":"Rue Saint-Ambroise",
    "iso:country":"CA",
    "sg:address":"4020 Rue Saint-Ambroise",
    "sg:city":"Montreal",
    "sg:classifiers":[
        {
            "category":"Wholesale",
            "subcategory":"Durable Goods & Equipment",
            "type":"Manufacturing & Wholesale Goods"
        }
    ],
    "sg:phone":"+1 514 939 1330",
    "sg:postcode":"H4C 2C7",
    "sg:province":"QC",
    "sg:tags":[
        "importer"
    ],
    "wof:name":"Bryner International Inc",
    "wof:placetype":"venue"
},
  "geometry": {"coordinates":[-73.58061981199999,45.4752006531],"type":"Point"}
}