{
  "type": "Feature",
  "properties": {
    "addr:full":"1370 Rue DE Coulomb Boucherville QC J4B 7J4",
    "addr:housenumber":"1370",
    "addr:postcode":"j4b 7j4",
    "addr:street":"Rue De Coulomb",
    "iso:country":"CA",
    "sg:address":"1370 Rue DE Coulomb",
    "sg:city":"Boucherville",
    "sg:classifiers":[
        {
            "category":"Manufacturing",
            "subcategory":"Signs",
            "type":"Manufacturing & Wholesale Goods"
        }
    ],
    "sg:phone":"+1 450 655 6866",
    "sg:postcode":"J4B 7J4",
    "sg:province":"QC",
    "wof:name":"Enseignes Access Inc",
    "wof:placetype":"venue"
},
  "geometry": {"coordinates":[-73.437325,45.56015],"type":"Point"}
}