{
  "type": "Feature",
  "properties": {
    "iso:country":"CA",
    "sg:address":"9600 Boul DE L'Acadie",
    "sg:city":"Montreal",
    "sg:phone":"+1 514 383 0030",
    "sg:postcode":"H4N 1L8",
    "sg:province":"QC",
    "sg:tags":[
        "equipment",
        "supply"
    ],
    "wof:name":"Tzanet Inc",
    "wof:placetype":"venue"
},
  "geometry": {"coordinates":[-73.3577804565,45.3339691162],"type":"Point"}
}