{
  "type": "Feature",
  "properties": {
    "iso:country":"CA",
    "sg:city":"Bouctouche",
    "sg:classifiers":[
        {
            "category":"Education",
            "subcategory":"School",
            "type":"Public Place"
        }
    ],
    "sg:phone":"+1 506 743 7220",
    "sg:postcode":"E4S 3N1",
    "sg:province":"NB",
    "wof:name":"Dr-Marguerite-Michaud Ecole",
    "wof:placetype":"venue"
},
  "geometry": {"coordinates":[-64.72281646730001,46.4728050232],"type":"Point"}
}