{
  "type": "Feature",
  "properties": {
    "iso:country":"CA",
    "sg:address":"544 Yonge St",
    "sg:city":"Toronto",
    "sg:classifiers":[
        {
            "category":"Shopping",
            "subcategory":"Used Merchandise",
            "type":"Retail Goods"
        }
    ],
    "sg:phone":"+1 416 923 5537",
    "sg:postcode":"M4Y 1Y8",
    "sg:province":"ON",
    "sg:tags":[
        "book",
        "rare",
        "dealer"
    ],
    "wof:name":"Orion Book Store",
    "wof:placetype":"venue"
},
  "geometry": {"coordinates":[-79.384475708,43.6642570496],"type":"Point"}
}