{
  "type": "Feature",
  "properties": {
    "addr:full":"1468 Ch Gaspe Brigham QC J2K 4B4",
    "addr:housenumber":"1468",
    "addr:postcode":"j2k 4b4",
    "addr:street":"Ch Gaspe",
    "iso:country":"CA",
    "sg:address":"1468 Ch Gaspe",
    "sg:city":"Brigham",
    "sg:classifiers":[
        {
            "category":"Manufacturing",
            "subcategory":"Lumber",
            "type":"Manufacturing & Wholesale Goods"
        }
    ],
    "sg:phone":"+1 450 263 6060",
    "sg:postcode":"J2K 4B4",
    "sg:province":"QC",
    "sg:tags":[
        "syrup",
        "maple",
        "sugar"
    ],
    "wof:name":"Cabane Du Pic Bois",
    "wof:placetype":"venue"
},
  "geometry": {"coordinates":[-72.708229,45.252876],"type":"Point"}
}