{
  "type": "Feature",
  "properties": {
    "addr:full":"1229 Ellesmere Rd Scarborough ON M1P 4V8",
    "addr:housenumber":"1229",
    "addr:postcode":"m1p 4v8",
    "addr:street":"Ellesmere Rd",
    "iso:country":"CA",
    "sg:address":"1229 Ellesmere Rd",
    "sg:city":"Scarborough",
    "sg:classifiers":[
        {
            "category":"Travel",
            "subcategory":"Bed & Breakfast",
            "type":"Entertainment"
        }
    ],
    "sg:phone":"+1 416 392 5650",
    "sg:postcode":"M1P 4V8",
    "sg:province":"ON",
    "sg:tags":[
        "government",
        "hostel"
    ],
    "wof:name":"Toronto Hostels",
    "wof:placetype":"venue"
},
  "geometry": {"coordinates":[-79.2670059204,43.7687187195],"type":"Point"}
}