{
  "type": "Feature",
  "properties": {
    "addr:full":"Laval QC H7N 1A1",
    "addr:postcode":"h7n 1a1",
    "iso:country":"CA",
    "sg:city":"Laval",
    "sg:classifiers":[
        {
            "category":"Health Services",
            "subcategory":"Doctor",
            "type":"Services"
        }
    ],
    "sg:phone":"+1 450 668 7400",
    "sg:postcode":"H7N 1A1",
    "sg:province":"QC",
    "sg:tags":[
        "clinic",
        "nurse",
        "registry"
    ],
    "wof:name":"Sante Express",
    "wof:placetype":"venue"
},
  "geometry": {"coordinates":[-73.7051696777,45.5812110901],"type":"Point"}
}