{
  "type": "Feature",
  "properties": {
    "addr:full":"167 Centre St Drumheller AB T0J 0Y0",
    "addr:housenumber":"167",
    "addr:postcode":"t0j 0y0",
    "addr:street":"Centre St",
    "iso:country":"CA",
    "sg:address":"167 Centre St",
    "sg:city":"Drumheller",
    "sg:classifiers":[
        {
            "category":"Shopping",
            "subcategory":"Pharmacy",
            "type":"Retail Goods"
        }
    ],
    "sg:phone":"+1 403 823 3784",
    "sg:postcode":"T0J 0Y0",
    "sg:province":"AB",
    "wof:name":"Riverside Value Drug Mart",
    "wof:placetype":"venue"
},
  "geometry": {"coordinates":[-112.591995,51.394897],"type":"Point"}
}