{
  "type": "Feature",
  "properties": {
    "addr:full":"6362 Main St Stouffville ON L4A 1G9",
    "addr:housenumber":"6362",
    "addr:postcode":"l4a 1g9",
    "addr:street":"Main St",
    "iso:country":"CA",
    "sg:address":"6362 Main St",
    "sg:city":"Stouffville",
    "sg:classifiers":[
        {
            "category":"Retail",
            "subcategory":"Animal Services",
            "type":"Services"
        }
    ],
    "sg:phone":"+1 905 642 3647",
    "sg:postcode":"L4A 1G9",
    "sg:province":"ON",
    "sg:tags":[
        "pet",
        "grooming",
        "washing"
    ],
    "wof:name":"Laundra Mutt",
    "wof:placetype":"venue"
},
  "geometry": {"coordinates":[-79.2439498901,43.9721031189],"type":"Point"}
}