{
  "type": "Feature",
  "properties": {
    "iso:country":"CA",
    "sg:address":"90 Rue Michaud",
    "sg:city":"Saint-Gabriel-DE-Brandon",
    "sg:classifiers":[
        {
            "category":"Personal",
            "subcategory":"Beauty Salon",
            "type":"Services"
        }
    ],
    "sg:phone":"+1 450 835 4549",
    "sg:postcode":"J0K 2N0",
    "sg:province":"QC",
    "wof:name":"Salon K",
    "wof:placetype":"venue"
},
  "geometry": {"coordinates":[-73.38022613530001,46.2937164307],"type":"Point"}
}