{
  "type": "Feature",
  "properties": {
    "addr:full":"1814 20 Ave Coaldale AB T1M 1N1",
    "addr:housenumber":"1814",
    "addr:postcode":"t1m 1n1",
    "addr:street":"20 Ave",
    "iso:country":"CA",
    "sg:address":"1814 20 Ave",
    "sg:city":"Coaldale",
    "sg:classifiers":[
        {
            "category":"Travel",
            "subcategory":"Hotels & Motels",
            "type":"Entertainment"
        }
    ],
    "sg:phone":"+1 403 345 3080",
    "sg:postcode":"T1M 1N1",
    "sg:province":"AB",
    "wof:name":"Ventura Hotel",
    "wof:placetype":"venue"
},
  "geometry": {"coordinates":[-112.61994934099999,49.7277565002],"type":"Point"}
}