{
  "type": "Feature",
  "properties": {
    "addr:full":"2989 272 St Aldergrove BC V4W 3R3",
    "addr:housenumber":"2989",
    "addr:postcode":"v4w 3r3",
    "addr:street":"272 St",
    "iso:country":"CA",
    "sg:address":"2989 272 St",
    "sg:city":"Aldergrove",
    "sg:classifiers":[
        {
            "category":"Restaurant",
            "type":"Food & Drink"
        }
    ],
    "sg:phone":"+1 604 607 6698",
    "sg:postcode":"V4W 3R3",
    "sg:province":"BC",
    "sg:tags":[
        "delicatessen"
    ],
    "wof:name":"Oso Good Europe & Meat Deli",
    "wof:placetype":"venue"
},
  "geometry": {"coordinates":[-122.47088599999999,49.057564],"type":"Point"}
}