{
  "type": "Feature",
  "properties": {
    "addr:full":"195 Boul Fiset Sorel-Tracy QC J3P 3P3",
    "addr:housenumber":"195",
    "addr:postcode":"j3p 3p3",
    "addr:street":"Boul Fiset",
    "iso:country":"CA",
    "sg:address":"195 Boul Fiset",
    "sg:city":"Sorel-Tracy",
    "sg:classifiers":[
        {
            "category":"Personal",
            "subcategory":"Beauty Salon",
            "type":"Services"
        }
    ],
    "sg:phone":"+1 450 743 9361",
    "sg:postcode":"J3P 3P3",
    "sg:province":"QC",
    "wof:name":"Ghislaine Centre D'Esthetique",
    "wof:placetype":"venue"
},
  "geometry": {"coordinates":[-73.101608,46.042011],"type":"Point"}
}