{
  "type": "Feature",
  "properties": {
    "addr:full":"Etobicoke ON M9P 3B6",
    "addr:postcode":"m9p 3b6",
    "iso:country":"CA",
    "sg:city":"Etobicoke",
    "sg:classifiers":[
        {
            "category":"Retail",
            "subcategory":"Repair Shop",
            "type":"Services"
        }
    ],
    "sg:phone":"+1 416 614 7529",
    "sg:postcode":"M9P 3B6",
    "sg:province":"ON",
    "sg:tags":[
        "repairing",
        "music",
        "refinishing",
        "dealer"
    ],
    "wof:name":"A Sharp School of Music",
    "wof:placetype":"venue"
},
  "geometry": {"coordinates":[-79.530563,43.69091],"type":"Point"}
}