{
  "type": "Feature",
  "properties": {
    "addr:full":"1839 Brilliant Rd Castlegar BC V1N 4K2",
    "addr:housenumber":"1839",
    "addr:postcode":"v1n 4k2",
    "addr:street":"Brilliant Rd",
    "iso:country":"CA",
    "sg:address":"1839 Brilliant Rd",
    "sg:city":"Castlegar",
    "sg:classifiers":[
        {
            "category":"Wholesale",
            "subcategory":"Construction Materials",
            "type":"Manufacturing & Wholesale Goods"
        }
    ],
    "sg:phone":"+1 250 365 2330",
    "sg:postcode":"V1N 4K2",
    "sg:province":"BC",
    "sg:tags":[
        "lumber"
    ],
    "wof:name":"Selkirk Cedar & Lumber",
    "wof:placetype":"venue"
},
  "geometry": {"coordinates":[-117.65418200000001,49.296253],"type":"Point"}
}