{
  "type": "Feature",
  "properties": {
    "addr:full":"40 Centennial Pky N Hamilton ON L8E 1H6",
    "addr:housenumber":"40",
    "addr:postcode":"l8e 1h6",
    "addr:street":"Centennial Pky N",
    "iso:country":"CA",
    "sg:address":"40 Centennial Pky N",
    "sg:city":"Hamilton",
    "sg:classifiers":[
        {
            "category":"Health Services",
            "subcategory":"Doctor",
            "type":"Services"
        }
    ],
    "sg:phone":"+1 905 561 8096",
    "sg:postcode":"L8E 1H6",
    "sg:province":"ON",
    "sg:tags":[
        "dentist"
    ],
    "wof:name":"Vujovic & Vujovic",
    "wof:placetype":"venue"
},
  "geometry": {"coordinates":[-79.763474,43.229397],"type":"Point"}
}