{
  "type": "Feature",
  "properties": {
    "iso:country":"CA",
    "sg:city":"Niagara Falls",
    "sg:classifiers":[
        {
            "category":"Professional",
            "subcategory":"Employment Agencies",
            "type":"Services"
        }
    ],
    "sg:phone":"+1 905 358 0021",
    "sg:postcode":"L2J 1A3",
    "sg:province":"ON",
    "sg:tags":[
        "opportunity"
    ],
    "wof:name":"Niagara Falls Employment Help",
    "wof:placetype":"venue"
},
  "geometry": {"coordinates":[-79.09744262700001,43.1151428223],"type":"Point"}
}