{
  "type": "Feature",
  "properties": {
    "addr:full":"1631 Yew St Vancouver BC V6K 3E6",
    "addr:housenumber":"1631",
    "addr:postcode":"v6k 3e6",
    "addr:street":"Yew St",
    "iso:country":"CA",
    "sg:address":"1631 Yew St",
    "sg:city":"Vancouver",
    "sg:classifiers":[
        {
            "category":"Restaurant",
            "type":"Food & Drink"
        }
    ],
    "sg:phone":"+1 604 731 4018",
    "sg:postcode":"V6K 3E6",
    "sg:province":"BC",
    "wof:name":"Cafe Zen on Yew",
    "wof:placetype":"venue"
},
  "geometry": {"coordinates":[-123.155197144,49.2714080811],"type":"Point"}
}