{
  "type": "Feature",
  "properties": {
    "addr:full":"55 Mill St S Port Hope ON L1A 2S7",
    "addr:housenumber":"55",
    "addr:postcode":"l1a 2s7",
    "addr:street":"Mill St S",
    "iso:country":"CA",
    "sg:address":"55 Mill St S",
    "sg:city":"Port Hope",
    "sg:classifiers":[
        {
            "category":"Restaurant",
            "type":"Food & Drink"
        }
    ],
    "sg:phone":"+1 905 885 8730",
    "sg:postcode":"L1A 2S7",
    "sg:province":"ON",
    "wof:name":"Kfc",
    "wof:placetype":"venue"
},
  "geometry": {"coordinates":[-78.2912979126,43.9484863281],"type":"Point"}
}