{
  "type": "Feature",
  "properties": {
    "iso:country":"CA",
    "sg:address":"3091 Homestead Dr",
    "sg:city":"Mount Hope",
    "sg:classifiers":[
        {
            "category":"Recreation",
            "type":"Entertainment"
        }
    ],
    "sg:phone":"+1 905 679 9809",
    "sg:postcode":"L0R 1W0",
    "sg:province":"ON",
    "sg:tags":[
        "club",
        "curling"
    ],
    "wof:name":"Glanford Curling Club",
    "wof:placetype":"venue"
},
  "geometry": {"coordinates":[-79.9126586914,43.1597976685],"type":"Point"}
}