{
  "type": "Feature",
  "properties": {
    "addr:full":"3650 Langstaff Rd Woodbridge ON L4L 9A8",
    "addr:housenumber":"3650",
    "addr:postcode":"l4l 9a8",
    "addr:street":"Langstaff Rd",
    "iso:country":"CA",
    "sg:address":"3650 Langstaff Rd",
    "sg:city":"Woodbridge",
    "sg:classifiers":[
        {
            "category":"Shopping",
            "subcategory":"Florist",
            "type":"Retail Goods"
        }
    ],
    "sg:phone":"+1 905 264 5459",
    "sg:postcode":"L4L 9A8",
    "sg:province":"ON",
    "wof:name":"Sandrina Floral & Gift Ltd",
    "wof:placetype":"venue"
},
  "geometry": {"coordinates":[-79.54922500000001,43.808491],"type":"Point"}
}