{
  "type": "Feature",
  "properties": {
    "addr:full":"2625 Line 12 Bradford ON L3Z 2A5",
    "addr:housenumber":"2625",
    "addr:postcode":"l3z 2a5",
    "addr:street":"Line 12",
    "iso:country":"CA",
    "sg:address":"2625 Line 12",
    "sg:city":"Bradford",
    "sg:classifiers":[
        {
            "category":"Building & Trades",
            "subcategory":"Construction",
            "type":"Services"
        }
    ],
    "sg:phone":"+1 416 766 2191",
    "sg:postcode":"L3Z 2A5",
    "sg:province":"ON",
    "sg:tags":[
        "excavating",
        "contractor"
    ],
    "wof:name":"Lansdowne Excavation",
    "wof:placetype":"venue"
},
  "geometry": {"coordinates":[-79.56366,44.114552],"type":"Point"}
}