{
  "type": "Feature",
  "properties": {
    "iso:country":"CA",
    "sg:address":"RR 1",
    "sg:city":"Sutton West",
    "sg:classifiers":[
        {
            "category":"Building & Trades",
            "subcategory":"Landscaping Services",
            "type":"Services"
        }
    ],
    "sg:phone":"+1 905 722 9860",
    "sg:postcode":"L0E 1R0",
    "sg:province":"ON",
    "sg:tags":[
        "tree"
    ],
    "wof:name":"Forest Glenn Tree Care Inc",
    "wof:placetype":"venue"
},
  "geometry": {"coordinates":[-79.361237,44.304867],"type":"Point"}
}