{
  "type": "Feature",
  "properties": {
    "addr:full":"Victoria BC V9A 7M8",
    "addr:postcode":"v9a 7m8",
    "iso:country":"CA",
    "sg:city":"Victoria",
    "sg:classifiers":[
        {
            "category":"Travel",
            "subcategory":"Travel Agent",
            "type":"Entertainment"
        }
    ],
    "sg:phone":"+1 250 953 2900",
    "sg:postcode":"V9A 7M8",
    "sg:province":"BC",
    "sg:tags":[
        "agency",
        "bureau"
    ],
    "wof:name":"Uniglobe Pacific Travel Ltd",
    "wof:placetype":"venue"
},
  "geometry": {"coordinates":[-123.364517212,48.428314209],"type":"Point"}
}