{
  "type": "Feature",
  "properties": {
    "addr:full":"4210 4th Ave Whitehorse YT Y1A 1K1",
    "addr:housenumber":"4210",
    "addr:postcode":"y1a 1k1",
    "addr:street":"4Th Ave",
    "iso:country":"CA",
    "sg:address":"4210 4th Ave",
    "sg:city":"Whitehorse",
    "sg:classifiers":[
        {
            "category":"Government",
            "subcategory":"Office",
            "type":"Public Place"
        }
    ],
    "sg:phone":"+1 867 668 8340",
    "sg:postcode":"Y1A 1K1",
    "sg:province":"YT",
    "sg:tags":[
        "village"
    ],
    "wof:name":"Whitehorse Building Inspection",
    "wof:placetype":"venue"
},
  "geometry": {"coordinates":[-135.06407165499999,60.7264175415],"type":"Point"}
}