{
  "type": "Feature",
  "properties": {
    "iso:country":"CA",
    "sg:address":"2915 Boul Du Cure-Labelle",
    "sg:city":"Prevost",
    "sg:classifiers":[
        {
            "category":"Retail",
            "subcategory":"Auto Repair",
            "type":"Services"
        }
    ],
    "sg:phone":"+1 450 224 4026",
    "sg:postcode":"J0R 1T0",
    "sg:province":"QC",
    "sg:tags":[
        "body",
        "automobile",
        "painting"
    ],
    "wof:name":"Speciale Carrosserie",
    "wof:placetype":"venue"
},
  "geometry": {"coordinates":[-74.0702056885,45.8613014221],"type":"Point"}
}