{
  "type": "Feature",
  "properties": {
    "addr:full":"2675 Rue DE Varennes Trois-Rivieres QC G8Z 3P4",
    "addr:housenumber":"2675",
    "addr:postcode":"g8z 3p4",
    "addr:street":"Rue De Varennes Trois-Rivieres",
    "iso:country":"CA",
    "sg:address":"2675 Rue DE Varennes",
    "sg:city":"Trois-Rivieres",
    "sg:classifiers":[
        {
            "category":"Health Services",
            "subcategory":"Chiropractor",
            "type":"Services"
        }
    ],
    "sg:phone":"+1 819 378 1313",
    "sg:postcode":"G8Z 3P4",
    "sg:province":"QC",
    "wof:name":"Marchand, Jean-Denis DC",
    "wof:placetype":"venue"
},
  "geometry": {"coordinates":[-72.55841100000001,46.360958],"type":"Point"}
}