{
  "type": "Feature",
  "properties": {
    "addr:full":"8149 Bench Row Rd Vernon BC V1H 1H3",
    "addr:housenumber":"8149",
    "addr:postcode":"v1h 1h3",
    "addr:street":"Bench Row Rd",
    "iso:country":"CA",
    "sg:address":"8149 Bench Row Rd",
    "sg:city":"Vernon",
    "sg:classifiers":[
        {
            "category":"Building & Trades",
            "subcategory":"Construction",
            "type":"Services"
        }
    ],
    "sg:phone":"+1 250 542 3276",
    "sg:postcode":"V1H 1H3",
    "sg:province":"BC",
    "sg:tags":[
        "contractor",
        "general"
    ],
    "wof:name":"Landing Construction CO",
    "wof:placetype":"venue"
},
  "geometry": {"coordinates":[-119.37034606900001,50.225818634],"type":"Point"}
}