{
  "type": "Feature",
  "properties": {
    "addr:full":"North York ON M3M 2G6",
    "addr:postcode":"m3m 2g6",
    "iso:country":"CA",
    "sg:city":"North York",
    "sg:classifiers":[
        {
            "category":"Health Services",
            "subcategory":"Chiropractor",
            "type":"Services"
        }
    ],
    "sg:phone":"+1 416 638 2225",
    "sg:postcode":"M3M 2G6",
    "sg:province":"ON",
    "wof:name":"Network Care Ctr",
    "wof:placetype":"venue"
},
  "geometry": {"coordinates":[-79.48245199999999,43.729244],"type":"Point"}
}