{
  "type": "Feature",
  "properties": {
    "addr:full":"260 9E Ave Ferme-Neuve QC J0W 1C0",
    "addr:housenumber":"260",
    "addr:postcode":"j0w 1c0",
    "addr:street":"9E Ave",
    "iso:country":"CA",
    "sg:address":"260 9E Ave",
    "sg:city":"Ferme-Neuve",
    "sg:classifiers":[
        {
            "category":"Retail",
            "subcategory":"Animal Services",
            "type":"Services"
        }
    ],
    "sg:phone":"+1 819 587 2244",
    "sg:postcode":"J0W 1C0",
    "sg:province":"QC",
    "sg:tags":[
        "pet",
        "shop",
        "grooming",
        "washing"
    ],
    "wof:name":"Centre Animalier Chez Kiam",
    "wof:placetype":"venue"
},
  "geometry": {"coordinates":[-75.45281199999999,46.701519],"type":"Point"}
}