{
  "type": "Feature",
  "properties": {
    "addr:full":"540 Main St Hudson Bay SK S0E 0Y0",
    "addr:housenumber":"540",
    "addr:postcode":"s0e 0y0",
    "addr:street":"Main St",
    "iso:country":"CA",
    "sg:address":"540 Main St",
    "sg:city":"Hudson Bay",
    "sg:classifiers":[
        {
            "category":"Organizations",
            "subcategory":"Religious Organization",
            "type":"Services"
        }
    ],
    "sg:phone":"+1 306 865 2623",
    "sg:postcode":"S0E 0Y0",
    "sg:province":"SK",
    "sg:tags":[
        "church"
    ],
    "wof:name":"Pineridge Fellowship Chapel",
    "wof:placetype":"venue"
},
  "geometry": {"coordinates":[-102.391228,52.855785],"type":"Point"}
}