{
  "type": "Feature",
  "properties": {
    "addr:full":"400 Park Ave W Chatham ON N7M 1W9",
    "addr:housenumber":"400",
    "addr:postcode":"n7m 1w9",
    "addr:street":"Park Ave W",
    "iso:country":"CA",
    "sg:address":"400 Park Ave W",
    "sg:city":"Chatham",
    "sg:classifiers":[
        {
            "category":"Building & Trades",
            "subcategory":"Electrical",
            "type":"Services"
        }
    ],
    "sg:phone":"+1 519 351 0484",
    "sg:postcode":"N7M 1W9",
    "sg:province":"ON",
    "sg:tags":[
        "electric",
        "contractor"
    ],
    "wof:name":"Honey Electric Ltd",
    "wof:placetype":"venue"
},
  "geometry": {"coordinates":[-82.1892242432,42.3883895874],"type":"Point"}
}