{
  "type": "Feature",
  "properties": {
    "addr:full":"6114 County Rd 46 Comber ON N0P 1J0",
    "addr:housenumber":"6114;46",
    "addr:postcode":"n0p 1j0",
    "addr:street":"County Rd",
    "iso:country":"CA",
    "sg:address":"6114 County Rd 46",
    "sg:city":"Comber",
    "sg:phone":"+1 519 687 2112",
    "sg:postcode":"N0P 1J0",
    "sg:province":"ON",
    "sg:tags":[
        "oil"
    ],
    "wof:name":"Jack Smith Fuels",
    "wof:placetype":"venue"
},
  "geometry": {"coordinates":[-82.552757,42.231224],"type":"Point"}
}