{
  "type": "Feature",
  "properties": {
    "iso:country":"CA",
    "sg:address":"301 Mississauga Ave",
    "sg:city":"Elliot Lake",
    "sg:classifiers":[
        {
            "category":"Recreation",
            "type":"Entertainment"
        }
    ],
    "sg:phone":"+1 705 461 7209",
    "sg:postcode":"P5A 1E8",
    "sg:province":"ON",
    "sg:tags":[
        "government",
        "swimming"
    ],
    "wof:name":"Elliot Lake Municipal Pool",
    "wof:placetype":"venue"
},
  "geometry": {"coordinates":[-82.661277771,46.3757247925],"type":"Point"}
}