{
  "type": "Feature",
  "properties": {
    "addr:full":"4814 50 St Red Deer AB T4N 1X4",
    "addr:housenumber":"4814",
    "addr:postcode":"t4n 1x4",
    "addr:street":"50 St",
    "iso:country":"CA",
    "sg:address":"4814 50 St",
    "sg:city":"Red Deer",
    "sg:classifiers":[
        {
            "category":"Real Estate",
            "subcategory":"Real Estate Agent",
            "type":"Services"
        }
    ],
    "sg:phone":"+1 403 342 7700",
    "sg:postcode":"T4N 1X4",
    "sg:province":"AB",
    "wof:name":"Royal Carpet Realty Ltd",
    "wof:placetype":"venue"
},
  "geometry": {"coordinates":[-113.809555,52.269142],"type":"Point"}
}