{
  "type": "Feature",
  "properties": {
    "iso:country":"CA",
    "sg:city":"Niagara on the Lake",
    "sg:classifiers":[
        {
            "category":"Shopping",
            "subcategory":"Clothing, Apparel, & Fashions",
            "type":"Retail Goods"
        }
    ],
    "sg:phone":"+1 905 468 8011",
    "sg:postcode":"L0S 1J0",
    "sg:province":"ON",
    "sg:tags":[
        "hat"
    ],
    "wof:name":"Beau Chapeau Hat Shop",
    "wof:placetype":"venue"
},
  "geometry": {"coordinates":[-79.0748062134,43.2565994263],"type":"Point"}
}