{
  "type": "Feature",
  "properties": {
    "addr:full":"4341 50 St NW Edmonton AB T6L 7E8",
    "addr:housenumber":"4341",
    "addr:postcode":"t6l 7e8",
    "addr:street":"50 St Nw",
    "iso:country":"CA",
    "sg:address":"4341 50 St NW",
    "sg:city":"Edmonton",
    "sg:classifiers":[
        {
            "category":"Restaurant",
            "type":"Food & Drink"
        }
    ],
    "sg:phone":"+1 780 490 5577",
    "sg:postcode":"T6L 7E8",
    "sg:province":"AB",
    "sg:tags":[
        "shop",
        "coffee"
    ],
    "wof:name":"Cappuccino Affair",
    "wof:placetype":"venue"
},
  "geometry": {"coordinates":[-113.417778,53.480846],"type":"Point"}
}