{
  "type": "Feature",
  "properties": {
    "addr:full":"8725 158 St Surrey BC V4N 1G9",
    "addr:housenumber":"8725",
    "addr:postcode":"v4n 1g9",
    "addr:street":"158 St",
    "iso:country":"CA",
    "sg:address":"8725 158 St",
    "sg:city":"Surrey",
    "sg:classifiers":[
        {
            "category":"Organizations",
            "subcategory":"Religious Organization",
            "type":"Services"
        }
    ],
    "sg:phone":"+1 604 597 2255",
    "sg:postcode":"V4N 1G9",
    "sg:province":"BC",
    "sg:tags":[
        "church"
    ],
    "wof:name":"Fleetwood Gospel Hall",
    "wof:placetype":"venue"
},
  "geometry": {"coordinates":[-122.785255432,49.1614494324],"type":"Point"}
}