{
  "type": "Feature",
  "properties": {
    "addr:full":"8300 Rue Industrielle Sorel-Tracy QC J3R 5R3",
    "addr:housenumber":"8300",
    "addr:postcode":"j3r 5r3",
    "addr:street":"Rue Industrielle",
    "iso:country":"CA",
    "sg:address":"8300 Rue Industrielle",
    "sg:city":"Sorel-Tracy",
    "sg:classifiers":[
        {
            "category":"Social Services",
            "subcategory":"Child Care",
            "type":"Services"
        }
    ],
    "sg:phone":"+1 450 746 0842",
    "sg:postcode":"J3R 5R3",
    "sg:province":"QC",
    "wof:name":"Cpe LA Marelle Inc",
    "wof:placetype":"venue"
},
  "geometry": {"coordinates":[-73.156441,46.013805],"type":"Point"}
}