{
  "type": "Feature",
  "properties": {
    "addr:full":"98 Shawinigan Dr SW Calgary AB T2Y 2V7",
    "addr:housenumber":"98",
    "addr:postcode":"t2y 2v7",
    "addr:street":"Shawinigan Dr Sw",
    "iso:country":"CA",
    "sg:address":"98 Shawinigan Dr SW",
    "sg:city":"Calgary",
    "sg:classifiers":[
        {
            "category":"Wholesale",
            "subcategory":"Machinery & Supplies",
            "type":"Manufacturing & Wholesale Goods"
        }
    ],
    "sg:phone":"+1 403 256 0409",
    "sg:postcode":"T2Y 2V7",
    "sg:province":"AB",
    "sg:tags":[
        "instrument",
        "surveying"
    ],
    "wof:name":"R H Optical Instruments Svc",
    "wof:placetype":"venue"
},
  "geometry": {"coordinates":[-114.080536,50.905338],"type":"Point"}
}