{
  "type": "Feature",
  "properties": {
    "iso:country":"CA",
    "sg:address":"240 Skinner St",
    "sg:city":"Nanaimo",
    "sg:classifiers":[
        {
            "category":"Bars & Pubs",
            "type":"Food & Drink"
        }
    ],
    "sg:phone":"+1 250 753 8787",
    "sg:postcode":"V9R 5E9",
    "sg:province":"BC",
    "sg:tags":[
        "club",
        "night"
    ],
    "wof:name":"Desperado's",
    "wof:placetype":"venue"
},
  "geometry": {"coordinates":[-123.938652,49.16827],"type":"Point"}
}