{
  "type": "Feature",
  "properties": {
    "addr:full":"Lorette MB R0A 0Y0",
    "addr:postcode":"r0a 0y0",
    "iso:country":"CA",
    "sg:city":"Lorette",
    "sg:classifiers":[
        {
            "category":"Recreation",
            "type":"Entertainment"
        }
    ],
    "sg:phone":"+1 204 878 4155",
    "sg:postcode":"R0A 0Y0",
    "sg:province":"MB",
    "sg:tags":[
        "hall",
        "auditorium"
    ],
    "wof:name":"Centre Jubinville",
    "wof:placetype":"venue"
},
  "geometry": {"coordinates":[-96.874702,49.739723],"type":"Point"}
}