{
  "type": "Feature",
  "properties": {
    "addr:full":"5845 Rue Saint-Jacques Montreal QC H4A 2G1",
    "addr:housenumber":"5845",
    "addr:postcode":"h4a 2g1",
    "addr:street":"Rue Saint-Jacques",
    "iso:country":"CA",
    "sg:address":"5845 Rue Saint-Jacques",
    "sg:city":"Montreal",
    "sg:classifiers":[
        {
            "category":"Retail",
            "subcategory":"Auto Repair",
            "type":"Services"
        }
    ],
    "sg:phone":"+1 514 487 9388",
    "sg:postcode":"H4A 2G1",
    "sg:province":"QC",
    "sg:tags":[
        "body",
        "automobile",
        "painting"
    ],
    "wof:name":"International Sports Car",
    "wof:placetype":"venue"
},
  "geometry": {"coordinates":[-73.610824585,45.4662742615],"type":"Point"}
}