{
  "type": "Feature",
  "properties": {
    "addr:full":"Surrey BC V4A 4N3",
    "addr:postcode":"v4a 4n3",
    "iso:country":"CA",
    "sg:city":"Surrey",
    "sg:classifiers":[
        {
            "category":"Restaurant",
            "type":"Food & Drink"
        }
    ],
    "sg:phone":"+1 604 541 7400",
    "sg:postcode":"V4A 4N3",
    "sg:province":"BC",
    "wof:name":"Buon Appetito",
    "wof:placetype":"venue"
},
  "geometry": {"coordinates":[-122.801323,49.033222],"type":"Point"}
}