{
  "type": "Feature",
  "properties": {
    "addr:full":"Calgary AB T2E 7H7",
    "addr:postcode":"t2e 7h7",
    "iso:country":"CA",
    "sg:city":"Calgary",
    "sg:classifiers":[
        {
            "category":"Freight",
            "type":"Transportation"
        }
    ],
    "sg:phone":"+1 403 295 1505",
    "sg:postcode":"T2E 7H7",
    "sg:province":"AB",
    "wof:name":"Transera Intl Logistics Ltd",
    "wof:placetype":"venue"
},
  "geometry": {"coordinates":[-114.04476200000001,51.11404],"type":"Point"}
}