{
  "type": "Feature",
  "properties": {
    "addr:full":"103 Second St E Duchess AB T0J 0Z0",
    "addr:housenumber":"103",
    "addr:postcode":"t0j 0z0",
    "addr:street":"Second St E Duchess",
    "iso:country":"CA",
    "sg:address":"103 Second St E",
    "sg:city":"Duchess",
    "sg:classifiers":[
        {
            "category":"Government",
            "subcategory":"Office",
            "type":"Public Place"
        }
    ],
    "sg:phone":"+1 403 378 4452",
    "sg:postcode":"T0J 0Z0",
    "sg:province":"AB",
    "sg:tags":[
        "municipality"
    ],
    "wof:name":"Village of Duchess Office",
    "wof:placetype":"venue"
},
  "geometry": {"coordinates":[-111.903648,50.732094],"type":"Point"}
}