{
  "type": "Feature",
  "properties": {
    "addr:full":"288 Victoria St Sudbury ON P3C 1K4",
    "addr:housenumber":"288",
    "addr:postcode":"p3c 1k4",
    "addr:street":"Victoria St",
    "iso:country":"CA",
    "sg:address":"288 Victoria St",
    "sg:city":"Sudbury",
    "sg:classifiers":[
        {
            "category":"Wholesale",
            "subcategory":"Electrical",
            "type":"Manufacturing & Wholesale Goods"
        }
    ],
    "sg:phone":"+1 705 674 6070",
    "sg:postcode":"P3C 1K4",
    "sg:province":"ON",
    "sg:tags":[
        "alarm",
        "burglar",
        "system"
    ],
    "wof:name":"Derro Security & Alarm Systems",
    "wof:placetype":"venue"
},
  "geometry": {"coordinates":[-81.006432,46.489346],"type":"Point"}
}