{
  "type": "Feature",
  "properties": {
    "addr:full":"6405 Boul Gouin O Montreal QC H4K 1A9",
    "addr:housenumber":"6405",
    "addr:postcode":"h4k 1a9",
    "addr:street":"Boul Gouin O",
    "iso:country":"CA",
    "sg:address":"6405 Boul Gouin O",
    "sg:city":"Montreal",
    "sg:classifiers":[
        {
            "category":"Social Services",
            "subcategory":"Child Care",
            "type":"Services"
        }
    ],
    "sg:phone":"+1 514 331 8555",
    "sg:postcode":"H4K 1A9",
    "sg:province":"QC",
    "wof:name":"Garderie Kinderville Daycare",
    "wof:placetype":"venue"
},
  "geometry": {"coordinates":[-73.72427399999999,45.529251],"type":"Point"}
}