{
  "type": "Feature",
  "properties": {
    "addr:full":"200 Rue Heriot # B Drummondville QC J2C 1J8",
    "addr:housenumber":"200",
    "addr:postcode":"j2c 1j8",
    "addr:street":"Rue Heriot # B",
    "iso:country":"CA",
    "sg:address":"200 Rue Heriot # B",
    "sg:city":"Drummondville",
    "sg:classifiers":[
        {
            "category":"Wholesale",
            "subcategory":"Office Equipment",
            "type":"Manufacturing & Wholesale Goods"
        }
    ],
    "sg:phone":"+1 819 477 7476",
    "sg:postcode":"J2C 1J8",
    "sg:province":"QC",
    "sg:tags":[
        "machine",
        "duplicating",
        "copying"
    ],
    "wof:name":"Service & Equipement Jdl",
    "wof:placetype":"venue"
},
  "geometry": {"coordinates":[-72.48941802980001,45.8856658936],"type":"Point"}
}