{
  "type": "Feature",
  "properties": {
    "addr:full":"4729 50 St St Paul AB T0A 3A4",
    "addr:housenumber":"4729",
    "addr:postcode":"t0a 3a4",
    "addr:street":"50 St",
    "iso:country":"CA",
    "sg:address":"4729 50 St",
    "sg:city":"St Paul",
    "sg:classifiers":[
        {
            "category":"Home & Garden",
            "subcategory":"Home Furnishings",
            "type":"Retail Goods"
        }
    ],
    "sg:phone":"+1 780 645 5003",
    "sg:postcode":"T0A 3A4",
    "sg:province":"AB",
    "sg:tags":[
        "curtain",
        "made",
        "drapery"
    ],
    "wof:name":"Custom Curtains By Carole",
    "wof:placetype":"venue"
},
  "geometry": {"coordinates":[-111.296936,53.988678],"type":"Point"}
}