{
  "type": "Feature",
  "properties": {
    "addr:full":"Elmsdale NS B2S 1C9",
    "addr:postcode":"b2s 1c9",
    "iso:country":"CA",
    "sg:city":"Elmsdale",
    "sg:classifiers":[
        {
            "category":"Autos & Motor Vehicles",
            "subcategory":"Auto Supplies",
            "type":"Retail Goods"
        }
    ],
    "sg:phone":"+1 902 883 7040",
    "sg:postcode":"B2S 1C9",
    "sg:province":"NS",
    "sg:tags":[
        "automobile",
        "parts"
    ],
    "wof:name":"Sangster's Automotive Supplies",
    "wof:placetype":"venue"
},
  "geometry": {"coordinates":[-63.5238227844,44.9525184631],"type":"Point"}
}