{
  "type": "Feature",
  "properties": {
    "addr:full":"15 Rue Du Sault-Au-Matelot Quebec QC G1K 3Y7",
    "addr:housenumber":"15",
    "addr:postcode":"g1k 3y7",
    "addr:street":"Rue Du Sault-Au-Matelot",
    "iso:country":"CA",
    "sg:address":"15 Rue Du Sault-Au-Matelot",
    "sg:city":"Quebec",
    "sg:classifiers":[
        {
            "category":"Travel",
            "subcategory":"Hotels & Motels",
            "type":"Entertainment"
        }
    ],
    "sg:phone":"+1 418 692 4823",
    "sg:postcode":"G1K 3Y7",
    "sg:province":"QC",
    "wof:name":"Hotel Le Priori",
    "wof:placetype":"venue"
},
  "geometry": {"coordinates":[-71.203293,46.814346],"type":"Point"}
}