{
  "type": "Feature",
  "properties": {
    "addr:full":"4535 Av D'Orleans Montreal QC H1X 2K3",
    "addr:housenumber":"4535",
    "addr:postcode":"h1x 2k3",
    "addr:street":"Av D'Orleans",
    "iso:country":"CA",
    "sg:address":"4535 Av D'Orleans",
    "sg:city":"Montreal",
    "sg:classifiers":[
        {
            "category":"Health Services",
            "subcategory":"Doctor",
            "type":"Services"
        }
    ],
    "sg:phone":"+1 514 259 5760",
    "sg:postcode":"H1X 2K3",
    "sg:province":"QC",
    "sg:tags":[
        "dentist"
    ],
    "wof:name":"Di Nolfo, Charles DDS",
    "wof:placetype":"venue"
},
  "geometry": {"coordinates":[-73.563919,45.555401],"type":"Point"}
}