{
  "type": "Feature",
  "properties": {
    "addr:full":"Grande Prairie AB T8V 0Y3",
    "addr:postcode":"t8v 0y3",
    "iso:country":"CA",
    "sg:city":"Grande Prairie",
    "sg:classifiers":[
        {
            "category":"Professional",
            "subcategory":"Accounting & Tax Preparation",
            "type":"Services"
        }
    ],
    "sg:phone":"+1 780 538 2500",
    "sg:postcode":"T8V 0Y3",
    "sg:province":"AB",
    "sg:tags":[
        "bookkeeping",
        "general"
    ],
    "wof:name":"Office Handlers Inc",
    "wof:placetype":"venue"
},
  "geometry": {"coordinates":[-118.79821,55.171707],"type":"Point"}
}