{
  "type": "Feature",
  "properties": {
    "addr:full":"718 Division St Kingston ON K7K 4B9",
    "addr:housenumber":"718",
    "addr:postcode":"k7k 4b9",
    "addr:street":"Division St",
    "iso:country":"CA",
    "sg:address":"718 Division St",
    "sg:city":"Kingston",
    "sg:classifiers":[
        {
            "category":"Real Estate",
            "subcategory":"Developer",
            "type":"Services"
        }
    ],
    "sg:phone":"+1 613 548 4343",
    "sg:postcode":"K7K 4B9",
    "sg:province":"ON",
    "sg:tags":[
        "cemetery"
    ],
    "wof:name":"St Mary's Cemetery",
    "wof:placetype":"venue"
},
  "geometry": {"coordinates":[-76.496567,44.250904],"type":"Point"}
}