{
  "type": "Feature",
  "properties": {
    "addr:full":"935 Rte DE LA Seigneurie Saint-Roch-Des-Aulnaies QC G0R 4E0",
    "addr:housenumber":"935",
    "addr:postcode":"g0r 4e0",
    "addr:street":"Rte De La Seigneurie",
    "iso:country":"CA",
    "sg:address":"935 Rte DE LA Seigneurie",
    "sg:city":"Saint-Roch-Des-Aulnaies",
    "sg:classifiers":[
        {
            "category":"Shopping",
            "subcategory":"Hobbies, Toys, & Games",
            "type":"Retail Goods"
        }
    ],
    "sg:phone":"+1 418 354 2182",
    "sg:postcode":"G0R 4E0",
    "sg:province":"QC",
    "sg:tags":[
        "kite"
    ],
    "wof:name":"Gite Du Cerf-Volant",
    "wof:placetype":"venue"
},
  "geometry": {"coordinates":[-70.1727981567,47.310634613],"type":"Point"}
}