{
  "type": "Feature",
  "properties": {
    "addr:full":"Hamilton ON L8P 3A9",
    "addr:postcode":"l8p 3a9",
    "iso:country":"CA",
    "sg:city":"Hamilton",
    "sg:classifiers":[
        {
            "category":"Health Services",
            "subcategory":"Doctor",
            "type":"Services"
        }
    ],
    "sg:phone":"+1 905 524 1125",
    "sg:postcode":"L8P 3A9",
    "sg:province":"ON",
    "sg:tags":[
        "physician",
        "surgeon"
    ],
    "wof:name":"Mosakoski, J F MD",
    "wof:placetype":"venue"
},
  "geometry": {"coordinates":[-79.871963501,43.2503433228],"type":"Point"}
}