{
  "type": "Feature",
  "properties": {
    "addr:full":"905 Marlborough Wood Halifax NS B3H 1H9",
    "addr:housenumber":"905",
    "addr:postcode":"b3h 1h9",
    "addr:street":"Marlborough Wood",
    "iso:country":"CA",
    "sg:address":"905 Marlborough Wood",
    "sg:city":"Halifax",
    "sg:classifiers":[
        {
            "category":"Professional",
            "subcategory":"Management & Consulting",
            "type":"Services"
        }
    ],
    "sg:phone":"+1 902 429 2205",
    "sg:postcode":"B3H 1H9",
    "sg:province":"NS",
    "sg:tags":[
        "marketing",
        "export",
        "consultant"
    ],
    "wof:name":"R & D Lyons Consultants Ltd",
    "wof:placetype":"venue"
},
  "geometry": {"coordinates":[-63.5870933533,44.628818512],"type":"Point"}
}