{
  "type": "Feature",
  "properties": {
    "addr:full":"44360 Yale Rd Chilliwack BC V2R 4H1",
    "addr:housenumber":"44360",
    "addr:postcode":"v2r 4h1",
    "addr:street":"Yale Rd",
    "iso:country":"CA",
    "sg:address":"44360 Yale Rd",
    "sg:city":"Chilliwack",
    "sg:classifiers":[
        {
            "category":"Manufacturing",
            "subcategory":"Tools & Machinery",
            "type":"Manufacturing & Wholesale Goods"
        }
    ],
    "sg:phone":"+1 604 792 0402",
    "sg:postcode":"V2R 4H1",
    "sg:province":"BC",
    "wof:name":"Pacific Coast Articulated",
    "wof:placetype":"venue"
},
  "geometry": {"coordinates":[-121.996651,49.144909],"type":"Point"}
}