{
  "type": "Feature",
  "properties": {
    "addr:full":"353 Eveline St Selkirk MB R1A 1N1",
    "addr:housenumber":"353",
    "addr:postcode":"r1a 1n1",
    "addr:street":"Eveline St",
    "iso:country":"CA",
    "sg:address":"353 Eveline St",
    "sg:city":"Selkirk",
    "sg:classifiers":[
        {
            "category":"Health Services",
            "subcategory":"Optometrist",
            "type":"Services"
        }
    ],
    "sg:phone":"+1 204 482 5726",
    "sg:postcode":"R1A 1N1",
    "sg:province":"MB",
    "wof:name":"Selkirk Vision Ctr",
    "wof:placetype":"venue"
},
  "geometry": {"coordinates":[-96.871368,50.142048],"type":"Point"}
}