{
  "type": "Feature",
  "properties": {
    "addr:full":"5603 148 St NW Edmonton AB T6H 4T7",
    "addr:housenumber":"5603",
    "addr:postcode":"t6h 4t7",
    "addr:street":"148 St Nw",
    "iso:country":"CA",
    "sg:address":"5603 148 St NW",
    "sg:city":"Edmonton",
    "sg:classifiers":[
        {
            "category":"Education",
            "subcategory":"School",
            "type":"Public Place"
        }
    ],
    "sg:phone":"+1 780 434 1190",
    "sg:postcode":"T6H 4T7",
    "sg:province":"AB",
    "wof:name":"Tempo School",
    "wof:placetype":"venue"
},
  "geometry": {"coordinates":[-113.57485200000001,53.494286],"type":"Point"}
}