{
  "type": "Feature",
  "properties": {
    "addr:full":"124 Cote Du Passage Levis QC G6V 5S9",
    "addr:housenumber":"124",
    "addr:postcode":"g6v 5s9",
    "addr:street":"Cote Du Passage",
    "iso:country":"CA",
    "sg:address":"124 Cote Du Passage",
    "sg:city":"Levis",
    "sg:classifiers":[
        {
            "category":"Personal",
            "subcategory":"Beauty Salon",
            "type":"Services"
        }
    ],
    "sg:phone":"+1 418 838 2525",
    "sg:postcode":"G6V 5S9",
    "sg:province":"QC",
    "sg:tags":[
        "school"
    ],
    "wof:name":"Institut Matis Sylvie Leclerc",
    "wof:placetype":"venue"
},
  "geometry": {"coordinates":[-71.18143463129999,46.8049087524],"type":"Point"}
}