{
  "type": "Feature",
  "properties": {
    "addr:full":"961 Pond Mills Rd London ON N6N 1C3",
    "addr:housenumber":"961",
    "addr:postcode":"n6n 1c3",
    "addr:street":"Pond Mills Rd",
    "iso:country":"CA",
    "sg:address":"961 Pond Mills Rd",
    "sg:city":"London",
    "sg:classifiers":[
        {
            "category":"Home & Garden",
            "subcategory":"Building Materials",
            "type":"Retail Goods"
        }
    ],
    "sg:phone":"+1 519 681 2870",
    "sg:postcode":"N6N 1C3",
    "sg:province":"ON",
    "sg:tags":[
        "siding"
    ],
    "wof:name":"Gentek Building Products Ltd",
    "wof:placetype":"venue"
},
  "geometry": {"coordinates":[-81.1905212402,42.9307746887],"type":"Point"}
}