{
  "type": "Feature",
  "properties": {
    "iso:country":"CA",
    "sg:address":"562 Catharine St N",
    "sg:city":"Hamilton",
    "sg:classifiers":[
        {
            "category":"Freight",
            "type":"Transportation"
        }
    ],
    "sg:phone":"+1 905 524 0576",
    "sg:postcode":"L8L 4V5",
    "sg:province":"ON",
    "sg:tags":[
        "commercial",
        "storage"
    ],
    "wof:name":"Econo Storage & Rental",
    "wof:placetype":"venue"
},
  "geometry": {"coordinates":[-79.857681,43.272175],"type":"Point"}
}