{
  "type": "Feature",
  "properties": {
    "addr:full":"2085 Yonge St Toronto ON M4S 2A4",
    "addr:housenumber":"2085",
    "addr:postcode":"m4s 2a4",
    "addr:street":"Yonge St",
    "iso:country":"CA",
    "sg:address":"2085 Yonge St",
    "sg:city":"Toronto",
    "sg:classifiers":[
        {
            "category":"Shopping",
            "subcategory":"Clothing, Apparel, & Fashions",
            "type":"Retail Goods"
        }
    ],
    "sg:phone":"+1 416 485 2568",
    "sg:postcode":"M4S 2A4",
    "sg:province":"ON",
    "sg:tags":[
        "furnishing"
    ],
    "wof:name":"Testa Uomo",
    "wof:placetype":"venue"
},
  "geometry": {"coordinates":[-79.39733886720001,43.7027702332],"type":"Point"}
}