{
  "type": "Feature",
  "properties": {
    "addr:full":"1255 Venables St Vancouver BC V6A 3X6",
    "addr:housenumber":"1255",
    "addr:postcode":"v6a 3x6",
    "addr:street":"Venables St",
    "iso:country":"CA",
    "sg:address":"1255 Venables St",
    "sg:city":"Vancouver",
    "sg:classifiers":[
        {
            "category":"Manufacturing",
            "subcategory":"Tools & Machinery",
            "type":"Manufacturing & Wholesale Goods"
        }
    ],
    "sg:phone":"+1 604 253 6611",
    "sg:postcode":"V6A 3X6",
    "sg:province":"BC",
    "sg:tags":[
        "machine",
        "making",
        "ice",
        "equipment"
    ],
    "wof:name":"Russell Food Equipment Ltd",
    "wof:placetype":"venue"
},
  "geometry": {"coordinates":[-123.07810974100001,49.2769432068],"type":"Point"}
}