{
  "type": "Feature",
  "properties": {
    "addr:full":"Surrey BC V3R 4B1",
    "addr:postcode":"v3r 4b1",
    "iso:country":"CA",
    "sg:city":"Surrey",
    "sg:classifiers":[
        {
            "category":"Travel",
            "subcategory":"Travel Agent",
            "type":"Entertainment"
        }
    ],
    "sg:phone":"+1 604 583 1388",
    "sg:postcode":"V3R 4B1",
    "sg:province":"BC",
    "sg:tags":[
        "agency",
        "bureau"
    ],
    "wof:name":"Sea World Travel",
    "wof:placetype":"venue"
},
  "geometry": {"coordinates":[-122.806618,49.190735],"type":"Point"}
}