{
  "type": "Feature",
  "properties": {
    "addr:full":"129 South St Gananoque ON K7G 1A1",
    "addr:housenumber":"129",
    "addr:postcode":"k7g 1a1",
    "addr:street":"South St",
    "iso:country":"CA",
    "sg:address":"129 South St",
    "sg:city":"Gananoque",
    "sg:classifiers":[
        {
            "category":"Recreation",
            "subcategory":"Marina",
            "type":"Entertainment"
        }
    ],
    "sg:phone":"+1 613 382 4315",
    "sg:postcode":"K7G 1A1",
    "sg:province":"ON",
    "sg:tags":[
        "dealer",
        "boat",
        "sales"
    ],
    "wof:name":"Gordon Marine Ltd",
    "wof:placetype":"venue"
},
  "geometry": {"coordinates":[-76.156631,44.325733],"type":"Point"}
}