{
  "type": "Feature",
  "properties": {
    "addr:full":"Montreal QC H3H 1R4",
    "addr:postcode":"h3h 1r4",
    "iso:country":"CA",
    "sg:city":"Montreal",
    "sg:classifiers":[
        {
            "category":"Professional",
            "subcategory":"Business Services",
            "type":"Services"
        }
    ],
    "sg:phone":"+1 514 933 9916",
    "sg:postcode":"H3H 1R4",
    "sg:province":"QC",
    "sg:tags":[
        "notary"
    ],
    "wof:name":"Dumont Plante",
    "wof:placetype":"venue"
},
  "geometry": {"coordinates":[-73.549133,45.522472],"type":"Point"}
}