{
  "type": "Feature",
  "properties": {
    "iso:country":"CA",
    "sg:address":"47 Rue Du Parc",
    "sg:city":"Amqui",
    "sg:classifiers":[
        {
            "category":"Autos & Motor Vehicles",
            "subcategory":"Fuel & Gas Station",
            "type":"Retail Goods"
        }
    ],
    "sg:phone":"+1 418 629 2528",
    "sg:postcode":"G5J 2L7",
    "sg:province":"QC",
    "sg:tags":[
        "oil"
    ],
    "wof:name":"Station Leon Deschenes",
    "wof:placetype":"venue"
},
  "geometry": {"coordinates":[-67.43561553959999,48.4626159668],"type":"Point"}
}