{
  "type": "Feature",
  "properties": {
    "iso:country":"CA",
    "sg:address":"60 Churchill Dr",
    "sg:city":"Barrie",
    "sg:classifiers":[
        {
            "category":"Wholesale",
            "subcategory":"Scrap",
            "type":"Manufacturing & Wholesale Goods"
        }
    ],
    "sg:phone":"+1 705 733 2573",
    "sg:postcode":"L4N 8Z5",
    "sg:province":"ON",
    "sg:tags":[
        "waste"
    ],
    "wof:name":"2 R Svc Inc",
    "wof:placetype":"venue"
},
  "geometry": {"coordinates":[-79.6756820679,44.3440628052],"type":"Point"}
}