{
  "type": "Feature",
  "properties": {
    "addr:full":"5205 Rue Saint-Zotique E Montreal QC H1T 1N6",
    "addr:housenumber":"5205",
    "addr:postcode":"h1t 1n6",
    "addr:street":"Rue Saint-Zotique E",
    "iso:country":"CA",
    "sg:address":"5205 Rue Saint-Zotique E",
    "sg:city":"Montreal",
    "sg:classifiers":[
        {
            "category":"Organizations",
            "subcategory":"Religious Organization",
            "type":"Services"
        }
    ],
    "sg:phone":"+1 514 727 3723",
    "sg:postcode":"H1T 1N6",
    "sg:province":"QC",
    "sg:tags":[
        "church"
    ],
    "wof:name":"Fabrique St-Bonaventure",
    "wof:placetype":"venue"
},
  "geometry": {"coordinates":[-73.57395935060001,45.5749282837],"type":"Point"}
}