{
  "type": "Feature",
  "properties": {
    "addr:full":"Guelph ON N1H 1B1",
    "addr:postcode":"n1h 1b1",
    "iso:country":"CA",
    "sg:city":"Guelph",
    "sg:classifiers":[
        {
            "category":"Health Services",
            "subcategory":"Medical Lab",
            "type":"Services"
        }
    ],
    "sg:phone":"+1 519 767 0550",
    "sg:postcode":"N1H 1B1",
    "sg:province":"ON",
    "sg:tags":[
        "laboratory"
    ],
    "wof:name":"Guelph Nuclear Imaging",
    "wof:placetype":"venue"
},
  "geometry": {"coordinates":[-80.2780761719,43.5486869812],"type":"Point"}
}