{
  "type": "Feature",
  "properties": {
    "addr:full":"1411 Bellevue Ave West Vancouver BC V7T 1C3",
    "addr:housenumber":"1411",
    "addr:postcode":"v7t 1c3",
    "addr:street":"Bellevue Ave",
    "iso:country":"CA",
    "sg:address":"1411 Bellevue Ave",
    "sg:city":"West Vancouver",
    "sg:classifiers":[
        {
            "category":"Shopping",
            "subcategory":"Clothing, Apparel, & Fashions",
            "type":"Retail Goods"
        }
    ],
    "sg:phone":"+1 604 925 1812",
    "sg:postcode":"V7T 1C3",
    "sg:province":"BC",
    "sg:tags":[
        "tailor",
        "furnishing"
    ],
    "wof:name":"Mensroom",
    "wof:placetype":"venue"
},
  "geometry": {"coordinates":[-123.15464,49.327496],"type":"Point"}
}