{
  "type": "Feature",
  "properties": {
    "iso:country":"CA",
    "sg:address":"539 First St",
    "sg:city":"London",
    "sg:classifiers":[
        {
            "category":"Recreation",
            "type":"Entertainment"
        }
    ],
    "sg:phone":"+1 519 453 5664",
    "sg:postcode":"N5V 1Z5",
    "sg:province":"ON",
    "sg:tags":[
        "bingo",
        "game"
    ],
    "wof:name":"Lucky Days Bingo",
    "wof:placetype":"venue"
},
  "geometry": {"coordinates":[-81.197205,43.004814],"type":"Point"}
}