{
  "type": "Feature",
  "properties": {
    "addr:full":"28 Medway Rd Arva ON N0M 1C0",
    "addr:housenumber":"28",
    "addr:postcode":"n0m 1c0",
    "addr:street":"Medway Rd",
    "iso:country":"CA",
    "sg:address":"28 Medway Rd",
    "sg:city":"Arva",
    "sg:classifiers":[
        {
            "category":"Personal",
            "subcategory":"Beauty Salon",
            "type":"Services"
        }
    ],
    "sg:phone":"+1 519 667 3006",
    "sg:postcode":"N0M 1C0",
    "sg:province":"ON",
    "wof:name":"Robert's Hair Studio",
    "wof:placetype":"venue"
},
  "geometry": {"coordinates":[-81.350792,43.034271],"type":"Point"}
}