{
  "type": "Feature",
  "properties": {
    "iso:country":"CA",
    "sg:city":"Coquitlam",
    "sg:classifiers":[
        {
            "category":"Manufacturing",
            "subcategory":"Signs",
            "type":"Manufacturing & Wholesale Goods"
        }
    ],
    "sg:phone":"+1 604 524 4990",
    "sg:postcode":"V3K 6X7",
    "sg:province":"BC",
    "sg:tags":[
        "screen",
        "printing"
    ],
    "wof:name":"Harbour Screenprint Inc",
    "wof:placetype":"venue"
},
  "geometry": {"coordinates":[-122.854743958,49.2278175354],"type":"Point"}
}