{
  "type": "Feature",
  "properties": {
    "addr:full":"52 Dunluce Rd NW Edmonton AB T5X 4N9",
    "addr:housenumber":"52",
    "addr:postcode":"t5x 4n9",
    "addr:street":"Dunluce Rd Nw",
    "iso:country":"CA",
    "sg:address":"52 Dunluce Rd NW",
    "sg:city":"Edmonton",
    "sg:classifiers":[
        {
            "category":"Home & Garden",
            "subcategory":"Garden Supply",
            "type":"Retail Goods"
        }
    ],
    "sg:phone":"+1 780 446 4785",
    "sg:postcode":"T5X 4N9",
    "sg:province":"AB",
    "sg:tags":[
        "sprinkler"
    ],
    "wof:name":"Design Irrigation Ltd",
    "wof:placetype":"venue"
},
  "geometry": {"coordinates":[-113.526436,53.627876],"type":"Point"}
}