{
  "type": "Feature",
  "properties": {
    "addr:full":"6537 Taylor Ave Comber ON N0P 1J0",
    "addr:housenumber":"6537",
    "addr:postcode":"n0p 1j0",
    "addr:street":"Taylor Ave",
    "iso:country":"CA",
    "sg:address":"6537 Taylor Ave",
    "sg:city":"Comber",
    "sg:classifiers":[
        {
            "category":"Manufacturing",
            "subcategory":"Tools & Machinery",
            "type":"Manufacturing & Wholesale Goods"
        }
    ],
    "sg:phone":"+1 519 687 3243",
    "sg:postcode":"N0P 1J0",
    "sg:province":"ON",
    "sg:tags":[
        "mold"
    ],
    "wof:name":"Comber Tool & Mold Ltd",
    "wof:placetype":"venue"
},
  "geometry": {"coordinates":[-82.554642,42.22908],"type":"Point"}
}