{
  "type": "Feature",
  "properties": {
    "iso:country":"CA",
    "sg:city":"Mississauga",
    "sg:classifiers":[
        {
            "category":"Shopping",
            "subcategory":"Clothing, Apparel, & Fashions",
            "type":"Retail Goods"
        }
    ],
    "sg:phone":"+1 905 896 2484",
    "sg:postcode":"L5A 3Y1",
    "sg:province":"ON",
    "sg:tags":[
        "tailor"
    ],
    "wof:name":"Quality Stitch Alteration Shop",
    "wof:placetype":"venue"
},
  "geometry": {"coordinates":[-79.625748,43.601788],"type":"Point"}
}