{
  "type": "Feature",
  "properties": {
    "addr:full":"St Paul AB T0A 3A0",
    "addr:postcode":"t0a 3a0",
    "iso:country":"CA",
    "sg:city":"St Paul",
    "sg:classifiers":[
        {
            "category":"Manufacturing",
            "subcategory":"Tools & Machinery",
            "type":"Manufacturing & Wholesale Goods"
        }
    ],
    "sg:phone":"+1 780 645 3321",
    "sg:postcode":"T0A 3A0",
    "sg:province":"AB",
    "sg:tags":[
        "machine",
        "shop"
    ],
    "wof:name":"St Paul Foundry Ltd",
    "wof:placetype":"venue"
},
  "geometry": {"coordinates":[-111.292603,53.99152],"type":"Point"}
}