{
  "type": "Feature",
  "properties": {
    "addr:full":"681 Athabasca St W Kamloops BC V2H 1C5",
    "addr:housenumber":"681",
    "addr:postcode":"bc v2h 1c5",
    "addr:street":"Athabasca St W",
    "iso:country":"CA",
    "sg:address":"681 Athabasca St W",
    "sg:city":"Kamloops",
    "sg:classifiers":[
        {
            "category":"Manufacturing",
            "subcategory":"Tools & Machinery",
            "type":"Manufacturing & Wholesale Goods"
        }
    ],
    "sg:phone":"+1 250 851 9991",
    "sg:postcode":"V2H 1C5",
    "sg:province":"BC",
    "sg:tags":[
        "contractor"
    ],
    "wof:name":"Pyrotech Asphalt Equipment Mfg",
    "wof:placetype":"venue"
},
  "geometry": {"coordinates":[-120.326263,50.68285],"type":"Point"}
}