{
  "type": "Feature",
  "properties": {
    "addr:full":"85 Station St Duncan BC V9L 1M2",
    "addr:housenumber":"85",
    "addr:postcode":"v9l 1m2",
    "addr:street":"Station St",
    "iso:country":"CA",
    "sg:address":"85 Station St",
    "sg:city":"Duncan",
    "sg:classifiers":[
        {
            "category":"Shopping",
            "subcategory":"Hobbies, Toys, & Games",
            "type":"Retail Goods"
        }
    ],
    "sg:phone":"+1 250 748 5545",
    "sg:postcode":"V9L 1M2",
    "sg:province":"BC",
    "wof:name":"Red Balloon Toy Shop",
    "wof:placetype":"venue"
},
  "geometry": {"coordinates":[-123.707984924,48.7778091431],"type":"Point"}
}