{
  "type": "Feature",
  "properties": {
    "addr:full":"348 Main St Louisdale NS B0E 1V0",
    "addr:housenumber":"348",
    "addr:postcode":"b0e 1v0",
    "addr:street":"Main St",
    "iso:country":"CA",
    "sg:address":"348 Main St",
    "sg:city":"Louisdale",
    "sg:classifiers":[
        {
            "category":"Food & Beverages",
            "subcategory":"Groceries & Convenience Stores",
            "type":"Retail Goods"
        }
    ],
    "sg:phone":"+1 902 345 2818",
    "sg:postcode":"B0E 1V0",
    "sg:province":"NS",
    "sg:tags":[
        "grocer"
    ],
    "wof:name":"Louisdale CO-OP Society Ltd",
    "wof:placetype":"venue"
},
  "geometry": {"coordinates":[-61.0648994446,45.6109695435],"type":"Point"}
}