{
  "type": "Feature",
  "properties": {
    "addr:full":"8798 7E Av Montreal QC H1Z 2V3",
    "addr:housenumber":"8798",
    "addr:postcode":"h1z 2v3",
    "addr:street":"7E Av",
    "iso:country":"CA",
    "sg:address":"8798 7E Av",
    "sg:city":"Montreal",
    "sg:classifiers":[
        {
            "category":"Manufacturing",
            "subcategory":"Furniture",
            "type":"Manufacturing & Wholesale Goods"
        }
    ],
    "sg:phone":"+1 514 725 2077",
    "sg:postcode":"H1Z 2V3",
    "sg:province":"QC",
    "wof:name":"Fauteuil Magique",
    "wof:placetype":"venue"
},
  "geometry": {"coordinates":[-73.62500799999999,45.567535],"type":"Point"}
}