{
  "type": "Feature",
  "properties": {
    "addr:full":"2500 132 Rte Saint-Anicet QC J0S 1M0",
    "addr:housenumber":"2500",
    "addr:postcode":"j0s 1m0",
    "addr:street":"132 Rte",
    "iso:country":"CA",
    "sg:address":"2500 132 Rte",
    "sg:city":"Saint-Anicet",
    "sg:classifiers":[
        {
            "category":"Travel",
            "subcategory":"Campground",
            "type":"Entertainment"
        }
    ],
    "sg:phone":"+1 450 264 4310",
    "sg:postcode":"J0S 1M0",
    "sg:province":"QC",
    "wof:name":"Camping Le Dauphin Inc",
    "wof:placetype":"venue"
},
  "geometry": {"coordinates":[-74.3591918945,45.137134552],"type":"Point"}
}