{
  "type": "Feature",
  "properties": {
    "addr:full":"97 Railside Rd North York ON M3A 1B2",
    "addr:housenumber":"97",
    "addr:postcode":"m3a 1b2",
    "addr:street":"Railside Rd",
    "iso:country":"CA",
    "sg:address":"97 Railside Rd",
    "sg:city":"North York",
    "sg:classifiers":[
        {
            "category":"Education",
            "subcategory":"School",
            "type":"Public Place"
        }
    ],
    "sg:phone":"+1 416 393 5406",
    "sg:postcode":"M3A 1B2",
    "sg:province":"ON",
    "wof:name":"Metropolitan Separate School",
    "wof:placetype":"venue"
},
  "geometry": {"coordinates":[-79.324051,43.736137],"type":"Point"}
}