{
  "type": "Feature",
  "properties": {
    "addr:full":"Sainte-Foy QC G1X 4P1",
    "addr:postcode":"g1x 4p1",
    "iso:country":"CA",
    "sg:city":"Sainte-Foy",
    "sg:classifiers":[
        {
            "category":"Personal",
            "subcategory":"Beauty Salon",
            "type":"Services"
        }
    ],
    "sg:phone":"+1 418 650 3136",
    "sg:postcode":"G1X 4P1",
    "sg:province":"QC",
    "sg:tags":[
        "manicuring"
    ],
    "wof:name":"Clinique DE Soins DE Pieds",
    "wof:placetype":"venue"
},
  "geometry": {"coordinates":[-71.33550262449999,46.7611961365],"type":"Point"}
}