{
  "type": "Feature",
  "properties": {
    "addr:full":"611 Rue Principale Clair NB E7A 2H1",
    "addr:housenumber":"611",
    "addr:postcode":"e7a 2h1",
    "addr:street":"Rue Principale",
    "iso:country":"CA",
    "sg:address":"611 Rue Principale",
    "sg:city":"Clair",
    "sg:classifiers":[
        {
            "category":"Food & Beverages",
            "subcategory":"Groceries & Convenience Stores",
            "type":"Retail Goods"
        }
    ],
    "sg:phone":"+1 506 992 2150",
    "sg:postcode":"E7A 2H1",
    "sg:province":"NB",
    "sg:tags":[
        "grocer"
    ],
    "wof:name":"Bonichoix",
    "wof:placetype":"venue"
},
  "geometry": {"coordinates":[-68.600182,47.25798],"type":"Point"}
}