{
  "type": "Feature",
  "properties": {
    "addr:full":"4397 Crawford Rd Armstrong BC V0E 1B4",
    "addr:housenumber":"4397",
    "addr:postcode":"v0e 1b4",
    "addr:street":"Crawford Rd",
    "iso:country":"CA",
    "sg:address":"4397 Crawford Rd",
    "sg:city":"Armstrong",
    "sg:classifiers":[
        {
            "category":"Retail",
            "subcategory":"Animal Services",
            "type":"Services"
        }
    ],
    "sg:phone":"+1 250 546 3298",
    "sg:postcode":"V0E 1B4",
    "sg:province":"BC",
    "sg:tags":[
        "pet",
        "grooming",
        "washing"
    ],
    "wof:name":"Katrina's Doggie Clip",
    "wof:placetype":"venue"
},
  "geometry": {"coordinates":[-119.183701,50.441818],"type":"Point"}
}