{
  "type": "Feature",
  "properties": {
    "addr:full":"1827 Woodward Dr Ottawa ON K2C 0P9",
    "addr:housenumber":"1827",
    "addr:postcode":"k2c 0p9",
    "addr:street":"Woodward Dr",
    "iso:country":"CA",
    "sg:address":"1827 Woodward Dr",
    "sg:city":"Ottawa",
    "sg:classifiers":[
        {
            "category":"Professional",
            "subcategory":"Management & Consulting",
            "type":"Services"
        }
    ],
    "sg:phone":"+1 613 225 5640",
    "sg:postcode":"K2C 0P9",
    "sg:province":"ON",
    "sg:tags":[
        "construction"
    ],
    "wof:name":"William S Burnside Ltd",
    "wof:placetype":"venue"
},
  "geometry": {"coordinates":[-75.75202178959999,45.3693008423],"type":"Point"}
}