{
  "type": "Feature",
  "properties": {
    "addr:full":"2740 9th Line Innisfil ON L9S 3Z8",
    "addr:housenumber":"2740",
    "addr:postcode":"l9s 3z8",
    "addr:street":"9Th Line",
    "iso:country":"CA",
    "sg:address":"2740 9th Line",
    "sg:city":"Innisfil",
    "sg:classifiers":[
        {
            "category":"Building & Trades",
            "subcategory":"Construction",
            "type":"Services"
        }
    ],
    "sg:phone":"+1 705 436 5254",
    "sg:postcode":"L9S 3Z8",
    "sg:province":"ON",
    "sg:tags":[
        "excavating",
        "contractor"
    ],
    "wof:name":"Dave Dobinson Excavating",
    "wof:placetype":"venue"
},
  "geometry": {"coordinates":[-79.6425476074,44.3067588806],"type":"Point"}
}