{
  "type": "Feature",
  "properties": {
    "addr:full":"10046 164 St NW Edmonton AB T5P 4Y3",
    "addr:housenumber":"10046",
    "addr:postcode":"t5p 4y3",
    "addr:street":"164 St Nw",
    "iso:country":"CA",
    "sg:address":"10046 164 St NW",
    "sg:city":"Edmonton",
    "sg:classifiers":[
        {
            "category":"Professional",
            "subcategory":"Computer Services",
            "type":"Services"
        }
    ],
    "sg:phone":"+1 780 489 8010",
    "sg:postcode":"T5P 4Y3",
    "sg:province":"AB",
    "sg:tags":[
        "leasing"
    ],
    "wof:name":"Synergistic Computors",
    "wof:placetype":"venue"
},
  "geometry": {"coordinates":[-113.604766846,53.5402374268],"type":"Point"}
}