{
  "type": "Feature",
  "properties": {
    "addr:full":"116 Christie Park Manor SW Calgary AB T3H 2E8",
    "addr:housenumber":"116",
    "addr:postcode":"t3h 2e8",
    "addr:street":"Christie Park Manor Sw",
    "iso:country":"CA",
    "sg:address":"116 Christie Park Manor SW",
    "sg:city":"Calgary",
    "sg:classifiers":[
        {
            "category":"Professional",
            "subcategory":"Business Services",
            "type":"Services"
        }
    ],
    "sg:phone":"+1 403 217 6200",
    "sg:postcode":"T3H 2E8",
    "sg:province":"AB",
    "sg:tags":[
        "paralegal"
    ],
    "wof:name":"D R Paralegal Svc Ltd",
    "wof:placetype":"venue"
},
  "geometry": {"coordinates":[-114.173134,51.0397],"type":"Point"}
}