{
  "type": "Feature",
  "properties": {
    "addr:full":"1661 Queen St E Toronto ON M4L 1G5",
    "addr:housenumber":"1661",
    "addr:postcode":"m4l 1g5",
    "addr:street":"Queen St E",
    "iso:country":"CA",
    "sg:address":"1661 Queen St E",
    "sg:city":"Toronto",
    "sg:classifiers":[
        {
            "category":"Sports & Exercise",
            "subcategory":"Race Track",
            "type":"Entertainment"
        }
    ],
    "sg:phone":"+1 416 698 3136",
    "sg:postcode":"M4L 1G5",
    "sg:province":"ON",
    "wof:name":"Champions Greenwood",
    "wof:placetype":"venue"
},
  "geometry": {"coordinates":[-79.3124008179,43.6671905518],"type":"Point"}
}