{
  "type": "Feature",
  "properties": {
    "addr:full":"19 Mark Ave Moncton NB E1C 7H1",
    "addr:housenumber":"19",
    "addr:postcode":"e1c 7h1",
    "addr:street":"Mark Ave",
    "iso:country":"CA",
    "sg:address":"19 Mark Ave",
    "sg:city":"Moncton",
    "sg:classifiers":[
        {
            "category":"Social Services",
            "type":"Services"
        }
    ],
    "sg:phone":"+1 506 382 3663",
    "sg:postcode":"E1C 7H1",
    "sg:province":"NB",
    "sg:tags":[
        "organization",
        "welfare"
    ],
    "wof:name":"Open Hands Food Bank",
    "wof:placetype":"venue"
},
  "geometry": {"coordinates":[-64.8080215454,46.097568512],"type":"Point"}
}