{
  "type": "Feature",
  "properties": {
    "addr:full":"Frankford ON K0K 2C0",
    "addr:postcode":"k0k 2c0",
    "iso:country":"CA",
    "sg:city":"Frankford",
    "sg:classifiers":[
        {
            "category":"Manufacturing",
            "subcategory":"Wood Products",
            "type":"Manufacturing & Wholesale Goods"
        }
    ],
    "sg:phone":"+1 613 398 1616",
    "sg:postcode":"K0K 2C0",
    "sg:province":"ON",
    "sg:tags":[
        "pallet",
        "skid"
    ],
    "wof:name":"Quinn & Quinn",
    "wof:placetype":"venue"
},
  "geometry": {"coordinates":[-77.523239,44.208981],"type":"Point"}
}