{
  "type": "Feature",
  "properties": {
    "addr:full":"252 Kantola Rd Lively ON P3Y 1G9",
    "addr:housenumber":"252",
    "addr:postcode":"p3y 1g9",
    "addr:street":"Kantola Rd",
    "iso:country":"CA",
    "sg:address":"252 Kantola Rd",
    "sg:city":"Lively",
    "sg:classifiers":[
        {
            "category":"Retail",
            "subcategory":"Repair Shop",
            "type":"Services"
        }
    ],
    "sg:phone":"+1 705 692 5032",
    "sg:postcode":"P3Y 1G9",
    "sg:province":"ON",
    "sg:tags":[
        "lock",
        "locksmith"
    ],
    "wof:name":"Walden Locksmithing",
    "wof:placetype":"venue"
},
  "geometry": {"coordinates":[-81.11599731450001,46.4074554443],"type":"Point"}
}