{
  "type": "Feature",
  "properties": {
    "iso:country":"CA",
    "sg:address":"129 Boul Industriel",
    "sg:city":"Repentigny",
    "sg:classifiers":[
        {
            "category":"Autos & Motor Vehicles",
            "subcategory":"Fuel & Gas Station",
            "type":"Retail Goods"
        }
    ],
    "sg:phone":"+1 450 585 9089",
    "sg:postcode":"J6A 7K4",
    "sg:province":"QC",
    "sg:tags":[
        "oil"
    ],
    "wof:name":"Shell Industrial",
    "wof:placetype":"venue"
},
  "geometry": {"coordinates":[-73.4457855225,45.7558822632],"type":"Point"}
}