{
  "type": "Feature",
  "properties": {
    "addr:full":"Edmonton AB T6H 5R7",
    "addr:postcode":"t6h 5r7",
    "iso:country":"CA",
    "sg:city":"Edmonton",
    "sg:classifiers":[
        {
            "category":"Banks & Credit Unions",
            "subcategory":"Investment Brokerage",
            "type":"Services"
        }
    ],
    "sg:phone":"+1 780 438 3500",
    "sg:postcode":"T6H 5R7",
    "sg:province":"AB",
    "wof:name":"Almasa Capital Inc",
    "wof:placetype":"venue"
},
  "geometry": {"coordinates":[-113.494903565,53.4822425842],"type":"Point"}
}