{
  "type": "Feature",
  "properties": {
    "addr:full":"St Catharines ON L2W 1A2",
    "addr:postcode":"l2w 1a2",
    "iso:country":"CA",
    "sg:city":"St Catharines",
    "sg:classifiers":[
        {
            "category":"Shopping",
            "subcategory":"Gifts & Souvenirs",
            "type":"Retail Goods"
        }
    ],
    "sg:phone":"+1 905 688 7755",
    "sg:postcode":"L2W 1A2",
    "sg:province":"ON",
    "sg:tags":[
        "game",
        "supply"
    ],
    "wof:name":"Bazaar Marketing Group",
    "wof:placetype":"venue"
},
  "geometry": {"coordinates":[-79.27505499999999,43.175152],"type":"Point"}
}