{
  "type": "Feature",
  "properties": {
    "addr:full":"3566 Cordiale Dr Vancouver BC V5S 4H3",
    "addr:housenumber":"3566",
    "addr:postcode":"v5s 4h3",
    "addr:street":"Cordiale Dr",
    "iso:country":"CA",
    "sg:address":"3566 Cordiale Dr",
    "sg:city":"Vancouver",
    "sg:classifiers":[
        {
            "category":"Retail",
            "subcategory":"Laundry & Dry Cleaning",
            "type":"Services"
        }
    ],
    "sg:phone":"+1 604 451 9585",
    "sg:postcode":"V5S 4H3",
    "sg:province":"BC",
    "sg:tags":[
        "cleaners",
        "rug",
        "carpet"
    ],
    "wof:name":"Watts Carpet & Upholstery Clnr",
    "wof:placetype":"venue"
},
  "geometry": {"coordinates":[-123.02677199999999,49.209724],"type":"Point"}
}