{
  "type": "Feature",
  "properties": {
    "addr:full":"116 Research Dr #112D Saskatoon SK S7N 3R3",
    "addr:housenumber":"116",
    "addr:postcode":"s7n 3r3",
    "addr:street":"Research Dr # 112D",
    "iso:country":"CA",
    "sg:address":"116 Research Dr #112D",
    "sg:city":"Saskatoon",
    "sg:classifiers":[
        {
            "category":"Organizations",
            "subcategory":"Professional Association",
            "type":"Services"
        }
    ],
    "sg:phone":"+1 306 244 3889",
    "sg:postcode":"S7N 3R3",
    "sg:province":"SK",
    "wof:name":"Saskatchewan Advanced Tech",
    "wof:placetype":"venue"
},
  "geometry": {"coordinates":[-106.62577819800001,52.1426277161],"type":"Point"}
}