{
  "type": "Feature",
  "properties": {
    "addr:full":"1815 Rue Du Mont-Blanc Sainte-Adele QC J8B 2Z8",
    "addr:housenumber":"1815",
    "addr:postcode":"j8b 2z8",
    "addr:street":"Rue Du Mont-Blanc Sainte-Adele",
    "iso:country":"CA",
    "sg:address":"1815 Rue Du Mont-Blanc",
    "sg:city":"Sainte-Adele",
    "sg:classifiers":[
        {
            "category":"Recreation",
            "type":"Entertainment"
        }
    ],
    "sg:phone":"+1 450 229 6592",
    "sg:postcode":"J8B 2Z8",
    "sg:province":"QC",
    "sg:tags":[
        "stable"
    ],
    "wof:name":"Club Equestre Chanteclerc",
    "wof:placetype":"venue"
},
  "geometry": {"coordinates":[-74.149895,45.955708],"type":"Point"}
}