{
  "type": "Feature",
  "properties": {
    "iso:country":"CA",
    "sg:address":"460 2E Av",
    "sg:city":"Weedon",
    "sg:classifiers":[
        {
            "category":"Health Services",
            "subcategory":"Doctor",
            "type":"Services"
        }
    ],
    "sg:phone":"+1 819 877 5400",
    "sg:postcode":"J0B 3J0",
    "sg:province":"QC",
    "sg:tags":[
        "dentist"
    ],
    "wof:name":"Clinique Dentaire Giard",
    "wof:placetype":"venue"
},
  "geometry": {"coordinates":[-71.4623641968,45.7053451538],"type":"Point"}
}