{
  "type": "Feature",
  "properties": {
    "addr:full":"PO Box 40 Milo AB T0L 1L0",
    "addr:housenumber":"po box 40",
    "addr:postcode":"t0l 1l0",
    "iso:country":"CA",
    "sg:address":"PO Box 40",
    "sg:city":"Milo",
    "sg:classifiers":[
        {
            "category":"Organizations",
            "subcategory":"Religious Organization",
            "type":"Services"
        }
    ],
    "sg:phone":"+1 403 599 3806",
    "sg:postcode":"T0L 1L0",
    "sg:province":"AB",
    "sg:tags":[
        "church"
    ],
    "wof:name":"Milo United Church",
    "wof:placetype":"venue"
},
  "geometry": {"coordinates":[-112.884041,50.57217],"type":"Point"}
}