{
  "type": "Feature",
  "properties": {
    "addr:full":"Balcarres SK S0G 0C0",
    "addr:postcode":"s0g 0c0",
    "addr:street":"Balcarres",
    "iso:country":"CA",
    "sg:city":"Balcarres",
    "sg:classifiers":[
        {
            "category":"Social Services",
            "subcategory":"Child Care",
            "type":"Services"
        }
    ],
    "sg:phone":"+1 306 334 2618",
    "sg:postcode":"S0G 0C0",
    "sg:province":"SK",
    "wof:name":"Star Blanket Daycare",
    "wof:placetype":"venue"
},
  "geometry": {"coordinates":[-103.54782104500001,50.798160553],"type":"Point"}
}