{
  "type": "Feature",
  "properties": {
    "addr:full":"2288 18 Ave NE Calgary AB T2E 8R1",
    "addr:housenumber":"2288",
    "addr:postcode":"t2e 8r1",
    "addr:street":"18 Ave Ne",
    "iso:country":"CA",
    "sg:address":"2288 18 Ave NE",
    "sg:city":"Calgary",
    "sg:classifiers":[
        {
            "category":"Social Services",
            "type":"Services"
        }
    ],
    "sg:phone":"+1 403 291 2205",
    "sg:postcode":"T2E 8R1",
    "sg:province":"AB",
    "sg:tags":[
        "front",
        "organization",
        "store",
        "welfare"
    ],
    "wof:name":"Alpine Glass Ltd",
    "wof:placetype":"venue"
},
  "geometry": {"coordinates":[-114.007446289,51.0691452026],"type":"Point"}
}