{
  "type": "Feature",
  "properties": {
    "addr:full":"151 Robinson St Oakville ON L6J 7N3",
    "addr:housenumber":"151",
    "addr:postcode":"l6j 7n3",
    "addr:street":"Robinson St",
    "iso:country":"CA",
    "sg:address":"151 Robinson St",
    "sg:city":"Oakville",
    "sg:classifiers":[
        {
            "category":"Personal",
            "subcategory":"Beauty Salon",
            "type":"Services"
        }
    ],
    "sg:phone":"+1 905 845 6803",
    "sg:postcode":"L6J 7N3",
    "sg:province":"ON",
    "wof:name":"Paul Vincent Hair Design",
    "wof:placetype":"venue"
},
  "geometry": {"coordinates":[-79.668716,43.44429],"type":"Point"}
}