{
  "type": "Feature",
  "properties": {
    "addr:full":"Winnipeg MB R3H 0Y9",
    "addr:postcode":"r3h 0y9",
    "iso:country":"CA",
    "sg:city":"Winnipeg",
    "sg:classifiers":[
        {
            "category":"Wholesale",
            "subcategory":"Machinery & Supplies",
            "type":"Manufacturing & Wholesale Goods"
        }
    ],
    "sg:phone":"+1 204 783 3344",
    "sg:postcode":"R3H 0Y9",
    "sg:province":"MB",
    "sg:tags":[
        "equipment",
        "hydraulic"
    ],
    "wof:name":"Allquip Industrial Supply Inc",
    "wof:placetype":"venue"
},
  "geometry": {"coordinates":[-97.19931800000001,49.907574],"type":"Point"}
}