{
  "type": "Feature",
  "properties": {
    "addr:full":"109 1st St Bassano AB T0J 0B0",
    "addr:housenumber":"109",
    "addr:postcode":"t0j 0b0",
    "addr:street":"1St St",
    "iso:country":"CA",
    "sg:address":"109 1st St",
    "sg:city":"Bassano",
    "sg:classifiers":[
        {
            "category":"Sports & Exercise",
            "subcategory":"Golf",
            "type":"Entertainment"
        }
    ],
    "sg:phone":"+1 403 641 4016",
    "sg:postcode":"T0J 0B0",
    "sg:province":"AB",
    "sg:tags":[
        "course"
    ],
    "wof:name":"Bassano Golf & Curling",
    "wof:placetype":"venue"
},
  "geometry": {"coordinates":[-112.474784851,50.7886924744],"type":"Point"}
}