{
  "type": "Feature",
  "properties": {
    "addr:full":"Barrie ON L4N 3A8",
    "addr:postcode":"l4n 3a8",
    "iso:country":"CA",
    "sg:city":"Barrie",
    "sg:classifiers":[
        {
            "category":"Retail",
            "subcategory":"Auto Repair",
            "type":"Services"
        }
    ],
    "sg:phone":"+1 705 728 0254",
    "sg:postcode":"L4N 3A8",
    "sg:province":"ON",
    "sg:tags":[
        "repairing",
        "automobile",
        "muffler",
        "exhaust"
    ],
    "wof:name":"Acadia Car Clinic",
    "wof:placetype":"venue"
},
  "geometry": {"coordinates":[-79.693932,44.382732],"type":"Point"}
}