{
  "type": "Feature",
  "properties": {
    "addr:full":"403 Rang Saint-Charles Tring-Jonction QC G0N 1X0",
    "addr:housenumber":"403",
    "addr:postcode":"g0n 1x0",
    "addr:street":"Rang Saint-Charles",
    "iso:country":"CA",
    "sg:address":"403 Rang Saint-Charles",
    "sg:city":"Tring-Jonction",
    "sg:classifiers":[
        {
            "category":"Building & Trades",
            "subcategory":"Electrical",
            "type":"Services"
        }
    ],
    "sg:phone":"+1 418 426 2651",
    "sg:postcode":"G0N 1X0",
    "sg:province":"QC",
    "sg:tags":[
        "electric",
        "contractor"
    ],
    "wof:name":"Lessard H-Ls Electrique Inc",
    "wof:placetype":"venue"
},
  "geometry": {"coordinates":[-70.97605900000001,46.254089],"type":"Point"}
}