{
  "type": "Feature",
  "properties": {
    "addr:full":"Winnipeg MB R2G 3Z7",
    "addr:postcode":"r2g 3z7",
    "iso:country":"CA",
    "sg:city":"Winnipeg",
    "sg:classifiers":[
        {
            "category":"Restaurant",
            "type":"Food & Drink"
        }
    ],
    "sg:phone":"+1 204 339 5452",
    "sg:postcode":"R2G 3Z7",
    "sg:province":"MB",
    "wof:name":"Subway Sandwiches & Salads",
    "wof:placetype":"venue"
},
  "geometry": {"coordinates":[-97.092422,49.938763],"type":"Point"}
}