{
  "type": "Feature",
  "properties": {
    "addr:full":"3308 Danforth Ave Scarborough ON M1L 1C4",
    "addr:housenumber":"3308",
    "addr:postcode":"m1l 1c4",
    "addr:street":"Danforth Ave",
    "iso:country":"CA",
    "sg:address":"3308 Danforth Ave",
    "sg:city":"Scarborough",
    "sg:classifiers":[
        {
            "category":"Food & Beverages",
            "subcategory":"Bakery",
            "type":"Retail Goods"
        }
    ],
    "sg:phone":"+1 416 699 6211",
    "sg:postcode":"M1L 1C4",
    "sg:province":"ON",
    "sg:tags":[
        "baker"
    ],
    "wof:name":"National Home Bakery",
    "wof:placetype":"venue"
},
  "geometry": {"coordinates":[-79.279518,43.693306],"type":"Point"}
}