{
  "type": "Feature",
  "properties": {
    "addr:full":"1204 Valleyfield Rd Montague PE C0A 1R0",
    "addr:housenumber":"1204",
    "addr:postcode":"c0a 1r0",
    "addr:street":"Valleyfield Rd",
    "iso:country":"CA",
    "sg:address":"1204 Valleyfield Rd",
    "sg:city":"Montague",
    "sg:classifiers":[
        {
            "category":"Building & Trades",
            "subcategory":"Construction",
            "type":"Services"
        }
    ],
    "sg:phone":"+1 902 838 4741",
    "sg:postcode":"C0A 1R0",
    "sg:province":"PE",
    "sg:tags":[
        "painter"
    ],
    "wof:name":"P Forrester & Sons",
    "wof:placetype":"venue"
},
  "geometry": {"coordinates":[-62.65892,46.151871],"type":"Point"}
}