{
  "type": "Feature",
  "properties": {
    "addr:full":"355 Wellington St London ON N6A 3N7",
    "addr:housenumber":"355",
    "addr:postcode":"n6a 3n7",
    "addr:street":"Wellington St",
    "iso:country":"CA",
    "sg:address":"355 Wellington St",
    "sg:city":"London",
    "sg:classifiers":[
        {
            "category":"Food & Beverages",
            "subcategory":"Bakery",
            "type":"Retail Goods"
        }
    ],
    "sg:phone":"+1 519 642 4524",
    "sg:postcode":"N6A 3N7",
    "sg:province":"ON",
    "sg:tags":[
        "tea",
        "coffee",
        "doughnut"
    ],
    "wof:name":"Tim Hortons",
    "wof:placetype":"venue"
},
  "geometry": {"coordinates":[-81.2445678711,42.9831962585],"type":"Point"}
}