{
  "type": "Feature",
  "properties": {
    "addr:full":"Tahsis BC V0P 1X0",
    "addr:postcode":"v0p 1x0",
    "iso:country":"CA",
    "sg:city":"Tahsis",
    "sg:classifiers":[
        {
            "category":"Food & Beverages",
            "subcategory":"Bakery",
            "type":"Retail Goods"
        }
    ],
    "sg:phone":"+1 250 934 6671",
    "sg:postcode":"V0P 1X0",
    "sg:province":"BC",
    "sg:tags":[
        "baker"
    ],
    "wof:name":"Savage Biscuit",
    "wof:placetype":"venue"
},
  "geometry": {"coordinates":[-126.65303,49.933533],"type":"Point"}
}