{
  "type": "Feature",
  "properties": {
    "addr:full":"156 Sugar Maple Rd St George Brant ON N0E 1N0",
    "addr:housenumber":"156",
    "addr:postcode":"n0e 1n0",
    "addr:street":"Sugar Maple Rd",
    "iso:country":"CA",
    "sg:address":"156 Sugar Maple Rd",
    "sg:city":"St George Brant",
    "sg:classifiers":[
        {
            "category":"Manufacturing",
            "subcategory":"Metals",
            "type":"Manufacturing & Wholesale Goods"
        }
    ],
    "sg:phone":"+1 519 448 4588",
    "sg:postcode":"N0E 1N0",
    "sg:province":"ON",
    "sg:tags":[
        "spring"
    ],
    "wof:name":"Western Spring & Wire",
    "wof:placetype":"venue"
},
  "geometry": {"coordinates":[-80.4266586304,43.1024703979],"type":"Point"}
}