{
  "type": "Feature",
  "properties": {
    "addr:full":"249 6E Rue Crabtree QC J0K 1B0",
    "addr:housenumber":"249",
    "addr:postcode":"j0k 1b0",
    "addr:street":"6E Rue Crabtree",
    "iso:country":"CA",
    "sg:address":"249 6E Rue",
    "sg:city":"Crabtree",
    "sg:classifiers":[
        {
            "category":"Building & Trades",
            "subcategory":"Plumbing",
            "type":"Services"
        }
    ],
    "sg:phone":"+1 450 753 0349",
    "sg:postcode":"J0K 1B0",
    "sg:province":"QC",
    "sg:tags":[
        "conditioning",
        "air",
        "refrigeration",
        "system",
        "contractor"
    ],
    "wof:name":"Excel-Air Refrigeration Inc",
    "wof:placetype":"venue"
},
  "geometry": {"coordinates":[-73.4773864746,45.9610900879],"type":"Point"}
}