{
  "type": "Feature",
  "properties": {
    "iso:country":"CA",
    "sg:address":"1431 Fort Lawrence Rd",
    "sg:city":"Amherst",
    "sg:classifiers":[
        {
            "category":"Wholesale",
            "subcategory":"Durable Goods & Equipment",
            "type":"Manufacturing & Wholesale Goods"
        }
    ],
    "sg:phone":"+1 902 667 9985",
    "sg:postcode":"B4H 3Y5",
    "sg:province":"NS",
    "sg:tags":[
        "environmental",
        "product"
    ],
    "wof:name":"Atkinson & Assoc",
    "wof:placetype":"venue"
},
  "geometry": {"coordinates":[-64.2099304199,45.8320388794],"type":"Point"}
}