{
  "type": "Feature",
  "properties": {
    "addr:full":"210 Boul Lemire O Drummondville QC J2B 8A9",
    "addr:housenumber":"210",
    "addr:postcode":"j2b 8a9",
    "addr:street":"Boul Lemire O",
    "iso:country":"CA",
    "sg:address":"210 Boul Lemire O",
    "sg:city":"Drummondville",
    "sg:classifiers":[
        {
            "category":"Farming",
            "subcategory":"Nursery",
            "type":"Manufacturing & Wholesale Goods"
        }
    ],
    "sg:phone":"+1 819 474 3488",
    "sg:postcode":"J2B 8A9",
    "sg:province":"QC",
    "sg:tags":[
        "greenhouse"
    ],
    "wof:name":"Rose Drummond",
    "wof:placetype":"venue"
},
  "geometry": {"coordinates":[-72.5380554199,45.885974884],"type":"Point"}
}