{
  "type": "Feature",
  "properties": {
    "addr:full":"97 Wilson St #14 Woodstock ON N4S 3N8",
    "addr:housenumber":"97",
    "addr:postcode":"n4s 3n8",
    "addr:street":"Wilson St # 14",
    "iso:country":"CA",
    "sg:address":"97 Wilson St #14",
    "sg:city":"Woodstock",
    "sg:classifiers":[
        {
            "category":"Retail",
            "subcategory":"Auto Repair",
            "type":"Services"
        }
    ],
    "sg:phone":"+1 519 539 9553",
    "sg:postcode":"N4S 3N8",
    "sg:province":"ON",
    "sg:tags":[
        "transmission",
        "automobile",
        "repairing"
    ],
    "wof:name":"Phoenix Transmissions",
    "wof:placetype":"venue"
},
  "geometry": {"coordinates":[-80.74588799999999,43.127232],"type":"Point"}
}