{
  "type": "Feature",
  "properties": {
    "addr:full":"1251 Kennedy Rd Scarborough ON M1P 2L4",
    "addr:housenumber":"1251",
    "addr:postcode":"m1p 2l4",
    "addr:street":"Kennedy Rd",
    "iso:country":"CA",
    "sg:address":"1251 Kennedy Rd",
    "sg:city":"Scarborough",
    "sg:classifiers":[
        {
            "category":"Retail",
            "subcategory":"Auto Repair",
            "type":"Services"
        }
    ],
    "sg:phone":"+1 416 755 2772",
    "sg:postcode":"M1P 2L4",
    "sg:province":"ON",
    "sg:tags":[
        "body",
        "automobile",
        "painting"
    ],
    "wof:name":"Impera Body & Paint Shop",
    "wof:placetype":"venue"
},
  "geometry": {"coordinates":[-79.27739699999999,43.756611],"type":"Point"}
}