{
  "type": "Feature",
  "properties": {
    "addr:full":"Edmonton AB T6H 5P9",
    "addr:postcode":"t6h 5p9",
    "iso:country":"CA",
    "sg:city":"Edmonton",
    "sg:classifiers":[
        {
            "category":"Professional",
            "subcategory":"Lawyer & Legal Services",
            "type":"Services"
        }
    ],
    "sg:phone":"+1 780 436 8554",
    "sg:postcode":"T6H 5P9",
    "sg:province":"AB",
    "sg:tags":[
        "attorney"
    ],
    "wof:name":"Worton Hunter & Callaghan",
    "wof:placetype":"venue"
},
  "geometry": {"coordinates":[-113.496262,53.492722],"type":"Point"}
}