{
  "type": "Feature",
  "properties": {
    "iso:country":"CA",
    "sg:address":"3755 Rue Sainte-Catherine E",
    "sg:city":"Montreal",
    "sg:classifiers":[
        {
            "category":"Shopping",
            "subcategory":"Stationery & Office Supplies",
            "type":"Retail Goods"
        }
    ],
    "sg:phone":"+1 514 253 0444",
    "sg:postcode":"H1W 2E9",
    "sg:province":"QC",
    "sg:tags":[
        "computer",
        "parts"
    ],
    "wof:name":"Fournitures D'Ordinateur",
    "wof:placetype":"venue"
},
  "geometry": {"coordinates":[-73.5378952026,45.544757843],"type":"Point"}
}