{
  "type": "Feature",
  "properties": {
    "iso:country":"CA",
    "sg:address":"650 Ontario St",
    "sg:city":"Stratford",
    "sg:classifiers":[
        {
            "category":"Restaurant",
            "type":"Food & Drink"
        }
    ],
    "sg:phone":"+1 519 271 8091",
    "sg:postcode":"N5A 3J5",
    "sg:province":"ON",
    "sg:tags":[
        "shop",
        "coffee"
    ],
    "wof:name":"Donut Mill",
    "wof:placetype":"venue"
},
  "geometry": {"coordinates":[-80.9596252441,43.3711280823],"type":"Point"}
}