{
  "type": "Feature",
  "properties": {
    "addr:full":"531 Florence Rd Florence ON N0P 1R0",
    "addr:housenumber":"531",
    "addr:postcode":"n0p 1r0",
    "addr:street":"Florence Rd",
    "iso:country":"CA",
    "sg:address":"531 Florence Rd",
    "sg:city":"Florence",
    "sg:classifiers":[
        {
            "category":"Education",
            "subcategory":"Library",
            "type":"Public Place"
        }
    ],
    "sg:phone":"+1 519 692 3213",
    "sg:postcode":"N0P 1R0",
    "sg:province":"ON",
    "wof:name":"Florence Library",
    "wof:placetype":"venue"
},
  "geometry": {"coordinates":[-82.008492,42.652851],"type":"Point"}
}