{
  "type": "Feature",
  "properties": {
    "addr:full":"Delta BC V4G 1J6",
    "addr:postcode":"v4g 1j6",
    "iso:country":"CA",
    "sg:city":"Delta",
    "sg:classifiers":[
        {
            "category":"Personal",
            "subcategory":"Beauty Salon",
            "type":"Services"
        }
    ],
    "sg:phone":"+1 604 583 7151",
    "sg:postcode":"V4G 1J6",
    "sg:province":"BC",
    "sg:tags":[
        "aromatherapy"
    ],
    "wof:name":"Saje Nature's Remedies",
    "wof:placetype":"venue"
},
  "geometry": {"coordinates":[-122.940529,49.150288],"type":"Point"}
}