{
  "type": "Feature",
  "properties": {
    "addr:full":"50 Rue Maskinonge Saint-Gabriel-DE-Brandon QC J0K 2N0",
    "addr:housenumber":"50",
    "addr:postcode":"j0k 2n0",
    "addr:street":"Rue Maskinonge",
    "iso:country":"CA",
    "sg:address":"50 Rue Maskinonge",
    "sg:city":"Saint-Gabriel-DE-Brandon",
    "sg:classifiers":[
        {
            "category":"Real Estate",
            "subcategory":"Real Estate Operator",
            "type":"Services"
        }
    ],
    "sg:phone":"+1 450 835 5625",
    "sg:postcode":"J0K 2N0",
    "sg:province":"QC",
    "sg:tags":[
        "apartment"
    ],
    "wof:name":"Office Municipal D'Habitation",
    "wof:placetype":"venue"
},
  "geometry": {"coordinates":[-73.386208,46.295052],"type":"Point"}
}