{
  "type": "Feature",
  "properties": {
    "addr:full":"938 Mountain Rd Moncton NB E1C 2S2",
    "addr:housenumber":"938",
    "addr:postcode":"e1c 2s2",
    "addr:street":"Mountain Rd",
    "iso:country":"CA",
    "sg:address":"938 Mountain Rd",
    "sg:city":"Moncton",
    "sg:classifiers":[
        {
            "category":"Bars & Pubs",
            "type":"Food & Drink"
        }
    ],
    "sg:phone":"+1 506 858 8844",
    "sg:postcode":"E1C 2S2",
    "sg:province":"NB",
    "sg:tags":[
        "club",
        "night"
    ],
    "wof:name":"Voo Doo",
    "wof:placetype":"venue"
},
  "geometry": {"coordinates":[-64.8141174316,46.1017875671],"type":"Point"}
}