{
  "type": "Feature",
  "properties": {
    "addr:full":"25 Heritage Rd Markham ON L3P 1M3",
    "addr:housenumber":"25",
    "addr:postcode":"l3p 1m3",
    "addr:street":"Heritage Rd",
    "iso:country":"CA",
    "sg:address":"25 Heritage Rd",
    "sg:city":"Markham",
    "sg:classifiers":[
        {
            "category":"Retail",
            "subcategory":"Auto Repair",
            "type":"Services"
        }
    ],
    "sg:phone":"+1 905 294 5942",
    "sg:postcode":"L3P 1M3",
    "sg:province":"ON",
    "sg:tags":[
        "machine",
        "automobile",
        "shop"
    ],
    "wof:name":"Rainbow's Automotive Svc Ltd",
    "wof:placetype":"venue"
},
  "geometry": {"coordinates":[-79.280136,43.87088],"type":"Point"}
}