{
  "type": "Feature",
  "properties": {
    "addr:full":"1515 Rue Notre-Dame Lachine QC H8S 2E4",
    "addr:housenumber":"1515",
    "addr:postcode":"h8s 2e4",
    "addr:street":"Rue Notre-Dame",
    "iso:country":"CA",
    "sg:address":"1515 Rue Notre-Dame",
    "sg:city":"Lachine",
    "sg:classifiers":[
        {
            "category":"Health Services",
            "subcategory":"Doctor",
            "type":"Services"
        }
    ],
    "sg:phone":"+1 514 634 7146",
    "sg:postcode":"H8S 2E4",
    "sg:province":"QC",
    "sg:tags":[
        "physician",
        "surgeon"
    ],
    "wof:name":"Centre Medical Notre-Dame",
    "wof:placetype":"venue"
},
  "geometry": {"coordinates":[-73.677643,45.434849],"type":"Point"}
}