{
  "type": "Feature",
  "properties": {
    "addr:full":"522 Church St Micmac NS B0N 1W0",
    "addr:housenumber":"522",
    "addr:postcode":"b0n 1w0",
    "addr:street":"Church St",
    "iso:country":"CA",
    "sg:address":"522 Church St",
    "sg:city":"Micmac",
    "sg:classifiers":[
        {
            "category":"Organizations",
            "subcategory":"Professional Association",
            "type":"Services"
        }
    ],
    "sg:phone":"+1 902 758 2049",
    "sg:postcode":"B0N 1W0",
    "sg:province":"NS",
    "wof:name":"Shubenacadie Band Council",
    "wof:placetype":"venue"
},
  "geometry": {"coordinates":[-63.485565,45.092442],"type":"Point"}
}