{
  "type": "Feature",
  "properties": {
    "addr:full":"Sooke BC V0S 1N0",
    "addr:postcode":"v0s 1n0",
    "iso:country":"CA",
    "sg:city":"Sooke",
    "sg:classifiers":[
        {
            "category":"Social Services",
            "type":"Services"
        }
    ],
    "sg:phone":"+1 250 642 5152",
    "sg:postcode":"V0S 1N0",
    "sg:province":"BC",
    "sg:tags":[
        "organization",
        "welfare"
    ],
    "wof:name":"Sooke Family Resource Society",
    "wof:placetype":"venue"
},
  "geometry": {"coordinates":[-123.72506,48.3759],"type":"Point"}
}