{
  "type": "Feature",
  "properties": {
    "addr:full":"20 Rue Principale N Sutton QC J0E 2K0",
    "addr:housenumber":"20",
    "addr:postcode":"j0e 2k0",
    "addr:street":"Rue Principale N",
    "iso:country":"CA",
    "sg:address":"20 Rue Principale N",
    "sg:city":"Sutton",
    "sg:classifiers":[
        {
            "category":"Cinema",
            "subcategory":"Movie Rental",
            "type":"Entertainment"
        }
    ],
    "sg:phone":"+1 450 538 8484",
    "sg:postcode":"J0E 2K0",
    "sg:province":"QC",
    "sg:tags":[
        "video",
        "game",
        "tape",
        "leasing"
    ],
    "wof:name":"Video Sutton",
    "wof:placetype":"venue"
},
  "geometry": {"coordinates":[-72.615891,45.107849],"type":"Point"}
}