{
  "type": "Feature",
  "properties": {
    "addr:full":"4 Henry Welsh Dr North York ON M2R 3P4",
    "addr:housenumber":"4",
    "addr:postcode":"m2r 3p4",
    "addr:street":"Henry Welsh Dr",
    "iso:country":"CA",
    "sg:address":"4 Henry Welsh Dr",
    "sg:city":"North York",
    "sg:classifiers":[
        {
            "category":"Organizations",
            "subcategory":"Religious Organization",
            "type":"Services"
        }
    ],
    "sg:phone":"+1 416 741 1682",
    "sg:postcode":"M2R 3P4",
    "sg:province":"ON",
    "sg:tags":[
        "church"
    ],
    "wof:name":"MT Olive Sda Church",
    "wof:placetype":"venue"
},
  "geometry": {"coordinates":[-79.454178,43.773884],"type":"Point"}
}