{
  "type": "Feature",
  "properties": {
    "addr:full":"1177 Aerowood Dr Mississauga ON L4W 1Y6",
    "addr:housenumber":"1177",
    "addr:postcode":"l4w 1y6",
    "addr:street":"Aerowood Dr",
    "iso:country":"CA",
    "sg:address":"1177 Aerowood Dr",
    "sg:city":"Mississauga",
    "sg:classifiers":[
        {
            "category":"Wholesale",
            "subcategory":"Stationery",
            "type":"Manufacturing & Wholesale Goods"
        }
    ],
    "sg:phone":"+1 905 629 2702",
    "sg:postcode":"L4W 1Y6",
    "sg:province":"ON",
    "sg:tags":[
        "corrugated",
        "solid",
        "fiber",
        "box"
    ],
    "wof:name":"Independent Corrugator Inc",
    "wof:placetype":"venue"
},
  "geometry": {"coordinates":[-79.63916,43.639172],"type":"Point"}
}