{
  "type": "Feature",
  "properties": {
    "addr:full":"Uxbridge ON L9P 1V9",
    "addr:postcode":"l9p 1v9",
    "iso:country":"CA",
    "sg:city":"Uxbridge",
    "sg:classifiers":[
        {
            "category":"Health Services",
            "subcategory":"Optometrist",
            "type":"Services"
        }
    ],
    "sg:phone":"+1 905 852 3191",
    "sg:postcode":"L9P 1V9",
    "sg:province":"ON",
    "wof:name":"Mc Mullen, Ronald S OD",
    "wof:placetype":"venue"
},
  "geometry": {"coordinates":[-79.122756958,44.1077384949],"type":"Point"}
}