{
  "type": "Feature",
  "properties": {
    "addr:full":"64 Edmonton City Centre NW Edmonton AB T5J 2Y7",
    "addr:housenumber":"64",
    "addr:postcode":"t5j 2y7",
    "addr:street":"Edmonton;Nw",
    "iso:country":"CA",
    "sg:address":"64 Edmonton City Centre NW",
    "sg:city":"Edmonton",
    "sg:classifiers":[
        {
            "category":"Food & Beverages",
            "subcategory":"Candy",
            "type":"Retail Goods"
        }
    ],
    "sg:phone":"+1 780 414 1819",
    "sg:postcode":"T5J 2Y7",
    "sg:province":"AB",
    "sg:tags":[
        "popcorn",
        "supply"
    ],
    "wof:name":"Too Corny Gourmet Popcorn",
    "wof:placetype":"venue"
},
  "geometry": {"coordinates":[-113.490371704,53.5462188721],"type":"Point"}
}