{
  "type": "Feature",
  "properties": {
    "addr:full":"118 Rue Church Buckingham QC J8L 1P1",
    "addr:housenumber":"118",
    "addr:postcode":"j8l 1p1",
    "addr:street":"Rue Church",
    "iso:country":"CA",
    "sg:address":"118 Rue Church",
    "sg:city":"Buckingham",
    "sg:classifiers":[
        {
            "category":"Restaurant",
            "type":"Food & Drink"
        }
    ],
    "sg:phone":"+1 819 986 9161",
    "sg:postcode":"J8L 1P1",
    "sg:province":"QC",
    "wof:name":"B J Restaurant",
    "wof:placetype":"venue"
},
  "geometry": {"coordinates":[-75.41340599999999,45.584274],"type":"Point"}
}