{
  "type": "Feature",
  "properties": {
    "addr:full":"RR 1 Doyles NL A0N 1J0",
    "addr:postcode":"a0n 1j0",
    "addr:street":"Rr 1",
    "iso:country":"CA",
    "sg:address":"RR 1",
    "sg:city":"Doyles",
    "sg:classifiers":[
        {
            "category":"Travel",
            "subcategory":"Hotels & Motels",
            "type":"Entertainment"
        }
    ],
    "sg:phone":"+1 709 955 2535",
    "sg:postcode":"A0N 1J0",
    "sg:province":"NL",
    "wof:name":"Mac Lellan Country Inn",
    "wof:placetype":"venue"
},
  "geometry": {"coordinates":[-59.195911,47.824608],"type":"Point"}
}