{
  "type": "Feature",
  "properties": {
    "addr:full":"182 Main St Wellington ON K0K 3L0",
    "addr:housenumber":"182",
    "addr:postcode":"k0k 3l0",
    "addr:street":"Main St",
    "iso:country":"CA",
    "sg:address":"182 Main St",
    "sg:city":"Wellington",
    "sg:classifiers":[
        {
            "category":"Shopping",
            "subcategory":"Florist",
            "type":"Retail Goods"
        }
    ],
    "sg:phone":"+1 613 399 2064",
    "sg:postcode":"K0K 3L0",
    "sg:province":"ON",
    "sg:tags":[
        "nurseryman"
    ],
    "wof:name":"Wight Greenhouses",
    "wof:placetype":"venue"
},
  "geometry": {"coordinates":[-77.3411407471,43.9521408081],"type":"Point"}
}