{
  "type": "Feature",
  "properties": {
    "iso:country":"CA",
    "sg:city":"Richmond",
    "sg:classifiers":[
        {
            "category":"Freight",
            "type":"Transportation"
        }
    ],
    "sg:phone":"+1 604 276 8809",
    "sg:postcode":"V7B 1K5",
    "sg:province":"BC",
    "wof:name":"Carson Freight Svc",
    "wof:placetype":"venue"
},
  "geometry": {"coordinates":[-123.165489,49.192066],"type":"Point"}
}