{
  "type": "Feature",
  "properties": {
    "iso:country":"CA",
    "sg:city":"Saint-Cesaire",
    "sg:classifiers":[
        {
            "category":"Professional",
            "subcategory":"Engineering",
            "type":"Services"
        }
    ],
    "sg:phone":"+1 450 469 2136",
    "sg:postcode":"J0L 1T0",
    "sg:province":"QC",
    "sg:tags":[
        "engineer"
    ],
    "wof:name":"Enviro-Consul Enr",
    "wof:placetype":"venue"
},
  "geometry": {"coordinates":[-73.02494812010001,45.4161262512],"type":"Point"}
}