{
  "type": "Feature",
  "properties": {
    "iso:country":"CA",
    "sg:address":"6825 Boul DE LA Rive-Sud",
    "sg:city":"Levis",
    "sg:classifiers":[
        {
            "category":"Retail",
            "subcategory":"Auto Repair",
            "type":"Services"
        }
    ],
    "sg:phone":"+1 418 833 3441",
    "sg:postcode":"G6V 9H5",
    "sg:province":"QC",
    "sg:tags":[
        "repairing",
        "automobile",
        "body"
    ],
    "wof:name":"Radiateurs Levis Inc",
    "wof:placetype":"venue"
},
  "geometry": {"coordinates":[-71.1610412598,46.8096427917],"type":"Point"}
}