{
  "type": "Feature",
  "properties": {
    "addr:full":"Calgary AB T1Y 5L3",
    "addr:postcode":"t1y 5l3",
    "iso:country":"CA",
    "sg:city":"Calgary",
    "sg:classifiers":[
        {
            "category":"Manufacturing",
            "subcategory":"Glass & Minerals",
            "type":"Manufacturing & Wholesale Goods"
        }
    ],
    "sg:phone":"+1 403 250 5676",
    "sg:postcode":"T1Y 5L3",
    "sg:province":"AB",
    "sg:tags":[
        "abrasive",
        "product"
    ],
    "wof:name":"Sp 3L Td",
    "wof:placetype":"venue"
},
  "geometry": {"coordinates":[-113.99711600000001,51.086773],"type":"Point"}
}