{
  "type": "Feature",
  "properties": {
    "addr:full":"Abbotsford BC V2S 2E1",
    "addr:postcode":"v2s 2e1",
    "iso:country":"CA",
    "sg:city":"Abbotsford",
    "sg:classifiers":[
        {
            "category":"Shopping",
            "type":"Retail Goods"
        }
    ],
    "sg:phone":"+1 604 852 3930",
    "sg:postcode":"V2S 2E1",
    "sg:province":"BC",
    "sg:tags":[
        "orthopedic",
        "appliance"
    ],
    "wof:name":"Fraser Valley Advanced Ortho",
    "wof:placetype":"venue"
},
  "geometry": {"coordinates":[-122.26508331300001,49.0359153748],"type":"Point"}
}