{
  "type": "Feature",
  "properties": {
    "addr:full":"Vancouver BC V6A 2A1",
    "addr:postcode":"v6a 2a1",
    "iso:country":"CA",
    "sg:city":"Vancouver",
    "sg:classifiers":[
        {
            "category":"Health Services",
            "subcategory":"Doctor",
            "type":"Services"
        }
    ],
    "sg:phone":"+1 604 685 5620",
    "sg:postcode":"V6A 2A1",
    "sg:province":"BC",
    "sg:tags":[
        "dentist"
    ],
    "wof:name":"Robert E Patton Inc",
    "wof:placetype":"venue"
},
  "geometry": {"coordinates":[-123.09053,49.278252],"type":"Point"}
}