{
  "type": "Feature",
  "properties": {
    "iso:country":"CA",
    "sg:address":"6807 Rue DE Marseille",
    "sg:city":"Montreal",
    "sg:classifiers":[
        {
            "category":"Organizations",
            "subcategory":"Professional Association",
            "type":"Services"
        }
    ],
    "sg:phone":"+1 514 254 7437",
    "sg:postcode":"H1N 1M6",
    "sg:province":"QC",
    "wof:name":"Camping Familial Comm Inc",
    "wof:placetype":"venue"
},
  "geometry": {"coordinates":[-73.538338,45.583336],"type":"Point"}
}