{
  "type": "Feature",
  "properties": {
    "addr:full":"23 White Ave Bragg Creek AB T0L 0K0",
    "addr:housenumber":"23",
    "addr:postcode":"t0l 0k0",
    "addr:street":"White Ave",
    "iso:country":"CA",
    "sg:address":"23 White Ave",
    "sg:city":"Bragg Creek",
    "sg:classifiers":[
        {
            "category":"Recreation",
            "type":"Entertainment"
        }
    ],
    "sg:phone":"+1 403 949 4277",
    "sg:postcode":"T0L 0K0",
    "sg:province":"AB",
    "sg:tags":[
        "hall",
        "auditorium"
    ],
    "wof:name":"Bragg Creek Community Assn",
    "wof:placetype":"venue"
},
  "geometry": {"coordinates":[-114.561874,50.950348],"type":"Point"}
}