{
  "type": "Feature",
  "properties": {
    "addr:full":"34 1/2 Rte Du President-Kenned Saint-Henri-DE-Levis QC G0R 3E0",
    "addr:housenumber":"1 / 2",
    "addr:postcode":"g0r 3e0",
    "addr:street":"34;Rte Du President-Kenned Saint-Henri-De-Levis",
    "iso:country":"CA",
    "sg:address":"34 1/2 Rte Du President-Kenned",
    "sg:city":"Saint-Henri-DE-Levis",
    "sg:classifiers":[
        {
            "category":"Manufacturing",
            "subcategory":"Tools & Machinery",
            "type":"Manufacturing & Wholesale Goods"
        }
    ],
    "sg:phone":"+1 418 882 5115",
    "sg:postcode":"G0R 3E0",
    "sg:province":"QC",
    "sg:tags":[
        "machine",
        "shop"
    ],
    "wof:name":"Atelier Multi-Drive",
    "wof:placetype":"venue"
},
  "geometry": {"coordinates":[-71.07176200000001,46.689098],"type":"Point"}
}