{
  "type": "Feature",
  "properties": {
    "iso:country":"CA",
    "sg:address":"1927 Rue Papineau",
    "sg:city":"Longueuil",
    "sg:classifiers":[
        {
            "category":"Retail",
            "subcategory":"Repair Shop",
            "type":"Services"
        }
    ],
    "sg:phone":"+1 514 256 2003",
    "sg:postcode":"J4K 3L7",
    "sg:province":"QC",
    "sg:tags":[
        "lock",
        "locksmith"
    ],
    "wof:name":"Action Serrurier Alarme",
    "wof:placetype":"venue"
},
  "geometry": {"coordinates":[-73.4907073975,45.5137062073],"type":"Point"}
}