{
  "type": "Feature",
  "properties": {
    "addr:full":"439 Government St Dryden ON P8N 2P4",
    "addr:housenumber":"439",
    "addr:postcode":"p8n 2p4",
    "addr:street":"Government St",
    "iso:country":"CA",
    "sg:address":"439 Government St",
    "sg:city":"Dryden",
    "sg:classifiers":[
        {
            "category":"Food & Beverages",
            "subcategory":"Groceries & Convenience Stores",
            "type":"Retail Goods"
        }
    ],
    "sg:phone":"+1 807 221 6667",
    "sg:postcode":"P8N 2P4",
    "sg:province":"ON",
    "sg:tags":[
        "frozen"
    ],
    "wof:name":"M & M Meat Shops",
    "wof:placetype":"venue"
},
  "geometry": {"coordinates":[-92.829239,49.786293],"type":"Point"}
}