{
  "type": "Feature",
  "properties": {
    "addr:full":"Upperton NB E5N 2N7",
    "addr:postcode":"e5n 2n7",
    "iso:country":"CA",
    "sg:city":"Upperton",
    "sg:classifiers":[
        {
            "category":"Organizations",
            "subcategory":"Religious Organization",
            "type":"Services"
        }
    ],
    "sg:phone":"+1 506 362 6247",
    "sg:postcode":"E5N 2N7",
    "sg:province":"NB",
    "sg:tags":[
        "church"
    ],
    "wof:name":"Spirit of Freedom Pent Church",
    "wof:placetype":"venue"
},
  "geometry": {"coordinates":[-65.61232757569999,45.4971313477],"type":"Point"}
}