{
  "type": "Feature",
  "properties": {
    "addr:full":"3990 Boul Saint-Martin O Laval QC H7T 1B8",
    "addr:housenumber":"3990",
    "addr:postcode":"h7t 1b8",
    "addr:street":"Boul Saint-Martin O",
    "iso:country":"CA",
    "sg:address":"3990 Boul Saint-Martin O",
    "sg:city":"Laval",
    "sg:classifiers":[
        {
            "category":"Personal",
            "subcategory":"Beauty Salon",
            "type":"Services"
        }
    ],
    "sg:phone":"+1 450 682 0208",
    "sg:postcode":"H7T 1B8",
    "sg:province":"QC",
    "wof:name":"Salon Jo-Ann Lajeunesse Inc",
    "wof:placetype":"venue"
},
  "geometry": {"coordinates":[-73.7618637085,45.5506134033],"type":"Point"}
}