{
  "type": "Feature",
  "properties": {
    "addr:full":"22 Rue DE L'Eglise Sud Lacolle QC J0J 1J0",
    "addr:housenumber":"22",
    "addr:postcode":"j0j 1j0",
    "addr:street":"Rue De L'Eglise Sud",
    "iso:country":"CA",
    "sg:address":"22 Rue DE L'Eglise Sud",
    "sg:city":"Lacolle",
    "sg:classifiers":[
        {
            "category":"Restaurant",
            "type":"Food & Drink"
        }
    ],
    "sg:phone":"+1 450 246 4004",
    "sg:postcode":"J0J 1J0",
    "sg:province":"QC",
    "wof:name":"Resto Rue DE L'Eglise",
    "wof:placetype":"venue"
},
  "geometry": {"coordinates":[-73.372147,45.079021],"type":"Point"}
}