{
  "type": "Feature",
  "properties": {
    "addr:full":"Calgary AB T1Y 4T7",
    "addr:postcode":"t1y 4t7",
    "iso:country":"CA",
    "sg:city":"Calgary",
    "sg:classifiers":[
        {
            "category":"Professional",
            "type":"Services"
        }
    ],
    "sg:phone":"+1 403 291 0865",
    "sg:postcode":"T1Y 4T7",
    "sg:province":"AB",
    "sg:tags":[
        "arts",
        "artist"
    ],
    "wof:name":"Greco Studios Ltd",
    "wof:placetype":"venue"
},
  "geometry": {"coordinates":[-113.997559,51.084545],"type":"Point"}
}