{
  "type": "Feature",
  "properties": {
    "addr:full":"445 Boundary Rd Sault Ste Marie ON P6A 5Z2",
    "addr:housenumber":"445",
    "addr:postcode":"p6a 5z2",
    "addr:street":"Boundary Rd",
    "iso:country":"CA",
    "sg:address":"445 Boundary Rd",
    "sg:city":"Sault Ste Marie",
    "sg:classifiers":[
        {
            "category":"Organizations",
            "subcategory":"Professional Association",
            "type":"Services"
        }
    ],
    "sg:phone":"+1 705 759 2741",
    "sg:postcode":"P6A 5Z2",
    "sg:province":"ON",
    "wof:name":"Community Living Algoma",
    "wof:placetype":"venue"
},
  "geometry": {"coordinates":[-84.271034,46.513657],"type":"Point"}
}