{
  "type": "Feature",
  "properties": {
    "addr:full":"Calgary AB T2N 3R7",
    "addr:postcode":"t2n 3r7",
    "iso:country":"CA",
    "sg:city":"Calgary",
    "sg:classifiers":[
        {
            "category":"Shopping",
            "subcategory":"Florist",
            "type":"Retail Goods"
        }
    ],
    "sg:phone":"+1 403 283 6747",
    "sg:postcode":"T2N 3R7",
    "sg:province":"AB",
    "wof:name":"Blush Flowers & Gifts",
    "wof:placetype":"venue"
},
  "geometry": {"coordinates":[-114.10833700000001,51.052631],"type":"Point"}
}