{
  "type": "Feature",
  "properties": {
    "iso:country":"CA",
    "sg:address":"667 County Rd 20",
    "sg:city":"Kingsville",
    "sg:classifiers":[
        {
            "category":"Building & Trades",
            "subcategory":"Construction",
            "type":"Services"
        }
    ],
    "sg:phone":"+1 519 733 5882",
    "sg:postcode":"N9Y 2E6",
    "sg:province":"ON",
    "sg:tags":[
        "masonry",
        "contractor"
    ],
    "wof:name":"Santal Homes Ltd",
    "wof:placetype":"venue"
},
  "geometry": {"coordinates":[-82.74031066889999,42.0378837585],"type":"Point"}
}