{
  "type": "Feature",
  "properties": {
    "iso:country":"CA",
    "sg:address":"12295 Highway 50 # 7",
    "sg:city":"Bolton",
    "sg:classifiers":[
        {
            "category":"Building & Trades",
            "subcategory":"Construction",
            "type":"Services"
        }
    ],
    "sg:phone":"+1 905 857 2543",
    "sg:postcode":"L7E 1M2",
    "sg:province":"ON",
    "sg:tags":[
        "general",
        "contractor"
    ],
    "wof:name":"Lisgar Construction CO",
    "wof:placetype":"venue"
},
  "geometry": {"coordinates":[-79.739433,43.880852],"type":"Point"}
}