{
  "type": "Feature",
  "properties": {
    "iso:country":"CA",
    "sg:city":"Winnipeg",
    "sg:classifiers":[
        {
            "category":"Manufacturing",
            "subcategory":"Printing",
            "type":"Manufacturing & Wholesale Goods"
        }
    ],
    "sg:phone":"+1 204 475 6799",
    "sg:postcode":"R3B 1G7",
    "sg:province":"MB",
    "sg:tags":[
        "publisher"
    ],
    "wof:name":"Great Plains Publications",
    "wof:placetype":"venue"
},
  "geometry": {"coordinates":[-97.14134979249999,49.8969764709],"type":"Point"}
}