{
  "type": "Feature",
  "properties": {
    "addr:full":"Saskatoon SK S7K 5W2",
    "addr:postcode":"s7k 5w2",
    "iso:country":"CA",
    "sg:city":"Saskatoon",
    "sg:classifiers":[
        {
            "category":"Mining & Drilling",
            "type":"Manufacturing & Wholesale Goods"
        }
    ],
    "sg:phone":"+1 306 665 8411",
    "sg:postcode":"S7K 5W2",
    "sg:province":"SK",
    "sg:tags":[
        "jacking",
        "mud",
        "contractor"
    ],
    "wof:name":"Nykmac Industries Ltd",
    "wof:placetype":"venue"
},
  "geometry": {"coordinates":[-106.665061951,52.168712616],"type":"Point"}
}