{
  "type": "Feature",
  "properties": {
    "addr:full":"Pickering ON L1W 3R3",
    "addr:postcode":"l1w 3r3",
    "iso:country":"CA",
    "sg:city":"Pickering",
    "sg:classifiers":[
        {
            "category":"Restaurant",
            "type":"Food & Drink"
        }
    ],
    "sg:phone":"+1 905 420 2309",
    "sg:postcode":"L1W 3R3",
    "sg:province":"ON",
    "sg:tags":[
        "cafe"
    ],
    "wof:name":"Classic Coffee House",
    "wof:placetype":"venue"
},
  "geometry": {"coordinates":[-79.0802154541,43.8303756714],"type":"Point"}
}