{
  "type": "Feature",
  "properties": {
    "addr:full":"4056 Blakie Rd London ON N6L 1P7",
    "addr:housenumber":"4056",
    "addr:postcode":"n6l 1p7",
    "addr:street":"Blakie Rd",
    "iso:country":"CA",
    "sg:address":"4056 Blakie Rd",
    "sg:city":"London",
    "sg:classifiers":[
        {
            "category":"Professional",
            "subcategory":"Research",
            "type":"Services"
        }
    ],
    "sg:phone":"+1 519 652 5833",
    "sg:postcode":"N6L 1P7",
    "sg:province":"ON",
    "sg:tags":[
        "control",
        "development",
        "electronic"
    ],
    "wof:name":"Oes Inc",
    "wof:placetype":"venue"
},
  "geometry": {"coordinates":[-81.24923706049999,42.9201927185],"type":"Point"}
}