{
  "type": "Feature",
  "properties": {
    "iso:country":"CA",
    "sg:address":"122 Michener Rd",
    "sg:city":"Chatham",
    "sg:classifiers":[
        {
            "category":"Real Estate",
            "subcategory":"Real Estate Agent",
            "type":"Services"
        }
    ],
    "sg:phone":"+1 519 351 2395",
    "sg:postcode":"N7L 4C1",
    "sg:province":"ON",
    "wof:name":"Doub, John",
    "wof:placetype":"venue"
},
  "geometry": {"coordinates":[-82.1772766113,42.4213485718],"type":"Point"}
}