{
  "type": "Feature",
  "properties": {
    "addr:full":"430 5 Ave E Cardston AB T0K 0K0",
    "addr:housenumber":"430",
    "addr:postcode":"t0k 0k0",
    "addr:street":"5 Ave E Cardston",
    "iso:country":"CA",
    "sg:address":"430 5 Ave E",
    "sg:city":"Cardston",
    "sg:classifiers":[
        {
            "category":"Education",
            "subcategory":"School",
            "type":"Public Place"
        }
    ],
    "sg:phone":"+1 403 653 4958",
    "sg:postcode":"T0K 0K0",
    "sg:province":"AB",
    "wof:name":"Cardston Jr High School",
    "wof:placetype":"venue"
},
  "geometry": {"coordinates":[-113.292519,49.195683],"type":"Point"}
}