{
  "type": "Feature",
  "properties": {
    "addr:full":"540 Rte DE Martinville Compton QC J0B 1L0",
    "addr:housenumber":"540",
    "addr:postcode":"j0b 1l0",
    "addr:street":"Rte De Martinville",
    "iso:country":"CA",
    "sg:address":"540 Rte DE Martinville",
    "sg:city":"Compton",
    "sg:classifiers":[
        {
            "category":"Wholesale",
            "subcategory":"Machinery & Supplies",
            "type":"Manufacturing & Wholesale Goods"
        }
    ],
    "sg:phone":"+1 819 835 5502",
    "sg:postcode":"J0B 1L0",
    "sg:province":"QC",
    "sg:tags":[
        "equipment",
        "dairy"
    ],
    "wof:name":"Richard Equipement Laitier Inc",
    "wof:placetype":"venue"
},
  "geometry": {"coordinates":[-71.75951385499999,45.2552986145],"type":"Point"}
}