{
  "type": "Feature",
  "properties": {
    "addr:full":"80 Dundas St Cambridge ON N1R 5S2",
    "addr:housenumber":"80",
    "addr:postcode":"n1r 5s2",
    "addr:street":"Dundas St",
    "iso:country":"CA",
    "sg:address":"80 Dundas St",
    "sg:city":"Cambridge",
    "sg:classifiers":[
        {
            "category":"Cinema",
            "subcategory":"Movie Rental",
            "type":"Entertainment"
        }
    ],
    "sg:phone":"+1 519 623 3099",
    "sg:postcode":"N1R 5S2",
    "sg:province":"ON",
    "sg:tags":[
        "leasing",
        "video",
        "disc",
        "tape"
    ],
    "wof:name":"Blockbuster Video Canada",
    "wof:placetype":"venue"
},
  "geometry": {"coordinates":[-80.29402899999999,43.358448],"type":"Point"}
}