{
  "type": "Feature",
  "properties": {
    "iso:country":"CA",
    "sg:address":"10240 115 St NW",
    "sg:city":"Edmonton",
    "sg:classifiers":[
        {
            "category":"Recreation",
            "type":"Entertainment"
        }
    ],
    "sg:phone":"+1 780 471 1932",
    "sg:postcode":"T5K 1T8",
    "sg:province":"AB",
    "sg:tags":[
        "center",
        "hall",
        "auditorium"
    ],
    "wof:name":"Spruce Avenue Community Ctr",
    "wof:placetype":"venue"
},
  "geometry": {"coordinates":[-113.519669,53.543579],"type":"Point"}
}