{
  "type": "Feature",
  "properties": {
    "addr:full":"10240 115 St NW Edmonton AB T5K 1T8",
    "addr:housenumber":"10240",
    "addr:postcode":"t5k 1t8",
    "addr:street":"115 St Nw",
    "iso:country":"CA",
    "sg:address":"10240 115 St NW",
    "sg:city":"Edmonton",
    "sg:classifiers":[
        {
            "category":"Recreation",
            "type":"Entertainment"
        }
    ],
    "sg:phone":"+1 780 471 1932",
    "sg:postcode":"T5K 1T8",
    "sg:province":"AB",
    "sg:tags":[
        "center",
        "hall",
        "auditorium"
    ],
    "wof:name":"Spruce Avenue Community Ctr",
    "wof:placetype":"venue"
},
  "geometry": {"coordinates":[-113.51966899999999,53.543579],"type":"Point"}
}