{
  "type": "Feature",
  "properties": {
    "iso:country":"CA",
    "sg:address":"645 Richmond St",
    "sg:city":"London",
    "sg:classifiers":[
        {
            "category":"Restaurant",
            "type":"Food & Drink"
        }
    ],
    "sg:phone":"+1 519 645 6400",
    "sg:postcode":"N6A 3G7",
    "sg:province":"ON",
    "wof:name":"Mongolian Grill",
    "wof:placetype":"venue"
},
  "geometry": {"coordinates":[-81.251404,42.991882],"type":"Point"}
}