{
  "type": "Feature",
  "properties": {
    "addr:full":"645 Richmond St London ON N6A 3G7",
    "addr:housenumber":"645",
    "addr:postcode":"n6a 3g7",
    "addr:street":"Richmond St",
    "iso:country":"CA",
    "sg:address":"645 Richmond St",
    "sg:city":"London",
    "sg:classifiers":[
        {
            "category":"Restaurant",
            "type":"Food & Drink"
        }
    ],
    "sg:phone":"+1 519 645 6400",
    "sg:postcode":"N6A 3G7",
    "sg:province":"ON",
    "wof:name":"Mongolian Grill",
    "wof:placetype":"venue"
},
  "geometry": {"coordinates":[-81.25140399999999,42.991882],"type":"Point"}
}