{
  "type": "Feature",
  "properties": {
    "addr:full":"14 Hallowell Grant Rd Antigonish NS B2G 2L6",
    "addr:housenumber":"14",
    "addr:postcode":"b2g 2l6",
    "addr:street":"Hallowell Grant Rd",
    "iso:country":"CA",
    "sg:address":"14 Hallowell Grant Rd",
    "sg:city":"Antigonish",
    "sg:classifiers":[
        {
            "category":"Wholesale",
            "subcategory":"Construction Materials",
            "type":"Manufacturing & Wholesale Goods"
        }
    ],
    "sg:phone":"+1 902 863 1071",
    "sg:postcode":"B2G 2L6",
    "sg:province":"NS",
    "sg:tags":[
        "sand",
        "gravel"
    ],
    "wof:name":"Kell's Enterprises",
    "wof:placetype":"venue"
},
  "geometry": {"coordinates":[-61.99427,45.622189],"type":"Point"}
}