{
  "type": "Feature",
  "properties": {
    "addr:full":"461 Mcintyre St W North Bay ON P1B 2Z3",
    "addr:housenumber":"461",
    "addr:postcode":"p1b 2z3",
    "addr:street":"Mcintyre St W",
    "iso:country":"CA",
    "sg:address":"461 Mcintyre St W",
    "sg:city":"North Bay",
    "sg:classifiers":[
        {
            "category":"Professional",
            "subcategory":"Lawyer & Legal Services",
            "type":"Services"
        }
    ],
    "sg:phone":"+1 705 476 1110",
    "sg:postcode":"P1B 2Z3",
    "sg:province":"ON",
    "sg:tags":[
        "attorney"
    ],
    "wof:name":"Gregson, Nathalie",
    "wof:placetype":"venue"
},
  "geometry": {"coordinates":[-79.46717099999999,46.315571],"type":"Point"}
}