{
  "type": "Feature",
  "properties": {
    "addr:full":"6555 Boul Metropolitain E # 407 Saint-Leonard QC H1P 3H3",
    "addr:housenumber":"6555",
    "addr:postcode":"h1p 3h3",
    "addr:street":"Boul Metropolitain E # 407",
    "iso:country":"CA",
    "sg:address":"6555 Boul Metropolitain E # 407",
    "sg:city":"Saint-Leonard",
    "sg:classifiers":[
        {
            "category":"Professional",
            "subcategory":"Computer Services",
            "type":"Services"
        }
    ],
    "sg:phone":"+1 514 321 4505",
    "sg:postcode":"H1P 3H3",
    "sg:province":"QC",
    "sg:tags":[
        "information",
        "system",
        "consultant"
    ],
    "wof:name":"Interpro Consultants Inc",
    "wof:placetype":"venue"
},
  "geometry": {"coordinates":[-73.57635500000001,45.595268],"type":"Point"}
}