{
  "type": "Feature",
  "properties": {
    "iso:country":"CA",
    "sg:city":"Revelstoke",
    "sg:classifiers":[
        {
            "category":"Utilities",
            "subcategory":"Fuel Oil & Lpg",
            "type":"Services"
        }
    ],
    "sg:phone":"+1 250 837 5119",
    "sg:postcode":"V0E 2S0",
    "sg:province":"BC",
    "sg:tags":[
        "propane",
        "lottery",
        "gas",
        "agent"
    ],
    "wof:name":"Frontier Super Save",
    "wof:placetype":"venue"
},
  "geometry": {"coordinates":[-118.214477539,51.0101470947],"type":"Point"}
}