{
  "type": "Feature",
  "properties": {
    "addr:full":"Birsay SK S0L 0G0",
    "addr:postcode":"s0l 0g0",
    "addr:street":"Birsay",
    "iso:country":"CA",
    "sg:city":"Birsay",
    "sg:classifiers":[
        {
            "category":"Travel",
            "subcategory":"Hotels & Motels",
            "type":"Entertainment"
        }
    ],
    "sg:phone":"+1 306 573 4446",
    "sg:postcode":"S0L 0G0",
    "sg:province":"SK",
    "sg:tags":[
        "resort"
    ],
    "wof:name":"Hitchcock's Hideaway",
    "wof:placetype":"venue"
},
  "geometry": {"coordinates":[-106.985146,51.094364],"type":"Point"}
}