{
  "type": "Feature",
  "properties": {
    "iso:country":"CA",
    "sg:address":"49 Copeland Rd",
    "sg:city":"Brampton",
    "sg:classifiers":[
        {
            "category":"Building & Trades",
            "subcategory":"Construction",
            "type":"Services"
        }
    ],
    "sg:phone":"+1 905 796 1819",
    "sg:postcode":"L6Y 2S5",
    "sg:province":"ON",
    "sg:tags":[
        "home",
        "painter",
        "improvement"
    ],
    "wof:name":"Prim & Proper Painter",
    "wof:placetype":"venue"
},
  "geometry": {"coordinates":[-79.7525253296,43.6609573364],"type":"Point"}
}