{
  "type": "Feature",
  "properties": {
    "addr:full":"Laval QC H7V 3Y4",
    "addr:postcode":"h7v 3y4",
    "iso:country":"CA",
    "sg:city":"Laval",
    "sg:classifiers":[
        {
            "category":"Shopping",
            "subcategory":"Pharmacy",
            "type":"Retail Goods"
        }
    ],
    "sg:phone":"+1 450 682 7711",
    "sg:postcode":"H7V 3Y4",
    "sg:province":"QC",
    "wof:name":"Uniprix",
    "wof:placetype":"venue"
},
  "geometry": {"coordinates":[-73.740196228,45.5450515747],"type":"Point"}
}