{
  "type": "Feature",
  "properties": {
    "addr:full":"Edson AB T7E 1V1",
    "addr:postcode":"t7e 1v1",
    "iso:country":"CA",
    "sg:city":"Edson",
    "sg:classifiers":[
        {
            "category":"Health Services",
            "subcategory":"Doctor",
            "type":"Services"
        }
    ],
    "sg:phone":"+1 780 723 3366",
    "sg:postcode":"T7E 1V1",
    "sg:province":"AB",
    "sg:tags":[
        "clinic"
    ],
    "wof:name":"Edson Medical Ctr",
    "wof:placetype":"venue"
},
  "geometry": {"coordinates":[-116.433983,53.585228],"type":"Point"}
}