{
  "type": "Feature",
  "properties": {
    "addr:full":"12 Drapeau St Balmoral NB E8E 1H2",
    "addr:housenumber":"12",
    "addr:postcode":"e8e 1h2",
    "addr:street":"Drapeau St",
    "iso:country":"CA",
    "sg:address":"12 Drapeau St",
    "sg:city":"Balmoral",
    "sg:classifiers":[
        {
            "category":"Restaurant",
            "type":"Food & Drink"
        }
    ],
    "sg:phone":"+1 506 826 1122",
    "sg:postcode":"E8E 1H2",
    "sg:province":"NB",
    "sg:tags":[
        "chicken",
        "dinner"
    ],
    "wof:name":"Poulet Fritou",
    "wof:placetype":"venue"
},
  "geometry": {"coordinates":[-66.405823,47.98307],"type":"Point"}
}