{
  "type": "Feature",
  "properties": {
    "addr:full":"381 2nd Ave Campbell River BC V9W 3V1",
    "addr:housenumber":"381",
    "addr:postcode":"v9w 3v1",
    "addr:street":"2Nd Ave",
    "iso:country":"CA",
    "sg:address":"381 2nd Ave",
    "sg:city":"Campbell River",
    "sg:classifiers":[
        {
            "category":"Government",
            "subcategory":"Office",
            "type":"Public Place"
        }
    ],
    "sg:phone":"+1 250 286 7063",
    "sg:postcode":"V9W 3V1",
    "sg:province":"BC",
    "wof:name":"Campbell River Community Hlth",
    "wof:placetype":"venue"
},
  "geometry": {"coordinates":[-125.243301,50.010937],"type":"Point"}
}