{
  "type": "Feature",
  "properties": {
    "addr:full":"9 Kakulu Rd #A Kanata ON K2L 2L4",
    "addr:housenumber":"9",
    "addr:postcode":"k2l 2l4",
    "addr:street":"Kakulu Rd # A",
    "iso:country":"CA",
    "sg:address":"9 Kakulu Rd #A",
    "sg:city":"Kanata",
    "sg:classifiers":[
        {
            "category":"Restaurant",
            "type":"Food & Drink"
        }
    ],
    "sg:phone":"+1 613 592 0000",
    "sg:postcode":"K2L 2L4",
    "sg:province":"ON",
    "wof:name":"Maple Court Dining Lounge",
    "wof:placetype":"venue"
},
  "geometry": {"coordinates":[-75.881699,45.309868],"type":"Point"}
}