{
  "type": "Feature",
  "properties": {
    "addr:full":"299 Victoria St Centralia ON N0M 1K0",
    "addr:housenumber":"299",
    "addr:postcode":"n0m 1k0",
    "addr:street":"Victoria St",
    "iso:country":"CA",
    "sg:address":"299 Victoria St",
    "sg:city":"Centralia",
    "sg:classifiers":[
        {
            "category":"Building & Trades",
            "subcategory":"Electrical",
            "type":"Services"
        }
    ],
    "sg:phone":"+1 519 228 6679",
    "sg:postcode":"N0M 1K0",
    "sg:province":"ON",
    "sg:tags":[
        "electric",
        "contractor"
    ],
    "wof:name":"Hodge Electric Ltd",
    "wof:placetype":"venue"
},
  "geometry": {"coordinates":[-81.47207641599999,43.2826576233],"type":"Point"}
}