{
  "type": "Feature",
  "properties": {
    "addr:full":"146 Kennedy Ave Sydney NS B1P 3K8",
    "addr:housenumber":"146",
    "addr:postcode":"b1p 3k8",
    "addr:street":"Kennedy Ave",
    "iso:country":"CA",
    "sg:address":"146 Kennedy Ave",
    "sg:city":"Sydney",
    "sg:classifiers":[
        {
            "category":"Professional",
            "subcategory":"Business Services",
            "type":"Services"
        }
    ],
    "sg:phone":"+1 902 567 0332",
    "sg:postcode":"B1P 3K8",
    "sg:province":"NS",
    "sg:tags":[
        "designer",
        "marine",
        "diver",
        "contractor"
    ],
    "wof:name":"Offshore Diving & Salvage Ltd",
    "wof:placetype":"venue"
},
  "geometry": {"coordinates":[-60.171295,46.127151],"type":"Point"}
}