{
  "type": "Feature",
  "properties": {
    "addr:full":"Chambord QC G0W 1G0",
    "addr:postcode":"g0w 1g0",
    "iso:country":"CA",
    "sg:city":"Chambord",
    "sg:classifiers":[
        {
            "category":"Recreation",
            "type":"Entertainment"
        }
    ],
    "sg:phone":"+1 418 342 8387",
    "sg:postcode":"G0W 1G0",
    "sg:province":"QC",
    "sg:tags":[
        "government",
        "hall",
        "auditorium"
    ],
    "wof:name":"Centre Communautaire-Chambord",
    "wof:placetype":"venue"
},
  "geometry": {"coordinates":[-72.0559997559,48.4283027649],"type":"Point"}
}