{
  "type": "Feature",
  "properties": {
    "iso:country":"CA",
    "sg:address":"1751 Ch Du Lac-Renaud",
    "sg:city":"Sainte-Adele",
    "sg:classifiers":[
        {
            "category":"Building & Trades",
            "subcategory":"Construction",
            "type":"Services"
        }
    ],
    "sg:phone":"+1 450 229 6811",
    "sg:postcode":"J8B 2T5",
    "sg:province":"QC",
    "sg:tags":[
        "general",
        "contractor"
    ],
    "wof:name":"Construction Stewart Inc",
    "wof:placetype":"venue"
},
  "geometry": {"coordinates":[-74.19440460209999,45.929775238],"type":"Point"}
}