{
  "type": "Feature",
  "properties": {
    "addr:full":"Telkwa BC V0J 2X0",
    "addr:postcode":"v0j 2x0",
    "iso:country":"CA",
    "sg:city":"Telkwa",
    "sg:classifiers":[
        {
            "category":"Manufacturing",
            "subcategory":"Lumber",
            "type":"Manufacturing & Wholesale Goods"
        }
    ],
    "sg:phone":"+1 250 846 5060",
    "sg:postcode":"V0J 2X0",
    "sg:province":"BC",
    "sg:tags":[
        "forester"
    ],
    "wof:name":"Pro-Tech Forest Resources Ltd",
    "wof:placetype":"venue"
},
  "geometry": {"coordinates":[-127.05880000000001,54.70892],"type":"Point"}
}