{
  "type": "Feature",
  "properties": {
    "addr:full":"275 Muskoka Rd N Gravenhurst ON P1P 1X2",
    "addr:housenumber":"275",
    "addr:postcode":"p1p 1x2",
    "addr:street":"Muskoka Rd N",
    "iso:country":"CA",
    "sg:address":"275 Muskoka Rd N",
    "sg:city":"Gravenhurst",
    "sg:classifiers":[
        {
            "category":"Shopping",
            "subcategory":"Used Merchandise",
            "type":"Retail Goods"
        }
    ],
    "sg:phone":"+1 705 687 5079",
    "sg:postcode":"P1P 1X2",
    "sg:province":"ON",
    "sg:tags":[
        "second",
        "hand",
        "store",
        "furniture"
    ],
    "wof:name":"Elephant's Trunk",
    "wof:placetype":"venue"
},
  "geometry": {"coordinates":[-79.37487792970001,44.921257019],"type":"Point"}
}