{
  "type": "Feature",
  "properties": {
    "addr:full":"109 Marion St Winnipeg MB R2H 0T2",
    "addr:housenumber":"109",
    "addr:postcode":"r2h 0t2",
    "addr:street":"Marion St",
    "iso:country":"CA",
    "sg:address":"109 Marion St",
    "sg:city":"Winnipeg",
    "sg:classifiers":[
        {
            "category":"Restaurant",
            "type":"Food & Drink"
        }
    ],
    "sg:phone":"+1 204 231 1403",
    "sg:postcode":"R2H 0T2",
    "sg:province":"MB",
    "wof:name":"Pasquale's Restaurant",
    "wof:placetype":"venue"
},
  "geometry": {"coordinates":[-97.124031,49.881535],"type":"Point"}
}