{
  "type": "Feature",
  "properties": {
    "addr:full":"11580 Twigg Pl Richmond BC V6V 2K7",
    "addr:postcode":"11580;v6v 2k7",
    "addr:street":"Twigg Pl",
    "iso:country":"CA",
    "sg:address":"11580 Twigg Pl",
    "sg:city":"Richmond",
    "sg:classifiers":[
        {
            "category":"Wholesale",
            "subcategory":"Auto Parts",
            "type":"Manufacturing & Wholesale Goods"
        }
    ],
    "sg:phone":"+1 604 325 8220",
    "sg:postcode":"V6V 2K7",
    "sg:province":"BC",
    "sg:tags":[
        "automobile",
        "rebuilt"
    ],
    "wof:name":"H T Auto Wrecking Ltd",
    "wof:placetype":"venue"
},
  "geometry": {"coordinates":[-123.09610000000001,49.202812],"type":"Point"}
}