{
  "type": "Feature",
  "properties": {
    "addr:full":"302 Main St Biggar SK S0K 0M0",
    "addr:housenumber":"302",
    "addr:postcode":"s0k 0m0",
    "addr:street":"Main St",
    "iso:country":"CA",
    "sg:address":"302 Main St",
    "sg:city":"Biggar",
    "sg:classifiers":[
        {
            "category":"Manufacturing",
            "subcategory":"Motor Vehicles & Parts",
            "type":"Manufacturing & Wholesale Goods"
        }
    ],
    "sg:phone":"+1 306 948 5214",
    "sg:postcode":"S0K 0M0",
    "sg:province":"SK",
    "sg:tags":[
        "equipment",
        "truck"
    ],
    "wof:name":"Wheelex",
    "wof:placetype":"venue"
},
  "geometry": {"coordinates":[-107.984947205,52.0559539795],"type":"Point"}
}