{
  "type": "Feature",
  "properties": {
    "addr:full":"1003 Boul Cure-Labelle Laval QC H7V 2V6",
    "addr:housenumber":"1003",
    "addr:postcode":"h7v 2v6",
    "addr:street":"Boul Cure-Labelle",
    "iso:country":"CA",
    "sg:address":"1003 Boul Cure-Labelle",
    "sg:city":"Laval",
    "sg:classifiers":[
        {
            "category":"Cinema",
            "subcategory":"Movie Rental",
            "type":"Entertainment"
        }
    ],
    "sg:phone":"+1 450 687 4222",
    "sg:postcode":"H7V 2V6",
    "sg:province":"QC",
    "sg:tags":[
        "leasing",
        "video",
        "disc",
        "tape"
    ],
    "wof:name":"Video Super Choix",
    "wof:placetype":"venue"
},
  "geometry": {"coordinates":[-73.750198,45.542873],"type":"Point"}
}