{
  "type": "Feature",
  "properties": {
    "iso:country":"CA",
    "sg:address":"910 Cobalt Cres",
    "sg:city":"Thunder Bay",
    "sg:classifiers":[
        {
            "category":"Organizations",
            "subcategory":"Labor Organization",
            "type":"Services"
        }
    ],
    "sg:phone":"+1 807 623 7335",
    "sg:postcode":"P7B 5W3",
    "sg:province":"ON",
    "wof:name":"Health & Insurance Plan Admin",
    "wof:placetype":"venue"
},
  "geometry": {"coordinates":[-89.255043,48.411201],"type":"Point"}
}