{
  "type": "Feature",
  "properties": {
    "addr:full":"7622 Rockpoole Dr Vancouver BC V5X 4T1",
    "addr:housenumber":"7622",
    "addr:postcode":"v5x 4t1",
    "addr:street":"Rockpoole Dr",
    "iso:country":"CA",
    "sg:address":"7622 Rockpoole Dr",
    "sg:city":"Vancouver",
    "sg:classifiers":[
        {
            "category":"Real Estate",
            "subcategory":"Real Estate Operator",
            "type":"Services"
        }
    ],
    "sg:phone":"+1 604 323 0330",
    "sg:postcode":"V5X 4T1",
    "sg:province":"BC",
    "sg:tags":[
        "condominium"
    ],
    "wof:name":"Springs At Langara",
    "wof:placetype":"venue"
},
  "geometry": {"coordinates":[-123.111374,49.216206],"type":"Point"}
}