{
  "type": "Feature",
  "properties": {
    "addr:full":"Saint-Jerome QC J7Z 1X8",
    "addr:postcode":"j7z 1x8",
    "iso:country":"CA",
    "sg:city":"Saint-Jerome",
    "sg:classifiers":[
        {
            "category":"Social Services",
            "subcategory":"Child Care",
            "type":"Services"
        }
    ],
    "sg:phone":"+1 450 569 6424",
    "sg:postcode":"J7Z 1X8",
    "sg:province":"QC",
    "wof:name":"Rcpe Des Laurentides",
    "wof:placetype":"venue"
},
  "geometry": {"coordinates":[-74.001358,45.778244],"type":"Point"}
}