{
  "type": "Feature",
  "properties": {
    "addr:full":"1715 Rue Plessis Montreal QC H2L 2X8",
    "addr:housenumber":"1715",
    "addr:postcode":"h2l 2x8",
    "addr:street":"Rue Plessis",
    "iso:country":"CA",
    "sg:address":"1715 Rue Plessis",
    "sg:city":"Montreal",
    "sg:classifiers":[
        {
            "category":"Real Estate",
            "subcategory":"Architect",
            "type":"Services"
        }
    ],
    "sg:phone":"+1 514 525 6120",
    "sg:postcode":"H2L 2X8",
    "sg:province":"QC",
    "wof:name":"Jason Cushing Architecte",
    "wof:placetype":"venue"
},
  "geometry": {"coordinates":[-73.5577163696,45.5223045349],"type":"Point"}
}