{
  "type": "Feature",
  "properties": {
    "addr:full":"9185 Torbram Rd Brampton ON L6S 3L2",
    "addr:housenumber":"9185",
    "addr:postcode":"l6s 3l2",
    "addr:street":"Torbram Rd",
    "iso:country":"CA",
    "sg:address":"9185 Torbram Rd",
    "sg:city":"Brampton",
    "sg:classifiers":[
        {
            "category":"Food & Beverages",
            "subcategory":"Meat & Fish",
            "type":"Retail Goods"
        }
    ],
    "sg:phone":"+1 905 791 4486",
    "sg:postcode":"L6S 3L2",
    "sg:province":"ON",
    "sg:tags":[
        "frozen"
    ],
    "wof:name":"M & M Meat Shops",
    "wof:placetype":"venue"
},
  "geometry": {"coordinates":[-79.720268,43.744221],"type":"Point"}
}