{
  "type": "Feature",
  "properties": {
    "addr:full":"36 4th Ave Burns Lake BC V0J 1E0",
    "addr:housenumber":"36",
    "addr:postcode":"v0j 1e0",
    "addr:street":"4Th Ave Burns",
    "iso:country":"CA",
    "sg:address":"36 4th Ave",
    "sg:city":"Burns Lake",
    "sg:classifiers":[
        {
            "category":"Shopping",
            "subcategory":"Used Merchandise",
            "type":"Retail Goods"
        }
    ],
    "sg:phone":"+1 250 692 7666",
    "sg:postcode":"V0J 1E0",
    "sg:province":"BC",
    "sg:tags":[
        "clothing"
    ],
    "wof:name":"Thrift Shop",
    "wof:placetype":"venue"
},
  "geometry": {"coordinates":[-125.763931274,54.2308349609],"type":"Point"}
}