{
  "type": "Feature",
  "properties": {
    "addr:full":"3952 Quadra St Victoria BC V8X 1J6",
    "addr:housenumber":"3952",
    "addr:postcode":"v8x 1j6",
    "addr:street":"Quadra St",
    "iso:country":"CA",
    "sg:address":"3952 Quadra St",
    "sg:city":"Victoria",
    "sg:classifiers":[
        {
            "category":"Freight",
            "type":"Transportation"
        }
    ],
    "sg:phone":"+1 250 727 2311",
    "sg:postcode":"V8X 1J6",
    "sg:province":"BC",
    "sg:tags":[
        "commercial",
        "storage"
    ],
    "wof:name":"Old Winery Self Storage Ltd",
    "wof:placetype":"venue"
},
  "geometry": {"coordinates":[-123.36200714100001,48.448890686],"type":"Point"}
}