{
  "type": "Feature",
  "properties": {
    "addr:full":"19 Brackley Point Rd Charlottetown PE C1A 6Y1",
    "addr:housenumber":"19",
    "addr:postcode":"c1a 6y1",
    "addr:street":"Brackley Point Rd",
    "iso:country":"CA",
    "sg:address":"19 Brackley Point Rd",
    "sg:city":"Charlottetown",
    "sg:classifiers":[
        {
            "category":"Shopping",
            "subcategory":"Pharmacy",
            "type":"Retail Goods"
        }
    ],
    "sg:phone":"+1 902 628 8900",
    "sg:postcode":"C1A 6Y1",
    "sg:province":"PE",
    "wof:name":"Sherwood Drug Mart Ltd",
    "wof:placetype":"venue"
},
  "geometry": {"coordinates":[-63.1204795837,46.2597389221],"type":"Point"}
}