{
  "type": "Feature",
  "properties": {
    "addr:full":"Fenelon Falls ON K0M 1N0",
    "addr:postcode":"k0m 1n0",
    "iso:country":"CA",
    "sg:city":"Fenelon Falls",
    "sg:classifiers":[
        {
            "category":"Education",
            "subcategory":"School",
            "type":"Public Place"
        }
    ],
    "sg:phone":"+1 705 887 2001",
    "sg:postcode":"K0M 1N0",
    "sg:province":"ON",
    "wof:name":"Langton Public School",
    "wof:placetype":"venue"
},
  "geometry": {"coordinates":[-78.732338,44.52877],"type":"Point"}
}