{
  "type": "Feature",
  "properties": {
    "addr:full":"Brampton ON L6T 4H7",
    "addr:postcode":"l6t 4h7",
    "iso:country":"CA",
    "sg:city":"Brampton",
    "sg:classifiers":[
        {
            "category":"Shopping",
            "type":"Retail Goods"
        }
    ],
    "sg:phone":"+1 905 793 7227",
    "sg:postcode":"L6T 4H7",
    "sg:province":"ON",
    "sg:tags":[
        "candle"
    ],
    "wof:name":"Hope Candle Ltd",
    "wof:placetype":"venue"
},
  "geometry": {"coordinates":[-79.6799240112,43.7110404968],"type":"Point"}
}