{
  "type": "Feature",
  "properties": {
    "addr:full":"RR 12 STN P Thunder Bay ON P7B 5E3",
    "addr:housenumber":"12",
    "addr:postcode":"p7b 5e3",
    "addr:street":"Rr;P Thunder",
    "iso:country":"CA",
    "sg:address":"RR 12 STN P",
    "sg:city":"Thunder Bay",
    "sg:classifiers":[
        {
            "category":"Farming",
            "subcategory":"Livestock Farm",
            "type":"Manufacturing & Wholesale Goods"
        }
    ],
    "sg:phone":"+1 807 767 3067",
    "sg:postcode":"P7B 5E3",
    "sg:province":"ON",
    "sg:tags":[
        "breeder",
        "animal"
    ],
    "wof:name":"Brackenbrae Collies Reg'd",
    "wof:placetype":"venue"
},
  "geometry": {"coordinates":[-89.245476,48.381699],"type":"Point"}
}