{
  "type": "Feature",
  "properties": {
    "addr:full":"Sainte-Rose-Du-Nord QC G0V 1T0",
    "addr:postcode":"g0v 1t0",
    "iso:country":"CA",
    "sg:city":"Sainte-Rose-Du-Nord",
    "sg:classifiers":[
        {
            "category":"Restaurant",
            "type":"Food & Drink"
        }
    ],
    "sg:phone":"+1 418 675 1053",
    "sg:postcode":"G0V 1T0",
    "sg:province":"QC",
    "wof:name":"Cafe DE LA Poste Inc",
    "wof:placetype":"venue"
},
  "geometry": {"coordinates":[-70.62082700000001,48.415779],"type":"Point"}
}