{
  "type": "Feature",
  "properties": {
    "addr:full":"Seaforth ON N0K 1W0",
    "addr:postcode":"n0k 1w0",
    "iso:country":"CA",
    "sg:city":"Seaforth",
    "sg:classifiers":[
        {
            "category":"Professional",
            "subcategory":"Accounting & Tax Preparation",
            "type":"Services"
        }
    ],
    "sg:phone":"+1 519 527 0672",
    "sg:postcode":"N0K 1W0",
    "sg:province":"ON",
    "sg:tags":[
        "accountant"
    ],
    "wof:name":"Norris, John A M",
    "wof:placetype":"venue"
},
  "geometry": {"coordinates":[-81.3929672241,43.5536460876],"type":"Point"}
}