{
  "type": "Feature",
  "properties": {
    "addr:full":"29 Water St Summerside PE C1N 1A4",
    "addr:housenumber":"29",
    "addr:postcode":"c1n 1a4",
    "addr:street":"Water St",
    "iso:country":"CA",
    "sg:address":"29 Water St",
    "sg:city":"Summerside",
    "sg:classifiers":[
        {
            "category":"Retail",
            "subcategory":"Auto Repair",
            "type":"Services"
        }
    ],
    "sg:phone":"+1 902 436 2192",
    "sg:postcode":"C1N 1A4",
    "sg:province":"PE",
    "sg:tags":[
        "machine",
        "glass",
        "shop",
        "automobile"
    ],
    "wof:name":"Apple Auto Glass",
    "wof:placetype":"venue"
},
  "geometry": {"coordinates":[-63.7761802673,46.3917236328],"type":"Point"}
}