{
  "type": "Feature",
  "properties": {
    "iso:country":"CA",
    "sg:address":"4274 11th Ave",
    "sg:city":"Hazelton",
    "sg:classifiers":[
        {
            "category":"Government",
            "subcategory":"Office",
            "type":"Public Place"
        }
    ],
    "sg:phone":"+1 250 842 4137",
    "sg:postcode":"V0J 1Y0",
    "sg:province":"BC",
    "wof:name":"BC Good Feeling Gathering Pl",
    "wof:placetype":"venue"
},
  "geometry": {"coordinates":[-127.643867493,55.2642593384],"type":"Point"}
}