{
  "type": "Feature",
  "properties": {
    "addr:full":"8445 Main St Vancouver BC V5X 3M3",
    "addr:housenumber":"8445",
    "addr:postcode":"v5x 3m3",
    "addr:street":"Main St",
    "iso:country":"CA",
    "sg:address":"8445 Main St",
    "sg:city":"Vancouver",
    "sg:classifiers":[
        {
            "category":"Shopping",
            "subcategory":"Computers & Home Electronics",
            "type":"Retail Goods"
        }
    ],
    "sg:phone":"+1 604 325 8880",
    "sg:postcode":"V5X 3M3",
    "sg:province":"BC",
    "sg:tags":[
        "parts",
        "supply"
    ],
    "wof:name":"Lin Haw Intl CO Ltd",
    "wof:placetype":"venue"
},
  "geometry": {"coordinates":[-123.102546692,49.2084350586],"type":"Point"}
}