{
  "type": "Feature",
  "properties": {
    "iso:country":"CA",
    "sg:address":"551 Richmond St",
    "sg:city":"London",
    "sg:classifiers":[
        {
            "category":"Home & Garden",
            "subcategory":"Home Furnishings",
            "type":"Retail Goods"
        }
    ],
    "sg:phone":"+1 519 850 5477",
    "sg:postcode":"N6A 3E9",
    "sg:province":"ON",
    "sg:tags":[
        "kitchen",
        "accessory"
    ],
    "wof:name":"Kiss the Cook",
    "wof:placetype":"venue"
},
  "geometry": {"coordinates":[-81.250755,42.988579],"type":"Point"}
}