{
  "type": "Feature",
  "properties": {
    "addr:full":"4425 Legion Ave Terrace BC V8G 1N7",
    "addr:housenumber":"4425",
    "addr:postcode":"v8g 1n7",
    "addr:street":"Legion Ave",
    "iso:country":"CA",
    "sg:address":"4425 Legion Ave",
    "sg:city":"Terrace",
    "sg:classifiers":[
        {
            "category":"Organizations",
            "subcategory":"Community Association",
            "type":"Services"
        }
    ],
    "sg:phone":"+1 250 635 5825",
    "sg:postcode":"V8G 1N7",
    "sg:province":"BC",
    "sg:tags":[
        "fraternal"
    ],
    "wof:name":"Royal Canadian Legion Terrace",
    "wof:placetype":"venue"
},
  "geometry": {"coordinates":[-128.57679748499999,54.5156211853],"type":"Point"}
}