{
  "type": "Feature",
  "properties": {
    "addr:full":"1575 Drew Rd Mississauga ON L5S 1S5",
    "addr:housenumber":"1575",
    "addr:postcode":"l5s 1s5",
    "addr:street":"Drew Rd",
    "iso:country":"CA",
    "sg:address":"1575 Drew Rd",
    "sg:city":"Mississauga",
    "sg:classifiers":[
        {
            "category":"Wholesale",
            "subcategory":"Chemicals & Plastics",
            "type":"Manufacturing & Wholesale Goods"
        }
    ],
    "sg:phone":"+1 905 677 2324",
    "sg:postcode":"L5S 1S5",
    "sg:province":"ON",
    "wof:name":"Silgan Plastics Canada",
    "wof:placetype":"venue"
},
  "geometry": {"coordinates":[-79.6805725098,43.6824226379],"type":"Point"}
}