{
  "type": "Feature",
  "properties": {
    "addr:full":"51 Sackville Dr Lower Sackville NS B4C 2R2",
    "addr:housenumber":"51",
    "addr:postcode":"b4c 2r2",
    "addr:street":"Sackville Dr",
    "iso:country":"CA",
    "sg:address":"51 Sackville Dr",
    "sg:city":"Lower Sackville",
    "sg:classifiers":[
        {
            "category":"Freight",
            "type":"Transportation"
        }
    ],
    "sg:phone":"+1 902 865 1601",
    "sg:postcode":"B4C 2R2",
    "sg:province":"NS",
    "sg:tags":[
        "courier"
    ],
    "wof:name":"Cobequid Petro-Canada",
    "wof:placetype":"venue"
},
  "geometry": {"coordinates":[-63.664738,44.752842],"type":"Point"}
}