{
  "type": "Feature",
  "properties": {
    "addr:full":"9837 Third St Sidney BC V8L 3A6",
    "addr:housenumber":"9837",
    "addr:postcode":"v8l 3a6",
    "addr:street":"Third St",
    "iso:country":"CA",
    "sg:address":"9837 Third St",
    "sg:city":"Sidney",
    "sg:classifiers":[
        {
            "category":"Government",
            "subcategory":"Fire Station",
            "type":"Public Place"
        }
    ],
    "sg:phone":"+1 250 656 2121",
    "sg:postcode":"V8L 3A6",
    "sg:province":"BC",
    "sg:tags":[
        "department"
    ],
    "wof:name":"Sidney Fire Chief Ofc",
    "wof:placetype":"venue"
},
  "geometry": {"coordinates":[-123.397621155,48.6498146057],"type":"Point"}
}