{
  "type": "Feature",
  "properties": {
    "addr:full":"198 Algoma St S Thunder Bay ON P7B 3B9",
    "addr:housenumber":"198",
    "addr:postcode":"p7b 3b9",
    "addr:street":"Algoma St S",
    "iso:country":"CA",
    "sg:address":"198 Algoma St S",
    "sg:city":"Thunder Bay",
    "sg:classifiers":[
        {
            "category":"Shopping",
            "subcategory":"Books",
            "type":"Retail Goods"
        }
    ],
    "sg:phone":"+1 807 345 9841",
    "sg:postcode":"P7B 3B9",
    "sg:province":"ON",
    "sg:tags":[
        "dealer"
    ],
    "wof:name":"Folino's Superette",
    "wof:placetype":"venue"
},
  "geometry": {"coordinates":[-89.230667,48.430855],"type":"Point"}
}