{
  "type": "Feature",
  "properties": {
    "addr:full":"1671 Renfrew St Vancouver BC V5K 4C9",
    "addr:housenumber":"1671",
    "addr:postcode":"v5k 4c9",
    "addr:street":"Renfrew St",
    "iso:country":"CA",
    "sg:address":"1671 Renfrew St",
    "sg:city":"Vancouver",
    "sg:classifiers":[
        {
            "category":"Retail",
            "subcategory":"Laundry & Dry Cleaning",
            "type":"Services"
        }
    ],
    "sg:phone":"+1 604 254 9800",
    "sg:postcode":"V5K 4C9",
    "sg:province":"BC",
    "sg:tags":[
        "cleaners"
    ],
    "wof:name":"Van City 1 Hour Dry Cleaners",
    "wof:placetype":"venue"
},
  "geometry": {"coordinates":[-123.04440307599999,49.2698631287],"type":"Point"}
}