{
  "type": "Feature",
  "properties": {
    "addr:full":"139 50E Rue E Charlesbourg QC G1H 2L2",
    "addr:housenumber":"139",
    "addr:postcode":"g1h 2l2",
    "addr:street":"50E Rue E",
    "iso:country":"CA",
    "sg:address":"139 50E Rue E",
    "sg:city":"Charlesbourg",
    "sg:classifiers":[
        {
            "category":"Real Estate",
            "subcategory":"Real Estate Agent",
            "type":"Services"
        }
    ],
    "sg:phone":"+1 418 623 5531",
    "sg:postcode":"G1H 2L2",
    "sg:province":"QC",
    "sg:tags":[
        "authorities",
        "housing"
    ],
    "wof:name":"Immeuble Paul E Richard Inc",
    "wof:placetype":"venue"
},
  "geometry": {"coordinates":[-71.2514038086,46.8456192017],"type":"Point"}
}