{
  "type": "Feature",
  "properties": {
    "addr:full":"256 Josephine St Wingham ON N0G 2W0",
    "addr:housenumber":"256",
    "addr:postcode":"n0g 2w0",
    "addr:street":"Josephine St",
    "iso:country":"CA",
    "sg:address":"256 Josephine St",
    "sg:city":"Wingham",
    "sg:classifiers":[
        {
            "category":"Shopping",
            "subcategory":"Shoes",
            "type":"Retail Goods"
        }
    ],
    "sg:phone":"+1 519 357 1840",
    "sg:postcode":"N0G 2W0",
    "sg:province":"ON",
    "wof:name":"2 Step Shoes",
    "wof:placetype":"venue"
},
  "geometry": {"coordinates":[-81.31270599370001,43.8868637085],"type":"Point"}
}