{
  "type": "Feature",
  "properties": {
    "addr:full":"Shippagan NB E8S 1N2",
    "addr:postcode":"e8s 1n2",
    "iso:country":"CA",
    "sg:city":"Shippagan",
    "sg:classifiers":[
        {
            "category":"Shopping",
            "subcategory":"Stationery & Office Supplies",
            "type":"Retail Goods"
        }
    ],
    "sg:phone":"+1 506 336 9009",
    "sg:postcode":"E8S 1N2",
    "sg:province":"NB",
    "sg:tags":[
        "stationer"
    ],
    "wof:name":"Buro",
    "wof:placetype":"venue"
},
  "geometry": {"coordinates":[-64.709442,47.743931],"type":"Point"}
}