{
  "type": "Feature",
  "properties": {
    "addr:full":"5294 Main St Orono ON L0B 1M0",
    "addr:housenumber":"5294",
    "addr:postcode":"l0b 1m0",
    "addr:street":"Main St",
    "iso:country":"CA",
    "sg:address":"5294 Main St",
    "sg:city":"Orono",
    "sg:classifiers":[
        {
            "category":"Shopping",
            "subcategory":"Discount & Variety Stores",
            "type":"Retail Goods"
        }
    ],
    "sg:phone":"+1 905 983 9291",
    "sg:postcode":"L0B 1M0",
    "sg:province":"ON",
    "wof:name":"Sunny's Restaurant Inc",
    "wof:placetype":"venue"
},
  "geometry": {"coordinates":[-78.6170425415,43.9760818481],"type":"Point"}
}