{
  "type": "Feature",
  "properties": {
    "addr:full":"2709 Rue Principale Sainte-Justine-DE-Newton QC J0P 1T0",
    "addr:housenumber":"2709",
    "addr:postcode":"j0p 1t0",
    "addr:street":"Rue Principale",
    "iso:country":"CA",
    "sg:address":"2709 Rue Principale",
    "sg:city":"Sainte-Justine-DE-Newton",
    "sg:classifiers":[
        {
            "category":"Organizations",
            "subcategory":"Religious Organization",
            "type":"Services"
        }
    ],
    "sg:phone":"+1 450 764 3393",
    "sg:postcode":"J0P 1T0",
    "sg:province":"QC",
    "sg:tags":[
        "church"
    ],
    "wof:name":"Eglise Ste-Justine",
    "wof:placetype":"venue"
},
  "geometry": {"coordinates":[-74.40710449220001,45.3739433289],"type":"Point"}
}