{
  "type": "Feature",
  "properties": {
    "iso:country":"CA",
    "sg:address":"1119 Fennell Ave E",
    "sg:city":"Hamilton",
    "sg:classifiers":[
        {
            "category":"Restaurant",
            "type":"Food & Drink"
        }
    ],
    "sg:phone":"+1 905 310 1010",
    "sg:postcode":"L8T 1S2",
    "sg:province":"ON",
    "sg:tags":[
        "pizza"
    ],
    "wof:name":"Pizza Hut",
    "wof:placetype":"venue"
},
  "geometry": {"coordinates":[-79.829216,43.225639],"type":"Point"}
}