{
  "type": "Feature",
  "properties": {
    "addr:full":"655 Rue Principale Saint-Faustin-Lac-Carre QC J0T 1J3",
    "addr:housenumber":"655",
    "addr:postcode":"j0t 1j3",
    "addr:street":"Rue Principale",
    "iso:country":"CA",
    "sg:address":"655 Rue Principale",
    "sg:city":"Saint-Faustin-Lac-Carre",
    "sg:classifiers":[
        {
            "category":"Food & Beverages",
            "subcategory":"Groceries & Convenience Stores",
            "type":"Retail Goods"
        }
    ],
    "sg:phone":"+1 819 688 2993",
    "sg:postcode":"J0T 1J3",
    "sg:province":"QC",
    "wof:name":"Depanneur Jm Delisle",
    "wof:placetype":"venue"
},
  "geometry": {"coordinates":[-74.4786,46.116081],"type":"Point"}
}