{
  "type": "Feature",
  "properties": {
    "addr:full":"90 Queen St Marlbank ON K0K 2L0",
    "addr:housenumber":"90",
    "addr:postcode":"k0k 2l0",
    "addr:street":"Queen St",
    "iso:country":"CA",
    "sg:address":"90 Queen St",
    "sg:city":"Marlbank",
    "sg:classifiers":[
        {
            "category":"Organizations",
            "subcategory":"Religious Organization",
            "type":"Services"
        }
    ],
    "sg:phone":"+1 613 478 6055",
    "sg:postcode":"K0K 2L0",
    "sg:province":"ON",
    "sg:tags":[
        "church"
    ],
    "wof:name":"Marlbank Pentecostal Church",
    "wof:placetype":"venue"
},
  "geometry": {"coordinates":[-77.09343,44.43536],"type":"Point"}
}