{
  "type": "Feature",
  "properties": {
    "addr:full":"1 King St York ON M9N 1K8",
    "addr:housenumber":"1",
    "addr:postcode":"m9n 1k8",
    "addr:street":"King St",
    "iso:country":"CA",
    "sg:address":"1 King St",
    "sg:city":"York",
    "sg:classifiers":[
        {
            "category":"Organizations",
            "subcategory":"Religious Organization",
            "type":"Services"
        }
    ],
    "sg:phone":"+1 416 241 7544",
    "sg:postcode":"M9N 1K8",
    "sg:province":"ON",
    "sg:tags":[
        "church"
    ],
    "wof:name":"Central United Church",
    "wof:placetype":"venue"
},
  "geometry": {"coordinates":[-79.52040100000001,43.701481],"type":"Point"}
}