{
  "type": "Feature",
  "properties": {
    "addr:full":"1524 Byland Rd Kelowna BC V1Z 1A8",
    "addr:housenumber":"1524",
    "addr:postcode":"v1z 1a8",
    "addr:street":"Byland Rd",
    "iso:country":"CA",
    "sg:address":"1524 Byland Rd",
    "sg:city":"Kelowna",
    "sg:classifiers":[
        {
            "category":"Manufacturing",
            "subcategory":"Buildings",
            "type":"Manufacturing & Wholesale Goods"
        }
    ],
    "sg:phone":"+1 250 769 5177",
    "sg:postcode":"V1Z 1A8",
    "sg:province":"BC",
    "sg:tags":[
        "prefab"
    ],
    "wof:name":"Big Valley Custom Homes",
    "wof:placetype":"venue"
},
  "geometry": {"coordinates":[-119.580658,49.863041],"type":"Point"}
}