{
  "type": "Feature",
  "properties": {
    "addr:full":"1281 Davenport Rd Toronto ON M6H 2H3",
    "addr:housenumber":"1281",
    "addr:postcode":"m6h 2h3",
    "addr:street":"Davenport Rd",
    "iso:country":"CA",
    "sg:address":"1281 Davenport Rd",
    "sg:city":"Toronto",
    "sg:classifiers":[
        {
            "category":"Shopping",
            "subcategory":"Discount & Variety Stores",
            "type":"Retail Goods"
        }
    ],
    "sg:phone":"+1 416 535 7469",
    "sg:postcode":"M6H 2H3",
    "sg:province":"ON",
    "wof:name":"Salem Smoke Shop",
    "wof:placetype":"venue"
},
  "geometry": {"coordinates":[-79.4372558594,43.6738548279],"type":"Point"}
}