{
  "type": "Feature",
  "properties": {
    "addr:full":"601 Newpark Blvd Newmarket ON L3X 2S2",
    "addr:housenumber":"601",
    "addr:postcode":"l3x 2s2",
    "addr:street":"Newpark Blvd",
    "iso:country":"CA",
    "sg:address":"601 Newpark Blvd",
    "sg:city":"Newmarket",
    "sg:classifiers":[
        {
            "category":"Education",
            "subcategory":"School",
            "type":"Public Place"
        }
    ],
    "sg:phone":"+1 905 898 6257",
    "sg:postcode":"L3X 2S2",
    "sg:province":"ON",
    "wof:name":"Country Garden Montessori Inc",
    "wof:placetype":"venue"
},
  "geometry": {"coordinates":[-79.44658660890001,44.037979126],"type":"Point"}
}