{
  "type": "Feature",
  "properties": {
    "addr:full":"150 John St Toronto ON M5V 3E3",
    "addr:housenumber":"150",
    "addr:postcode":"m5v 3e3",
    "addr:street":"John St",
    "iso:country":"CA",
    "sg:address":"150 John St",
    "sg:city":"Toronto",
    "sg:classifiers":[
        {
            "category":"Government",
            "subcategory":"Office",
            "type":"Public Place"
        }
    ],
    "sg:phone":"+1 416 973 3012",
    "sg:postcode":"M5V 3E3",
    "sg:province":"ON",
    "wof:name":"Canada National Film Board",
    "wof:placetype":"venue"
},
  "geometry": {"coordinates":[-79.39097599999999,43.6492],"type":"Point"}
}