{
  "type": "Feature",
  "properties": {
    "addr:full":"3315 Fairview St Burlington ON L7N 3N9",
    "addr:housenumber":"3315",
    "addr:postcode":"l7n 3n9",
    "addr:street":"Fairview St",
    "iso:country":"CA",
    "sg:address":"3315 Fairview St",
    "sg:city":"Burlington",
    "sg:classifiers":[
        {
            "category":"Restaurant",
            "type":"Food & Drink"
        }
    ],
    "sg:phone":"+1 905 631 6215",
    "sg:postcode":"L7N 3N9",
    "sg:province":"ON",
    "wof:name":"Licks Homeburger & Ice Cream",
    "wof:placetype":"venue"
},
  "geometry": {"coordinates":[-79.78662109379999,43.353767395],"type":"Point"}
}