{
  "type": "Feature",
  "properties": {
    "iso:country":"CA",
    "sg:address":"90 Saunders Rd",
    "sg:city":"Barrie",
    "sg:classifiers":[
        {
            "category":"Wholesale",
            "subcategory":"Auto Parts",
            "type":"Manufacturing & Wholesale Goods"
        }
    ],
    "sg:phone":"+1 705 726 2333",
    "sg:postcode":"L4N 9A8",
    "sg:province":"ON",
    "sg:tags":[
        "body",
        "automobile",
        "shop"
    ],
    "wof:name":"Akn Automotive Ltd",
    "wof:placetype":"venue"
},
  "geometry": {"coordinates":[-79.68087,44.329548],"type":"Point"}
}