{
  "type": "Feature",
  "properties": {
    "addr:full":"3003 Rue Picard Saint-Hyacinthe QC J2S 1H2",
    "addr:housenumber":"3003",
    "addr:postcode":"j2s 1h2",
    "addr:street":"Rue Picard",
    "iso:country":"CA",
    "sg:address":"3003 Rue Picard",
    "sg:city":"Saint-Hyacinthe",
    "sg:classifiers":[
        {
            "category":"Retail",
            "subcategory":"Car Wash",
            "type":"Services"
        }
    ],
    "sg:phone":"+1 450 774 0456",
    "sg:postcode":"J2S 1H2",
    "sg:province":"QC",
    "sg:tags":[
        "polishing",
        "washing"
    ],
    "wof:name":"Cirage D'Auto Bernard Inc",
    "wof:placetype":"venue"
},
  "geometry": {"coordinates":[-72.9730300903,45.6382255554],"type":"Point"}
}