{
  "type": "Feature",
  "properties": {
    "addr:full":"900 Maple Ave Burlington ON L7S 2J8",
    "addr:housenumber":"900",
    "addr:postcode":"l7s 2j8",
    "addr:street":"Maple Ave",
    "iso:country":"CA",
    "sg:address":"900 Maple Ave",
    "sg:city":"Burlington",
    "sg:classifiers":[
        {
            "category":"Retail",
            "subcategory":"Photofinishing",
            "type":"Services"
        }
    ],
    "sg:phone":"+1 905 333 5772",
    "sg:postcode":"L7S 2J8",
    "sg:province":"ON",
    "sg:tags":[
        "photo",
        "photographic",
        "supply"
    ],
    "wof:name":"Black's Photography",
    "wof:placetype":"venue"
},
  "geometry": {"coordinates":[-79.8197250366,43.3278236389],"type":"Point"}
}