{
  "type": "Feature",
  "properties": {
    "addr:full":"128 Main St S Melita MB R0M 1L0",
    "addr:housenumber":"128",
    "addr:postcode":"r0m 1l0",
    "addr:street":"Main St S Melita",
    "iso:country":"CA",
    "sg:address":"128 Main St S",
    "sg:city":"Melita",
    "sg:classifiers":[
        {
            "category":"Manufacturing",
            "subcategory":"Printing",
            "type":"Manufacturing & Wholesale Goods"
        }
    ],
    "sg:phone":"+1 204 522 3491",
    "sg:postcode":"R0M 1L0",
    "sg:province":"MB",
    "sg:tags":[
        "newspaper"
    ],
    "wof:name":"Melita New Era",
    "wof:placetype":"venue"
},
  "geometry": {"coordinates":[-100.99102000000001,49.270107],"type":"Point"}
}