{
  "type": "Feature",
  "properties": {
    "iso:country":"CA",
    "sg:city":"Vineland",
    "sg:classifiers":[
        {
            "category":"Retail",
            "subcategory":"Auto Repair",
            "type":"Services"
        }
    ],
    "sg:phone":"+1 905 562 8338",
    "sg:postcode":"L0R 2C0",
    "sg:province":"ON",
    "sg:tags":[
        "repairing",
        "automobile"
    ],
    "wof:name":"Mark's Automotive",
    "wof:placetype":"venue"
},
  "geometry": {"coordinates":[-79.39172363279999,43.1508178711],"type":"Point"}
}