{
  "type": "Feature",
  "properties": {
    "addr:full":"Daisy Lane #3 Clavet SK S0K 0Y0",
    "addr:postcode":"s0k 0y0",
    "addr:street":"Daisy Lane # 3 Clavet",
    "iso:country":"CA",
    "sg:address":"Daisy Lane #3",
    "sg:city":"Clavet",
    "sg:classifiers":[
        {
            "category":"Building & Trades",
            "subcategory":"Construction",
            "type":"Services"
        }
    ],
    "sg:phone":"+1 306 242 9998",
    "sg:postcode":"S0K 0Y0",
    "sg:province":"SK",
    "sg:tags":[
        "insulation",
        "heat",
        "contractor"
    ],
    "wof:name":"Industrial Insulation Svc Ltd",
    "wof:placetype":"venue"
},
  "geometry": {"coordinates":[-106.374123,51.997356],"type":"Point"}
}