{
  "type": "Feature",
  "properties": {
    "iso:country":"CA",
    "sg:address":"360 21st St E",
    "sg:city":"North Vancouver",
    "sg:classifiers":[
        {
            "category":"Professional",
            "subcategory":"Management & Consulting",
            "type":"Services"
        }
    ],
    "sg:phone":"+1 604 987 1859",
    "sg:postcode":"V7L 3B8",
    "sg:province":"BC",
    "sg:tags":[
        "consultant",
        "energy",
        "conservation"
    ],
    "wof:name":"Airflow Energy Ltd",
    "wof:placetype":"venue"
},
  "geometry": {"coordinates":[-123.064109802,49.3283576965],"type":"Point"}
}