{
  "type": "Feature",
  "properties": {
    "addr:full":"1185 Boul Moody # 250 Terrebonne QC J6W 3Z5",
    "addr:housenumber":"1185",
    "addr:postcode":"j6w 3z5",
    "addr:street":"Boul Moody # 250",
    "iso:country":"CA",
    "sg:address":"1185 Boul Moody # 250",
    "sg:city":"Terrebonne",
    "sg:classifiers":[
        {
            "category":"Restaurant",
            "type":"Food & Drink"
        }
    ],
    "sg:phone":"+1 450 471 2660",
    "sg:postcode":"J6W 3Z5",
    "sg:province":"QC",
    "wof:name":"Chateau Royal Inc",
    "wof:placetype":"venue"
},
  "geometry": {"coordinates":[-73.64804100000001,45.702183],"type":"Point"}
}