{
  "type": "Feature",
  "properties": {
    "addr:full":"3284 Boul Saint-Martin O Laval QC H7T 1A1",
    "addr:housenumber":"3284",
    "addr:postcode":"h7t 1a1",
    "addr:street":"Boul Saint-Martin O",
    "iso:country":"CA",
    "sg:address":"3284 Boul Saint-Martin O",
    "sg:city":"Laval",
    "sg:classifiers":[
        {
            "category":"Personal",
            "subcategory":"Beauty Salon",
            "type":"Services"
        }
    ],
    "sg:phone":"+1 450 682 4534",
    "sg:postcode":"H7T 1A1",
    "sg:province":"QC",
    "sg:tags":[
        "manicuring"
    ],
    "wof:name":"Ongles Acryliques",
    "wof:placetype":"venue"
},
  "geometry": {"coordinates":[-73.748268,45.556648],"type":"Point"}
}