{
  "type": "Feature",
  "properties": {
    "iso:country":"CA",
    "sg:address":"17203 103 Ave NW",
    "sg:city":"Edmonton",
    "sg:classifiers":[
        {
            "category":"Professional",
            "subcategory":"Engineering",
            "type":"Services"
        }
    ],
    "sg:phone":"+1 780 488 6800",
    "sg:postcode":"T5S 1J4",
    "sg:province":"AB",
    "sg:tags":[
        "engineer"
    ],
    "wof:name":"Earth Tech Canada Inc",
    "wof:placetype":"venue"
},
  "geometry": {"coordinates":[-113.618156,53.545151],"type":"Point"}
}