{
  "type": "Feature",
  "properties": {
    "addr:full":"10768 Av Moisan Montreal-Nord QC H1G 4N4",
    "addr:postcode":"h1g 4n4",
    "addr:street":"Av Moisan",
    "iso:country":"CA",
    "sg:address":"10768 Av Moisan",
    "sg:city":"Montreal-Nord",
    "sg:classifiers":[
        {
            "category":"Retail",
            "subcategory":"Auto Repair",
            "type":"Services"
        }
    ],
    "sg:phone":"+1 514 325 5057",
    "sg:postcode":"H1G 4N4",
    "sg:province":"QC",
    "sg:tags":[
        "body",
        "automobile",
        "painting"
    ],
    "wof:name":"Carrosserie Kenny Morel",
    "wof:placetype":"venue"
},
  "geometry": {"coordinates":[-73.616013,45.600822],"type":"Point"}
}