{
  "type": "Feature",
  "properties": {
    "addr:full":"92 Terrace Hill St Brantford ON N3R 1G3",
    "addr:housenumber":"92",
    "addr:postcode":"n3r 1g3",
    "addr:street":"Terrace;St",
    "iso:country":"CA",
    "sg:address":"92 Terrace Hill St",
    "sg:city":"Brantford",
    "sg:classifiers":[
        {
            "category":"Organizations",
            "subcategory":"Religious Organization",
            "type":"Services"
        }
    ],
    "sg:phone":"+1 519 752 9290",
    "sg:postcode":"N3R 1G3",
    "sg:province":"ON",
    "sg:tags":[
        "church"
    ],
    "wof:name":"Ukrainian Catholic Church",
    "wof:placetype":"venue"
},
  "geometry": {"coordinates":[-80.268806,43.15004],"type":"Point"}
}