{
  "type": "Feature",
  "properties": {
    "addr:full":"Victoria BC V8W 1J6",
    "addr:postcode":"v8w 1j6",
    "iso:country":"CA",
    "sg:city":"Victoria",
    "sg:classifiers":[
        {
            "category":"Professional",
            "subcategory":"Lawyer & Legal Services",
            "type":"Services"
        }
    ],
    "sg:phone":"+1 250 384 1804",
    "sg:postcode":"V8W 1J6",
    "sg:province":"BC",
    "sg:tags":[
        "attorney"
    ],
    "wof:name":"Loney, Susan J",
    "wof:placetype":"venue"
},
  "geometry": {"coordinates":[-123.36713399999999,48.425823],"type":"Point"}
}