{
  "type": "Feature",
  "properties": {
    "addr:full":"PO Box 375 Wembley AB T0H 3S0",
    "addr:housenumber":"po;375",
    "addr:postcode":"t0h 3s0",
    "addr:street":"Box",
    "iso:country":"CA",
    "sg:address":"PO Box 375",
    "sg:city":"Wembley",
    "sg:classifiers":[
        {
            "category":"Manufacturing",
            "subcategory":"Lumber",
            "type":"Manufacturing & Wholesale Goods"
        }
    ],
    "sg:phone":"+1 780 766 3255",
    "sg:postcode":"T0H 3S0",
    "sg:province":"AB",
    "sg:tags":[
        "sawmill"
    ],
    "wof:name":"J C Ruxton Ventures Ltd",
    "wof:placetype":"venue"
},
  "geometry": {"coordinates":[-119.139198303,55.1647949219],"type":"Point"}
}