{
  "type": "Feature",
  "properties": {
    "addr:full":"RR 3 STN Main Essex ON N8M 2X7",
    "addr:postcode":"n8m 2x7",
    "addr:street":"Rr 3 Stn Main",
    "iso:country":"CA",
    "sg:address":"RR 3 STN Main",
    "sg:city":"Essex",
    "sg:classifiers":[
        {
            "category":"Organizations",
            "subcategory":"Religious Organization",
            "type":"Services"
        }
    ],
    "sg:phone":"+1 519 727 5309",
    "sg:postcode":"N8M 2X7",
    "sg:province":"ON",
    "sg:tags":[
        "church"
    ],
    "wof:name":"Puce Baptist Church",
    "wof:placetype":"venue"
},
  "geometry": {"coordinates":[-82.8196716309,42.1728248596],"type":"Point"}
}