{
  "type": "Feature",
  "properties": {
    "iso:country":"CA",
    "sg:address":"46 St Clair Ave E",
    "sg:city":"Toronto",
    "sg:classifiers":[
        {
            "category":"Shopping",
            "subcategory":"Computers & Home Electronics",
            "type":"Retail Goods"
        }
    ],
    "sg:phone":"+1 416 967 7894",
    "sg:postcode":"M4T 1M9",
    "sg:province":"ON",
    "sg:tags":[
        "equipment",
        "dealer"
    ],
    "wof:name":"Soft Comp",
    "wof:placetype":"venue"
},
  "geometry": {"coordinates":[-79.3921051025,43.6886291504],"type":"Point"}
}