{
  "type": "Feature",
  "properties": {
    "addr:full":"Laval QC H7M 3Y2",
    "addr:postcode":"h7m 3y2",
    "iso:country":"CA",
    "sg:city":"Laval",
    "sg:classifiers":[
        {
            "category":"Professional",
            "subcategory":"Lawyer & Legal Services",
            "type":"Services"
        }
    ],
    "sg:phone":"+1 450 901 0151",
    "sg:postcode":"H7M 3Y2",
    "sg:province":"QC",
    "sg:tags":[
        "attorney"
    ],
    "wof:name":"Turcotte Nolet",
    "wof:placetype":"venue"
},
  "geometry": {"coordinates":[-73.71217346189999,45.5765304565],"type":"Point"}
}