{
  "type": "Feature",
  "properties": {
    "addr:full":"491 9th St E Cornwall ON K6H 2V6",
    "addr:housenumber":"491",
    "addr:postcode":"k6h 2v6",
    "addr:street":"9Th St E",
    "iso:country":"CA",
    "sg:address":"491 9th St E",
    "sg:city":"Cornwall",
    "sg:classifiers":[
        {
            "category":"Home & Garden",
            "subcategory":"Carpets & Floor Coverings",
            "type":"Retail Goods"
        }
    ],
    "sg:phone":"+1 613 932 8462",
    "sg:postcode":"K6H 2V6",
    "sg:province":"ON",
    "sg:tags":[
        "material",
        "rug"
    ],
    "wof:name":"Mainville Flooring Ltd",
    "wof:placetype":"venue"
},
  "geometry": {"coordinates":[-74.72453308110001,45.0317306519],"type":"Point"}
}