{
  "type": "Feature",
  "properties": {
    "addr:full":"10 Kelly Crt Charlottetown PE C1A 9P8",
    "addr:housenumber":"10",
    "addr:postcode":"c1a 9p8",
    "addr:street":"Kelly Crt",
    "iso:country":"CA",
    "sg:address":"10 Kelly Crt",
    "sg:city":"Charlottetown",
    "sg:classifiers":[
        {
            "category":"Wholesale",
            "subcategory":"Electrical",
            "type":"Manufacturing & Wholesale Goods"
        }
    ],
    "sg:phone":"+1 902 892 5463",
    "sg:postcode":"C1A 9P8",
    "sg:province":"PE",
    "sg:tags":[
        "control",
        "security",
        "system"
    ],
    "wof:name":"Health-Line",
    "wof:placetype":"venue"
},
  "geometry": {"coordinates":[-63.151398,46.254917],"type":"Point"}
}