{
  "type": "Feature",
  "properties": {
    "addr:full":"Fitzgerald Ln Bonavista NL A0C 1B0",
    "addr:postcode":"a0c 1b0",
    "addr:street":"Fitzgerald Ln",
    "iso:country":"CA",
    "sg:address":"Fitzgerald Ln",
    "sg:city":"Bonavista",
    "sg:classifiers":[
        {
            "category":"Organizations",
            "subcategory":"Religious Organization",
            "type":"Services"
        }
    ],
    "sg:phone":"+1 709 468 7220",
    "sg:postcode":"A0C 1B0",
    "sg:province":"NL",
    "sg:tags":[
        "church"
    ],
    "wof:name":"Grace Pentecostal Church",
    "wof:placetype":"venue"
},
  "geometry": {"coordinates":[-53.099129,48.656128],"type":"Point"}
}