{
  "type": "Feature",
  "properties": {
    "addr:full":"Brigus NL A0A 1K0",
    "addr:postcode":"a0a 1k0",
    "iso:country":"CA",
    "sg:city":"Brigus",
    "sg:classifiers":[
        {
            "category":"Health Services",
            "subcategory":"Doctor",
            "type":"Services"
        }
    ],
    "sg:phone":"+1 709 528 4601",
    "sg:postcode":"A0A 1K0",
    "sg:province":"NL",
    "sg:tags":[
        "physician",
        "surgeon"
    ],
    "wof:name":"Crosbie, D R MD",
    "wof:placetype":"venue"
},
  "geometry": {"coordinates":[-53.232132,47.530632],"type":"Point"}
}