{
  "type": "Feature",
  "properties": {
    "addr:full":"1591 Bayview Ave East York ON M4G 3B5",
    "addr:housenumber":"1591",
    "addr:postcode":"m4g 3b5",
    "addr:street":"Bayview Ave",
    "iso:country":"CA",
    "sg:address":"1591 Bayview Ave",
    "sg:city":"East York",
    "sg:classifiers":[
        {
            "category":"Shopping",
            "subcategory":"Clothing, Apparel, & Fashions",
            "type":"Retail Goods"
        }
    ],
    "sg:phone":"+1 416 483 5400",
    "sg:postcode":"M4G 3B5",
    "sg:province":"ON",
    "wof:name":"Trend Shoppe",
    "wof:placetype":"venue"
},
  "geometry": {"coordinates":[-79.3750839233,43.7060623169],"type":"Point"}
}