{
  "type": "Feature",
  "properties": {
    "addr:full":"322 2 Ave S Lethbridge AB T1J 0C1",
    "addr:housenumber":"322",
    "addr:postcode":"t1j 0c1",
    "addr:street":"2 Ave S",
    "iso:country":"CA",
    "sg:address":"322 2 Ave S",
    "sg:city":"Lethbridge",
    "sg:classifiers":[
        {
            "category":"Food & Beverages",
            "subcategory":"Specialty",
            "type":"Retail Goods"
        }
    ],
    "sg:phone":"+1 403 327 5337",
    "sg:postcode":"T1J 0C1",
    "sg:province":"AB",
    "sg:tags":[
        "oriental"
    ],
    "wof:name":"R Nakagama CO",
    "wof:placetype":"venue"
},
  "geometry": {"coordinates":[-112.84310913100001,49.6965637207],"type":"Point"}
}