{
  "type": "Feature",
  "properties": {
    "addr:full":"3630 Rhodes Dr Windsor ON N8W 5A4",
    "addr:housenumber":"3630",
    "addr:postcode":"n8w 5a4",
    "addr:street":"Rhodes Dr",
    "iso:country":"CA",
    "sg:address":"3630 Rhodes Dr",
    "sg:city":"Windsor",
    "sg:classifiers":[
        {
            "category":"Personal",
            "type":"Services"
        }
    ],
    "sg:phone":"+1 519 944 6900",
    "sg:postcode":"N8W 5A4",
    "sg:province":"ON",
    "sg:tags":[
        "credit",
        "accountant",
        "debt",
        "counseling"
    ],
    "wof:name":"Bdo Dunwoody Ltd",
    "wof:placetype":"venue"
},
  "geometry": {"coordinates":[-82.965782,42.282143],"type":"Point"}
}