{
  "type": "Feature",
  "properties": {
    "addr:full":"8600 Boul Marie-Victorin Brossard QC J4X 1A1",
    "addr:housenumber":"8600",
    "addr:postcode":"j4x 1a1",
    "addr:street":"Boul Marie-Victorin",
    "iso:country":"CA",
    "sg:address":"8600 Boul Marie-Victorin",
    "sg:city":"Brossard",
    "sg:classifiers":[
        {
            "category":"Health Services",
            "subcategory":"Nursing And Care Facility",
            "type":"Services"
        }
    ],
    "sg:phone":"+1 450 923 1430",
    "sg:postcode":"J4X 1A1",
    "sg:province":"QC",
    "sg:tags":[
        "home",
        "rest"
    ],
    "wof:name":"Centre D'Accueil M Ferron",
    "wof:placetype":"venue"
},
  "geometry": {"coordinates":[-73.4933166504,45.4463539124],"type":"Point"}
}