{
  "type": "Feature",
  "properties": {
    "addr:full":"509 Pioneer Ave North Battleford SK S9A 4A5",
    "addr:housenumber":"509",
    "addr:postcode":"s9a 4a5",
    "addr:street":"Pioneer Ave",
    "iso:country":"CA",
    "sg:address":"509 Pioneer Ave",
    "sg:city":"North Battleford",
    "sg:classifiers":[
        {
            "category":"Government",
            "subcategory":"Office",
            "type":"Public Place"
        }
    ],
    "sg:phone":"+1 306 446 7646",
    "sg:postcode":"S9A 4A5",
    "sg:province":"SK",
    "wof:name":"Saskatchewan Extension Svc",
    "wof:placetype":"venue"
},
  "geometry": {"coordinates":[-108.280998,52.764339],"type":"Point"}
}