{
  "type": "Feature",
  "properties": {
    "addr:full":"14204 118 Ave NW Edmonton AB T5L 2M5",
    "addr:housenumber":"14204",
    "addr:postcode":"t5l 2m5",
    "addr:street":"118 Ave Nw",
    "iso:country":"CA",
    "sg:address":"14204 118 Ave NW",
    "sg:city":"Edmonton",
    "sg:classifiers":[
        {
            "category":"Restaurant",
            "type":"Food & Drink"
        }
    ],
    "sg:phone":"+1 780 453 6652",
    "sg:postcode":"T5L 2M5",
    "sg:province":"AB",
    "wof:name":"Harvey's",
    "wof:placetype":"venue"
},
  "geometry": {"coordinates":[-113.566467285,53.5706367493],"type":"Point"}
}