{
  "type": "Feature",
  "properties": {
    "addr:full":"529 17E Av Lachine QC H8S 3P2",
    "addr:housenumber":"529",
    "addr:postcode":"h8s 3p2",
    "addr:street":"17E Av",
    "iso:country":"CA",
    "sg:address":"529 17E Av",
    "sg:city":"Lachine",
    "sg:classifiers":[
        {
            "category":"Freight",
            "type":"Transportation"
        }
    ],
    "sg:phone":"+1 514 637 8383",
    "sg:postcode":"H8S 3P2",
    "sg:province":"QC",
    "sg:tags":[
        "trucking"
    ],
    "wof:name":"Transport Normali",
    "wof:placetype":"venue"
},
  "geometry": {"coordinates":[-73.679253,45.438622],"type":"Point"}
}