{
  "type": "Feature",
  "properties": {
    "addr:full":"Lemoyne QC J4R 2L3",
    "addr:postcode":"j4r 2l3",
    "iso:country":"CA",
    "sg:city":"Lemoyne",
    "sg:classifiers":[
        {
            "category":"Personal",
            "subcategory":"Beauty Salon",
            "type":"Services"
        }
    ],
    "sg:phone":"+1 450 671 0797",
    "sg:postcode":"J4R 2L3",
    "sg:province":"QC",
    "wof:name":"Coiffure Sol",
    "wof:placetype":"venue"
},
  "geometry": {"coordinates":[-73.4906387329,45.5019226074],"type":"Point"}
}