{
  "type": "Feature",
  "properties": {
    "addr:full":"518 Rogers Rd York ON M6M 1B3",
    "addr:housenumber":"518",
    "addr:postcode":"m6m 1b3",
    "addr:street":"Rogers Rd",
    "iso:country":"CA",
    "sg:address":"518 Rogers Rd",
    "sg:city":"York",
    "sg:classifiers":[
        {
            "category":"Shopping",
            "subcategory":"Florist",
            "type":"Retail Goods"
        }
    ],
    "sg:phone":"+1 416 653 0634",
    "sg:postcode":"M6M 1B3",
    "sg:province":"ON",
    "wof:name":"Ciano Florist Ltd",
    "wof:placetype":"venue"
},
  "geometry": {"coordinates":[-79.468475,43.682304],"type":"Point"}
}