{
  "type": "Feature",
  "properties": {
    "addr:full":"100 Industrial Ave Carleton Place ON K7C 3T2",
    "addr:housenumber":"100",
    "addr:postcode":"k7c 3t2",
    "addr:street":"Industrial Ave",
    "iso:country":"CA",
    "sg:address":"100 Industrial Ave",
    "sg:city":"Carleton Place",
    "sg:classifiers":[
        {
            "category":"Wholesale",
            "subcategory":"Machinery & Supplies",
            "type":"Manufacturing & Wholesale Goods"
        }
    ],
    "sg:phone":"+1 613 257 4440",
    "sg:postcode":"K7C 3T2",
    "sg:province":"ON",
    "sg:tags":[
        "contractor"
    ],
    "wof:name":"Champion Road Machinery Sales",
    "wof:placetype":"venue"
},
  "geometry": {"coordinates":[-76.1475524902,45.1495132446],"type":"Point"}
}