{
  "type": "Feature",
  "properties": {
    "addr:full":"940 Notre Dame Dr Kamloops BC V2C 6J2",
    "addr:housenumber":"940",
    "addr:postcode":"bc v2c 6j2",
    "addr:street":"Notre Dame Dr",
    "iso:country":"CA",
    "sg:address":"940 Notre Dame Dr",
    "sg:city":"Kamloops",
    "sg:classifiers":[
        {
            "category":"Autos & Motor Vehicles",
            "subcategory":"Auto Supplies",
            "type":"Retail Goods"
        }
    ],
    "sg:phone":"+1 250 374 9922",
    "sg:postcode":"V2C 6J2",
    "sg:province":"BC",
    "sg:tags":[
        "automobile",
        "parts"
    ],
    "wof:name":"Lordco Auto Parts Ltd",
    "wof:placetype":"venue"
},
  "geometry": {"coordinates":[-120.36512,50.663578],"type":"Point"}
}