{
  "type": "Feature",
  "properties": {
    "iso:country":"CA",
    "sg:address":"2184 Orient Park Dr",
    "sg:city":"Gloucester",
    "sg:classifiers":[
        {
            "category":"Building & Trades",
            "subcategory":"Landscaping Services",
            "type":"Services"
        }
    ],
    "sg:phone":"+1 613 837 4879",
    "sg:postcode":"K1B 4V9",
    "sg:province":"ON",
    "sg:tags":[
        "landscape",
        "contractor"
    ],
    "wof:name":"Tree Care & Landscaping",
    "wof:placetype":"venue"
},
  "geometry": {"coordinates":[-75.5604171753,45.4333610535],"type":"Point"}
}