{
  "type": "Feature",
  "properties": {
    "addr:full":"100 Close Ave Toronto ON M6K 2V3",
    "addr:housenumber":"100",
    "addr:postcode":"m6k 2v3",
    "addr:street":"Close Ave",
    "iso:country":"CA",
    "sg:address":"100 Close Ave",
    "sg:city":"Toronto",
    "sg:classifiers":[
        {
            "category":"Social Services",
            "subcategory":"Child Care",
            "type":"Services"
        }
    ],
    "sg:phone":"+1 416 530 0683",
    "sg:postcode":"M6K 2V3",
    "sg:province":"ON",
    "wof:name":"Parkdale Beach Child Care Ctr",
    "wof:placetype":"venue"
},
  "geometry": {"coordinates":[-79.43454,43.636589],"type":"Point"}
}