{
  "type": "Feature",
  "properties": {
    "addr:full":"26 Portage St St George NB E5C 3L6",
    "addr:housenumber":"26",
    "addr:postcode":"e5c 3l6",
    "addr:street":"Portage St",
    "iso:country":"CA",
    "sg:address":"26 Portage St",
    "sg:city":"St George",
    "sg:classifiers":[
        {
            "category":"Retail",
            "subcategory":"Funeral Services",
            "type":"Services"
        }
    ],
    "sg:phone":"+1 506 755 3533",
    "sg:postcode":"E5C 3L6",
    "sg:province":"NB",
    "sg:tags":[
        "director"
    ],
    "wof:name":"St George Funeral Home",
    "wof:placetype":"venue"
},
  "geometry": {"coordinates":[-66.8251495361,45.1295394897],"type":"Point"}
}