{
  "type": "Feature",
  "properties": {
    "addr:full":"3108 Carp Rd Carp ON K0A 1L0",
    "addr:housenumber":"3108",
    "addr:postcode":"k0a 1l0",
    "addr:street":"Carp Rd",
    "iso:country":"CA",
    "sg:address":"3108 Carp Rd",
    "sg:city":"Carp",
    "sg:classifiers":[
        {
            "category":"Professional",
            "subcategory":"Research",
            "type":"Services"
        }
    ],
    "sg:phone":"+1 613 839 3053",
    "sg:postcode":"K0A 1L0",
    "sg:province":"ON",
    "sg:tags":[
        "environmental",
        "ecological"
    ],
    "wof:name":"Wesa",
    "wof:placetype":"venue"
},
  "geometry": {"coordinates":[-76.00299835209999,45.3183937073],"type":"Point"}
}