{
  "type": "Feature",
  "properties": {
    "addr:full":"53472 Range Road 231 Sherwood Park AB T8A 4V4",
    "addr:housenumber":"53472",
    "addr:postcode":"t8a 4v4",
    "addr:street":"Range Road 231;Park",
    "iso:country":"CA",
    "sg:address":"53472 Range Road 231",
    "sg:city":"Sherwood Park",
    "sg:classifiers":[
        {
            "category":"Freight",
            "type":"Transportation"
        }
    ],
    "sg:phone":"+1 780 416 1777",
    "sg:postcode":"T8A 4V4",
    "sg:province":"AB",
    "sg:tags":[
        "trucking"
    ],
    "wof:name":"Dka Trucking",
    "wof:placetype":"venue"
},
  "geometry": {"coordinates":[-113.27073669400001,53.5961112976],"type":"Point"}
}