{
  "type": "Feature",
  "properties": {
    "addr:full":"Richmond BC V7E 3L6",
    "addr:postcode":"v7e 3l6",
    "iso:country":"CA",
    "sg:city":"Richmond",
    "sg:classifiers":[
        {
            "category":"Shopping",
            "subcategory":"Used Merchandise",
            "type":"Retail Goods"
        }
    ],
    "sg:phone":"+1 604 272 0560",
    "sg:postcode":"V7E 3L6",
    "sg:province":"BC",
    "sg:tags":[
        "clothing"
    ],
    "wof:name":"Echante Consignment Boutique",
    "wof:placetype":"venue"
},
  "geometry": {"coordinates":[-123.184463501,49.1258010864],"type":"Point"}
}