{
  "type": "Feature",
  "properties": {
    "iso:country":"CA",
    "sg:address":"7168 Bank St",
    "sg:city":"Metcalfe",
    "sg:classifiers":[
        {
            "category":"Restaurant",
            "type":"Food & Drink"
        }
    ],
    "sg:phone":"+1 613 821 3749",
    "sg:postcode":"K0A 2P0",
    "sg:province":"ON",
    "wof:name":"Mike's Pizzeria & Restaurant",
    "wof:placetype":"venue"
},
  "geometry": {"coordinates":[-75.49657440190001,45.2287521362],"type":"Point"}
}