{
  "type": "Feature",
  "properties": {
    "addr:full":"16 Rue J.-B.-Bernier Saint-Anselme QC G0R 2N0",
    "addr:housenumber":"16",
    "addr:postcode":"g0r 2n0",
    "addr:street":"Rue J.-B.-Bernier",
    "iso:country":"CA",
    "sg:address":"16 Rue J.-B.-Bernier",
    "sg:city":"Saint-Anselme",
    "sg:classifiers":[
        {
            "category":"Retail",
            "subcategory":"Auto Repair",
            "type":"Services"
        }
    ],
    "sg:phone":"+1 418 885 4224",
    "sg:postcode":"G0R 2N0",
    "sg:province":"QC",
    "sg:tags":[
        "repairing",
        "automobile"
    ],
    "wof:name":"Garage Armand Roy Enr",
    "wof:placetype":"venue"
},
  "geometry": {"coordinates":[-70.9547958374,46.622882843],"type":"Point"}
}