{
  "type": "Feature",
  "properties": {
    "iso:country":"CA",
    "sg:address":"9676 Hwy 224",
    "sg:city":"Upper Musquodoboit",
    "sg:classifiers":[
        {
            "category":"Wholesale",
            "subcategory":"Machinery & Supplies",
            "type":"Manufacturing & Wholesale Goods"
        }
    ],
    "sg:phone":"+1 902 568 2755",
    "sg:postcode":"B0N 2M0",
    "sg:province":"NS",
    "sg:tags":[
        "equipment",
        "industrial",
        "sawmill"
    ],
    "wof:name":"Musquodoboit Valley Resource",
    "wof:placetype":"venue"
},
  "geometry": {"coordinates":[-62.95356,45.13266],"type":"Point"}
}