{
  "type": "Feature",
  "properties": {
    "iso:country":"CA",
    "sg:address":"398 Ontario St",
    "sg:city":"St Catharines",
    "sg:classifiers":[
        {
            "category":"Home & Garden",
            "subcategory":"Building Materials",
            "type":"Retail Goods"
        }
    ],
    "sg:phone":"+1 905 685 0412",
    "sg:postcode":"L2R 5L8",
    "sg:province":"ON",
    "sg:tags":[
        "paint"
    ],
    "wof:name":"Color Your World",
    "wof:placetype":"venue"
},
  "geometry": {"coordinates":[-79.265953064,43.1753158569],"type":"Point"}
}