{
  "type": "Feature",
  "properties": {
    "addr:full":"1260 Rue Des Cascades O Saint-Hyacinthe QC J2S 3H1",
    "addr:housenumber":"1260",
    "addr:postcode":"j2s 3h1",
    "addr:street":"Rue Des Cascades O",
    "iso:country":"CA",
    "sg:address":"1260 Rue Des Cascades O",
    "sg:city":"Saint-Hyacinthe",
    "sg:classifiers":[
        {
            "category":"Wholesale",
            "subcategory":"Non-durable Goods",
            "type":"Manufacturing & Wholesale Goods"
        }
    ],
    "sg:phone":"+1 450 774 7060",
    "sg:postcode":"J2S 3H1",
    "sg:province":"QC",
    "sg:tags":[
        "leather"
    ],
    "wof:name":"J-G Dolbec Ltee",
    "wof:placetype":"venue"
},
  "geometry": {"coordinates":[-72.9443511963,45.6257247925],"type":"Point"}
}