{
  "type": "Feature",
  "properties": {
    "iso:country":"CA",
    "sg:city":"Gloucester",
    "sg:classifiers":[
        {
            "category":"Building & Trades",
            "subcategory":"Landscaping Services",
            "type":"Services"
        }
    ],
    "sg:phone":"+1 613 739 4204",
    "sg:postcode":"K1G 3N2",
    "sg:province":"ON",
    "sg:tags":[
        "landscape",
        "contractor"
    ],
    "wof:name":"Ashbury Landscaping & Cnsltng",
    "wof:placetype":"venue"
},
  "geometry": {"coordinates":[-75.5937423706,45.3824005127],"type":"Point"}
}