{
  "type": "Feature",
  "properties": {
    "addr:full":"7626 100 Ave Peace River AB T8S 1M5",
    "addr:housenumber":"7626",
    "addr:postcode":"t8s 1m5",
    "addr:street":"100 Ave",
    "iso:country":"CA",
    "sg:address":"7626 100 Ave",
    "sg:city":"Peace River",
    "sg:classifiers":[
        {
            "category":"Home & Garden",
            "subcategory":"Furniture",
            "type":"Retail Goods"
        }
    ],
    "sg:phone":"+1 780 624 5000",
    "sg:postcode":"T8S 1M5",
    "sg:province":"AB",
    "wof:name":"Flair Furniture Countrywide",
    "wof:placetype":"venue"
},
  "geometry": {"coordinates":[-117.342529,56.233299],"type":"Point"}
}