{
  "type": "Feature",
  "properties": {
    "iso:country":"CA",
    "sg:city":"Saint-Laurent",
    "sg:classifiers":[
        {
            "category":"Manufacturing",
            "subcategory":"Printing",
            "type":"Manufacturing & Wholesale Goods"
        }
    ],
    "sg:phone":"+1 514 744 1184",
    "sg:postcode":"H4M 2V6",
    "sg:province":"QC",
    "sg:tags":[
        "publisher"
    ],
    "wof:name":"Canadian Journal of Urology",
    "wof:placetype":"venue"
},
  "geometry": {"coordinates":[-73.681221,45.496807],"type":"Point"}
}