{
  "type": "Feature",
  "properties": {
    "addr:full":"2616 Centre St NE Calgary AB T2E 2V4",
    "addr:housenumber":"2616",
    "addr:postcode":"t2e 2v4",
    "addr:street":"Centre St Ne",
    "iso:country":"CA",
    "sg:address":"2616 Centre St NE",
    "sg:city":"Calgary",
    "sg:classifiers":[
        {
            "category":"Food & Beverages",
            "subcategory":"Groceries & Convenience Stores",
            "type":"Retail Goods"
        }
    ],
    "sg:phone":"+1 403 277 4311",
    "sg:postcode":"T2E 2V4",
    "sg:province":"AB",
    "sg:tags":[
        "grocer"
    ],
    "wof:name":"Family Groceteria",
    "wof:placetype":"venue"
},
  "geometry": {"coordinates":[-114.062363,51.075394],"type":"Point"}
}