{
  "type": "Feature",
  "properties": {
    "iso:country":"CA",
    "sg:city":"Verdun",
    "sg:classifiers":[
        {
            "category":"Health Services",
            "subcategory":"Doctor",
            "type":"Services"
        }
    ],
    "sg:phone":"+1 514 768 3550",
    "sg:postcode":"H4G 1L7",
    "sg:province":"QC",
    "sg:tags":[
        "dentist"
    ],
    "wof:name":"DO, Bich-Chau DDS",
    "wof:placetype":"venue"
},
  "geometry": {"coordinates":[-73.571762085,45.4604225159],"type":"Point"}
}