{
  "type": "Feature",
  "properties": {
    "addr:full":"22 Cecil St Toronto ON M5T 1N2",
    "addr:housenumber":"22",
    "addr:postcode":"m5t 1n2",
    "addr:street":"Cecil St",
    "iso:country":"CA",
    "sg:address":"22 Cecil St",
    "sg:city":"Toronto",
    "sg:classifiers":[
        {
            "category":"Organizations",
            "subcategory":"Religious Organization",
            "type":"Services"
        }
    ],
    "sg:phone":"+1 416 598 4596",
    "sg:postcode":"M5T 1N2",
    "sg:province":"ON",
    "wof:name":"Canadian Chinese Buddhist Ming",
    "wof:placetype":"venue"
},
  "geometry": {"coordinates":[-79.3956604004,43.6569900513],"type":"Point"}
}