{
  "type": "Feature",
  "properties": {
    "addr:full":"525 Cote St Ottawa ON K1K 0Z8",
    "addr:housenumber":"525",
    "addr:postcode":"k1k 0z8",
    "addr:street":"Cote St",
    "iso:country":"CA",
    "sg:address":"525 Cote St",
    "sg:city":"Ottawa",
    "sg:classifiers":[
        {
            "category":"Recreation",
            "type":"Entertainment"
        }
    ],
    "sg:phone":"+1 613 742 6767",
    "sg:postcode":"K1K 0Z8",
    "sg:province":"ON",
    "sg:tags":[
        "government",
        "hall",
        "auditorium"
    ],
    "wof:name":"Complexe St Laurent",
    "wof:placetype":"venue"
},
  "geometry": {"coordinates":[-75.64645400000001,45.435635],"type":"Point"}
}