{
  "type": "Feature",
  "properties": {
    "iso:country":"CA",
    "sg:address":"331 Victoria St",
    "sg:city":"Kamloops",
    "sg:classifiers":[
        {
            "category":"Shopping",
            "subcategory":"Optical Goods",
            "type":"Retail Goods"
        }
    ],
    "sg:phone":"+1 250 851 8992",
    "sg:postcode":"V2C 2A3",
    "sg:province":"BC",
    "sg:tags":[
        "sun",
        "goggles",
        "sunglasses",
        "optician"
    ],
    "wof:name":"Eyes International",
    "wof:placetype":"venue"
},
  "geometry": {"coordinates":[-120.33354187,50.6757316589],"type":"Point"}
}