{
  "type": "Feature",
  "properties": {
    "addr:full":"1291 Principale St Saint-Come-Liniere QC G0M 1J0",
    "addr:housenumber":"1291",
    "addr:postcode":"g0m 1j0",
    "addr:street":"Principale St",
    "iso:country":"CA",
    "sg:address":"1291 Principale St",
    "sg:city":"Saint-Come-Liniere",
    "sg:classifiers":[
        {
            "category":"Retail",
            "subcategory":"Auto Repair",
            "type":"Services"
        }
    ],
    "sg:phone":"+1 418 685 3444",
    "sg:postcode":"G0M 1J0",
    "sg:province":"QC",
    "sg:tags":[
        "repairing",
        "automobile"
    ],
    "wof:name":"Garage Marcel Nadeau",
    "wof:placetype":"venue"
},
  "geometry": {"coordinates":[-70.526787,46.059879],"type":"Point"}
}