{
  "type": "Feature",
  "properties": {
    "addr:full":"948 Zelco Dr Burlington ON L7L 4Y3",
    "addr:housenumber":"948",
    "addr:postcode":"l7l 4y3",
    "addr:street":"Zelco Dr",
    "iso:country":"CA",
    "sg:address":"948 Zelco Dr",
    "sg:city":"Burlington",
    "sg:classifiers":[
        {
            "category":"Building & Trades",
            "subcategory":"Equipment Rental",
            "type":"Services"
        }
    ],
    "sg:phone":"+1 905 639 6169",
    "sg:postcode":"L7L 4Y3",
    "sg:province":"ON",
    "sg:tags":[
        "crane",
        "contractor"
    ],
    "wof:name":"Double D Crane Svc",
    "wof:placetype":"venue"
},
  "geometry": {"coordinates":[-79.771507,43.376659],"type":"Point"}
}