{
  "type": "Feature",
  "properties": {
    "addr:full":"2999 Kingston Rd Scarborough ON M1M 1P1",
    "addr:housenumber":"2999",
    "addr:postcode":"m1m 1p1",
    "addr:street":"Kingston Rd",
    "iso:country":"CA",
    "sg:address":"2999 Kingston Rd",
    "sg:city":"Scarborough",
    "sg:classifiers":[
        {
            "category":"Shopping",
            "subcategory":"Pharmacy",
            "type":"Retail Goods"
        }
    ],
    "sg:phone":"+1 416 261 6114",
    "sg:postcode":"M1M 1P1",
    "sg:province":"ON",
    "wof:name":"Shoppers Drug Mart",
    "wof:placetype":"venue"
},
  "geometry": {"coordinates":[-79.23144499999999,43.725739],"type":"Point"}
}