{
  "type": "Feature",
  "properties": {
    "addr:full":"4762 Boul Samson Laval QC H7W 2H7",
    "addr:housenumber":"4762",
    "addr:postcode":"h7w 2h7",
    "addr:street":"Boul Samson",
    "iso:country":"CA",
    "sg:address":"4762 Boul Samson",
    "sg:city":"Laval",
    "sg:classifiers":[
        {
            "category":"Health Services",
            "subcategory":"Doctor",
            "type":"Services"
        }
    ],
    "sg:phone":"+1 450 681 2188",
    "sg:postcode":"H7W 2H7",
    "sg:province":"QC",
    "sg:tags":[
        "dentist"
    ],
    "wof:name":"Clinique Dentaire B Toukmanian",
    "wof:placetype":"venue"
},
  "geometry": {"coordinates":[-73.761169,45.527767],"type":"Point"}
}