{
  "type": "Feature",
  "properties": {
    "iso:country":"CA",
    "sg:address":"1348 Hamilton Rd",
    "sg:city":"London",
    "sg:classifiers":[
        {
            "category":"Freight",
            "type":"Transportation"
        }
    ],
    "sg:phone":"+1 519 659 8878",
    "sg:postcode":"N5W 5W9",
    "sg:province":"ON",
    "sg:tags":[
        "commercial",
        "storage"
    ],
    "wof:name":"Hamilton Road Storage",
    "wof:placetype":"venue"
},
  "geometry": {"coordinates":[-81.1581497192,42.9706687927],"type":"Point"}
}