{
  "type": "Feature",
  "properties": {
    "addr:full":"2005 14 Ave Wainwright AB T9W 1T9",
    "addr:housenumber":"2005",
    "addr:postcode":"t9w 1t9",
    "addr:street":"14 Ave",
    "iso:country":"CA",
    "sg:address":"2005 14 Ave",
    "sg:city":"Wainwright",
    "sg:classifiers":[
        {
            "category":"Retail",
            "subcategory":"Repair Shop",
            "type":"Services"
        }
    ],
    "sg:phone":"+1 780 842 9134",
    "sg:postcode":"T9W 1T9",
    "sg:province":"AB",
    "sg:tags":[
        "lock",
        "glass",
        "locksmith"
    ],
    "wof:name":"Eagle Lock & Glass",
    "wof:placetype":"venue"
},
  "geometry": {"coordinates":[-110.841621,52.843262],"type":"Point"}
}