{
  "type": "Feature",
  "properties": {
    "addr:full":"5495 Victoria Ave Montreal QC H3W 2P9",
    "addr:housenumber":"5495",
    "addr:postcode":"h3w 2p9",
    "addr:street":"Victoria Ave",
    "iso:country":"CA",
    "sg:address":"5495 Victoria Ave",
    "sg:city":"Montreal",
    "sg:classifiers":[
        {
            "category":"Personal",
            "subcategory":"Beauty Salon",
            "type":"Services"
        }
    ],
    "sg:phone":"+1 514 733 9255",
    "sg:postcode":"H3W 2P9",
    "sg:province":"QC",
    "wof:name":"Beaute Select",
    "wof:placetype":"venue"
},
  "geometry": {"coordinates":[-73.63145400000001,45.491783],"type":"Point"}
}