{
  "type": "Feature",
  "properties": {
    "addr:full":"111 Lake Louise Dr Lake Louise AB T0L 1E0",
    "addr:housenumber":"111",
    "addr:postcode":"t0l 1e0",
    "addr:street":"Lake Louise Dr",
    "iso:country":"CA",
    "sg:address":"111 Lake Louise Dr",
    "sg:city":"Lake Louise",
    "sg:classifiers":[
        {
            "category":"Food & Beverages",
            "subcategory":"Candy",
            "type":"Retail Goods"
        }
    ],
    "sg:phone":"+1 403 522 3507",
    "sg:postcode":"T0L 1E0",
    "sg:province":"AB",
    "sg:tags":[
        "confectionery"
    ],
    "wof:name":"Goodies",
    "wof:placetype":"venue"
},
  "geometry": {"coordinates":[-116.212554932,51.4170303345],"type":"Point"}
}