{
  "type": "Feature",
  "properties": {
    "addr:full":"Saint-Felicien QC G8K 1R3",
    "addr:postcode":"g8k 1r3",
    "iso:country":"CA",
    "sg:city":"Saint-Felicien",
    "sg:classifiers":[
        {
            "category":"Shopping",
            "subcategory":"Pharmacy",
            "type":"Retail Goods"
        }
    ],
    "sg:phone":"+1 418 679 0330",
    "sg:postcode":"G8K 1R3",
    "sg:province":"QC",
    "wof:name":"Pharmacie Famili-Prix",
    "wof:placetype":"venue"
},
  "geometry": {"coordinates":[-72.4439163208,48.6507301331],"type":"Point"}
}