{
  "type": "Feature",
  "properties": {
    "iso:country":"CA",
    "sg:city":"Mississauga",
    "sg:classifiers":[
        {
            "category":"Manufacturing",
            "subcategory":"Glass & Minerals",
            "type":"Manufacturing & Wholesale Goods"
        }
    ],
    "sg:phone":"+1 905 238 0128",
    "sg:postcode":"L4W 1R9",
    "sg:province":"ON",
    "sg:tags":[
        "scientific",
        "apparatus"
    ],
    "wof:name":"Namdar Custom Glass Blowing",
    "wof:placetype":"venue"
},
  "geometry": {"coordinates":[-79.6264038086,43.6419410706],"type":"Point"}
}