{
  "type": "Feature",
  "properties": {
    "iso:country":"CA",
    "sg:city":"Shannon",
    "sg:classifiers":[
        {
            "category":"Utilities",
            "subcategory":"Cable",
            "type":"Services"
        }
    ],
    "sg:phone":"+1 418 844 3849",
    "sg:postcode":"G0A 4N0",
    "sg:province":"QC",
    "sg:tags":[
        "television"
    ],
    "wof:name":"Shannon Vision",
    "wof:placetype":"venue"
},
  "geometry": {"coordinates":[-71.518997,46.88913],"type":"Point"}
}