{
  "type": "Feature",
  "properties": {
    "addr:full":"Dartmouth NS B2V 1E8",
    "addr:postcode":"b2v 1e8",
    "iso:country":"CA",
    "sg:city":"Dartmouth",
    "sg:classifiers":[
        {
            "category":"Shopping",
            "subcategory":"Computers & Home Electronics",
            "type":"Retail Goods"
        }
    ],
    "sg:phone":"+1 902 462 4453",
    "sg:postcode":"B2V 1E8",
    "sg:province":"NS",
    "sg:tags":[
        "equipment",
        "dealer"
    ],
    "wof:name":"Rde Computer Sales",
    "wof:placetype":"venue"
},
  "geometry": {"coordinates":[-63.493488,44.671597],"type":"Point"}
}