{
  "type": "Feature",
  "properties": {
    "addr:full":"Vancouver BC V6K 2G8",
    "addr:postcode":"v6k 2g8",
    "iso:country":"CA",
    "sg:city":"Vancouver",
    "sg:classifiers":[
        {
            "category":"Professional",
            "subcategory":"Lawyer & Legal Services",
            "type":"Services"
        }
    ],
    "sg:phone":"+1 604 733 5611",
    "sg:postcode":"V6K 2G8",
    "sg:province":"BC",
    "sg:tags":[
        "attorney"
    ],
    "wof:name":"Lipetz & CO",
    "wof:placetype":"venue"
},
  "geometry": {"coordinates":[-123.17011261,49.2639846802],"type":"Point"}
}