{
  "type": "Feature",
  "properties": {
    "iso:country":"CA",
    "sg:address":"183 Cedar St",
    "sg:city":"Sudbury",
    "sg:classifiers":[
        {
            "category":"Restaurant",
            "type":"Food & Drink"
        }
    ],
    "sg:phone":"+1 705 675 1888",
    "sg:postcode":"P3E 1B5",
    "sg:province":"ON",
    "wof:name":"Dionysos Restaurant",
    "wof:placetype":"venue"
},
  "geometry": {"coordinates":[-80.98989105219999,46.4921264648],"type":"Point"}
}