{
  "type": "Feature",
  "properties": {
    "iso:country":"CA",
    "sg:address":"45 West Wilmot St # A",
    "sg:city":"Richmond Hill",
    "sg:classifiers":[
        {
            "category":"Professional",
            "subcategory":"Computer Services",
            "type":"Services"
        }
    ],
    "sg:phone":"+1 905 771 7090",
    "sg:postcode":"L4B 1K1",
    "sg:province":"ON",
    "sg:tags":[
        "consultant"
    ],
    "wof:name":"Summit Business Systems Ltd",
    "wof:placetype":"venue"
},
  "geometry": {"coordinates":[-79.3887557983,43.8524894714],"type":"Point"}
}