{
  "type": "Feature",
  "properties": {
    "iso:country":"CA",
    "sg:city":"Langley",
    "sg:classifiers":[
        {
            "category":"Restaurant",
            "type":"Food & Drink"
        }
    ],
    "sg:phone":"+1 604 539 9222",
    "sg:postcode":"V3A 9J7",
    "sg:province":"BC",
    "wof:name":"White Spot Triple O's",
    "wof:placetype":"venue"
},
  "geometry": {"coordinates":[-122.666275024,49.1132354736],"type":"Point"}
}