{
  "type": "Feature",
  "properties": {
    "iso:country":"CA",
    "sg:city":"Etobicoke",
    "sg:classifiers":[
        {
            "category":"Organizations",
            "subcategory":"Professional Association",
            "type":"Services"
        }
    ],
    "sg:phone":"+1 416 364 9333",
    "sg:postcode":"M9W 5Z5",
    "sg:province":"ON",
    "wof:name":"Canadian Vechicle Mfrs Assoc",
    "wof:placetype":"venue"
},
  "geometry": {"coordinates":[-79.587509,43.689041],"type":"Point"}
}