{
  "type": "Feature",
  "properties": {
    "addr:full":"400 Oakdale Rd North York ON M3N 1W5",
    "addr:housenumber":"400",
    "addr:postcode":"m3n 1w5",
    "addr:street":"Oakdale Rd",
    "iso:country":"CA",
    "sg:address":"400 Oakdale Rd",
    "sg:city":"North York",
    "sg:classifiers":[
        {
            "category":"Retail",
            "subcategory":"Repair Shop",
            "type":"Services"
        }
    ],
    "sg:phone":"+1 416 740 7120",
    "sg:postcode":"M3N 1W5",
    "sg:province":"ON",
    "sg:tags":[
        "refinishing",
        "furniture"
    ],
    "wof:name":"Dreschsel Business Interiors",
    "wof:placetype":"venue"
},
  "geometry": {"coordinates":[-79.52699279789999,43.7483863831],"type":"Point"}
}