{
  "type": "Feature",
  "properties": {
    "addr:full":"175 Stahl's Rd Huntsville ON P1H 2J4",
    "addr:housenumber":"175",
    "addr:postcode":"p1h 2j4",
    "addr:street":"Stahl'S Rd",
    "iso:country":"CA",
    "sg:address":"175 Stahl's Rd",
    "sg:city":"Huntsville",
    "sg:classifiers":[
        {
            "category":"Retail",
            "subcategory":"Animal Services",
            "type":"Services"
        }
    ],
    "sg:phone":"+1 705 789 7380",
    "sg:postcode":"P1H 2J4",
    "sg:province":"ON",
    "sg:tags":[
        "pet",
        "boarding",
        "sitting"
    ],
    "wof:name":"Doggie Motel Kennel",
    "wof:placetype":"venue"
},
  "geometry": {"coordinates":[-79.218002,45.326561],"type":"Point"}
}