{
  "type": "Feature",
  "properties": {
    "addr:full":"194 5E Av Saint-Gabriel-DE-Valcartier QC G0A 4S0",
    "addr:housenumber":"194",
    "addr:postcode":"g0a 4s0",
    "addr:street":"5E Av Saint-Gabriel-De-Valcartier",
    "iso:country":"CA",
    "sg:address":"194 5E Av",
    "sg:city":"Saint-Gabriel-DE-Valcartier",
    "sg:classifiers":[
        {
            "category":"Building & Trades",
            "subcategory":"Construction",
            "type":"Services"
        }
    ],
    "sg:phone":"+1 418 844 2368",
    "sg:postcode":"G0A 4S0",
    "sg:province":"QC",
    "sg:tags":[
        "maker",
        "cabinet"
    ],
    "wof:name":"Atelier Rolland Rousseau",
    "wof:placetype":"venue"
},
  "geometry": {"coordinates":[-71.466667,46.949444],"type":"Point"}
}