{
  "type": "Feature",
  "properties": {
    "addr:full":"Halifax NS B3K 1Z7",
    "addr:postcode":"b3k 1z7",
    "iso:country":"CA",
    "sg:city":"Halifax",
    "sg:classifiers":[
        {
            "category":"Education",
            "subcategory":"Special Training",
            "type":"Public Place"
        }
    ],
    "sg:phone":"+1 902 455 4411",
    "sg:postcode":"B3K 1Z7",
    "sg:province":"NS",
    "sg:tags":[
        "school",
        "language"
    ],
    "wof:name":"Alliance Francaise",
    "wof:placetype":"venue"
},
  "geometry": {"coordinates":[-63.5992546082,44.6621932983],"type":"Point"}
}