{
  "type": "Feature",
  "properties": {
    "addr:full":"1832 Boul Wallberg Dolbeau-Mistassini QC G8L 1H9",
    "addr:housenumber":"1832",
    "addr:postcode":"g8l 1h9",
    "addr:street":"Boul Wallberg",
    "iso:country":"CA",
    "sg:address":"1832 Boul Wallberg",
    "sg:city":"Dolbeau-Mistassini",
    "sg:classifiers":[
        {
            "category":"Social Services",
            "type":"Services"
        }
    ],
    "sg:phone":"+1 418 276 4224",
    "sg:postcode":"G8L 1H9",
    "sg:province":"QC",
    "sg:tags":[
        "organization",
        "welfare"
    ],
    "wof:name":"Maison Colombe-Veilleux",
    "wof:placetype":"venue"
},
  "geometry": {"coordinates":[-72.2347946167,48.8828086853],"type":"Point"}
}