{
  "type": "Feature",
  "properties": {
    "addr:full":"56 Rue Du Banc Gaspe QC G4X 5E2",
    "addr:housenumber":"56",
    "addr:postcode":"g4x 5e2",
    "addr:street":"Rue Du Banc Gaspe",
    "iso:country":"CA",
    "sg:address":"56 Rue Du Banc",
    "sg:city":"Gaspe",
    "sg:classifiers":[
        {
            "category":"Home & Garden",
            "subcategory":"Building Materials",
            "type":"Retail Goods"
        }
    ],
    "sg:phone":"+1 418 269 3693",
    "sg:postcode":"G4X 5E2",
    "sg:province":"QC",
    "sg:tags":[
        "door"
    ],
    "wof:name":"Materiaux Armand Dumaresq",
    "wof:placetype":"venue"
},
  "geometry": {"coordinates":[-64.39041900629999,48.9953575134],"type":"Point"}
}