{
  "type": "Feature",
  "properties": {
    "iso:country":"CA",
    "sg:city":"Renfrew",
    "sg:classifiers":[
        {
            "category":"Autos & Motor Vehicles",
            "subcategory":"Automobile Sales",
            "type":"Retail Goods"
        }
    ],
    "sg:phone":"+1 613 432 7036",
    "sg:postcode":"K7V 2R8",
    "sg:province":"ON",
    "sg:tags":[
        "car",
        "dealer"
    ],
    "wof:name":"Jim New Preowned",
    "wof:placetype":"venue"
},
  "geometry": {"coordinates":[-76.6704940796,45.4692611694],"type":"Point"}
}