{
  "type": "Feature",
  "properties": {
    "addr:full":"83 West St Stephenville NL A2N 1E6",
    "addr:housenumber":"83",
    "addr:postcode":"a2n 1e6",
    "addr:street":"West St",
    "iso:country":"CA",
    "sg:address":"83 West St",
    "sg:city":"Stephenville",
    "sg:classifiers":[
        {
            "category":"Personal",
            "subcategory":"Beauty Salon",
            "type":"Services"
        }
    ],
    "sg:phone":"+1 709 643 9892",
    "sg:postcode":"A2N 1E6",
    "sg:province":"NL",
    "wof:name":"Esther's Beauty Salon",
    "wof:placetype":"venue"
},
  "geometry": {"coordinates":[-58.5909233093,48.5464668274],"type":"Point"}
}