{
  "type": "Feature",
  "properties": {
    "iso:country":"CA",
    "sg:address":"8560 Baxter Pl",
    "sg:city":"Burnaby",
    "sg:classifiers":[
        {
            "category":"Manufacturing",
            "subcategory":"Tools & Machinery",
            "type":"Manufacturing & Wholesale Goods"
        }
    ],
    "sg:phone":"+1 604 421 5500",
    "sg:postcode":"V5A 4T2",
    "sg:province":"BC",
    "sg:tags":[
        "machine",
        "equipment",
        "mining",
        "shop",
        "supply"
    ],
    "wof:name":"T M Engineering Ltd",
    "wof:placetype":"venue"
},
  "geometry": {"coordinates":[-122.9141922,49.2590942383],"type":"Point"}
}