{
  "type": "Feature",
  "properties": {
    "addr:full":"16795 Rue Oakwood Pierrefonds QC H9H 5K7",
    "addr:housenumber":"16795",
    "addr:postcode":"h9h 5k7",
    "addr:street":"Rue Oakwood",
    "iso:country":"CA",
    "sg:address":"16795 Rue Oakwood",
    "sg:city":"Pierrefonds",
    "sg:classifiers":[
        {
            "category":"Utilities",
            "subcategory":"Refuse",
            "type":"Services"
        }
    ],
    "sg:phone":"+1 514 696 4509",
    "sg:postcode":"H9H 5K7",
    "sg:province":"QC",
    "sg:tags":[
        "landfill"
    ],
    "wof:name":"Entreprises Envronnementales",
    "wof:placetype":"venue"
},
  "geometry": {"coordinates":[-73.8671875,45.4635162354],"type":"Point"}
}