{
  "type": "Feature",
  "properties": {
    "addr:full":"2577 Ch Du Foulon Sillery QC G1T 1X9",
    "addr:housenumber":"2577",
    "addr:postcode":"g1t 1x9",
    "addr:street":"Ch Du Foulon",
    "iso:country":"CA",
    "sg:address":"2577 Ch Du Foulon",
    "sg:city":"Sillery",
    "sg:classifiers":[
        {
            "category":"Organizations",
            "subcategory":"Professional Association",
            "type":"Services"
        }
    ],
    "sg:phone":"+1 418 656 0900",
    "sg:postcode":"G1T 1X9",
    "sg:province":"QC",
    "wof:name":"Helicopter Assn of Canada",
    "wof:placetype":"venue"
},
  "geometry": {"coordinates":[-71.266327,46.761192],"type":"Point"}
}