{
  "type": "Feature",
  "properties": {
    "addr:full":"Trois-Rivieres QC G8Y 5B8",
    "addr:postcode":"g8y 5b8",
    "iso:country":"CA",
    "sg:city":"Trois-Rivieres",
    "sg:classifiers":[
        {
            "category":"Insurance",
            "subcategory":"Insurance Agent",
            "type":"Services"
        }
    ],
    "sg:phone":"+1 819 376 8666",
    "sg:postcode":"G8Y 5B8",
    "sg:province":"QC",
    "wof:name":"Services Financiers LA Laurent",
    "wof:placetype":"venue"
},
  "geometry": {"coordinates":[-72.59144592289999,46.3594436646],"type":"Point"}
}