{
  "type": "Feature",
  "properties": {
    "iso:country":"CA",
    "sg:address":"1855 Cameron St",
    "sg:city":"Regina",
    "sg:classifiers":[
        {
            "category":"Manufacturing",
            "subcategory":"Signs",
            "type":"Manufacturing & Wholesale Goods"
        }
    ],
    "sg:phone":"+1 306 352 2211",
    "sg:postcode":"S4T 2T9",
    "sg:province":"SK",
    "wof:name":"Pls Sign & Graphic Ind Ltd",
    "wof:placetype":"venue"
},
  "geometry": {"coordinates":[-104.625175476,50.4492721558],"type":"Point"}
}