{
  "type": "Feature",
  "properties": {
    "addr:full":"4 King St W Toronto ON M5H 1B6",
    "addr:housenumber":"4",
    "addr:postcode":"m5h 1b6",
    "addr:street":"King St W",
    "iso:country":"CA",
    "sg:address":"4 King St W",
    "sg:city":"Toronto",
    "sg:classifiers":[
        {
            "category":"Shopping",
            "subcategory":"Tobacco",
            "type":"Retail Goods"
        }
    ],
    "sg:phone":"+1 416 594 2402",
    "sg:postcode":"M5H 1B6",
    "sg:province":"ON",
    "sg:tags":[
        "cigarette",
        "cigar",
        "dealer"
    ],
    "wof:name":"Ucs Group Ltd",
    "wof:placetype":"venue"
},
  "geometry": {"coordinates":[-79.37808200000001,43.649185],"type":"Point"}
}