{
  "type": "Feature",
  "properties": {
    "addr:full":"806 Clearwater Lake Rd Port Sydney ON P0B 1L0",
    "addr:housenumber":"806",
    "addr:postcode":"p0b 1l0",
    "addr:street":"Clearwater Lake Rd",
    "iso:country":"CA",
    "sg:address":"806 Clearwater Lake Rd",
    "sg:city":"Port Sydney",
    "sg:classifiers":[
        {
            "category":"Building & Trades",
            "subcategory":"Construction",
            "type":"Services"
        }
    ],
    "sg:phone":"+1 705 385 1269",
    "sg:postcode":"P0B 1L0",
    "sg:province":"ON",
    "sg:tags":[
        "waterproofing",
        "contractor"
    ],
    "wof:name":"Muskoka Tar & Feather",
    "wof:placetype":"venue"
},
  "geometry": {"coordinates":[-79.2378234863,45.1917724609],"type":"Point"}
}