{
  "type": "Feature",
  "properties": {
    "addr:full":"2575 Rue Roy Sherbrooke QC J1K 1B9",
    "addr:housenumber":"2575",
    "addr:postcode":"j1k 1b9",
    "addr:street":"Rue Roy",
    "iso:country":"CA",
    "sg:address":"2575 Rue Roy",
    "sg:city":"Sherbrooke",
    "sg:classifiers":[
        {
            "category":"Wholesale",
            "subcategory":"Machinery & Supplies",
            "type":"Manufacturing & Wholesale Goods"
        }
    ],
    "sg:phone":"+1 819 566 5533",
    "sg:postcode":"J1K 1B9",
    "sg:province":"QC",
    "sg:tags":[
        "equipment",
        "hydraulic"
    ],
    "wof:name":"Hydraulique Sms DE L'Estrie",
    "wof:placetype":"venue"
},
  "geometry": {"coordinates":[-71.9356765747,45.3909111023],"type":"Point"}
}