{
  "type": "Feature",
  "properties": {
    "addr:full":"Mississauga ON L5V 2N6",
    "addr:postcode":"l5v 2n6",
    "iso:country":"CA",
    "sg:city":"Mississauga",
    "sg:classifiers":[
        {
            "category":"Shopping",
            "subcategory":"Gifts & Souvenirs",
            "type":"Retail Goods"
        }
    ],
    "sg:phone":"+1 905 755 0440",
    "sg:postcode":"L5V 2N6",
    "sg:province":"ON",
    "sg:tags":[
        "shop"
    ],
    "wof:name":"Mika's Japenese Gifts",
    "wof:placetype":"venue"
},
  "geometry": {"coordinates":[-79.688377,43.606472],"type":"Point"}
}