{
  "type": "Feature",
  "properties": {
    "addr:full":"Bishopton QC J0B 1G0",
    "addr:postcode":"j0b 1g0",
    "iso:country":"CA",
    "sg:city":"Bishopton",
    "sg:classifiers":[
        {
            "category":"Building & Trades",
            "subcategory":"Construction",
            "type":"Services"
        }
    ],
    "sg:phone":"+1 819 884 5404",
    "sg:postcode":"J0B 1G0",
    "sg:province":"QC",
    "sg:tags":[
        "excavating",
        "contractor"
    ],
    "wof:name":"Excavation Lyndon Betts",
    "wof:placetype":"venue"
},
  "geometry": {"coordinates":[-71.58643341059999,45.5884590149],"type":"Point"}
}