{
  "type": "Feature",
  "properties": {
    "addr:full":"NW 10 19 4W Lundar MB R0C 1Y0",
    "addr:housenumber":"19 4w",
    "addr:postcode":"r0c 1y0",
    "addr:street":"Nw 10",
    "iso:country":"CA",
    "sg:address":"NW 10 19 4W",
    "sg:city":"Lundar",
    "sg:classifiers":[
        {
            "category":"Building & Trades",
            "subcategory":"Construction",
            "type":"Services"
        }
    ],
    "sg:phone":"+1 204 762 5849",
    "sg:postcode":"R0C 1Y0",
    "sg:province":"MB",
    "sg:tags":[
        "maker",
        "cabinet"
    ],
    "wof:name":"Hans Bieri Custom Woodwork",
    "wof:placetype":"venue"
},
  "geometry": {"coordinates":[-98.030525,50.697609],"type":"Point"}
}