{
  "type": "Feature",
  "properties": {
    "addr:full":"General Delivery Consort AB T0C 1B0",
    "addr:postcode":"t0c 1b0",
    "iso:country":"CA",
    "sg:address":"General Delivery",
    "sg:city":"Consort",
    "sg:classifiers":[
        {
            "category":"Organizations",
            "subcategory":"Professional Association",
            "type":"Services"
        }
    ],
    "sg:phone":"+1 403 577 3876",
    "sg:postcode":"T0C 1B0",
    "sg:province":"AB",
    "sg:tags":[
        "club"
    ],
    "wof:name":"Royal Canadian Legion",
    "wof:placetype":"venue"
},
  "geometry": {"coordinates":[-110.766082764,52.0071601868],"type":"Point"}
}