{
  "type": "Feature",
  "properties": {
    "addr:full":"139 Casselholme Cres New Dundee ON N0B 2E0",
    "addr:housenumber":"139",
    "addr:postcode":"n0b 2e0",
    "addr:street":"Casselholme Cres",
    "iso:country":"CA",
    "sg:address":"139 Casselholme Cres",
    "sg:city":"New Dundee",
    "sg:classifiers":[
        {
            "category":"Freight",
            "type":"Transportation"
        }
    ],
    "sg:phone":"+1 519 696 2576",
    "sg:postcode":"N0B 2E0",
    "sg:province":"ON",
    "sg:tags":[
        "trucking"
    ],
    "wof:name":"Poll Transport Inc",
    "wof:placetype":"venue"
},
  "geometry": {"coordinates":[-80.5323181152,43.3459129333],"type":"Point"}
}