{
  "type": "Feature",
  "properties": {
    "addr:full":"3015 London Line Wyoming ON N0N 1T0",
    "addr:housenumber":"3015",
    "addr:postcode":"n0n 1t0",
    "addr:street":"London Line",
    "iso:country":"CA",
    "sg:address":"3015 London Line",
    "sg:city":"Wyoming",
    "sg:classifiers":[
        {
            "category":"Building & Trades",
            "subcategory":"Landscaping Services",
            "type":"Services"
        }
    ],
    "sg:phone":"+1 519 542 7337",
    "sg:postcode":"N0N 1T0",
    "sg:province":"ON",
    "sg:tags":[
        "lawn",
        "contractor",
        "landscape",
        "maintenance",
        "grounds"
    ],
    "wof:name":"Sarnia Turf Svc",
    "wof:placetype":"venue"
},
  "geometry": {"coordinates":[-82.1638259888,42.9804000854],"type":"Point"}
}