{
  "type": "Feature",
  "properties": {
    "iso:country":"CA",
    "sg:address":"702 Railway Ave",
    "sg:city":"Rocanville",
    "sg:classifiers":[
        {
            "category":"Travel",
            "subcategory":"Hotels & Motels",
            "type":"Entertainment"
        }
    ],
    "sg:phone":"+1 306 645 2625",
    "sg:postcode":"S0A 3L0",
    "sg:province":"SK",
    "wof:name":"Hag's Hideaway",
    "wof:placetype":"venue"
},
  "geometry": {"coordinates":[-101.699920654,50.3824424744],"type":"Point"}
}