{
  "type": "Feature",
  "properties": {
    "iso:country":"CA",
    "sg:address":"12539 128 St NW",
    "sg:city":"Edmonton",
    "sg:classifiers":[
        {
            "category":"Building & Trades",
            "subcategory":"Construction",
            "type":"Services"
        }
    ],
    "sg:phone":"+1 780 452 4848",
    "sg:postcode":"T5L 1C9",
    "sg:province":"AB",
    "sg:tags":[
        "dry wall",
        "contractor"
    ],
    "wof:name":"Centennial Drywall & Texturing",
    "wof:placetype":"venue"
},
  "geometry": {"coordinates":[-113.542640686,53.5818405151],"type":"Point"}
}