{
  "type": "Feature",
  "properties": {
    "addr:full":"314 Rue Saint-Hubert Granby QC J2G 5N3",
    "addr:housenumber":"314",
    "addr:postcode":"j2g 5n3",
    "addr:street":"Rue Saint-Hubert",
    "iso:country":"CA",
    "sg:address":"314 Rue Saint-Hubert",
    "sg:city":"Granby",
    "sg:classifiers":[
        {
            "category":"Local Transit",
            "type":"Transportation"
        }
    ],
    "sg:phone":"+1 450 375 2069",
    "sg:postcode":"J2G 5N3",
    "sg:province":"QC",
    "sg:tags":[
        "handicapped"
    ],
    "wof:name":"Ami Bus Inc",
    "wof:placetype":"venue"
},
  "geometry": {"coordinates":[-72.729202,45.411659],"type":"Point"}
}