{
  "type": "Feature",
  "properties": {
    "addr:full":"10204 100 Ave Fort Saskatchewan AB T8L 1Y8",
    "addr:housenumber":"10204",
    "addr:postcode":"t8l 1y8",
    "addr:street":"100 Ave",
    "iso:country":"CA",
    "sg:address":"10204 100 Ave",
    "sg:city":"Fort Saskatchewan",
    "sg:classifiers":[
        {
            "category":"Personal",
            "subcategory":"Barber",
            "type":"Services"
        }
    ],
    "sg:phone":"+1 780 998 1977",
    "sg:postcode":"T8L 1Y8",
    "sg:province":"AB",
    "wof:name":"Fort Barbershop",
    "wof:placetype":"venue"
},
  "geometry": {"coordinates":[-113.21353149399999,53.7124176025],"type":"Point"}
}