{
  "type": "Feature",
  "properties": {
    "addr:full":"450 Lougheed Rd Kelowna BC V1X 7R8",
    "addr:housenumber":"450",
    "addr:postcode":"v1x 7r8",
    "addr:street":"Lougheed Rd",
    "iso:country":"CA",
    "sg:address":"450 Lougheed Rd",
    "sg:city":"Kelowna",
    "sg:classifiers":[
        {
            "category":"Building & Trades",
            "subcategory":"Construction",
            "type":"Services"
        }
    ],
    "sg:phone":"+1 250 765 4411",
    "sg:postcode":"V1X 7R8",
    "sg:province":"BC",
    "sg:tags":[
        "siding",
        "contractor"
    ],
    "wof:name":"Kaycan Limited",
    "wof:placetype":"venue"
},
  "geometry": {"coordinates":[-119.38974,49.924824],"type":"Point"}
}