{
  "type": "Feature",
  "properties": {
    "addr:full":"Ottawa ON K1V 8B9",
    "addr:postcode":"k1v 8b9",
    "iso:country":"CA",
    "sg:city":"Ottawa",
    "sg:classifiers":[
        {
            "category":"Organizations",
            "subcategory":"Professional Association",
            "type":"Services"
        }
    ],
    "sg:phone":"+1 613 738 1639",
    "sg:postcode":"K1V 8B9",
    "sg:province":"ON",
    "wof:name":"Greater Ottawa Truckers Assn",
    "wof:placetype":"venue"
},
  "geometry": {"coordinates":[-75.6709518433,45.3752441406],"type":"Point"}
}