{
  "type": "Feature",
  "properties": {
    "addr:full":"78 Charterhouse Cres London ON N5W 5V5",
    "addr:housenumber":"78",
    "addr:postcode":"n5w 5v5",
    "addr:street":"Charterhouse Cres",
    "iso:country":"CA",
    "sg:address":"78 Charterhouse Cres",
    "sg:city":"London",
    "sg:classifiers":[
        {
            "category":"Retail",
            "subcategory":"Auto Repair",
            "type":"Services"
        }
    ],
    "sg:phone":"+1 519 451 0027",
    "sg:postcode":"N5W 5V5",
    "sg:province":"ON",
    "sg:tags":[
        "repairing",
        "automobile"
    ],
    "wof:name":"For Wheels Auto Care Inc",
    "wof:placetype":"venue"
},
  "geometry": {"coordinates":[-81.17017364500001,42.9893493652],"type":"Point"}
}