{
  "type": "Feature",
  "properties": {
    "addr:full":"11 Bridge St Almonte ON K0A 1A0",
    "addr:housenumber":"11",
    "addr:postcode":"k0a 1a0",
    "addr:street":"Bridge St",
    "iso:country":"CA",
    "sg:address":"11 Bridge St",
    "sg:city":"Almonte",
    "sg:classifiers":[
        {
            "category":"Restaurant",
            "type":"Food & Drink"
        }
    ],
    "sg:phone":"+1 613 256 3792",
    "sg:postcode":"K0A 1A0",
    "sg:province":"ON",
    "wof:name":"Canadian Cafe",
    "wof:placetype":"venue"
},
  "geometry": {"coordinates":[-76.193901,45.226025],"type":"Point"}
}