{
  "type": "Feature",
  "properties": {
    "addr:full":"155 Meadowvale Rd Scarborough ON M1C 1S2",
    "addr:housenumber":"155",
    "addr:postcode":"m1c 1s2",
    "addr:street":"Meadowvale Rd",
    "iso:country":"CA",
    "sg:address":"155 Meadowvale Rd",
    "sg:city":"Scarborough",
    "sg:classifiers":[
        {
            "category":"Building & Trades",
            "subcategory":"Construction",
            "type":"Services"
        }
    ],
    "sg:phone":"+1 416 431 2859",
    "sg:postcode":"M1C 1S2",
    "sg:province":"ON",
    "sg:tags":[
        "detection",
        "splicing",
        "installation",
        "cable"
    ],
    "wof:name":"Contact Cabling Systems",
    "wof:placetype":"venue"
},
  "geometry": {"coordinates":[-79.15986599999999,43.783863],"type":"Point"}
}