{
  "type": "Feature",
  "properties": {
    "addr:full":"70 Mornelle Crt Scarborough ON M1E 4S8",
    "addr:housenumber":"70",
    "addr:postcode":"m1e 4s8",
    "addr:street":"Mornelle Crt",
    "iso:country":"CA",
    "sg:address":"70 Mornelle Crt",
    "sg:city":"Scarborough",
    "sg:classifiers":[
        {
            "category":"Professional",
            "subcategory":"Business Services",
            "type":"Services"
        }
    ],
    "sg:phone":"+1 416 282 5824",
    "sg:postcode":"M1E 4S8",
    "sg:province":"ON",
    "sg:tags":[
        "process",
        "server"
    ],
    "wof:name":"Legal Process Svc",
    "wof:placetype":"venue"
},
  "geometry": {"coordinates":[-79.19644927980001,43.7865028381],"type":"Point"}
}