{
  "type": "Feature",
  "properties": {
    "addr:full":"375 Ch D'Aylmer Aylmer QC J9H 1A5",
    "addr:housenumber":"375",
    "addr:postcode":"j9h 1a5",
    "addr:street":"Ch D'Aylmer",
    "iso:country":"CA",
    "sg:address":"375 Ch D'Aylmer",
    "sg:city":"Aylmer",
    "sg:classifiers":[
        {
            "category":"Banks & Credit Unions",
            "subcategory":"Bank",
            "type":"Services"
        }
    ],
    "sg:phone":"+1 819 684 4952",
    "sg:postcode":"J9H 1A5",
    "sg:province":"QC",
    "wof:name":"Caisses Desjardins",
    "wof:placetype":"venue"
},
  "geometry": {"coordinates":[-75.824608,45.396294],"type":"Point"}
}