{
  "type": "Feature",
  "properties": {
    "addr:full":"186 Rue Lindsay Drummondville QC J2C 1N9",
    "addr:housenumber":"186",
    "addr:postcode":"j2c 1n9",
    "addr:street":"Rue Lindsay",
    "iso:country":"CA",
    "sg:address":"186 Rue Lindsay",
    "sg:city":"Drummondville",
    "sg:classifiers":[
        {
            "category":"Manufacturing",
            "subcategory":"Printing",
            "type":"Manufacturing & Wholesale Goods"
        }
    ],
    "sg:phone":"+1 819 478 4824",
    "sg:postcode":"J2C 1N9",
    "sg:province":"QC",
    "sg:tags":[
        "printer"
    ],
    "wof:name":"Imprimerie Studio Plubicite",
    "wof:placetype":"venue"
},
  "geometry": {"coordinates":[-72.490021,45.884258],"type":"Point"}
}