{
  "type": "Feature",
  "properties": {
    "addr:full":"90 Main St Hillsburgh ON N0B 1Z0",
    "addr:housenumber":"90",
    "addr:postcode":"n0b 1z0",
    "addr:street":"Main St",
    "iso:country":"CA",
    "sg:address":"90 Main St",
    "sg:city":"Hillsburgh",
    "sg:classifiers":[
        {
            "category":"Restaurant",
            "type":"Food & Drink"
        }
    ],
    "sg:phone":"+1 519 855 6378",
    "sg:postcode":"N0B 1Z0",
    "sg:province":"ON",
    "sg:tags":[
        "baker"
    ],
    "wof:name":"Pantry Shelf Bake Shop & Tea",
    "wof:placetype":"venue"
},
  "geometry": {"coordinates":[-80.1431655884,43.7895317078],"type":"Point"}
}