{
  "type": "Feature",
  "properties": {
    "iso:country":"CA",
    "sg:address":"80 Thickson Rd S",
    "sg:city":"Whitby",
    "sg:classifiers":[
        {
            "category":"Food & Beverages",
            "subcategory":"Groceries & Convenience Stores",
            "type":"Retail Goods"
        }
    ],
    "sg:phone":"+1 905 430 2258",
    "sg:postcode":"L1N 7T2",
    "sg:province":"ON",
    "wof:name":"Thickson Convenience Store",
    "wof:placetype":"venue"
},
  "geometry": {"coordinates":[-78.91153,43.882954],"type":"Point"}
}