{
  "type": "Feature",
  "properties": {
    "addr:full":"Sechelt BC V0N 3A0",
    "addr:postcode":"v0n 3a0",
    "iso:country":"CA",
    "sg:city":"Sechelt",
    "sg:classifiers":[
        {
            "category":"Shopping",
            "type":"Retail Goods"
        }
    ],
    "sg:phone":"+1 604 885 6322",
    "sg:postcode":"V0N 3A0",
    "sg:province":"BC",
    "sg:tags":[
        "picture",
        "frame"
    ],
    "wof:name":"Suncoast Gallery",
    "wof:placetype":"venue"
},
  "geometry": {"coordinates":[-123.759552,49.472195],"type":"Point"}
}