{
  "type": "Feature",
  "properties": {
    "addr:full":"41 Covington Rd North York ON M6A 1G2",
    "addr:housenumber":"41",
    "addr:postcode":"m6a 1g2",
    "addr:street":"Covington Rd",
    "iso:country":"CA",
    "sg:address":"41 Covington Rd",
    "sg:city":"North York",
    "sg:classifiers":[
        {
            "category":"Manufacturing",
            "subcategory":"Signs",
            "type":"Manufacturing & Wholesale Goods"
        }
    ],
    "sg:phone":"+1 416 783 1487",
    "sg:postcode":"M6A 1G2",
    "sg:province":"ON",
    "wof:name":"Modern Sign & Engraving CO",
    "wof:placetype":"venue"
},
  "geometry": {"coordinates":[-79.4338378906,43.7200393677],"type":"Point"}
}