{
  "type": "Feature",
  "properties": {
    "addr:full":"2128 4th Ave W Vancouver BC V6K 1N6",
    "addr:housenumber":"2128",
    "addr:postcode":"v6k 1n6",
    "addr:street":"4Th Ave W",
    "iso:country":"CA",
    "sg:address":"2128 4th Ave W",
    "sg:city":"Vancouver",
    "sg:classifiers":[
        {
            "category":"Shopping",
            "subcategory":"Clothing, Apparel, & Fashions",
            "type":"Retail Goods"
        }
    ],
    "sg:phone":"+1 604 732 4455",
    "sg:postcode":"V6K 1N6",
    "sg:province":"BC",
    "wof:name":"Mantique Fashions Ltd",
    "wof:placetype":"venue"
},
  "geometry": {"coordinates":[-123.15351867699999,49.2680549622],"type":"Point"}
}