{
  "type": "Feature",
  "properties": {
    "addr:full":"414 Av Saint-Sacrement Quebec QC G1N 3Y3",
    "addr:postcode":"g1n 3y3",
    "addr:street":"414 Av Saint-Sacrement",
    "iso:country":"CA",
    "sg:address":"414 Av Saint-Sacrement",
    "sg:city":"Quebec",
    "sg:classifiers":[
        {
            "category":"Wholesale",
            "subcategory":"Chemicals & Plastics",
            "type":"Manufacturing & Wholesale Goods"
        }
    ],
    "sg:phone":"+1 418 688 8286",
    "sg:postcode":"G1N 3Y3",
    "sg:province":"QC",
    "sg:tags":[
        "adhesive",
        "glue"
    ],
    "wof:name":"Margna Inc",
    "wof:placetype":"venue"
},
  "geometry": {"coordinates":[-71.2605514526,46.8009223938],"type":"Point"}
}