{
  "type": "Feature",
  "properties": {
    "addr:full":"Lac-Des-Ecorces QC J0W 1H0",
    "addr:postcode":"j0w 1h0",
    "iso:country":"CA",
    "sg:city":"Lac-Des-Ecorces",
    "sg:classifiers":[
        {
            "category":"Food & Beverages",
            "subcategory":"Groceries & Convenience Stores",
            "type":"Retail Goods"
        }
    ],
    "sg:phone":"+1 819 585 2565",
    "sg:postcode":"J0W 1H0",
    "sg:province":"QC",
    "sg:tags":[
        "grocer"
    ],
    "wof:name":"Epicerie Falardeau Enr",
    "wof:placetype":"venue"
},
  "geometry": {"coordinates":[-75.366501,46.55793],"type":"Point"}
}