{
  "type": "Feature",
  "properties": {
    "addr:full":"1938 Bloor St W Toronto ON M6P 3K8",
    "addr:housenumber":"1938",
    "addr:postcode":"m6p 3k8",
    "addr:street":"Bloor St W",
    "iso:country":"CA",
    "sg:address":"1938 Bloor St W",
    "sg:city":"Toronto",
    "sg:classifiers":[
        {
            "category":"Shopping",
            "subcategory":"Pharmacy",
            "type":"Retail Goods"
        }
    ],
    "sg:phone":"+1 416 769 2222",
    "sg:postcode":"M6P 3K8",
    "sg:province":"ON",
    "wof:name":"High Park Pharmacy",
    "wof:placetype":"venue"
},
  "geometry": {"coordinates":[-79.4667510986,43.6533470154],"type":"Point"}
}