{
  "type": "Feature",
  "properties": {
    "addr:full":"4004 Ch Saint-Paul Laterriere QC G7N 1C5",
    "addr:housenumber":"4004",
    "addr:postcode":"g7n 1c5",
    "addr:street":"Ch Saint-Paul Laterriere",
    "iso:country":"CA",
    "sg:address":"4004 Ch Saint-Paul",
    "sg:city":"Laterriere",
    "sg:classifiers":[
        {
            "category":"Building & Trades",
            "subcategory":"Construction",
            "type":"Services"
        }
    ],
    "sg:phone":"+1 418 543 5528",
    "sg:postcode":"G7N 1C5",
    "sg:province":"QC",
    "sg:tags":[
        "general",
        "contractor"
    ],
    "wof:name":"Habitalogik Enr",
    "wof:placetype":"venue"
},
  "geometry": {"coordinates":[-71.1509170532,48.3548316956],"type":"Point"}
}