{
  "type": "Feature",
  "properties": {
    "addr:full":"1150 Denman St Vancouver BC V6G 2M9",
    "addr:housenumber":"1150",
    "addr:postcode":"v6g 2m9",
    "addr:street":"Denman St",
    "iso:country":"CA",
    "sg:address":"1150 Denman St",
    "sg:city":"Vancouver",
    "sg:classifiers":[
        {
            "category":"Travel",
            "subcategory":"Hotels & Motels",
            "type":"Entertainment"
        }
    ],
    "sg:phone":"+1 604 685 2231",
    "sg:postcode":"V6G 2M9",
    "sg:province":"BC",
    "wof:name":"English Bay Apartment Hotel",
    "wof:placetype":"venue"
},
  "geometry": {"coordinates":[-123.14097595200001,49.2876319885],"type":"Point"}
}