{
  "type": "Feature",
  "properties": {
    "addr:full":"237 Dundas St E Toronto ON M5A 1Z7",
    "addr:housenumber":"237",
    "addr:postcode":"m5a 1z7",
    "addr:street":"Dundas St E",
    "iso:country":"CA",
    "sg:address":"237 Dundas St E",
    "sg:city":"Toronto",
    "sg:classifiers":[
        {
            "category":"Professional",
            "subcategory":"Employment Agencies",
            "type":"Services"
        }
    ],
    "sg:phone":"+1 416 892 7368",
    "sg:postcode":"M5A 1Z7",
    "sg:province":"ON",
    "wof:name":"Actsent Enterprises",
    "wof:placetype":"venue"
},
  "geometry": {"coordinates":[-79.37274932859999,43.6578102112],"type":"Point"}
}