{
  "type": "Feature",
  "properties": {
    "addr:full":"2690 Okanagan Ave SE Salmon Arm BC V1E 4N2",
    "addr:housenumber":"2690",
    "addr:postcode":"v1e 4n2",
    "addr:street":"Okanagan Ave Se",
    "iso:country":"CA",
    "sg:address":"2690 Okanagan Ave SE",
    "sg:city":"Salmon Arm",
    "sg:classifiers":[
        {
            "category":"Education",
            "subcategory":"School",
            "type":"Public Place"
        }
    ],
    "sg:phone":"+1 250 832 7021",
    "sg:postcode":"V1E 4N2",
    "sg:province":"BC",
    "wof:name":"Resource Centre",
    "wof:placetype":"venue"
},
  "geometry": {"coordinates":[-119.250229,50.699703],"type":"Point"}
}