{
  "type": "Feature",
  "properties": {
    "iso:country":"CA",
    "sg:address":"NE 2345 6th W of 4",
    "sg:city":"Wainwright",
    "sg:classifiers":[
        {
            "category":"Building & Trades",
            "subcategory":"Construction",
            "type":"Services"
        }
    ],
    "sg:phone":"+1 780 842 3677",
    "sg:postcode":"T9W 1T3",
    "sg:province":"AB",
    "sg:tags":[
        "repairing",
        "remodeling",
        "contractor"
    ],
    "wof:name":"Dng Construction",
    "wof:placetype":"venue"
},
  "geometry": {"coordinates":[-110.852020264,52.8433837891],"type":"Point"}
}