{
  "type": "Feature",
  "properties": {
    "addr:full":"Vancouver BC V5R 5W2",
    "addr:postcode":"v5r 5w2",
    "iso:country":"CA",
    "sg:city":"Vancouver",
    "sg:classifiers":[
        {
            "category":"Organizations",
            "subcategory":"Professional Association",
            "type":"Services"
        }
    ],
    "sg:phone":"+1 604 451 0150",
    "sg:postcode":"V5R 5W2",
    "sg:province":"BC",
    "wof:name":"American Society For Quality",
    "wof:placetype":"venue"
},
  "geometry": {"coordinates":[-123.02438354500001,49.2324142456],"type":"Point"}
}