{
  "type": "Feature",
  "properties": {
    "addr:full":"40 Centre Brighton ON K0K 1H0",
    "addr:housenumber":"40",
    "addr:postcode":"k0k 1h0",
    "addr:street":"Centre",
    "iso:country":"CA",
    "sg:address":"40 Centre",
    "sg:city":"Brighton",
    "sg:classifiers":[
        {
            "category":"Organizations",
            "subcategory":"Religious Organization",
            "type":"Services"
        }
    ],
    "sg:phone":"+1 613 475 1590",
    "sg:postcode":"K0K 1H0",
    "sg:province":"ON",
    "sg:tags":[
        "church"
    ],
    "wof:name":"Holy Angels Parish",
    "wof:placetype":"venue"
},
  "geometry": {"coordinates":[-77.74065400000001,44.037739],"type":"Point"}
}