{
  "type": "Feature",
  "properties": {
    "addr:full":"515 Av Delmar Pointe-Claire QC H9R 4A7",
    "addr:housenumber":"515",
    "addr:postcode":"h9r 4a7",
    "addr:street":"Av Delmar",
    "iso:country":"CA",
    "sg:address":"515 Av Delmar",
    "sg:city":"Pointe-Claire",
    "sg:classifiers":[
        {
            "category":"Manufacturing",
            "subcategory":"Printing",
            "type":"Manufacturing & Wholesale Goods"
        }
    ],
    "sg:phone":"+1 514 694 3044",
    "sg:postcode":"H9R 4A7",
    "sg:province":"QC",
    "sg:tags":[
        "printer"
    ],
    "wof:name":"Imprimerie Litho Excel",
    "wof:placetype":"venue"
},
  "geometry": {"coordinates":[-73.803558,45.46772],"type":"Point"}
}