{
  "type": "Feature",
  "properties": {
    "addr:full":"447 Edward St Rivers MB R0K 1X0",
    "addr:housenumber":"447",
    "addr:postcode":"r0k 1x0",
    "addr:street":"Edward St",
    "iso:country":"CA",
    "sg:address":"447 Edward St",
    "sg:city":"Rivers",
    "sg:classifiers":[
        {
            "category":"Organizations",
            "subcategory":"Religious Organization",
            "type":"Services"
        }
    ],
    "sg:phone":"+1 204 328 7882",
    "sg:postcode":"R0K 1X0",
    "sg:province":"MB",
    "sg:tags":[
        "church"
    ],
    "wof:name":"Rivers Baptist Church",
    "wof:placetype":"venue"
},
  "geometry": {"coordinates":[-100.23764038100001,50.0292854309],"type":"Point"}
}