{
  "type": "Feature",
  "properties": {
    "addr:full":"2095 Caribou St W Moose Jaw SK S6H 4N7",
    "addr:housenumber":"2095",
    "addr:postcode":"s6h 4n7",
    "addr:street":"Caribou St W",
    "iso:country":"CA",
    "sg:address":"2095 Caribou St W",
    "sg:city":"Moose Jaw",
    "sg:classifiers":[
        {
            "category":"Freight",
            "type":"Transportation"
        }
    ],
    "sg:phone":"+1 306 693 2277",
    "sg:postcode":"S6H 4N7",
    "sg:province":"SK",
    "sg:tags":[
        "trucking"
    ],
    "wof:name":"Triple G Carriers",
    "wof:placetype":"venue"
},
  "geometry": {"coordinates":[-105.530693,50.388088],"type":"Point"}
}