{
  "type": "Feature",
  "properties": {
    "addr:full":"22264 10 Hwy Langley BC V2Y 2K6",
    "addr:housenumber":"22264",
    "addr:postcode":"v2y 2k6",
    "addr:street":"10 Hwy",
    "iso:country":"CA",
    "sg:address":"22264 10 Hwy",
    "sg:city":"Langley",
    "sg:classifiers":[
        {
            "category":"Wholesale",
            "subcategory":"Farm Supplies",
            "type":"Manufacturing & Wholesale Goods"
        }
    ],
    "sg:phone":"+1 604 888 6555",
    "sg:postcode":"V2Y 2K6",
    "sg:province":"BC",
    "sg:tags":[
        "bulb",
        "seed"
    ],
    "wof:name":"Van Noort Bulb CO",
    "wof:placetype":"venue"
},
  "geometry": {"coordinates":[-122.673858643,49.1124305725],"type":"Point"}
}