{
  "type": "Feature",
  "properties": {
    "addr:full":"1555 Rue Janelle Drummondville QC J2C 5S5",
    "addr:housenumber":"1555",
    "addr:postcode":"j2c 5s5",
    "addr:street":"Rue Janelle",
    "iso:country":"CA",
    "sg:address":"1555 Rue Janelle",
    "sg:city":"Drummondville",
    "sg:classifiers":[
        {
            "category":"Building & Trades",
            "subcategory":"Construction",
            "type":"Services"
        }
    ],
    "sg:phone":"+1 819 472 2559",
    "sg:postcode":"J2C 5S5",
    "sg:province":"QC",
    "sg:tags":[
        "general",
        "contractor"
    ],
    "wof:name":"Construction Bertrand Dionne",
    "wof:placetype":"venue"
},
  "geometry": {"coordinates":[-72.52175099999999,45.8839],"type":"Point"}
}