{
  "type": "Feature",
  "properties": {
    "addr:full":"11009 89 Ave NW Edmonton AB T6G 0Z7",
    "addr:housenumber":"11009",
    "addr:postcode":"t6g 0z7",
    "addr:street":"89 Ave Nw",
    "iso:country":"CA",
    "sg:address":"11009 89 Ave NW",
    "sg:city":"Edmonton",
    "sg:classifiers":[
        {
            "category":"Organizations",
            "subcategory":"Community Association",
            "type":"Services"
        }
    ],
    "sg:phone":"+1 780 432 1162",
    "sg:postcode":"T6G 0Z7",
    "sg:province":"AB",
    "sg:tags":[
        "sorority",
        "fraternity",
        "fraternal"
    ],
    "wof:name":"Phi Gamma Delta Fraternity",
    "wof:placetype":"venue"
},
  "geometry": {"coordinates":[-113.515480041,53.5246582031],"type":"Point"}
}