{
  "type": "Feature",
  "properties": {
    "addr:full":"50 Boul Cartier O Laval QC H7N 2H4",
    "addr:housenumber":"50",
    "addr:postcode":"h7n 2h4",
    "addr:street":"Boul Cartier O",
    "iso:country":"CA",
    "sg:address":"50 Boul Cartier O",
    "sg:city":"Laval",
    "sg:classifiers":[
        {
            "category":"Autos & Motor Vehicles",
            "subcategory":"Fuel & Gas Station",
            "type":"Retail Goods"
        }
    ],
    "sg:phone":"+1 450 669 0228",
    "sg:postcode":"H7N 2H4",
    "sg:province":"QC",
    "sg:tags":[
        "oil"
    ],
    "wof:name":"Ultramar",
    "wof:placetype":"venue"
},
  "geometry": {"coordinates":[-73.68863677980001,45.5591812134],"type":"Point"}
}