{
  "type": "Feature",
  "properties": {
    "iso:country":"CA",
    "sg:address":"13511 70 St NW",
    "sg:city":"Edmonton",
    "sg:classifiers":[
        {
            "category":"Health Services",
            "subcategory":"Clinic",
            "type":"Services"
        }
    ],
    "sg:phone":"+1 780 475 9355",
    "sg:postcode":"T5C 0K5",
    "sg:province":"AB",
    "sg:tags":[
        "food",
        "diet"
    ],
    "wof:name":"Herbalife Products",
    "wof:placetype":"venue"
},
  "geometry": {"coordinates":[-113.448936,53.597244],"type":"Point"}
}