{
  "type": "Feature",
  "properties": {
    "addr:full":"14743 134 Ave NW Edmonton AB T5L 4S9",
    "addr:housenumber":"14743",
    "addr:postcode":"t5l 4s9",
    "addr:street":"134 Ave Nw",
    "iso:country":"CA",
    "sg:address":"14743 134 Ave NW",
    "sg:city":"Edmonton",
    "sg:classifiers":[
        {
            "category":"Manufacturing",
            "subcategory":"Paper Products",
            "type":"Manufacturing & Wholesale Goods"
        }
    ],
    "sg:phone":"+1 780 452 5681",
    "sg:postcode":"T5L 4S9",
    "sg:province":"AB",
    "sg:tags":[
        "bag"
    ],
    "wof:name":"Western Concord Mfg Ltd",
    "wof:placetype":"venue"
},
  "geometry": {"coordinates":[-113.57498200000001,53.593426],"type":"Point"}
}