{
  "type": "Feature",
  "properties": {
    "addr:full":"6 Rockhaven Dr Halifax NS B3M 1Z9",
    "addr:housenumber":"6",
    "addr:postcode":"b3m 1z9",
    "addr:street":"Rockhaven Dr",
    "iso:country":"CA",
    "sg:address":"6 Rockhaven Dr",
    "sg:city":"Halifax",
    "sg:classifiers":[
        {
            "category":"Professional",
            "subcategory":"Business Services",
            "type":"Services"
        }
    ],
    "sg:phone":"+1 902 443 7851",
    "sg:postcode":"B3M 1Z9",
    "sg:province":"NS",
    "sg:tags":[
        "translator",
        "interpreter"
    ],
    "wof:name":"Adc Spanish Language Svc",
    "wof:placetype":"venue"
},
  "geometry": {"coordinates":[-63.659679,44.679577],"type":"Point"}
}