{
  "type": "Feature",
  "properties": {
    "addr:full":"933 Pacific St Vancouver BC V6Z 2K2",
    "addr:housenumber":"933",
    "addr:postcode":"v6z 2k2",
    "addr:street":"Pacific St",
    "iso:country":"CA",
    "sg:address":"933 Pacific St",
    "sg:city":"Vancouver",
    "sg:classifiers":[
        {
            "category":"Professional",
            "subcategory":"Accounting & Tax Preparation",
            "type":"Services"
        }
    ],
    "sg:phone":"+1 604 681 5482",
    "sg:postcode":"V6Z 2K2",
    "sg:province":"BC",
    "sg:tags":[
        "accountant"
    ],
    "wof:name":"Seims, Barry",
    "wof:placetype":"venue"
},
  "geometry": {"coordinates":[-123.131523132,49.2765541077],"type":"Point"}
}