{
  "type": "Feature",
  "properties": {
    "addr:full":"6355 Boul Maricourt Saint-Hubert QC J3Y 1S8",
    "addr:housenumber":"6355",
    "addr:postcode":"j3y 1s8",
    "addr:street":"Boul Maricourt",
    "iso:country":"CA",
    "sg:address":"6355 Boul Maricourt",
    "sg:city":"Saint-Hubert",
    "sg:classifiers":[
        {
            "category":"Organizations",
            "subcategory":"Labor Organization",
            "type":"Services"
        }
    ],
    "sg:phone":"+1 450 445 2228",
    "sg:postcode":"J3Y 1S8",
    "sg:province":"QC",
    "wof:name":"Syndicat Des Cols Bleus",
    "wof:placetype":"venue"
},
  "geometry": {"coordinates":[-73.4145812988,45.4793930054],"type":"Point"}
}