{
  "type": "Feature",
  "properties": {
    "iso:country":"CA",
    "sg:city":"Lloydminster",
    "sg:classifiers":[
        {
            "category":"Organizations",
            "subcategory":"Religious Organization",
            "type":"Services"
        }
    ],
    "sg:phone":"+1 780 875 8959",
    "sg:postcode":"T9V 0W4",
    "sg:province":"AB",
    "sg:tags":[
        "church"
    ],
    "wof:name":"United Church of Canada",
    "wof:placetype":"venue"
},
  "geometry": {"coordinates":[-110.00564575200001,53.2807922363],"type":"Point"}
}