{
  "type": "Feature",
  "properties": {
    "addr:full":"400 Macalpine Cres Fort Mcmurray AB T9H 4B1",
    "addr:housenumber":"400",
    "addr:postcode":"t9h 4b1",
    "addr:street":"Macalpine Cres",
    "iso:country":"CA",
    "sg:address":"400 Macalpine Cres",
    "sg:city":"Fort Mcmurray",
    "sg:classifiers":[
        {
            "category":"Freight",
            "type":"Transportation"
        }
    ],
    "sg:phone":"+1 780 791 1478",
    "sg:postcode":"T9H 4B1",
    "sg:province":"AB",
    "sg:tags":[
        "trucking"
    ],
    "wof:name":"Duke's Transport Ltd",
    "wof:placetype":"venue"
},
  "geometry": {"coordinates":[-111.344368,56.668186],"type":"Point"}
}