{
  "type": "Feature",
  "properties": {
    "addr:full":"Gilbert Rd 225 Dawson Creek BC V1G 4L1",
    "addr:housenumber":"225",
    "addr:postcode":"v1g 4l1",
    "addr:street":"Gilbert Rd",
    "iso:country":"CA",
    "sg:address":"Gilbert Rd 225",
    "sg:city":"Dawson Creek",
    "sg:classifiers":[
        {
            "category":"Retail",
            "subcategory":"Repair Shop",
            "type":"Services"
        }
    ],
    "sg:phone":"+1 250 782 1446",
    "sg:postcode":"V1G 4L1",
    "sg:province":"BC",
    "sg:tags":[
        "plumbing",
        "drain",
        "cleaning",
        "sewer"
    ],
    "wof:name":"Drain Surgeon",
    "wof:placetype":"venue"
},
  "geometry": {"coordinates":[-120.237060547,55.7617263794],"type":"Point"}
}