{
  "type": "Feature",
  "properties": {
    "addr:full":"16625 Commonage Rd Winfield BC V4V 1B2",
    "addr:housenumber":"16625",
    "addr:postcode":"v4v 1b2",
    "addr:street":"Commonage Rd",
    "iso:country":"CA",
    "sg:address":"16625 Commonage Rd",
    "sg:city":"Winfield",
    "sg:classifiers":[
        {
            "category":"Government",
            "subcategory":"Fire Station",
            "type":"Public Place"
        }
    ],
    "sg:phone":"+1 ",
    "sg:postcode":"V4V 1B2",
    "sg:province":"BC",
    "sg:tags":[
        "department"
    ],
    "wof:name":"Lake Country District Fire",
    "wof:placetype":"venue"
},
  "geometry": {"coordinates":[-119.405601502,50.0245361328],"type":"Point"}
}