{
  "type": "Feature",
  "properties": {
    "addr:full":"447 Rue Montgomery Saint-Sylvestre QC G0S 3C0",
    "addr:housenumber":"447",
    "addr:postcode":"g0s 3c0",
    "addr:street":"Rue Montgomery",
    "iso:country":"CA",
    "sg:address":"447 Rue Montgomery",
    "sg:city":"Saint-Sylvestre",
    "sg:classifiers":[
        {
            "category":"Manufacturing",
            "subcategory":"Lumber",
            "type":"Manufacturing & Wholesale Goods"
        }
    ],
    "sg:phone":"+1 418 596 2748",
    "sg:postcode":"G0S 3C0",
    "sg:province":"QC",
    "sg:tags":[
        "syrup",
        "maple",
        "sugar"
    ],
    "wof:name":"Cabane A Sucre Du Pere Normand",
    "wof:placetype":"venue"
},
  "geometry": {"coordinates":[-71.2620010376,46.3620605469],"type":"Point"}
}