{
  "type": "Feature",
  "properties": {
    "addr:full":"2746 Dufferin St North York ON M6B 3R4",
    "addr:housenumber":"2746",
    "addr:postcode":"m6b 3r4",
    "addr:street":"Dufferin St",
    "iso:country":"CA",
    "sg:address":"2746 Dufferin St",
    "sg:city":"North York",
    "sg:classifiers":[
        {
            "category":"Organizations",
            "subcategory":"Religious Organization",
            "type":"Services"
        }
    ],
    "sg:phone":"+1 416 782 4175",
    "sg:postcode":"M6B 3R4",
    "sg:province":"ON",
    "sg:tags":[
        "church"
    ],
    "wof:name":"Fairbank United Church",
    "wof:placetype":"venue"
},
  "geometry": {"coordinates":[-79.4525146484,43.7032737732],"type":"Point"}
}