{
  "type": "Feature",
  "properties": {
    "iso:country":"CA",
    "sg:address":"12901 Madeira Park Rd",
    "sg:city":"Madeira Park",
    "sg:classifiers":[
        {
            "category":"Restaurant",
            "type":"Food & Drink"
        }
    ],
    "sg:phone":"+1 604 883 9655",
    "sg:postcode":"V0N 2H0",
    "sg:province":"BC",
    "wof:name":"Hamburger Stand in Madeira Pk",
    "wof:placetype":"venue"
},
  "geometry": {"coordinates":[-124.023620605,49.6208534241],"type":"Point"}
}