{
  "type": "Feature",
  "properties": {
    "addr:full":"12901 Madeira Park Rd Madeira Park BC V0N 2H0",
    "addr:housenumber":"12901",
    "addr:postcode":"v0n 2h0",
    "addr:street":"Madeira Park Rd",
    "iso:country":"CA",
    "sg:address":"12901 Madeira Park Rd",
    "sg:city":"Madeira Park",
    "sg:classifiers":[
        {
            "category":"Restaurant",
            "type":"Food & Drink"
        }
    ],
    "sg:phone":"+1 604 883 9655",
    "sg:postcode":"V0N 2H0",
    "sg:province":"BC",
    "wof:name":"Hamburger Stand in Madeira Pk",
    "wof:placetype":"venue"
},
  "geometry": {"coordinates":[-124.023620605,49.6208534241],"type":"Point"}
}