{
  "type": "Feature",
  "properties": {
    "addr:full":"495 Yonge St Barrie ON L4N 4E1",
    "addr:housenumber":"495",
    "addr:postcode":"l4n 4e1",
    "addr:street":"Yonge St",
    "iso:country":"CA",
    "sg:address":"495 Yonge St",
    "sg:city":"Barrie",
    "sg:classifiers":[
        {
            "category":"Retail",
            "subcategory":"Veterinary Services",
            "type":"Services"
        }
    ],
    "sg:phone":"+1 705 726 5031",
    "sg:postcode":"L4N 4E1",
    "sg:province":"ON",
    "sg:tags":[
        "veterinarian"
    ],
    "wof:name":"Aldergrove Animal Clinic Pc",
    "wof:placetype":"venue"
},
  "geometry": {"coordinates":[-79.6570510864,44.362247467],"type":"Point"}
}