{
  "type": "Feature",
  "properties": {
    "addr:full":"6007 54 Ave Taber AB T1G 1X4",
    "addr:housenumber":"6007",
    "addr:postcode":"t1g 1x4",
    "addr:street":"54 Ave",
    "iso:country":"CA",
    "sg:address":"6007 54 Ave",
    "sg:city":"Taber",
    "sg:classifiers":[
        {
            "category":"Building & Trades",
            "subcategory":"Construction",
            "type":"Services"
        }
    ],
    "sg:phone":"+1 403 223 4933",
    "sg:postcode":"T1G 1X4",
    "sg:province":"AB",
    "sg:tags":[
        "excavating",
        "contractor"
    ],
    "wof:name":"J R Trenching",
    "wof:placetype":"venue"
},
  "geometry": {"coordinates":[-112.132446,49.790287],"type":"Point"}
}