{
  "type": "Feature",
  "properties": {
    "addr:full":"RR 5 STN Main Belleville ON K8N 4Z5",
    "addr:postcode":"k8n 4z5",
    "addr:street":"Rr 5 Stn",
    "iso:country":"CA",
    "sg:address":"RR 5 STN Main",
    "sg:city":"Belleville",
    "sg:classifiers":[
        {
            "category":"Building & Trades",
            "subcategory":"Construction",
            "type":"Services"
        }
    ],
    "sg:phone":"+1 613 962 2443",
    "sg:postcode":"K8N 4Z5",
    "sg:province":"ON",
    "sg:tags":[
        "solarium"
    ],
    "wof:name":"Custom Deck & Solarium",
    "wof:placetype":"venue"
},
  "geometry": {"coordinates":[-77.38189697270001,44.1610450745],"type":"Point"}
}