{
  "type": "Feature",
  "properties": {
    "addr:full":"272 Belleville Rd Napanee ON K7R 2R5",
    "addr:housenumber":"272",
    "addr:postcode":"k7r 2r5",
    "addr:street":"Belleville Rd",
    "iso:country":"CA",
    "sg:address":"272 Belleville Rd",
    "sg:city":"Napanee",
    "sg:classifiers":[
        {
            "category":"Restaurant",
            "type":"Food & Drink"
        }
    ],
    "sg:phone":"+1 613 354 0233",
    "sg:postcode":"K7R 2R5",
    "sg:province":"ON",
    "sg:tags":[
        "pizza"
    ],
    "wof:name":"Bubba's Pizzeria & Restaurant",
    "wof:placetype":"venue"
},
  "geometry": {"coordinates":[-76.9612045288,44.2485656738],"type":"Point"}
}