{
  "type": "Feature",
  "properties": {
    "addr:full":"162 Av Marier Vaudreuil-Dorion QC J7V 6V8",
    "addr:postcode":"j7v 6v8",
    "addr:street":"162 Av Marier",
    "iso:country":"CA",
    "sg:address":"162 Av Marier",
    "sg:city":"Vaudreuil-Dorion",
    "sg:classifiers":[
        {
            "category":"Building & Trades",
            "subcategory":"Construction",
            "type":"Services"
        }
    ],
    "sg:phone":"+1 450 455 9726",
    "sg:postcode":"J7V 6V8",
    "sg:province":"QC",
    "sg:tags":[
        "excavating",
        "contractor",
        "general"
    ],
    "wof:name":"Excavations Camara Inc",
    "wof:placetype":"venue"
},
  "geometry": {"coordinates":[-74.0195236206,45.3849716187],"type":"Point"}
}