{
  "type": "Feature",
  "properties": {
    "addr:full":"7101 120 St Delta BC V4E 2A9",
    "addr:housenumber":"7101",
    "addr:postcode":"v4e 2a9",
    "addr:street":"120 St",
    "iso:country":"CA",
    "sg:address":"7101 120 St",
    "sg:city":"Delta",
    "sg:classifiers":[
        {
            "category":"Insurance",
            "subcategory":"Insurance Agent",
            "type":"Services"
        }
    ],
    "sg:phone":"+1 604 594 3441",
    "sg:postcode":"V4E 2A9",
    "sg:province":"BC",
    "wof:name":"Atkinson & Terry Insurance",
    "wof:placetype":"venue"
},
  "geometry": {"coordinates":[-122.890556335,49.1321983337],"type":"Point"}
}