{
  "type": "Feature",
  "properties": {
    "addr:full":"Richmond BC V6Y 2B6",
    "addr:postcode":"v6y 2b6",
    "iso:country":"CA",
    "sg:city":"Richmond",
    "sg:classifiers":[
        {
            "category":"Utilities",
            "subcategory":"Mobile Phone",
            "type":"Services"
        }
    ],
    "sg:phone":"+1 604 276 8177",
    "sg:postcode":"V6Y 2B6",
    "sg:province":"BC",
    "sg:tags":[
        "telephone",
        "cellular"
    ],
    "wof:name":"Cellular One",
    "wof:placetype":"venue"
},
  "geometry": {"coordinates":[-123.136658,49.166374],"type":"Point"}
}