{
  "type": "Feature",
  "properties": {
    "addr:full":"11800 Rue Sherbrooke E Pointe-Aux-Trembles QC H1B 1C4",
    "addr:housenumber":"11800",
    "addr:postcode":"h1b 1c4",
    "addr:street":"Rue Sherbrooke E Pointe-Aux-Trembles",
    "iso:country":"CA",
    "sg:address":"11800 Rue Sherbrooke E",
    "sg:city":"Pointe-Aux-Trembles",
    "sg:classifiers":[
        {
            "category":"Building & Trades",
            "subcategory":"Construction",
            "type":"Services"
        }
    ],
    "sg:phone":"+1 450 973 1249",
    "sg:postcode":"H1B 1C4",
    "sg:province":"QC",
    "sg:tags":[
        "swimming",
        "designer",
        "dealer",
        "pool",
        "greenhouse"
    ],
    "wof:name":"Piscines Trevi Inc",
    "wof:placetype":"venue"
},
  "geometry": {"coordinates":[-73.514755249,45.6403923035],"type":"Point"}
}