{
  "type": "Feature",
  "properties": {
    "addr:full":"46 Argyle St Markdale ON N0C 1H0",
    "addr:housenumber":"46",
    "addr:postcode":"n0c 1h0",
    "addr:street":"Argyle St",
    "iso:country":"CA",
    "sg:address":"46 Argyle St",
    "sg:city":"Markdale",
    "sg:classifiers":[
        {
            "category":"Manufacturing",
            "subcategory":"Printing",
            "type":"Manufacturing & Wholesale Goods"
        }
    ],
    "sg:phone":"+1 519 986 2134",
    "sg:postcode":"N0C 1H0",
    "sg:province":"ON",
    "sg:tags":[
        "printer"
    ],
    "wof:name":"Murray's Print Shop",
    "wof:placetype":"venue"
},
  "geometry": {"coordinates":[-80.6506118774,44.3183784485],"type":"Point"}
}