{
  "type": "Feature",
  "properties": {
    "addr:full":"479 Arklow Dr Dartmouth NS B2W 4S1",
    "addr:housenumber":"479",
    "addr:postcode":"b2w 4s1",
    "addr:street":"Arklow Dr",
    "iso:country":"CA",
    "sg:address":"479 Arklow Dr",
    "sg:city":"Dartmouth",
    "sg:classifiers":[
        {
            "category":"Social Services",
            "subcategory":"Child Care",
            "type":"Services"
        }
    ],
    "sg:phone":"+1 902 462 5964",
    "sg:postcode":"B2W 4S1",
    "sg:province":"NS",
    "wof:name":"Discovery World Day Care Ltd",
    "wof:placetype":"venue"
},
  "geometry": {"coordinates":[-63.483204,44.677971],"type":"Point"}
}