{
  "type": "Feature",
  "properties": {
    "addr:full":"705 Av Du Pont N # 445 Alma QC G8B 6T5",
    "addr:postcode":"g8b 6t5",
    "addr:street":"705 Av Du Pont N # 445",
    "iso:country":"CA",
    "sg:address":"705 Av Du Pont N # 445",
    "sg:city":"Alma",
    "sg:classifiers":[
        {
            "category":"Shopping",
            "subcategory":"Department Store",
            "type":"Retail Goods"
        }
    ],
    "sg:phone":"+1 418 662 0358",
    "sg:postcode":"G8B 6T5",
    "sg:province":"QC",
    "wof:name":"Zellers",
    "wof:placetype":"venue"
},
  "geometry": {"coordinates":[-71.642212,48.56197],"type":"Point"}
}