{
  "type": "Feature",
  "properties": {
    "addr:full":"80 George Henry Blvd North York ON M2J 1E7",
    "addr:housenumber":"80",
    "addr:postcode":"m2j 1e7",
    "addr:street":"George Henry Blvd",
    "iso:country":"CA",
    "sg:address":"80 George Henry Blvd",
    "sg:city":"North York",
    "sg:classifiers":[
        {
            "category":"Education",
            "subcategory":"School",
            "type":"Public Place"
        }
    ],
    "sg:phone":"+1 416 502 1769",
    "sg:postcode":"M2J 1E7",
    "sg:province":"ON",
    "wof:name":"Montessori Education Ctr Ltd",
    "wof:placetype":"venue"
},
  "geometry": {"coordinates":[-79.3507156372,43.7732315063],"type":"Point"}
}