{
  "type": "Feature",
  "properties": {
    "addr:full":"90 Belfield Rd Etobicoke ON M9W 1G4",
    "addr:housenumber":"90",
    "addr:postcode":"m9w 1g4",
    "addr:street":"Belfield Rd",
    "iso:country":"CA",
    "sg:address":"90 Belfield Rd",
    "sg:city":"Etobicoke",
    "sg:classifiers":[
        {
            "category":"Manufacturing",
            "subcategory":"Tools & Machinery",
            "type":"Manufacturing & Wholesale Goods"
        }
    ],
    "sg:phone":"+1 416 249 9171",
    "sg:postcode":"M9W 1G4",
    "sg:province":"ON",
    "sg:tags":[
        "equipment",
        "electric"
    ],
    "wof:name":"S & C Electric Canada Ltd",
    "wof:placetype":"venue"
},
  "geometry": {"coordinates":[-79.5710601807,43.7031555176],"type":"Point"}
}