{
  "type": "Feature",
  "properties": {
    "addr:full":"10009 98th St Grande Cache AB T0E 0Y0",
    "addr:housenumber":"10009",
    "addr:postcode":"t0e 0y0",
    "addr:street":"98Th St",
    "iso:country":"CA",
    "sg:address":"10009 98th St",
    "sg:city":"Grande Cache",
    "sg:classifiers":[
        {
            "category":"Freight",
            "type":"Transportation"
        }
    ],
    "sg:phone":"+1 780 827 5353",
    "sg:postcode":"T0E 0Y0",
    "sg:province":"AB",
    "sg:tags":[
        "trucking"
    ],
    "wof:name":"E & L Trucking",
    "wof:placetype":"venue"
},
  "geometry": {"coordinates":[-119.109649658,53.889995575],"type":"Point"}
}