{
  "type": "Feature",
  "properties": {
    "iso:country":"CA",
    "sg:address":"PO Box 147",
    "sg:city":"Harrowsmith",
    "sg:classifiers":[
        {
            "category":"Organizations",
            "subcategory":"Religious Organization",
            "type":"Services"
        }
    ],
    "sg:phone":"+1 613 372 2525",
    "sg:postcode":"K0H 1V0",
    "sg:province":"ON",
    "sg:tags":[
        "church"
    ],
    "wof:name":"Harrowsmith United Church",
    "wof:placetype":"venue"
},
  "geometry": {"coordinates":[-76.66557312010001,44.4049949646],"type":"Point"}
}