{
  "type": "Feature",
  "properties": {
    "addr:full":"Hotsprings Rd Nakusp BC V0G 1R0",
    "addr:postcode":"v0g 1r0",
    "addr:street":"Hotsprings Rd",
    "iso:country":"CA",
    "sg:address":"Hotsprings Rd",
    "sg:city":"Nakusp",
    "sg:classifiers":[
        {
            "category":"Airline",
            "type":"Transportation"
        }
    ],
    "sg:phone":"+1 250 265 3434",
    "sg:postcode":"V0G 1R0",
    "sg:province":"BC",
    "sg:tags":[
        "helicopter",
        "aircraft",
        "tours",
        "charter",
        "maintenance"
    ],
    "wof:name":"Highland Helicopters Ltd",
    "wof:placetype":"venue"
},
  "geometry": {"coordinates":[-117.808784,50.259754],"type":"Point"}
}