{
  "type": "Feature",
  "properties": {
    "addr:full":"Lachine QC H8T 3E4",
    "addr:postcode":"h8t 3e4",
    "iso:country":"CA",
    "sg:city":"Lachine",
    "sg:classifiers":[
        {
            "category":"Building & Trades",
            "subcategory":"Construction",
            "type":"Services"
        }
    ],
    "sg:phone":"+1 514 631 7999",
    "sg:postcode":"H8T 3E4",
    "sg:province":"QC",
    "sg:tags":[
        "general",
        "contractor"
    ],
    "wof:name":"Construction Reliance-Canada",
    "wof:placetype":"venue"
},
  "geometry": {"coordinates":[-73.7019119263,45.4565963745],"type":"Point"}
}