{
  "type": "Feature",
  "properties": {
    "iso:country":"CA",
    "sg:address":"2651 County Rd 12",
    "sg:city":"Essex",
    "sg:classifiers":[
        {
            "category":"Education",
            "subcategory":"School",
            "type":"Public Place"
        }
    ],
    "sg:phone":"+1 519 776 8118",
    "sg:postcode":"N8M 2X6",
    "sg:province":"ON",
    "wof:name":"Colchester North Public School",
    "wof:placetype":"venue"
},
  "geometry": {"coordinates":[-82.8196716309,42.1728248596],"type":"Point"}
}