{
  "type": "Feature",
  "properties": {
    "addr:full":"1 Queen St Charlottetown PE C1A 4A2",
    "addr:housenumber":"1",
    "addr:postcode":"c1a 4a2",
    "addr:street":"Queen St",
    "iso:country":"CA",
    "sg:address":"1 Queen St",
    "sg:city":"Charlottetown",
    "sg:classifiers":[
        {
            "category":"Government",
            "subcategory":"Office",
            "type":"Public Place"
        }
    ],
    "sg:phone":"+1 902 566 7996",
    "sg:postcode":"C1A 4A2",
    "sg:province":"PE",
    "wof:name":"Pei Shellfish Leasing",
    "wof:placetype":"venue"
},
  "geometry": {"coordinates":[-63.123692,46.230923],"type":"Point"}
}