{
  "type": "Feature",
  "properties": {
    "addr:full":"354 Elizabeth St # B Guelph ON N1E 2X7",
    "addr:housenumber":"354",
    "addr:postcode":"n1e 2x7",
    "addr:street":"Elizabeth St # B",
    "iso:country":"CA",
    "sg:address":"354 Elizabeth St # B",
    "sg:city":"Guelph",
    "sg:classifiers":[
        {
            "category":"Retail",
            "subcategory":"Auto Repair",
            "type":"Services"
        }
    ],
    "sg:phone":"+1 519 763 6457",
    "sg:postcode":"N1E 2X7",
    "sg:province":"ON",
    "sg:tags":[
        "body",
        "automobile",
        "painting"
    ],
    "wof:name":"International Auto Body Floor",
    "wof:placetype":"venue"
},
  "geometry": {"coordinates":[-80.23095703120001,43.5552177429],"type":"Point"}
}