{
  "type": "Feature",
  "properties": {
    "addr:full":"47 Cedar St Cambridge ON N1S 1V4",
    "addr:housenumber":"47",
    "addr:postcode":"n1s 1v4",
    "addr:street":"Cedar St",
    "iso:country":"CA",
    "sg:address":"47 Cedar St",
    "sg:city":"Cambridge",
    "sg:classifiers":[
        {
            "category":"Home & Garden",
            "subcategory":"Household Appliances",
            "type":"Retail Goods"
        }
    ],
    "sg:phone":"+1 519 621 6350",
    "sg:postcode":"N1S 1V4",
    "sg:province":"ON",
    "wof:name":"Halstead's Used Appliances",
    "wof:placetype":"venue"
},
  "geometry": {"coordinates":[-80.3212585449,43.3527107239],"type":"Point"}
}