{
  "type": "Feature",
  "properties": {
    "addr:full":"11 Victoria Ave Belleville ON K8N 1Z5",
    "addr:housenumber":"11",
    "addr:postcode":"k8n 1z5",
    "addr:street":"Victoria Ave",
    "iso:country":"CA",
    "sg:address":"11 Victoria Ave",
    "sg:city":"Belleville",
    "sg:classifiers":[
        {
            "category":"Social Services",
            "type":"Services"
        }
    ],
    "sg:phone":"+1 613 966 8833",
    "sg:postcode":"K8N 1Z5",
    "sg:province":"ON",
    "sg:tags":[
        "organization",
        "welfare"
    ],
    "wof:name":"Canadian National Institute",
    "wof:placetype":"venue"
},
  "geometry": {"coordinates":[-77.384888,44.16626],"type":"Point"}
}