{
  "type": "Feature",
  "properties": {
    "addr:full":"Royal Pl Gerald SK S0A 1B0",
    "addr:postcode":"s0a 1b0",
    "addr:street":"Royal Pl",
    "iso:country":"CA",
    "sg:address":"Royal Pl",
    "sg:city":"Gerald",
    "sg:classifiers":[
        {
            "category":"Building & Trades",
            "subcategory":"Electrical",
            "type":"Services"
        }
    ],
    "sg:phone":"+1 306 745 6547",
    "sg:postcode":"S0A 1B0",
    "sg:province":"SK",
    "sg:tags":[
        "electric",
        "contractor"
    ],
    "wof:name":"Doug's Electric",
    "wof:placetype":"venue"
},
  "geometry": {"coordinates":[-101.789794922,50.6668434143],"type":"Point"}
}