{
  "type": "Feature",
  "properties": {
    "iso:country":"CA",
    "sg:city":"Calgary",
    "sg:classifiers":[
        {
            "category":"Shopping",
            "subcategory":"Photographic Equipment",
            "type":"Retail Goods"
        }
    ],
    "sg:phone":"+1 403 270 0922",
    "sg:postcode":"T2E 6S7",
    "sg:province":"AB",
    "wof:name":"Phototech Camera Repair Svc",
    "wof:placetype":"venue"
},
  "geometry": {"coordinates":[-114.053665161,51.0871086121],"type":"Point"}
}