{
  "type": "Feature",
  "properties": {
    "addr:full":"49 Coldwater Rd North York ON M3B 1Y8",
    "addr:housenumber":"49",
    "addr:postcode":"m3b 1y8",
    "addr:street":"Coldwater Rd",
    "iso:country":"CA",
    "sg:address":"49 Coldwater Rd",
    "sg:city":"North York",
    "sg:classifiers":[
        {
            "category":"Wholesale",
            "subcategory":"Electrical",
            "type":"Manufacturing & Wholesale Goods"
        }
    ],
    "sg:phone":"+1 416 445 2001",
    "sg:postcode":"M3B 1Y8",
    "sg:province":"ON",
    "sg:tags":[
        "alarm",
        "burglar",
        "system"
    ],
    "wof:name":"Alarm Force Industries Inc",
    "wof:placetype":"venue"
},
  "geometry": {"coordinates":[-79.35939,43.754913],"type":"Point"}
}