{
  "type": "Feature",
  "properties": {
    "addr:full":"320 Rue Saint-Jacques Saint-Jean-Sur-Richelieu QC J3B 2L4",
    "addr:housenumber":"320",
    "addr:postcode":"j3b 2l4",
    "addr:street":"Rue Saint-Jacques",
    "iso:country":"CA",
    "sg:address":"320 Rue Saint-Jacques",
    "sg:city":"Saint-Jean-Sur-Richelieu",
    "sg:classifiers":[
        {
            "category":"Home & Garden",
            "subcategory":"Household Appliances",
            "type":"Retail Goods"
        }
    ],
    "sg:phone":"+1 450 347 4993",
    "sg:postcode":"J3B 2L4",
    "sg:province":"QC",
    "wof:name":"Dextraze Service",
    "wof:placetype":"venue"
},
  "geometry": {"coordinates":[-73.262337,45.30592],"type":"Point"}
}