{
  "type": "Feature",
  "properties": {
    "addr:full":"Bedford QC J0J 1A0",
    "addr:postcode":"j0j 1a0",
    "iso:country":"CA",
    "sg:city":"Bedford",
    "sg:classifiers":[
        {
            "category":"Government",
            "subcategory":"Office",
            "type":"Public Place"
        }
    ],
    "sg:phone":"+1 450 248 3333",
    "sg:postcode":"J0J 1A0",
    "sg:province":"QC",
    "sg:tags":[
        "village"
    ],
    "wof:name":"Bedford Protection Civile",
    "wof:placetype":"venue"
},
  "geometry": {"coordinates":[-72.985985,45.119801],"type":"Point"}
}