{
  "type": "Feature",
  "properties": {
    "addr:full":"9303 82A Ave Fort St John BC V1J 6S2",
    "addr:housenumber":"9303",
    "addr:postcode":"v1j 6s2",
    "addr:street":"82A Ave",
    "iso:country":"CA",
    "sg:address":"9303 82A Ave",
    "sg:city":"Fort St John",
    "sg:classifiers":[
        {
            "category":"Freight",
            "type":"Transportation"
        }
    ],
    "sg:phone":"+1 250 787 0398",
    "sg:postcode":"V1J 6S2",
    "sg:province":"BC",
    "sg:tags":[
        "trucking"
    ],
    "wof:name":"Fedderly Transportation Ltd",
    "wof:placetype":"venue"
},
  "geometry": {"coordinates":[-120.847458,56.252464],"type":"Point"}
}