{
  "type": "Feature",
  "properties": {
    "iso:country":"CA",
    "sg:address":"2145 Summerfield Blvd SE",
    "sg:city":"Airdrie",
    "sg:classifiers":[
        {
            "category":"Food & Beverages",
            "subcategory":"Groceries & Convenience Stores",
            "type":"Retail Goods"
        }
    ],
    "sg:phone":"+1 403 948 3507",
    "sg:postcode":"T4B 1X5",
    "sg:province":"AB",
    "wof:name":"Mac's Convenience Stores Ltd",
    "wof:placetype":"venue"
},
  "geometry": {"coordinates":[-114.01097106900001,51.2736625671],"type":"Point"}
}