{
  "type": "Feature",
  "properties": {
    "addr:full":"6095 Dunn St Niagara Falls ON L2G 2P3",
    "addr:housenumber":"6095",
    "addr:postcode":"l2g 2p3",
    "addr:street":"Dunn St",
    "iso:country":"CA",
    "sg:address":"6095 Dunn St",
    "sg:city":"Niagara Falls",
    "sg:classifiers":[
        {
            "category":"Autos & Motor Vehicles",
            "subcategory":"Auto Supplies",
            "type":"Retail Goods"
        }
    ],
    "sg:phone":"+1 905 356 4414",
    "sg:postcode":"L2G 2P3",
    "sg:province":"ON",
    "sg:tags":[
        "automobile",
        "parts"
    ],
    "wof:name":"Collee Automotive Supplies Ltd",
    "wof:placetype":"venue"
},
  "geometry": {"coordinates":[-79.094887,43.078823],"type":"Point"}
}