{
  "type": "Feature",
  "properties": {
    "addr:full":"3145 Gladwin Rd Abbotsford BC V2T 5T4",
    "addr:housenumber":"3145",
    "addr:postcode":"v2t 5t4",
    "addr:street":"Gladwin Rd",
    "iso:country":"CA",
    "sg:address":"3145 Gladwin Rd",
    "sg:city":"Abbotsford",
    "sg:classifiers":[
        {
            "category":"Education",
            "subcategory":"Special Training",
            "type":"Public Place"
        }
    ],
    "sg:phone":"+1 604 854 8160",
    "sg:postcode":"V2T 5T4",
    "sg:province":"BC",
    "sg:tags":[
        "school",
        "tutoring",
        "language"
    ],
    "wof:name":"Gladwin Language Ctr",
    "wof:placetype":"venue"
},
  "geometry": {"coordinates":[-122.31607099999999,49.058956],"type":"Point"}
}