{
  "type": "Feature",
  "properties": {
    "addr:full":"Saskatoon SK S7K 7G9",
    "addr:postcode":"s7k 7g9",
    "iso:country":"CA",
    "sg:city":"Saskatoon",
    "sg:classifiers":[
        {
            "category":"Wholesale",
            "subcategory":"Electrical",
            "type":"Manufacturing & Wholesale Goods"
        }
    ],
    "sg:phone":"+1 306 665 2852",
    "sg:postcode":"S7K 7G9",
    "sg:province":"SK",
    "sg:tags":[
        "light",
        "tube",
        "lighting",
        "bulb"
    ],
    "wof:name":"Lite Mor Distributors",
    "wof:placetype":"venue"
},
  "geometry": {"coordinates":[-106.646247864,52.1843681335],"type":"Point"}
}