{
  "type": "Feature",
  "properties": {
    "addr:full":"Mississauga ON L4W 4N5",
    "addr:postcode":"l4w 4n5",
    "iso:country":"CA",
    "sg:city":"Mississauga",
    "sg:classifiers":[
        {
            "category":"Wholesale",
            "subcategory":"Durable Goods & Equipment",
            "type":"Manufacturing & Wholesale Goods"
        }
    ],
    "sg:phone":"+1 905 212 1550",
    "sg:postcode":"L4W 4N5",
    "sg:province":"ON",
    "sg:tags":[
        "exporter"
    ],
    "wof:name":"Cecor Inc",
    "wof:placetype":"venue"
},
  "geometry": {"coordinates":[-79.6438217163,43.6307373047],"type":"Point"}
}