{
  "type": "Feature",
  "properties": {
    "addr:full":"26821 Old Yale Rd Aldergrove BC V4W 3E4",
    "addr:housenumber":"26821",
    "addr:postcode":"v4w 3e4",
    "addr:street":"Old Yale Rd",
    "iso:country":"CA",
    "sg:address":"26821 Old Yale Rd",
    "sg:city":"Aldergrove",
    "sg:classifiers":[
        {
            "category":"Building & Trades",
            "subcategory":"Equipment Rental",
            "type":"Services"
        }
    ],
    "sg:phone":"+1 604 856 7745",
    "sg:postcode":"V4W 3E4",
    "sg:province":"BC",
    "sg:tags":[
        "contractor"
    ],
    "wof:name":"Aldergrove Eze Rent-It Ctr",
    "wof:placetype":"venue"
},
  "geometry": {"coordinates":[-122.480812,49.059189],"type":"Point"}
}