{
  "type": "Feature",
  "properties": {
    "addr:full":"Dorval QC H9S 2B6",
    "addr:postcode":"h9s 2b6",
    "iso:country":"CA",
    "sg:city":"Dorval",
    "sg:classifiers":[
        {
            "category":"Professional",
            "subcategory":"Management & Consulting",
            "type":"Services"
        }
    ],
    "sg:phone":"+1 514 636 5351",
    "sg:postcode":"H9S 2B6",
    "sg:province":"QC",
    "sg:tags":[
        "employee",
        "consultant",
        "benefit"
    ],
    "wof:name":"Armstrong-Mc Cready Inc",
    "wof:placetype":"venue"
},
  "geometry": {"coordinates":[-73.7354049683,45.4398727417],"type":"Point"}
}