{
  "type": "Feature",
  "properties": {
    "addr:full":"Richard Lake Dr Sudbury ON P3E 4N1",
    "addr:postcode":"p3e 4n1",
    "addr:street":"Richard Lake Dr",
    "iso:country":"CA",
    "sg:address":"Richard Lake Dr",
    "sg:city":"Sudbury",
    "sg:classifiers":[
        {
            "category":"Travel",
            "subcategory":"Campground",
            "type":"Entertainment"
        }
    ],
    "sg:phone":"+1 705 522 8471",
    "sg:postcode":"P3E 4N1",
    "sg:province":"ON",
    "wof:name":"Ukrainian National Federation",
    "wof:placetype":"venue"
},
  "geometry": {"coordinates":[-80.920998,46.432171],"type":"Point"}
}