{
  "type": "Feature",
  "properties": {
    "addr:full":"Freelton ON L0R 1K0",
    "addr:postcode":"l0r 1k0",
    "iso:country":"CA",
    "sg:city":"Freelton",
    "sg:classifiers":[
        {
            "category":"Retail",
            "subcategory":"Animal Services",
            "type":"Services"
        }
    ],
    "sg:phone":"+1 905 659 2532",
    "sg:postcode":"L0R 1K0",
    "sg:province":"ON",
    "sg:tags":[
        "pet",
        "boarding",
        "sitting"
    ],
    "wof:name":"Country Haven Kennels",
    "wof:placetype":"venue"
},
  "geometry": {"coordinates":[-80.0391464233,43.4004554749],"type":"Point"}
}