{
  "type": "Feature",
  "properties": {
    "addr:full":"22 Davidson St Barrie ON L4M 3R8",
    "addr:housenumber":"22",
    "addr:postcode":"l4m 3r8",
    "addr:street":"Davidson St",
    "iso:country":"CA",
    "sg:address":"22 Davidson St",
    "sg:city":"Barrie",
    "sg:classifiers":[
        {
            "category":"Education",
            "subcategory":"School",
            "type":"Public Place"
        }
    ],
    "sg:phone":"+1 705 728 3307",
    "sg:postcode":"L4M 3R8",
    "sg:province":"ON",
    "wof:name":"Oakley Park School",
    "wof:placetype":"venue"
},
  "geometry": {"coordinates":[-79.6880493164,44.3995285034],"type":"Point"}
}