{
  "type": "Feature",
  "properties": {
    "addr:full":"Sherwood Park AB T8A 3H9",
    "addr:postcode":"t8a 3h9",
    "iso:country":"CA",
    "sg:city":"Sherwood Park",
    "sg:classifiers":[
        {
            "category":"Building & Trades",
            "subcategory":"Cleaning & Sanitation",
            "type":"Services"
        }
    ],
    "sg:phone":"+1 780 467 4849",
    "sg:postcode":"T8A 3H9",
    "sg:province":"AB",
    "sg:tags":[
        "steam",
        "maintenance"
    ],
    "wof:name":"Aqua Clean Mobile Wash Svc",
    "wof:placetype":"venue"
},
  "geometry": {"coordinates":[-113.295417786,53.5296707153],"type":"Point"}
}