{
  "type": "Feature",
  "properties": {
    "addr:full":"5604 103A St NW Edmonton AB T6H 2J5",
    "addr:housenumber":"5604",
    "addr:postcode":"t6h 2j5",
    "addr:street":"103A St Nw",
    "iso:country":"CA",
    "sg:address":"5604 103A St NW",
    "sg:city":"Edmonton",
    "sg:classifiers":[
        {
            "category":"Manufacturing",
            "subcategory":"Glass & Minerals",
            "type":"Manufacturing & Wholesale Goods"
        }
    ],
    "sg:phone":"+1 780 432 0972",
    "sg:postcode":"T6H 2J5",
    "sg:province":"AB",
    "sg:tags":[
        "top",
        "counter",
        "marble"
    ],
    "wof:name":"Allstone Inc",
    "wof:placetype":"venue"
},
  "geometry": {"coordinates":[-113.494598,53.493301],"type":"Point"}
}