{
  "type": "Feature",
  "properties": {
    "iso:country":"CA",
    "sg:address":"1225 Wonderland Rd N",
    "sg:city":"London",
    "sg:classifiers":[
        {
            "category":"Shopping",
            "subcategory":"Jewelry",
            "type":"Retail Goods"
        }
    ],
    "sg:phone":"+1 519 473 6300",
    "sg:postcode":"N6G 2V9",
    "sg:province":"ON",
    "sg:tags":[
        "jeweler"
    ],
    "wof:name":"Western Jewellery of Ontario",
    "wof:placetype":"venue"
},
  "geometry": {"coordinates":[-81.303558,43.005066],"type":"Point"}
}