{
  "type": "Feature",
  "properties": {
    "addr:full":"6211 39 Ave Stettler AB T0C 2L1",
    "addr:housenumber":"6211",
    "addr:postcode":"t0c 2l1",
    "addr:street":"39 Ave",
    "iso:country":"CA",
    "sg:address":"6211 39 Ave",
    "sg:city":"Stettler",
    "sg:classifiers":[
        {
            "category":"Building & Trades",
            "subcategory":"Electrical",
            "type":"Services"
        }
    ],
    "sg:phone":"+1 403 742 2013",
    "sg:postcode":"T0C 2L1",
    "sg:province":"AB",
    "sg:tags":[
        "electric",
        "contractor"
    ],
    "wof:name":"Triple G Electric",
    "wof:placetype":"venue"
},
  "geometry": {"coordinates":[-112.72751599999999,52.312347],"type":"Point"}
}