{
  "type": "Feature",
  "properties": {
    "addr:full":"Westbank BC V4T 2E9",
    "addr:postcode":"v4t 2e9",
    "iso:country":"CA",
    "sg:city":"Westbank",
    "sg:classifiers":[
        {
            "category":"Utilities",
            "subcategory":"Mobile Phone",
            "type":"Services"
        }
    ],
    "sg:phone":"+1 250 768 8843",
    "sg:postcode":"V4T 2E9",
    "sg:province":"BC",
    "sg:tags":[
        "telephone",
        "cellular"
    ],
    "wof:name":"Tac Mobility",
    "wof:placetype":"venue"
},
  "geometry": {"coordinates":[-119.62958500000001,49.828381],"type":"Point"}
}