{
  "type": "Feature",
  "properties": {
    "addr:full":"280 Main St Wellington ON K0K 3L0",
    "addr:housenumber":"280",
    "addr:postcode":"k0k 3l0",
    "addr:street":"Main St",
    "iso:country":"CA",
    "sg:address":"280 Main St",
    "sg:city":"Wellington",
    "sg:classifiers":[
        {
            "category":"Restaurant",
            "type":"Food & Drink"
        }
    ],
    "sg:phone":"+1 613 399 3432",
    "sg:postcode":"K0K 3L0",
    "sg:province":"ON",
    "wof:name":"Wellington Grill",
    "wof:placetype":"venue"
},
  "geometry": {"coordinates":[-77.3494567871,43.9518127441],"type":"Point"}
}