{
  "type": "Feature",
  "properties": {
    "addr:full":"988 Broadway W Vancouver BC V5Z 1K7",
    "addr:housenumber":"988",
    "addr:postcode":"v5z 1k7",
    "addr:street":"Broadway W",
    "iso:country":"CA",
    "sg:address":"988 Broadway W",
    "sg:city":"Vancouver",
    "sg:classifiers":[
        {
            "category":"Shopping",
            "subcategory":"Clothing, Apparel, & Fashions",
            "type":"Retail Goods"
        }
    ],
    "sg:phone":"+1 604 732 5822",
    "sg:postcode":"V5Z 1K7",
    "sg:province":"BC",
    "sg:tags":[
        "tailor"
    ],
    "wof:name":"Mike's Tailor & Drycleaning",
    "wof:placetype":"venue"
},
  "geometry": {"coordinates":[-123.126175,49.263271],"type":"Point"}
}