{
  "type": "Feature",
  "properties": {
    "addr:full":"1147 Varsity Estates Rise NW Calgary AB T3B 2V9",
    "addr:housenumber":"1147",
    "addr:postcode":"t3b 2v9",
    "addr:street":"Varsity Estates Rise Nw",
    "iso:country":"CA",
    "sg:address":"1147 Varsity Estates Rise NW",
    "sg:city":"Calgary",
    "sg:classifiers":[
        {
            "category":"Real Estate",
            "subcategory":"Real Estate Agent",
            "type":"Services"
        }
    ],
    "sg:phone":"+1 403 247 6165",
    "sg:postcode":"T3B 2V9",
    "sg:province":"AB",
    "sg:tags":[
        "consultant"
    ],
    "wof:name":"Canmar Services",
    "wof:placetype":"venue"
},
  "geometry": {"coordinates":[-114.16795349100001,51.1006546021],"type":"Point"}
}