{
  "type": "Feature",
  "properties": {
    "addr:full":"668 Brunswick St Fredericton NB E3B 1H6",
    "addr:housenumber":"668",
    "addr:postcode":"e3b 1h6",
    "addr:street":"Brunswick St",
    "iso:country":"CA",
    "sg:address":"668 Brunswick St",
    "sg:city":"Fredericton",
    "sg:classifiers":[
        {
            "category":"Museum",
            "type":"Entertainment"
        }
    ],
    "sg:phone":"+1 506 457 2340",
    "sg:postcode":"E3B 1H6",
    "sg:province":"NB",
    "wof:name":"Science East Inc",
    "wof:placetype":"venue"
},
  "geometry": {"coordinates":[-66.6392211914,45.9586105347],"type":"Point"}
}