{
  "type": "Feature",
  "properties": {
    "addr:full":"585 Lakeshore Rd E Mississauga ON L5G 1H9",
    "addr:housenumber":"585",
    "addr:postcode":"l5g 1h9",
    "addr:street":"Lakeshore Rd E",
    "iso:country":"CA",
    "sg:address":"585 Lakeshore Rd E",
    "sg:city":"Mississauga",
    "sg:classifiers":[
        {
            "category":"Food & Beverages",
            "subcategory":"Groceries & Convenience Stores",
            "type":"Retail Goods"
        }
    ],
    "sg:phone":"+1 905 274 3996",
    "sg:postcode":"L5G 1H9",
    "sg:province":"ON",
    "sg:tags":[
        "grocer"
    ],
    "wof:name":"J H Convenience Store",
    "wof:placetype":"venue"
},
  "geometry": {"coordinates":[-79.56814575200001,43.5682830811],"type":"Point"}
}