{
  "type": "Feature",
  "properties": {
    "iso:country":"CA",
    "sg:city":"Kamloops",
    "sg:classifiers":[
        {
            "category":"Personal",
            "subcategory":"Beauty Salon",
            "type":"Services"
        }
    ],
    "sg:phone":"+1 250 374 1236",
    "sg:postcode":"V2C 4N6",
    "sg:province":"BC",
    "sg:tags":[
        "hair",
        "good",
        "supply"
    ],
    "wof:name":"Classy Cuts",
    "wof:placetype":"venue"
},
  "geometry": {"coordinates":[-120.272079,50.678658],"type":"Point"}
}