{
  "type": "Feature",
  "properties": {
    "iso:country":"CA",
    "sg:address":"5 Elliott St",
    "sg:city":"London",
    "sg:classifiers":[
        {
            "category":"Wholesale",
            "subcategory":"Medical Equipment & Supplies",
            "type":"Manufacturing & Wholesale Goods"
        }
    ],
    "sg:phone":"+1 519 672 8759",
    "sg:postcode":"N5Y 2E1",
    "sg:province":"ON",
    "sg:tags":[
        "dental"
    ],
    "wof:name":"Henry Schein Arcona",
    "wof:placetype":"venue"
},
  "geometry": {"coordinates":[-81.232269,43.002064],"type":"Point"}
}