{
  "type": "Feature",
  "properties": {
    "addr:full":"3864 Quarry Rd Beamsville ON L0R 1B2",
    "addr:housenumber":"3864",
    "addr:postcode":"l0r 1b2",
    "addr:street":"Quarry Rd",
    "iso:country":"CA",
    "sg:address":"3864 Quarry Rd",
    "sg:city":"Beamsville",
    "sg:classifiers":[
        {
            "category":"Building & Trades",
            "subcategory":"Construction",
            "type":"Services"
        }
    ],
    "sg:phone":"+1 905 641 0161",
    "sg:postcode":"L0R 1B2",
    "sg:province":"ON",
    "sg:tags":[
        "contractor",
        "general"
    ],
    "wof:name":"Quarrystone Construction Ltd",
    "wof:placetype":"venue"
},
  "geometry": {"coordinates":[-79.455414,43.147396],"type":"Point"}
}