{
  "type": "Feature",
  "properties": {
    "addr:full":"1485 Rue Des Marguerites Plessisville QC G6L 3P3",
    "addr:housenumber":"1485",
    "addr:postcode":"g6l 3p3",
    "addr:street":"Rue Des Marguerites",
    "iso:country":"CA",
    "sg:address":"1485 Rue Des Marguerites",
    "sg:city":"Plessisville",
    "sg:classifiers":[
        {
            "category":"Building & Trades",
            "subcategory":"Electrical",
            "type":"Services"
        }
    ],
    "sg:phone":"+1 819 362 3928",
    "sg:postcode":"G6L 3P3",
    "sg:province":"QC",
    "sg:tags":[
        "electric",
        "contractor"
    ],
    "wof:name":"Entreprises Brindle Electrique",
    "wof:placetype":"venue"
},
  "geometry": {"coordinates":[-71.76020812989999,46.2084465027],"type":"Point"}
}