{
  "type": "Feature",
  "properties": {
    "addr:full":"9215 40 St SE Calgary AB T2C 4Z5",
    "addr:housenumber":"9215",
    "addr:postcode":"t2c 4z5",
    "addr:street":"40 St Se",
    "iso:country":"CA",
    "sg:address":"9215 40 St SE",
    "sg:city":"Calgary",
    "sg:classifiers":[
        {
            "category":"Wholesale",
            "subcategory":"Construction Materials",
            "type":"Manufacturing & Wholesale Goods"
        }
    ],
    "sg:phone":"+1 403 280 0790",
    "sg:postcode":"T2C 4Z5",
    "sg:province":"AB",
    "sg:tags":[
        "lumber"
    ],
    "wof:name":"Evans-Tedham Lumber",
    "wof:placetype":"venue"
},
  "geometry": {"coordinates":[-113.97605133099999,50.9692268372],"type":"Point"}
}