{
  "type": "Feature",
  "properties": {
    "addr:full":"3 Ch DE LA Serme Messines QC J0X 2J0",
    "addr:housenumber":"3",
    "addr:postcode":"j0x 2j0",
    "addr:street":"Ch De La Serme",
    "iso:country":"CA",
    "sg:address":"3 Ch DE LA Serme",
    "sg:city":"Messines",
    "sg:classifiers":[
        {
            "category":"Government",
            "subcategory":"Office",
            "type":"Public Place"
        }
    ],
    "sg:phone":"+1 819 465 2323",
    "sg:postcode":"J0X 2J0",
    "sg:province":"QC",
    "sg:tags":[
        "village"
    ],
    "wof:name":"Messines Bureau Municipal",
    "wof:placetype":"venue"
},
  "geometry": {"coordinates":[-76.0212097168,46.2480964661],"type":"Point"}
}