{
  "type": "Feature",
  "properties": {
    "addr:full":"6242 99 St NW Edmonton AB T6E 6C7",
    "addr:housenumber":"6242",
    "addr:postcode":"t6e 6c7",
    "addr:street":"99 St Nw",
    "iso:country":"CA",
    "sg:address":"6242 99 St NW",
    "sg:city":"Edmonton",
    "sg:classifiers":[
        {
            "category":"Shopping",
            "subcategory":"Shoes",
            "type":"Retail Goods"
        }
    ],
    "sg:phone":"+1 780 434 7992",
    "sg:postcode":"T6E 6C7",
    "sg:province":"AB",
    "wof:name":"Red Wing Shoe Store",
    "wof:placetype":"venue"
},
  "geometry": {"coordinates":[-113.486503601,53.4988517761],"type":"Point"}
}