{
  "type": "Feature",
  "properties": {
    "addr:full":"202 Rue Principale S Amos QC J9T 2J7",
    "addr:housenumber":"202",
    "addr:postcode":"j9t 2j7",
    "addr:street":"Rue Principale S Amos",
    "iso:country":"CA",
    "sg:address":"202 Rue Principale S",
    "sg:city":"Amos",
    "sg:classifiers":[
        {
            "category":"Health Services",
            "subcategory":"Doctor",
            "type":"Services"
        }
    ],
    "sg:phone":"+1 819 727 3442",
    "sg:postcode":"J9T 2J7",
    "sg:province":"QC",
    "sg:tags":[
        "clinic"
    ],
    "wof:name":"Hainault, Pierre-Paul",
    "wof:placetype":"venue"
},
  "geometry": {"coordinates":[-78.115753,48.567875],"type":"Point"}
}