{
  "type": "Feature",
  "properties": {
    "addr:full":"Quebec QC G2K 2H6",
    "addr:postcode":"g2k 2h6",
    "iso:country":"CA",
    "sg:city":"Quebec",
    "sg:classifiers":[
        {
            "category":"Insurance",
            "subcategory":"Insurance Agent",
            "type":"Services"
        }
    ],
    "sg:phone":"+1 418 627 1080",
    "sg:postcode":"G2K 2H6",
    "sg:province":"QC",
    "wof:name":"Cote, Chantal",
    "wof:placetype":"venue"
},
  "geometry": {"coordinates":[-71.2969055176,46.833278656],"type":"Point"}
}