{
  "type": "Feature",
  "properties": {
    "addr:full":"Montreal QC H2Y 1S6",
    "addr:postcode":"h2y 1s6",
    "iso:country":"CA",
    "sg:city":"Montreal",
    "sg:classifiers":[
        {
            "category":"Real Estate",
            "subcategory":"Architect",
            "type":"Services"
        }
    ],
    "sg:phone":"+1 514 285 5502",
    "sg:postcode":"H2Y 1S6",
    "sg:province":"QC",
    "wof:name":"Nomade Architecture",
    "wof:placetype":"venue"
},
  "geometry": {"coordinates":[-73.555069,45.506653],"type":"Point"}
}