{
  "type": "Feature",
  "properties": {
    "addr:full":"2798 4th Ave W Vancouver BC V6K 1R1",
    "addr:housenumber":"2798",
    "addr:postcode":"v6k 1r1",
    "addr:street":"4Th Ave W",
    "iso:country":"CA",
    "sg:address":"2798 4th Ave W",
    "sg:city":"Vancouver",
    "sg:classifiers":[
        {
            "category":"Food & Beverages",
            "subcategory":"Fruits & Vegetables",
            "type":"Retail Goods"
        }
    ],
    "sg:phone":"+1 604 737 7647",
    "sg:postcode":"V6K 1R1",
    "sg:province":"BC",
    "sg:tags":[
        "produce"
    ],
    "wof:name":"Nadi's Produce",
    "wof:placetype":"venue"
},
  "geometry": {"coordinates":[-123.16812133800001,49.2681808472],"type":"Point"}
}