{
  "type": "Feature",
  "properties": {
    "addr:full":"502 Boundary Rd Pembroke ON K8A 6L6",
    "addr:housenumber":"502",
    "addr:postcode":"k8a 6l6",
    "addr:street":"Boundary Rd",
    "iso:country":"CA",
    "sg:address":"502 Boundary Rd",
    "sg:city":"Pembroke",
    "sg:classifiers":[
        {
            "category":"Wholesale",
            "subcategory":"Office Equipment",
            "type":"Manufacturing & Wholesale Goods"
        }
    ],
    "sg:phone":"+1 613 735 1525",
    "sg:postcode":"K8A 6L6",
    "sg:province":"ON",
    "sg:tags":[
        "accounting",
        "bookkeeping",
        "system"
    ],
    "wof:name":"Van Bavel & Doyle",
    "wof:placetype":"venue"
},
  "geometry": {"coordinates":[-77.14595799999999,45.82798],"type":"Point"}
}