{
  "type": "Feature",
  "properties": {
    "addr:full":"505 Heber St N St Pierre Jolys MB R0A 1V0",
    "addr:housenumber":"505",
    "addr:postcode":"r0a 1v0",
    "addr:street":"Heber St N St Pierre Jolys",
    "iso:country":"CA",
    "sg:address":"505 Heber St N",
    "sg:city":"St Pierre Jolys",
    "sg:classifiers":[
        {
            "category":"Education",
            "subcategory":"Library",
            "type":"Public Place"
        }
    ],
    "sg:phone":"+1 204 433 7729",
    "sg:postcode":"R0A 1V0",
    "sg:province":"MB",
    "wof:name":"Bibliotheque Regional Jolys",
    "wof:placetype":"venue"
},
  "geometry": {"coordinates":[-96.9851226807,49.4407081604],"type":"Point"}
}