{
  "type": "Feature",
  "properties": {
    "iso:country":"CA",
    "sg:city":"Maria",
    "sg:classifiers":[
        {
            "category":"Retail",
            "subcategory":"Funeral Services",
            "type":"Services"
        }
    ],
    "sg:phone":"+1 418 759 3011",
    "sg:postcode":"G0C 1Y0",
    "sg:province":"QC",
    "sg:tags":[
        "director"
    ],
    "wof:name":"Santerre & Fils Enr",
    "wof:placetype":"venue"
},
  "geometry": {"coordinates":[-65.99383544920001,48.1708030701],"type":"Point"}
}