{
  "type": "Feature",
  "properties": {
    "addr:full":"Mississauga ON L5T 2J5",
    "addr:postcode":"l5t 2j5",
    "iso:country":"CA",
    "sg:city":"Mississauga",
    "sg:classifiers":[
        {
            "category":"Wholesale",
            "subcategory":"Durable Goods & Equipment",
            "type":"Manufacturing & Wholesale Goods"
        }
    ],
    "sg:phone":"+1 905 670 8158",
    "sg:postcode":"L5T 2J5",
    "sg:province":"ON",
    "sg:tags":[
        "machine",
        "shop",
        "engineering",
        "supply"
    ],
    "wof:name":"Coltech Design",
    "wof:placetype":"venue"
},
  "geometry": {"coordinates":[-79.667534,43.666138],"type":"Point"}
}