{
  "type": "Feature",
  "properties": {
    "addr:full":"Vancouver BC V5V 4C2",
    "addr:postcode":"v5v 4c2",
    "iso:country":"CA",
    "sg:city":"Vancouver",
    "sg:classifiers":[
        {
            "category":"Professional",
            "subcategory":"Business Services",
            "type":"Services"
        }
    ],
    "sg:phone":"+1 604 876 8598",
    "sg:postcode":"V5V 4C2",
    "sg:province":"BC",
    "sg:tags":[
        "notary"
    ],
    "wof:name":"Chan, Patricia",
    "wof:placetype":"venue"
},
  "geometry": {"coordinates":[-123.089973,49.254967],"type":"Point"}
}