{
  "type": "Feature",
  "properties": {
    "iso:country":"CA",
    "sg:address":"268 Don Park Rd",
    "sg:city":"Markham",
    "sg:classifiers":[
        {
            "category":"Manufacturing",
            "subcategory":"Metals",
            "type":"Manufacturing & Wholesale Goods"
        }
    ],
    "sg:phone":"+1 905 475 1229",
    "sg:postcode":"L3R 1C3",
    "sg:province":"ON",
    "sg:tags":[
        "anodizing"
    ],
    "wof:name":"Dependable Anodizing Ltd",
    "wof:placetype":"venue"
},
  "geometry": {"coordinates":[-79.3453674316,43.8251228333],"type":"Point"}
}