{
  "type": "Feature",
  "properties": {
    "addr:full":"RR 6 STN Main Saskatoon SK S7K 3J9",
    "addr:postcode":"s7k 3j9",
    "addr:street":"Rr 6 Stn",
    "iso:country":"CA",
    "sg:address":"RR 6 STN Main",
    "sg:city":"Saskatoon",
    "sg:classifiers":[
        {
            "category":"Building & Trades",
            "subcategory":"Construction",
            "type":"Services"
        }
    ],
    "sg:phone":"+1 306 373 9833",
    "sg:postcode":"S7K 3J9",
    "sg:province":"SK",
    "sg:tags":[
        "roofing",
        "consultant"
    ],
    "wof:name":"Scottco Roof Consultants Ltd",
    "wof:placetype":"venue"
},
  "geometry": {"coordinates":[-106.659317,52.130505],"type":"Point"}
}