{
  "type": "Feature",
  "properties": {
    "addr:full":"New Westminster BC V3M 1K8",
    "addr:postcode":"v3m 1k8",
    "iso:country":"CA",
    "sg:city":"New Westminster",
    "sg:classifiers":[
        {
            "category":"Manufacturing",
            "subcategory":"Tools & Machinery",
            "type":"Manufacturing & Wholesale Goods"
        }
    ],
    "sg:phone":"+1 604 525 1604",
    "sg:postcode":"V3M 1K8",
    "sg:province":"BC",
    "sg:tags":[
        "equipment",
        "hydraulic",
        "supply"
    ],
    "wof:name":"Ram Hydraulics & Air Ltd",
    "wof:placetype":"venue"
},
  "geometry": {"coordinates":[-122.918861389,49.2023468018],"type":"Point"}
}