{
  "type": "Feature",
  "properties": {
    "addr:full":"198 Queen St E Brampton ON L6V 1B7",
    "addr:housenumber":"198",
    "addr:postcode":"l6v 1b7",
    "addr:street":"Queen St E",
    "iso:country":"CA",
    "sg:address":"198 Queen St E",
    "sg:city":"Brampton",
    "sg:classifiers":[
        {
            "category":"Food & Beverages",
            "subcategory":"Liquor & Beverages",
            "type":"Retail Goods"
        }
    ],
    "sg:phone":"+1 905 451 4685",
    "sg:postcode":"L6V 1B7",
    "sg:province":"ON",
    "sg:tags":[
        "beer",
        "ale"
    ],
    "wof:name":"Beer Store",
    "wof:placetype":"venue"
},
  "geometry": {"coordinates":[-79.75192300000001,43.693626],"type":"Point"}
}