{
  "type": "Feature",
  "properties": {
    "addr:full":"270 Elm St Sudbury ON P3C 1V4",
    "addr:housenumber":"270",
    "addr:postcode":"p3c 1v4",
    "addr:street":"Elm St",
    "iso:country":"CA",
    "sg:address":"270 Elm St",
    "sg:city":"Sudbury",
    "sg:classifiers":[
        {
            "category":"Professional",
            "subcategory":"Lawyer & Legal Services",
            "type":"Services"
        }
    ],
    "sg:phone":"+1 705 671 3532",
    "sg:postcode":"P3C 1V4",
    "sg:province":"ON",
    "sg:tags":[
        "attorney"
    ],
    "wof:name":"Florentis Law Office",
    "wof:placetype":"venue"
},
  "geometry": {"coordinates":[-81.005486,46.493256],"type":"Point"}
}