{
  "type": "Feature",
  "properties": {
    "iso:country":"CA",
    "sg:address":"2500 Rue L.-O.-David",
    "sg:city":"Montreal",
    "sg:classifiers":[
        {
            "category":"Retail",
            "subcategory":"Portrait Studio",
            "type":"Services"
        }
    ],
    "sg:phone":"+1 514 722 7422",
    "sg:postcode":"H2A 1N1",
    "sg:province":"QC",
    "sg:tags":[
        "photographer"
    ],
    "wof:name":"Art Creations Photo Video",
    "wof:placetype":"venue"
},
  "geometry": {"coordinates":[-73.606682,45.555691],"type":"Point"}
}