{
  "type": "Feature",
  "properties": {
    "addr:full":"2500 Rue L.-O.-David Montreal QC H2A 1N1",
    "addr:housenumber":"2500",
    "addr:postcode":"h2a 1n1",
    "addr:street":"Rue L.-O.-David",
    "iso:country":"CA",
    "sg:address":"2500 Rue L.-O.-David",
    "sg:city":"Montreal",
    "sg:classifiers":[
        {
            "category":"Retail",
            "subcategory":"Portrait Studio",
            "type":"Services"
        }
    ],
    "sg:phone":"+1 514 722 7422",
    "sg:postcode":"H2A 1N1",
    "sg:province":"QC",
    "sg:tags":[
        "photographer"
    ],
    "wof:name":"Art Creations Photo Video",
    "wof:placetype":"venue"
},
  "geometry": {"coordinates":[-73.60668200000001,45.555691],"type":"Point"}
}