{
  "type": "Feature",
  "properties": {
    "addr:full":"2793 Carp Rd Carp ON K0A 1L0",
    "addr:housenumber":"2793",
    "addr:postcode":"k0a 1l0",
    "addr:street":"Carp Rd",
    "iso:country":"CA",
    "sg:address":"2793 Carp Rd",
    "sg:city":"Carp",
    "sg:classifiers":[
        {
            "category":"Manufacturing",
            "subcategory":"Motor Vehicles & Parts",
            "type":"Manufacturing & Wholesale Goods"
        }
    ],
    "sg:phone":"+1 613 836 0505",
    "sg:postcode":"K0A 1L0",
    "sg:province":"ON",
    "sg:tags":[
        "equipment",
        "truck"
    ],
    "wof:name":"Prime Road Machinery Inc",
    "wof:placetype":"venue"
},
  "geometry": {"coordinates":[-75.983581543,45.3023376465],"type":"Point"}
}