{
  "type": "Feature",
  "properties": {
    "addr:full":"16417 117 Ave NW Edmonton AB T5M 3V3",
    "addr:housenumber":"16417",
    "addr:postcode":"t5m 3v3",
    "addr:street":"117 Ave Nw",
    "iso:country":"CA",
    "sg:address":"16417 117 Ave NW",
    "sg:city":"Edmonton",
    "sg:classifiers":[
        {
            "category":"Recreation",
            "type":"Entertainment"
        }
    ],
    "sg:phone":"+1 780 453 3209",
    "sg:postcode":"T5M 3V3",
    "sg:province":"AB",
    "sg:tags":[
        "instruction",
        "gymnastic"
    ],
    "wof:name":"Horizon Gymnastics Club",
    "wof:placetype":"venue"
},
  "geometry": {"coordinates":[-113.60495758099999,53.5676002502],"type":"Point"}
}