{
  "type": "Feature",
  "properties": {
    "addr:full":"Brentwood Bay BC V8M 1C5",
    "addr:postcode":"v8m 1c5",
    "iso:country":"CA",
    "sg:city":"Brentwood Bay",
    "sg:classifiers":[
        {
            "category":"Professional",
            "subcategory":"Research",
            "type":"Services"
        }
    ],
    "sg:phone":"+1 250 652 1334",
    "sg:postcode":"V8M 1C5",
    "sg:province":"BC",
    "sg:tags":[
        "environmental",
        "ecological"
    ],
    "wof:name":"Geo Sea Consulting Ltd",
    "wof:placetype":"venue"
},
  "geometry": {"coordinates":[-123.46661400000001,48.57811],"type":"Point"}
}