{
  "type": "Feature",
  "properties": {
    "iso:country":"CA",
    "sg:address":"70 Hawkwood Blvd NW",
    "sg:city":"Calgary",
    "sg:classifiers":[
        {
            "category":"Shopping",
            "type":"Retail Goods"
        }
    ],
    "sg:phone":"+1 403 241 5400",
    "sg:postcode":"T3G 2R9",
    "sg:province":"AB",
    "sg:tags":[
        "cosmetic",
        "perfume"
    ],
    "wof:name":"Mary Kay Cosmetics",
    "wof:placetype":"venue"
},
  "geometry": {"coordinates":[-114.167831421,51.1243553162],"type":"Point"}
}