{
  "type": "Feature",
  "properties": {
    "addr:full":"1102 Government St Victoria BC V8W 1Y2",
    "addr:housenumber":"1102",
    "addr:postcode":"v8w 1y2",
    "addr:street":"Government St",
    "iso:country":"CA",
    "sg:address":"1102 Government St",
    "sg:city":"Victoria",
    "sg:classifiers":[
        {
            "category":"Shopping",
            "subcategory":"Gifts & Souvenirs",
            "type":"Retail Goods"
        }
    ],
    "sg:phone":"+1 250 388 5477",
    "sg:postcode":"V8W 1Y2",
    "sg:province":"BC",
    "sg:tags":[
        "shop"
    ],
    "wof:name":"James Bay Trading CO Ltd",
    "wof:placetype":"venue"
},
  "geometry": {"coordinates":[-123.368004,48.424999],"type":"Point"}
}