{
  "type": "Feature",
  "properties": {
    "iso:country":"CA",
    "sg:address":"5258 Brenton-Page Rd",
    "sg:city":"Cassidy",
    "sg:classifiers":[
        {
            "category":"Building & Trades",
            "subcategory":"Construction",
            "type":"Services"
        }
    ],
    "sg:phone":"+1 250 245 0240",
    "sg:postcode":"V0R 1H0",
    "sg:province":"BC",
    "sg:tags":[
        "concrete",
        "contractor"
    ],
    "wof:name":"Bedrock Redi-Mix Ltd",
    "wof:placetype":"venue"
},
  "geometry": {"coordinates":[-123.862815857,49.0647201538],"type":"Point"}
}