{
  "type": "Feature",
  "properties": {
    "addr:full":"40 Rue Evangeline Granby QC J2G 8K1",
    "addr:housenumber":"40",
    "addr:postcode":"j2g 8k1",
    "addr:street":"Rue Evangeline",
    "iso:country":"CA",
    "sg:address":"40 Rue Evangeline",
    "sg:city":"Granby",
    "sg:classifiers":[
        {
            "category":"Home & Garden",
            "subcategory":"Household Appliances",
            "type":"Retail Goods"
        }
    ],
    "sg:phone":"+1 450 378 2686",
    "sg:postcode":"J2G 8K1",
    "sg:province":"QC",
    "wof:name":"Centre Du Rasoir & Plus",
    "wof:placetype":"venue"
},
  "geometry": {"coordinates":[-72.74861900000001,45.413528],"type":"Point"}
}