{
  "type": "Feature",
  "properties": {
    "addr:full":"Stony Plain AB T7Z 1V8",
    "addr:postcode":"t7z 1v8",
    "iso:country":"CA",
    "sg:city":"Stony Plain",
    "sg:classifiers":[
        {
            "category":"Travel",
            "subcategory":"Campground",
            "type":"Entertainment"
        }
    ],
    "sg:phone":"+1 780 963 4505",
    "sg:postcode":"T7Z 1V8",
    "sg:province":"AB",
    "wof:name":"Stony Plain Lion Campground",
    "wof:placetype":"venue"
},
  "geometry": {"coordinates":[-113.992546081,53.5446052551],"type":"Point"}
}