{
  "type": "Feature",
  "properties": {
    "iso:country":"CA",
    "sg:address":"668 Cartier St",
    "sg:city":"Casselman",
    "sg:classifiers":[
        {
            "category":"Bars & Pubs",
            "type":"Food & Drink"
        }
    ],
    "sg:phone":"+1 613 764 5608",
    "sg:postcode":"K0A 1M0",
    "sg:province":"ON",
    "wof:name":"Karina's Pub",
    "wof:placetype":"venue"
},
  "geometry": {"coordinates":[-75.08809661870001,45.313129425],"type":"Point"}
}