{
  "type": "Feature",
  "properties": {
    "addr:full":"Salmo BC V0G 1Z0",
    "addr:postcode":"v0g 1z0",
    "iso:country":"CA",
    "sg:city":"Salmo",
    "sg:classifiers":[
        {
            "category":"Education",
            "subcategory":"School",
            "type":"Public Place"
        }
    ],
    "sg:phone":"+1 250 357 2226",
    "sg:postcode":"V0G 1Z0",
    "sg:province":"BC",
    "wof:name":"Salmo Secondary School",
    "wof:placetype":"venue"
},
  "geometry": {"coordinates":[-117.282814,49.191986],"type":"Point"}
}