{
  "type": "Feature",
  "properties": {
    "addr:full":"4465 Boul Bourque Rock Forest QC J1N 1S4",
    "addr:housenumber":"4465",
    "addr:postcode":"j1n 1s4",
    "addr:street":"Boul Bourque",
    "iso:country":"CA",
    "sg:address":"4465 Boul Bourque",
    "sg:city":"Rock Forest",
    "sg:classifiers":[
        {
            "category":"Autos & Motor Vehicles",
            "subcategory":"Automobile Sales",
            "type":"Retail Goods"
        }
    ],
    "sg:phone":"+1 819 569 9111",
    "sg:postcode":"J1N 1S4",
    "sg:province":"QC",
    "sg:tags":[
        "car",
        "dealer"
    ],
    "wof:name":"Volkswagen DE L'Estrie",
    "wof:placetype":"venue"
},
  "geometry": {"coordinates":[-71.9776306152,45.3775634766],"type":"Point"}
}