{
  "type": "Feature",
  "properties": {
    "addr:full":"28 Cote DE LA Fabrique Quebec QC G1R 3V7",
    "addr:housenumber":"28",
    "addr:postcode":"g1r 3v7",
    "addr:street":"Cote De La Fabrique",
    "iso:country":"CA",
    "sg:address":"28 Cote DE LA Fabrique",
    "sg:city":"Quebec",
    "sg:classifiers":[
        {
            "category":"Shopping",
            "subcategory":"Luggage & Leather Goods",
            "type":"Retail Goods"
        }
    ],
    "sg:phone":"+1 418 692 1409",
    "sg:postcode":"G1R 3V7",
    "sg:province":"QC",
    "sg:tags":[
        "shoes"
    ],
    "wof:name":"Cuir Arizona Inc",
    "wof:placetype":"venue"
},
  "geometry": {"coordinates":[-71.2074813843,46.8143310547],"type":"Point"}
}