{
  "type": "Feature",
  "properties": {
    "addr:full":"Pain Court ON N0P 1Z0",
    "addr:postcode":"n0p 1z0",
    "addr:street":"Court",
    "iso:country":"CA",
    "sg:city":"Pain Court",
    "sg:classifiers":[
        {
            "category":"Wholesale",
            "subcategory":"Vending Machines",
            "type":"Manufacturing & Wholesale Goods"
        }
    ],
    "sg:phone":"+1 519 436 6872",
    "sg:postcode":"N0P 1Z0",
    "sg:province":"ON",
    "wof:name":"Vend King",
    "wof:placetype":"venue"
},
  "geometry": {"coordinates":[-82.30889892579999,42.3846702576],"type":"Point"}
}