{
  "type": "Feature",
  "properties": {
    "iso:country":"CA",
    "sg:address":"PO Box 101",
    "sg:city":"Cherhill",
    "sg:classifiers":[
        {
            "category":"Mining & Drilling",
            "type":"Manufacturing & Wholesale Goods"
        }
    ],
    "sg:phone":"+1 780 785 3211",
    "sg:postcode":"T0E 0J0",
    "sg:province":"AB",
    "sg:tags":[
        "company",
        "oil"
    ],
    "wof:name":"Benson Petroleum Ltd",
    "wof:placetype":"venue"
},
  "geometry": {"coordinates":[-114.68444061300001,53.820400238],"type":"Point"}
}