{
  "type": "Feature",
  "properties": {
    "addr:full":"9 Kent St W Lindsay ON K9V 2X9",
    "addr:housenumber":"9",
    "addr:postcode":"k9v 2x9",
    "addr:street":"Kent St W",
    "iso:country":"CA",
    "sg:address":"9 Kent St W",
    "sg:city":"Lindsay",
    "sg:classifiers":[
        {
            "category":"Shopping",
            "subcategory":"Discount & Variety Stores",
            "type":"Retail Goods"
        }
    ],
    "sg:phone":"+1 705 324 4263",
    "sg:postcode":"K9V 2X9",
    "sg:province":"ON",
    "wof:name":"Mr Convenience",
    "wof:placetype":"venue"
},
  "geometry": {"coordinates":[-78.7350158691,44.355342865],"type":"Point"}
}