{
  "type": "Feature",
  "properties": {
    "addr:full":"Chatsworth ON N0H 1G0",
    "addr:postcode":"n0h 1g0",
    "iso:country":"CA",
    "sg:city":"Chatsworth",
    "sg:classifiers":[
        {
            "category":"Professional",
            "subcategory":"Business Services",
            "type":"Services"
        }
    ],
    "sg:phone":"+1 519 794 2749",
    "sg:postcode":"N0H 1G0",
    "sg:province":"ON",
    "sg:tags":[
        "water",
        "treatment"
    ],
    "wof:name":"Ecowater Systems",
    "wof:placetype":"venue"
},
  "geometry": {"coordinates":[-80.89311218260001,44.4562492371],"type":"Point"}
}