{
  "type": "Feature",
  "properties": {
    "iso:country":"CA",
    "sg:city":"Toronto",
    "sg:classifiers":[
        {
            "category":"Wholesale",
            "subcategory":"Apparel",
            "type":"Manufacturing & Wholesale Goods"
        }
    ],
    "sg:phone":"+1 416 486 3374",
    "sg:postcode":"M4S 2C6",
    "sg:province":"ON",
    "sg:tags":[
        "handbag"
    ],
    "wof:name":"Accessory Network",
    "wof:placetype":"venue"
},
  "geometry": {"coordinates":[-79.398201,43.705006],"type":"Point"}
}