{
  "type": "Feature",
  "properties": {
    "addr:full":"602 Assiniboine Ave Maryfield SK S0G 3K0",
    "addr:housenumber":"602",
    "addr:postcode":"s0g 3k0",
    "addr:street":"Assiniboine Ave",
    "iso:country":"CA",
    "sg:address":"602 Assiniboine Ave",
    "sg:city":"Maryfield",
    "sg:classifiers":[
        {
            "category":"Government",
            "subcategory":"Office",
            "type":"Public Place"
        }
    ],
    "sg:phone":"+1 306 646 2143",
    "sg:postcode":"S0G 3K0",
    "sg:province":"SK",
    "sg:tags":[
        "village"
    ],
    "wof:name":"Village of Maryfield Office",
    "wof:placetype":"venue"
},
  "geometry": {"coordinates":[-101.531532,49.83754],"type":"Point"}
}