{
  "type": "Feature",
  "properties": {
    "addr:full":"744 4 Ave SW Calgary AB T2P 3T4",
    "addr:housenumber":"744",
    "addr:postcode":"t2p 3t4",
    "addr:street":"4 Ave Sw",
    "iso:country":"CA",
    "sg:address":"744 4 Ave SW",
    "sg:city":"Calgary",
    "sg:classifiers":[
        {
            "category":"Professional",
            "subcategory":"Research",
            "type":"Services"
        }
    ],
    "sg:phone":"+1 403 264 7109",
    "sg:postcode":"T2P 3T4",
    "sg:province":"AB",
    "sg:tags":[
        "environmental",
        "ecological"
    ],
    "wof:name":"Ramsay & Assoc Cnsltng Svc",
    "wof:placetype":"venue"
},
  "geometry": {"coordinates":[-114.077164,51.049847],"type":"Point"}
}