{
  "type": "Feature",
  "properties": {
    "addr:full":"Duncan BC V9L 6W3",
    "addr:postcode":"v9l 6w3",
    "iso:country":"CA",
    "sg:city":"Duncan",
    "sg:classifiers":[
        {
            "category":"Wholesale",
            "subcategory":"Construction Materials",
            "type":"Manufacturing & Wholesale Goods"
        }
    ],
    "sg:phone":"+1 250 715 1485",
    "sg:postcode":"V9L 6W3",
    "sg:province":"BC",
    "sg:tags":[
        "lumber"
    ],
    "wof:name":"Hardwoods",
    "wof:placetype":"venue"
},
  "geometry": {"coordinates":[-123.70738220200001,48.779094696],"type":"Point"}
}