{
  "type": "Feature",
  "properties": {
    "addr:full":"397 Dundas St W #200 Toronto ON M5T 1G6",
    "addr:housenumber":"397",
    "addr:postcode":"m5t 1g6",
    "addr:street":"Dundas St W # 200",
    "iso:country":"CA",
    "sg:address":"397 Dundas St W #200",
    "sg:city":"Toronto",
    "sg:classifiers":[
        {
            "category":"Manufacturing",
            "subcategory":"Printing",
            "type":"Manufacturing & Wholesale Goods"
        }
    ],
    "sg:phone":"+1 416 597 0317",
    "sg:postcode":"M5T 1G6",
    "sg:province":"ON",
    "sg:tags":[
        "printer"
    ],
    "wof:name":"Ray Printing",
    "wof:placetype":"venue"
},
  "geometry": {"coordinates":[-79.3947067261,43.6534919739],"type":"Point"}
}