{
  "type": "Feature",
  "properties": {
    "addr:full":"Thornhill ON L4J 6X1",
    "addr:postcode":"l4j 6x1",
    "iso:country":"CA",
    "sg:city":"Thornhill",
    "sg:classifiers":[
        {
            "category":"Professional",
            "subcategory":"Business Services",
            "type":"Services"
        }
    ],
    "sg:phone":"+1 905 731 3313",
    "sg:postcode":"L4J 6X1",
    "sg:province":"ON",
    "sg:tags":[
        "orthopedic",
        "appliance",
        "made"
    ],
    "wof:name":"Doctus Quality Health Care",
    "wof:placetype":"venue"
},
  "geometry": {"coordinates":[-79.43310546879999,43.7953224182],"type":"Point"}
}