{
  "type": "Feature",
  "properties": {
    "addr:full":"1006 Nairn Ave Winnipeg MB R2L 0Y2",
    "addr:housenumber":"1006",
    "addr:postcode":"r2l 0y2",
    "addr:street":"Nairn Ave",
    "iso:country":"CA",
    "sg:address":"1006 Nairn Ave",
    "sg:city":"Winnipeg",
    "sg:classifiers":[
        {
            "category":"Government",
            "subcategory":"Office",
            "type":"Public Place"
        }
    ],
    "sg:phone":"+1 204 985 8043",
    "sg:postcode":"R2L 0Y2",
    "sg:province":"MB",
    "wof:name":"Manitoba Driver & Vehicle",
    "wof:placetype":"venue"
},
  "geometry": {"coordinates":[-97.08148956300001,49.9004249573],"type":"Point"}
}