{
  "type": "Feature",
  "properties": {
    "addr:full":"2918 Kingsway Vancouver BC V5R 5J3",
    "addr:housenumber":"2918",
    "addr:postcode":"v5r 5j3",
    "addr:street":"Kingsway",
    "iso:country":"CA",
    "sg:address":"2918 Kingsway",
    "sg:city":"Vancouver",
    "sg:classifiers":[
        {
            "category":"Autos & Motor Vehicles",
            "subcategory":"Fuel & Gas Station",
            "type":"Retail Goods"
        }
    ],
    "sg:phone":"+1 604 437 0822",
    "sg:postcode":"V5R 5J3",
    "sg:province":"BC",
    "sg:tags":[
        "oil"
    ],
    "wof:name":"Metrotown Pantry",
    "wof:placetype":"venue"
},
  "geometry": {"coordinates":[-123.04524231000001,49.2361030579],"type":"Point"}
}