{
  "type": "Feature",
  "properties": {
    "iso:country":"CA",
    "sg:address":"2379 Rang Saint-Paul",
    "sg:city":"Chicoutimi",
    "sg:classifiers":[
        {
            "category":"Retail",
            "subcategory":"Auto Repair",
            "type":"Services"
        }
    ],
    "sg:phone":"+1 418 693 0294",
    "sg:postcode":"G7K 1E8",
    "sg:province":"QC",
    "sg:tags":[
        "body",
        "automobile",
        "painting"
    ],
    "wof:name":"Debossage Ghislain & Gaetan",
    "wof:placetype":"venue"
},
  "geometry": {"coordinates":[-71.11651611329999,48.3861618042],"type":"Point"}
}