{
  "type": "Feature",
  "properties": {
    "iso:country":"CA",
    "sg:address":"206 Stockton Ave",
    "sg:city":"Okotoks",
    "sg:classifiers":[
        {
            "category":"Retail",
            "subcategory":"Animal Services",
            "type":"Services"
        }
    ],
    "sg:phone":"+1 403 938 2238",
    "sg:postcode":"T1S 1A9",
    "sg:province":"AB",
    "sg:tags":[
        "pet",
        "grooming",
        "washing"
    ],
    "wof:name":"Country Pets & Grooming",
    "wof:placetype":"venue"
},
  "geometry": {"coordinates":[-113.953697205,50.7204971313],"type":"Point"}
}