{
  "type": "Feature",
  "properties": {
    "iso:country":"CA",
    "sg:address":"735 Rue Gamache",
    "sg:city":"Victoriaville",
    "sg:classifiers":[
        {
            "category":"Home & Garden",
            "subcategory":"Carpets & Floor Coverings",
            "type":"Retail Goods"
        }
    ],
    "sg:phone":"+1 819 751 2525",
    "sg:postcode":"G6P 6R8",
    "sg:province":"QC",
    "sg:tags":[
        "tile",
        "rug"
    ],
    "wof:name":"Tapis Guy Ouellette Inc",
    "wof:placetype":"venue"
},
  "geometry": {"coordinates":[-71.9663238525,46.0383453369],"type":"Point"}
}