{
  "type": "Feature",
  "properties": {
    "addr:full":"Calgary AB T2G 4B5",
    "addr:postcode":"t2g 4b5",
    "iso:country":"CA",
    "sg:city":"Calgary",
    "sg:classifiers":[
        {
            "category":"Wholesale",
            "subcategory":"Electrical",
            "type":"Manufacturing & Wholesale Goods"
        }
    ],
    "sg:phone":"+1 403 243 6919",
    "sg:postcode":"T2G 4B5",
    "sg:province":"AB",
    "sg:tags":[
        "electric",
        "motor"
    ],
    "wof:name":"Murray's Electric Motor Rewind",
    "wof:placetype":"venue"
},
  "geometry": {"coordinates":[-114.050873,51.011398],"type":"Point"}
}