{
  "type": "Feature",
  "properties": {
    "addr:full":"3222 Eglinton Ave E Scarborough ON M1J 2H6",
    "addr:housenumber":"3222",
    "addr:postcode":"m1j 2h6",
    "addr:street":"Eglinton Ave E",
    "iso:country":"CA",
    "sg:address":"3222 Eglinton Ave E",
    "sg:city":"Scarborough",
    "sg:classifiers":[
        {
            "category":"Restaurant",
            "type":"Food & Drink"
        }
    ],
    "sg:phone":"+1 416 261 7016",
    "sg:postcode":"M1J 2H6",
    "sg:province":"ON",
    "wof:name":"Little Bavaria Restaurant",
    "wof:placetype":"venue"
},
  "geometry": {"coordinates":[-79.21822400000001,43.743519],"type":"Point"}
}