{
  "type": "Feature",
  "properties": {
    "addr:full":"506 6E Rang Saint-Jude QC J0H 1P0",
    "addr:housenumber":"506",
    "addr:postcode":"j0h 1p0",
    "addr:street":"6E Rang Saint-Jude",
    "iso:country":"CA",
    "sg:address":"506 6E Rang",
    "sg:city":"Saint-Jude",
    "sg:classifiers":[
        {
            "category":"Building & Trades",
            "subcategory":"Construction",
            "type":"Services"
        }
    ],
    "sg:phone":"+1 450 792 2479",
    "sg:postcode":"J0H 1P0",
    "sg:province":"QC",
    "sg:tags":[
        "masonry",
        "contractor"
    ],
    "wof:name":"DE Busschere Bergeron Enr",
    "wof:placetype":"venue"
},
  "geometry": {"coordinates":[-73.0370788574,45.7667198181],"type":"Point"}
}