{
  "type": "Feature",
  "properties": {
    "iso:country":"CA",
    "sg:address":"1256 Danforth Rd",
    "sg:city":"Scarborough",
    "sg:classifiers":[
        {
            "category":"Health Services",
            "subcategory":"Doctor",
            "type":"Services"
        }
    ],
    "sg:phone":"+1 416 261 3500",
    "sg:postcode":"M1J 1E5",
    "sg:province":"ON",
    "sg:tags":[
        "physician",
        "surgeon"
    ],
    "wof:name":"Ung, Berton MD",
    "wof:placetype":"venue"
},
  "geometry": {"coordinates":[-79.24597167970001,43.7379570007],"type":"Point"}
}