{
  "type": "Feature",
  "properties": {
    "addr:full":"Toronto ON M4P 3B5",
    "addr:postcode":"m4p 3b5",
    "iso:country":"CA",
    "sg:city":"Toronto",
    "sg:classifiers":[
        {
            "category":"Professional",
            "subcategory":"Management & Consulting",
            "type":"Services"
        }
    ],
    "sg:phone":"+1 416 322 3030",
    "sg:postcode":"M4P 3B5",
    "sg:province":"ON",
    "sg:tags":[
        "communications",
        "consultant"
    ],
    "wof:name":"Trillium Corporate Comms Inc",
    "wof:placetype":"venue"
},
  "geometry": {"coordinates":[-79.39362300000001,43.707878],"type":"Point"}
}