{
  "type": "Feature",
  "properties": {
    "addr:full":"400 Canarctic Dr North York ON M3J 2V3",
    "addr:housenumber":"400",
    "addr:postcode":"m3j 2v3",
    "addr:street":"Canarctic Dr",
    "iso:country":"CA",
    "sg:address":"400 Canarctic Dr",
    "sg:city":"North York",
    "sg:classifiers":[
        {
            "category":"Wholesale",
            "subcategory":"Durable Goods & Equipment",
            "type":"Manufacturing & Wholesale Goods"
        }
    ],
    "sg:phone":"+1 416 663 5523",
    "sg:postcode":"M3J 2V3",
    "sg:province":"ON",
    "sg:tags":[
        "importer"
    ],
    "wof:name":"Dana Imports CO",
    "wof:placetype":"venue"
},
  "geometry": {"coordinates":[-79.4870681763,43.7768325806],"type":"Point"}
}