{
  "type": "Feature",
  "properties": {
    "iso:country":"CA",
    "sg:address":"450 Boul Saint-Germain",
    "sg:city":"Rimouski",
    "sg:classifiers":[
        {
            "category":"Building & Trades",
            "subcategory":"Construction",
            "type":"Services"
        }
    ],
    "sg:phone":"+1 418 722 4418",
    "sg:postcode":"G5L 3P1",
    "sg:province":"QC",
    "sg:tags":[
        "excavating",
        "contractor"
    ],
    "wof:name":"Mercier, Guy",
    "wof:placetype":"venue"
},
  "geometry": {"coordinates":[-68.5523986816,48.4393615723],"type":"Point"}
}