{
  "type": "Feature",
  "properties": {
    "addr:full":"3010 32 St S Lethbridge AB T1K 7B4",
    "addr:housenumber":"3010",
    "addr:postcode":"t1k 7b4",
    "addr:street":"32 St S",
    "iso:country":"CA",
    "sg:address":"3010 32 St S",
    "sg:city":"Lethbridge",
    "sg:classifiers":[
        {
            "category":"Wholesale",
            "subcategory":"Machinery & Supplies",
            "type":"Manufacturing & Wholesale Goods"
        }
    ],
    "sg:phone":"+1 403 328 6326",
    "sg:postcode":"T1K 7B4",
    "sg:province":"AB",
    "sg:tags":[
        "hardware",
        "farm",
        "equipment"
    ],
    "wof:name":"Peavey Mart",
    "wof:placetype":"venue"
},
  "geometry": {"coordinates":[-112.79762268099999,49.664730072],"type":"Point"}
}