{
  "type": "Feature",
  "properties": {
    "addr:full":"384 Market Ave Grand Forks BC V0H 1H0",
    "addr:housenumber":"384",
    "addr:postcode":"v0h 1h0",
    "addr:street":"Market Ave",
    "iso:country":"CA",
    "sg:address":"384 Market Ave",
    "sg:city":"Grand Forks",
    "sg:classifiers":[
        {
            "category":"Professional",
            "subcategory":"Lawyer & Legal Services",
            "type":"Services"
        }
    ],
    "sg:phone":"+1 250 442 8360",
    "sg:postcode":"V0H 1H0",
    "sg:province":"BC",
    "sg:tags":[
        "attorney"
    ],
    "wof:name":"Deanna Ludowicz Law Office",
    "wof:placetype":"venue"
},
  "geometry": {"coordinates":[-118.43907900000001,49.031532],"type":"Point"}
}