{
  "type": "Feature",
  "properties": {
    "iso:country":"CA",
    "sg:address":"501 Alliance Ave",
    "sg:city":"York",
    "sg:classifiers":[
        {
            "category":"Shopping",
            "subcategory":"Stationery & Office Supplies",
            "type":"Retail Goods"
        }
    ],
    "sg:phone":"+1 416 760 0009",
    "sg:postcode":"M6N 2J1",
    "sg:province":"ON",
    "sg:tags":[
        "educational",
        "material"
    ],
    "wof:name":"Cambridge Education Group Inc",
    "wof:placetype":"venue"
},
  "geometry": {"coordinates":[-79.4887084961,43.6768913269],"type":"Point"}
}