{
  "type": "Feature",
  "properties": {
    "iso:country":"CA",
    "sg:address":"955 Rte Jean-Gauvin",
    "sg:city":"Sainte-Foy",
    "sg:classifiers":[
        {
            "category":"Education",
            "subcategory":"Special Training",
            "type":"Public Place"
        }
    ],
    "sg:phone":"+1 418 877 9658",
    "sg:postcode":"G1X 4M5",
    "sg:province":"QC",
    "sg:tags":[
        "instruction",
        "driving"
    ],
    "wof:name":"Ecole DE Conduite Tecnic",
    "wof:placetype":"venue"
},
  "geometry": {"coordinates":[-71.3662567139,46.7617683411],"type":"Point"}
}