{
  "type": "Feature",
  "properties": {
    "addr:full":"456 22E Av E Blainville QC J7C 4L8",
    "addr:housenumber":"456",
    "addr:postcode":"j7c 4l8",
    "addr:street":"22E Av E",
    "iso:country":"CA",
    "sg:address":"456 22E Av E",
    "sg:city":"Blainville",
    "sg:classifiers":[
        {
            "category":"Manufacturing",
            "subcategory":"Building Materials",
            "type":"Manufacturing & Wholesale Goods"
        }
    ],
    "sg:phone":"+1 450 433 0363",
    "sg:postcode":"J7C 4L8",
    "sg:province":"QC",
    "sg:tags":[
        "molding"
    ],
    "wof:name":"Moulures Quatrieme Dimension",
    "wof:placetype":"venue"
},
  "geometry": {"coordinates":[-73.8485412598,45.6562271118],"type":"Point"}
}