{
  "type": "Feature",
  "properties": {
    "addr:full":"12403 67 St NW Edmonton AB T5B 1N2",
    "addr:housenumber":"12403",
    "addr:postcode":"t5b 1n2",
    "addr:street":"67 St Nw",
    "iso:country":"CA",
    "sg:address":"12403 67 St NW",
    "sg:city":"Edmonton",
    "sg:phone":"+1 780 471 2255",
    "sg:postcode":"T5B 1N2",
    "sg:province":"AB",
    "sg:tags":[
        "tanner"
    ],
    "wof:name":"Edmonton Fur Tanners Ltd",
    "wof:placetype":"venue"
},
  "geometry": {"coordinates":[-113.444397,53.580017],"type":"Point"}
}