{
  "type": "Feature",
  "properties": {
    "addr:full":"124 7 Ave SE Calgary AB T2G 0H5",
    "addr:housenumber":"124",
    "addr:postcode":"t2g 0h5",
    "addr:street":"7 Ave Se",
    "iso:country":"CA",
    "sg:address":"124 7 Ave SE",
    "sg:city":"Calgary",
    "sg:classifiers":[
        {
            "category":"Travel",
            "subcategory":"Hotels & Motels",
            "type":"Entertainment"
        }
    ],
    "sg:phone":"+1 403 262 4641",
    "sg:postcode":"T2G 0H5",
    "sg:province":"AB",
    "wof:name":"Hotel Regis Plaza",
    "wof:placetype":"venue"
},
  "geometry": {"coordinates":[-114.062271,51.046566],"type":"Point"}
}