{
  "type": "Feature",
  "properties": {
    "addr:full":"Toronto ON M4L 3W6",
    "addr:postcode":"m4l 3w6",
    "iso:country":"CA",
    "sg:city":"Toronto",
    "sg:classifiers":[
        {
            "category":"Organizations",
            "subcategory":"Professional Association",
            "type":"Services"
        }
    ],
    "sg:phone":"+1 416 693 5466",
    "sg:postcode":"M4L 3W6",
    "sg:province":"ON",
    "sg:tags":[
        "club"
    ],
    "wof:name":"Lions Club of Toronto",
    "wof:placetype":"venue"
},
  "geometry": {"coordinates":[-79.312912,43.661713],"type":"Point"}
}