{
  "type": "Feature",
  "properties": {
    "addr:full":"10010 Fyfe Ave North Battleford SK S9A 3E6",
    "addr:postcode":"10010;s9a 3e6",
    "addr:street":"Fyfe Ave",
    "iso:country":"CA",
    "sg:address":"10010 Fyfe Ave",
    "sg:city":"North Battleford",
    "sg:classifiers":[
        {
            "category":"Government",
            "subcategory":"Office",
            "type":"Public Place"
        }
    ],
    "sg:phone":"+1 306 446 5000",
    "sg:postcode":"S9A 3E6",
    "sg:province":"SK",
    "wof:name":"Sask Energy",
    "wof:placetype":"venue"
},
  "geometry": {"coordinates":[-108.26134500000001,52.748482],"type":"Point"}
}