{
  "type": "Feature",
  "properties": {
    "addr:full":"3115 Boul Hochelaga Sainte-Foy QC G1W 2P9",
    "addr:housenumber":"3115",
    "addr:postcode":"g1w 2p9",
    "addr:street":"Boul Hochelaga",
    "iso:country":"CA",
    "sg:address":"3115 Boul Hochelaga",
    "sg:city":"Sainte-Foy",
    "sg:classifiers":[
        {
            "category":"Autos & Motor Vehicles",
            "subcategory":"Auto Supplies",
            "type":"Retail Goods"
        }
    ],
    "sg:phone":"+1 418 653 0841",
    "sg:postcode":"G1W 2P9",
    "sg:province":"QC",
    "sg:tags":[
        "repairing",
        "automobile"
    ],
    "wof:name":"Goodyear Pneus & Mecanique",
    "wof:placetype":"venue"
},
  "geometry": {"coordinates":[-71.30139200000001,46.763851],"type":"Point"}
}