{
  "type": "Feature",
  "properties": {
    "addr:full":"53 Rue Principale Sainte-Francoise QC G0L 3B0",
    "addr:housenumber":"53",
    "addr:postcode":"g0l 3b0",
    "addr:street":"Rue Principale",
    "iso:country":"CA",
    "sg:address":"53 Rue Principale",
    "sg:city":"Sainte-Francoise",
    "sg:classifiers":[
        {
            "category":"Food & Beverages",
            "subcategory":"Groceries & Convenience Stores",
            "type":"Retail Goods"
        }
    ],
    "sg:phone":"+1 418 851 1229",
    "sg:postcode":"G0L 3B0",
    "sg:province":"QC",
    "sg:tags":[
        "grocer"
    ],
    "wof:name":"Epicerie Rioux",
    "wof:placetype":"venue"
},
  "geometry": {"coordinates":[-69.058594,48.090878],"type":"Point"}
}