{
  "type": "Feature",
  "properties": {
    "iso:country":"CA",
    "sg:address":"861 Church St",
    "sg:city":"Windsor",
    "sg:classifiers":[
        {
            "category":"Professional",
            "subcategory":"Business Services",
            "type":"Services"
        }
    ],
    "sg:phone":"+1 519 252 4234",
    "sg:postcode":"N9A 4T8",
    "sg:province":"ON",
    "sg:tags":[
        "lecture",
        "bureau",
        "seminar"
    ],
    "wof:name":"June Cox Enterprises",
    "wof:placetype":"venue"
},
  "geometry": {"coordinates":[-83.0390625,42.3096923828],"type":"Point"}
}