{
  "type": "Feature",
  "properties": {
    "addr:full":"621 Ch Ozias-Leduc Otterburn Park QC J3H 2M7",
    "addr:housenumber":"621",
    "addr:postcode":"j3h 2m7",
    "addr:street":"Ch Ozias-Leduc;Park",
    "iso:country":"CA",
    "sg:address":"621 Ch Ozias-Leduc",
    "sg:city":"Otterburn Park",
    "sg:classifiers":[
        {
            "category":"Shopping",
            "subcategory":"Pharmacy",
            "type":"Retail Goods"
        }
    ],
    "sg:phone":"+1 450 446 8166",
    "sg:postcode":"J3H 2M7",
    "sg:province":"QC",
    "wof:name":"Famili-Prix",
    "wof:placetype":"venue"
},
  "geometry": {"coordinates":[-73.1896972656,45.5394821167],"type":"Point"}
}