{
  "type": "Feature",
  "properties": {
    "addr:full":"Dartmouth NS B2W 2S7",
    "addr:postcode":"b2w 2s7",
    "iso:country":"CA",
    "sg:city":"Dartmouth",
    "sg:classifiers":[
        {
            "category":"Personal",
            "subcategory":"Beauty Salon",
            "type":"Services"
        }
    ],
    "sg:phone":"+1 902 434 7123",
    "sg:postcode":"B2W 2S7",
    "sg:province":"NS",
    "wof:name":"Galante's European Hair Design",
    "wof:placetype":"venue"
},
  "geometry": {"coordinates":[-63.5305709839,44.6731567383],"type":"Point"}
}