{
  "type": "Feature",
  "properties": {
    "iso:country":"CA",
    "sg:address":"1700 Corydon Ave",
    "sg:city":"Winnipeg",
    "sg:classifiers":[
        {
            "category":"Real Estate",
            "subcategory":"Real Estate Operator",
            "type":"Services"
        }
    ],
    "sg:phone":"+1 204 489 7055",
    "sg:postcode":"R3N 0K1",
    "sg:province":"MB",
    "sg:tags":[
        "mall",
        "shopping",
        "center"
    ],
    "wof:name":"Corydon Village Mall Ltd",
    "wof:placetype":"venue"
},
  "geometry": {"coordinates":[-97.196716,49.863628],"type":"Point"}
}