{
  "type": "Feature",
  "properties": {
    "addr:full":"11 Av Hebert Baie-Comeau QC G4Z 1K8",
    "addr:postcode":"g4z 1k8",
    "addr:street":"11 Av Hebert",
    "iso:country":"CA",
    "sg:address":"11 Av Hebert",
    "sg:city":"Baie-Comeau",
    "sg:classifiers":[
        {
            "category":"Personal",
            "subcategory":"Beauty Salon",
            "type":"Services"
        }
    ],
    "sg:phone":"+1 418 296 2596",
    "sg:postcode":"G4Z 1K8",
    "sg:province":"QC",
    "wof:name":"Salon Coiffure Lucie Jacob",
    "wof:placetype":"venue"
},
  "geometry": {"coordinates":[-68.15674591059999,49.2191619873],"type":"Point"}
}