{
  "type": "Feature",
  "properties": {
    "addr:full":"1096 Rue Principale Albertville QC G0J 1A0",
    "addr:housenumber":"1096",
    "addr:postcode":"g0j 1a0",
    "addr:street":"Rue Principale",
    "iso:country":"CA",
    "sg:address":"1096 Rue Principale",
    "sg:city":"Albertville",
    "sg:classifiers":[
        {
            "category":"Education",
            "subcategory":"School",
            "type":"Public Place"
        }
    ],
    "sg:phone":"+1 418 756 3228",
    "sg:postcode":"G0J 1A0",
    "sg:province":"QC",
    "wof:name":"Ecole St-Raphael Albertville",
    "wof:placetype":"venue"
},
  "geometry": {"coordinates":[-67.373009,48.322128],"type":"Point"}
}