{
  "type": "Feature",
  "properties": {
    "addr:full":"29 Rue Saint-Pierre E Val-Brillant QC G0J 3L0",
    "addr:housenumber":"29",
    "addr:postcode":"g0j 3l0",
    "addr:street":"Rue Saint-Pierre E Val-Brillant",
    "iso:country":"CA",
    "sg:address":"29 Rue Saint-Pierre E",
    "sg:city":"Val-Brillant",
    "sg:classifiers":[
        {
            "category":"Restaurant",
            "type":"Food & Drink"
        }
    ],
    "sg:phone":"+1 418 742 3281",
    "sg:postcode":"G0J 3L0",
    "sg:province":"QC",
    "sg:tags":[
        "caterer"
    ],
    "wof:name":"Traiteur Cote",
    "wof:placetype":"venue"
},
  "geometry": {"coordinates":[-67.54418200000001,48.532822],"type":"Point"}
}