{
  "type": "Feature",
  "properties": {
    "addr:full":"789 111 Rte E LA Sarre QC J9Z 2X2",
    "addr:housenumber":"111",
    "addr:postcode":"j9z 2x2",
    "addr:street":"Rte E La Sarre",
    "iso:country":"CA",
    "sg:address":"789 111 Rte E",
    "sg:city":"LA Sarre",
    "sg:classifiers":[
        {
            "category":"Travel",
            "subcategory":"Hotels & Motels",
            "type":"Entertainment"
        }
    ],
    "sg:phone":"+1 819 333 2165",
    "sg:postcode":"J9Z 2X2",
    "sg:province":"QC",
    "wof:name":"Motel Claire",
    "wof:placetype":"venue"
},
  "geometry": {"coordinates":[-79.20031738279999,48.7975616455],"type":"Point"}
}