{
  "type": "Feature",
  "properties": {
    "iso:country":"CA",
    "sg:city":"Trail",
    "sg:classifiers":[
        {
            "category":"Health Services",
            "subcategory":"Doctor",
            "type":"Services"
        }
    ],
    "sg:phone":"+1 250 368 8802",
    "sg:postcode":"V1R 4T1",
    "sg:province":"BC",
    "sg:tags":[
        "physician",
        "clinic",
        "surgeon"
    ],
    "wof:name":"Sekirk Family Medicine",
    "wof:placetype":"venue"
},
  "geometry": {"coordinates":[-117.71221160899999,49.0964508057],"type":"Point"}
}