{
  "type": "Feature",
  "properties": {
    "addr:full":"Hawkestone ON L0L 1T0",
    "addr:postcode":"l0l 1t0",
    "iso:country":"CA",
    "sg:city":"Hawkestone",
    "sg:classifiers":[
        {
            "category":"Recreation",
            "type":"Entertainment"
        }
    ],
    "sg:phone":"+1 705 487 2711",
    "sg:postcode":"L0L 1T0",
    "sg:province":"ON",
    "sg:tags":[
        "stable"
    ],
    "wof:name":"Powys Hall Equestrian Ctr",
    "wof:placetype":"venue"
},
  "geometry": {"coordinates":[-79.4678726196,44.497467041],"type":"Point"}
}