{
  "type": "Feature",
  "properties": {
    "addr:full":"142 Longwood Rd N Hamilton ON L8S 3V9",
    "addr:housenumber":"142",
    "addr:postcode":"l8s 3v9",
    "addr:street":"Longwood Rd N",
    "iso:country":"CA",
    "sg:address":"142 Longwood Rd N",
    "sg:city":"Hamilton",
    "sg:classifiers":[
        {
            "category":"Professional",
            "subcategory":"Management & Consulting",
            "type":"Services"
        }
    ],
    "sg:phone":"+1 905 777 0001",
    "sg:postcode":"L8S 3V9",
    "sg:province":"ON",
    "sg:tags":[
        "consultant",
        "business"
    ],
    "wof:name":"Sterry Technical Support Svc",
    "wof:placetype":"venue"
},
  "geometry": {"coordinates":[-79.898338,43.268032],"type":"Point"}
}