{
  "type": "Feature",
  "properties": {
    "addr:full":"Lakefield ON K0L 2H0",
    "addr:postcode":"k0l 2h0",
    "iso:country":"CA",
    "sg:city":"Lakefield",
    "sg:classifiers":[
        {
            "category":"Building & Trades",
            "subcategory":"Construction",
            "type":"Services"
        }
    ],
    "sg:phone":"+1 705 652 8781",
    "sg:postcode":"K0L 2H0",
    "sg:province":"ON",
    "sg:tags":[
        "excavating",
        "contractor"
    ],
    "wof:name":"I D Dunford Haulage & Blldzng",
    "wof:placetype":"venue"
},
  "geometry": {"coordinates":[-78.2727813721,44.4225082397],"type":"Point"}
}