{
  "type": "Feature",
  "properties": {
    "addr:full":"274 Av Michaud Rimouski QC G5L 6A2",
    "addr:postcode":"g5l 6a2",
    "addr:street":"274 Av Michaud",
    "iso:country":"CA",
    "sg:address":"274 Av Michaud",
    "sg:city":"Rimouski",
    "sg:classifiers":[
        {
            "category":"Communications",
            "subcategory":"Film & Video Production",
            "type":"Services"
        }
    ],
    "sg:phone":"+1 418 725 0211",
    "sg:postcode":"G5L 6A2",
    "sg:province":"QC",
    "sg:tags":[
        "taping"
    ],
    "wof:name":"Paraloeil",
    "wof:placetype":"venue"
},
  "geometry": {"coordinates":[-68.5298614502,48.4420700073],"type":"Point"}
}