{
  "type": "Feature",
  "properties": {
    "addr:full":"48 Ch Laurier Saint-Norbert-D'Arthabaska QC G0P 1B0",
    "addr:housenumber":"48",
    "addr:postcode":"g0p 1b0",
    "addr:street":"Ch Laurier",
    "iso:country":"CA",
    "sg:address":"48 Ch Laurier",
    "sg:city":"Saint-Norbert-D'Arthabaska",
    "sg:classifiers":[
        {
            "category":"Autos & Motor Vehicles",
            "subcategory":"Automobile Sales",
            "type":"Retail Goods"
        }
    ],
    "sg:phone":"+1 819 369 9392",
    "sg:postcode":"G0P 1B0",
    "sg:province":"QC",
    "sg:tags":[
        "body",
        "car"
    ],
    "wof:name":"Garage Rene Labbe Auto Vette",
    "wof:placetype":"venue"
},
  "geometry": {"coordinates":[-71.883736,46.068264],"type":"Point"}
}