{
  "type": "Feature",
  "properties": {
    "addr:full":"108 Yorkville Ave Toronto ON M5R 1B9",
    "addr:housenumber":"108",
    "addr:postcode":"m5r 1b9",
    "addr:street":"Yorkville Ave",
    "iso:country":"CA",
    "sg:address":"108 Yorkville Ave",
    "sg:city":"Toronto",
    "sg:classifiers":[
        {
            "category":"Restaurant",
            "type":"Food & Drink"
        }
    ],
    "sg:phone":"+1 416 975 9084",
    "sg:postcode":"M5R 1B9",
    "sg:province":"ON",
    "wof:name":"Asuka Japanese Restaurant",
    "wof:placetype":"venue"
},
  "geometry": {"coordinates":[-79.392662,43.670959],"type":"Point"}
}