{
  "type": "Feature",
  "properties": {
    "iso:country":"CA",
    "sg:address":"4 Queen St W",
    "sg:city":"Cambridge",
    "sg:classifiers":[
        {
            "category":"Personal",
            "subcategory":"Beauty Salon",
            "type":"Services"
        }
    ],
    "sg:phone":"+1 519 651 2852",
    "sg:postcode":"N3C 1G1",
    "sg:province":"ON",
    "wof:name":"Dalena's Hair Design",
    "wof:placetype":"venue"
},
  "geometry": {"coordinates":[-80.3111038208,43.4309654236],"type":"Point"}
}