{
  "type": "Feature",
  "properties": {
    "addr:full":"778 Somerset St W Ottawa ON K1R 6R2",
    "addr:housenumber":"778",
    "addr:postcode":"k1r 6r2",
    "addr:street":"Somerset St W",
    "iso:country":"CA",
    "sg:address":"778 Somerset St W",
    "sg:city":"Ottawa",
    "sg:classifiers":[
        {
            "category":"Restaurant",
            "type":"Food & Drink"
        }
    ],
    "sg:phone":"+1 613 238 5815",
    "sg:postcode":"K1R 6R2",
    "sg:province":"ON",
    "wof:name":"Tom's Diner",
    "wof:placetype":"venue"
},
  "geometry": {"coordinates":[-75.70974,45.409878],"type":"Point"}
}