{
  "type": "Feature",
  "properties": {
    "addr:full":"623 Ash Grove Oakbank MB R0E 1J0",
    "addr:housenumber":"623",
    "addr:postcode":"r0e 1j0",
    "addr:street":"Ash Grove",
    "iso:country":"CA",
    "sg:address":"623 Ash Grove",
    "sg:city":"Oakbank",
    "sg:classifiers":[
        {
            "category":"Shopping",
            "subcategory":"Jewelry",
            "type":"Retail Goods"
        }
    ],
    "sg:phone":"+1 204 444 2962",
    "sg:postcode":"R0E 1J0",
    "sg:province":"MB",
    "sg:tags":[
        "jeweler"
    ],
    "wof:name":"Fran's Jewellers & Gift Btq",
    "wof:placetype":"venue"
},
  "geometry": {"coordinates":[-96.84240699999999,49.937611],"type":"Point"}
}