{
  "type": "Feature",
  "properties": {
    "iso:country":"CA",
    "sg:address":"2244 Lefeuvre Rd",
    "sg:city":"Abbotsford",
    "sg:classifiers":[
        {
            "category":"Education",
            "subcategory":"Special Training",
            "type":"Public Place"
        }
    ],
    "sg:phone":"+1 604 607 7735",
    "sg:postcode":"V4X 1C6",
    "sg:province":"BC",
    "sg:tags":[
        "instruction",
        "driving"
    ],
    "wof:name":"Pro Formance Racing Series",
    "wof:placetype":"venue"
},
  "geometry": {"coordinates":[-122.448402,49.042774],"type":"Point"}
}