{
  "type": "Feature",
  "properties": {
    "addr:full":"2333 Millar Ave Saskatoon SK S7K 2Y3",
    "addr:housenumber":"2333",
    "addr:postcode":"s7k 2y3",
    "addr:street":"Millar Ave",
    "iso:country":"CA",
    "sg:address":"2333 Millar Ave",
    "sg:city":"Saskatoon",
    "sg:classifiers":[
        {
            "category":"Home & Garden",
            "subcategory":"Garden Supply",
            "type":"Retail Goods"
        }
    ],
    "sg:phone":"+1 306 978 3988",
    "sg:postcode":"S7K 2Y3",
    "sg:province":"SK",
    "sg:tags":[
        "center",
        "landscape",
        "contractor"
    ],
    "wof:name":"River City Ornamental",
    "wof:placetype":"venue"
},
  "geometry": {"coordinates":[-106.648765564,52.1629104614],"type":"Point"}
}