{
  "type": "Feature",
  "properties": {
    "addr:full":"334 University Ave Fredericton NB E3B 4J1",
    "addr:housenumber":"334",
    "addr:postcode":"e3b 4j1",
    "addr:street":"University Ave",
    "iso:country":"CA",
    "sg:address":"334 University Ave",
    "sg:city":"Fredericton",
    "sg:classifiers":[
        {
            "category":"Real Estate",
            "subcategory":"Real Estate Agent",
            "type":"Services"
        }
    ],
    "sg:phone":"+1 506 472 4663",
    "sg:postcode":"E3B 4J1",
    "sg:province":"NB",
    "sg:tags":[
        "inspection"
    ],
    "wof:name":"House Master",
    "wof:placetype":"venue"
},
  "geometry": {"coordinates":[-66.63610799999999,45.952744],"type":"Point"}
}