{
  "type": "Feature",
  "properties": {
    "addr:full":"151 Park St Waterloo ON N2L 1Y5",
    "addr:housenumber":"151",
    "addr:postcode":"n2l 1y5",
    "addr:street":"Park St",
    "iso:country":"CA",
    "sg:address":"151 Park St",
    "sg:city":"Waterloo",
    "sg:classifiers":[
        {
            "category":"Health Services",
            "subcategory":"Medical Lab",
            "type":"Services"
        }
    ],
    "sg:phone":"+1 519 742 1467",
    "sg:postcode":"N2L 1Y5",
    "sg:province":"ON",
    "sg:tags":[
        "laboratory"
    ],
    "wof:name":"Caley Orthodontic Lab Ltd",
    "wof:placetype":"venue"
},
  "geometry": {"coordinates":[-80.520195,43.458393],"type":"Point"}
}