{
  "type": "Feature",
  "properties": {
    "addr:full":"3447 Douglas St Victoria BC V8Z 3L6",
    "addr:housenumber":"3447",
    "addr:postcode":"v8z 3l6",
    "addr:street":"Douglas St",
    "iso:country":"CA",
    "sg:address":"3447 Douglas St",
    "sg:city":"Victoria",
    "sg:classifiers":[
        {
            "category":"Autos & Motor Vehicles",
            "subcategory":"Fuel & Gas Station",
            "type":"Retail Goods"
        }
    ],
    "sg:phone":"+1 250 475 6695",
    "sg:postcode":"V8Z 3L6",
    "sg:province":"BC",
    "sg:tags":[
        "oil"
    ],
    "wof:name":"Town & Country Svc",
    "wof:placetype":"venue"
},
  "geometry": {"coordinates":[-123.372329712,48.4476699829],"type":"Point"}
}