{
  "type": "Feature",
  "properties": {
    "addr:full":"13705 100 St Grande Prairie AB T8V 4H4",
    "addr:housenumber":"13705",
    "addr:postcode":"t8v 4h4",
    "addr:street":"100 St",
    "iso:country":"CA",
    "sg:address":"13705 100 St",
    "sg:city":"Grande Prairie",
    "sg:classifiers":[
        {
            "category":"Wholesale",
            "subcategory":"Petroleum",
            "type":"Manufacturing & Wholesale Goods"
        }
    ],
    "sg:phone":"+1 780 532 2050",
    "sg:postcode":"T8V 4H4",
    "sg:province":"AB",
    "sg:tags":[
        "bulk",
        "oil",
        "gasoline"
    ],
    "wof:name":"United Farmers of Alberta",
    "wof:placetype":"venue"
},
  "geometry": {"coordinates":[-118.794197,55.199711],"type":"Point"}
}