{
  "type": "Feature",
  "properties": {
    "addr:full":"1490 Boul DE Maisonneuve O Montreal QC H3G 1N1",
    "addr:housenumber":"1490",
    "addr:postcode":"h3g 1n1",
    "addr:street":"Boul De Maisonneuve O",
    "iso:country":"CA",
    "sg:address":"1490 Boul DE Maisonneuve O",
    "sg:city":"Montreal",
    "sg:classifiers":[
        {
            "category":"Restaurant",
            "type":"Food & Drink"
        }
    ],
    "sg:phone":"+1 514 931 1570",
    "sg:postcode":"H3G 1N1",
    "sg:province":"QC",
    "wof:name":"Cafe Depot",
    "wof:placetype":"venue"
},
  "geometry": {"coordinates":[-73.55534400000001,45.521343],"type":"Point"}
}