{
  "type": "Feature",
  "properties": {
    "addr:full":"1833 Crescent Rd Victoria BC V8S 2G7",
    "addr:housenumber":"1833",
    "addr:postcode":"v8s 2g7",
    "addr:street":"Crescent Rd",
    "iso:country":"CA",
    "sg:address":"1833 Crescent Rd",
    "sg:city":"Victoria",
    "sg:classifiers":[
        {
            "category":"Shopping",
            "subcategory":"Computers & Home Electronics",
            "type":"Retail Goods"
        }
    ],
    "sg:phone":"+1 250 370 1305",
    "sg:postcode":"V8S 2G7",
    "sg:province":"BC",
    "sg:tags":[
        "software"
    ],
    "wof:name":"Systemsfarm Software Inc",
    "wof:placetype":"venue"
},
  "geometry": {"coordinates":[-123.32907104500001,48.4120597839],"type":"Point"}
}