{
  "type": "Feature",
  "properties": {
    "addr:full":"Gambo NL A0G 1T0",
    "addr:postcode":"gambo;a0g 1t0",
    "iso:country":"CA",
    "sg:city":"Gambo",
    "sg:classifiers":[
        {
            "category":"Personal",
            "subcategory":"Beauty Salon",
            "type":"Services"
        }
    ],
    "sg:phone":"+1 709 674 4441",
    "sg:postcode":"A0G 1T0",
    "sg:province":"NL",
    "wof:name":"Precision Cuts",
    "wof:placetype":"venue"
},
  "geometry": {"coordinates":[-54.211369,48.786751],"type":"Point"}
}