{
  "type": "Feature",
  "properties": {
    "addr:full":"225 Main St Laird SK S0K 2H0",
    "addr:housenumber":"225",
    "addr:postcode":"s0k 2h0",
    "addr:street":"Main St",
    "iso:country":"CA",
    "sg:address":"225 Main St",
    "sg:city":"Laird",
    "sg:classifiers":[
        {
            "category":"Government",
            "subcategory":"Office",
            "type":"Public Place"
        }
    ],
    "sg:phone":"+1 306 223 4292",
    "sg:postcode":"S0K 2H0",
    "sg:province":"SK",
    "sg:tags":[
        "repairing",
        "automobile",
        "village"
    ],
    "wof:name":"Laird Garage",
    "wof:placetype":"venue"
},
  "geometry": {"coordinates":[-106.590118,52.711208],"type":"Point"}
}