{
  "type": "Feature",
  "properties": {
    "iso:country":"CA",
    "sg:address":"1469 George St",
    "sg:city":"White Rock",
    "sg:classifiers":[
        {
            "category":"Organizations",
            "subcategory":"Community Association",
            "type":"Services"
        }
    ],
    "sg:phone":"+1 604 538 4016",
    "sg:postcode":"V4B 4A2",
    "sg:province":"BC",
    "sg:tags":[
        "fraternal"
    ],
    "wof:name":"Elk's Lodge",
    "wof:placetype":"venue"
},
  "geometry": {"coordinates":[-122.799934,49.028732],"type":"Point"}
}