{
  "type": "Feature",
  "properties": {
    "addr:full":"23397 Prince Albert Rd Chatham ON N7M 5J1",
    "addr:housenumber":"23397",
    "addr:postcode":"n7m 5j1",
    "addr:street":"Prince Albert Rd",
    "iso:country":"CA",
    "sg:address":"23397 Prince Albert Rd",
    "sg:city":"Chatham",
    "sg:classifiers":[
        {
            "category":"Shopping",
            "type":"Retail Goods"
        }
    ],
    "sg:phone":"+1 519 351 8077",
    "sg:postcode":"N7M 5J1",
    "sg:province":"ON",
    "sg:tags":[
        "wedding",
        "supply"
    ],
    "wof:name":"Merie's Cake 'N' Stuff",
    "wof:placetype":"venue"
},
  "geometry": {"coordinates":[-82.16325399999999,42.434399],"type":"Point"}
}