{
  "type": "Feature",
  "properties": {
    "iso:country":"CA",
    "sg:address":"9 Whiteway Pl",
    "sg:city":"St. John's",
    "sg:classifiers":[
        {
            "category":"Banks & Credit Unions",
            "subcategory":"Investment Brokerage",
            "type":"Services"
        }
    ],
    "sg:phone":"+1 709 738 2903",
    "sg:postcode":"A1B 1J7",
    "sg:province":"NL",
    "wof:name":"Rocky & Marine Ltd",
    "wof:placetype":"venue"
},
  "geometry": {"coordinates":[-52.7226066589,47.5712966919],"type":"Point"}
}