{
  "type": "Feature",
  "properties": {
    "addr:full":"Montreal QC H3B 1A2",
    "addr:postcode":"h3b 1a2",
    "iso:country":"CA",
    "sg:city":"Montreal",
    "sg:classifiers":[
        {
            "category":"Shopping",
            "subcategory":"Music",
            "type":"Retail Goods"
        }
    ],
    "sg:phone":"+1 514 393 6410",
    "sg:postcode":"H3B 1A2",
    "sg:province":"QC",
    "sg:tags":[
        "compact",
        "record",
        "disc",
        "tape"
    ],
    "wof:name":"Ricochet Disques",
    "wof:placetype":"venue"
},
  "geometry": {"coordinates":[-73.5605316162,45.5133514404],"type":"Point"}
}