{
  "type": "Feature",
  "properties": {
    "addr:full":"219 Rue Jacques-Cartier N Saint-Jean-Sur-Richelieu QC J3B 6T3",
    "addr:housenumber":"219",
    "addr:postcode":"j3b 6t3",
    "addr:street":"Rue Jacques-Cartier N",
    "iso:country":"CA",
    "sg:address":"219 Rue Jacques-Cartier N",
    "sg:city":"Saint-Jean-Sur-Richelieu",
    "sg:classifiers":[
        {
            "category":"Manufacturing",
            "subcategory":"Apparel",
            "type":"Manufacturing & Wholesale Goods"
        }
    ],
    "sg:phone":"+1 450 346 1141",
    "sg:postcode":"J3B 6T3",
    "sg:province":"QC",
    "sg:tags":[
        "flag",
        "banner"
    ],
    "wof:name":"Societe Nationale-Quebecois",
    "wof:placetype":"venue"
},
  "geometry": {"coordinates":[-73.2532501221,45.3067626953],"type":"Point"}
}