{
  "type": "Feature",
  "properties": {
    "addr:full":"PO Box 750 Evansburg AB T0E 0T0",
    "addr:housenumber":"po",
    "addr:postcode":"t0e 0t0",
    "addr:street":"Box 750",
    "iso:country":"CA",
    "sg:address":"PO Box 750",
    "sg:city":"Evansburg",
    "sg:classifiers":[
        {
            "category":"Wholesale",
            "subcategory":"Machinery & Supplies",
            "type":"Manufacturing & Wholesale Goods"
        }
    ],
    "sg:phone":"+1 780 727 2056",
    "sg:postcode":"T0E 0T0",
    "sg:province":"AB",
    "sg:tags":[
        "farm",
        "equipment"
    ],
    "wof:name":"B & P Svc & Repair",
    "wof:placetype":"venue"
},
  "geometry": {"coordinates":[-115.021156,53.593845],"type":"Point"}
}