{
  "type": "Feature",
  "properties": {
    "iso:country":"CA",
    "sg:address":"21071 Dalton Rd",
    "sg:city":"Sutton West",
    "sg:classifiers":[
        {
            "category":"Health Services",
            "subcategory":"Doctor",
            "type":"Services"
        }
    ],
    "sg:phone":"+1 905 722 9070",
    "sg:postcode":"L0E 1R0",
    "sg:province":"ON",
    "sg:tags":[
        "physician",
        "surgeon"
    ],
    "wof:name":"Moir, Vivian MD",
    "wof:placetype":"venue"
},
  "geometry": {"coordinates":[-79.364571,44.307949],"type":"Point"}
}