{
  "type": "Feature",
  "properties": {
    "addr:full":"3150 Rue Massenet Brossard QC J4Y 1J1",
    "addr:housenumber":"3150",
    "addr:postcode":"j4y 1j1",
    "addr:street":"Rue Massenet",
    "iso:country":"CA",
    "sg:address":"3150 Rue Massenet",
    "sg:city":"Brossard",
    "sg:classifiers":[
        {
            "category":"Building & Trades",
            "subcategory":"Plumbing",
            "type":"Services"
        }
    ],
    "sg:phone":"+1 450 462 3275",
    "sg:postcode":"J4Y 1J1",
    "sg:province":"QC",
    "sg:tags":[
        "contractor"
    ],
    "wof:name":"Plomberie Charbonneau Inc",
    "wof:placetype":"venue"
},
  "geometry": {"coordinates":[-73.456062,45.459663],"type":"Point"}
}