{
  "type": "Feature",
  "properties": {
    "addr:full":"South Porcupine ON P0N 1H0",
    "addr:postcode":"p0n 1h0",
    "addr:street":"South",
    "iso:country":"CA",
    "sg:city":"South Porcupine",
    "sg:classifiers":[
        {
            "category":"Retail",
            "subcategory":"Repair Shop",
            "type":"Services"
        }
    ],
    "sg:phone":"+1 705 235 8950",
    "sg:postcode":"P0N 1H0",
    "sg:province":"ON",
    "sg:tags":[
        "tool",
        "parts"
    ],
    "wof:name":"Porcupine Air Tool Repair",
    "wof:placetype":"venue"
},
  "geometry": {"coordinates":[-81.20747375489999,48.4707450867],"type":"Point"}
}