{
  "type": "Feature",
  "properties": {
    "iso:country":"CA",
    "sg:city":"Waterloo",
    "sg:classifiers":[
        {
            "category":"Sports & Exercise",
            "subcategory":"Golf",
            "type":"Entertainment"
        }
    ],
    "sg:phone":"+1 519 888 0575",
    "sg:postcode":"N2J 3Z4",
    "sg:province":"ON",
    "sg:tags":[
        "course"
    ],
    "wof:name":"Westhill Meadows Golf Course",
    "wof:placetype":"venue"
},
  "geometry": {"coordinates":[-80.520691,43.463139],"type":"Point"}
}