{
  "type": "Feature",
  "properties": {
    "addr:full":"120 Isabella St Parry Sound ON P2A 1N1",
    "addr:housenumber":"120",
    "addr:postcode":"p2a 1n1",
    "addr:street":"Isabella St",
    "iso:country":"CA",
    "sg:address":"120 Isabella St",
    "sg:city":"Parry Sound",
    "sg:classifiers":[
        {
            "category":"Building & Trades",
            "subcategory":"Construction",
            "type":"Services"
        }
    ],
    "sg:phone":"+1 705 746 7011",
    "sg:postcode":"P2A 1N1",
    "sg:province":"ON",
    "sg:tags":[
        "general",
        "contractor"
    ],
    "wof:name":"M Tucci Construction Ltd",
    "wof:placetype":"venue"
},
  "geometry": {"coordinates":[-80.037544,45.3535],"type":"Point"}
}