{
  "type": "Feature",
  "properties": {
    "iso:country":"CA",
    "sg:address":"4400 32 St # 905",
    "sg:city":"Vernon",
    "sg:classifiers":[
        {
            "category":"Restaurant",
            "type":"Food & Drink"
        }
    ],
    "sg:phone":"+1 250 558 5949",
    "sg:postcode":"V1T 9H2",
    "sg:province":"BC",
    "wof:name":"Joey's Only Seafood Restaurant",
    "wof:placetype":"venue"
},
  "geometry": {"coordinates":[-119.27421569800001,50.2766571045],"type":"Point"}
}