{
  "type": "Feature",
  "properties": {
    "iso:country":"CA",
    "sg:address":"1620 Dundas St",
    "sg:city":"London",
    "sg:classifiers":[
        {
            "category":"Shopping",
            "subcategory":"Hobbies, Toys, & Games",
            "type":"Retail Goods"
        }
    ],
    "sg:phone":"+1 519 451 1833",
    "sg:postcode":"N5W 3C4",
    "sg:province":"ON",
    "sg:tags":[
        "model",
        "supply"
    ],
    "wof:name":"Avf Hobbies",
    "wof:placetype":"venue"
},
  "geometry": {"coordinates":[-81.191238,43.000549],"type":"Point"}
}