{
  "type": "Feature",
  "properties": {
    "iso:country":"CA",
    "sg:address":"Mc Elligot Dr",
    "sg:city":"Beachburg",
    "sg:classifiers":[
        {
            "category":"Recreation",
            "type":"Entertainment"
        }
    ],
    "sg:phone":"+1 613 584 3032",
    "sg:postcode":"K0J 1C0",
    "sg:province":"ON",
    "sg:tags":[
        "course",
        "golf"
    ],
    "wof:name":"Deep River Golf Club Inc",
    "wof:placetype":"venue"
},
  "geometry": {"coordinates":[-76.8517990112,45.7250289917],"type":"Point"}
}