{
  "type": "Feature",
  "properties": {
    "iso:country":"CA",
    "sg:address":"254 Almont Ave",
    "sg:city":"New Glasgow",
    "sg:classifiers":[
        {
            "category":"Building & Trades",
            "subcategory":"Electrical",
            "type":"Services"
        }
    ],
    "sg:phone":"+1 902 752 5266",
    "sg:postcode":"B2H 3G9",
    "sg:province":"NS",
    "sg:tags":[
        "electric",
        "contractor"
    ],
    "wof:name":"Phillip Murray Electric",
    "wof:placetype":"venue"
},
  "geometry": {"coordinates":[-62.6378173828,45.5934562683],"type":"Point"}
}