{
  "type": "Feature",
  "properties": {
    "addr:full":"Montreal QC H3S 1Y7",
    "addr:postcode":"h3s 1y7",
    "iso:country":"CA",
    "sg:city":"Montreal",
    "sg:classifiers":[
        {
            "category":"Restaurant",
            "type":"Food & Drink"
        }
    ],
    "sg:phone":"+1 514 734 1221",
    "sg:postcode":"H3S 1Y7",
    "sg:province":"QC",
    "wof:name":"Bocadillos Snack",
    "wof:placetype":"venue"
},
  "geometry": {"coordinates":[-73.6287231445,45.4994659424],"type":"Point"}
}