{
  "type": "Feature",
  "properties": {
    "addr:full":"Church St Guysborough NS B0H 1N0",
    "addr:postcode":"b0h 1n0",
    "addr:street":"Church St",
    "iso:country":"CA",
    "sg:address":"Church St",
    "sg:city":"Guysborough",
    "sg:classifiers":[
        {
            "category":"Museum",
            "type":"Entertainment"
        }
    ],
    "sg:phone":"+1 902 533 4008",
    "sg:postcode":"B0H 1N0",
    "sg:province":"NS",
    "wof:name":"Guysborough Historical Society",
    "wof:placetype":"venue"
},
  "geometry": {"coordinates":[-61.5033874512,45.3940658569],"type":"Point"}
}