{
  "type": "Feature",
  "properties": {
    "addr:full":"153 Railway Ave N Grandview MB R0L 0Y0",
    "addr:housenumber":"153",
    "addr:postcode":"r0l 0y0",
    "addr:street":"Railway Ave N",
    "iso:country":"CA",
    "sg:address":"153 Railway Ave N",
    "sg:city":"Grandview",
    "sg:classifiers":[
        {
            "category":"Home & Garden",
            "subcategory":"Garden Supply",
            "type":"Retail Goods"
        }
    ],
    "sg:phone":"+1 204 546 2823",
    "sg:postcode":"R0L 0Y0",
    "sg:province":"MB",
    "sg:tags":[
        "engine",
        "lawn"
    ],
    "wof:name":"Grandview Small Motor Shop",
    "wof:placetype":"venue"
},
  "geometry": {"coordinates":[-100.69960021999999,51.1684112549],"type":"Point"}
}