{
  "type": "Feature",
  "properties": {
    "addr:full":"10 Meander Close Carlisle ON L0R 1H1",
    "addr:housenumber":"10",
    "addr:postcode":"l0r 1h1",
    "addr:street":"Meander Close",
    "iso:country":"CA",
    "sg:address":"10 Meander Close",
    "sg:city":"Carlisle",
    "sg:classifiers":[
        {
            "category":"Freight",
            "type":"Transportation"
        }
    ],
    "sg:phone":"+1 905 689 2727",
    "sg:postcode":"L0R 1H1",
    "sg:province":"ON",
    "sg:tags":[
        "consultant"
    ],
    "wof:name":"Blair H Gough & Assoc Inc",
    "wof:placetype":"venue"
},
  "geometry": {"coordinates":[-79.97776,43.389629],"type":"Point"}
}