{
  "type": "Feature",
  "properties": {
    "iso:country":"CA",
    "sg:address":"1216 Boul Cure-Labelle",
    "sg:city":"Laval",
    "sg:classifiers":[
        {
            "category":"Restaurant",
            "type":"Food & Drink"
        }
    ],
    "sg:phone":"+1 450 681 3307",
    "sg:postcode":"H7V 2V5",
    "sg:province":"QC",
    "wof:name":"Restaurant Chez Lien",
    "wof:placetype":"venue"
},
  "geometry": {"coordinates":[-73.753304,45.545277],"type":"Point"}
}