{
  "type": "Feature",
  "properties": {
    "addr:full":"664 Topsail Rd St. John's NL A1E 2E2",
    "addr:housenumber":"664",
    "addr:postcode":"a1e 2e2",
    "addr:street":"Topsail Rd",
    "iso:country":"CA",
    "sg:address":"664 Topsail Rd",
    "sg:city":"St. John's",
    "sg:classifiers":[
        {
            "category":"Banks & Credit Unions",
            "subcategory":"Bank",
            "type":"Services"
        }
    ],
    "sg:phone":"+1 709 576 4606",
    "sg:postcode":"A1E 2E2",
    "sg:province":"NL",
    "wof:name":"Royal Bank Financial Group",
    "wof:placetype":"venue"
},
  "geometry": {"coordinates":[-52.771591,47.52449],"type":"Point"}
}