{
  "type": "Feature",
  "properties": {
    "addr:full":"Woodbridge ON L4L 2C7",
    "addr:postcode":"l4l 2c7",
    "iso:country":"CA",
    "sg:city":"Woodbridge",
    "sg:classifiers":[
        {
            "category":"Shopping",
            "subcategory":"Clothing, Apparel, & Fashions",
            "type":"Retail Goods"
        }
    ],
    "sg:phone":"+1 905 850 8262",
    "sg:postcode":"L4L 2C7",
    "sg:province":"ON",
    "sg:tags":[
        "furnishing"
    ],
    "wof:name":"Divo Clothing",
    "wof:placetype":"venue"
},
  "geometry": {"coordinates":[-79.6099243164,43.7769355774],"type":"Point"}
}