{
  "type": "Feature",
  "properties": {
    "addr:full":"121 5th St SE Portage LA Prairie MB R1N 1H5",
    "addr:housenumber":"121",
    "addr:postcode":"r1n 1h5",
    "addr:street":"5Th St Se",
    "iso:country":"CA",
    "sg:address":"121 5th St SE",
    "sg:city":"Portage LA Prairie",
    "sg:classifiers":[
        {
            "category":"Organizations",
            "subcategory":"Religious Organization",
            "type":"Services"
        }
    ],
    "sg:phone":"+1 204 239 7203",
    "sg:postcode":"R1N 1H5",
    "sg:province":"MB",
    "sg:tags":[
        "church"
    ],
    "wof:name":"Portage Alliance Church",
    "wof:placetype":"venue"
},
  "geometry": {"coordinates":[-98.283424,49.969753],"type":"Point"}
}