{
  "type": "Feature",
  "properties": {
    "addr:full":"2935 Boul Laframboise Saint-Hyacinthe QC J2S 4Z3",
    "addr:housenumber":"2935",
    "addr:postcode":"j2s 4z3",
    "addr:street":"Boul Laframboise",
    "iso:country":"CA",
    "sg:address":"2935 Boul Laframboise",
    "sg:city":"Saint-Hyacinthe",
    "sg:classifiers":[
        {
            "category":"Shopping",
            "subcategory":"Pharmacy",
            "type":"Retail Goods"
        }
    ],
    "sg:phone":"+1 450 774 7954",
    "sg:postcode":"J2S 4Z3",
    "sg:province":"QC",
    "wof:name":"Jean Coutu",
    "wof:placetype":"venue"
},
  "geometry": {"coordinates":[-72.964066,45.634216],"type":"Point"}
}