{
  "type": "Feature",
  "properties": {
    "addr:full":"Dartmouth NS B3B 1V7",
    "addr:postcode":"b3b 1v7",
    "iso:country":"CA",
    "sg:city":"Dartmouth",
    "sg:classifiers":[
        {
            "category":"Professional",
            "subcategory":"Detective & Security Services",
            "type":"Services"
        }
    ],
    "sg:phone":"+1 902 468 9001",
    "sg:postcode":"B3B 1V7",
    "sg:province":"NS",
    "sg:tags":[
        "investigator"
    ],
    "wof:name":"D F Barry & Assoc",
    "wof:placetype":"venue"
},
  "geometry": {"coordinates":[-63.609947,44.705791],"type":"Point"}
}