{
  "type": "Feature",
  "properties": {
    "addr:full":"3513 Lake Shore Blvd W Etobicoke ON M8W 1N5",
    "addr:housenumber":"3513",
    "addr:postcode":"m8w 1n5",
    "addr:street":"Lake Shore Blvd W",
    "iso:country":"CA",
    "sg:address":"3513 Lake Shore Blvd W",
    "sg:city":"Etobicoke",
    "sg:classifiers":[
        {
            "category":"Retail",
            "subcategory":"Repair Shop",
            "type":"Services"
        }
    ],
    "sg:phone":"+1 416 251 9326",
    "sg:postcode":"M8W 1N5",
    "sg:province":"ON",
    "sg:tags":[
        "refinishing",
        "furniture"
    ],
    "wof:name":"Badger & Son",
    "wof:placetype":"venue"
},
  "geometry": {"coordinates":[-79.5315856934,43.5947952271],"type":"Point"}
}