{
  "type": "Feature",
  "properties": {
    "iso:country":"CA",
    "sg:address":"1751 Boul Saint-Jean-Baptiste",
    "sg:city":"Chicoutimi",
    "sg:classifiers":[
        {
            "category":"Education",
            "subcategory":"College",
            "type":"Public Place"
        }
    ],
    "sg:phone":"+1 418 545 9144",
    "sg:postcode":"G7H 7V1",
    "sg:province":"QC",
    "sg:tags":[
        "academic",
        "school"
    ],
    "wof:name":"Centre Ephata",
    "wof:placetype":"venue"
},
  "geometry": {"coordinates":[-71.0174255371,48.4079360962],"type":"Point"}
}