{
  "type": "Feature",
  "properties": {
    "addr:full":"297 Victoria St N Kitchener ON N2H 5E1",
    "addr:housenumber":"297",
    "addr:postcode":"n2h 5e1",
    "addr:street":"Victoria St N",
    "iso:country":"CA",
    "sg:address":"297 Victoria St N",
    "sg:city":"Kitchener",
    "sg:classifiers":[
        {
            "category":"Restaurant",
            "type":"Food & Drink"
        }
    ],
    "sg:phone":"+1 519 743 4945",
    "sg:postcode":"N2H 5E1",
    "sg:province":"ON",
    "wof:name":"Jimmy's Lunch",
    "wof:placetype":"venue"
},
  "geometry": {"coordinates":[-80.484818,43.457661],"type":"Point"}
}