{
  "type": "Feature",
  "properties": {
    "addr:full":"117 King St Whitby ON L1N 4Z1",
    "addr:housenumber":"117",
    "addr:postcode":"l1n 4z1",
    "addr:street":"King St",
    "iso:country":"CA",
    "sg:address":"117 King St",
    "sg:city":"Whitby",
    "sg:classifiers":[
        {
            "category":"Professional",
            "subcategory":"Lawyer & Legal Services",
            "type":"Services"
        }
    ],
    "sg:phone":"+1 905 668 7704",
    "sg:postcode":"L1N 4Z1",
    "sg:province":"ON",
    "sg:tags":[
        "attorney"
    ],
    "wof:name":"Babbs, Donna",
    "wof:placetype":"venue"
},
  "geometry": {"coordinates":[-78.9452209473,43.8778305054],"type":"Point"}
}