{
  "type": "Feature",
  "properties": {
    "iso:country":"CA",
    "sg:address":"160 Maple St",
    "sg:city":"Melita",
    "sg:classifiers":[
        {
            "category":"Home & Garden",
            "subcategory":"Building Materials",
            "type":"Retail Goods"
        }
    ],
    "sg:phone":"+1 204 522 3278",
    "sg:postcode":"R0M 1L0",
    "sg:province":"MB",
    "sg:tags":[
        "lumber"
    ],
    "wof:name":"Stewart's Lumber & Supply",
    "wof:placetype":"venue"
},
  "geometry": {"coordinates":[-100.993537903,49.2708740234],"type":"Point"}
}