{
  "type": "Feature",
  "properties": {
    "iso:country":"CA",
    "sg:city":"Kelowna",
    "sg:classifiers":[
        {
            "category":"Shopping",
            "subcategory":"Used Merchandise",
            "type":"Retail Goods"
        }
    ],
    "sg:phone":"+1 250 860 7744",
    "sg:postcode":"V1X 4J8",
    "sg:province":"BC",
    "sg:tags":[
        "pawnbroker"
    ],
    "wof:name":"Darky's Pawn Inc",
    "wof:placetype":"venue"
},
  "geometry": {"coordinates":[-119.409607,49.900204],"type":"Point"}
}