{
  "type": "Feature",
  "properties": {
    "addr:full":"Kelowna BC V1X 4J8",
    "addr:postcode":"v1x 4j8",
    "iso:country":"CA",
    "sg:city":"Kelowna",
    "sg:classifiers":[
        {
            "category":"Shopping",
            "subcategory":"Used Merchandise",
            "type":"Retail Goods"
        }
    ],
    "sg:phone":"+1 250 860 7744",
    "sg:postcode":"V1X 4J8",
    "sg:province":"BC",
    "sg:tags":[
        "pawnbroker"
    ],
    "wof:name":"Darky's Pawn Inc",
    "wof:placetype":"venue"
},
  "geometry": {"coordinates":[-119.40960699999999,49.900204],"type":"Point"}
}