{
  "type": "Feature",
  "properties": {
    "addr:full":"Gravenhurst ON P1P 1R1",
    "addr:postcode":"p1p 1r1",
    "iso:country":"CA",
    "sg:city":"Gravenhurst",
    "sg:classifiers":[
        {
            "category":"Shopping",
            "subcategory":"Computers & Home Electronics",
            "type":"Retail Goods"
        }
    ],
    "sg:phone":"+1 705 687 8076",
    "sg:postcode":"P1P 1R1",
    "sg:province":"ON",
    "sg:tags":[
        "equipment",
        "dealer"
    ],
    "wof:name":"Brunton Farm",
    "wof:placetype":"venue"
},
  "geometry": {"coordinates":[-79.373695,44.920841],"type":"Point"}
}