{
  "type": "Feature",
  "properties": {
    "addr:full":"6277 Av Lennox Montreal QC H3S 2N6",
    "addr:housenumber":"6277",
    "addr:postcode":"h3s 2n6",
    "addr:street":"Av Lennox",
    "iso:country":"CA",
    "sg:address":"6277 Av Lennox",
    "sg:city":"Montreal",
    "sg:classifiers":[
        {
            "category":"Real Estate",
            "subcategory":"Real Estate Agent",
            "type":"Services"
        }
    ],
    "sg:phone":"+1 514 342 6597",
    "sg:postcode":"H3S 2N6",
    "sg:province":"QC",
    "sg:tags":[
        "investment"
    ],
    "wof:name":"Astor Holdings Inc",
    "wof:placetype":"venue"
},
  "geometry": {"coordinates":[-73.623276,45.512989],"type":"Point"}
}