{
  "type": "Feature",
  "properties": {
    "addr:full":"3323 118 Ave NW Edmonton AB T5W 4X1",
    "addr:housenumber":"3323",
    "addr:postcode":"t5w 4x1",
    "addr:street":"118 Ave Nw",
    "iso:country":"CA",
    "sg:address":"3323 118 Ave NW",
    "sg:city":"Edmonton",
    "sg:classifiers":[
        {
            "category":"Banks & Credit Unions",
            "subcategory":"Bank",
            "type":"Services"
        }
    ],
    "sg:phone":"+1 780 477 9715",
    "sg:postcode":"T5W 4X1",
    "sg:province":"AB",
    "sg:tags":[
        "cashing",
        "check"
    ],
    "wof:name":"Financial Stop",
    "wof:placetype":"venue"
},
  "geometry": {"coordinates":[-113.392616,53.57019],"type":"Point"}
}