{
  "type": "Feature",
  "properties": {
    "addr:full":"358 Simpson St New Westminster BC V3L 3J9",
    "addr:housenumber":"358",
    "addr:postcode":"v3l 3j9",
    "addr:street":"Simpson St",
    "iso:country":"CA",
    "sg:address":"358 Simpson St",
    "sg:city":"New Westminster",
    "sg:classifiers":[
        {
            "category":"Travel",
            "subcategory":"Hotels & Motels",
            "type":"Entertainment"
        }
    ],
    "sg:phone":"+1 604 524 3060",
    "sg:postcode":"V3L 3J9",
    "sg:province":"BC",
    "sg:tags":[
        "breakfast",
        "accommodation",
        "bed"
    ],
    "wof:name":"Hillhouse Bed & Breakfast",
    "wof:placetype":"venue"
},
  "geometry": {"coordinates":[-122.89613300000001,49.224483],"type":"Point"}
}