{
  "type": "Feature",
  "properties": {
    "iso:country":"CA",
    "sg:address":"6560 Sooke Rd",
    "sg:city":"Sooke",
    "sg:classifiers":[
        {
            "category":"Education",
            "subcategory":"School",
            "type":"Public Place"
        }
    ],
    "sg:phone":"+1 250 642 5431",
    "sg:postcode":"V0S 1N0",
    "sg:province":"BC",
    "wof:name":"Sooke Elementary",
    "wof:placetype":"venue"
},
  "geometry": {"coordinates":[-123.71621704099999,48.3799781799],"type":"Point"}
}