{
  "type": "Feature",
  "properties": {
    "addr:full":"1144 Av Cartier Quebec QC G1R 2S5",
    "addr:housenumber":"1144",
    "addr:postcode":"g1r 2s5",
    "addr:street":"Av Cartier",
    "iso:country":"CA",
    "sg:address":"1144 Av Cartier",
    "sg:city":"Quebec",
    "sg:classifiers":[
        {
            "category":"Restaurant",
            "type":"Food & Drink"
        }
    ],
    "sg:phone":"+1 418 647 1313",
    "sg:postcode":"G1R 2S5",
    "sg:province":"QC",
    "wof:name":"Restaurant Momento",
    "wof:placetype":"venue"
},
  "geometry": {"coordinates":[-71.2253646851,46.8031654358],"type":"Point"}
}