{
  "type": "Feature",
  "properties": {
    "addr:full":"55 Harbour Sq Toronto ON M5J 2L1",
    "addr:housenumber":"55",
    "addr:postcode":"m5j 2l1",
    "addr:street":"Harbour Sq",
    "iso:country":"CA",
    "sg:address":"55 Harbour Sq",
    "sg:city":"Toronto",
    "sg:classifiers":[
        {
            "category":"Banks & Credit Unions",
            "subcategory":"Investment Brokerage",
            "type":"Services"
        }
    ],
    "sg:phone":"+1 416 362 4570",
    "sg:postcode":"M5J 2L1",
    "sg:province":"ON",
    "sg:tags":[
        "security"
    ],
    "wof:name":"Elexon Securities Corp",
    "wof:placetype":"venue"
},
  "geometry": {"coordinates":[-79.37893699999999,43.641399],"type":"Point"}
}