{
  "type": "Feature",
  "properties": {
    "addr:full":"Hearst ON P0L 1N0",
    "addr:postcode":"p0l 1n0",
    "iso:country":"CA",
    "sg:city":"Hearst",
    "sg:classifiers":[
        {
            "category":"Organizations",
            "subcategory":"Religious Organization",
            "type":"Services"
        }
    ],
    "sg:phone":"+1 705 362 8405",
    "sg:postcode":"P0L 1N0",
    "sg:province":"ON",
    "sg:tags":[
        "church"
    ],
    "wof:name":"Presbytere DE Jogues",
    "wof:placetype":"venue"
},
  "geometry": {"coordinates":[-83.6649475098,49.6893157959],"type":"Point"}
}