{
  "type": "Feature",
  "properties": {
    "iso:country":"CA",
    "sg:address":"8030 Rue Normandie",
    "sg:city":"Brossard",
    "sg:classifiers":[
        {
            "category":"Professional",
            "subcategory":"Management & Consulting",
            "type":"Services"
        }
    ],
    "sg:phone":"+1 450 445 8443",
    "sg:postcode":"J4Y 1W6",
    "sg:province":"QC",
    "sg:tags":[
        "consultant",
        "instructional"
    ],
    "wof:name":"Pause Formation En Entreprises",
    "wof:placetype":"venue"
},
  "geometry": {"coordinates":[-73.46542358400001,45.4476928711],"type":"Point"}
}