{
  "type": "Feature",
  "properties": {
    "addr:full":"Peterborough ON K9J 2T8",
    "addr:postcode":"k9j 2t8",
    "iso:country":"CA",
    "sg:city":"Peterborough",
    "sg:classifiers":[
        {
            "category":"Health Services",
            "subcategory":"Health Practitioner",
            "type":"Services"
        }
    ],
    "sg:phone":"+1 705 745 7640",
    "sg:postcode":"K9J 2T8",
    "sg:province":"ON",
    "sg:tags":[
        "midwife"
    ],
    "wof:name":"Kawartha Community Midwives",
    "wof:placetype":"venue"
},
  "geometry": {"coordinates":[-78.321648,44.30349],"type":"Point"}
}