{
  "type": "Feature",
  "properties": {
    "addr:full":"Musgrave Harbour NL A0G 3J0",
    "addr:postcode":"a0g 3j0",
    "addr:street":"Musgrave",
    "iso:country":"CA",
    "sg:city":"Musgrave Harbour",
    "sg:classifiers":[
        {
            "category":"Organizations",
            "subcategory":"Religious Organization",
            "type":"Services"
        }
    ],
    "sg:phone":"+1 709 655 2847",
    "sg:postcode":"A0G 3J0",
    "sg:province":"NL",
    "sg:tags":[
        "church"
    ],
    "wof:name":"Pentecostal Church",
    "wof:placetype":"venue"
},
  "geometry": {"coordinates":[-53.964298,49.44767],"type":"Point"}
}