{
  "type": "Feature",
  "properties": {
    "addr:full":"Mississauga ON L5S 1H1",
    "addr:postcode":"l5s 1h1",
    "iso:country":"CA",
    "sg:city":"Mississauga",
    "sg:classifiers":[
        {
            "category":"Professional",
            "subcategory":"Advertising",
            "type":"Services"
        }
    ],
    "sg:phone":"+1 905 405 0550",
    "sg:postcode":"L5S 1H1",
    "sg:province":"ON",
    "sg:tags":[
        "designer",
        "display",
        "producer"
    ],
    "wof:name":"M & M Exhibits",
    "wof:placetype":"venue"
},
  "geometry": {"coordinates":[-79.65701300000001,43.694534],"type":"Point"}
}