{
  "type": "Feature",
  "properties": {
    "addr:full":"676 Chilco St Vancouver BC V6G 3B3",
    "addr:housenumber":"676",
    "addr:postcode":"v6g 3b3",
    "addr:street":"Chilco St",
    "iso:country":"CA",
    "sg:address":"676 Chilco St",
    "sg:city":"Vancouver",
    "sg:classifiers":[
        {
            "category":"Personal",
            "type":"Services"
        }
    ],
    "sg:phone":"+1 604 688 0770",
    "sg:postcode":"V6G 3B3",
    "sg:province":"BC",
    "sg:tags":[
        "wedding",
        "chapel"
    ],
    "wof:name":"Chapel At Stanley Park",
    "wof:placetype":"venue"
},
  "geometry": {"coordinates":[-123.137032,49.294117],"type":"Point"}
}