{
  "type": "Feature",
  "properties": {
    "addr:full":"3236 Broadway W Vancouver BC V6K 2H4",
    "addr:housenumber":"3236",
    "addr:postcode":"v6k 2h4",
    "addr:street":"Broadway W",
    "iso:country":"CA",
    "sg:address":"3236 Broadway W",
    "sg:city":"Vancouver",
    "sg:classifiers":[
        {
            "category":"Food & Beverages",
            "subcategory":"Bakery",
            "type":"Retail Goods"
        }
    ],
    "sg:phone":"+1 604 730 9553",
    "sg:postcode":"V6K 2H4",
    "sg:province":"BC",
    "sg:tags":[
        "baker"
    ],
    "wof:name":"Mascotte Bakery & Cafe Ltd",
    "wof:placetype":"venue"
},
  "geometry": {"coordinates":[-123.17654400000001,49.264057],"type":"Point"}
}