{
  "type": "Feature",
  "properties": {
    "addr:full":"Victoria BC V9B 5E3",
    "addr:postcode":"v9b 5e3",
    "iso:country":"CA",
    "sg:city":"Victoria",
    "sg:classifiers":[
        {
            "category":"Shopping",
            "subcategory":"Clothing, Apparel, & Fashions",
            "type":"Retail Goods"
        }
    ],
    "sg:phone":"+1 250 474 2597",
    "sg:postcode":"V9B 5E3",
    "sg:province":"BC",
    "sg:tags":[
        "jean"
    ],
    "wof:name":"Bootlegger",
    "wof:placetype":"venue"
},
  "geometry": {"coordinates":[-123.36451700000001,48.428314],"type":"Point"}
}