{
  "type": "Feature",
  "properties": {
    "addr:full":"407 Boul Cartier O Laval QC H7N 2L1",
    "addr:housenumber":"407",
    "addr:postcode":"h7n 2l1",
    "addr:street":"Boul Cartier O",
    "iso:country":"CA",
    "sg:address":"407 Boul Cartier O",
    "sg:city":"Laval",
    "sg:classifiers":[
        {
            "category":"Food & Beverages",
            "subcategory":"Groceries & Convenience Stores",
            "type":"Retail Goods"
        }
    ],
    "sg:phone":"+1 450 688 7082",
    "sg:postcode":"H7N 2L1",
    "sg:province":"QC",
    "wof:name":"Couche-Tard",
    "wof:placetype":"venue"
},
  "geometry": {"coordinates":[-73.71291351319999,45.5495796204],"type":"Point"}
}