{
  "type": "Feature",
  "properties": {
    "addr:full":"315 Avenue F S Saskatoon SK S7M 1T3",
    "addr:housenumber":"315",
    "addr:postcode":"s7m 1t3",
    "addr:street":"Avenue F S",
    "iso:country":"CA",
    "sg:address":"315 Avenue F S",
    "sg:city":"Saskatoon",
    "sg:classifiers":[
        {
            "category":"Organizations",
            "subcategory":"Professional Association",
            "type":"Services"
        }
    ],
    "sg:phone":"+1 306 975 9153",
    "sg:postcode":"S7M 1T3",
    "sg:province":"SK",
    "wof:name":"Western Region Metis Women's",
    "wof:placetype":"venue"
},
  "geometry": {"coordinates":[-106.678497315,52.1258468628],"type":"Point"}
}