{
  "type": "Feature",
  "properties": {
    "iso:country":"CA",
    "sg:address":"2302 Bridge Rd",
    "sg:city":"Oakville",
    "sg:classifiers":[
        {
            "category":"Recreation",
            "type":"Entertainment"
        }
    ],
    "sg:phone":"+1 905 815 5979",
    "sg:postcode":"L6L 2G6",
    "sg:province":"ON",
    "sg:tags":[
        "government",
        "swimming"
    ],
    "wof:name":"Q E Park Pool",
    "wof:placetype":"venue"
},
  "geometry": {"coordinates":[-79.721146,43.406387],"type":"Point"}
}