{
  "type": "Feature",
  "properties": {
    "addr:full":"1602 Lakeside Rd S Lethbridge AB T1K 3G8",
    "addr:housenumber":"1602",
    "addr:postcode":"t1k 3g8",
    "addr:street":"Lakeside Rd S",
    "iso:country":"CA",
    "sg:address":"1602 Lakeside Rd S",
    "sg:city":"Lethbridge",
    "sg:classifiers":[
        {
            "category":"Freight",
            "type":"Transportation"
        }
    ],
    "sg:phone":"+1 403 320 8810",
    "sg:postcode":"T1K 3G8",
    "sg:province":"AB",
    "sg:tags":[
        "field",
        "oil",
        "trucking"
    ],
    "wof:name":"Lyle Grover Inc",
    "wof:placetype":"venue"
},
  "geometry": {"coordinates":[-112.79428100600001,49.6760215759],"type":"Point"}
}