{
  "type": "Feature",
  "properties": {
    "addr:full":"31 Railway Ave Sinclair MB R0M 2A0",
    "addr:housenumber":"31",
    "addr:postcode":"r0m 2a0",
    "addr:street":"Railway Ave",
    "iso:country":"CA",
    "sg:address":"31 Railway Ave",
    "sg:city":"Sinclair",
    "sg:classifiers":[
        {
            "category":"Food & Beverages",
            "subcategory":"Groceries & Convenience Stores",
            "type":"Retail Goods"
        }
    ],
    "sg:phone":"+1 204 662 4461",
    "sg:postcode":"R0M 2A0",
    "sg:province":"MB",
    "sg:tags":[
        "grocer"
    ],
    "wof:name":"Wiebe's Corner Store",
    "wof:placetype":"venue"
},
  "geometry": {"coordinates":[-101.292816,49.569382],"type":"Point"}
}