{
  "type": "Feature",
  "properties": {
    "addr:full":"10209 123 St NW Edmonton AB T5N 1N3",
    "addr:housenumber":"10209",
    "addr:postcode":"t5n 1n3",
    "addr:street":"123 St Nw",
    "iso:country":"CA",
    "sg:address":"10209 123 St NW",
    "sg:city":"Edmonton",
    "sg:classifiers":[
        {
            "category":"Education",
            "subcategory":"Special Training",
            "type":"Public Place"
        }
    ],
    "sg:phone":"+1 780 732 1262",
    "sg:postcode":"T5N 1N3",
    "sg:province":"AB",
    "sg:tags":[
        "instruction",
        "music"
    ],
    "wof:name":"Cantilon Choirs",
    "wof:placetype":"venue"
},
  "geometry": {"coordinates":[-113.53389,53.543282],"type":"Point"}
}