{
  "type": "Feature",
  "properties": {
    "addr:full":"Etobicoke ON M9P 3B6",
    "addr:postcode":"m9p 3b6",
    "iso:country":"CA",
    "sg:city":"Etobicoke",
    "sg:classifiers":[
        {
            "category":"Utilities",
            "subcategory":"Mobile Phone",
            "type":"Services"
        }
    ],
    "sg:phone":"+1 416 241 6626",
    "sg:postcode":"M9P 3B6",
    "sg:province":"ON",
    "sg:tags":[
        "telephone",
        "cellular"
    ],
    "wof:name":"Neocell Wireless",
    "wof:placetype":"venue"
},
  "geometry": {"coordinates":[-79.5305633545,43.6909103394],"type":"Point"}
}