{
  "type": "Feature",
  "properties": {
    "addr:full":"310 Boul Tache E Montmagny QC G5V 1C8",
    "addr:housenumber":"310",
    "addr:postcode":"g5v 1c8",
    "addr:street":"Boul Tache E",
    "iso:country":"CA",
    "sg:address":"310 Boul Tache E",
    "sg:city":"Montmagny",
    "sg:classifiers":[
        {
            "category":"Shopping",
            "subcategory":"Florist",
            "type":"Retail Goods"
        }
    ],
    "sg:phone":"+1 418 248 0117",
    "sg:postcode":"G5V 1C8",
    "sg:province":"QC",
    "wof:name":"Fleuriste DE Montmagny Inc",
    "wof:placetype":"venue"
},
  "geometry": {"coordinates":[-70.54486083979999,46.9848709106],"type":"Point"}
}