{
  "type": "Feature",
  "properties": {
    "iso:country":"CA",
    "sg:address":"5100 Harvester Rd",
    "sg:city":"Burlington",
    "sg:classifiers":[
        {
            "category":"Wholesale",
            "subcategory":"Meat",
            "type":"Manufacturing & Wholesale Goods"
        }
    ],
    "sg:phone":"+1 905 681 5050",
    "sg:postcode":"L7L 4X4",
    "sg:province":"ON",
    "sg:tags":[
        "packer"
    ],
    "wof:name":"Maple Meats Distribution Ctr",
    "wof:placetype":"venue"
},
  "geometry": {"coordinates":[-79.765106,43.379513],"type":"Point"}
}