{
  "type": "Feature",
  "properties": {
    "addr:full":"510 77 Ave SE # C Calgary AB T2H 1C3",
    "addr:housenumber":"510",
    "addr:postcode":"t2h 1c3",
    "addr:street":"77 Ave Se # C",
    "iso:country":"CA",
    "sg:address":"510 77 Ave SE # C",
    "sg:city":"Calgary",
    "sg:classifiers":[
        {
            "category":"Shopping",
            "subcategory":"Used Merchandise",
            "type":"Retail Goods"
        }
    ],
    "sg:phone":"+1 403 301 0155",
    "sg:postcode":"T2H 1C3",
    "sg:province":"AB",
    "sg:tags":[
        "flea",
        "market"
    ],
    "wof:name":"Heritage Flea Market",
    "wof:placetype":"venue"
},
  "geometry": {"coordinates":[-114.051277,50.984528],"type":"Point"}
}