{
  "type": "Feature",
  "properties": {
    "addr:full":"Stonewall MB R0C 2Z0",
    "addr:postcode":"r0c 2z0",
    "iso:country":"CA",
    "sg:city":"Stonewall",
    "sg:classifiers":[
        {
            "category":"Autos & Motor Vehicles",
            "subcategory":"Auto Supplies",
            "type":"Retail Goods"
        }
    ],
    "sg:phone":"+1 204 467 2466",
    "sg:postcode":"R0C 2Z0",
    "sg:province":"MB",
    "sg:tags":[
        "automobile",
        "parts"
    ],
    "wof:name":"Piston Ring Auto Value",
    "wof:placetype":"venue"
},
  "geometry": {"coordinates":[-97.3266296387,50.1346893311],"type":"Point"}
}