{
  "type": "Feature",
  "properties": {
    "iso:country":"CA",
    "sg:city":"Mount Hope",
    "sg:classifiers":[
        {
            "category":"Wholesale",
            "subcategory":"Meat",
            "type":"Manufacturing & Wholesale Goods"
        }
    ],
    "sg:phone":"+1 905 679 6821",
    "sg:postcode":"L0R 1W0",
    "sg:province":"ON",
    "sg:tags":[
        "butchering"
    ],
    "wof:name":"Gourmet Meats Ltd",
    "wof:placetype":"venue"
},
  "geometry": {"coordinates":[-79.92482757569999,43.1335487366],"type":"Point"}
}