{
  "type": "Feature",
  "properties": {
    "iso:country":"CA",
    "sg:address":"1 First Canadian Pl",
    "sg:city":"Toronto",
    "sg:classifiers":[
        {
            "category":"Health Services",
            "subcategory":"Doctor",
            "type":"Services"
        }
    ],
    "sg:phone":"+1 416 868 1066",
    "sg:postcode":"M5X 1C8",
    "sg:province":"ON",
    "sg:tags":[
        "dentist"
    ],
    "wof:name":"Lebovic Jacobs Altman",
    "wof:placetype":"venue"
},
  "geometry": {"coordinates":[-79.3806686401,43.6486778259],"type":"Point"}
}