{
  "type": "Feature",
  "properties": {
    "addr:full":"458 Logy Bay Rd St. John's NL A1A 5C6",
    "addr:housenumber":"458",
    "addr:postcode":"a1a 5c6",
    "addr:street":"Logy Bay Rd",
    "iso:country":"CA",
    "sg:address":"458 Logy Bay Rd",
    "sg:city":"St. John's",
    "sg:classifiers":[
        {
            "category":"Manufacturing",
            "subcategory":"Printing",
            "type":"Manufacturing & Wholesale Goods"
        }
    ],
    "sg:phone":"+1 709 726 7060",
    "sg:postcode":"A1A 5C6",
    "sg:province":"NL",
    "sg:tags":[
        "printer"
    ],
    "wof:name":"Stirling Press",
    "wof:placetype":"venue"
},
  "geometry": {"coordinates":[-52.679508,47.62904],"type":"Point"}
}