{
  "type": "Feature",
  "properties": {
    "addr:full":"3390 Wolfedale Rd Mississauga ON L5C 1W4",
    "addr:housenumber":"3390",
    "addr:postcode":"l5c 1w4",
    "addr:street":"Wolfedale Rd",
    "iso:country":"CA",
    "sg:address":"3390 Wolfedale Rd",
    "sg:city":"Mississauga",
    "sg:classifiers":[
        {
            "category":"Autos & Motor Vehicles",
            "subcategory":"Automobile Sales",
            "type":"Retail Goods"
        }
    ],
    "sg:phone":"+1 416 565 5956",
    "sg:postcode":"L5C 1W4",
    "sg:province":"ON",
    "sg:tags":[
        "car",
        "dealer"
    ],
    "wof:name":"R L Dubeau Auto Svc",
    "wof:placetype":"venue"
},
  "geometry": {"coordinates":[-79.64733099999999,43.570652],"type":"Point"}
}