{
  "type": "Feature",
  "properties": {
    "addr:full":"620 Rue Cathcart # 600 Montreal QC H3B 1M1",
    "addr:housenumber":"620",
    "addr:postcode":"h3b 1m1",
    "addr:street":"Rue Cathcart # 600",
    "iso:country":"CA",
    "sg:address":"620 Rue Cathcart # 600",
    "sg:city":"Montreal",
    "sg:classifiers":[
        {
            "category":"Manufacturing",
            "subcategory":"Jewelry",
            "type":"Manufacturing & Wholesale Goods"
        }
    ],
    "sg:phone":"+1 514 875 0323",
    "sg:postcode":"H3B 1M1",
    "sg:province":"QC",
    "wof:name":"Bijouterie Mano",
    "wof:placetype":"venue"
},
  "geometry": {"coordinates":[-73.56838999999999,45.503242],"type":"Point"}
}