{
  "type": "Feature",
  "properties": {
    "addr:full":"146 Colonnade Rd Nepean ON K2E 7Y1",
    "addr:housenumber":"146",
    "addr:postcode":"k2e 7y1",
    "addr:street":"Colonnade Rd",
    "iso:country":"CA",
    "sg:address":"146 Colonnade Rd",
    "sg:city":"Nepean",
    "sg:classifiers":[
        {
            "category":"Professional",
            "subcategory":"Computer Services",
            "type":"Services"
        }
    ],
    "sg:phone":"+1 613 224 2048",
    "sg:postcode":"K2E 7Y1",
    "sg:province":"ON",
    "sg:tags":[
        "internet"
    ],
    "wof:name":"Profitline",
    "wof:placetype":"venue"
},
  "geometry": {"coordinates":[-75.7049255371,45.3438186646],"type":"Point"}
}