{
  "type": "Feature",
  "properties": {
    "iso:country":"CA",
    "sg:city":"Calgary",
    "sg:classifiers":[
        {
            "category":"Shopping",
            "subcategory":"Stationery & Office Supplies",
            "type":"Retail Goods"
        }
    ],
    "sg:phone":"+1 403 252 9511",
    "sg:postcode":"T2H 1Z5",
    "sg:province":"AB",
    "sg:tags":[
        "equipment",
        "material",
        "handling",
        "system",
        "filing"
    ],
    "wof:name":"Foothills Filing/Storage Syst",
    "wof:placetype":"venue"
},
  "geometry": {"coordinates":[-114.04544067400001,51.004989624],"type":"Point"}
}