{
  "type": "Feature",
  "properties": {
    "addr:full":"Halifax NS B3J 3N2",
    "addr:postcode":"ns b3j 3n2",
    "iso:country":"CA",
    "sg:city":"Halifax",
    "sg:classifiers":[
        {
            "category":"Food & Beverages",
            "subcategory":"Meat & Fish",
            "type":"Retail Goods"
        }
    ],
    "sg:phone":"+1 902 422 2883",
    "sg:postcode":"B3J 3N2",
    "sg:province":"NS",
    "sg:tags":[
        "seafood"
    ],
    "wof:name":"High Liner Foods Inc",
    "wof:placetype":"venue"
},
  "geometry": {"coordinates":[-63.576473,44.652599],"type":"Point"}
}