{
  "type": "Feature",
  "properties": {
    "addr:full":"313 138 Rte Les Escoumins QC G0T 1K0",
    "addr:housenumber":"138",
    "addr:postcode":"g0t 1k0",
    "addr:street":"Rte",
    "iso:country":"CA",
    "sg:address":"313 138 Rte",
    "sg:city":"Les Escoumins",
    "sg:classifiers":[
        {
            "category":"Shopping",
            "subcategory":"Catalog Store",
            "type":"Retail Goods"
        }
    ],
    "sg:phone":"+1 418 233 2518",
    "sg:postcode":"G0T 1K0",
    "sg:province":"QC",
    "sg:tags":[
        "mail",
        "order",
        "internet"
    ],
    "wof:name":"Sears Canada Inc",
    "wof:placetype":"venue"
},
  "geometry": {"coordinates":[-69.40437300000001,48.352894],"type":"Point"}
}