{
  "type": "Feature",
  "properties": {
    "iso:country":"CA",
    "sg:address":"146 Park St N",
    "sg:city":"Hamilton",
    "sg:classifiers":[
        {
            "category":"Organizations",
            "subcategory":"Religious Organization",
            "type":"Services"
        }
    ],
    "sg:phone":"+1 905 527 4216",
    "sg:postcode":"L8R 2N3",
    "sg:province":"ON",
    "sg:tags":[
        "church"
    ],
    "wof:name":"St Mary's Church",
    "wof:placetype":"venue"
},
  "geometry": {"coordinates":[-79.86991119379999,43.2620658875],"type":"Point"}
}