{
  "type": "Feature",
  "properties": {
    "iso:country":"CA",
    "sg:address":"830 South Service Rd",
    "sg:city":"Stoney Creek",
    "sg:classifiers":[
        {
            "category":"Manufacturing",
            "subcategory":"Metals",
            "type":"Manufacturing & Wholesale Goods"
        }
    ],
    "sg:phone":"+1 905 643 3300",
    "sg:postcode":"L8E 5M7",
    "sg:province":"ON",
    "sg:tags":[
        "steel",
        "processing"
    ],
    "wof:name":"Nova Steel Processing Ctr Ltd",
    "wof:placetype":"venue"
},
  "geometry": {"coordinates":[-79.6819610596,43.2272720337],"type":"Point"}
}