{
  "type": "Feature",
  "properties": {
    "addr:full":"1 Dunfield Rd Swastika ON P0K 1T0",
    "addr:housenumber":"1",
    "addr:postcode":"p0k 1t0",
    "addr:street":"Dunfield Rd",
    "iso:country":"CA",
    "sg:address":"1 Dunfield Rd",
    "sg:city":"Swastika",
    "sg:classifiers":[
        {
            "category":"Real Estate",
            "subcategory":"Developer",
            "type":"Services"
        }
    ],
    "sg:phone":"+1 705 567 9365",
    "sg:postcode":"P0K 1T0",
    "sg:province":"ON",
    "sg:tags":[
        "cemetery"
    ],
    "wof:name":"Kirkland Cemetery",
    "wof:placetype":"venue"
},
  "geometry": {"coordinates":[-80.103218,48.109074],"type":"Point"}
}