{
  "type": "Feature",
  "properties": {
    "iso:country":"CA",
    "sg:address":"96 Mill Rd",
    "sg:city":"Morinville",
    "sg:classifiers":[
        {
            "category":"Shopping",
            "subcategory":"Bicycles & Sporting Goods",
            "type":"Retail Goods"
        }
    ],
    "sg:phone":"+1 780 939 3866",
    "sg:postcode":"T8R 1P1",
    "sg:province":"AB",
    "sg:tags":[
        "tent"
    ],
    "wof:name":"Wolfchild Tipis & Tents",
    "wof:placetype":"venue"
},
  "geometry": {"coordinates":[-113.648208618,53.8000183105],"type":"Point"}
}