{
  "type": "Feature",
  "properties": {
    "addr:full":"Calgary AB T2C 0A7",
    "addr:postcode":"t2c 0a7",
    "iso:country":"CA",
    "sg:city":"Calgary",
    "sg:classifiers":[
        {
            "category":"Manufacturing",
            "subcategory":"Food",
            "type":"Manufacturing & Wholesale Goods"
        }
    ],
    "sg:phone":"+1 403 236 0155",
    "sg:postcode":"T2C 0A7",
    "sg:province":"AB",
    "sg:tags":[
        "beverage"
    ],
    "wof:name":"Flora Beverage CO Ltd",
    "wof:placetype":"venue"
},
  "geometry": {"coordinates":[-113.992058,51.005627],"type":"Point"}
}