{
  "type": "Feature",
  "properties": {
    "addr:full":"89 Queens Quay W Toronto ON M5J 2T5",
    "addr:housenumber":"89",
    "addr:postcode":"m5j 2t5",
    "addr:street":"Queens Quay W",
    "iso:country":"CA",
    "sg:address":"89 Queens Quay W",
    "sg:city":"Toronto",
    "sg:classifiers":[
        {
            "category":"Food & Beverages",
            "subcategory":"Groceries & Convenience Stores",
            "type":"Retail Goods"
        }
    ],
    "sg:phone":"+1 416 203 1928",
    "sg:postcode":"M5J 2T5",
    "sg:province":"ON",
    "sg:tags":[
        "grocer"
    ],
    "wof:name":"A1 Han Brothers Ltd",
    "wof:placetype":"venue"
},
  "geometry": {"coordinates":[-79.377983,43.64048],"type":"Point"}
}