{
  "type": "Feature",
  "properties": {
    "iso:country":"CA",
    "sg:city":"Saint-Calixte",
    "sg:classifiers":[
        {
            "category":"Social Services",
            "subcategory":"Child Care",
            "type":"Services"
        }
    ],
    "sg:phone":"+1 450 222 2111",
    "sg:postcode":"J0K 1Z0",
    "sg:province":"QC",
    "wof:name":"Service DE Garde LA Gentiane",
    "wof:placetype":"venue"
},
  "geometry": {"coordinates":[-73.8494796753,45.9528274536],"type":"Point"}
}