{
  "type": "Feature",
  "properties": {
    "addr:full":"200 Boul Marcel-Laurin Saint-Laurent QC H4M 2L5",
    "addr:housenumber":"200",
    "addr:postcode":"h4m 2l5",
    "addr:street":"Boul Marcel-Laurin",
    "iso:country":"CA",
    "sg:address":"200 Boul Marcel-Laurin",
    "sg:city":"Saint-Laurent",
    "sg:classifiers":[
        {
            "category":"Autos & Motor Vehicles",
            "subcategory":"Automobile Sales",
            "type":"Retail Goods"
        }
    ],
    "sg:phone":"+1 514 744 2811",
    "sg:postcode":"H4M 2L5",
    "sg:province":"QC",
    "sg:tags":[
        "equipment",
        "aircraft",
        "parts",
        "supply"
    ],
    "wof:name":"Honeywell",
    "wof:placetype":"venue"
},
  "geometry": {"coordinates":[-73.674942,45.5033],"type":"Point"}
}