{
  "type": "Feature",
  "properties": {
    "addr:full":"929 Main St Vancouver BC V6A 2V8",
    "addr:housenumber":"929",
    "addr:postcode":"v6a 2v8",
    "addr:street":"Main St",
    "iso:country":"CA",
    "sg:address":"929 Main St",
    "sg:city":"Vancouver",
    "sg:classifiers":[
        {
            "category":"Shopping",
            "subcategory":"Used Merchandise",
            "type":"Retail Goods"
        }
    ],
    "sg:phone":"+1 604 684 9914",
    "sg:postcode":"V6A 2V8",
    "sg:province":"BC",
    "sg:tags":[
        "antique"
    ],
    "wof:name":"Source Enterprises Ltd",
    "wof:placetype":"venue"
},
  "geometry": {"coordinates":[-123.10002900000001,49.276516],"type":"Point"}
}