{
  "type": "Feature",
  "properties": {
    "addr:full":"PO Box 39002 Rpo Adelaide Cent London ON N5Y 5L1",
    "addr:housenumber":"po box",
    "addr:postcode":"39002;n5y 5l1",
    "addr:street":"Cent",
    "iso:country":"CA",
    "sg:address":"PO Box 39002 Rpo Adelaide Cent",
    "sg:city":"London",
    "sg:classifiers":[
        {
            "category":"Health Services",
            "subcategory":"Clinic",
            "type":"Services"
        }
    ],
    "sg:phone":"+1 519 679 6592",
    "sg:postcode":"N5Y 5L1",
    "sg:province":"ON",
    "sg:tags":[
        "holistic",
        "practitioner"
    ],
    "wof:name":"Schiffco Health & Wellness",
    "wof:placetype":"venue"
},
  "geometry": {"coordinates":[-81.246216,42.986897],"type":"Point"}
}