{
  "type": "Feature",
  "properties": {
    "addr:full":"87 Shorncliffe Rd Etobicoke ON M8Z 5K3",
    "addr:housenumber":"87",
    "addr:postcode":"m8z 5k3",
    "addr:street":"Shorncliffe Rd",
    "iso:country":"CA",
    "sg:address":"87 Shorncliffe Rd",
    "sg:city":"Etobicoke",
    "sg:classifiers":[
        {
            "category":"Retail",
            "subcategory":"Auto Repair",
            "type":"Services"
        }
    ],
    "sg:phone":"+1 416 231 6710",
    "sg:postcode":"M8Z 5K3",
    "sg:province":"ON",
    "sg:tags":[
        "body",
        "automobile",
        "painting"
    ],
    "wof:name":"West End Auto Body",
    "wof:placetype":"venue"
},
  "geometry": {"coordinates":[-79.542084,43.626347],"type":"Point"}
}