{
  "type": "Feature",
  "properties": {
    "addr:full":"722 Main St E Hamilton ON L8M 1K9",
    "addr:housenumber":"722",
    "addr:postcode":"l8m 1k9",
    "addr:street":"Main St E",
    "iso:country":"CA",
    "sg:address":"722 Main St E",
    "sg:city":"Hamilton",
    "sg:classifiers":[
        {
            "category":"Shopping",
            "subcategory":"Discount & Variety Stores",
            "type":"Retail Goods"
        }
    ],
    "sg:phone":"+1 905 544 3084",
    "sg:postcode":"L8M 1K9",
    "sg:province":"ON",
    "wof:name":"Milk Mart",
    "wof:placetype":"venue"
},
  "geometry": {"coordinates":[-79.840782,43.247803],"type":"Point"}
}