{
  "type": "Feature",
  "properties": {
    "addr:full":"352 Rue Labrecque Sainte-Marie QC G6E 1W9",
    "addr:housenumber":"352",
    "addr:postcode":"g6e 1w9",
    "addr:street":"Rue Labrecque",
    "iso:country":"CA",
    "sg:address":"352 Rue Labrecque",
    "sg:city":"Sainte-Marie",
    "sg:classifiers":[
        {
            "category":"Insurance",
            "subcategory":"Life Insurance",
            "type":"Services"
        }
    ],
    "sg:phone":"+1 418 387 4502",
    "sg:postcode":"G6E 1W9",
    "sg:province":"QC",
    "wof:name":"Services Assurances-Vie Savi",
    "wof:placetype":"venue"
},
  "geometry": {"coordinates":[-71.014008,46.437153],"type":"Point"}
}