{
  "type": "Feature",
  "properties": {
    "addr:full":"76 Mcintyre Rd Schumacher ON P0N 1G0",
    "addr:housenumber":"76",
    "addr:postcode":"p0n 1g0",
    "addr:street":"Mcintyre Rd",
    "iso:country":"CA",
    "sg:address":"76 Mcintyre Rd",
    "sg:city":"Schumacher",
    "sg:classifiers":[
        {
            "category":"Organizations",
            "subcategory":"Professional Association",
            "type":"Services"
        }
    ],
    "sg:phone":"+1 705 360 1900",
    "sg:postcode":"P0N 1G0",
    "sg:province":"ON",
    "sg:tags":[
        "chambers",
        "commerce"
    ],
    "wof:name":"Timmins Chamber of Commerce",
    "wof:placetype":"venue"
},
  "geometry": {"coordinates":[-81.29834747309999,48.4766807556],"type":"Point"}
}