{
  "type": "Feature",
  "properties": {
    "iso:country":"CA",
    "sg:address":"569 Main St",
    "sg:city":"Winchester",
    "sg:classifiers":[
        {
            "category":"Health Services",
            "subcategory":"Chiropractor",
            "type":"Services"
        }
    ],
    "sg:phone":"+1 613 774 3944",
    "sg:postcode":"K0C 2K0",
    "sg:province":"ON",
    "wof:name":"Winchester Chiropractic Ctr",
    "wof:placetype":"venue"
},
  "geometry": {"coordinates":[-75.3603591919,45.0905570984],"type":"Point"}
}