{
  "type": "Feature",
  "properties": {
    "addr:full":"6045 Creditview Rd #20 Mississauga ON L5V 2A8",
    "addr:housenumber":"6045",
    "addr:postcode":"l5v 2a8",
    "addr:street":"Creditview Rd # 20",
    "iso:country":"CA",
    "sg:address":"6045 Creditview Rd #20",
    "sg:city":"Mississauga",
    "sg:classifiers":[
        {
            "category":"Health Services",
            "subcategory":"Chiropractor",
            "type":"Services"
        }
    ],
    "sg:phone":"+1 905 567 0202",
    "sg:postcode":"L5V 2A8",
    "sg:province":"ON",
    "wof:name":"Heartland Chiropractic",
    "wof:placetype":"venue"
},
  "geometry": {"coordinates":[-79.713249,43.598721],"type":"Point"}
}