{
  "type": "Feature",
  "properties": {
    "addr:full":"New Westminster BC V3M 2B3",
    "addr:postcode":"v3m 2b3",
    "iso:country":"CA",
    "sg:city":"New Westminster",
    "sg:classifiers":[
        {
            "category":"Food & Beverages",
            "subcategory":"Specialty",
            "type":"Retail Goods"
        }
    ],
    "sg:phone":"+1 604 526 7525",
    "sg:postcode":"V3M 2B3",
    "sg:province":"BC",
    "sg:tags":[
        "health",
        "diet"
    ],
    "wof:name":"Galloway's Specialty Foods Ltd",
    "wof:placetype":"venue"
},
  "geometry": {"coordinates":[-122.90957641599999,49.2063598633],"type":"Point"}
}