{
  "type": "Feature",
  "properties": {
    "iso:country":"CA",
    "sg:city":"Saint-Ephrem-DE-Beauce",
    "sg:phone":"+1 418 484 2013",
    "sg:postcode":"G0M 1R0",
    "sg:province":"QC",
    "sg:tags":[
        "food",
        "equipment",
        "processing",
        "heating",
        "contractor"
    ],
    "wof:name":"Ferblanterie Ls Bilodeau",
    "wof:placetype":"venue"
},
  "geometry": {"coordinates":[-70.953934,46.059105],"type":"Point"}
}