{
  "type": "Feature",
  "properties": {
    "iso:country":"CA",
    "sg:city":"Hawkesbury",
    "sg:classifiers":[
        {
            "category":"Insurance",
            "subcategory":"Insurance Agent",
            "type":"Services"
        }
    ],
    "sg:phone":"+1 613 632 4174",
    "sg:postcode":"K6A 1A3",
    "sg:province":"ON",
    "wof:name":"Canada Brokerlink Inc",
    "wof:placetype":"venue"
},
  "geometry": {"coordinates":[-74.610481,45.609463],"type":"Point"}
}