{
  "type": "Feature",
  "properties": {
    "iso:country":"CA",
    "sg:address":"6505 Tecumseh Rd E",
    "sg:city":"Windsor",
    "sg:classifiers":[
        {
            "category":"Banks & Credit Unions",
            "subcategory":"Bank",
            "type":"Services"
        }
    ],
    "sg:phone":"+1 519 944 8387",
    "sg:postcode":"N8T 1E7",
    "sg:province":"ON",
    "sg:tags":[
        "loan",
        "real estate"
    ],
    "wof:name":"Norlite Financial Svc",
    "wof:placetype":"venue"
},
  "geometry": {"coordinates":[-82.94747161870001,42.3111495972],"type":"Point"}
}