{
  "type": "Feature",
  "properties": {
    "addr:full":"247 Bricker St Port Elgin ON N0H 2C1",
    "addr:housenumber":"247",
    "addr:postcode":"n0h 2c1",
    "addr:street":"Bricker St",
    "iso:country":"CA",
    "sg:address":"247 Bricker St",
    "sg:city":"Port Elgin",
    "sg:classifiers":[
        {
            "category":"Health Services",
            "subcategory":"Podiatrist",
            "type":"Services"
        }
    ],
    "sg:phone":"+1 519 832 6969",
    "sg:postcode":"N0H 2C1",
    "sg:province":"ON",
    "wof:name":"Fit Feet",
    "wof:placetype":"venue"
},
  "geometry": {"coordinates":[-81.39390563960001,44.4266281128],"type":"Point"}
}