{
  "type": "Feature",
  "properties": {
    "addr:full":"2884 Ch Sainte-Marie Mascouche QC J7K 1N5",
    "addr:housenumber":"2884",
    "addr:postcode":"j7k 1n5",
    "addr:street":"Ch Sainte-Marie",
    "iso:country":"CA",
    "sg:address":"2884 Ch Sainte-Marie",
    "sg:city":"Mascouche",
    "sg:classifiers":[
        {
            "category":"Food & Beverages",
            "subcategory":"Bakery",
            "type":"Retail Goods"
        }
    ],
    "sg:phone":"+1 450 474 2698",
    "sg:postcode":"J7K 1N5",
    "sg:province":"QC",
    "sg:tags":[
        "baker"
    ],
    "wof:name":"Patisserie Madeline",
    "wof:placetype":"venue"
},
  "geometry": {"coordinates":[-73.60478999999999,45.749279],"type":"Point"}
}