{
  "type": "Feature",
  "properties": {
    "addr:full":"Gibsons BC V0N 1V4",
    "addr:postcode":"v0n 1v4",
    "iso:country":"CA",
    "sg:city":"Gibsons",
    "sg:classifiers":[
        {
            "category":"Manufacturing",
            "subcategory":"Metals",
            "type":"Manufacturing & Wholesale Goods"
        }
    ],
    "sg:phone":"+1 604 886 9159",
    "sg:postcode":"V0N 1V4",
    "sg:province":"BC",
    "sg:tags":[
        "steel"
    ],
    "wof:name":"John Enevoldson Welding & Ind",
    "wof:placetype":"venue"
},
  "geometry": {"coordinates":[-123.526672,49.406509],"type":"Point"}
}