{
  "type": "Feature",
  "properties": {
    "addr:full":"10803 95 St NW Edmonton AB T5H 2E2",
    "addr:housenumber":"10803",
    "addr:postcode":"t5h 2e2",
    "addr:street":"95 St Nw",
    "iso:country":"CA",
    "sg:address":"10803 95 St NW",
    "sg:city":"Edmonton",
    "sg:classifiers":[
        {
            "category":"Personal",
            "subcategory":"Beauty Salon",
            "type":"Services"
        }
    ],
    "sg:phone":"+1 780 420 0458",
    "sg:postcode":"T5H 2E2",
    "sg:province":"AB",
    "wof:name":"T K Shapers Hairstyling",
    "wof:placetype":"venue"
},
  "geometry": {"coordinates":[-113.483947754,53.5549163818],"type":"Point"}
}