{
  "type": "Feature",
  "properties": {
    "addr:full":"702 12 Ave # 1 Nisku AB T9E 7P7",
    "addr:postcode":"t9e 7p7",
    "addr:street":"702 12 Ave # 1",
    "iso:country":"CA",
    "sg:address":"702 12 Ave # 1",
    "sg:city":"Nisku",
    "sg:classifiers":[
        {
            "category":"Freight",
            "type":"Transportation"
        }
    ],
    "sg:phone":"+1 780 955 7603",
    "sg:postcode":"T9E 7P7",
    "sg:province":"AB",
    "sg:tags":[
        "courier"
    ],
    "wof:name":"Nisku Dispatch",
    "wof:placetype":"venue"
},
  "geometry": {"coordinates":[-113.52123260499999,53.311290741],"type":"Point"}
}