{
  "type": "Feature",
  "properties": {
    "addr:full":"170 University Ave Toronto ON M5H 3B3",
    "addr:housenumber":"170",
    "addr:postcode":"m5h 3b3",
    "addr:street":"University Ave",
    "iso:country":"CA",
    "sg:address":"170 University Ave",
    "sg:city":"Toronto",
    "sg:classifiers":[
        {
            "category":"Professional",
            "subcategory":"Computer Services",
            "type":"Services"
        }
    ],
    "sg:phone":"+1 416 542 1590",
    "sg:postcode":"M5H 3B3",
    "sg:province":"ON",
    "sg:tags":[
        "internet"
    ],
    "wof:name":"Navaha Networks Inc",
    "wof:placetype":"venue"
},
  "geometry": {"coordinates":[-79.3855438232,43.6487541199],"type":"Point"}
}