{
  "type": "Feature",
  "properties": {
    "iso:country":"CA",
    "sg:city":"Peterborough",
    "sg:classifiers":[
        {
            "category":"Home & Garden",
            "subcategory":"Furniture",
            "type":"Retail Goods"
        }
    ],
    "sg:phone":"+1 705 745 2284",
    "sg:postcode":"K9L 1C3",
    "sg:province":"ON",
    "wof:name":"Sofa World",
    "wof:placetype":"venue"
},
  "geometry": {"coordinates":[-78.3039016724,44.3197898865],"type":"Point"}
}