{
  "type": "Feature",
  "properties": {
    "addr:full":"1357 Rue Nelles Sainte-Foy QC G1W 3B4",
    "addr:housenumber":"1357",
    "addr:postcode":"g1w 3b4",
    "addr:street":"Rue Nelles Sainte-Foy",
    "iso:country":"CA",
    "sg:address":"1357 Rue Nelles",
    "sg:city":"Sainte-Foy",
    "sg:classifiers":[
        {
            "category":"Building & Trades",
            "subcategory":"Electrical",
            "type":"Services"
        }
    ],
    "sg:phone":"+1 418 652 1152",
    "sg:postcode":"G1W 3B4",
    "sg:province":"QC",
    "sg:tags":[
        "electric",
        "contractor"
    ],
    "wof:name":"Elect Inc",
    "wof:placetype":"venue"
},
  "geometry": {"coordinates":[-71.26820373539999,46.7691955566],"type":"Point"}
}