{
  "type": "Feature",
  "properties": {
    "addr:full":"6410 Arbroath St Burnaby BC V5E 1C4",
    "addr:postcode":"6410;v5e 1c4",
    "addr:street":"Arbroath St",
    "iso:country":"CA",
    "sg:address":"6410 Arbroath St",
    "sg:city":"Burnaby",
    "sg:classifiers":[
        {
            "category":"Building & Trades",
            "subcategory":"Construction",
            "type":"Services"
        }
    ],
    "sg:phone":"+1 604 437 6006",
    "sg:postcode":"V5E 1C4",
    "sg:province":"BC",
    "sg:tags":[
        "railing"
    ],
    "wof:name":"Accurate Aluminum Ltd",
    "wof:placetype":"venue"
},
  "geometry": {"coordinates":[-122.97075700000001,49.218178],"type":"Point"}
}