{
  "type": "Feature",
  "properties": {
    "addr:full":"765 172 St Surrey BC V3S 9R3",
    "addr:housenumber":"765 172",
    "addr:postcode":"v3s 9r3",
    "addr:street":"St",
    "iso:country":"CA",
    "sg:address":"765 172 St",
    "sg:city":"Surrey",
    "sg:classifiers":[
        {
            "category":"Recreation",
            "type":"Entertainment"
        }
    ],
    "sg:phone":"+1 604 541 1214",
    "sg:postcode":"V3S 9R3",
    "sg:province":"BC",
    "sg:tags":[
        "range",
        "practice",
        "golf"
    ],
    "wof:name":"Peace Arch Golf Ctr",
    "wof:placetype":"venue"
},
  "geometry": {"coordinates":[-122.746437073,49.0153923035],"type":"Point"}
}