{
  "type": "Feature",
  "properties": {
    "iso:country":"CA",
    "sg:address":"719 Stewart Ave",
    "sg:city":"Kamloops",
    "sg:classifiers":[
        {
            "category":"Organizations",
            "subcategory":"Religious Organization",
            "type":"Services"
        }
    ],
    "sg:phone":"+1 250 376 2251",
    "sg:postcode":"V2B 3W8",
    "sg:province":"BC",
    "sg:tags":[
        "church"
    ],
    "wof:name":"Cornerstone Comm Apostolic Ch",
    "wof:placetype":"venue"
},
  "geometry": {"coordinates":[-120.36673,50.694851],"type":"Point"}
}