{
  "type": "Feature",
  "properties": {
    "iso:country":"CA",
    "sg:city":"Vancouver",
    "sg:classifiers":[
        {
            "category":"Health Services",
            "subcategory":"Doctor",
            "type":"Services"
        }
    ],
    "sg:phone":"+1 604 325 1234",
    "sg:postcode":"V5W 2Z5",
    "sg:province":"BC",
    "sg:tags":[
        "physician",
        "surgeon"
    ],
    "wof:name":"Tai Services",
    "wof:placetype":"venue"
},
  "geometry": {"coordinates":[-123.090415955,49.2316970825],"type":"Point"}
}