{
  "type": "Feature",
  "properties": {
    "addr:full":"866 Rue Saint-Jacques Saint-Jean-Sur-Richelieu QC J3B 2N1",
    "addr:housenumber":"866",
    "addr:postcode":"j3b 2n1",
    "addr:street":"Rue Saint-Jacques",
    "iso:country":"CA",
    "sg:address":"866 Rue Saint-Jacques",
    "sg:city":"Saint-Jean-Sur-Richelieu",
    "sg:classifiers":[
        {
            "category":"Home & Garden",
            "subcategory":"Building Materials",
            "type":"Retail Goods"
        }
    ],
    "sg:phone":"+1 450 358 2011",
    "sg:postcode":"J3B 2N1",
    "sg:province":"QC",
    "sg:tags":[
        "glass",
        "window",
        "plate"
    ],
    "wof:name":"Vitrerie 2000 Enr",
    "wof:placetype":"venue"
},
  "geometry": {"coordinates":[-73.2869186401,45.3060798645],"type":"Point"}
}