{
  "type": "Feature",
  "properties": {
    "addr:full":"1157 Boul Monseigneur-DE Laval Baie-Saint-Paul QC G3Z 2W7",
    "addr:housenumber":"1157",
    "addr:postcode":"g3z 2w7",
    "addr:street":"Boul Monseigneur-De Laval",
    "iso:country":"CA",
    "sg:address":"1157 Boul Monseigneur-DE Laval",
    "sg:city":"Baie-Saint-Paul",
    "sg:classifiers":[
        {
            "category":"Wholesale",
            "subcategory":"Machinery & Supplies",
            "type":"Manufacturing & Wholesale Goods"
        }
    ],
    "sg:phone":"+1 418 435 2262",
    "sg:postcode":"G3Z 2W7",
    "sg:province":"QC",
    "sg:tags":[
        "farm",
        "equipment"
    ],
    "wof:name":"Garage Denis Morin Inc",
    "wof:placetype":"venue"
},
  "geometry": {"coordinates":[-70.5296783447,47.4665603638],"type":"Point"}
}