{
  "type": "Feature",
  "properties": {
    "addr:full":"2465 Dixie Rd Mississauga ON L4Y 2A1",
    "addr:housenumber":"2465",
    "addr:postcode":"l4y 2a1",
    "addr:street":"Dixie Rd",
    "iso:country":"CA",
    "sg:address":"2465 Dixie Rd",
    "sg:city":"Mississauga",
    "sg:classifiers":[
        {
            "category":"Autos & Motor Vehicles",
            "subcategory":"Auto Supplies",
            "type":"Retail Goods"
        }
    ],
    "sg:phone":"+1 905 281 1858",
    "sg:postcode":"L4Y 2A1",
    "sg:province":"ON",
    "sg:tags":[
        "automobile",
        "parts"
    ],
    "wof:name":"Kar Auto Parts",
    "wof:placetype":"venue"
},
  "geometry": {"coordinates":[-79.579933,43.606754],"type":"Point"}
}