{
  "type": "Feature",
  "properties": {
    "addr:full":"5790 Av Pierre-DE Coubertin Montreal QC H1N 1R4",
    "addr:housenumber":"5790",
    "addr:postcode":"h1n 1r4",
    "addr:street":"Av Pierre-De Coubertin",
    "iso:country":"CA",
    "sg:address":"5790 Av Pierre-DE Coubertin",
    "sg:city":"Montreal",
    "sg:classifiers":[
        {
            "category":"Organizations",
            "subcategory":"Professional Association",
            "type":"Services"
        }
    ],
    "sg:phone":"+1 514 354 5378",
    "sg:postcode":"H1N 1R4",
    "sg:province":"QC",
    "wof:name":"Chambre DE Commerce DE L'Est",
    "wof:placetype":"venue"
},
  "geometry": {"coordinates":[-73.54043579099999,45.5720062256],"type":"Point"}
}