{
  "type": "Feature",
  "properties": {
    "addr:full":"94 Peacock Bay Rd Huntsville ON P1H 2J2",
    "addr:housenumber":"94",
    "addr:postcode":"p1h 2j2",
    "addr:street":"Peacock Bay Rd",
    "iso:country":"CA",
    "sg:address":"94 Peacock Bay Rd",
    "sg:city":"Huntsville",
    "sg:classifiers":[
        {
            "category":"Recreation",
            "subcategory":"Marina",
            "type":"Entertainment"
        }
    ],
    "sg:phone":"+1 705 789 3755",
    "sg:postcode":"P1H 2J2",
    "sg:province":"ON",
    "wof:name":"Peacock Bay Marina",
    "wof:placetype":"venue"
},
  "geometry": {"coordinates":[-79.32444,45.358078],"type":"Point"}
}