{
  "type": "Feature",
  "properties": {
    "iso:country":"CA",
    "sg:address":"6855 Meadowvale Town Centre Ci # Ci",
    "sg:city":"Mississauga",
    "sg:classifiers":[
        {
            "category":"Health Services",
            "subcategory":"Optometrist",
            "type":"Services"
        }
    ],
    "sg:phone":"+1 905 821 3576",
    "sg:postcode":"L5N 2Y1",
    "sg:province":"ON",
    "wof:name":"Ahmed, Sabrina OD",
    "wof:placetype":"venue"
},
  "geometry": {"coordinates":[-79.758659,43.58445],"type":"Point"}
}