{
  "type": "Feature",
  "properties": {
    "addr:full":"127 Goderich St Auburn ON N0M 1E0",
    "addr:housenumber":"127",
    "addr:postcode":"n0m 1e0",
    "addr:street":"Goderich St",
    "iso:country":"CA",
    "sg:address":"127 Goderich St",
    "sg:city":"Auburn",
    "sg:classifiers":[
        {
            "category":"Utilities",
            "subcategory":"Refuse",
            "type":"Services"
        }
    ],
    "sg:phone":"+1 519 526 7799",
    "sg:postcode":"N0M 1E0",
    "sg:province":"ON",
    "sg:tags":[
        "garbage",
        "collection"
    ],
    "wof:name":"Chamney Sanitation Ltd",
    "wof:placetype":"venue"
},
  "geometry": {"coordinates":[-81.5335845947,43.7714958191],"type":"Point"}
}