{
  "type": "Feature",
  "properties": {
    "addr:full":"Etobicoke ON M8V 1J7",
    "addr:postcode":"m8v 1j7",
    "iso:country":"CA",
    "sg:city":"Etobicoke",
    "sg:classifiers":[
        {
            "category":"Health Services",
            "subcategory":"Hospital",
            "type":"Services"
        }
    ],
    "sg:phone":"+1 416 251 8666",
    "sg:postcode":"M8V 1J7",
    "sg:province":"ON",
    "sg:tags":[
        "mental"
    ],
    "wof:name":"Among Friends",
    "wof:placetype":"venue"
},
  "geometry": {"coordinates":[-79.50629425050001,43.6007080078],"type":"Point"}
}