{
  "type": "Feature",
  "properties": {
    "addr:full":"Etobicoke ON M9W 5L7",
    "addr:postcode":"m9w 5l7",
    "iso:country":"CA",
    "sg:city":"Etobicoke",
    "sg:classifiers":[
        {
            "category":"Restaurant",
            "type":"Food & Drink"
        }
    ],
    "sg:phone":"+1 416 675 6622",
    "sg:postcode":"M9W 5L7",
    "sg:province":"ON",
    "wof:name":"Harvey's",
    "wof:placetype":"venue"
},
  "geometry": {"coordinates":[-79.605576,43.730057],"type":"Point"}
}