{
  "type": "Feature",
  "properties": {
    "addr:full":"1001 Venables St Vancouver BC V6A 3R9",
    "addr:housenumber":"1001",
    "addr:postcode":"v6a 3r9",
    "addr:street":"Venables St",
    "iso:country":"CA",
    "sg:address":"1001 Venables St",
    "sg:city":"Vancouver",
    "sg:classifiers":[
        {
            "category":"Home & Garden",
            "subcategory":"Building Materials",
            "type":"Retail Goods"
        }
    ],
    "sg:phone":"+1 604 255 8511",
    "sg:postcode":"V6A 3R9",
    "sg:province":"BC",
    "sg:tags":[
        "plumbing",
        "fixture",
        "supply"
    ],
    "wof:name":"Beaver Plumbing & Elec Supply",
    "wof:placetype":"venue"
},
  "geometry": {"coordinates":[-123.082489014,49.2769126892],"type":"Point"}
}