{
  "type": "Feature",
  "properties": {
    "addr:full":"270 the Kingsway Etobicoke ON M9A 3T7",
    "addr:housenumber":"270",
    "addr:postcode":"m9a 3t7",
    "addr:street":"The Kingsway",
    "iso:country":"CA",
    "sg:address":"270 the Kingsway",
    "sg:city":"Etobicoke",
    "sg:classifiers":[
        {
            "category":"Personal",
            "subcategory":"Beauty Salon",
            "type":"Services"
        }
    ],
    "sg:phone":"+1 416 231 9774",
    "sg:postcode":"M9A 3T7",
    "sg:province":"ON",
    "sg:tags":[
        "day"
    ],
    "wof:name":"Humbertown Village Spa",
    "wof:placetype":"venue"
},
  "geometry": {"coordinates":[-79.52010300000001,43.662872],"type":"Point"}
}