{
  "type": "Feature",
  "properties": {
    "addr:full":"11819 Tannery Rd Surrey BC V3V 3W8",
    "addr:housenumber":"11819",
    "addr:postcode":"v3v 3w8",
    "addr:street":"Tannery Rd",
    "iso:country":"CA",
    "sg:address":"11819 Tannery Rd",
    "sg:city":"Surrey",
    "sg:classifiers":[
        {
            "category":"Manufacturing",
            "subcategory":"Signs",
            "type":"Manufacturing & Wholesale Goods"
        }
    ],
    "sg:phone":"+1 604 580 4400",
    "sg:postcode":"V3V 3W8",
    "sg:province":"BC",
    "wof:name":"Shakespeare Signs Ltd",
    "wof:placetype":"venue"
},
  "geometry": {"coordinates":[-122.895301819,49.1975517273],"type":"Point"}
}