{
  "type": "Feature",
  "properties": {
    "iso:country":"CA",
    "sg:address":"872 the Queensway",
    "sg:city":"Etobicoke",
    "sg:classifiers":[
        {
            "category":"Restaurant",
            "type":"Food & Drink"
        }
    ],
    "sg:phone":"+1 416 259 4246",
    "sg:postcode":"M8Z 1N7",
    "sg:province":"ON",
    "wof:name":"Sushi 2 Go",
    "wof:placetype":"venue"
},
  "geometry": {"coordinates":[-79.51034545900001,43.6247596741],"type":"Point"}
}