{
  "type": "Feature",
  "properties": {
    "iso:country":"CA",
    "sg:address":"1809 Beaufort Ave",
    "sg:city":"Comox",
    "sg:classifiers":[
        {
            "category":"Government",
            "subcategory":"Office",
            "type":"Public Place"
        }
    ],
    "sg:phone":"+1 250 339 7775",
    "sg:postcode":"V9M 1R9",
    "sg:province":"BC",
    "sg:tags":[
        "village"
    ],
    "wof:name":"Comox Woodstove Burning Info",
    "wof:placetype":"venue"
},
  "geometry": {"coordinates":[-124.927246094,49.6726112366],"type":"Point"}
}