{
  "type": "Feature",
  "properties": {
    "addr:full":"St Thomas ON N5P 4B5",
    "addr:postcode":"n5p 4b5",
    "iso:country":"CA",
    "sg:city":"St Thomas",
    "sg:classifiers":[
        {
            "category":"Retail",
            "subcategory":"Auto Repair",
            "type":"Services"
        }
    ],
    "sg:phone":"+1 519 637 9925",
    "sg:postcode":"N5P 4B5",
    "sg:province":"ON",
    "sg:tags":[
        "machine",
        "automobile",
        "engine",
        "shop"
    ],
    "wof:name":"Consolidated Engine & Machine",
    "wof:placetype":"venue"
},
  "geometry": {"coordinates":[-81.1527099609,42.7868537903],"type":"Point"}
}