{
  "type": "Feature",
  "properties": {
    "addr:full":"550 Limoges Rd Limoges ON K0A 2M0",
    "addr:housenumber":"550",
    "addr:postcode":"k0a 2m0",
    "addr:street":"Limoges Rd",
    "iso:country":"CA",
    "sg:address":"550 Limoges Rd",
    "sg:city":"Limoges",
    "sg:classifiers":[
        {
            "category":"Food & Beverages",
            "subcategory":"Groceries & Convenience Stores",
            "type":"Retail Goods"
        }
    ],
    "sg:phone":"+1 613 443 1678",
    "sg:postcode":"K0A 2M0",
    "sg:province":"ON",
    "wof:name":"Pronto Food Marts",
    "wof:placetype":"venue"
},
  "geometry": {"coordinates":[-75.252647,45.331104],"type":"Point"}
}