{
  "type": "Feature",
  "properties": {
    "addr:full":"Calgary AB T2P 3C4",
    "addr:postcode":"t2p 3c4",
    "iso:country":"CA",
    "sg:city":"Calgary",
    "sg:classifiers":[
        {
            "category":"Travel",
            "subcategory":"Travel Agent",
            "type":"Entertainment"
        }
    ],
    "sg:phone":"+1 403 531 8300",
    "sg:postcode":"T2P 3C4",
    "sg:province":"AB",
    "sg:tags":[
        "agency",
        "bureau"
    ],
    "wof:name":"Carlson Wagonlit Travel",
    "wof:placetype":"venue"
},
  "geometry": {"coordinates":[-114.067947,51.048622],"type":"Point"}
}