{
  "type": "Feature",
  "properties": {
    "addr:full":"Calgary AB T2G 4A7",
    "addr:postcode":"t2g 4a7",
    "iso:country":"CA",
    "sg:city":"Calgary",
    "sg:classifiers":[
        {
            "category":"Manufacturing",
            "subcategory":"Electronics",
            "type":"Manufacturing & Wholesale Goods"
        }
    ],
    "sg:phone":"+1 403 717 0310",
    "sg:postcode":"T2G 4A7",
    "sg:province":"AB",
    "sg:tags":[
        "equipment",
        "electronic",
        "supply"
    ],
    "wof:name":"Alta Industrial Automation Ltd",
    "wof:placetype":"venue"
},
  "geometry": {"coordinates":[-114.053268,51.01865],"type":"Point"}
}