{
  "type": "Feature",
  "properties": {
    "addr:full":"1166 the Queensway Etobicoke ON M8Z 1R5",
    "addr:housenumber":"1166",
    "addr:postcode":"m8z 1r5",
    "addr:street":"The Queensway",
    "iso:country":"CA",
    "sg:address":"1166 the Queensway",
    "sg:city":"Etobicoke",
    "sg:classifiers":[
        {
            "category":"Food & Beverages",
            "subcategory":"Specialty",
            "type":"Retail Goods"
        }
    ],
    "sg:phone":"+1 416 259 0542",
    "sg:postcode":"M8Z 1R5",
    "sg:province":"ON",
    "sg:tags":[
        "health",
        "diet"
    ],
    "wof:name":"S & H Health Foods",
    "wof:placetype":"venue"
},
  "geometry": {"coordinates":[-79.52141571040001,43.6222724915],"type":"Point"}
}