{
  "type": "Feature",
  "properties": {
    "iso:country":"CA",
    "sg:address":"231 Laurier Ave E",
    "sg:city":"Ottawa",
    "sg:classifiers":[
        {
            "category":"Restaurant",
            "type":"Food & Drink"
        }
    ],
    "sg:phone":"+1 613 565 8888",
    "sg:postcode":"K1N 6P1",
    "sg:province":"ON",
    "sg:tags":[
        "sandwich"
    ],
    "wof:name":"Subway Sandwiches & Salads",
    "wof:placetype":"venue"
},
  "geometry": {"coordinates":[-75.6817245483,45.4259910583],"type":"Point"}
}