{
  "type": "Feature",
  "properties": {
    "addr:full":"106 Mutual St Toronto ON M5B 2R7",
    "addr:postcode":"m5b 2r7",
    "addr:street":"Mutual St",
    "iso:country":"CA",
    "sg:address":"106 Mutual St",
    "sg:city":"Toronto",
    "sg:classifiers":[
        {
            "category":"Retail",
            "subcategory":"Veterinary Services",
            "type":"Services"
        }
    ],
    "sg:phone":"+1 416 868 1545",
    "sg:postcode":"M5B 2R7",
    "sg:province":"ON",
    "sg:tags":[
        "veterinarian"
    ],
    "wof:name":"Animal Clinic",
    "wof:placetype":"venue"
},
  "geometry": {"coordinates":[-79.375969,43.657139],"type":"Point"}
}