{
  "type": "Feature",
  "properties": {
    "addr:full":"11 Gibb St Oshawa ON L1H 2J9",
    "addr:housenumber":"11",
    "addr:postcode":"l1h 2j9",
    "addr:street":"Gibb St",
    "iso:country":"CA",
    "sg:address":"11 Gibb St",
    "sg:city":"Oshawa",
    "sg:classifiers":[
        {
            "category":"Health Services",
            "subcategory":"Doctor",
            "type":"Services"
        }
    ],
    "sg:phone":"+1 905 579 7882",
    "sg:postcode":"L1H 2J9",
    "sg:province":"ON",
    "sg:tags":[
        "dentist"
    ],
    "wof:name":"Glazier Dental Ctr",
    "wof:placetype":"venue"
},
  "geometry": {"coordinates":[-78.860786,43.890209],"type":"Point"}
}