{
  "type": "Feature",
  "properties": {
    "addr:full":"10412 159 St NW Edmonton AB T5P 3A7",
    "addr:housenumber":"10412",
    "addr:postcode":"t5p 3a7",
    "addr:street":"159 St Nw",
    "iso:country":"CA",
    "sg:address":"10412 159 St NW",
    "sg:city":"Edmonton",
    "sg:classifiers":[
        {
            "category":"Organizations",
            "subcategory":"Religious Organization",
            "type":"Services"
        }
    ],
    "sg:phone":"+1 780 484 5933",
    "sg:postcode":"T5P 3A7",
    "sg:province":"AB",
    "sg:tags":[
        "church"
    ],
    "wof:name":"Holy Spirit Roman Catholic Chr",
    "wof:placetype":"venue"
},
  "geometry": {"coordinates":[-113.595794678,53.5468406677],"type":"Point"}
}