{
  "type": "Feature",
  "properties": {
    "addr:full":"955 Rue Lucien-L'Allier Montreal QC H3G 2C2",
    "addr:housenumber":"955",
    "addr:postcode":"h3g 2c2",
    "addr:street":"Rue Lucien-L'Allier",
    "iso:country":"CA",
    "sg:address":"955 Rue Lucien-L'Allier",
    "sg:city":"Montreal",
    "sg:classifiers":[
        {
            "category":"Shopping",
            "subcategory":"Tobacco",
            "type":"Retail Goods"
        }
    ],
    "sg:phone":"+1 514 989 1160",
    "sg:postcode":"H3G 2C2",
    "sg:province":"QC",
    "sg:tags":[
        "cigarette",
        "cigar",
        "dealer"
    ],
    "wof:name":"Tabagie Metro Lucien L'Allier",
    "wof:placetype":"venue"
},
  "geometry": {"coordinates":[-73.554558,45.502434],"type":"Point"}
}