{
  "type": "Feature",
  "properties": {
    "addr:full":"18 Kempford Blvd North York ON M2N 2B9",
    "addr:housenumber":"18",
    "addr:postcode":"m2n 2b9",
    "addr:street":"Kempford Blvd",
    "iso:country":"CA",
    "sg:address":"18 Kempford Blvd",
    "sg:city":"North York",
    "sg:classifiers":[
        {
            "category":"Social Services",
            "subcategory":"Child Care",
            "type":"Services"
        }
    ],
    "sg:phone":"+1 416 222 0151",
    "sg:postcode":"M2N 2B9",
    "sg:province":"ON",
    "wof:name":"St Cyril's B & A School Club",
    "wof:placetype":"venue"
},
  "geometry": {"coordinates":[-79.4155578613,43.7769203186],"type":"Point"}
}