{
  "type": "Feature",
  "properties": {
    "addr:full":"6088 12th Ave Burnaby BC V3N 2J1",
    "addr:housenumber":"6088",
    "addr:postcode":"v3n 2j1",
    "addr:street":"12Th Ave",
    "iso:country":"CA",
    "sg:address":"6088 12th Ave",
    "sg:city":"Burnaby",
    "sg:classifiers":[
        {
            "category":"Professional",
            "subcategory":"Advertising",
            "type":"Services"
        }
    ],
    "sg:phone":"+1 604 522 6362",
    "sg:postcode":"V3N 2J1",
    "sg:province":"BC",
    "sg:tags":[
        "marketing",
        "counselor",
        "consultant"
    ],
    "wof:name":"Mesich Media Advertising Ltd",
    "wof:placetype":"venue"
},
  "geometry": {"coordinates":[-122.970146,49.198318],"type":"Point"}
}