{
  "type": "Feature",
  "properties": {
    "addr:full":"4830 Byng Rd Port Hardy BC V0N 2P0",
    "addr:housenumber":"4830",
    "addr:postcode":"v0n 2p0",
    "addr:street":"Byng Rd",
    "iso:country":"CA",
    "sg:address":"4830 Byng Rd",
    "sg:city":"Port Hardy",
    "sg:classifiers":[
        {
            "category":"Building & Trades",
            "subcategory":"Equipment Rental",
            "type":"Services"
        }
    ],
    "sg:phone":"+1 250 949 6353",
    "sg:postcode":"V0N 2P0",
    "sg:province":"BC",
    "sg:tags":[
        "aircraft",
        "charter",
        "leasing",
        "company",
        "airline"
    ],
    "wof:name":"Pacific Coastal Airlines Ltd",
    "wof:placetype":"venue"
},
  "geometry": {"coordinates":[-127.48732800000001,50.690571],"type":"Point"}
}