{
  "type": "Feature",
  "properties": {
    "addr:full":"208 1st Ave Field BC V0A 1G0",
    "addr:housenumber":"208",
    "addr:postcode":"v0a 1g0",
    "addr:street":"1St Ave",
    "iso:country":"CA",
    "sg:address":"208 1st Ave",
    "sg:city":"Field",
    "sg:classifiers":[
        {
            "category":"Travel",
            "subcategory":"Hotels & Motels",
            "type":"Entertainment"
        }
    ],
    "sg:phone":"+1 250 343 6446",
    "sg:postcode":"V0A 1G0",
    "sg:province":"BC",
    "sg:tags":[
        "resort"
    ],
    "wof:name":"Stephen Creek Guest Cabin",
    "wof:placetype":"venue"
},
  "geometry": {"coordinates":[-116.481658935,51.4040222168],"type":"Point"}
}