{
  "type": "Feature",
  "properties": {
    "addr:full":"Montreal QC H3B 3W4",
    "addr:postcode":"h3b 3w4",
    "iso:country":"CA",
    "sg:city":"Montreal",
    "sg:classifiers":[
        {
            "category":"Organizations",
            "subcategory":"Professional Association",
            "type":"Services"
        }
    ],
    "sg:phone":"+1 514 878 1105",
    "sg:postcode":"H3B 3W4",
    "sg:province":"QC",
    "sg:tags":[
        "accountant"
    ],
    "wof:name":"Societe Des Comptables En Mgmt",
    "wof:placetype":"venue"
},
  "geometry": {"coordinates":[-73.569298,45.502979],"type":"Point"}
}