{
  "type": "Feature",
  "properties": {
    "addr:full":"7940 118 St Delta BC V4C 6H1",
    "addr:housenumber":"7940",
    "addr:postcode":"v4c 6h1",
    "addr:street":"118 St",
    "iso:country":"CA",
    "sg:address":"7940 118 St",
    "sg:city":"Delta",
    "sg:classifiers":[
        {
            "category":"Organizations",
            "subcategory":"Religious Organization",
            "type":"Services"
        }
    ],
    "sg:phone":"+1 604 543 7712",
    "sg:postcode":"V4C 6H1",
    "sg:province":"BC",
    "sg:tags":[
        "church"
    ],
    "wof:name":"Nordel Fellowship Baptist",
    "wof:placetype":"venue"
},
  "geometry": {"coordinates":[-122.895813,49.147823],"type":"Point"}
}