{
  "type": "Feature",
  "properties": {
    "iso:country":"CA",
    "sg:address":"485 Rte Des Bosquets",
    "sg:city":"Sainte-Marie-DE-Blandford",
    "sg:classifiers":[
        {
            "category":"Education",
            "subcategory":"School",
            "type":"Public Place"
        }
    ],
    "sg:phone":"+1 819 283 2833",
    "sg:postcode":"G0X 2W0",
    "sg:province":"QC",
    "wof:name":"Centre D'Education Des Adultes",
    "wof:placetype":"venue"
},
  "geometry": {"coordinates":[-72.1779785156,46.3250427246],"type":"Point"}
}