{
  "type": "Feature",
  "properties": {
    "addr:full":"725 Portage Ave Winnipeg MB R3G 0M8",
    "addr:housenumber":"725",
    "addr:postcode":"r3g 0m8",
    "addr:street":"Portage Ave",
    "iso:country":"CA",
    "sg:address":"725 Portage Ave",
    "sg:city":"Winnipeg",
    "sg:classifiers":[
        {
            "category":"Manufacturing",
            "subcategory":"Printing",
            "type":"Manufacturing & Wholesale Goods"
        }
    ],
    "sg:phone":"+1 204 775 8721",
    "sg:postcode":"R3G 0M8",
    "sg:province":"MB",
    "sg:tags":[
        "printer"
    ],
    "wof:name":"Kromar Printing Ltd",
    "wof:placetype":"venue"
},
  "geometry": {"coordinates":[-97.1624832153,49.8876419067],"type":"Point"}
}