{
  "type": "Feature",
  "properties": {
    "addr:full":"60 Mill St Almonte ON K0A 1A0",
    "addr:housenumber":"60",
    "addr:postcode":"k0a 1a0",
    "addr:street":"Mill St",
    "iso:country":"CA",
    "sg:address":"60 Mill St",
    "sg:city":"Almonte",
    "sg:classifiers":[
        {
            "category":"Shopping",
            "subcategory":"Hobbies, Toys, & Games",
            "type":"Retail Goods"
        }
    ],
    "sg:phone":"+1 613 256 0257",
    "sg:postcode":"K0A 1A0",
    "sg:province":"ON",
    "sg:tags":[
        "product",
        "ceramic"
    ],
    "wof:name":"Stella's Crafty Corner",
    "wof:placetype":"venue"
},
  "geometry": {"coordinates":[-76.19602966310001,45.2252807617],"type":"Point"}
}