{
  "type": "Feature",
  "properties": {
    "addr:full":"30 Maberley Rd Winnipeg MB R2P 0E2",
    "addr:housenumber":"30",
    "addr:postcode":"r2p 0e2",
    "addr:street":"Maberley Rd",
    "iso:country":"CA",
    "sg:address":"30 Maberley Rd",
    "sg:city":"Winnipeg",
    "sg:classifiers":[
        {
            "category":"Social Services",
            "subcategory":"Child Care",
            "type":"Services"
        }
    ],
    "sg:phone":"+1 204 632 7516",
    "sg:postcode":"R2P 0E2",
    "sg:province":"MB",
    "wof:name":"Elwick Before & After School",
    "wof:placetype":"venue"
},
  "geometry": {"coordinates":[-97.1654510498,49.9447669983],"type":"Point"}
}