{
  "type": "Feature",
  "properties": {
    "iso:country":"CA",
    "sg:city":"London",
    "sg:classifiers":[
        {
            "category":"Wholesale",
            "subcategory":"Toys & Hobbies",
            "type":"Manufacturing & Wholesale Goods"
        }
    ],
    "sg:phone":"+1 519 680 3080",
    "sg:postcode":"N6E 1R3",
    "sg:province":"ON",
    "wof:name":"Brio Scanditoy Inc",
    "wof:placetype":"venue"
},
  "geometry": {"coordinates":[-81.2082824707,42.9354400635],"type":"Point"}
}