{
  "type": "Feature",
  "properties": {
    "addr:full":"627 Taylor St E Saskatoon SK S7H 1V9",
    "addr:housenumber":"627",
    "addr:postcode":"s7h 1v9",
    "addr:street":"Taylor St E",
    "iso:country":"CA",
    "sg:address":"627 Taylor St E",
    "sg:city":"Saskatoon",
    "sg:classifiers":[
        {
            "category":"Organizations",
            "subcategory":"Religious Organization",
            "type":"Services"
        }
    ],
    "sg:phone":"+1 306 343 9535",
    "sg:postcode":"S7H 1V9",
    "sg:province":"SK",
    "sg:tags":[
        "church"
    ],
    "wof:name":"St Paul's Lutheran Church",
    "wof:placetype":"venue"
},
  "geometry": {"coordinates":[-106.65509,52.107471],"type":"Point"}
}