{
  "type": "Feature",
  "properties": {
    "addr:full":"2296 Cheverie St Oakville ON L6J 6B2",
    "addr:housenumber":"2296",
    "addr:postcode":"l6j 6b2",
    "addr:street":"Cheverie St",
    "iso:country":"CA",
    "sg:address":"2296 Cheverie St",
    "sg:city":"Oakville",
    "sg:classifiers":[
        {
            "category":"Real Estate",
            "subcategory":"Real Estate Agent",
            "type":"Services"
        }
    ],
    "sg:phone":"+1 905 845 8258",
    "sg:postcode":"L6J 6B2",
    "sg:province":"ON",
    "sg:tags":[
        "appraiser"
    ],
    "wof:name":"Valufax Real Estate Appraisals",
    "wof:placetype":"venue"
},
  "geometry": {"coordinates":[-79.63500999999999,43.477448],"type":"Point"}
}