{
  "type": "Feature",
  "properties": {
    "addr:full":"1306 Algoma Rd Gloucester ON K1B 3W8",
    "addr:housenumber":"1306",
    "addr:postcode":"k1b 3w8",
    "addr:street":"Algoma Rd",
    "iso:country":"CA",
    "sg:address":"1306 Algoma Rd",
    "sg:city":"Gloucester",
    "sg:classifiers":[
        {
            "category":"Professional",
            "subcategory":"Management & Consulting",
            "type":"Services"
        }
    ],
    "sg:phone":"+1 613 248 0755",
    "sg:postcode":"K1B 3W8",
    "sg:province":"ON",
    "sg:tags":[
        "aviation",
        "consultant"
    ],
    "wof:name":"Accident Cause Analysis",
    "wof:placetype":"venue"
},
  "geometry": {"coordinates":[-75.61884307859999,45.4167289734],"type":"Point"}
}