{
  "type": "Feature",
  "properties": {
    "addr:full":"1590 Queensway Prince George BC V2L 1L7",
    "addr:housenumber":"1590",
    "addr:postcode":"v2l 1l7",
    "addr:street":"Queensway",
    "iso:country":"CA",
    "sg:address":"1590 Queensway",
    "sg:city":"Prince George",
    "sg:classifiers":[
        {
            "category":"Organizations",
            "subcategory":"Religious Organization",
            "type":"Services"
        }
    ],
    "sg:phone":"+1 250 564 7134",
    "sg:postcode":"V2L 1L7",
    "sg:province":"BC",
    "sg:tags":[
        "church"
    ],
    "wof:name":"Gospel Chapel",
    "wof:placetype":"venue"
},
  "geometry": {"coordinates":[-122.741996765,53.909526825],"type":"Point"}
}