{
  "type": "Feature",
  "properties": {
    "addr:full":"67 Preston St Ottawa ON K1R 7N6",
    "addr:housenumber":"67",
    "addr:postcode":"k1r 7n6",
    "addr:street":"Preston St",
    "iso:country":"CA",
    "sg:address":"67 Preston St",
    "sg:city":"Ottawa",
    "sg:classifiers":[
        {
            "category":"Professional",
            "type":"Services"
        }
    ],
    "sg:phone":"+1 613 864 2879",
    "sg:postcode":"K1R 7N6",
    "sg:province":"ON",
    "sg:tags":[
        "art",
        "restoring"
    ],
    "wof:name":"Heritage Guild",
    "wof:placetype":"venue"
},
  "geometry": {"coordinates":[-75.71494300000001,45.409901],"type":"Point"}
}