{
  "type": "Feature",
  "properties": {
    "addr:full":"1390 Prince of Wales Dr Ottawa ON K2C 3N6",
    "addr:housenumber":"1390",
    "addr:postcode":"k2c 3n6",
    "addr:street":"Prince Of Wales Dr",
    "iso:country":"CA",
    "sg:address":"1390 Prince of Wales Dr",
    "sg:city":"Ottawa",
    "sg:classifiers":[
        {
            "category":"Banks & Credit Unions",
            "subcategory":"Investment Brokerage",
            "type":"Services"
        }
    ],
    "sg:phone":"+1 613 225 7775",
    "sg:postcode":"K2C 3N6",
    "sg:province":"ON",
    "sg:tags":[
        "consultant",
        "planning",
        "financial"
    ],
    "wof:name":"Mc Kechnie Financial Svc Inc",
    "wof:placetype":"venue"
},
  "geometry": {"coordinates":[-75.7026596069,45.3698425293],"type":"Point"}
}