{
  "type": "Feature",
  "properties": {
    "addr:full":"129 Regent Ave W Winnipeg MB R2C 1R1",
    "addr:housenumber":"129",
    "addr:postcode":"r2c 1r1",
    "addr:street":"Regent Ave W",
    "iso:country":"CA",
    "sg:address":"129 Regent Ave W",
    "sg:city":"Winnipeg",
    "sg:classifiers":[
        {
            "category":"Restaurant",
            "type":"Food & Drink"
        }
    ],
    "sg:phone":"+1 204 222 3245",
    "sg:postcode":"R2C 1R1",
    "sg:province":"MB",
    "wof:name":"Copa Cambana Pizza & Rstrnt",
    "wof:placetype":"venue"
},
  "geometry": {"coordinates":[-97.00354799999999,49.895206],"type":"Point"}
}