{
  "type": "Feature",
  "properties": {
    "iso:country":"CA",
    "sg:city":"Rosemere",
    "sg:classifiers":[
        {
            "category":"Shopping",
            "subcategory":"Clothing, Apparel, & Fashions",
            "type":"Retail Goods"
        }
    ],
    "sg:phone":"+1 450 437 3827",
    "sg:postcode":"J7A 3T2",
    "sg:province":"QC",
    "wof:name":"Boutique Marie Claire",
    "wof:placetype":"venue"
},
  "geometry": {"coordinates":[-73.817055,45.632904],"type":"Point"}
}