{
  "type": "Feature",
  "properties": {
    "iso:country":"CA",
    "sg:address":"53 Rue Principale",
    "sg:city":"LA Sarre",
    "sg:classifiers":[
        {
            "category":"Food & Beverages",
            "subcategory":"Groceries & Convenience Stores",
            "type":"Retail Goods"
        }
    ],
    "sg:phone":"+1 819 333 2548",
    "sg:postcode":"J9Z 1W7",
    "sg:province":"QC",
    "wof:name":"Depanneur LA Sarre Enrg",
    "wof:placetype":"venue"
},
  "geometry": {"coordinates":[-79.20510899999999,48.814358],"type":"Point"}
}