{
  "type": "Feature",
  "properties": {
    "iso:country":"CA",
    "sg:address":"3840 Boul Taschereau",
    "sg:city":"Greenfield Park",
    "sg:classifiers":[
        {
            "category":"Food & Beverages",
            "subcategory":"Fruits & Vegetables",
            "type":"Retail Goods"
        }
    ],
    "sg:phone":"+1 450 465 0440",
    "sg:postcode":"J4V 2H9",
    "sg:province":"QC",
    "sg:tags":[
        "produce"
    ],
    "wof:name":"Fruiterie Du 440",
    "wof:placetype":"venue"
},
  "geometry": {"coordinates":[-73.4700164795,45.4870262146],"type":"Point"}
}