{
  "type": "Feature",
  "properties": {
    "iso:country":"CA",
    "sg:city":"Toronto",
    "sg:classifiers":[
        {
            "category":"Shopping",
            "subcategory":"Gifts & Souvenirs",
            "type":"Retail Goods"
        }
    ],
    "sg:phone":"+1 416 926 0288",
    "sg:postcode":"M5S 3A5",
    "sg:province":"ON",
    "sg:tags":[
        "basket",
        "parcel"
    ],
    "wof:name":"Gifts To Britain",
    "wof:placetype":"venue"
},
  "geometry": {"coordinates":[-79.3877029419,43.6660575867],"type":"Point"}
}