{
  "type": "Feature",
  "properties": {
    "addr:full":"25 Saint Mary St Toronto ON M4Y 1R2",
    "addr:housenumber":"25",
    "addr:postcode":"m4y 1r2",
    "addr:street":"Saint Mary St",
    "iso:country":"CA",
    "sg:address":"25 Saint Mary St",
    "sg:city":"Toronto",
    "sg:classifiers":[
        {
            "category":"Professional",
            "subcategory":"Lawyer & Legal Services",
            "type":"Services"
        }
    ],
    "sg:phone":"+1 416 961 1339",
    "sg:postcode":"M4Y 1R2",
    "sg:province":"ON",
    "sg:tags":[
        "attorney"
    ],
    "wof:name":"Smith, Gary",
    "wof:placetype":"venue"
},
  "geometry": {"coordinates":[-79.387039,43.667591],"type":"Point"}
}