{
  "type": "Feature",
  "properties": {
    "addr:full":"Whitehorse YT Y1A 1Y8",
    "addr:postcode":"y1a 1y8",
    "iso:country":"CA",
    "sg:city":"Whitehorse",
    "sg:classifiers":[
        {
            "category":"Manufacturing",
            "subcategory":"Printing",
            "type":"Manufacturing & Wholesale Goods"
        }
    ],
    "sg:phone":"+1 867 633 3232",
    "sg:postcode":"Y1A 1Y8",
    "sg:province":"YT",
    "sg:tags":[
        "printer"
    ],
    "wof:name":"Cracker Jack Media",
    "wof:placetype":"venue"
},
  "geometry": {"coordinates":[-135.054733,60.716682],"type":"Point"}
}