{
  "type": "Feature",
  "properties": {
    "iso:country":"CA",
    "sg:city":"Yamachiche",
    "sg:classifiers":[
        {
            "category":"Insurance",
            "subcategory":"Insurance Agent",
            "type":"Services"
        }
    ],
    "sg:phone":"+1 819 296 3934",
    "sg:postcode":"G0X 3L0",
    "sg:province":"QC",
    "wof:name":"Assurances Jean Villemure Inc",
    "wof:placetype":"venue"
},
  "geometry": {"coordinates":[-72.82894134519999,46.2835502625],"type":"Point"}
}