{
  "type": "Feature",
  "properties": {
    "addr:full":"2471 Marine Dr # 9 West Vancouver BC V7V 1L3",
    "addr:housenumber":"2471",
    "addr:postcode":"v7v 1l3",
    "addr:street":"Marine Dr # 9",
    "iso:country":"CA",
    "sg:address":"2471 Marine Dr # 9",
    "sg:city":"West Vancouver",
    "sg:classifiers":[
        {
            "category":"Recreation",
            "type":"Entertainment"
        }
    ],
    "sg:phone":"+1 604 921 9798",
    "sg:postcode":"V7V 1L3",
    "sg:province":"BC",
    "sg:tags":[
        "instruction",
        "swimming"
    ],
    "wof:name":"West Vancouver Otters Swim Clb",
    "wof:placetype":"venue"
},
  "geometry": {"coordinates":[-123.181229,49.334812],"type":"Point"}
}