{
  "type": "Feature",
  "properties": {
    "iso:country":"CA",
    "sg:address":"1 York St",
    "sg:city":"Picton",
    "sg:classifiers":[
        {
            "category":"Retail",
            "subcategory":"Auto Repair",
            "type":"Services"
        }
    ],
    "sg:phone":"+1 613 476 8430",
    "sg:postcode":"K0K 2T0",
    "sg:province":"ON",
    "sg:tags":[
        "repairing",
        "automobile"
    ],
    "wof:name":"Arnie's Muffler & General Rpr",
    "wof:placetype":"venue"
},
  "geometry": {"coordinates":[-77.1401977539,44.0070724487],"type":"Point"}
}