{
  "type": "Feature",
  "properties": {
    "addr:full":"Surrey BC V3R 8X8",
    "addr:postcode":"v3r 8x8",
    "iso:country":"CA",
    "sg:city":"Surrey",
    "sg:classifiers":[
        {
            "category":"Retail",
            "subcategory":"Laundry & Dry Cleaning",
            "type":"Services"
        }
    ],
    "sg:phone":"+1 604 589 1800",
    "sg:postcode":"V3R 8X8",
    "sg:province":"BC",
    "sg:tags":[
        "cleaners"
    ],
    "wof:name":"Save on Dry Cleaning Ltd",
    "wof:placetype":"venue"
},
  "geometry": {"coordinates":[-122.80072,49.185871],"type":"Point"}
}