{
  "type": "Feature",
  "properties": {
    "addr:full":"932 King St W Toronto ON M5V 1P5",
    "addr:housenumber":"932",
    "addr:postcode":"m5v 1p5",
    "addr:street":"King St W",
    "iso:country":"CA",
    "sg:address":"932 King St W",
    "sg:city":"Toronto",
    "sg:classifiers":[
        {
            "category":"Personal",
            "subcategory":"Beauty Salon",
            "type":"Services"
        }
    ],
    "sg:phone":"+1 416 504 9832",
    "sg:postcode":"M5V 1P5",
    "sg:province":"ON",
    "wof:name":"Mario Lupo Hair Design",
    "wof:placetype":"venue"
},
  "geometry": {"coordinates":[-79.411247,43.642311],"type":"Point"}
}