{
  "type": "Feature",
  "properties": {
    "addr:full":"692 Danforth Ave Toronto ON M4J 1L1",
    "addr:housenumber":"692",
    "addr:postcode":"m4j 1l1",
    "addr:street":"Danforth Ave",
    "iso:country":"CA",
    "sg:address":"692 Danforth Ave",
    "sg:city":"Toronto",
    "sg:classifiers":[
        {
            "category":"Shopping",
            "subcategory":"Optical Goods",
            "type":"Retail Goods"
        }
    ],
    "sg:phone":"+1 416 463 6498",
    "sg:postcode":"M4J 1L1",
    "sg:province":"ON",
    "sg:tags":[
        "optician"
    ],
    "wof:name":"Kappa Optical",
    "wof:placetype":"venue"
},
  "geometry": {"coordinates":[-79.3437957764,43.6792564392],"type":"Point"}
}