{
  "type": "Feature",
  "properties": {
    "addr:full":"200 Kortright Rd W Guelph ON N1G 4X8",
    "addr:housenumber":"200",
    "addr:postcode":"n1g 4x8",
    "addr:street":"Kortright Rd W",
    "iso:country":"CA",
    "sg:address":"200 Kortright Rd W",
    "sg:city":"Guelph",
    "sg:classifiers":[
        {
            "category":"Banks & Credit Unions",
            "subcategory":"Bank",
            "type":"Services"
        }
    ],
    "sg:phone":"+1 519 763 3111",
    "sg:postcode":"N1G 4X8",
    "sg:province":"ON",
    "wof:name":"Td Canada Trust",
    "wof:placetype":"venue"
},
  "geometry": {"coordinates":[-80.220856,43.513386],"type":"Point"}
}