{
  "type": "Feature",
  "properties": {
    "addr:full":"87 Commonwealth Dr # A Botwood NL A0H 1E0",
    "addr:housenumber":"87",
    "addr:postcode":"a0h 1e0",
    "addr:street":"Commonwealth Dr # A Botwood",
    "iso:country":"CA",
    "sg:address":"87 Commonwealth Dr # A",
    "sg:city":"Botwood",
    "sg:classifiers":[
        {
            "category":"Restaurant",
            "type":"Food & Drink"
        }
    ],
    "sg:phone":"+1 709 257 2583",
    "sg:postcode":"A0H 1E0",
    "sg:province":"NL",
    "sg:tags":[
        "caterer"
    ],
    "wof:name":"C & E Catering",
    "wof:placetype":"venue"
},
  "geometry": {"coordinates":[-55.3473205566,49.1534500122],"type":"Point"}
}