{
  "type": "Feature",
  "properties": {
    "addr:full":"Pickering ON L1W 3G7",
    "addr:postcode":"l1w 3g7",
    "iso:country":"CA",
    "sg:city":"Pickering",
    "sg:classifiers":[
        {
            "category":"Professional",
            "subcategory":"Business Services",
            "type":"Services"
        }
    ],
    "sg:phone":"+1 905 837 2667",
    "sg:postcode":"L1W 3G7",
    "sg:province":"ON",
    "sg:tags":[
        "interior",
        "consultant",
        "design",
        "decorator"
    ],
    "wof:name":"Colours & Concepts",
    "wof:placetype":"venue"
},
  "geometry": {"coordinates":[-79.0657196045,43.8333435059],"type":"Point"}
}