{
  "type": "Feature",
  "properties": {
    "addr:full":"Etobicoke ON M9V 4E4",
    "addr:postcode":"m9v 4e4",
    "iso:country":"CA",
    "sg:city":"Etobicoke",
    "sg:classifiers":[
        {
            "category":"Food & Beverages",
            "subcategory":"Groceries & Convenience Stores",
            "type":"Retail Goods"
        }
    ],
    "sg:phone":"+1 416 742 3561",
    "sg:postcode":"M9V 4E4",
    "sg:province":"ON",
    "wof:name":"Sunrise Food Fair",
    "wof:placetype":"venue"
},
  "geometry": {"coordinates":[-79.600899,43.730728],"type":"Point"}
}