{
  "type": "Feature",
  "properties": {
    "addr:full":"Langley BC V3A 4K7",
    "addr:postcode":"v3a 4k7",
    "iso:country":"CA",
    "sg:city":"Langley",
    "sg:classifiers":[
        {
            "category":"Retail",
            "subcategory":"Auto Repair",
            "type":"Services"
        }
    ],
    "sg:phone":"+1 604 534 6823",
    "sg:postcode":"V3A 4K7",
    "sg:province":"BC",
    "sg:tags":[
        "repairing",
        "automobile"
    ],
    "wof:name":"Murrayville Auto Svc",
    "wof:placetype":"venue"
},
  "geometry": {"coordinates":[-122.66696899999999,49.109364],"type":"Point"}
}