{
  "type": "Feature",
  "properties": {
    "addr:full":"9984 Boul DE Saint-Canut Mirabel QC J7N 1K1",
    "addr:housenumber":"9984",
    "addr:postcode":"j7n 1k1",
    "addr:street":"Boul De Saint-Canut",
    "iso:country":"CA",
    "sg:address":"9984 Boul DE Saint-Canut",
    "sg:city":"Mirabel",
    "sg:classifiers":[
        {
            "category":"Education",
            "subcategory":"School",
            "type":"Public Place"
        }
    ],
    "sg:phone":"+1 450 438 0424",
    "sg:postcode":"J7N 1K1",
    "sg:province":"QC",
    "wof:name":"Ste-Anne Ecole",
    "wof:placetype":"venue"
},
  "geometry": {"coordinates":[-74.082489,45.717762],"type":"Point"}
}