{
  "type": "Feature",
  "properties": {
    "addr:full":"Berkeley ON N0H 1C0",
    "addr:postcode":"n0h 1c0",
    "iso:country":"CA",
    "sg:city":"Berkeley",
    "sg:classifiers":[
        {
            "category":"Retail",
            "subcategory":"Auto Repair",
            "type":"Services"
        }
    ],
    "sg:phone":"+1 519 986 2398",
    "sg:postcode":"N0H 1C0",
    "sg:province":"ON",
    "sg:tags":[
        "repairing",
        "automobile"
    ],
    "wof:name":"Williamson's Garage",
    "wof:placetype":"venue"
},
  "geometry": {"coordinates":[-80.727417,44.366329],"type":"Point"}
}