{
  "type": "Feature",
  "properties": {
    "iso:country":"CA",
    "sg:address":"7084 Smith Industrial Dr",
    "sg:city":"Mcgregor",
    "sg:classifiers":[
        {
            "category":"Wholesale",
            "subcategory":"Scrap",
            "type":"Manufacturing & Wholesale Goods"
        }
    ],
    "sg:phone":"+1 519 726 4299",
    "sg:postcode":"N0R 1J0",
    "sg:province":"ON",
    "sg:tags":[
        "recycling",
        "center"
    ],
    "wof:name":"Cdl Recyclers Inc",
    "wof:placetype":"venue"
},
  "geometry": {"coordinates":[-82.993637085,42.1623954773],"type":"Point"}
}