{
  "type": "Feature",
  "properties": {
    "addr:full":"33 Rue Girouard Victoriaville QC G6P 5S6",
    "addr:housenumber":"33",
    "addr:postcode":"g6p 5s6",
    "addr:street":"Rue Girouard",
    "iso:country":"CA",
    "sg:address":"33 Rue Girouard",
    "sg:city":"Victoriaville",
    "sg:classifiers":[
        {
            "category":"Health Services",
            "subcategory":"Doctor",
            "type":"Services"
        }
    ],
    "sg:phone":"+1 819 357 8700",
    "sg:postcode":"G6P 5S6",
    "sg:province":"QC",
    "sg:tags":[
        "dentist"
    ],
    "wof:name":"Larochelle, J-Francois DDS",
    "wof:placetype":"venue"
},
  "geometry": {"coordinates":[-71.936668,46.051884],"type":"Point"}
}