{
  "type": "Feature",
  "properties": {
    "addr:full":"1440 101 Ave Dawson Creek BC V1G 2A5",
    "addr:housenumber":"1440",
    "addr:postcode":"v1g 2a5",
    "addr:street":"101 Ave",
    "iso:country":"CA",
    "sg:address":"1440 101 Ave",
    "sg:city":"Dawson Creek",
    "sg:classifiers":[
        {
            "category":"Retail",
            "subcategory":"Auto Repair",
            "type":"Services"
        }
    ],
    "sg:phone":"+1 250 782 8823",
    "sg:postcode":"V1G 2A5",
    "sg:province":"BC",
    "sg:tags":[
        "body",
        "automobile",
        "painting"
    ],
    "wof:name":"Pace Autobody",
    "wof:placetype":"venue"
},
  "geometry": {"coordinates":[-120.242332,55.760929],"type":"Point"}
}