{
  "type": "Feature",
  "properties": {
    "addr:full":"474 Dundas St Woodstock ON N4S 1C4",
    "addr:housenumber":"474",
    "addr:postcode":"n4s 1c4",
    "addr:street":"Dundas St",
    "iso:country":"CA",
    "sg:address":"474 Dundas St",
    "sg:city":"Woodstock",
    "sg:classifiers":[
        {
            "category":"Restaurant",
            "type":"Food & Drink"
        }
    ],
    "sg:phone":"+1 519 537 7623",
    "sg:postcode":"N4S 1C4",
    "sg:province":"ON",
    "sg:tags":[
        "product",
        "dairy",
        "caterer"
    ],
    "wof:name":"Dairy Capital Cheese Shoppe",
    "wof:placetype":"venue"
},
  "geometry": {"coordinates":[-80.757339,43.129868],"type":"Point"}
}