{
  "type": "Feature",
  "properties": {
    "addr:full":"469 South Ave Spruce Grove AB T7X 4G2",
    "addr:housenumber":"469",
    "addr:postcode":"t7x 4g2",
    "addr:street":"South Ave",
    "iso:country":"CA",
    "sg:address":"469 South Ave",
    "sg:city":"Spruce Grove",
    "sg:classifiers":[
        {
            "category":"Building & Trades",
            "subcategory":"Electrical",
            "type":"Services"
        }
    ],
    "sg:phone":"+1 780 962 0241",
    "sg:postcode":"T7X 4G2",
    "sg:province":"AB",
    "sg:tags":[
        "electric",
        "contractor"
    ],
    "wof:name":"Lee Electric",
    "wof:placetype":"venue"
},
  "geometry": {"coordinates":[-118.862190247,55.0251312256],"type":"Point"}
}