{
  "type": "Feature",
  "properties": {
    "addr:full":"786 Dufferin Ave Winnipeg MB R2W 2Z6",
    "addr:housenumber":"786",
    "addr:postcode":"r2w 2z6",
    "addr:street":"Dufferin Ave",
    "iso:country":"CA",
    "sg:address":"786 Dufferin Ave",
    "sg:city":"Winnipeg",
    "sg:classifiers":[
        {
            "category":"Manufacturing",
            "subcategory":"Metals",
            "type":"Manufacturing & Wholesale Goods"
        }
    ],
    "sg:phone":"+1 204 582 1002",
    "sg:postcode":"R2W 2Z6",
    "sg:province":"MB",
    "sg:tags":[
        "fabricating",
        "work",
        "sheet",
        "contractor"
    ],
    "wof:name":"Advance Sheet Metal CO Ltd",
    "wof:placetype":"venue"
},
  "geometry": {"coordinates":[-97.157906,49.916325],"type":"Point"}
}