{
  "type": "Feature",
  "properties": {
    "iso:country":"CA",
    "sg:address":"486 Chebucto St",
    "sg:city":"Baddeck",
    "sg:classifiers":[
        {
            "category":"Insurance",
            "subcategory":"Insurance Agent",
            "type":"Services"
        }
    ],
    "sg:phone":"+1 902 295 2560",
    "sg:postcode":"B0E 1B0",
    "sg:province":"NS",
    "wof:name":"A A Munro Insurance Ltd",
    "wof:placetype":"venue"
},
  "geometry": {"coordinates":[-60.749641,46.100491],"type":"Point"}
}