{
  "type": "Feature",
  "properties": {
    "iso:country":"CA",
    "sg:address":"708 Victoria Ave",
    "sg:city":"Regina",
    "sg:classifiers":[
        {
            "category":"Restaurant",
            "type":"Food & Drink"
        }
    ],
    "sg:phone":"+1 306 359 3888",
    "sg:postcode":"S4N 0R3",
    "sg:province":"SK",
    "wof:name":"Triple 8 Pizza",
    "wof:placetype":"venue"
},
  "geometry": {"coordinates":[-104.59101867699999,50.447303772],"type":"Point"}
}