{
  "type": "Feature",
  "properties": {
    "addr:full":"640 Mckeown Ave North Bay ON P1B 7M2",
    "addr:housenumber":"640",
    "addr:postcode":"p1b 7m2",
    "addr:street":"Mckeown Ave",
    "iso:country":"CA",
    "sg:address":"640 Mckeown Ave",
    "sg:city":"North Bay",
    "sg:classifiers":[
        {
            "category":"Manufacturing",
            "subcategory":"Tools & Machinery",
            "type":"Manufacturing & Wholesale Goods"
        }
    ],
    "sg:phone":"+1 705 472 3320",
    "sg:postcode":"P1B 7M2",
    "sg:province":"ON",
    "sg:tags":[
        "equipment",
        "mining",
        "trencher",
        "supply"
    ],
    "wof:name":"Atlas Copco Exploration Prdcts",
    "wof:placetype":"venue"
},
  "geometry": {"coordinates":[-79.479736,46.332333],"type":"Point"}
}