{
  "type": "Feature",
  "properties": {
    "addr:full":"3806 Albert St Regina SK S4S 3R1",
    "addr:housenumber":"3806",
    "addr:postcode":"s4s 3r1",
    "addr:street":"Albert St",
    "iso:country":"CA",
    "sg:address":"3806 Albert St",
    "sg:city":"Regina",
    "sg:classifiers":[
        {
            "category":"Cinema",
            "subcategory":"Movie Theater",
            "type":"Entertainment"
        }
    ],
    "sg:phone":"+1 306 359 6353",
    "sg:postcode":"S4S 3R1",
    "sg:province":"SK",
    "wof:name":"Rainbow Cinemas",
    "wof:placetype":"venue"
},
  "geometry": {"coordinates":[-104.618370056,50.4185142517],"type":"Point"}
}