{
  "type": "Feature",
  "properties": {
    "addr:full":"26 Union St Bedford NS B4A 2B5",
    "addr:housenumber":"26",
    "addr:postcode":"b4a 2b5",
    "addr:street":"Union St",
    "iso:country":"CA",
    "sg:address":"26 Union St",
    "sg:city":"Bedford",
    "sg:classifiers":[
        {
            "category":"Banks & Credit Unions",
            "subcategory":"Financial Services",
            "type":"Services"
        }
    ],
    "sg:phone":"+1 902 493 5484",
    "sg:postcode":"B4A 2B5",
    "sg:province":"NS",
    "sg:tags":[
        "bankruptcy",
        "trustee"
    ],
    "wof:name":"Wbli Inc",
    "wof:placetype":"venue"
},
  "geometry": {"coordinates":[-63.660851,44.732212],"type":"Point"}
}