{
  "type": "Feature",
  "properties": {
    "addr:full":"1649 Boul Pie-Xi N Val-Belair QC G3J 1L4",
    "addr:housenumber":"1649",
    "addr:postcode":"g3j 1l4",
    "addr:street":"Boul Pie-Xi N",
    "iso:country":"CA",
    "sg:address":"1649 Boul Pie-Xi N",
    "sg:city":"Val-Belair",
    "sg:classifiers":[
        {
            "category":"Retail",
            "subcategory":"Auto Repair",
            "type":"Services"
        }
    ],
    "sg:phone":"+1 418 842 3789",
    "sg:postcode":"G3J 1L4",
    "sg:province":"QC",
    "sg:tags":[
        "repairing",
        "automobile"
    ],
    "wof:name":"Atelier Mecanique Val-Belair",
    "wof:placetype":"venue"
},
  "geometry": {"coordinates":[-71.440826,46.870125],"type":"Point"}
}