{
  "type": "Feature",
  "properties": {
    "addr:full":"Beauport QC G1E 7C8",
    "addr:postcode":"qc g1e 7c8",
    "iso:country":"CA",
    "sg:city":"Beauport",
    "sg:classifiers":[
        {
            "category":"Professional",
            "subcategory":"Lawyer & Legal Services",
            "type":"Services"
        }
    ],
    "sg:phone":"+1 418 660 2001",
    "sg:postcode":"G1E 7C8",
    "sg:province":"QC",
    "sg:tags":[
        "attorney"
    ],
    "wof:name":"Leclerc, Carl",
    "wof:placetype":"venue"
},
  "geometry": {"coordinates":[-71.218681,46.854279],"type":"Point"}
}