{
  "type": "Feature",
  "properties": {
    "addr:full":"283 Tower Rd Lindsay ON K9V 4R4",
    "addr:housenumber":"283",
    "addr:postcode":"k9v 4r4",
    "addr:street":"Tower Rd",
    "iso:country":"CA",
    "sg:address":"283 Tower Rd",
    "sg:city":"Lindsay",
    "sg:classifiers":[
        {
            "category":"Retail",
            "subcategory":"Portrait Studio",
            "type":"Services"
        }
    ],
    "sg:phone":"+1 705 324 3985",
    "sg:postcode":"K9V 4R4",
    "sg:province":"ON",
    "sg:tags":[
        "photographer"
    ],
    "wof:name":"Shelley James Photography",
    "wof:placetype":"venue"
},
  "geometry": {"coordinates":[-78.68272399999999,44.277168],"type":"Point"}
}