{
  "type": "Feature",
  "properties": {
    "iso:country":"CA",
    "sg:address":"6 Isabella St",
    "sg:city":"Perth",
    "sg:classifiers":[
        {
            "category":"Manufacturing",
            "subcategory":"Printing",
            "type":"Manufacturing & Wholesale Goods"
        }
    ],
    "sg:phone":"+1 613 267 5780",
    "sg:postcode":"K7H 2W5",
    "sg:province":"ON",
    "sg:tags":[
        "printer"
    ],
    "wof:name":"Print & Copy Shop",
    "wof:placetype":"venue"
},
  "geometry": {"coordinates":[-76.2511291504,44.9060249329],"type":"Point"}
}