{
  "type": "Feature",
  "properties": {
    "addr:full":"2239 King Rd King City ON L7B 1G2",
    "addr:housenumber":"2239",
    "addr:postcode":"l7b 1g2",
    "addr:street":"King Rd",
    "iso:country":"CA",
    "sg:address":"2239 King Rd",
    "sg:city":"King City",
    "sg:classifiers":[
        {
            "category":"Professional",
            "subcategory":"Accounting & Tax Preparation",
            "type":"Services"
        }
    ],
    "sg:phone":"+1 905 833 5353",
    "sg:postcode":"L7B 1G2",
    "sg:province":"ON",
    "sg:tags":[
        "bookkeeping",
        "general"
    ],
    "wof:name":"Personal Tax Svc King City Ltd",
    "wof:placetype":"venue"
},
  "geometry": {"coordinates":[-79.5277709961,43.9287490845],"type":"Point"}
}