{
  "type": "Feature",
  "properties": {
    "addr:full":"4614 Woodgreen Dr West Vancouver BC V7S 2V2",
    "addr:housenumber":"4614",
    "addr:postcode":"v7s 2v2",
    "addr:street":"Woodgreen Dr",
    "iso:country":"CA",
    "sg:address":"4614 Woodgreen Dr",
    "sg:city":"West Vancouver",
    "sg:classifiers":[
        {
            "category":"Building & Trades",
            "subcategory":"Construction",
            "type":"Services"
        }
    ],
    "sg:phone":"+1 604 921 9260",
    "sg:postcode":"V7S 2V2",
    "sg:province":"BC",
    "sg:tags":[
        "general",
        "contractor"
    ],
    "wof:name":"Camelot Construction Ltd",
    "wof:placetype":"venue"
},
  "geometry": {"coordinates":[-123.24456024200001,49.3544120789],"type":"Point"}
}