{
  "type": "Feature",
  "properties": {
    "addr:full":"17 Rue DE L'Eglise Riviere-Trois-Pistoles QC G0L 2E0",
    "addr:housenumber":"17",
    "addr:postcode":"g0l 2e0",
    "addr:street":"Rue De L'Eglise Riviere-Trois-Pistoles",
    "iso:country":"CA",
    "sg:address":"17 Rue DE L'Eglise",
    "sg:city":"Riviere-Trois-Pistoles",
    "sg:classifiers":[
        {
            "category":"Recreation",
            "type":"Entertainment"
        }
    ],
    "sg:phone":"+1 418 851 2006",
    "sg:postcode":"G0L 2E0",
    "sg:province":"QC",
    "sg:tags":[
        "center"
    ],
    "wof:name":"Comite Des Loisirs Notre-Dame",
    "wof:placetype":"venue"
},
  "geometry": {"coordinates":[-69.211395,48.096008],"type":"Point"}
}