{
  "type": "Feature",
  "properties": {
    "addr:full":"8 Loyalist Dr Brighton ON K0K 1H0",
    "addr:housenumber":"8",
    "addr:postcode":"k0k 1h0",
    "addr:street":"Loyalist Dr",
    "iso:country":"CA",
    "sg:address":"8 Loyalist Dr",
    "sg:city":"Brighton",
    "sg:classifiers":[
        {
            "category":"Building & Trades",
            "subcategory":"Electrical",
            "type":"Services"
        }
    ],
    "sg:phone":"+1 613 475 5818",
    "sg:postcode":"K0K 1H0",
    "sg:province":"ON",
    "sg:tags":[
        "electric",
        "contractor"
    ],
    "wof:name":"Kenlin Electric",
    "wof:placetype":"venue"
},
  "geometry": {"coordinates":[-77.7305679321,44.0345077515],"type":"Point"}
}