{
  "type": "Feature",
  "properties": {
    "addr:full":"6007 16th Ave E Markham ON L3P 2B2",
    "addr:housenumber":"6007",
    "addr:postcode":"l3p 2b2",
    "addr:street":"16Th Ave E",
    "iso:country":"CA",
    "sg:address":"6007 16th Ave E",
    "sg:city":"Markham",
    "sg:classifiers":[
        {
            "category":"Building & Trades",
            "subcategory":"Construction",
            "type":"Services"
        }
    ],
    "sg:phone":"+1 905 201 0580",
    "sg:postcode":"L3P 2B2",
    "sg:province":"ON",
    "sg:tags":[
        "home",
        "improvement"
    ],
    "wof:name":"Nova Decor",
    "wof:placetype":"venue"
},
  "geometry": {"coordinates":[-79.263008,43.892097],"type":"Point"}
}