{
  "type": "Feature",
  "properties": {
    "addr:full":"1082 Rue Aime-Gravel LA Baie QC G7B 2M5",
    "addr:housenumber":"1082",
    "addr:postcode":"g7b 2m5",
    "addr:street":"Rue Aime-Gravel",
    "iso:country":"CA",
    "sg:address":"1082 Rue Aime-Gravel",
    "sg:city":"LA Baie",
    "sg:classifiers":[
        {
            "category":"Restaurant",
            "type":"Food & Drink"
        }
    ],
    "sg:phone":"+1 418 544 3369",
    "sg:postcode":"G7B 2M5",
    "sg:province":"QC",
    "wof:name":"Mc Donald's",
    "wof:placetype":"venue"
},
  "geometry": {"coordinates":[-70.8821563721,48.3369522095],"type":"Point"}
}