{
  "type": "Feature",
  "properties": {
    "addr:full":"5370 Munro Crt Burlington ON L7L 5N8",
    "addr:housenumber":"5370",
    "addr:postcode":"l7l 5n8",
    "addr:street":"Munro Crt",
    "iso:country":"CA",
    "sg:address":"5370 Munro Crt",
    "sg:city":"Burlington",
    "sg:classifiers":[
        {
            "category":"Professional",
            "subcategory":"Management & Consulting",
            "type":"Services"
        }
    ],
    "sg:phone":"+1 905 632 8787",
    "sg:postcode":"L7L 5N8",
    "sg:province":"ON",
    "sg:tags":[
        "project",
        "consultant",
        "product"
    ],
    "wof:name":"Lawhill Limited",
    "wof:placetype":"venue"
},
  "geometry": {"coordinates":[-79.757851,43.389912],"type":"Point"}
}