{
  "type": "Feature",
  "properties": {
    "addr:full":"1936 Av Saint-Marc Shawinigan QC G9N 2J1",
    "addr:housenumber":"1936",
    "addr:postcode":"g9n 2j1",
    "addr:street":"Av Saint-Marc",
    "iso:country":"CA",
    "sg:address":"1936 Av Saint-Marc",
    "sg:city":"Shawinigan",
    "sg:classifiers":[
        {
            "category":"Insurance",
            "subcategory":"Insurance Agent",
            "type":"Services"
        }
    ],
    "sg:phone":"+1 819 537 5711",
    "sg:postcode":"G9N 2J1",
    "sg:province":"QC",
    "wof:name":"Assurances Generales-Caisses",
    "wof:placetype":"venue"
},
  "geometry": {"coordinates":[-72.743065,46.553127],"type":"Point"}
}