{
  "type": "Feature",
  "properties": {
    "addr:full":"Chelsea QC J9B 1K9",
    "addr:postcode":"qc j9b 1k9",
    "iso:country":"CA",
    "sg:city":"Chelsea",
    "sg:classifiers":[
        {
            "category":"Social Services",
            "subcategory":"Child Care",
            "type":"Services"
        }
    ],
    "sg:phone":"+1 819 827 0787",
    "sg:postcode":"J9B 1K9",
    "sg:province":"QC",
    "wof:name":"Montessori DE Chelsea",
    "wof:placetype":"venue"
},
  "geometry": {"coordinates":[-75.788918,45.504341],"type":"Point"}
}