{
  "type": "Feature",
  "properties": {
    "addr:full":"1381 Rue DE LA Sapiniere Val-David QC J0T 2N0",
    "addr:housenumber":"1381",
    "addr:postcode":"j0t 2n0",
    "addr:street":"Rue De La Sapiniere",
    "iso:country":"CA",
    "sg:address":"1381 Rue DE LA Sapiniere",
    "sg:city":"Val-David",
    "sg:classifiers":[
        {
            "category":"Autos & Motor Vehicles",
            "subcategory":"Boat Sales",
            "type":"Retail Goods"
        }
    ],
    "sg:phone":"+1 819 322 6880",
    "sg:postcode":"J0T 2N0",
    "sg:province":"QC",
    "sg:tags":[
        "dealer",
        "canoe"
    ],
    "wof:name":"Pause Plein Air",
    "wof:placetype":"venue"
},
  "geometry": {"coordinates":[-74.20797,46.031551],"type":"Point"}
}