{
  "type": "Feature",
  "properties": {
    "addr:full":"13221 Loyalist Pky Picton ON K0K 2T0",
    "addr:housenumber":"13221",
    "addr:postcode":"k0k 2t0",
    "addr:street":"Loyalist Pky",
    "iso:country":"CA",
    "sg:address":"13221 Loyalist Pky",
    "sg:city":"Picton",
    "sg:classifiers":[
        {
            "category":"Retail",
            "subcategory":"Auto Repair",
            "type":"Services"
        }
    ],
    "sg:phone":"+1 613 476 2188",
    "sg:postcode":"K0K 2T0",
    "sg:province":"ON",
    "sg:tags":[
        "automobile",
        "testing",
        "emission",
        "dealer"
    ],
    "wof:name":"Stormy's Automotive Ctr",
    "wof:placetype":"venue"
},
  "geometry": {"coordinates":[-77.15790557859999,44.0010910034],"type":"Point"}
}