{
  "type": "Feature",
  "properties": {
    "addr:full":"125 Eddystone Ave North York ON M3N 1H5",
    "addr:housenumber":"125",
    "addr:postcode":"m3n 1h5",
    "addr:street":"Eddystone Ave",
    "iso:country":"CA",
    "sg:address":"125 Eddystone Ave",
    "sg:city":"North York",
    "sg:classifiers":[
        {
            "category":"Wholesale",
            "subcategory":"Non-durable Goods",
            "type":"Manufacturing & Wholesale Goods"
        }
    ],
    "sg:phone":"+1 416 746 3391",
    "sg:postcode":"M3N 1H5",
    "sg:province":"ON",
    "sg:tags":[
        "plaster",
        "product"
    ],
    "wof:name":"Dorik Design Ltd",
    "wof:placetype":"venue"
},
  "geometry": {"coordinates":[-79.5187911987,43.7482719421],"type":"Point"}
}