{
  "type": "Feature",
  "properties": {
    "addr:full":"Highway 10 Flin Flon MB R8A 1N7",
    "addr:postcode":"r8a 1n7",
    "addr:street":"Highway 10 Flin Flon",
    "iso:country":"CA",
    "sg:address":"Highway 10",
    "sg:city":"Flin Flon",
    "sg:classifiers":[
        {
            "category":"Building & Trades",
            "subcategory":"Construction",
            "type":"Services"
        }
    ],
    "sg:phone":"+1 204 687 5503",
    "sg:postcode":"R8A 1N7",
    "sg:province":"MB",
    "sg:tags":[
        "paving",
        "contractor"
    ],
    "wof:name":"Whitford Paving",
    "wof:placetype":"venue"
},
  "geometry": {"coordinates":[-101.876960754,54.7682189941],"type":"Point"}
}