{
  "type": "Feature",
  "properties": {
    "addr:full":"5085 Rue Rideau Quebec QC G2E 5H5",
    "addr:housenumber":"5085",
    "addr:postcode":"g2e 5h5",
    "addr:street":"Rue Rideau",
    "iso:country":"CA",
    "sg:address":"5085 Rue Rideau",
    "sg:city":"Quebec",
    "sg:classifiers":[
        {
            "category":"Manufacturing",
            "subcategory":"Metals",
            "type":"Manufacturing & Wholesale Goods"
        }
    ],
    "sg:phone":"+1 418 872 7224",
    "sg:postcode":"G2E 5H5",
    "sg:province":"QC",
    "sg:tags":[
        "ironwork"
    ],
    "wof:name":"Metal Presto Inc",
    "wof:placetype":"venue"
},
  "geometry": {"coordinates":[-71.32433319090001,46.7976913452],"type":"Point"}
}