{
  "type": "Feature",
  "properties": {
    "addr:full":"1297 Topsail Rd Paradise NL A1L 1N8",
    "addr:housenumber":"1297",
    "addr:postcode":"a1l 1n8",
    "addr:street":"Topsail Rd",
    "iso:country":"CA",
    "sg:address":"1297 Topsail Rd",
    "sg:city":"Paradise",
    "sg:classifiers":[
        {
            "category":"Manufacturing",
            "subcategory":"Building Materials",
            "type":"Manufacturing & Wholesale Goods"
        }
    ],
    "sg:phone":"+1 709 782 3101",
    "sg:postcode":"A1L 1N8",
    "sg:province":"NL",
    "sg:tags":[
        "roofing",
        "truss"
    ],
    "wof:name":"Chester Dawe Ltd",
    "wof:placetype":"venue"
},
  "geometry": {"coordinates":[-52.8455200195,47.5346794128],"type":"Point"}
}