{
  "type": "Feature",
  "properties": {
    "addr:full":"521 Rue Dufferin Stanstead QC J0B 3E0",
    "addr:housenumber":"521",
    "addr:postcode":"j0b 3e0",
    "addr:street":"Rue Dufferin",
    "iso:country":"CA",
    "sg:address":"521 Rue Dufferin",
    "sg:city":"Stanstead",
    "sg:classifiers":[
        {
            "category":"Professional",
            "subcategory":"Accounting & Tax Preparation",
            "type":"Services"
        }
    ],
    "sg:phone":"+1 819 876 2654",
    "sg:postcode":"J0B 3E0",
    "sg:province":"QC",
    "sg:tags":[
        "return",
        "filing"
    ],
    "wof:name":"Desgreniers, Nicole",
    "wof:placetype":"venue"
},
  "geometry": {"coordinates":[-72.093979,45.015652],"type":"Point"}
}