{
  "type": "Feature",
  "properties": {
    "addr:full":"Toronto ON M5B 2H1",
    "addr:postcode":"m5b 2h1",
    "iso:country":"CA",
    "sg:city":"Toronto",
    "sg:classifiers":[
        {
            "category":"Food & Beverages",
            "subcategory":"Bakery",
            "type":"Retail Goods"
        }
    ],
    "sg:phone":"+1 416 977 8927",
    "sg:postcode":"M5B 2H1",
    "sg:province":"ON",
    "wof:name":"Pretzelmaker",
    "wof:placetype":"venue"
},
  "geometry": {"coordinates":[-79.37975299999999,43.653236],"type":"Point"}
}