{
  "type": "Feature",
  "properties": {
    "iso:country":"CA",
    "sg:city":"St-Sauveur-Des-Monts",
    "sg:classifiers":[
        {
            "category":"Food & Beverages",
            "subcategory":"Bakery",
            "type":"Retail Goods"
        }
    ],
    "sg:phone":"+1 450 227 2632",
    "sg:postcode":"J0R 1R0",
    "sg:province":"QC",
    "sg:tags":[
        "baker"
    ],
    "wof:name":"Boulangerie Page",
    "wof:placetype":"venue"
},
  "geometry": {"coordinates":[-74.15702056879999,45.8953323364],"type":"Point"}
}