{
  "type": "Feature",
  "properties": {
    "addr:full":"121 Hayes Rd Thompson MB R8N 1M3",
    "addr:housenumber":"121",
    "addr:postcode":"r8n 1m3",
    "addr:street":"Hayes Rd",
    "iso:country":"CA",
    "sg:address":"121 Hayes Rd",
    "sg:city":"Thompson",
    "sg:classifiers":[
        {
            "category":"Autos & Motor Vehicles",
            "subcategory":"Auto Supplies",
            "type":"Retail Goods"
        }
    ],
    "sg:phone":"+1 204 677 3925",
    "sg:postcode":"R8N 1M3",
    "sg:province":"MB",
    "sg:tags":[
        "tire"
    ],
    "wof:name":"Northland Tire",
    "wof:placetype":"venue"
},
  "geometry": {"coordinates":[-97.866112,55.730663],"type":"Point"}
}