{
  "type": "Feature",
  "properties": {
    "addr:full":"Mississauga ON L4Z 3C9",
    "addr:postcode":"l4z 3c9",
    "iso:country":"CA",
    "sg:city":"Mississauga",
    "sg:classifiers":[
        {
            "category":"Professional",
            "subcategory":"Business Services",
            "type":"Services"
        }
    ],
    "sg:phone":"+1 905 568 9540",
    "sg:postcode":"L4Z 3C9",
    "sg:province":"ON",
    "sg:tags":[
        "fund",
        "promotion",
        "raising"
    ],
    "wof:name":"Mark IV Promotions Inc",
    "wof:placetype":"venue"
},
  "geometry": {"coordinates":[-79.66493199999999,43.62215],"type":"Point"}
}