{
  "type": "Feature",
  "properties": {
    "addr:full":"20 Bram Crt Brampton ON L6W 3R6",
    "addr:housenumber":"20",
    "addr:postcode":"l6w 3r6",
    "addr:street":"Bram Crt",
    "iso:country":"CA",
    "sg:address":"20 Bram Crt",
    "sg:city":"Brampton",
    "sg:classifiers":[
        {
            "category":"Wholesale",
            "subcategory":"Auto Parts",
            "type":"Manufacturing & Wholesale Goods"
        }
    ],
    "sg:phone":"+1 905 459 9332",
    "sg:postcode":"L6W 3R6",
    "sg:province":"ON",
    "sg:tags":[
        "body",
        "automobile",
        "shop"
    ],
    "wof:name":"Ontario Spray Booth Ltd",
    "wof:placetype":"venue"
},
  "geometry": {"coordinates":[-79.71595000000001,43.684181],"type":"Point"}
}