{
  "type": "Feature",
  "properties": {
    "addr:full":"500 Hensall Cir Mississauga ON L5A 1Y1",
    "addr:housenumber":"500",
    "addr:postcode":"l5a 1y1",
    "addr:street":"Hensall Cir",
    "iso:country":"CA",
    "sg:address":"500 Hensall Cir",
    "sg:city":"Mississauga",
    "sg:classifiers":[
        {
            "category":"Health Services",
            "subcategory":"Medical Lab",
            "type":"Services"
        }
    ],
    "sg:phone":"+1 905 273 5933",
    "sg:postcode":"L5A 1Y1",
    "sg:province":"ON",
    "sg:tags":[
        "laboratory"
    ],
    "wof:name":"Exceltec Dental Laboratory",
    "wof:placetype":"venue"
},
  "geometry": {"coordinates":[-79.60427900000001,43.590115],"type":"Point"}
}