{
  "type": "Feature",
  "properties": {
    "addr:full":"Brockville ON K6V 5T3",
    "addr:postcode":"k6v 5t3",
    "iso:country":"CA",
    "sg:city":"Brockville",
    "sg:classifiers":[
        {
            "category":"Home & Garden",
            "subcategory":"Building Materials",
            "type":"Retail Goods"
        }
    ],
    "sg:phone":"+1 613 342 7148",
    "sg:postcode":"K6V 5T3",
    "sg:province":"ON",
    "sg:tags":[
        "glass",
        "window",
        "plate"
    ],
    "wof:name":"Deluxe Auto Glass & Trim",
    "wof:placetype":"venue"
},
  "geometry": {"coordinates":[-75.683014,44.590389],"type":"Point"}
}