{
  "type": "Feature",
  "properties": {
    "iso:country":"CA",
    "sg:address":"624 Rue Notre-Dame",
    "sg:city":"Repentigny",
    "sg:classifiers":[
        {
            "category":"Autos & Motor Vehicles",
            "subcategory":"Automobile Sales",
            "type":"Retail Goods"
        }
    ],
    "sg:phone":"+1 450 585 8303",
    "sg:postcode":"J6A 2T9",
    "sg:province":"QC",
    "sg:tags":[
        "car",
        "dealer"
    ],
    "wof:name":"Mag Auto",
    "wof:placetype":"venue"
},
  "geometry": {"coordinates":[-73.4339675903,45.7496032715],"type":"Point"}
}