{
  "type": "Feature",
  "properties": {
    "iso:country":"CA",
    "sg:address":"55 Myrtle St",
    "sg:city":"Winnipeg",
    "sg:classifiers":[
        {
            "category":"Building & Trades",
            "subcategory":"Plumbing",
            "type":"Services"
        }
    ],
    "sg:phone":"+1 204 774 0285",
    "sg:postcode":"R3E 2R3",
    "sg:province":"MB",
    "sg:tags":[
        "cleaning",
        "contractor"
    ],
    "wof:name":"Canadian Mechanical Specialty",
    "wof:placetype":"venue"
},
  "geometry": {"coordinates":[-97.1764831543,49.9079437256],"type":"Point"}
}