{
  "type": "Feature",
  "properties": {
    "addr:full":"PO Box 72 Big Trout Lake ON P0V 1G0",
    "addr:housenumber":"po box 72",
    "addr:postcode":"p0v 1g0",
    "addr:street":"Trout",
    "iso:country":"CA",
    "sg:address":"PO Box 72",
    "sg:city":"Big Trout Lake",
    "sg:classifiers":[
        {
            "category":"Organizations",
            "subcategory":"Religious Organization",
            "type":"Services"
        }
    ],
    "sg:phone":"+1 807 537 1169",
    "sg:postcode":"P0V 1G0",
    "sg:province":"ON",
    "sg:tags":[
        "church"
    ],
    "wof:name":"Pentecostal Church",
    "wof:placetype":"venue"
},
  "geometry": {"coordinates":[-89.8350906372,53.8187599182],"type":"Point"}
}