{
  "type": "Feature",
  "properties": {
    "addr:full":"1250 108E Av Saint-Georges-DE-Champlain QC G9T 5K4",
    "addr:housenumber":"1250",
    "addr:postcode":"g9t 5k4",
    "addr:street":"108E Av Saint-Georges-De-Champlain",
    "iso:country":"CA",
    "sg:address":"1250 108E Av",
    "sg:city":"Saint-Georges-DE-Champlain",
    "sg:classifiers":[
        {
            "category":"Real Estate",
            "subcategory":"Real Estate Agent",
            "type":"Services"
        }
    ],
    "sg:phone":"+1 819 533 3000",
    "sg:postcode":"G9T 5K4",
    "sg:province":"QC",
    "sg:tags":[
        "agency",
        "rental"
    ],
    "wof:name":"Buromobil St Maurice",
    "wof:placetype":"venue"
},
  "geometry": {"coordinates":[-72.34311700000001,46.44104],"type":"Point"}
}