{
  "type": "Feature",
  "properties": {
    "addr:full":"2710 Lillian Ave Windsor ON N8X 4W9",
    "addr:housenumber":"2710",
    "addr:postcode":"n8x 4w9",
    "addr:street":"Lillian Ave",
    "iso:country":"CA",
    "sg:address":"2710 Lillian Ave",
    "sg:city":"Windsor",
    "sg:classifiers":[
        {
            "category":"Education",
            "subcategory":"Library",
            "type":"Public Place"
        }
    ],
    "sg:phone":"+1 519 966 3441",
    "sg:postcode":"N8X 4W9",
    "sg:province":"ON",
    "wof:name":"Remington Park Library",
    "wof:placetype":"venue"
},
  "geometry": {"coordinates":[-83.006615,42.285351],"type":"Point"}
}