{
  "type": "Feature",
  "properties": {
    "addr:full":"705 Central Ave N Ste Rose Du Lac MB R0L 1S0",
    "addr:housenumber":"705",
    "addr:postcode":"r0l 1s0",
    "addr:street":"Central Ave N Ste Rose Du Lac",
    "iso:country":"CA",
    "sg:address":"705 Central Ave N",
    "sg:city":"Ste Rose Du Lac",
    "sg:classifiers":[
        {
            "category":"Home & Garden",
            "subcategory":"Building Materials",
            "type":"Retail Goods"
        }
    ],
    "sg:phone":"+1 204 447 2545",
    "sg:postcode":"R0L 1S0",
    "sg:province":"MB",
    "sg:tags":[
        "lumber"
    ],
    "wof:name":"Ste Rose Consumers CO-OP Ltd",
    "wof:placetype":"venue"
},
  "geometry": {"coordinates":[-99.52394099999999,51.064289],"type":"Point"}
}