{
  "type": "Feature",
  "properties": {
    "addr:full":"4431 Dorchester Rd Niagara Falls ON L2E 6N5",
    "addr:housenumber":"4431",
    "addr:postcode":"l2e 6n5",
    "addr:street":"Dorchester Rd",
    "iso:country":"CA",
    "sg:address":"4431 Dorchester Rd",
    "sg:city":"Niagara Falls",
    "sg:classifiers":[
        {
            "category":"Education",
            "subcategory":"Special Training",
            "type":"Public Place"
        }
    ],
    "sg:phone":"+1 905 374 7999",
    "sg:postcode":"L2E 6N5",
    "sg:province":"ON",
    "sg:tags":[
        "instruction",
        "music"
    ],
    "wof:name":"Musically Inclined",
    "wof:placetype":"venue"
},
  "geometry": {"coordinates":[-79.11162567140001,43.1090393066],"type":"Point"}
}