{
  "type": "Feature",
  "properties": {
    "addr:full":"Red Deer AB T4R 1N9",
    "addr:postcode":"t4r 1n9",
    "iso:country":"CA",
    "sg:city":"Red Deer",
    "sg:classifiers":[
        {
            "category":"Restaurant",
            "type":"Food & Drink"
        }
    ],
    "sg:phone":"+1 403 347 8118",
    "sg:postcode":"T4R 1N9",
    "sg:province":"AB",
    "wof:name":"New York Fries",
    "wof:placetype":"venue"
},
  "geometry": {"coordinates":[-113.807006836,52.2450561523],"type":"Point"}
}