{
  "type": "Feature",
  "properties": {
    "addr:full":"331 Glendower Circt Scarborough ON M1T 2Z7",
    "addr:housenumber":"331",
    "addr:postcode":"m1t 2z7",
    "addr:street":"Glendower Circt",
    "iso:country":"CA",
    "sg:address":"331 Glendower Circt",
    "sg:city":"Scarborough",
    "sg:classifiers":[
        {
            "category":"Restaurant",
            "type":"Food & Drink"
        }
    ],
    "sg:phone":"+1 416 299 6393",
    "sg:postcode":"M1T 2Z7",
    "sg:province":"ON",
    "wof:name":"Caribbean Hut",
    "wof:placetype":"venue"
},
  "geometry": {"coordinates":[-79.3041687012,43.7974624634],"type":"Point"}
}