{
  "type": "Feature",
  "properties": {
    "addr:full":"1910 Av Clinton Montreal QC H3S 1L1",
    "addr:housenumber":"1910",
    "addr:postcode":"h3s 1l1",
    "addr:street":"Av Clinton",
    "iso:country":"CA",
    "sg:address":"1910 Av Clinton",
    "sg:city":"Montreal",
    "sg:classifiers":[
        {
            "category":"Professional",
            "subcategory":"Business Services",
            "type":"Services"
        }
    ],
    "sg:phone":"+1 514 342 2210",
    "sg:postcode":"H3S 1L1",
    "sg:province":"QC",
    "sg:tags":[
        "translator",
        "interpreter"
    ],
    "wof:name":"Traduction Betty Howell Inc",
    "wof:placetype":"venue"
},
  "geometry": {"coordinates":[-73.62325286870001,45.5143814087],"type":"Point"}
}