{
  "type": "Feature",
  "properties": {
    "addr:full":"Concord ON L4K 2H6",
    "addr:postcode":"l4k 2h6",
    "iso:country":"CA",
    "sg:city":"Concord",
    "sg:classifiers":[
        {
            "category":"Retail",
            "subcategory":"Auto Repair",
            "type":"Services"
        }
    ],
    "sg:phone":"+1 905 669 1301",
    "sg:postcode":"L4K 2H6",
    "sg:province":"ON",
    "sg:tags":[
        "clutches"
    ],
    "wof:name":"S K Wellman CO of Canada Ltd",
    "wof:placetype":"venue"
},
  "geometry": {"coordinates":[-79.4962692261,43.8099212646],"type":"Point"}
}