{
  "type": "Feature",
  "properties": {
    "addr:full":"219 Roncesvalles Ave Toronto ON M6R 2L6",
    "addr:housenumber":"219",
    "addr:postcode":"m6r 2l6",
    "addr:street":"Roncesvalles Ave",
    "iso:country":"CA",
    "sg:address":"219 Roncesvalles Ave",
    "sg:city":"Toronto",
    "sg:classifiers":[
        {
            "category":"Food & Beverages",
            "subcategory":"Specialty",
            "type":"Retail Goods"
        }
    ],
    "sg:phone":"+1 416 537 1428",
    "sg:postcode":"M6R 2L6",
    "sg:province":"ON",
    "sg:tags":[
        "health",
        "diet"
    ],
    "wof:name":"Q I Natural Foods",
    "wof:placetype":"venue"
},
  "geometry": {"coordinates":[-79.4486160278,43.6457176208],"type":"Point"}
}