{
  "type": "Feature",
  "properties": {
    "addr:full":"789 Portage Ave Winnipeg MB R3G 0N3",
    "addr:housenumber":"789",
    "addr:postcode":"r3g 0n3",
    "addr:street":"Portage Ave",
    "iso:country":"CA",
    "sg:address":"789 Portage Ave",
    "sg:city":"Winnipeg",
    "sg:classifiers":[
        {
            "category":"Restaurant",
            "type":"Food & Drink"
        }
    ],
    "sg:phone":"+1 204 772 2539",
    "sg:postcode":"R3G 0N3",
    "sg:province":"MB",
    "wof:name":"Paradise Restaurant",
    "wof:placetype":"venue"
},
  "geometry": {"coordinates":[-97.16543579099999,49.8868675232],"type":"Point"}
}