{
  "type": "Feature",
  "properties": {
    "addr:full":"3181 Rue Saint-Jacques Montreal QC H4C 1G7",
    "addr:housenumber":"3181",
    "addr:postcode":"h4c 1g7",
    "addr:street":"Rue Saint-Jacques",
    "iso:country":"CA",
    "sg:address":"3181 Rue Saint-Jacques",
    "sg:city":"Montreal",
    "sg:classifiers":[
        {
            "category":"Manufacturing",
            "subcategory":"Printing",
            "type":"Manufacturing & Wholesale Goods"
        }
    ],
    "sg:phone":"+1 514 932 5210",
    "sg:postcode":"H4C 1G7",
    "sg:province":"QC",
    "sg:tags":[
        "screen"
    ],
    "wof:name":"J B Gillies Reg'd",
    "wof:placetype":"venue"
},
  "geometry": {"coordinates":[-73.58034499999999,45.483509],"type":"Point"}
}