{
  "type": "Feature",
  "properties": {
    "addr:full":"5109 44th St Valleyview AB T0H 3N0",
    "addr:housenumber":"5109",
    "addr:postcode":"ab t0h 3n0",
    "addr:street":"44Th St",
    "iso:country":"CA",
    "sg:address":"5109 44th St",
    "sg:city":"Valleyview",
    "sg:classifiers":[
        {
            "category":"Education",
            "subcategory":"School",
            "type":"Public Place"
        }
    ],
    "sg:phone":"+1 780 524 3562",
    "sg:postcode":"T0H 3N0",
    "sg:province":"AB",
    "wof:name":"St Stephen's School",
    "wof:placetype":"venue"
},
  "geometry": {"coordinates":[-117.26824999999999,55.071388],"type":"Point"}
}