{
  "type": "Feature",
  "properties": {
    "addr:full":"128 Tenth Ave E New Westminster BC V3L 4R6",
    "addr:housenumber":"128",
    "addr:postcode":"v3l 4r6",
    "addr:street":"Tenth Ave E",
    "iso:country":"CA",
    "sg:address":"128 Tenth Ave E",
    "sg:city":"New Westminster",
    "sg:classifiers":[
        {
            "category":"Wholesale",
            "subcategory":"Electrical",
            "type":"Manufacturing & Wholesale Goods"
        }
    ],
    "sg:phone":"+1 604 520 7759",
    "sg:postcode":"V3L 4R6",
    "sg:province":"BC",
    "sg:tags":[
        "fire",
        "equipment",
        "alarm",
        "protection",
        "system"
    ],
    "wof:name":"Great West Fire & Safety",
    "wof:placetype":"venue"
},
  "geometry": {"coordinates":[-122.910995,49.227722],"type":"Point"}
}