{
  "type": "Feature",
  "properties": {
    "addr:full":"5452 53 Ave SE Calgary AB T2C 4R3",
    "addr:housenumber":"5452",
    "addr:postcode":"t2c 4r3",
    "addr:street":"53 Ave Se",
    "iso:country":"CA",
    "sg:address":"5452 53 Ave SE",
    "sg:city":"Calgary",
    "sg:classifiers":[
        {
            "category":"Wholesale",
            "subcategory":"Machinery & Supplies",
            "type":"Manufacturing & Wholesale Goods"
        }
    ],
    "sg:phone":"+1 403 279 7488",
    "sg:postcode":"T2C 4R3",
    "sg:province":"AB",
    "sg:tags":[
        "packaging"
    ],
    "wof:name":"Trimeg Holdings Ltd",
    "wof:placetype":"venue"
},
  "geometry": {"coordinates":[-113.954903,51.005219],"type":"Point"}
}