{
  "type": "Feature",
  "properties": {
    "addr:full":"180 Rue DE Monseigneur-Panet Nicolet QC J3T 1S6",
    "addr:housenumber":"180",
    "addr:postcode":"j3t 1s6",
    "addr:street":"Rue De Monseigneur-Panet",
    "iso:country":"CA",
    "sg:address":"180 Rue DE Monseigneur-Panet",
    "sg:city":"Nicolet",
    "sg:classifiers":[
        {
            "category":"Government",
            "subcategory":"Office",
            "type":"Public Place"
        }
    ],
    "sg:phone":"+1 819 293 6901",
    "sg:postcode":"J3T 1S6",
    "sg:province":"QC",
    "sg:tags":[
        "village"
    ],
    "wof:name":"Nicolet Administration Gen",
    "wof:placetype":"venue"
},
  "geometry": {"coordinates":[-72.616028,46.22855],"type":"Point"}
}