{
  "type": "Feature",
  "properties": {
    "addr:full":"191 Centennial Pky N Hamilton ON L8E 1H8",
    "addr:housenumber":"191",
    "addr:postcode":"l8e 1h8",
    "addr:street":"Centennial Pky N",
    "iso:country":"CA",
    "sg:address":"191 Centennial Pky N",
    "sg:city":"Hamilton",
    "sg:classifiers":[
        {
            "category":"Autos & Motor Vehicles",
            "subcategory":"Automobile Sales",
            "type":"Retail Goods"
        }
    ],
    "sg:phone":"+1 905 561 1202",
    "sg:postcode":"L8E 1H8",
    "sg:province":"ON",
    "sg:tags":[
        "car",
        "dealer"
    ],
    "wof:name":"Parkway Toyota Ltd",
    "wof:placetype":"venue"
},
  "geometry": {"coordinates":[-79.76127624510001,43.2354698181],"type":"Point"}
}