{
  "type": "Feature",
  "properties": {
    "addr:full":"39 Voyager Crt N Etobicoke ON M9W 4Y2",
    "addr:housenumber":"39",
    "addr:postcode":"m9w 4y2",
    "addr:street":"Voyager Crt N",
    "iso:country":"CA",
    "sg:address":"39 Voyager Crt N",
    "sg:city":"Etobicoke",
    "sg:classifiers":[
        {
            "category":"Freight",
            "type":"Transportation"
        }
    ],
    "sg:phone":"+1 416 674 5330",
    "sg:postcode":"M9W 4Y2",
    "sg:province":"ON",
    "sg:tags":[
        "mover"
    ],
    "wof:name":"Sea Jamaica Shipping Ltd",
    "wof:placetype":"venue"
},
  "geometry": {"coordinates":[-79.588295,43.678406],"type":"Point"}
}