{
  "type": "Feature",
  "properties": {
    "addr:full":"Owen Sound ON N4K 5N3",
    "addr:postcode":"n4k 5n3",
    "iso:country":"CA",
    "sg:city":"Owen Sound",
    "sg:classifiers":[
        {
            "category":"Building & Trades",
            "subcategory":"Construction",
            "type":"Services"
        }
    ],
    "sg:phone":"+1 519 371 3464",
    "sg:postcode":"N4K 5N3",
    "sg:province":"ON",
    "sg:tags":[
        "marking",
        "maintenance",
        "parking"
    ],
    "wof:name":"Enviropro Solutions",
    "wof:placetype":"venue"
},
  "geometry": {"coordinates":[-80.942604,44.564877],"type":"Point"}
}