{
  "type": "Feature",
  "properties": {
    "iso:country":"CA",
    "sg:address":"895 Empire Rd",
    "sg:city":"Sherkston",
    "sg:classifiers":[
        {
            "category":"Organizations",
            "subcategory":"Religious Organization",
            "type":"Services"
        }
    ],
    "sg:phone":"+1 905 894 3462",
    "sg:postcode":"L0S 1R0",
    "sg:province":"ON",
    "sg:tags":[
        "church"
    ],
    "wof:name":"Grace United Brethren Church",
    "wof:placetype":"venue"
},
  "geometry": {"coordinates":[-79.1343383789,42.8866004944],"type":"Point"}
}