{
  "type": "Feature",
  "properties": {
    "iso:country":"CA",
    "sg:address":"470 Appleby Line",
    "sg:city":"Burlington",
    "sg:classifiers":[
        {
            "category":"Restaurant",
            "type":"Food & Drink"
        }
    ],
    "sg:phone":"+1 905 632 7827",
    "sg:postcode":"L7L 2Y2",
    "sg:province":"ON",
    "sg:tags":[
        "sandwich"
    ],
    "wof:name":"Club Sub",
    "wof:placetype":"venue"
},
  "geometry": {"coordinates":[-79.75318145750001,43.3666687012],"type":"Point"}
}