{
  "type": "Feature",
  "properties": {
    "addr:full":"175 1st Ave E Englefeld SK S0K 1N0",
    "addr:housenumber":"175",
    "addr:postcode":"s0k 1n0",
    "addr:street":"1St Ave E Englefeld",
    "iso:country":"CA",
    "sg:address":"175 1st Ave E",
    "sg:city":"Englefeld",
    "sg:classifiers":[
        {
            "category":"Manufacturing",
            "subcategory":"Tools & Machinery",
            "type":"Manufacturing & Wholesale Goods"
        }
    ],
    "sg:phone":"+1 306 287 3702",
    "sg:postcode":"S0K 1N0",
    "sg:province":"SK",
    "sg:tags":[
        "windmill"
    ],
    "wof:name":"Koenders Windmills Inc",
    "wof:placetype":"venue"
},
  "geometry": {"coordinates":[-104.65439600000001,52.158932],"type":"Point"}
}