{
  "type": "Feature",
  "properties": {
    "addr:full":"12 Auto Plaza Ave Pointe-Claire QC H9R 4W6",
    "addr:housenumber":"12",
    "addr:postcode":"h9r 4w6",
    "addr:street":"Auto Plaza Ave",
    "iso:country":"CA",
    "sg:address":"12 Auto Plaza Ave",
    "sg:city":"Pointe-Claire",
    "sg:classifiers":[
        {
            "category":"Autos & Motor Vehicles",
            "subcategory":"Automobile Sales",
            "type":"Retail Goods"
        }
    ],
    "sg:phone":"+1 514 694 1510",
    "sg:postcode":"H9R 4W6",
    "sg:province":"QC",
    "sg:tags":[
        "car",
        "dealer"
    ],
    "wof:name":"Fairview Toyota Inc",
    "wof:placetype":"venue"
},
  "geometry": {"coordinates":[-73.833832,45.467373],"type":"Point"}
}