{
  "type": "Feature",
  "properties": {
    "iso:country":"CA",
    "sg:city":"Burnaby",
    "sg:classifiers":[
        {
            "category":"Health Services",
            "subcategory":"Medical Lab",
            "type":"Services"
        }
    ],
    "sg:phone":"+1 604 437 5333",
    "sg:postcode":"V5E 2P7",
    "sg:province":"BC",
    "sg:tags":[
        "laboratory",
        "optical"
    ],
    "wof:name":"K W Optical Ltd",
    "wof:placetype":"venue"
},
  "geometry": {"coordinates":[-122.96862793,49.2149810791],"type":"Point"}
}