{
  "type": "Feature",
  "properties": {
    "addr:full":"Toronto ON M4W 3C7",
    "addr:postcode":"m4w 3c7",
    "iso:country":"CA",
    "sg:city":"Toronto",
    "sg:classifiers":[
        {
            "category":"Professional",
            "subcategory":"Advertising",
            "type":"Services"
        }
    ],
    "sg:phone":"+1 416 961 4060",
    "sg:postcode":"M4W 3C7",
    "sg:province":"ON",
    "sg:tags":[
        "counselor"
    ],
    "wof:name":"Bowen & Binstock Advertising",
    "wof:placetype":"venue"
},
  "geometry": {"coordinates":[-79.3884963989,43.6739463806],"type":"Point"}
}