{
  "type": "Feature",
  "properties": {
    "addr:full":"Mississauga ON L5K 1P9",
    "addr:postcode":"l5k 1p9",
    "iso:country":"CA",
    "sg:city":"Mississauga",
    "sg:classifiers":[
        {
            "category":"Personal",
            "subcategory":"Beauty Salon",
            "type":"Services"
        }
    ],
    "sg:phone":"+1 905 855 2344",
    "sg:postcode":"L5K 1P9",
    "sg:province":"ON",
    "sg:tags":[
        "day"
    ],
    "wof:name":"Sherwood Village Spa",
    "wof:placetype":"venue"
},
  "geometry": {"coordinates":[-79.662575,43.539948],"type":"Point"}
}