{
  "type": "Feature",
  "properties": {
    "addr:full":"6289 148 St Surrey BC V3S 3C3",
    "addr:housenumber":"6289",
    "addr:postcode":"v3s 3c3",
    "addr:street":"148 St",
    "iso:country":"CA",
    "sg:address":"6289 148 St",
    "sg:city":"Surrey",
    "sg:classifiers":[
        {
            "category":"Building & Trades",
            "subcategory":"Landscaping Services",
            "type":"Services"
        }
    ],
    "sg:phone":"+1 604 599 0638",
    "sg:postcode":"V3S 3C3",
    "sg:province":"BC",
    "sg:tags":[
        "paving",
        "landscape",
        "contractor"
    ],
    "wof:name":"Pay Less Paving Ltd",
    "wof:placetype":"venue"
},
  "geometry": {"coordinates":[-122.81241607699999,49.1167602539],"type":"Point"}
}