{
  "type": "Feature",
  "properties": {
    "addr:full":"85 Bedford St Westport ON K0G 1X0",
    "addr:housenumber":"85",
    "addr:postcode":"k0g 1x0",
    "addr:street":"Bedford St",
    "iso:country":"CA",
    "sg:address":"85 Bedford St",
    "sg:city":"Westport",
    "sg:classifiers":[
        {
            "category":"Organizations",
            "subcategory":"Religious Organization",
            "type":"Services"
        }
    ],
    "sg:phone":"+1 613 273 2141",
    "sg:postcode":"K0G 1X0",
    "sg:province":"ON",
    "sg:tags":[
        "church"
    ],
    "wof:name":"Free Methodist Church",
    "wof:placetype":"venue"
},
  "geometry": {"coordinates":[-76.40821800000001,44.680054],"type":"Point"}
}