{
  "type": "Feature",
  "properties": {
    "addr:full":"Simcoe ON N3Y 4J9",
    "addr:postcode":"n3y 4j9",
    "iso:country":"CA",
    "sg:city":"Simcoe",
    "sg:classifiers":[
        {
            "category":"Wholesale",
            "subcategory":"Machinery & Supplies",
            "type":"Manufacturing & Wholesale Goods"
        }
    ],
    "sg:phone":"+1 519 426 1090",
    "sg:postcode":"N3Y 4J9",
    "sg:province":"ON",
    "sg:tags":[
        "farm",
        "equipment"
    ],
    "wof:name":"Norfolk Tractor CO",
    "wof:placetype":"venue"
},
  "geometry": {"coordinates":[-80.3052902222,42.8359031677],"type":"Point"}
}