{
  "type": "Feature",
  "properties": {
    "addr:full":"2810 Matheson Blvd E # 200 Mississauga ON L4W 4X7",
    "addr:housenumber":"2810",
    "addr:postcode":"l4w 4x7",
    "addr:street":"Matheson Blvd E # 200",
    "iso:country":"CA",
    "sg:address":"2810 Matheson Blvd E # 200",
    "sg:city":"Mississauga",
    "sg:classifiers":[
        {
            "category":"Real Estate",
            "subcategory":"Real Estate Operator",
            "type":"Services"
        }
    ],
    "sg:phone":"+1 905 625 5025",
    "sg:postcode":"L4W 4X7",
    "sg:province":"ON",
    "sg:tags":[
        "building",
        "mail",
        "box",
        "parks"
    ],
    "wof:name":"Rostie Group",
    "wof:placetype":"venue"
},
  "geometry": {"coordinates":[-79.594849,43.665146],"type":"Point"}
}