{
  "type": "Feature",
  "properties": {
    "addr:full":"1316 Martindale Rd Sudbury ON P3E 4J5",
    "addr:housenumber":"1316",
    "addr:postcode":"p3e 4j5",
    "addr:street":"Martindale Rd",
    "iso:country":"CA",
    "sg:address":"1316 Martindale Rd",
    "sg:city":"Sudbury",
    "sg:classifiers":[
        {
            "category":"Retail",
            "subcategory":"Veterinary Services",
            "type":"Services"
        }
    ],
    "sg:phone":"+1 705 522 9399",
    "sg:postcode":"P3E 4J5",
    "sg:province":"ON",
    "sg:tags":[
        "veterinarian"
    ],
    "wof:name":"Suitor, James DVM",
    "wof:placetype":"venue"
},
  "geometry": {"coordinates":[-81.00885772709999,46.4653129578],"type":"Point"}
}