{
  "type": "Feature",
  "properties": {
    "addr:full":"547 32E Av Pointe-Aux-Trembles QC H1A 3L3",
    "addr:housenumber":"547",
    "addr:postcode":"h1a 3l3",
    "addr:street":"32E Av Pointe-Aux-Trembles",
    "iso:country":"CA",
    "sg:address":"547 32E Av",
    "sg:city":"Pointe-Aux-Trembles",
    "sg:classifiers":[
        {
            "category":"Organizations",
            "subcategory":"Religious Organization",
            "type":"Services"
        }
    ],
    "sg:phone":"+1 514 498 2668",
    "sg:postcode":"H1A 3L3",
    "sg:province":"QC",
    "sg:tags":[
        "church"
    ],
    "wof:name":"LA Luz Del Mundo",
    "wof:placetype":"venue"
},
  "geometry": {"coordinates":[-73.4928741455,45.6561355591],"type":"Point"}
}