{
  "type": "Feature",
  "properties": {
    "addr:full":"Forteau NL A0K 2P0",
    "addr:postcode":"a0k 2p0",
    "iso:country":"CA",
    "sg:city":"Forteau",
    "sg:classifiers":[
        {
            "category":"Government",
            "subcategory":"Office",
            "type":"Public Place"
        }
    ],
    "sg:phone":"+1 709 931 2908",
    "sg:postcode":"A0K 2P0",
    "sg:province":"NL",
    "wof:name":"Newfoundland Dev & Rural Rnwl",
    "wof:placetype":"venue"
},
  "geometry": {"coordinates":[-56.9576225281,51.4730949402],"type":"Point"}
}