{
  "type": "Feature",
  "properties": {
    "iso:country":"CA",
    "sg:address":"11723 Woodbine Ave",
    "sg:city":"Gormley",
    "sg:classifiers":[
        {
            "category":"Retail",
            "subcategory":"Animal Services",
            "type":"Services"
        }
    ],
    "sg:phone":"+1 905 887 2614",
    "sg:postcode":"L0H 1G0",
    "sg:province":"ON",
    "sg:tags":[
        "pet",
        "boarding",
        "sitting"
    ],
    "wof:name":"L J Kennels Reg",
    "wof:placetype":"venue"
},
  "geometry": {"coordinates":[-79.377945,43.929764],"type":"Point"}
}