{
  "type": "Feature",
  "properties": {
    "iso:country":"CA",
    "sg:address":"468 Mcnicoll Ave",
    "sg:city":"North York",
    "sg:classifiers":[
        {
            "category":"Building & Trades",
            "subcategory":"Construction",
            "type":"Services"
        }
    ],
    "sg:phone":"+1 416 499 5915",
    "sg:postcode":"M2H 2E1",
    "sg:province":"ON",
    "sg:tags":[
        "painter"
    ],
    "wof:name":"Educated Painters & Decorators",
    "wof:placetype":"venue"
},
  "geometry": {"coordinates":[-79.3408660889,43.8037452698],"type":"Point"}
}