{
  "type": "Feature",
  "properties": {
    "addr:full":"121 Prince St Sydney NS B1P 5K2",
    "addr:housenumber":"121",
    "addr:postcode":"b1p 5k2",
    "addr:street":"Prince St",
    "iso:country":"CA",
    "sg:address":"121 Prince St",
    "sg:city":"Sydney",
    "sg:classifiers":[
        {
            "category":"Retail",
            "subcategory":"Auto Repair",
            "type":"Services"
        }
    ],
    "sg:phone":"+1 902 539 2122",
    "sg:postcode":"B1P 5K2",
    "sg:province":"NS",
    "sg:tags":[
        "repairing",
        "automobile"
    ],
    "wof:name":"Sydney Radiator",
    "wof:placetype":"venue"
},
  "geometry": {"coordinates":[-60.1919708252,46.1386680603],"type":"Point"}
}