{
  "type": "Feature",
  "properties": {
    "iso:country":"CA",
    "sg:address":"2700 Boul Laurier",
    "sg:city":"Sainte-Foy",
    "sg:classifiers":[
        {
            "category":"Restaurant",
            "type":"Food & Drink"
        }
    ],
    "sg:phone":"+1 418 657 7994",
    "sg:postcode":"G1V 2L8",
    "sg:province":"QC",
    "sg:tags":[
        "caterer"
    ],
    "wof:name":"Viennoiserie Quebec Enr",
    "wof:placetype":"venue"
},
  "geometry": {"coordinates":[-71.284073,46.769676],"type":"Point"}
}