{
  "type": "Feature",
  "properties": {
    "addr:full":"2952 41st Ave E Vancouver BC V5R 2X5",
    "addr:housenumber":"2952",
    "addr:postcode":"v5r 2x5",
    "addr:street":"41St Ave E",
    "iso:country":"CA",
    "sg:address":"2952 41st Ave E",
    "sg:city":"Vancouver",
    "sg:classifiers":[
        {
            "category":"Education",
            "subcategory":"Special Training",
            "type":"Public Place"
        }
    ],
    "sg:phone":"+1 604 439 1776",
    "sg:postcode":"V5R 2X5",
    "sg:province":"BC",
    "sg:tags":[
        "instruction",
        "music"
    ],
    "wof:name":"Gail L Craig Music Studio",
    "wof:placetype":"venue"
},
  "geometry": {"coordinates":[-123.04428900000001,49.23288],"type":"Point"}
}