{
  "type": "Feature",
  "properties": {
    "addr:full":"2020 Appleby Line Burlington ON L7L 6M6",
    "addr:housenumber":"2020",
    "addr:postcode":"l7l 6m6",
    "addr:street":"Appleby Line",
    "iso:country":"CA",
    "sg:address":"2020 Appleby Line",
    "sg:city":"Burlington",
    "sg:classifiers":[
        {
            "category":"Shopping",
            "type":"Retail Goods"
        }
    ],
    "sg:phone":"+1 905 331 7381",
    "sg:postcode":"L7L 6M6",
    "sg:province":"ON",
    "sg:tags":[
        "pet",
        "shop"
    ],
    "wof:name":"Pet Paradise Ltd",
    "wof:placetype":"venue"
},
  "geometry": {"coordinates":[-79.791382,43.394371],"type":"Point"}
}