{
  "type": "Feature",
  "properties": {
    "iso:country":"CA",
    "sg:address":"59 Industrial Rd",
    "sg:city":"Richmond Hill",
    "sg:classifiers":[
        {
            "category":"Retail",
            "subcategory":"Auto Repair",
            "type":"Services"
        }
    ],
    "sg:phone":"+1 905 886 2442",
    "sg:postcode":"L4C 2Y2",
    "sg:province":"ON",
    "sg:tags":[
        "repairing",
        "automobile"
    ],
    "wof:name":"Magicare",
    "wof:placetype":"venue"
},
  "geometry": {"coordinates":[-79.4388427734,43.88722229],"type":"Point"}
}