{
  "type": "Feature",
  "properties": {
    "iso:country":"CA",
    "sg:address":"300 Rue Beaubien E",
    "sg:city":"Montreal",
    "sg:classifiers":[
        {
            "category":"Health Services",
            "subcategory":"Doctor",
            "type":"Services"
        }
    ],
    "sg:phone":"+1 514 276 2020",
    "sg:postcode":"H2S 1R8",
    "sg:province":"QC",
    "sg:tags":[
        "clinic"
    ],
    "wof:name":"Clinique Medicale Metro Beaubi",
    "wof:placetype":"venue"
},
  "geometry": {"coordinates":[-73.605949,45.532879],"type":"Point"}
}