{
  "type": "Feature",
  "properties": {
    "addr:full":"Sherwood Park AB T8A 3X3",
    "addr:postcode":"t8a 3x3",
    "iso:country":"CA",
    "sg:city":"Sherwood Park",
    "sg:classifiers":[
        {
            "category":"Professional",
            "subcategory":"Accounting & Tax Preparation",
            "type":"Services"
        }
    ],
    "sg:phone":"+1 780 464 7007",
    "sg:postcode":"T8A 3X3",
    "sg:province":"AB",
    "sg:tags":[
        "return",
        "filing"
    ],
    "wof:name":"Smart Tax",
    "wof:placetype":"venue"
},
  "geometry": {"coordinates":[-113.295417786,53.527469635],"type":"Point"}
}