{
  "type": "Feature",
  "properties": {
    "addr:full":"Deep Brook NS B0S 1J0",
    "addr:postcode":"b0s 1j0",
    "iso:country":"CA",
    "sg:city":"Deep Brook",
    "sg:classifiers":[
        {
            "category":"Food & Beverages",
            "subcategory":"Groceries & Convenience Stores",
            "type":"Retail Goods"
        }
    ],
    "sg:phone":"+1 902 638 8161",
    "sg:postcode":"B0S 1J0",
    "sg:province":"NS",
    "sg:tags":[
        "grocer"
    ],
    "wof:name":"Deep Brook General Store",
    "wof:placetype":"venue"
},
  "geometry": {"coordinates":[-65.67337000000001,44.626499],"type":"Point"}
}