{
  "type": "Feature",
  "properties": {
    "addr:full":"Toronto ON M6P 4A2",
    "addr:postcode":"m6p 4a2",
    "iso:country":"CA",
    "sg:city":"Toronto",
    "sg:classifiers":[
        {
            "category":"Building & Trades",
            "subcategory":"Construction",
            "type":"Services"
        }
    ],
    "sg:phone":"+1 416 766 8031",
    "sg:postcode":"M6P 4A2",
    "sg:province":"ON",
    "sg:tags":[
        "windows",
        "siding",
        "contractor"
    ],
    "wof:name":"Abbi Aluminum Ltd",
    "wof:placetype":"venue"
},
  "geometry": {"coordinates":[-79.456734,43.664654],"type":"Point"}
}