{
  "type": "Feature",
  "properties": {
    "iso:country":"CA",
    "sg:address":"8515 Rue Saint-Jacques",
    "sg:city":"Mirabel",
    "sg:classifiers":[
        {
            "category":"Restaurant",
            "type":"Food & Drink"
        }
    ],
    "sg:phone":"+1 450 475 6222",
    "sg:postcode":"J7N 2A3",
    "sg:province":"QC",
    "wof:name":"Restaurant Chez Agathe",
    "wof:placetype":"venue"
},
  "geometry": {"coordinates":[-73.98388671879999,45.6347465515],"type":"Point"}
}