{
  "type": "Feature",
  "properties": {
    "addr:full":"Rimouski QC G5L 5J5",
    "addr:postcode":"g5l 5j5",
    "iso:country":"CA",
    "sg:city":"Rimouski",
    "sg:classifiers":[
        {
            "category":"Professional",
            "subcategory":"Credit Reporting & Collection",
            "type":"Services"
        }
    ],
    "sg:phone":"+1 418 721 0807",
    "sg:postcode":"G5L 5J5",
    "sg:province":"QC",
    "sg:tags":[
        "agency"
    ],
    "wof:name":"Agence DE Recouvrement Colegal",
    "wof:placetype":"venue"
},
  "geometry": {"coordinates":[-68.5228271484,48.4479751587],"type":"Point"}
}