{
  "type": "Feature",
  "properties": {
    "addr:full":"4403 118 Ave NW Edmonton AB T5W 1A8",
    "addr:housenumber":"4403",
    "addr:postcode":"t5w 1a8",
    "addr:street":"118 Ave Nw",
    "iso:country":"CA",
    "sg:address":"4403 118 Ave NW",
    "sg:city":"Edmonton",
    "sg:classifiers":[
        {
            "category":"Travel",
            "subcategory":"Hotels & Motels",
            "type":"Entertainment"
        }
    ],
    "sg:phone":"+1 780 479 3923",
    "sg:postcode":"T5W 1A8",
    "sg:province":"AB",
    "wof:name":"Beverly Motel Ltd",
    "wof:placetype":"venue"
},
  "geometry": {"coordinates":[-113.409492493,53.5701446533],"type":"Point"}
}