{
  "type": "Feature",
  "properties": {
    "addr:full":"9387 Holmes St Burnaby BC V3N 4C3",
    "addr:housenumber":"9387",
    "addr:postcode":"v3n 4c3",
    "addr:street":"Holmes St",
    "iso:country":"CA",
    "sg:address":"9387 Holmes St",
    "sg:city":"Burnaby",
    "sg:classifiers":[
        {
            "category":"Education",
            "subcategory":"School",
            "type":"Public Place"
        }
    ],
    "sg:phone":"+1 604 526 9768",
    "sg:postcode":"V3N 4C3",
    "sg:province":"BC",
    "wof:name":"St Michael's School",
    "wof:placetype":"venue"
},
  "geometry": {"coordinates":[-122.89769,49.235474],"type":"Point"}
}