{
  "type": "Feature",
  "properties": {
    "addr:full":"27 Manitou Dr Kitchener ON N2C 1K9",
    "addr:housenumber":"27",
    "addr:postcode":"n2c 1k9",
    "addr:street":"Manitou Dr",
    "iso:country":"CA",
    "sg:address":"27 Manitou Dr",
    "sg:city":"Kitchener",
    "sg:classifiers":[
        {
            "category":"Organizations",
            "subcategory":"Professional Association",
            "type":"Services"
        }
    ],
    "sg:phone":"+1 519 896 6233",
    "sg:postcode":"N2C 1K9",
    "sg:province":"ON",
    "wof:name":"Madd Waterloo Region",
    "wof:placetype":"venue"
},
  "geometry": {"coordinates":[-80.45143899999999,43.416779],"type":"Point"}
}