{
  "type": "Feature",
  "properties": {
    "addr:full":"8350 Holmes Rd Fort Steele BC V0B 1N0",
    "addr:housenumber":"8350",
    "addr:postcode":"bc v0b 1n0",
    "addr:street":"Holmes Rd",
    "iso:country":"CA",
    "sg:address":"8350 Holmes Rd",
    "sg:city":"Fort Steele",
    "sg:classifiers":[
        {
            "category":"Travel",
            "subcategory":"Hotels & Motels",
            "type":"Entertainment"
        }
    ],
    "sg:phone":"+1 250 426 6306",
    "sg:postcode":"V0B 1N0",
    "sg:province":"BC",
    "sg:tags":[
        "ranch",
        "guest"
    ],
    "wof:name":"Top of the World Ltd",
    "wof:placetype":"venue"
},
  "geometry": {"coordinates":[-115.629051,49.616142],"type":"Point"}
}