{
  "type": "Feature",
  "properties": {
    "iso:country":"CA",
    "sg:address":"4463 Chesswood Dr",
    "sg:city":"North York",
    "sg:classifiers":[
        {
            "category":"Wholesale",
            "subcategory":"Auto Parts",
            "type":"Manufacturing & Wholesale Goods"
        }
    ],
    "sg:phone":"+1 416 633 9272",
    "sg:postcode":"M3J 2C2",
    "sg:province":"ON",
    "sg:tags":[
        "automobile",
        "wrecking"
    ],
    "wof:name":"North York Core Supply Inc",
    "wof:placetype":"venue"
},
  "geometry": {"coordinates":[-79.4765701294,43.7622642517],"type":"Point"}
}