{
  "type": "Feature",
  "properties": {
    "addr:full":"103 Dundas St W Whitby ON L1N 2M1",
    "addr:housenumber":"103",
    "addr:postcode":"l1n 2m1",
    "addr:street":"Dundas St W",
    "iso:country":"CA",
    "sg:address":"103 Dundas St W",
    "sg:city":"Whitby",
    "sg:classifiers":[
        {
            "category":"Education",
            "subcategory":"Special Training",
            "type":"Public Place"
        }
    ],
    "sg:phone":"+1 905 666 8780",
    "sg:postcode":"L1N 2M1",
    "sg:province":"ON",
    "sg:tags":[
        "instruction",
        "music"
    ],
    "wof:name":"Whitby Early Childwood Music",
    "wof:placetype":"venue"
},
  "geometry": {"coordinates":[-78.942345,43.879753],"type":"Point"}
}