{
  "type": "Feature",
  "properties": {
    "addr:full":"57 Central Ave N Swift Current SK S9H 0K8",
    "addr:housenumber":"57",
    "addr:postcode":"s9h 0k8",
    "addr:street":"Central Ave N",
    "iso:country":"CA",
    "sg:address":"57 Central Ave N",
    "sg:city":"Swift Current",
    "sg:classifiers":[
        {
            "category":"Travel",
            "subcategory":"Hotels & Motels",
            "type":"Entertainment"
        }
    ],
    "sg:phone":"+1 306 778 2222",
    "sg:postcode":"S9H 0K8",
    "sg:province":"SK",
    "wof:name":"York Hotel Promotions",
    "wof:placetype":"venue"
},
  "geometry": {"coordinates":[-107.799682617,50.2827987671],"type":"Point"}
}