{
  "type": "Feature",
  "properties": {
    "addr:full":"168 Locke St S Hamilton ON L8P 4A9",
    "addr:housenumber":"168",
    "addr:postcode":"l8p 4a9",
    "addr:street":"Locke St S",
    "iso:country":"CA",
    "sg:address":"168 Locke St S",
    "sg:city":"Hamilton",
    "sg:classifiers":[
        {
            "category":"Shopping",
            "subcategory":"Used Merchandise",
            "type":"Retail Goods"
        }
    ],
    "sg:phone":"+1 905 523 5018",
    "sg:postcode":"L8P 4A9",
    "sg:province":"ON",
    "sg:tags":[
        "antique"
    ],
    "wof:name":"Olive's Oddments",
    "wof:placetype":"venue"
},
  "geometry": {"coordinates":[-79.88548278810001,43.2561912537],"type":"Point"}
}