{
  "type": "Feature",
  "properties": {
    "iso:country":"CA",
    "sg:city":"Burnaby",
    "sg:classifiers":[
        {
            "category":"Building & Trades",
            "subcategory":"Construction",
            "type":"Services"
        }
    ],
    "sg:phone":"+1 604 298 9300",
    "sg:postcode":"V5C 3K8",
    "sg:province":"BC",
    "sg:tags":[
        "painter"
    ],
    "wof:name":"Solution Painting & Decorating",
    "wof:placetype":"venue"
},
  "geometry": {"coordinates":[-123.018028259,49.2728042603],"type":"Point"}
}