{
  "type": "Feature",
  "properties": {
    "addr:full":"363 Rue DE LA Concorde Montreal QC H3A 1J3",
    "addr:housenumber":"363",
    "addr:postcode":"h3a 1j3",
    "addr:street":"Rue De La Concorde",
    "iso:country":"CA",
    "sg:address":"363 Rue DE LA Concorde",
    "sg:city":"Montreal",
    "sg:classifiers":[
        {
            "category":"Parking",
            "type":"Transportation"
        }
    ],
    "sg:phone":"+1 514 287 0530",
    "sg:postcode":"H3A 1J3",
    "sg:province":"QC",
    "sg:tags":[
        "garage"
    ],
    "wof:name":"Stationnement Cle",
    "wof:placetype":"venue"
},
  "geometry": {"coordinates":[-73.5705413818,45.5074768066],"type":"Point"}
}