{
  "type": "Feature",
  "properties": {
    "iso:country":"CA",
    "sg:address":"4 Sylvia St",
    "sg:city":"Kitchener",
    "sg:classifiers":[
        {
            "category":"Professional",
            "type":"Services"
        }
    ],
    "sg:phone":"+1 519 579 5837",
    "sg:postcode":"N2K 1E7",
    "sg:province":"ON",
    "sg:tags":[
        "distributing",
        "establishment"
    ],
    "wof:name":"Turtle Creek Distribution",
    "wof:placetype":"venue"
},
  "geometry": {"coordinates":[-80.465775,43.482044],"type":"Point"}
}