{
  "type": "Feature",
  "properties": {
    "addr:full":"PO Box 220 Blairmore AB T0K 0E0",
    "addr:housenumber":"po",
    "addr:postcode":"t0k 0e0",
    "addr:street":"Box 220",
    "iso:country":"CA",
    "sg:address":"PO Box 220",
    "sg:city":"Blairmore",
    "sg:classifiers":[
        {
            "category":"Building & Trades",
            "subcategory":"Equipment Rental",
            "type":"Services"
        }
    ],
    "sg:phone":"+1 403 562 8442",
    "sg:postcode":"T0K 0E0",
    "sg:province":"AB",
    "sg:tags":[
        "helicopter",
        "aircraft",
        "leasing",
        "charter"
    ],
    "wof:name":"Bighorn Helicopter Inc",
    "wof:placetype":"venue"
},
  "geometry": {"coordinates":[-114.43698120099999,49.6076583862],"type":"Point"}
}