{
  "type": "Feature",
  "properties": {
    "addr:full":"5 Windward Dr Grimsby ON L3M 4E8",
    "addr:housenumber":"5",
    "addr:postcode":"l3m 4e8",
    "addr:street":"Windward Dr",
    "iso:country":"CA",
    "sg:address":"5 Windward Dr",
    "sg:city":"Grimsby",
    "sg:classifiers":[
        {
            "category":"Food & Beverages",
            "subcategory":"Groceries & Convenience Stores",
            "type":"Retail Goods"
        }
    ],
    "sg:phone":"+1 905 309 6447",
    "sg:postcode":"L3M 4E8",
    "sg:province":"ON",
    "sg:tags":[
        "grocer"
    ],
    "wof:name":"News & Pops Express",
    "wof:placetype":"venue"
},
  "geometry": {"coordinates":[-79.601151,43.209354],"type":"Point"}
}