{
  "type": "Feature",
  "properties": {
    "addr:full":"5511 Tomken Rd # 1 Mississauga ON L4W 4B8",
    "addr:housenumber":"5511",
    "addr:postcode":"l4w 4b8",
    "addr:street":"Tomken Rd # 1",
    "iso:country":"CA",
    "sg:address":"5511 Tomken Rd # 1",
    "sg:city":"Mississauga",
    "sg:classifiers":[
        {
            "category":"Manufacturing",
            "subcategory":"Tools & Machinery",
            "type":"Manufacturing & Wholesale Goods"
        }
    ],
    "sg:phone":"+1 905 206 0508",
    "sg:postcode":"L4W 4B8",
    "sg:province":"ON",
    "sg:tags":[
        "industrial",
        "truck"
    ],
    "wof:name":"Noveltek Material Handling Ltd",
    "wof:placetype":"venue"
},
  "geometry": {"coordinates":[-79.646523,43.637287],"type":"Point"}
}