{
  "type": "Feature",
  "properties": {
    "iso:country":"CA",
    "sg:address":"74 Broadway",
    "sg:city":"Corner Brook",
    "sg:classifiers":[
        {
            "category":"Wholesale",
            "subcategory":"Electrical",
            "type":"Manufacturing & Wholesale Goods"
        }
    ],
    "sg:phone":"+1 709 634 6351",
    "sg:postcode":"A2H 4C8",
    "sg:province":"NL",
    "sg:tags":[
        "sound",
        "system",
        "high",
        "equipment",
        "stereophonic",
        "fidelity"
    ],
    "wof:name":"Altronics Limited",
    "wof:placetype":"venue"
},
  "geometry": {"coordinates":[-57.955581665,48.952709198],"type":"Point"}
}