{
  "type": "Feature",
  "properties": {
    "iso:country":"CA",
    "sg:address":"2300 Boul Pere-Lelievre",
    "sg:city":"Quebec",
    "sg:classifiers":[
        {
            "category":"Recreation",
            "type":"Entertainment"
        }
    ],
    "sg:phone":"+1 418 683 8499",
    "sg:postcode":"G1P 2X5",
    "sg:province":"QC",
    "sg:tags":[
        "martial",
        "arts",
        "instruction"
    ],
    "wof:name":"Studios Unis D'Auto Defense",
    "wof:placetype":"venue"
},
  "geometry": {"coordinates":[-71.2982177734,46.8117828369],"type":"Point"}
}