{
  "type": "Feature",
  "properties": {
    "addr:full":"69 Military Rd St. John's NL A1C 2C7",
    "addr:housenumber":"69",
    "addr:postcode":"a1c 2c7",
    "addr:street":"Military Rd",
    "iso:country":"CA",
    "sg:address":"69 Military Rd",
    "sg:city":"St. John's",
    "sg:classifiers":[
        {
            "category":"Food & Beverages",
            "subcategory":"Groceries & Convenience Stores",
            "type":"Retail Goods"
        }
    ],
    "sg:phone":"+1 709 722 2210",
    "sg:postcode":"A1C 2C7",
    "sg:province":"NL",
    "wof:name":"Needs Convenience Store",
    "wof:placetype":"venue"
},
  "geometry": {"coordinates":[-52.705894,47.570728],"type":"Point"}
}