{
  "type": "Feature",
  "properties": {
    "addr:full":"Sainte-Foy QC G1X 4G6",
    "addr:postcode":"g1x 4g6",
    "iso:country":"CA",
    "sg:city":"Sainte-Foy",
    "sg:classifiers":[
        {
            "category":"Insurance",
            "subcategory":"Insurance Agent",
            "type":"Services"
        }
    ],
    "sg:phone":"+1 418 658 8330",
    "sg:postcode":"G1X 4G6",
    "sg:province":"QC",
    "sg:tags":[
        "adjuster"
    ],
    "wof:name":"Morin Bourget Denys Inc",
    "wof:placetype":"venue"
},
  "geometry": {"coordinates":[-71.3329620361,46.7618103027],"type":"Point"}
}