{
  "type": "Feature",
  "properties": {
    "addr:full":"9250 Heritage Lane Coldstream BC V1B 2N2",
    "addr:housenumber":"9250",
    "addr:postcode":"bc v1b 2n2",
    "addr:street":"Heritage Lane",
    "iso:country":"CA",
    "sg:address":"9250 Heritage Lane",
    "sg:city":"Coldstream",
    "sg:classifiers":[
        {
            "category":"Professional",
            "subcategory":"Lawyer & Legal Services",
            "type":"Services"
        }
    ],
    "sg:phone":"+1 250 542 9242",
    "sg:postcode":"V1B 2N2",
    "sg:province":"BC",
    "sg:tags":[
        "attorney"
    ],
    "wof:name":"Skobalski, J Glen",
    "wof:placetype":"venue"
},
  "geometry": {"coordinates":[-119.222679,50.228107],"type":"Point"}
}