{
  "type": "Feature",
  "properties": {
    "addr:full":"2655 Boul Du Royaume # 200 Jonquiere QC G7S 4S9",
    "addr:housenumber":"2655",
    "addr:postcode":"g7s 4s9",
    "addr:street":"Boul Du Royaume # 200",
    "iso:country":"CA",
    "sg:address":"2655 Boul Du Royaume # 200",
    "sg:city":"Jonquiere",
    "sg:classifiers":[
        {
            "category":"Real Estate",
            "subcategory":"Real Estate Operator",
            "type":"Services"
        }
    ],
    "sg:phone":"+1 418 548 8241",
    "sg:postcode":"G7S 4S9",
    "sg:province":"QC",
    "sg:tags":[
        "mall",
        "shopping",
        "center"
    ],
    "wof:name":"Faubourg Sagamie Inc",
    "wof:placetype":"venue"
},
  "geometry": {"coordinates":[-71.16847199999999,48.40501],"type":"Point"}
}