{
  "type": "Feature",
  "properties": {
    "addr:full":"4532 50 Ave Lacombe AB T4L 2B6",
    "addr:housenumber":"4532",
    "addr:postcode":"t4l 2b6",
    "addr:street":"50 Ave",
    "iso:country":"CA",
    "sg:address":"4532 50 Ave",
    "sg:city":"Lacombe",
    "sg:classifiers":[
        {
            "category":"Shopping",
            "subcategory":"Used Merchandise",
            "type":"Retail Goods"
        }
    ],
    "sg:phone":"+1 403 782 4719",
    "sg:postcode":"T4L 2B6",
    "sg:province":"AB",
    "sg:tags":[
        "second",
        "store",
        "hand"
    ],
    "wof:name":"Lacombe Secondhand",
    "wof:placetype":"venue"
},
  "geometry": {"coordinates":[-113.72483800000001,52.463245],"type":"Point"}
}