{
  "type": "Feature",
  "properties": {
    "iso:country":"CA",
    "sg:city":"London",
    "sg:classifiers":[
        {
            "category":"Real Estate",
            "subcategory":"Real Estate Operator",
            "type":"Services"
        }
    ],
    "sg:phone":"+1 519 471 6047",
    "sg:postcode":"N6H 4R4",
    "sg:province":"ON",
    "sg:tags":[
        "apartment"
    ],
    "wof:name":"Oakridge Park Town Homes",
    "wof:placetype":"venue"
},
  "geometry": {"coordinates":[-81.31690979,42.9749336243],"type":"Point"}
}