{
  "type": "Feature",
  "properties": {
    "addr:full":"Edson AB T7E 1T9",
    "addr:postcode":"t7e 1t9",
    "iso:country":"CA",
    "sg:city":"Edson",
    "sg:classifiers":[
        {
            "category":"Airline",
            "type":"Transportation"
        }
    ],
    "sg:phone":"+1 780 723 6422",
    "sg:postcode":"T7E 1T9",
    "sg:province":"AB",
    "sg:tags":[
        "rental",
        "aircraft",
        "leasing",
        "charter"
    ],
    "wof:name":"Highland Helicopters Ltd",
    "wof:placetype":"venue"
},
  "geometry": {"coordinates":[-116.450706482,53.5811500549],"type":"Point"}
}