{
  "type": "Feature",
  "properties": {
    "addr:full":"914 Concession 2 Sdrd Walkerton ON N0G 2V0",
    "addr:housenumber":"914",
    "addr:postcode":"n0g 2v0",
    "addr:street":"Concession 2 Sdrd Walkerton",
    "iso:country":"CA",
    "sg:address":"914 Concession 2 Sdrd",
    "sg:city":"Walkerton",
    "sg:classifiers":[
        {
            "category":"Building & Trades",
            "subcategory":"Electrical",
            "type":"Services"
        }
    ],
    "sg:phone":"+1 519 881 0727",
    "sg:postcode":"N0G 2V0",
    "sg:province":"ON",
    "sg:tags":[
        "cleaners",
        "vacuum",
        "electric",
        "contractor"
    ],
    "wof:name":"Rks Electric",
    "wof:placetype":"venue"
},
  "geometry": {"coordinates":[-81.15213012700001,44.1281814575],"type":"Point"}
}