{
  "type": "Feature",
  "properties": {
    "addr:full":"8818 17 Sideroad Everett ON L0M 1J0",
    "addr:housenumber":"8818",
    "addr:postcode":"l0m 1j0",
    "addr:street":"17 Sideroad",
    "iso:country":"CA",
    "sg:address":"8818 17 Sideroad",
    "sg:city":"Everett",
    "sg:classifiers":[
        {
            "category":"Building & Trades",
            "subcategory":"Construction",
            "type":"Services"
        }
    ],
    "sg:phone":"+1 705 435 7334",
    "sg:postcode":"L0M 1J0",
    "sg:province":"ON",
    "sg:tags":[
        "home",
        "improvement"
    ],
    "wof:name":"Dimitry Carpentry",
    "wof:placetype":"venue"
},
  "geometry": {"coordinates":[-79.9664611816,44.2249984741],"type":"Point"}
}