{
  "type": "Feature",
  "properties": {
    "addr:full":"502 Rue Du Conseil Sherbrooke QC J1G 1K1",
    "addr:housenumber":"502",
    "addr:postcode":"j1g 1k1",
    "addr:street":"Rue Du Conseil",
    "iso:country":"CA",
    "sg:address":"502 Rue Du Conseil",
    "sg:city":"Sherbrooke",
    "sg:classifiers":[
        {
            "category":"Education",
            "subcategory":"School",
            "type":"Public Place"
        }
    ],
    "sg:phone":"+1 819 820 7492",
    "sg:postcode":"J1G 1K1",
    "sg:province":"QC",
    "sg:tags":[
        "academic",
        "special"
    ],
    "wof:name":"Ecole DE Couture Fibrelle",
    "wof:placetype":"venue"
},
  "geometry": {"coordinates":[-71.8775939941,45.4035568237],"type":"Point"}
}