{
  "type": "Feature",
  "properties": {
    "addr:full":"250 Boul Cartier O Laval QC H7N 5S5",
    "addr:housenumber":"250",
    "addr:postcode":"h7n 5s5",
    "addr:street":"Boul Cartier O",
    "iso:country":"CA",
    "sg:address":"250 Boul Cartier O",
    "sg:city":"Laval",
    "sg:classifiers":[
        {
            "category":"Social Services",
            "type":"Services"
        }
    ],
    "sg:phone":"+1 450 668 1803",
    "sg:postcode":"H7N 5S5",
    "sg:province":"QC",
    "sg:tags":[
        "organization",
        "welfare"
    ],
    "wof:name":"Clsc-Chsld Du Marigot",
    "wof:placetype":"venue"
},
  "geometry": {"coordinates":[-73.6952819824,45.5583229065],"type":"Point"}
}