{
  "type": "Feature",
  "properties": {
    "addr:full":"1225 112 Rte Weedon QC J0B 3J0",
    "addr:housenumber":"1225",
    "addr:postcode":"j0b 3j0",
    "addr:street":"112 Rte",
    "iso:country":"CA",
    "sg:address":"1225 112 Rte",
    "sg:city":"Weedon",
    "sg:classifiers":[
        {
            "category":"Travel",
            "subcategory":"Campground",
            "type":"Entertainment"
        }
    ],
    "sg:phone":"+1 819 877 5000",
    "sg:postcode":"J0B 3J0",
    "sg:province":"QC",
    "sg:tags":[
        "tennis",
        "court"
    ],
    "wof:name":"Camping Beau Soleil",
    "wof:placetype":"venue"
},
  "geometry": {"coordinates":[-71.4597167969,45.7093696594],"type":"Point"}
}