{
  "type": "Feature",
  "properties": {
    "addr:full":"Victoria BC V8X 1J8",
    "addr:postcode":"v8x 1j8",
    "iso:country":"CA",
    "sg:city":"Victoria",
    "sg:classifiers":[
        {
            "category":"Shopping",
            "subcategory":"Computers & Home Electronics",
            "type":"Retail Goods"
        }
    ],
    "sg:phone":"+1 250 727 2046",
    "sg:postcode":"V8X 1J8",
    "sg:province":"BC",
    "sg:tags":[
        "equipment",
        "dealer",
        "pharmacy"
    ],
    "wof:name":"London Drugs Ltd",
    "wof:placetype":"venue"
},
  "geometry": {"coordinates":[-123.36200714100001,48.448890686],"type":"Point"}
}