{
  "type": "Feature",
  "properties": {
    "addr:full":"8 Place Legault Mont-Royal QC H4P 1Y1",
    "addr:housenumber":"8",
    "addr:postcode":"h4p 1y1",
    "addr:street":"Place Legault",
    "iso:country":"CA",
    "sg:address":"8 Place Legault",
    "sg:city":"Mont-Royal",
    "sg:classifiers":[
        {
            "category":"Retail",
            "subcategory":"Auto Repair",
            "type":"Services"
        }
    ],
    "sg:phone":"+1 514 738 7433",
    "sg:postcode":"H4P 1Y1",
    "sg:province":"QC",
    "sg:tags":[
        "repairing",
        "automobile"
    ],
    "wof:name":"Garage Sport Cote Des Neiges",
    "wof:placetype":"venue"
},
  "geometry": {"coordinates":[-73.645515,45.501823],"type":"Point"}
}