{
  "type": "Feature",
  "properties": {
    "addr:full":"8634 22nd Ave Coleman AB T0K 0M0",
    "addr:housenumber":"8634",
    "addr:postcode":"t0k 0m0",
    "addr:street":"22Nd Ave",
    "iso:country":"CA",
    "sg:address":"8634 22nd Ave",
    "sg:city":"Coleman",
    "sg:classifiers":[
        {
            "category":"Building & Trades",
            "subcategory":"Cleaning & Sanitation",
            "type":"Services"
        }
    ],
    "sg:phone":"+1 403 563 5595",
    "sg:postcode":"T0K 0M0",
    "sg:province":"AB",
    "sg:tags":[
        "janitor"
    ],
    "wof:name":"Complete Clean Janitorial Svc",
    "wof:placetype":"venue"
},
  "geometry": {"coordinates":[-114.488663,49.637074],"type":"Point"}
}