{
  "type": "Feature",
  "properties": {
    "addr:full":"9996 Hwy 16 Guysborough NS B0H 1N0",
    "addr:housenumber":"9996",
    "addr:postcode":"b0h 1n0",
    "addr:street":"Hwy 16",
    "iso:country":"CA",
    "sg:address":"9996 Hwy 16",
    "sg:city":"Guysborough",
    "sg:classifiers":[
        {
            "category":"Insurance",
            "subcategory":"Insurance Agent",
            "type":"Services"
        }
    ],
    "sg:phone":"+1 902 533 2005",
    "sg:postcode":"B0H 1N0",
    "sg:province":"NS",
    "wof:name":"Guysborough Insurance Svc Ltd",
    "wof:placetype":"venue"
},
  "geometry": {"coordinates":[-61.5056,45.386608],"type":"Point"}
}