{
  "type": "Feature",
  "properties": {
    "addr:full":"154 Lucas St Richmond Hill ON L4C 4P5",
    "addr:housenumber":"154",
    "addr:postcode":"l4c 4p5",
    "addr:street":"Lucas St",
    "iso:country":"CA",
    "sg:address":"154 Lucas St",
    "sg:city":"Richmond Hill",
    "sg:classifiers":[
        {
            "category":"Professional",
            "subcategory":"Accounting & Tax Preparation",
            "type":"Services"
        }
    ],
    "sg:phone":"+1 905 770 1505",
    "sg:postcode":"L4C 4P5",
    "sg:province":"ON",
    "sg:tags":[
        "consultant",
        "bookkeeping",
        "management",
        "business",
        "general"
    ],
    "wof:name":"A A Business Svc",
    "wof:placetype":"venue"
},
  "geometry": {"coordinates":[-79.44515228269999,43.8798713684],"type":"Point"}
}