{
  "type": "Feature",
  "properties": {
    "addr:full":"4180 Kingston Rd Scarborough ON M1E 2M4",
    "addr:housenumber":"4180",
    "addr:postcode":"m1e 2m4",
    "addr:street":"Kingston Rd",
    "iso:country":"CA",
    "sg:address":"4180 Kingston Rd",
    "sg:city":"Scarborough",
    "sg:classifiers":[
        {
            "category":"Retail",
            "subcategory":"Laundry & Dry Cleaning",
            "type":"Services"
        }
    ],
    "sg:phone":"+1 416 282 1461",
    "sg:postcode":"M1E 2M4",
    "sg:province":"ON",
    "sg:tags":[
        "cleaners"
    ],
    "wof:name":"Hyway Cleaners",
    "wof:placetype":"venue"
},
  "geometry": {"coordinates":[-79.1980133057,43.7588272095],"type":"Point"}
}