{
  "type": "Feature",
  "properties": {
    "addr:full":"300 Rue Du Docteur-Poulin Marieville QC J3M 1L7",
    "addr:housenumber":"300",
    "addr:postcode":"j3m 1l7",
    "addr:street":"Rue Du Docteur-Poulin",
    "iso:country":"CA",
    "sg:address":"300 Rue Du Docteur-Poulin",
    "sg:city":"Marieville",
    "sg:classifiers":[
        {
            "category":"Professional",
            "subcategory":"Research",
            "type":"Services"
        }
    ],
    "sg:phone":"+1 450 460 4475",
    "sg:postcode":"J3M 1L7",
    "sg:province":"QC",
    "sg:tags":[
        "home",
        "philanthropic",
        "rest"
    ],
    "wof:name":"Centre Rouville Residence Ste",
    "wof:placetype":"venue"
},
  "geometry": {"coordinates":[-73.1588668823,45.4350967407],"type":"Point"}
}