{
  "type": "Feature",
  "properties": {
    "addr:full":"2452 Queen St E Brampton ON L6S 5X9",
    "addr:housenumber":"2452",
    "addr:postcode":"l6s 5x9",
    "addr:street":"Queen St E",
    "iso:country":"CA",
    "sg:address":"2452 Queen St E",
    "sg:city":"Brampton",
    "sg:classifiers":[
        {
            "category":"Restaurant",
            "type":"Food & Drink"
        }
    ],
    "sg:phone":"+1 905 791 8168",
    "sg:postcode":"L6S 5X9",
    "sg:province":"ON",
    "wof:name":"Denny's Restaurant",
    "wof:placetype":"venue"
},
  "geometry": {"coordinates":[-79.70283499999999,43.737644],"type":"Point"}
}