{
  "type": "Feature",
  "properties": {
    "addr:full":"Hull QC J8Y 6T9",
    "addr:postcode":"j8y 6t9",
    "iso:country":"CA",
    "sg:city":"Hull",
    "sg:classifiers":[
        {
            "category":"Food & Beverages",
            "subcategory":"Groceries & Convenience Stores",
            "type":"Retail Goods"
        }
    ],
    "sg:phone":"+1 819 595 1344",
    "sg:postcode":"J8Y 6T9",
    "sg:province":"QC",
    "sg:tags":[
        "grocer"
    ],
    "wof:name":"Super C",
    "wof:placetype":"venue"
},
  "geometry": {"coordinates":[-75.72924041749999,45.4504203796],"type":"Point"}
}