{
  "type": "Feature",
  "properties": {
    "addr:full":"7815 King George Hwy Surrey BC V3W 5B1",
    "addr:housenumber":"7815",
    "addr:postcode":"v3w 5b1",
    "addr:street":"King George Hwy",
    "iso:country":"CA",
    "sg:address":"7815 King George Hwy",
    "sg:city":"Surrey",
    "sg:classifiers":[
        {
            "category":"Home & Garden",
            "subcategory":"Building Materials",
            "type":"Retail Goods"
        }
    ],
    "sg:phone":"+1 604 596 1077",
    "sg:postcode":"V3W 5B1",
    "sg:province":"BC",
    "sg:tags":[
        "plumbing",
        "fixture",
        "supply"
    ],
    "wof:name":"Hillcrest Plumbing Discount",
    "wof:placetype":"venue"
},
  "geometry": {"coordinates":[-122.845840454,49.1449050903],"type":"Point"}
}