{
  "type": "Feature",
  "properties": {
    "addr:full":"10215 176 St NW Edmonton AB T5S 1M1",
    "addr:housenumber":"10215",
    "addr:postcode":"t5s 1m1",
    "addr:street":"176 St Nw",
    "iso:country":"CA",
    "sg:address":"10215 176 St NW",
    "sg:city":"Edmonton",
    "sg:classifiers":[
        {
            "category":"Organizations",
            "subcategory":"Professional Association",
            "type":"Services"
        }
    ],
    "sg:phone":"+1 780 489 1991",
    "sg:postcode":"T5S 1M1",
    "sg:province":"AB",
    "wof:name":"Landscape Alberta Nrsry Trade",
    "wof:placetype":"venue"
},
  "geometry": {"coordinates":[-113.623672,53.543743],"type":"Point"}
}