{
  "type": "Feature",
  "properties": {
    "iso:country":"CA",
    "sg:address":"902 Rosser Ave",
    "sg:city":"Brandon",
    "sg:classifiers":[
        {
            "category":"Shopping",
            "subcategory":"Jewelry",
            "type":"Retail Goods"
        }
    ],
    "sg:phone":"+1 204 727 5500",
    "sg:postcode":"R7A 0L4",
    "sg:province":"MB",
    "sg:tags":[
        "jeweler"
    ],
    "wof:name":"Zeke's Quality Jewellers Ltd",
    "wof:placetype":"venue"
},
  "geometry": {"coordinates":[-99.95026397709999,49.8483390808],"type":"Point"}
}