{
  "type": "Feature",
  "properties": {
    "addr:full":"131 Moraine Rd Canmore AB T1W 1J6",
    "addr:housenumber":"131",
    "addr:postcode":"t1w 1j6",
    "addr:street":"Moraine Rd",
    "iso:country":"CA",
    "sg:address":"131 Moraine Rd",
    "sg:city":"Canmore",
    "sg:classifiers":[
        {
            "category":"Building & Trades",
            "subcategory":"Construction",
            "type":"Services"
        }
    ],
    "sg:phone":"+1 403 678 6990",
    "sg:postcode":"T1W 1J6",
    "sg:province":"AB",
    "sg:tags":[
        "general",
        "contractor"
    ],
    "wof:name":"Impact Construction",
    "wof:placetype":"venue"
},
  "geometry": {"coordinates":[-115.32914,51.080006],"type":"Point"}
}