{
  "type": "Feature",
  "properties": {
    "addr:full":"350 Boul Industriel Saint-Jean-Sur-Richelieu QC J3B 4S6",
    "addr:housenumber":"350",
    "addr:postcode":"j3b 4s6",
    "addr:street":"Boul Industriel",
    "iso:country":"CA",
    "sg:address":"350 Boul Industriel",
    "sg:city":"Saint-Jean-Sur-Richelieu",
    "sg:classifiers":[
        {
            "category":"Wholesale",
            "subcategory":"Machinery & Supplies",
            "type":"Manufacturing & Wholesale Goods"
        }
    ],
    "sg:phone":"+1 450 347 5254",
    "sg:postcode":"J3B 4S6",
    "sg:province":"QC",
    "sg:tags":[
        "equipment",
        "railroad"
    ],
    "wof:name":"Portec Rail Products Ltd",
    "wof:placetype":"venue"
},
  "geometry": {"coordinates":[-73.2849273682,45.3094100952],"type":"Point"}
}