{
  "type": "Feature",
  "properties": {
    "addr:full":"161 Grandin St Winnipeg MB R2H 0A8",
    "addr:housenumber":"161",
    "addr:postcode":"r2h 0a8",
    "addr:street":"Grandin St",
    "iso:country":"CA",
    "sg:address":"161 Grandin St",
    "sg:city":"Winnipeg",
    "sg:classifiers":[
        {
            "category":"Recreation",
            "type":"Entertainment"
        }
    ],
    "sg:phone":"+1 204 233 6365",
    "sg:postcode":"R2H 0A8",
    "sg:province":"MB",
    "sg:tags":[
        "bingo",
        "game"
    ],
    "wof:name":"Kinsmen Tv Bingo",
    "wof:placetype":"venue"
},
  "geometry": {"coordinates":[-97.1261520386,49.8961791992],"type":"Point"}
}