{
  "type": "Feature",
  "properties": {
    "addr:full":"Richmond Hill ON L4B 1B9",
    "addr:postcode":"l4b 1b9",
    "iso:country":"CA",
    "sg:city":"Richmond Hill",
    "sg:classifiers":[
        {
            "category":"Professional",
            "subcategory":"Accounting & Tax Preparation",
            "type":"Services"
        }
    ],
    "sg:phone":"+1 905 709 0070",
    "sg:postcode":"L4B 1B9",
    "sg:province":"ON",
    "sg:tags":[
        "accountant"
    ],
    "wof:name":"Cranston & Krozonouski",
    "wof:placetype":"venue"
},
  "geometry": {"coordinates":[-79.3862915039,43.8453788757],"type":"Point"}
}