{
  "type": "Feature",
  "properties": {
    "addr:full":"Sainte-Marthe QC J0P 1W0",
    "addr:postcode":"j0p 1w0",
    "iso:country":"CA",
    "sg:city":"Sainte-Marthe",
    "sg:classifiers":[
        {
            "category":"Building & Trades",
            "subcategory":"Construction",
            "type":"Services"
        }
    ],
    "sg:phone":"+1 450 459 4294",
    "sg:postcode":"J0P 1W0",
    "sg:province":"QC",
    "sg:tags":[
        "excavating",
        "contractor"
    ],
    "wof:name":"Excavation G Lalonde Inc",
    "wof:placetype":"venue"
},
  "geometry": {"coordinates":[-74.303596,45.407623],"type":"Point"}
}