{
  "type": "Feature",
  "properties": {
    "addr:full":"Calgary AB T2J 6G2",
    "addr:postcode":"t2j 6g2",
    "iso:country":"CA",
    "sg:city":"Calgary",
    "sg:classifiers":[
        {
            "category":"Banks & Credit Unions",
            "subcategory":"Bank",
            "type":"Services"
        }
    ],
    "sg:phone":"+1 403 292 8336",
    "sg:postcode":"T2J 6G2",
    "sg:province":"AB",
    "wof:name":"Royal Bank Financial Group",
    "wof:placetype":"venue"
},
  "geometry": {"coordinates":[-114.03048699999999,50.931244],"type":"Point"}
}