{
  "type": "Feature",
  "properties": {
    "addr:full":"230 Main St W North Bay ON P1B 2T7",
    "addr:housenumber":"230",
    "addr:postcode":"p1b 2t7",
    "addr:street":"Main St W",
    "iso:country":"CA",
    "sg:address":"230 Main St W",
    "sg:city":"North Bay",
    "sg:classifiers":[
        {
            "category":"Organizations",
            "subcategory":"Labor Organization",
            "type":"Services"
        }
    ],
    "sg:phone":"+1 705 494 8853",
    "sg:postcode":"P1B 2T7",
    "sg:province":"ON",
    "wof:name":"Caw Local 991",
    "wof:placetype":"venue"
},
  "geometry": {"coordinates":[-79.46573600000001,46.312611],"type":"Point"}
}