{
  "type": "Feature",
  "properties": {
    "iso:country":"CA",
    "sg:address":"11620 Horseshoe Way # 100",
    "sg:city":"Richmond",
    "sg:classifiers":[
        {
            "category":"Building & Trades",
            "subcategory":"Cleaning & Sanitation",
            "type":"Services"
        }
    ],
    "sg:phone":"+1 604 274 0477",
    "sg:postcode":"V7A 4V5",
    "sg:province":"BC",
    "sg:tags":[
        "janitor"
    ],
    "wof:name":"Arodal Services Ltd",
    "wof:placetype":"venue"
},
  "geometry": {"coordinates":[-123.095627,49.127506],"type":"Point"}
}