{
  "type": "Feature",
  "properties": {
    "addr:full":"141 Rue Henri Bourassa Papineauville QC J0V 1R0",
    "addr:housenumber":"141",
    "addr:postcode":"j0v 1r0",
    "addr:street":"Rue Henri Bourassa",
    "iso:country":"CA",
    "sg:address":"141 Rue Henri Bourassa",
    "sg:city":"Papineauville",
    "sg:classifiers":[
        {
            "category":"Bars & Pubs",
            "type":"Food & Drink"
        }
    ],
    "sg:phone":"+1 819 427 8201",
    "sg:postcode":"J0V 1R0",
    "sg:province":"QC",
    "sg:tags":[
        "lounge",
        "cocktail"
    ],
    "wof:name":"Bar Monette",
    "wof:placetype":"venue"
},
  "geometry": {"coordinates":[-75.0169296265,45.6160964966],"type":"Point"}
}