{
  "type": "Feature",
  "properties": {
    "addr:full":"6988 Landooz Rd Prince George BC V2K 5S1",
    "addr:housenumber":"6988",
    "addr:postcode":"v2k 5s1",
    "addr:street":"Landooz Rd",
    "iso:country":"CA",
    "sg:address":"6988 Landooz Rd",
    "sg:city":"Prince George",
    "sg:classifiers":[
        {
            "category":"Manufacturing",
            "subcategory":"Lumber",
            "type":"Manufacturing & Wholesale Goods"
        }
    ],
    "sg:phone":"+1 250 962 4700",
    "sg:postcode":"V2K 5S1",
    "sg:province":"BC",
    "wof:name":"Canfor Prince George Sawmill",
    "wof:placetype":"venue"
},
  "geometry": {"coordinates":[-122.639336,54.005974],"type":"Point"}
}