{
  "type": "Feature",
  "properties": {
    "iso:country":"CA",
    "sg:address":"4242 Dundas St W",
    "sg:city":"Etobicoke",
    "sg:classifiers":[
        {
            "category":"Home & Garden",
            "subcategory":"Home Furnishings",
            "type":"Retail Goods"
        }
    ],
    "sg:phone":"+1 416 236 3611",
    "sg:postcode":"M8X 1Y6",
    "sg:province":"ON",
    "sg:tags":[
        "lighting",
        "fixture"
    ],
    "wof:name":"Living Lighting",
    "wof:placetype":"venue"
},
  "geometry": {"coordinates":[-79.511818,43.660275],"type":"Point"}
}