{
  "type": "Feature",
  "properties": {
    "addr:full":"9905 Tecumseh Rd E Windsor ON N8R 1A5",
    "addr:housenumber":"9905",
    "addr:postcode":"n8r 1a5",
    "addr:street":"Tecumseh Rd E",
    "iso:country":"CA",
    "sg:address":"9905 Tecumseh Rd E",
    "sg:city":"Windsor",
    "sg:classifiers":[
        {
            "category":"Food & Beverages",
            "subcategory":"Groceries & Convenience Stores",
            "type":"Retail Goods"
        }
    ],
    "sg:phone":"+1 519 735 9270",
    "sg:postcode":"N8R 1A5",
    "sg:province":"ON",
    "sg:tags":[
        "grocer"
    ],
    "wof:name":"M & M Meat Shops",
    "wof:placetype":"venue"
},
  "geometry": {"coordinates":[-82.9183425903,42.3139801025],"type":"Point"}
}