{
  "type": "Feature",
  "properties": {
    "addr:full":"NE 29-1-1W Altona MB R0G 0B0",
    "addr:postcode":"r0g 0b0",
    "addr:street":"Ne",
    "iso:country":"CA",
    "sg:address":"NE 29-1-1W",
    "sg:city":"Altona",
    "sg:classifiers":[
        {
            "category":"Retail",
            "subcategory":"Auto Repair",
            "type":"Services"
        }
    ],
    "sg:phone":"+1 204 324 6083",
    "sg:postcode":"R0G 0B0",
    "sg:province":"MB",
    "sg:tags":[
        "automobile",
        "customizing"
    ],
    "wof:name":"Touch of Gold",
    "wof:placetype":"venue"
},
  "geometry": {"coordinates":[-97.551216,49.103539],"type":"Point"}
}