{
  "type": "Feature",
  "properties": {
    "addr:full":"2068 Governors Rd Copetown ON L0R 1J0",
    "addr:housenumber":"2068",
    "addr:postcode":"l0r 1j0",
    "addr:street":"Governors Rd",
    "iso:country":"CA",
    "sg:address":"2068 Governors Rd",
    "sg:city":"Copetown",
    "sg:classifiers":[
        {
            "category":"Building & Trades",
            "subcategory":"Landscaping Services",
            "type":"Services"
        }
    ],
    "sg:phone":"+1 905 388 3364",
    "sg:postcode":"L0R 1J0",
    "sg:province":"ON",
    "sg:tags":[
        "tree"
    ],
    "wof:name":"Greenhow Tree Svc",
    "wof:placetype":"venue"
},
  "geometry": {"coordinates":[-80.05754852290001,43.2438278198],"type":"Point"}
}