{
  "type": "Feature",
  "properties": {
    "iso:country":"CA",
    "sg:address":"623 Mccowan Rd",
    "sg:city":"Scarborough",
    "sg:classifiers":[
        {
            "category":"Restaurant",
            "type":"Food & Drink"
        }
    ],
    "sg:phone":"+1 416 431 9155",
    "sg:postcode":"M1J 1K2",
    "sg:province":"ON",
    "wof:name":"Mc Cowan Fish & Chips",
    "wof:placetype":"venue"
},
  "geometry": {"coordinates":[-79.244301,43.753136],"type":"Point"}
}