{
  "type": "Feature",
  "properties": {
    "addr:full":"623 Mccowan Rd Scarborough ON M1J 1K2",
    "addr:housenumber":"623",
    "addr:postcode":"m1j 1k2",
    "addr:street":"Mccowan Rd",
    "iso:country":"CA",
    "sg:address":"623 Mccowan Rd",
    "sg:city":"Scarborough",
    "sg:classifiers":[
        {
            "category":"Restaurant",
            "type":"Food & Drink"
        }
    ],
    "sg:phone":"+1 416 431 9155",
    "sg:postcode":"M1J 1K2",
    "sg:province":"ON",
    "wof:name":"Mc Cowan Fish & Chips",
    "wof:placetype":"venue"
},
  "geometry": {"coordinates":[-79.24430099999999,43.753136],"type":"Point"}
}