{
  "type": "Feature",
  "properties": {
    "addr:full":"10411 90 St Fort St John BC V1J 6S6",
    "addr:housenumber":"10411",
    "addr:postcode":"v1j 6s6",
    "addr:street":"90 St",
    "iso:country":"CA",
    "sg:address":"10411 90 St",
    "sg:city":"Fort St John",
    "sg:classifiers":[
        {
            "category":"Building & Trades",
            "subcategory":"Plumbing",
            "type":"Services"
        }
    ],
    "sg:phone":"+1 250 785 2238",
    "sg:postcode":"V1J 6S6",
    "sg:province":"BC",
    "sg:tags":[
        "mechanical",
        "contractor"
    ],
    "wof:name":"Das Mechanical",
    "wof:placetype":"venue"
},
  "geometry": {"coordinates":[-120.82888031,56.2505187988],"type":"Point"}
}