{
  "type": "Feature",
  "properties": {
    "iso:country":"CA",
    "sg:city":"Winnipeg",
    "sg:classifiers":[
        {
            "category":"Retail",
            "subcategory":"Laundry & Dry Cleaning",
            "type":"Services"
        }
    ],
    "sg:phone":"+1 204 989 4950",
    "sg:postcode":"R3P 1V5",
    "sg:province":"MB",
    "sg:tags":[
        "cleaners"
    ],
    "wof:name":"Perth's",
    "wof:placetype":"venue"
},
  "geometry": {"coordinates":[-97.214516,49.866356],"type":"Point"}
}