{
  "type": "Feature",
  "properties": {
    "iso:country":"CA",
    "sg:address":"2917 28 Ave # 200",
    "sg:city":"Vernon",
    "sg:classifiers":[
        {
            "category":"Banks & Credit Unions",
            "subcategory":"Investment Brokerage",
            "type":"Services"
        }
    ],
    "sg:phone":"+1 250 549 3411",
    "sg:postcode":"V1T 8L1",
    "sg:province":"BC",
    "wof:name":"Scotia Mc Leod Inc",
    "wof:placetype":"venue"
},
  "geometry": {"coordinates":[-119.269493103,50.262336731],"type":"Point"}
}