{
  "type": "Feature",
  "properties": {
    "addr:full":"Old Kaleden Rd Okanagan Falls BC V0H 1R0",
    "addr:postcode":"v0h 1r0",
    "addr:street":"Kaleden Rd",
    "iso:country":"CA",
    "sg:address":"Old Kaleden Rd",
    "sg:city":"Okanagan Falls",
    "sg:classifiers":[
        {
            "category":"Farming",
            "subcategory":"Aquatic Farm",
            "type":"Manufacturing & Wholesale Goods"
        }
    ],
    "sg:phone":"+1 250 497 5156",
    "sg:postcode":"V0H 1R0",
    "sg:province":"BC",
    "sg:tags":[
        "hatchery",
        "fish"
    ],
    "wof:name":"Limespring Limited",
    "wof:placetype":"venue"
},
  "geometry": {"coordinates":[-119.571518,49.344383],"type":"Point"}
}