{
  "type": "Feature",
  "properties": {
    "addr:full":"Killarney MB R0K 1G0",
    "addr:postcode":"r0k 1g0",
    "iso:country":"CA",
    "sg:city":"Killarney",
    "sg:classifiers":[
        {
            "category":"Shopping",
            "subcategory":"Bicycles & Sporting Goods",
            "type":"Retail Goods"
        }
    ],
    "sg:phone":"+1 204 523 8839",
    "sg:postcode":"R0K 1G0",
    "sg:province":"MB",
    "sg:tags":[
        "gun",
        "gunsmith"
    ],
    "wof:name":"Bill's Gun Repair & Shooting",
    "wof:placetype":"venue"
},
  "geometry": {"coordinates":[-99.65715026860001,49.1804351807],"type":"Point"}
}