{
  "type": "Feature",
  "properties": {
    "addr:full":"1322 Rue Sainte-Julie Trois-Rivieres QC G9A 1Y6",
    "addr:housenumber":"1322",
    "addr:postcode":"g9a 1y6",
    "addr:street":"Rue Sainte-Julie Trois-Rivieres",
    "iso:country":"CA",
    "sg:address":"1322 Rue Sainte-Julie",
    "sg:city":"Trois-Rivieres",
    "sg:classifiers":[
        {
            "category":"Organizations",
            "subcategory":"Professional Association",
            "type":"Services"
        }
    ],
    "sg:phone":"+1 819 374 9566",
    "sg:postcode":"G9A 1Y6",
    "sg:province":"QC",
    "wof:name":"Association Des Handicapes",
    "wof:placetype":"venue"
},
  "geometry": {"coordinates":[-72.5496673584,46.3511123657],"type":"Point"}
}