{
  "type": "Feature",
  "properties": {
    "addr:full":"6404 Central Saanich Rd Victoria BC V8Z 5T7",
    "addr:housenumber":"6404",
    "addr:postcode":"v8z 5t7",
    "addr:street":"Central Saanich Rd",
    "iso:country":"CA",
    "sg:address":"6404 Central Saanich Rd",
    "sg:city":"Victoria",
    "sg:classifiers":[
        {
            "category":"Retail",
            "subcategory":"Animal Services",
            "type":"Services"
        }
    ],
    "sg:phone":"+1 250 652 1462",
    "sg:postcode":"V8Z 5T7",
    "sg:province":"BC",
    "sg:tags":[
        "center",
        "equestrian",
        "stable"
    ],
    "wof:name":"Westside Stables",
    "wof:placetype":"venue"
},
  "geometry": {"coordinates":[-123.36451700000001,48.428314],"type":"Point"}
}