{
  "type": "Feature",
  "properties": {
    "addr:full":"1142 Smythe St Fredericton NB E3B 3H5",
    "addr:housenumber":"1142",
    "addr:postcode":"e3b 3h5",
    "addr:street":"Smythe St",
    "iso:country":"CA",
    "sg:address":"1142 Smythe St",
    "sg:city":"Fredericton",
    "sg:classifiers":[
        {
            "category":"Banks & Credit Unions",
            "subcategory":"Bank",
            "type":"Services"
        }
    ],
    "sg:phone":"+1 506 458 8774",
    "sg:postcode":"E3B 3H5",
    "sg:province":"NB",
    "wof:name":"Cibc",
    "wof:placetype":"venue"
},
  "geometry": {"coordinates":[-66.6682357788,45.9439888],"type":"Point"}
}