{
  "type": "Feature",
  "properties": {
    "addr:full":"1281 Speers Rd Oakville ON L6L 2X5",
    "addr:housenumber":"1281",
    "addr:postcode":"l6l 2x5",
    "addr:street":"Speers Rd",
    "iso:country":"CA",
    "sg:address":"1281 Speers Rd",
    "sg:city":"Oakville",
    "sg:classifiers":[
        {
            "category":"Building & Trades",
            "subcategory":"Equipment Rental",
            "type":"Services"
        }
    ],
    "sg:phone":"+1 905 825 0544",
    "sg:postcode":"L6L 2X5",
    "sg:province":"ON",
    "sg:tags":[
        "yard",
        "scaffolding"
    ],
    "wof:name":"Steeplejack Services",
    "wof:placetype":"venue"
},
  "geometry": {"coordinates":[-79.710266,43.426186],"type":"Point"}
}