{
  "type": "Feature",
  "properties": {
    "iso:country":"CA",
    "sg:address":"1281 Speers Rd",
    "sg:city":"Oakville",
    "sg:classifiers":[
        {
            "category":"Building & Trades",
            "subcategory":"Equipment Rental",
            "type":"Services"
        }
    ],
    "sg:phone":"+1 905 825 0544",
    "sg:postcode":"L6L 2X5",
    "sg:province":"ON",
    "sg:tags":[
        "yard",
        "scaffolding"
    ],
    "wof:name":"Steeplejack Services",
    "wof:placetype":"venue"
},
  "geometry": {"coordinates":[-79.710266,43.426186],"type":"Point"}
}