{
  "type": "Feature",
  "properties": {
    "addr:full":"160 Main St Sussex NB E4E 3E2",
    "addr:housenumber":"160",
    "addr:postcode":"e4e 3e2",
    "addr:street":"Main St",
    "iso:country":"CA",
    "sg:address":"160 Main St",
    "sg:city":"Sussex",
    "sg:classifiers":[
        {
            "category":"Restaurant",
            "type":"Food & Drink"
        }
    ],
    "sg:phone":"+1 506 432 6677",
    "sg:postcode":"E4E 3E2",
    "sg:province":"NB",
    "wof:name":"Mc Donald's",
    "wof:placetype":"venue"
},
  "geometry": {"coordinates":[-65.525757,45.724674],"type":"Point"}
}