{
  "type": "Feature",
  "properties": {
    "addr:full":"2810 Bremner Ave Red Deer AB T4R 1M9",
    "addr:housenumber":"2810",
    "addr:postcode":"t4r 1m9",
    "addr:street":"Bremner Ave",
    "iso:country":"CA",
    "sg:address":"2810 Bremner Ave",
    "sg:city":"Red Deer",
    "sg:classifiers":[
        {
            "category":"Bars & Pubs",
            "type":"Food & Drink"
        }
    ],
    "sg:phone":"+1 403 348 0400",
    "sg:postcode":"T4R 1M9",
    "sg:province":"AB",
    "wof:name":"Jim & Jer's Pub",
    "wof:placetype":"venue"
},
  "geometry": {"coordinates":[-113.810333,52.245644],"type":"Point"}
}