{
  "type": "Feature",
  "properties": {
    "iso:country":"CA",
    "sg:address":"10910 Av DE Cobourg",
    "sg:city":"Montreal-Nord",
    "sg:classifiers":[
        {
            "category":"Building & Trades",
            "subcategory":"Construction",
            "type":"Services"
        }
    ],
    "sg:phone":"+1 514 324 6671",
    "sg:postcode":"H1H 4X4",
    "sg:province":"QC",
    "sg:tags":[
        "tile",
        "repairing",
        "remodeling",
        "contractor"
    ],
    "wof:name":"Dominique Tuile Enrg",
    "wof:placetype":"venue"
},
  "geometry": {"coordinates":[-73.6455612183,45.5871276855],"type":"Point"}
}