{
  "type": "Feature",
  "properties": {
    "addr:full":"Hamilton ON L9C 2Z9",
    "addr:postcode":"l9c 2z9",
    "iso:country":"CA",
    "sg:city":"Hamilton",
    "sg:classifiers":[
        {
            "category":"Professional",
            "subcategory":"Business Services",
            "type":"Services"
        }
    ],
    "sg:phone":"+1 905 387 3377",
    "sg:postcode":"L9C 2Z9",
    "sg:province":"ON",
    "sg:tags":[
        "recording",
        "studio"
    ],
    "wof:name":"Swordfish Digital Audio",
    "wof:placetype":"venue"
},
  "geometry": {"coordinates":[-79.88078299999999,43.231319],"type":"Point"}
}