{
  "type": "Feature",
  "properties": {
    "addr:full":"502 5 Ave S Lethbridge AB T1J 0T8",
    "addr:housenumber":"502",
    "addr:postcode":"t1j 0t8",
    "addr:street":"5 Ave S",
    "iso:country":"CA",
    "sg:address":"502 5 Ave S",
    "sg:city":"Lethbridge",
    "sg:classifiers":[
        {
            "category":"Insurance",
            "subcategory":"Insurance Agent",
            "type":"Services"
        }
    ],
    "sg:phone":"+1 403 382 2820",
    "sg:postcode":"T1J 0T8",
    "sg:province":"AB",
    "wof:name":"CO-Operators General Insurance",
    "wof:placetype":"venue"
},
  "geometry": {"coordinates":[-112.83978999999999,49.692688],"type":"Point"}
}