{
  "type": "Feature",
  "properties": {
    "addr:full":"2315 Eva Chase BC V0E 1M0",
    "addr:housenumber":"2315",
    "addr:postcode":"bc v0e 1m0",
    "addr:street":"Eva Chase",
    "iso:country":"CA",
    "sg:address":"2315 Eva",
    "sg:city":"Chase",
    "sg:classifiers":[
        {
            "category":"Building & Trades",
            "subcategory":"Electrical",
            "type":"Services"
        }
    ],
    "sg:phone":"+1 250 679 3352",
    "sg:postcode":"V0E 1M0",
    "sg:province":"BC",
    "sg:tags":[
        "electric",
        "contractor"
    ],
    "wof:name":"Quantal Electric",
    "wof:placetype":"venue"
},
  "geometry": {"coordinates":[-119.684303,50.816067],"type":"Point"}
}