{
  "type": "Feature",
  "properties": {
    "addr:full":"43 Myrtle St St Thomas ON N5R 2E6",
    "addr:housenumber":"43",
    "addr:postcode":"n5r 2e6",
    "addr:street":"Myrtle St",
    "iso:country":"CA",
    "sg:address":"43 Myrtle St",
    "sg:city":"St Thomas",
    "sg:classifiers":[
        {
            "category":"Education",
            "subcategory":"School",
            "type":"Public Place"
        }
    ],
    "sg:phone":"+1 519 631 4940",
    "sg:postcode":"N5R 2E6",
    "sg:province":"ON",
    "wof:name":"Myrtle Elementary School",
    "wof:placetype":"venue"
},
  "geometry": {"coordinates":[-81.186539,42.772362],"type":"Point"}
}