{
  "type": "Feature",
  "properties": {
    "addr:full":"Nickorick Beach Wakaw SK S0K 4P0",
    "addr:postcode":"s0k 4p0",
    "iso:country":"CA",
    "sg:address":"Nickorick Beach",
    "sg:city":"Wakaw",
    "sg:classifiers":[
        {
            "category":"Insurance",
            "subcategory":"Insurance Agent",
            "type":"Services"
        }
    ],
    "sg:phone":"+1 306 233 5500",
    "sg:postcode":"S0K 4P0",
    "sg:province":"SK",
    "wof:name":"Prince Albert Insurance Ltd",
    "wof:placetype":"venue"
},
  "geometry": {"coordinates":[-105.74270629900001,52.6529502869],"type":"Point"}
}