{
  "type": "Feature",
  "properties": {
    "addr:full":"180 Boul Hebert Edmundston NB E3V 2S7",
    "addr:housenumber":"180",
    "addr:postcode":"e3v 2s7",
    "addr:street":"Boul Hebert",
    "iso:country":"CA",
    "sg:address":"180 Boul Hebert",
    "sg:city":"Edmundston",
    "sg:classifiers":[
        {
            "category":"Shopping",
            "type":"Retail Goods"
        }
    ],
    "sg:phone":"+1 506 735 6481",
    "sg:postcode":"E3V 2S7",
    "sg:province":"NB",
    "sg:tags":[
        "religious"
    ],
    "wof:name":"Boutique Lumiere & Verite",
    "wof:placetype":"venue"
},
  "geometry": {"coordinates":[-68.316116333,47.3734664917],"type":"Point"}
}