{
  "type": "Feature",
  "properties": {
    "iso:country":"CA",
    "sg:city":"Grande Prairie",
    "sg:classifiers":[
        {
            "category":"Home & Garden",
            "subcategory":"Carpets & Floor Coverings",
            "type":"Retail Goods"
        }
    ],
    "sg:phone":"+1 780 513 2182",
    "sg:postcode":"T8V 1L7",
    "sg:province":"AB",
    "sg:tags":[
        "material"
    ],
    "wof:name":"T & R Hardwood Flooring",
    "wof:placetype":"venue"
},
  "geometry": {"coordinates":[-118.79549408,55.17735672],"type":"Point"}
}