{
  "type": "Feature",
  "properties": {
    "addr:full":"Calgary AB T2H 0T3",
    "addr:postcode":"t2h 0t3",
    "iso:country":"CA",
    "sg:city":"Calgary",
    "sg:classifiers":[
        {
            "category":"Building & Trades",
            "subcategory":"Construction",
            "type":"Services"
        }
    ],
    "sg:phone":"+1 403 251 2556",
    "sg:postcode":"T2H 0T3",
    "sg:province":"AB",
    "sg:tags":[
        "insulation",
        "heat",
        "contractor"
    ],
    "wof:name":"Albrico Services Ltd",
    "wof:placetype":"venue"
},
  "geometry": {"coordinates":[-114.062904,50.99192],"type":"Point"}
}