{
  "type": "Feature",
  "properties": {
    "addr:full":"Summerland BC V0H 1Z0",
    "addr:postcode":"v0h 1z0",
    "iso:country":"CA",
    "sg:city":"Summerland",
    "sg:classifiers":[
        {
            "category":"Restaurant",
            "type":"Food & Drink"
        }
    ],
    "sg:phone":"+1 250 494 1000",
    "sg:postcode":"V0H 1Z0",
    "sg:province":"BC",
    "sg:tags":[
        "pizza"
    ],
    "wof:name":"Prima Pizza",
    "wof:placetype":"venue"
},
  "geometry": {"coordinates":[-119.681030273,49.6015014648],"type":"Point"}
}