{
  "type": "Feature",
  "properties": {
    "addr:full":"431 Albert St Renfrew ON K7V 1V8",
    "addr:housenumber":"431",
    "addr:postcode":"k7v 1v8",
    "addr:street":"Albert St",
    "iso:country":"CA",
    "sg:address":"431 Albert St",
    "sg:city":"Renfrew",
    "sg:classifiers":[
        {
            "category":"Organizations",
            "subcategory":"Religious Organization",
            "type":"Services"
        }
    ],
    "sg:phone":"+1 613 432 7607",
    "sg:postcode":"K7V 1V8",
    "sg:province":"ON",
    "sg:tags":[
        "church"
    ],
    "wof:name":"Christian Reform Church",
    "wof:placetype":"venue"
},
  "geometry": {"coordinates":[-76.6969299316,45.4805526733],"type":"Point"}
}