{
  "type": "Feature",
  "properties": {
    "iso:country":"CA",
    "sg:address":"1037 Spinney Dr",
    "sg:city":"Dawson Creek",
    "sg:classifiers":[
        {
            "category":"Building & Trades",
            "subcategory":"Electrical",
            "type":"Services"
        }
    ],
    "sg:phone":"+1 250 782 4662",
    "sg:postcode":"V1G 1S6",
    "sg:province":"BC",
    "sg:tags":[
        "electric",
        "contractor"
    ],
    "wof:name":"Mile O Electric",
    "wof:placetype":"venue"
},
  "geometry": {"coordinates":[-120.22893524200001,55.7636642456],"type":"Point"}
}