{
  "type": "Feature",
  "properties": {
    "iso:country":"CA",
    "sg:address":"3975 Rue Notre-Dame O",
    "sg:city":"Montreal",
    "sg:classifiers":[
        {
            "category":"Organizations",
            "subcategory":"Religious Organization",
            "type":"Services"
        }
    ],
    "sg:phone":"+1 514 931 2838",
    "sg:postcode":"H4C 1R2",
    "sg:province":"QC",
    "wof:name":"Alpha & Omega Ministries",
    "wof:placetype":"venue"
},
  "geometry": {"coordinates":[-73.53430175779999,45.54662323],"type":"Point"}
}