{
  "type": "Feature",
  "properties": {
    "addr:full":"4090 Westview Ave Powell River BC V8A 3H8",
    "addr:housenumber":"4090",
    "addr:postcode":"v8a 3h8",
    "addr:street":"Westview Ave Powell",
    "iso:country":"CA",
    "sg:address":"4090 Westview Ave",
    "sg:city":"Powell River",
    "sg:classifiers":[
        {
            "category":"Professional",
            "subcategory":"Accounting & Tax Preparation",
            "type":"Services"
        }
    ],
    "sg:phone":"+1 604 485 2617",
    "sg:postcode":"V8A 3H8",
    "sg:province":"BC",
    "sg:tags":[
        "accountant"
    ],
    "wof:name":"Knight Bookkeeping Svc",
    "wof:placetype":"venue"
},
  "geometry": {"coordinates":[-124.515357971,49.8259162903],"type":"Point"}
}