{
  "type": "Feature",
  "properties": {
    "addr:full":"365 Rue Soumande Vanier QC G1M 1A5",
    "addr:housenumber":"365",
    "addr:postcode":"g1m 1a5",
    "addr:street":"Rue Soumande",
    "iso:country":"CA",
    "sg:address":"365 Rue Soumande",
    "sg:city":"Vanier",
    "sg:classifiers":[
        {
            "category":"Shopping",
            "subcategory":"Gifts & Souvenirs",
            "type":"Retail Goods"
        }
    ],
    "sg:phone":"+1 418 681 0644",
    "sg:postcode":"G1M 1A5",
    "sg:province":"QC",
    "sg:tags":[
        "shop",
        "party",
        "fabric",
        "supply"
    ],
    "wof:name":"Bou Clair Inc",
    "wof:placetype":"venue"
},
  "geometry": {"coordinates":[-71.2542877197,46.8202362061],"type":"Point"}
}