{
  "type": "Feature",
  "properties": {
    "addr:full":"165 Rue Saint-Joseph E Quebec QC G1K 3A8",
    "addr:housenumber":"165",
    "addr:postcode":"g1k 3a8",
    "addr:street":"Rue Saint-Joseph E",
    "iso:country":"CA",
    "sg:address":"165 Rue Saint-Joseph E",
    "sg:city":"Quebec",
    "sg:classifiers":[
        {
            "category":"Personal",
            "subcategory":"Beauty Salon",
            "type":"Services"
        }
    ],
    "sg:phone":"+1 418 524 5783",
    "sg:postcode":"G1K 3A8",
    "sg:province":"QC",
    "wof:name":"Salon Continental",
    "wof:placetype":"venue"
},
  "geometry": {"coordinates":[-71.228905,46.812691],"type":"Point"}
}