{
  "type": "Feature",
  "properties": {
    "addr:full":"12520 Vickers Way Richmond BC V6V 1H9",
    "addr:housenumber":"12520",
    "addr:postcode":"v6v 1h9",
    "addr:street":"Vickers Way",
    "iso:country":"CA",
    "sg:address":"12520 Vickers Way",
    "sg:city":"Richmond",
    "sg:classifiers":[
        {
            "category":"Retail",
            "subcategory":"Auto Repair",
            "type":"Services"
        }
    ],
    "sg:phone":"+1 604 278 1111",
    "sg:postcode":"V6V 1H9",
    "sg:province":"BC",
    "sg:tags":[
        "repairing",
        "automobile"
    ],
    "wof:name":"Premier Transmissions",
    "wof:placetype":"venue"
},
  "geometry": {"coordinates":[-123.085006714,49.1911621094],"type":"Point"}
}