{
  "type": "Feature",
  "properties": {
    "addr:full":"130 Waverly Rd Bowmanville ON L1C 3W9",
    "addr:housenumber":"130",
    "addr:postcode":"l1c 3w9",
    "addr:street":"Waverly Rd",
    "iso:country":"CA",
    "sg:address":"130 Waverly Rd",
    "sg:city":"Bowmanville",
    "sg:classifiers":[
        {
            "category":"Shopping",
            "subcategory":"Pharmacy",
            "type":"Retail Goods"
        }
    ],
    "sg:phone":"+1 905 623 2333",
    "sg:postcode":"L1C 3W9",
    "sg:province":"ON",
    "wof:name":"Global Drug Mart",
    "wof:placetype":"venue"
},
  "geometry": {"coordinates":[-78.6922531128,43.9013633728],"type":"Point"}
}