{
  "type": "Feature",
  "properties": {
    "addr:full":"1698 156 St Surrey BC V4A 4T1",
    "addr:housenumber":"1698",
    "addr:postcode":"v4a 4t1",
    "addr:street":"156 St",
    "iso:country":"CA",
    "sg:address":"1698 156 St",
    "sg:city":"Surrey",
    "sg:classifiers":[
        {
            "category":"Social Services",
            "subcategory":"Child Care",
            "type":"Services"
        }
    ],
    "sg:phone":"+1 604 536 4346",
    "sg:postcode":"V4A 4T1",
    "sg:province":"BC",
    "wof:name":"Rainbow Park Preschool Ltd",
    "wof:placetype":"venue"
},
  "geometry": {"coordinates":[-122.790054321,49.0327720642],"type":"Point"}
}