{
  "type": "Feature",
  "properties": {
    "addr:full":"9022 109 St Grande Prairie AB T8V 4K8",
    "addr:housenumber":"9022",
    "addr:postcode":"t8v 4k8",
    "addr:street":"109 St",
    "iso:country":"CA",
    "sg:address":"9022 109 St",
    "sg:city":"Grande Prairie",
    "sg:classifiers":[
        {
            "category":"Building & Trades",
            "subcategory":"Plumbing",
            "type":"Services"
        }
    ],
    "sg:phone":"+1 780 814 0681",
    "sg:postcode":"T8V 4K8",
    "sg:province":"AB",
    "sg:tags":[
        "heating",
        "contractor"
    ],
    "wof:name":"Acme Hvac Svc",
    "wof:placetype":"venue"
},
  "geometry": {"coordinates":[-118.823502,55.161922],"type":"Point"}
}