{
  "type": "Feature",
  "properties": {
    "addr:full":"Saint-Elie QC G0X 2N0",
    "addr:postcode":"g0x 2n0",
    "iso:country":"CA",
    "sg:city":"Saint-Elie",
    "sg:classifiers":[
        {
            "category":"Building & Trades",
            "subcategory":"Construction",
            "type":"Services"
        }
    ],
    "sg:phone":"+1 819 221 5291",
    "sg:postcode":"G0X 2N0",
    "sg:province":"QC",
    "sg:tags":[
        "masonry",
        "contractor"
    ],
    "wof:name":"Hilibert Come Maconnerie",
    "wof:placetype":"venue"
},
  "geometry": {"coordinates":[-72.9540634155,46.4865455627],"type":"Point"}
}