{
  "type": "Feature",
  "properties": {
    "addr:full":"15 Main St Brighton ON K0K 1H0",
    "addr:housenumber":"15",
    "addr:postcode":"k0k 1h0",
    "addr:street":"Main St",
    "iso:country":"CA",
    "sg:address":"15 Main St",
    "sg:city":"Brighton",
    "sg:classifiers":[
        {
            "category":"Shopping",
            "subcategory":"Used Merchandise",
            "type":"Retail Goods"
        }
    ],
    "sg:phone":"+1 613 475 0003",
    "sg:postcode":"K0K 1H0",
    "sg:province":"ON",
    "sg:tags":[
        "antique"
    ],
    "wof:name":"Main Street Market",
    "wof:placetype":"venue"
},
  "geometry": {"coordinates":[-77.73741099999999,44.041969],"type":"Point"}
}