{
  "type": "Feature",
  "properties": {
    "addr:full":"800 Griffiths Way # 10 Vancouver BC V6B 6G1",
    "addr:housenumber":"800",
    "addr:postcode":"bc v6b 6g1",
    "addr:street":"Griffiths Way # 10",
    "iso:country":"CA",
    "sg:address":"800 Griffiths Way # 10",
    "sg:city":"Vancouver",
    "sg:classifiers":[
        {
            "category":"Arena",
            "subcategory":"Sports Club",
            "type":"Entertainment"
        }
    ],
    "sg:phone":"+1 604 899 7400",
    "sg:postcode":"V6B 6G1",
    "sg:province":"BC",
    "sg:tags":[
        "athletic",
        "marketing",
        "program",
        "stadium",
        "fields"
    ],
    "wof:name":"General Motors Place",
    "wof:placetype":"venue"
},
  "geometry": {"coordinates":[-123.11013,49.277798],"type":"Point"}
}