{
  "type": "Feature",
  "properties": {
    "iso:country":"CA",
    "sg:address":"33 Rue Prud'Homme E",
    "sg:city":"Saint-Remi",
    "sg:classifiers":[
        {
            "category":"Shopping",
            "subcategory":"Clothing, Apparel, & Fashions",
            "type":"Retail Goods"
        }
    ],
    "sg:phone":"+1 450 454 9847",
    "sg:postcode":"J0L 2L0",
    "sg:province":"QC",
    "sg:tags":[
        "boutique"
    ],
    "wof:name":"Lingerie Gauthier",
    "wof:placetype":"venue"
},
  "geometry": {"coordinates":[-73.6164932251,45.2612304688],"type":"Point"}
}