{
  "type": "Feature",
  "properties": {
    "addr:full":"Sainte-Helene-DE-Kamouraska QC G0L 3J0",
    "addr:postcode":"g0l 3j0",
    "iso:country":"CA",
    "sg:city":"Sainte-Helene-DE-Kamouraska",
    "sg:classifiers":[
        {
            "category":"Building & Trades",
            "subcategory":"Construction",
            "type":"Services"
        }
    ],
    "sg:phone":"+1 418 492 6513",
    "sg:postcode":"G0L 3J0",
    "sg:province":"QC",
    "sg:tags":[
        "excavating",
        "contractor"
    ],
    "wof:name":"Dionne, Gilles",
    "wof:placetype":"venue"
},
  "geometry": {"coordinates":[-69.86264801030001,47.5639762878],"type":"Point"}
}