{
  "type": "Feature",
  "properties": {
    "addr:full":"64 Av Dallaire Rouyn-Noranda QC J9X 4S7",
    "addr:postcode":"j9x 4s7",
    "addr:street":"64 Av Dallaire",
    "iso:country":"CA",
    "sg:address":"64 Av Dallaire",
    "sg:city":"Rouyn-Noranda",
    "sg:classifiers":[
        {
            "category":"Real Estate",
            "subcategory":"Surveying",
            "type":"Services"
        }
    ],
    "sg:phone":"+1 819 797 6330",
    "sg:postcode":"J9X 4S7",
    "sg:province":"QC",
    "sg:tags":[
        "surveyor"
    ],
    "wof:name":"Polygone Enr",
    "wof:placetype":"venue"
},
  "geometry": {"coordinates":[-79.022705,48.241215],"type":"Point"}
}