{
  "type": "Feature",
  "properties": {
    "addr:full":"1310 Grand Marais Rd W Windsor ON N9E 1E4",
    "addr:housenumber":"1310",
    "addr:postcode":"n9e 1e4",
    "addr:street":"Grand Marais Rd W",
    "iso:country":"CA",
    "sg:address":"1310 Grand Marais Rd W",
    "sg:city":"Windsor",
    "sg:classifiers":[
        {
            "category":"Education",
            "subcategory":"Library",
            "type":"Public Place"
        }
    ],
    "sg:phone":"+1 519 969 5880",
    "sg:postcode":"N9E 1E4",
    "sg:province":"ON",
    "wof:name":"Nikola Budmir Library",
    "wof:placetype":"venue"
},
  "geometry": {"coordinates":[-83.0262145996,42.2683448792],"type":"Point"}
}