{
  "type": "Feature",
  "properties": {
    "addr:full":"Victoria BC V8Z 3G3",
    "addr:postcode":"v8z 3g3",
    "iso:country":"CA",
    "sg:city":"Victoria",
    "sg:classifiers":[
        {
            "category":"Retail",
            "subcategory":"Animal Services",
            "type":"Services"
        }
    ],
    "sg:phone":"+1 250 727 3040",
    "sg:postcode":"V8Z 3G3",
    "sg:province":"BC",
    "sg:tags":[
        "pet",
        "grooming",
        "washing"
    ],
    "wof:name":"All Fur Paws Pet Spa",
    "wof:placetype":"venue"
},
  "geometry": {"coordinates":[-123.364517212,48.428314209],"type":"Point"}
}