{
  "type": "Feature",
  "properties": {
    "addr:full":"PO Box 218 Bashaw AB T0B 0H0",
    "addr:housenumber":"po",
    "addr:postcode":"t0b 0h0",
    "addr:street":"Box 218 Bashaw",
    "iso:country":"CA",
    "sg:address":"PO Box 218",
    "sg:city":"Bashaw",
    "sg:classifiers":[
        {
            "category":"Professional",
            "subcategory":"Engineering",
            "type":"Services"
        }
    ],
    "sg:phone":"+1 780 877 3922",
    "sg:postcode":"T0B 0H0",
    "sg:province":"AB",
    "sg:tags":[
        "engineer"
    ],
    "wof:name":"Stremco Engineering Ltd",
    "wof:placetype":"venue"
},
  "geometry": {"coordinates":[-112.970879,52.583778],"type":"Point"}
}