{
  "type": "Feature",
  "properties": {
    "addr:full":"129 Rue Principale Saint-Jacques NB E7B 1V6",
    "addr:housenumber":"129",
    "addr:postcode":"e7b 1v6",
    "addr:street":"Rue Principale",
    "iso:country":"CA",
    "sg:address":"129 Rue Principale",
    "sg:city":"Saint-Jacques",
    "sg:classifiers":[
        {
            "category":"Retail",
            "subcategory":"Auto Repair",
            "type":"Services"
        }
    ],
    "sg:phone":"+1 506 735 7804",
    "sg:postcode":"E7B 1V6",
    "sg:province":"NB",
    "sg:tags":[
        "repairing",
        "automobile"
    ],
    "wof:name":"Dionne Garage Ltee",
    "wof:placetype":"venue"
},
  "geometry": {"coordinates":[-68.37744903559999,47.4183998108],"type":"Point"}
}