{
  "type": "Feature",
  "properties": {
    "addr:full":"Industrial Rd Bowsman MB R0L 0H0",
    "addr:postcode":"r0l 0h0",
    "addr:street":"Industrial Rd",
    "iso:country":"CA",
    "sg:address":"Industrial Rd",
    "sg:city":"Bowsman",
    "sg:classifiers":[
        {
            "category":"Freight",
            "type":"Transportation"
        }
    ],
    "sg:phone":"+1 204 238 4321",
    "sg:postcode":"R0L 0H0",
    "sg:province":"MB",
    "sg:tags":[
        "grain",
        "elevator"
    ],
    "wof:name":"Agricore United",
    "wof:placetype":"venue"
},
  "geometry": {"coordinates":[-101.216812,52.235847],"type":"Point"}
}