{
  "type": "Feature",
  "properties": {
    "iso:country":"CA",
    "sg:city":"Souris",
    "sg:classifiers":[
        {
            "category":"Farming",
            "subcategory":"Farm & Veterinary Services",
            "type":"Manufacturing & Wholesale Goods"
        }
    ],
    "sg:phone":"+1 204 483 7333",
    "sg:postcode":"R0K 2C0",
    "sg:province":"MB",
    "sg:tags":[
        "seed",
        "grain",
        "cleaning"
    ],
    "wof:name":"Prairie Sun Seeds Ltd",
    "wof:placetype":"venue"
},
  "geometry": {"coordinates":[-100.256264,49.620827],"type":"Point"}
}