{
  "type": "Feature",
  "properties": {
    "addr:full":"314 Macbeth Cres West Vancouver BC V7T 1V7",
    "addr:housenumber":"314",
    "addr:postcode":"v7t 1v7",
    "addr:street":"Macbeth Cres",
    "iso:country":"CA",
    "sg:address":"314 Macbeth Cres",
    "sg:city":"West Vancouver",
    "sg:classifiers":[
        {
            "category":"Building & Trades",
            "subcategory":"Landscaping Services",
            "type":"Services"
        }
    ],
    "sg:phone":"+1 604 926 3662",
    "sg:postcode":"V7T 1V7",
    "sg:province":"BC",
    "sg:tags":[
        "tree"
    ],
    "wof:name":"Streamside Tree Svc Ltd",
    "wof:placetype":"venue"
},
  "geometry": {"coordinates":[-123.12505299999999,49.333511],"type":"Point"}
}