{
  "type": "Feature",
  "properties": {
    "iso:country":"CA",
    "sg:address":"1730 Gardenbriar Rd",
    "sg:city":"Thunder Bay",
    "sg:classifiers":[
        {
            "category":"Building & Trades",
            "subcategory":"Construction",
            "type":"Services"
        }
    ],
    "sg:phone":"+1 807 577 4372",
    "sg:postcode":"P7K 1E2",
    "sg:province":"ON",
    "sg:tags":[
        "painter"
    ],
    "wof:name":"Jerry Latus Painting",
    "wof:placetype":"venue"
},
  "geometry": {"coordinates":[-89.3410873413,48.3842315674],"type":"Point"}
}