{
  "type": "Feature",
  "properties": {
    "addr:full":"936 Broadview Ave Toronto ON M4K 2R1",
    "addr:housenumber":"936",
    "addr:postcode":"m4k 2r1",
    "addr:street":"Broadview Ave",
    "iso:country":"CA",
    "sg:address":"936 Broadview Ave",
    "sg:city":"Toronto",
    "sg:classifiers":[
        {
            "category":"Retail",
            "subcategory":"Laundry & Dry Cleaning",
            "type":"Services"
        }
    ],
    "sg:phone":"+1 416 466 9736",
    "sg:postcode":"M4K 2R1",
    "sg:province":"ON",
    "sg:tags":[
        "cleaners"
    ],
    "wof:name":"Broadview Dry Cleaners",
    "wof:placetype":"venue"
},
  "geometry": {"coordinates":[-79.3578262329,43.6811752319],"type":"Point"}
}