{
  "type": "Feature",
  "properties": {
    "addr:full":"13030 St Albert Trail NW Edmonton AB T5L 4Y6",
    "addr:housenumber":"13030",
    "addr:postcode":"t5l 4y6",
    "addr:street":"St Albert Trail Nw",
    "iso:country":"CA",
    "sg:address":"13030 St Albert Trail NW",
    "sg:city":"Edmonton",
    "sg:classifiers":[
        {
            "category":"Home & Garden",
            "subcategory":"Furniture",
            "type":"Retail Goods"
        }
    ],
    "sg:phone":"+1 780 488 9200",
    "sg:postcode":"T5L 4Y6",
    "sg:province":"AB",
    "wof:name":"Sofa Land",
    "wof:placetype":"venue"
},
  "geometry": {"coordinates":[-113.56512499999999,53.589684],"type":"Point"}
}