{
  "type": "Feature",
  "properties": {
    "addr:full":"46467 Riverside Dr Chilliwack BC V2P 3L7",
    "addr:housenumber":"46467",
    "addr:postcode":"v2p 3l7",
    "addr:street":"Riverside Dr",
    "iso:country":"CA",
    "sg:address":"46467 Riverside Dr",
    "sg:city":"Chilliwack",
    "sg:classifiers":[
        {
            "category":"Personal",
            "subcategory":"Shoe Repair & Shine",
            "type":"Services"
        }
    ],
    "sg:phone":"+1 604 795 2340",
    "sg:postcode":"V2P 3L7",
    "sg:province":"BC",
    "sg:tags":[
        "repairing",
        "boot"
    ],
    "wof:name":"Pat's Quality Shoe Repair",
    "wof:placetype":"venue"
},
  "geometry": {"coordinates":[-121.938805,49.180767],"type":"Point"}
}