{
  "type": "Feature",
  "properties": {
    "addr:full":"9814 Willow St Chemainus BC V0R 1K0",
    "addr:housenumber":"9814",
    "addr:postcode":"v0r 1k0",
    "addr:street":"Willow St",
    "iso:country":"CA",
    "sg:address":"9814 Willow St",
    "sg:city":"Chemainus",
    "sg:classifiers":[
        {
            "category":"Organizations",
            "subcategory":"Religious Organization",
            "type":"Services"
        }
    ],
    "sg:phone":"+1 250 246 3463",
    "sg:postcode":"V0R 1K0",
    "sg:province":"BC",
    "sg:tags":[
        "church"
    ],
    "wof:name":"Chemainus United Church",
    "wof:placetype":"venue"
},
  "geometry": {"coordinates":[-123.718742371,48.9238586426],"type":"Point"}
}