{
  "type": "Feature",
  "properties": {
    "addr:full":"1 Keewatin Dr Moosonee ON P0L 1Y0",
    "addr:housenumber":"1",
    "addr:postcode":"p0l 1y0",
    "addr:street":"Keewatin Dr",
    "iso:country":"CA",
    "sg:address":"1 Keewatin Dr",
    "sg:city":"Moosonee",
    "sg:classifiers":[
        {
            "category":"Education",
            "subcategory":"School",
            "type":"Public Place"
        }
    ],
    "sg:phone":"+1 705 336 2903",
    "sg:postcode":"P0L 1Y0",
    "sg:province":"ON",
    "sg:tags":[
        "boards"
    ],
    "wof:name":"James Bay Lowlands Scdry Sclbd",
    "wof:placetype":"venue"
},
  "geometry": {"coordinates":[-80.640625,51.273418],"type":"Point"}
}