{
  "type": "Feature",
  "properties": {
    "addr:full":"1220 Rue Peel Montreal QC H3B 2T6",
    "addr:housenumber":"1220",
    "addr:postcode":"h3b 2t6",
    "addr:street":"Rue Peel",
    "iso:country":"CA",
    "sg:address":"1220 Rue Peel",
    "sg:city":"Montreal",
    "sg:classifiers":[
        {
            "category":"Organizations",
            "subcategory":"Professional Association",
            "type":"Services"
        }
    ],
    "sg:phone":"+1 514 878 9798",
    "sg:postcode":"H3B 2T6",
    "sg:province":"QC",
    "wof:name":"Centre Espagnol Culturel Inc",
    "wof:placetype":"venue"
},
  "geometry": {"coordinates":[-73.572303772,45.4996147156],"type":"Point"}
}