{
  "type": "Feature",
  "properties": {
    "addr:full":"1505 27E Rue Quebec QC G1J 1C1",
    "addr:housenumber":"1505",
    "addr:postcode":"g1j 1c1",
    "addr:street":"27E Rue Quebec",
    "iso:country":"CA",
    "sg:address":"1505 27E Rue",
    "sg:city":"Quebec",
    "sg:classifiers":[
        {
            "category":"Personal",
            "subcategory":"Beauty Salon",
            "type":"Services"
        }
    ],
    "sg:phone":"+1 418 523 7506",
    "sg:postcode":"G1J 1C1",
    "sg:province":"QC",
    "wof:name":"Salon Michel Villeneuve",
    "wof:placetype":"venue"
},
  "geometry": {"coordinates":[-71.2351608276,46.8452377319],"type":"Point"}
}