{
  "type": "Feature",
  "properties": {
    "addr:full":"370 Broadway E #123 Vancouver BC V5T 4G5",
    "addr:housenumber":"370",
    "addr:postcode":"v5t 4g5",
    "addr:street":"Broadway E # 123",
    "iso:country":"CA",
    "sg:address":"370 Broadway E #123",
    "sg:city":"Vancouver",
    "sg:classifiers":[
        {
            "category":"Food & Beverages",
            "subcategory":"Liquor & Beverages",
            "type":"Retail Goods"
        }
    ],
    "sg:phone":"+1 604 660 6675",
    "sg:postcode":"V5T 4G5",
    "sg:province":"BC",
    "sg:tags":[
        "store"
    ],
    "wof:name":"Vancouver Liquor Stores-Govt",
    "wof:placetype":"venue"
},
  "geometry": {"coordinates":[-123.097206116,49.262714386],"type":"Point"}
}