{
  "type": "Feature",
  "properties": {
    "addr:full":"5252 Rue Jean-Talon O Montreal QC H4P 1X3",
    "addr:housenumber":"5252",
    "addr:postcode":"h4p 1x3",
    "addr:street":"Rue Jean-Talon O",
    "iso:country":"CA",
    "sg:address":"5252 Rue Jean-Talon O",
    "sg:city":"Montreal",
    "sg:classifiers":[
        {
            "category":"Restaurant",
            "type":"Food & Drink"
        }
    ],
    "sg:phone":"+1 514 739 2647",
    "sg:postcode":"H4P 1X3",
    "sg:province":"QC",
    "wof:name":"Restaurant Amir",
    "wof:placetype":"venue"
},
  "geometry": {"coordinates":[-73.6519775391,45.4951057434],"type":"Point"}
}