{
  "type": "Feature",
  "properties": {
    "addr:full":"8671 120 St Delta BC V4C 6R4",
    "addr:housenumber":"8671",
    "addr:postcode":"v4c 6r4",
    "addr:street":"120 St",
    "iso:country":"CA",
    "sg:address":"8671 120 St",
    "sg:city":"Delta",
    "sg:classifiers":[
        {
            "category":"Restaurant",
            "type":"Food & Drink"
        }
    ],
    "sg:phone":"+1 604 597 4062",
    "sg:postcode":"V4C 6R4",
    "sg:province":"BC",
    "wof:name":"Dalat Vietnamese Restaurant",
    "wof:placetype":"venue"
},
  "geometry": {"coordinates":[-122.890503,49.160908],"type":"Point"}
}