{
  "type": "Feature",
  "properties": {
    "addr:full":"3524 Mainway Burlington ON L7M 1A8",
    "addr:housenumber":"3524",
    "addr:postcode":"l7m 1a8",
    "addr:street":"Mainway",
    "iso:country":"CA",
    "sg:address":"3524 Mainway",
    "sg:city":"Burlington",
    "sg:classifiers":[
        {
            "category":"Professional",
            "subcategory":"Accounting & Tax Preparation",
            "type":"Services"
        }
    ],
    "sg:phone":"+1 905 319 0566",
    "sg:postcode":"L7M 1A8",
    "sg:province":"ON",
    "sg:tags":[
        "accountant"
    ],
    "wof:name":"Gateman, Jared CA",
    "wof:placetype":"venue"
},
  "geometry": {"coordinates":[-79.797203,43.370251],"type":"Point"}
}