{
  "type": "Feature",
  "properties": {
    "addr:full":"425 Edenderry Line Ennismore ON K0L 1T0",
    "addr:housenumber":"425",
    "addr:postcode":"k0l 1t0",
    "addr:street":"Edenderry Line",
    "iso:country":"CA",
    "sg:address":"425 Edenderry Line",
    "sg:city":"Ennismore",
    "sg:classifiers":[
        {
            "category":"Manufacturing",
            "subcategory":"Metals",
            "type":"Manufacturing & Wholesale Goods"
        }
    ],
    "sg:phone":"+1 705 292 7953",
    "sg:postcode":"K0L 1T0",
    "sg:province":"ON",
    "sg:tags":[
        "downspouts",
        "gutter"
    ],
    "wof:name":"Kawartha Eavestroughing & Sdng",
    "wof:placetype":"venue"
},
  "geometry": {"coordinates":[-78.42817700000001,44.410664],"type":"Point"}
}