{
  "type": "Feature",
  "properties": {
    "addr:full":"590 River St Thunder Bay ON P7A 3S4",
    "addr:housenumber":"590",
    "addr:postcode":"p7a 3s4",
    "addr:street":"River St",
    "iso:country":"CA",
    "sg:address":"590 River St",
    "sg:city":"Thunder Bay",
    "sg:classifiers":[
        {
            "category":"Food & Beverages",
            "subcategory":"Bakery",
            "type":"Retail Goods"
        }
    ],
    "sg:phone":"+1 807 768 5959",
    "sg:postcode":"P7A 3S4",
    "sg:province":"ON",
    "sg:tags":[
        "doughnut"
    ],
    "wof:name":"Tim Hortons",
    "wof:placetype":"venue"
},
  "geometry": {"coordinates":[-89.2312088013,48.4473686218],"type":"Point"}
}