{
  "type": "Feature",
  "properties": {
    "addr:full":"3350 Fairview St Burlington ON L7N 3L5",
    "addr:housenumber":"3350",
    "addr:postcode":"l7n 3l5",
    "addr:street":"Fairview St",
    "iso:country":"CA",
    "sg:address":"3350 Fairview St",
    "sg:city":"Burlington",
    "sg:classifiers":[
        {
            "category":"Home & Garden",
            "subcategory":"Garden Supply",
            "type":"Retail Goods"
        }
    ],
    "sg:phone":"+1 905 634 7700",
    "sg:postcode":"L7N 3L5",
    "sg:province":"ON",
    "sg:tags":[
        "house",
        "bird",
        "feeder"
    ],
    "wof:name":"Wild Birds Unlimited",
    "wof:placetype":"venue"
},
  "geometry": {"coordinates":[-79.785355,43.354202],"type":"Point"}
}