{
  "type": "Feature",
  "properties": {
    "addr:full":"50 Greenfield Rd Lindsay ON K9V 4R2",
    "addr:housenumber":"50",
    "addr:postcode":"k9v 4r2",
    "addr:street":"Greenfield Rd",
    "iso:country":"CA",
    "sg:address":"50 Greenfield Rd",
    "sg:city":"Lindsay",
    "sg:classifiers":[
        {
            "category":"Freight",
            "type":"Transportation"
        }
    ],
    "sg:phone":"+1 705 328 0061",
    "sg:postcode":"K9V 4R2",
    "sg:province":"ON",
    "sg:tags":[
        "commercial",
        "storage"
    ],
    "wof:name":"Kawartha Mini Storage",
    "wof:placetype":"venue"
},
  "geometry": {"coordinates":[-78.76643371580001,44.3451156616],"type":"Point"}
}