{
  "type": "Feature",
  "properties": {
    "iso:country":"CA",
    "sg:address":"515 Richmond St",
    "sg:city":"London",
    "sg:classifiers":[
        {
            "category":"Shopping",
            "type":"Retail Goods"
        }
    ],
    "sg:phone":"+1 519 642 1907",
    "sg:postcode":"N6A 5N4",
    "sg:province":"ON",
    "sg:tags":[
        "stamp",
        "collector",
        "for"
    ],
    "wof:name":"Canada Post Corp",
    "wof:placetype":"venue"
},
  "geometry": {"coordinates":[-81.250877,42.987278],"type":"Point"}
}