{
  "type": "Feature",
  "properties": {
    "addr:full":"Thedford ON N0M 2N0",
    "addr:postcode":"n0m 2n0",
    "iso:country":"CA",
    "sg:city":"Thedford",
    "sg:classifiers":[
        {
            "category":"Sports & Exercise",
            "subcategory":"Golf",
            "type":"Entertainment"
        }
    ],
    "sg:phone":"+1 519 296 4653",
    "sg:postcode":"N0M 2N0",
    "sg:province":"ON",
    "sg:tags":[
        "course"
    ],
    "wof:name":"Widder Station Golf & Country",
    "wof:placetype":"venue"
},
  "geometry": {"coordinates":[-81.85785675050001,43.1591262817],"type":"Point"}
}