{
  "type": "Feature",
  "properties": {
    "iso:country":"CA",
    "sg:city":"Ottawa",
    "sg:classifiers":[
        {
            "category":"Real Estate",
            "subcategory":"Real Estate Operator",
            "type":"Services"
        }
    ],
    "sg:phone":"+1 613 236 2559",
    "sg:postcode":"K1N 6L9",
    "sg:province":"ON",
    "sg:tags":[
        "apartment"
    ],
    "wof:name":"Sans Souci Apartments",
    "wof:placetype":"venue"
},
  "geometry": {"coordinates":[-75.683609,45.426445],"type":"Point"}
}