{
  "type": "Feature",
  "properties": {
    "addr:full":"7001 Mumford Rd # 200 Halifax NS B3L 2H8",
    "addr:housenumber":"7001",
    "addr:postcode":"b3l 2h8",
    "addr:street":"Mumford Rd # 200",
    "iso:country":"CA",
    "sg:address":"7001 Mumford Rd # 200",
    "sg:city":"Halifax",
    "sg:classifiers":[
        {
            "category":"Wholesale",
            "subcategory":"Non-durable Goods",
            "type":"Manufacturing & Wholesale Goods"
        }
    ],
    "sg:phone":"+1 902 454 7333",
    "sg:postcode":"B3L 2H8",
    "sg:province":"NS",
    "sg:tags":[
        "interior",
        "bedding"
    ],
    "wof:name":"Second Glance Interiors Ltd",
    "wof:placetype":"venue"
},
  "geometry": {"coordinates":[-63.619663,44.647785],"type":"Point"}
}