{
  "type": "Feature",
  "properties": {
    "addr:full":"59 George St N Peterborough ON K9J 3G2",
    "addr:housenumber":"59",
    "addr:postcode":"k9j 3g2",
    "addr:street":"George St N",
    "iso:country":"CA",
    "sg:address":"59 George St N",
    "sg:city":"Peterborough",
    "sg:classifiers":[
        {
            "category":"Communications",
            "subcategory":"Radio Station",
            "type":"Services"
        }
    ],
    "sg:phone":"+1 705 742 8844",
    "sg:postcode":"K9J 3G2",
    "sg:province":"ON",
    "sg:tags":[
        "company",
        "broadcasting"
    ],
    "wof:name":"Ckpt",
    "wof:placetype":"venue"
},
  "geometry": {"coordinates":[-78.319458,44.294949],"type":"Point"}
}