{
  "type": "Feature",
  "properties": {
    "addr:full":"10514 Youbou Rd Youbou BC V0R 3E1",
    "addr:housenumber":"10514",
    "addr:postcode":"v0r 3e1",
    "addr:street":"Youbou Rd",
    "iso:country":"CA",
    "sg:address":"10514 Youbou Rd",
    "sg:city":"Youbou",
    "sg:classifiers":[
        {
            "category":"Autos & Motor Vehicles",
            "subcategory":"Fuel & Gas Station",
            "type":"Retail Goods"
        }
    ],
    "sg:phone":"+1 250 745 3433",
    "sg:postcode":"V0R 3E1",
    "sg:province":"BC",
    "sg:tags":[
        "oil"
    ],
    "wof:name":"Daly's Auto Ctr",
    "wof:placetype":"venue"
},
  "geometry": {"coordinates":[-124.20870208700001,48.8747634888],"type":"Point"}
}