{
  "type": "Feature",
  "properties": {
    "addr:full":"2354 Danforth Ave Toronto ON M4C 1K7",
    "addr:housenumber":"2354",
    "addr:postcode":"m4c 1k7",
    "addr:street":"Danforth Ave",
    "iso:country":"CA",
    "sg:address":"2354 Danforth Ave",
    "sg:city":"Toronto",
    "sg:classifiers":[
        {
            "category":"Professional",
            "subcategory":"Lawyer & Legal Services",
            "type":"Services"
        }
    ],
    "sg:phone":"+1 416 422 2107",
    "sg:postcode":"M4C 1K7",
    "sg:province":"ON",
    "sg:tags":[
        "attorney"
    ],
    "wof:name":"Glatt, Louis",
    "wof:placetype":"venue"
},
  "geometry": {"coordinates":[-79.30634307859999,43.6873054504],"type":"Point"}
}