{
  "type": "Feature",
  "properties": {
    "addr:full":"73 Bridge St Carleton Place ON K7C 2V4",
    "addr:housenumber":"73",
    "addr:postcode":"k7c 2v4",
    "addr:street":"Bridge St",
    "iso:country":"CA",
    "sg:address":"73 Bridge St",
    "sg:city":"Carleton Place",
    "sg:classifiers":[
        {
            "category":"Restaurant",
            "type":"Food & Drink"
        }
    ],
    "sg:phone":"+1 613 257 7595",
    "sg:postcode":"K7C 2V4",
    "sg:province":"ON",
    "wof:name":"Eating Place",
    "wof:placetype":"venue"
},
  "geometry": {"coordinates":[-76.14411200000001,45.138515],"type":"Point"}
}