{
  "type": "Feature",
  "properties": {
    "addr:full":"1755 Main St Moncton NB E1E 1H2",
    "addr:housenumber":"1755",
    "addr:postcode":"e1e 1h2",
    "addr:street":"Main St",
    "iso:country":"CA",
    "sg:address":"1755 Main St",
    "sg:city":"Moncton",
    "sg:classifiers":[
        {
            "category":"Retail",
            "subcategory":"Veterinary Services",
            "type":"Services"
        }
    ],
    "sg:phone":"+1 506 389 2121",
    "sg:postcode":"E1E 1H2",
    "sg:province":"NB",
    "sg:tags":[
        "veterinarian"
    ],
    "wof:name":"Maritime Animal Hospital Ltd",
    "wof:placetype":"venue"
},
  "geometry": {"coordinates":[-64.79789,46.078072],"type":"Point"}
}