{
  "type": "Feature",
  "properties": {
    "iso:country":"CA",
    "sg:address":"36 Helen St",
    "sg:city":"Fenelon Falls",
    "sg:classifiers":[
        {
            "category":"Travel",
            "subcategory":"Hotels & Motels",
            "type":"Entertainment"
        }
    ],
    "sg:phone":"+1 705 887 9000",
    "sg:postcode":"K0M 1N0",
    "sg:province":"ON",
    "wof:name":"Fenelon Inn",
    "wof:placetype":"venue"
},
  "geometry": {"coordinates":[-78.7411956787,44.533946991],"type":"Point"}
}