{
  "type": "Feature",
  "properties": {
    "addr:full":"633 Bloor St W Toronto ON M6G 1K8",
    "addr:housenumber":"633",
    "addr:postcode":"m6g 1k8",
    "addr:street":"Bloor St W",
    "iso:country":"CA",
    "sg:address":"633 Bloor St W",
    "sg:city":"Toronto",
    "sg:classifiers":[
        {
            "category":"Manufacturing",
            "subcategory":"Retail Goods",
            "type":"Manufacturing & Wholesale Goods"
        }
    ],
    "sg:phone":"+1 416 729 0282",
    "sg:postcode":"M6G 1K8",
    "sg:province":"ON",
    "sg:tags":[
        "match"
    ],
    "wof:name":"Ad Weaver Match Canada",
    "wof:placetype":"venue"
},
  "geometry": {"coordinates":[-79.414406,43.66428],"type":"Point"}
}