{
  "type": "Feature",
  "properties": {
    "addr:full":"Gormley ON L0H 1G0",
    "addr:postcode":"l0h 1g0",
    "iso:country":"CA",
    "sg:city":"Gormley",
    "sg:classifiers":[
        {
            "category":"Building & Trades",
            "subcategory":"Cleaning & Sanitation",
            "type":"Services"
        }
    ],
    "sg:phone":"+1 905 888 8820",
    "sg:postcode":"L0H 1G0",
    "sg:province":"ON",
    "sg:tags":[
        "janitor"
    ],
    "wof:name":"J R Tinderblox",
    "wof:placetype":"venue"
},
  "geometry": {"coordinates":[-79.38303399999999,43.954693],"type":"Point"}
}