{
  "type": "Feature",
  "properties": {
    "addr:full":"1745 Rue Decarie Saint-Laurent QC H4L 3N5",
    "addr:housenumber":"1745",
    "addr:postcode":"h4l 3n5",
    "addr:street":"Rue Decarie",
    "iso:country":"CA",
    "sg:address":"1745 Rue Decarie",
    "sg:city":"Saint-Laurent",
    "sg:classifiers":[
        {
            "category":"Social Services",
            "subcategory":"Child Care",
            "type":"Services"
        }
    ],
    "sg:phone":"+1 514 747 5822",
    "sg:postcode":"H4L 3N5",
    "sg:province":"QC",
    "wof:name":"Garderie Le Jardin DE Reves",
    "wof:placetype":"venue"
},
  "geometry": {"coordinates":[-73.692047,45.520412],"type":"Point"}
}