{
  "type": "Feature",
  "properties": {
    "addr:full":"3073 Dundas St W Toronto ON M6P 1Z5",
    "addr:housenumber":"3073",
    "addr:postcode":"m6p 1z5",
    "addr:street":"Dundas St W",
    "iso:country":"CA",
    "sg:address":"3073 Dundas St W",
    "sg:city":"Toronto",
    "sg:classifiers":[
        {
            "category":"Retail",
            "subcategory":"Laundry & Dry Cleaning",
            "type":"Services"
        }
    ],
    "sg:phone":"+1 416 769 2743",
    "sg:postcode":"M6P 1Z5",
    "sg:province":"ON",
    "sg:tags":[
        "cleaners"
    ],
    "wof:name":"Skyway Cleaners",
    "wof:placetype":"venue"
},
  "geometry": {"coordinates":[-79.47178599999999,43.665363],"type":"Point"}
}