{
  "type": "Feature",
  "properties": {
    "addr:full":"Montreal QC H3H 1G6",
    "addr:postcode":"h3h 1g6",
    "iso:country":"CA",
    "sg:city":"Montreal",
    "sg:classifiers":[
        {
            "category":"Shopping",
            "subcategory":"Computers & Home Electronics",
            "type":"Retail Goods"
        }
    ],
    "sg:phone":"+1 514 495 8446",
    "sg:postcode":"H3H 1G6",
    "sg:province":"QC",
    "sg:tags":[
        "software"
    ],
    "wof:name":"Account Mate Inc",
    "wof:placetype":"venue"
},
  "geometry": {"coordinates":[-73.55439,45.512287],"type":"Point"}
}