{
  "type": "Feature",
  "properties": {
    "addr:full":"38 Shannon Dr Moncton NB E1G 4X6",
    "addr:housenumber":"38",
    "addr:postcode":"e1g 4x6",
    "addr:street":"Shannon Dr",
    "iso:country":"CA",
    "sg:address":"38 Shannon Dr",
    "sg:city":"Moncton",
    "sg:classifiers":[
        {
            "category":"Building & Trades",
            "subcategory":"Construction",
            "type":"Services"
        }
    ],
    "sg:phone":"+1 506 866 9889",
    "sg:postcode":"E1G 4X6",
    "sg:province":"NB",
    "sg:tags":[
        "roofing",
        "contractor"
    ],
    "wof:name":"Ruscana Intertrade Inc",
    "wof:placetype":"venue"
},
  "geometry": {"coordinates":[-64.86098480219999,46.1162261963],"type":"Point"}
}