{
  "type": "Feature",
  "properties": {
    "addr:full":"Greenfield Park QC J4V 1M1",
    "addr:postcode":"j4v 1m1",
    "addr:street":"Park",
    "iso:country":"CA",
    "sg:city":"Greenfield Park",
    "sg:classifiers":[
        {
            "category":"Health Services",
            "subcategory":"Doctor",
            "type":"Services"
        }
    ],
    "sg:phone":"+1 450 465 6211",
    "sg:postcode":"J4V 1M1",
    "sg:province":"QC",
    "sg:tags":[
        "physician",
        "surgeon"
    ],
    "wof:name":"Leroux, Pierre MD",
    "wof:placetype":"venue"
},
  "geometry": {"coordinates":[-73.4922790527,45.4896621704],"type":"Point"}
}