{
  "type": "Feature",
  "properties": {
    "addr:full":"214 4th St Rainy River ON P0W 1L0",
    "addr:housenumber":"214",
    "addr:postcode":"p0w 1l0",
    "addr:street":"4Th St",
    "iso:country":"CA",
    "sg:address":"214 4th St",
    "sg:city":"Rainy River",
    "sg:classifiers":[
        {
            "category":"Food & Beverages",
            "subcategory":"Bakery",
            "type":"Retail Goods"
        }
    ],
    "sg:phone":"+1 807 852 3830",
    "sg:postcode":"P0W 1L0",
    "sg:province":"ON",
    "sg:tags":[
        "baker"
    ],
    "wof:name":"Quality Bakery",
    "wof:placetype":"venue"
},
  "geometry": {"coordinates":[-94.568184,48.719383],"type":"Point"}
}