{
  "type": "Feature",
  "properties": {
    "addr:full":"41736 Cardiff Rd Brussels ON N0G 1H0",
    "addr:housenumber":"41736",
    "addr:postcode":"n0g 1h0",
    "addr:street":"Cardiff Rd",
    "iso:country":"CA",
    "sg:address":"41736 Cardiff Rd",
    "sg:city":"Brussels",
    "sg:classifiers":[
        {
            "category":"Manufacturing",
            "subcategory":"Metals",
            "type":"Manufacturing & Wholesale Goods"
        }
    ],
    "sg:phone":"+1 519 887 6571",
    "sg:postcode":"N0G 1H0",
    "sg:province":"ON",
    "sg:tags":[
        "hardware"
    ],
    "wof:name":"Better Bilt Products",
    "wof:placetype":"venue"
},
  "geometry": {"coordinates":[-81.25166299999999,43.741852],"type":"Point"}
}