{
  "type": "Feature",
  "properties": {
    "addr:full":"2235 Ch DE L'Eglise S Des Ruisseaux QC J9L 3G6",
    "addr:postcode":"2235;j9l 3g6",
    "addr:street":"Ch De L'Eglise S Des Ruisseaux",
    "iso:country":"CA",
    "sg:address":"2235 Ch DE L'Eglise S",
    "sg:city":"Des Ruisseaux",
    "sg:classifiers":[
        {
            "category":"Building & Trades",
            "subcategory":"Landscaping Services",
            "type":"Services"
        }
    ],
    "sg:phone":"+1 819 623 5821",
    "sg:postcode":"J9L 3G6",
    "sg:province":"QC",
    "sg:tags":[
        "sod",
        "sodding"
    ],
    "wof:name":"Entreprises G Aubin Enr",
    "wof:placetype":"venue"
},
  "geometry": {"coordinates":[-75.585762,46.555317],"type":"Point"}
}