{
  "type": "Feature",
  "properties": {
    "iso:country":"CA",
    "sg:city":"Windsor",
    "sg:classifiers":[
        {
            "category":"Building & Trades",
            "subcategory":"Construction",
            "type":"Services"
        }
    ],
    "sg:phone":"+1 519 974 4466",
    "sg:postcode":"N8T 2W8",
    "sg:province":"ON",
    "sg:tags":[
        "maker",
        "cabinet"
    ],
    "wof:name":"Casa Kitchen Ctr",
    "wof:placetype":"venue"
},
  "geometry": {"coordinates":[-82.940903,42.293385],"type":"Point"}
}