{
  "type": "Feature",
  "properties": {
    "addr:full":"86 Fourth Ave Hudson ON P0V 1X0",
    "addr:housenumber":"86",
    "addr:postcode":"p0v 1x0",
    "addr:street":"Fourth Ave",
    "iso:country":"CA",
    "sg:address":"86 Fourth Ave",
    "sg:city":"Hudson",
    "sg:classifiers":[
        {
            "category":"Retail",
            "subcategory":"Auto Repair",
            "type":"Services"
        }
    ],
    "sg:phone":"+1 807 582 9726",
    "sg:postcode":"P0V 1X0",
    "sg:province":"ON",
    "sg:tags":[
        "repairing",
        "automobile"
    ],
    "wof:name":"Gord's Repair",
    "wof:placetype":"venue"
},
  "geometry": {"coordinates":[-92.169303894,50.090839386],"type":"Point"}
}