{
  "type": "Feature",
  "properties": {
    "addr:full":"RR 4 STN Mpp Prince Albert SK S6V 5R2",
    "addr:postcode":"s6v 5r2",
    "addr:street":"Rr 4 Stn",
    "iso:country":"CA",
    "sg:address":"RR 4 STN Mpp",
    "sg:city":"Prince Albert",
    "sg:classifiers":[
        {
            "category":"Recreation",
            "type":"Entertainment"
        }
    ],
    "sg:phone":"+1 306 929 2234",
    "sg:postcode":"S6V 5R2",
    "sg:province":"SK",
    "sg:tags":[
        "party",
        "fishing"
    ],
    "wof:name":"Nagle Lake Outfitters",
    "wof:placetype":"venue"
},
  "geometry": {"coordinates":[-105.752876282,53.1994400024],"type":"Point"}
}