{
  "type": "Feature",
  "properties": {
    "addr:full":"5450 Ch DE LA Cote-Des-Neiges # 525 Montreal QC H3T 1Y6",
    "addr:housenumber":"# 525",
    "addr:postcode":"5450;h3t 1y6",
    "addr:street":"Ch De La Cote-Des-Neiges",
    "iso:country":"CA",
    "sg:address":"5450 Ch DE LA Cote-Des-Neiges # 525",
    "sg:city":"Montreal",
    "sg:classifiers":[
        {
            "category":"Government",
            "subcategory":"Office",
            "type":"Public Place"
        }
    ],
    "sg:phone":"+1 514 737 1124",
    "sg:postcode":"H3T 1Y6",
    "sg:province":"QC",
    "sg:tags":[
        "federal",
        "affairs"
    ],
    "wof:name":"Consul Honoraire DE Jamaique",
    "wof:placetype":"venue"
},
  "geometry": {"coordinates":[-73.6240158081,45.4969749451],"type":"Point"}
}