{
  "type": "Feature",
  "properties": {
    "addr:full":"281 Main St W North Bay ON P1B 2T8",
    "addr:housenumber":"281",
    "addr:postcode":"p1b 2t8",
    "addr:street":"Main St W",
    "iso:country":"CA",
    "sg:address":"281 Main St W",
    "sg:city":"North Bay",
    "sg:classifiers":[
        {
            "category":"Restaurant",
            "type":"Food & Drink"
        }
    ],
    "sg:phone":"+1 705 497 9797",
    "sg:postcode":"P1B 2T8",
    "sg:province":"ON",
    "sg:tags":[
        "pizza"
    ],
    "wof:name":"Topper's Pizza",
    "wof:placetype":"venue"
},
  "geometry": {"coordinates":[-79.46649932859999,46.3129997253],"type":"Point"}
}