{
  "type": "Feature",
  "properties": {
    "iso:country":"CA",
    "sg:city":"Montreal",
    "sg:classifiers":[
        {
            "category":"Retail",
            "subcategory":"Auto Repair",
            "type":"Services"
        }
    ],
    "sg:phone":"+1 514 484 1822",
    "sg:postcode":"H4B 2Z7",
    "sg:province":"QC",
    "sg:tags":[
        "repairing",
        "automobile"
    ],
    "wof:name":"Transmission Montreal Ouest",
    "wof:placetype":"venue"
},
  "geometry": {"coordinates":[-73.63721466059999,45.4553794861],"type":"Point"}
}