{
  "type": "Feature",
  "properties": {
    "addr:full":"8147 Rue Grenache Anjou QC H1J 1C4",
    "addr:housenumber":"8147",
    "addr:postcode":"h1j 1c4",
    "addr:street":"Rue Grenache",
    "iso:country":"CA",
    "sg:address":"8147 Rue Grenache",
    "sg:city":"Anjou",
    "sg:classifiers":[
        {
            "category":"Freight",
            "type":"Transportation"
        }
    ],
    "sg:phone":"+1 514 354 5353",
    "sg:postcode":"H1J 1C4",
    "sg:province":"QC",
    "sg:tags":[
        "trucking"
    ],
    "wof:name":"Transport Gilles Perreault",
    "wof:placetype":"venue"
},
  "geometry": {"coordinates":[-73.57048,45.614819],"type":"Point"}
}