{
  "type": "Feature",
  "properties": {
    "addr:full":"Vancouver BC V6H 4A7",
    "addr:postcode":"v6h 4a7",
    "iso:country":"CA",
    "sg:city":"Vancouver",
    "sg:classifiers":[
        {
            "category":"Arena",
            "subcategory":"Sports Club",
            "type":"Entertainment"
        }
    ],
    "sg:phone":"+1 604 738 2468",
    "sg:postcode":"V6H 4A7",
    "sg:province":"BC",
    "sg:tags":[
        "manager",
        "recruiter",
        "promoter"
    ],
    "wof:name":"Premier's Sport Awards Program",
    "wof:placetype":"venue"
},
  "geometry": {"coordinates":[-123.135223,49.263596],"type":"Point"}
}