{
  "type": "Feature",
  "properties": {
    "addr:full":"Scarborough ON M1S 1V2",
    "addr:postcode":"m1s 1v2",
    "iso:country":"CA",
    "sg:city":"Scarborough",
    "sg:classifiers":[
        {
            "category":"Professional",
            "subcategory":"Lawyer & Legal Services",
            "type":"Services"
        }
    ],
    "sg:phone":"+1 416 609 8040",
    "sg:postcode":"M1S 1V2",
    "sg:province":"ON",
    "sg:tags":[
        "notary",
        "attorney"
    ],
    "wof:name":"Edmond Andrade & Assoc",
    "wof:placetype":"venue"
},
  "geometry": {"coordinates":[-79.2636566162,43.7887191772],"type":"Point"}
}