{
  "type": "Feature",
  "properties": {
    "iso:country":"CA",
    "sg:address":"PO Box 9",
    "sg:city":"Tete-A-LA-Baleine",
    "sg:classifiers":[
        {
            "category":"Banks & Credit Unions",
            "subcategory":"Bank",
            "type":"Services"
        }
    ],
    "sg:phone":"+1 418 242 2061",
    "sg:postcode":"G0G 2W0",
    "sg:province":"QC",
    "wof:name":"Caisse Desjardins Tete-Baleine",
    "wof:placetype":"venue"
},
  "geometry": {"coordinates":[-70.3310241699,47.416179657],"type":"Point"}
}