{
  "type": "Feature",
  "properties": {
    "addr:full":"201 Avenue B S Saskatoon SK S7M 1M3",
    "addr:housenumber":"201",
    "addr:postcode":"s7m 1m3",
    "addr:street":"Avenue",
    "iso:country":"CA",
    "sg:address":"201 Avenue B S",
    "sg:city":"Saskatoon",
    "sg:classifiers":[
        {
            "category":"Professional",
            "subcategory":"Art Services",
            "type":"Services"
        }
    ],
    "sg:phone":"+1 306 955 3723",
    "sg:postcode":"S7M 1M3",
    "sg:province":"SK",
    "sg:tags":[
        "graphic",
        "designer"
    ],
    "wof:name":"Randy's Graphics For Hire",
    "wof:placetype":"venue"
},
  "geometry": {"coordinates":[-106.672073,52.127525],"type":"Point"}
}