{
  "type": "Feature",
  "properties": {
    "iso:country":"CA",
    "sg:address":"696 Portage Ave # 105",
    "sg:city":"Winnipeg",
    "sg:classifiers":[
        {
            "category":"Professional",
            "subcategory":"Management & Consulting",
            "type":"Services"
        }
    ],
    "sg:phone":"+1 204 774 5689",
    "sg:postcode":"R3G 0M6",
    "sg:province":"MB",
    "sg:tags":[
        "system"
    ],
    "wof:name":"Little Office Svc",
    "wof:placetype":"venue"
},
  "geometry": {"coordinates":[-97.1610946655,49.8876342773],"type":"Point"}
}