{
  "type": "Feature",
  "properties": {
    "addr:full":"226 Lakeshore Rd W Oakville ON L6K 1E8",
    "addr:housenumber":"226",
    "addr:postcode":"l6k 1e8",
    "addr:street":"Lakeshore Rd W",
    "iso:country":"CA",
    "sg:address":"226 Lakeshore Rd W",
    "sg:city":"Oakville",
    "sg:classifiers":[
        {
            "category":"Shopping",
            "subcategory":"Photographic Equipment",
            "type":"Retail Goods"
        }
    ],
    "sg:phone":"+1 905 844 6991",
    "sg:postcode":"L6K 1E8",
    "sg:province":"ON",
    "sg:tags":[
        "supply"
    ],
    "wof:name":"Mc Cutcheon's Foto Source",
    "wof:placetype":"venue"
},
  "geometry": {"coordinates":[-79.6786727905,43.4357566833],"type":"Point"}
}