{
  "type": "Feature",
  "properties": {
    "addr:full":"419 Coxwell Ave Toronto ON M4L 3B9",
    "addr:housenumber":"419",
    "addr:postcode":"m4l 3b9",
    "addr:street":"Coxwell Ave",
    "iso:country":"CA",
    "sg:address":"419 Coxwell Ave",
    "sg:city":"Toronto",
    "sg:classifiers":[
        {
            "category":"Social Services",
            "subcategory":"Child Care",
            "type":"Services"
        }
    ],
    "sg:phone":"+1 416 463 3955",
    "sg:postcode":"M4L 3B9",
    "sg:province":"ON",
    "wof:name":"Petit Chaperon Rouge",
    "wof:placetype":"venue"
},
  "geometry": {"coordinates":[-79.32075500000001,43.676983],"type":"Point"}
}