{
  "type": "Feature",
  "properties": {
    "iso:country":"CA",
    "sg:city":"Western Bay",
    "sg:classifiers":[
        {
            "category":"Organizations",
            "subcategory":"Professional Association",
            "type":"Services"
        }
    ],
    "sg:phone":"+1 709 598 2023",
    "sg:postcode":"A0A 4J0",
    "sg:province":"NL",
    "wof:name":"North Shore Regional Dev Assn",
    "wof:placetype":"venue"
},
  "geometry": {"coordinates":[-53.0859222412,47.8829498291],"type":"Point"}
}