{
  "type": "Feature",
  "properties": {
    "addr:full":"1 William St E Smiths Falls ON K7A 1C1",
    "addr:housenumber":"1",
    "addr:postcode":"k7a 1c1",
    "addr:street":"William St E",
    "iso:country":"CA",
    "sg:address":"1 William St E",
    "sg:city":"Smiths Falls",
    "sg:classifiers":[
        {
            "category":"Shopping",
            "subcategory":"Bicycles & Sporting Goods",
            "type":"Retail Goods"
        }
    ],
    "sg:phone":"+1 613 284 4233",
    "sg:postcode":"K7A 1C1",
    "sg:province":"ON",
    "sg:tags":[
        "sportswear"
    ],
    "wof:name":"Marie's Designs",
    "wof:placetype":"venue"
},
  "geometry": {"coordinates":[-76.021027,44.900379],"type":"Point"}
}