{
  "type": "Feature",
  "properties": {
    "addr:full":"21029 42 Ave Langley BC V3A 5A2",
    "addr:housenumber":"21029",
    "addr:postcode":"v3a 5a2",
    "addr:street":"42 Ave",
    "iso:country":"CA",
    "sg:address":"21029 42 Ave",
    "sg:city":"Langley",
    "sg:classifiers":[
        {
            "category":"Building & Trades",
            "subcategory":"Construction",
            "type":"Services"
        }
    ],
    "sg:phone":"+1 604 530 3142",
    "sg:postcode":"V3A 5A2",
    "sg:province":"BC",
    "sg:tags":[
        "product",
        "asphalt"
    ],
    "wof:name":"Lark Services Ltd",
    "wof:placetype":"venue"
},
  "geometry": {"coordinates":[-122.64078499999999,49.078548],"type":"Point"}
}