{
  "type": "Feature",
  "properties": {
    "addr:full":"310 Alexander St Whitehorse YT Y1A 2L6",
    "addr:housenumber":"310",
    "addr:postcode":"y1a 2l6",
    "addr:street":"Alexander St",
    "iso:country":"CA",
    "sg:address":"310 Alexander St",
    "sg:city":"Whitehorse",
    "sg:classifiers":[
        {
            "category":"Retail",
            "subcategory":"Repair Shop",
            "type":"Services"
        }
    ],
    "sg:phone":"+1 867 667 2330",
    "sg:postcode":"Y1A 2L6",
    "sg:province":"YT",
    "sg:tags":[
        "repairing",
        "tool",
        "electric"
    ],
    "wof:name":"Oscar's Electric Ltd",
    "wof:placetype":"venue"
},
  "geometry": {"coordinates":[-135.057662964,60.7231559753],"type":"Point"}
}