{
  "type": "Feature",
  "properties": {
    "iso:country":"CA",
    "sg:address":"375 Route 8",
    "sg:city":"Nashwaak Village",
    "sg:classifiers":[
        {
            "category":"Food & Beverages",
            "subcategory":"Groceries & Convenience Stores",
            "type":"Retail Goods"
        }
    ],
    "sg:phone":"+1 506 450 9975",
    "sg:postcode":"E6C 1M5",
    "sg:province":"NB",
    "wof:name":"Nashwaak 6-12",
    "wof:placetype":"venue"
},
  "geometry": {"coordinates":[-66.6057052612,46.105014801],"type":"Point"}
}