{
  "type": "Feature",
  "properties": {
    "addr:full":"Cacouna QC G0L 1G0",
    "addr:postcode":"g0l 1g0",
    "iso:country":"CA",
    "sg:city":"Cacouna",
    "sg:classifiers":[
        {
            "category":"Recreation",
            "type":"Entertainment"
        }
    ],
    "sg:phone":"+1 418 862 0163",
    "sg:postcode":"G0L 1G0",
    "sg:province":"QC",
    "sg:tags":[
        "center",
        "government"
    ],
    "wof:name":"Cacouna Loisirs Kakou",
    "wof:placetype":"venue"
},
  "geometry": {"coordinates":[-69.50769805909999,47.909614563],"type":"Point"}
}