{
  "type": "Feature",
  "properties": {
    "iso:country":"CA",
    "sg:address":"RR 3 Lcd 9",
    "sg:city":"Edmonton",
    "sg:classifiers":[
        {
            "category":"Organizations",
            "subcategory":"Religious Organization",
            "type":"Services"
        }
    ],
    "sg:phone":"+1 780 955 7305",
    "sg:postcode":"T6H 4N7",
    "sg:province":"AB",
    "sg:tags":[
        "church"
    ],
    "wof:name":"Heimtal Moravian Church",
    "wof:placetype":"venue"
},
  "geometry": {"coordinates":[-113.490371704,53.5462188721],"type":"Point"}
}