{
  "type": "Feature",
  "properties": {
    "iso:country":"CA",
    "sg:address":"166 Ronald Prom",
    "sg:city":"Montreal-Ouest",
    "sg:classifiers":[
        {
            "category":"Building & Trades",
            "subcategory":"Construction",
            "type":"Services"
        }
    ],
    "sg:phone":"+1 514 485 2692",
    "sg:postcode":"H4X 1M8",
    "sg:province":"QC",
    "sg:tags":[
        "repairing",
        "remodeling",
        "contractor"
    ],
    "wof:name":"Bendar & Ayalon",
    "wof:placetype":"venue"
},
  "geometry": {"coordinates":[-73.640938,45.448875],"type":"Point"}
}