{
  "type": "Feature",
  "properties": {
    "iso:country":"CA",
    "sg:address":"1691 Rte Marie-Victorin",
    "sg:city":"Varennes",
    "sg:classifiers":[
        {
            "category":"Retail",
            "subcategory":"Auto Repair",
            "type":"Services"
        }
    ],
    "sg:phone":"+1 450 652 7979",
    "sg:postcode":"J3X 1P7",
    "sg:province":"QC",
    "sg:tags":[
        "body",
        "automobile",
        "painting"
    ],
    "wof:name":"Carrosserie Lg Enr",
    "wof:placetype":"venue"
},
  "geometry": {"coordinates":[-73.4338226318,45.6685447693],"type":"Point"}
}