{
  "type": "Feature",
  "properties": {
    "addr:full":"Pierrefonds QC H9H 3E2",
    "addr:postcode":"h9h 3e2",
    "iso:country":"CA",
    "sg:city":"Pierrefonds",
    "sg:classifiers":[
        {
            "category":"Retail",
            "subcategory":"Laundry & Dry Cleaning",
            "type":"Services"
        }
    ],
    "sg:phone":"+1 514 620 8049",
    "sg:postcode":"H9H 3E2",
    "sg:province":"QC",
    "sg:tags":[
        "cleaners"
    ],
    "wof:name":"Nettoyeurs Daoust",
    "wof:placetype":"venue"
},
  "geometry": {"coordinates":[-73.8745727539,45.4670066833],"type":"Point"}
}