{
  "type": "Feature",
  "properties": {
    "addr:full":"84 Adelaide St E Toronto ON M5C 1K9",
    "addr:housenumber":"84",
    "addr:postcode":"m5c 1k9",
    "addr:street":"Adelaide St E",
    "iso:country":"CA",
    "sg:address":"84 Adelaide St E",
    "sg:city":"Toronto",
    "sg:classifiers":[
        {
            "category":"Organizations",
            "subcategory":"Non-profit Organization",
            "type":"Services"
        }
    ],
    "sg:phone":"+1 416 364 2332",
    "sg:postcode":"M5C 1K9",
    "sg:province":"ON",
    "sg:tags":[
        "addiction",
        "treatment",
        "center"
    ],
    "wof:name":"Adelaide Addiction Recovery",
    "wof:placetype":"venue"
},
  "geometry": {"coordinates":[-79.374641,43.651386],"type":"Point"}
}