{
  "type": "Feature",
  "properties": {
    "iso:country":"CA",
    "sg:city":"Newmarket",
    "sg:classifiers":[
        {
            "category":"Building & Trades",
            "subcategory":"Cleaning & Sanitation",
            "type":"Services"
        }
    ],
    "sg:phone":"+1 905 898 1088",
    "sg:postcode":"L3Y 7T9",
    "sg:province":"ON",
    "sg:tags":[
        "janitor"
    ],
    "wof:name":"Global Clean Inc",
    "wof:placetype":"venue"
},
  "geometry": {"coordinates":[-79.4594497681,44.059627533],"type":"Point"}
}