{
  "type": "Feature",
  "properties": {
    "addr:full":"3326 Portage Ave Winnipeg MB R3K 0Z1",
    "addr:housenumber":"3326",
    "addr:postcode":"r3k 0z1",
    "addr:street":"Portage Ave",
    "iso:country":"CA",
    "sg:address":"3326 Portage Ave",
    "sg:city":"Winnipeg",
    "sg:classifiers":[
        {
            "category":"Shopping",
            "type":"Retail Goods"
        }
    ],
    "sg:phone":"+1 204 837 3227",
    "sg:postcode":"R3K 0Z1",
    "sg:province":"MB",
    "sg:tags":[
        "pet",
        "food",
        "supply"
    ],
    "wof:name":"Pet Valu",
    "wof:placetype":"venue"
},
  "geometry": {"coordinates":[-97.296333,49.88205],"type":"Point"}
}