{
  "type": "Feature",
  "properties": {
    "addr:full":"86 Byng Ave North York ON M2N 4K4",
    "addr:housenumber":"86",
    "addr:postcode":"m2n 4k4",
    "addr:street":"Byng Ave",
    "iso:country":"CA",
    "sg:address":"86 Byng Ave",
    "sg:city":"North York",
    "sg:classifiers":[
        {
            "category":"Building & Trades",
            "subcategory":"Construction",
            "type":"Services"
        }
    ],
    "sg:phone":"+1 416 686 0484",
    "sg:postcode":"M2N 4K4",
    "sg:province":"ON",
    "sg:tags":[
        "roofing",
        "contractor"
    ],
    "wof:name":"New Parliament Roofing & Snow",
    "wof:placetype":"venue"
},
  "geometry": {"coordinates":[-79.41055297849999,43.7776374817],"type":"Point"}
}