{
  "type": "Feature",
  "properties": {
    "addr:full":"1239 12 Ave SW Calgary AB T3C 3R8",
    "addr:housenumber":"1239",
    "addr:postcode":"t3c 3r8",
    "addr:street":"12 Ave Sw",
    "iso:country":"CA",
    "sg:address":"1239 12 Ave SW",
    "sg:city":"Calgary",
    "sg:classifiers":[
        {
            "category":"Real Estate",
            "subcategory":"Real Estate Operator",
            "type":"Services"
        }
    ],
    "sg:phone":"+1 403 244 2414",
    "sg:postcode":"T3C 3R8",
    "sg:province":"AB",
    "sg:tags":[
        "apartment"
    ],
    "wof:name":"Edinburgh House",
    "wof:placetype":"venue"
},
  "geometry": {"coordinates":[-114.08992000000001,51.042034],"type":"Point"}
}