{
  "type": "Feature",
  "properties": {
    "iso:country":"CA",
    "sg:city":"Concord",
    "sg:classifiers":[
        {
            "category":"Manufacturing",
            "subcategory":"Tools & Machinery",
            "type":"Manufacturing & Wholesale Goods"
        }
    ],
    "sg:phone":"+1 905 761 6434",
    "sg:postcode":"L4K 4Z5",
    "sg:province":"ON",
    "wof:name":"Jda Progress Industries",
    "wof:placetype":"venue"
},
  "geometry": {"coordinates":[-79.5342636108,43.8010940552],"type":"Point"}
}