{
  "type": "Feature",
  "properties": {
    "iso:country":"CA",
    "sg:address":"117 Rue DE LA Commune E",
    "sg:city":"Montreal",
    "sg:classifiers":[
        {
            "category":"Communications",
            "subcategory":"Film & Video Production",
            "type":"Services"
        }
    ],
    "sg:phone":"+1 514 398 9006",
    "sg:postcode":"H2Y 1J1",
    "sg:province":"QC",
    "sg:tags":[
        "audio"
    ],
    "wof:name":"Eureka Production Multimedia",
    "wof:placetype":"venue"
},
  "geometry": {"coordinates":[-73.552605,45.506733],"type":"Point"}
}