{
  "type": "Feature",
  "properties": {
    "addr:full":"1025 Montee Masson Mascouche QC J7K 2L9",
    "addr:housenumber":"1025",
    "addr:postcode":"j7k 2l9",
    "addr:street":"Montee Masson",
    "iso:country":"CA",
    "sg:address":"1025 Montee Masson",
    "sg:city":"Mascouche",
    "sg:classifiers":[
        {
            "category":"Health Services",
            "subcategory":"Doctor",
            "type":"Services"
        }
    ],
    "sg:phone":"+1 450 474 6000",
    "sg:postcode":"J7K 2L9",
    "sg:province":"QC",
    "sg:tags":[
        "physician",
        "surgeon"
    ],
    "wof:name":"Clinique Medicale Mascouche",
    "wof:placetype":"venue"
},
  "geometry": {"coordinates":[-73.6065750122,45.7468032837],"type":"Point"}
}