{
  "type": "Feature",
  "properties": {
    "iso:country":"CA",
    "sg:address":"184 Principale St W",
    "sg:city":"LA Broquerie",
    "sg:classifiers":[
        {
            "category":"Home & Garden",
            "subcategory":"Building Materials",
            "type":"Retail Goods"
        }
    ],
    "sg:phone":"+1 204 424 5333",
    "sg:postcode":"R0A 0W0",
    "sg:province":"MB",
    "sg:tags":[
        "lumber"
    ],
    "wof:name":"LA Broquerie Lumber",
    "wof:placetype":"venue"
},
  "geometry": {"coordinates":[-96.5105667114,49.480670929],"type":"Point"}
}