{
  "type": "Feature",
  "properties": {
    "addr:full":"4860 Boul Notre-Dame Laval QC H7W 1V4",
    "addr:housenumber":"4860",
    "addr:postcode":"h7w 1v4",
    "addr:street":"Boul Notre-Dame",
    "iso:country":"CA",
    "sg:address":"4860 Boul Notre-Dame",
    "sg:city":"Laval",
    "sg:classifiers":[
        {
            "category":"Organizations",
            "subcategory":"Religious Organization",
            "type":"Services"
        }
    ],
    "sg:phone":"+1 450 682 6606",
    "sg:postcode":"H7W 1V4",
    "sg:province":"QC",
    "sg:tags":[
        "synagogue"
    ],
    "wof:name":"Communaute Sepharade DE Laval",
    "wof:placetype":"venue"
},
  "geometry": {"coordinates":[-73.7693481445,45.5344810486],"type":"Point"}
}