{
  "type": "Feature",
  "properties": {
    "addr:full":"352 Queen St N Paisley ON N0G 2N0",
    "addr:housenumber":"352",
    "addr:postcode":"n0g 2n0",
    "addr:street":"Queen St N",
    "iso:country":"CA",
    "sg:address":"352 Queen St N",
    "sg:city":"Paisley",
    "sg:classifiers":[
        {
            "category":"Manufacturing",
            "subcategory":"Jewelry",
            "type":"Manufacturing & Wholesale Goods"
        }
    ],
    "sg:phone":"+1 519 353 5773",
    "sg:postcode":"N0G 2N0",
    "sg:province":"ON",
    "sg:tags":[
        "craft",
        "craftsman",
        "supply"
    ],
    "wof:name":"Mac Namara Gallery",
    "wof:placetype":"venue"
},
  "geometry": {"coordinates":[-81.27373504640001,44.3075866699],"type":"Point"}
}