{
  "type": "Feature",
  "properties": {
    "addr:full":"7663 Rue Centrale Lasalle QC H8P 1L4",
    "addr:housenumber":"7663",
    "addr:postcode":"h8p 1l4",
    "addr:street":"Rue Centrale",
    "iso:country":"CA",
    "sg:address":"7663 Rue Centrale",
    "sg:city":"Lasalle",
    "sg:classifiers":[
        {
            "category":"Professional",
            "subcategory":"Business Services",
            "type":"Services"
        }
    ],
    "sg:phone":"+1 514 365 3455",
    "sg:postcode":"H8P 1L4",
    "sg:province":"QC",
    "sg:tags":[
        "notary"
    ],
    "wof:name":"Deomontigny & Tremblay",
    "wof:placetype":"venue"
},
  "geometry": {"coordinates":[-73.598167,45.430763],"type":"Point"}
}