{
  "type": "Feature",
  "properties": {
    "addr:full":"289 Dundas St E Mississauga ON L5A 1X1",
    "addr:housenumber":"289",
    "addr:postcode":"l5a 1x1",
    "addr:street":"Dundas St E",
    "iso:country":"CA",
    "sg:address":"289 Dundas St E",
    "sg:city":"Mississauga",
    "sg:classifiers":[
        {
            "category":"Food & Beverages",
            "subcategory":"Bakery",
            "type":"Retail Goods"
        }
    ],
    "sg:phone":"+1 905 896 7245",
    "sg:postcode":"L5A 1X1",
    "sg:province":"ON",
    "sg:tags":[
        "baker"
    ],
    "wof:name":"Trigo Bakery",
    "wof:placetype":"venue"
},
  "geometry": {"coordinates":[-79.60931396479999,43.5865821838],"type":"Point"}
}