{
  "type": "Feature",
  "properties": {
    "addr:full":"114 Atwood Ave Rainy River ON P0W 1L0",
    "addr:housenumber":"114",
    "addr:postcode":"p0w 1l0",
    "addr:street":"Atwood Ave",
    "iso:country":"CA",
    "sg:address":"114 Atwood Ave",
    "sg:city":"Rainy River",
    "sg:classifiers":[
        {
            "category":"Retail",
            "subcategory":"Auto Repair",
            "type":"Services"
        }
    ],
    "sg:phone":"+1 807 852 3851",
    "sg:postcode":"P0W 1L0",
    "sg:province":"ON",
    "sg:tags":[
        "repairing",
        "automobile"
    ],
    "wof:name":"Border Service",
    "wof:placetype":"venue"
},
  "geometry": {"coordinates":[-94.570679,48.72205],"type":"Point"}
}