{
  "type": "Feature",
  "properties": {
    "iso:country":"CA",
    "sg:address":"175 Eileen Ave",
    "sg:city":"York",
    "sg:classifiers":[
        {
            "category":"Wholesale",
            "subcategory":"Durable Goods & Equipment",
            "type":"Manufacturing & Wholesale Goods"
        }
    ],
    "sg:phone":"+1 416 766 0510",
    "sg:postcode":"M6N 1W3",
    "sg:province":"ON",
    "sg:tags":[
        "electronic",
        "representative"
    ],
    "wof:name":"Wilson Enterprises",
    "wof:placetype":"venue"
},
  "geometry": {"coordinates":[-79.503159,43.666882],"type":"Point"}
}