{
  "type": "Feature",
  "properties": {
    "addr:full":"30 Carlton St Toronto ON M5B 2E9",
    "addr:housenumber":"30",
    "addr:postcode":"m5b 2e9",
    "addr:street":"Carlton St",
    "iso:country":"CA",
    "sg:address":"30 Carlton St",
    "sg:city":"Toronto",
    "sg:classifiers":[
        {
            "category":"Travel",
            "subcategory":"Travel Agent",
            "type":"Entertainment"
        }
    ],
    "sg:phone":"+1 416 593 0593",
    "sg:postcode":"M5B 2E9",
    "sg:province":"ON",
    "sg:tags":[
        "agency",
        "bureau"
    ],
    "wof:name":"Safeway Travel Svc",
    "wof:placetype":"venue"
},
  "geometry": {"coordinates":[-79.38144699999999,43.661541],"type":"Point"}
}