{
  "type": "Feature",
  "properties": {
    "iso:country":"CA",
    "sg:address":"320 2 St NE",
    "sg:city":"Slave Lake",
    "sg:classifiers":[
        {
            "category":"Education",
            "subcategory":"Library",
            "type":"Public Place"
        }
    ],
    "sg:phone":"+1 780 849 5250",
    "sg:postcode":"T0G 2A0",
    "sg:province":"AB",
    "wof:name":"Slave Lake Municipal Library",
    "wof:placetype":"venue"
},
  "geometry": {"coordinates":[-114.769996643,55.2838783264],"type":"Point"}
}