{
  "type": "Feature",
  "properties": {
    "addr:full":"102 Second Ave NW Riverton MB R0C 2R0",
    "addr:housenumber":"102",
    "addr:postcode":"r0c 2r0",
    "addr:street":"Second Ave Nw",
    "iso:country":"CA",
    "sg:address":"102 Second Ave NW",
    "sg:city":"Riverton",
    "sg:classifiers":[
        {
            "category":"Organizations",
            "subcategory":"Religious Organization",
            "type":"Services"
        }
    ],
    "sg:phone":"+1 204 472 3442",
    "sg:postcode":"R0C 2R0",
    "sg:province":"MB",
    "sg:tags":[
        "church"
    ],
    "wof:name":"Roman Catholic Ctr",
    "wof:placetype":"venue"
},
  "geometry": {"coordinates":[-96.99645200000001,50.998413],"type":"Point"}
}