{
  "type": "Feature",
  "properties": {
    "addr:full":"31 Rue Turgeon Sainte-Therese QC J7E 3H2",
    "addr:housenumber":"31",
    "addr:postcode":"j7e 3h2",
    "addr:street":"Rue Turgeon Sainte-Therese",
    "iso:country":"CA",
    "sg:address":"31 Rue Turgeon",
    "sg:city":"Sainte-Therese",
    "sg:classifiers":[
        {
            "category":"Health Services",
            "subcategory":"Health Practitioner",
            "type":"Services"
        }
    ],
    "sg:phone":"+1 450 437 4333",
    "sg:postcode":"J7E 3H2",
    "sg:province":"QC",
    "sg:tags":[
        "psychologist"
    ],
    "wof:name":"Yelle, Yvan",
    "wof:placetype":"venue"
},
  "geometry": {"coordinates":[-73.84056854249999,45.6386947632],"type":"Point"}
}