{
  "type": "Feature",
  "properties": {
    "addr:full":"936 Chaplin St E Swift Current SK S9H 1J7",
    "addr:housenumber":"936",
    "addr:postcode":"s9h 1j7",
    "addr:street":"Chaplin St E",
    "iso:country":"CA",
    "sg:address":"936 Chaplin St E",
    "sg:city":"Swift Current",
    "sg:classifiers":[
        {
            "category":"Food & Beverages",
            "subcategory":"Groceries & Convenience Stores",
            "type":"Retail Goods"
        }
    ],
    "sg:phone":"+1 306 773 6225",
    "sg:postcode":"S9H 1J7",
    "sg:province":"SK",
    "sg:tags":[
        "grocer"
    ],
    "wof:name":"Elmwood Grocery",
    "wof:placetype":"venue"
},
  "geometry": {"coordinates":[-107.78685760499999,50.2851676941],"type":"Point"}
}