{
  "type": "Feature",
  "properties": {
    "iso:country":"CA",
    "sg:city":"North Vancouver",
    "sg:classifiers":[
        {
            "category":"Building & Trades",
            "subcategory":"Cleaning & Sanitation",
            "type":"Services"
        }
    ],
    "sg:phone":"+1 604 987 7030",
    "sg:postcode":"V7M 3L4",
    "sg:province":"BC",
    "sg:tags":[
        "janitor"
    ],
    "wof:name":"Hollyburn Maintenance Ltd",
    "wof:placetype":"venue"
},
  "geometry": {"coordinates":[-123.083557129,49.3109321594],"type":"Point"}
}