{
  "type": "Feature",
  "properties": {
    "addr:full":"Hamilton ON L8W 2E1",
    "addr:postcode":"l8w 2e1",
    "iso:country":"CA",
    "sg:city":"Hamilton",
    "sg:classifiers":[
        {
            "category":"Professional",
            "subcategory":"Engineering",
            "type":"Services"
        }
    ],
    "sg:phone":"+1 905 383 3733",
    "sg:postcode":"L8W 2E1",
    "sg:province":"ON",
    "sg:tags":[
        "engineer"
    ],
    "wof:name":"Landtek Limited",
    "wof:placetype":"venue"
},
  "geometry": {"coordinates":[-79.837234,43.192558],"type":"Point"}
}