{
  "type": "Feature",
  "properties": {
    "iso:country":"CA",
    "sg:address":"69 Langarth St W",
    "sg:city":"London",
    "sg:classifiers":[
        {
            "category":"Professional",
            "subcategory":"Research",
            "type":"Services"
        }
    ],
    "sg:phone":"+1 519 434 0319",
    "sg:postcode":"N6J 1P5",
    "sg:province":"ON",
    "sg:tags":[
        "archaeologist"
    ],
    "wof:name":"D R Poulton & Assoc Inc",
    "wof:placetype":"venue"
},
  "geometry": {"coordinates":[-81.26765441889999,42.9645004272],"type":"Point"}
}