{
  "type": "Feature",
  "properties": {
    "addr:full":"210 Cornhill St Moncton NB E1C 6L6",
    "addr:housenumber":"210",
    "addr:postcode":"e1c 6l6",
    "addr:street":"Cornhill St",
    "iso:country":"CA",
    "sg:address":"210 Cornhill St",
    "sg:city":"Moncton",
    "sg:classifiers":[
        {
            "category":"Personal",
            "type":"Services"
        }
    ],
    "sg:phone":"+1 506 389 9851",
    "sg:postcode":"E1C 6L6",
    "sg:province":"NB",
    "sg:tags":[
        "therapist",
        "massage"
    ],
    "wof:name":"Natural Concern For Health",
    "wof:placetype":"venue"
},
  "geometry": {"coordinates":[-64.793594,46.090454],"type":"Point"}
}