{
  "type": "Feature",
  "properties": {
    "iso:country":"CA",
    "sg:address":"47 Fairway Cres",
    "sg:city":"Amherstburg",
    "sg:classifiers":[
        {
            "category":"Wholesale",
            "subcategory":"Auto Parts",
            "type":"Manufacturing & Wholesale Goods"
        }
    ],
    "sg:phone":"+1 519 736 1351",
    "sg:postcode":"N9V 3T5",
    "sg:province":"ON",
    "sg:tags":[
        "automobile",
        "supply"
    ],
    "wof:name":"Classic Engine Supplies Inc",
    "wof:placetype":"venue"
},
  "geometry": {"coordinates":[-83.103843689,42.1403427124],"type":"Point"}
}