{
  "type": "Feature",
  "properties": {
    "iso:country":"CA",
    "sg:city":"Toronto",
    "sg:classifiers":[
        {
            "category":"Professional",
            "subcategory":"Computer Services",
            "type":"Services"
        }
    ],
    "sg:phone":"+1 416 960 5535",
    "sg:postcode":"M5R 1A3",
    "sg:province":"ON",
    "sg:tags":[
        "internet"
    ],
    "wof:name":"Netcastor Corp",
    "wof:placetype":"venue"
},
  "geometry": {"coordinates":[-79.3907318115,43.6704978943],"type":"Point"}
}