{
  "type": "Feature",
  "properties": {
    "addr:full":"211 Banff Ave Banff AB T1L 1B8",
    "addr:housenumber":"211",
    "addr:postcode":"t1l 1b8",
    "addr:street":"Banff Ave",
    "iso:country":"CA",
    "sg:address":"211 Banff Ave",
    "sg:city":"Banff",
    "sg:classifiers":[
        {
            "category":"Banks & Credit Unions",
            "subcategory":"Bank",
            "type":"Services"
        }
    ],
    "sg:phone":"+1 403 760 6630",
    "sg:postcode":"T1L 1B8",
    "sg:province":"AB",
    "sg:tags":[
        "broker",
        "foreign",
        "dealer",
        "exchange"
    ],
    "wof:name":"Custom House Currency Exchange",
    "wof:placetype":"venue"
},
  "geometry": {"coordinates":[-115.571022,51.176929],"type":"Point"}
}