{
  "type": "Feature",
  "properties": {
    "addr:full":"185 Huron Rd Sebringville ON N0K 1X0",
    "addr:housenumber":"185",
    "addr:postcode":"n0k 1x0",
    "addr:street":"Huron Rd",
    "iso:country":"CA",
    "sg:address":"185 Huron Rd",
    "sg:city":"Sebringville",
    "sg:classifiers":[
        {
            "category":"Building & Trades",
            "subcategory":"Electrical",
            "type":"Services"
        }
    ],
    "sg:phone":"+1 519 393 6778",
    "sg:postcode":"N0K 1X0",
    "sg:province":"ON",
    "sg:tags":[
        "electric",
        "contractor"
    ],
    "wof:name":"Smith Electric",
    "wof:placetype":"venue"
},
  "geometry": {"coordinates":[-81.05233,43.402973],"type":"Point"}
}