{
  "type": "Feature",
  "properties": {
    "addr:full":"Scarborough ON M1L 4T3",
    "addr:postcode":"m1l 4t3",
    "iso:country":"CA",
    "sg:city":"Scarborough",
    "sg:classifiers":[
        {
            "category":"Organizations",
            "subcategory":"Religious Organization",
            "type":"Services"
        }
    ],
    "sg:phone":"+1 416 699 7077",
    "sg:postcode":"M1L 4T3",
    "sg:province":"ON",
    "wof:name":"Pontifical Mission Societies",
    "wof:placetype":"venue"
},
  "geometry": {"coordinates":[-79.281387,43.692627],"type":"Point"}
}