{
  "type": "Feature",
  "properties": {
    "addr:full":"Winnipeg MB R2C 1R2",
    "addr:postcode":"r2c 1r2",
    "iso:country":"CA",
    "sg:city":"Winnipeg",
    "sg:classifiers":[
        {
            "category":"Health Services",
            "subcategory":"Doctor",
            "type":"Services"
        }
    ],
    "sg:phone":"+1 204 222 4297",
    "sg:postcode":"R2C 1R2",
    "sg:province":"MB",
    "sg:tags":[
        "dentist"
    ],
    "wof:name":"Maxim, G P DDS",
    "wof:placetype":"venue"
},
  "geometry": {"coordinates":[-97.0059051514,49.8950119019],"type":"Point"}
}