{
  "type": "Feature",
  "properties": {
    "addr:full":"22262 Highway 17 Iron Bridge ON P0R 1H0",
    "addr:housenumber":"22262",
    "addr:postcode":"p0r 1h0",
    "addr:street":"Highway 17 Iron Bridge",
    "iso:country":"CA",
    "sg:address":"22262 Highway 17",
    "sg:city":"Iron Bridge",
    "sg:classifiers":[
        {
            "category":"Retail",
            "subcategory":"Repair Shop",
            "type":"Services"
        }
    ],
    "sg:phone":"+1 705 843 0506",
    "sg:postcode":"P0R 1H0",
    "sg:province":"ON",
    "sg:tags":[
        "welding"
    ],
    "wof:name":"Rousseau Welding & Mechanical",
    "wof:placetype":"venue"
},
  "geometry": {"coordinates":[-83.21959699999999,46.278603],"type":"Point"}
}