{
  "type": "Feature",
  "properties": {
    "addr:full":"Lethbridge AB T1H 2V3",
    "addr:postcode":"t1h 2v3",
    "iso:country":"CA",
    "sg:city":"Lethbridge",
    "sg:classifiers":[
        {
            "category":"Home & Garden",
            "subcategory":"Household Appliances",
            "type":"Retail Goods"
        }
    ],
    "sg:phone":"+1 403 320 0300",
    "sg:postcode":"T1H 2V3",
    "sg:province":"AB",
    "sg:tags":[
        "cleaners",
        "vacuum"
    ],
    "wof:name":"Rainbow Vacuum Sales & Svc",
    "wof:placetype":"venue"
},
  "geometry": {"coordinates":[-112.82427215600001,49.7219276428],"type":"Point"}
}