{
  "type": "Feature",
  "properties": {
    "addr:full":"General Delivery Carnarvon ON K0M 1J0",
    "addr:postcode":"k0m 1j0",
    "iso:country":"CA",
    "sg:address":"General Delivery",
    "sg:city":"Carnarvon",
    "sg:classifiers":[
        {
            "category":"Education",
            "subcategory":"Library",
            "type":"Public Place"
        }
    ],
    "sg:phone":"+1 705 489 2402",
    "sg:postcode":"K0M 1J0",
    "sg:province":"ON",
    "wof:name":"Haliburton County Public Lbry",
    "wof:placetype":"venue"
},
  "geometry": {"coordinates":[-78.69813499999999,45.045044],"type":"Point"}
}