{
  "type": "Feature",
  "properties": {
    "iso:country":"CA",
    "sg:address":"215 Shields Crt",
    "sg:city":"Markham",
    "sg:classifiers":[
        {
            "category":"Retail",
            "subcategory":"Auto Repair",
            "type":"Services"
        }
    ],
    "sg:phone":"+1 905 305 8348",
    "sg:postcode":"L3R 8V2",
    "sg:province":"ON",
    "sg:tags":[
        "transmission",
        "equipment",
        "power"
    ],
    "wof:name":"Flender Power Transmission Ltd",
    "wof:placetype":"venue"
},
  "geometry": {"coordinates":[-79.362991333,43.8333053589],"type":"Point"}
}