{
  "type": "Feature",
  "properties": {
    "addr:full":"85 Old Highway 17 N Sault Ste Marie ON P6A 5K7",
    "addr:housenumber":"85",
    "addr:postcode":"p6a 5k7",
    "addr:street":"Old Highway 17 N",
    "iso:country":"CA",
    "sg:address":"85 Old Highway 17 N",
    "sg:city":"Sault Ste Marie",
    "sg:classifiers":[
        {
            "category":"Sports & Exercise",
            "subcategory":"Golf",
            "type":"Entertainment"
        }
    ],
    "sg:phone":"+1 705 759 8776",
    "sg:postcode":"P6A 5K7",
    "sg:province":"ON",
    "sg:tags":[
        "course"
    ],
    "wof:name":"Root River Golf Club",
    "wof:placetype":"venue"
},
  "geometry": {"coordinates":[-84.3479003906,46.5182800293],"type":"Point"}
}