{
  "type": "Feature",
  "properties": {
    "addr:full":"43 Mill St W Elora ON N0B 1S0",
    "addr:housenumber":"43",
    "addr:postcode":"n0b 1s0",
    "addr:street":"Mill St W",
    "iso:country":"CA",
    "sg:address":"43 Mill St W",
    "sg:city":"Elora",
    "sg:classifiers":[
        {
            "category":"Cinema",
            "subcategory":"Movie Theater",
            "type":"Entertainment"
        }
    ],
    "sg:phone":"+1 519 846 0191",
    "sg:postcode":"N0B 1S0",
    "sg:province":"ON",
    "wof:name":"Gorge Cinema",
    "wof:placetype":"venue"
},
  "geometry": {"coordinates":[-80.430229,43.681118],"type":"Point"}
}