{
  "type": "Feature",
  "properties": {
    "addr:full":"500 Rue Commerciale O Chandler QC G0C 1K0",
    "addr:housenumber":"500",
    "addr:postcode":"g0c 1k0",
    "addr:street":"Rue Commerciale O",
    "iso:country":"CA",
    "sg:address":"500 Rue Commerciale O",
    "sg:city":"Chandler",
    "sg:classifiers":[
        {
            "category":"Autos & Motor Vehicles",
            "subcategory":"Fuel & Gas Station",
            "type":"Retail Goods"
        }
    ],
    "sg:phone":"+1 418 689 2722",
    "sg:postcode":"G0C 1K0",
    "sg:province":"QC",
    "sg:tags":[
        "oil"
    ],
    "wof:name":"Entreprises Walter Jones",
    "wof:placetype":"venue"
},
  "geometry": {"coordinates":[-64.70066799999999,48.345722],"type":"Point"}
}