{
  "type": "Feature",
  "properties": {
    "addr:full":"497 Kensington St Winnipeg MB R3J 1J8",
    "addr:housenumber":"497",
    "addr:postcode":"r3j 1j8",
    "addr:street":"Kensington St",
    "iso:country":"CA",
    "sg:address":"497 Kensington St",
    "sg:city":"Winnipeg",
    "sg:classifiers":[
        {
            "category":"Building & Trades",
            "subcategory":"Construction",
            "type":"Services"
        }
    ],
    "sg:phone":"+1 204 788 1759",
    "sg:postcode":"R3J 1J8",
    "sg:province":"MB",
    "sg:tags":[
        "painter"
    ],
    "wof:name":"Minerva Painting & Decorating",
    "wof:placetype":"venue"
},
  "geometry": {"coordinates":[-97.204574585,49.8901329041],"type":"Point"}
}