{
  "type": "Feature",
  "properties": {
    "iso:country":"CA",
    "sg:address":"208 Kaien Rd",
    "sg:city":"Prince Rupert",
    "sg:classifiers":[
        {
            "category":"Manufacturing",
            "subcategory":"Tools & Machinery",
            "type":"Manufacturing & Wholesale Goods"
        }
    ],
    "sg:phone":"+1 250 624 3253",
    "sg:postcode":"V8J 3R5",
    "sg:province":"BC",
    "sg:tags":[
        "machine",
        "shop"
    ],
    "wof:name":"Harbour Machining",
    "wof:placetype":"venue"
},
  "geometry": {"coordinates":[-130.269332886,54.3159484863],"type":"Point"}
}