{
  "type": "Feature",
  "properties": {
    "iso:country":"CA",
    "sg:address":"239 Wellington St",
    "sg:city":"St Thomas",
    "sg:classifiers":[
        {
            "category":"Retail",
            "subcategory":"Auto Repair",
            "type":"Services"
        }
    ],
    "sg:phone":"+1 519 631 6440",
    "sg:postcode":"N5R 2S6",
    "sg:province":"ON",
    "sg:tags":[
        "repairing",
        "automobile"
    ],
    "wof:name":"Midas Auto Svc Experts",
    "wof:placetype":"venue"
},
  "geometry": {"coordinates":[-81.1818237305,42.7752037048],"type":"Point"}
}