{
  "type": "Feature",
  "properties": {
    "addr:full":"Woodville Berwick NS B0P 1E0",
    "addr:postcode":"b0p 1e0",
    "iso:country":"CA",
    "sg:address":"Woodville",
    "sg:city":"Berwick",
    "sg:classifiers":[
        {
            "category":"Building & Trades",
            "subcategory":"Landscaping Services",
            "type":"Services"
        }
    ],
    "sg:phone":"+1 902 538 7829",
    "sg:postcode":"B0P 1E0",
    "sg:province":"NS",
    "sg:tags":[
        "landscape",
        "contractor"
    ],
    "wof:name":"Pride & Joy Lawn & Garden Care",
    "wof:placetype":"venue"
},
  "geometry": {"coordinates":[-64.7377243042,45.0498161316],"type":"Point"}
}