{
  "type": "Feature",
  "properties": {
    "addr:full":"54 Dunromin Ave Truro NS B2N 4M5",
    "addr:housenumber":"54",
    "addr:postcode":"b2n 4m5",
    "addr:street":"Dunromin Ave",
    "iso:country":"CA",
    "sg:address":"54 Dunromin Ave",
    "sg:city":"Truro",
    "sg:classifiers":[
        {
            "category":"Organizations",
            "subcategory":"Religious Organization",
            "type":"Services"
        }
    ],
    "sg:phone":"+1 902 895 5433",
    "sg:postcode":"B2N 4M5",
    "sg:province":"NS",
    "sg:tags":[
        "church"
    ],
    "wof:name":"Abundant Life Victory Church",
    "wof:placetype":"venue"
},
  "geometry": {"coordinates":[-63.28904,45.36602],"type":"Point"}
}