{
  "type": "Feature",
  "properties": {
    "addr:full":"1337 Queen Cres Moose Jaw SK S6H 3G5",
    "addr:housenumber":"1337",
    "addr:postcode":"s6h 3g5",
    "addr:street":"Queen Cres",
    "iso:country":"CA",
    "sg:address":"1337 Queen Cres",
    "sg:city":"Moose Jaw",
    "sg:classifiers":[
        {
            "category":"Building & Trades",
            "subcategory":"Electrical",
            "type":"Services"
        }
    ],
    "sg:phone":"+1 306 693 4044",
    "sg:postcode":"S6H 3G5",
    "sg:province":"SK",
    "sg:tags":[
        "electric",
        "contractor"
    ],
    "wof:name":"L B Clark Electric",
    "wof:placetype":"venue"
},
  "geometry": {"coordinates":[-105.573959,50.40546],"type":"Point"}
}