{
  "type": "Feature",
  "properties": {
    "iso:country":"CA",
    "sg:city":"Mississauga",
    "sg:classifiers":[
        {
            "category":"Building & Trades",
            "subcategory":"Plumbing",
            "type":"Services"
        }
    ],
    "sg:phone":"+1 905 507 6375",
    "sg:postcode":"L4Z 3E4",
    "sg:province":"ON",
    "sg:tags":[
        "air",
        "conditioning",
        "contractor",
        "system",
        "heating"
    ],
    "wof:name":"Environmental Air Systems",
    "wof:placetype":"venue"
},
  "geometry": {"coordinates":[-79.6675796509,43.6286354065],"type":"Point"}
}