{
  "type": "Feature",
  "properties": {
    "addr:full":"100 Cowdray Crt Scarborough ON M1S 5C8",
    "addr:housenumber":"100",
    "addr:postcode":"m1s 5c8",
    "addr:street":"Cowdray Crt",
    "iso:country":"CA",
    "sg:address":"100 Cowdray Crt",
    "sg:city":"Scarborough",
    "sg:classifiers":[
        {
            "category":"Professional",
            "subcategory":"Accounting & Tax Preparation",
            "type":"Services"
        }
    ],
    "sg:phone":"+1 416 293 2903",
    "sg:postcode":"M1S 5C8",
    "sg:province":"ON",
    "sg:tags":[
        "accountant"
    ],
    "wof:name":"Rcm Asian Business Ctr",
    "wof:placetype":"venue"
},
  "geometry": {"coordinates":[-79.285179,43.781013],"type":"Point"}
}