{
  "type": "Feature",
  "properties": {
    "addr:full":"1760 Rothesay Rd Rothesay NB E2H 2J5",
    "addr:housenumber":"1760",
    "addr:postcode":"e2h 2j5",
    "addr:street":"Rothesay Rd",
    "iso:country":"CA",
    "sg:address":"1760 Rothesay Rd",
    "sg:city":"Rothesay",
    "sg:classifiers":[
        {
            "category":"Organizations",
            "subcategory":"Religious Organization",
            "type":"Services"
        }
    ],
    "sg:phone":"+1 506 847 7696",
    "sg:postcode":"E2H 2J5",
    "sg:province":"NB",
    "sg:tags":[
        "church"
    ],
    "wof:name":"St James Anglican Church",
    "wof:placetype":"venue"
},
  "geometry": {"coordinates":[-66.01578521730001,45.3494491577],"type":"Point"}
}