{
  "type": "Feature",
  "properties": {
    "addr:full":"9 Hamilton Pl Saskatoon SK S7L 3N3",
    "addr:housenumber":"9",
    "addr:postcode":"s7l 3n3",
    "addr:street":"Hamilton Pl",
    "iso:country":"CA",
    "sg:address":"9 Hamilton Pl",
    "sg:city":"Saskatoon",
    "sg:classifiers":[
        {
            "category":"Wholesale",
            "subcategory":"Meat",
            "type":"Manufacturing & Wholesale Goods"
        }
    ],
    "sg:phone":"+1 306 384 3388",
    "sg:postcode":"S7L 3N3",
    "sg:province":"SK",
    "wof:name":"W A Kobie's Foods Inc",
    "wof:placetype":"venue"
},
  "geometry": {"coordinates":[-106.708862305,52.1387939453],"type":"Point"}
}