{
  "type": "Feature",
  "properties": {
    "addr:full":"2490 Bloor St W # 400 York ON M6S 1R4",
    "addr:housenumber":"2490",
    "addr:postcode":"m6s 1r4",
    "addr:street":"Bloor St W # 400",
    "iso:country":"CA",
    "sg:address":"2490 Bloor St W # 400",
    "sg:city":"York",
    "sg:classifiers":[
        {
            "category":"Professional",
            "subcategory":"Lawyer & Legal Services",
            "type":"Services"
        }
    ],
    "sg:phone":"+1 416 760 7076",
    "sg:postcode":"M6S 1R4",
    "sg:province":"ON",
    "sg:tags":[
        "attorney"
    ],
    "wof:name":"Nelson, C Ann",
    "wof:placetype":"venue"
},
  "geometry": {"coordinates":[-79.490562,43.647991],"type":"Point"}
}