{
  "type": "Feature",
  "properties": {
    "addr:full":"9516 86 Ave NW Edmonton AB T6C 1J7",
    "addr:housenumber":"9516",
    "addr:postcode":"t6c 1j7",
    "addr:street":"86 Ave Nw",
    "iso:country":"CA",
    "sg:address":"9516 86 Ave NW",
    "sg:city":"Edmonton",
    "sg:classifiers":[
        {
            "category":"Building & Trades",
            "subcategory":"Cleaning & Sanitation",
            "type":"Services"
        }
    ],
    "sg:phone":"+1 780 440 1211",
    "sg:postcode":"T6C 1J7",
    "sg:province":"AB",
    "sg:tags":[
        "furnace",
        "fireplace",
        "chimney"
    ],
    "wof:name":"Britcan Furnace Cleaning Ltd",
    "wof:placetype":"venue"
},
  "geometry": {"coordinates":[-113.473342895,53.5221405029],"type":"Point"}
}