{
  "type": "Feature",
  "properties": {
    "addr:full":"111 King St E Oshawa ON L1H 1B8",
    "addr:housenumber":"111",
    "addr:postcode":"l1h 1b8",
    "addr:street":"King St E",
    "iso:country":"CA",
    "sg:address":"111 King St E",
    "sg:city":"Oshawa",
    "sg:classifiers":[
        {
            "category":"Shopping",
            "type":"Retail Goods"
        }
    ],
    "sg:phone":"+1 905 721 3536",
    "sg:postcode":"L1H 1B8",
    "sg:province":"ON",
    "sg:tags":[
        "hearing",
        "equipment",
        "supply",
        "impaired"
    ],
    "wof:name":"Clinic Hearing Aid Ctr",
    "wof:placetype":"venue"
},
  "geometry": {"coordinates":[-78.8595657349,43.8983879089],"type":"Point"}
}