{
  "type": "Feature",
  "properties": {
    "iso:country":"CA",
    "sg:address":"100 Young St",
    "sg:city":"Ottawa",
    "sg:classifiers":[
        {
            "category":"Social Services",
            "type":"Services"
        }
    ],
    "sg:phone":"+1 613 722 8163",
    "sg:postcode":"K1Y 3P7",
    "sg:province":"ON",
    "sg:tags":[
        "counselor",
        "marriage",
        "family"
    ],
    "wof:name":"Holy Family Ctr",
    "wof:placetype":"venue"
},
  "geometry": {"coordinates":[-75.7160186768,45.4008865356],"type":"Point"}
}