{
  "type": "Feature",
  "properties": {
    "addr:full":"Dartmouth NS B3B 1J4",
    "addr:postcode":"b3b 1j4",
    "iso:country":"CA",
    "sg:city":"Dartmouth",
    "sg:classifiers":[
        {
            "category":"Manufacturing",
            "subcategory":"Metals",
            "type":"Manufacturing & Wholesale Goods"
        }
    ],
    "sg:phone":"+1 902 468 2025",
    "sg:postcode":"B3B 1J4",
    "sg:province":"NS",
    "sg:tags":[
        "fiber",
        "optics",
        "system"
    ],
    "wof:name":"Trispec Communications",
    "wof:placetype":"venue"
},
  "geometry": {"coordinates":[-63.6103057861,44.704826355],"type":"Point"}
}