{
  "type": "Feature",
  "properties": {
    "addr:full":"Ingersoll ON N5C 3J5",
    "addr:postcode":"n5c 3j5",
    "iso:country":"CA",
    "sg:city":"Ingersoll",
    "sg:classifiers":[
        {
            "category":"Professional",
            "subcategory":"Computer Services",
            "type":"Services"
        }
    ],
    "sg:phone":"+1 519 423 6703",
    "sg:postcode":"N5C 3J5",
    "sg:province":"ON",
    "sg:tags":[
        "television",
        "radio",
        "internet"
    ],
    "wof:name":"Zorra Tv & Appliances Sales",
    "wof:placetype":"venue"
},
  "geometry": {"coordinates":[-80.88385,43.038116],"type":"Point"}
}