{
  "type": "Feature",
  "properties": {
    "addr:full":"705 Matheson Blvd E Mississauga ON L4Z 3X9",
    "addr:housenumber":"705",
    "addr:postcode":"l4z 3x9",
    "addr:street":"Matheson Blvd E",
    "iso:country":"CA",
    "sg:address":"705 Matheson Blvd E",
    "sg:city":"Mississauga",
    "sg:classifiers":[
        {
            "category":"Health Services",
            "subcategory":"Health Practitioner",
            "type":"Services"
        }
    ],
    "sg:phone":"+1 905 501 7523",
    "sg:postcode":"L4Z 3X9",
    "sg:province":"ON",
    "sg:tags":[
        "nutritionist",
        "dietitian"
    ],
    "wof:name":"Nutritech",
    "wof:placetype":"venue"
},
  "geometry": {"coordinates":[-79.65068100000001,43.628452],"type":"Point"}
}