{
  "type": "Feature",
  "properties": {
    "iso:country":"CA",
    "sg:address":"1071 Rue Begin",
    "sg:city":"Saint-Laurent",
    "sg:classifiers":[
        {
            "category":"Shopping",
            "subcategory":"Stationery & Office Supplies",
            "type":"Retail Goods"
        }
    ],
    "sg:phone":"+1 514 337 6161",
    "sg:postcode":"H4R 1V8",
    "sg:province":"QC",
    "sg:tags":[
        "printing"
    ],
    "wof:name":"Papiers Experts Jm",
    "wof:placetype":"venue"
},
  "geometry": {"coordinates":[-73.711227417,45.4931221008],"type":"Point"}
}