{
  "type": "Feature",
  "properties": {
    "iso:country":"CA",
    "sg:address":"2125 11th Ave",
    "sg:city":"Regina",
    "sg:classifiers":[
        {
            "category":"Restaurant",
            "type":"Food & Drink"
        }
    ],
    "sg:phone":"+1 306 359 1555",
    "sg:postcode":"S4P 3X3",
    "sg:province":"SK",
    "wof:name":"Western Pizza",
    "wof:placetype":"venue"
},
  "geometry": {"coordinates":[-104.61125946,50.4501991272],"type":"Point"}
}