{
  "type": "Feature",
  "properties": {
    "addr:full":"1057 Barrington St Halifax NS B3H 2P8",
    "addr:housenumber":"1057",
    "addr:postcode":"b3h 2p8",
    "addr:street":"Barrington St",
    "iso:country":"CA",
    "sg:address":"1057 Barrington St",
    "sg:city":"Halifax",
    "sg:classifiers":[
        {
            "category":"Professional",
            "subcategory":"Engineering",
            "type":"Services"
        }
    ],
    "sg:phone":"+1 902 429 3790",
    "sg:postcode":"B3H 2P8",
    "sg:province":"NS",
    "sg:tags":[
        "engineer"
    ],
    "wof:name":"D & L Engineering Sales Ltd",
    "wof:placetype":"venue"
},
  "geometry": {"coordinates":[-63.569477,44.637383],"type":"Point"}
}