{
  "type": "Feature",
  "properties": {
    "iso:country":"CA",
    "sg:city":"Etobicoke",
    "sg:classifiers":[
        {
            "category":"Retail",
            "subcategory":"Auto Rental",
            "type":"Services"
        }
    ],
    "sg:phone":"+1 416 252 5074",
    "sg:postcode":"M8Z 1K2",
    "sg:province":"ON",
    "sg:tags":[
        "renting",
        "truck",
        "leasing"
    ],
    "wof:name":"Project Truck Rentals Ltd",
    "wof:placetype":"venue"
},
  "geometry": {"coordinates":[-79.5240402222,43.6158180237],"type":"Point"}
}