{
  "type": "Feature",
  "properties": {
    "iso:country":"CA",
    "sg:address":"140 Waverley Dr",
    "sg:city":"Guelph",
    "sg:classifiers":[
        {
            "category":"Education",
            "subcategory":"School",
            "type":"Public Place"
        }
    ],
    "sg:phone":"+1 519 824 7742",
    "sg:postcode":"N1E 1H2",
    "sg:province":"ON",
    "wof:name":"Waverley Drive Public School",
    "wof:placetype":"venue"
},
  "geometry": {"coordinates":[-80.2588806152,43.5728302002],"type":"Point"}
}