{
  "type": "Feature",
  "properties": {
    "addr:full":"355 Rue Montcalm Rosemere QC J7A 3B2",
    "addr:housenumber":"355",
    "addr:postcode":"j7a 3b2",
    "addr:street":"Rue Montcalm",
    "iso:country":"CA",
    "sg:address":"355 Rue Montcalm",
    "sg:city":"Rosemere",
    "sg:classifiers":[
        {
            "category":"Professional",
            "subcategory":"Accounting & Tax Preparation",
            "type":"Services"
        }
    ],
    "sg:phone":"+1 450 621 6930",
    "sg:postcode":"J7A 3B2",
    "sg:province":"QC",
    "sg:tags":[
        "accountant"
    ],
    "wof:name":"Gruman, Victor",
    "wof:placetype":"venue"
},
  "geometry": {"coordinates":[-73.799896,45.644657],"type":"Point"}
}