{
  "type": "Feature",
  "properties": {
    "addr:full":"1480 Boul Saint-Joseph E Montreal QC H2J 1M5",
    "addr:housenumber":"1480",
    "addr:postcode":"h2j 1m5",
    "addr:street":"Boul Saint-Joseph E",
    "iso:country":"CA",
    "sg:address":"1480 Boul Saint-Joseph E",
    "sg:city":"Montreal",
    "sg:classifiers":[
        {
            "category":"Health Services",
            "subcategory":"Doctor",
            "type":"Services"
        }
    ],
    "sg:phone":"+1 514 521 4395",
    "sg:postcode":"H2J 1M5",
    "sg:province":"QC",
    "sg:tags":[
        "physician",
        "surgeon"
    ],
    "wof:name":"G A Gervais Inc",
    "wof:placetype":"venue"
},
  "geometry": {"coordinates":[-73.58074999999999,45.533558],"type":"Point"}
}