{
  "type": "Feature",
  "properties": {
    "addr:full":"Vancouver BC V5L 4B2",
    "addr:postcode":"v5l 4b2",
    "iso:country":"CA",
    "sg:city":"Vancouver",
    "sg:classifiers":[
        {
            "category":"Building & Trades",
            "subcategory":"Landscaping Services",
            "type":"Services"
        }
    ],
    "sg:phone":"+1 604 253 8994",
    "sg:postcode":"V5L 4B2",
    "sg:province":"BC",
    "sg:tags":[
        "landscape",
        "contractor"
    ],
    "wof:name":"Lilla Landscaping",
    "wof:placetype":"venue"
},
  "geometry": {"coordinates":[-123.06740600000001,49.273678],"type":"Point"}
}