{
  "type": "Feature",
  "properties": {
    "iso:country":"CA",
    "sg:city":"Surrey",
    "sg:classifiers":[
        {
            "category":"Arts & Performance",
            "subcategory":"Theater",
            "type":"Entertainment"
        }
    ],
    "sg:phone":"+1 604 531 8209",
    "sg:postcode":"V4A 9C5",
    "sg:province":"BC",
    "sg:tags":[
        "instruction",
        "music"
    ],
    "wof:name":"Hlus, Donald G",
    "wof:placetype":"venue"
},
  "geometry": {"coordinates":[-122.80364227299999,49.0355491638],"type":"Point"}
}