{
  "type": "Feature",
  "properties": {
    "addr:full":"1309 Bay Ave Trail BC V1R 4A7",
    "addr:housenumber":"1309",
    "addr:postcode":"bc v1r 4a7",
    "addr:street":"Bay Ave Trail",
    "iso:country":"CA",
    "sg:address":"1309 Bay Ave",
    "sg:city":"Trail",
    "sg:classifiers":[
        {
            "category":"Professional",
            "subcategory":"Lawyer & Legal Services",
            "type":"Services"
        }
    ],
    "sg:phone":"+1 250 368 6455",
    "sg:postcode":"V1R 4A7",
    "sg:province":"BC",
    "sg:tags":[
        "attorney"
    ],
    "wof:name":"Cromarty, Barbara",
    "wof:placetype":"venue"
},
  "geometry": {"coordinates":[-117.70779419,49.096157074],"type":"Point"}
}