{
  "type": "Feature",
  "properties": {
    "addr:full":"Calgary AB T2H 2S1",
    "addr:postcode":"t2h 2s1",
    "iso:country":"CA",
    "sg:city":"Calgary",
    "sg:classifiers":[
        {
            "category":"Home & Garden",
            "subcategory":"Furniture",
            "type":"Retail Goods"
        }
    ],
    "sg:phone":"+1 403 253 8200",
    "sg:postcode":"T2H 2S1",
    "sg:province":"AB",
    "wof:name":"Bondar's Fine Furniture",
    "wof:placetype":"venue"
},
  "geometry": {"coordinates":[-114.04019165,50.9913215637],"type":"Point"}
}