{
  "type": "Feature",
  "properties": {
    "addr:full":"379 Dundas St London ON N6B 1V5",
    "addr:housenumber":"379",
    "addr:postcode":"n6b 1v5",
    "addr:street":"Dundas St",
    "iso:country":"CA",
    "sg:address":"379 Dundas St",
    "sg:city":"London",
    "sg:classifiers":[
        {
            "category":"Social Services",
            "type":"Services"
        }
    ],
    "sg:phone":"+1 519 434 7111",
    "sg:postcode":"N6B 1V5",
    "sg:province":"ON",
    "sg:tags":[
        "organization",
        "welfare"
    ],
    "wof:name":"Children in Need Program Inc",
    "wof:placetype":"venue"
},
  "geometry": {"coordinates":[-81.2407531738,42.9860725403],"type":"Point"}
}