{
  "type": "Feature",
  "properties": {
    "iso:country":"CA",
    "sg:address":"17 Montgomerie St",
    "sg:city":"Corner Brook",
    "sg:classifiers":[
        {
            "category":"Social Services",
            "subcategory":"Child Care",
            "type":"Services"
        }
    ],
    "sg:phone":"+1 709 637 2121",
    "sg:postcode":"A2H 2P8",
    "sg:province":"NL",
    "sg:tags":[
        "kindergarten",
        "academic",
        "school"
    ],
    "wof:name":"Academy Canada Daycare",
    "wof:placetype":"venue"
},
  "geometry": {"coordinates":[-57.9298858643,48.9509086609],"type":"Point"}
}