{
  "type": "Feature",
  "properties": {
    "addr:full":"Scarborough ON M1K 2N8",
    "addr:postcode":"m1k 2n8",
    "iso:country":"CA",
    "sg:city":"Scarborough",
    "sg:classifiers":[
        {
            "category":"Health Services",
            "subcategory":"Chiropractor",
            "type":"Services"
        }
    ],
    "sg:phone":"+1 416 755 7017",
    "sg:postcode":"M1K 2N8",
    "sg:province":"ON",
    "wof:name":"Proactive Chiropractic Group",
    "wof:placetype":"venue"
},
  "geometry": {"coordinates":[-79.2687835693,43.7318954468],"type":"Point"}
}