{
  "type": "Feature",
  "properties": {
    "addr:full":"324 2nd St Kamsack SK S0A 1S0",
    "addr:housenumber":"324",
    "addr:postcode":"s0a 1s0",
    "addr:street":"2Nd St",
    "iso:country":"CA",
    "sg:address":"324 2nd St",
    "sg:city":"Kamsack",
    "sg:classifiers":[
        {
            "category":"Organizations",
            "subcategory":"Professional Association",
            "type":"Services"
        }
    ],
    "sg:phone":"+1 306 542 2686",
    "sg:postcode":"S0A 1S0",
    "sg:province":"SK",
    "sg:tags":[
        "club"
    ],
    "wof:name":"Royal Canadian Legion",
    "wof:placetype":"venue"
},
  "geometry": {"coordinates":[-101.89679717999999,51.5607948303],"type":"Point"}
}