{
  "type": "Feature",
  "properties": {
    "addr:full":"25 Cedar Dr Stellarton NS B0K 1S0",
    "addr:housenumber":"25",
    "addr:postcode":"b0k 1s0",
    "addr:street":"Cedar Dr",
    "iso:country":"CA",
    "sg:address":"25 Cedar Dr",
    "sg:city":"Stellarton",
    "sg:classifiers":[
        {
            "category":"Building & Trades",
            "subcategory":"Construction",
            "type":"Services"
        }
    ],
    "sg:phone":"+1 902 752 4172",
    "sg:postcode":"B0K 1S0",
    "sg:province":"NS",
    "sg:tags":[
        "well",
        "drilling"
    ],
    "wof:name":"C & J Martin Well Drilling CO",
    "wof:placetype":"venue"
},
  "geometry": {"coordinates":[-62.6750106812,45.548122406],"type":"Point"}
}