{
  "type": "Feature",
  "properties": {
    "addr:full":"8695 10th Ave Burnaby BC V3N 2S9",
    "addr:housenumber":"8695",
    "addr:postcode":"v3n 2s9",
    "addr:street":"10Th Ave",
    "iso:country":"CA",
    "sg:address":"8695 10th Ave",
    "sg:city":"Burnaby",
    "sg:classifiers":[
        {
            "category":"Health Services",
            "subcategory":"Doctor",
            "type":"Services"
        }
    ],
    "sg:phone":"+1 604 526 8030",
    "sg:postcode":"V3N 2S9",
    "sg:province":"BC",
    "sg:tags":[
        "dentist"
    ],
    "wof:name":"Battrum, Herb A DDS",
    "wof:placetype":"venue"
},
  "geometry": {"coordinates":[-122.90546399999999,49.23106],"type":"Point"}
}