{
  "type": "Feature",
  "properties": {
    "iso:country":"CA",
    "sg:address":"770 Mohawk Rd W #2",
    "sg:city":"Hamilton",
    "sg:classifiers":[
        {
            "category":"Health Services",
            "subcategory":"Doctor",
            "type":"Services"
        }
    ],
    "sg:phone":"+1 905 388 4543",
    "sg:postcode":"L9C 1X9",
    "sg:province":"ON",
    "sg:tags":[
        "physician",
        "surgeon"
    ],
    "wof:name":"Black, Rick MD",
    "wof:placetype":"venue"
},
  "geometry": {"coordinates":[-79.9201507568,43.2337875366],"type":"Point"}
}