{
  "type": "Feature",
  "properties": {
    "iso:country":"CA",
    "sg:city":"Markham",
    "sg:classifiers":[
        {
            "category":"Freight",
            "type":"Transportation"
        }
    ],
    "sg:phone":"+1 905 513 9600",
    "sg:postcode":"L3R 9R7",
    "sg:province":"ON",
    "sg:tags":[
        "delivery",
        "courier"
    ],
    "wof:name":"Little Guys Delivery",
    "wof:placetype":"venue"
},
  "geometry": {"coordinates":[-79.331024,43.837372],"type":"Point"}
}