{
  "type": "Feature",
  "properties": {
    "addr:full":"Main St E Ridgetown ON N0P 2C0",
    "addr:postcode":"n0p 2c0",
    "addr:street":"Main St E",
    "iso:country":"CA",
    "sg:address":"Main St E",
    "sg:city":"Ridgetown",
    "sg:classifiers":[
        {
            "category":"Professional",
            "subcategory":"Management & Consulting",
            "type":"Services"
        }
    ],
    "sg:phone":"+1 519 674 1595",
    "sg:postcode":"N0P 2C0",
    "sg:province":"ON",
    "sg:tags":[
        "agricultural",
        "consultant"
    ],
    "wof:name":"Kent Federation of Agriculture",
    "wof:placetype":"venue"
},
  "geometry": {"coordinates":[-81.878586,42.445091],"type":"Point"}
}