{
  "type": "Feature",
  "properties": {
    "addr:full":"536 133 Rte Sabrevois QC J0J 2G0",
    "addr:housenumber":"133",
    "addr:postcode":"j0j 2g0",
    "addr:street":"Rte Sabrevois",
    "iso:country":"CA",
    "sg:address":"536 133 Rte",
    "sg:city":"Sabrevois",
    "sg:classifiers":[
        {
            "category":"Shopping",
            "subcategory":"Used Merchandise",
            "type":"Retail Goods"
        }
    ],
    "sg:phone":"+1 450 347 0426",
    "sg:postcode":"J0J 2G0",
    "sg:province":"QC",
    "sg:tags":[
        "furniture"
    ],
    "wof:name":"Maxi Meubles",
    "wof:placetype":"venue"
},
  "geometry": {"coordinates":[-73.23049899999999,45.20639],"type":"Point"}
}