{
  "type": "Feature",
  "properties": {
    "iso:country":"CA",
    "sg:city":"Winnipeg",
    "sg:classifiers":[
        {
            "category":"Real Estate",
            "subcategory":"Real Estate Agent",
            "type":"Services"
        }
    ],
    "sg:phone":"+1 204 943 1933",
    "sg:postcode":"R3C 1C4",
    "sg:province":"MB",
    "sg:tags":[
        "consultant",
        "company",
        "land"
    ],
    "wof:name":"M R Consultants Inc",
    "wof:placetype":"venue"
},
  "geometry": {"coordinates":[-97.135597229,49.8868026733],"type":"Point"}
}