{
  "type": "Feature",
  "properties": {
    "addr:full":"RR 2 Lcd Main Orangeville ON L9W 2Y9",
    "addr:postcode":"l9w 2y9",
    "addr:street":"Rr 2 Lcd Main",
    "iso:country":"CA",
    "sg:address":"RR 2 Lcd Main",
    "sg:city":"Orangeville",
    "sg:classifiers":[
        {
            "category":"Freight",
            "type":"Transportation"
        }
    ],
    "sg:phone":"+1 519 942 4080",
    "sg:postcode":"L9W 2Y9",
    "sg:province":"ON",
    "sg:tags":[
        "trucking"
    ],
    "wof:name":"Jonker Trucking Inc",
    "wof:placetype":"venue"
},
  "geometry": {"coordinates":[-80.093491,43.920116],"type":"Point"}
}