{
  "type": "Feature",
  "properties": {
    "addr:full":"15 Gourok Ave Dartmouth NS B2X 2B1",
    "addr:housenumber":"15",
    "addr:postcode":"b2x 2b1",
    "addr:street":"Gourok Ave",
    "iso:country":"CA",
    "sg:address":"15 Gourok Ave",
    "sg:city":"Dartmouth",
    "sg:classifiers":[
        {
            "category":"Wholesale",
            "subcategory":"Machinery & Supplies",
            "type":"Manufacturing & Wholesale Goods"
        }
    ],
    "sg:phone":"+1 902 434 9516",
    "sg:postcode":"B2X 2B1",
    "sg:province":"NS",
    "sg:tags":[
        "electrolysis",
        "beauty"
    ],
    "wof:name":"Tlc Electrolysis",
    "wof:placetype":"venue"
},
  "geometry": {"coordinates":[-63.53727,44.695332],"type":"Point"}
}