{
  "type": "Feature",
  "properties": {
    "addr:full":"1 St. Paul St St Catharines ON L2R 7L2",
    "addr:housenumber":"1",
    "addr:postcode":"l2r 7l2",
    "addr:street":"St. Paul St",
    "iso:country":"CA",
    "sg:address":"1 St. Paul St",
    "sg:city":"St Catharines",
    "sg:classifiers":[
        {
            "category":"Restaurant",
            "type":"Food & Drink"
        }
    ],
    "sg:phone":"+1 905 684 9219",
    "sg:postcode":"L2R 7L2",
    "sg:province":"ON",
    "wof:name":"Red Hot Chili Pepper Bar",
    "wof:placetype":"venue"
},
  "geometry": {"coordinates":[-79.245766,43.1553],"type":"Point"}
}