{
  "type": "Feature",
  "properties": {
    "iso:country":"CA",
    "sg:address":"65 University Ave E",
    "sg:city":"Waterloo",
    "sg:classifiers":[
        {
            "category":"Personal",
            "subcategory":"Beauty Salon",
            "type":"Services"
        }
    ],
    "sg:phone":"+1 519 886 3232",
    "sg:postcode":"N2J 2V9",
    "sg:province":"ON",
    "wof:name":"Appearances Hair & Beauty",
    "wof:placetype":"venue"
},
  "geometry": {"coordinates":[-80.5215682983,43.4772453308],"type":"Point"}
}