{
  "type": "Feature",
  "properties": {
    "iso:country":"CA",
    "sg:address":"730 Griffith Crt",
    "sg:city":"Burlington",
    "sg:classifiers":[
        {
            "category":"Wholesale",
            "subcategory":"Machinery & Supplies",
            "type":"Manufacturing & Wholesale Goods"
        }
    ],
    "sg:phone":"+1 905 634 7375",
    "sg:postcode":"L7L 5R9",
    "sg:province":"ON",
    "sg:tags":[
        "equipment",
        "mining"
    ],
    "wof:name":"Unacom Mineral Processing Inc",
    "wof:placetype":"venue"
},
  "geometry": {"coordinates":[-79.772202,43.366604],"type":"Point"}
}