{
  "type": "Feature",
  "properties": {
    "iso:country":"CA",
    "sg:city":"Quebec",
    "sg:classifiers":[
        {
            "category":"Banks & Credit Unions",
            "subcategory":"Investment Brokerage",
            "type":"Services"
        }
    ],
    "sg:phone":"+1 418 624 4600",
    "sg:postcode":"G2K 2H6",
    "sg:province":"QC",
    "sg:tags":[
        "advisory",
        "financial"
    ],
    "wof:name":"Services Financiers Teraxis",
    "wof:placetype":"venue"
},
  "geometry": {"coordinates":[-71.2969055176,46.833278656],"type":"Point"}
}