{
  "type": "Feature",
  "properties": {
    "addr:full":"4 Sunset Crt Smiths Creek NB E4G 2T9",
    "addr:housenumber":"4",
    "addr:postcode":"e4g 2t9",
    "addr:street":"Sunset Crt;Creek",
    "iso:country":"CA",
    "sg:address":"4 Sunset Crt",
    "sg:city":"Smiths Creek",
    "sg:classifiers":[
        {
            "category":"Manufacturing",
            "subcategory":"Tools & Machinery",
            "type":"Manufacturing & Wholesale Goods"
        }
    ],
    "sg:phone":"+1 506 432 4196",
    "sg:postcode":"E4G 2T9",
    "sg:province":"NB",
    "sg:tags":[
        "equipment",
        "system",
        "automation"
    ],
    "wof:name":"Kontrol Automation & Computer",
    "wof:placetype":"venue"
},
  "geometry": {"coordinates":[-65.483566,45.778488],"type":"Point"}
}