{
  "type": "Feature",
  "properties": {
    "addr:full":"St-Paul QC J6E 8K7",
    "addr:postcode":"j6e 8k7",
    "iso:country":"CA",
    "sg:city":"St-Paul",
    "sg:classifiers":[
        {
            "category":"Wholesale",
            "subcategory":"Stationery",
            "type":"Manufacturing & Wholesale Goods"
        }
    ],
    "sg:phone":"+1 450 756 0000",
    "sg:postcode":"J6E 8K7",
    "sg:province":"QC",
    "sg:tags":[
        "cardboard"
    ],
    "wof:name":"Cartons Rlf",
    "wof:placetype":"venue"
},
  "geometry": {"coordinates":[-73.44556427000001,45.9850463867],"type":"Point"}
}