{
  "type": "Feature",
  "properties": {
    "iso:country":"CA",
    "sg:address":"9960 Ch DE LA Cote-DE-Liesse",
    "sg:city":"Lachine",
    "sg:classifiers":[
        {
            "category":"Wholesale",
            "subcategory":"Groceries",
            "type":"Manufacturing & Wholesale Goods"
        }
    ],
    "sg:phone":"+1 514 636 5114",
    "sg:postcode":"H8T 1A1",
    "sg:province":"QC",
    "sg:tags":[
        "frozen",
        "food",
        "broker"
    ],
    "wof:name":"Fishery Products Intl",
    "wof:placetype":"venue"
},
  "geometry": {"coordinates":[-73.7148971558,45.4678077698],"type":"Point"}
}