{
  "type": "Feature",
  "properties": {
    "addr:full":"Lethbridge AB T1K 2R3",
    "addr:postcode":"t1k 2r3",
    "iso:country":"CA",
    "sg:city":"Lethbridge",
    "sg:classifiers":[
        {
            "category":"Personal",
            "type":"Services"
        }
    ],
    "sg:phone":"+1 403 315 0376",
    "sg:postcode":"T1K 2R3",
    "sg:province":"AB",
    "sg:tags":[
        "therapist",
        "massage"
    ],
    "wof:name":"Perfect Balance Massage",
    "wof:placetype":"venue"
},
  "geometry": {"coordinates":[-112.80297899999999,49.678196],"type":"Point"}
}