{
  "type": "Feature",
  "properties": {
    "addr:full":"125 Wellington St W Aurora ON L4G 2P3",
    "addr:housenumber":"125",
    "addr:postcode":"l4g 2p3",
    "addr:street":"Wellington St W",
    "iso:country":"CA",
    "sg:address":"125 Wellington St W",
    "sg:city":"Aurora",
    "sg:classifiers":[
        {
            "category":"Professional",
            "subcategory":"Research",
            "type":"Services"
        }
    ],
    "sg:phone":"+1 905 841 9030",
    "sg:postcode":"L4G 2P3",
    "sg:province":"ON",
    "sg:tags":[
        "foundation",
        "philanthropic"
    ],
    "wof:name":"Jump Rope For Heart",
    "wof:placetype":"venue"
},
  "geometry": {"coordinates":[-79.477684021,43.9973182678],"type":"Point"}
}