{
  "type": "Feature",
  "properties": {
    "addr:full":"1071 Midland Ave Scarborough ON M1K 4G7",
    "addr:housenumber":"1071",
    "addr:postcode":"m1k 4g7",
    "addr:street":"Midland Ave",
    "iso:country":"CA",
    "sg:address":"1071 Midland Ave",
    "sg:city":"Scarborough",
    "sg:classifiers":[
        {
            "category":"Organizations",
            "subcategory":"Religious Organization",
            "type":"Services"
        }
    ],
    "sg:phone":"+1 416 701 1831",
    "sg:postcode":"M1K 4G7",
    "sg:province":"ON",
    "wof:name":"Marketplace Ministries",
    "wof:placetype":"venue"
},
  "geometry": {"coordinates":[-79.26108551030001,43.7421340942],"type":"Point"}
}