{
  "type": "Feature",
  "properties": {
    "addr:full":"7894 Ch Du Portage-Des-Roches Laterriere QC G7N 2A1",
    "addr:postcode":"7894;g7n 2a1",
    "addr:street":"Ch Du Portage-Des-Roches Laterriere",
    "iso:country":"CA",
    "sg:address":"7894 Ch Du Portage-Des-Roches",
    "sg:city":"Laterriere",
    "sg:classifiers":[
        {
            "category":"Travel",
            "subcategory":"Campground",
            "type":"Entertainment"
        }
    ],
    "sg:phone":"+1 418 678 2657",
    "sg:postcode":"G7N 2A1",
    "sg:province":"QC",
    "wof:name":"Camping LA Rocaille",
    "wof:placetype":"venue"
},
  "geometry": {"coordinates":[-71.1992721558,48.3081817627],"type":"Point"}
}