{
  "type": "Feature",
  "properties": {
    "addr:full":"573 1/2 Grey St London ON N6B 1H6",
    "addr:housenumber":"573 1 / 2",
    "addr:postcode":"n6b 1h6",
    "addr:street":"Grey St",
    "iso:country":"CA",
    "sg:address":"573 1/2 Grey St",
    "sg:city":"London",
    "sg:classifiers":[
        {
            "category":"Building & Trades",
            "subcategory":"Construction",
            "type":"Services"
        }
    ],
    "sg:phone":"+1 519 663 1182",
    "sg:postcode":"N6B 1H6",
    "sg:province":"ON",
    "sg:tags":[
        "downspouts",
        "gutter"
    ],
    "wof:name":"Ken Geddes & Son Sheet Metal",
    "wof:placetype":"venue"
},
  "geometry": {"coordinates":[-81.229347,42.981037],"type":"Point"}
}