{
  "type": "Feature",
  "properties": {
    "addr:full":"1200 Boul Chomedey #770 Laval QC H7V 3Z3",
    "addr:housenumber":"1200;# 770",
    "addr:postcode":"h7v 3z3",
    "addr:street":"Boul Chomedey",
    "iso:country":"CA",
    "sg:address":"1200 Boul Chomedey #770",
    "sg:city":"Laval",
    "sg:classifiers":[
        {
            "category":"Insurance",
            "subcategory":"Insurance Agent",
            "type":"Services"
        }
    ],
    "sg:phone":"+1 450 686 4066",
    "sg:postcode":"H7V 3Z3",
    "sg:province":"QC",
    "wof:name":"Arcand Hayhurst Assoc Inc",
    "wof:placetype":"venue"
},
  "geometry": {"coordinates":[-73.743835,45.54924],"type":"Point"}
}