{
  "type": "Feature",
  "properties": {
    "addr:full":"2903 Dewdney Ave Regina SK S4T 0Y1",
    "addr:housenumber":"2903",
    "addr:postcode":"s4t 0y1",
    "addr:street":"Dewdney Ave",
    "iso:country":"CA",
    "sg:address":"2903 Dewdney Ave",
    "sg:city":"Regina",
    "sg:classifiers":[
        {
            "category":"Wholesale",
            "subcategory":"Electrical",
            "type":"Manufacturing & Wholesale Goods"
        }
    ],
    "sg:phone":"+1 306 522 3667",
    "sg:postcode":"S4T 0Y1",
    "sg:province":"SK",
    "sg:tags":[
        "alarm",
        "burglar",
        "system"
    ],
    "wof:name":"L S Security",
    "wof:placetype":"venue"
},
  "geometry": {"coordinates":[-104.622704,50.454998],"type":"Point"}
}