{
  "type": "Feature",
  "properties": {
    "iso:country":"CA",
    "sg:address":"576 Church St",
    "sg:city":"Toronto",
    "sg:classifiers":[
        {
            "category":"Health Services",
            "subcategory":"Hospital",
            "type":"Services"
        }
    ],
    "sg:phone":"+1 416 323 0223",
    "sg:postcode":"M4Y 2E3",
    "sg:province":"ON",
    "sg:tags":[
        "organization",
        "social",
        "mental",
        "welfare"
    ],
    "wof:name":"Progress Place Rehab Ctr",
    "wof:placetype":"venue"
},
  "geometry": {"coordinates":[-79.381378,43.666706],"type":"Point"}
}