{
  "type": "Feature",
  "properties": {
    "addr:full":"7330 Rue Saint-Hubert Montreal QC H2R 2N3",
    "addr:housenumber":"7330",
    "addr:postcode":"h2r 2n3",
    "addr:street":"Rue Saint-Hubert",
    "iso:country":"CA",
    "sg:address":"7330 Rue Saint-Hubert",
    "sg:city":"Montreal",
    "sg:classifiers":[
        {
            "category":"Shopping",
            "subcategory":"Pharmacy",
            "type":"Retail Goods"
        }
    ],
    "sg:phone":"+1 514 279 6369",
    "sg:postcode":"H2R 2N3",
    "sg:province":"QC",
    "wof:name":"Nguyen, Lan",
    "wof:placetype":"venue"
},
  "geometry": {"coordinates":[-73.6156997681,45.5417327881],"type":"Point"}
}