{
  "type": "Feature",
  "properties": {
    "addr:full":"812 College St Toronto ON M6G 1C8",
    "addr:housenumber":"812",
    "addr:postcode":"m6g 1c8",
    "addr:street":"College St",
    "iso:country":"CA",
    "sg:address":"812 College St",
    "sg:city":"Toronto",
    "sg:classifiers":[
        {
            "category":"Food & Beverages",
            "subcategory":"Bakery",
            "type":"Retail Goods"
        }
    ],
    "sg:phone":"+1 416 536 9981",
    "sg:postcode":"M6G 1C8",
    "sg:province":"ON",
    "sg:tags":[
        "baker"
    ],
    "wof:name":"National Bakery & Pastry",
    "wof:placetype":"venue"
},
  "geometry": {"coordinates":[-79.421989,43.654678],"type":"Point"}
}