{
  "type": "Feature",
  "properties": {
    "addr:full":"857 Boul Des Bois-Francs S Victoriaville QC G6P 5W1",
    "addr:housenumber":"857",
    "addr:postcode":"g6p 5w1",
    "addr:street":"Boul Des Bois-Francs S",
    "iso:country":"CA",
    "sg:address":"857 Boul Des Bois-Francs S",
    "sg:city":"Victoriaville",
    "sg:classifiers":[
        {
            "category":"Manufacturing",
            "subcategory":"Leather Goods",
            "type":"Manufacturing & Wholesale Goods"
        }
    ],
    "sg:phone":"+1 819 357 3138",
    "sg:postcode":"G6P 5W1",
    "sg:province":"QC",
    "sg:tags":[
        "clothes"
    ],
    "wof:name":"Cuirs Rochefort",
    "wof:placetype":"venue"
},
  "geometry": {"coordinates":[-71.91935700000001,46.04052],"type":"Point"}
}