{
  "type": "Feature",
  "properties": {
    "iso:country":"CA",
    "sg:address":"19982 56 Ave",
    "sg:city":"Langley",
    "sg:classifiers":[
        {
            "category":"Retail",
            "subcategory":"Auto Repair",
            "type":"Services"
        }
    ],
    "sg:phone":"+1 604 514 8759",
    "sg:postcode":"V3A 3X9",
    "sg:province":"BC",
    "sg:tags":[
        "repairing",
        "automobile"
    ],
    "wof:name":"Husky Garage",
    "wof:placetype":"venue"
},
  "geometry": {"coordinates":[-122.66904449499999,49.1042633057],"type":"Point"}
}