{
  "type": "Feature",
  "properties": {
    "addr:full":"398 Aberdeen St SE Medicine Hat AB T1A 0R2",
    "addr:housenumber":"398",
    "addr:postcode":"t1a 0r2",
    "addr:street":"Aberdeen St Se",
    "iso:country":"CA",
    "sg:address":"398 Aberdeen St SE",
    "sg:city":"Medicine Hat",
    "sg:classifiers":[
        {
            "category":"Shopping",
            "subcategory":"Bicycles & Sporting Goods",
            "type":"Retail Goods"
        }
    ],
    "sg:phone":"+1 403 580 3133",
    "sg:postcode":"T1A 0R2",
    "sg:province":"AB",
    "sg:tags":[
        "archery",
        "range"
    ],
    "wof:name":"Teliske Archery",
    "wof:placetype":"venue"
},
  "geometry": {"coordinates":[-110.677727,50.035961],"type":"Point"}
}