{
  "type": "Feature",
  "properties": {
    "addr:full":"PO Box 239 Joussard AB T0G 1J0",
    "addr:housenumber":"po",
    "addr:postcode":"t0g 1j0",
    "addr:street":"Box 239 Joussard",
    "iso:country":"CA",
    "sg:address":"PO Box 239",
    "sg:city":"Joussard",
    "sg:classifiers":[
        {
            "category":"Social Services",
            "type":"Services"
        }
    ],
    "sg:phone":"+1 780 776 3811",
    "sg:postcode":"T0G 1J0",
    "sg:province":"AB",
    "sg:tags":[
        "organization",
        "welfare"
    ],
    "wof:name":"Big Lakes Family & Comm Svc",
    "wof:placetype":"venue"
},
  "geometry": {"coordinates":[-115.95022582999999,55.3978767395],"type":"Point"}
}