{
  "type": "Feature",
  "properties": {
    "addr:full":"1072 Bloor St W Toronto ON M6H 1M6",
    "addr:housenumber":"1072",
    "addr:postcode":"m6h 1m6",
    "addr:street":"Bloor St W",
    "iso:country":"CA",
    "sg:address":"1072 Bloor St W",
    "sg:city":"Toronto",
    "sg:classifiers":[
        {
            "category":"Shopping",
            "type":"Retail Goods"
        }
    ],
    "sg:phone":"+1 416 516 9277",
    "sg:postcode":"M6H 1M6",
    "sg:province":"ON",
    "sg:tags":[
        "shop",
        "bridal",
        "wedding",
        "supply"
    ],
    "wof:name":"Youthful Dreams",
    "wof:placetype":"venue"
},
  "geometry": {"coordinates":[-79.43351,43.660381],"type":"Point"}
}