{
  "type": "Feature",
  "properties": {
    "iso:country":"CA",
    "sg:address":"6238 Rue Iberville",
    "sg:city":"Montreal",
    "sg:classifiers":[
        {
            "category":"Retail",
            "subcategory":"Auto Repair",
            "type":"Services"
        }
    ],
    "sg:phone":"+1 514 376 7767",
    "sg:postcode":"H2J 2C4",
    "sg:province":"QC",
    "sg:tags":[
        "repairing",
        "automobile"
    ],
    "wof:name":"Garage Jean-Marc Boucher Inc",
    "wof:placetype":"venue"
},
  "geometry": {"coordinates":[-73.58897399999999,45.547604],"type":"Point"}
}