{
  "type": "Feature",
  "properties": {
    "addr:full":"1270 Rue DE Repentigny Quebec QC G1S 1Y3",
    "addr:housenumber":"1270",
    "addr:postcode":"g1s 1y3",
    "addr:street":"Rue De Repentigny",
    "iso:country":"CA",
    "sg:address":"1270 Rue DE Repentigny",
    "sg:city":"Quebec",
    "sg:classifiers":[
        {
            "category":"Health Services",
            "subcategory":"Health Practitioner",
            "type":"Services"
        }
    ],
    "sg:phone":"+1 418 681 0038",
    "sg:postcode":"G1S 1Y3",
    "sg:province":"QC",
    "sg:tags":[
        "psychologist"
    ],
    "wof:name":"Bernier, Marielle",
    "wof:placetype":"venue"
},
  "geometry": {"coordinates":[-71.2491,46.792656],"type":"Point"}
}