{
  "type": "Feature",
  "properties": {
    "addr:full":"125 Deplonty Rd Bruce Mines ON P0R 1C0",
    "addr:housenumber":"125",
    "addr:postcode":"p0r 1c0",
    "addr:street":"Deplonty Rd",
    "iso:country":"CA",
    "sg:address":"125 Deplonty Rd",
    "sg:city":"Bruce Mines",
    "sg:classifiers":[
        {
            "category":"Home & Garden",
            "subcategory":"Garden Supply",
            "type":"Retail Goods"
        }
    ],
    "sg:phone":"+1 705 782 6677",
    "sg:postcode":"P0R 1C0",
    "sg:province":"ON",
    "sg:tags":[
        "nurseryman",
        "center"
    ],
    "wof:name":"Lawrence's Springwater Farms",
    "wof:placetype":"venue"
},
  "geometry": {"coordinates":[-83.7941436768,46.3002090454],"type":"Point"}
}