{
  "type": "Feature",
  "properties": {
    "addr:full":"26 Bloor St Capreol ON P0M 1H0",
    "addr:housenumber":"26",
    "addr:postcode":"p0m 1h0",
    "addr:street":"Bloor St",
    "iso:country":"CA",
    "sg:address":"26 Bloor St",
    "sg:city":"Capreol",
    "sg:classifiers":[
        {
            "category":"Museum",
            "type":"Entertainment"
        }
    ],
    "sg:phone":"+1 705 858 5050",
    "sg:postcode":"P0M 1H0",
    "sg:province":"ON",
    "sg:tags":[
        "government"
    ],
    "wof:name":"Northern Ontario Railroad Msum",
    "wof:placetype":"venue"
},
  "geometry": {"coordinates":[-80.921875,46.7052268982],"type":"Point"}
}