{
  "type": "Feature",
  "properties": {
    "iso:country":"CA",
    "sg:address":"579 Boul Sainte-Madeleine",
    "sg:city":"Sainte-Marthe-Du-Cap",
    "sg:classifiers":[
        {
            "category":"Manufacturing",
            "subcategory":"Metals",
            "type":"Manufacturing & Wholesale Goods"
        }
    ],
    "sg:phone":"+1 819 693 4039",
    "sg:postcode":"G8T 9J8",
    "sg:province":"QC",
    "sg:tags":[
        "plumbing",
        "fixture",
        "supply"
    ],
    "wof:name":"Robinetterie Jalo Inc",
    "wof:placetype":"venue"
},
  "geometry": {"coordinates":[-72.4957733154,46.3753814697],"type":"Point"}
}