{
  "type": "Feature",
  "properties": {
    "addr:full":"Oakville ON L6J 7W5",
    "addr:postcode":"l6j 7w5",
    "iso:country":"CA",
    "sg:city":"Oakville",
    "sg:classifiers":[
        {
            "category":"Wholesale",
            "subcategory":"Hardware",
            "type":"Manufacturing & Wholesale Goods"
        }
    ],
    "sg:phone":"+1 905 338 2999",
    "sg:postcode":"L6J 7W5",
    "sg:province":"ON",
    "sg:tags":[
        "ventilating",
        "equipment"
    ],
    "wof:name":"Spring Air Systems Inc",
    "wof:placetype":"venue"
},
  "geometry": {"coordinates":[-79.6625747681,43.4748497009],"type":"Point"}
}