{
  "type": "Feature",
  "properties": {
    "addr:full":"900 Hanwell Rd #14 Fredericton NB E3B 6A2",
    "addr:housenumber":"900",
    "addr:postcode":"e3b 6a2",
    "addr:street":"Hanwell Rd # 14",
    "iso:country":"CA",
    "sg:address":"900 Hanwell Rd #14",
    "sg:city":"Fredericton",
    "sg:classifiers":[
        {
            "category":"Sports & Exercise",
            "subcategory":"Gym",
            "type":"Entertainment"
        }
    ],
    "sg:phone":"+1 506 455 2878",
    "sg:postcode":"E3B 6A2",
    "sg:province":"NB",
    "sg:tags":[
        "control",
        "weight",
        "club",
        "gymnasium",
        "health",
        "studio"
    ],
    "wof:name":"Curves For Women",
    "wof:placetype":"venue"
},
  "geometry": {"coordinates":[-66.686249,45.952267],"type":"Point"}
}