{
  "type": "Feature",
  "properties": {
    "addr:full":"974 Topsail Rd Mount Pearl NL A1N 3K2",
    "addr:housenumber":"974",
    "addr:postcode":"a1n 3k2",
    "addr:street":"Topsail Rd",
    "iso:country":"CA",
    "sg:address":"974 Topsail Rd",
    "sg:city":"Mount Pearl",
    "sg:classifiers":[
        {
            "category":"Wholesale",
            "subcategory":"Machinery & Supplies",
            "type":"Manufacturing & Wholesale Goods"
        }
    ],
    "sg:phone":"+1 709 368 1456",
    "sg:postcode":"A1N 3K2",
    "sg:province":"NL",
    "sg:tags":[
        "marine",
        "electronic"
    ],
    "wof:name":"Sealand Marine Elec Sales Svc",
    "wof:placetype":"venue"
},
  "geometry": {"coordinates":[-52.80444,47.523918],"type":"Point"}
}