{
  "type": "Feature",
  "properties": {
    "addr:full":"1490 Columbia Ave Port Coquitlam BC V3C 1C3",
    "addr:housenumber":"1490",
    "addr:postcode":"v3c 1c3",
    "addr:street":"Columbia Ave",
    "iso:country":"CA",
    "sg:address":"1490 Columbia Ave",
    "sg:city":"Port Coquitlam",
    "sg:classifiers":[
        {
            "category":"Arts & Performance",
            "subcategory":"Theater",
            "type":"Entertainment"
        }
    ],
    "sg:phone":"+1 604 468 7797",
    "sg:postcode":"V3C 1C3",
    "sg:province":"BC",
    "sg:tags":[
        "live",
        "wedding",
        "music",
        "supply"
    ],
    "wof:name":"K & R Mobile Audio",
    "wof:placetype":"venue"
},
  "geometry": {"coordinates":[-122.775482178,49.241809845],"type":"Point"}
}