{
  "type": "Feature",
  "properties": {
    "addr:full":"1960 Ch Laliberte N Saint-Denis-DE-Brompton QC J0B 2P0",
    "addr:postcode":"1960;j0b 2p0",
    "addr:street":"Ch Laliberte N Saint-Denis-De-Brompton",
    "iso:country":"CA",
    "sg:address":"1960 Ch Laliberte N",
    "sg:city":"Saint-Denis-DE-Brompton",
    "sg:classifiers":[
        {
            "category":"Manufacturing",
            "subcategory":"Motor Vehicles & Parts",
            "type":"Manufacturing & Wholesale Goods"
        }
    ],
    "sg:phone":"+1 819 846 2622",
    "sg:postcode":"J0B 2P0",
    "sg:province":"QC",
    "sg:tags":[
        "designer",
        "trailer"
    ],
    "wof:name":"Remorques Laroche",
    "wof:placetype":"venue"
},
  "geometry": {"coordinates":[-72.05172,45.446629],"type":"Point"}
}