{
  "type": "Feature",
  "properties": {
    "addr:full":"7823 25 St NW Edmonton AB T6P 1N4",
    "addr:housenumber":"7823",
    "addr:postcode":"t6p 1n4",
    "addr:street":"25 St Nw",
    "iso:country":"CA",
    "sg:address":"7823 25 St NW",
    "sg:city":"Edmonton",
    "sg:classifiers":[
        {
            "category":"Manufacturing",
            "subcategory":"Metals",
            "type":"Manufacturing & Wholesale Goods"
        }
    ],
    "sg:phone":"+1 780 440 2737",
    "sg:postcode":"T6P 1N4",
    "sg:province":"AB",
    "sg:tags":[
        "fastener",
        "bolt"
    ],
    "wof:name":"M & Z Ind Supply Ltd",
    "wof:placetype":"venue"
},
  "geometry": {"coordinates":[-113.379608154,53.5880813599],"type":"Point"}
}