{
  "type": "Feature",
  "properties": {
    "addr:full":"Calgary AB T3E 7C4",
    "addr:postcode":"t3e 7c4",
    "iso:country":"CA",
    "sg:city":"Calgary",
    "sg:classifiers":[
        {
            "category":"Insurance",
            "subcategory":"Health Insurance",
            "type":"Services"
        }
    ],
    "sg:phone":"+1 403 240 3026",
    "sg:postcode":"T3E 7C4",
    "sg:province":"AB",
    "sg:tags":[
        "surgical",
        "hospitalization",
        "plan"
    ],
    "wof:name":"Diamond Optical Vision Care",
    "wof:placetype":"venue"
},
  "geometry": {"coordinates":[-114.162216187,51.0176429749],"type":"Point"}
}