{
  "type": "Feature",
  "properties": {
    "addr:full":"Brossard QC J4W 2V6",
    "addr:postcode":"j4w 2v6",
    "iso:country":"CA",
    "sg:city":"Brossard",
    "sg:classifiers":[
        {
            "category":"Manufacturing",
            "subcategory":"Tools & Machinery",
            "type":"Manufacturing & Wholesale Goods"
        }
    ],
    "sg:phone":"+1 450 923 9295",
    "sg:postcode":"J4W 2V6",
    "sg:province":"QC",
    "sg:tags":[
        "garage",
        "parking"
    ],
    "wof:name":"Parcometres Mac Kay Ltee",
    "wof:placetype":"venue"
},
  "geometry": {"coordinates":[-73.474998,45.473873],"type":"Point"}
}