{
  "type": "Feature",
  "properties": {
    "addr:full":"9 Oakdene Cres Toronto ON M4J 4H8",
    "addr:housenumber":"9",
    "addr:postcode":"m4j 4h8",
    "addr:street":"Oakdene Cres",
    "iso:country":"CA",
    "sg:address":"9 Oakdene Cres",
    "sg:city":"Toronto",
    "sg:classifiers":[
        {
            "category":"Building & Trades",
            "subcategory":"Equipment Rental",
            "type":"Services"
        }
    ],
    "sg:phone":"+1 416 463 7135",
    "sg:postcode":"M4J 4H8",
    "sg:province":"ON",
    "sg:tags":[
        "leasing"
    ],
    "wof:name":"Glover Financial Svc",
    "wof:placetype":"venue"
},
  "geometry": {"coordinates":[-79.331566,43.682884],"type":"Point"}
}