{
  "type": "Feature",
  "properties": {
    "addr:full":"Magnetawan ON P0A 1P0",
    "addr:postcode":"p0a 1p0",
    "iso:country":"CA",
    "sg:city":"Magnetawan",
    "sg:classifiers":[
        {
            "category":"Travel",
            "subcategory":"Campground",
            "type":"Entertainment"
        }
    ],
    "sg:phone":"+1 705 387 3923",
    "sg:postcode":"P0A 1P0",
    "sg:province":"ON",
    "sg:tags":[
        "camp"
    ],
    "wof:name":"Camp Kahquah",
    "wof:placetype":"venue"
},
  "geometry": {"coordinates":[-79.6290817261,45.7302131653],"type":"Point"}
}