{
  "type": "Feature",
  "properties": {
    "iso:country":"CA",
    "sg:address":"1522 Bella Vista Dr",
    "sg:city":"Cumberland",
    "sg:classifiers":[
        {
            "category":"Shopping",
            "type":"Retail Goods"
        }
    ],
    "sg:phone":"+1 613 833 1386",
    "sg:postcode":"K4C 1A7",
    "sg:province":"ON",
    "sg:tags":[
        "wedding",
        "supply"
    ],
    "wof:name":"Robinson Photography",
    "wof:placetype":"venue"
},
  "geometry": {"coordinates":[-75.4595489502,45.5123977661],"type":"Point"}
}