{
  "type": "Feature",
  "properties": {
    "addr:full":"82 Brock St W Uxbridge ON L9P 1P4",
    "addr:housenumber":"82",
    "addr:postcode":"l9p 1p4",
    "addr:street":"Brock St W",
    "iso:country":"CA",
    "sg:address":"82 Brock St W",
    "sg:city":"Uxbridge",
    "sg:classifiers":[
        {
            "category":"Shopping",
            "subcategory":"Jewelry",
            "type":"Retail Goods"
        }
    ],
    "sg:phone":"+1 905 852 7846",
    "sg:postcode":"L9P 1P4",
    "sg:province":"ON",
    "sg:tags":[
        "jeweler"
    ],
    "wof:name":"Rutledge Jewellers",
    "wof:placetype":"venue"
},
  "geometry": {"coordinates":[-79.12409973139999,44.1084213257],"type":"Point"}
}