{
  "type": "Feature",
  "properties": {
    "addr:full":"Sioux Narrows ON P0X 1N0",
    "addr:postcode":"p0x 1n0",
    "iso:country":"CA",
    "sg:city":"Sioux Narrows",
    "sg:classifiers":[
        {
            "category":"Shopping",
            "subcategory":"Gifts & Souvenirs",
            "type":"Retail Goods"
        }
    ],
    "sg:phone":"+1 807 226 5700",
    "sg:postcode":"P0X 1N0",
    "sg:province":"ON",
    "sg:tags":[
        "shop",
        "nurseryman"
    ],
    "wof:name":"Plants & Crafts",
    "wof:placetype":"venue"
},
  "geometry": {"coordinates":[-94.01765399999999,49.393009],"type":"Point"}
}