{
  "type": "Feature",
  "properties": {
    "iso:country":"CA",
    "sg:address":"6623 Bench Dr",
    "sg:city":"Prince George",
    "sg:classifiers":[
        {
            "category":"Real Estate",
            "subcategory":"Real Estate Agent",
            "type":"Services"
        }
    ],
    "sg:phone":"+1 250 960 1133",
    "sg:postcode":"V2K 4Z1",
    "sg:province":"BC",
    "sg:tags":[
        "appraiser"
    ],
    "wof:name":"Finden Appraisals",
    "wof:placetype":"venue"
},
  "geometry": {"coordinates":[-122.841690063,53.9616546631],"type":"Point"}
}