{
  "type": "Feature",
  "properties": {
    "addr:full":"393 Rte 283 Saint-Paul-DE-Montminy QC G0R 3Y0",
    "addr:housenumber":"393",
    "addr:postcode":"g0r 3y0",
    "addr:street":"Rte 283",
    "iso:country":"CA",
    "sg:address":"393 Rte 283",
    "sg:city":"Saint-Paul-DE-Montminy",
    "sg:classifiers":[
        {
            "category":"Restaurant",
            "type":"Food & Drink"
        }
    ],
    "sg:phone":"+1 418 469 2952",
    "sg:postcode":"G0R 3Y0",
    "sg:province":"QC",
    "wof:name":"Casse-Croute Au Coin Du Routie",
    "wof:placetype":"venue"
},
  "geometry": {"coordinates":[-70.3604354858,46.7308654785],"type":"Point"}
}