{
  "type": "Feature",
  "properties": {
    "addr:full":"1510 Rue Bergeron Trois-Rivieres QC G8Y 3E4",
    "addr:housenumber":"1510",
    "addr:postcode":"g8y 3e4",
    "addr:street":"Rue Bergeron Trois-Rivieres",
    "iso:country":"CA",
    "sg:address":"1510 Rue Bergeron",
    "sg:city":"Trois-Rivieres",
    "sg:classifiers":[
        {
            "category":"Personal",
            "subcategory":"Beauty Salon",
            "type":"Services"
        }
    ],
    "sg:phone":"+1 819 370 6065",
    "sg:postcode":"G8Y 3E4",
    "sg:province":"QC",
    "wof:name":"Coiffure Projection Lcm",
    "wof:placetype":"venue"
},
  "geometry": {"coordinates":[-72.606522,46.370167],"type":"Point"}
}