{
  "type": "Feature",
  "properties": {
    "addr:full":"64 Magnum Dr Schomberg ON L0G 1T0",
    "addr:housenumber":"64",
    "addr:postcode":"l0g 1t0",
    "addr:street":"Magnum Dr",
    "iso:country":"CA",
    "sg:address":"64 Magnum Dr",
    "sg:city":"Schomberg",
    "sg:classifiers":[
        {
            "category":"Autos & Motor Vehicles",
            "subcategory":"Boat Sales",
            "type":"Retail Goods"
        }
    ],
    "sg:phone":"+1 905 939 0963",
    "sg:postcode":"L0G 1T0",
    "sg:province":"ON",
    "sg:tags":[
        "outboard"
    ],
    "wof:name":"Speedmaster Limited",
    "wof:placetype":"venue"
},
  "geometry": {"coordinates":[-79.67645263670001,44.009765625],"type":"Point"}
}