{
  "type": "Feature",
  "properties": {
    "iso:country":"CA",
    "sg:city":"Toronto",
    "sg:classifiers":[
        {
            "category":"Communications",
            "subcategory":"Film & Video Production",
            "type":"Services"
        }
    ],
    "sg:phone":"+1 416 368 1989",
    "sg:postcode":"M5A 3X9",
    "sg:province":"ON",
    "sg:tags":[
        "taping"
    ],
    "wof:name":"Idea Bank",
    "wof:placetype":"venue"
},
  "geometry": {"coordinates":[-79.3683013916,43.6523513794],"type":"Point"}
}