{
  "type": "Feature",
  "properties": {
    "addr:full":"5205 Rue Sainte-Lucie Saint-Hubert QC J3Y 2B4",
    "addr:housenumber":"5205",
    "addr:postcode":"j3y 2b4",
    "addr:street":"Rue Sainte-Lucie",
    "iso:country":"CA",
    "sg:address":"5205 Rue Sainte-Lucie",
    "sg:city":"Saint-Hubert",
    "sg:classifiers":[
        {
            "category":"Building & Trades",
            "subcategory":"Cleaning & Sanitation",
            "type":"Services"
        }
    ],
    "sg:phone":"+1 450 678 0241",
    "sg:postcode":"J3Y 2B4",
    "sg:province":"QC",
    "sg:tags":[
        "cleaners",
        "janitor",
        "rug",
        "carpet"
    ],
    "wof:name":"Services Entretien 4 Saisons",
    "wof:placetype":"venue"
},
  "geometry": {"coordinates":[-73.441696167,45.4793586731],"type":"Point"}
}