{
  "type": "Feature",
  "properties": {
    "iso:country":"CA",
    "sg:address":"1066 Western Ave",
    "sg:city":"Peterborough",
    "sg:classifiers":[
        {
            "category":"Organizations",
            "subcategory":"Religious Organization",
            "type":"Services"
        }
    ],
    "sg:phone":"+1 705 745 8623",
    "sg:postcode":"K9J 5W6",
    "sg:province":"ON",
    "sg:tags":[
        "church"
    ],
    "wof:name":"St Alphonsus Church",
    "wof:placetype":"venue"
},
  "geometry": {"coordinates":[-78.3408660889,44.2909011841],"type":"Point"}
}