{
  "type": "Feature",
  "properties": {
    "iso:country":"CA",
    "sg:address":"1196 Broadway Ave S",
    "sg:city":"Williams Lake",
    "sg:classifiers":[
        {
            "category":"Restaurant",
            "type":"Food & Drink"
        }
    ],
    "sg:phone":"+1 250 398 9344",
    "sg:postcode":"V2G 1A2",
    "sg:province":"BC",
    "wof:name":"Subway Sandwiches & Salads",
    "wof:placetype":"venue"
},
  "geometry": {"coordinates":[-122.12203979500001,52.1259841919],"type":"Point"}
}