{
  "type": "Feature",
  "properties": {
    "addr:full":"361 Rue Principale Saint-Vallier QC G0R 4J0",
    "addr:housenumber":"361",
    "addr:postcode":"g0r 4j0",
    "addr:street":"Rue Principale",
    "iso:country":"CA",
    "sg:address":"361 Rue Principale",
    "sg:city":"Saint-Vallier",
    "sg:classifiers":[
        {
            "category":"Banks & Credit Unions",
            "subcategory":"Bank",
            "type":"Services"
        }
    ],
    "sg:phone":"+1 418 887 3337",
    "sg:postcode":"G0R 4J0",
    "sg:province":"QC",
    "wof:name":"Caisses Desjardins",
    "wof:placetype":"venue"
},
  "geometry": {"coordinates":[-70.82205200200001,46.8928794861],"type":"Point"}
}