{
  "type": "Feature",
  "properties": {
    "addr:full":"2969 Rue Fleury E Montreal QC H2B 1M3",
    "addr:housenumber":"2969",
    "addr:postcode":"h2b 1m3",
    "addr:street":"Rue Fleury E",
    "iso:country":"CA",
    "sg:address":"2969 Rue Fleury E",
    "sg:city":"Montreal",
    "sg:classifiers":[
        {
            "category":"Food & Beverages",
            "subcategory":"Groceries & Convenience Stores",
            "type":"Retail Goods"
        }
    ],
    "sg:phone":"+1 514 385 3547",
    "sg:postcode":"H2B 1M3",
    "sg:province":"QC",
    "sg:tags":[
        "grocer"
    ],
    "wof:name":"Marche D'Alimentation Caraibes",
    "wof:placetype":"venue"
},
  "geometry": {"coordinates":[-73.644623,45.579185],"type":"Point"}
}