{
  "type": "Feature",
  "properties": {
    "addr:full":"203 Railway Ave E Canora SK S0A 0L0",
    "addr:housenumber":"203",
    "addr:postcode":"s0a 0l0",
    "addr:street":"Railway Ave E Canora",
    "iso:country":"CA",
    "sg:address":"203 Railway Ave E",
    "sg:city":"Canora",
    "sg:classifiers":[
        {
            "category":"Wholesale",
            "subcategory":"Machinery & Supplies",
            "type":"Manufacturing & Wholesale Goods"
        }
    ],
    "sg:phone":"+1 306 563 5601",
    "sg:postcode":"S0A 0L0",
    "sg:province":"SK",
    "sg:tags":[
        "agricultural",
        "implement",
        "parts",
        "automobile"
    ],
    "wof:name":"Canora Auto Electric Ltd",
    "wof:placetype":"venue"
},
  "geometry": {"coordinates":[-102.432434,51.635456],"type":"Point"}
}