{
  "type": "Feature",
  "properties": {
    "iso:country":"CA",
    "sg:city":"Mississauga",
    "sg:classifiers":[
        {
            "category":"Shopping",
            "subcategory":"Music",
            "type":"Retail Goods"
        }
    ],
    "sg:phone":"+1 905 607 6177",
    "sg:postcode":"L5L 5R4",
    "sg:province":"ON",
    "sg:tags":[
        "compact",
        "record",
        "disc",
        "tape"
    ],
    "wof:name":"Entertainment Warehouse",
    "wof:placetype":"venue"
},
  "geometry": {"coordinates":[-79.6951828003,43.5183944702],"type":"Point"}
}