{
  "type": "Feature",
  "properties": {
    "iso:country":"CA",
    "sg:address":"9558 Yellowhead Trail NW",
    "sg:city":"Edmonton",
    "sg:classifiers":[
        {
            "category":"Food & Beverages",
            "subcategory":"Specialty",
            "type":"Retail Goods"
        }
    ],
    "sg:phone":"+1 780 414 1300",
    "sg:postcode":"T5G 0W4",
    "sg:province":"AB",
    "sg:tags":[
        "water",
        "bulk",
        "company"
    ],
    "wof:name":"O'Canada Water Corp",
    "wof:placetype":"venue"
},
  "geometry": {"coordinates":[-113.488457,53.581757],"type":"Point"}
}