{
  "type": "Feature",
  "properties": {
    "addr:full":"Harbor Vue Rd Little Current ON P0P 1K0",
    "addr:postcode":"p0p 1k0",
    "addr:street":"Vue Rd",
    "iso:country":"CA",
    "sg:address":"Harbor Vue Rd",
    "sg:city":"Little Current",
    "sg:classifiers":[
        {
            "category":"Freight",
            "type":"Transportation"
        }
    ],
    "sg:phone":"+1 705 368 3565",
    "sg:postcode":"P0P 1K0",
    "sg:province":"ON",
    "sg:tags":[
        "trucking"
    ],
    "wof:name":"Randy Noble Trucking Ltd",
    "wof:placetype":"venue"
},
  "geometry": {"coordinates":[-81.92063899999999,45.972031],"type":"Point"}
}