{
  "type": "Feature",
  "properties": {
    "addr:full":"4805 48 Ave Red Deer AB T4N 3T2",
    "addr:housenumber":"4805",
    "addr:postcode":"t4n 3t2",
    "addr:street":"48 Ave",
    "iso:country":"CA",
    "sg:address":"4805 48 Ave",
    "sg:city":"Red Deer",
    "sg:classifiers":[
        {
            "category":"Mining & Drilling",
            "type":"Manufacturing & Wholesale Goods"
        }
    ],
    "sg:phone":"+1 403 346 5648",
    "sg:postcode":"T4N 3T2",
    "sg:province":"AB",
    "sg:tags":[
        "field",
        "oil",
        "business"
    ],
    "wof:name":"Wes Can Oilfield Vacuum & Tank",
    "wof:placetype":"venue"
},
  "geometry": {"coordinates":[-113.808853,52.267242],"type":"Point"}
}