{
  "type": "Feature",
  "properties": {
    "addr:full":"146 Larch St Sudbury ON P3E 1C2",
    "addr:housenumber":"146",
    "addr:postcode":"p3e 1c2",
    "addr:street":"Larch St",
    "iso:country":"CA",
    "sg:address":"146 Larch St",
    "sg:city":"Sudbury",
    "sg:classifiers":[
        {
            "category":"Social Services",
            "type":"Services"
        }
    ],
    "sg:phone":"+1 705 673 1175",
    "sg:postcode":"P3E 1C2",
    "sg:province":"ON",
    "sg:tags":[
        "organization",
        "addiction",
        "welfare",
        "center",
        "treatment"
    ],
    "wof:name":"Salvation Army",
    "wof:placetype":"venue"
},
  "geometry": {"coordinates":[-80.99132537840001,46.491481781],"type":"Point"}
}