{
  "type": "Feature",
  "properties": {
    "iso:country":"CA",
    "sg:address":"780 Taylor Creek Dr",
    "sg:city":"Orleans",
    "sg:classifiers":[
        {
            "category":"Building & Trades",
            "subcategory":"Construction",
            "type":"Services"
        }
    ],
    "sg:phone":"+1 613 841 2481",
    "sg:postcode":"K1C 1T1",
    "sg:province":"ON",
    "sg:tags":[
        "water",
        "restoration",
        "damage"
    ],
    "wof:name":"Diresco Consulting Inc",
    "wof:placetype":"venue"
},
  "geometry": {"coordinates":[-75.48388671879999,45.4924316406],"type":"Point"}
}