{
  "type": "Feature",
  "properties": {
    "addr:full":"9249 50 St NW Edmonton AB T6B 3B6",
    "addr:housenumber":"9249",
    "addr:postcode":"t6b 3b6",
    "addr:street":"50 St Nw",
    "iso:country":"CA",
    "sg:address":"9249 50 St NW",
    "sg:city":"Edmonton",
    "sg:classifiers":[
        {
            "category":"Professional",
            "subcategory":"Business Services",
            "type":"Services"
        }
    ],
    "sg:phone":"+1 780 468 4118",
    "sg:postcode":"T6B 3B6",
    "sg:province":"AB",
    "sg:tags":[
        "interior",
        "consultant",
        "design",
        "decorator"
    ],
    "wof:name":"Designabilities",
    "wof:placetype":"venue"
},
  "geometry": {"coordinates":[-113.417931,53.528519],"type":"Point"}
}