{
  "type": "Feature",
  "properties": {
    "addr:full":"223 Union St E Waterloo ON N2J 1E1",
    "addr:housenumber":"223",
    "addr:postcode":"n2j 1e1",
    "addr:street":"Union St E",
    "iso:country":"CA",
    "sg:address":"223 Union St E",
    "sg:city":"Waterloo",
    "sg:classifiers":[
        {
            "category":"Organizations",
            "subcategory":"Religious Organization",
            "type":"Services"
        }
    ],
    "sg:phone":"+1 519 741 5019",
    "sg:postcode":"N2J 1E1",
    "sg:province":"ON",
    "sg:tags":[
        "church"
    ],
    "wof:name":"German Gospel Church",
    "wof:placetype":"venue"
},
  "geometry": {"coordinates":[-80.50312,43.465942],"type":"Point"}
}