{
  "type": "Feature",
  "properties": {
    "addr:full":"Manning AB T0H 2M0",
    "addr:postcode":"t0h 2m0",
    "iso:country":"CA",
    "sg:city":"Manning",
    "sg:classifiers":[
        {
            "category":"Health Services",
            "subcategory":"Hospital",
            "type":"Services"
        }
    ],
    "sg:phone":"+1 780 836 3391",
    "sg:postcode":"T0H 2M0",
    "sg:province":"AB",
    "wof:name":"Manning Community Health Ctr",
    "wof:placetype":"venue"
},
  "geometry": {"coordinates":[-117.631248474,56.9233016968],"type":"Point"}
}