{
  "type": "Feature",
  "properties": {
    "iso:country":"CA",
    "sg:address":"2108 Rue Belvedere S",
    "sg:city":"Ascot",
    "sg:classifiers":[
        {
            "category":"Health Services",
            "subcategory":"Chiropractor",
            "type":"Services"
        }
    ],
    "sg:phone":"+1 819 562 3999",
    "sg:postcode":"J1H 5W5",
    "sg:province":"QC",
    "wof:name":"Clinique Chiropratique",
    "wof:placetype":"venue"
},
  "geometry": {"coordinates":[-71.893738,45.373554],"type":"Point"}
}