{
  "type": "Feature",
  "properties": {
    "addr:full":"215 Drumlin Cir Concord ON L4K 3E4",
    "addr:housenumber":"215",
    "addr:postcode":"l4k 3e4",
    "addr:street":"Drumlin Cir",
    "iso:country":"CA",
    "sg:address":"215 Drumlin Cir",
    "sg:city":"Concord",
    "sg:classifiers":[
        {
            "category":"Manufacturing",
            "subcategory":"Tools & Machinery",
            "type":"Manufacturing & Wholesale Goods"
        }
    ],
    "sg:phone":"+1 905 738 2424",
    "sg:postcode":"L4K 3E4",
    "sg:province":"ON",
    "sg:tags":[
        "mold"
    ],
    "wof:name":"Fgl Precision Works Ltd",
    "wof:placetype":"venue"
},
  "geometry": {"coordinates":[-79.48921199999999,43.785786],"type":"Point"}
}