{
  "type": "Feature",
  "properties": {
    "addr:full":"73 Rue Saint-Octave Saint-Romuald QC G6W 3T2",
    "addr:housenumber":"73",
    "addr:postcode":"g6w 3t2",
    "addr:street":"Rue Saint-Octave",
    "iso:country":"CA",
    "sg:address":"73 Rue Saint-Octave",
    "sg:city":"Saint-Romuald",
    "sg:classifiers":[
        {
            "category":"Manufacturing",
            "subcategory":"Signs",
            "type":"Manufacturing & Wholesale Goods"
        }
    ],
    "sg:phone":"+1 418 834 8115",
    "sg:postcode":"G6W 3T2",
    "sg:province":"QC",
    "wof:name":"Enseigne Promobile Enr",
    "wof:placetype":"venue"
},
  "geometry": {"coordinates":[-71.25846900000001,46.747841],"type":"Point"}
}