{
  "type": "Feature",
  "properties": {
    "addr:full":"466 Gertrude Ave Winnipeg MB R3L 0M8",
    "addr:housenumber":"466",
    "addr:postcode":"r3l 0m8",
    "addr:street":"Gertrude Ave",
    "iso:country":"CA",
    "sg:address":"466 Gertrude Ave",
    "sg:city":"Winnipeg",
    "sg:classifiers":[
        {
            "category":"Organizations",
            "subcategory":"Membership Organization",
            "type":"Services"
        }
    ],
    "sg:phone":"+1 204 284 7562",
    "sg:postcode":"R3L 0M8",
    "sg:province":"MB",
    "sg:tags":[
        "association"
    ],
    "wof:name":"Block Parent Program-Winnipeg",
    "wof:placetype":"venue"
},
  "geometry": {"coordinates":[-97.1441497803,49.8757095337],"type":"Point"}
}