{
  "type": "Feature",
  "properties": {
    "iso:country":"CA",
    "sg:address":"255 Main St",
    "sg:city":"Liverpool",
    "sg:classifiers":[
        {
            "category":"Shopping",
            "subcategory":"Pharmacy",
            "type":"Retail Goods"
        }
    ],
    "sg:phone":"+1 902 354 7101",
    "sg:postcode":"B0T 1K0",
    "sg:province":"NS",
    "wof:name":"Pharmasave",
    "wof:placetype":"venue"
},
  "geometry": {"coordinates":[-64.71602630620001,44.0386161804],"type":"Point"}
}