{
  "type": "Feature",
  "properties": {
    "addr:full":"250 1st St E Cardston AB T0K 0K0",
    "addr:housenumber":"250",
    "addr:postcode":"t0k 0k0",
    "addr:street":"1St St E Cardston",
    "iso:country":"CA",
    "sg:address":"250 1st St E",
    "sg:city":"Cardston",
    "sg:classifiers":[
        {
            "category":"Wholesale",
            "subcategory":"Construction Materials",
            "type":"Manufacturing & Wholesale Goods"
        }
    ],
    "sg:phone":"+1 403 653 3230",
    "sg:postcode":"T0K 0K0",
    "sg:province":"AB",
    "sg:tags":[
        "sand",
        "gravel"
    ],
    "wof:name":"Sage Management Ltd",
    "wof:placetype":"venue"
},
  "geometry": {"coordinates":[-113.29879800000001,49.200394],"type":"Point"}
}