{
  "type": "Feature",
  "properties": {
    "addr:full":"1451 Rang Du Petit-Bois Louiseville QC J5V 2L4",
    "addr:housenumber":"1451",
    "addr:postcode":"j5v 2l4",
    "addr:street":"Rang Du Petit-Bois",
    "iso:country":"CA",
    "sg:address":"1451 Rang Du Petit-Bois",
    "sg:city":"Louiseville",
    "sg:classifiers":[
        {
            "category":"Shopping",
            "subcategory":"Clothing, Apparel, & Fashions",
            "type":"Retail Goods"
        }
    ],
    "sg:phone":"+1 819 227 2607",
    "sg:postcode":"J5V 2L4",
    "sg:province":"QC",
    "sg:tags":[
        "theatrical",
        "costume"
    ],
    "wof:name":"Livernoche Location",
    "wof:placetype":"venue"
},
  "geometry": {"coordinates":[-72.98084299999999,46.241859],"type":"Point"}
}