{
  "type": "Feature",
  "properties": {
    "addr:full":"Western Bay NL A0A 4J0",
    "addr:postcode":"a0a 4j0",
    "addr:street":"Western",
    "iso:country":"CA",
    "sg:city":"Western Bay",
    "sg:classifiers":[
        {
            "category":"Wholesale",
            "subcategory":"Machinery & Supplies",
            "type":"Manufacturing & Wholesale Goods"
        }
    ],
    "sg:phone":"+1 709 596 1811",
    "sg:postcode":"A0A 4J0",
    "sg:province":"NL",
    "sg:tags":[
        "burial",
        "vault"
    ],
    "wof:name":"Noel's Funeral Homes Ltd",
    "wof:placetype":"venue"
},
  "geometry": {"coordinates":[-53.085922,47.88295],"type":"Point"}
}