{
  "type": "Feature",
  "properties": {
    "addr:full":"11222 Car Valois Quebec QC G2A 1T6",
    "addr:housenumber":"11222",
    "addr:postcode":"g2a 1t6",
    "addr:street":"Car Valois",
    "iso:country":"CA",
    "sg:address":"11222 Car Valois",
    "sg:city":"Quebec",
    "sg:classifiers":[
        {
            "category":"Building & Trades",
            "subcategory":"Landscaping Services",
            "type":"Services"
        }
    ],
    "sg:phone":"+1 418 842 0133",
    "sg:postcode":"G2A 1T6",
    "sg:province":"QC",
    "sg:tags":[
        "landscape",
        "contractor"
    ],
    "wof:name":"Terrassement Gomes",
    "wof:placetype":"venue"
},
  "geometry": {"coordinates":[-71.341652,46.859772],"type":"Point"}
}