{
  "type": "Feature",
  "properties": {
    "addr:full":"46 Ch DE LA Savane Gatineau QC J8T 7Z3",
    "addr:housenumber":"46",
    "addr:postcode":"j8t 7z3",
    "addr:street":"Ch De La Savane",
    "iso:country":"CA",
    "sg:address":"46 Ch DE LA Savane",
    "sg:city":"Gatineau",
    "sg:classifiers":[
        {
            "category":"Professional",
            "subcategory":"Management & Consulting",
            "type":"Services"
        }
    ],
    "sg:phone":"+1 819 561 2002",
    "sg:postcode":"J8T 7Z3",
    "sg:province":"QC",
    "sg:tags":[
        "consultant",
        "instructional",
        "computer",
        "training"
    ],
    "wof:name":"Centre DE Formation Levis",
    "wof:placetype":"venue"
},
  "geometry": {"coordinates":[-75.700615,45.473801],"type":"Point"}
}