{
  "type": "Feature",
  "properties": {
    "addr:full":"3502 44th Ave Stony Plain AB T7Z 1L1",
    "addr:housenumber":"3502",
    "addr:postcode":"t7z 1l1",
    "addr:street":"44Th Ave",
    "iso:country":"CA",
    "sg:address":"3502 44th Ave",
    "sg:city":"Stony Plain",
    "sg:classifiers":[
        {
            "category":"Retail",
            "subcategory":"Funeral Services",
            "type":"Services"
        }
    ],
    "sg:phone":"+1 780 963 2520",
    "sg:postcode":"T7Z 1L1",
    "sg:province":"AB",
    "sg:tags":[
        "director",
        "plan"
    ],
    "wof:name":"Parkland Funeral Svc",
    "wof:placetype":"venue"
},
  "geometry": {"coordinates":[-113.979134,53.538288],"type":"Point"}
}