{
  "type": "Feature",
  "properties": {
    "iso:country":"CA",
    "sg:address":"29 Ravine Rd",
    "sg:city":"St Catharines",
    "sg:classifiers":[
        {
            "category":"Professional",
            "subcategory":"Computer Services",
            "type":"Services"
        }
    ],
    "sg:phone":"+1 905 682 4327",
    "sg:postcode":"L2P 3A6",
    "sg:province":"ON",
    "sg:tags":[
        "repair",
        "dealer",
        "equipment"
    ],
    "wof:name":"New Gamein Town",
    "wof:placetype":"venue"
},
  "geometry": {"coordinates":[-79.2200546265,43.1590995789],"type":"Point"}
}