{
  "type": "Feature",
  "properties": {
    "addr:full":"Kamloops BC V2C 4N6",
    "addr:postcode":"bc v2c 4n6",
    "iso:country":"CA",
    "sg:city":"Kamloops",
    "sg:classifiers":[
        {
            "category":"Restaurant",
            "type":"Food & Drink"
        }
    ],
    "sg:phone":"+1 250 372 8558",
    "sg:postcode":"V2C 4N6",
    "sg:province":"BC",
    "wof:name":"Subway Sandwiches & Salads",
    "wof:placetype":"venue"
},
  "geometry": {"coordinates":[-120.272079468,50.6786575317],"type":"Point"}
}