{
  "type": "Feature",
  "properties": {
    "addr:full":"2625 78 Ave SE Calgary AB T2C 3B7",
    "addr:housenumber":"2625",
    "addr:postcode":"t2c 3b7",
    "addr:street":"78 Ave Se",
    "iso:country":"CA",
    "sg:address":"2625 78 Ave SE",
    "sg:city":"Calgary",
    "sg:classifiers":[
        {
            "category":"Organizations",
            "subcategory":"Professional Association",
            "type":"Services"
        }
    ],
    "sg:phone":"+1 403 279 3636",
    "sg:postcode":"T2C 3B7",
    "sg:province":"AB",
    "sg:tags":[
        "hall",
        "auditorium"
    ],
    "wof:name":"Royal Canadian Legion",
    "wof:placetype":"venue"
},
  "geometry": {"coordinates":[-113.999771,50.98296],"type":"Point"}
}