{
  "type": "Feature",
  "properties": {
    "iso:country":"CA",
    "sg:address":"124 Anne St S",
    "sg:city":"Barrie",
    "sg:classifiers":[
        {
            "category":"Retail",
            "subcategory":"Auto Repair",
            "type":"Services"
        }
    ],
    "sg:phone":"+1 705 737 4822",
    "sg:postcode":"L4N 6A2",
    "sg:province":"ON",
    "sg:tags":[
        "repairing",
        "automobile"
    ],
    "wof:name":"Abram's Service Ctr",
    "wof:placetype":"venue"
},
  "geometry": {"coordinates":[-79.698273,44.374104],"type":"Point"}
}