{
  "type": "Feature",
  "properties": {
    "addr:full":"4390 Boul DE LA Concorde E Laval QC H7C 2R4",
    "addr:housenumber":"4390",
    "addr:postcode":"h7c 2r4",
    "addr:street":"Boul De La Concorde E",
    "iso:country":"CA",
    "sg:address":"4390 Boul DE LA Concorde E",
    "sg:city":"Laval",
    "sg:classifiers":[
        {
            "category":"Bars & Pubs",
            "type":"Food & Drink"
        }
    ],
    "sg:phone":"+1 450 661 1511",
    "sg:postcode":"H7C 2R4",
    "sg:province":"QC",
    "wof:name":"Don Quichotte",
    "wof:placetype":"venue"
},
  "geometry": {"coordinates":[-73.64917,45.603657],"type":"Point"}
}