{
  "type": "Feature",
  "properties": {
    "addr:full":"Scarborough ON M1J 2G1",
    "addr:postcode":"m1j 2g1",
    "iso:country":"CA",
    "sg:city":"Scarborough",
    "sg:classifiers":[
        {
            "category":"Real Estate",
            "subcategory":"Real Estate Operator",
            "type":"Services"
        }
    ],
    "sg:phone":"+1 416 261 2076",
    "sg:postcode":"M1J 2G1",
    "sg:province":"ON",
    "sg:tags":[
        "apartment"
    ],
    "wof:name":"Renato Developments",
    "wof:placetype":"venue"
},
  "geometry": {"coordinates":[-79.22623400000001,43.741444],"type":"Point"}
}