{
  "type": "Feature",
  "properties": {
    "iso:country":"CA",
    "sg:address":"6062 Hwy 542",
    "sg:city":"Mindemoya",
    "sg:classifiers":[
        {
            "category":"Health Services",
            "subcategory":"Health Practitioner",
            "type":"Services"
        }
    ],
    "sg:phone":"+1 705 377 4225",
    "sg:postcode":"P0P 1S0",
    "sg:province":"ON",
    "sg:tags":[
        "nurse",
        "registry"
    ],
    "wof:name":"Victorian Order of Nurses",
    "wof:placetype":"venue"
},
  "geometry": {"coordinates":[-82.1414489746,45.7419433594],"type":"Point"}
}