{
  "type": "Feature",
  "properties": {
    "addr:full":"150 Ryan St Summerside PE C1N 6G2",
    "addr:housenumber":"150",
    "addr:postcode":"c1n 6g2",
    "addr:street":"Ryan St",
    "iso:country":"CA",
    "sg:address":"150 Ryan St",
    "sg:city":"Summerside",
    "sg:classifiers":[
        {
            "category":"Education",
            "subcategory":"School",
            "type":"Public Place"
        }
    ],
    "sg:phone":"+1 902 888 8486",
    "sg:postcode":"C1N 6G2",
    "sg:province":"PE",
    "wof:name":"Athena Consolidated School",
    "wof:placetype":"venue"
},
  "geometry": {"coordinates":[-63.779034,46.410927],"type":"Point"}
}