{
  "type": "Feature",
  "properties": {
    "addr:full":"3617 117 Ave NW Edmonton AB T5W 0X9",
    "addr:housenumber":"3617",
    "addr:postcode":"t5w 0x9",
    "addr:street":"117 Ave Nw",
    "iso:country":"CA",
    "sg:address":"3617 117 Ave NW",
    "sg:city":"Edmonton",
    "sg:classifiers":[
        {
            "category":"Organizations",
            "subcategory":"Professional Association",
            "type":"Services"
        }
    ],
    "sg:phone":"+1 780 477 1030",
    "sg:postcode":"T5W 0X9",
    "sg:province":"AB",
    "wof:name":"Alberta Union of School",
    "wof:placetype":"venue"
},
  "geometry": {"coordinates":[-113.39720199999999,53.569344],"type":"Point"}
}