{
  "type": "Feature",
  "properties": {
    "addr:full":"136 Avenue Rd Toronto ON M5R 2H6",
    "addr:housenumber":"136",
    "addr:postcode":"m5r 2h6",
    "addr:street":"Avenue Rd",
    "iso:country":"CA",
    "sg:address":"136 Avenue Rd",
    "sg:city":"Toronto",
    "sg:classifiers":[
        {
            "category":"Shopping",
            "subcategory":"Florist",
            "type":"Retail Goods"
        }
    ],
    "sg:phone":"+1 416 922 5651",
    "sg:postcode":"M5R 2H6",
    "sg:province":"ON",
    "wof:name":"Kay & Young Florist",
    "wof:placetype":"venue"
},
  "geometry": {"coordinates":[-79.39662199999999,43.674351],"type":"Point"}
}