{
  "type": "Feature",
  "properties": {
    "addr:full":"2216 Long Lake Rd Sudbury ON P3E 5H1",
    "addr:housenumber":"2216",
    "addr:postcode":"p3e 5h1",
    "addr:street":"Long Lake Rd",
    "iso:country":"CA",
    "sg:address":"2216 Long Lake Rd",
    "sg:city":"Sudbury",
    "sg:classifiers":[
        {
            "category":"Mining & Drilling",
            "type":"Manufacturing & Wholesale Goods"
        }
    ],
    "sg:phone":"+1 705 522 2440",
    "sg:postcode":"P3E 5H1",
    "sg:province":"ON",
    "sg:tags":[
        "stone"
    ],
    "wof:name":"Canadian Colour Rock",
    "wof:placetype":"venue"
},
  "geometry": {"coordinates":[-81.00505099999999,46.446926],"type":"Point"}
}