{
  "type": "Feature",
  "properties": {
    "addr:full":"1593 Wilson Ave North York ON M3L 1A5",
    "addr:housenumber":"1593",
    "addr:postcode":"m3l 1a5",
    "addr:street":"Wilson Ave",
    "iso:country":"CA",
    "sg:address":"1593 Wilson Ave",
    "sg:city":"North York",
    "sg:classifiers":[
        {
            "category":"Personal",
            "subcategory":"Tanning Parlor",
            "type":"Services"
        }
    ],
    "sg:phone":"+1 416 241 3544",
    "sg:postcode":"M3L 1A5",
    "sg:province":"ON",
    "sg:tags":[
        "salon"
    ],
    "wof:name":"Tropical Island Tanning",
    "wof:placetype":"venue"
},
  "geometry": {"coordinates":[-79.510521,43.720406],"type":"Point"}
}