{
  "type": "Feature",
  "properties": {
    "addr:full":"49 Holliday Dr Whitby ON L1P 1G4",
    "addr:housenumber":"49",
    "addr:postcode":"l1p 1g4",
    "addr:street":"Holliday Dr",
    "iso:country":"CA",
    "sg:address":"49 Holliday Dr",
    "sg:city":"Whitby",
    "sg:classifiers":[
        {
            "category":"Education",
            "subcategory":"Special Training",
            "type":"Public Place"
        }
    ],
    "sg:phone":"+1 905 430 3875",
    "sg:postcode":"L1P 1G4",
    "sg:province":"ON",
    "sg:tags":[
        "management"
    ],
    "wof:name":"Practical Personnel Mgmt Svc",
    "wof:placetype":"venue"
},
  "geometry": {"coordinates":[-78.962051,43.889442],"type":"Point"}
}