{
  "type": "Feature",
  "properties": {
    "addr:full":"8383 Boul Saint-Michel Montreal QC H1Z 3E7",
    "addr:housenumber":"8383",
    "addr:postcode":"h1z 3e7",
    "addr:street":"Boul Saint-Michel",
    "iso:country":"CA",
    "sg:address":"8383 Boul Saint-Michel",
    "sg:city":"Montreal",
    "sg:classifiers":[
        {
            "category":"Autos & Motor Vehicles",
            "subcategory":"Fuel & Gas Station",
            "type":"Retail Goods"
        }
    ],
    "sg:phone":"+1 514 727 0251",
    "sg:postcode":"H1Z 3E7",
    "sg:province":"QC",
    "sg:tags":[
        "oil"
    ],
    "wof:name":"Ultramar",
    "wof:placetype":"venue"
},
  "geometry": {"coordinates":[-73.61436500000001,45.566124],"type":"Point"}
}