{
  "type": "Feature",
  "properties": {
    "addr:full":"188 Bradwick Dr Concord ON L4K 1K8",
    "addr:housenumber":"188",
    "addr:postcode":"l4k 1k8",
    "addr:street":"Bradwick Dr",
    "iso:country":"CA",
    "sg:address":"188 Bradwick Dr",
    "sg:city":"Concord",
    "sg:classifiers":[
        {
            "category":"Building & Trades",
            "subcategory":"Construction",
            "type":"Services"
        }
    ],
    "sg:phone":"+1 905 669 1094",
    "sg:postcode":"L4K 1K8",
    "sg:province":"ON",
    "sg:tags":[
        "foundation"
    ],
    "wof:name":"Mcf Concrete Forming Ltd",
    "wof:placetype":"venue"
},
  "geometry": {"coordinates":[-79.48882293699999,43.8153533936],"type":"Point"}
}