{
  "type": "Feature",
  "properties": {
    "iso:country":"CA",
    "sg:address":"2006 Ch Saint-Louis # 1",
    "sg:city":"Sillery",
    "sg:classifiers":[
        {
            "category":"Recreation",
            "type":"Entertainment"
        }
    ],
    "sg:phone":"+1 418 650 6002",
    "sg:postcode":"G1T 1P1",
    "sg:province":"QC",
    "sg:tags":[
        "instruction",
        "yoga"
    ],
    "wof:name":"Institut International DE Yoga",
    "wof:placetype":"venue"
},
  "geometry": {"coordinates":[-71.249977,46.779167],"type":"Point"}
}