{
  "type": "Feature",
  "properties": {
    "iso:country":"CA",
    "sg:address":"9440 Ch DE LA Cote-DE-Liesse",
    "sg:city":"Lachine",
    "sg:classifiers":[
        {
            "category":"Wholesale",
            "subcategory":"Machinery & Supplies",
            "type":"Manufacturing & Wholesale Goods"
        }
    ],
    "sg:phone":"+1 514 636 1243",
    "sg:postcode":"H8T 1A1",
    "sg:province":"QC",
    "sg:tags":[
        "equipment",
        "material",
        "handling"
    ],
    "wof:name":"Loadmaster Equipment Ltd",
    "wof:placetype":"venue"
},
  "geometry": {"coordinates":[-73.7109375,45.4707450867],"type":"Point"}
}