{
  "type": "Feature",
  "properties": {
    "addr:full":"817 Broadway Ave Saskatoon SK S7N 1B5",
    "addr:housenumber":"817",
    "addr:postcode":"s7n 1b5",
    "addr:street":"Broadway Ave",
    "iso:country":"CA",
    "sg:address":"817 Broadway Ave",
    "sg:city":"Saskatoon",
    "sg:classifiers":[
        {
            "category":"Bars & Pubs",
            "type":"Food & Drink"
        }
    ],
    "sg:phone":"+1 306 244 4155",
    "sg:postcode":"S7N 1B5",
    "sg:province":"SK",
    "sg:tags":[
        "club",
        "night"
    ],
    "wof:name":"Buds on Broadway",
    "wof:placetype":"venue"
},
  "geometry": {"coordinates":[-106.656448,52.117558],"type":"Point"}
}