{
  "type": "Feature",
  "properties": {
    "addr:full":"7670 Rue Lajeunesse Montreal QC H2R 2J2",
    "addr:housenumber":"7670",
    "addr:postcode":"h2r 2j2",
    "addr:street":"Rue Lajeunesse",
    "iso:country":"CA",
    "sg:address":"7670 Rue Lajeunesse",
    "sg:city":"Montreal",
    "sg:classifiers":[
        {
            "category":"Retail",
            "subcategory":"Auto Repair",
            "type":"Services"
        }
    ],
    "sg:phone":"+1 514 271 5706",
    "sg:postcode":"H2R 2J2",
    "sg:province":"QC",
    "sg:tags":[
        "repairing",
        "automobile"
    ],
    "wof:name":"Station Service Pan & Fils Inc",
    "wof:placetype":"venue"
},
  "geometry": {"coordinates":[-73.621803,45.54174],"type":"Point"}
}