{
  "type": "Feature",
  "properties": {
    "addr:full":"16409 111 Ave NW Edmonton AB T5M 2S2",
    "addr:housenumber":"16409",
    "addr:postcode":"t5m 2s2",
    "addr:street":"111 Ave Nw",
    "iso:country":"CA",
    "sg:address":"16409 111 Ave NW",
    "sg:city":"Edmonton",
    "sg:classifiers":[
        {
            "category":"Wholesale",
            "subcategory":"Hardware",
            "type":"Manufacturing & Wholesale Goods"
        }
    ],
    "sg:phone":"+1 780 484 3113",
    "sg:postcode":"T5M 2S2",
    "sg:province":"AB",
    "sg:tags":[
        "fastener"
    ],
    "wof:name":"Edmonton Fasteners & Tools Ltd",
    "wof:placetype":"venue"
},
  "geometry": {"coordinates":[-113.60509491000001,53.559135437],"type":"Point"}
}