{
  "type": "Feature",
  "properties": {
    "addr:full":"135 Victoria Ave #102 Belleville ON K8N 2B1",
    "addr:housenumber":"135",
    "addr:postcode":"k8n 2b1",
    "addr:street":"Victoria Ave # 102",
    "iso:country":"CA",
    "sg:address":"135 Victoria Ave #102",
    "sg:city":"Belleville",
    "sg:classifiers":[
        {
            "category":"Insurance",
            "subcategory":"Insurance Agent",
            "type":"Services"
        }
    ],
    "sg:phone":"+1 613 962 3476",
    "sg:postcode":"K8N 2B1",
    "sg:province":"ON",
    "wof:name":"Pilot Insurance CO",
    "wof:placetype":"venue"
},
  "geometry": {"coordinates":[-77.377037,44.168324],"type":"Point"}
}