{
  "type": "Feature",
  "properties": {
    "addr:full":"248 40th Ave E Vancouver BC V5W 1L8",
    "addr:housenumber":"248",
    "addr:postcode":"v5w 1l8",
    "addr:street":"40Th Ave E",
    "iso:country":"CA",
    "sg:address":"248 40th Ave E",
    "sg:city":"Vancouver",
    "sg:classifiers":[
        {
            "category":"Professional",
            "subcategory":"Computer Services",
            "type":"Services"
        }
    ],
    "sg:phone":"+1 604 324 1511",
    "sg:postcode":"V5W 1L8",
    "sg:province":"BC",
    "sg:tags":[
        "consultant",
        "designer"
    ],
    "wof:name":"Advanced Systems Consultants",
    "wof:placetype":"venue"
},
  "geometry": {"coordinates":[-123.100479126,49.2342948914],"type":"Point"}
}