{
  "type": "Feature",
  "properties": {
    "addr:full":"203 Bosworth St Wynyard SK S0A 4T0",
    "addr:housenumber":"203",
    "addr:postcode":"s0a 4t0",
    "addr:street":"Bosworth St",
    "iso:country":"CA",
    "sg:address":"203 Bosworth St",
    "sg:city":"Wynyard",
    "sg:classifiers":[
        {
            "category":"Home & Garden",
            "subcategory":"Furniture",
            "type":"Retail Goods"
        }
    ],
    "sg:phone":"+1 306 554 2235",
    "sg:postcode":"S0A 4T0",
    "sg:province":"SK",
    "wof:name":"Harold's Furniture",
    "wof:placetype":"venue"
},
  "geometry": {"coordinates":[-104.186103821,51.7703933716],"type":"Point"}
}