{
  "type": "Feature",
  "properties": {
    "addr:full":"10206 99 Ave # A Fort Saskatchewan AB T8L 1Y1",
    "addr:housenumber":"10206",
    "addr:postcode":"t8l 1y1",
    "addr:street":"99 Ave # A",
    "iso:country":"CA",
    "sg:address":"10206 99 Ave # A",
    "sg:city":"Fort Saskatchewan",
    "sg:classifiers":[
        {
            "category":"Real Estate",
            "subcategory":"Real Estate Agent",
            "type":"Services"
        }
    ],
    "sg:phone":"+1 780 998 7368",
    "sg:postcode":"T8L 1Y1",
    "sg:province":"AB",
    "sg:tags":[
        "management"
    ],
    "wof:name":"Oakwood Management Ltd",
    "wof:placetype":"venue"
},
  "geometry": {"coordinates":[-113.211861,53.71069],"type":"Point"}
}