{
  "type": "Feature",
  "properties": {
    "addr:full":"124 University Ave Charlottetown PE C1A 4L3",
    "addr:housenumber":"124",
    "addr:postcode":"c1a 4l3",
    "addr:street":"University Ave",
    "iso:country":"CA",
    "sg:address":"124 University Ave",
    "sg:city":"Charlottetown",
    "sg:classifiers":[
        {
            "category":"Retail",
            "subcategory":"Laundry & Dry Cleaning",
            "type":"Services"
        }
    ],
    "sg:phone":"+1 902 368 3412",
    "sg:postcode":"C1A 4L3",
    "sg:province":"PE",
    "sg:tags":[
        "cleaners"
    ],
    "wof:name":"Betty Brite Dry Cleaners",
    "wof:placetype":"venue"
},
  "geometry": {"coordinates":[-63.12886,46.237339],"type":"Point"}
}