{
  "type": "Feature",
  "properties": {
    "addr:full":"2790 Sunnyside Rd Anmore BC V3H 4W9",
    "addr:housenumber":"2790",
    "addr:postcode":"v3h 4w9",
    "addr:street":"Sunnyside Rd",
    "iso:country":"CA",
    "sg:address":"2790 Sunnyside Rd",
    "sg:city":"Anmore",
    "sg:classifiers":[
        {
            "category":"Manufacturing",
            "subcategory":"Furniture",
            "type":"Manufacturing & Wholesale Goods"
        }
    ],
    "sg:phone":"+1 604 469 6427",
    "sg:postcode":"V3H 4W9",
    "sg:province":"BC",
    "sg:tags":[
        "pet",
        "shop",
        "equipment"
    ],
    "wof:name":"Universal Marine Industries",
    "wof:placetype":"venue"
},
  "geometry": {"coordinates":[-122.855567932,49.3153572083],"type":"Point"}
}