{
  "type": "Feature",
  "properties": {
    "iso:country":"CA",
    "sg:address":"15 Mill Sq",
    "sg:city":"Alexandria",
    "sg:classifiers":[
        {
            "category":"Personal",
            "subcategory":"Beauty Salon",
            "type":"Services"
        }
    ],
    "sg:phone":"+1 613 525 4921",
    "sg:postcode":"K0C 1A0",
    "sg:province":"ON",
    "wof:name":"Uptown Hair Designs",
    "wof:placetype":"venue"
},
  "geometry": {"coordinates":[-74.6361083984,45.3102378845],"type":"Point"}
}