{
  "type": "Feature",
  "properties": {
    "addr:full":"Sherwood Park AB T8H 1S8",
    "addr:postcode":"t8h 1s8",
    "iso:country":"CA",
    "sg:city":"Sherwood Park",
    "sg:classifiers":[
        {
            "category":"Health Services",
            "subcategory":"Doctor",
            "type":"Services"
        }
    ],
    "sg:phone":"+1 780 467 6880",
    "sg:postcode":"T8H 1S8",
    "sg:province":"AB",
    "sg:tags":[
        "dentist"
    ],
    "wof:name":"Caruk, Christopher DDS",
    "wof:placetype":"venue"
},
  "geometry": {"coordinates":[-113.317352,53.541416],"type":"Point"}
}