{
  "type": "Feature",
  "properties": {
    "addr:full":"660 Eglinton Ave W Mississauga ON L5R 3V2",
    "addr:housenumber":"660",
    "addr:postcode":"l5r 3v2",
    "addr:street":"Eglinton Ave W",
    "iso:country":"CA",
    "sg:address":"660 Eglinton Ave W",
    "sg:city":"Mississauga",
    "sg:classifiers":[
        {
            "category":"Restaurant",
            "type":"Food & Drink"
        }
    ],
    "sg:phone":"+1 905 507 3988",
    "sg:postcode":"L5R 3V2",
    "sg:province":"ON",
    "wof:name":"Sam Woo Restaurant",
    "wof:placetype":"venue"
},
  "geometry": {"coordinates":[-79.66803,43.593124],"type":"Point"}
}