{
  "type": "Feature",
  "properties": {
    "iso:country":"CA",
    "sg:address":"183 King George Hwy",
    "sg:city":"Miramichi",
    "sg:classifiers":[
        {
            "category":"Organizations",
            "subcategory":"Professional Association",
            "type":"Services"
        }
    ],
    "sg:phone":"+1 506 622 4916",
    "sg:postcode":"E1V 1K8",
    "sg:province":"NB",
    "wof:name":"A A Castle Group",
    "wof:placetype":"venue"
},
  "geometry": {"coordinates":[-65.5848236084,46.9770584106],"type":"Point"}
}