{
  "type": "Feature",
  "properties": {
    "addr:full":"175 St. Paul Cres St Catharines ON L2S 1N4",
    "addr:housenumber":"175",
    "addr:postcode":"l2s 1n4",
    "addr:street":"St. Paul Cres",
    "iso:country":"CA",
    "sg:address":"175 St. Paul Cres",
    "sg:city":"St Catharines",
    "sg:classifiers":[
        {
            "category":"Retail",
            "subcategory":"Auto Repair",
            "type":"Services"
        }
    ],
    "sg:phone":"+1 905 682 6400",
    "sg:postcode":"L2S 1N4",
    "sg:province":"ON",
    "sg:tags":[
        "body",
        "automobile",
        "painting"
    ],
    "wof:name":"Morrison's Auto Body & Sales",
    "wof:placetype":"venue"
},
  "geometry": {"coordinates":[-79.251457,43.147877],"type":"Point"}
}