{
  "type": "Feature",
  "properties": {
    "iso:country":"CA",
    "sg:city":"Saskatoon",
    "sg:classifiers":[
        {
            "category":"Food & Beverages",
            "subcategory":"Bakery",
            "type":"Retail Goods"
        }
    ],
    "sg:phone":"+1 306 244 1957",
    "sg:postcode":"S7K 2Y2",
    "sg:province":"SK",
    "sg:tags":[
        "baker"
    ],
    "wof:name":"Traeger's Bakery",
    "wof:placetype":"venue"
},
  "geometry": {"coordinates":[-106.648308,52.162945],"type":"Point"}
}