{
  "type": "Feature",
  "properties": {
    "addr:full":"11835 40 Ave NW Edmonton AB T6J 0R8",
    "addr:housenumber":"11835",
    "addr:postcode":"t6j 0r8",
    "addr:street":"40 Ave Nw",
    "iso:country":"CA",
    "sg:address":"11835 40 Ave NW",
    "sg:city":"Edmonton",
    "sg:classifiers":[
        {
            "category":"Food & Beverages",
            "subcategory":"Groceries & Convenience Stores",
            "type":"Retail Goods"
        }
    ],
    "sg:phone":"+1 780 436 7480",
    "sg:postcode":"T6J 0R8",
    "sg:province":"AB",
    "sg:tags":[
        "grocer"
    ],
    "wof:name":"Mac's Convenience Stores Ltd",
    "wof:placetype":"venue"
},
  "geometry": {"coordinates":[-113.537132,53.476151],"type":"Point"}
}