{
  "type": "Feature",
  "properties": {
    "addr:full":"180 Attwell Dr Etobicoke ON M9W 6A9",
    "addr:housenumber":"180",
    "addr:postcode":"m9w 6a9",
    "addr:street":"Attwell Dr",
    "iso:country":"CA",
    "sg:address":"180 Attwell Dr",
    "sg:city":"Etobicoke",
    "sg:classifiers":[
        {
            "category":"Restaurant",
            "type":"Food & Drink"
        }
    ],
    "sg:phone":"+1 416 679 9662",
    "sg:postcode":"M9W 6A9",
    "sg:province":"ON",
    "sg:tags":[
        "shop",
        "coffee"
    ],
    "wof:name":"Cupps Coffe House",
    "wof:placetype":"venue"
},
  "geometry": {"coordinates":[-79.587547,43.689175],"type":"Point"}
}