{
  "type": "Feature",
  "properties": {
    "iso:country":"CA",
    "sg:address":"190 Matheson Blvd E",
    "sg:city":"Mississauga",
    "sg:classifiers":[
        {
            "category":"Building & Trades",
            "subcategory":"Plumbing",
            "type":"Services"
        }
    ],
    "sg:phone":"+1 905 890 0077",
    "sg:postcode":"L4Z 1X1",
    "sg:province":"ON",
    "sg:tags":[
        "steel",
        "sheet",
        "work",
        "metal",
        "contractor"
    ],
    "wof:name":"Commex Group Mfg Inc",
    "wof:placetype":"venue"
},
  "geometry": {"coordinates":[-79.6681671143,43.6211166382],"type":"Point"}
}