{
  "type": "Feature",
  "properties": {
    "addr:full":"132 Rue Principale Laval QC H7X 3V2",
    "addr:housenumber":"132",
    "addr:postcode":"h7x 3v2",
    "addr:street":"Rue Principale",
    "iso:country":"CA",
    "sg:address":"132 Rue Principale",
    "sg:city":"Laval",
    "sg:classifiers":[
        {
            "category":"Building & Trades",
            "subcategory":"Construction",
            "type":"Services"
        }
    ],
    "sg:phone":"+1 450 969 3300",
    "sg:postcode":"H7X 3V2",
    "sg:province":"QC",
    "sg:tags":[
        "general",
        "contractor"
    ],
    "wof:name":"Betaplex Inc",
    "wof:placetype":"venue"
},
  "geometry": {"coordinates":[-73.79789,45.536125],"type":"Point"}
}