{
  "type": "Feature",
  "properties": {
    "addr:full":"Windermere BC V0B 2L0",
    "addr:postcode":"bc v0b 2l0",
    "iso:country":"CA",
    "sg:city":"Windermere",
    "sg:classifiers":[
        {
            "category":"Building & Trades",
            "subcategory":"Construction",
            "type":"Services"
        }
    ],
    "sg:phone":"+1 250 342 8870",
    "sg:postcode":"V0B 2L0",
    "sg:province":"BC",
    "sg:tags":[
        "general",
        "contractor"
    ],
    "wof:name":"Columbia View Homes",
    "wof:placetype":"venue"
},
  "geometry": {"coordinates":[-115.975570679,50.4655265808],"type":"Point"}
}