{
  "type": "Feature",
  "properties": {
    "iso:country":"CA",
    "sg:city":"Foster",
    "sg:classifiers":[
        {
            "category":"Travel",
            "subcategory":"Hotels & Motels",
            "type":"Entertainment"
        }
    ],
    "sg:phone":"+1 450 243 4272",
    "sg:postcode":"J0E 1R0",
    "sg:province":"QC",
    "wof:name":"Auberge Du Joli Vent",
    "wof:placetype":"venue"
},
  "geometry": {"coordinates":[-72.50146484379999,45.2944641113],"type":"Point"}
}