{
  "type": "Feature",
  "properties": {
    "iso:country":"CA",
    "sg:address":"272 Larch St",
    "sg:city":"Sudbury",
    "sg:classifiers":[
        {
            "category":"Insurance",
            "subcategory":"Insurance Agent",
            "type":"Services"
        }
    ],
    "sg:phone":"+1 705 674 1974",
    "sg:postcode":"P3B 1M1",
    "sg:province":"ON",
    "wof:name":"Conaty & Conaty",
    "wof:placetype":"venue"
},
  "geometry": {"coordinates":[-80.98802947999999,46.4914665222],"type":"Point"}
}