{
  "type": "Feature",
  "properties": {
    "addr:full":"7077 Ch DE LA Cote-Saint-Luc Cote Saint-Luc QC H4V 1J2",
    "addr:postcode":"7077;h4v 1j2",
    "addr:street":"Ch De La Cote-Saint-Luc Cote",
    "iso:country":"CA",
    "sg:address":"7077 Ch DE LA Cote-Saint-Luc",
    "sg:city":"Cote Saint-Luc",
    "sg:classifiers":[
        {
            "category":"Shopping",
            "subcategory":"Clothing, Apparel, & Fashions",
            "type":"Retail Goods"
        }
    ],
    "sg:phone":"+1 514 487 6636",
    "sg:postcode":"H4V 1J2",
    "sg:province":"QC",
    "sg:tags":[
        "lingerie"
    ],
    "wof:name":"Lingerie Karine",
    "wof:placetype":"venue"
},
  "geometry": {"coordinates":[-73.65412902830001,45.4652938843],"type":"Point"}
}