{
  "type": "Feature",
  "properties": {
    "iso:country":"CA",
    "sg:address":"101 Broad St",
    "sg:city":"Cut Knife",
    "sg:classifiers":[
        {
            "category":"Restaurant",
            "type":"Food & Drink"
        }
    ],
    "sg:phone":"+1 306 398 2566",
    "sg:postcode":"S0M 0N0",
    "sg:province":"SK",
    "wof:name":"Cut Knife Family Restaurant",
    "wof:placetype":"venue"
},
  "geometry": {"coordinates":[-109.02110290500001,52.7436714172],"type":"Point"}
}