{
  "type": "Feature",
  "properties": {
    "addr:full":"1226 Mcgill Rd Kamloops BC V2C 6N6",
    "addr:housenumber":"1226",
    "addr:postcode":"bc v2c 6n6",
    "addr:street":"Mcgill Rd",
    "iso:country":"CA",
    "sg:address":"1226 Mcgill Rd",
    "sg:city":"Kamloops",
    "sg:classifiers":[
        {
            "category":"Freight",
            "type":"Transportation"
        }
    ],
    "sg:phone":"+1 250 828 2287",
    "sg:postcode":"V2C 6N6",
    "sg:province":"BC",
    "sg:tags":[
        "commercial",
        "storage"
    ],
    "wof:name":"Mc Gill Mini Storage",
    "wof:placetype":"venue"
},
  "geometry": {"coordinates":[-120.372681,50.669983],"type":"Point"}
}