{
  "type": "Feature",
  "properties": {
    "addr:full":"Surrey BC V3S 6C4",
    "addr:postcode":"v3s 6c4",
    "iso:country":"CA",
    "sg:city":"Surrey",
    "sg:classifiers":[
        {
            "category":"Manufacturing",
            "subcategory":"Tools & Machinery",
            "type":"Manufacturing & Wholesale Goods"
        }
    ],
    "sg:phone":"+1 604 576 2800",
    "sg:postcode":"V3S 6C4",
    "sg:province":"BC",
    "sg:tags":[
        "equipment",
        "hydraulic",
        "supply"
    ],
    "wof:name":"Colco International Ind Ltd",
    "wof:placetype":"venue"
},
  "geometry": {"coordinates":[-122.72444900000001,49.102428],"type":"Point"}
}