{
  "type": "Feature",
  "properties": {
    "addr:full":"1035 26 St NE Calgary AB T2A 6K8",
    "addr:housenumber":"1035",
    "addr:postcode":"t2a 6k8",
    "addr:street":"26 St Ne",
    "iso:country":"CA",
    "sg:address":"1035 26 St NE",
    "sg:city":"Calgary",
    "sg:phone":"+1 403 248 3277",
    "sg:postcode":"T2A 6K8",
    "sg:province":"AB",
    "sg:tags":[
        "system",
        "equipment",
        "shelving",
        "filing",
        "supply"
    ],
    "wof:name":"Metro Associates",
    "wof:placetype":"venue"
},
  "geometry": {"coordinates":[-113.996239,51.060802],"type":"Point"}
}