{
  "type": "Feature",
  "properties": {
    "addr:full":"Whitehorse YT Y1A 2V2",
    "addr:postcode":"y1a 2v2",
    "iso:country":"CA",
    "sg:city":"Whitehorse",
    "sg:classifiers":[
        {
            "category":"Freight",
            "type":"Transportation"
        }
    ],
    "sg:phone":"+1 867 667 4322",
    "sg:postcode":"Y1A 2V2",
    "sg:province":"YT",
    "sg:tags":[
        "mover",
        "commercial"
    ],
    "wof:name":"Polaris Moving & Storage Ltd",
    "wof:placetype":"venue"
},
  "geometry": {"coordinates":[-135.074997,60.737816],"type":"Point"}
}