{
  "type": "Feature",
  "properties": {
    "addr:full":"1065 Rte Edouard-Vii Saint-Philippe QC J0L 2K0",
    "addr:housenumber":"1065",
    "addr:postcode":"j0l 2k0",
    "addr:street":"Rte Edouard-Vii",
    "iso:country":"CA",
    "sg:address":"1065 Rte Edouard-Vii",
    "sg:city":"Saint-Philippe",
    "sg:classifiers":[
        {
            "category":"Autos & Motor Vehicles",
            "subcategory":"Boat Sales",
            "type":"Retail Goods"
        }
    ],
    "sg:phone":"+1 450 659 3093",
    "sg:postcode":"J0L 2K0",
    "sg:province":"QC",
    "sg:tags":[
        "propeller",
        "repairing"
    ],
    "wof:name":"Services Marins Gilles Tougas",
    "wof:placetype":"venue"
},
  "geometry": {"coordinates":[-73.4688949585,45.3874511719],"type":"Point"}
}