{
  "type": "Feature",
  "properties": {
    "iso:country":"CA",
    "sg:city":"Saint-Aubert",
    "sg:classifiers":[
        {
            "category":"Education",
            "subcategory":"School",
            "type":"Public Place"
        }
    ],
    "sg:phone":"+1 418 598 3207",
    "sg:postcode":"G0R 2R0",
    "sg:province":"QC",
    "wof:name":"Ecole Aubert-DE-Gaspe",
    "wof:placetype":"venue"
},
  "geometry": {"coordinates":[-70.213051,47.185459],"type":"Point"}
}