{
  "type": "Feature",
  "properties": {
    "addr:full":"995 Rue Prevost Saint-Pierre-Ile-D'Orleans QC G0A 4E0",
    "addr:housenumber":"995",
    "addr:postcode":"g0a 4e0",
    "addr:street":"Rue Prevost Saint-Pierre-Ile-D'Orleans",
    "iso:country":"CA",
    "sg:address":"995 Rue Prevost",
    "sg:city":"Saint-Pierre-Ile-D'Orleans",
    "sg:classifiers":[
        {
            "category":"Food & Beverages",
            "subcategory":"Bakery",
            "type":"Retail Goods"
        }
    ],
    "sg:phone":"+1 418 828 2287",
    "sg:postcode":"G0A 4E0",
    "sg:province":"QC",
    "sg:tags":[
        "caterer"
    ],
    "wof:name":"Buffets Maison Enr",
    "wof:placetype":"venue"
},
  "geometry": {"coordinates":[-73.3609237671,45.5325012207],"type":"Point"}
}