{
  "type": "Feature",
  "properties": {
    "addr:full":"930 Rue Sainte-Catherine O Montreal QC H3B 1E2",
    "addr:housenumber":"930",
    "addr:postcode":"h3b 1e2",
    "addr:street":"Rue Sainte-Catherine O",
    "iso:country":"CA",
    "sg:address":"930 Rue Sainte-Catherine O",
    "sg:city":"Montreal",
    "sg:classifiers":[
        {
            "category":"Shopping",
            "subcategory":"Bicycles & Sporting Goods",
            "type":"Retail Goods"
        }
    ],
    "sg:phone":"+1 514 866 1914",
    "sg:postcode":"H3B 1E2",
    "sg:province":"QC",
    "sg:tags":[
        "sportswear"
    ],
    "wof:name":"Sports Experts",
    "wof:placetype":"venue"
},
  "geometry": {"coordinates":[-73.55767822270001,45.5165252686],"type":"Point"}
}