{
  "type": "Feature",
  "properties": {
    "addr:full":"Comox BC V9M 3M2",
    "addr:postcode":"v9m 3m2",
    "iso:country":"CA",
    "sg:city":"Comox",
    "sg:classifiers":[
        {
            "category":"Recreation",
            "type":"Entertainment"
        }
    ],
    "sg:phone":"+1 250 339 5992",
    "sg:postcode":"V9M 3M2",
    "sg:province":"BC",
    "sg:tags":[
        "martial",
        "arts",
        "instruction"
    ],
    "wof:name":"House of Kenpo Karate School",
    "wof:placetype":"venue"
},
  "geometry": {"coordinates":[-124.924880981,49.6728401184],"type":"Point"}
}