{
  "type": "Feature",
  "properties": {
    "addr:full":"46 Boul Panoramique Dolbeau-Mistassini QC G8L 5G9",
    "addr:housenumber":"46",
    "addr:postcode":"g8l 5g9",
    "addr:street":"Boul Panoramique",
    "iso:country":"CA",
    "sg:address":"46 Boul Panoramique",
    "sg:city":"Dolbeau-Mistassini",
    "sg:classifiers":[
        {
            "category":"Travel",
            "subcategory":"Hotels & Motels",
            "type":"Entertainment"
        }
    ],
    "sg:phone":"+1 418 276 1492",
    "sg:postcode":"G8L 5G9",
    "sg:province":"QC",
    "wof:name":"Motel Chute Des Peres Inc",
    "wof:placetype":"venue"
},
  "geometry": {"coordinates":[-72.21030426030001,48.8974342346],"type":"Point"}
}