{
  "type": "Feature",
  "properties": {
    "addr:full":"2157 Rue Fleury E # 201 Montreal QC H2B 1K1",
    "addr:housenumber":"2157",
    "addr:postcode":"h2b 1k1",
    "addr:street":"Rue Fleury E # 201",
    "iso:country":"CA",
    "sg:address":"2157 Rue Fleury E # 201",
    "sg:city":"Montreal",
    "sg:classifiers":[
        {
            "category":"Health Services",
            "subcategory":"Doctor",
            "type":"Services"
        }
    ],
    "sg:phone":"+1 514 388 2600",
    "sg:postcode":"H2B 1K1",
    "sg:province":"QC",
    "sg:tags":[
        "physician",
        "surgeon"
    ],
    "wof:name":"Sante Fleury",
    "wof:placetype":"venue"
},
  "geometry": {"coordinates":[-73.65078735349999,45.5719490051],"type":"Point"}
}