{
  "type": "Feature",
  "properties": {
    "iso:country":"CA",
    "sg:address":"1081 Ch Principal",
    "sg:city":"Saint-Joseph-Du-Lac",
    "sg:classifiers":[
        {
            "category":"Restaurant",
            "type":"Food & Drink"
        }
    ],
    "sg:phone":"+1 450 491 1144",
    "sg:postcode":"J0N 1M0",
    "sg:province":"QC",
    "wof:name":"Pizza Express",
    "wof:placetype":"venue"
},
  "geometry": {"coordinates":[-74.0061416626,45.533706665],"type":"Point"}
}