{
  "type": "Feature",
  "properties": {
    "addr:full":"10844 170 St NW Edmonton AB T5S 2H7",
    "addr:housenumber":"10844",
    "addr:postcode":"t5s 2h7",
    "addr:street":"170 St Nw",
    "iso:country":"CA",
    "sg:address":"10844 170 St NW",
    "sg:city":"Edmonton",
    "sg:classifiers":[
        {
            "category":"Home & Garden",
            "subcategory":"Home Furnishings",
            "type":"Retail Goods"
        }
    ],
    "sg:phone":"+1 780 453 5714",
    "sg:postcode":"T5S 2H7",
    "sg:province":"AB",
    "sg:tags":[
        "lighting",
        "fixture"
    ],
    "wof:name":"Robinson Lighting & Bath Ctr",
    "wof:placetype":"venue"
},
  "geometry": {"coordinates":[-113.615661621,53.5551185608],"type":"Point"}
}