{
  "type": "Feature",
  "properties": {
    "addr:full":"991 St John Ave Pincher Creek AB T0K 1W0",
    "addr:housenumber":"991",
    "addr:postcode":"t0k 1w0",
    "addr:street":"St John Ave",
    "iso:country":"CA",
    "sg:address":"991 St John Ave",
    "sg:city":"Pincher Creek",
    "sg:classifiers":[
        {
            "category":"Retail",
            "subcategory":"Laundry & Dry Cleaning",
            "type":"Services"
        }
    ],
    "sg:phone":"+1 403 627 4261",
    "sg:postcode":"T0K 1W0",
    "sg:province":"AB",
    "sg:tags":[
        "cleaners"
    ],
    "wof:name":"Economy Cleaners",
    "wof:placetype":"venue"
},
  "geometry": {"coordinates":[-113.944213867,49.4850082397],"type":"Point"}
}