{
  "type": "Feature",
  "properties": {
    "addr:full":"RR 4 Roseneath ON K0K 2X0",
    "addr:postcode":"k0k 2x0",
    "addr:street":"Rr 4",
    "iso:country":"CA",
    "sg:address":"RR 4",
    "sg:city":"Roseneath",
    "sg:classifiers":[
        {
            "category":"Restaurant",
            "type":"Food & Drink"
        }
    ],
    "sg:phone":"+1 905 352 2626",
    "sg:postcode":"K0K 2X0",
    "sg:province":"ON",
    "sg:tags":[
        "banquet",
        "rooms"
    ],
    "wof:name":"Fenela Hall",
    "wof:placetype":"venue"
},
  "geometry": {"coordinates":[-78.057236,44.193539],"type":"Point"}
}