{
  "type": "Feature",
  "properties": {
    "addr:full":"6151 Russell Pl Port Alberni BC V9Y 7W3",
    "addr:housenumber":"6151",
    "addr:postcode":"v9y 7w3",
    "addr:street":"Russell Pl",
    "iso:country":"CA",
    "sg:address":"6151 Russell Pl",
    "sg:city":"Port Alberni",
    "sg:classifiers":[
        {
            "category":"Social Services",
            "subcategory":"Adult Care",
            "type":"Services"
        }
    ],
    "sg:phone":"+1 250 724 5655",
    "sg:postcode":"V9Y 7W3",
    "sg:province":"BC",
    "sg:tags":[
        "community",
        "facility"
    ],
    "wof:name":"Rainbow Gardens",
    "wof:placetype":"venue"
},
  "geometry": {"coordinates":[-124.84626799999999,49.269138],"type":"Point"}
}