{
  "type": "Feature",
  "properties": {
    "addr:full":"Scarborough ON M1H 3A3",
    "addr:postcode":"m1h 3a3",
    "iso:country":"CA",
    "sg:city":"Scarborough",
    "sg:classifiers":[
        {
            "category":"Food & Beverages",
            "subcategory":"Groceries & Convenience Stores",
            "type":"Retail Goods"
        }
    ],
    "sg:phone":"+1 416 438 2583",
    "sg:postcode":"M1H 3A3",
    "sg:province":"ON",
    "sg:tags":[
        "grocer"
    ],
    "wof:name":"Toluwa African Foods & Beauty",
    "wof:placetype":"venue"
},
  "geometry": {"coordinates":[-79.23899841310001,43.7567672729],"type":"Point"}
}