{
  "type": "Feature",
  "properties": {
    "addr:full":"5033 Rue Berri #1 Montreal QC H2J 2S1",
    "addr:housenumber":"5033",
    "addr:postcode":"h2j 2s1",
    "addr:street":"Rue Berri # 1",
    "iso:country":"CA",
    "sg:address":"5033 Rue Berri #1",
    "sg:city":"Montreal",
    "sg:classifiers":[
        {
            "category":"Travel",
            "subcategory":"Travel Agent",
            "type":"Entertainment"
        }
    ],
    "sg:phone":"+1 514 842 9666",
    "sg:postcode":"H2J 2S1",
    "sg:province":"QC",
    "sg:tags":[
        "agency",
        "bureau"
    ],
    "wof:name":"Voyages Le Tassili",
    "wof:placetype":"venue"
},
  "geometry": {"coordinates":[-73.587479,45.527908],"type":"Point"}
}