{
  "type": "Feature",
  "properties": {
    "addr:full":"Gibsons BC V0N 1V7",
    "addr:postcode":"v0n 1v7",
    "iso:country":"CA",
    "sg:city":"Gibsons",
    "sg:classifiers":[
        {
            "category":"Health Services",
            "subcategory":"Health Practitioner",
            "type":"Services"
        }
    ],
    "sg:phone":"+1 604 886 6666",
    "sg:postcode":"V0N 1V7",
    "sg:province":"BC",
    "sg:tags":[
        "physiotherapist"
    ],
    "wof:name":"Gibsons Physiotherapy Clinic",
    "wof:placetype":"venue"
},
  "geometry": {"coordinates":[-123.520752,49.406818],"type":"Point"}
}