{
  "type": "Feature",
  "properties": {
    "iso:country":"CA",
    "sg:address":"780 Rue Des Patriotes",
    "sg:city":"Laval",
    "sg:classifiers":[
        {
            "category":"Building & Trades",
            "subcategory":"Landscaping Services",
            "type":"Services"
        }
    ],
    "sg:phone":"+1 450 628 3592",
    "sg:postcode":"H7L 2M7",
    "sg:province":"QC",
    "sg:tags":[
        "lawn",
        "maintenance",
        "grounds"
    ],
    "wof:name":"Martin Harnois Terrassement",
    "wof:placetype":"venue"
},
  "geometry": {"coordinates":[-73.783333,45.620258],"type":"Point"}
}