{
  "type": "Feature",
  "properties": {
    "iso:country":"CA",
    "sg:city":"Vancouver",
    "sg:classifiers":[
        {
            "category":"Social Services",
            "type":"Services"
        }
    ],
    "sg:phone":"+1 604 732 4204",
    "sg:postcode":"V6H 3K2",
    "sg:province":"BC",
    "sg:tags":[
        "counselor"
    ],
    "wof:name":"Life Force Seminars Inc",
    "wof:placetype":"venue"
},
  "geometry": {"coordinates":[-123.138962,49.257206],"type":"Point"}
}