{
  "type": "Feature",
  "properties": {
    "addr:full":"Highway 48 Pefferlaw ON L0E 1N0",
    "addr:postcode":"l0e 1n0",
    "addr:street":"Highway 48 Pefferlaw",
    "iso:country":"CA",
    "sg:address":"Highway 48",
    "sg:city":"Pefferlaw",
    "sg:classifiers":[
        {
            "category":"Recreation",
            "subcategory":"Marina",
            "type":"Entertainment"
        }
    ],
    "sg:phone":"+1 705 437 1340",
    "sg:postcode":"L0E 1N0",
    "sg:province":"ON",
    "sg:tags":[
        "dealer",
        "boat",
        "sales"
    ],
    "wof:name":"Everglades Marina",
    "wof:placetype":"venue"
},
  "geometry": {"coordinates":[-79.19375599999999,44.311722],"type":"Point"}
}