{
  "type": "Feature",
  "properties": {
    "addr:full":"412 Summerhill Ave Toronto ON M4W 2E4",
    "addr:housenumber":"412",
    "addr:postcode":"m4w 2e4",
    "addr:street":"Summerhill Ave",
    "iso:country":"CA",
    "sg:address":"412 Summerhill Ave",
    "sg:city":"Toronto",
    "sg:classifiers":[
        {
            "category":"Shopping",
            "subcategory":"Pharmacy",
            "type":"Retail Goods"
        }
    ],
    "sg:phone":"+1 416 921 2222",
    "sg:postcode":"M4W 2E4",
    "sg:province":"ON",
    "wof:name":"Marshall's Drug Store",
    "wof:placetype":"venue"
},
  "geometry": {"coordinates":[-79.376999,43.685947],"type":"Point"}
}