{
  "type": "Feature",
  "properties": {
    "addr:full":"15820 87 Ave NW Edmonton AB T5R 5Z1",
    "addr:housenumber":"15820",
    "addr:postcode":"t5r 5z1",
    "addr:street":"87 Ave Nw",
    "iso:country":"CA",
    "sg:address":"15820 87 Ave NW",
    "sg:city":"Edmonton",
    "sg:classifiers":[
        {
            "category":"Restaurant",
            "type":"Food & Drink"
        }
    ],
    "sg:phone":"+1 780 421 4677",
    "sg:postcode":"T5R 5Z1",
    "sg:province":"AB",
    "wof:name":"Brewsters Brewing CO & Rstrnt",
    "wof:placetype":"venue"
},
  "geometry": {"coordinates":[-113.59556600000001,53.519615],"type":"Point"}
}