{
  "type": "Feature",
  "properties": {
    "addr:full":"Pointe-Claire QC H9R 5P1",
    "addr:postcode":"h9r 5p1",
    "iso:country":"CA",
    "sg:city":"Pointe-Claire",
    "sg:classifiers":[
        {
            "category":"Personal",
            "subcategory":"Beauty Salon",
            "type":"Services"
        }
    ],
    "sg:phone":"+1 514 428 5813",
    "sg:postcode":"H9R 5P1",
    "sg:province":"QC",
    "wof:name":"Via Esthetica",
    "wof:placetype":"venue"
},
  "geometry": {"coordinates":[-73.83149719239999,45.469581604],"type":"Point"}
}