{
  "type": "Feature",
  "properties": {
    "addr:full":"5332 Boul Harwood Hudson QC J0P 1H0",
    "addr:housenumber":"5332",
    "addr:postcode":"j0p 1h0",
    "addr:street":"Boul Harwood",
    "iso:country":"CA",
    "sg:address":"5332 Boul Harwood",
    "sg:city":"Hudson",
    "sg:classifiers":[
        {
            "category":"Building & Trades",
            "subcategory":"Construction",
            "type":"Services"
        }
    ],
    "sg:phone":"+1 450 458 7527",
    "sg:postcode":"J0P 1H0",
    "sg:province":"QC",
    "sg:tags":[
        "excavating",
        "landscape",
        "contractor"
    ],
    "wof:name":"Entreprises Pierre Poirier",
    "wof:placetype":"venue"
},
  "geometry": {"coordinates":[-74.111694,45.430679],"type":"Point"}
}