{
  "type": "Feature",
  "properties": {
    "addr:full":"2449 Rue St Joseph Sainte-Perpetue QC J0C 1R0",
    "addr:housenumber":"2449",
    "addr:postcode":"j0c 1r0",
    "addr:street":"Rue St Joseph Sainte-Perpetue",
    "iso:country":"CA",
    "sg:address":"2449 Rue St Joseph",
    "sg:city":"Sainte-Perpetue",
    "sg:classifiers":[
        {
            "category":"Wholesale",
            "subcategory":"Auto Parts",
            "type":"Manufacturing & Wholesale Goods"
        }
    ],
    "sg:phone":"+1 819 336 6662",
    "sg:postcode":"J0C 1R0",
    "sg:province":"QC",
    "sg:tags":[
        "scooter",
        "motorcycle",
        "motor"
    ],
    "wof:name":"Atelier Lampron",
    "wof:placetype":"venue"
},
  "geometry": {"coordinates":[-72.4619522095,46.079536438],"type":"Point"}
}