{
  "type": "Feature",
  "properties": {
    "addr:full":"6 Fermor Ave Winnipeg MB R2M 0Y2",
    "addr:housenumber":"6",
    "addr:postcode":"r2m 0y2",
    "addr:street":"Fermor Ave",
    "iso:country":"CA",
    "sg:address":"6 Fermor Ave",
    "sg:city":"Winnipeg",
    "sg:classifiers":[
        {
            "category":"Education",
            "subcategory":"Library",
            "type":"Public Place"
        }
    ],
    "sg:phone":"+1 204 986 5628",
    "sg:postcode":"R2M 0Y2",
    "sg:province":"MB",
    "wof:name":"St Vital Branch Library",
    "wof:placetype":"venue"
},
  "geometry": {"coordinates":[-97.113907,49.851616],"type":"Point"}
}