{
  "type": "Feature",
  "properties": {
    "addr:full":"128 Anne St S Barrie ON L4N 6A2",
    "addr:housenumber":"128",
    "addr:postcode":"l4n 6a2",
    "addr:street":"Anne St S",
    "iso:country":"CA",
    "sg:address":"128 Anne St S",
    "sg:city":"Barrie",
    "sg:classifiers":[
        {
            "category":"Professional",
            "subcategory":"Computer Services",
            "type":"Services"
        }
    ],
    "sg:phone":"+1 705 727 0733",
    "sg:postcode":"L4N 6A2",
    "sg:province":"ON",
    "sg:tags":[
        "supply",
        "parts",
        "internet"
    ],
    "wof:name":"Trans Data Communications",
    "wof:placetype":"venue"
},
  "geometry": {"coordinates":[-79.698059082,44.3738632202],"type":"Point"}
}