{
  "type": "Feature",
  "properties": {
    "addr:full":"6363 Northam Dr Mississauga ON L4V 1N5",
    "addr:housenumber":"6363",
    "addr:postcode":"l4v 1n5",
    "addr:street":"Northam Dr",
    "iso:country":"CA",
    "sg:address":"6363 Northam Dr",
    "sg:city":"Mississauga",
    "sg:classifiers":[
        {
            "category":"Wholesale",
            "subcategory":"Apparel",
            "type":"Manufacturing & Wholesale Goods"
        }
    ],
    "sg:phone":"+1 905 677 6211",
    "sg:postcode":"L4V 1N5",
    "sg:province":"ON",
    "sg:tags":[
        "baby",
        "accessory"
    ],
    "wof:name":"Playtex Limited Canada",
    "wof:placetype":"venue"
},
  "geometry": {"coordinates":[-79.617935,43.696655],"type":"Point"}
}