{
  "type": "Feature",
  "properties": {
    "addr:full":"1112 Winnipeg St Regina SK S4R 1J6",
    "addr:housenumber":"1112",
    "addr:postcode":"s4r 1j6",
    "addr:street":"Winnipeg St",
    "iso:country":"CA",
    "sg:address":"1112 Winnipeg St",
    "sg:city":"Regina",
    "sg:classifiers":[
        {
            "category":"Education",
            "subcategory":"School",
            "type":"Public Place"
        }
    ],
    "sg:phone":"+1 306 522 4493",
    "sg:postcode":"S4R 1J6",
    "sg:province":"SK",
    "wof:name":"Regina Adult Learning Ctr",
    "wof:placetype":"venue"
},
  "geometry": {"coordinates":[-104.595444,50.461082],"type":"Point"}
}