{
  "type": "Feature",
  "properties": {
    "addr:full":"Edmonton AB T5K 1T4",
    "addr:postcode":"t5k 1t4",
    "iso:country":"CA",
    "sg:city":"Edmonton",
    "sg:classifiers":[
        {
            "category":"Real Estate",
            "subcategory":"Real Estate Operator",
            "type":"Services"
        }
    ],
    "sg:phone":"+1 780 414 6844",
    "sg:postcode":"T5K 1T4",
    "sg:province":"AB",
    "sg:tags":[
        "apartment"
    ],
    "wof:name":"Prominence Place Apartments",
    "wof:placetype":"venue"
},
  "geometry": {"coordinates":[-113.51921844500001,53.5425605774],"type":"Point"}
}