{
  "type": "Feature",
  "properties": {
    "addr:full":"2625 Av Watt Sainte-Foy QC G1P 3T2",
    "addr:housenumber":"2625",
    "addr:postcode":"g1p 3t2",
    "addr:street":"Av Watt",
    "iso:country":"CA",
    "sg:address":"2625 Av Watt",
    "sg:city":"Sainte-Foy",
    "sg:classifiers":[
        {
            "category":"Bus Charters",
            "type":"Transportation"
        }
    ],
    "sg:phone":"+1 418 658 0914",
    "sg:postcode":"G1P 3T2",
    "sg:province":"QC",
    "sg:tags":[
        "rental"
    ],
    "wof:name":"Autobus Tremblay & Paradis Inc",
    "wof:placetype":"venue"
},
  "geometry": {"coordinates":[-71.303467,46.787876],"type":"Point"}
}