{
  "type": "Feature",
  "properties": {
    "iso:country":"CA",
    "sg:address":"5900 Rue Jean-Talon E",
    "sg:city":"Saint-Leonard",
    "sg:classifiers":[
        {
            "category":"Personal",
            "type":"Services"
        }
    ],
    "sg:phone":"+1 514 256 4868",
    "sg:postcode":"H1S 1M2",
    "sg:province":"QC",
    "sg:tags":[
        "dating"
    ],
    "wof:name":"Amis DE Cupidon Enr",
    "wof:placetype":"venue"
},
  "geometry": {"coordinates":[-73.5794830322,45.5860671997],"type":"Point"}
}