{
  "type": "Feature",
  "properties": {
    "addr:full":"5990 Av Durocher Outremont QC H2V 3Y4",
    "addr:housenumber":"5990",
    "addr:postcode":"h2v 3y4",
    "addr:street":"Av Durocher",
    "iso:country":"CA",
    "sg:address":"5990 Av Durocher",
    "sg:city":"Outremont",
    "sg:classifiers":[
        {
            "category":"Health Services",
            "subcategory":"Health Practitioner",
            "type":"Services"
        }
    ],
    "sg:phone":"+1 514 270 5950",
    "sg:postcode":"H2V 3Y4",
    "sg:province":"QC",
    "sg:tags":[
        "psychologist"
    ],
    "wof:name":"Pelletier Roch",
    "wof:placetype":"venue"
},
  "geometry": {"coordinates":[-73.6083984375,45.5229072571],"type":"Point"}
}