{
  "type": "Feature",
  "properties": {
    "addr:full":"1950 Marine Dr West Vancouver BC V7V 1J8",
    "addr:housenumber":"1950",
    "addr:postcode":"v7v 1j8",
    "addr:street":"Marine Dr",
    "iso:country":"CA",
    "sg:address":"1950 Marine Dr",
    "sg:city":"West Vancouver",
    "sg:classifiers":[
        {
            "category":"Restaurant",
            "type":"Food & Drink"
        }
    ],
    "sg:phone":"+1 604 925 4551",
    "sg:postcode":"V7V 1J8",
    "sg:province":"BC",
    "sg:tags":[
        "shop",
        "coffee"
    ],
    "wof:name":"Murchie's Tea & Coffee Bar",
    "wof:placetype":"venue"
},
  "geometry": {"coordinates":[-123.16545105,49.3289489746],"type":"Point"}
}