{
  "type": "Feature",
  "properties": {
    "addr:full":"12294 104 Ave Surrey BC V3V 3H3",
    "addr:housenumber":"12294",
    "addr:postcode":"v3v 3h3",
    "addr:street":"104 Ave",
    "iso:country":"CA",
    "sg:address":"12294 104 Ave",
    "sg:city":"Surrey",
    "sg:classifiers":[
        {
            "category":"Manufacturing",
            "subcategory":"Watercraft",
            "type":"Manufacturing & Wholesale Goods"
        }
    ],
    "sg:phone":"+1 604 589 4225",
    "sg:postcode":"V3V 3H3",
    "sg:province":"BC",
    "sg:tags":[
        "boat"
    ],
    "wof:name":"Reyse Marine",
    "wof:placetype":"venue"
},
  "geometry": {"coordinates":[-122.881111,49.19178],"type":"Point"}
}