{
  "type": "Feature",
  "properties": {
    "addr:full":"4855 Rue Jarry E Saint-Leonard QC H1R 3G1",
    "addr:housenumber":"4855",
    "addr:postcode":"h1r 3g1",
    "addr:street":"Rue Jarry E",
    "iso:country":"CA",
    "sg:address":"4855 Rue Jarry E",
    "sg:city":"Saint-Leonard",
    "sg:classifiers":[
        {
            "category":"Restaurant",
            "type":"Food & Drink"
        }
    ],
    "sg:phone":"+1 514 325 7770",
    "sg:postcode":"H1R 3G1",
    "sg:province":"QC",
    "wof:name":"Restaurant Costa Del Sole",
    "wof:placetype":"venue"
},
  "geometry": {"coordinates":[-73.59631299999999,45.578918],"type":"Point"}
}