{
  "type": "Feature",
  "properties": {
    "addr:full":"1131 Rue Denault Beloeil QC J3G 3V6",
    "addr:housenumber":"1131",
    "addr:postcode":"j3g 3v6",
    "addr:street":"Rue Denault",
    "iso:country":"CA",
    "sg:address":"1131 Rue Denault",
    "sg:city":"Beloeil",
    "sg:classifiers":[
        {
            "category":"Building & Trades",
            "subcategory":"Electrical",
            "type":"Services"
        }
    ],
    "sg:phone":"+1 450 467 0918",
    "sg:postcode":"J3G 3V6",
    "sg:province":"QC",
    "sg:tags":[
        "electric",
        "contractor"
    ],
    "wof:name":"Noel Martin Electrique",
    "wof:placetype":"venue"
},
  "geometry": {"coordinates":[-73.20405599999999,45.580395],"type":"Point"}
}