{
  "type": "Feature",
  "properties": {
    "iso:country":"CA",
    "sg:address":"220 Main St",
    "sg:city":"Schomberg",
    "sg:classifiers":[
        {
            "category":"Personal",
            "subcategory":"Beauty Salon",
            "type":"Services"
        }
    ],
    "sg:phone":"+1 905 939 2329",
    "sg:postcode":"L0G 1T0",
    "sg:province":"ON",
    "wof:name":"Scents of Heaven",
    "wof:placetype":"venue"
},
  "geometry": {"coordinates":[-79.68371582029999,44.0020980835],"type":"Point"}
}