{
  "type": "Feature",
  "properties": {
    "addr:full":"11 Cerilli Cres Sudbury ON P3E 5R3",
    "addr:housenumber":"11",
    "addr:postcode":"p3e 5r3",
    "addr:street":"Cerilli Cres",
    "iso:country":"CA",
    "sg:address":"11 Cerilli Cres",
    "sg:city":"Sudbury",
    "sg:classifiers":[
        {
            "category":"Manufacturing",
            "subcategory":"Printing",
            "type":"Manufacturing & Wholesale Goods"
        }
    ],
    "sg:phone":"+1 705 523 3331",
    "sg:postcode":"P3E 5R3",
    "sg:province":"ON",
    "sg:tags":[
        "publisher"
    ],
    "wof:name":"Physical Education Digest",
    "wof:placetype":"venue"
},
  "geometry": {"coordinates":[-80.9794540405,46.4588737488],"type":"Point"}
}