{
  "type": "Feature",
  "properties": {
    "addr:full":"Bancroft ON K0L 1C0",
    "addr:postcode":"k0l 1c0",
    "iso:country":"CA",
    "sg:city":"Bancroft",
    "sg:classifiers":[
        {
            "category":"Building & Trades",
            "subcategory":"Construction",
            "type":"Services"
        }
    ],
    "sg:phone":"+1 613 332 4287",
    "sg:postcode":"K0L 1C0",
    "sg:province":"ON",
    "sg:tags":[
        "excavating",
        "contractor"
    ],
    "wof:name":"Robert Donovan Excavating",
    "wof:placetype":"venue"
},
  "geometry": {"coordinates":[-77.85334777830001,45.0565414429],"type":"Point"}
}