{
  "type": "Feature",
  "properties": {
    "addr:full":"1134 Rue Sainte-Catherine O Montreal QC H3B 1H4",
    "addr:housenumber":"1134",
    "addr:postcode":"h3b 1h4",
    "addr:street":"Rue Sainte-Catherine O",
    "iso:country":"CA",
    "sg:address":"1134 Rue Sainte-Catherine O",
    "sg:city":"Montreal",
    "sg:classifiers":[
        {
            "category":"Banks & Credit Unions",
            "subcategory":"Investment Brokerage",
            "type":"Services"
        }
    ],
    "sg:phone":"+1 514 876 3600",
    "sg:postcode":"H3B 1H4",
    "sg:province":"QC",
    "wof:name":"B Lowi Ltd",
    "wof:placetype":"venue"
},
  "geometry": {"coordinates":[-73.556595,45.517708],"type":"Point"}
}