{
  "type": "Feature",
  "properties": {
    "iso:country":"CA",
    "sg:city":"Vancouver",
    "sg:classifiers":[
        {
            "category":"Professional",
            "subcategory":"Business Services",
            "type":"Services"
        }
    ],
    "sg:phone":"+1 604 732 0648",
    "sg:postcode":"V6J 1G1",
    "sg:province":"BC",
    "sg:tags":[
        "recording",
        "studio"
    ],
    "wof:name":"Gotham City Studio Inc",
    "wof:placetype":"venue"
},
  "geometry": {"coordinates":[-123.142891,49.270489],"type":"Point"}
}