{
  "type": "Feature",
  "properties": {
    "addr:full":"1236 King St W Toronto ON M6K 1G4",
    "addr:housenumber":"1236",
    "addr:postcode":"m6k 1g4",
    "addr:street":"King St W",
    "iso:country":"CA",
    "sg:address":"1236 King St W",
    "sg:city":"Toronto",
    "sg:classifiers":[
        {
            "category":"Food & Beverages",
            "subcategory":"Groceries & Convenience Stores",
            "type":"Retail Goods"
        }
    ],
    "sg:phone":"+1 416 534 5962",
    "sg:postcode":"M6K 1G4",
    "sg:province":"ON",
    "sg:tags":[
        "grocer"
    ],
    "wof:name":"Kings Food Market",
    "wof:placetype":"venue"
},
  "geometry": {"coordinates":[-79.428658,43.638821],"type":"Point"}
}