{
  "type": "Feature",
  "properties": {
    "iso:country":"CA",
    "sg:city":"Canmore",
    "sg:classifiers":[
        {
            "category":"Professional",
            "subcategory":"Business Services",
            "type":"Services"
        }
    ],
    "sg:phone":"+1 403 678 5900",
    "sg:postcode":"T1W 2B7",
    "sg:province":"AB",
    "sg:tags":[
        "advertising",
        "embroidery"
    ],
    "wof:name":"Mountain Image Distr Ltd",
    "wof:placetype":"venue"
},
  "geometry": {"coordinates":[-115.361152649,51.0893058777],"type":"Point"}
}