{
  "type": "Feature",
  "properties": {
    "addr:full":"Toronto ON M4P 1K1",
    "addr:postcode":"m4p 1k1",
    "iso:country":"CA",
    "sg:city":"Toronto",
    "sg:classifiers":[
        {
            "category":"Shopping",
            "subcategory":"Florist",
            "type":"Retail Goods"
        }
    ],
    "sg:phone":"+1 416 440 0077",
    "sg:postcode":"M4P 1K1",
    "sg:province":"ON",
    "wof:name":"Flowers of the World",
    "wof:placetype":"venue"
},
  "geometry": {"coordinates":[-79.3920059204,43.7079467773],"type":"Point"}
}