{
  "type": "Feature",
  "properties": {
    "addr:full":"3360 Keele St North York ON M3J 1L5",
    "addr:housenumber":"3360",
    "addr:postcode":"m3j 1l5",
    "addr:street":"Keele St",
    "iso:country":"CA",
    "sg:address":"3360 Keele St",
    "sg:city":"North York",
    "sg:classifiers":[
        {
            "category":"Shopping",
            "subcategory":"Department Store",
            "type":"Retail Goods"
        }
    ],
    "sg:phone":"+1 416 633 8949",
    "sg:postcode":"M3J 1L5",
    "sg:province":"ON",
    "sg:tags":[
        "shop"
    ],
    "wof:name":"Dollar Haven",
    "wof:placetype":"venue"
},
  "geometry": {"coordinates":[-79.48696099999999,43.746353],"type":"Point"}
}