{
  "type": "Feature",
  "properties": {
    "addr:full":"681 15th St W Prince Albert SK S6V 7H9",
    "addr:housenumber":"681",
    "addr:postcode":"s6v 7h9",
    "addr:street":"15Th St",
    "iso:country":"CA",
    "sg:address":"681 15th St W",
    "sg:city":"Prince Albert",
    "sg:classifiers":[
        {
            "category":"Health Services",
            "subcategory":"Doctor",
            "type":"Services"
        }
    ],
    "sg:phone":"+1 306 764 6244",
    "sg:postcode":"S6V 7H9",
    "sg:province":"SK",
    "sg:tags":[
        "physician",
        "surgeon"
    ],
    "wof:name":"Maciel, E MD",
    "wof:placetype":"venue"
},
  "geometry": {"coordinates":[-105.771873,53.199169],"type":"Point"}
}