{
  "type": "Feature",
  "properties": {
    "addr:full":"Charlesbourg QC G1H 6K1",
    "addr:postcode":"g1h 6k1",
    "iso:country":"CA",
    "sg:city":"Charlesbourg",
    "sg:classifiers":[
        {
            "category":"Arts & Performance",
            "subcategory":"Theater",
            "type":"Entertainment"
        }
    ],
    "sg:phone":"+1 418 626 0034",
    "sg:postcode":"G1H 6K1",
    "sg:province":"QC",
    "sg:tags":[
        "musician"
    ],
    "wof:name":"Agence Musicale Roland Martel",
    "wof:placetype":"venue"
},
  "geometry": {"coordinates":[-71.260941,46.853554],"type":"Point"}
}