{
  "type": "Feature",
  "properties": {
    "addr:full":"120 Mcdonald St Saint John NB E2J 1M5",
    "addr:housenumber":"120",
    "addr:postcode":"e2j 1m5",
    "addr:street":"Mcdonald St",
    "iso:country":"CA",
    "sg:address":"120 Mcdonald St",
    "sg:city":"Saint John",
    "sg:classifiers":[
        {
            "category":"Real Estate",
            "subcategory":"Real Estate Operator",
            "type":"Services"
        }
    ],
    "sg:phone":"+1 506 658 1249",
    "sg:postcode":"E2J 1M5",
    "sg:province":"NB",
    "sg:tags":[
        "mall",
        "shopping",
        "center"
    ],
    "wof:name":"Loch Lomond Mall",
    "wof:placetype":"venue"
},
  "geometry": {"coordinates":[-66.02853399999999,45.287697],"type":"Point"}
}