{
  "type": "Feature",
  "properties": {
    "addr:full":"Calgary AB T2X 1Z2",
    "addr:postcode":"t2x 1z2",
    "iso:country":"CA",
    "sg:city":"Calgary",
    "sg:classifiers":[
        {
            "category":"Utilities",
            "subcategory":"Natural Gas",
            "type":"Services"
        }
    ],
    "sg:phone":"+1 403 254 4116",
    "sg:postcode":"T2X 1Z2",
    "sg:province":"AB",
    "wof:name":"Jonan Gas Marketing Ltd",
    "wof:placetype":"venue"
},
  "geometry": {"coordinates":[-114.069595337,50.9210128784],"type":"Point"}
}