{
  "type": "Feature",
  "properties": {
    "addr:full":"322 Regional Rd 20 Hagersville ON N0A 1H0",
    "addr:housenumber":"322;20",
    "addr:postcode":"n0a 1h0",
    "addr:street":"Regional Rd",
    "iso:country":"CA",
    "sg:address":"322 Regional Rd 20",
    "sg:city":"Hagersville",
    "sg:classifiers":[
        {
            "category":"Building & Trades",
            "subcategory":"Construction",
            "type":"Services"
        }
    ],
    "sg:phone":"+1 519 428 0096",
    "sg:postcode":"N0A 1H0",
    "sg:province":"ON",
    "sg:tags":[
        "excavating",
        "road",
        "contractor"
    ],
    "wof:name":"Anders Contracting",
    "wof:placetype":"venue"
},
  "geometry": {"coordinates":[-80.051132,42.962654],"type":"Point"}
}