{
  "type": "Feature",
  "properties": {
    "iso:country":"CA",
    "sg:address":"2691 Viscount Way # 103",
    "sg:city":"Richmond",
    "sg:classifiers":[
        {
            "category":"Professional",
            "subcategory":"Testing Lab",
            "type":"Services"
        }
    ],
    "sg:phone":"+1 604 231 8165",
    "sg:postcode":"V6V 2R5",
    "sg:province":"BC",
    "sg:tags":[
        "laboratory"
    ],
    "wof:name":"Pioneer Laboratories Inc",
    "wof:placetype":"venue"
},
  "geometry": {"coordinates":[-123.079063,49.193817],"type":"Point"}
}