{
  "type": "Feature",
  "properties": {
    "iso:country":"CA",
    "sg:address":"548 Rue Des Erables",
    "sg:city":"Sainte-Eulalie",
    "sg:classifiers":[
        {
            "category":"Education",
            "subcategory":"School",
            "type":"Public Place"
        }
    ],
    "sg:phone":"+1 819 225 4668",
    "sg:postcode":"G0Z 1E0",
    "sg:province":"QC",
    "wof:name":"Ecole Des Arbrisseaux",
    "wof:placetype":"venue"
},
  "geometry": {"coordinates":[-72.2442398071,46.1150932312],"type":"Point"}
}