{
  "type": "Feature",
  "properties": {
    "addr:full":"301 Rue DE London Sherbrooke QC J1H 3M6",
    "addr:housenumber":"301",
    "addr:postcode":"j1h 3m6",
    "addr:street":"Rue De London",
    "iso:country":"CA",
    "sg:address":"301 Rue DE London",
    "sg:city":"Sherbrooke",
    "sg:classifiers":[
        {
            "category":"Organizations",
            "subcategory":"Religious Organization",
            "type":"Services"
        }
    ],
    "sg:phone":"+1 819 564 8415",
    "sg:postcode":"J1H 3M6",
    "sg:province":"QC",
    "sg:tags":[
        "home",
        "retirement",
        "community",
        "retreat",
        "house"
    ],
    "wof:name":"London Residence",
    "wof:placetype":"venue"
},
  "geometry": {"coordinates":[-71.903465271,45.4028778076],"type":"Point"}
}