{
  "type": "Feature",
  "properties": {
    "addr:full":"Lloydminster AB T9V 0K3",
    "addr:postcode":"t9v 0k3",
    "iso:country":"CA",
    "sg:city":"Lloydminster",
    "sg:classifiers":[
        {
            "category":"Insurance",
            "subcategory":"Insurance Agent",
            "type":"Services"
        }
    ],
    "sg:phone":"+1 780 875 7223",
    "sg:postcode":"T9V 0K3",
    "sg:province":"AB",
    "wof:name":"Border City Insurance Svc Ltd",
    "wof:placetype":"venue"
},
  "geometry": {"coordinates":[-110.00822448700001,53.2823982239],"type":"Point"}
}