{
  "type": "Feature",
  "properties": {
    "iso:country":"CA",
    "sg:address":"205 1st Ave N",
    "sg:city":"Vauxhall",
    "sg:classifiers":[
        {
            "category":"Wholesale",
            "subcategory":"Petroleum",
            "type":"Manufacturing & Wholesale Goods"
        }
    ],
    "sg:phone":"+1 403 654 2137",
    "sg:postcode":"T0K 2K0",
    "sg:province":"AB",
    "sg:tags":[
        "bulk",
        "oil",
        "gasoline"
    ],
    "wof:name":"Vauxhall CO-OP Petroleums Ltd",
    "wof:placetype":"venue"
},
  "geometry": {"coordinates":[-112.10061645499999,50.0669288635],"type":"Point"}
}