{
  "type": "Feature",
  "properties": {
    "addr:full":"24 Spruce Dr Kippens NL A2N 3T7",
    "addr:housenumber":"24",
    "addr:postcode":"a2n 3t7",
    "addr:street":"Spruce Dr",
    "iso:country":"CA",
    "sg:address":"24 Spruce Dr",
    "sg:city":"Kippens",
    "sg:classifiers":[
        {
            "category":"Wholesale",
            "subcategory":"Electrical",
            "type":"Manufacturing & Wholesale Goods"
        }
    ],
    "sg:phone":"+1 709 643 3279",
    "sg:postcode":"A2N 3T7",
    "sg:province":"NL",
    "sg:tags":[
        "disposal",
        "garbage"
    ],
    "wof:name":"Containerized Sanitation Ltd",
    "wof:placetype":"venue"
},
  "geometry": {"coordinates":[-58.6222801208,48.5486602783],"type":"Point"}
}