{
  "type": "Feature",
  "properties": {
    "addr:full":"Edmonton AB T6B 2L5",
    "addr:postcode":"t6b 2l5",
    "iso:country":"CA",
    "sg:city":"Edmonton",
    "sg:classifiers":[
        {
            "category":"Professional",
            "subcategory":"Accounting & Tax Preparation",
            "type":"Services"
        }
    ],
    "sg:phone":"+1 780 451 2713",
    "sg:postcode":"T6B 2L5",
    "sg:province":"AB",
    "sg:tags":[
        "accountant"
    ],
    "wof:name":"Kalmacoff, James CA",
    "wof:placetype":"venue"
},
  "geometry": {"coordinates":[-113.417900085,53.532043457],"type":"Point"}
}