{
  "type": "Feature",
  "properties": {
    "iso:country":"CA",
    "sg:address":"365 Rue Racine E",
    "sg:city":"Chicoutimi",
    "sg:classifiers":[
        {
            "category":"Shopping",
            "subcategory":"Clothing, Apparel, & Fashions",
            "type":"Retail Goods"
        }
    ],
    "sg:phone":"+1 418 543 6565",
    "sg:postcode":"G7H 1S8",
    "sg:province":"QC",
    "sg:tags":[
        "fur",
        "business"
    ],
    "wof:name":"Fourrures Patrice Menard",
    "wof:placetype":"venue"
},
  "geometry": {"coordinates":[-71.05744934080001,48.427696228],"type":"Point"}
}