{
  "type": "Feature",
  "properties": {
    "addr:full":"275 Bloomfield Rd Chatham ON N7M 5J5",
    "addr:housenumber":"275",
    "addr:postcode":"n7m 5j5",
    "addr:street":"Bloomfield Rd",
    "iso:country":"CA",
    "sg:address":"275 Bloomfield Rd",
    "sg:city":"Chatham",
    "sg:classifiers":[
        {
            "category":"Wholesale",
            "subcategory":"Chemicals & Plastics",
            "type":"Manufacturing & Wholesale Goods"
        }
    ],
    "sg:phone":"+1 519 436 1130",
    "sg:postcode":"N7M 5J5",
    "sg:province":"ON",
    "sg:tags":[
        "alcohol"
    ],
    "wof:name":"Commercial Alcohols Inc",
    "wof:placetype":"venue"
},
  "geometry": {"coordinates":[-82.222275,42.384167],"type":"Point"}
}