{
  "type": "Feature",
  "properties": {
    "addr:full":"240 Colonization Ave S Dryden ON P8N 2M8",
    "addr:housenumber":"240",
    "addr:postcode":"p8n 2m8",
    "addr:street":"Colonization Ave S",
    "iso:country":"CA",
    "sg:address":"240 Colonization Ave S",
    "sg:city":"Dryden",
    "sg:classifiers":[
        {
            "category":"Organizations",
            "subcategory":"Membership Organization",
            "type":"Services"
        }
    ],
    "sg:phone":"+1 807 223 2515",
    "sg:postcode":"P8N 2M8",
    "sg:province":"ON",
    "wof:name":"Girl Guides of Canada",
    "wof:placetype":"venue"
},
  "geometry": {"coordinates":[-92.825142,49.773113],"type":"Point"}
}