{
  "type": "Feature",
  "properties": {
    "addr:full":"Bonnyville AB T9N 2H2",
    "addr:postcode":"t9n 2h2",
    "iso:country":"CA",
    "sg:city":"Bonnyville",
    "sg:classifiers":[
        {
            "category":"Travel",
            "subcategory":"Travel Agent",
            "type":"Entertainment"
        }
    ],
    "sg:phone":"+1 780 826 6161",
    "sg:postcode":"T9N 2H2",
    "sg:province":"AB",
    "sg:tags":[
        "agency",
        "bureau"
    ],
    "wof:name":"Gala Travel",
    "wof:placetype":"venue"
},
  "geometry": {"coordinates":[-110.737510681,54.2681846619],"type":"Point"}
}