{
  "type": "Feature",
  "properties": {
    "addr:full":"15877 Pacific Ave White Rock BC V4B 1S8",
    "addr:housenumber":"15877",
    "addr:postcode":"v4b 1s8",
    "addr:street":"Pacific Ave",
    "iso:country":"CA",
    "sg:address":"15877 Pacific Ave",
    "sg:city":"White Rock",
    "sg:classifiers":[
        {
            "category":"Social Services",
            "type":"Services"
        }
    ],
    "sg:phone":"+1 604 536 3480",
    "sg:postcode":"V4B 1S8",
    "sg:province":"BC",
    "sg:tags":[
        "community"
    ],
    "wof:name":"Whale House Program",
    "wof:placetype":"venue"
},
  "geometry": {"coordinates":[-122.782844544,49.0203170776],"type":"Point"}
}