{
  "type": "Feature",
  "properties": {
    "addr:full":"145 Stone Rd Callander ON P0H 1H0",
    "addr:housenumber":"145",
    "addr:postcode":"p0h 1h0",
    "addr:street":"Stone Rd",
    "iso:country":"CA",
    "sg:address":"145 Stone Rd",
    "sg:city":"Callander",
    "sg:classifiers":[
        {
            "category":"Manufacturing",
            "subcategory":"Tools & Machinery",
            "type":"Manufacturing & Wholesale Goods"
        }
    ],
    "sg:phone":"+1 705 752 3288",
    "sg:postcode":"P0H 1H0",
    "sg:province":"ON",
    "sg:tags":[
        "machine",
        "shop"
    ],
    "wof:name":"Hoffman Custom Machining & Mfg",
    "wof:placetype":"venue"
},
  "geometry": {"coordinates":[-79.36174,46.192982],"type":"Point"}
}