{
  "type": "Feature",
  "properties": {
    "addr:full":"Unity SK S0K 4L0",
    "addr:postcode":"s0k 4l0",
    "iso:country":"CA",
    "sg:city":"Unity",
    "sg:classifiers":[
        {
            "category":"Health Services",
            "subcategory":"Doctor",
            "type":"Services"
        }
    ],
    "sg:phone":"+1 306 228 2967",
    "sg:postcode":"S0K 4L0",
    "sg:province":"SK",
    "sg:tags":[
        "dentist"
    ],
    "wof:name":"Unity Dental Clinic",
    "wof:placetype":"venue"
},
  "geometry": {"coordinates":[-109.159889221,52.4416122437],"type":"Point"}
}