{
  "type": "Feature",
  "properties": {
    "addr:full":"369 Wilson Ave North York ON M3H 1T3",
    "addr:housenumber":"369",
    "addr:postcode":"m3h 1t3",
    "addr:street":"Wilson Ave",
    "iso:country":"CA",
    "sg:address":"369 Wilson Ave",
    "sg:city":"North York",
    "sg:classifiers":[
        {
            "category":"Food & Beverages",
            "subcategory":"Bakery",
            "type":"Retail Goods"
        }
    ],
    "sg:phone":"+1 416 630 6163",
    "sg:postcode":"M3H 1T3",
    "sg:province":"ON",
    "sg:tags":[
        "baker"
    ],
    "wof:name":"Beirut Bakery",
    "wof:placetype":"venue"
},
  "geometry": {"coordinates":[-79.4371414185,43.736656189],"type":"Point"}
}