{
  "type": "Feature",
  "properties": {
    "addr:full":"1 Eglinton Ave E Toronto ON M4P 3A1",
    "addr:housenumber":"1",
    "addr:postcode":"m4p 3a1",
    "addr:street":"Eglinton Ave E",
    "iso:country":"CA",
    "sg:address":"1 Eglinton Ave E",
    "sg:city":"Toronto",
    "sg:classifiers":[
        {
            "category":"Professional",
            "subcategory":"Accounting & Tax Preparation",
            "type":"Services"
        }
    ],
    "sg:phone":"+1 416 489 5711",
    "sg:postcode":"M4P 3A1",
    "sg:province":"ON",
    "sg:tags":[
        "accountant"
    ],
    "wof:name":"Brass Sevitt & Assoc",
    "wof:placetype":"venue"
},
  "geometry": {"coordinates":[-79.39814800000001,43.70665],"type":"Point"}
}