{
  "type": "Feature",
  "properties": {
    "addr:full":"854 Rue Mcmanamy Sherbrooke QC J1H 2N3",
    "addr:housenumber":"854",
    "addr:postcode":"j1h 2n3",
    "addr:street":"Rue Mcmanamy",
    "iso:country":"CA",
    "sg:address":"854 Rue Mcmanamy",
    "sg:city":"Sherbrooke",
    "sg:classifiers":[
        {
            "category":"Health Services",
            "subcategory":"Medical Lab",
            "type":"Services"
        }
    ],
    "sg:phone":"+1 819 565 2971",
    "sg:postcode":"J1H 2N3",
    "sg:province":"QC",
    "wof:name":"Marc's Denturologiste",
    "wof:placetype":"venue"
},
  "geometry": {"coordinates":[-71.898804,45.389515],"type":"Point"}
}