{
  "type": "Feature",
  "properties": {
    "iso:country":"CA",
    "sg:city":"Three Hills",
    "sg:classifiers":[
        {
            "category":"Retail",
            "subcategory":"Veterinary Services",
            "type":"Services"
        }
    ],
    "sg:phone":"+1 403 443 2030",
    "sg:postcode":"T0M 2A0",
    "sg:province":"AB",
    "sg:tags":[
        "veterinarian"
    ],
    "wof:name":"Kneehill Veterinary Svc",
    "wof:placetype":"venue"
},
  "geometry": {"coordinates":[-113.24514770499999,51.7071495056],"type":"Point"}
}