{
  "type": "Feature",
  "properties": {
    "addr:full":"Toronto ON M4N 2L3",
    "addr:postcode":"m4n 2l3",
    "iso:country":"CA",
    "sg:city":"Toronto",
    "sg:classifiers":[
        {
            "category":"Personal",
            "subcategory":"Beauty Salon",
            "type":"Services"
        }
    ],
    "sg:phone":"+1 416 480 9996",
    "sg:postcode":"M4N 2L3",
    "sg:province":"ON",
    "wof:name":"Danexa Salon & Spa",
    "wof:placetype":"venue"
},
  "geometry": {"coordinates":[-79.402809,43.728104],"type":"Point"}
}