{
  "type": "Feature",
  "properties": {
    "addr:full":"Mississauga ON L5T 1G1",
    "addr:postcode":"l5t 1g1",
    "iso:country":"CA",
    "sg:city":"Mississauga",
    "sg:classifiers":[
        {
            "category":"Wholesale",
            "subcategory":"Stationery",
            "type":"Manufacturing & Wholesale Goods"
        }
    ],
    "sg:phone":"+1 905 564 7622",
    "sg:postcode":"L5T 1G1",
    "sg:province":"ON",
    "sg:tags":[
        "product",
        "paper"
    ],
    "wof:name":"Blackhawk Papers Ltd",
    "wof:placetype":"venue"
},
  "geometry": {"coordinates":[-79.6576385498,43.6486434937],"type":"Point"}
}