{
  "type": "Feature",
  "properties": {
    "iso:country":"CA",
    "sg:address":"289 Whitewood Ave",
    "sg:city":"New Liskeard",
    "sg:classifiers":[
        {
            "category":"Personal",
            "subcategory":"Beauty Salon",
            "type":"Services"
        }
    ],
    "sg:phone":"+1 705 647 7274",
    "sg:postcode":"P0J 1P0",
    "sg:province":"ON",
    "wof:name":"Mariette's Beauty Salon",
    "wof:placetype":"venue"
},
  "geometry": {"coordinates":[-79.6825866699,47.508808136],"type":"Point"}
}