{
  "type": "Feature",
  "properties": {
    "iso:country":"CA",
    "sg:city":"Laval",
    "sg:classifiers":[
        {
            "category":"Food & Beverages",
            "subcategory":"Specialty",
            "type":"Retail Goods"
        }
    ],
    "sg:phone":"+1 450 622 5957",
    "sg:postcode":"H7P 1T8",
    "sg:province":"QC",
    "sg:tags":[
        "vitamin"
    ],
    "wof:name":"Panier Sante Le Petit Prince",
    "wof:placetype":"venue"
},
  "geometry": {"coordinates":[-73.79541015620001,45.5791053772],"type":"Point"}
}