{
  "type": "Feature",
  "properties": {
    "addr:full":"Kanata ON K2M 2G8",
    "addr:postcode":"k2m 2g8",
    "iso:country":"CA",
    "sg:city":"Kanata",
    "sg:classifiers":[
        {
            "category":"Building & Trades",
            "subcategory":"Plumbing",
            "type":"Services"
        }
    ],
    "sg:phone":"+1 613 591 1338",
    "sg:postcode":"K2M 2G8",
    "sg:province":"ON",
    "sg:tags":[
        "conditioning",
        "air",
        "system",
        "contractor"
    ],
    "wof:name":"Modern Niagara Hvac Svc",
    "wof:placetype":"venue"
},
  "geometry": {"coordinates":[-75.870987,45.288883],"type":"Point"}
}