{
  "type": "Feature",
  "properties": {
    "addr:full":"Calgary AB T2A 2K2",
    "addr:postcode":"t2a 2k2",
    "iso:country":"CA",
    "sg:city":"Calgary",
    "sg:classifiers":[
        {
            "category":"Food & Beverages",
            "subcategory":"Specialty",
            "type":"Retail Goods"
        }
    ],
    "sg:phone":"+1 403 248 1077",
    "sg:postcode":"T2A 2K2",
    "sg:province":"AB",
    "sg:tags":[
        "health",
        "diet"
    ],
    "wof:name":"Sangster's Health Ctr",
    "wof:placetype":"venue"
},
  "geometry": {"coordinates":[-113.979935,51.052528],"type":"Point"}
}