{
  "type": "Feature",
  "properties": {
    "addr:full":"263 Rue Saint-Paul Quebec QC G1K 3W6",
    "addr:housenumber":"263",
    "addr:postcode":"g1k 3w6",
    "addr:street":"Rue Saint-Paul",
    "iso:country":"CA",
    "sg:address":"263 Rue Saint-Paul",
    "sg:city":"Quebec",
    "sg:classifiers":[
        {
            "category":"Shopping",
            "subcategory":"Florist",
            "type":"Retail Goods"
        }
    ],
    "sg:phone":"+1 418 692 5040",
    "sg:postcode":"G1K 3W6",
    "sg:province":"QC",
    "wof:name":"Fleurs Concept Enr",
    "wof:placetype":"venue"
},
  "geometry": {"coordinates":[-71.21054100000001,46.816982],"type":"Point"}
}