{
  "type": "Feature",
  "properties": {
    "addr:full":"800 Rue Dollard Buckingham QC J8L 3H3",
    "addr:housenumber":"800",
    "addr:postcode":"j8l 3h3",
    "addr:street":"Rue Dollard",
    "iso:country":"CA",
    "sg:address":"800 Rue Dollard",
    "sg:city":"Buckingham",
    "sg:classifiers":[
        {
            "category":"Retail",
            "subcategory":"Auto Repair",
            "type":"Services"
        }
    ],
    "sg:phone":"+1 819 986 6033",
    "sg:postcode":"J8L 3H3",
    "sg:province":"QC",
    "sg:tags":[
        "automobile",
        "rustproofing",
        "undercoating"
    ],
    "wof:name":"Antirouille Krown",
    "wof:placetype":"venue"
},
  "geometry": {"coordinates":[-75.4071426392,45.5797233582],"type":"Point"}
}