{
  "type": "Feature",
  "properties": {
    "addr:full":"401 Boul Du Domaine Sainte-Therese QC J7E 4S4",
    "addr:housenumber":"401",
    "addr:postcode":"j7e 4s4",
    "addr:street":"Boul Du Domaine",
    "iso:country":"CA",
    "sg:address":"401 Boul Du Domaine",
    "sg:city":"Sainte-Therese",
    "sg:classifiers":[
        {
            "category":"Education",
            "subcategory":"School",
            "type":"Public Place"
        }
    ],
    "sg:phone":"+1 450 433 5400",
    "sg:postcode":"J7E 4S4",
    "sg:province":"QC",
    "wof:name":"Polyvalente Sainte-Therese",
    "wof:placetype":"venue"
},
  "geometry": {"coordinates":[-73.827507,45.64859],"type":"Point"}
}