{
  "type": "Feature",
  "properties": {
    "iso:country":"CA",
    "sg:city":"Quebec",
    "sg:classifiers":[
        {
            "category":"Home & Garden",
            "subcategory":"Building Materials",
            "type":"Retail Goods"
        }
    ],
    "sg:phone":"+1 418 871 0798",
    "sg:postcode":"G1P 4C6",
    "sg:province":"QC",
    "sg:tags":[
        "windows",
        "repairing",
        "remodeling",
        "contractor"
    ],
    "wof:name":"Quebec Multi-Renove Inc",
    "wof:placetype":"venue"
},
  "geometry": {"coordinates":[-71.3058853149,46.8062324524],"type":"Point"}
}