{
  "type": "Feature",
  "properties": {
    "addr:full":"3344 King George Hwy Surrey BC V4P 1A8",
    "addr:housenumber":"3344",
    "addr:postcode":"v4p 1a8",
    "addr:street":"King George Hwy",
    "iso:country":"CA",
    "sg:address":"3344 King George Hwy",
    "sg:city":"Surrey",
    "sg:classifiers":[
        {
            "category":"Health Services",
            "subcategory":"Chiropractor",
            "type":"Services"
        }
    ],
    "sg:phone":"+1 604 535 3357",
    "sg:postcode":"V4P 1A8",
    "sg:province":"BC",
    "wof:name":"Wolfgang Kliem Chiropractic",
    "wof:placetype":"venue"
},
  "geometry": {"coordinates":[-122.814781,49.062836],"type":"Point"}
}