{
  "type": "Feature",
  "properties": {
    "addr:full":"Saskatoon SK S7K 4A7",
    "addr:postcode":"s7k 4a7",
    "iso:country":"CA",
    "sg:city":"Saskatoon",
    "sg:classifiers":[
        {
            "category":"Organizations",
            "subcategory":"Professional Association",
            "type":"Services"
        }
    ],
    "sg:phone":"+1 306 975 7700",
    "sg:postcode":"S7K 4A7",
    "sg:province":"SK",
    "wof:name":"United Way of Saskatoon",
    "wof:placetype":"venue"
},
  "geometry": {"coordinates":[-106.65616607699999,52.1326751709],"type":"Point"}
}