{
  "type": "Feature",
  "properties": {
    "iso:country":"CA",
    "sg:city":"Matane",
    "sg:classifiers":[
        {
            "category":"Retail",
            "subcategory":"Repair Shop",
            "type":"Services"
        }
    ],
    "sg:phone":"+1 418 562 3217",
    "sg:postcode":"G4W 2Z2",
    "sg:province":"QC",
    "sg:tags":[
        "lock",
        "locksmith"
    ],
    "wof:name":"Serrurier Fillion Inc",
    "wof:placetype":"venue"
},
  "geometry": {"coordinates":[-67.529914856,48.8376083374],"type":"Point"}
}