{
  "type": "Feature",
  "properties": {
    "addr:full":"52892 Bunker Rd Rosedale BC V0X 1X0",
    "addr:housenumber":"52892",
    "addr:postcode":"v0x 1x0",
    "addr:street":"Bunker Rd",
    "iso:country":"CA",
    "sg:address":"52892 Bunker Rd",
    "sg:city":"Rosedale",
    "sg:classifiers":[
        {
            "category":"Restaurant",
            "type":"Food & Drink"
        }
    ],
    "sg:phone":"+1 604 794 7044",
    "sg:postcode":"V0X 1X0",
    "sg:province":"BC",
    "wof:name":"Trillium",
    "wof:placetype":"venue"
},
  "geometry": {"coordinates":[-121.805625916,49.1821098328],"type":"Point"}
}