{
  "type": "Feature",
  "properties": {
    "addr:full":"303 9th St S Humboldt SK S0K 2A0",
    "addr:housenumber":"303",
    "addr:postcode":"s0k 2a0",
    "addr:street":"9Th St S",
    "iso:country":"CA",
    "sg:address":"303 9th St S",
    "sg:city":"Humboldt",
    "sg:classifiers":[
        {
            "category":"Wholesale",
            "subcategory":"Machinery & Supplies",
            "type":"Manufacturing & Wholesale Goods"
        }
    ],
    "sg:phone":"+1 306 682 5590",
    "sg:postcode":"S0K 2A0",
    "sg:province":"SK",
    "sg:tags":[
        "agricultural",
        "implement"
    ],
    "wof:name":"Western Canada Agricultural",
    "wof:placetype":"venue"
},
  "geometry": {"coordinates":[-105.124512,52.197868],"type":"Point"}
}