{
  "type": "Feature",
  "properties": {
    "addr:full":"2370 Rue Allard Montreal QC H4E 2K9",
    "addr:housenumber":"2370",
    "addr:postcode":"h4e 2k9",
    "addr:street":"Rue Allard",
    "iso:country":"CA",
    "sg:address":"2370 Rue Allard",
    "sg:city":"Montreal",
    "sg:classifiers":[
        {
            "category":"Personal",
            "subcategory":"Beauty Salon",
            "type":"Services"
        }
    ],
    "sg:phone":"+1 514 768 5933",
    "sg:postcode":"H4E 2K9",
    "sg:province":"QC",
    "wof:name":"Salon DE Beaute France Enr",
    "wof:placetype":"venue"
},
  "geometry": {"coordinates":[-73.592888,45.451061],"type":"Point"}
}