{
  "type": "Feature",
  "properties": {
    "iso:country":"CA",
    "sg:address":"314 Bay St",
    "sg:city":"Thunder Bay",
    "sg:classifiers":[
        {
            "category":"Restaurant",
            "type":"Food & Drink"
        }
    ],
    "sg:phone":"+1 807 345 6323",
    "sg:postcode":"P7B 1S1",
    "sg:province":"ON",
    "wof:name":"Hoito Restaurant",
    "wof:placetype":"venue"
},
  "geometry": {"coordinates":[-89.23012542719999,48.4322891235],"type":"Point"}
}