{
  "type": "Feature",
  "properties": {
    "iso:country":"CA",
    "sg:address":"4020 Av Hingston",
    "sg:city":"Montreal",
    "sg:classifiers":[
        {
            "category":"Social Services",
            "subcategory":"Child Care",
            "type":"Services"
        }
    ],
    "sg:phone":"+1 514 484 3352",
    "sg:postcode":"H4A 2J7",
    "sg:province":"QC",
    "wof:name":"Garderie Communautaire",
    "wof:placetype":"venue"
},
  "geometry": {"coordinates":[-73.6239776611,45.4686851501],"type":"Point"}
}