{
  "type": "Feature",
  "properties": {
    "addr:full":"1203 Saint Martins Dr Pickering ON L1W 1M9",
    "addr:housenumber":"1203",
    "addr:postcode":"l1w 1m9",
    "addr:street":"Saint Martins Dr",
    "iso:country":"CA",
    "sg:address":"1203 Saint Martins Dr",
    "sg:city":"Pickering",
    "sg:classifiers":[
        {
            "category":"Social Services",
            "subcategory":"Child Care",
            "type":"Services"
        }
    ],
    "sg:phone":"+1 905 831 2140",
    "sg:postcode":"L1W 1M9",
    "sg:province":"ON",
    "wof:name":"Kids 'R' US",
    "wof:placetype":"venue"
},
  "geometry": {"coordinates":[-79.091751,43.826092],"type":"Point"}
}