{
  "type": "Feature",
  "properties": {
    "addr:full":"2220 1E Av Quebec QC G1L 3N1",
    "addr:housenumber":"2220",
    "addr:postcode":"g1l 3n1",
    "addr:street":"1E Av",
    "iso:country":"CA",
    "sg:address":"2220 1E Av",
    "sg:city":"Quebec",
    "sg:classifiers":[
        {
            "category":"Organizations",
            "subcategory":"Religious Organization",
            "type":"Services"
        }
    ],
    "sg:phone":"+1 418 529 0183",
    "sg:postcode":"G1L 3N1",
    "sg:province":"QC",
    "sg:tags":[
        "home",
        "retirement",
        "community",
        "retreat",
        "house"
    ],
    "wof:name":"Manoir St-Amand",
    "wof:placetype":"venue"
},
  "geometry": {"coordinates":[-71.24039459230001,46.8328208923],"type":"Point"}
}