{
  "type": "Feature",
  "properties": {
    "addr:full":"PO Box 187 Reefs Harbour NL A0K 4L0",
    "addr:housenumber":"po",
    "addr:postcode":"a0k 4l0",
    "addr:street":"Box 187 Reefs",
    "iso:country":"CA",
    "sg:address":"PO Box 187",
    "sg:city":"Reefs Harbour",
    "sg:classifiers":[
        {
            "category":"Freight",
            "type":"Transportation"
        }
    ],
    "sg:phone":"+1 709 847 4300",
    "sg:postcode":"A0K 4L0",
    "sg:province":"NL",
    "sg:tags":[
        "trucking"
    ],
    "wof:name":"Gnr Enterprises",
    "wof:placetype":"venue"
},
  "geometry": {"coordinates":[-57.0238494873,51.021320343],"type":"Point"}
}