{
  "type": "Feature",
  "properties": {
    "addr:full":"2356 Finch Ave W North York ON M9M 2C7",
    "addr:housenumber":"2356",
    "addr:postcode":"m9m 2c7",
    "addr:street":"Finch Ave W",
    "iso:country":"CA",
    "sg:address":"2356 Finch Ave W",
    "sg:city":"North York",
    "sg:classifiers":[
        {
            "category":"Restaurant",
            "type":"Food & Drink"
        }
    ],
    "sg:phone":"+1 416 743 4776",
    "sg:postcode":"M9M 2C7",
    "sg:province":"ON",
    "wof:name":"Cane Grove Restaurant",
    "wof:placetype":"venue"
},
  "geometry": {"coordinates":[-79.5440979004,43.7518577576],"type":"Point"}
}