{
  "type": "Feature",
  "properties": {
    "iso:country":"CA",
    "sg:address":"795 Warden Ave",
    "sg:city":"Scarborough",
    "sg:classifiers":[
        {
            "category":"Shopping",
            "type":"Retail Goods"
        }
    ],
    "sg:phone":"+1 416 751 8883",
    "sg:postcode":"M1L 4C4",
    "sg:province":"ON",
    "sg:tags":[
        "art",
        "gallery",
        "dealer"
    ],
    "wof:name":"African Village",
    "wof:placetype":"venue"
},
  "geometry": {"coordinates":[-79.28717041020001,43.7270736694],"type":"Point"}
}