{
  "type": "Feature",
  "properties": {
    "addr:full":"Calgary AB T3G 2P6",
    "addr:postcode":"t3g 2p6",
    "iso:country":"CA",
    "sg:city":"Calgary",
    "sg:classifiers":[
        {
            "category":"Banks & Credit Unions",
            "subcategory":"Bank",
            "type":"Services"
        }
    ],
    "sg:phone":"+1 403 208 4542",
    "sg:postcode":"T3G 2P6",
    "sg:province":"AB",
    "sg:tags":[
        "cashing",
        "loan",
        "check"
    ],
    "wof:name":"Money Mart",
    "wof:placetype":"venue"
},
  "geometry": {"coordinates":[-114.199943542,51.125415802],"type":"Point"}
}