{
  "type": "Feature",
  "properties": {
    "iso:country":"CA",
    "sg:address":"430 Rue Dunver",
    "sg:city":"Chateauguay",
    "sg:classifiers":[
        {
            "category":"Retail",
            "subcategory":"Portrait Studio",
            "type":"Services"
        }
    ],
    "sg:phone":"+1 450 691 3711",
    "sg:postcode":"J6J 2J4",
    "sg:province":"QC",
    "sg:tags":[
        "photographer"
    ],
    "wof:name":"Studio Jacques Turcot",
    "wof:placetype":"venue"
},
  "geometry": {"coordinates":[-73.71509552000001,45.3627357483],"type":"Point"}
}