{
  "type": "Feature",
  "properties": {
    "addr:full":"100 Mile House BC V0K 2E0",
    "addr:postcode":"v0k 2e0",
    "iso:country":"CA",
    "sg:city":"100 Mile House",
    "sg:classifiers":[
        {
            "category":"Health Services",
            "subcategory":"Chiropractor",
            "type":"Services"
        }
    ],
    "sg:phone":"+1 250 395 4833",
    "sg:postcode":"V0K 2E0",
    "sg:province":"BC",
    "wof:name":"Chiropractic Associates",
    "wof:placetype":"venue"
},
  "geometry": {"coordinates":[-121.29737854,51.6421318054],"type":"Point"}
}