{
  "type": "Feature",
  "properties": {
    "addr:full":"15 DE LA Station Saint-Ephrem-DE-Beauce QC G0M 1R0",
    "addr:postcode":"g0m 1r0",
    "addr:street":"15 De La Station Saint-Ephrem-De-Beauce",
    "iso:country":"CA",
    "sg:address":"15 DE LA Station",
    "sg:city":"Saint-Ephrem-DE-Beauce",
    "sg:classifiers":[
        {
            "category":"Education",
            "subcategory":"School",
            "type":"Public Place"
        }
    ],
    "sg:phone":"+1 418 484 2160",
    "sg:postcode":"G0M 1R0",
    "sg:province":"QC",
    "wof:name":"Convent St-Ephrem",
    "wof:placetype":"venue"
},
  "geometry": {"coordinates":[-70.9531097412,46.0596199036],"type":"Point"}
}