{
  "type": "Feature",
  "properties": {
    "addr:full":"339 Main St N Markham ON L3P 1Z2",
    "addr:housenumber":"339",
    "addr:postcode":"l3p 1z2",
    "addr:street":"Main St N",
    "iso:country":"CA",
    "sg:address":"339 Main St N",
    "sg:city":"Markham",
    "sg:classifiers":[
        {
            "category":"Professional",
            "subcategory":"Accounting & Tax Preparation",
            "type":"Services"
        }
    ],
    "sg:phone":"+1 905 201 8073",
    "sg:postcode":"L3P 1Z2",
    "sg:province":"ON",
    "sg:tags":[
        "accountant"
    ],
    "wof:name":"Professional Management Svc",
    "wof:placetype":"venue"
},
  "geometry": {"coordinates":[-79.2632827759,43.8893432617],"type":"Point"}
}