{
  "type": "Feature",
  "properties": {
    "addr:full":"585 Bay St Victoria BC V8T 1P5",
    "addr:housenumber":"585",
    "addr:postcode":"v8t 1p5",
    "addr:street":"Bay St",
    "iso:country":"CA",
    "sg:address":"585 Bay St",
    "sg:city":"Victoria",
    "sg:classifiers":[
        {
            "category":"Wholesale",
            "subcategory":"Hardware",
            "type":"Manufacturing & Wholesale Goods"
        }
    ],
    "sg:phone":"+1 250 386 4328",
    "sg:postcode":"V8T 1P5",
    "sg:province":"BC",
    "sg:tags":[
        "equipment",
        "furnace",
        "heating",
        "system"
    ],
    "wof:name":"Sinclair Supply Ltd",
    "wof:placetype":"venue"
},
  "geometry": {"coordinates":[-123.369629,48.435802],"type":"Point"}
}