{
  "type": "Feature",
  "properties": {
    "addr:full":"2588 Rue Bernard-Pilon Saint-Mathieu-DE-Beloeil QC J3G 4S5",
    "addr:housenumber":"2588",
    "addr:postcode":"j3g 4s5",
    "addr:street":"Rue Bernard-Pilon",
    "iso:country":"CA",
    "sg:address":"2588 Rue Bernard-Pilon",
    "sg:city":"Saint-Mathieu-DE-Beloeil",
    "sg:classifiers":[
        {
            "category":"Manufacturing",
            "subcategory":"Tools & Machinery",
            "type":"Manufacturing & Wholesale Goods"
        }
    ],
    "sg:phone":"+1 450 464 1723",
    "sg:postcode":"J3G 4S5",
    "sg:province":"QC",
    "sg:tags":[
        "equipment",
        "laboratory",
        "supply"
    ],
    "wof:name":"Simport Plastiques Ltee",
    "wof:placetype":"venue"
},
  "geometry": {"coordinates":[-73.254272,45.573952],"type":"Point"}
}