{
  "type": "Feature",
  "properties": {
    "iso:country":"CA",
    "sg:address":"8924 149 St NW",
    "sg:city":"Edmonton",
    "sg:classifiers":[
        {
            "category":"Food & Beverages",
            "subcategory":"Liquor & Beverages",
            "type":"Retail Goods"
        }
    ],
    "sg:phone":"+1 780 481 6868",
    "sg:postcode":"T5R 1B8",
    "sg:province":"AB",
    "sg:tags":[
        "store"
    ],
    "wof:name":"Liquor Select Ltd",
    "wof:placetype":"venue"
},
  "geometry": {"coordinates":[-113.57807159399999,53.5218086243],"type":"Point"}
}