{
  "type": "Feature",
  "properties": {
    "addr:full":"4939 Rue DE LA Fabrique Laval QC H7C 1E4",
    "addr:housenumber":"4939",
    "addr:postcode":"h7c 1e4",
    "addr:street":"Rue De La Fabrique",
    "iso:country":"CA",
    "sg:address":"4939 Rue DE LA Fabrique",
    "sg:city":"Laval",
    "sg:classifiers":[
        {
            "category":"Recreation",
            "type":"Entertainment"
        }
    ],
    "sg:phone":"+1 450 661 1225",
    "sg:postcode":"H7C 1E4",
    "sg:province":"QC",
    "sg:tags":[
        "club",
        "skating",
        "instruction"
    ],
    "wof:name":"Club DE Patinage Artistique",
    "wof:placetype":"venue"
},
  "geometry": {"coordinates":[-73.6501541138,45.613117218],"type":"Point"}
}