{
  "type": "Feature",
  "properties": {
    "addr:full":"RR 2 Tignish PE C0B 2B0",
    "addr:postcode":"c0b 2b0",
    "addr:street":"Rr 2",
    "iso:country":"CA",
    "sg:address":"RR 2",
    "sg:city":"Tignish",
    "sg:classifiers":[
        {
            "category":"Building & Trades",
            "subcategory":"Construction",
            "type":"Services"
        }
    ],
    "sg:phone":"+1 902 882 2000",
    "sg:postcode":"C0B 2B0",
    "sg:province":"PE",
    "sg:tags":[
        "well",
        "drilling"
    ],
    "wof:name":"Mac Donald Watson Well Drillin",
    "wof:placetype":"venue"
},
  "geometry": {"coordinates":[-64.03338599999999,46.951317],"type":"Point"}
}