{
  "type": "Feature",
  "properties": {
    "addr:full":"375 Rue Temiscouata Riviere-Du-Loup QC G5R 2Y9",
    "addr:housenumber":"375",
    "addr:postcode":"g5r 2y9",
    "addr:street":"Rue Temiscouata Riviere-Du-Loup",
    "iso:country":"CA",
    "sg:address":"375 Rue Temiscouata",
    "sg:city":"Riviere-Du-Loup",
    "sg:classifiers":[
        {
            "category":"Autos & Motor Vehicles",
            "subcategory":"Automobile Sales",
            "type":"Retail Goods"
        }
    ],
    "sg:phone":"+1 418 862 7231",
    "sg:postcode":"G5R 2Y9",
    "sg:province":"QC",
    "sg:tags":[
        "truck"
    ],
    "wof:name":"Centre Routier Inc",
    "wof:placetype":"venue"
},
  "geometry": {"coordinates":[-69.505486,47.821327],"type":"Point"}
}