{
  "type": "Feature",
  "properties": {
    "addr:full":"209 Water St St Andrews NB E5B 1B3",
    "addr:housenumber":"209",
    "addr:postcode":"e5b 1b3",
    "addr:street":"Water St",
    "iso:country":"CA",
    "sg:address":"209 Water St",
    "sg:city":"St Andrews",
    "sg:classifiers":[
        {
            "category":"Shopping",
            "subcategory":"Crafts & Fabrics",
            "type":"Retail Goods"
        }
    ],
    "sg:phone":"+1 506 529 3190",
    "sg:postcode":"E5B 1B3",
    "sg:province":"NB",
    "sg:tags":[
        "woolen"
    ],
    "wof:name":"Cottage Craft Tweeds & Yarns",
    "wof:placetype":"venue"
},
  "geometry": {"coordinates":[-67.052795,45.073635],"type":"Point"}
}