{
  "type": "Feature",
  "properties": {
    "addr:full":"13666 Rue DE L'Eglise Mirabel QC J7J 1H9",
    "addr:housenumber":"13666",
    "addr:postcode":"j7j 1h9",
    "addr:street":"Rue De L'Eglise",
    "iso:country":"CA",
    "sg:address":"13666 Rue DE L'Eglise",
    "sg:city":"Mirabel",
    "sg:classifiers":[
        {
            "category":"Manufacturing",
            "subcategory":"Furniture",
            "type":"Manufacturing & Wholesale Goods"
        }
    ],
    "sg:phone":"+1 450 433 0397",
    "sg:postcode":"J7J 1H9",
    "sg:province":"QC",
    "wof:name":"Armoires Et Meubles M Groulx",
    "wof:placetype":"venue"
},
  "geometry": {"coordinates":[-73.929817,45.70462],"type":"Point"}
}