{
  "type": "Feature",
  "properties": {
    "addr:full":"3549 Opie Cres Prince George BC V2N 1B8",
    "addr:housenumber":"3549",
    "addr:postcode":"v2n 1b8",
    "addr:street":"Opie Cres",
    "iso:country":"CA",
    "sg:address":"3549 Opie Cres",
    "sg:city":"Prince George",
    "sg:classifiers":[
        {
            "category":"Mining & Drilling",
            "type":"Manufacturing & Wholesale Goods"
        }
    ],
    "sg:phone":"+1 250 564 7786",
    "sg:postcode":"V2N 1B8",
    "sg:province":"BC",
    "sg:tags":[
        "contractor"
    ],
    "wof:name":"Jempland Construction Ltd",
    "wof:placetype":"venue"
},
  "geometry": {"coordinates":[-122.786057,53.900642],"type":"Point"}
}