{
  "type": "Feature",
  "properties": {
    "addr:full":"Gloucester ON K1J 9H3",
    "addr:postcode":"k1j 9h3",
    "iso:country":"CA",
    "sg:city":"Gloucester",
    "sg:classifiers":[
        {
            "category":"Retail",
            "subcategory":"Auto Repair",
            "type":"Services"
        }
    ],
    "sg:phone":"+1 613 745 1421",
    "sg:postcode":"K1J 9H3",
    "sg:province":"ON",
    "sg:tags":[
        "repairing",
        "automobile"
    ],
    "wof:name":"Best Garage",
    "wof:placetype":"venue"
},
  "geometry": {"coordinates":[-75.58313800000001,45.458916],"type":"Point"}
}