{
  "type": "Feature",
  "properties": {
    "addr:full":"1040 Av Rockland Outremont QC H2V 3A1",
    "addr:housenumber":"1040",
    "addr:postcode":"h2v 3a1",
    "addr:street":"Av Rockland",
    "iso:country":"CA",
    "sg:address":"1040 Av Rockland",
    "sg:city":"Outremont",
    "sg:classifiers":[
        {
            "category":"Manufacturing",
            "subcategory":"Chemicals & Compounds",
            "type":"Manufacturing & Wholesale Goods"
        }
    ],
    "sg:phone":"+1 514 270 8241",
    "sg:postcode":"H2V 3A1",
    "sg:province":"QC",
    "sg:tags":[
        "equipment",
        "cosmetic"
    ],
    "wof:name":"Laboratoire Dr Renaud Inc",
    "wof:placetype":"venue"
},
  "geometry": {"coordinates":[-73.62172700000001,45.5186],"type":"Point"}
}