{
  "type": "Feature",
  "properties": {
    "addr:full":"Warwick St Digby NS B0V 1A0",
    "addr:postcode":"b0v 1a0",
    "addr:street":"Warwick St",
    "iso:country":"CA",
    "sg:address":"Warwick St",
    "sg:city":"Digby",
    "sg:classifiers":[
        {
            "category":"Organizations",
            "subcategory":"Non-profit Organization",
            "type":"Services"
        }
    ],
    "sg:phone":"+1 902 245 5824",
    "sg:postcode":"B0V 1A0",
    "sg:province":"NS",
    "sg:tags":[
        "charitable",
        "institution"
    ],
    "wof:name":"Good Neighbor",
    "wof:placetype":"venue"
},
  "geometry": {"coordinates":[-65.755753,44.618107],"type":"Point"}
}