{
  "type": "Feature",
  "properties": {
    "addr:full":"39 Pembroke St W Pembroke ON K8A 6Y6",
    "addr:housenumber":"39",
    "addr:postcode":"k8a 6y6",
    "addr:street":"Pembroke St W",
    "iso:country":"CA",
    "sg:address":"39 Pembroke St W",
    "sg:city":"Pembroke",
    "sg:classifiers":[
        {
            "category":"Professional",
            "subcategory":"Lawyer & Legal Services",
            "type":"Services"
        }
    ],
    "sg:phone":"+1 613 735 2555",
    "sg:postcode":"K8A 6Y6",
    "sg:province":"ON",
    "sg:tags":[
        "attorney"
    ],
    "wof:name":"Sammon, M Peter",
    "wof:placetype":"venue"
},
  "geometry": {"coordinates":[-77.113258,45.826317],"type":"Point"}
}