{
  "type": "Feature",
  "properties": {
    "addr:full":"Longlac ON P0T 2A0",
    "addr:postcode":"p0t 2a0",
    "iso:country":"CA",
    "sg:city":"Longlac",
    "sg:classifiers":[
        {
            "category":"Travel",
            "subcategory":"Hotels & Motels",
            "type":"Entertainment"
        }
    ],
    "sg:phone":"+1 807 876 4176",
    "sg:postcode":"P0T 2A0",
    "sg:province":"ON",
    "sg:tags":[
        "tourist",
        "accommodation"
    ],
    "wof:name":"Northwood Lodging",
    "wof:placetype":"venue"
},
  "geometry": {"coordinates":[-86.5350494385,49.7805366516],"type":"Point"}
}