{
  "type": "Feature",
  "properties": {
    "addr:full":"2059 Rue Saint-Hubert Montreal QC H2L 3Z6",
    "addr:housenumber":"2059",
    "addr:postcode":"h2l 3z6",
    "addr:street":"Rue Saint-Hubert",
    "iso:country":"CA",
    "sg:address":"2059 Rue Saint-Hubert",
    "sg:city":"Montreal",
    "sg:classifiers":[
        {
            "category":"Real Estate",
            "subcategory":"Architect",
            "type":"Services"
        }
    ],
    "sg:phone":"+1 514 528 5421",
    "sg:postcode":"H2L 3Z6",
    "sg:province":"QC",
    "wof:name":"Peterson Architects",
    "wof:placetype":"venue"
},
  "geometry": {"coordinates":[-73.565331,45.5186],"type":"Point"}
}