{
  "type": "Feature",
  "properties": {
    "addr:full":"525 Lowry's Rd Parksville BC V9P 2R8",
    "addr:housenumber":"525",
    "addr:postcode":"v9p 2r8",
    "addr:street":"Lowry'S Rd",
    "iso:country":"CA",
    "sg:address":"525 Lowry's Rd",
    "sg:city":"Parksville",
    "sg:classifiers":[
        {
            "category":"Sports & Exercise",
            "subcategory":"Golf",
            "type":"Entertainment"
        }
    ],
    "sg:phone":"+1 250 248 8161",
    "sg:postcode":"V9P 2R8",
    "sg:province":"BC",
    "sg:tags":[
        "course"
    ],
    "wof:name":"Morningstar Golf Course Ltd",
    "wof:placetype":"venue"
},
  "geometry": {"coordinates":[-124.313637,49.319691],"type":"Point"}
}