{
  "type": "Feature",
  "properties": {
    "addr:full":"Markham ON L3R 8E7",
    "addr:postcode":"l3r 8e7",
    "iso:country":"CA",
    "sg:city":"Markham",
    "sg:classifiers":[
        {
            "category":"Manufacturing",
            "subcategory":"Tools & Machinery",
            "type":"Manufacturing & Wholesale Goods"
        }
    ],
    "sg:phone":"+1 905 475 0862",
    "sg:postcode":"L3R 8E7",
    "sg:province":"ON",
    "sg:tags":[
        "die",
        "maker"
    ],
    "wof:name":"Jayar Die & Design CO",
    "wof:placetype":"venue"
},
  "geometry": {"coordinates":[-79.359222,43.844303],"type":"Point"}
}