{
  "type": "Feature",
  "properties": {
    "addr:full":"1070 Av DE L'Hotel-DE-Ville Montreal QC H2X 3A6",
    "addr:housenumber":"1070",
    "addr:postcode":"h2x 3a6",
    "addr:street":"Av De L'Hotel-De-Ville",
    "iso:country":"CA",
    "sg:address":"1070 Av DE L'Hotel-DE-Ville",
    "sg:city":"Montreal",
    "sg:classifiers":[
        {
            "category":"Real Estate",
            "subcategory":"Real Estate Agent",
            "type":"Services"
        }
    ],
    "sg:phone":"+1 514 879 1325",
    "sg:postcode":"H2X 3A6",
    "sg:province":"QC",
    "sg:tags":[
        "authorities",
        "housing"
    ],
    "wof:name":"Logements Communautaires",
    "wof:placetype":"venue"
},
  "geometry": {"coordinates":[-73.5565490723,45.5091819763],"type":"Point"}
}