{
  "type": "Feature",
  "properties": {
    "addr:full":"Sainte-Marie QC G6E 1M6",
    "addr:postcode":"g6e 1m6",
    "iso:country":"CA",
    "sg:city":"Sainte-Marie",
    "sg:classifiers":[
        {
            "category":"Retail",
            "subcategory":"Veterinary Services",
            "type":"Services"
        }
    ],
    "sg:phone":"+1 418 387 2111",
    "sg:postcode":"G6E 1M6",
    "sg:province":"QC",
    "sg:tags":[
        "attorney",
        "veterinarian"
    ],
    "wof:name":"Clinique Veterinaire Du Comp",
    "wof:placetype":"venue"
},
  "geometry": {"coordinates":[-71.03478200000001,46.453655],"type":"Point"}
}