{
  "type": "Feature",
  "properties": {
    "addr:full":"45 Av Des Freres Drummondville QC J2B 6A2",
    "addr:postcode":"j2b 6a2",
    "addr:street":"45 Av Des Freres",
    "iso:country":"CA",
    "sg:address":"45 Av Des Freres",
    "sg:city":"Drummondville",
    "sg:classifiers":[
        {
            "category":"Education",
            "subcategory":"School",
            "type":"Public Place"
        }
    ],
    "sg:phone":"+1 819 474 0753",
    "sg:postcode":"J2B 6A2",
    "sg:province":"QC",
    "wof:name":"Jeanne-Mance Ecole",
    "wof:placetype":"venue"
},
  "geometry": {"coordinates":[-72.47863,45.881081],"type":"Point"}
}