{
  "type": "Feature",
  "properties": {
    "addr:full":"4929 Rue Jarry E Saint-Leonard QC H1R 1Y1",
    "addr:housenumber":"4929",
    "addr:postcode":"h1r 1y1",
    "addr:street":"Rue Jarry E",
    "iso:country":"CA",
    "sg:address":"4929 Rue Jarry E",
    "sg:city":"Saint-Leonard",
    "sg:classifiers":[
        {
            "category":"Professional",
            "subcategory":"Business Services",
            "type":"Services"
        }
    ],
    "sg:phone":"+1 514 324 1024",
    "sg:postcode":"H1R 1Y1",
    "sg:province":"QC",
    "sg:tags":[
        "inventory"
    ],
    "wof:name":"Igp Specialiste D'Inventaire",
    "wof:placetype":"venue"
},
  "geometry": {"coordinates":[-73.5955734253,45.5797615051],"type":"Point"}
}