{
  "type": "Feature",
  "properties": {
    "addr:full":"Edmonton AB T6L 6W6",
    "addr:postcode":"t6l 6w6",
    "iso:country":"CA",
    "sg:city":"Edmonton",
    "sg:classifiers":[
        {
            "category":"Health Services",
            "subcategory":"Doctor",
            "type":"Services"
        }
    ],
    "sg:phone":"+1 780 450 3200",
    "sg:postcode":"T6L 6W6",
    "sg:province":"AB",
    "sg:tags":[
        "physician",
        "surgeon"
    ],
    "wof:name":"Heston, Jonathan P MD",
    "wof:placetype":"venue"
},
  "geometry": {"coordinates":[-113.427932739,53.4580116272],"type":"Point"}
}