{
  "type": "Feature",
  "properties": {
    "addr:full":"1104 Eglinton Ave W Toronto ON M6C 2E2",
    "addr:housenumber":"1104",
    "addr:postcode":"m6c 2e2",
    "addr:street":"Eglinton Ave W",
    "iso:country":"CA",
    "sg:address":"1104 Eglinton Ave W",
    "sg:city":"Toronto",
    "sg:classifiers":[
        {
            "category":"Shopping",
            "type":"Retail Goods"
        }
    ],
    "sg:phone":"+1 416 781 6885",
    "sg:postcode":"M6C 2E2",
    "sg:province":"ON",
    "sg:tags":[
        "shop",
        "bridal",
        "wedding",
        "supply"
    ],
    "wof:name":"Crowning Glory Bridal Access",
    "wof:placetype":"venue"
},
  "geometry": {"coordinates":[-79.4317245483,43.6997947693],"type":"Point"}
}