{
  "type": "Feature",
  "properties": {
    "iso:country":"CA",
    "sg:city":"Surrey",
    "sg:classifiers":[
        {
            "category":"Government",
            "subcategory":"Office",
            "type":"Public Place"
        }
    ],
    "sg:phone":"+1 604 587 4750",
    "sg:postcode":"V3R 0Z7",
    "sg:province":"BC",
    "wof:name":"British Columbia Public Health",
    "wof:placetype":"venue"
},
  "geometry": {"coordinates":[-122.798301697,49.1880340576],"type":"Point"}
}