{
  "type": "Feature",
  "properties": {
    "addr:full":"Scarborough ON M1H 3C7",
    "addr:postcode":"m1h 3c7",
    "iso:country":"CA",
    "sg:city":"Scarborough",
    "sg:classifiers":[
        {
            "category":"Shopping",
            "subcategory":"Clothing, Apparel, & Fashions",
            "type":"Retail Goods"
        }
    ],
    "sg:phone":"+1 416 431 3334",
    "sg:postcode":"M1H 3C7",
    "sg:province":"ON",
    "sg:tags":[
        "swimwear",
        "accessory"
    ],
    "wof:name":"Omni Swim Aquatic Supplies Inc",
    "wof:placetype":"venue"
},
  "geometry": {"coordinates":[-79.2420578003,43.7761039734],"type":"Point"}
}