{
  "type": "Feature",
  "properties": {
    "addr:full":"80 Rue Notre-Dame O Montreal QC H2Y 1S6",
    "addr:housenumber":"80",
    "addr:postcode":"h2y 1s6",
    "addr:street":"Rue Notre-Dame O",
    "iso:country":"CA",
    "sg:address":"80 Rue Notre-Dame O",
    "sg:city":"Montreal",
    "sg:classifiers":[
        {
            "category":"Shopping",
            "subcategory":"Gifts & Souvenirs",
            "type":"Retail Goods"
        }
    ],
    "sg:phone":"+1 514 286 7154",
    "sg:postcode":"H2Y 1S6",
    "sg:province":"QC",
    "sg:tags":[
        "shop"
    ],
    "wof:name":"New Bazar",
    "wof:placetype":"venue"
},
  "geometry": {"coordinates":[-73.5550003052,45.506778717],"type":"Point"}
}