{
  "type": "Feature",
  "properties": {
    "iso:country":"CA",
    "sg:city":"Grande Prairie",
    "sg:classifiers":[
        {
            "category":"Building & Trades",
            "subcategory":"Electrical",
            "type":"Services"
        }
    ],
    "sg:phone":"+1 780 532 5029",
    "sg:postcode":"T8V 6M3",
    "sg:province":"AB",
    "sg:tags":[
        "electric",
        "contractor"
    ],
    "wof:name":"Jdl Electric",
    "wof:placetype":"venue"
},
  "geometry": {"coordinates":[-118.811042786,55.167263031],"type":"Point"}
}