{
  "type": "Feature",
  "properties": {
    "addr:full":"Quebec QC G2E 5E2",
    "addr:postcode":"qc g2e 5e2",
    "iso:country":"CA",
    "sg:city":"Quebec",
    "sg:classifiers":[
        {
            "category":"Wholesale",
            "subcategory":"Machinery & Supplies",
            "type":"Manufacturing & Wholesale Goods"
        }
    ],
    "sg:phone":"+1 418 877 0333",
    "sg:postcode":"G2E 5E2",
    "sg:province":"QC",
    "sg:tags":[
        "equipment",
        "industrial"
    ],
    "wof:name":"Industrie Ld Inc",
    "wof:placetype":"venue"
},
  "geometry": {"coordinates":[-71.329521,46.801933],"type":"Point"}
}