{
  "type": "Feature",
  "properties": {
    "iso:country":"CA",
    "sg:address":"2000 Airport Rd NE",
    "sg:city":"Calgary",
    "sg:classifiers":[
        {
            "category":"Restaurant",
            "type":"Food & Drink"
        }
    ],
    "sg:phone":"+1 403 291 0069",
    "sg:postcode":"T2E 6W5",
    "sg:province":"AB",
    "wof:name":"Manchu Wok",
    "wof:placetype":"venue"
},
  "geometry": {"coordinates":[-114.010803223,51.1343574524],"type":"Point"}
}