{
  "type": "Feature",
  "properties": {
    "addr:full":"1790 Rue Pilon Saint-Andre-D'Argenteuil QC J0V 1X0",
    "addr:housenumber":"1790",
    "addr:postcode":"j0v 1x0",
    "addr:street":"Rue Pilon",
    "iso:country":"CA",
    "sg:address":"1790 Rue Pilon",
    "sg:city":"Saint-Andre-D'Argenteuil",
    "sg:classifiers":[
        {
            "category":"Wholesale",
            "subcategory":"Toys & Hobbies",
            "type":"Manufacturing & Wholesale Goods"
        }
    ],
    "sg:phone":"+1 450 537 8267",
    "sg:postcode":"J0V 1X0",
    "sg:province":"QC",
    "sg:tags":[
        "firework"
    ],
    "wof:name":"Distribution S Lavoie Enr",
    "wof:placetype":"venue"
},
  "geometry": {"coordinates":[-74.294327,45.525341],"type":"Point"}
}