{
  "type": "Feature",
  "properties": {
    "addr:full":"Coquitlam BC V3E 3J7",
    "addr:postcode":"v3e 3j7",
    "iso:country":"CA",
    "sg:city":"Coquitlam",
    "sg:classifiers":[
        {
            "category":"Health Services",
            "subcategory":"Doctor",
            "type":"Services"
        }
    ],
    "sg:phone":"+1 604 927 2525",
    "sg:postcode":"V3E 3J7",
    "sg:province":"BC",
    "sg:tags":[
        "dentist"
    ],
    "wof:name":"Plateau Village Dental Ctr",
    "wof:placetype":"venue"
},
  "geometry": {"coordinates":[-122.80304717999999,49.2968902588],"type":"Point"}
}