{
  "type": "Feature",
  "properties": {
    "iso:country":"CA",
    "sg:city":"Mont-Saint-Hilaire",
    "sg:classifiers":[
        {
            "category":"Travel",
            "subcategory":"Campground",
            "type":"Entertainment"
        }
    ],
    "sg:phone":"+1 450 467 2518",
    "sg:postcode":"J3H 4X8",
    "sg:province":"QC",
    "wof:name":"Camping Laurier",
    "wof:placetype":"venue"
},
  "geometry": {"coordinates":[-73.176437,45.572491],"type":"Point"}
}