{
  "type": "Feature",
  "properties": {
    "iso:country":"CA",
    "sg:city":"Petersburg",
    "sg:classifiers":[
        {
            "category":"Retail",
            "subcategory":"Auto Repair",
            "type":"Services"
        }
    ],
    "sg:phone":"+1 519 634 8243",
    "sg:postcode":"N0B 2H0",
    "sg:province":"ON",
    "sg:tags":[
        "repairing",
        "automobile"
    ],
    "wof:name":"Old Fashioned Svc",
    "wof:placetype":"venue"
},
  "geometry": {"coordinates":[-80.583199,43.417038],"type":"Point"}
}