{
  "type": "Feature",
  "properties": {
    "addr:full":"3000 Falconbridge Hwy Garson ON P3L 1J6",
    "addr:housenumber":"3000",
    "addr:postcode":"p3l 1j6",
    "addr:street":"Falconbridge Hwy",
    "iso:country":"CA",
    "sg:address":"3000 Falconbridge Hwy",
    "sg:city":"Garson",
    "sg:classifiers":[
        {
            "category":"Food & Beverages",
            "subcategory":"Bakery",
            "type":"Retail Goods"
        }
    ],
    "sg:phone":"+1 705 693 7887",
    "sg:postcode":"P3L 1J6",
    "sg:province":"ON",
    "sg:tags":[
        "doughnut"
    ],
    "wof:name":"Tim Hortons",
    "wof:placetype":"venue"
},
  "geometry": {"coordinates":[-80.87706756590001,46.5491714478],"type":"Point"}
}