{
  "type": "Feature",
  "properties": {
    "addr:full":"Chase BC V0E 1M0",
    "addr:postcode":"v0e 1m0",
    "iso:country":"CA",
    "sg:city":"Chase",
    "sg:classifiers":[
        {
            "category":"Wholesale",
            "subcategory":"Construction Materials",
            "type":"Manufacturing & Wholesale Goods"
        }
    ],
    "sg:phone":"+1 250 679 8656",
    "sg:postcode":"V0E 1M0",
    "sg:province":"BC",
    "sg:tags":[
        "timberland",
        "company",
        "timber"
    ],
    "wof:name":"Owl Ridge Timber Framing",
    "wof:placetype":"venue"
},
  "geometry": {"coordinates":[-119.694588,50.811214],"type":"Point"}
}