{
  "type": "Feature",
  "properties": {
    "addr:full":"1076 Mainland St Vancouver BC V6B 2T4",
    "addr:housenumber":"1076",
    "addr:postcode":"bc v6b 2t4",
    "addr:street":"Mainland St",
    "iso:country":"CA",
    "sg:address":"1076 Mainland St",
    "sg:city":"Vancouver",
    "sg:classifiers":[
        {
            "category":"Manufacturing",
            "subcategory":"Food",
            "type":"Manufacturing & Wholesale Goods"
        }
    ],
    "sg:phone":"+1 604 684 2499",
    "sg:postcode":"V6B 2T4",
    "sg:province":"BC",
    "sg:tags":[
        "bakery",
        "prod",
        "cookie"
    ],
    "wof:name":"Boulangerie LA Parisienne Ltd",
    "wof:placetype":"venue"
},
  "geometry": {"coordinates":[-123.119911194,49.2757987976],"type":"Point"}
}