{
  "type": "Feature",
  "properties": {
    "iso:country":"CA",
    "sg:address":"353 Mountain Ave",
    "sg:city":"Winnipeg",
    "sg:classifiers":[
        {
            "category":"Organizations",
            "subcategory":"Religious Organization",
            "type":"Services"
        }
    ],
    "sg:phone":"+1 204 582 2363",
    "sg:postcode":"R2W 1J9",
    "sg:province":"MB",
    "sg:tags":[
        "church"
    ],
    "wof:name":"Ethiopian Orthodox Church",
    "wof:placetype":"venue"
},
  "geometry": {"coordinates":[-97.1327819824,49.9208106995],"type":"Point"}
}