{
  "type": "Feature",
  "properties": {
    "addr:full":"Main St Richmound SK S0N 2E0",
    "addr:postcode":"s0n 2e0",
    "addr:street":"Main St",
    "iso:country":"CA",
    "sg:address":"Main St",
    "sg:city":"Richmound",
    "sg:classifiers":[
        {
            "category":"Travel",
            "subcategory":"Hotels & Motels",
            "type":"Entertainment"
        }
    ],
    "sg:phone":"+1 306 669 2022",
    "sg:postcode":"S0N 2E0",
    "sg:province":"SK",
    "wof:name":"Richmound Hotel",
    "wof:placetype":"venue"
},
  "geometry": {"coordinates":[-109.755126953,50.4553604126],"type":"Point"}
}