{
  "type": "Feature",
  "properties": {
    "addr:full":"8471 Rue Saint-Denis Montreal QC H2P 2G9",
    "addr:housenumber":"8471",
    "addr:postcode":"h2p 2g9",
    "addr:street":"Rue Saint-Denis",
    "iso:country":"CA",
    "sg:address":"8471 Rue Saint-Denis",
    "sg:city":"Montreal",
    "sg:classifiers":[
        {
            "category":"Cinema",
            "subcategory":"Movie Theater",
            "type":"Entertainment"
        }
    ],
    "sg:phone":"+1 514 383 3972",
    "sg:postcode":"H2P 2G9",
    "sg:province":"QC",
    "wof:name":"20 Jours Du Theatre A Risque",
    "wof:placetype":"venue"
},
  "geometry": {"coordinates":[-73.634621,45.544323],"type":"Point"}
}