{
  "type": "Feature",
  "properties": {
    "addr:full":"615 Gauvin Rd Dieppe NB E1A 1M7",
    "addr:housenumber":"615",
    "addr:postcode":"e1a 1m7",
    "addr:street":"Gauvin Rd",
    "iso:country":"CA",
    "sg:address":"615 Gauvin Rd",
    "sg:city":"Dieppe",
    "sg:classifiers":[
        {
            "category":"Personal",
            "subcategory":"Beauty Salon",
            "type":"Services"
        }
    ],
    "sg:phone":"+1 506 855 2233",
    "sg:postcode":"E1A 1M7",
    "sg:province":"NB",
    "wof:name":"Beau Look",
    "wof:placetype":"venue"
},
  "geometry": {"coordinates":[-64.72912599999999,46.09816],"type":"Point"}
}