{
  "type": "Feature",
  "properties": {
    "addr:full":"602 Pittsburg Ave Selkirk MB R1A 0W9",
    "addr:housenumber":"602",
    "addr:postcode":"r1a 0w9",
    "addr:street":"Pittsburg Ave",
    "iso:country":"CA",
    "sg:address":"602 Pittsburg Ave",
    "sg:city":"Selkirk",
    "sg:classifiers":[
        {
            "category":"Retail",
            "subcategory":"Auto Repair",
            "type":"Services"
        }
    ],
    "sg:phone":"+1 204 482 6128",
    "sg:postcode":"R1A 0W9",
    "sg:province":"MB",
    "sg:tags":[
        "repairing",
        "automobile",
        "wrecker"
    ],
    "wof:name":"Supreme Auto",
    "wof:placetype":"venue"
},
  "geometry": {"coordinates":[-96.8974533081,50.1326828003],"type":"Point"}
}