{
  "type": "Feature",
  "properties": {
    "addr:full":"219 Rue Commerciale Cabano QC G0L 1E0",
    "addr:housenumber":"219",
    "addr:postcode":"g0l 1e0",
    "addr:street":"Rue Commerciale",
    "iso:country":"CA",
    "sg:address":"219 Rue Commerciale",
    "sg:city":"Cabano",
    "sg:classifiers":[
        {
            "category":"Shopping",
            "subcategory":"Florist",
            "type":"Retail Goods"
        }
    ],
    "sg:phone":"+1 418 854 2647",
    "sg:postcode":"G0L 1E0",
    "sg:province":"QC",
    "wof:name":"Cabano Fleuriste Inc",
    "wof:placetype":"venue"
},
  "geometry": {"coordinates":[-68.873336792,47.6757354736],"type":"Point"}
}