{
  "type": "Feature",
  "properties": {
    "addr:full":"Saskatoon SK S7K 5M5",
    "addr:postcode":"s7k 5m5",
    "iso:country":"CA",
    "sg:city":"Saskatoon",
    "sg:classifiers":[
        {
            "category":"Government",
            "subcategory":"Office",
            "type":"Public Place"
        }
    ],
    "sg:phone":"+1 306 933 5930",
    "sg:postcode":"S7K 5M5",
    "sg:province":"SK",
    "wof:name":"Saskatchewan Family Justice",
    "wof:placetype":"venue"
},
  "geometry": {"coordinates":[-106.661171,52.12606],"type":"Point"}
}