{
  "type": "Feature",
  "properties": {
    "addr:full":"Brampton ON L6T 4Y8",
    "addr:postcode":"l6t 4y8",
    "iso:country":"CA",
    "sg:city":"Brampton",
    "sg:classifiers":[
        {
            "category":"Building & Trades",
            "subcategory":"Electrical",
            "type":"Services"
        }
    ],
    "sg:phone":"+1 905 455 8121",
    "sg:postcode":"L6T 4Y8",
    "sg:province":"ON",
    "sg:tags":[
        "electric",
        "contractor"
    ],
    "wof:name":"Ntt Electric",
    "wof:placetype":"venue"
},
  "geometry": {"coordinates":[-79.727188,43.704842],"type":"Point"}
}