{
  "type": "Feature",
  "properties": {
    "addr:full":"1200 United Blvd Coquitlam BC V3K 6T4",
    "addr:housenumber":"1200",
    "addr:postcode":"v3k 6t4",
    "addr:street":"United Blvd",
    "iso:country":"CA",
    "sg:address":"1200 United Blvd",
    "sg:city":"Coquitlam",
    "sg:classifiers":[
        {
            "category":"Wholesale",
            "subcategory":"Scrap",
            "type":"Manufacturing & Wholesale Goods"
        }
    ],
    "sg:phone":"+1 604 521 1715",
    "sg:postcode":"V3K 6T4",
    "sg:province":"BC",
    "sg:tags":[
        "waste"
    ],
    "wof:name":"Wastech Services Ltd",
    "wof:placetype":"venue"
},
  "geometry": {"coordinates":[-122.85861969,49.2303009033],"type":"Point"}
}