{
  "type": "Feature",
  "properties": {
    "addr:full":"4118 Johnston Rd Invermere BC V0A 1K4",
    "addr:housenumber":"4118",
    "addr:postcode":"v0a 1k4",
    "addr:street":"Johnston Rd",
    "iso:country":"CA",
    "sg:address":"4118 Johnston Rd",
    "sg:city":"Invermere",
    "sg:classifiers":[
        {
            "category":"Building & Trades",
            "subcategory":"Construction",
            "type":"Services"
        }
    ],
    "sg:phone":"+1 250 342 6695",
    "sg:postcode":"V0A 1K4",
    "sg:province":"BC",
    "sg:tags":[
        "road",
        "contractor"
    ],
    "wof:name":"William P Mc Intosh Logging",
    "wof:placetype":"venue"
},
  "geometry": {"coordinates":[-116.030373,50.509171],"type":"Point"}
}