{
  "type": "Feature",
  "properties": {
    "iso:country":"CA",
    "sg:address":"132 Cumberland St",
    "sg:city":"Toronto",
    "sg:classifiers":[
        {
            "category":"Shopping",
            "subcategory":"Used Merchandise",
            "type":"Retail Goods"
        }
    ],
    "sg:phone":"+1 416 964 1362",
    "sg:postcode":"M5R 1A6",
    "sg:province":"ON",
    "sg:tags":[
        "antique"
    ],
    "wof:name":"Berson Gifts & Antiques",
    "wof:placetype":"venue"
},
  "geometry": {"coordinates":[-79.39231872560001,43.6701812744],"type":"Point"}
}