{
  "type": "Feature",
  "properties": {
    "addr:full":"801 Central Ave Greenwood NS B0P 1N0",
    "addr:housenumber":"801",
    "addr:postcode":"b0p 1n0",
    "addr:street":"Central Ave",
    "iso:country":"CA",
    "sg:address":"801 Central Ave",
    "sg:city":"Greenwood",
    "sg:classifiers":[
        {
            "category":"Restaurant",
            "type":"Food & Drink"
        }
    ],
    "sg:phone":"+1 902 765 4477",
    "sg:postcode":"B0P 1N0",
    "sg:province":"NS",
    "sg:tags":[
        "pizza"
    ],
    "wof:name":"Pizza Delight",
    "wof:placetype":"venue"
},
  "geometry": {"coordinates":[-64.93441799999999,44.971844],"type":"Point"}
}