{
  "type": "Feature",
  "properties": {
    "addr:full":"721 Government St # 102 Victoria BC V8W 1W5",
    "addr:housenumber":"721",
    "addr:postcode":"v8w 1w5",
    "addr:street":"Government St # 102",
    "iso:country":"CA",
    "sg:address":"721 Government St # 102",
    "sg:city":"Victoria",
    "sg:classifiers":[
        {
            "category":"Shopping",
            "subcategory":"Luggage & Leather Goods",
            "type":"Retail Goods"
        }
    ],
    "sg:phone":"+1 250 382 3166",
    "sg:postcode":"V8W 1W5",
    "sg:province":"BC",
    "sg:tags":[
        "apparel"
    ],
    "wof:name":"Collections By 5th Ave",
    "wof:placetype":"venue"
},
  "geometry": {"coordinates":[-123.368515015,48.4211158752],"type":"Point"}
}