{
  "type": "Feature",
  "properties": {
    "addr:full":"7213 Rue Cordner Lasalle QC H8N 2J7",
    "addr:housenumber":"7213",
    "addr:postcode":"h8n 2j7",
    "addr:street":"Rue Cordner",
    "iso:country":"CA",
    "sg:address":"7213 Rue Cordner",
    "sg:city":"Lasalle",
    "sg:classifiers":[
        {
            "category":"Manufacturing",
            "subcategory":"Paper Products",
            "type":"Manufacturing & Wholesale Goods"
        }
    ],
    "sg:phone":"+1 514 595 0555",
    "sg:postcode":"H8N 2J7",
    "sg:province":"QC",
    "sg:tags":[
        "envelope"
    ],
    "wof:name":"Supremex Inc",
    "wof:placetype":"venue"
},
  "geometry": {"coordinates":[-73.62381000000001,45.445797],"type":"Point"}
}