{
  "type": "Feature",
  "properties": {
    "addr:full":"275 Boul Des Laurentides Saint-Jerome QC J7Z 7K8",
    "addr:housenumber":"275",
    "addr:postcode":"j7z 7k8",
    "addr:street":"Boul Des Laurentides",
    "iso:country":"CA",
    "sg:address":"275 Boul Des Laurentides",
    "sg:city":"Saint-Jerome",
    "sg:classifiers":[
        {
            "category":"Real Estate",
            "subcategory":"Real Estate Agent",
            "type":"Services"
        }
    ],
    "sg:phone":"+1 450 565 3355",
    "sg:postcode":"J7Z 7K8",
    "sg:province":"QC",
    "wof:name":"Capitale St-Jerome Inc",
    "wof:placetype":"venue"
},
  "geometry": {"coordinates":[-73.996574,45.765293],"type":"Point"}
}