{
  "type": "Feature",
  "properties": {
    "addr:full":"4030 50 St Red Deer AB T4N 1W4",
    "addr:housenumber":"4030",
    "addr:postcode":"t4n 1w4",
    "addr:street":"50 St",
    "iso:country":"CA",
    "sg:address":"4030 50 St",
    "sg:city":"Red Deer",
    "sg:classifiers":[
        {
            "category":"Restaurant",
            "type":"Food & Drink"
        }
    ],
    "sg:phone":"+1 403 347 8901",
    "sg:postcode":"T4N 1W4",
    "sg:province":"AB",
    "sg:tags":[
        "parlor",
        "ice",
        "cream"
    ],
    "wof:name":"Little Ice Cream & Soda Shoppe",
    "wof:placetype":"venue"
},
  "geometry": {"coordinates":[-113.790992737,52.2669067383],"type":"Point"}
}