{
  "type": "Feature",
  "properties": {
    "addr:full":"5350 Brendan Lane Oldcastle ON N0R 1L0",
    "addr:housenumber":"5350",
    "addr:postcode":"n0r 1l0",
    "addr:street":"Brendan Lane",
    "iso:country":"CA",
    "sg:address":"5350 Brendan Lane",
    "sg:city":"Oldcastle",
    "sg:classifiers":[
        {
            "category":"Wholesale",
            "subcategory":"Machinery & Supplies",
            "type":"Manufacturing & Wholesale Goods"
        }
    ],
    "sg:phone":"+1 519 737 1281",
    "sg:postcode":"N0R 1L0",
    "sg:province":"ON",
    "sg:tags":[
        "equipment",
        "material",
        "handling"
    ],
    "wof:name":"Liftow Limited",
    "wof:placetype":"venue"
},
  "geometry": {"coordinates":[-82.960838,42.235069],"type":"Point"}
}