{
  "type": "Feature",
  "properties": {
    "addr:full":"Saint-Leonard QC H1R 1B3",
    "addr:postcode":"h1r 1b3",
    "iso:country":"CA",
    "sg:city":"Saint-Leonard",
    "sg:classifiers":[
        {
            "category":"Wholesale",
            "subcategory":"Machinery & Supplies",
            "type":"Manufacturing & Wholesale Goods"
        }
    ],
    "sg:phone":"+1 514 326 5940",
    "sg:postcode":"H1R 1B3",
    "sg:province":"QC",
    "sg:tags":[
        "barrels",
        "drum",
        "pail"
    ],
    "wof:name":"Joseph Lebel Inc",
    "wof:placetype":"venue"
},
  "geometry": {"coordinates":[-73.6131820679,45.5975532532],"type":"Point"}
}