{
  "type": "Feature",
  "properties": {
    "addr:full":"Burnaby BC V5C 2K4",
    "addr:postcode":"v5c 2k4",
    "iso:country":"CA",
    "sg:city":"Burnaby",
    "sg:classifiers":[
        {
            "category":"Education",
            "subcategory":"Special Training",
            "type":"Public Place"
        }
    ],
    "sg:phone":"+1 604 299 3830",
    "sg:postcode":"V5C 2K4",
    "sg:province":"BC",
    "sg:tags":[
        "instruction",
        "driving"
    ],
    "wof:name":"Young Drivers of Canada",
    "wof:placetype":"venue"
},
  "geometry": {"coordinates":[-123.002059937,49.2808685303],"type":"Point"}
}