{
  "type": "Feature",
  "properties": {
    "addr:full":"2225 Erin Mills Pky # 154A Mississauga ON L5K 1T9",
    "addr:housenumber":"2225",
    "addr:postcode":"l5k 1t9",
    "addr:street":"Erin Mills Pky # 154A",
    "iso:country":"CA",
    "sg:address":"2225 Erin Mills Pky # 154A",
    "sg:city":"Mississauga",
    "sg:classifiers":[
        {
            "category":"Education",
            "subcategory":"Special Training",
            "type":"Public Place"
        }
    ],
    "sg:phone":"+1 905 823 6284",
    "sg:postcode":"L5K 1T9",
    "sg:province":"ON",
    "sg:tags":[
        "tutoring"
    ],
    "wof:name":"Academy For Mathematics",
    "wof:placetype":"venue"
},
  "geometry": {"coordinates":[-79.6544418335,43.5290374756],"type":"Point"}
}