{
  "type": "Feature",
  "properties": {
    "addr:full":"1532 Chemong Rd Peterborough ON K9J 6X2",
    "addr:housenumber":"1532",
    "addr:postcode":"k9j 6x2",
    "addr:street":"Chemong Rd",
    "iso:country":"CA",
    "sg:address":"1532 Chemong Rd",
    "sg:city":"Peterborough",
    "sg:classifiers":[
        {
            "category":"Building & Trades",
            "subcategory":"Plumbing",
            "type":"Services"
        }
    ],
    "sg:phone":"+1 705 742 9259",
    "sg:postcode":"K9J 6X2",
    "sg:province":"ON",
    "sg:tags":[
        "contractor"
    ],
    "wof:name":"Peter Cooks Maintenance",
    "wof:placetype":"venue"
},
  "geometry": {"coordinates":[-78.3468170166,44.3345718384],"type":"Point"}
}