{
  "type": "Feature",
  "properties": {
    "iso:country":"CA",
    "sg:address":"21 Fir St",
    "sg:city":"Waterloo",
    "sg:classifiers":[
        {
            "category":"Building & Trades",
            "subcategory":"Cleaning & Sanitation",
            "type":"Services"
        }
    ],
    "sg:phone":"+1 519 880 9118",
    "sg:postcode":"N2L 3H4",
    "sg:province":"ON",
    "sg:tags":[
        "janitor"
    ],
    "wof:name":"Machan's Office Maintenance",
    "wof:placetype":"venue"
},
  "geometry": {"coordinates":[-80.5269241333,43.4770622253],"type":"Point"}
}