{
  "type": "Feature",
  "properties": {
    "iso:country":"CA",
    "sg:address":"Cp 142 Succ Roxboro",
    "sg:city":"Roxboro",
    "sg:classifiers":[
        {
            "category":"Manufacturing",
            "subcategory":"Printing",
            "type":"Manufacturing & Wholesale Goods"
        }
    ],
    "sg:phone":"+1 514 421 6440",
    "sg:postcode":"H8Y 3E8",
    "sg:province":"QC",
    "sg:tags":[
        "printer"
    ],
    "wof:name":"Imprimerie Perfection",
    "wof:placetype":"venue"
},
  "geometry": {"coordinates":[-73.80658,45.509548],"type":"Point"}
}