{
  "type": "Feature",
  "properties": {
    "addr:full":"439 8E Rang N Saint-Ephrem-DE-Beauce QC G0M 1R0",
    "addr:housenumber":"439",
    "addr:postcode":"g0m 1r0",
    "addr:street":"8E Rang N",
    "iso:country":"CA",
    "sg:address":"439 8E Rang N",
    "sg:city":"Saint-Ephrem-DE-Beauce",
    "sg:classifiers":[
        {
            "category":"Farming",
            "subcategory":"Farm",
            "type":"Manufacturing & Wholesale Goods"
        }
    ],
    "sg:phone":"+1 418 484 3609",
    "sg:postcode":"G0M 1R0",
    "sg:province":"QC",
    "wof:name":"Ferme Ran-Porc",
    "wof:placetype":"venue"
},
  "geometry": {"coordinates":[-70.97410600000001,46.097862],"type":"Point"}
}