{
  "type": "Feature",
  "properties": {
    "iso:country":"CA",
    "sg:city":"Nepean",
    "sg:classifiers":[
        {
            "category":"Health Services",
            "subcategory":"Doctor",
            "type":"Services"
        }
    ],
    "sg:phone":"+1 613 825 8397",
    "sg:postcode":"K2J 3R2",
    "sg:province":"ON",
    "sg:tags":[
        "physician",
        "surgeon"
    ],
    "wof:name":"Spencer, Nigel MD",
    "wof:placetype":"venue"
},
  "geometry": {"coordinates":[-75.7571563721,45.286026001],"type":"Point"}
}