{
  "type": "Feature",
  "properties": {
    "addr:full":"119 Smoothstone Cres Saskatoon SK S7J 4T1",
    "addr:housenumber":"119",
    "addr:postcode":"s7j 4t1",
    "addr:street":"Smoothstone Cres",
    "iso:country":"CA",
    "sg:address":"119 Smoothstone Cres",
    "sg:city":"Saskatoon",
    "sg:classifiers":[
        {
            "category":"Autos & Motor Vehicles",
            "subcategory":"Automobile Sales",
            "type":"Retail Goods"
        }
    ],
    "sg:phone":"+1 306 374 4722",
    "sg:postcode":"S7J 4T1",
    "sg:province":"SK",
    "sg:tags":[
        "parts",
        "snowmobile",
        "accessory"
    ],
    "wof:name":"Stony Rapids Snowmobile Ctr",
    "wof:placetype":"venue"
},
  "geometry": {"coordinates":[-106.581779,52.098812],"type":"Point"}
}