{
  "type": "Feature",
  "properties": {
    "addr:full":"Berthierville QC J0K 1A0",
    "addr:postcode":"j0k 1a0",
    "iso:country":"CA",
    "sg:city":"Berthierville",
    "sg:classifiers":[
        {
            "category":"Autos & Motor Vehicles",
            "subcategory":"Auto Supplies",
            "type":"Retail Goods"
        }
    ],
    "sg:phone":"+1 450 836 6063",
    "sg:postcode":"J0K 1A0",
    "sg:province":"QC",
    "sg:tags":[
        "automobile",
        "parts"
    ],
    "wof:name":"S B Performance",
    "wof:placetype":"venue"
},
  "geometry": {"coordinates":[-73.186081,46.081772],"type":"Point"}
}