{
  "type": "Feature",
  "properties": {
    "addr:full":"6323 Main St Stouffville ON L4A 1G5",
    "addr:housenumber":"6323",
    "addr:postcode":"l4a 1g5",
    "addr:street":"Main St",
    "iso:country":"CA",
    "sg:address":"6323 Main St",
    "sg:city":"Stouffville",
    "sg:classifiers":[
        {
            "category":"Banks & Credit Unions",
            "subcategory":"Bank",
            "type":"Services"
        }
    ],
    "sg:phone":"+1 905 640 3631",
    "sg:postcode":"L4A 1G5",
    "sg:province":"ON",
    "wof:name":"Scotiabank",
    "wof:placetype":"venue"
},
  "geometry": {"coordinates":[-79.2462921143,43.9713287354],"type":"Point"}
}