{
  "type": "Feature",
  "properties": {
    "addr:full":"51 Village Centre Pl Mississauga ON L4Z 1V9",
    "addr:housenumber":"51",
    "addr:postcode":"l4z 1v9",
    "addr:street":"Village Centre Pl",
    "iso:country":"CA",
    "sg:address":"51 Village Centre Pl",
    "sg:city":"Mississauga",
    "sg:classifiers":[
        {
            "category":"Restaurant",
            "type":"Food & Drink"
        }
    ],
    "sg:phone":"+1 905 272 4342",
    "sg:postcode":"L4Z 1V9",
    "sg:province":"ON",
    "wof:name":"Saffron Cafe",
    "wof:placetype":"venue"
},
  "geometry": {"coordinates":[-79.6410446167,43.6008071899],"type":"Point"}
}