{
  "type": "Feature",
  "properties": {
    "iso:country":"CA",
    "sg:address":"637 Av Meloche",
    "sg:city":"Dorval",
    "sg:classifiers":[
        {
            "category":"Wholesale",
            "subcategory":"Machinery & Supplies",
            "type":"Manufacturing & Wholesale Goods"
        }
    ],
    "sg:phone":"+1 514 631 3506",
    "sg:postcode":"H9P 2T1",
    "sg:province":"QC",
    "sg:tags":[
        "director",
        "funeral"
    ],
    "wof:name":"Batesville Canada",
    "wof:placetype":"venue"
},
  "geometry": {"coordinates":[-73.726997,45.454082],"type":"Point"}
}