{
  "type": "Feature",
  "properties": {
    "iso:country":"CA",
    "sg:address":"354 Boul Des Prairies",
    "sg:city":"Laval",
    "sg:classifiers":[
        {
            "category":"Wholesale",
            "subcategory":"Machinery & Supplies",
            "type":"Manufacturing & Wholesale Goods"
        }
    ],
    "sg:phone":"+1 450 667 0733",
    "sg:postcode":"H7N 2V7",
    "sg:province":"QC",
    "sg:tags":[
        "fuel",
        "equipment",
        "injection"
    ],
    "wof:name":"Les Pompes Diesel Laval Inc",
    "wof:placetype":"venue"
},
  "geometry": {"coordinates":[-73.705452,45.547642],"type":"Point"}
}