{
  "type": "Feature",
  "properties": {
    "addr:full":"524 Rue Galt O Sherbrooke QC J1H 1Y9",
    "addr:housenumber":"524",
    "addr:postcode":"j1h 1y9",
    "addr:street":"Rue Galt O",
    "iso:country":"CA",
    "sg:address":"524 Rue Galt O",
    "sg:city":"Sherbrooke",
    "sg:classifiers":[
        {
            "category":"Wholesale",
            "subcategory":"Auto Parts",
            "type":"Manufacturing & Wholesale Goods"
        }
    ],
    "sg:phone":"+1 819 566 2226",
    "sg:postcode":"J1H 1Y9",
    "sg:province":"QC",
    "sg:tags":[
        "automobile",
        "rebuilt",
        "supply"
    ],
    "wof:name":"Pieces D'Autos Usagees Inc",
    "wof:placetype":"venue"
},
  "geometry": {"coordinates":[-71.893585,45.394382],"type":"Point"}
}