{
  "type": "Feature",
  "properties": {
    "addr:full":"4572 Route 134 Allardville NB E8L 1E4",
    "addr:housenumber":"4572",
    "addr:postcode":"e8l 1e4",
    "addr:street":"Route 134",
    "iso:country":"CA",
    "sg:address":"4572 Route 134",
    "sg:city":"Allardville",
    "sg:classifiers":[
        {
            "category":"Education",
            "subcategory":"School",
            "type":"Public Place"
        }
    ],
    "sg:phone":"+1 506 725 2407",
    "sg:postcode":"E8L 1E4",
    "sg:province":"NB",
    "wof:name":"Ecole Francois-Xavier-Daigle",
    "wof:placetype":"venue"
},
  "geometry": {"coordinates":[-65.4931716919,47.4757843018],"type":"Point"}
}