{
  "type": "Feature",
  "properties": {
    "addr:full":"960 Boul Du Royaume O Chicoutimi QC G7H 5B1",
    "addr:housenumber":"960",
    "addr:postcode":"g7h 5b1",
    "addr:street":"Boul Du Royaume O",
    "iso:country":"CA",
    "sg:address":"960 Boul Du Royaume O",
    "sg:city":"Chicoutimi",
    "sg:classifiers":[
        {
            "category":"Wholesale",
            "subcategory":"Auto Parts",
            "type":"Manufacturing & Wholesale Goods"
        }
    ],
    "sg:phone":"+1 418 696 4045",
    "sg:postcode":"G7H 5B1",
    "sg:province":"QC",
    "sg:tags":[
        "equipment",
        "towing",
        "truck"
    ],
    "wof:name":"Plamondon Camquip Ltee",
    "wof:placetype":"venue"
},
  "geometry": {"coordinates":[-71.103706,48.384411],"type":"Point"}
}