{
  "type": "Feature",
  "properties": {
    "addr:full":"491 Davenport Rd Toronto ON M4V 1B7",
    "addr:housenumber":"491",
    "addr:postcode":"m4v 1b7",
    "addr:street":"Davenport Rd",
    "iso:country":"CA",
    "sg:address":"491 Davenport Rd",
    "sg:city":"Toronto",
    "sg:classifiers":[
        {
            "category":"Real Estate",
            "subcategory":"Architect",
            "type":"Services"
        }
    ],
    "sg:phone":"+1 416 968 9120",
    "sg:postcode":"M4V 1B7",
    "sg:province":"ON",
    "wof:name":"John C Houghton & Assoc",
    "wof:placetype":"venue"
},
  "geometry": {"coordinates":[-79.406494,43.677704],"type":"Point"}
}