{
  "type": "Feature",
  "properties": {
    "addr:full":"Calgary AB T2S 2T8",
    "addr:postcode":"t2s 2t8",
    "iso:country":"CA",
    "sg:city":"Calgary",
    "sg:classifiers":[
        {
            "category":"Professional",
            "subcategory":"Engineering",
            "type":"Services"
        }
    ],
    "sg:phone":"+1 403 292 0834",
    "sg:postcode":"T2S 2T8",
    "sg:province":"AB",
    "sg:tags":[
        "engineer"
    ],
    "wof:name":"Willumsen Ventures Inc",
    "wof:placetype":"venue"
},
  "geometry": {"coordinates":[-114.06735229500001,51.0376815796],"type":"Point"}
}