{
  "type": "Feature",
  "properties": {
    "addr:full":"1261 Rue Volta Boucherville QC J4B 7M7",
    "addr:housenumber":"1261",
    "addr:postcode":"j4b 7m7",
    "addr:street":"Rue Volta",
    "iso:country":"CA",
    "sg:address":"1261 Rue Volta",
    "sg:city":"Boucherville",
    "sg:classifiers":[
        {
            "category":"Wholesale",
            "subcategory":"Machinery & Supplies",
            "type":"Manufacturing & Wholesale Goods"
        }
    ],
    "sg:phone":"+1 450 449 4358",
    "sg:postcode":"J4B 7M7",
    "sg:province":"QC",
    "sg:tags":[
        "equipment",
        "conveyor",
        "conveying"
    ],
    "wof:name":"Abf System Inc",
    "wof:placetype":"venue"
},
  "geometry": {"coordinates":[-73.443489,45.565258],"type":"Point"}
}