{
  "type": "Feature",
  "properties": {
    "addr:full":"332 Bay St Sault Ste Marie ON P6A 1X1",
    "addr:housenumber":"332",
    "addr:postcode":"p6a 1x1",
    "addr:street":"Bay St",
    "iso:country":"CA",
    "sg:address":"332 Bay St",
    "sg:city":"Sault Ste Marie",
    "sg:classifiers":[
        {
            "category":"Travel",
            "subcategory":"Hotels & Motels",
            "type":"Entertainment"
        }
    ],
    "sg:phone":"+1 705 759 1400",
    "sg:postcode":"P6A 1X1",
    "sg:province":"ON",
    "wof:name":"Travelodge",
    "wof:placetype":"venue"
},
  "geometry": {"coordinates":[-84.33647918699999,46.5125045776],"type":"Point"}
}