{
  "type": "Feature",
  "properties": {
    "iso:country":"CA",
    "sg:address":"6670 Dellpark Dr",
    "sg:city":"Niagara Falls",
    "sg:classifiers":[
        {
            "category":"Professional",
            "subcategory":"Accounting & Tax Preparation",
            "type":"Services"
        }
    ],
    "sg:phone":"+1 905 356 0220",
    "sg:postcode":"L2J 2B8",
    "sg:province":"ON",
    "sg:tags":[
        "accountant"
    ],
    "wof:name":"Friesen, Rudolf CA",
    "wof:placetype":"venue"
},
  "geometry": {"coordinates":[-79.1089706421,43.1348228455],"type":"Point"}
}