{
  "type": "Feature",
  "properties": {
    "iso:country":"CA",
    "sg:address":"329 Stewart Blvd",
    "sg:city":"Brockville",
    "sg:classifiers":[
        {
            "category":"Food & Beverages",
            "subcategory":"Groceries & Convenience Stores",
            "type":"Retail Goods"
        }
    ],
    "sg:phone":"+1 613 342 8830",
    "sg:postcode":"K6V 4W8",
    "sg:province":"ON",
    "wof:name":"Mac's Convenience Stores Ltd",
    "wof:placetype":"venue"
},
  "geometry": {"coordinates":[-75.7041854858,44.6005935669],"type":"Point"}
}