{
  "type": "Feature",
  "properties": {
    "addr:full":"102 River Ave Cochrane AB T4C 2C3",
    "addr:housenumber":"102",
    "addr:postcode":"t4c 2c3",
    "addr:street":"River Ave",
    "iso:country":"CA",
    "sg:address":"102 River Ave",
    "sg:city":"Cochrane",
    "sg:classifiers":[
        {
            "category":"Retail",
            "subcategory":"Car Wash",
            "type":"Services"
        }
    ],
    "sg:phone":"+1 403 932 5751",
    "sg:postcode":"T4C 2C3",
    "sg:province":"AB",
    "sg:tags":[
        "polishing",
        "washing"
    ],
    "wof:name":"Car Wash Corral",
    "wof:placetype":"venue"
},
  "geometry": {"coordinates":[-114.463959,51.186646],"type":"Point"}
}