{
  "type": "Feature",
  "properties": {
    "addr:full":"66 Henderson Ave Thornhill ON L3T 2K7",
    "addr:housenumber":"66",
    "addr:postcode":"l3t 2k7",
    "addr:street":"Henderson Ave",
    "iso:country":"CA",
    "sg:address":"66 Henderson Ave",
    "sg:city":"Thornhill",
    "sg:classifiers":[
        {
            "category":"Education",
            "subcategory":"School",
            "type":"Public Place"
        }
    ],
    "sg:phone":"+1 905 889 3132",
    "sg:postcode":"L3T 2K7",
    "sg:province":"ON",
    "wof:name":"Henderson Avenue Public School",
    "wof:placetype":"venue"
},
  "geometry": {"coordinates":[-79.408493042,43.8050270081],"type":"Point"}
}