{
  "type": "Feature",
  "properties": {
    "addr:full":"Mississauga ON L5T 1X4",
    "addr:postcode":"l5t 1x4",
    "iso:country":"CA",
    "sg:city":"Mississauga",
    "sg:classifiers":[
        {
            "category":"Restaurant",
            "type":"Food & Drink"
        }
    ],
    "sg:phone":"+1 905 795 2990",
    "sg:postcode":"L5T 1X4",
    "sg:province":"ON",
    "sg:tags":[
        "caterer"
    ],
    "wof:name":"Scarlett House Catering",
    "wof:placetype":"venue"
},
  "geometry": {"coordinates":[-79.660027,43.664917],"type":"Point"}
}