{
  "type": "Feature",
  "properties": {
    "addr:full":"5638 Power Rd Gloucester ON K1G 3N4",
    "addr:housenumber":"5638",
    "addr:postcode":"k1g 3n4",
    "addr:street":"Power Rd",
    "iso:country":"CA",
    "sg:address":"5638 Power Rd",
    "sg:city":"Gloucester",
    "sg:classifiers":[
        {
            "category":"Manufacturing",
            "subcategory":"Glass & Minerals",
            "type":"Manufacturing & Wholesale Goods"
        }
    ],
    "sg:phone":"+1 613 822 1300",
    "sg:postcode":"K1G 3N4",
    "sg:province":"ON",
    "sg:tags":[
        "product",
        "marble"
    ],
    "wof:name":"Arban Terrazzo Marble & Tile",
    "wof:placetype":"venue"
},
  "geometry": {"coordinates":[-75.560776,45.300823],"type":"Point"}
}