{
  "type": "Feature",
  "properties": {
    "addr:full":"334 Ch Boucher Aylmer QC J9H 5C9",
    "addr:housenumber":"334",
    "addr:postcode":"j9h 5c9",
    "addr:street":"Ch Boucher",
    "iso:country":"CA",
    "sg:address":"334 Ch Boucher",
    "sg:city":"Aylmer",
    "sg:classifiers":[
        {
            "category":"Building & Trades",
            "subcategory":"Electrical",
            "type":"Services"
        }
    ],
    "sg:phone":"+1 819 685 0864",
    "sg:postcode":"J9H 5C9",
    "sg:province":"QC",
    "sg:tags":[
        "electric",
        "contractor"
    ],
    "wof:name":"Charlebois Electriques",
    "wof:placetype":"venue"
},
  "geometry": {"coordinates":[-75.869339,45.423389],"type":"Point"}
}