{
  "type": "Feature",
  "properties": {
    "addr:full":"46 Hayden St Toronto ON M4Y 1V8",
    "addr:housenumber":"46",
    "addr:postcode":"m4y 1v8",
    "addr:street":"Hayden St",
    "iso:country":"CA",
    "sg:address":"46 Hayden St",
    "sg:city":"Toronto",
    "sg:classifiers":[
        {
            "category":"Education",
            "subcategory":"Special Training",
            "type":"Public Place"
        }
    ],
    "sg:phone":"+1 416 925 4652",
    "sg:postcode":"M4Y 1V8",
    "sg:province":"ON",
    "sg:tags":[
        "school",
        "language"
    ],
    "wof:name":"Spanish Centre For Language",
    "wof:placetype":"venue"
},
  "geometry": {"coordinates":[-79.38442999999999,43.669941],"type":"Point"}
}