{
  "type": "Feature",
  "properties": {
    "addr:full":"Westbank BC V4T 1Y2",
    "addr:postcode":"v4t 1y2",
    "iso:country":"CA",
    "sg:city":"Westbank",
    "sg:classifiers":[
        {
            "category":"Shopping",
            "type":"Retail Goods"
        }
    ],
    "sg:phone":"+1 250 768 9440",
    "sg:postcode":"V4T 1Y2",
    "sg:province":"BC",
    "sg:tags":[
        "feed",
        "pet",
        "supply"
    ],
    "wof:name":"Hickok's Country Supply",
    "wof:placetype":"venue"
},
  "geometry": {"coordinates":[-119.618622,49.835766],"type":"Point"}
}