{
  "type": "Feature",
  "properties": {
    "addr:full":"Toronto ON M6S 4W4",
    "addr:postcode":"m6s 4w4",
    "iso:country":"CA",
    "sg:city":"Toronto",
    "sg:classifiers":[
        {
            "category":"Health Services",
            "subcategory":"Doctor",
            "type":"Services"
        }
    ],
    "sg:phone":"+1 416 766 2901",
    "sg:postcode":"M6S 4W4",
    "sg:province":"ON",
    "sg:tags":[
        "physician",
        "surgeon"
    ],
    "wof:name":"Wait, J H MD",
    "wof:placetype":"venue"
},
  "geometry": {"coordinates":[-79.48365800000001,43.649368],"type":"Point"}
}