{
  "type": "Feature",
  "properties": {
    "addr:full":"180 Mary St # 10 Port Perry ON L9L 1C4",
    "addr:housenumber":"180",
    "addr:postcode":"l9l 1c4",
    "addr:street":"Mary St # 10",
    "iso:country":"CA",
    "sg:address":"180 Mary St # 10",
    "sg:city":"Port Perry",
    "sg:classifiers":[
        {
            "category":"Professional",
            "subcategory":"Management & Consulting",
            "type":"Services"
        }
    ],
    "sg:phone":"+1 905 985 2955",
    "sg:postcode":"L9L 1C4",
    "sg:province":"ON",
    "sg:tags":[
        "consultant",
        "business"
    ],
    "wof:name":"Systems Approach Strategies",
    "wof:placetype":"venue"
},
  "geometry": {"coordinates":[-78.9430236816,44.1038169861],"type":"Point"}
}