{
  "type": "Feature",
  "properties": {
    "addr:full":"830 Queenston Rd Stoney Creek ON L8G 4A8",
    "addr:housenumber":"830",
    "addr:postcode":"l8g 4a8",
    "addr:street":"Queenston Rd",
    "iso:country":"CA",
    "sg:address":"830 Queenston Rd",
    "sg:city":"Stoney Creek",
    "sg:classifiers":[
        {
            "category":"Recreation",
            "type":"Entertainment"
        }
    ],
    "sg:phone":"+1 905 664 2026",
    "sg:postcode":"L8G 4A8",
    "sg:province":"ON",
    "sg:tags":[
        "tennis",
        "court"
    ],
    "wof:name":"Stoney Creek Tennis Club House",
    "wof:placetype":"venue"
},
  "geometry": {"coordinates":[-79.762749,43.227623],"type":"Point"}
}