{
  "type": "Feature",
  "properties": {
    "addr:full":"100 Rue DE L'Ermitage Victoriaville QC G6P 9N2",
    "addr:housenumber":"100",
    "addr:postcode":"g6p 9n2",
    "addr:street":"Rue De L'Ermitage",
    "iso:country":"CA",
    "sg:address":"100 Rue DE L'Ermitage",
    "sg:city":"Victoriaville",
    "sg:classifiers":[
        {
            "category":"Social Services",
            "subcategory":"Job Training",
            "type":"Services"
        }
    ],
    "sg:phone":"+1 819 752 5668",
    "sg:postcode":"G6P 9N2",
    "sg:province":"QC",
    "sg:tags":[
        "rehabilitation"
    ],
    "wof:name":"Domremy Mauricie Ctr Du Quebec",
    "wof:placetype":"venue"
},
  "geometry": {"coordinates":[-71.961388,46.060333],"type":"Point"}
}