{
  "type": "Feature",
  "properties": {
    "addr:full":"68 Rue Alexandre Salaberry-DE-Valleyfield QC J6S 3J8",
    "addr:housenumber":"68",
    "addr:postcode":"j6s 3j8",
    "addr:street":"Rue Alexandre",
    "iso:country":"CA",
    "sg:address":"68 Rue Alexandre",
    "sg:city":"Salaberry-DE-Valleyfield",
    "sg:classifiers":[
        {
            "category":"Manufacturing",
            "subcategory":"Tools & Machinery",
            "type":"Manufacturing & Wholesale Goods"
        }
    ],
    "sg:phone":"+1 450 373 8155",
    "sg:postcode":"J6S 3J8",
    "sg:province":"QC",
    "sg:tags":[
        "conditioning",
        "air",
        "refrigeration",
        "system",
        "contractor"
    ],
    "wof:name":"C Lanoue Electrique Inc",
    "wof:placetype":"venue"
},
  "geometry": {"coordinates":[-74.134041,45.262691],"type":"Point"}
}