{
  "type": "Feature",
  "properties": {
    "addr:full":"87 Rue Ontario O Montreal QC H2X 1Y8",
    "addr:housenumber":"87",
    "addr:postcode":"h2x 1y8",
    "addr:street":"Rue Ontario O",
    "iso:country":"CA",
    "sg:address":"87 Rue Ontario O",
    "sg:city":"Montreal",
    "sg:classifiers":[
        {
            "category":"Real Estate",
            "subcategory":"Real Estate Agent",
            "type":"Services"
        }
    ],
    "sg:phone":"+1 514 840 8300",
    "sg:postcode":"H2X 1Y8",
    "sg:province":"QC",
    "sg:tags":[
        "management"
    ],
    "wof:name":"Nexacor Realty Mgmt Inc",
    "wof:placetype":"venue"
},
  "geometry": {"coordinates":[-73.56663500000001,45.51215],"type":"Point"}
}