{
  "type": "Feature",
  "properties": {
    "addr:full":"5 Church St #45 Westport ON K0G 1X0",
    "addr:housenumber":"5",
    "addr:postcode":"k0g 1x0",
    "addr:street":"Church St # 45",
    "iso:country":"CA",
    "sg:address":"5 Church St #45",
    "sg:city":"Westport",
    "sg:classifiers":[
        {
            "category":"Personal",
            "subcategory":"Barber",
            "type":"Services"
        }
    ],
    "sg:phone":"+1 613 273 2145",
    "sg:postcode":"K0G 1X0",
    "sg:province":"ON",
    "wof:name":"Murphy's Barber & Sports Shop",
    "wof:placetype":"venue"
},
  "geometry": {"coordinates":[-76.396446228,44.6792144775],"type":"Point"}
}