{
  "type": "Feature",
  "properties": {
    "iso:country":"CA",
    "sg:address":"1472 Danforth Ave",
    "sg:city":"Toronto",
    "sg:classifiers":[
        {
            "category":"Personal",
            "subcategory":"Beauty Salon",
            "type":"Services"
        }
    ],
    "sg:phone":"+1 416 465 3710",
    "sg:postcode":"M4J 1N4",
    "sg:province":"ON",
    "sg:tags":[
        "spa",
        "day"
    ],
    "wof:name":"Amethyst Spa & Salon",
    "wof:placetype":"venue"
},
  "geometry": {"coordinates":[-79.32601165769999,43.682975769],"type":"Point"}
}