{
  "type": "Feature",
  "properties": {
    "iso:country":"CA",
    "sg:city":"Richmond Hill",
    "sg:classifiers":[
        {
            "category":"Manufacturing",
            "subcategory":"Printing",
            "type":"Manufacturing & Wholesale Goods"
        }
    ],
    "sg:phone":"+1 905 764 3424",
    "sg:postcode":"L4B 1K1",
    "sg:province":"ON",
    "sg:tags":[
        "printer"
    ],
    "wof:name":"Shea Graphics Inc",
    "wof:placetype":"venue"
},
  "geometry": {"coordinates":[-79.388573,43.852516],"type":"Point"}
}