{
  "type": "Feature",
  "properties": {
    "addr:full":"780 Windmill Rd # 103 Dartmouth NS B3B 1T3",
    "addr:housenumber":"780",
    "addr:postcode":"b3b 1t3",
    "addr:street":"Windmill Rd # 103",
    "iso:country":"CA",
    "sg:address":"780 Windmill Rd # 103",
    "sg:city":"Dartmouth",
    "sg:classifiers":[
        {
            "category":"Wholesale",
            "subcategory":"Machinery & Supplies",
            "type":"Manufacturing & Wholesale Goods"
        }
    ],
    "sg:phone":"+1 902 468 4775",
    "sg:postcode":"B3B 1T3",
    "sg:province":"NS",
    "sg:tags":[
        "control"
    ],
    "wof:name":"Everst Automation Inc",
    "wof:placetype":"venue"
},
  "geometry": {"coordinates":[-63.609699,44.702942],"type":"Point"}
}