{
  "type": "Feature",
  "properties": {
    "addr:full":"Carp ON K0A 1L0",
    "addr:postcode":"k0a 1l0",
    "iso:country":"CA",
    "sg:city":"Carp",
    "sg:classifiers":[
        {
            "category":"Retail",
            "subcategory":"Auto Rental",
            "type":"Services"
        }
    ],
    "sg:phone":"+1 613 839 7737",
    "sg:postcode":"K0A 1L0",
    "sg:province":"ON",
    "sg:tags":[
        "renting",
        "leasing",
        "trailer"
    ],
    "wof:name":"Zimrace",
    "wof:placetype":"venue"
},
  "geometry": {"coordinates":[-76.035004,45.344193],"type":"Point"}
}