{
  "type": "Feature",
  "properties": {
    "addr:full":"3944 Quadra St Victoria BC V8X 1J6",
    "addr:housenumber":"3944",
    "addr:postcode":"v8x 1j6",
    "addr:street":"Quadra St",
    "iso:country":"CA",
    "sg:address":"3944 Quadra St",
    "sg:city":"Victoria",
    "sg:classifiers":[
        {
            "category":"Manufacturing",
            "subcategory":"Rubber & Plastics",
            "type":"Manufacturing & Wholesale Goods"
        }
    ],
    "sg:phone":"+1 250 727 3545",
    "sg:postcode":"V8X 1J6",
    "sg:province":"BC",
    "wof:name":"Industrial Plastics & Paints",
    "wof:placetype":"venue"
},
  "geometry": {"coordinates":[-123.36200700000001,48.448891],"type":"Point"}
}