{
  "type": "Feature",
  "properties": {
    "addr:full":"146 Ch D'Adamsville Bromont QC J2L 2Y6",
    "addr:housenumber":"146",
    "addr:postcode":"j2l 2y6",
    "addr:street":"Ch D'Adamsville",
    "iso:country":"CA",
    "sg:address":"146 Ch D'Adamsville",
    "sg:city":"Bromont",
    "sg:classifiers":[
        {
            "category":"Organizations",
            "subcategory":"Professional Association",
            "type":"Services"
        }
    ],
    "sg:phone":"+1 450 263 0456",
    "sg:postcode":"J2L 2Y6",
    "sg:province":"QC",
    "sg:tags":[
        "club"
    ],
    "wof:name":"Hotel Adamsville",
    "wof:placetype":"venue"
},
  "geometry": {"coordinates":[-72.7566986084,45.3172836304],"type":"Point"}
}