{
  "type": "Feature",
  "properties": {
    "addr:full":"113 Cow Bay Rd Prince Rupert BC V8J 1A2",
    "addr:housenumber":"113",
    "addr:postcode":"v8j 1a2",
    "addr:street":"Cow Bay Rd",
    "iso:country":"CA",
    "sg:address":"113 Cow Bay Rd",
    "sg:city":"Prince Rupert",
    "sg:classifiers":[
        {
            "category":"Restaurant",
            "type":"Food & Drink"
        }
    ],
    "sg:phone":"+1 250 624 3072",
    "sg:postcode":"V8J 1A2",
    "sg:province":"BC",
    "wof:name":"Smiles Seafood Cafe Ltd",
    "wof:placetype":"venue"
},
  "geometry": {"coordinates":[-130.31930542000001,54.3189697266],"type":"Point"}
}