{
  "type": "Feature",
  "properties": {
    "addr:full":"1024 O'Brien St North Bay ON P1B 5X4",
    "addr:housenumber":"1024",
    "addr:postcode":"p1b 5x4",
    "addr:street":"O'Brien St",
    "iso:country":"CA",
    "sg:address":"1024 O'Brien St",
    "sg:city":"North Bay",
    "sg:classifiers":[
        {
            "category":"Personal",
            "subcategory":"Barber",
            "type":"Services"
        }
    ],
    "sg:phone":"+1 705 497 8888",
    "sg:postcode":"P1B 5X4",
    "sg:province":"ON",
    "wof:name":"Archie's Barber Shop",
    "wof:placetype":"venue"
},
  "geometry": {"coordinates":[-79.45545199999999,46.33744],"type":"Point"}
}