{
  "type": "Feature",
  "properties": {
    "iso:country":"CA",
    "sg:address":"959 Ch Denison E",
    "sg:city":"Canton DE Shefford",
    "sg:classifiers":[
        {
            "category":"Bus Charters",
            "type":"Transportation"
        }
    ],
    "sg:phone":"+1 450 372 2961",
    "sg:postcode":"J2G 8C7",
    "sg:province":"QC",
    "sg:tags":[
        "rental"
    ],
    "wof:name":"Autobus Bromont Inc",
    "wof:placetype":"venue"
},
  "geometry": {"coordinates":[-72.47402954099999,45.3321380615],"type":"Point"}
}