{
  "type": "Feature",
  "properties": {
    "addr:full":"1423 Gerrard St E Toronto ON M4L 1Z7",
    "addr:housenumber":"1423",
    "addr:postcode":"m4l 1z7",
    "addr:street":"Gerrard St E",
    "iso:country":"CA",
    "sg:address":"1423 Gerrard St E",
    "sg:city":"Toronto",
    "sg:classifiers":[
        {
            "category":"Restaurant",
            "type":"Food & Drink"
        }
    ],
    "sg:phone":"+1 416 463 2222",
    "sg:postcode":"M4L 1Z7",
    "sg:province":"ON",
    "wof:name":"Kwality Restaurant",
    "wof:placetype":"venue"
},
  "geometry": {"coordinates":[-79.322487,43.672016],"type":"Point"}
}