{
  "type": "Feature",
  "properties": {
    "iso:country":"CA",
    "sg:address":"5690 Boul Cavendish",
    "sg:city":"Cote Saint-Luc",
    "sg:classifiers":[
        {
            "category":"Health Services",
            "subcategory":"Hospital",
            "type":"Services"
        }
    ],
    "sg:phone":"+1 514 369 2222",
    "sg:postcode":"H4W 1S7",
    "sg:province":"QC",
    "wof:name":"Centre Hospitalier Mont-Sinai",
    "wof:placetype":"venue"
},
  "geometry": {"coordinates":[-73.657829,45.474087],"type":"Point"}
}