{
  "type": "Feature",
  "properties": {
    "addr:full":"163 Centre St Rosedale Station AB T0J 2V0",
    "addr:housenumber":"163",
    "addr:postcode":"t0j 2v0",
    "addr:street":"Centre St",
    "iso:country":"CA",
    "sg:address":"163 Centre St",
    "sg:city":"Rosedale Station",
    "sg:classifiers":[
        {
            "category":"Restaurant",
            "type":"Food & Drink"
        }
    ],
    "sg:phone":"+1 403 823 8515",
    "sg:postcode":"T0J 2V0",
    "sg:province":"AB",
    "wof:name":"Cool Castle",
    "wof:placetype":"venue"
},
  "geometry": {"coordinates":[-112.631889,51.418919],"type":"Point"}
}