{
  "type": "Feature",
  "properties": {
    "iso:country":"CA",
    "sg:city":"London",
    "sg:classifiers":[
        {
            "category":"Health Services",
            "subcategory":"Doctor",
            "type":"Services"
        }
    ],
    "sg:phone":"+1 519 668 6844",
    "sg:postcode":"N6E 3H3",
    "sg:province":"ON",
    "sg:tags":[
        "dentist"
    ],
    "wof:name":"Perkins, Robert D DDS",
    "wof:placetype":"venue"
},
  "geometry": {"coordinates":[-81.237335,42.940437],"type":"Point"}
}