{
  "type": "Feature",
  "properties": {
    "addr:full":"279 King St Bridgewater NS B4V 1A7",
    "addr:housenumber":"279",
    "addr:postcode":"b4v 1a7",
    "addr:street":"King St",
    "iso:country":"CA",
    "sg:address":"279 King St",
    "sg:city":"Bridgewater",
    "sg:classifiers":[
        {
            "category":"Taxi",
            "type":"Transportation"
        }
    ],
    "sg:phone":"+1 902 543 5686",
    "sg:postcode":"B4V 1A7",
    "sg:province":"NS",
    "sg:tags":[
        "taxicab"
    ],
    "wof:name":"Charlie's Taxi",
    "wof:placetype":"venue"
},
  "geometry": {"coordinates":[-64.5123748779,44.3736228943],"type":"Point"}
}