{
  "type": "Feature",
  "properties": {
    "addr:full":"9841 110 St NW Edmonton AB T5K 2P5",
    "addr:housenumber":"9841",
    "addr:postcode":"t5k 2p5",
    "addr:street":"110 St Nw",
    "iso:country":"CA",
    "sg:address":"9841 110 St NW",
    "sg:city":"Edmonton",
    "sg:classifiers":[
        {
            "category":"Food & Beverages",
            "subcategory":"Groceries & Convenience Stores",
            "type":"Retail Goods"
        }
    ],
    "sg:phone":"+1 780 451 2295",
    "sg:postcode":"T5K 2P5",
    "sg:province":"AB",
    "sg:tags":[
        "grocer"
    ],
    "wof:name":"Alberta First Grocery & Deli",
    "wof:placetype":"venue"
},
  "geometry": {"coordinates":[-113.51005600000001,53.536327],"type":"Point"}
}