{
  "type": "Feature",
  "properties": {
    "addr:full":"8800 Thorold Stone Rd Niagara Falls ON L2E 6S4",
    "addr:housenumber":"8800",
    "addr:postcode":"l2e 6s4",
    "addr:street":"Thorold Stone Rd",
    "iso:country":"CA",
    "sg:address":"8800 Thorold Stone Rd",
    "sg:city":"Niagara Falls",
    "sg:classifiers":[
        {
            "category":"Manufacturing",
            "subcategory":"Chemicals & Compounds",
            "type":"Manufacturing & Wholesale Goods"
        }
    ],
    "sg:phone":"+1 905 357 3131",
    "sg:postcode":"L2E 6S4",
    "sg:province":"ON",
    "sg:tags":[
        "plastic"
    ],
    "wof:name":"Oxy Vinyls Canada Inc",
    "wof:placetype":"venue"
},
  "geometry": {"coordinates":[-79.14733099999999,43.113804],"type":"Point"}
}