{
  "type": "Feature",
  "properties": {
    "addr:full":"1886 Rue Notre-Dame O Montreal QC H3J 1M6",
    "addr:housenumber":"1886",
    "addr:postcode":"h3j 1m6",
    "addr:street":"Rue Notre-Dame O",
    "iso:country":"CA",
    "sg:address":"1886 Rue Notre-Dame O",
    "sg:city":"Montreal",
    "sg:classifiers":[
        {
            "category":"Shopping",
            "subcategory":"Used Merchandise",
            "type":"Retail Goods"
        }
    ],
    "sg:phone":"+1 514 933 6375",
    "sg:postcode":"H3J 1M6",
    "sg:province":"QC",
    "sg:tags":[
        "antique"
    ],
    "wof:name":"Obsession Antiques",
    "wof:placetype":"venue"
},
  "geometry": {"coordinates":[-73.54733299999999,45.519402],"type":"Point"}
}