{
  "type": "Feature",
  "properties": {
    "addr:full":"General Delivery Cadotte Lake AB T0H 0N0",
    "addr:postcode":"t0h 0n0",
    "iso:country":"CA",
    "sg:address":"General Delivery",
    "sg:city":"Cadotte Lake",
    "sg:classifiers":[
        {
            "category":"Social Services",
            "subcategory":"Child Care",
            "type":"Services"
        }
    ],
    "sg:phone":"+1 780 629 2538",
    "sg:postcode":"T0H 0N0",
    "sg:province":"AB",
    "wof:name":"Woodland Cree Band Daycare",
    "wof:placetype":"venue"
},
  "geometry": {"coordinates":[-116.37187957800001,56.4680938721],"type":"Point"}
}