{
  "type": "Feature",
  "properties": {
    "iso:country":"CA",
    "sg:address":"560 Albert",
    "sg:city":"Winchester",
    "sg:classifiers":[
        {
            "category":"Health Services",
            "subcategory":"Doctor",
            "type":"Services"
        }
    ],
    "sg:phone":"+1 613 774 1445",
    "sg:postcode":"K0C 2K0",
    "sg:province":"ON",
    "sg:tags":[
        "physician",
        "surgeon"
    ],
    "wof:name":"Blakslee, James M MD",
    "wof:placetype":"venue"
},
  "geometry": {"coordinates":[-75.3492355347,45.0905075073],"type":"Point"}
}