{
  "type": "Feature",
  "properties": {
    "addr:full":"Surrey BC V3W 3N4",
    "addr:postcode":"v3w 3n4",
    "iso:country":"CA",
    "sg:city":"Surrey",
    "sg:classifiers":[
        {
            "category":"Professional",
            "subcategory":"Detective & Security Services",
            "type":"Services"
        }
    ],
    "sg:phone":"+1 604 572 7336",
    "sg:postcode":"V3W 3N4",
    "sg:province":"BC",
    "sg:tags":[
        "investigator"
    ],
    "wof:name":"J P Moore Investigations Ltd",
    "wof:placetype":"venue"
},
  "geometry": {"coordinates":[-122.89024353000001,49.1544532776],"type":"Point"}
}