{
  "type": "Feature",
  "properties": {
    "addr:full":"887 Wall St Winnipeg MB R3G 2T9",
    "addr:housenumber":"887",
    "addr:postcode":"r3g 2t9",
    "addr:street":"Wall St",
    "iso:country":"CA",
    "sg:address":"887 Wall St",
    "sg:city":"Winnipeg",
    "sg:classifiers":[
        {
            "category":"Autos & Motor Vehicles",
            "subcategory":"Auto Supplies",
            "type":"Retail Goods"
        }
    ],
    "sg:phone":"+1 204 783 7223",
    "sg:postcode":"R3G 2T9",
    "sg:province":"MB",
    "sg:tags":[
        "automobile",
        "parts"
    ],
    "wof:name":"Softy's Speed Shop",
    "wof:placetype":"venue"
},
  "geometry": {"coordinates":[-97.181984,49.893032],"type":"Point"}
}