{
  "type": "Feature",
  "properties": {
    "addr:full":"Calgary AB T2E 8T6",
    "addr:postcode":"t2e 8t6",
    "iso:country":"CA",
    "sg:city":"Calgary",
    "sg:classifiers":[
        {
            "category":"Banks & Credit Unions",
            "subcategory":"Bank",
            "type":"Services"
        }
    ],
    "sg:phone":"+1 403 291 5151",
    "sg:postcode":"T2E 8T6",
    "sg:province":"AB",
    "sg:tags":[
        "loan"
    ],
    "wof:name":"Indian Agri-Business Corp",
    "wof:placetype":"venue"
},
  "geometry": {"coordinates":[-114.006820679,51.0687141418],"type":"Point"}
}