{
  "type": "Feature",
  "properties": {
    "addr:full":"Vancouver BC V6H 1H6",
    "addr:postcode":"v6h 1h6",
    "iso:country":"CA",
    "sg:city":"Vancouver",
    "sg:classifiers":[
        {
            "category":"Professional",
            "subcategory":"Business Services",
            "type":"Services"
        }
    ],
    "sg:phone":"+1 604 878 0450",
    "sg:postcode":"V6H 1H6",
    "sg:province":"BC",
    "sg:tags":[
        "notary"
    ],
    "wof:name":"Mehta, Devika",
    "wof:placetype":"venue"
},
  "geometry": {"coordinates":[-123.13636,49.26371],"type":"Point"}
}