{
  "type": "Feature",
  "properties": {
    "addr:full":"2 Fenton Rd Markham ON L3R 7B3",
    "addr:housenumber":"2",
    "addr:postcode":"l3r 7b3",
    "addr:street":"Fenton Rd",
    "iso:country":"CA",
    "sg:address":"2 Fenton Rd",
    "sg:city":"Markham",
    "sg:classifiers":[
        {
            "category":"Food & Beverages",
            "subcategory":"Groceries & Convenience Stores",
            "type":"Retail Goods"
        }
    ],
    "sg:phone":"+1 905 415 8508",
    "sg:postcode":"L3R 7B3",
    "sg:province":"ON",
    "sg:tags":[
        "grocer"
    ],
    "wof:name":"Priya Grocery",
    "wof:placetype":"venue"
},
  "geometry": {"coordinates":[-79.291946,43.827351],"type":"Point"}
}