{
  "type": "Feature",
  "properties": {
    "iso:country":"CA",
    "sg:address":"6001 53 St",
    "sg:city":"Olds",
    "sg:classifiers":[
        {
            "category":"Building & Trades",
            "subcategory":"Plumbing",
            "type":"Services"
        }
    ],
    "sg:phone":"+1 403 556 1669",
    "sg:postcode":"T4H 1L4",
    "sg:province":"AB",
    "sg:tags":[
        "contractor"
    ],
    "wof:name":"Brent Beaudoin Plumbing & Htg",
    "wof:placetype":"venue"
},
  "geometry": {"coordinates":[-114.123123169,51.7915802002],"type":"Point"}
}