{
  "type": "Feature",
  "properties": {
    "addr:full":"9429 Ch Cote-DE-Liesse Dorval QC H9P 2N9",
    "addr:postcode":"9429;h9p 2n9",
    "addr:street":"Ch Cote-De-Liesse",
    "iso:country":"CA",
    "sg:address":"9429 Ch Cote-DE-Liesse",
    "sg:city":"Dorval",
    "sg:classifiers":[
        {
            "category":"Home & Garden",
            "subcategory":"Building Materials",
            "type":"Retail Goods"
        }
    ],
    "sg:phone":"+1 514 420 0520",
    "sg:postcode":"H9P 2N9",
    "sg:province":"QC",
    "sg:tags":[
        "door"
    ],
    "wof:name":"Constructal Hardware Inc",
    "wof:placetype":"venue"
},
  "geometry": {"coordinates":[-73.71169999999999,45.471088],"type":"Point"}
}