{
  "type": "Feature",
  "properties": {
    "addr:full":"6604 187 St NW Edmonton AB T5T 2N2",
    "addr:housenumber":"6604",
    "addr:postcode":"t5t 2n2",
    "addr:street":"187 St Nw",
    "iso:country":"CA",
    "sg:address":"6604 187 St NW",
    "sg:city":"Edmonton",
    "sg:classifiers":[
        {
            "category":"Professional",
            "subcategory":"Engineering",
            "type":"Services"
        }
    ],
    "sg:phone":"+1 780 918 5555",
    "sg:postcode":"T5T 2N2",
    "sg:province":"AB",
    "sg:tags":[
        "engineer"
    ],
    "wof:name":"Traffic Solutions Consulting",
    "wof:placetype":"venue"
},
  "geometry": {"coordinates":[-113.644424,53.501335],"type":"Point"}
}