{
  "type": "Feature",
  "properties": {
    "addr:full":"8925 62 Ave NW Edmonton AB T6E 5L2",
    "addr:housenumber":"8925",
    "addr:postcode":"t6e 5l2",
    "addr:street":"62 Ave Nw",
    "iso:country":"CA",
    "sg:address":"8925 62 Ave NW",
    "sg:city":"Edmonton",
    "sg:classifiers":[
        {
            "category":"Building & Trades",
            "subcategory":"Construction",
            "type":"Services"
        }
    ],
    "sg:phone":"+1 780 465 9016",
    "sg:postcode":"T6E 5L2",
    "sg:province":"AB",
    "sg:tags":[
        "field",
        "oil",
        "jacks",
        "steeple"
    ],
    "wof:name":"Steeplejack Services Canada",
    "wof:placetype":"venue"
},
  "geometry": {"coordinates":[-113.465431,53.498402],"type":"Point"}
}