{
  "type": "Feature",
  "properties": {
    "addr:full":"645 Lansdowne St W Peterborough ON K9J 7Y5",
    "addr:housenumber":"645",
    "addr:postcode":"k9j 7y5",
    "addr:street":"Lansdowne St W",
    "iso:country":"CA",
    "sg:address":"645 Lansdowne St W",
    "sg:city":"Peterborough",
    "sg:classifiers":[
        {
            "category":"Personal",
            "subcategory":"Beauty Salon",
            "type":"Services"
        }
    ],
    "sg:phone":"+1 705 741 1211",
    "sg:postcode":"K9J 7Y5",
    "sg:province":"ON",
    "wof:name":"Cut Above",
    "wof:placetype":"venue"
},
  "geometry": {"coordinates":[-78.332855,44.284908],"type":"Point"}
}