{
  "type": "Feature",
  "properties": {
    "addr:full":"5126 48 Ave Vegreville AB T9C 1M7",
    "addr:housenumber":"5126",
    "addr:postcode":"t9c 1m7",
    "addr:street":"48 Ave",
    "iso:country":"CA",
    "sg:address":"5126 48 Ave",
    "sg:city":"Vegreville",
    "sg:classifiers":[
        {
            "category":"Organizations",
            "subcategory":"Religious Organization",
            "type":"Services"
        }
    ],
    "sg:phone":"+1 780 632 2338",
    "sg:postcode":"T9C 1M7",
    "sg:province":"AB",
    "sg:tags":[
        "church"
    ],
    "wof:name":"United Church of Canada",
    "wof:placetype":"venue"
},
  "geometry": {"coordinates":[-112.057777,53.49472],"type":"Point"}
}