{
  "type": "Feature",
  "properties": {
    "addr:full":"630 Rue Cabot Chicoutimi QC G7G 4G8",
    "addr:housenumber":"630",
    "addr:postcode":"g7g 4g8",
    "addr:street":"Rue Cabot",
    "iso:country":"CA",
    "sg:address":"630 Rue Cabot",
    "sg:city":"Chicoutimi",
    "sg:classifiers":[
        {
            "category":"Government",
            "subcategory":"Office",
            "type":"Public Place"
        }
    ],
    "sg:phone":"+1 418 698 3230",
    "sg:postcode":"G7G 4G8",
    "sg:province":"QC",
    "sg:tags":[
        "village"
    ],
    "wof:name":"Chicoutimi Chantier Du Pere",
    "wof:placetype":"venue"
},
  "geometry": {"coordinates":[-71.06726074220001,48.448841095],"type":"Point"}
}