{
  "type": "Feature",
  "properties": {
    "addr:full":"90 Winges Rd Woodbridge ON L4L 6A9",
    "addr:housenumber":"90",
    "addr:postcode":"l4l 6a9",
    "addr:street":"Winges Rd",
    "iso:country":"CA",
    "sg:address":"90 Winges Rd",
    "sg:city":"Woodbridge",
    "sg:classifiers":[
        {
            "category":"Professional",
            "subcategory":"Business Services",
            "type":"Services"
        }
    ],
    "sg:phone":"+1 905 850 0661",
    "sg:postcode":"L4L 6A9",
    "sg:province":"ON",
    "sg:tags":[
        "embroidery"
    ],
    "wof:name":"F M Embroidery Ltd",
    "wof:placetype":"venue"
},
  "geometry": {"coordinates":[-79.553185,43.787067],"type":"Point"}
}