{
  "type": "Feature",
  "properties": {
    "addr:full":"11939 224 St #208 Maple Ridge BC V2X 6B2",
    "addr:housenumber":"11939",
    "addr:postcode":"v2x 6b2",
    "addr:street":"224 St # 208",
    "iso:country":"CA",
    "sg:address":"11939 224 St #208",
    "sg:city":"Maple Ridge",
    "sg:classifiers":[
        {
            "category":"Professional",
            "subcategory":"Lawyer & Legal Services",
            "type":"Services"
        }
    ],
    "sg:phone":"+1 604 463 4386",
    "sg:postcode":"V2X 6B2",
    "sg:province":"BC",
    "sg:tags":[
        "attorney"
    ],
    "wof:name":"Mc Leod, Susan K",
    "wof:placetype":"venue"
},
  "geometry": {"coordinates":[-122.601959228,49.219291687],"type":"Point"}
}