{
  "type": "Feature",
  "properties": {
    "addr:full":"134 St. Peters Rd Charlottetown PE C1A 5P4",
    "addr:housenumber":"134",
    "addr:postcode":"c1a 5p4",
    "addr:street":"St. Peters Rd",
    "iso:country":"CA",
    "sg:address":"134 St. Peters Rd",
    "sg:city":"Charlottetown",
    "sg:classifiers":[
        {
            "category":"Home & Garden",
            "subcategory":"Furniture",
            "type":"Retail Goods"
        }
    ],
    "sg:phone":"+1 902 892 4111",
    "sg:postcode":"C1A 5P4",
    "sg:province":"PE",
    "wof:name":"Leon's Furniture Ltd",
    "wof:placetype":"venue"
},
  "geometry": {"coordinates":[-63.11916,46.258591],"type":"Point"}
}