{
  "type": "Feature",
  "properties": {
    "addr:full":"4281 Rue Des Pins Shipshaw QC G7P 1L8",
    "addr:housenumber":"4281",
    "addr:postcode":"g7p 1l8",
    "addr:street":"Rue Des Pins",
    "iso:country":"CA",
    "sg:address":"4281 Rue Des Pins",
    "sg:city":"Shipshaw",
    "sg:classifiers":[
        {
            "category":"Organizations",
            "subcategory":"Religious Organization",
            "type":"Services"
        }
    ],
    "sg:phone":"+1 418 547 6856",
    "sg:postcode":"G7P 1L8",
    "sg:province":"QC",
    "sg:tags":[
        "church"
    ],
    "wof:name":"Presbytere St-Jean-Vianney",
    "wof:placetype":"venue"
},
  "geometry": {"coordinates":[-71.266456604,48.5065498352],"type":"Point"}
}