{
  "type": "Feature",
  "properties": {
    "addr:full":"3650 Boul DE LA Rive-Sud Levis QC G6W 7L3",
    "addr:housenumber":"3650",
    "addr:postcode":"g6w 7l3",
    "addr:street":"Boul De La Rive-Sud",
    "iso:country":"CA",
    "sg:address":"3650 Boul DE LA Rive-Sud",
    "sg:city":"Levis",
    "sg:classifiers":[
        {
            "category":"Manufacturing",
            "subcategory":"Tools & Machinery",
            "type":"Manufacturing & Wholesale Goods"
        }
    ],
    "sg:phone":"+1 418 837 2147",
    "sg:postcode":"G6W 7L3",
    "sg:province":"QC",
    "sg:tags":[
        "shovel"
    ],
    "wof:name":"Construction Raoul Pelletier",
    "wof:placetype":"venue"
},
  "geometry": {"coordinates":[-71.200119,46.769798],"type":"Point"}
}