{
  "type": "Feature",
  "properties": {
    "addr:full":"302 Southwest Dr W Richer MB R0E 1S0",
    "addr:housenumber":"302",
    "addr:postcode":"r0e 1s0",
    "addr:street":"Southwest Dr W Richer",
    "iso:country":"CA",
    "sg:address":"302 Southwest Dr W",
    "sg:city":"Richer",
    "sg:classifiers":[
        {
            "category":"Home & Garden",
            "subcategory":"Building Materials",
            "type":"Retail Goods"
        }
    ],
    "sg:phone":"+1 204 422 5608",
    "sg:postcode":"R0E 1S0",
    "sg:province":"MB",
    "sg:tags":[
        "mixed",
        "concrete"
    ],
    "wof:name":"Perimeter Concrete Ltd",
    "wof:placetype":"venue"
},
  "geometry": {"coordinates":[-96.4568023682,49.6563835144],"type":"Point"}
}