{
  "type": "Feature",
  "properties": {
    "addr:full":"705 Rue Sainte-Catherine O Montreal QC H3B 4G5",
    "addr:housenumber":"705",
    "addr:postcode":"h3b 4g5",
    "addr:street":"Rue Sainte-Catherine O",
    "iso:country":"CA",
    "sg:address":"705 Rue Sainte-Catherine O",
    "sg:city":"Montreal",
    "sg:classifiers":[
        {
            "category":"Wholesale",
            "subcategory":"Electrical",
            "type":"Manufacturing & Wholesale Goods"
        }
    ],
    "sg:phone":"+1 514 847 0303",
    "sg:postcode":"H3B 4G5",
    "sg:province":"QC",
    "sg:tags":[
        "shaver"
    ],
    "wof:name":"Boutik Electrik",
    "wof:placetype":"venue"
},
  "geometry": {"coordinates":[-73.5591964722,45.5153617859],"type":"Point"}
}