{
  "type": "Feature",
  "properties": {
    "addr:full":"1062 Homer St Vancouver BC V6B 2W9",
    "addr:housenumber":"1062",
    "addr:postcode":"bc v6b 2w9",
    "addr:street":"Homer St",
    "iso:country":"CA",
    "sg:address":"1062 Homer St",
    "sg:city":"Vancouver",
    "sg:classifiers":[
        {
            "category":"Home & Garden",
            "subcategory":"Furniture",
            "type":"Retail Goods"
        }
    ],
    "sg:phone":"+1 604 331 2363",
    "sg:postcode":"V6B 2W9",
    "sg:province":"BC",
    "wof:name":"Montauk Vancouver",
    "wof:placetype":"venue"
},
  "geometry": {"coordinates":[-123.12086499999999,49.276642],"type":"Point"}
}