{
  "type": "Feature",
  "properties": {
    "addr:full":"4599 Chateau Blvd Whistler BC V0N 1B4",
    "addr:housenumber":"4599",
    "addr:postcode":"v0n 1b4",
    "addr:street":"Chateau Blvd",
    "iso:country":"CA",
    "sg:address":"4599 Chateau Blvd",
    "sg:city":"Whistler",
    "sg:classifiers":[
        {
            "category":"Personal",
            "type":"Services"
        }
    ],
    "sg:phone":"+1 604 938 2086",
    "sg:postcode":"V0N 1B4",
    "sg:province":"BC",
    "sg:tags":[
        "therapist",
        "massage"
    ],
    "wof:name":"Spa At Chateau Whistler Ltd",
    "wof:placetype":"venue"
},
  "geometry": {"coordinates":[-122.94581604,50.1171302795],"type":"Point"}
}