{
  "type": "Feature",
  "properties": {
    "addr:full":"2750 Heather St Vancouver BC V5Z 4M2",
    "addr:housenumber":"2750",
    "addr:postcode":"v5z 4m2",
    "addr:street":"Heather St",
    "iso:country":"CA",
    "sg:address":"2750 Heather St",
    "sg:city":"Vancouver",
    "sg:classifiers":[
        {
            "category":"Shopping",
            "subcategory":"Books",
            "type":"Retail Goods"
        }
    ],
    "sg:phone":"+1 604 875 5588",
    "sg:postcode":"V5Z 4M2",
    "sg:province":"BC",
    "sg:tags":[
        "dealer"
    ],
    "wof:name":"Ubc Health Sciences Bookshop",
    "wof:placetype":"venue"
},
  "geometry": {"coordinates":[-123.119743,49.260929],"type":"Point"}
}