{
  "type": "Feature",
  "properties": {
    "addr:full":"584 Rue Leonard Saint-Eustache QC J7R 6J6",
    "addr:housenumber":"584",
    "addr:postcode":"j7r 6j6",
    "addr:street":"Rue Leonard",
    "iso:country":"CA",
    "sg:address":"584 Rue Leonard",
    "sg:city":"Saint-Eustache",
    "sg:classifiers":[
        {
            "category":"Building & Trades",
            "subcategory":"Electrical",
            "type":"Services"
        }
    ],
    "sg:phone":"+1 450 491 6346",
    "sg:postcode":"J7R 6J6",
    "sg:province":"QC",
    "sg:tags":[
        "electric",
        "contractor"
    ],
    "wof:name":"Marmax Electrique Inc",
    "wof:placetype":"venue"
},
  "geometry": {"coordinates":[-73.927544,45.575268],"type":"Point"}
}