{
  "type": "Feature",
  "properties": {
    "addr:full":"210 1st St Sointula BC V0N 3E0",
    "addr:housenumber":"210",
    "addr:postcode":"v0n 3e0",
    "addr:street":"1St St",
    "iso:country":"CA",
    "sg:address":"210 1st St",
    "sg:city":"Sointula",
    "sg:classifiers":[
        {
            "category":"Banks & Credit Unions",
            "subcategory":"Bank",
            "type":"Services"
        }
    ],
    "sg:phone":"+1 250 973 6551",
    "sg:postcode":"V0N 3E0",
    "sg:province":"BC",
    "wof:name":"Cibc",
    "wof:placetype":"venue"
},
  "geometry": {"coordinates":[-127.017357,50.627266],"type":"Point"}
}