{
  "type": "Feature",
  "properties": {
    "addr:full":"1259 Deer Walk Bowen Island BC V0N 1G0",
    "addr:housenumber":"1259",
    "addr:postcode":"v0n 1g0",
    "addr:street":"Deer Walk",
    "iso:country":"CA",
    "sg:address":"1259 Deer Walk",
    "sg:city":"Bowen Island",
    "sg:classifiers":[
        {
            "category":"Professional",
            "subcategory":"Management & Consulting",
            "type":"Services"
        }
    ],
    "sg:phone":"+1 604 947 0493",
    "sg:postcode":"V0N 1G0",
    "sg:province":"BC",
    "sg:tags":[
        "consultant",
        "business",
        "marketing"
    ],
    "wof:name":"Comp Quest Consulting Inc",
    "wof:placetype":"venue"
},
  "geometry": {"coordinates":[-123.326752,49.391018],"type":"Point"}
}