{
  "type": "Feature",
  "properties": {
    "addr:full":"Grafton ON K0K 2G0",
    "addr:postcode":"k0k 2g0",
    "iso:country":"CA",
    "sg:city":"Grafton",
    "sg:classifiers":[
        {
            "category":"Retail",
            "subcategory":"Repair Shop",
            "type":"Services"
        }
    ],
    "sg:phone":"+1 905 349 2040",
    "sg:postcode":"K0K 2G0",
    "sg:province":"ON",
    "sg:tags":[
        "automobile",
        "top",
        "upholstery",
        "upholsterer"
    ],
    "wof:name":"Keith's Auto Upholstery",
    "wof:placetype":"venue"
},
  "geometry": {"coordinates":[-78.024307251,43.9923858643],"type":"Point"}
}