{
  "type": "Feature",
  "properties": {
    "addr:full":"Victoria BC V9A 7C5",
    "addr:postcode":"v9a 7c5",
    "iso:country":"CA",
    "sg:city":"Victoria",
    "sg:classifiers":[
        {
            "category":"Restaurant",
            "type":"Food & Drink"
        }
    ],
    "sg:phone":"+1 250 384 7144",
    "sg:postcode":"V9A 7C5",
    "sg:province":"BC",
    "wof:name":"Brass Duck Restaurant",
    "wof:placetype":"venue"
},
  "geometry": {"coordinates":[-123.364517212,48.428314209],"type":"Point"}
}