{
  "type": "Feature",
  "properties": {
    "addr:full":"578 Victoria St Cobourg ON K9A 5A4",
    "addr:housenumber":"578",
    "addr:postcode":"k9a 5a4",
    "addr:street":"Victoria St",
    "iso:country":"CA",
    "sg:address":"578 Victoria St",
    "sg:city":"Cobourg",
    "sg:classifiers":[
        {
            "category":"Building & Trades",
            "subcategory":"Construction",
            "type":"Services"
        }
    ],
    "sg:phone":"+1 905 372 0189",
    "sg:postcode":"K9A 5A4",
    "sg:province":"ON",
    "sg:tags":[
        "fire",
        "restoration",
        "general",
        "damage",
        "contractor"
    ],
    "wof:name":"Superior Restoration",
    "wof:placetype":"venue"
},
  "geometry": {"coordinates":[-78.17701,43.966381],"type":"Point"}
}