{
  "type": "Feature",
  "properties": {
    "addr:full":"RR 1 Tilley AB T0J 3K0",
    "addr:postcode":"t0j 3k0",
    "addr:street":"Rr 1 Tilley",
    "iso:country":"CA",
    "sg:address":"RR 1",
    "sg:city":"Tilley",
    "sg:classifiers":[
        {
            "category":"Wholesale",
            "subcategory":"Auto Parts",
            "type":"Manufacturing & Wholesale Goods"
        }
    ],
    "sg:phone":"+1 403 377 2484",
    "sg:postcode":"T0J 3K0",
    "sg:province":"AB",
    "sg:tags":[
        "automobile",
        "rebuilt"
    ],
    "wof:name":"Flatla Auto Wrecking",
    "wof:placetype":"venue"
},
  "geometry": {"coordinates":[-111.652794,50.45071],"type":"Point"}
}