{
  "type": "Feature",
  "properties": {
    "addr:full":"Courtenay BC V9N 1G8",
    "addr:postcode":"v9n 1g8",
    "iso:country":"CA",
    "sg:city":"Courtenay",
    "sg:classifiers":[
        {
            "category":"Personal",
            "subcategory":"Beauty Salon",
            "type":"Services"
        }
    ],
    "sg:phone":"+1 250 338 8552",
    "sg:postcode":"V9N 1G8",
    "sg:province":"BC",
    "wof:name":"Extreme Ends Hair Design",
    "wof:placetype":"venue"
},
  "geometry": {"coordinates":[-124.99968,49.691669],"type":"Point"}
}