{
  "type": "Feature",
  "properties": {
    "addr:full":"73 Water St N #403 Cambridge ON N1R 7L6",
    "addr:housenumber":"73",
    "addr:postcode":"n1r 7l6",
    "addr:street":"Water St N # 403",
    "iso:country":"CA",
    "sg:address":"73 Water St N #403",
    "sg:city":"Cambridge",
    "sg:classifiers":[
        {
            "category":"Professional",
            "subcategory":"Lawyer & Legal Services",
            "type":"Services"
        }
    ],
    "sg:phone":"+1 519 621 2450",
    "sg:postcode":"N1R 7L6",
    "sg:province":"ON",
    "sg:tags":[
        "attorney"
    ],
    "wof:name":"Pettitt Schwarz",
    "wof:placetype":"venue"
},
  "geometry": {"coordinates":[-80.315178,43.361755],"type":"Point"}
}