{
  "type": "Feature",
  "properties": {
    "addr:full":"1430 Prince of Wales Dr Ottawa ON K2C 1N6",
    "addr:housenumber":"1430",
    "addr:postcode":"k2c 1n6",
    "addr:street":"Prince Of Wales Dr",
    "iso:country":"CA",
    "sg:address":"1430 Prince of Wales Dr",
    "sg:city":"Ottawa",
    "sg:classifiers":[
        {
            "category":"Personal",
            "subcategory":"Beauty Salon",
            "type":"Services"
        }
    ],
    "sg:phone":"+1 613 727 0455",
    "sg:postcode":"K2C 1N6",
    "sg:province":"ON",
    "wof:name":"Contemporary Hair Design",
    "wof:placetype":"venue"
},
  "geometry": {"coordinates":[-75.70161437989999,45.3689498901],"type":"Point"}
}