{
  "type": "Feature",
  "properties": {
    "addr:full":"14 William St Hantsport NS B0P 1P0",
    "addr:housenumber":"14",
    "addr:postcode":"b0p 1p0",
    "addr:street":"William St",
    "iso:country":"CA",
    "sg:address":"14 William St",
    "sg:city":"Hantsport",
    "sg:classifiers":[
        {
            "category":"Health Services",
            "subcategory":"Doctor",
            "type":"Services"
        }
    ],
    "sg:phone":"+1 902 684 3325",
    "sg:postcode":"B0P 1P0",
    "sg:province":"NS",
    "sg:tags":[
        "physician",
        "surgeon"
    ],
    "wof:name":"Wile, Iona MD",
    "wof:placetype":"venue"
},
  "geometry": {"coordinates":[-64.183891,45.064922],"type":"Point"}
}