{
  "type": "Feature",
  "properties": {
    "addr:full":"507 - 977 Mainland St Vancouver V6B1T2",
    "addr:housenumber":"977",
    "addr:postcode":"v6b1t2",
    "addr:street":"Mainland St",
    "iso:country":"CA",
    "sg:address":"507 - 977 Mainland St",
    "sg:city":"Vancouver",
    "sg:classifiers":[
        {
            "category":"Professional",
            "subcategory":"Management & Consulting",
            "type":"Services"
        }
    ],
    "sg:postcode":"V6B1T2",
    "sg:tags":[
        "public-relations-publicity-media-headlines-stories-press-coverage-news"
    ],
    "sg:website":"http://www.megawattpr.com",
    "wof:name":"Megawatt PR",
    "wof:placetype":"venue"
},
  "geometry": {"coordinates":[-123.118619,49.2768846],"type":"Point"}
}