{
  "type": "Feature",
  "properties": {
    "addr:full":"951 Matheson Blvd E Mississauga ON L4W 2R7",
    "addr:housenumber":"951",
    "addr:postcode":"l4w 2r7",
    "addr:street":"Matheson Blvd E",
    "iso:country":"CA",
    "sg:address":"951 Matheson Blvd E",
    "sg:city":"Mississauga",
    "sg:classifiers":[
        {
            "category":"Manufacturing",
            "subcategory":"Furniture",
            "type":"Manufacturing & Wholesale Goods"
        }
    ],
    "sg:phone":"+1 905 897 2333",
    "sg:postcode":"L4W 2R7",
    "sg:province":"ON",
    "sg:tags":[
        "equipment",
        "supply"
    ],
    "wof:name":"Gbs Barbecues Inc",
    "wof:placetype":"venue"
},
  "geometry": {"coordinates":[-79.643005,43.632442],"type":"Point"}
}