{
  "type": "Feature",
  "properties": {
    "addr:full":"143 Av Lambert Beauceville QC G5X 1T5",
    "addr:postcode":"g5x 1t5",
    "addr:street":"143 Av Lambert",
    "iso:country":"CA",
    "sg:address":"143 Av Lambert",
    "sg:city":"Beauceville",
    "sg:classifiers":[
        {
            "category":"Building & Trades",
            "subcategory":"Construction",
            "type":"Services"
        }
    ],
    "sg:phone":"+1 418 774 5329",
    "sg:postcode":"G5X 1T5",
    "sg:province":"QC",
    "sg:tags":[
        "paving",
        "contractor"
    ],
    "wof:name":"Pavages DE Beauce Ltee",
    "wof:placetype":"venue"
},
  "geometry": {"coordinates":[-70.804886,46.226566],"type":"Point"}
}