{
  "type": "Feature",
  "properties": {
    "addr:full":"6380 Hurontario St Mississauga ON L5W 1N3",
    "addr:housenumber":"6380",
    "addr:postcode":"l5w 1n3",
    "addr:street":"Hurontario St",
    "iso:country":"CA",
    "sg:address":"6380 Hurontario St",
    "sg:city":"Mississauga",
    "sg:classifiers":[
        {
            "category":"Recreation",
            "type":"Entertainment"
        }
    ],
    "sg:phone":"+1 905 564 3383",
    "sg:postcode":"L5W 1N3",
    "sg:province":"ON",
    "sg:tags":[
        "range",
        "practice",
        "golf"
    ],
    "wof:name":"Practice Tee",
    "wof:placetype":"venue"
},
  "geometry": {"coordinates":[-79.690246582,43.634021759],"type":"Point"}
}