{
  "type": "Feature",
  "properties": {
    "addr:full":"42 Northline Rd East York ON M4B 3E2",
    "addr:housenumber":"42",
    "addr:postcode":"m4b 3e2",
    "addr:street":"Northline Rd",
    "iso:country":"CA",
    "sg:address":"42 Northline Rd",
    "sg:city":"East York",
    "sg:classifiers":[
        {
            "category":"Manufacturing",
            "subcategory":"Building Materials",
            "type":"Manufacturing & Wholesale Goods"
        }
    ],
    "sg:phone":"+1 416 787 5015",
    "sg:postcode":"M4B 3E2",
    "sg:province":"ON",
    "sg:tags":[
        "concrete",
        "product"
    ],
    "wof:name":"Dufferin Manufacturing CO",
    "wof:placetype":"venue"
},
  "geometry": {"coordinates":[-79.31484985349999,43.7146835327],"type":"Point"}
}