{
  "type": "Feature",
  "properties": {
    "addr:full":"1035 Brant St # 10A Burlington ON L7R 4X6",
    "addr:housenumber":"1035;10a",
    "addr:postcode":"l7r 4x6",
    "addr:street":"Brant St #",
    "iso:country":"CA",
    "sg:address":"1035 Brant St # 10A",
    "sg:city":"Burlington",
    "sg:classifiers":[
        {
            "category":"Health Services",
            "subcategory":"Health Practitioner",
            "type":"Services"
        }
    ],
    "sg:phone":"+1 905 681 2388",
    "sg:postcode":"L7R 4X6",
    "sg:province":"ON",
    "sg:tags":[
        "homeopath"
    ],
    "wof:name":"Clinical Consultants",
    "wof:placetype":"venue"
},
  "geometry": {"coordinates":[-79.818321228,43.3391304016],"type":"Point"}
}