{
  "type": "Feature",
  "properties": {
    "addr:full":"177 Provost St New Glasgow NS B2H 2P8",
    "addr:housenumber":"177",
    "addr:postcode":"b2h 2p8",
    "addr:street":"Provost St",
    "iso:country":"CA",
    "sg:address":"177 Provost St",
    "sg:city":"New Glasgow",
    "sg:classifiers":[
        {
            "category":"Shopping",
            "subcategory":"Used Merchandise",
            "type":"Retail Goods"
        }
    ],
    "sg:phone":"+1 902 752 1804",
    "sg:postcode":"B2H 2P8",
    "sg:province":"NS",
    "sg:tags":[
        "clothing"
    ],
    "wof:name":"Salvation Army Thrift Store",
    "wof:placetype":"venue"
},
  "geometry": {"coordinates":[-62.645466,45.586826],"type":"Point"}
}