{
  "type": "Feature",
  "properties": {
    "addr:full":"761 4E Rue Iberville QC J2X 3N8",
    "addr:housenumber":"761",
    "addr:postcode":"j2x 3n8",
    "addr:street":"4E Rue Iberville",
    "iso:country":"CA",
    "sg:address":"761 4E Rue",
    "sg:city":"Iberville",
    "sg:classifiers":[
        {
            "category":"Manufacturing",
            "subcategory":"Metals",
            "type":"Manufacturing & Wholesale Goods"
        }
    ],
    "sg:phone":"+1 450 346 1566",
    "sg:postcode":"J2X 3N8",
    "sg:province":"QC",
    "sg:tags":[
        "solder",
        "welding"
    ],
    "wof:name":"Creation Harvey Metal",
    "wof:placetype":"venue"
},
  "geometry": {"coordinates":[-73.238297,45.305237],"type":"Point"}
}