{
  "type": "Feature",
  "properties": {
    "iso:country":"CA",
    "sg:address":"573 90E Rue",
    "sg:city":"Saint-Georges",
    "sg:classifiers":[
        {
            "category":"Shopping",
            "subcategory":"Computers & Home Electronics",
            "type":"Retail Goods"
        }
    ],
    "sg:phone":"+1 418 228 2676",
    "sg:postcode":"G5Y 3L1",
    "sg:province":"QC",
    "sg:tags":[
        "equipment",
        "electronic",
        "telephone",
        "cellular"
    ],
    "wof:name":"Dumoulin-Electronique",
    "wof:placetype":"venue"
},
  "geometry": {"coordinates":[-70.69329071040001,46.1325454712],"type":"Point"}
}