{
  "type": "Feature",
  "properties": {
    "iso:country":"CA",
    "sg:address":"1190 Boul Des Seigneurs",
    "sg:city":"Terrebonne",
    "sg:classifiers":[
        {
            "category":"Shopping",
            "subcategory":"Florist",
            "type":"Retail Goods"
        }
    ],
    "sg:phone":"+1 450 471 0193",
    "sg:postcode":"J6W 3W4",
    "sg:province":"QC",
    "wof:name":"Fleuriste Des Seigneurs Inc",
    "wof:placetype":"venue"
},
  "geometry": {"coordinates":[-73.6464004517,45.7001800537],"type":"Point"}
}