{
  "type": "Feature",
  "properties": {
    "addr:full":"Kinmount ON K0M 2A0",
    "addr:postcode":"k0m 2a0",
    "iso:country":"CA",
    "sg:city":"Kinmount",
    "sg:classifiers":[
        {
            "category":"Restaurant",
            "type":"Food & Drink"
        }
    ],
    "sg:phone":"+1 705 488 2683",
    "sg:postcode":"K0M 2A0",
    "sg:province":"ON",
    "wof:name":"Kinvale Restaurant",
    "wof:placetype":"venue"
},
  "geometry": {"coordinates":[-78.65147399999999,44.780891],"type":"Point"}
}