{
  "type": "Feature",
  "properties": {
    "addr:full":"530 Railway Ave Radville SK S0C 2G0",
    "addr:housenumber":"530",
    "addr:postcode":"s0c 2g0",
    "addr:street":"Railway Ave",
    "iso:country":"CA",
    "sg:address":"530 Railway Ave",
    "sg:city":"Radville",
    "sg:classifiers":[
        {
            "category":"Building & Trades",
            "subcategory":"Construction",
            "type":"Services"
        }
    ],
    "sg:phone":"+1 306 869 2585",
    "sg:postcode":"S0C 2G0",
    "sg:province":"SK",
    "sg:tags":[
        "sand",
        "gravel",
        "excavating",
        "contractor"
    ],
    "wof:name":"Larsens' Cst & Redi-Mix",
    "wof:placetype":"venue"
},
  "geometry": {"coordinates":[-104.294662,49.460075],"type":"Point"}
}