{
  "type": "Feature",
  "properties": {
    "addr:full":"54505 Range Rd 242 RR 4 Namao AB T0A 2N0",
    "addr:housenumber":"54505;242",
    "addr:postcode":"t0a 2n0",
    "addr:street":"Range Rd;Rr 4 Namao",
    "iso:country":"CA",
    "sg:address":"54505 Range Rd 242 RR 4",
    "sg:city":"Namao",
    "sg:classifiers":[
        {
            "category":"Shopping",
            "subcategory":"Clothing, Apparel, & Fashions",
            "type":"Retail Goods"
        }
    ],
    "sg:phone":"+1 780 973 5343",
    "sg:postcode":"T0A 2N0",
    "sg:province":"AB",
    "sg:tags":[
        "tailor"
    ],
    "wof:name":"Vicki Lynn Enterprises",
    "wof:placetype":"venue"
},
  "geometry": {"coordinates":[-113.442413,53.708344],"type":"Point"}
}