{
  "type": "Feature",
  "properties": {
    "addr:full":"1525 Boul Louis-Frechette Nicolet QC J3T 1M3",
    "addr:housenumber":"1525",
    "addr:postcode":"j3t 1m3",
    "addr:street":"Boul Louis-Frechette",
    "iso:country":"CA",
    "sg:address":"1525 Boul Louis-Frechette",
    "sg:city":"Nicolet",
    "sg:classifiers":[
        {
            "category":"Health Services",
            "subcategory":"Doctor",
            "type":"Services"
        }
    ],
    "sg:phone":"+1 819 293 8033",
    "sg:postcode":"J3T 1M3",
    "sg:province":"QC",
    "sg:tags":[
        "dentist"
    ],
    "wof:name":"Centre Dentaire",
    "wof:placetype":"venue"
},
  "geometry": {"coordinates":[-72.605011,46.236969],"type":"Point"}
}