{
  "type": "Feature",
  "properties": {
    "addr:full":"563 Mccallum Rd Abbotsford BC V2S 8A1",
    "addr:housenumber":"563",
    "addr:postcode":"v2s 8a1",
    "addr:street":"Mccallum Rd",
    "iso:country":"CA",
    "sg:address":"563 Mccallum Rd",
    "sg:city":"Abbotsford",
    "sg:classifiers":[
        {
            "category":"Building & Trades",
            "subcategory":"Landscaping Services",
            "type":"Services"
        }
    ],
    "sg:phone":"+1 604 853 4610",
    "sg:postcode":"V2S 8A1",
    "sg:province":"BC",
    "sg:tags":[
        "landscape",
        "contractor"
    ],
    "wof:name":"Eastbridge Landscaping",
    "wof:placetype":"venue"
},
  "geometry": {"coordinates":[-122.293663,49.012665],"type":"Point"}
}