{
  "type": "Feature",
  "properties": {
    "iso:country":"CA",
    "sg:address":"2000 Thurston Dr # 35B",
    "sg:city":"Ottawa",
    "sg:classifiers":[
        {
            "category":"Building & Trades",
            "subcategory":"Construction",
            "type":"Services"
        }
    ],
    "sg:phone":"+1 613 228 9663",
    "sg:postcode":"K1G 4K7",
    "sg:province":"ON",
    "sg:tags":[
        "resurfacing",
        "laying",
        "refinishing",
        "floor"
    ],
    "wof:name":"M Floors",
    "wof:placetype":"venue"
},
  "geometry": {"coordinates":[-75.6234054565,45.3786888123],"type":"Point"}
}