{
  "type": "Feature",
  "properties": {
    "addr:full":"Surrey BC V3W 3N4",
    "addr:postcode":"v3w 3n4",
    "iso:country":"CA",
    "sg:city":"Surrey",
    "sg:classifiers":[
        {
            "category":"Manufacturing",
            "subcategory":"Printing",
            "type":"Manufacturing & Wholesale Goods"
        }
    ],
    "sg:phone":"+1 604 592 2233",
    "sg:postcode":"V3W 3N4",
    "sg:province":"BC",
    "sg:tags":[
        "newspaper"
    ],
    "wof:name":"Apna Media Group Inc",
    "wof:placetype":"venue"
},
  "geometry": {"coordinates":[-122.890244,49.155022],"type":"Point"}
}