{
  "type": "Feature",
  "properties": {
    "iso:country":"CA",
    "sg:address":"850 Rue DE Puyjalon",
    "sg:city":"Baie-Comeau",
    "sg:classifiers":[
        {
            "category":"Shopping",
            "subcategory":"Used Merchandise",
            "type":"Retail Goods"
        }
    ],
    "sg:phone":"+1 418 589 7881",
    "sg:postcode":"G5C 1N1",
    "sg:province":"QC",
    "sg:tags":[
        "clothing"
    ],
    "wof:name":"Depannage DE L'Anse Inc",
    "wof:placetype":"venue"
},
  "geometry": {"coordinates":[-68.25778961180001,49.1919746399],"type":"Point"}
}