{
  "type": "Feature",
  "properties": {
    "addr:full":"461 Rue Labelle Saint-Jerome QC J7Z 5L4",
    "addr:housenumber":"461",
    "addr:postcode":"j7z 5l4",
    "addr:street":"Rue Labelle Saint-Jerome",
    "iso:country":"CA",
    "sg:address":"461 Rue Labelle",
    "sg:city":"Saint-Jerome",
    "sg:classifiers":[
        {
            "category":"Food & Beverages",
            "subcategory":"Liquor & Beverages",
            "type":"Retail Goods"
        }
    ],
    "sg:phone":"+1 450 438 3755",
    "sg:postcode":"J7Z 5L4",
    "sg:province":"QC",
    "sg:tags":[
        "store"
    ],
    "wof:name":"Saq",
    "wof:placetype":"venue"
},
  "geometry": {"coordinates":[-74.0032653809,45.7800941467],"type":"Point"}
}