{
  "type": "Feature",
  "properties": {
    "addr:full":"33 King St W Cobourg ON K9A 2M1",
    "addr:housenumber":"33",
    "addr:postcode":"k9a 2m1",
    "addr:street":"King St W",
    "iso:country":"CA",
    "sg:address":"33 King St W",
    "sg:city":"Cobourg",
    "sg:classifiers":[
        {
            "category":"Shopping",
            "subcategory":"Shoes",
            "type":"Retail Goods"
        }
    ],
    "sg:phone":"+1 905 372 9464",
    "sg:postcode":"K9A 2M1",
    "sg:province":"ON",
    "wof:name":"Beebe Boot Shop Ltd",
    "wof:placetype":"venue"
},
  "geometry": {"coordinates":[-78.166634,43.959587],"type":"Point"}
}