{
  "type": "Feature",
  "properties": {
    "addr:full":"Hwy 1 Virden MB R0M 2C0",
    "addr:postcode":"r0m 2c0",
    "addr:street":"Hwy 1 Virden",
    "iso:country":"CA",
    "sg:address":"Hwy 1",
    "sg:city":"Virden",
    "sg:classifiers":[
        {
            "category":"Restaurant",
            "type":"Food & Drink"
        }
    ],
    "sg:phone":"+1 204 748 6698",
    "sg:postcode":"R0M 2C0",
    "sg:province":"MB",
    "wof:name":"Subway Sandwiches & Salads",
    "wof:placetype":"venue"
},
  "geometry": {"coordinates":[-100.919120789,49.8558540344],"type":"Point"}
}