{
  "type": "Feature",
  "properties": {
    "iso:country":"CA",
    "sg:address":"69 Dundas St E",
    "sg:city":"Belleville",
    "sg:classifiers":[
        {
            "category":"Shopping",
            "type":"Retail Goods"
        }
    ],
    "sg:phone":"+1 613 968 4684",
    "sg:postcode":"K8N 1B9",
    "sg:province":"ON",
    "sg:tags":[
        "equipment",
        "wine",
        "supply"
    ],
    "wof:name":"Brew Jays",
    "wof:placetype":"venue"
},
  "geometry": {"coordinates":[-77.3791732788,44.1614990234],"type":"Point"}
}