{
  "type": "Feature",
  "properties": {
    "addr:full":"2075 Wyandotte St W Windsor ON N9B 1J8",
    "addr:housenumber":"2075",
    "addr:postcode":"n9b 1j8",
    "addr:street":"Wyandotte St W",
    "iso:country":"CA",
    "sg:address":"2075 Wyandotte St W",
    "sg:city":"Windsor",
    "sg:classifiers":[
        {
            "category":"Food & Beverages",
            "subcategory":"Groceries & Convenience Stores",
            "type":"Retail Goods"
        }
    ],
    "sg:phone":"+1 519 258 1882",
    "sg:postcode":"N9B 1J8",
    "sg:province":"ON",
    "sg:tags":[
        "grocer"
    ],
    "wof:name":"Wingli Oriental Food & Grocery",
    "wof:placetype":"venue"
},
  "geometry": {"coordinates":[-83.059692,42.305965],"type":"Point"}
}