{
  "type": "Feature",
  "properties": {
    "addr:full":"Toronto ON M5C 2X8",
    "addr:postcode":"m5c 2x8",
    "iso:country":"CA",
    "sg:city":"Toronto",
    "sg:classifiers":[
        {
            "category":"Organizations",
            "subcategory":"Professional Association",
            "type":"Services"
        }
    ],
    "sg:phone":"+1 416 362 1969",
    "sg:postcode":"M5C 2X8",
    "sg:province":"ON",
    "wof:name":"Prospectors & Developers Assn",
    "wof:placetype":"venue"
},
  "geometry": {"coordinates":[-79.3766174316,43.6495246887],"type":"Point"}
}