{
  "type": "Feature",
  "properties": {
    "addr:full":"175 Argyle St S Renfrew ON K7V 1T6",
    "addr:housenumber":"175",
    "addr:postcode":"k7v 1t6",
    "addr:street":"Argyle St S",
    "iso:country":"CA",
    "sg:address":"175 Argyle St S",
    "sg:city":"Renfrew",
    "sg:classifiers":[
        {
            "category":"Health Services",
            "subcategory":"Doctor",
            "type":"Services"
        }
    ],
    "sg:phone":"+1 613 432 6596",
    "sg:postcode":"K7V 1T6",
    "sg:province":"ON",
    "sg:tags":[
        "physician",
        "surgeon"
    ],
    "wof:name":"Kidd, Robert F MD",
    "wof:placetype":"venue"
},
  "geometry": {"coordinates":[-76.685059,45.47176],"type":"Point"}
}