{
  "type": "Feature",
  "properties": {
    "addr:full":"1770 Market St Halifax NS B3J 3M3",
    "addr:housenumber":"1770",
    "addr:postcode":"ns b3j 3m3",
    "addr:street":"Market St",
    "iso:country":"CA",
    "sg:address":"1770 Market St",
    "sg:city":"Halifax",
    "sg:classifiers":[
        {
            "category":"Restaurant",
            "type":"Food & Drink"
        }
    ],
    "sg:phone":"+1 902 425 5779",
    "sg:postcode":"B3J 3M3",
    "sg:province":"NS",
    "sg:tags":[
        "shop",
        "coffee"
    ],
    "wof:name":"Coffee Corner",
    "wof:placetype":"venue"
},
  "geometry": {"coordinates":[-63.576538,44.647324],"type":"Point"}
}