{
  "type": "Feature",
  "properties": {
    "iso:country":"CA",
    "sg:address":"5889 Victoria Dr",
    "sg:city":"Vancouver",
    "sg:classifiers":[
        {
            "category":"Food & Beverages",
            "subcategory":"Fruits & Vegetables",
            "type":"Retail Goods"
        }
    ],
    "sg:phone":"+1 604 327 1814",
    "sg:postcode":"V5P 3W5",
    "sg:province":"BC",
    "sg:tags":[
        "produce"
    ],
    "wof:name":"Consumers Food Market",
    "wof:placetype":"venue"
},
  "geometry": {"coordinates":[-123.06578064,49.2307395935],"type":"Point"}
}