{
  "type": "Feature",
  "properties": {
    "iso:country":"CA",
    "sg:city":"Humboldt",
    "sg:classifiers":[
        {
            "category":"Manufacturing",
            "subcategory":"Tools & Machinery",
            "type":"Manufacturing & Wholesale Goods"
        }
    ],
    "sg:phone":"+1 306 682 0738",
    "sg:postcode":"S0K 2A0",
    "sg:province":"SK",
    "sg:tags":[
        "farm",
        "agricultural",
        "implement",
        "supply"
    ],
    "wof:name":"Kmk Sales",
    "wof:placetype":"venue"
},
  "geometry": {"coordinates":[-105.122940063,52.1973686218],"type":"Point"}
}