{
  "type": "Feature",
  "properties": {
    "iso:country":"CA",
    "sg:address":"1783 Marine Dr",
    "sg:city":"West Vancouver",
    "sg:classifiers":[
        {
            "category":"Restaurant",
            "type":"Food & Drink"
        }
    ],
    "sg:phone":"+1 604 926 6113",
    "sg:postcode":"V7V 1J5",
    "sg:province":"BC",
    "wof:name":"Kfc",
    "wof:placetype":"venue"
},
  "geometry": {"coordinates":[-123.161766052,49.3288154602],"type":"Point"}
}