{
  "type": "Feature",
  "properties": {
    "iso:country":"CA",
    "sg:address":"Hwy 19 S",
    "sg:city":"Central Butte",
    "sg:classifiers":[
        {
            "category":"Retail",
            "subcategory":"Auto Repair",
            "type":"Services"
        }
    ],
    "sg:phone":"+1 306 796 4787",
    "sg:postcode":"S0H 0T0",
    "sg:province":"SK",
    "sg:tags":[
        "repairing",
        "automobile"
    ],
    "wof:name":"Hawk's Auto Supplies",
    "wof:placetype":"venue"
},
  "geometry": {"coordinates":[-106.503311157,50.8050193787],"type":"Point"}
}