{
  "type": "Feature",
  "properties": {
    "iso:country":"CA",
    "sg:city":"Cabano",
    "sg:classifiers":[
        {
            "category":"Building & Trades",
            "subcategory":"Electrical",
            "type":"Services"
        }
    ],
    "sg:phone":"+1 418 854 2531",
    "sg:postcode":"G0L 1E0",
    "sg:province":"QC",
    "sg:tags":[
        "electric",
        "contractor"
    ],
    "wof:name":"Electricite Cle Mar Inc",
    "wof:placetype":"venue"
},
  "geometry": {"coordinates":[-68.8815460205,47.680809021],"type":"Point"}
}