{
  "type": "Feature",
  "properties": {
    "addr:full":"1 Newcastle Ave Nanaimo BC V9S 4H6",
    "addr:housenumber":"1",
    "addr:postcode":"v9s 4h6",
    "addr:street":"Newcastle Ave",
    "iso:country":"CA",
    "sg:address":"1 Newcastle Ave",
    "sg:city":"Nanaimo",
    "sg:classifiers":[
        {
            "category":"Retail",
            "subcategory":"Funeral Services",
            "type":"Services"
        }
    ],
    "sg:phone":"+1 250 753 2032",
    "sg:postcode":"V9S 4H6",
    "sg:province":"BC",
    "sg:tags":[
        "director"
    ],
    "wof:name":"Sands Funeral Chapel",
    "wof:placetype":"venue"
},
  "geometry": {"coordinates":[-123.942100525,49.1720466614],"type":"Point"}
}