{
  "type": "Feature",
  "properties": {
    "addr:full":"3164 Yonge St Toronto ON M4N 2K6",
    "addr:housenumber":"3164",
    "addr:postcode":"m4n 2k6",
    "addr:street":"Yonge St",
    "iso:country":"CA",
    "sg:address":"3164 Yonge St",
    "sg:city":"Toronto",
    "sg:classifiers":[
        {
            "category":"Professional",
            "subcategory":"Accounting & Tax Preparation",
            "type":"Services"
        }
    ],
    "sg:phone":"+1 416 250 6557",
    "sg:postcode":"M4N 2K6",
    "sg:province":"ON",
    "sg:tags":[
        "accountant"
    ],
    "wof:name":"Stastny & CO",
    "wof:placetype":"venue"
},
  "geometry": {"coordinates":[-79.4029083252,43.7271537781],"type":"Point"}
}