{
  "type": "Feature",
  "properties": {
    "addr:full":"2109 Yonge St Toronto ON M4S 2A4",
    "addr:housenumber":"2109",
    "addr:postcode":"m4s 2a4",
    "addr:street":"Yonge St",
    "iso:country":"CA",
    "sg:address":"2109 Yonge St",
    "sg:city":"Toronto",
    "sg:classifiers":[
        {
            "category":"Home & Garden",
            "subcategory":"Home Furnishings",
            "type":"Retail Goods"
        }
    ],
    "sg:phone":"+1 416 480 2273",
    "sg:postcode":"M4S 2A4",
    "sg:province":"ON",
    "sg:tags":[
        "linen"
    ],
    "wof:name":"Linen Centre",
    "wof:placetype":"venue"
},
  "geometry": {"coordinates":[-79.3974304199,43.7031440735],"type":"Point"}
}