{
  "type": "Feature",
  "properties": {
    "iso:country":"CA",
    "sg:city":"Vancouver",
    "sg:classifiers":[
        {
            "category":"Insurance",
            "subcategory":"Insurance Agent",
            "type":"Services"
        }
    ],
    "sg:phone":"+1 604 683 3692",
    "sg:postcode":"V6Z 2E8",
    "sg:province":"BC",
    "wof:name":"Interco Insurance Ltd",
    "wof:placetype":"venue"
},
  "geometry": {"coordinates":[-123.128342,49.279427],"type":"Point"}
}