{
  "type": "Feature",
  "properties": {
    "iso:country":"CA",
    "sg:address":"107 12th St E",
    "sg:city":"North Vancouver",
    "sg:classifiers":[
        {
            "category":"Restaurant",
            "type":"Food & Drink"
        }
    ],
    "sg:phone":"+1 604 987 5622",
    "sg:postcode":"V7L 2J3",
    "sg:province":"BC",
    "wof:name":"Colosseum Pizza & Steak House",
    "wof:placetype":"venue"
},
  "geometry": {"coordinates":[-123.071899414,49.3187980652],"type":"Point"}
}