{
  "type": "Feature",
  "properties": {
    "addr:full":"66 Welham Rd Barrie ON L4N 8Y4",
    "addr:housenumber":"66",
    "addr:postcode":"l4n 8y4",
    "addr:street":"Welham Rd",
    "iso:country":"CA",
    "sg:address":"66 Welham Rd",
    "sg:city":"Barrie",
    "sg:classifiers":[
        {
            "category":"Wholesale",
            "subcategory":"Farm Supplies",
            "type":"Manufacturing & Wholesale Goods"
        }
    ],
    "sg:phone":"+1 705 728 8700",
    "sg:postcode":"L4N 8Y4",
    "sg:province":"ON",
    "sg:tags":[
        "feed"
    ],
    "wof:name":"Northern Feeds Ltd",
    "wof:placetype":"venue"
},
  "geometry": {"coordinates":[-79.6735839844,44.3561325073],"type":"Point"}
}