{
  "type": "Feature",
  "properties": {
    "iso:country":"CA",
    "sg:city":"Edmonton",
    "sg:classifiers":[
        {
            "category":"Professional",
            "subcategory":"Business Services",
            "type":"Services"
        }
    ],
    "sg:phone":"+1 780 423 3228",
    "sg:postcode":"T5H 4J1",
    "sg:province":"AB",
    "sg:tags":[
        "license"
    ],
    "wof:name":"Quality Registries",
    "wof:placetype":"venue"
},
  "geometry": {"coordinates":[-113.488311768,53.5488014221],"type":"Point"}
}