{
  "type": "Feature",
  "properties": {
    "iso:country":"CA",
    "sg:city":"Dartmouth",
    "sg:classifiers":[
        {
            "category":"Professional",
            "subcategory":"Lawyer & Legal Services",
            "type":"Services"
        }
    ],
    "sg:phone":"+1 902 469 9500",
    "sg:postcode":"B2Y 2N4",
    "sg:province":"NS",
    "sg:tags":[
        "attorney"
    ],
    "wof:name":"Moors, Jeffrey S",
    "wof:placetype":"venue"
},
  "geometry": {"coordinates":[-63.5703582764,44.6658554077],"type":"Point"}
}