{
  "type": "Feature",
  "properties": {
    "iso:country":"CA",
    "sg:address":"355 Admiral Blvd",
    "sg:city":"Mississauga",
    "sg:classifiers":[
        {
            "category":"Building & Trades",
            "subcategory":"Plumbing",
            "type":"Services"
        }
    ],
    "sg:phone":"+1 905 565 6042",
    "sg:postcode":"L5T 2N1",
    "sg:province":"ON",
    "sg:tags":[
        "mechanical",
        "contractor"
    ],
    "wof:name":"Webber Mechanical",
    "wof:placetype":"venue"
},
  "geometry": {"coordinates":[-79.69473266599999,43.6496009827],"type":"Point"}
}