{
  "type": "Feature",
  "properties": {
    "addr:full":"1311 Main St Geraldton ON P0T 1M0",
    "addr:housenumber":"1311",
    "addr:postcode":"p0t 1m0",
    "addr:street":"Main St",
    "iso:country":"CA",
    "sg:address":"1311 Main St",
    "sg:city":"Geraldton",
    "sg:classifiers":[
        {
            "category":"Professional",
            "subcategory":"Management & Consulting",
            "type":"Services"
        }
    ],
    "sg:phone":"+1 807 854 1722",
    "sg:postcode":"P0T 1M0",
    "sg:province":"ON",
    "sg:tags":[
        "consultant",
        "business"
    ],
    "wof:name":"Gord Furlong Consolidated Ents",
    "wof:placetype":"venue"
},
  "geometry": {"coordinates":[-86.95291899999999,49.708324],"type":"Point"}
}