{
  "type": "Feature",
  "properties": {
    "iso:country":"CA",
    "sg:address":"2421 Holly Lane",
    "sg:city":"Ottawa",
    "sg:classifiers":[
        {
            "category":"Manufacturing",
            "subcategory":"Tools & Machinery",
            "type":"Manufacturing & Wholesale Goods"
        }
    ],
    "sg:phone":"+1 613 526 0435",
    "sg:postcode":"K1V 7P2",
    "sg:province":"ON",
    "sg:tags":[
        "fire",
        "extinguisher",
        "recorder",
        "time"
    ],
    "wof:name":"Simplex Grinnell",
    "wof:placetype":"venue"
},
  "geometry": {"coordinates":[-75.6387634277,45.3791122437],"type":"Point"}
}