{
  "type": "Feature",
  "properties": {
    "addr:full":"1315 Strathcona St Winnipeg MB R3E 2Y4",
    "addr:housenumber":"1315",
    "addr:postcode":"r3e 2y4",
    "addr:street":"Strathcona St",
    "iso:country":"CA",
    "sg:address":"1315 Strathcona St",
    "sg:city":"Winnipeg",
    "sg:classifiers":[
        {
            "category":"Organizations",
            "subcategory":"Professional Association",
            "type":"Services"
        }
    ],
    "sg:phone":"+1 204 783 7340",
    "sg:postcode":"R3E 2Y4",
    "sg:province":"MB",
    "sg:tags":[
        "club"
    ],
    "wof:name":"Clifton Community Club",
    "wof:placetype":"venue"
},
  "geometry": {"coordinates":[-97.189804,49.901176],"type":"Point"}
}