{
  "type": "Feature",
  "properties": {
    "addr:full":"15 Colborne St Fenelon Falls ON K0M 1N0",
    "addr:housenumber":"15",
    "addr:postcode":"k0m 1n0",
    "addr:street":"Colborne St",
    "iso:country":"CA",
    "sg:address":"15 Colborne St",
    "sg:city":"Fenelon Falls",
    "sg:classifiers":[
        {
            "category":"Restaurant",
            "type":"Food & Drink"
        }
    ],
    "sg:phone":"+1 705 887 2432",
    "sg:postcode":"K0M 1N0",
    "sg:province":"ON",
    "wof:name":"Sun Ming Restaurant",
    "wof:placetype":"venue"
},
  "geometry": {"coordinates":[-78.736847,44.536495],"type":"Point"}
}