{
  "type": "Feature",
  "properties": {
    "iso:country":"CA",
    "sg:address":"6666 Av Lamont",
    "sg:city":"Montreal",
    "sg:classifiers":[
        {
            "category":"Building & Trades",
            "subcategory":"Landscaping Services",
            "type":"Services"
        }
    ],
    "sg:phone":"+1 514 766 8390",
    "sg:postcode":"H4E 2T7",
    "sg:province":"QC",
    "sg:tags":[
        "landscape",
        "contractor"
    ],
    "wof:name":"Paysagiste Robert Caucci Inc",
    "wof:placetype":"venue"
},
  "geometry": {"coordinates":[-73.603218,45.450466],"type":"Point"}
}