{
  "type": "Feature",
  "properties": {
    "addr:full":"109 Rue Champlain Salaberry-DE-Valleyfield QC J6T 1W9",
    "addr:housenumber":"109",
    "addr:postcode":"j6t 1w9",
    "addr:street":"Rue Champlain",
    "iso:country":"CA",
    "sg:address":"109 Rue Champlain",
    "sg:city":"Salaberry-DE-Valleyfield",
    "sg:classifiers":[
        {
            "category":"Shopping",
            "subcategory":"Stationery & Office Supplies",
            "type":"Retail Goods"
        }
    ],
    "sg:phone":"+1 450 373 4544",
    "sg:postcode":"J6T 1W9",
    "sg:province":"QC",
    "sg:tags":[
        "stationer"
    ],
    "wof:name":"Librairie Jamunik Enrg",
    "wof:placetype":"venue"
},
  "geometry": {"coordinates":[-74.13005800000001,45.254597],"type":"Point"}
}