{
  "type": "Feature",
  "properties": {
    "addr:full":"36083 97th St Oliver BC V0H 1T0",
    "addr:housenumber":"36083",
    "addr:postcode":"bc v0h 1t0",
    "addr:street":"97Th St",
    "iso:country":"CA",
    "sg:address":"36083 97th St",
    "sg:city":"Oliver",
    "sg:classifiers":[
        {
            "category":"Manufacturing",
            "subcategory":"Printing",
            "type":"Manufacturing & Wholesale Goods"
        }
    ],
    "sg:phone":"+1 250 498 4006",
    "sg:postcode":"V0H 1T0",
    "sg:province":"BC",
    "sg:tags":[
        "printer"
    ],
    "wof:name":"Oliver Printing",
    "wof:placetype":"venue"
},
  "geometry": {"coordinates":[-119.550209,49.184727],"type":"Point"}
}