{
  "type": "Feature",
  "properties": {
    "addr:full":"2 Howey Bay Rd Red Lake ON P0V 2M0",
    "addr:housenumber":"2",
    "addr:postcode":"p0v 2m0",
    "addr:street":"Howey Bay Rd",
    "iso:country":"CA",
    "sg:address":"2 Howey Bay Rd",
    "sg:city":"Red Lake",
    "sg:classifiers":[
        {
            "category":"Health Services",
            "subcategory":"Optometrist",
            "type":"Services"
        }
    ],
    "sg:phone":"+1 807 727 2849",
    "sg:postcode":"P0V 2M0",
    "sg:province":"ON",
    "wof:name":"Chapman, Paul OD",
    "wof:placetype":"venue"
},
  "geometry": {"coordinates":[-93.818611,51.018028],"type":"Point"}
}