{
  "type": "Feature",
  "properties": {
    "addr:full":"2425 Townline Rd Abbotsford BC V2T 6L6",
    "addr:housenumber":"2425",
    "addr:postcode":"v2t 6l6",
    "addr:street":"Townline Rd",
    "iso:country":"CA",
    "sg:address":"2425 Townline Rd",
    "sg:city":"Abbotsford",
    "sg:classifiers":[
        {
            "category":"Wholesale",
            "subcategory":"Farm Supplies",
            "type":"Manufacturing & Wholesale Goods"
        }
    ],
    "sg:phone":"+1 604 850 1108",
    "sg:postcode":"V2T 6L6",
    "sg:province":"BC",
    "sg:tags":[
        "feed"
    ],
    "wof:name":"Clearbrook Grain & Milling CO",
    "wof:placetype":"venue"
},
  "geometry": {"coordinates":[-122.360268,49.046532],"type":"Point"}
}