{
  "type": "Feature",
  "properties": {
    "addr:full":"2207 Millstream Rd Victoria BC V9B 6H4",
    "addr:housenumber":"2207",
    "addr:postcode":"v9b 6h4",
    "addr:street":"Millstream Rd",
    "iso:country":"CA",
    "sg:address":"2207 Millstream Rd",
    "sg:city":"Victoria",
    "sg:classifiers":[
        {
            "category":"Organizations",
            "subcategory":"Religious Organization",
            "type":"Services"
        }
    ],
    "sg:phone":"+1 250 474 8875",
    "sg:postcode":"V9B 6H4",
    "sg:province":"BC",
    "sg:tags":[
        "church"
    ],
    "wof:name":"Westshore Alliance Church",
    "wof:placetype":"venue"
},
  "geometry": {"coordinates":[-123.364517212,48.428314209],"type":"Point"}
}