{
  "type": "Feature",
  "properties": {
    "addr:full":"96 1st St SW Teulon MB R0C 3B0",
    "addr:housenumber":"96",
    "addr:postcode":"r0c 3b0",
    "addr:street":"1St St Sw",
    "iso:country":"CA",
    "sg:address":"96 1st St SW",
    "sg:city":"Teulon",
    "sg:classifiers":[
        {
            "category":"Freight",
            "type":"Transportation"
        }
    ],
    "sg:phone":"+1 204 886 2607",
    "sg:postcode":"R0C 3B0",
    "sg:province":"MB",
    "sg:tags":[
        "grain",
        "elevator"
    ],
    "wof:name":"N M Paterson & Sons Ltd",
    "wof:placetype":"venue"
},
  "geometry": {"coordinates":[-97.26309204099999,50.3857460022],"type":"Point"}
}