{
  "type": "Feature",
  "properties": {
    "addr:full":"Regina SK S4P 2J6",
    "addr:postcode":"s4p 2j6",
    "iso:country":"CA",
    "sg:city":"Regina",
    "sg:classifiers":[
        {
            "category":"Government",
            "subcategory":"Office",
            "type":"Public Place"
        }
    ],
    "sg:phone":"+1 306 780 5401",
    "sg:postcode":"S4P 2J6",
    "sg:province":"SK",
    "wof:name":"Canada Legal Surveys Div",
    "wof:placetype":"venue"
},
  "geometry": {"coordinates":[-104.610984802,50.4437217712],"type":"Point"}
}