{
  "type": "Feature",
  "properties": {
    "addr:full":"51 Rue Saint-Pierre Saint-Chrysostome QC J0S 1R0",
    "addr:housenumber":"51",
    "addr:postcode":"j0s 1r0",
    "addr:street":"Rue Saint-Pierre",
    "iso:country":"CA",
    "sg:address":"51 Rue Saint-Pierre",
    "sg:city":"Saint-Chrysostome",
    "sg:classifiers":[
        {
            "category":"Education",
            "subcategory":"School",
            "type":"Public Place"
        }
    ],
    "sg:phone":"+1 450 826 3134",
    "sg:postcode":"J0S 1R0",
    "sg:province":"QC",
    "wof:name":"St-Joseph Ecole",
    "wof:placetype":"venue"
},
  "geometry": {"coordinates":[-73.75784299999999,45.103832],"type":"Point"}
}