{
  "type": "Feature",
  "properties": {
    "iso:country":"CA",
    "sg:address":"66 Pond Rd",
    "sg:city":"Rocky Harbour",
    "sg:classifiers":[
        {
            "category":"Travel",
            "subcategory":"Hotels & Motels",
            "type":"Entertainment"
        }
    ],
    "sg:phone":"+1 709 458 2225",
    "sg:postcode":"A0K 4N0",
    "sg:province":"NL",
    "sg:tags":[
        "breakfast",
        "accommodation",
        "bed"
    ],
    "wof:name":"Adam's Bed & Breakfast",
    "wof:placetype":"venue"
},
  "geometry": {"coordinates":[-57.9127807617,49.5939064026],"type":"Point"}
}