{
  "type": "Feature",
  "properties": {
    "iso:country":"CA",
    "sg:city":"Maple Ridge",
    "sg:classifiers":[
        {
            "category":"Education",
            "subcategory":"Special Training",
            "type":"Public Place"
        }
    ],
    "sg:phone":"+1 604 463 7329",
    "sg:postcode":"V2X 7X7",
    "sg:province":"BC",
    "sg:tags":[
        "tutoring"
    ],
    "wof:name":"Sylvan Learning Ctr",
    "wof:placetype":"venue"
},
  "geometry": {"coordinates":[-122.59965515099999,49.2206382751],"type":"Point"}
}