{
  "type": "Feature",
  "properties": {
    "addr:full":"600 Hespeler Rd Cambridge ON N1R 8H2",
    "addr:housenumber":"600",
    "addr:postcode":"n1r 8h2",
    "addr:street":"Hespeler Rd",
    "iso:country":"CA",
    "sg:address":"600 Hespeler Rd",
    "sg:city":"Cambridge",
    "sg:classifiers":[
        {
            "category":"Banks & Credit Unions",
            "subcategory":"Bank",
            "type":"Services"
        }
    ],
    "sg:phone":"+1 519 624 1200",
    "sg:postcode":"N1R 8H2",
    "sg:province":"ON",
    "wof:name":"Bank of Montreal",
    "wof:placetype":"venue"
},
  "geometry": {"coordinates":[-80.327156,43.404247],"type":"Point"}
}