{
  "type": "Feature",
  "properties": {
    "addr:full":"2431 St Jean Blvd Saint-Maurice QC G0X 2X0",
    "addr:housenumber":"2431",
    "addr:postcode":"g0x 2x0",
    "addr:street":"St Jean Blvd",
    "iso:country":"CA",
    "sg:address":"2431 St Jean Blvd",
    "sg:city":"Saint-Maurice",
    "sg:classifiers":[
        {
            "category":"Government",
            "subcategory":"Office",
            "type":"Public Place"
        }
    ],
    "sg:phone":"+1 819 373 7188",
    "sg:postcode":"G0X 2X0",
    "sg:province":"QC",
    "sg:tags":[
        "village"
    ],
    "wof:name":"St-Maurice Salle Municipalite",
    "wof:placetype":"venue"
},
  "geometry": {"coordinates":[-72.532455,46.468105],"type":"Point"}
}