{
  "type": "Feature",
  "properties": {
    "addr:full":"Toronto ON M5T 3B3",
    "addr:postcode":"m5t 3b3",
    "iso:country":"CA",
    "sg:city":"Toronto",
    "sg:classifiers":[
        {
            "category":"Shopping",
            "subcategory":"Luggage & Leather Goods",
            "type":"Retail Goods"
        }
    ],
    "sg:phone":"+1 416 599 1467",
    "sg:postcode":"M5T 3B3",
    "sg:province":"ON",
    "sg:tags":[
        "clothes"
    ],
    "wof:name":"Quality Kay Leather CO",
    "wof:placetype":"venue"
},
  "geometry": {"coordinates":[-79.397575,43.650982],"type":"Point"}
}