{
  "type": "Feature",
  "properties": {
    "addr:full":"32 Willow Ave E Oakbank MB R0E 1J2",
    "addr:housenumber":"32",
    "addr:postcode":"r0e 1j2",
    "addr:street":"Willow Ave E",
    "iso:country":"CA",
    "sg:address":"32 Willow Ave E",
    "sg:city":"Oakbank",
    "sg:classifiers":[
        {
            "category":"Professional",
            "subcategory":"Management & Consulting",
            "type":"Services"
        }
    ],
    "sg:phone":"+1 204 444 3922",
    "sg:postcode":"R0E 1J2",
    "sg:province":"MB",
    "sg:tags":[
        "consultant",
        "training"
    ],
    "wof:name":"Training Plus",
    "wof:placetype":"venue"
},
  "geometry": {"coordinates":[-96.8424072266,49.9376106262],"type":"Point"}
}