{
  "type": "Feature",
  "properties": {
    "addr:full":"Etobicoke ON M9A 1B7",
    "addr:postcode":"m9a 1b7",
    "iso:country":"CA",
    "sg:city":"Etobicoke",
    "sg:classifiers":[
        {
            "category":"Health Services",
            "subcategory":"Chiropractor",
            "type":"Services"
        }
    ],
    "sg:phone":"+1 416 231 7177",
    "sg:postcode":"M9A 1B7",
    "sg:province":"ON",
    "wof:name":"Islington Village Chiropractic",
    "wof:placetype":"venue"
},
  "geometry": {"coordinates":[-79.52913665769999,43.6485671997],"type":"Point"}
}