{
  "type": "Feature",
  "properties": {
    "addr:full":"2973 Lake City Way Burnaby BC V5A 2Z6",
    "addr:housenumber":"2973",
    "addr:postcode":"v5a 2z6",
    "addr:street":"Lake City Way",
    "iso:country":"CA",
    "sg:address":"2973 Lake City Way",
    "sg:city":"Burnaby",
    "sg:classifiers":[
        {
            "category":"Manufacturing",
            "subcategory":"Printing",
            "type":"Manufacturing & Wholesale Goods"
        }
    ],
    "sg:phone":"+1 604 420 1611",
    "sg:postcode":"V5A 2Z6",
    "sg:province":"BC",
    "sg:tags":[
        "printer"
    ],
    "wof:name":"David Printing Svc Ltd",
    "wof:placetype":"venue"
},
  "geometry": {"coordinates":[-122.937957764,49.2580108643],"type":"Point"}
}