{
  "type": "Feature",
  "properties": {
    "addr:full":"7 Market St Paris ON N3L 3A3",
    "addr:housenumber":"7",
    "addr:postcode":"n3l 3a3",
    "addr:street":"Market St",
    "iso:country":"CA",
    "sg:address":"7 Market St",
    "sg:city":"Paris",
    "sg:classifiers":[
        {
            "category":"Real Estate",
            "subcategory":"Real Estate Operator",
            "type":"Services"
        }
    ],
    "sg:phone":"+1 519 442 4642",
    "sg:postcode":"N3L 3A3",
    "sg:province":"ON",
    "sg:tags":[
        "apartment"
    ],
    "wof:name":"Jmk Holdings",
    "wof:placetype":"venue"
},
  "geometry": {"coordinates":[-80.39463000000001,43.202381],"type":"Point"}
}