{
  "type": "Feature",
  "properties": {
    "iso:country":"CA",
    "sg:city":"Toronto",
    "sg:classifiers":[
        {
            "category":"Professional",
            "type":"Services"
        }
    ],
    "sg:phone":"+1 416 367 9494",
    "sg:postcode":"M5A 4L5",
    "sg:province":"ON",
    "sg:tags":[
        "arranger",
        "music",
        "composer"
    ],
    "wof:name":"Panama Productions",
    "wof:placetype":"venue"
},
  "geometry": {"coordinates":[-79.3667373657,43.6517448425],"type":"Point"}
}