{
  "type": "Feature",
  "properties": {
    "iso:country":"CA",
    "sg:city":"Mississauga",
    "sg:classifiers":[
        {
            "category":"Autos & Motor Vehicles",
            "subcategory":"Auto Supplies",
            "type":"Retail Goods"
        }
    ],
    "sg:phone":"+1 905 795 0800",
    "sg:postcode":"L5T 1G2",
    "sg:province":"ON",
    "sg:tags":[
        "tire"
    ],
    "wof:name":"Yokohama Tire Inc",
    "wof:placetype":"venue"
},
  "geometry": {"coordinates":[-79.659134,43.656746],"type":"Point"}
}