{
  "type": "Feature",
  "properties": {
    "addr:full":"Drayton Valley AB T7A 1R8",
    "addr:postcode":"t7a 1r8",
    "addr:street":"Drayton",
    "iso:country":"CA",
    "sg:city":"Drayton Valley",
    "sg:classifiers":[
        {
            "category":"Building & Trades",
            "subcategory":"Equipment Rental",
            "type":"Services"
        }
    ],
    "sg:phone":"+1 780 542 4096",
    "sg:postcode":"T7A 1R8",
    "sg:province":"AB",
    "sg:tags":[
        "yard"
    ],
    "wof:name":"Altam Holdings Ltd",
    "wof:placetype":"venue"
},
  "geometry": {"coordinates":[-114.98689299999999,53.227997],"type":"Point"}
}