{
  "type": "Feature",
  "properties": {
    "addr:full":"Port Carling ON P0B 1J0",
    "addr:postcode":"p0b 1j0",
    "iso:country":"CA",
    "sg:city":"Port Carling",
    "sg:classifiers":[
        {
            "category":"Building & Trades",
            "subcategory":"Landscaping Services",
            "type":"Services"
        }
    ],
    "sg:phone":"+1 705 765 6629",
    "sg:postcode":"P0B 1J0",
    "sg:province":"ON",
    "sg:tags":[
        "tree",
        "landscape",
        "contractor"
    ],
    "wof:name":"Muskoka Greenscaping",
    "wof:placetype":"venue"
},
  "geometry": {"coordinates":[-79.641907,45.097618],"type":"Point"}
}