{
  "type": "Feature",
  "properties": {
    "iso:country":"CA",
    "sg:address":"5939 6 St NE",
    "sg:city":"Calgary",
    "sg:classifiers":[
        {
            "category":"Wholesale",
            "subcategory":"Fruits & Vegetables",
            "type":"Manufacturing & Wholesale Goods"
        }
    ],
    "sg:phone":"+1 403 295 8461",
    "sg:postcode":"T2K 5R5",
    "sg:province":"AB",
    "wof:name":"Sun Fresh Produce Inc",
    "wof:placetype":"venue"
},
  "geometry": {"coordinates":[-114.048904419,51.1057891846],"type":"Point"}
}