{
  "type": "Feature",
  "properties": {
    "addr:full":"2777 Island Hwy Campbell River BC V9W 2H4",
    "addr:housenumber":"2777",
    "addr:postcode":"v9w 2h4",
    "addr:street":"Island Hwy",
    "iso:country":"CA",
    "sg:address":"2777 Island Hwy",
    "sg:city":"Campbell River",
    "sg:classifiers":[
        {
            "category":"Autos & Motor Vehicles",
            "subcategory":"Automobile Sales",
            "type":"Retail Goods"
        }
    ],
    "sg:phone":"+1 250 287 9133",
    "sg:postcode":"V9W 2H4",
    "sg:province":"BC",
    "sg:tags":[
        "repairing",
        "car"
    ],
    "wof:name":"Bill Howich Chrysler Campbell",
    "wof:placetype":"venue"
},
  "geometry": {"coordinates":[-125.26889,50.044735],"type":"Point"}
}