{
  "type": "Feature",
  "properties": {
    "iso:country":"CA",
    "sg:address":"3401 Rue Saint-Antoine O",
    "sg:city":"Westmount",
    "sg:classifiers":[
        {
            "category":"Communications",
            "subcategory":"Film & Video Production",
            "type":"Services"
        }
    ],
    "sg:phone":"+1 514 276 9066",
    "sg:postcode":"H3Z 1X1",
    "sg:province":"QC",
    "sg:tags":[
        "television",
        "producer"
    ],
    "wof:name":"Punch International",
    "wof:placetype":"venue"
},
  "geometry": {"coordinates":[-73.583275,45.48381],"type":"Point"}
}