{
  "type": "Feature",
  "properties": {
    "addr:full":"2092 Enterprise Way Kelowna BC V1Y 6H7",
    "addr:housenumber":"2092",
    "addr:postcode":"v1y 6h7",
    "addr:street":"Enterprise Way",
    "iso:country":"CA",
    "sg:address":"2092 Enterprise Way",
    "sg:city":"Kelowna",
    "sg:classifiers":[
        {
            "category":"Manufacturing",
            "subcategory":"Paper Products",
            "type":"Manufacturing & Wholesale Goods"
        }
    ],
    "sg:phone":"+1 250 860 2274",
    "sg:postcode":"V1Y 6H7",
    "sg:province":"BC",
    "sg:tags":[
        "corrugated",
        "box",
        "fiber",
        "package",
        "solid",
        "development",
        "designing"
    ],
    "wof:name":"Crown Packaging",
    "wof:placetype":"venue"
},
  "geometry": {"coordinates":[-119.44240600000001,49.88332],"type":"Point"}
}