{
  "type": "Feature",
  "properties": {
    "addr:full":"428 Kennedy Rd S Saint-Come-Liniere QC G0M 1J0",
    "addr:housenumber":"428",
    "addr:postcode":"g0m 1j0",
    "addr:street":"Kennedy Rd S Saint-Come-Liniere",
    "iso:country":"CA",
    "sg:address":"428 Kennedy Rd S",
    "sg:city":"Saint-Come-Liniere",
    "sg:classifiers":[
        {
            "category":"Manufacturing",
            "subcategory":"Apparel",
            "type":"Manufacturing & Wholesale Goods"
        }
    ],
    "sg:phone":"+1 418 685 3571",
    "sg:postcode":"G0M 1J0",
    "sg:province":"QC",
    "sg:tags":[
        "clothing"
    ],
    "wof:name":"Vetements Clodan Inc",
    "wof:placetype":"venue"
},
  "geometry": {"coordinates":[-70.580421,46.07814],"type":"Point"}
}