{
  "type": "Feature",
  "properties": {
    "addr:full":"1980 Ch Du Tremblay Longueuil QC J4N 1A7",
    "addr:postcode":"1980;j4n 1a7",
    "addr:street":"Ch Du Tremblay",
    "iso:country":"CA",
    "sg:address":"1980 Ch Du Tremblay",
    "sg:city":"Longueuil",
    "sg:classifiers":[
        {
            "category":"Retail",
            "subcategory":"Auto Repair",
            "type":"Services"
        }
    ],
    "sg:phone":"+1 450 468 9025",
    "sg:postcode":"J4N 1A7",
    "sg:province":"QC",
    "sg:tags":[
        "repairing",
        "automobile"
    ],
    "wof:name":"Garage Du Tremblay Inc",
    "wof:placetype":"venue"
},
  "geometry": {"coordinates":[-73.4500961304,45.546081543],"type":"Point"}
}