{
  "type": "Feature",
  "properties": {
    "addr:full":"575 Hwy 21 S Maple Creek SK S0N 1N0",
    "addr:housenumber":"575",
    "addr:postcode":"s0n 1n0",
    "addr:street":"Hwy 21 S;Creek",
    "iso:country":"CA",
    "sg:address":"575 Hwy 21 S",
    "sg:city":"Maple Creek",
    "sg:classifiers":[
        {
            "category":"Health Services",
            "subcategory":"Hospital",
            "type":"Services"
        }
    ],
    "sg:phone":"+1 306 662 2611",
    "sg:postcode":"S0N 1N0",
    "sg:province":"SK",
    "wof:name":"Maple Creek Hospital",
    "wof:placetype":"venue"
},
  "geometry": {"coordinates":[-109.486099243,49.9028091431],"type":"Point"}
}