{
  "type": "Feature",
  "properties": {
    "iso:country":"CA",
    "sg:address":"17 Morrison Dr",
    "sg:city":"St Thomas",
    "sg:classifiers":[
        {
            "category":"Health Services",
            "subcategory":"Nursing And Care Facility",
            "type":"Services"
        }
    ],
    "sg:phone":"+1 519 633 1519",
    "sg:postcode":"N5R 4S5",
    "sg:province":"ON",
    "sg:tags":[
        "home",
        "retirement",
        "community"
    ],
    "wof:name":"Festival Gardens Homes",
    "wof:placetype":"venue"
},
  "geometry": {"coordinates":[-81.1728591919,42.7646255493],"type":"Point"}
}