{
  "type": "Feature",
  "properties": {
    "addr:full":"Etobicoke ON M8Z 5E7",
    "addr:postcode":"m8z 5e7",
    "iso:country":"CA",
    "sg:city":"Etobicoke",
    "sg:classifiers":[
        {
            "category":"Manufacturing",
            "subcategory":"Tools & Machinery",
            "type":"Manufacturing & Wholesale Goods"
        }
    ],
    "sg:phone":"+1 416 255 3322",
    "sg:postcode":"M8Z 5E7",
    "sg:province":"ON",
    "sg:tags":[
        "disposal",
        "garbage",
        "equipment"
    ],
    "wof:name":"Serquip Limited",
    "wof:placetype":"venue"
},
  "geometry": {"coordinates":[-79.523499,43.614292],"type":"Point"}
}