{
  "type": "Feature",
  "properties": {
    "addr:full":"648 Boul Laure Sept-Iles QC G4R 1X9",
    "addr:housenumber":"648",
    "addr:postcode":"g4r 1x9",
    "addr:street":"Boul Laure Sept-Iles",
    "iso:country":"CA",
    "sg:address":"648 Boul Laure",
    "sg:city":"Sept-Iles",
    "sg:classifiers":[
        {
            "category":"Home & Garden",
            "subcategory":"Home Furnishings",
            "type":"Retail Goods"
        }
    ],
    "sg:phone":"+1 418 962 1815",
    "sg:postcode":"G4R 1X9",
    "sg:province":"QC",
    "sg:tags":[
        "shades",
        "lamp",
        "lighting"
    ],
    "wof:name":"Luminaire Nova",
    "wof:placetype":"venue"
},
  "geometry": {"coordinates":[-66.37988300000001,50.216843],"type":"Point"}
}