{
  "type": "Feature",
  "properties": {
    "addr:full":"88 Av Rouleau Rimouski QC G5L 7J8",
    "addr:postcode":"g5l 7j8",
    "addr:street":"88 Av Rouleau",
    "iso:country":"CA",
    "sg:address":"88 Av Rouleau",
    "sg:city":"Rimouski",
    "sg:classifiers":[
        {
            "category":"Restaurant",
            "type":"Food & Drink"
        }
    ],
    "sg:phone":"+1 418 724 2288",
    "sg:postcode":"G5L 7J8",
    "sg:province":"QC",
    "wof:name":"Restaurants Pfk",
    "wof:placetype":"venue"
},
  "geometry": {"coordinates":[-68.53452299999999,48.448391],"type":"Point"}
}