{
  "type": "Feature",
  "properties": {
    "iso:country":"CA",
    "sg:address":"1089 Peoples Rd",
    "sg:city":"Sault Ste Marie",
    "sg:classifiers":[
        {
            "category":"Autos & Motor Vehicles",
            "subcategory":"Auto Supplies",
            "type":"Retail Goods"
        }
    ],
    "sg:phone":"+1 705 946 5200",
    "sg:postcode":"P6C 3W4",
    "sg:province":"ON",
    "sg:tags":[
        "repairing",
        "automobile",
        "parts",
        "radiator"
    ],
    "wof:name":"Eagle Radiator Svc",
    "wof:placetype":"venue"
},
  "geometry": {"coordinates":[-84.351303,46.549335],"type":"Point"}
}