{
  "type": "Feature",
  "properties": {
    "addr:full":"Carcross YT Y0B 1B0",
    "addr:postcode":"y0b 1b0",
    "iso:country":"CA",
    "sg:city":"Carcross",
    "sg:classifiers":[
        {
            "category":"Government",
            "subcategory":"Office",
            "type":"Public Place"
        }
    ],
    "sg:phone":"+1 867 821 2677",
    "sg:postcode":"Y0B 1B0",
    "sg:province":"YT",
    "sg:tags":[
        "department",
        "police"
    ],
    "wof:name":"Carcross Royal Canadian",
    "wof:placetype":"venue"
},
  "geometry": {"coordinates":[-134.69987499999999,60.166199],"type":"Point"}
}