{
  "type": "Feature",
  "properties": {
    "addr:full":"500 Topsail Rd St. John's NL A1E 2C2",
    "addr:housenumber":"500",
    "addr:postcode":"a1e 2c2",
    "addr:street":"Topsail Rd",
    "iso:country":"CA",
    "sg:address":"500 Topsail Rd",
    "sg:city":"St. John's",
    "sg:classifiers":[
        {
            "category":"Autos & Motor Vehicles",
            "subcategory":"Fuel & Gas Station",
            "type":"Retail Goods"
        }
    ],
    "sg:phone":"+1 709 364 4208",
    "sg:postcode":"A1E 2C2",
    "sg:province":"NL",
    "sg:tags":[
        "oil"
    ],
    "wof:name":"Topsail Road Esso",
    "wof:placetype":"venue"
},
  "geometry": {"coordinates":[-52.7567634583,47.5308380127],"type":"Point"}
}