{
  "type": "Feature",
  "properties": {
    "addr:full":"1255 Finch Ave W North York ON M3J 2G4",
    "addr:housenumber":"1255",
    "addr:postcode":"m3j 2g4",
    "addr:street":"Finch Ave W",
    "iso:country":"CA",
    "sg:address":"1255 Finch Ave W",
    "sg:city":"North York",
    "sg:classifiers":[
        {
            "category":"Home & Garden",
            "subcategory":"Furniture",
            "type":"Retail Goods"
        }
    ],
    "sg:phone":"+1 416 630 1777",
    "sg:postcode":"M3J 2G4",
    "sg:province":"ON",
    "wof:name":"Bad Boy Furniture & Appliances",
    "wof:placetype":"venue"
},
  "geometry": {"coordinates":[-79.486816,43.764267],"type":"Point"}
}