{
  "type": "Feature",
  "properties": {
    "addr:full":"3679 Rue Ontario E Montreal QC H1W 1S1",
    "addr:housenumber":"3679",
    "addr:postcode":"h1w 1s1",
    "addr:street":"Rue Ontario E",
    "iso:country":"CA",
    "sg:address":"3679 Rue Ontario E",
    "sg:city":"Montreal",
    "sg:classifiers":[
        {
            "category":"Shopping",
            "subcategory":"Jewelry",
            "type":"Retail Goods"
        }
    ],
    "sg:phone":"+1 514 522 3309",
    "sg:postcode":"H1W 1S1",
    "sg:province":"QC",
    "sg:tags":[
        "jeweler"
    ],
    "wof:name":"Bijouterie Gaucher",
    "wof:placetype":"venue"
},
  "geometry": {"coordinates":[-73.544449,45.546043],"type":"Point"}
}