{
  "type": "Feature",
  "properties": {
    "addr:full":"1470 Rue Des Erables Saint-Blaise-Sur-Richelieu QC J0J 1W0",
    "addr:housenumber":"1470",
    "addr:postcode":"j0j 1w0",
    "addr:street":"Rue Des Erables",
    "iso:country":"CA",
    "sg:address":"1470 Rue Des Erables",
    "sg:city":"Saint-Blaise-Sur-Richelieu",
    "sg:classifiers":[
        {
            "category":"Personal",
            "subcategory":"Beauty Salon",
            "type":"Services"
        }
    ],
    "sg:phone":"+1 450 358 9609",
    "sg:postcode":"J0J 1W0",
    "sg:province":"QC",
    "wof:name":"Salon Chez Marie",
    "wof:placetype":"venue"
},
  "geometry": {"coordinates":[-73.295517,45.240063],"type":"Point"}
}