{
  "type": "Feature",
  "properties": {
    "iso:country":"CA",
    "sg:city":"Guelph",
    "sg:classifiers":[
        {
            "category":"Food & Beverages",
            "subcategory":"Liquor & Beverages",
            "type":"Retail Goods"
        }
    ],
    "sg:phone":"+1 519 822 5621",
    "sg:postcode":"N1G 1G8",
    "sg:province":"ON",
    "sg:tags":[
        "beer",
        "ale"
    ],
    "wof:name":"Beer Store",
    "wof:placetype":"venue"
},
  "geometry": {"coordinates":[-80.24942016599999,43.5291557312],"type":"Point"}
}