{
  "type": "Feature",
  "properties": {
    "addr:full":"12411 Barnes Dr Richmond BC V6V 1H7",
    "addr:housenumber":"12411",
    "addr:postcode":"v6v 1h7",
    "addr:street":"Barnes Dr",
    "iso:country":"CA",
    "sg:address":"12411 Barnes Dr",
    "sg:city":"Richmond",
    "sg:classifiers":[
        {
            "category":"Building & Trades",
            "subcategory":"Construction",
            "type":"Services"
        }
    ],
    "sg:phone":"+1 604 270 1034",
    "sg:postcode":"V6V 1H7",
    "sg:province":"BC",
    "sg:tags":[
        "general",
        "contractor"
    ],
    "wof:name":"Corporate Projects Ltd",
    "wof:placetype":"venue"
},
  "geometry": {"coordinates":[-123.086517,49.189789],"type":"Point"}
}