{
  "type": "Feature",
  "properties": {
    "addr:full":"Ottawa ON K1G 4K8",
    "addr:postcode":"k1g 4k8",
    "iso:country":"CA",
    "sg:city":"Ottawa",
    "sg:classifiers":[
        {
            "category":"Professional",
            "subcategory":"Management & Consulting",
            "type":"Services"
        }
    ],
    "sg:phone":"+1 613 738 1348",
    "sg:postcode":"K1G 4K8",
    "sg:province":"ON",
    "sg:tags":[
        "consultant",
        "business"
    ],
    "wof:name":"Touch Stone Solutions Ltd",
    "wof:placetype":"venue"
},
  "geometry": {"coordinates":[-75.6213607788,45.3795051575],"type":"Point"}
}