{
  "type": "Feature",
  "properties": {
    "addr:full":"1888 King St Bridgewater NS B4V 2W9",
    "addr:housenumber":"1888",
    "addr:postcode":"b4v 2w9",
    "addr:street":"King St",
    "iso:country":"CA",
    "sg:address":"1888 King St",
    "sg:city":"Bridgewater",
    "sg:classifiers":[
        {
            "category":"Retail",
            "subcategory":"Auto Repair",
            "type":"Services"
        }
    ],
    "sg:phone":"+1 902 543 0034",
    "sg:postcode":"B4V 2W9",
    "sg:province":"NS",
    "sg:tags":[
        "truck"
    ],
    "wof:name":"South Shore Truck Ctr",
    "wof:placetype":"venue"
},
  "geometry": {"coordinates":[-64.52607,44.384689],"type":"Point"}
}