{
  "type": "Feature",
  "properties": {
    "addr:full":"2359 Rue Guenette Saint-Laurent QC H4R 2E9",
    "addr:housenumber":"2359",
    "addr:postcode":"h4r 2e9",
    "addr:street":"Rue Guenette",
    "iso:country":"CA",
    "sg:address":"2359 Rue Guenette",
    "sg:city":"Saint-Laurent",
    "sg:classifiers":[
        {
            "category":"Manufacturing",
            "subcategory":"Printing",
            "type":"Manufacturing & Wholesale Goods"
        }
    ],
    "sg:phone":"+1 514 745 0333",
    "sg:postcode":"H4R 2E9",
    "sg:province":"QC",
    "sg:tags":[
        "printer"
    ],
    "wof:name":"Imprimerie Lariviere Inc",
    "wof:placetype":"venue"
},
  "geometry": {"coordinates":[-73.72689800000001,45.49931],"type":"Point"}
}