{
  "type": "Feature",
  "properties": {
    "iso:country":"CA",
    "sg:address":"2359 Rue Guenette",
    "sg:city":"Saint-Laurent",
    "sg:classifiers":[
        {
            "category":"Manufacturing",
            "subcategory":"Printing",
            "type":"Manufacturing & Wholesale Goods"
        }
    ],
    "sg:phone":"+1 514 745 0333",
    "sg:postcode":"H4R 2E9",
    "sg:province":"QC",
    "sg:tags":[
        "printer"
    ],
    "wof:name":"Imprimerie Lariviere Inc",
    "wof:placetype":"venue"
},
  "geometry": {"coordinates":[-73.726898,45.49931],"type":"Point"}
}