{
  "type": "Feature",
  "properties": {
    "addr:full":"18 Dallington Dr North York ON M2J 2G3",
    "addr:housenumber":"18",
    "addr:postcode":"m2j 2g3",
    "addr:street":"Dallington Dr",
    "iso:country":"CA",
    "sg:address":"18 Dallington Dr",
    "sg:city":"North York",
    "sg:classifiers":[
        {
            "category":"Social Services",
            "subcategory":"Child Care",
            "type":"Services"
        }
    ],
    "sg:phone":"+1 416 490 9360",
    "sg:postcode":"M2J 2G3",
    "sg:province":"ON",
    "wof:name":"Rendezvous Child Care Ctr",
    "wof:placetype":"venue"
},
  "geometry": {"coordinates":[-79.354462,43.777538],"type":"Point"}
}