{
  "type": "Feature",
  "properties": {
    "addr:full":"10 Rue Chateaubriand Hull QC J9A 1J1",
    "addr:housenumber":"10",
    "addr:postcode":"j9a 1j1",
    "addr:street":"Rue Chateaubriand",
    "iso:country":"CA",
    "sg:address":"10 Rue Chateaubriand",
    "sg:city":"Hull",
    "sg:classifiers":[
        {
            "category":"Professional",
            "subcategory":"Accounting & Tax Preparation",
            "type":"Services"
        }
    ],
    "sg:phone":"+1 819 778 7770",
    "sg:postcode":"J9A 1J1",
    "sg:province":"QC",
    "sg:tags":[
        "accountant"
    ],
    "wof:name":"Chevrier, Jacques",
    "wof:placetype":"venue"
},
  "geometry": {"coordinates":[-75.738235,45.423401],"type":"Point"}
}