{
  "type": "Feature",
  "properties": {
    "addr:full":"9 Pine Cres Hay River NT X0E 0R5",
    "addr:housenumber":"9",
    "addr:postcode":"x0e 0r5",
    "addr:street":"Pine Cres",
    "iso:country":"CA",
    "sg:address":"9 Pine Cres",
    "sg:city":"Hay River",
    "sg:classifiers":[
        {
            "category":"Professional",
            "subcategory":"Advertising",
            "type":"Services"
        }
    ],
    "sg:phone":"+1 867 874 4709",
    "sg:postcode":"X0E 0R5",
    "sg:province":"NT",
    "sg:tags":[
        "counselor"
    ],
    "wof:name":"Thomson Holdings",
    "wof:placetype":"venue"
},
  "geometry": {"coordinates":[-115.782166,60.82058],"type":"Point"}
}