{
  "type": "Feature",
  "properties": {
    "iso:country":"CA",
    "sg:address":"3904 Clarence Rd",
    "sg:city":"Lawrencetown.",
    "sg:classifiers":[
        {
            "category":"Wholesale",
            "subcategory":"Fruits & Vegetables",
            "type":"Manufacturing & Wholesale Goods"
        }
    ],
    "sg:phone":"+1 902 825 3289",
    "sg:postcode":"B0S 1M0",
    "sg:province":"NS",
    "wof:name":"Den Haan Enterprises",
    "wof:placetype":"venue"
},
  "geometry": {"coordinates":[-63.3385314941,44.6454391479],"type":"Point"}
}