{
  "type": "Feature",
  "properties": {
    "iso:country":"CA",
    "sg:city":"Sainte-Foy",
    "sg:classifiers":[
        {
            "category":"Insurance",
            "subcategory":"Insurance Agent",
            "type":"Services"
        }
    ],
    "sg:phone":"+1 418 529 1234",
    "sg:postcode":"G1V 4W2",
    "sg:province":"QC",
    "sg:tags":[
        "consultant"
    ],
    "wof:name":"Aon Parizeau",
    "wof:placetype":"venue"
},
  "geometry": {"coordinates":[-71.281059,46.771248],"type":"Point"}
}