{
  "type": "Feature",
  "properties": {
    "iso:country":"CA",
    "sg:address":"2020 No. 6 Rd",
    "sg:city":"Richmond",
    "sg:classifiers":[
        {
            "category":"Manufacturing",
            "subcategory":"Metals",
            "type":"Manufacturing & Wholesale Goods"
        }
    ],
    "sg:phone":"+1 604 276 2838",
    "sg:postcode":"V6V 1P1",
    "sg:province":"BC",
    "sg:tags":[
        "steel"
    ],
    "wof:name":"A & R Metal Industries Ltd",
    "wof:placetype":"venue"
},
  "geometry": {"coordinates":[-123.06904602,49.1985092163],"type":"Point"}
}