{
  "type": "Feature",
  "properties": {
    "addr:full":"1731 Kootenay Ave Prince Rupert BC V8J 4A3",
    "addr:housenumber":"1731",
    "addr:postcode":"v8j 4a3",
    "addr:street":"Kootenay Ave",
    "iso:country":"CA",
    "sg:address":"1731 Kootenay Ave",
    "sg:city":"Prince Rupert",
    "sg:classifiers":[
        {
            "category":"Farming",
            "subcategory":"Fish & Marine Products",
            "type":"Manufacturing & Wholesale Goods"
        }
    ],
    "sg:phone":"+1 250 624 9678",
    "sg:postcode":"V8J 4A3",
    "sg:province":"BC",
    "sg:tags":[
        "fisherman"
    ],
    "wof:name":"Denway Enterprises Inc",
    "wof:placetype":"venue"
},
  "geometry": {"coordinates":[-130.339371,54.299278],"type":"Point"}
}