{
  "type": "Feature",
  "properties": {
    "addr:full":"11 Balsam Ave Kirkland Lake ON P2N 1W7",
    "addr:housenumber":"11",
    "addr:postcode":"p2n 1w7",
    "addr:street":"Balsam Ave",
    "iso:country":"CA",
    "sg:address":"11 Balsam Ave",
    "sg:city":"Kirkland Lake",
    "sg:classifiers":[
        {
            "category":"Manufacturing",
            "subcategory":"Signs",
            "type":"Manufacturing & Wholesale Goods"
        }
    ],
    "sg:phone":"+1 705 568 8467",
    "sg:postcode":"P2N 1W7",
    "sg:province":"ON",
    "wof:name":"Didine, Mark",
    "wof:placetype":"venue"
},
  "geometry": {"coordinates":[-80.0255279541,48.1434288025],"type":"Point"}
}