{
  "type": "Feature",
  "properties": {
    "iso:country":"CA",
    "sg:address":"10878 Mccowan Rd",
    "sg:city":"Markham",
    "sg:classifiers":[
        {
            "category":"Building & Trades",
            "subcategory":"Construction",
            "type":"Services"
        }
    ],
    "sg:phone":"+1 905 471 9571",
    "sg:postcode":"L3P 3J3",
    "sg:province":"ON",
    "sg:tags":[
        "general",
        "contractor"
    ],
    "wof:name":"Hammer Construction",
    "wof:placetype":"venue"
},
  "geometry": {"coordinates":[-79.298752,43.925911],"type":"Point"}
}