{
  "type": "Feature",
  "properties": {
    "addr:full":"Cold Lake AB T9M 1X2",
    "addr:postcode":"t9m 1x2",
    "iso:country":"CA",
    "sg:city":"Cold Lake",
    "sg:classifiers":[
        {
            "category":"Shopping",
            "subcategory":"Music",
            "type":"Retail Goods"
        }
    ],
    "sg:phone":"+1 780 594 2744",
    "sg:postcode":"T9M 1X2",
    "sg:province":"AB",
    "sg:tags":[
        "player",
        "disc",
        "video",
        "cassette",
        "recorder",
        "tape"
    ],
    "wof:name":"Movie Gallery",
    "wof:placetype":"venue"
},
  "geometry": {"coordinates":[-110.20594,54.414524],"type":"Point"}
}