{
  "type": "Feature",
  "properties": {
    "addr:full":"Halifax NS B3J 3J9",
    "addr:postcode":"ns b3j 3j9",
    "iso:country":"CA",
    "sg:city":"Halifax",
    "sg:classifiers":[
        {
            "category":"Government",
            "subcategory":"Office",
            "type":"Public Place"
        }
    ],
    "sg:phone":"+1 902 424 4111",
    "sg:postcode":"B3J 3J9",
    "sg:province":"NS",
    "wof:name":"Nova Scotia Human Rights Comm",
    "wof:placetype":"venue"
},
  "geometry": {"coordinates":[-63.572891,44.647415],"type":"Point"}
}