{
  "type": "Feature",
  "properties": {
    "addr:full":"Hamilton ON L8P 1R4",
    "addr:postcode":"l8p 1r4",
    "iso:country":"CA",
    "sg:city":"Hamilton",
    "sg:classifiers":[
        {
            "category":"Real Estate",
            "subcategory":"Real Estate Operator",
            "type":"Services"
        }
    ],
    "sg:phone":"+1 905 527 4262",
    "sg:postcode":"L8P 1R4",
    "sg:province":"ON",
    "sg:tags":[
        "apartment"
    ],
    "wof:name":"Holmstead Land Holding Ltd",
    "wof:placetype":"venue"
},
  "geometry": {"coordinates":[-79.878281,43.255306],"type":"Point"}
}