{
  "type": "Feature",
  "properties": {
    "addr:full":"Saint-Laurent QC H4N 2M5",
    "addr:postcode":"h4n 2m5",
    "iso:country":"CA",
    "sg:city":"Saint-Laurent",
    "sg:classifiers":[
        {
            "category":"Wholesale",
            "subcategory":"Office Equipment",
            "type":"Manufacturing & Wholesale Goods"
        }
    ],
    "sg:phone":"+1 514 337 2677",
    "sg:postcode":"H4N 2M5",
    "sg:province":"QC",
    "sg:tags":[
        "accounting",
        "bookkeeping",
        "system"
    ],
    "wof:name":"Info Comptabilite Plus Inc",
    "wof:placetype":"venue"
},
  "geometry": {"coordinates":[-73.6530075073,45.5246582031],"type":"Point"}
}