{
  "type": "Feature",
  "properties": {
    "iso:country":"CA",
    "sg:address":"2638 Hastings St E",
    "sg:city":"Vancouver",
    "sg:classifiers":[
        {
            "category":"Food & Beverages",
            "subcategory":"Bakery",
            "type":"Retail Goods"
        }
    ],
    "sg:phone":"+1 604 255 6714",
    "sg:postcode":"V5K 1Z6",
    "sg:province":"BC",
    "sg:tags":[
        "baker"
    ],
    "wof:name":"Panda Bear Foods Ltd",
    "wof:placetype":"venue"
},
  "geometry": {"coordinates":[-123.050811768,49.2810134888],"type":"Point"}
}