{
  "type": "Feature",
  "properties": {
    "addr:full":"1225 St Mary's Rd Winnipeg MB R2M 5L5",
    "addr:housenumber":"1225",
    "addr:postcode":"r2m 5l5",
    "addr:street":"St Mary'S Rd",
    "iso:country":"CA",
    "sg:address":"1225 St Mary's Rd",
    "sg:city":"Winnipeg",
    "sg:classifiers":[
        {
            "category":"Restaurant",
            "type":"Food & Drink"
        }
    ],
    "sg:phone":"+1 204 257 6097",
    "sg:postcode":"R2M 5L5",
    "sg:province":"MB",
    "wof:name":"Taco Time",
    "wof:placetype":"venue"
},
  "geometry": {"coordinates":[-97.11454000000001,49.828995],"type":"Point"}
}