{
  "type": "Feature",
  "properties": {
    "addr:full":"5395 Timberlane Rd Powell River BC V8A 4Z6",
    "addr:housenumber":"5395",
    "addr:postcode":"v8a 4z6",
    "addr:street":"Timberlane Rd",
    "iso:country":"CA",
    "sg:address":"5395 Timberlane Rd",
    "sg:city":"Powell River",
    "sg:classifiers":[
        {
            "category":"Organizations",
            "subcategory":"Professional Association",
            "type":"Services"
        }
    ],
    "sg:phone":"+1 604 483 3856",
    "sg:postcode":"V8A 4Z6",
    "sg:province":"BC",
    "wof:name":"Powell River Fine Arts Assn",
    "wof:placetype":"venue"
},
  "geometry": {"coordinates":[-124.54183999999999,49.865154],"type":"Point"}
}