{
  "type": "Feature",
  "properties": {
    "iso:country":"CA",
    "sg:address":"230 Macdonnell St",
    "sg:city":"Kingston",
    "sg:classifiers":[
        {
            "category":"Organizations",
            "subcategory":"Religious Organization",
            "type":"Services"
        }
    ],
    "sg:phone":"+1 613 548 7270",
    "sg:postcode":"K7L 4C2",
    "sg:province":"ON",
    "sg:tags":[
        "church"
    ],
    "wof:name":"Kingston Chinese Alliance Chr",
    "wof:placetype":"venue"
},
  "geometry": {"coordinates":[-76.505287,44.2323],"type":"Point"}
}