{
  "type": "Feature",
  "properties": {
    "addr:full":"Hull QC J8X 2K4",
    "addr:postcode":"j8x 2k4",
    "iso:country":"CA",
    "sg:city":"Hull",
    "sg:classifiers":[
        {
            "category":"Travel",
            "subcategory":"Travel Agent",
            "type":"Entertainment"
        }
    ],
    "sg:phone":"+1 819 777 2522",
    "sg:postcode":"J8X 2K4",
    "sg:province":"QC",
    "sg:tags":[
        "agency",
        "bureau"
    ],
    "wof:name":"Voyages G Travel",
    "wof:placetype":"venue"
},
  "geometry": {"coordinates":[-75.715881,45.426338],"type":"Point"}
}