{
  "type": "Feature",
  "properties": {
    "addr:full":"12734 Boul Industriel Pointe-Aux-Trembles QC H1A 3V2",
    "addr:housenumber":"12734",
    "addr:postcode":"h1a 3v2",
    "addr:street":"Boul Industriel",
    "iso:country":"CA",
    "sg:address":"12734 Boul Industriel",
    "sg:city":"Pointe-Aux-Trembles",
    "sg:classifiers":[
        {
            "category":"Real Estate",
            "subcategory":"Real Estate Agent",
            "type":"Services"
        }
    ],
    "sg:phone":"+1 514 498 4788",
    "sg:postcode":"H1A 3V2",
    "sg:province":"QC",
    "wof:name":"Placements Dubeau Enr",
    "wof:placetype":"venue"
},
  "geometry": {"coordinates":[-73.5161361694,45.6552352905],"type":"Point"}
}