{
  "type": "Feature",
  "properties": {
    "addr:full":"579 Barnes Dr Goffs NS B2T 1K3",
    "addr:housenumber":"579",
    "addr:postcode":"b2t 1k3",
    "addr:street":"Barnes Dr",
    "iso:country":"CA",
    "sg:address":"579 Barnes Dr",
    "sg:city":"Goffs",
    "sg:classifiers":[
        {
            "category":"Airport",
            "type":"Transportation"
        }
    ],
    "sg:phone":"+1 902 873 2250",
    "sg:postcode":"B2T 1K3",
    "sg:province":"NS",
    "wof:name":"Imp Group Aerospace Div",
    "wof:placetype":"venue"
},
  "geometry": {"coordinates":[-63.4665145874,44.8896026611],"type":"Point"}
}