{
  "type": "Feature",
  "properties": {
    "addr:full":"Matane QC G4W 3W8",
    "addr:postcode":"g4w 3w8",
    "iso:country":"CA",
    "sg:city":"Matane",
    "sg:classifiers":[
        {
            "category":"Shopping",
            "subcategory":"Shoes",
            "type":"Retail Goods"
        }
    ],
    "sg:phone":"+1 418 562 4942",
    "sg:postcode":"G4W 3W8",
    "sg:province":"QC",
    "wof:name":"Nero-Bianco",
    "wof:placetype":"venue"
},
  "geometry": {"coordinates":[-67.535309,48.851803],"type":"Point"}
}