{
  "type": "Feature",
  "properties": {
    "addr:full":"550 Rue Guizot E Montreal QC H2P 1N3",
    "addr:housenumber":"550",
    "addr:postcode":"h2p 1n3",
    "addr:street":"Rue Guizot E",
    "iso:country":"CA",
    "sg:address":"550 Rue Guizot E",
    "sg:city":"Montreal",
    "sg:classifiers":[
        {
            "category":"Food & Beverages",
            "subcategory":"Groceries & Convenience Stores",
            "type":"Retail Goods"
        }
    ],
    "sg:phone":"+1 514 274 2388",
    "sg:postcode":"H2P 1N3",
    "sg:province":"QC",
    "sg:tags":[
        "grocer"
    ],
    "wof:name":"Marche Fu-Nan Enr",
    "wof:placetype":"venue"
},
  "geometry": {"coordinates":[-73.6315078735,45.5446968079],"type":"Point"}
}