{
  "type": "Feature",
  "properties": {
    "addr:full":"Edmonton AB T6G 1E6",
    "addr:postcode":"t6g 1e6",
    "iso:country":"CA",
    "sg:city":"Edmonton",
    "sg:classifiers":[
        {
            "category":"Professional",
            "subcategory":"Lawyer & Legal Services",
            "type":"Services"
        }
    ],
    "sg:phone":"+1 780 433 9000",
    "sg:postcode":"T6G 1E6",
    "sg:province":"AB",
    "sg:tags":[
        "attorney"
    ],
    "wof:name":"DE Villars Jones",
    "wof:placetype":"venue"
},
  "geometry": {"coordinates":[-113.51217699999999,53.521393],"type":"Point"}
}