{
  "type": "Feature",
  "properties": {
    "addr:full":"NE 22 6 5W Carman MB R0G 0J0",
    "addr:housenumber":"6 5w",
    "addr:postcode":"r0g 0j0",
    "addr:street":"Ne 22",
    "iso:country":"CA",
    "sg:address":"NE 22 6 5W",
    "sg:city":"Carman",
    "sg:classifiers":[
        {
            "category":"Farming",
            "subcategory":"Livestock Farm",
            "type":"Manufacturing & Wholesale Goods"
        }
    ],
    "sg:phone":"+1 204 745 3884",
    "sg:postcode":"R0G 0J0",
    "sg:province":"MB",
    "sg:tags":[
        "feeding"
    ],
    "wof:name":"Abbott Cattle CO Ltd",
    "wof:placetype":"venue"
},
  "geometry": {"coordinates":[-98.002319,49.508606],"type":"Point"}
}