{
  "type": "Feature",
  "properties": {
    "addr:full":"48 Southport St Toronto ON M6S 3N3",
    "addr:housenumber":"48",
    "addr:postcode":"m6s 3n3",
    "addr:street":"Southport St",
    "iso:country":"CA",
    "sg:address":"48 Southport St",
    "sg:city":"Toronto",
    "sg:classifiers":[
        {
            "category":"Banks & Credit Unions",
            "subcategory":"Bank",
            "type":"Services"
        }
    ],
    "sg:phone":"+1 416 763 5124",
    "sg:postcode":"M6S 3N3",
    "sg:province":"ON",
    "wof:name":"Cibc",
    "wof:placetype":"venue"
},
  "geometry": {"coordinates":[-79.47180899999999,43.637562],"type":"Point"}
}