{
  "type": "Feature",
  "properties": {
    "addr:full":"6699 Campobello Rd Mississauga ON L5N 2L7",
    "addr:housenumber":"6699",
    "addr:postcode":"l5n 2l7",
    "addr:street":"Campobello Rd",
    "iso:country":"CA",
    "sg:address":"6699 Campobello Rd",
    "sg:city":"Mississauga",
    "sg:classifiers":[
        {
            "category":"Professional",
            "subcategory":"Computer Services",
            "type":"Services"
        }
    ],
    "sg:phone":"+1 905 826 3922",
    "sg:postcode":"L5N 2L7",
    "sg:province":"ON",
    "wof:name":"Ama Computers Inc",
    "wof:placetype":"venue"
},
  "geometry": {"coordinates":[-79.73290252690001,43.6083335876],"type":"Point"}
}