{
  "type": "Feature",
  "properties": {
    "addr:full":"2279 Rue Fleury E Montreal QC H2B 1K7",
    "addr:housenumber":"2279",
    "addr:postcode":"h2b 1k7",
    "addr:street":"Rue Fleury E",
    "iso:country":"CA",
    "sg:address":"2279 Rue Fleury E",
    "sg:city":"Montreal",
    "sg:classifiers":[
        {
            "category":"Personal",
            "subcategory":"Beauty Salon",
            "type":"Services"
        }
    ],
    "sg:phone":"+1 514 389 8859",
    "sg:postcode":"H2B 1K7",
    "sg:province":"QC",
    "wof:name":"Studio DE LA Coiffure",
    "wof:placetype":"venue"
},
  "geometry": {"coordinates":[-73.649506,45.573498],"type":"Point"}
}