{
  "type": "Feature",
  "properties": {
    "addr:full":"Toronto ON M5T 2X6",
    "addr:postcode":"m5t 2x6",
    "iso:country":"CA",
    "sg:city":"Toronto",
    "sg:classifiers":[
        {
            "category":"Professional",
            "subcategory":"Management & Consulting",
            "type":"Services"
        }
    ],
    "sg:phone":"+1 416 977 9676",
    "sg:postcode":"M5T 2X6",
    "sg:province":"ON",
    "sg:tags":[
        "consultant",
        "business"
    ],
    "wof:name":"Ruth Lewis & Assoc",
    "wof:placetype":"venue"
},
  "geometry": {"coordinates":[-79.389755249,43.6526412964],"type":"Point"}
}