{
  "type": "Feature",
  "properties": {
    "addr:full":"3064 Pitt St Cornwall ON K6K 1B1",
    "addr:housenumber":"3064",
    "addr:postcode":"k6k 1b1",
    "addr:street":"Pitt St",
    "iso:country":"CA",
    "sg:address":"3064 Pitt St",
    "sg:city":"Cornwall",
    "sg:classifiers":[
        {
            "category":"Autos & Motor Vehicles",
            "subcategory":"Fuel & Gas Station",
            "type":"Retail Goods"
        }
    ],
    "sg:phone":"+1 613 937 0284",
    "sg:postcode":"K6K 1B1",
    "sg:province":"ON",
    "sg:tags":[
        "oil"
    ],
    "wof:name":"Seaway Gas & Fuel Ltd",
    "wof:placetype":"venue"
},
  "geometry": {"coordinates":[-74.76366400000001,45.061726],"type":"Point"}
}