{
  "type": "Feature",
  "properties": {
    "iso:country":"CA",
    "sg:address":"300 Boul Decarie",
    "sg:city":"Saint-Laurent",
    "sg:classifiers":[
        {
            "category":"Manufacturing",
            "subcategory":"Pottery",
            "type":"Manufacturing & Wholesale Goods"
        }
    ],
    "sg:phone":"+1 514 747 6727",
    "sg:postcode":"H4N 2M2",
    "sg:province":"QC",
    "wof:name":"Compagnie Ling",
    "wof:placetype":"venue"
},
  "geometry": {"coordinates":[-73.669418,45.505985],"type":"Point"}
}