{
  "type": "Feature",
  "properties": {
    "addr:full":"300 Boul Decarie Saint-Laurent QC H4N 2M2",
    "addr:housenumber":"300",
    "addr:postcode":"h4n 2m2",
    "addr:street":"Boul Decarie",
    "iso:country":"CA",
    "sg:address":"300 Boul Decarie",
    "sg:city":"Saint-Laurent",
    "sg:classifiers":[
        {
            "category":"Manufacturing",
            "subcategory":"Pottery",
            "type":"Manufacturing & Wholesale Goods"
        }
    ],
    "sg:phone":"+1 514 747 6727",
    "sg:postcode":"H4N 2M2",
    "sg:province":"QC",
    "wof:name":"Compagnie Ling",
    "wof:placetype":"venue"
},
  "geometry": {"coordinates":[-73.66941799999999,45.505985],"type":"Point"}
}