{
  "type": "Feature",
  "properties": {
    "addr:full":"44675 Watson Rd Chilliwack BC V2R 2Y6",
    "addr:housenumber":"44675",
    "addr:postcode":"v2r 2y6",
    "addr:street":"Watson Rd",
    "iso:country":"CA",
    "sg:address":"44675 Watson Rd",
    "sg:city":"Chilliwack",
    "sg:classifiers":[
        {
            "category":"Real Estate",
            "subcategory":"Developer",
            "type":"Services"
        }
    ],
    "sg:phone":"+1 604 824 5577",
    "sg:postcode":"V2R 2Y6",
    "sg:province":"BC",
    "sg:tags":[
        "cemetery"
    ],
    "wof:name":"Vedder View Gardens Cemetery",
    "wof:placetype":"venue"
},
  "geometry": {"coordinates":[-121.96276899999999,49.111221],"type":"Point"}
}