{
  "type": "Feature",
  "properties": {
    "addr:full":"Toronto ON M5V 2G9",
    "addr:postcode":"m5v 2g9",
    "iso:country":"CA",
    "sg:city":"Toronto",
    "sg:classifiers":[
        {
            "category":"Professional",
            "subcategory":"Advertising",
            "type":"Services"
        }
    ],
    "sg:phone":"+1 416 593 7017",
    "sg:postcode":"M5V 2G9",
    "sg:province":"ON",
    "sg:tags":[
        "communications",
        "counselor",
        "consultant"
    ],
    "wof:name":"Manifest Communications Inc",
    "wof:placetype":"venue"
},
  "geometry": {"coordinates":[-79.39301300050001,43.6482620239],"type":"Point"}
}