{
  "type": "Feature",
  "properties": {
    "addr:full":"9106 109 St Grande Prairie AB T8V 4K8",
    "addr:housenumber":"9106",
    "addr:postcode":"t8v 4k8",
    "addr:street":"109 St",
    "iso:country":"CA",
    "sg:address":"9106 109 St",
    "sg:city":"Grande Prairie",
    "sg:classifiers":[
        {
            "category":"Building & Trades",
            "subcategory":"Electrical",
            "type":"Services"
        }
    ],
    "sg:phone":"+1 780 539 4466",
    "sg:postcode":"T8V 4K8",
    "sg:province":"AB",
    "sg:tags":[
        "electric",
        "contractor"
    ],
    "wof:name":"Terel Electric Ltd",
    "wof:placetype":"venue"
},
  "geometry": {"coordinates":[-118.823509,55.162506],"type":"Point"}
}