{
  "type": "Feature",
  "properties": {
    "addr:full":"326 Boul Fiset Sorel-Tracy QC J3P 3R2",
    "addr:housenumber":"326",
    "addr:postcode":"j3p 3r2",
    "addr:street":"Boul Fiset",
    "iso:country":"CA",
    "sg:address":"326 Boul Fiset",
    "sg:city":"Sorel-Tracy",
    "sg:classifiers":[
        {
            "category":"Organizations",
            "subcategory":"Professional Association",
            "type":"Services"
        }
    ],
    "sg:phone":"+1 450 743 9252",
    "sg:postcode":"J3P 3R2",
    "sg:province":"QC",
    "wof:name":"Centre D'Aide & D'Information",
    "wof:placetype":"venue"
},
  "geometry": {"coordinates":[-73.095215,46.037003],"type":"Point"}
}