{
  "type": "Feature",
  "properties": {
    "addr:full":"4916 Hankin St # A Thorsby AB T0C 2P0",
    "addr:housenumber":"4916",
    "addr:postcode":"t0c 2p0",
    "addr:street":"Hankin St # A",
    "iso:country":"CA",
    "sg:address":"4916 Hankin St # A",
    "sg:city":"Thorsby",
    "sg:classifiers":[
        {
            "category":"Shopping",
            "subcategory":"Florist",
            "type":"Retail Goods"
        }
    ],
    "sg:phone":"+1 780 789 2600",
    "sg:postcode":"T0C 2P0",
    "sg:province":"AB",
    "sg:tags":[
        "shop",
        "gift"
    ],
    "wof:name":"Balloons & Blossoms",
    "wof:placetype":"venue"
},
  "geometry": {"coordinates":[-114.047813416,53.2266998291],"type":"Point"}
}