{
  "type": "Feature",
  "properties": {
    "addr:full":"1095 Wilton Grove Rd London ON N6N 1C9",
    "addr:housenumber":"1095",
    "addr:postcode":"n6n 1c9",
    "addr:street":"Wilton Grove Rd",
    "iso:country":"CA",
    "sg:address":"1095 Wilton Grove Rd",
    "sg:city":"London",
    "sg:classifiers":[
        {
            "category":"Freight",
            "type":"Transportation"
        }
    ],
    "sg:phone":"+1 519 681 3800",
    "sg:postcode":"N6N 1C9",
    "sg:province":"ON",
    "sg:tags":[
        "trucking"
    ],
    "wof:name":"Slh Transport Inc",
    "wof:placetype":"venue"
},
  "geometry": {"coordinates":[-81.18895000000001,42.928307],"type":"Point"}
}