{
  "type": "Feature",
  "properties": {
    "addr:full":"260 Rue Notre-Dame Le Gardeur QC J5Z 3C5",
    "addr:housenumber":"260",
    "addr:postcode":"j5z 3c5",
    "addr:street":"Rue Notre-Dame",
    "iso:country":"CA",
    "sg:address":"260 Rue Notre-Dame",
    "sg:city":"Le Gardeur",
    "sg:classifiers":[
        {
            "category":"Building & Trades",
            "subcategory":"Construction",
            "type":"Services"
        }
    ],
    "sg:phone":"+1 450 581 5275",
    "sg:postcode":"J5Z 3C5",
    "sg:province":"QC",
    "sg:tags":[
        "excavating",
        "designer",
        "contractor",
        "dealer",
        "pool",
        "swimming"
    ],
    "wof:name":"Ms Lachance Enr",
    "wof:placetype":"venue"
},
  "geometry": {"coordinates":[-73.4757156372,45.7467346191],"type":"Point"}
}