{
  "type": "Feature",
  "properties": {
    "addr:full":"7376 Rue Lajeunesse Montreal QC H2R 2H8",
    "addr:housenumber":"7376",
    "addr:postcode":"h2r 2h8",
    "addr:street":"Rue Lajeunesse",
    "iso:country":"CA",
    "sg:address":"7376 Rue Lajeunesse",
    "sg:city":"Montreal",
    "sg:classifiers":[
        {
            "category":"Social Services",
            "type":"Services"
        }
    ],
    "sg:phone":"+1 514 277 7574",
    "sg:postcode":"H2R 2H8",
    "sg:province":"QC",
    "sg:tags":[
        "organization",
        "welfare"
    ],
    "wof:name":"Centre Des Aines DE Villeray",
    "wof:placetype":"venue"
},
  "geometry": {"coordinates":[-73.61740112299999,45.5404586792],"type":"Point"}
}