{
  "type": "Feature",
  "properties": {
    "addr:full":"177 St Alphonse Ave Ste Anne MB R5H 1G3",
    "addr:housenumber":"177",
    "addr:postcode":"r5h 1g3",
    "addr:street":"St Alphonse Ave",
    "iso:country":"CA",
    "sg:address":"177 St Alphonse Ave",
    "sg:city":"Ste Anne",
    "sg:classifiers":[
        {
            "category":"Education",
            "subcategory":"School",
            "type":"Public Place"
        }
    ],
    "sg:phone":"+1 204 422 8776",
    "sg:postcode":"R5H 1G3",
    "sg:province":"MB",
    "wof:name":"Ste Anne Elementary School",
    "wof:placetype":"venue"
},
  "geometry": {"coordinates":[-96.652428,49.6712],"type":"Point"}
}