{
  "type": "Feature",
  "properties": {
    "addr:full":"314 Ch DE LA Tete-Du-Lac Pohenegamook QC G0L 1J0",
    "addr:housenumber":"314",
    "addr:postcode":"g0l 1j0",
    "addr:street":"Ch De La Tete-Du-Lac Pohenegamook",
    "iso:country":"CA",
    "sg:address":"314 Ch DE LA Tete-Du-Lac",
    "sg:city":"Pohenegamook",
    "sg:phone":"+1 418 859 3071",
    "sg:postcode":"G0L 1J0",
    "sg:province":"QC",
    "sg:tags":[
        "food",
        "equipment",
        "processing",
        "maple",
        "sugar"
    ],
    "wof:name":"Roland Patry & Fils Inc",
    "wof:placetype":"venue"
},
  "geometry": {"coordinates":[-69.154251,47.454922],"type":"Point"}
}