{
  "type": "Feature",
  "properties": {
    "addr:full":"42 Lakeview Rd Halfmoon Bay AB T4S 1S1",
    "addr:housenumber":"42",
    "addr:postcode":"t4s 1s1",
    "addr:street":"Lakeview Rd",
    "iso:country":"CA",
    "sg:address":"42 Lakeview Rd",
    "sg:city":"Halfmoon Bay",
    "sg:classifiers":[
        {
            "category":"Retail",
            "subcategory":"Repair Shop",
            "type":"Services"
        }
    ],
    "sg:phone":"+1 403 887 3400",
    "sg:postcode":"T4S 1S1",
    "sg:province":"AB",
    "sg:tags":[
        "lock",
        "locksmith"
    ],
    "wof:name":"John's Lock & Key Ltd",
    "wof:placetype":"venue"
},
  "geometry": {"coordinates":[-114.174301,52.346321],"type":"Point"}
}