{
  "type": "Feature",
  "properties": {
    "addr:full":"21628 48 Ave Langley BC V3A 3M8",
    "addr:housenumber":"21628",
    "addr:postcode":"v3a 3m8",
    "addr:street":"48 Ave",
    "iso:country":"CA",
    "sg:address":"21628 48 Ave",
    "sg:city":"Langley",
    "sg:classifiers":[
        {
            "category":"Travel",
            "subcategory":"Hotels & Motels",
            "type":"Entertainment"
        }
    ],
    "sg:phone":"+1 604 533 5569",
    "sg:postcode":"V3A 3M8",
    "sg:province":"BC",
    "sg:tags":[
        "breakfast",
        "accommodation",
        "bed"
    ],
    "wof:name":"Traveller's Hotel B & B",
    "wof:placetype":"venue"
},
  "geometry": {"coordinates":[-122.623916626,49.0892791748],"type":"Point"}
}