{
  "type": "Feature",
  "properties": {
    "addr:full":"Laval QC H7W 4C6",
    "addr:postcode":"h7w 4c6",
    "iso:country":"CA",
    "sg:city":"Laval",
    "sg:classifiers":[
        {
            "category":"Autos & Motor Vehicles",
            "subcategory":"Boat Sales",
            "type":"Retail Goods"
        }
    ],
    "sg:phone":"+1 450 686 0479",
    "sg:postcode":"H7W 4C6",
    "sg:province":"QC",
    "sg:tags":[
        "top",
        "upholstery",
        "cover"
    ],
    "wof:name":"Decor Marine",
    "wof:placetype":"venue"
},
  "geometry": {"coordinates":[-73.7547,45.522728],"type":"Point"}
}