{
  "type": "Feature",
  "properties": {
    "addr:full":"139 Castor St Russell ON K4R 1C7",
    "addr:housenumber":"139",
    "addr:postcode":"k4r 1c7",
    "addr:street":"Castor St",
    "iso:country":"CA",
    "sg:address":"139 Castor St",
    "sg:city":"Russell",
    "sg:classifiers":[
        {
            "category":"Organizations",
            "subcategory":"Religious Organization",
            "type":"Services"
        }
    ],
    "sg:phone":"+1 613 445 3226",
    "sg:postcode":"K4R 1C7",
    "sg:province":"ON",
    "sg:tags":[
        "church"
    ],
    "wof:name":"St Mary's Anglican Church Hall",
    "wof:placetype":"venue"
},
  "geometry": {"coordinates":[-75.36071,45.25687],"type":"Point"}
}