{
  "type": "Feature",
  "properties": {
    "addr:full":"270 Rue Principale Sainte-Emelie-DE-L'Energie QC J0K 2K0",
    "addr:housenumber":"270",
    "addr:postcode":"j0k 2k0",
    "addr:street":"Rue Principale",
    "iso:country":"CA",
    "sg:address":"270 Rue Principale",
    "sg:city":"Sainte-Emelie-DE-L'Energie",
    "sg:classifiers":[
        {
            "category":"Food & Beverages",
            "subcategory":"Groceries & Convenience Stores",
            "type":"Retail Goods"
        }
    ],
    "sg:phone":"+1 450 886 5059",
    "sg:postcode":"J0K 2K0",
    "sg:province":"QC",
    "wof:name":"Depanneur Du Ctr Ste-Emelie",
    "wof:placetype":"venue"
},
  "geometry": {"coordinates":[-68.165398,48.429131],"type":"Point"}
}