{
  "type": "Feature",
  "properties": {
    "addr:full":"1525 Welch St North Vancouver BC V7P 1B5",
    "addr:housenumber":"1525",
    "addr:postcode":"v7p 1b5",
    "addr:street":"Welch St",
    "iso:country":"CA",
    "sg:address":"1525 Welch St",
    "sg:city":"North Vancouver",
    "sg:classifiers":[
        {
            "category":"Retail",
            "subcategory":"Auto Repair",
            "type":"Services"
        }
    ],
    "sg:phone":"+1 604 985 9181",
    "sg:postcode":"V7P 1B5",
    "sg:province":"BC",
    "sg:tags":[
        "repairing",
        "automobile"
    ],
    "wof:name":"Jaguar Plus Holdings Ltd",
    "wof:placetype":"venue"
},
  "geometry": {"coordinates":[-123.114998,49.317501],"type":"Point"}
}