{
  "type": "Feature",
  "properties": {
    "addr:full":"6 Caithness Ave Toronto ON M4J 3X7",
    "addr:housenumber":"6",
    "addr:postcode":"m4j 3x7",
    "addr:street":"Caithness Ave",
    "iso:country":"CA",
    "sg:address":"6 Caithness Ave",
    "sg:city":"Toronto",
    "sg:classifiers":[
        {
            "category":"Health Services",
            "subcategory":"Health Practitioner",
            "type":"Services"
        }
    ],
    "sg:phone":"+1 416 463 7888",
    "sg:postcode":"M4J 3X7",
    "sg:province":"ON",
    "sg:tags":[
        "acupuncture"
    ],
    "wof:name":"Vital Source Chinese Medicine",
    "wof:placetype":"venue"
},
  "geometry": {"coordinates":[-79.335067749,43.6810531616],"type":"Point"}
}