{
  "type": "Feature",
  "properties": {
    "addr:full":"188 Park St Chatham ON N7M 3R9",
    "addr:housenumber":"188",
    "addr:postcode":"n7m 3r9",
    "addr:street":"Park St",
    "iso:country":"CA",
    "sg:address":"188 Park St",
    "sg:city":"Chatham",
    "sg:classifiers":[
        {
            "category":"Shopping",
            "subcategory":"Discount & Variety Stores",
            "type":"Retail Goods"
        }
    ],
    "sg:phone":"+1 519 380 9436",
    "sg:postcode":"N7M 3R9",
    "sg:province":"ON",
    "wof:name":"Stirlings Variety",
    "wof:placetype":"venue"
},
  "geometry": {"coordinates":[-82.1761169434,42.4030342102],"type":"Point"}
}