{
  "type": "Feature",
  "properties": {
    "addr:full":"277 Lower Truro Rd Truro NS B2N 1B2",
    "addr:housenumber":"277",
    "addr:postcode":"b2n 1b2",
    "addr:street":"Lower Truro Rd",
    "iso:country":"CA",
    "sg:address":"277 Lower Truro Rd",
    "sg:city":"Truro",
    "sg:classifiers":[
        {
            "category":"Retail",
            "subcategory":"Auto Repair",
            "type":"Services"
        }
    ],
    "sg:phone":"+1 902 895 7444",
    "sg:postcode":"B2N 1B2",
    "sg:province":"NS",
    "sg:tags":[
        "repairing",
        "automobile"
    ],
    "wof:name":"Maxwell's Service Ctr",
    "wof:placetype":"venue"
},
  "geometry": {"coordinates":[-63.304344,45.358978],"type":"Point"}
}