{
  "type": "Feature",
  "properties": {
    "addr:full":"45 Av Saint-Laurent Louiseville QC J5V 1J5",
    "addr:postcode":"j5v 1j5",
    "addr:street":"45 Av Saint-Laurent",
    "iso:country":"CA",
    "sg:address":"45 Av Saint-Laurent",
    "sg:city":"Louiseville",
    "sg:classifiers":[
        {
            "category":"Health Services",
            "subcategory":"Doctor",
            "type":"Services"
        }
    ],
    "sg:phone":"+1 819 228 5515",
    "sg:postcode":"J5V 1J5",
    "sg:province":"QC",
    "sg:tags":[
        "clinic"
    ],
    "wof:name":"Clinique Dentaire Levesque Et",
    "wof:placetype":"venue"
},
  "geometry": {"coordinates":[-72.94066599999999,46.255878],"type":"Point"}
}