{
  "type": "Feature",
  "properties": {
    "iso:country":"CA",
    "sg:address":"10690 Mccowan Rd",
    "sg:city":"Markham",
    "sg:classifiers":[
        {
            "category":"Retail",
            "subcategory":"Repair Shop",
            "type":"Services"
        }
    ],
    "sg:phone":"+1 905 640 8442",
    "sg:postcode":"L3P 3J3",
    "sg:province":"ON",
    "sg:tags":[
        "antique",
        "restoring"
    ],
    "wof:name":"Mc Cowan Antiques",
    "wof:placetype":"venue"
},
  "geometry": {"coordinates":[-79.2969589233,43.9187011719],"type":"Point"}
}