{
  "type": "Feature",
  "properties": {
    "addr:full":"10611 Boul Pie-Ix Montreal-Nord QC H1H 4A3",
    "addr:housenumber":"10611",
    "addr:postcode":"h1h 4a3",
    "addr:street":"Boul Pie-Ix",
    "iso:country":"CA",
    "sg:address":"10611 Boul Pie-Ix",
    "sg:city":"Montreal-Nord",
    "sg:classifiers":[
        {
            "category":"Banks & Credit Unions",
            "subcategory":"Bank",
            "type":"Services"
        }
    ],
    "sg:phone":"+1 514 328 8230",
    "sg:postcode":"H1H 4A3",
    "sg:province":"QC",
    "wof:name":"Banque Royale",
    "wof:placetype":"venue"
},
  "geometry": {"coordinates":[-73.63464355470001,45.5886726379],"type":"Point"}
}