{
  "type": "Feature",
  "properties": {
    "iso:country":"CA",
    "sg:city":"Windsor",
    "sg:classifiers":[
        {
            "category":"Wholesale",
            "subcategory":"Machinery & Supplies",
            "type":"Manufacturing & Wholesale Goods"
        }
    ],
    "sg:phone":"+1 519 969 1152",
    "sg:postcode":"N8X 4L2",
    "sg:province":"ON",
    "sg:tags":[
        "pump"
    ],
    "wof:name":"Suburban Distributors Ltd",
    "wof:placetype":"venue"
},
  "geometry": {"coordinates":[-82.9964675903,42.2776985168],"type":"Point"}
}