{
  "type": "Feature",
  "properties": {
    "addr:full":"16 Penner Ave Blumenort MB R0A 0C0",
    "addr:housenumber":"16",
    "addr:postcode":"r0a 0c0",
    "addr:street":"Penner Ave",
    "iso:country":"CA",
    "sg:address":"16 Penner Ave",
    "sg:city":"Blumenort",
    "sg:classifiers":[
        {
            "category":"Building & Trades",
            "subcategory":"Construction",
            "type":"Services"
        }
    ],
    "sg:phone":"+1 204 326 1341",
    "sg:postcode":"R0A 0C0",
    "sg:province":"MB",
    "sg:tags":[
        "general",
        "contractor"
    ],
    "wof:name":"Penn-CO Construction Ltd",
    "wof:placetype":"venue"
},
  "geometry": {"coordinates":[-96.69016999999999,49.604256],"type":"Point"}
}