{
  "type": "Feature",
  "properties": {
    "addr:full":"Saint-Anaclet QC G0K 1H0",
    "addr:postcode":"g0k 1h0",
    "iso:country":"CA",
    "sg:city":"Saint-Anaclet",
    "sg:classifiers":[
        {
            "category":"Retail",
            "subcategory":"Animal Services",
            "type":"Services"
        }
    ],
    "sg:phone":"+1 418 725 7199",
    "sg:postcode":"G0K 1H0",
    "sg:province":"QC",
    "sg:tags":[
        "pet",
        "boarding",
        "sitting"
    ],
    "wof:name":"Auberge Animaliere",
    "wof:placetype":"venue"
},
  "geometry": {"coordinates":[-68.4098815918,48.4665107727],"type":"Point"}
}