{
  "type": "Feature",
  "properties": {
    "addr:full":"2835 37 St SW Calgary AB T3E 3B3",
    "addr:housenumber":"2835",
    "addr:postcode":"t3e 3b3",
    "addr:street":"37 St Sw",
    "iso:country":"CA",
    "sg:address":"2835 37 St SW",
    "sg:city":"Calgary",
    "sg:classifiers":[
        {
            "category":"Restaurant",
            "type":"Food & Drink"
        }
    ],
    "sg:phone":"+1 403 242 0468",
    "sg:postcode":"T3E 3B3",
    "sg:province":"AB",
    "wof:name":"Plato Family Restaurant",
    "wof:placetype":"venue"
},
  "geometry": {"coordinates":[-114.141319275,51.0297813416],"type":"Point"}
}