{
  "type": "Feature",
  "properties": {
    "iso:country":"CA",
    "sg:city":"Longueuil",
    "sg:classifiers":[
        {
            "category":"Real Estate",
            "subcategory":"Real Estate Agent",
            "type":"Services"
        }
    ],
    "sg:phone":"+1 450 442 4148",
    "sg:postcode":"J4K 5J3",
    "sg:province":"QC",
    "wof:name":"Corporation Immobiliere",
    "wof:placetype":"venue"
},
  "geometry": {"coordinates":[-73.5229797363,45.5276451111],"type":"Point"}
}