{
  "type": "Feature",
  "properties": {
    "addr:full":"110 Eugenie St W #252 Windsor ON N8X 4Y6",
    "addr:housenumber":"110",
    "addr:postcode":"n8x 4y6",
    "addr:street":"Eugenie St W # 252",
    "iso:country":"CA",
    "sg:address":"110 Eugenie St W #252",
    "sg:city":"Windsor",
    "sg:classifiers":[
        {
            "category":"Professional",
            "subcategory":"Management & Consulting",
            "type":"Services"
        }
    ],
    "sg:phone":"+1 519 776 9022",
    "sg:postcode":"N8X 4Y6",
    "sg:province":"ON",
    "sg:tags":[
        "consultant",
        "safety",
        "business"
    ],
    "wof:name":"Nicholas & Assoc Safety Conslt",
    "wof:placetype":"venue"
},
  "geometry": {"coordinates":[-83.0191040039,42.2862548828],"type":"Point"}
}