{
  "type": "Feature",
  "properties": {
    "addr:full":"Scarborough ON M1V 5E4",
    "addr:postcode":"m1v 5e4",
    "iso:country":"CA",
    "sg:city":"Scarborough",
    "sg:classifiers":[
        {
            "category":"Shopping",
            "subcategory":"Optical Goods",
            "type":"Retail Goods"
        }
    ],
    "sg:phone":"+1 416 609 0224",
    "sg:postcode":"M1V 5E4",
    "sg:province":"ON",
    "sg:tags":[
        "optician"
    ],
    "wof:name":"J R Optical Labs",
    "wof:placetype":"venue"
},
  "geometry": {"coordinates":[-79.256767,43.818161],"type":"Point"}
}