{
  "type": "Feature",
  "properties": {
    "addr:full":"Vancouver BC V6M 3W6",
    "addr:postcode":"v6m 3w6",
    "iso:country":"CA",
    "sg:city":"Vancouver",
    "sg:classifiers":[
        {
            "category":"Food & Beverages",
            "subcategory":"Liquor & Beverages",
            "type":"Retail Goods"
        }
    ],
    "sg:phone":"+1 604 269 9040",
    "sg:postcode":"V6M 3W6",
    "sg:province":"BC",
    "sg:tags":[
        "store"
    ],
    "wof:name":"Free House Wine & Spirits Ltd",
    "wof:placetype":"venue"
},
  "geometry": {"coordinates":[-123.155731,49.23624],"type":"Point"}
}