{
  "type": "Feature",
  "properties": {
    "addr:full":"Richmond BC V6V 1J4",
    "addr:postcode":"v6v 1j4",
    "iso:country":"CA",
    "sg:city":"Richmond",
    "sg:classifiers":[
        {
            "category":"Wholesale",
            "subcategory":"Meat",
            "type":"Manufacturing & Wholesale Goods"
        }
    ],
    "sg:phone":"+1 604 278 7215",
    "sg:postcode":"V6V 1J4",
    "sg:province":"BC",
    "sg:tags":[
        "packer"
    ],
    "wof:name":"Sugiyama Meat Packer Ltd",
    "wof:placetype":"venue"
},
  "geometry": {"coordinates":[-123.088356018,49.1921958923],"type":"Point"}
}