{
  "type": "Feature",
  "properties": {
    "iso:country":"CA",
    "sg:city":"Innerkip",
    "sg:classifiers":[
        {
            "category":"Building & Trades",
            "subcategory":"Construction",
            "type":"Services"
        }
    ],
    "sg:phone":"+1 519 469 3217",
    "sg:postcode":"N0J 1M0",
    "sg:province":"ON",
    "sg:tags":[
        "drainage",
        "contractor"
    ],
    "wof:name":"R J Vance Drainage",
    "wof:placetype":"venue"
},
  "geometry": {"coordinates":[-80.64055633540001,43.2293548584],"type":"Point"}
}