{
  "type": "Feature",
  "properties": {
    "iso:country":"CA",
    "sg:address":"418 Church St",
    "sg:city":"Toronto",
    "sg:classifiers":[
        {
            "category":"Bars & Pubs",
            "type":"Food & Drink"
        }
    ],
    "sg:phone":"+1 416 977 4702",
    "sg:postcode":"M5B 2A3",
    "sg:province":"ON",
    "wof:name":"Gars Restaurants",
    "wof:placetype":"venue"
},
  "geometry": {"coordinates":[-79.379112,43.660889],"type":"Point"}
}