{
  "type": "Feature",
  "properties": {
    "addr:full":"3800 Boul Saint-Jean Dollard-Des-Ormeaux QC H9G 1X1",
    "addr:housenumber":"3800",
    "addr:postcode":"h9g 1x1",
    "addr:street":"Boul Saint-Jean",
    "iso:country":"CA",
    "sg:address":"3800 Boul Saint-Jean",
    "sg:city":"Dollard-Des-Ormeaux",
    "sg:classifiers":[
        {
            "category":"Restaurant",
            "type":"Food & Drink"
        }
    ],
    "sg:phone":"+1 514 626 5757",
    "sg:postcode":"H9G 1X1",
    "sg:province":"QC",
    "wof:name":"Boccacinos Restaurant",
    "wof:placetype":"venue"
},
  "geometry": {"coordinates":[-73.8363494873,45.4743080139],"type":"Point"}
}