{
  "type": "Feature",
  "properties": {
    "addr:full":"272 Main St Selkirk MB R1A 1S4",
    "addr:housenumber":"272",
    "addr:postcode":"r1a 1s4",
    "addr:street":"Main St",
    "iso:country":"CA",
    "sg:address":"272 Main St",
    "sg:city":"Selkirk",
    "sg:classifiers":[
        {
            "category":"Food & Beverages",
            "subcategory":"Specialty",
            "type":"Retail Goods"
        }
    ],
    "sg:phone":"+1 204 482 2277",
    "sg:postcode":"R1A 1S4",
    "sg:province":"MB",
    "sg:tags":[
        "water",
        "bulk",
        "company"
    ],
    "wof:name":"Water Shop",
    "wof:placetype":"venue"
},
  "geometry": {"coordinates":[-96.879448,50.139179],"type":"Point"}
}