{
  "type": "Feature",
  "properties": {
    "addr:full":"Mossleigh AB T0L 1P0",
    "addr:postcode":"t0l 1p0",
    "iso:country":"CA",
    "sg:city":"Mossleigh",
    "sg:classifiers":[
        {
            "category":"Travel",
            "subcategory":"Hotels & Motels",
            "type":"Entertainment"
        }
    ],
    "sg:phone":"+1 403 534 2444",
    "sg:postcode":"T0L 1P0",
    "sg:province":"AB",
    "wof:name":"Mossleigh Inn",
    "wof:placetype":"venue"
},
  "geometry": {"coordinates":[-113.326851,50.717903],"type":"Point"}
}