{
  "type": "Feature",
  "properties": {
    "addr:full":"187 Shore Club Rd Hubbards NS B0J 1T0",
    "addr:housenumber":"187",
    "addr:postcode":"b0j 1t0",
    "addr:street":"Shore Club Rd",
    "iso:country":"CA",
    "sg:address":"187 Shore Club Rd",
    "sg:city":"Hubbards",
    "sg:classifiers":[
        {
            "category":"Travel",
            "subcategory":"Hotels & Motels",
            "type":"Entertainment"
        }
    ],
    "sg:phone":"+1 902 857 2001",
    "sg:postcode":"B0J 1T0",
    "sg:province":"NS",
    "sg:tags":[
        "cottage",
        "cabin"
    ],
    "wof:name":"Rosewood Cottages & Gifts",
    "wof:placetype":"venue"
},
  "geometry": {"coordinates":[-64.054688,44.641193],"type":"Point"}
}