{
  "type": "Feature",
  "properties": {
    "addr:full":"1668 Av Lincoln Montreal QC H3H 1G9",
    "addr:housenumber":"1668",
    "addr:postcode":"h3h 1g9",
    "addr:street":"Av Lincoln",
    "iso:country":"CA",
    "sg:address":"1668 Av Lincoln",
    "sg:city":"Montreal",
    "sg:classifiers":[
        {
            "category":"Health Services",
            "subcategory":"Health Practitioner",
            "type":"Services"
        }
    ],
    "sg:phone":"+1 514 939 2632",
    "sg:postcode":"H3H 1G9",
    "sg:province":"QC",
    "sg:tags":[
        "psychologist"
    ],
    "wof:name":"Morrisson, Deborah",
    "wof:placetype":"venue"
},
  "geometry": {"coordinates":[-73.580849,45.495338],"type":"Point"}
}