{
  "type": "Feature",
  "properties": {
    "addr:full":"221 3rd St Craik SK S0G 0V0",
    "addr:housenumber":"221",
    "addr:postcode":"s0g 0v0",
    "addr:street":"3Rd St",
    "iso:country":"CA",
    "sg:address":"221 3rd St",
    "sg:city":"Craik",
    "sg:classifiers":[
        {
            "category":"Manufacturing",
            "subcategory":"Printing",
            "type":"Manufacturing & Wholesale Goods"
        }
    ],
    "sg:phone":"+1 306 734 2313",
    "sg:postcode":"S0G 0V0",
    "sg:province":"SK",
    "sg:tags":[
        "newspaper"
    ],
    "wof:name":"Craik Weekly News",
    "wof:placetype":"venue"
},
  "geometry": {"coordinates":[-105.817505,51.048805],"type":"Point"}
}