{
  "type": "Feature",
  "properties": {
    "addr:full":"Kirkfield ON K0M 2B0",
    "addr:postcode":"k0m 2b0",
    "addr:street":"Kirkfield",
    "iso:country":"CA",
    "sg:city":"Kirkfield",
    "sg:classifiers":[
        {
            "category":"Building & Trades",
            "subcategory":"Construction",
            "type":"Services"
        }
    ],
    "sg:phone":"+1 705 438 1103",
    "sg:postcode":"K0M 2B0",
    "sg:province":"ON",
    "sg:tags":[
        "siding",
        "heating",
        "contractor"
    ],
    "wof:name":"Lakeview Metal Products",
    "wof:placetype":"venue"
},
  "geometry": {"coordinates":[-79.047775,44.578781],"type":"Point"}
}