{
  "type": "Feature",
  "properties": {
    "addr:full":"350 Rue DE LA Corniche Saint-Nicolas QC G7A 2Y4",
    "addr:housenumber":"350",
    "addr:postcode":"g7a 2y4",
    "addr:street":"Rue De La Corniche",
    "iso:country":"CA",
    "sg:address":"350 Rue DE LA Corniche",
    "sg:city":"Saint-Nicolas",
    "sg:classifiers":[
        {
            "category":"Professional",
            "subcategory":"Business Services",
            "type":"Services"
        }
    ],
    "sg:phone":"+1 418 831 5586",
    "sg:postcode":"G7A 2Y4",
    "sg:province":"QC",
    "sg:tags":[
        "translator",
        "interpreter"
    ],
    "wof:name":"Poly Langues Traductions Enr",
    "wof:placetype":"venue"
},
  "geometry": {"coordinates":[-71.313103,46.734776],"type":"Point"}
}