{
  "type": "Feature",
  "properties": {
    "iso:country":"CA",
    "sg:address":"189 Victor Lewis Dr",
    "sg:city":"Winnipeg",
    "sg:classifiers":[
        {
            "category":"Real Estate",
            "subcategory":"Real Estate Operator",
            "type":"Services"
        }
    ],
    "sg:phone":"+1 204 489 2086",
    "sg:postcode":"R3P 2A2",
    "sg:province":"MB",
    "sg:tags":[
        "apartment"
    ],
    "wof:name":"Linden Woods Village",
    "wof:placetype":"venue"
},
  "geometry": {"coordinates":[-97.184471,49.844566],"type":"Point"}
}