{
  "type": "Feature",
  "properties": {
    "addr:full":"767 Douglas St Victoria BC V8W 2B4",
    "addr:housenumber":"767",
    "addr:postcode":"v8w 2b4",
    "addr:street":"Douglas St",
    "iso:country":"CA",
    "sg:address":"767 Douglas St",
    "sg:city":"Victoria",
    "sg:classifiers":[
        {
            "category":"Retail",
            "subcategory":"Auto Rental",
            "type":"Services"
        }
    ],
    "sg:phone":"+1 250 386 1213",
    "sg:postcode":"V8W 2B4",
    "sg:province":"BC",
    "sg:tags":[
        "renting",
        "automobile"
    ],
    "wof:name":"National Car & Truck Rental",
    "wof:placetype":"venue"
},
  "geometry": {"coordinates":[-123.365944,48.421406],"type":"Point"}
}