{
  "type": "Feature",
  "properties": {
    "addr:full":"1499 Irvine Rd Niagara on the Lake ON L0S 1J0",
    "addr:housenumber":"1499",
    "addr:postcode":"l0s 1j0",
    "addr:street":"Irvine Rd;On",
    "iso:country":"CA",
    "sg:address":"1499 Irvine Rd",
    "sg:city":"Niagara on the Lake",
    "sg:classifiers":[
        {
            "category":"Building & Trades",
            "subcategory":"Construction",
            "type":"Services"
        }
    ],
    "sg:phone":"+1 905 938 0408",
    "sg:postcode":"L0S 1J0",
    "sg:province":"ON",
    "sg:tags":[
        "water",
        "well",
        "drilling"
    ],
    "wof:name":"Ted Van Der Zalm Well Drilling",
    "wof:placetype":"venue"
},
  "geometry": {"coordinates":[-79.17152400000001,43.235283],"type":"Point"}
}