{
  "type": "Feature",
  "properties": {
    "iso:country":"CA",
    "sg:city":"Quebec",
    "sg:classifiers":[
        {
            "category":"Building & Trades",
            "subcategory":"Construction",
            "type":"Services"
        }
    ],
    "sg:phone":"+1 418 628 7290",
    "sg:postcode":"G2K 1W7",
    "sg:province":"QC",
    "sg:tags":[
        "general",
        "contractor"
    ],
    "wof:name":"Renovations Mailloux Enr",
    "wof:placetype":"venue"
},
  "geometry": {"coordinates":[-71.283699,46.85347],"type":"Point"}
}