{
  "type": "Feature",
  "properties": {
    "addr:full":"1405 Pender St E Vancouver BC V5L 1V7",
    "addr:housenumber":"1405",
    "addr:postcode":"v5l 1v7",
    "addr:street":"Pender St E",
    "iso:country":"CA",
    "sg:address":"1405 Pender St E",
    "sg:city":"Vancouver",
    "sg:classifiers":[
        {
            "category":"Retail",
            "subcategory":"Auto Repair",
            "type":"Services"
        }
    ],
    "sg:phone":"+1 604 255 0616",
    "sg:postcode":"V5L 1V7",
    "sg:province":"BC",
    "sg:tags":[
        "body",
        "automobile",
        "painting"
    ],
    "wof:name":"D & K Body Shop CO Ltd",
    "wof:placetype":"venue"
},
  "geometry": {"coordinates":[-123.075569153,49.2805862427],"type":"Point"}
}