{
  "type": "Feature",
  "properties": {
    "iso:country":"CA",
    "sg:address":"22332 Dewdney Trunk Rd",
    "sg:city":"Maple Ridge",
    "sg:classifiers":[
        {
            "category":"Home & Garden",
            "subcategory":"Household Appliances",
            "type":"Retail Goods"
        }
    ],
    "sg:phone":"+1 604 467 4169",
    "sg:postcode":"V2X 3J2",
    "sg:province":"BC",
    "sg:tags":[
        "vacuum"
    ],
    "wof:name":"Vacuum Shop",
    "wof:placetype":"venue"
},
  "geometry": {"coordinates":[-122.603652954,49.2203216553],"type":"Point"}
}