{
  "type": "Feature",
  "properties": {
    "iso:country":"CA",
    "sg:address":"15706 116 Ave NW",
    "sg:city":"Edmonton",
    "sg:classifiers":[
        {
            "category":"Retail",
            "subcategory":"Auto Rental",
            "type":"Services"
        }
    ],
    "sg:phone":"+1 780 451 2686",
    "sg:postcode":"T5M 3S5",
    "sg:province":"AB",
    "sg:tags":[
        "renting",
        "truck",
        "leasing"
    ],
    "wof:name":"Penske Truck Rental",
    "wof:placetype":"venue"
},
  "geometry": {"coordinates":[-113.592628479,53.5667572021],"type":"Point"}
}