{
  "type": "Feature",
  "properties": {
    "addr:full":"5602 Tenth Line W Mississauga ON L5M 7L9",
    "addr:housenumber":"5602",
    "addr:postcode":"l5m 7l9",
    "addr:street":"Tenth Line W",
    "iso:country":"CA",
    "sg:address":"5602 Tenth Line W",
    "sg:city":"Mississauga",
    "sg:classifiers":[
        {
            "category":"Shopping",
            "subcategory":"Pharmacy",
            "type":"Retail Goods"
        }
    ],
    "sg:phone":"+1 905 858 4618",
    "sg:postcode":"L5M 7L9",
    "sg:province":"ON",
    "wof:name":"Shoppers Drug Mart",
    "wof:placetype":"venue"
},
  "geometry": {"coordinates":[-79.7383804321,43.5561828613],"type":"Point"}
}