{
  "type": "Feature",
  "properties": {
    "addr:full":"143 Glenmorris St Cambridge ON N1S 2Z4",
    "addr:housenumber":"143",
    "addr:postcode":"n1s 2z4",
    "addr:street":"Glenmorris St",
    "iso:country":"CA",
    "sg:address":"143 Glenmorris St",
    "sg:city":"Cambridge",
    "sg:classifiers":[
        {
            "category":"Organizations",
            "subcategory":"Religious Organization",
            "type":"Services"
        }
    ],
    "sg:phone":"+1 519 621 1710",
    "sg:postcode":"N1S 2Z4",
    "sg:province":"ON",
    "sg:tags":[
        "church"
    ],
    "wof:name":"Westside Bible Chapel",
    "wof:placetype":"venue"
},
  "geometry": {"coordinates":[-80.32147999999999,43.344696],"type":"Point"}
}