{
  "type": "Feature",
  "properties": {
    "addr:full":"1484 Scott St Ottawa ON K1Y 2N4",
    "addr:housenumber":"1484",
    "addr:postcode":"k1y 2n4",
    "addr:street":"Scott St",
    "iso:country":"CA",
    "sg:address":"1484 Scott St",
    "sg:city":"Ottawa",
    "sg:classifiers":[
        {
            "category":"Recreation",
            "type":"Entertainment"
        }
    ],
    "sg:phone":"+1 613 761 6460",
    "sg:postcode":"K1Y 2N4",
    "sg:province":"ON",
    "sg:tags":[
        "martial",
        "arts",
        "instruction"
    ],
    "wof:name":"Sambo Centre D'Entrainement",
    "wof:placetype":"venue"
},
  "geometry": {"coordinates":[-75.731247,45.4049],"type":"Point"}
}