{
  "type": "Feature",
  "properties": {
    "iso:country":"CA",
    "sg:city":"Scarborough",
    "sg:classifiers":[
        {
            "category":"Manufacturing",
            "subcategory":"Printing",
            "type":"Manufacturing & Wholesale Goods"
        }
    ],
    "sg:phone":"+1 416 752 7580",
    "sg:postcode":"M1L 4J7",
    "sg:province":"ON",
    "sg:tags":[
        "printer"
    ],
    "wof:name":"Tjm Engraving Plus",
    "wof:placetype":"venue"
},
  "geometry": {"coordinates":[-79.2826309204,43.7249412537],"type":"Point"}
}