{
  "type": "Feature",
  "properties": {
    "addr:full":"6 Centerside Rd Tupperville ON N0P 2M0",
    "addr:housenumber":"6",
    "addr:postcode":"n0p 2m0",
    "addr:street":"Centerside Rd",
    "iso:country":"CA",
    "sg:address":"6 Centerside Rd",
    "sg:city":"Tupperville",
    "sg:classifiers":[
        {
            "category":"Wholesale",
            "subcategory":"Farm Supplies",
            "type":"Manufacturing & Wholesale Goods"
        }
    ],
    "sg:phone":"+1 519 627 4861",
    "sg:postcode":"N0P 2M0",
    "sg:province":"ON",
    "sg:tags":[
        "grain"
    ],
    "wof:name":"London Agricultural Comm",
    "wof:placetype":"venue"
},
  "geometry": {"coordinates":[-82.26955413819999,42.5898551941],"type":"Point"}
}