{
  "type": "Feature",
  "properties": {
    "addr:full":"Calgary AB T2J 2Y1",
    "addr:postcode":"t2j 2y1",
    "iso:country":"CA",
    "sg:city":"Calgary",
    "sg:classifiers":[
        {
            "category":"Personal",
            "subcategory":"Beauty Salon",
            "type":"Services"
        }
    ],
    "sg:phone":"+1 403 271 7755",
    "sg:postcode":"T2J 2Y1",
    "sg:province":"AB",
    "wof:name":"Zanoubia Hair Artistry",
    "wof:placetype":"venue"
},
  "geometry": {"coordinates":[-114.045852661,50.9606513977],"type":"Point"}
}