{
  "type": "Feature",
  "properties": {
    "iso:country":"CA",
    "sg:city":"Timmins",
    "sg:classifiers":[
        {
            "category":"Freight",
            "type":"Transportation"
        }
    ],
    "sg:phone":"+1 705 268 7542",
    "sg:postcode":"P4N 8R8",
    "sg:province":"ON",
    "sg:tags":[
        "mobile",
        "mover"
    ],
    "wof:name":"Onil Deschatelets Trucking Ltd",
    "wof:placetype":"venue"
},
  "geometry": {"coordinates":[-81.4111785889,48.4614906311],"type":"Point"}
}