{
  "type": "Feature",
  "properties": {
    "addr:full":"8760 132 Ave NW Edmonton AB T5E 0X8",
    "addr:housenumber":"8760",
    "addr:postcode":"t5e 0x8",
    "addr:street":"132 Ave Nw",
    "iso:country":"CA",
    "sg:address":"8760 132 Ave NW",
    "sg:city":"Edmonton",
    "sg:classifiers":[
        {
            "category":"Education",
            "subcategory":"School",
            "type":"Public Place"
        }
    ],
    "sg:phone":"+1 780 476 6251",
    "sg:postcode":"T5E 0X8",
    "sg:province":"AB",
    "wof:name":"Archbishop O'Leary High School",
    "wof:placetype":"venue"
},
  "geometry": {"coordinates":[-113.474151611,53.592300415],"type":"Point"}
}