{
  "type": "Feature",
  "properties": {
    "addr:full":"200 West Beaver Creek Rd Richmond Hill ON L4B 1B4",
    "addr:housenumber":"200",
    "addr:postcode":"l4b 1b4",
    "addr:street":"West Beaver Creek Rd",
    "iso:country":"CA",
    "sg:address":"200 West Beaver Creek Rd",
    "sg:city":"Richmond Hill",
    "sg:classifiers":[
        {
            "category":"Real Estate",
            "subcategory":"Developer",
            "type":"Services"
        }
    ],
    "sg:phone":"+1 905 762 9696",
    "sg:postcode":"L4B 1B4",
    "sg:province":"ON",
    "wof:name":"Generx Inc",
    "wof:placetype":"venue"
},
  "geometry": {"coordinates":[-79.38757324220001,43.8466033936],"type":"Point"}
}