{
  "type": "Feature",
  "properties": {
    "iso:country":"CA",
    "sg:address":"978 1st Ave W",
    "sg:city":"Owen Sound",
    "sg:classifiers":[
        {
            "category":"Real Estate",
            "subcategory":"Developer",
            "type":"Services"
        }
    ],
    "sg:phone":"+1 519 372 9790",
    "sg:postcode":"N4K 4K5",
    "sg:province":"ON",
    "sg:tags":[
        "town",
        "city",
        "land",
        "company",
        "regional",
        "planner"
    ],
    "wof:name":"Cuesta Planning Consultants",
    "wof:placetype":"venue"
},
  "geometry": {"coordinates":[-80.94481658940001,44.5667495728],"type":"Point"}
}