{
  "type": "Feature",
  "properties": {
    "addr:full":"3115 Glen Erin Dr #6 Mississauga ON L5L 1J3",
    "addr:housenumber":"3115",
    "addr:postcode":"l5l 1j3",
    "addr:street":"Glen Erin Dr # 6",
    "iso:country":"CA",
    "sg:address":"3115 Glen Erin Dr #6",
    "sg:city":"Mississauga",
    "sg:classifiers":[
        {
            "category":"Health Services",
            "subcategory":"Doctor",
            "type":"Services"
        }
    ],
    "sg:phone":"+1 905 828 5811",
    "sg:postcode":"L5L 1J3",
    "sg:province":"ON",
    "sg:tags":[
        "dentist"
    ],
    "wof:name":"Hait, Samuel DDS",
    "wof:placetype":"venue"
},
  "geometry": {"coordinates":[-79.677406,43.533703],"type":"Point"}
}