{
  "type": "Feature",
  "properties": {
    "addr:full":"281 Boul Saint-Jean Pointe-Claire QC H9R 3J1",
    "addr:housenumber":"281",
    "addr:postcode":"h9r 3j1",
    "addr:street":"Boul Saint-Jean",
    "iso:country":"CA",
    "sg:address":"281 Boul Saint-Jean",
    "sg:city":"Pointe-Claire",
    "sg:classifiers":[
        {
            "category":"Health Services",
            "subcategory":"Optometrist",
            "type":"Services"
        }
    ],
    "sg:phone":"+1 514 694 0836",
    "sg:postcode":"H9R 3J1",
    "sg:province":"QC",
    "wof:name":"Donnelly, James OD",
    "wof:placetype":"venue"
},
  "geometry": {"coordinates":[-73.8161697388,45.4456558228],"type":"Point"}
}