{
  "type": "Feature",
  "properties": {
    "addr:full":"5117 50 Ave Whitecourt AB T7S 1S8",
    "addr:housenumber":"5117",
    "addr:postcode":"t7s 1s8",
    "addr:street":"50 Ave",
    "iso:country":"CA",
    "sg:address":"5117 50 Ave",
    "sg:city":"Whitecourt",
    "sg:classifiers":[
        {
            "category":"Banks & Credit Unions",
            "subcategory":"Bank",
            "type":"Services"
        }
    ],
    "sg:phone":"+1 780 778 6895",
    "sg:postcode":"T7S 1S8",
    "sg:province":"AB",
    "wof:name":"Royal Bank Financial Group",
    "wof:placetype":"venue"
},
  "geometry": {"coordinates":[-115.687614,54.1404],"type":"Point"}
}