{
  "type": "Feature",
  "properties": {
    "addr:full":"52 Riverside Dr North Vancouver BC V7H 1T4",
    "addr:housenumber":"52",
    "addr:postcode":"v7h 1t4",
    "addr:street":"Riverside Dr",
    "iso:country":"CA",
    "sg:address":"52 Riverside Dr",
    "sg:city":"North Vancouver",
    "sg:classifiers":[
        {
            "category":"Manufacturing",
            "subcategory":"Chemicals & Compounds",
            "type":"Manufacturing & Wholesale Goods"
        }
    ],
    "sg:phone":"+1 604 924 1023",
    "sg:postcode":"V7H 1T4",
    "sg:province":"BC",
    "sg:tags":[
        "fertilizer"
    ],
    "wof:name":"International Bio Recovery",
    "wof:placetype":"venue"
},
  "geometry": {"coordinates":[-123.01411400000001,49.305],"type":"Point"}
}