{
  "type": "Feature",
  "properties": {
    "iso:country":"CA",
    "sg:address":"3333 Kingsway",
    "sg:city":"Vancouver",
    "sg:classifiers":[
        {
            "category":"Wholesale",
            "subcategory":"Machinery & Supplies",
            "type":"Manufacturing & Wholesale Goods"
        }
    ],
    "sg:phone":"+1 604 438 6066",
    "sg:postcode":"V5R 5K6",
    "sg:province":"BC",
    "sg:tags":[
        "salon",
        "beauty"
    ],
    "wof:name":"Jokki Beauty Ctr",
    "wof:placetype":"venue"
},
  "geometry": {"coordinates":[-123.034706116,49.2337112427],"type":"Point"}
}