{
  "type": "Feature",
  "properties": {
    "addr:full":"Pierrefonds QC H8Z 3C2",
    "addr:postcode":"h8z 3c2",
    "iso:country":"CA",
    "sg:city":"Pierrefonds",
    "sg:classifiers":[
        {
            "category":"Real Estate",
            "subcategory":"Real Estate Operator",
            "type":"Services"
        }
    ],
    "sg:phone":"+1 514 626 5155",
    "sg:postcode":"H8Z 3C2",
    "sg:province":"QC",
    "sg:tags":[
        "apartment"
    ],
    "wof:name":"Marina Centre",
    "wof:placetype":"venue"
},
  "geometry": {"coordinates":[-73.8525390625,45.4942131042],"type":"Point"}
}