{
  "type": "Feature",
  "properties": {
    "addr:full":"362 O'Connor Dr East York ON M4J 2V5",
    "addr:housenumber":"362",
    "addr:postcode":"m4j 2v5",
    "addr:street":"O'Connor Dr",
    "iso:country":"CA",
    "sg:address":"362 O'Connor Dr",
    "sg:city":"East York",
    "sg:classifiers":[
        {
            "category":"Building & Trades",
            "subcategory":"Electrical",
            "type":"Services"
        }
    ],
    "sg:phone":"+1 416 929 1700",
    "sg:postcode":"M4J 2V5",
    "sg:province":"ON",
    "sg:tags":[
        "electric",
        "contractor"
    ],
    "wof:name":"Astron Electric Ltd",
    "wof:placetype":"venue"
},
  "geometry": {"coordinates":[-79.353554,43.692467],"type":"Point"}
}