{
  "type": "Feature",
  "properties": {
    "addr:full":"Sainte-Foy QC G1X 4T5",
    "addr:postcode":"g1x 4t5",
    "iso:country":"CA",
    "sg:city":"Sainte-Foy",
    "sg:classifiers":[
        {
            "category":"Freight",
            "type":"Transportation"
        }
    ],
    "sg:phone":"+1 418 652 3399",
    "sg:postcode":"G1X 4T5",
    "sg:province":"QC",
    "sg:tags":[
        "courier"
    ],
    "wof:name":"Nationex",
    "wof:placetype":"venue"
},
  "geometry": {"coordinates":[-71.3308181763,46.7817802429],"type":"Point"}
}