{
  "type": "Feature",
  "properties": {
    "addr:full":"144 Rue Des Ecoliers Saint-Victor QC G0M 2B0",
    "addr:housenumber":"144",
    "addr:postcode":"g0m 2b0",
    "addr:street":"Rue Des Ecoliers",
    "iso:country":"CA",
    "sg:address":"144 Rue Des Ecoliers",
    "sg:city":"Saint-Victor",
    "sg:classifiers":[
        {
            "category":"Personal",
            "subcategory":"Beauty Salon",
            "type":"Services"
        }
    ],
    "sg:phone":"+1 418 588 6996",
    "sg:postcode":"G0M 2B0",
    "sg:province":"QC",
    "wof:name":"Salon DE Beaute Rachel",
    "wof:placetype":"venue"
},
  "geometry": {"coordinates":[-70.902023,46.145958],"type":"Point"}
}