{
  "type": "Feature",
  "properties": {
    "addr:full":"2174 Torquay Mews Mississauga ON L5N 2M6",
    "addr:housenumber":"2174",
    "addr:postcode":"l5n 2m6",
    "addr:street":"Torquay Mews",
    "iso:country":"CA",
    "sg:address":"2174 Torquay Mews",
    "sg:city":"Mississauga",
    "sg:classifiers":[
        {
            "category":"Manufacturing",
            "subcategory":"Rubber & Plastics",
            "type":"Manufacturing & Wholesale Goods"
        }
    ],
    "sg:phone":"+1 905 821 2393",
    "sg:postcode":"L5N 2M6",
    "sg:province":"ON",
    "sg:tags":[
        "mold",
        "maker"
    ],
    "wof:name":"Lung Sang Inc",
    "wof:placetype":"venue"
},
  "geometry": {"coordinates":[-79.741249,43.596149],"type":"Point"}
}