{
  "type": "Feature",
  "properties": {
    "addr:full":"Toronto ON M4S 3C4",
    "addr:postcode":"m4s 3c4",
    "iso:country":"CA",
    "sg:city":"Toronto",
    "sg:classifiers":[
        {
            "category":"Health Services",
            "subcategory":"Doctor",
            "type":"Services"
        }
    ],
    "sg:phone":"+1 416 487 6453",
    "sg:postcode":"M4S 3C4",
    "sg:province":"ON",
    "sg:tags":[
        "dentist"
    ],
    "wof:name":"Dukszta, A DDS",
    "wof:placetype":"venue"
},
  "geometry": {"coordinates":[-79.3962860107,43.697593689],"type":"Point"}
}