{
  "type": "Feature",
  "properties": {
    "addr:full":"1018 Mcnabb St Sault Ste Marie ON P6B 6J1",
    "addr:housenumber":"1018",
    "addr:postcode":"p6b 6j1",
    "addr:street":"Mcnabb St",
    "iso:country":"CA",
    "sg:address":"1018 Mcnabb St",
    "sg:city":"Sault Ste Marie",
    "sg:phone":"+1 705 945 8242",
    "sg:postcode":"P6B 6J1",
    "sg:province":"ON",
    "sg:tags":[
        "oil"
    ],
    "wof:name":"Le Clair Fuels",
    "wof:placetype":"venue"
},
  "geometry": {"coordinates":[-84.27806091310001,46.522769928],"type":"Point"}
}