{
  "type": "Feature",
  "properties": {
    "iso:country":"CA",
    "sg:city":"Surrey",
    "sg:classifiers":[
        {
            "category":"Professional",
            "subcategory":"Accounting & Tax Preparation",
            "type":"Services"
        }
    ],
    "sg:phone":"+1 604 531 4123",
    "sg:postcode":"V4A 9E3",
    "sg:province":"BC",
    "sg:tags":[
        "consultant",
        "accountant"
    ],
    "wof:name":"Watkins Odendaal",
    "wof:placetype":"venue"
},
  "geometry": {"coordinates":[-122.801368713,49.0375823975],"type":"Point"}
}