{
  "type": "Feature",
  "properties": {
    "addr:full":"4375 Rue Ontario E Montreal QC H1V 1K5",
    "addr:housenumber":"4375",
    "addr:postcode":"h1v 1k5",
    "addr:street":"Rue Ontario E",
    "iso:country":"CA",
    "sg:address":"4375 Rue Ontario E",
    "sg:city":"Montreal",
    "sg:classifiers":[
        {
            "category":"Organizations",
            "subcategory":"Professional Association",
            "type":"Services"
        }
    ],
    "sg:phone":"+1 514 256 7787",
    "sg:postcode":"H1V 1K5",
    "sg:province":"QC",
    "wof:name":"Concertation Sur Le Tourisme",
    "wof:placetype":"venue"
},
  "geometry": {"coordinates":[-73.53959655760001,45.5531578064],"type":"Point"}
}