{
  "type": "Feature",
  "properties": {
    "addr:full":"Edmonton AB T5M 4C1",
    "addr:postcode":"t5m 4c1",
    "iso:country":"CA",
    "sg:city":"Edmonton",
    "sg:classifiers":[
        {
            "category":"Manufacturing",
            "subcategory":"Toys & Sporting Goods",
            "type":"Manufacturing & Wholesale Goods"
        }
    ],
    "sg:phone":"+1 780 455 5146",
    "sg:postcode":"T5M 4C1",
    "sg:province":"AB",
    "sg:tags":[
        "equipment",
        "designer",
        "dealer",
        "pool",
        "swimming"
    ],
    "wof:name":"Cam-Mac Pools & Installations",
    "wof:placetype":"venue"
},
  "geometry": {"coordinates":[-113.597382,53.56855],"type":"Point"}
}