{
  "type": "Feature",
  "properties": {
    "iso:country":"CA",
    "sg:address":"2406 Rue Gertrude",
    "sg:city":"Carignan",
    "sg:classifiers":[
        {
            "category":"Health Services",
            "subcategory":"Doctor",
            "type":"Services"
        }
    ],
    "sg:phone":"+1 450 658 7809",
    "sg:postcode":"J3L 4H1",
    "sg:province":"QC",
    "sg:tags":[
        "clinic"
    ],
    "wof:name":"Clinique-Acupuncture Guilmain",
    "wof:placetype":"venue"
},
  "geometry": {"coordinates":[-73.3162689209,45.4512481689],"type":"Point"}
}