{
  "type": "Feature",
  "properties": {
    "addr:full":"1385 Alberni Hwy Parksville BC V9P 2B8",
    "addr:housenumber":"1385",
    "addr:postcode":"v9p 2b8",
    "addr:street":"Alberni Hwy",
    "iso:country":"CA",
    "sg:address":"1385 Alberni Hwy",
    "sg:city":"Parksville",
    "sg:classifiers":[
        {
            "category":"Restaurant",
            "type":"Food & Drink"
        }
    ],
    "sg:phone":"+1 250 248 4445",
    "sg:postcode":"V9P 2B8",
    "sg:province":"BC",
    "wof:name":"Trees Restaurant",
    "wof:placetype":"venue"
},
  "geometry": {"coordinates":[-124.32453155499999,49.3070106506],"type":"Point"}
}