{
  "type": "Feature",
  "properties": {
    "iso:country":"CA",
    "sg:address":"240 Lions Way",
    "sg:city":"Bowser",
    "sg:classifiers":[
        {
            "category":"Organizations",
            "subcategory":"Professional Association",
            "type":"Services"
        }
    ],
    "sg:phone":"+1 250 757 9711",
    "sg:postcode":"V0R 1G0",
    "sg:province":"BC",
    "wof:name":"Lighthouse Community Ctr",
    "wof:placetype":"venue"
},
  "geometry": {"coordinates":[-124.70038604699999,49.445110321],"type":"Point"}
}