{
  "type": "Feature",
  "properties": {
    "addr:full":"108 Hall St Lockeport NS B0T 1L0",
    "addr:housenumber":"108",
    "addr:postcode":"b0t 1l0",
    "addr:street":"Hall St",
    "iso:country":"CA",
    "sg:address":"108 Hall St",
    "sg:city":"Lockeport",
    "sg:classifiers":[
        {
            "category":"Organizations",
            "subcategory":"Religious Organization",
            "type":"Services"
        }
    ],
    "sg:phone":"+1 902 656 2653",
    "sg:postcode":"B0T 1L0",
    "sg:province":"NS",
    "sg:tags":[
        "church"
    ],
    "wof:name":"Lockeport Baptist Independent",
    "wof:placetype":"venue"
},
  "geometry": {"coordinates":[-65.115334,43.697021],"type":"Point"}
}