{
  "type": "Feature",
  "properties": {
    "addr:full":"Edmonton AB T5M 3V6",
    "addr:postcode":"t5m 3v6",
    "iso:country":"CA",
    "sg:city":"Edmonton",
    "sg:classifiers":[
        {
            "category":"Manufacturing",
            "subcategory":"Printing",
            "type":"Manufacturing & Wholesale Goods"
        }
    ],
    "sg:phone":"+1 780 483 7598",
    "sg:postcode":"T5M 3V6",
    "sg:province":"AB",
    "sg:tags":[
        "printer"
    ],
    "wof:name":"Provincial Laminating Supplies",
    "wof:placetype":"venue"
},
  "geometry": {"coordinates":[-113.611236572,53.5672836304],"type":"Point"}
}