{
  "type": "Feature",
  "properties": {
    "iso:country":"CA",
    "sg:city":"Vancouver",
    "sg:classifiers":[
        {
            "category":"Health Services",
            "subcategory":"Medical Lab",
            "type":"Services"
        }
    ],
    "sg:phone":"+1 604 266 1121",
    "sg:postcode":"V6N 3E6",
    "sg:province":"BC",
    "sg:tags":[
        "laboratory"
    ],
    "wof:name":"Technident Laboratory Inc",
    "wof:placetype":"venue"
},
  "geometry": {"coordinates":[-123.183418274,49.2346916199],"type":"Point"}
}