{
  "type": "Feature",
  "properties": {
    "iso:country":"CA",
    "sg:city":"Brampton",
    "sg:classifiers":[
        {
            "category":"Home & Garden",
            "subcategory":"Furniture",
            "type":"Retail Goods"
        }
    ],
    "sg:phone":"+1 905 455 5676",
    "sg:postcode":"L6W 4S2",
    "sg:province":"ON",
    "wof:name":"Moga Furniture Inc",
    "wof:placetype":"venue"
},
  "geometry": {"coordinates":[-79.7203674316,43.6774787903],"type":"Point"}
}