{
  "type": "Feature",
  "properties": {
    "addr:full":"3055 Sydenham Rd Elginburg ON K0H 1M0",
    "addr:housenumber":"3055",
    "addr:postcode":"k0h 1m0",
    "addr:street":"Sydenham Rd",
    "iso:country":"CA",
    "sg:address":"3055 Sydenham Rd",
    "sg:city":"Elginburg",
    "sg:classifiers":[
        {
            "category":"Professional",
            "subcategory":"Business Services",
            "type":"Services"
        }
    ],
    "sg:phone":"+1 613 542 4900",
    "sg:postcode":"K0H 1M0",
    "sg:province":"ON",
    "sg:tags":[
        "interior",
        "consultant",
        "design",
        "decorator"
    ],
    "wof:name":"Tall Pines Interiors Inc",
    "wof:placetype":"venue"
},
  "geometry": {"coordinates":[-76.54791299999999,44.339432],"type":"Point"}
}