{
  "type": "Feature",
  "properties": {
    "addr:full":"520 Parliament St Toronto ON M4X 1P5",
    "addr:housenumber":"520",
    "addr:postcode":"m4x 1p5",
    "addr:street":"Parliament St",
    "iso:country":"CA",
    "sg:address":"520 Parliament St",
    "sg:city":"Toronto",
    "sg:classifiers":[
        {
            "category":"Food & Beverages",
            "subcategory":"Groceries & Convenience Stores",
            "type":"Retail Goods"
        }
    ],
    "sg:phone":"+1 416 921 0624",
    "sg:postcode":"M4X 1P5",
    "sg:province":"ON",
    "wof:name":"Fairway Variety",
    "wof:placetype":"venue"
},
  "geometry": {"coordinates":[-79.3687515259,43.665927887],"type":"Point"}
}