{
  "type": "Feature",
  "properties": {
    "iso:country":"CA",
    "sg:address":"84 Boul Industriel",
    "sg:city":"Repentigny",
    "sg:classifiers":[
        {
            "category":"Cinema",
            "subcategory":"Movie Rental",
            "type":"Entertainment"
        }
    ],
    "sg:phone":"+1 450 582 3038",
    "sg:postcode":"J6A 4X6",
    "sg:province":"QC",
    "sg:tags":[
        "leasing",
        "video",
        "disc",
        "tape"
    ],
    "wof:name":"Superclub Videotron Ltee",
    "wof:placetype":"venue"
},
  "geometry": {"coordinates":[-73.44258880620001,45.7542228699],"type":"Point"}
}