{
  "type": "Feature",
  "properties": {
    "addr:full":"Niagara Falls ON L2G 7K3",
    "addr:postcode":"l2g 7k3",
    "iso:country":"CA",
    "sg:city":"Niagara Falls",
    "sg:classifiers":[
        {
            "category":"Shopping",
            "subcategory":"Computers & Home Electronics",
            "type":"Retail Goods"
        }
    ],
    "sg:phone":"+1 905 358 5878",
    "sg:postcode":"L2G 7K3",
    "sg:province":"ON",
    "sg:tags":[
        "equipment",
        "parts",
        "electronic",
        "supply"
    ],
    "wof:name":"Just Accessories",
    "wof:placetype":"venue"
},
  "geometry": {"coordinates":[-79.1118927002,43.0703125],"type":"Point"}
}