{
  "type": "Feature",
  "properties": {
    "iso:country":"CA",
    "sg:address":"6400 Ch DE LA Cote-DE-Liesse",
    "sg:city":"Saint-Laurent",
    "sg:classifiers":[
        {
            "category":"Manufacturing",
            "subcategory":"Textiles",
            "type":"Manufacturing & Wholesale Goods"
        }
    ],
    "sg:phone":"+1 514 737 5665",
    "sg:postcode":"H4T 1E3",
    "sg:province":"QC",
    "sg:tags":[
        "bathing",
        "suit"
    ],
    "wof:name":"Sgs Inc",
    "wof:placetype":"venue"
},
  "geometry": {"coordinates":[-73.6903839111,45.4861755371],"type":"Point"}
}