{
  "type": "Feature",
  "properties": {
    "addr:full":"296 Horsham Ave North York ON M2R 1G6",
    "addr:housenumber":"296",
    "addr:postcode":"m2r 1g6",
    "addr:street":"Horsham Ave",
    "iso:country":"CA",
    "sg:address":"296 Horsham Ave",
    "sg:city":"North York",
    "sg:classifiers":[
        {
            "category":"Building & Trades",
            "subcategory":"Landscaping Services",
            "type":"Services"
        }
    ],
    "sg:phone":"+1 416 224 1411",
    "sg:postcode":"M2R 1G6",
    "sg:province":"ON",
    "sg:tags":[
        "landscape",
        "contractor"
    ],
    "wof:name":"D & R Mazza Landscape Mntnc",
    "wof:placetype":"venue"
},
  "geometry": {"coordinates":[-79.430573,43.771194],"type":"Point"}
}