{
  "type": "Feature",
  "properties": {
    "addr:full":"1 Greenfield Rd Lindsay ON K9V 5N4",
    "addr:housenumber":"1",
    "addr:postcode":"k9v 5n4",
    "addr:street":"Greenfield Rd",
    "iso:country":"CA",
    "sg:address":"1 Greenfield Rd",
    "sg:city":"Lindsay",
    "sg:classifiers":[
        {
            "category":"Wholesale",
            "subcategory":"Farm Supplies",
            "type":"Manufacturing & Wholesale Goods"
        }
    ],
    "sg:phone":"+1 705 324 6273",
    "sg:postcode":"K9V 5N4",
    "sg:province":"ON",
    "sg:tags":[
        "bulb",
        "seed"
    ],
    "wof:name":"Mapleseed Inc",
    "wof:placetype":"venue"
},
  "geometry": {"coordinates":[-78.767899,44.347439],"type":"Point"}
}