{
  "type": "Feature",
  "properties": {
    "addr:full":"Port Alberni BC V9Y 1T7",
    "addr:postcode":"v9y 1t7",
    "iso:country":"CA",
    "sg:city":"Port Alberni",
    "sg:classifiers":[
        {
            "category":"Food & Beverages",
            "subcategory":"Bakery",
            "type":"Retail Goods"
        }
    ],
    "sg:phone":"+1 250 723 2213",
    "sg:postcode":"V9Y 1T7",
    "sg:province":"BC",
    "sg:tags":[
        "doughnut"
    ],
    "wof:name":"Donut Shop",
    "wof:placetype":"venue"
},
  "geometry": {"coordinates":[-124.81388855,49.234462738],"type":"Point"}
}