{
  "type": "Feature",
  "properties": {
    "addr:full":"2284 Douglas Rd Burnaby BC V5C 5A7",
    "addr:housenumber":"2284",
    "addr:postcode":"v5c 5a7",
    "addr:street":"Douglas Rd",
    "iso:country":"CA",
    "sg:address":"2284 Douglas Rd",
    "sg:city":"Burnaby",
    "sg:classifiers":[
        {
            "category":"Retail",
            "subcategory":"Portrait Studio",
            "type":"Services"
        }
    ],
    "sg:phone":"+1 604 299 8900",
    "sg:postcode":"V5C 5A7",
    "sg:province":"BC",
    "sg:tags":[
        "photographer"
    ],
    "wof:name":"Mjm Studios School Photos",
    "wof:placetype":"venue"
},
  "geometry": {"coordinates":[-122.988693,49.263699],"type":"Point"}
}