{
  "type": "Feature",
  "properties": {
    "iso:country":"CA",
    "sg:address":"760 Topsail Rd",
    "sg:city":"Mount Pearl",
    "sg:classifiers":[
        {
            "category":"Shopping",
            "type":"Retail Goods"
        }
    ],
    "sg:phone":"+1 709 745 5133",
    "sg:postcode":"A1N 3J5",
    "sg:province":"NL",
    "sg:tags":[
        "hearing",
        "equipment",
        "supply",
        "impaired"
    ],
    "wof:name":"Newfoundland Hearing Health",
    "wof:placetype":"venue"
},
  "geometry": {"coordinates":[-52.778191,47.523132],"type":"Point"}
}