{
  "type": "Feature",
  "properties": {
    "addr:full":"110 Cumberland St Toronto ON M5R 1A6",
    "addr:housenumber":"110",
    "addr:postcode":"m5r 1a6",
    "addr:street":"Cumberland St",
    "iso:country":"CA",
    "sg:address":"110 Cumberland St",
    "sg:city":"Toronto",
    "sg:classifiers":[
        {
            "category":"Personal",
            "subcategory":"Beauty Salon",
            "type":"Services"
        }
    ],
    "sg:phone":"+1 416 324 9008",
    "sg:postcode":"M5R 1A6",
    "sg:province":"ON",
    "wof:name":"Salon Vivace",
    "wof:placetype":"venue"
},
  "geometry": {"coordinates":[-79.391708374,43.6703033447],"type":"Point"}
}