{
  "type": "Feature",
  "properties": {
    "iso:country":"CA",
    "sg:address":"202 Barnardo Ave",
    "sg:city":"Peterborough",
    "sg:classifiers":[
        {
            "category":"Health Services",
            "subcategory":"Health Practitioner",
            "type":"Services"
        }
    ],
    "sg:phone":"+1 705 743 1731",
    "sg:postcode":"K9H 5V5",
    "sg:province":"ON",
    "sg:tags":[
        "nurse",
        "registry"
    ],
    "wof:name":"Pedicare Nursing Svc",
    "wof:placetype":"venue"
},
  "geometry": {"coordinates":[-78.322098,44.319813],"type":"Point"}
}