{
  "type": "Feature",
  "properties": {
    "addr:full":"Calgary AB T2E 6R9",
    "addr:postcode":"t2e 6r9",
    "iso:country":"CA",
    "sg:city":"Calgary",
    "sg:classifiers":[
        {
            "category":"Retail",
            "subcategory":"Auto Repair",
            "type":"Services"
        }
    ],
    "sg:phone":"+1 403 276 3700",
    "sg:postcode":"T2E 6R9",
    "sg:province":"AB",
    "sg:tags":[
        "automobile",
        "restoration",
        "classic"
    ],
    "wof:name":"British Sportscar Coachworks",
    "wof:placetype":"venue"
},
  "geometry": {"coordinates":[-114.053207398,51.0866737366],"type":"Point"}
}