{
  "type": "Feature",
  "properties": {
    "addr:full":"1023 Wellington St W Ottawa ON K1Y 2Y1",
    "addr:housenumber":"1023",
    "addr:postcode":"k1y 2y1",
    "addr:street":"Wellington St W",
    "iso:country":"CA",
    "sg:address":"1023 Wellington St W",
    "sg:city":"Ottawa",
    "sg:classifiers":[
        {
            "category":"Food & Beverages",
            "subcategory":"Groceries & Convenience Stores",
            "type":"Retail Goods"
        }
    ],
    "sg:phone":"+1 613 722 7497",
    "sg:postcode":"K1Y 2Y1",
    "sg:province":"ON",
    "wof:name":"Mac's Convenience Stores Ltd",
    "wof:placetype":"venue"
},
  "geometry": {"coordinates":[-75.723747,45.404957],"type":"Point"}
}