{
  "type": "Feature",
  "properties": {
    "addr:full":"102 Main St Picton ON K0K 2T0",
    "addr:housenumber":"102",
    "addr:postcode":"k0k 2t0",
    "addr:street":"Main St",
    "iso:country":"CA",
    "sg:address":"102 Main St",
    "sg:city":"Picton",
    "sg:classifiers":[
        {
            "category":"Real Estate",
            "subcategory":"Real Estate Agent",
            "type":"Services"
        }
    ],
    "sg:phone":"+1 613 476 2100",
    "sg:postcode":"K0K 2T0",
    "sg:province":"ON",
    "wof:name":"Lanthorn Real Estate Ltd",
    "wof:placetype":"venue"
},
  "geometry": {"coordinates":[-77.1462020874,44.0050354004],"type":"Point"}
}