{
  "type": "Feature",
  "properties": {
    "addr:full":"1050 Kelly Lake Rd Sudbury ON P3E 5P4",
    "addr:housenumber":"1050",
    "addr:postcode":"p3e 5p4",
    "addr:street":"Kelly Lake Rd",
    "iso:country":"CA",
    "sg:address":"1050 Kelly Lake Rd",
    "sg:city":"Sudbury",
    "sg:classifiers":[
        {
            "category":"Autos & Motor Vehicles",
            "subcategory":"Automobile Sales",
            "type":"Retail Goods"
        }
    ],
    "sg:phone":"+1 705 688 1700",
    "sg:postcode":"P3E 5P4",
    "sg:province":"ON",
    "sg:tags":[
        "truck"
    ],
    "wof:name":"Kenworth Sudbury",
    "wof:placetype":"venue"
},
  "geometry": {"coordinates":[-81.037109375,46.4697532654],"type":"Point"}
}