{
  "type": "Feature",
  "properties": {
    "addr:full":"33 Athabasca Ave Devon AB T9G 1G5",
    "addr:housenumber":"33",
    "addr:postcode":"t9g 1g5",
    "addr:street":"Athabasca Ave",
    "iso:country":"CA",
    "sg:address":"33 Athabasca Ave",
    "sg:city":"Devon",
    "sg:classifiers":[
        {
            "category":"Banks & Credit Unions",
            "subcategory":"Bank",
            "type":"Services"
        }
    ],
    "sg:phone":"+1 780 987 3368",
    "sg:postcode":"T9G 1G5",
    "sg:province":"AB",
    "wof:name":"Royal Bank Financial Group",
    "wof:placetype":"venue"
},
  "geometry": {"coordinates":[-113.729378,53.365608],"type":"Point"}
}