{
  "type": "Feature",
  "properties": {
    "iso:country":"CA",
    "sg:address":"33090 1st Ave",
    "sg:city":"Mission",
    "sg:classifiers":[
        {
            "category":"Shopping",
            "subcategory":"Used Merchandise",
            "type":"Retail Goods"
        }
    ],
    "sg:phone":"+1 604 826 8021",
    "sg:postcode":"V2V 1G3",
    "sg:province":"BC",
    "sg:tags":[
        "pawnbroker"
    ],
    "wof:name":"Belle's New & Used Collectable",
    "wof:placetype":"venue"
},
  "geometry": {"coordinates":[-122.307533264,49.1342468262],"type":"Point"}
}