{
  "type": "Feature",
  "properties": {
    "addr:full":"10021 Hwy 50 Kleinburg ON L0J 1C0",
    "addr:housenumber":"10021",
    "addr:postcode":"l0j 1c0",
    "addr:street":"Hwy 50",
    "iso:country":"CA",
    "sg:address":"10021 Hwy 50",
    "sg:city":"Kleinburg",
    "sg:classifiers":[
        {
            "category":"Retail",
            "subcategory":"Auto Repair",
            "type":"Services"
        }
    ],
    "sg:phone":"+1 905 893 3275",
    "sg:postcode":"L0J 1C0",
    "sg:province":"ON",
    "sg:tags":[
        "repairing",
        "automobile"
    ],
    "wof:name":"Tpi Automotive",
    "wof:placetype":"venue"
},
  "geometry": {"coordinates":[-79.6797332764,43.821472168],"type":"Point"}
}