{
  "type": "Feature",
  "properties": {
    "addr:full":"20385 64 Ave Langley BC V2Y 1N5",
    "addr:housenumber":"20385",
    "addr:postcode":"v2y 1n5",
    "addr:street":"64 Ave",
    "iso:country":"CA",
    "sg:address":"20385 64 Ave",
    "sg:city":"Langley",
    "sg:classifiers":[
        {
            "category":"Organizations",
            "subcategory":"Religious Organization",
            "type":"Services"
        }
    ],
    "sg:phone":"+1 604 514 2000",
    "sg:postcode":"V2Y 1N5",
    "sg:province":"BC",
    "sg:tags":[
        "church"
    ],
    "wof:name":"Campus Crusade For Christ",
    "wof:placetype":"venue"
},
  "geometry": {"coordinates":[-122.657546997,49.1190681458],"type":"Point"}
}