{
  "type": "Feature",
  "properties": {
    "iso:country":"CA",
    "sg:address":"300 Lakeshore Dr #708",
    "sg:city":"North Bay",
    "sg:classifiers":[
        {
            "category":"Shopping",
            "subcategory":"Clothing, Apparel, & Fashions",
            "type":"Retail Goods"
        }
    ],
    "sg:phone":"+1 705 476 9393",
    "sg:postcode":"P1A 3V2",
    "sg:province":"ON",
    "wof:name":"Alia",
    "wof:placetype":"venue"
},
  "geometry": {"coordinates":[-79.44878387449999,46.2828521729],"type":"Point"}
}