{
  "type": "Feature",
  "properties": {
    "addr:full":"1114 Rue Gauguin Boisbriand QC J7G 3A5",
    "addr:housenumber":"1114",
    "addr:postcode":"j7g 3a5",
    "addr:street":"Rue Gauguin",
    "iso:country":"CA",
    "sg:address":"1114 Rue Gauguin",
    "sg:city":"Boisbriand",
    "sg:classifiers":[
        {
            "category":"Home & Garden",
            "subcategory":"Furniture",
            "type":"Retail Goods"
        }
    ],
    "sg:phone":"+1 450 434 1143",
    "sg:postcode":"J7G 3A5",
    "sg:province":"QC",
    "sg:tags":[
        "equipment",
        "kitchen",
        "cabinet"
    ],
    "wof:name":"Armoire Luxorama Rosemere",
    "wof:placetype":"venue"
},
  "geometry": {"coordinates":[-73.833527,45.619205],"type":"Point"}
}