{
  "type": "Feature",
  "properties": {
    "iso:country":"CA",
    "sg:city":"Lower Woods Harbour",
    "sg:classifiers":[
        {
            "category":"Professional",
            "subcategory":"Business Services",
            "type":"Services"
        }
    ],
    "sg:phone":"+1 902 723 0169",
    "sg:postcode":"B0W 2E0",
    "sg:province":"NS",
    "sg:tags":[
        "embroidery"
    ],
    "wof:name":"Rose's Creative Stitches",
    "wof:placetype":"venue"
},
  "geometry": {"coordinates":[-65.7338256836,43.5277328491],"type":"Point"}
}