{
  "type": "Feature",
  "properties": {
    "addr:full":"627 Seymour Ave SW Calgary AB T2W 0N5",
    "addr:housenumber":"627",
    "addr:postcode":"t2w 0n5",
    "addr:street":"Seymour Ave Sw",
    "iso:country":"CA",
    "sg:address":"627 Seymour Ave SW",
    "sg:city":"Calgary",
    "sg:classifiers":[
        {
            "category":"Building & Trades",
            "subcategory":"Electrical",
            "type":"Services"
        }
    ],
    "sg:phone":"+1 403 253 4997",
    "sg:postcode":"T2W 0N5",
    "sg:province":"AB",
    "sg:tags":[
        "electric",
        "contractor"
    ],
    "wof:name":"Flh Electric",
    "wof:placetype":"venue"
},
  "geometry": {"coordinates":[-114.07828499999999,50.961224],"type":"Point"}
}