{
  "type": "Feature",
  "properties": {
    "addr:full":"Weyburn SK S4H 3A8",
    "addr:postcode":"s4h 3a8",
    "iso:country":"CA",
    "sg:city":"Weyburn",
    "sg:classifiers":[
        {
            "category":"Real Estate",
            "subcategory":"Real Estate Operator",
            "type":"Services"
        }
    ],
    "sg:phone":"+1 306 842 6768",
    "sg:postcode":"S4H 3A8",
    "sg:province":"SK",
    "sg:tags":[
        "apartment"
    ],
    "wof:name":"Greystone Manor",
    "wof:placetype":"venue"
},
  "geometry": {"coordinates":[-103.82875799999999,49.664227],"type":"Point"}
}