{
  "type": "Feature",
  "properties": {
    "addr:full":"567 Queen St W Toronto ON M5V 2B6",
    "addr:housenumber":"567",
    "addr:postcode":"m5v 2b6",
    "addr:street":"Queen St W",
    "iso:country":"CA",
    "sg:address":"567 Queen St W",
    "sg:city":"Toronto",
    "sg:classifiers":[
        {
            "category":"Restaurant",
            "type":"Food & Drink"
        }
    ],
    "sg:phone":"+1 416 504 1626",
    "sg:postcode":"M5V 2B6",
    "sg:province":"ON",
    "sg:tags":[
        "delivery"
    ],
    "wof:name":"Left Bank",
    "wof:placetype":"venue"
},
  "geometry": {"coordinates":[-79.400734,43.647709],"type":"Point"}
}