{
  "type": "Feature",
  "properties": {
    "addr:full":"71 George St S Brampton ON L6Y 1P4",
    "addr:housenumber":"71",
    "addr:postcode":"l6y 1p4",
    "addr:street":"George St S",
    "iso:country":"CA",
    "sg:address":"71 George St S",
    "sg:city":"Brampton",
    "sg:classifiers":[
        {
            "category":"Building & Trades",
            "subcategory":"Pest Control",
            "type":"Services"
        }
    ],
    "sg:phone":"+1 905 451 5937",
    "sg:postcode":"L6Y 1P4",
    "sg:province":"ON",
    "wof:name":"Abate Pest Control Ltd",
    "wof:placetype":"venue"
},
  "geometry": {"coordinates":[-79.759781,43.6842],"type":"Point"}
}