{
  "type": "Feature",
  "properties": {
    "addr:full":"716 Rte 220 Bonsecours QC J0E 1H0",
    "addr:housenumber":"716",
    "addr:postcode":"j0e 1h0",
    "addr:street":"Rte 220",
    "iso:country":"CA",
    "sg:address":"716 Rte 220",
    "sg:city":"Bonsecours",
    "sg:classifiers":[
        {
            "category":"Home & Garden",
            "subcategory":"Garden Supply",
            "type":"Retail Goods"
        }
    ],
    "sg:phone":"+1 450 532 4622",
    "sg:postcode":"J0E 1H0",
    "sg:province":"QC",
    "sg:tags":[
        "lawn",
        "scooter",
        "motor",
        "motorcycle"
    ],
    "wof:name":"Garage C Lussier Inc",
    "wof:placetype":"venue"
},
  "geometry": {"coordinates":[-72.293396,45.40377],"type":"Point"}
}