{
  "type": "Feature",
  "properties": {
    "addr:full":"1365 Dugald Rd Winnipeg MB R2J 0H3",
    "addr:housenumber":"1365",
    "addr:postcode":"r2j 0h3",
    "addr:street":"Dugald Rd",
    "iso:country":"CA",
    "sg:address":"1365 Dugald Rd",
    "sg:city":"Winnipeg",
    "sg:classifiers":[
        {
            "category":"Autos & Motor Vehicles",
            "subcategory":"Automobile Sales",
            "type":"Retail Goods"
        }
    ],
    "sg:phone":"+1 204 956 9277",
    "sg:postcode":"R2J 0H3",
    "sg:province":"MB",
    "sg:tags":[
        "equipment",
        "aircraft",
        "parts",
        "supply"
    ],
    "wof:name":"Winnipeg Aero Space Products",
    "wof:placetype":"venue"
},
  "geometry": {"coordinates":[-97.056366,49.88607],"type":"Point"}
}