{
  "type": "Feature",
  "properties": {
    "addr:full":"641 Somerset St W Ottawa ON K1R 5K3",
    "addr:housenumber":"641",
    "addr:postcode":"k1r 5k3",
    "addr:street":"Somerset St W",
    "iso:country":"CA",
    "sg:address":"641 Somerset St W",
    "sg:city":"Ottawa",
    "sg:classifiers":[
        {
            "category":"Restaurant",
            "type":"Food & Drink"
        }
    ],
    "sg:phone":"+1 613 569 9993",
    "sg:postcode":"K1R 5K3",
    "sg:province":"ON",
    "wof:name":"Man's Kitchen",
    "wof:placetype":"venue"
},
  "geometry": {"coordinates":[-75.704964,45.411957],"type":"Point"}
}