{
  "type": "Feature",
  "properties": {
    "iso:country":"CA",
    "sg:city":"Isle-Aux-Coudres",
    "sg:classifiers":[
        {
            "category":"Shopping",
            "subcategory":"Used Merchandise",
            "type":"Retail Goods"
        }
    ],
    "sg:phone":"+1 418 438 2675",
    "sg:postcode":"G0A 1X0",
    "sg:province":"QC",
    "sg:tags":[
        "shop",
        "gift"
    ],
    "wof:name":"Grenier DE Jeanne",
    "wof:placetype":"venue"
},
  "geometry": {"coordinates":[-70.4187545776,47.3759918213],"type":"Point"}
}