{
  "type": "Feature",
  "properties": {
    "addr:full":"91 Lake Dr E Keswick ON L4P 3E9",
    "addr:housenumber":"91",
    "addr:postcode":"l4p 3e9",
    "addr:street":"Lake Dr E",
    "iso:country":"CA",
    "sg:address":"91 Lake Dr E",
    "sg:city":"Keswick",
    "sg:classifiers":[
        {
            "category":"Building & Trades",
            "subcategory":"Construction",
            "type":"Services"
        }
    ],
    "sg:phone":"+1 905 989 1112",
    "sg:postcode":"L4P 3E9",
    "sg:province":"ON",
    "sg:tags":[
        "contractor"
    ],
    "wof:name":"Sharp Rk Construction",
    "wof:placetype":"venue"
},
  "geometry": {"coordinates":[-79.45631408689999,44.3076934814],"type":"Point"}
}