{
  "type": "Feature",
  "properties": {
    "addr:full":"1525 Victoria St Prince George BC V2L 2L4",
    "addr:housenumber":"1525",
    "addr:postcode":"v2l 2l4",
    "addr:street":"Victoria St",
    "iso:country":"CA",
    "sg:address":"1525 Victoria St",
    "sg:city":"Prince George",
    "sg:classifiers":[
        {
            "category":"Health Services",
            "subcategory":"Chiropractor",
            "type":"Services"
        }
    ],
    "sg:phone":"+1 250 562 2377",
    "sg:postcode":"V2L 2L4",
    "sg:province":"BC",
    "wof:name":"T C Warawa Inc",
    "wof:placetype":"venue"
},
  "geometry": {"coordinates":[-122.755332947,53.9103050232],"type":"Point"}
}