{
  "type": "Feature",
  "properties": {
    "addr:full":"337 William Ave Winnipeg MB R3A 0H8",
    "addr:housenumber":"337",
    "addr:postcode":"r3a 0h8",
    "addr:street":"William Ave",
    "iso:country":"CA",
    "sg:address":"337 William Ave",
    "sg:city":"Winnipeg",
    "sg:classifiers":[
        {
            "category":"Shopping",
            "type":"Retail Goods"
        }
    ],
    "sg:phone":"+1 204 943 7779",
    "sg:postcode":"R3A 0H8",
    "sg:province":"MB",
    "sg:tags":[
        "church",
        "religious",
        "supply"
    ],
    "wof:name":"Stephanchew Church Goods",
    "wof:placetype":"venue"
},
  "geometry": {"coordinates":[-97.1427993774,49.9002075195],"type":"Point"}
}