{
  "type": "Feature",
  "properties": {
    "iso:country":"CA",
    "sg:city":"Hagar",
    "sg:classifiers":[
        {
            "category":"Retail",
            "subcategory":"Auto Repair",
            "type":"Services"
        }
    ],
    "sg:phone":"+1 705 967 5515",
    "sg:postcode":"P0M 1X0",
    "sg:province":"ON",
    "sg:tags":[
        "repairing",
        "automobile"
    ],
    "wof:name":"Hagar's Service",
    "wof:placetype":"venue"
},
  "geometry": {"coordinates":[-80.4162445068,46.4543876648],"type":"Point"}
}