{
  "type": "Feature",
  "properties": {
    "addr:full":"Utopia ON L0M 1T0",
    "addr:postcode":"l0m 1t0",
    "iso:country":"CA",
    "sg:city":"Utopia",
    "sg:classifiers":[
        {
            "category":"Building & Trades",
            "subcategory":"Electrical",
            "type":"Services"
        }
    ],
    "sg:phone":"+1 705 722 0421",
    "sg:postcode":"L0M 1T0",
    "sg:province":"ON",
    "sg:tags":[
        "electric",
        "contractor"
    ],
    "wof:name":"Georgis Electrical Contracting",
    "wof:placetype":"venue"
},
  "geometry": {"coordinates":[-79.83861541749999,44.3324699402],"type":"Point"}
}