{
  "type": "Feature",
  "properties": {
    "addr:full":"3963 Rue Wellington Verdun QC H4G 1V6",
    "addr:housenumber":"3963",
    "addr:postcode":"h4g 1v6",
    "addr:street":"Rue Wellington",
    "iso:country":"CA",
    "sg:address":"3963 Rue Wellington",
    "sg:city":"Verdun",
    "sg:classifiers":[
        {
            "category":"Shopping",
            "subcategory":"Shoes",
            "type":"Retail Goods"
        }
    ],
    "sg:phone":"+1 514 762 5184",
    "sg:postcode":"H4G 1V6",
    "sg:province":"QC",
    "wof:name":"Chaussures Dupuis",
    "wof:placetype":"venue"
},
  "geometry": {"coordinates":[-73.567093,45.464172],"type":"Point"}
}