{
  "type": "Feature",
  "properties": {
    "addr:full":"44 Broadway St Redvers SK S0C 2H0",
    "addr:housenumber":"44",
    "addr:postcode":"s0c 2h0",
    "addr:street":"Broadway St",
    "iso:country":"CA",
    "sg:address":"44 Broadway St",
    "sg:city":"Redvers",
    "sg:classifiers":[
        {
            "category":"Education",
            "subcategory":"School",
            "type":"Public Place"
        }
    ],
    "sg:phone":"+1 306 452 6161",
    "sg:postcode":"S0C 2H0",
    "sg:province":"SK",
    "wof:name":"Redvers Schools",
    "wof:placetype":"venue"
},
  "geometry": {"coordinates":[-101.699142456,49.5762710571],"type":"Point"}
}