{
  "type": "Feature",
  "properties": {
    "addr:full":"293 Wilson St E Ancaster ON L9G 2B8",
    "addr:housenumber":"293",
    "addr:postcode":"l9g 2b8",
    "addr:street":"Wilson St E",
    "iso:country":"CA",
    "sg:address":"293 Wilson St E",
    "sg:city":"Ancaster",
    "sg:classifiers":[
        {
            "category":"Insurance",
            "subcategory":"Insurance Agent",
            "type":"Services"
        }
    ],
    "sg:phone":"+1 905 648 0818",
    "sg:postcode":"L9G 2B8",
    "sg:province":"ON",
    "wof:name":"Neziol Group",
    "wof:placetype":"venue"
},
  "geometry": {"coordinates":[-79.9774017334,43.2253112793],"type":"Point"}
}