{
  "type": "Feature",
  "properties": {
    "addr:full":"101 Broadway St Forest ON N0N 1J0",
    "addr:housenumber":"101",
    "addr:postcode":"n0n 1j0",
    "addr:street":"Broadway St",
    "iso:country":"CA",
    "sg:address":"101 Broadway St",
    "sg:city":"Forest",
    "sg:classifiers":[
        {
            "category":"Government",
            "subcategory":"Police Station",
            "type":"Public Place"
        }
    ],
    "sg:phone":"+1 519 786 2349",
    "sg:postcode":"N0N 1J0",
    "sg:province":"ON",
    "sg:tags":[
        "department"
    ],
    "wof:name":"Ontario Provincial Police",
    "wof:placetype":"venue"
},
  "geometry": {"coordinates":[-81.99239300000001,43.099808],"type":"Point"}
}