{
  "type": "Feature",
  "properties": {
    "iso:country":"CA",
    "sg:address":"88 Shoemaker St",
    "sg:city":"Kitchener",
    "sg:classifiers":[
        {
            "category":"Building & Trades",
            "subcategory":"Plumbing",
            "type":"Services"
        }
    ],
    "sg:phone":"+1 519 748 0935",
    "sg:postcode":"N2E 3G4",
    "sg:province":"ON",
    "sg:tags":[
        "conditioning",
        "air",
        "system",
        "contractor"
    ],
    "wof:name":"Summer Breeze Heating & Ac Ltd",
    "wof:placetype":"venue"
},
  "geometry": {"coordinates":[-80.47094,43.406853],"type":"Point"}
}