{
  "type": "Feature",
  "properties": {
    "addr:full":"1257 Rue University Montreal QC H3B 3A8",
    "addr:housenumber":"1257",
    "addr:postcode":"h3b 3a8",
    "addr:street":"Rue University",
    "iso:country":"CA",
    "sg:address":"1257 Rue University",
    "sg:city":"Montreal",
    "sg:classifiers":[
        {
            "category":"Shopping",
            "subcategory":"Hobbies, Toys, & Games",
            "type":"Retail Goods"
        }
    ],
    "sg:phone":"+1 514 954 4428",
    "sg:postcode":"H3B 3A8",
    "sg:province":"QC",
    "wof:name":"Educa-Jeux",
    "wof:placetype":"venue"
},
  "geometry": {"coordinates":[-73.5694274902,45.5030288696],"type":"Point"}
}