{
  "type": "Feature",
  "properties": {
    "addr:full":"Avonhurst SK S0G 0A0",
    "addr:postcode":"s0g 0a0",
    "addr:street":"Avonhurst Sk",
    "iso:country":"CA",
    "sg:city":"Avonhurst",
    "sg:classifiers":[
        {
            "category":"Wholesale",
            "subcategory":"Petroleum",
            "type":"Manufacturing & Wholesale Goods"
        }
    ],
    "sg:phone":"+1 306 771 2812",
    "sg:postcode":"S0G 0A0",
    "sg:province":"SK",
    "sg:tags":[
        "oil"
    ],
    "wof:name":"Avonhurst CO-Operative Store",
    "wof:placetype":"venue"
},
  "geometry": {"coordinates":[-104.142937,50.63007],"type":"Point"}
}