{
  "type": "Feature",
  "properties": {
    "iso:country":"CA",
    "sg:address":"246 Whitecap Cres",
    "sg:city":"Saskatoon",
    "sg:classifiers":[
        {
            "category":"Building & Trades",
            "subcategory":"Construction",
            "type":"Services"
        }
    ],
    "sg:phone":"+1 306 384 0885",
    "sg:postcode":"S7M 5C7",
    "sg:province":"SK",
    "sg:tags":[
        "masonry",
        "contractor"
    ],
    "wof:name":"Prairie Masonry",
    "wof:placetype":"venue"
},
  "geometry": {"coordinates":[-106.754753,52.118973],"type":"Point"}
}