{
  "type": "Feature",
  "properties": {
    "addr:full":"Sioux Narrows ON P0X 1N0",
    "addr:postcode":"p0x 1n0",
    "iso:country":"CA",
    "sg:city":"Sioux Narrows",
    "sg:classifiers":[
        {
            "category":"Education",
            "subcategory":"Library",
            "type":"Public Place"
        }
    ],
    "sg:phone":"+1 807 226 5204",
    "sg:postcode":"P0X 1N0",
    "sg:province":"ON",
    "wof:name":"Sioux Narrows Public Library",
    "wof:placetype":"venue"
},
  "geometry": {"coordinates":[-94.0960693359,49.4190254211],"type":"Point"}
}