{
  "type": "Feature",
  "properties": {
    "addr:full":"33357 South Fraser Way Abbotsford BC V2S 2B2",
    "addr:housenumber":"33357",
    "addr:postcode":"v2s 2b2",
    "addr:street":"South Fraser Way",
    "iso:country":"CA",
    "sg:address":"33357 South Fraser Way",
    "sg:city":"Abbotsford",
    "sg:classifiers":[
        {
            "category":"Manufacturing",
            "subcategory":"Apparel",
            "type":"Manufacturing & Wholesale Goods"
        }
    ],
    "sg:phone":"+1 604 859 6661",
    "sg:postcode":"V2S 2B2",
    "sg:province":"BC",
    "sg:tags":[
        "trophy",
        "emblem",
        "medal",
        "award"
    ],
    "wof:name":"Woodline Trophies",
    "wof:placetype":"venue"
},
  "geometry": {"coordinates":[-122.300293,49.050034],"type":"Point"}
}