{
  "type": "Feature",
  "properties": {
    "addr:full":"3675 Casorso Rd Kelowna BC V1W 3E1",
    "addr:housenumber":"3675",
    "addr:postcode":"v1w 3e1",
    "addr:street":"Casorso Rd",
    "iso:country":"CA",
    "sg:address":"3675 Casorso Rd",
    "sg:city":"Kelowna",
    "sg:classifiers":[
        {
            "category":"Education",
            "subcategory":"School",
            "type":"Public Place"
        }
    ],
    "sg:phone":"+1 250 763 8088",
    "sg:postcode":"V1W 3E1",
    "sg:province":"BC",
    "wof:name":"Casorso Elementary",
    "wof:placetype":"venue"
},
  "geometry": {"coordinates":[-119.48155199999999,49.852535],"type":"Point"}
}