{
  "type": "Feature",
  "properties": {
    "addr:full":"916 1 Ave NE Calgary AB T2E 0C5",
    "addr:housenumber":"916",
    "addr:postcode":"t2e 0c5",
    "addr:street":"1 Ave Ne",
    "iso:country":"CA",
    "sg:address":"916 1 Ave NE",
    "sg:city":"Calgary",
    "sg:classifiers":[
        {
            "category":"Restaurant",
            "type":"Food & Drink"
        }
    ],
    "sg:phone":"+1 403 263 3445",
    "sg:postcode":"T2E 0C5",
    "sg:province":"AB",
    "wof:name":"Dolce Vita Restaurant",
    "wof:placetype":"venue"
},
  "geometry": {"coordinates":[-114.04187,51.053371],"type":"Point"}
}