{
  "type": "Feature",
  "properties": {
    "iso:country":"CA",
    "sg:address":"3304 42 St",
    "sg:city":"Leduc",
    "sg:classifiers":[
        {
            "category":"Building & Trades",
            "subcategory":"Construction",
            "type":"Services"
        }
    ],
    "sg:phone":"+1 780 986 4581",
    "sg:postcode":"T9E 6C5",
    "sg:province":"AB",
    "sg:tags":[
        "painter"
    ],
    "wof:name":"Danny's Painting",
    "wof:placetype":"venue"
},
  "geometry": {"coordinates":[-113.530532837,53.2457275391],"type":"Point"}
}