{
  "type": "Feature",
  "properties": {
    "addr:full":"447 St Mary's Rd Winnipeg MB R2M 3K8",
    "addr:housenumber":"447",
    "addr:postcode":"r2m 3k8",
    "addr:street":"St Mary'S Rd",
    "iso:country":"CA",
    "sg:address":"447 St Mary's Rd",
    "sg:city":"Winnipeg",
    "sg:classifiers":[
        {
            "category":"Manufacturing",
            "subcategory":"Tools & Machinery",
            "type":"Manufacturing & Wholesale Goods"
        }
    ],
    "sg:phone":"+1 204 233 7017",
    "sg:postcode":"R2M 3K8",
    "sg:province":"MB",
    "sg:tags":[
        "machine",
        "shop"
    ],
    "wof:name":"St Vital Welding & Machine Ltd",
    "wof:placetype":"venue"
},
  "geometry": {"coordinates":[-97.14919999999999,49.889099],"type":"Point"}
}