{
  "type": "Feature",
  "properties": {
    "iso:country":"CA",
    "sg:city":"Grande Prairie",
    "sg:classifiers":[
        {
            "category":"Professional",
            "subcategory":"Lawyer & Legal Services",
            "type":"Services"
        }
    ],
    "sg:phone":"+1 780 539 9300",
    "sg:postcode":"T8V 0X9",
    "sg:province":"AB",
    "sg:tags":[
        "attorney"
    ],
    "wof:name":"Banks, Christian",
    "wof:placetype":"venue"
},
  "geometry": {"coordinates":[-118.795394898,55.1714553833],"type":"Point"}
}