{
  "type": "Feature",
  "properties": {
    "addr:full":"6749 120 St Delta BC V4E 2A7",
    "addr:housenumber":"6749",
    "addr:postcode":"v4e 2a7",
    "addr:street":"120 St",
    "iso:country":"CA",
    "sg:address":"6749 120 St",
    "sg:city":"Delta",
    "sg:classifiers":[
        {
            "category":"Social Services",
            "subcategory":"Child Care",
            "type":"Services"
        }
    ],
    "sg:phone":"+1 604 594 0910",
    "sg:postcode":"V4E 2A7",
    "sg:province":"BC",
    "wof:name":"Hilltop Christian Out of Schl",
    "wof:placetype":"venue"
},
  "geometry": {"coordinates":[-122.890556,49.125416],"type":"Point"}
}