{
  "type": "Feature",
  "properties": {
    "addr:full":"3855 5E Av Shawinigan-Sud QC G9P 1R8",
    "addr:housenumber":"3855",
    "addr:postcode":"g9p 1r8",
    "addr:street":"5E Av Shawinigan-Sud",
    "iso:country":"CA",
    "sg:address":"3855 5E Av",
    "sg:city":"Shawinigan-Sud",
    "sg:classifiers":[
        {
            "category":"Autos & Motor Vehicles",
            "subcategory":"Recreational Vehicle Sales",
            "type":"Retail Goods"
        }
    ],
    "sg:phone":"+1 819 537 8423",
    "sg:postcode":"G9P 1R8",
    "sg:province":"QC",
    "sg:tags":[
        "parts",
        "trailer"
    ],
    "wof:name":"Garage Marcel Heon",
    "wof:placetype":"venue"
},
  "geometry": {"coordinates":[-72.73198699949999,46.508895874],"type":"Point"}
}