{
  "type": "Feature",
  "properties": {
    "addr:full":"201 Ch Narrow's Canton Stanstead QC J1X 3W4",
    "addr:housenumber":"201",
    "addr:postcode":"j1x 3w4",
    "addr:street":"Ch Narrow'S Canton",
    "iso:country":"CA",
    "sg:address":"201 Ch Narrow's",
    "sg:city":"Canton Stanstead",
    "sg:classifiers":[
        {
            "category":"Recreation",
            "type":"Entertainment"
        }
    ],
    "sg:phone":"+1 819 876 5577",
    "sg:postcode":"J1X 3W4",
    "sg:province":"QC",
    "sg:tags":[
        "provincial",
        "parks"
    ],
    "wof:name":"Parc Forand",
    "wof:placetype":"venue"
},
  "geometry": {"coordinates":[-72.182716,45.107655],"type":"Point"}
}