{
  "type": "Feature",
  "properties": {
    "addr:full":"2390 Lakeshore Rd W Oakville ON L6L 1H5",
    "addr:housenumber":"2390",
    "addr:postcode":"l6l 1h5",
    "addr:street":"Lakeshore Rd W",
    "iso:country":"CA",
    "sg:address":"2390 Lakeshore Rd W",
    "sg:city":"Oakville",
    "sg:classifiers":[
        {
            "category":"Retail",
            "subcategory":"Self-service Laundry",
            "type":"Services"
        }
    ],
    "sg:phone":"+1 905 827 4823",
    "sg:postcode":"L6L 1H5",
    "sg:province":"ON",
    "sg:tags":[
        "cleaners"
    ],
    "wof:name":"Bronte Spins Laundromat",
    "wof:placetype":"venue"
},
  "geometry": {"coordinates":[-79.70970199999999,43.396042],"type":"Point"}
}