{
  "type": "Feature",
  "properties": {
    "iso:country":"CA",
    "sg:address":"14 Victoria Sq",
    "sg:city":"Colborne",
    "sg:classifiers":[
        {
            "category":"Social Services",
            "type":"Services"
        }
    ],
    "sg:phone":"+1 905 355 5883",
    "sg:postcode":"K0K 1S0",
    "sg:province":"ON",
    "sg:tags":[
        "senior",
        "citizen"
    ],
    "wof:name":"Vbj Memorial Ctr",
    "wof:placetype":"venue"
},
  "geometry": {"coordinates":[-77.88497924799999,44.0039520264],"type":"Point"}
}