{
  "type": "Feature",
  "properties": {
    "addr:full":"824 Brookfield Rd Ottawa ON K1V 6J3",
    "addr:housenumber":"824",
    "addr:postcode":"k1v 6j3",
    "addr:street":"Brookfield Rd",
    "iso:country":"CA",
    "sg:address":"824 Brookfield Rd",
    "sg:city":"Ottawa",
    "sg:classifiers":[
        {
            "category":"Education",
            "subcategory":"School",
            "type":"Public Place"
        }
    ],
    "sg:phone":"+1 613 733 0610",
    "sg:postcode":"K1V 6J3",
    "sg:province":"ON",
    "wof:name":"Brookfield High School",
    "wof:placetype":"venue"
},
  "geometry": {"coordinates":[-75.686333,45.373318],"type":"Point"}
}