{
  "type": "Feature",
  "properties": {
    "addr:full":"201 Union St Saint John NB E2L 1A9",
    "addr:housenumber":"201",
    "addr:postcode":"nb e2l 1a9",
    "addr:street":"Union St",
    "iso:country":"CA",
    "sg:address":"201 Union St",
    "sg:city":"Saint John",
    "sg:classifiers":[
        {
            "category":"Organizations",
            "subcategory":"Professional Association",
            "type":"Services"
        }
    ],
    "sg:phone":"+1 506 646 9120",
    "sg:postcode":"E2L 1A9",
    "sg:province":"NB",
    "wof:name":"Scouts Canada",
    "wof:placetype":"venue"
},
  "geometry": {"coordinates":[-66.05828099999999,45.275333],"type":"Point"}
}