{
  "type": "Feature",
  "properties": {
    "addr:full":"7355 Bayview Ave # 1C Thornhill ON L3T 5Z2",
    "addr:housenumber":"7355",
    "addr:postcode":"l3t 5z2",
    "addr:street":"Bayview Ave # 1C",
    "iso:country":"CA",
    "sg:address":"7355 Bayview Ave # 1C",
    "sg:city":"Thornhill",
    "sg:classifiers":[
        {
            "category":"Food & Beverages",
            "subcategory":"Bakery",
            "type":"Retail Goods"
        }
    ],
    "sg:phone":"+1 905 707 3375",
    "sg:postcode":"L3T 5Z2",
    "sg:province":"ON",
    "sg:tags":[
        "baker"
    ],
    "wof:name":"Delice Fine Cakes",
    "wof:placetype":"venue"
},
  "geometry": {"coordinates":[-79.399574,43.812817],"type":"Point"}
}