{
  "type": "Feature",
  "properties": {
    "addr:full":"71 Wyndham St S # D Guelph ON N1E 5R3",
    "addr:housenumber":"71",
    "addr:postcode":"n1e 5r3",
    "addr:street":"Wyndham St S # D",
    "iso:country":"CA",
    "sg:address":"71 Wyndham St S # D",
    "sg:city":"Guelph",
    "sg:classifiers":[
        {
            "category":"Manufacturing",
            "subcategory":"Tools & Machinery",
            "type":"Manufacturing & Wholesale Goods"
        }
    ],
    "sg:phone":"+1 519 836 3370",
    "sg:postcode":"N1E 5R3",
    "sg:province":"ON",
    "sg:tags":[
        "conditioning",
        "air",
        "system",
        "contractor"
    ],
    "wof:name":"Regal Air Ltd",
    "wof:placetype":"venue"
},
  "geometry": {"coordinates":[-80.241936,43.541771],"type":"Point"}
}