{
  "type": "Feature",
  "properties": {
    "iso:country":"CA",
    "sg:city":"Waterloo",
    "sg:classifiers":[
        {
            "category":"Shopping",
            "subcategory":"Jewelry",
            "type":"Retail Goods"
        }
    ],
    "sg:phone":"+1 519 747 0730",
    "sg:postcode":"N2V 2G8",
    "sg:province":"ON",
    "sg:tags":[
        "watch"
    ],
    "wof:name":"Time Factory Outlet",
    "wof:placetype":"venue"
},
  "geometry": {"coordinates":[-80.5543670654,43.505191803],"type":"Point"}
}