{
  "type": "Feature",
  "properties": {
    "iso:country":"CA",
    "sg:city":"Woodbridge",
    "sg:classifiers":[
        {
            "category":"Retail",
            "subcategory":"Auto Repair",
            "type":"Services"
        }
    ],
    "sg:phone":"+1 905 856 7867",
    "sg:postcode":"L4L 5X3",
    "sg:province":"ON",
    "sg:tags":[
        "repairing",
        "automobile"
    ],
    "wof:name":"One Stop Auto Ctr",
    "wof:placetype":"venue"
},
  "geometry": {"coordinates":[-79.569480896,43.7836418152],"type":"Point"}
}