{
  "type": "Feature",
  "properties": {
    "iso:country":"CA",
    "sg:city":"Saint-Donat-DE-Montcalm",
    "sg:classifiers":[
        {
            "category":"Manufacturing",
            "subcategory":"Signs",
            "type":"Manufacturing & Wholesale Goods"
        }
    ],
    "sg:phone":"+1 819 424 5075",
    "sg:postcode":"J0T 2C0",
    "sg:province":"QC",
    "wof:name":"Duo Design Enr",
    "wof:placetype":"venue"
},
  "geometry": {"coordinates":[-74.2121429443,46.3121566772],"type":"Point"}
}