{
  "type": "Feature",
  "properties": {
    "addr:full":"PO Box 95 Duntroon ON L0M 1H0",
    "addr:housenumber":"po box 95",
    "addr:postcode":"l0m 1h0",
    "iso:country":"CA",
    "sg:address":"PO Box 95",
    "sg:city":"Duntroon",
    "sg:classifiers":[
        {
            "category":"Building & Trades",
            "subcategory":"Electrical",
            "type":"Services"
        }
    ],
    "sg:phone":"+1 705 445 4536",
    "sg:postcode":"L0M 1H0",
    "sg:province":"ON",
    "sg:tags":[
        "equipment",
        "electric",
        "contractor"
    ],
    "wof:name":"Marritt Electric Ltd",
    "wof:placetype":"venue"
},
  "geometry": {"coordinates":[-80.1939163208,44.3979682922],"type":"Point"}
}