{
  "type": "Feature",
  "properties": {
    "addr:full":"Saint-Felix-DE-Valois QC J0K 2M0",
    "addr:postcode":"j0k 2m0",
    "iso:country":"CA",
    "sg:city":"Saint-Felix-DE-Valois",
    "sg:classifiers":[
        {
            "category":"Real Estate",
            "subcategory":"Real Estate Agent",
            "type":"Services"
        }
    ],
    "sg:phone":"+1 450 889 4634",
    "sg:postcode":"J0K 2M0",
    "sg:province":"QC",
    "sg:tags":[
        "tool",
        "agency",
        "rental"
    ],
    "wof:name":"Location Mille Items",
    "wof:placetype":"venue"
},
  "geometry": {"coordinates":[-73.447975,46.167194],"type":"Point"}
}