{
  "type": "Feature",
  "properties": {
    "iso:country":"CA",
    "sg:address":"PO Box 933",
    "sg:city":"Boyle",
    "sg:classifiers":[
        {
            "category":"Retail",
            "subcategory":"Repair Shop",
            "type":"Services"
        }
    ],
    "sg:phone":"+1 780 689 3027",
    "sg:postcode":"T0A 0M0",
    "sg:province":"AB",
    "sg:tags":[
        "taxidermist"
    ],
    "wof:name":"Pickerel Point Taxidermy",
    "wof:placetype":"venue"
},
  "geometry": {"coordinates":[-112.80447387700001,54.5873031616],"type":"Point"}
}