{
  "type": "Feature",
  "properties": {
    "addr:full":"Mississauga ON L4T 4H4",
    "addr:postcode":"l4t 4h4",
    "iso:country":"CA",
    "sg:city":"Mississauga",
    "sg:classifiers":[
        {
            "category":"Professional",
            "subcategory":"Printing & Photocopies",
            "type":"Services"
        }
    ],
    "sg:phone":"+1 905 673 0717",
    "sg:postcode":"L4T 4H4",
    "sg:province":"ON",
    "sg:tags":[
        "duplicating",
        "copying"
    ],
    "wof:name":"Sherwood Copy",
    "wof:placetype":"venue"
},
  "geometry": {"coordinates":[-79.657974,43.715141],"type":"Point"}
}