{
  "type": "Feature",
  "properties": {
    "addr:full":"2221 Simcoe Rd 11 Shanty Bay ON L0L 2L0",
    "addr:housenumber":"2221;11",
    "addr:postcode":"l0l 2l0",
    "addr:street":"Simcoe Rd;Shanty Bay",
    "iso:country":"CA",
    "sg:address":"2221 Simcoe Rd 11",
    "sg:city":"Shanty Bay",
    "sg:classifiers":[
        {
            "category":"Education",
            "subcategory":"School",
            "type":"Public Place"
        }
    ],
    "sg:phone":"+1 705 728 9591",
    "sg:postcode":"L0L 2L0",
    "sg:province":"ON",
    "wof:name":"W R Best Memorial School",
    "wof:placetype":"venue"
},
  "geometry": {"coordinates":[-79.58197800000001,44.412922],"type":"Point"}
}