{
  "type": "Feature",
  "properties": {
    "addr:full":"332 Wellington Rd London ON N6C 4P6",
    "addr:housenumber":"332",
    "addr:postcode":"n6c 4p6",
    "addr:street":"Wellington Rd",
    "iso:country":"CA",
    "sg:address":"332 Wellington Rd",
    "sg:city":"London",
    "sg:classifiers":[
        {
            "category":"Recreation",
            "type":"Entertainment"
        }
    ],
    "sg:phone":"+1 519 438 1317",
    "sg:postcode":"N6C 4P6",
    "sg:province":"ON",
    "sg:tags":[
        "club",
        "bridge"
    ],
    "wof:name":"Bridge Fokes",
    "wof:placetype":"venue"
},
  "geometry": {"coordinates":[-81.2314071655,42.9633712769],"type":"Point"}
}