{
  "type": "Feature",
  "properties": {
    "addr:full":"565 Welham Rd Barrie ON L4N 8Z6",
    "addr:housenumber":"565",
    "addr:postcode":"l4n 8z6",
    "addr:street":"Welham Rd",
    "iso:country":"CA",
    "sg:address":"565 Welham Rd",
    "sg:city":"Barrie",
    "sg:classifiers":[
        {
            "category":"Building & Trades",
            "subcategory":"Plumbing",
            "type":"Services"
        }
    ],
    "sg:phone":"+1 705 739 9541",
    "sg:postcode":"L4N 8Z6",
    "sg:province":"ON",
    "sg:tags":[
        "air",
        "conditioning",
        "contractor",
        "system",
        "heating"
    ],
    "wof:name":"Innisfil Air Conditioning Ltd",
    "wof:placetype":"venue"
},
  "geometry": {"coordinates":[-79.6700286865,44.341468811],"type":"Point"}
}