{
  "type": "Feature",
  "properties": {
    "addr:full":"5845 Glen Erin Dr Mississauga ON L5M 5J9",
    "addr:housenumber":"5845",
    "addr:postcode":"l5m 5j9",
    "addr:street":"Glen Erin Dr",
    "iso:country":"CA",
    "sg:address":"5845 Glen Erin Dr",
    "sg:city":"Mississauga",
    "sg:classifiers":[
        {
            "category":"Building & Trades",
            "subcategory":"Plumbing",
            "type":"Services"
        }
    ],
    "sg:phone":"+1 905 542 0919",
    "sg:postcode":"L5M 5J9",
    "sg:province":"ON",
    "sg:tags":[
        "ventilating",
        "contractor"
    ],
    "wof:name":"Thomas Technicals",
    "wof:placetype":"venue"
},
  "geometry": {"coordinates":[-79.733467,43.571247],"type":"Point"}
}