{
  "type": "Feature",
  "properties": {
    "iso:country":"CA",
    "sg:address":"Trans Canada Hwy E",
    "sg:city":"Richer",
    "sg:classifiers":[
        {
            "category":"Travel",
            "subcategory":"Hotels & Motels",
            "type":"Entertainment"
        }
    ],
    "sg:phone":"+1 204 422 5482",
    "sg:postcode":"R0E 1S0",
    "sg:province":"MB",
    "wof:name":"Richer Inn Motor Hotel",
    "wof:placetype":"venue"
},
  "geometry": {"coordinates":[-96.4568023682,49.6563835144],"type":"Point"}
}