{
  "type": "Feature",
  "properties": {
    "addr:full":"Thessalon ON P0R 1L0",
    "addr:postcode":"p0r 1l0",
    "iso:country":"CA",
    "sg:city":"Thessalon",
    "sg:classifiers":[
        {
            "category":"Organizations",
            "subcategory":"Religious Organization",
            "type":"Services"
        }
    ],
    "sg:phone":"+1 705 842 1888",
    "sg:postcode":"P0R 1L0",
    "sg:province":"ON",
    "wof:name":"Thessalon Bible Chapel",
    "wof:placetype":"venue"
},
  "geometry": {"coordinates":[-83.557671,46.25639],"type":"Point"}
}