{
  "type": "Feature",
  "properties": {
    "addr:full":"PO Box 722131 Calgary AB T2V 5H9",
    "addr:housenumber":"po",
    "addr:postcode":"t2v 5h9",
    "addr:street":"Box 722131",
    "iso:country":"CA",
    "sg:address":"PO Box 722131",
    "sg:city":"Calgary",
    "sg:classifiers":[
        {
            "category":"Mining & Drilling",
            "type":"Manufacturing & Wholesale Goods"
        }
    ],
    "sg:phone":"+1 403 251 2642",
    "sg:postcode":"T2V 5H9",
    "sg:province":"AB",
    "sg:tags":[
        "company",
        "oil"
    ],
    "wof:name":"Berry Creek Resources Ltd",
    "wof:placetype":"venue"
},
  "geometry": {"coordinates":[-114.063194275,51.0450744629],"type":"Point"}
}