{
  "type": "Feature",
  "properties": {
    "addr:full":"8280 Gilbert Rd Richmond BC V7C 3W7",
    "addr:housenumber":"8280",
    "addr:postcode":"bc v7c 3w7",
    "addr:street":"Gilbert Rd",
    "iso:country":"CA",
    "sg:address":"8280 Gilbert Rd",
    "sg:city":"Richmond",
    "sg:classifiers":[
        {
            "category":"Organizations",
            "subcategory":"Religious Organization",
            "type":"Services"
        }
    ],
    "sg:phone":"+1 604 277 2424",
    "sg:postcode":"V7C 3W7",
    "sg:province":"BC",
    "sg:tags":[
        "church"
    ],
    "wof:name":"Salvation Army",
    "wof:placetype":"venue"
},
  "geometry": {"coordinates":[-123.147552,49.153175],"type":"Point"}
}