{
  "type": "Feature",
  "properties": {
    "addr:full":"Nanaimo BC V9T 5V4",
    "addr:postcode":"v9t 5v4",
    "iso:country":"CA",
    "sg:city":"Nanaimo",
    "sg:classifiers":[
        {
            "category":"Restaurant",
            "type":"Food & Drink"
        }
    ],
    "sg:phone":"+1 250 729 7044",
    "sg:postcode":"V9T 5V4",
    "sg:province":"BC",
    "sg:tags":[
        "delicatessen"
    ],
    "wof:name":"Nellie's Dutch Deli",
    "wof:placetype":"venue"
},
  "geometry": {"coordinates":[-123.988441467,49.2000694275],"type":"Point"}
}