{
  "type": "Feature",
  "properties": {
    "iso:country":"CA",
    "sg:address":"200 Morton Dr",
    "sg:city":"Windsor",
    "sg:classifiers":[
        {
            "category":"Food & Beverages",
            "subcategory":"Specialty",
            "type":"Retail Goods"
        }
    ],
    "sg:phone":"+1 519 972 2225",
    "sg:postcode":"N9J 3W9",
    "sg:province":"ON",
    "sg:tags":[
        "salt"
    ],
    "wof:name":"Canadian Salt CO Ltd",
    "wof:placetype":"venue"
},
  "geometry": {"coordinates":[-83.103706,42.254169],"type":"Point"}
}