{
  "type": "Feature",
  "properties": {
    "addr:full":"5925 Mclaughlin Rd Mississauga ON L5R 1B8",
    "addr:housenumber":"5925",
    "addr:postcode":"l5r 1b8",
    "addr:street":"Mclaughlin Rd",
    "iso:country":"CA",
    "sg:address":"5925 Mclaughlin Rd",
    "sg:city":"Mississauga",
    "sg:classifiers":[
        {
            "category":"Manufacturing",
            "subcategory":"Tools & Machinery",
            "type":"Manufacturing & Wholesale Goods"
        }
    ],
    "sg:phone":"+1 905 507 4000",
    "sg:postcode":"L5R 1B8",
    "sg:province":"ON",
    "sg:tags":[
        "lighting",
        "fixture"
    ],
    "wof:name":"Cooper Lighting",
    "wof:placetype":"venue"
},
  "geometry": {"coordinates":[-79.68775939939999,43.6153335571],"type":"Point"}
}