{
  "type": "Feature",
  "properties": {
    "addr:full":"4139 16 St SE Calgary AB T2G 3R9",
    "addr:housenumber":"4139",
    "addr:postcode":"t2g 3r9",
    "addr:street":"16 St Se",
    "iso:country":"CA",
    "sg:address":"4139 16 St SE",
    "sg:city":"Calgary",
    "sg:classifiers":[
        {
            "category":"Building & Trades",
            "subcategory":"Construction",
            "type":"Services"
        }
    ],
    "sg:phone":"+1 403 263 8375",
    "sg:postcode":"T2G 3R9",
    "sg:province":"AB",
    "sg:tags":[
        "sandblasting"
    ],
    "wof:name":"Mega Industrial Coatings",
    "wof:placetype":"venue"
},
  "geometry": {"coordinates":[-114.02227020300001,51.0179367065],"type":"Point"}
}