{
  "type": "Feature",
  "properties": {
    "iso:country":"CA",
    "sg:address":"68 Boul Du Saguenay E",
    "sg:city":"Chicoutimi",
    "sg:classifiers":[
        {
            "category":"Food & Beverages",
            "subcategory":"Groceries & Convenience Stores",
            "type":"Retail Goods"
        }
    ],
    "sg:phone":"+1 418 696 2412",
    "sg:postcode":"G7H 1K4",
    "sg:province":"QC",
    "wof:name":"Depanneur Servi-Soir Enr",
    "wof:placetype":"venue"
},
  "geometry": {"coordinates":[-71.0662765503,48.4292144775],"type":"Point"}
}