{
  "type": "Feature",
  "properties": {
    "addr:full":"550 Av Ampere Laval QC H7N 5C5",
    "addr:housenumber":"550",
    "addr:postcode":"h7n 5c5",
    "addr:street":"Av Ampere",
    "iso:country":"CA",
    "sg:address":"550 Av Ampere",
    "sg:city":"Laval",
    "sg:classifiers":[
        {
            "category":"Retail",
            "subcategory":"Auto Repair",
            "type":"Services"
        }
    ],
    "sg:phone":"+1 450 669 2609",
    "sg:postcode":"H7N 5C5",
    "sg:province":"QC",
    "sg:tags":[
        "repairing",
        "automobile"
    ],
    "wof:name":"Garage Ampere Inc",
    "wof:placetype":"venue"
},
  "geometry": {"coordinates":[-73.708862,45.561802],"type":"Point"}
}