{
  "type": "Feature",
  "properties": {
    "addr:full":"3544 17th Ave W Vancouver BC V6S 1A1",
    "addr:housenumber":"3544",
    "addr:postcode":"v6s 1a1",
    "addr:street":"17Th Ave W",
    "iso:country":"CA",
    "sg:address":"3544 17th Ave W",
    "sg:city":"Vancouver",
    "sg:classifiers":[
        {
            "category":"Building & Trades",
            "subcategory":"Landscaping Services",
            "type":"Services"
        }
    ],
    "sg:phone":"+1 604 837 7437",
    "sg:postcode":"V6S 1A1",
    "sg:province":"BC",
    "sg:tags":[
        "lawn",
        "contractor",
        "landscape",
        "maintenance",
        "grounds"
    ],
    "wof:name":"Sid's Garden Svc",
    "wof:placetype":"venue"
},
  "geometry": {"coordinates":[-123.183273,49.257233],"type":"Point"}
}