{
  "type": "Feature",
  "properties": {
    "addr:full":"480 4th St E Stonewall MB R0C 2Z0",
    "addr:housenumber":"480",
    "addr:postcode":"r0c 2z0",
    "addr:street":"4Th St E",
    "iso:country":"CA",
    "sg:address":"480 4th St E",
    "sg:city":"Stonewall",
    "sg:phone":"+1 204 467 8267",
    "sg:postcode":"R0C 2Z0",
    "sg:province":"MB",
    "sg:tags":[
        "oil"
    ],
    "wof:name":"Shell Canada Agent",
    "wof:placetype":"venue"
},
  "geometry": {"coordinates":[-97.3223953247,50.1376533508],"type":"Point"}
}