{
  "type": "Feature",
  "properties": {
    "addr:full":"142 Martin Ross Ave North York ON M3J 2L4",
    "addr:housenumber":"142",
    "addr:postcode":"m3j 2l4",
    "addr:street":"Martin Ross Ave",
    "iso:country":"CA",
    "sg:address":"142 Martin Ross Ave",
    "sg:city":"North York",
    "sg:classifiers":[
        {
            "category":"Wholesale",
            "subcategory":"Groceries",
            "type":"Manufacturing & Wholesale Goods"
        }
    ],
    "sg:phone":"+1 416 736 3663",
    "sg:postcode":"M3J 2L4",
    "sg:province":"ON",
    "sg:tags":[
        "baker"
    ],
    "wof:name":"Sterling Foods",
    "wof:placetype":"venue"
},
  "geometry": {"coordinates":[-79.47850800000001,43.773254],"type":"Point"}
}