{
  "type": "Feature",
  "properties": {
    "addr:full":"5859 DE LA Savane Pl Saint-Hubert QC J3Y 8Y9",
    "addr:housenumber":"5859",
    "addr:postcode":"j3y 8y9",
    "addr:street":"De La Savane Pl",
    "iso:country":"CA",
    "sg:address":"5859 DE LA Savane Pl",
    "sg:city":"Saint-Hubert",
    "sg:classifiers":[
        {
            "category":"Shopping",
            "type":"Retail Goods"
        }
    ],
    "sg:phone":"+1 450 448 2805",
    "sg:postcode":"J3Y 8Y9",
    "sg:province":"QC",
    "sg:tags":[
        "aquarium"
    ],
    "wof:name":"Aquanov Canada Inc",
    "wof:placetype":"venue"
},
  "geometry": {"coordinates":[-73.42495700000001,45.501984],"type":"Point"}
}