{
  "type": "Feature",
  "properties": {
    "addr:full":"57 Rue Ontario O Montreal QC H2X 1Y8",
    "addr:housenumber":"57",
    "addr:postcode":"h2x 1y8",
    "addr:street":"Rue Ontario O",
    "iso:country":"CA",
    "sg:address":"57 Rue Ontario O",
    "sg:city":"Montreal",
    "sg:classifiers":[
        {
            "category":"Manufacturing",
            "subcategory":"Musical Instruments",
            "type":"Manufacturing & Wholesale Goods"
        }
    ],
    "sg:phone":"+1 514 288 4343",
    "sg:postcode":"H2X 1Y8",
    "sg:province":"QC",
    "sg:tags":[
        "violin",
        "maker"
    ],
    "wof:name":"Jules Saint-Michel Luthier Inc",
    "wof:placetype":"venue"
},
  "geometry": {"coordinates":[-73.566742,45.511753],"type":"Point"}
}