{
  "type": "Feature",
  "properties": {
    "addr:full":"20455 Douglas Cres Langley BC V3A 4B6",
    "addr:housenumber":"20455",
    "addr:postcode":"v3a 4b6",
    "addr:street":"Douglas Cres",
    "iso:country":"CA",
    "sg:address":"20455 Douglas Cres",
    "sg:city":"Langley",
    "sg:classifiers":[
        {
            "category":"Shopping",
            "subcategory":"Optical Goods",
            "type":"Retail Goods"
        }
    ],
    "sg:phone":"+1 604 514 0070",
    "sg:postcode":"V3A 4B6",
    "sg:province":"BC",
    "sg:tags":[
        "optician"
    ],
    "wof:name":"Ben Campen Vision Care Ctr",
    "wof:placetype":"venue"
},
  "geometry": {"coordinates":[-122.65522,49.103542],"type":"Point"}
}