{
  "type": "Feature",
  "properties": {
    "addr:full":"4812 Rue Saint-Urbain Montreal QC H2T 2W2",
    "addr:housenumber":"4812",
    "addr:postcode":"h2t 2w2",
    "addr:street":"Rue Saint-Urbain",
    "iso:country":"CA",
    "sg:address":"4812 Rue Saint-Urbain",
    "sg:city":"Montreal",
    "sg:classifiers":[
        {
            "category":"Food & Beverages",
            "subcategory":"Bakery",
            "type":"Retail Goods"
        }
    ],
    "sg:phone":"+1 514 270 2073",
    "sg:postcode":"H2T 2W2",
    "sg:province":"QC",
    "sg:tags":[
        "baker"
    ],
    "wof:name":"Jimmy's Bakery",
    "wof:placetype":"venue"
},
  "geometry": {"coordinates":[-73.590828,45.520309],"type":"Point"}
}