{
  "type": "Feature",
  "properties": {
    "addr:full":"120 Old Kingston Rd Ajax ON L1T 3Z2",
    "addr:housenumber":"120",
    "addr:postcode":"l1t 3z2",
    "addr:street":"Old Kingston Rd",
    "iso:country":"CA",
    "sg:address":"120 Old Kingston Rd",
    "sg:city":"Ajax",
    "sg:classifiers":[
        {
            "category":"Real Estate",
            "subcategory":"Real Estate Operator",
            "type":"Services"
        }
    ],
    "sg:phone":"+1 905 427 9354",
    "sg:postcode":"L1T 3Z2",
    "sg:province":"ON",
    "sg:tags":[
        "apartment"
    ],
    "wof:name":"Unity Village Local 183",
    "wof:placetype":"venue"
},
  "geometry": {"coordinates":[-79.060256958,43.8543701172],"type":"Point"}
}