{
  "type": "Feature",
  "properties": {
    "addr:full":"Highway 23 & Munro Mitchell ON N0K 1N0",
    "addr:postcode":"n0k 1n0",
    "addr:street":"Highway 23 &",
    "iso:country":"CA",
    "sg:address":"Highway 23 & Munro",
    "sg:city":"Mitchell",
    "sg:classifiers":[
        {
            "category":"Organizations",
            "subcategory":"Religious Organization",
            "type":"Services"
        }
    ],
    "sg:phone":"+1 519 273 1808",
    "sg:postcode":"N0K 1N0",
    "sg:province":"ON",
    "sg:tags":[
        "church"
    ],
    "wof:name":"Bethel Free Reformed Church",
    "wof:placetype":"venue"
},
  "geometry": {"coordinates":[-81.200211,43.468616],"type":"Point"}
}