{
  "type": "Feature",
  "properties": {
    "addr:full":"11754 124 St NW Edmonton AB T5M 0K9",
    "addr:housenumber":"11754",
    "addr:postcode":"t5m 0k9",
    "addr:street":"124 St Nw",
    "iso:country":"CA",
    "sg:address":"11754 124 St NW",
    "sg:city":"Edmonton",
    "sg:classifiers":[
        {
            "category":"Restaurant",
            "type":"Food & Drink"
        }
    ],
    "sg:phone":"+1 780 447 2607",
    "sg:postcode":"T5M 0K9",
    "sg:province":"AB",
    "wof:name":"Chandler's Restaurant",
    "wof:placetype":"venue"
},
  "geometry": {"coordinates":[-113.536148,53.569275],"type":"Point"}
}