{
  "type": "Feature",
  "properties": {
    "iso:country":"CA",
    "sg:address":"159 Tansley Dr",
    "sg:city":"Carp",
    "sg:classifiers":[
        {
            "category":"Recreation",
            "subcategory":"Marina",
            "type":"Entertainment"
        }
    ],
    "sg:phone":"+1 613 831 3728",
    "sg:postcode":"K0A 1L0",
    "sg:province":"ON",
    "sg:tags":[
        "repairing",
        "boat"
    ],
    "wof:name":"Capital City Acrylic Repair",
    "wof:placetype":"venue"
},
  "geometry": {"coordinates":[-75.97747039790001,45.3052749634],"type":"Point"}
}