{
  "type": "Feature",
  "properties": {
    "addr:full":"369 Mary St Wiarton ON N0H 2T0",
    "addr:housenumber":"369",
    "addr:postcode":"n0h 2t0",
    "addr:street":"Mary St",
    "iso:country":"CA",
    "sg:address":"369 Mary St",
    "sg:city":"Wiarton",
    "sg:classifiers":[
        {
            "category":"Shopping",
            "subcategory":"Pharmacy",
            "type":"Retail Goods"
        }
    ],
    "sg:phone":"+1 519 534 5090",
    "sg:postcode":"N0H 2T0",
    "sg:province":"ON",
    "wof:name":"Bayside Pharmacy",
    "wof:placetype":"venue"
},
  "geometry": {"coordinates":[-81.13865699999999,44.7383],"type":"Point"}
}