{
  "type": "Feature",
  "properties": {
    "addr:full":"163 Carriage Hill Dr Fredericton NB E3E 1A4",
    "addr:housenumber":"163",
    "addr:postcode":"e3e 1a4",
    "addr:street":"Carriage Hill Dr",
    "iso:country":"CA",
    "sg:address":"163 Carriage Hill Dr",
    "sg:city":"Fredericton",
    "sg:classifiers":[
        {
            "category":"Professional",
            "subcategory":"Engineering",
            "type":"Services"
        }
    ],
    "sg:phone":"+1 506 452 1804",
    "sg:postcode":"E3E 1A4",
    "sg:province":"NB",
    "sg:tags":[
        "engineer"
    ],
    "wof:name":"Skarborn Engineering Ltd",
    "wof:placetype":"venue"
},
  "geometry": {"coordinates":[-66.77220199999999,45.961746],"type":"Point"}
}