{
  "type": "Feature",
  "properties": {
    "iso:country":"CA",
    "sg:address":"163 Carriage Hill Dr",
    "sg:city":"Fredericton",
    "sg:classifiers":[
        {
            "category":"Professional",
            "subcategory":"Engineering",
            "type":"Services"
        }
    ],
    "sg:phone":"+1 506 452 1804",
    "sg:postcode":"E3E 1A4",
    "sg:province":"NB",
    "sg:tags":[
        "engineer"
    ],
    "wof:name":"Skarborn Engineering Ltd",
    "wof:placetype":"venue"
},
  "geometry": {"coordinates":[-66.772202,45.961746],"type":"Point"}
}