{
  "type": "Feature",
  "properties": {
    "addr:full":"28 Duffy Pl St. John's NL A1B 4M5",
    "addr:housenumber":"28",
    "addr:postcode":"a1b 4m5",
    "addr:street":"Duffy Pl",
    "iso:country":"CA",
    "sg:address":"28 Duffy Pl",
    "sg:city":"St. John's",
    "sg:classifiers":[
        {
            "category":"Shopping",
            "subcategory":"Clothing, Apparel, & Fashions",
            "type":"Retail Goods"
        }
    ],
    "sg:phone":"+1 709 722 0311",
    "sg:postcode":"A1B 4M5",
    "sg:province":"NL",
    "wof:name":"Jean Shop Ltd",
    "wof:placetype":"venue"
},
  "geometry": {"coordinates":[-52.775497,47.56179],"type":"Point"}
}