{
  "type": "Feature",
  "properties": {
    "iso:country":"CA",
    "sg:address":"582 Av Victoria",
    "sg:city":"Saint-Lambert",
    "sg:classifiers":[
        {
            "category":"Shopping",
            "subcategory":"Bicycles & Sporting Goods",
            "type":"Retail Goods"
        }
    ],
    "sg:phone":"+1 450 671 6166",
    "sg:postcode":"J4P 2J5",
    "sg:province":"QC",
    "sg:tags":[
        "equipment",
        "skateboard"
    ],
    "wof:name":"Palm Isle Skateshop",
    "wof:placetype":"venue"
},
  "geometry": {"coordinates":[-73.509811,45.500893],"type":"Point"}
}