{
  "type": "Feature",
  "properties": {
    "addr:full":"117 Boul J.-S.-Archambault Terrebonne QC J6W 4K3",
    "addr:housenumber":"117",
    "addr:postcode":"j6w 4k3",
    "addr:street":"Boul J.-S.-Archambault",
    "iso:country":"CA",
    "sg:address":"117 Boul J.-S.-Archambault",
    "sg:city":"Terrebonne",
    "sg:classifiers":[
        {
            "category":"Bars & Pubs",
            "type":"Food & Drink"
        }
    ],
    "sg:phone":"+1 450 471 0288",
    "sg:postcode":"J6W 4K3",
    "sg:province":"QC",
    "sg:tags":[
        "club",
        "night"
    ],
    "wof:name":"Bar Be L'Ile Fantastique",
    "wof:placetype":"venue"
},
  "geometry": {"coordinates":[-73.6470870972,45.69165802],"type":"Point"}
}