{
  "type": "Feature",
  "properties": {
    "addr:full":"91 South Front St Belleville ON K8N 2Y5",
    "addr:housenumber":"91",
    "addr:postcode":"k8n 2y5",
    "addr:street":"South Front St",
    "iso:country":"CA",
    "sg:address":"91 South Front St",
    "sg:city":"Belleville",
    "sg:classifiers":[
        {
            "category":"Food & Beverages",
            "subcategory":"Liquor & Beverages",
            "type":"Retail Goods"
        }
    ],
    "sg:phone":"+1 613 968 8559",
    "sg:postcode":"K8N 2Y5",
    "sg:province":"ON",
    "sg:tags":[
        "beer",
        "ale"
    ],
    "wof:name":"Beer Store",
    "wof:placetype":"venue"
},
  "geometry": {"coordinates":[-77.3785400391,44.1563682556],"type":"Point"}
}