{
  "type": "Feature",
  "properties": {
    "addr:full":"9037 Road 152 Gowanstown ON N0G 1Y0",
    "addr:housenumber":"9037",
    "addr:postcode":"n0g 1y0",
    "addr:street":"Road 152",
    "iso:country":"CA",
    "sg:address":"9037 Road 152",
    "sg:city":"Gowanstown",
    "sg:classifiers":[
        {
            "category":"Manufacturing",
            "subcategory":"Lumber",
            "type":"Manufacturing & Wholesale Goods"
        }
    ],
    "sg:phone":"+1 519 343 5126",
    "sg:postcode":"N0G 1Y0",
    "sg:province":"ON",
    "sg:tags":[
        "syrup",
        "maple",
        "sugar"
    ],
    "wof:name":"Martin's Maple Products",
    "wof:placetype":"venue"
},
  "geometry": {"coordinates":[-80.91905199999999,43.774345],"type":"Point"}
}