{
  "type": "Feature",
  "properties": {
    "addr:full":"48 Virginia St Welland ON L3C 7A4",
    "addr:housenumber":"48",
    "addr:postcode":"l3c 7a4",
    "addr:street":"Virginia St",
    "iso:country":"CA",
    "sg:address":"48 Virginia St",
    "sg:city":"Welland",
    "sg:classifiers":[
        {
            "category":"Building & Trades",
            "subcategory":"Construction",
            "type":"Services"
        }
    ],
    "sg:phone":"+1 905 732 6274",
    "sg:postcode":"L3C 7A4",
    "sg:province":"ON",
    "sg:tags":[
        "contractor"
    ],
    "wof:name":"Classic Home Construction Ltd",
    "wof:placetype":"venue"
},
  "geometry": {"coordinates":[-79.245903,43.005466],"type":"Point"}
}