{
  "type": "Feature",
  "properties": {
    "addr:full":"5600 Rue Donais Trois-Rivieres-Ouest QC G8Y 7A2",
    "addr:housenumber":"5600",
    "addr:postcode":"g8y 7a2",
    "addr:street":"Rue Donais Trois-Rivieres-Ouest",
    "iso:country":"CA",
    "sg:address":"5600 Rue Donais",
    "sg:city":"Trois-Rivieres-Ouest",
    "sg:classifiers":[
        {
            "category":"Building & Trades",
            "subcategory":"Construction",
            "type":"Services"
        }
    ],
    "sg:phone":"+1 819 372 2385",
    "sg:postcode":"G8Y 7A2",
    "sg:province":"QC",
    "sg:tags":[
        "masonry",
        "contractor"
    ],
    "wof:name":"Maconnerie Yvon Deshaies",
    "wof:placetype":"venue"
},
  "geometry": {"coordinates":[-72.59326934809999,46.3322525024],"type":"Point"}
}