{
  "type": "Feature",
  "properties": {
    "addr:full":"Sherwood Park AB T8B 1H8",
    "addr:postcode":"t8b 1h8",
    "iso:country":"CA",
    "sg:city":"Sherwood Park",
    "sg:classifiers":[
        {
            "category":"Professional",
            "subcategory":"Business Services",
            "type":"Services"
        }
    ],
    "sg:phone":"+1 780 499 0466",
    "sg:postcode":"T8B 1H8",
    "sg:province":"AB",
    "sg:tags":[
        "arbitration"
    ],
    "wof:name":"Resources International",
    "wof:placetype":"venue"
},
  "geometry": {"coordinates":[-113.29573822,53.5264015198],"type":"Point"}
}