{
  "type": "Feature",
  "properties": {
    "addr:full":"NE 15 17 15W Birnie MB R0J 0J0",
    "addr:housenumber":"17 15w",
    "addr:postcode":"r0j 0j0",
    "addr:street":"Ne 15",
    "iso:country":"CA",
    "sg:address":"NE 15 17 15W",
    "sg:city":"Birnie",
    "sg:classifiers":[
        {
            "category":"Building & Trades",
            "subcategory":"Construction",
            "type":"Services"
        }
    ],
    "sg:phone":"+1 204 966 3331",
    "sg:postcode":"R0J 0J0",
    "sg:province":"MB",
    "sg:tags":[
        "home",
        "builder"
    ],
    "wof:name":"Birnie Builders",
    "wof:placetype":"venue"
},
  "geometry": {"coordinates":[-99.44146728520001,50.4479103088],"type":"Point"}
}