{
  "type": "Feature",
  "properties": {
    "addr:full":"30 Main St Wellwood MB R0K 2H0",
    "addr:housenumber":"30",
    "addr:postcode":"r0k 2h0",
    "addr:street":"Main St",
    "iso:country":"CA",
    "sg:address":"30 Main St",
    "sg:city":"Wellwood",
    "sg:classifiers":[
        {
            "category":"Recreation",
            "type":"Entertainment"
        }
    ],
    "sg:phone":"+1 204 834 3078",
    "sg:postcode":"R0K 2H0",
    "sg:province":"MB",
    "sg:tags":[
        "hall",
        "auditorium"
    ],
    "wof:name":"Wellwood Community Club",
    "wof:placetype":"venue"
},
  "geometry": {"coordinates":[-99.33223724370001,50.0397949219],"type":"Point"}
}