{
  "type": "Feature",
  "properties": {
    "addr:full":"20 Rue Guilbault Sorel-Tracy QC J3P 5E2",
    "addr:housenumber":"20",
    "addr:postcode":"j3p 5e2",
    "addr:street":"Rue Guilbault",
    "iso:country":"CA",
    "sg:address":"20 Rue Guilbault",
    "sg:city":"Sorel-Tracy",
    "sg:classifiers":[
        {
            "category":"Health Services",
            "subcategory":"Doctor",
            "type":"Services"
        }
    ],
    "sg:phone":"+1 450 742 0982",
    "sg:postcode":"J3P 5E2",
    "sg:province":"QC",
    "sg:tags":[
        "physician",
        "surgeon"
    ],
    "wof:name":"Lafond, Serge DO",
    "wof:placetype":"venue"
},
  "geometry": {"coordinates":[-73.13176727290001,46.0211791992],"type":"Point"}
}