{
  "type": "Feature",
  "properties": {
    "addr:full":"Kelowna BC V1Y 1W1",
    "addr:postcode":"v1y 1w1",
    "iso:country":"CA",
    "sg:city":"Kelowna",
    "sg:classifiers":[
        {
            "category":"Professional",
            "subcategory":"Accounting & Tax Preparation",
            "type":"Services"
        }
    ],
    "sg:phone":"+1 250 762 8803",
    "sg:postcode":"V1Y 1W1",
    "sg:province":"BC",
    "sg:tags":[
        "consultant",
        "return",
        "filing"
    ],
    "wof:name":"H & R Block Canada Inc",
    "wof:placetype":"venue"
},
  "geometry": {"coordinates":[-119.49104309099999,49.8635253906],"type":"Point"}
}