{
  "type": "Feature",
  "properties": {
    "addr:full":"180 Georgia St W Vancouver BC V6B 4P4",
    "addr:housenumber":"180",
    "addr:postcode":"v6b 4p4",
    "addr:street":"Georgia St W",
    "iso:country":"CA",
    "sg:address":"180 Georgia St W",
    "sg:city":"Vancouver",
    "sg:classifiers":[
        {
            "category":"Travel",
            "subcategory":"Hotels & Motels",
            "type":"Entertainment"
        }
    ],
    "sg:phone":"+1 604 736 4388",
    "sg:postcode":"V6B 4P4",
    "sg:province":"BC",
    "sg:tags":[
        "reservation"
    ],
    "wof:name":"Sandman Hotels Inns & Suites",
    "wof:placetype":"venue"
},
  "geometry": {"coordinates":[-123.113152,49.279129],"type":"Point"}
}