{
  "type": "Feature",
  "properties": {
    "iso:country":"CA",
    "sg:address":"975 Martin Grove Rd",
    "sg:city":"Etobicoke",
    "sg:classifiers":[
        {
            "category":"Manufacturing",
            "subcategory":"Tools & Machinery",
            "type":"Manufacturing & Wholesale Goods"
        }
    ],
    "sg:phone":"+1 416 248 6800",
    "sg:postcode":"M9W 4V6",
    "sg:province":"ON",
    "sg:tags":[
        "equipment",
        "barbecue",
        "supply"
    ],
    "wof:name":"Smokey Manufacturing Inc",
    "wof:placetype":"venue"
},
  "geometry": {"coordinates":[-79.572784,43.696217],"type":"Point"}
}