{
  "type": "Feature",
  "properties": {
    "addr:full":"135 Anderson Ave Winnipeg MB R2W 5M9",
    "addr:housenumber":"135",
    "addr:postcode":"r2w 5m9",
    "addr:street":"Anderson Ave",
    "iso:country":"CA",
    "sg:address":"135 Anderson Ave",
    "sg:city":"Winnipeg",
    "sg:classifiers":[
        {
            "category":"Organizations",
            "subcategory":"Religious Organization",
            "type":"Services"
        }
    ],
    "sg:phone":"+1 204 586 8385",
    "sg:postcode":"R2W 5M9",
    "sg:province":"MB",
    "sg:tags":[
        "church"
    ],
    "wof:name":"St John's Cathedral",
    "wof:placetype":"venue"
},
  "geometry": {"coordinates":[-97.1249542236,49.9201316833],"type":"Point"}
}