{
  "type": "Feature",
  "properties": {
    "iso:country":"CA",
    "sg:city":"Montreal",
    "sg:classifiers":[
        {
            "category":"Organizations",
            "subcategory":"Professional Association",
            "type":"Services"
        }
    ],
    "sg:phone":"+1 514 844 5778",
    "sg:postcode":"H3A 2S9",
    "sg:province":"QC",
    "wof:name":"Ordre Des Ergotherapeutes Du",
    "wof:placetype":"venue"
},
  "geometry": {"coordinates":[-73.571304,45.50494],"type":"Point"}
}