{
  "type": "Feature",
  "properties": {
    "iso:country":"CA",
    "sg:address":"521 3 Ave NE",
    "sg:city":"Airdrie",
    "sg:classifiers":[
        {
            "category":"Travel",
            "subcategory":"Hotels & Motels",
            "type":"Entertainment"
        }
    ],
    "sg:phone":"+1 403 948 2233",
    "sg:postcode":"T4B 1R8",
    "sg:province":"AB",
    "wof:name":"Horseman Motel & Dining Lounge",
    "wof:placetype":"venue"
},
  "geometry": {"coordinates":[-114.00327301,51.294254303],"type":"Point"}
}