{
  "type": "Feature",
  "properties": {
    "addr:full":"7708 85 St NW Edmonton AB T6C 4K9",
    "addr:housenumber":"7708",
    "addr:postcode":"t6c 4k9",
    "addr:street":"85 St Nw",
    "iso:country":"CA",
    "sg:address":"7708 85 St NW",
    "sg:city":"Edmonton",
    "sg:classifiers":[
        {
            "category":"Organizations",
            "subcategory":"Professional Association",
            "type":"Services"
        }
    ],
    "sg:phone":"+1 780 469 2468",
    "sg:postcode":"T6C 4K9",
    "sg:province":"AB",
    "wof:name":"King Edward Park Comm League",
    "wof:placetype":"venue"
},
  "geometry": {"coordinates":[-113.458366394,53.513633728],"type":"Point"}
}