{
  "type": "Feature",
  "properties": {
    "iso:country":"CA",
    "sg:address":"930 Cawston Ave",
    "sg:city":"Kelowna",
    "sg:classifiers":[
        {
            "category":"Building & Trades",
            "subcategory":"Plumbing",
            "type":"Services"
        }
    ],
    "sg:phone":"+1 250 762 3874",
    "sg:postcode":"V1Y 6Z8",
    "sg:province":"BC",
    "sg:tags":[
        "contractor"
    ],
    "wof:name":"B T Plumbing",
    "wof:placetype":"venue"
},
  "geometry": {"coordinates":[-119.48174285899999,49.8917694092],"type":"Point"}
}