{
  "type": "Feature",
  "properties": {
    "addr:full":"70 King St E Cobourg ON K9A 1K9",
    "addr:housenumber":"70",
    "addr:postcode":"k9a 1k9",
    "addr:street":"King St E",
    "iso:country":"CA",
    "sg:address":"70 King St E",
    "sg:city":"Cobourg",
    "sg:classifiers":[
        {
            "category":"Retail",
            "subcategory":"Auto Repair",
            "type":"Services"
        }
    ],
    "sg:phone":"+1 905 372 7071",
    "sg:postcode":"K9A 1K9",
    "sg:province":"ON",
    "sg:tags":[
        "repairing",
        "automobile"
    ],
    "wof:name":"Jim's Auto Repair Svc",
    "wof:placetype":"venue"
},
  "geometry": {"coordinates":[-78.1626281738,43.9606552124],"type":"Point"}
}