{
  "type": "Feature",
  "properties": {
    "addr:full":"119 212 Rte E LA Patrie QC J0B 1Y0",
    "addr:housenumber":"212",
    "addr:postcode":"j0b 1y0",
    "addr:street":"Rte E La Patrie",
    "iso:country":"CA",
    "sg:address":"119 212 Rte E",
    "sg:city":"LA Patrie",
    "sg:classifiers":[
        {
            "category":"Professional",
            "subcategory":"Computer Services",
            "type":"Services"
        }
    ],
    "sg:phone":"+1 819 888 1022",
    "sg:postcode":"J0B 1Y0",
    "sg:province":"QC",
    "sg:tags":[
        "internet"
    ],
    "wof:name":"Vitrine Virtuelle DE LA Cote",
    "wof:placetype":"venue"
},
  "geometry": {"coordinates":[-71.1916885376,45.4016456604],"type":"Point"}
}