{
  "type": "Feature",
  "properties": {
    "addr:full":"Brampton ON L6S 5N6",
    "addr:postcode":"l6s 5n6",
    "iso:country":"CA",
    "sg:city":"Brampton",
    "sg:classifiers":[
        {
            "category":"Education",
            "subcategory":"Dance Studio",
            "type":"Public Place"
        }
    ],
    "sg:phone":"+1 905 458 9943",
    "sg:postcode":"L6S 5N6",
    "sg:province":"ON",
    "sg:tags":[
        "instruction",
        "dancing"
    ],
    "wof:name":"Coffey's Danc'n Place Ltd",
    "wof:placetype":"venue"
},
  "geometry": {"coordinates":[-79.710121,43.756325],"type":"Point"}
}