{
  "type": "Feature",
  "properties": {
    "addr:full":"7515 Macleod Trail SW Calgary AB T2H 0L8",
    "addr:housenumber":"7515",
    "addr:postcode":"t2h 0l8",
    "addr:street":"Macleod Trail Sw",
    "iso:country":"CA",
    "sg:address":"7515 Macleod Trail SW",
    "sg:city":"Calgary",
    "sg:classifiers":[
        {
            "category":"Building & Trades",
            "subcategory":"Equipment Rental",
            "type":"Services"
        }
    ],
    "sg:phone":"+1 403 258 1230",
    "sg:postcode":"T2H 0L8",
    "sg:province":"AB",
    "sg:tags":[
        "player",
        "recorder",
        "video"
    ],
    "wof:name":"Adult Super Store",
    "wof:placetype":"venue"
},
  "geometry": {"coordinates":[-114.071769714,50.9860191345],"type":"Point"}
}