{
  "type": "Feature",
  "properties": {
    "addr:full":"Winnipeg MB R3T 4Z8",
    "addr:postcode":"r3t 4z8",
    "iso:country":"CA",
    "sg:city":"Winnipeg",
    "sg:classifiers":[
        {
            "category":"Restaurant",
            "type":"Food & Drink"
        }
    ],
    "sg:phone":"+1 204 261 9614",
    "sg:postcode":"R3T 4Z8",
    "sg:province":"MB",
    "wof:name":"Smitty's Your Family's Rstr",
    "wof:placetype":"venue"
},
  "geometry": {"coordinates":[-97.15776099999999,49.790066],"type":"Point"}
}