{
  "type": "Feature",
  "properties": {
    "addr:full":"130 Hartzell Rd St Catharines ON L2P 1N7",
    "addr:housenumber":"130",
    "addr:postcode":"l2p 1n7",
    "addr:street":"Hartzell Rd",
    "iso:country":"CA",
    "sg:address":"130 Hartzell Rd",
    "sg:city":"St Catharines",
    "sg:classifiers":[
        {
            "category":"Shopping",
            "subcategory":"Music",
            "type":"Retail Goods"
        }
    ],
    "sg:phone":"+1 905 988 5333",
    "sg:postcode":"L2P 1N7",
    "sg:province":"ON",
    "sg:tags":[
        "compact",
        "record",
        "game",
        "video",
        "tape"
    ],
    "wof:name":"High Score Entertainment Exch",
    "wof:placetype":"venue"
},
  "geometry": {"coordinates":[-79.214066,43.149853],"type":"Point"}
}