{
  "type": "Feature",
  "properties": {
    "addr:full":"123 7 Ave SE Drumheller AB T0J 0Y6",
    "addr:housenumber":"123",
    "addr:postcode":"t0j 0y6",
    "addr:street":"7 Ave Se",
    "iso:country":"CA",
    "sg:address":"123 7 Ave SE",
    "sg:city":"Drumheller",
    "sg:classifiers":[
        {
            "category":"Retail",
            "subcategory":"Veterinary Services",
            "type":"Services"
        }
    ],
    "sg:phone":"+1 403 823 5400",
    "sg:postcode":"T0J 0Y6",
    "sg:province":"AB",
    "sg:tags":[
        "veterinarian"
    ],
    "wof:name":"Little, K DVM",
    "wof:placetype":"venue"
},
  "geometry": {"coordinates":[-112.70877075200001,51.4578704834],"type":"Point"}
}