{
  "type": "Feature",
  "properties": {
    "addr:full":"410 6 St S Lethbridge AB T1J 2C9",
    "addr:housenumber":"410 6",
    "addr:postcode":"t1j 2c9",
    "addr:street":"St S",
    "iso:country":"CA",
    "sg:address":"410 6 St S",
    "sg:city":"Lethbridge",
    "sg:classifiers":[
        {
            "category":"Professional",
            "subcategory":"Lawyer & Legal Services",
            "type":"Services"
        }
    ],
    "sg:phone":"+1 403 328 8856",
    "sg:postcode":"T1J 2C9",
    "sg:province":"AB",
    "sg:tags":[
        "attorney"
    ],
    "wof:name":"Cavilla, David C",
    "wof:placetype":"venue"
},
  "geometry": {"coordinates":[-112.83873748800001,49.6940841675],"type":"Point"}
}