{
  "type": "Feature",
  "properties": {
    "iso:country":"CA",
    "sg:city":"Orangeville",
    "sg:classifiers":[
        {
            "category":"Building & Trades",
            "subcategory":"Construction",
            "type":"Services"
        }
    ],
    "sg:phone":"+1 519 942 8912",
    "sg:postcode":"L9W 2Y8",
    "sg:province":"ON",
    "sg:tags":[
        "water",
        "excavating",
        "works",
        "contractor"
    ],
    "wof:name":"Gibson Contracting",
    "wof:placetype":"venue"
},
  "geometry": {"coordinates":[-80.093491,43.920116],"type":"Point"}
}