{
  "type": "Feature",
  "properties": {
    "addr:full":"2350 Rue Acadie Cap-Pele NB E4N 1C7",
    "addr:housenumber":"2350",
    "addr:postcode":"e4n 1c7",
    "addr:street":"Rue Acadie",
    "iso:country":"CA",
    "sg:address":"2350 Rue Acadie",
    "sg:city":"Cap-Pele",
    "sg:classifiers":[
        {
            "category":"Travel",
            "subcategory":"Hotels & Motels",
            "type":"Entertainment"
        }
    ],
    "sg:phone":"+1 506 577 4111",
    "sg:postcode":"E4N 1C7",
    "sg:province":"NB",
    "wof:name":"Motel Edco",
    "wof:placetype":"venue"
},
  "geometry": {"coordinates":[-64.3074264526,46.2205047607],"type":"Point"}
}