{
  "type": "Feature",
  "properties": {
    "iso:country":"CA",
    "sg:address":"1736 Boul Maloney E",
    "sg:city":"Gatineau",
    "sg:classifiers":[
        {
            "category":"Social Services",
            "type":"Services"
        }
    ],
    "sg:phone":"+1 819 669 7168",
    "sg:postcode":"J8R 1B3",
    "sg:province":"QC",
    "sg:tags":[
        "counselor",
        "human",
        "relations"
    ],
    "wof:name":"Renaissance",
    "wof:placetype":"venue"
},
  "geometry": {"coordinates":[-75.558792,45.504921],"type":"Point"}
}