{
  "type": "Feature",
  "properties": {
    "iso:country":"CA",
    "sg:city":"Concord",
    "sg:classifiers":[
        {
            "category":"Building & Trades",
            "subcategory":"Construction",
            "type":"Services"
        }
    ],
    "sg:phone":"+1 905 660 5665",
    "sg:postcode":"L4K 4K7",
    "sg:province":"ON",
    "sg:tags":[
        "general",
        "contractor"
    ],
    "wof:name":"Rafat General Contracting",
    "wof:placetype":"venue"
},
  "geometry": {"coordinates":[-79.5336761475,43.8083572388],"type":"Point"}
}