{
  "type": "Feature",
  "properties": {
    "addr:full":"Mississauga ON L4W 1G4",
    "addr:postcode":"l4w 1g4",
    "iso:country":"CA",
    "sg:city":"Mississauga",
    "sg:classifiers":[
        {
            "category":"Wholesale",
            "subcategory":"Scrap",
            "type":"Manufacturing & Wholesale Goods"
        }
    ],
    "sg:phone":"+1 905 206 9696",
    "sg:postcode":"L4W 1G4",
    "sg:province":"ON",
    "sg:tags":[
        "recycling",
        "center"
    ],
    "wof:name":"AAA Recycling",
    "wof:placetype":"venue"
},
  "geometry": {"coordinates":[-79.627746582,43.6307678223],"type":"Point"}
}