{
  "type": "Feature",
  "properties": {
    "addr:full":"811 Alward St Prince George BC V2M 2E8",
    "addr:housenumber":"811",
    "addr:postcode":"v2m 2e8",
    "addr:street":"Alward St",
    "iso:country":"CA",
    "sg:address":"811 Alward St",
    "sg:city":"Prince George",
    "sg:classifiers":[
        {
            "category":"Building & Trades",
            "subcategory":"Construction",
            "type":"Services"
        }
    ],
    "sg:phone":"+1 250 563 1615",
    "sg:postcode":"V2M 2E8",
    "sg:province":"BC",
    "sg:tags":[
        "painter"
    ],
    "wof:name":"Wayne's Painting",
    "wof:placetype":"venue"
},
  "geometry": {"coordinates":[-122.766593933,53.9174079895],"type":"Point"}
}