{
  "type": "Feature",
  "properties": {
    "addr:full":"Winnipeg MB R3G 0T3",
    "addr:postcode":"r3g 0t3",
    "iso:country":"CA",
    "sg:city":"Winnipeg",
    "sg:classifiers":[
        {
            "category":"Government",
            "subcategory":"Office",
            "type":"Public Place"
        }
    ],
    "sg:phone":"+1 204 945 6910",
    "sg:postcode":"R3G 0T3",
    "sg:province":"MB",
    "wof:name":"Schools Finance Branch",
    "wof:placetype":"venue"
},
  "geometry": {"coordinates":[-97.1837310791,49.8836479187],"type":"Point"}
}