{
  "type": "Feature",
  "properties": {
    "addr:full":"460 Yonge St Toronto ON M4Y 1W9",
    "addr:housenumber":"460",
    "addr:postcode":"m4y 1w9",
    "addr:street":"Yonge St",
    "iso:country":"CA",
    "sg:address":"460 Yonge St",
    "sg:city":"Toronto",
    "sg:classifiers":[
        {
            "category":"Restaurant",
            "type":"Food & Drink"
        }
    ],
    "sg:phone":"+1 416 966 4714",
    "sg:postcode":"M4Y 1W9",
    "sg:province":"ON",
    "wof:name":"Sizzlers",
    "wof:placetype":"venue"
},
  "geometry": {"coordinates":[-79.3834152222,43.6616897583],"type":"Point"}
}