{
  "type": "Feature",
  "properties": {
    "addr:full":"Wooler ON K0K 3M0",
    "addr:postcode":"k0k 3m0",
    "iso:country":"CA",
    "sg:city":"Wooler",
    "sg:classifiers":[
        {
            "category":"Local Transit",
            "type":"Transportation"
        }
    ],
    "sg:phone":"+1 613 397 3104",
    "sg:postcode":"K0K 3M0",
    "sg:province":"ON",
    "sg:tags":[
        "bus",
        "line"
    ],
    "wof:name":"C Smith Bus Lines",
    "wof:placetype":"venue"
},
  "geometry": {"coordinates":[-77.7004241943,44.1568756104],"type":"Point"}
}