{
  "type": "Feature",
  "properties": {
    "addr:full":"251 Vidal St N Sarnia ON N7T 5Y5",
    "addr:housenumber":"251",
    "addr:postcode":"n7t 5y5",
    "addr:street":"Vidal St N",
    "iso:country":"CA",
    "sg:address":"251 Vidal St N",
    "sg:city":"Sarnia",
    "sg:classifiers":[
        {
            "category":"Wholesale",
            "subcategory":"Machinery & Supplies",
            "type":"Manufacturing & Wholesale Goods"
        }
    ],
    "sg:phone":"+1 519 383 1225",
    "sg:postcode":"N7T 5Y5",
    "sg:province":"ON",
    "sg:tags":[
        "valve"
    ],
    "wof:name":"Floval Equipment Ltd",
    "wof:placetype":"venue"
},
  "geometry": {"coordinates":[-82.4044876099,42.9758834839],"type":"Point"}
}