{
  "type": "Feature",
  "properties": {
    "iso:country":"CA",
    "sg:address":"4262 Price Ave",
    "sg:city":"Gull Lake",
    "sg:classifiers":[
        {
            "category":"Wholesale",
            "subcategory":"Construction Materials",
            "type":"Manufacturing & Wholesale Goods"
        }
    ],
    "sg:phone":"+1 306 672 4415",
    "sg:postcode":"S0N 1A0",
    "sg:province":"SK",
    "sg:tags":[
        "sand",
        "gravel"
    ],
    "wof:name":"Central Gravel Ltd",
    "wof:placetype":"venue"
},
  "geometry": {"coordinates":[-108.483924866,50.0979690552],"type":"Point"}
}