{
  "type": "Feature",
  "properties": {
    "iso:country":"CA",
    "sg:address":"650 Boul Cure-Labelle",
    "sg:city":"Laval",
    "sg:classifiers":[
        {
            "category":"Social Services",
            "subcategory":"Child Care",
            "type":"Services"
        }
    ],
    "sg:phone":"+1 450 687 1213",
    "sg:postcode":"H7V 2T9",
    "sg:province":"QC",
    "wof:name":"Garderie D'Enfants Pays Des",
    "wof:placetype":"venue"
},
  "geometry": {"coordinates":[-73.7448043823,45.5375366211],"type":"Point"}
}