{
  "type": "Feature",
  "properties": {
    "addr:full":"914 Prince St Hearst ON P0L 1N0",
    "addr:housenumber":"914",
    "addr:postcode":"p0l 1n0",
    "addr:street":"Prince St",
    "iso:country":"CA",
    "sg:address":"914 Prince St",
    "sg:city":"Hearst",
    "sg:classifiers":[
        {
            "category":"Professional",
            "subcategory":"Lawyer & Legal Services",
            "type":"Services"
        }
    ],
    "sg:phone":"+1 705 362 5922",
    "sg:postcode":"P0L 1N0",
    "sg:province":"ON",
    "sg:tags":[
        "attorney"
    ],
    "wof:name":"Bourgeault Brunelle Dumais",
    "wof:placetype":"venue"
},
  "geometry": {"coordinates":[-83.66577100000001,49.688084],"type":"Point"}
}