{
  "type": "Feature",
  "properties": {
    "addr:full":"13010 Hwy 62 Hwy Madoc ON K0K 2K0",
    "addr:housenumber":"13010",
    "addr:postcode":"k0k 2k0",
    "addr:street":"Hwy 62 Hwy",
    "iso:country":"CA",
    "sg:address":"13010 Hwy 62 Hwy",
    "sg:city":"Madoc",
    "sg:classifiers":[
        {
            "category":"Wholesale",
            "subcategory":"Electrical",
            "type":"Manufacturing & Wholesale Goods"
        }
    ],
    "sg:phone":"+1 613 473 4490",
    "sg:postcode":"K0K 2K0",
    "sg:province":"ON",
    "sg:tags":[
        "fire",
        "equipment",
        "protection"
    ],
    "wof:name":"Class A Systems",
    "wof:placetype":"venue"
},
  "geometry": {"coordinates":[-77.47978973390001,44.5113601685],"type":"Point"}
}