{
  "type": "Feature",
  "properties": {
    "addr:full":"120 Dynamic Dr Scarborough ON M1V 5C8",
    "addr:housenumber":"120",
    "addr:postcode":"m1v 5c8",
    "addr:street":"Dynamic Dr",
    "iso:country":"CA",
    "sg:address":"120 Dynamic Dr",
    "sg:city":"Scarborough",
    "sg:classifiers":[
        {
            "category":"Real Estate",
            "subcategory":"Real Estate Operator",
            "type":"Services"
        }
    ],
    "sg:phone":"+1 416 298 9110",
    "sg:postcode":"M1V 5C8",
    "sg:province":"ON",
    "sg:tags":[
        "mall",
        "shopping",
        "center"
    ],
    "wof:name":"Yasin Shahab Plaza Inc",
    "wof:placetype":"venue"
},
  "geometry": {"coordinates":[-79.2521896362,43.8270339966],"type":"Point"}
}