{
  "type": "Feature",
  "properties": {
    "addr:full":"149 Rue Saint-Gabriel Saint-Gabriel-DE-Brandon QC J0K 2N0",
    "addr:housenumber":"149",
    "addr:postcode":"j0k 2n0",
    "addr:street":"Rue Saint-Gabriel",
    "iso:country":"CA",
    "sg:address":"149 Rue Saint-Gabriel",
    "sg:city":"Saint-Gabriel-DE-Brandon",
    "sg:classifiers":[
        {
            "category":"Bars & Pubs",
            "type":"Food & Drink"
        }
    ],
    "sg:phone":"+1 450 835 7334",
    "sg:postcode":"J0K 2N0",
    "sg:province":"QC",
    "sg:tags":[
        "lounge",
        "cocktail"
    ],
    "wof:name":"Bar Salon Royal Enr",
    "wof:placetype":"venue"
},
  "geometry": {"coordinates":[-73.38133999999999,46.291145],"type":"Point"}
}