{
  "type": "Feature",
  "properties": {
    "iso:country":"CA",
    "sg:city":"Rodney",
    "sg:classifiers":[
        {
            "category":"Travel",
            "subcategory":"Campground",
            "type":"Entertainment"
        }
    ],
    "sg:phone":"+1 519 785 2090",
    "sg:postcode":"N0L 2C0",
    "sg:province":"ON",
    "sg:tags":[
        "camp"
    ],
    "wof:name":"Ontario Bethel Park Bible Camp",
    "wof:placetype":"venue"
},
  "geometry": {"coordinates":[-81.68309021,42.5680351257],"type":"Point"}
}