{
  "type": "Feature",
  "properties": {
    "addr:full":"2782 Dafoe Rd Combermere ON K0J 1L0",
    "addr:housenumber":"2782",
    "addr:postcode":"k0j 1l0",
    "addr:street":"Dafoe Rd",
    "iso:country":"CA",
    "sg:address":"2782 Dafoe Rd",
    "sg:city":"Combermere",
    "sg:classifiers":[
        {
            "category":"Education",
            "subcategory":"School",
            "type":"Public Place"
        }
    ],
    "sg:phone":"+1 613 756 3708",
    "sg:postcode":"K0J 1L0",
    "sg:province":"ON",
    "wof:name":"George Vanier School",
    "wof:placetype":"venue"
},
  "geometry": {"coordinates":[-77.614182,45.365211],"type":"Point"}
}