{
  "type": "Feature",
  "properties": {
    "iso:country":"CA",
    "sg:address":"305 Parkhurst Dr",
    "sg:city":"Fredericton",
    "sg:classifiers":[
        {
            "category":"Social Services",
            "type":"Services"
        }
    ],
    "sg:phone":"+1 506 455 1260",
    "sg:postcode":"E3B 2K2",
    "sg:province":"NB",
    "sg:tags":[
        "counselor",
        "marriage",
        "family"
    ],
    "wof:name":"Jolene M Hartt Counselling Svc",
    "wof:placetype":"venue"
},
  "geometry": {"coordinates":[-66.665581,45.962746],"type":"Point"}
}