{
  "type": "Feature",
  "properties": {
    "addr:full":"951 Denison St # 9 Markham ON L3R 3W9",
    "addr:housenumber":"951",
    "addr:postcode":"l3r 3w9",
    "addr:street":"Denison St # 9",
    "iso:country":"CA",
    "sg:address":"951 Denison St # 9",
    "sg:city":"Markham",
    "sg:classifiers":[
        {
            "category":"Manufacturing",
            "subcategory":"Electronics",
            "type":"Manufacturing & Wholesale Goods"
        }
    ],
    "sg:phone":"+1 905 475 8641",
    "sg:postcode":"L3R 3W9",
    "sg:province":"ON",
    "sg:tags":[
        "fire",
        "alarm",
        "protection"
    ],
    "wof:name":"First Stage Fire Protection",
    "wof:placetype":"venue"
},
  "geometry": {"coordinates":[-79.33081799999999,43.82634],"type":"Point"}
}