{
  "type": "Feature",
  "properties": {
    "addr:full":"Saint-Gabriel-DE-Brandon QC J0K 2N0",
    "addr:postcode":"j0k 2n0",
    "iso:country":"CA",
    "sg:city":"Saint-Gabriel-DE-Brandon",
    "sg:classifiers":[
        {
            "category":"Bars & Pubs",
            "type":"Food & Drink"
        }
    ],
    "sg:phone":"+1 450 835 3151",
    "sg:postcode":"J0K 2N0",
    "sg:province":"QC",
    "sg:tags":[
        "lounge",
        "cocktail"
    ],
    "wof:name":"Bar Le Saloon",
    "wof:placetype":"venue"
},
  "geometry": {"coordinates":[-73.3804931641,46.2927856445],"type":"Point"}
}