{
  "type": "Feature",
  "properties": {
    "addr:full":"7825 Boul Taschereau Brossard QC J4Y 1A4",
    "addr:housenumber":"7825",
    "addr:postcode":"j4y 1a4",
    "addr:street":"Boul Taschereau",
    "iso:country":"CA",
    "sg:address":"7825 Boul Taschereau",
    "sg:city":"Brossard",
    "sg:classifiers":[
        {
            "category":"Shopping",
            "subcategory":"Bicycles & Sporting Goods",
            "type":"Retail Goods"
        }
    ],
    "sg:phone":"+1 450 678 5442",
    "sg:postcode":"J4Y 1A4",
    "sg:province":"QC",
    "wof:name":"L'Artiste Du Patin Enr",
    "wof:placetype":"venue"
},
  "geometry": {"coordinates":[-73.46616400000001,45.452606],"type":"Point"}
}