{
  "type": "Feature",
  "properties": {
    "addr:full":"901A 4Eav LA Pocatiere QC G0R 1Z0",
    "addr:housenumber":"901a 4eav",
    "addr:postcode":"g0r 1z0",
    "addr:street":"La Pocatiere",
    "iso:country":"CA",
    "sg:address":"901A 4Eav",
    "sg:city":"LA Pocatiere",
    "sg:classifiers":[
        {
            "category":"Local Transit",
            "type":"Transportation"
        }
    ],
    "sg:phone":"+1 418 856 5856",
    "sg:postcode":"G0R 1Z0",
    "sg:province":"QC",
    "sg:tags":[
        "organization",
        "line",
        "social",
        "welfare"
    ],
    "wof:name":"Trans-Apte Inc",
    "wof:placetype":"venue"
},
  "geometry": {"coordinates":[-70.03224899999999,47.369015],"type":"Point"}
}