{
  "type": "Feature",
  "properties": {
    "addr:full":"980 Pandora Ave Victoria BC V8V 3P3",
    "addr:housenumber":"980",
    "addr:postcode":"v8v 3p3",
    "addr:street":"Pandora Ave",
    "iso:country":"CA",
    "sg:address":"980 Pandora Ave",
    "sg:city":"Victoria",
    "sg:classifiers":[
        {
            "category":"Restaurant",
            "type":"Food & Drink"
        }
    ],
    "sg:phone":"+1 250 953 8190",
    "sg:postcode":"V8V 3P3",
    "sg:province":"BC",
    "wof:name":"Mc Donald's",
    "wof:placetype":"venue"
},
  "geometry": {"coordinates":[-123.356826782,48.4275016785],"type":"Point"}
}