{
  "type": "Feature",
  "properties": {
    "addr:full":"188 Rue Bellevue O Les Mechins QC G0J 1T0",
    "addr:housenumber":"188",
    "addr:postcode":"g0j 1t0",
    "addr:street":"Rue Bellevue O Les Mechins",
    "iso:country":"CA",
    "sg:address":"188 Rue Bellevue O",
    "sg:city":"Les Mechins",
    "sg:classifiers":[
        {
            "category":"Restaurant",
            "type":"Food & Drink"
        }
    ],
    "sg:phone":"+1 418 729 3631",
    "sg:postcode":"G0J 1T0",
    "sg:province":"QC",
    "wof:name":"Restaurant Bar Le Montagnard",
    "wof:placetype":"venue"
},
  "geometry": {"coordinates":[-66.95920599999999,49.005718],"type":"Point"}
}