{
  "type": "Feature",
  "properties": {
    "addr:full":"321 Center St Coronach SK S0H 0Z0",
    "addr:housenumber":"321",
    "addr:postcode":"s0h 0z0",
    "addr:street":"Center St",
    "iso:country":"CA",
    "sg:address":"321 Center St",
    "sg:city":"Coronach",
    "sg:classifiers":[
        {
            "category":"Organizations",
            "subcategory":"Religious Organization",
            "type":"Services"
        }
    ],
    "sg:phone":"+1 306 267 3343",
    "sg:postcode":"S0H 0Z0",
    "sg:province":"SK",
    "sg:tags":[
        "church"
    ],
    "wof:name":"Faith Lutheran Church",
    "wof:placetype":"venue"
},
  "geometry": {"coordinates":[-105.522614,49.113815],"type":"Point"}
}