{
  "type": "Feature",
  "properties": {
    "addr:full":"95 Orkney Cres London ON N5X 3R8",
    "addr:housenumber":"95",
    "addr:postcode":"n5x 3r8",
    "addr:street":"Orkney Cres",
    "iso:country":"CA",
    "sg:address":"95 Orkney Cres",
    "sg:city":"London",
    "sg:classifiers":[
        {
            "category":"Health Services",
            "subcategory":"Health Practitioner",
            "type":"Services"
        }
    ],
    "sg:phone":"+1 519 642 1084",
    "sg:postcode":"N5X 3R8",
    "sg:province":"ON",
    "sg:tags":[
        "psychologist"
    ],
    "wof:name":"Olinger, Joan L",
    "wof:placetype":"venue"
},
  "geometry": {"coordinates":[-81.265739,43.019096],"type":"Point"}
}