{
  "type": "Feature",
  "properties": {
    "addr:full":"288 Markham Rd Scarborough ON M1J 3C5",
    "addr:housenumber":"288",
    "addr:postcode":"m1j 3c5",
    "addr:street":"Markham Rd",
    "iso:country":"CA",
    "sg:address":"288 Markham Rd",
    "sg:city":"Scarborough",
    "sg:classifiers":[
        {
            "category":"Shopping",
            "subcategory":"Pharmacy",
            "type":"Retail Goods"
        }
    ],
    "sg:phone":"+1 416 266 3000",
    "sg:postcode":"M1J 3C5",
    "sg:province":"ON",
    "wof:name":"Sunrise Pharmacy",
    "wof:placetype":"venue"
},
  "geometry": {"coordinates":[-79.22035200000001,43.746143],"type":"Point"}
}