{
  "type": "Feature",
  "properties": {
    "addr:full":"259 Gross Ave Welland ON L3C 2V1",
    "addr:housenumber":"259",
    "addr:postcode":"l3c 2v1",
    "addr:street":"Gross Ave",
    "iso:country":"CA",
    "sg:address":"259 Gross Ave",
    "sg:city":"Welland",
    "sg:classifiers":[
        {
            "category":"Professional",
            "subcategory":"Computer Services",
            "type":"Services"
        }
    ],
    "sg:phone":"+1 905 735 9474",
    "sg:postcode":"L3C 2V1",
    "sg:province":"ON",
    "sg:tags":[
        "telephone"
    ],
    "wof:name":"Armbrust Telecommunications",
    "wof:placetype":"venue"
},
  "geometry": {"coordinates":[-79.270081,42.970791],"type":"Point"}
}