{
  "type": "Feature",
  "properties": {
    "addr:full":"140 Yorkville Ave Toronto ON M5R 1C2",
    "addr:housenumber":"140",
    "addr:postcode":"m5r 1c2",
    "addr:street":"Yorkville Ave",
    "iso:country":"CA",
    "sg:address":"140 Yorkville Ave",
    "sg:city":"Toronto",
    "sg:classifiers":[
        {
            "category":"Personal",
            "subcategory":"Beauty Salon",
            "type":"Services"
        }
    ],
    "sg:phone":"+1 416 921 2996",
    "sg:postcode":"M5R 1C2",
    "sg:province":"ON",
    "sg:tags":[
        "spa"
    ],
    "wof:name":"Jeanet Spa & Salon",
    "wof:placetype":"venue"
},
  "geometry": {"coordinates":[-79.3937072754,43.6707344055],"type":"Point"}
}