{
  "type": "Feature",
  "properties": {
    "iso:country":"CA",
    "sg:address":"5203 Rue Bannantyne",
    "sg:city":"Verdun",
    "sg:classifiers":[
        {
            "category":"Building & Trades",
            "subcategory":"Plumbing",
            "type":"Services"
        }
    ],
    "sg:phone":"+1 514 595 5302",
    "sg:postcode":"H4H 1E6",
    "sg:province":"QC",
    "sg:tags":[
        "conditioning",
        "air",
        "system",
        "contractor"
    ],
    "wof:name":"Aero Climat",
    "wof:placetype":"venue"
},
  "geometry": {"coordinates":[-73.5766220093,45.4545898438],"type":"Point"}
}