{
  "type": "Feature",
  "properties": {
    "addr:full":"2352 Av DE LA Montagne Shawinigan QC G9N 6K1",
    "addr:housenumber":"2352",
    "addr:postcode":"g9n 6k1",
    "addr:street":"Av De La Montagne",
    "iso:country":"CA",
    "sg:address":"2352 Av DE LA Montagne",
    "sg:city":"Shawinigan",
    "sg:classifiers":[
        {
            "category":"Personal",
            "type":"Services"
        }
    ],
    "sg:phone":"+1 819 539 4348",
    "sg:postcode":"G9N 6K1",
    "sg:province":"QC",
    "sg:tags":[
        "electrolysis"
    ],
    "wof:name":"Clinique D'Esthetique Doris",
    "wof:placetype":"venue"
},
  "geometry": {"coordinates":[-72.761543,46.571953],"type":"Point"}
}