{
  "type": "Feature",
  "properties": {
    "addr:full":"11 Chadwick Dr Ajax ON L1S 5W6",
    "addr:housenumber":"11",
    "addr:postcode":"l1s 5w6",
    "addr:street":"Chadwick Dr",
    "iso:country":"CA",
    "sg:address":"11 Chadwick Dr",
    "sg:city":"Ajax",
    "sg:classifiers":[
        {
            "category":"Retail",
            "subcategory":"Repair Shop",
            "type":"Services"
        }
    ],
    "sg:phone":"+1 905 444 0059",
    "sg:postcode":"L1S 5W6",
    "sg:province":"ON",
    "sg:tags":[
        "refinishing",
        "furniture"
    ],
    "wof:name":"Superior Office Svc",
    "wof:placetype":"venue"
},
  "geometry": {"coordinates":[-79.0317611694,43.8555526733],"type":"Point"}
}