{
  "type": "Feature",
  "properties": {
    "addr:full":"1177 Langs Cir Cambridge ON N3H 5E6",
    "addr:housenumber":"1177",
    "addr:postcode":"n3h 5e6",
    "addr:street":"Langs Cir",
    "iso:country":"CA",
    "sg:address":"1177 Langs Cir",
    "sg:city":"Cambridge",
    "sg:classifiers":[
        {
            "category":"Banks & Credit Unions",
            "subcategory":"Investment Brokerage",
            "type":"Services"
        }
    ],
    "sg:phone":"+1 519 653 9496",
    "sg:postcode":"N3H 5E6",
    "sg:province":"ON",
    "sg:tags":[
        "consultant",
        "planning",
        "financial"
    ],
    "wof:name":"Canada Loyal Financial",
    "wof:placetype":"venue"
},
  "geometry": {"coordinates":[-80.33631099999999,43.399155],"type":"Point"}
}