{
  "type": "Feature",
  "properties": {
    "addr:full":"3488 Fairlight Dr Saskatoon SK S7M 3Z4",
    "addr:housenumber":"3488",
    "addr:postcode":"s7m 3z4",
    "addr:street":"Fairlight Dr",
    "iso:country":"CA",
    "sg:address":"3488 Fairlight Dr",
    "sg:city":"Saskatoon",
    "sg:classifiers":[
        {
            "category":"Organizations",
            "subcategory":"Religious Organization",
            "type":"Services"
        }
    ],
    "sg:phone":"+1 306 384 0646",
    "sg:postcode":"S7M 3Z4",
    "sg:province":"SK",
    "sg:tags":[
        "church"
    ],
    "wof:name":"Westside Pentecostal Church",
    "wof:placetype":"venue"
},
  "geometry": {"coordinates":[-106.73268899999999,52.126183],"type":"Point"}
}