{
  "type": "Feature",
  "properties": {
    "addr:full":"South River NL A0A 3W0",
    "addr:postcode":"a0a 3w0",
    "iso:country":"CA",
    "sg:city":"South River",
    "sg:classifiers":[
        {
            "category":"Building & Trades",
            "subcategory":"Construction",
            "type":"Services"
        }
    ],
    "sg:phone":"+1 709 786 3561",
    "sg:postcode":"A0A 3W0",
    "sg:province":"NL",
    "sg:tags":[
        "water",
        "well",
        "drilling"
    ],
    "wof:name":"Martin B Hammond CO Ltd",
    "wof:placetype":"venue"
},
  "geometry": {"coordinates":[-53.269871,47.536968],"type":"Point"}
}