{
  "type": "Feature",
  "properties": {
    "addr:full":"5282 Canim Hendrix Lake Rd Buffalo Creek BC V0K 1G0",
    "addr:housenumber":"5282",
    "addr:postcode":"v0k 1g0",
    "addr:street":"Canim Hendrix Lake Rd",
    "iso:country":"CA",
    "sg:address":"5282 Canim Hendrix Lake Rd",
    "sg:city":"Buffalo Creek",
    "sg:classifiers":[
        {
            "category":"Education",
            "subcategory":"School",
            "type":"Public Place"
        }
    ],
    "sg:phone":"+1 250 397 2441",
    "sg:postcode":"V0K 1G0",
    "sg:province":"BC",
    "wof:name":"Buffalo Creek School",
    "wof:placetype":"venue"
},
  "geometry": {"coordinates":[-121.214546204,51.6824455261],"type":"Point"}
}