{
  "type": "Feature",
  "properties": {
    "addr:full":"522 South Dogwood St # 7 Campbell River BC V9W 6R4",
    "addr:housenumber":"522",
    "addr:postcode":"v9w 6r4",
    "addr:street":"South Dogwood St # 7",
    "iso:country":"CA",
    "sg:address":"522 South Dogwood St # 7",
    "sg:city":"Campbell River",
    "sg:classifiers":[
        {
            "category":"Shopping",
            "subcategory":"Bicycles & Sporting Goods",
            "type":"Retail Goods"
        }
    ],
    "sg:phone":"+1 250 286 9996",
    "sg:postcode":"V9W 6R4",
    "sg:province":"BC",
    "wof:name":"Granlund Firearms",
    "wof:placetype":"venue"
},
  "geometry": {"coordinates":[-125.24775699999999,49.997875],"type":"Point"}
}