{
  "type": "Feature",
  "properties": {
    "addr:full":"Richmond Hill ON L4C 9Y1",
    "addr:postcode":"l4c 9y1",
    "iso:country":"CA",
    "sg:city":"Richmond Hill",
    "sg:classifiers":[
        {
            "category":"Retail",
            "subcategory":"Laundry & Dry Cleaning",
            "type":"Services"
        }
    ],
    "sg:phone":"+1 905 508 7733",
    "sg:postcode":"L4C 9Y1",
    "sg:province":"ON",
    "sg:tags":[
        "cleaners"
    ],
    "wof:name":"Heritage Custom Cleaners",
    "wof:placetype":"venue"
},
  "geometry": {"coordinates":[-79.45919000000001,43.880402],"type":"Point"}
}